Workbook
Name CONTRATISTA: 'Mano de Obra'!$A$2:$D$2
Name CONTRATISTA: Materiales!$A$2
Name CONTRATISTA: 'Precio Equipos'!#REF!
Name CONTRATISTA: 'Rend. Equipos'!#REF!
Name CONTRATISTA: 'Sub CONTRATOS'!$A$2:$E$2
Name FECHA: Materiales!$D$4
Name FECHA: 'Precio Equipos'!#REF!
Name FECHA: 'Rend. Equipos'!$E$3
Name FECHA: 'Sub CONTRATOS'!$E$4
Name FECHA: 'Mano de Obra'!$D$4
Name INICIO: Materiales!$A$1
Name INICIO: 'Precio Equipos'!$A$1
Name INICIO: 'Rend. Equipos'!$A$1
Name INICIO: 'Sub CONTRATOS'!$A$1
Name INICIO: 'Mano de Obra'!$A$1
Name OBRA: 'Mano de Obra'!$A$3:$D$3
Name OBRA: Materiales!$A$3
Name OBRA: 'Precio Equipos'!#REF!
Name OBRA: 'Rend. Equipos'!#REF!
Name OBRA: 'Sub CONTRATOS'!$A$3:$E$3
Name PARTIDABASE: Materiales!$A$107:$D$107
Name PARTIDABASE: 'Precio Equipos'!#REF!
Name PARTIDABASE: 'Rend. Equipos'!$A$7:$E$7
Name PARTIDABASE: 'Sub CONTRATOS'!$A$8:$E$8
Name PARTIDABASE: 'Mano de Obra'!$A$8:$D$8
Name TITULO: 'Mano de Obra'!#REF!
Name TITULO: Materiales!#REF!
Name TITULO: 'Precio Equipos'!$A$4
Name TITULO: 'Rend. Equipos'!$A$2
Name TITULO: 'Sub CONTRATOS'!#REF!

Sheet RESUMEN
F2: GG | I2: 0 | L2: Mes: | M2: DICIEMBRE
F3: BB | I3: 0 | L3: Año: | M3: 2024
L4: Revisado: | M4: MC
D5: ANALISIS DE PRECIO UNITARIO - RESUMEN
F6: PRECIO UNITARIO
F7: Unitario Materiales: | I7: Unitario Mano de Obra: | L7: Unitario Equipos: | O7: REND.
A8: CODIGO | B8: REV | C8: P | D8: DETALLE | E8: u | F8: MAT | I8: MO | L8: EQUIPOS | M8: TOTAL | O8: u/dia
B9: SI | C9: 32 | D9: =+VLOOKUP("Partida:",'P-32'!$A$7:$G$7,2,FALSE) -> Movimiento de suelos para bases c/ aporte de tosca (e: 40 cm en 2 capas de 20 cm) | E9: =+'P-32'!$C$9 -> m3 | F9: =+VLOOKUP(F$7,'P-32'!F11:G65536,2,FALSE) -> 12754.673 | I9: =+VLOOKUP(I$7,'P-32'!F11:G65536,2,FALSE) -> 6056.8068 | L9: =+VLOOKUP(L$7,'P-32'!F11:G65536,2,FALSE) -> 34605.5 | M9: =SUM(F9:L9) -> 53416.98 | O9: =+'P-32'!$F$9 -> 25
A10: ARQUIN21 | B10: SI | C10: 33 | D10: =+VLOOKUP("Partida:",'P-33'!$A$7:$G$7,2,FALSE) -> Ladrillo común 12,5 x 5,5 x 25 (e:15 cm) | E10: =+'P-33'!$C$9 -> m2 | F10: =+VLOOKUP(F$7,'P-33'!F11:G65539,2,FALSE) -> 12909.38 | I10: =+VLOOKUP(I$7,'P-33'!F11:G65539,2,FALSE) -> 20969.668 | L10: =+VLOOKUP(L$7,'P-33'!F11:G65539,2,FALSE) -> 504.28267 | M10: =SUM(F10:L10) -> 34383.331 | O10: =+'P-33'!$F$9 -> 7
A11: ARQUIN21 | B11: SI | C11: 34 | D11: =+VLOOKUP("Partida:",'P-34'!$A$7:$G$7,2,FALSE) -> Ladrillo cerámico 8 x 18 x 33 cm | E11: =+'P-34'!$C$9 -> m2 | F11: =+VLOOKUP(F$7,'P-34'!$F11:$G65539,2,FALSE) -> 6590.9962 | I11: =+VLOOKUP(I$7,'P-34'!$F11:$G65539,2,FALSE) -> 9785.8452 | L11: =+VLOOKUP(L$7,'P-34'!$F11:$G65539,2,FALSE) -> 235.33191 | M11: =SUM(F11:L11) -> 16612.173 | O11: =+'P-34'!$F$9 -> 15
A12: ARQUIN21 | B12: SI | C12: 35 | D12: =+VLOOKUP("Partida:",'P-35'!$A$7:$G$7,2,FALSE) -> Ladrillo cerámico 12 x 18 x 33 cm | E12: =+'P-35'!$C$9 -> m2 | F12: =+VLOOKUP(F$7,'P-35'!$F11:$G65539,2,FALSE) -> 8314.4981 | I12: =+VLOOKUP(I$7,'P-35'!$F11:$G65539,2,FALSE) -> 9785.8452 | L12: =+VLOOKUP(L$7,'P-35'!$F11:$G65539,2,FALSE) -> 235.33191 | M12: =SUM(F12:L12) -> 18335.675 | O12: =+'P-35'!$F$9 -> 15
A13: ARQUIN21 | B13: SI | C13: 36 | D13: =+VLOOKUP("Partida:",'P-36'!$A$7:$G$7,2,FALSE) -> Ladrillo cerámico 18 x 18 x 33 cm | E13: =+'P-36'!$C$9 -> m2 | F13: =+VLOOKUP(F$7,'P-36'!$F11:$G65539,2,FALSE) -> 11492.44 | I13: =+VLOOKUP(I$7,'P-36'!$F11:$G65539,2,FALSE) -> 9785.8452 | L13: =+VLOOKUP(L$7,'P-36'!$F11:$G65539,2,FALSE) -> 235.33191 | M13: =SUM(F13:L13) -> 21513.617 | O13: =+'P-36'!$F$9 -> 15
A14: ARQUIN21 | B14: SI | C14: 37 | D14: =+VLOOKUP("Partida:",'P-37'!$A$7:$G$7,2,FALSE) -> Pared DOBLE Comun / 5 / LHC 08 - (ladrillo a la vista) | E14: =+'P-37'!$C$9 -> m2 | F14: =+VLOOKUP(F$7,'P-37'!$F11:$G65553,2,FALSE) -> 27983.302 | I14: =+VLOOKUP(I$7,'P-37'!$F11:$G65553,2,FALSE) -> 35327.556 | L14: =+VLOOKUP(L$7,'P-37'!$F11:$G65553,2,FALSE) -> 882.49467 | M14: =SUM(F14:L14) -> 64193.353 | O14: =+'P-37'!$F$9 -> 4
A15: ARQUIN21 | B15: SI | C15: 38 | D15: =+VLOOKUP("Partida:",'P-38'!$A$7:$G$7,2,FALSE) -> Ladrillo hueco portante 12 x 19 x 33 | E15: =+'P-38'!$C$9 -> m2 | F15: =+VLOOKUP(F$7,'P-38'!$F11:$G65539,2,FALSE) -> 11547.894 | I15: =+VLOOKUP(I$7,'P-38'!$F11:$G65539,2,FALSE) -> 9785.8452 | L15: =+VLOOKUP(L$7,'P-38'!$F11:$G65539,2,FALSE) -> 235.33191 | M15: =SUM(F15:L15) -> 21569.071 | O15: =+'P-38'!$F$9 -> 15
A16: ARQUIN21 | B16: SI | C16: 39 | D16: =+VLOOKUP("Partida:",'P-39'!$A$7:$G$7,2,FALSE) -> Amure puertas tipo (0,90 x 2,00 m) | E16: =+'P-39'!$C$9 -> u | F16: =+VLOOKUP(F$7,'P-39'!$F11:$G65537,2,FALSE) -> 4066.3296 | I16: =+VLOOKUP(I$7,'P-39'!$F11:$G65537,2,FALSE) -> 55045.379 | L16: =+VLOOKUP(L$7,'P-39'!$F11:$G65537,2,FALSE) -> 405.54862 | M16: =SUM(F16:L16) -> 59517.257 | O16: =+'P-39'!$F$9 -> 2
A17: ARQUIN21 | B17: SI | C17: 40 | D17: =+VLOOKUP("Partida:",'P-40'!$A$7:$G$7,2,FALSE) -> Amure Premarcos | E17: =+'P-40'!$C$9 -> u | F17: =+VLOOKUP(F$7,'P-40'!$F11:$G65537,2,FALSE) -> 1487.907 | I17: =+VLOOKUP(I$7,'P-40'!$F11:$G65537,2,FALSE) -> 36696.919 | L17: =+VLOOKUP(L$7,'P-40'!$F11:$G65537,2,FALSE) -> 202.77431 | M17: =SUM(F17:L17) -> 38387.601 | O17: =+'P-40'!$F$9 -> 4
A18: ARQUIN21 | B18: SI | C18: 41 | D18: =+VLOOKUP("Partida:",'P-41'!$A$7:$G$7,2,FALSE) -> Amure barandas (insertos c/1,00 m) | E18: =+'P-41'!$C$9 -> ml | F18: =+VLOOKUP(F$7,'P-41'!$F11:$G65538,2,FALSE) -> 308.02446 | I18: =+VLOOKUP(I$7,'P-41'!$F11:$G65538,2,FALSE) -> 29357.536 | L18: =+VLOOKUP(L$7,'P-41'!$F11:$G65538,2,FALSE) -> 276.57623 | M18: =SUM(F18:L18) -> 29942.136 | O18: =+'P-41'!$F$9 -> 5
A19: ARQUIN21 | B19: SI | C19: 42 | D19: =+VLOOKUP("Partida:",'P-42'!$A$7:$G$7,2,FALSE) -> Azotado hidrófugo | E19: =+'P-42'!$C$9 -> m2 | F19: =+VLOOKUP(F$7,'P-42'!$F11:$G65537,2,FALSE) -> 809.61503 | I19: =+VLOOKUP(I$7,'P-42'!$F11:$G65537,2,FALSE) -> 3938.2618 | L19: =+VLOOKUP(L$7,'P-42'!$F11:$G65537,2,FALSE) -> 126.07067 | M19: =SUM(F19:L19) -> 4873.9475 | O19: =+'P-42'!$F$9 -> 28
A20: ARQUIN21 | B20: SI | C20: 43 | D20: =+VLOOKUP("Partida:",'P-43'!$A$7:$G$7,2,FALSE) -> Interior jaharro a la cal + Enlucido a la cal | E20: =+'P-43'!$C$9 -> m2 | F20: =+VLOOKUP(F$7,'P-43'!$F11:$G65540,2,FALSE) -> 2735.3164 | I20: =+VLOOKUP(I$7,'P-43'!$F11:$G65540,2,FALSE) -> 20914.412 | L20: =+VLOOKUP(L$7,'P-43'!$F11:$G65540,2,FALSE) -> 588.32978 | M20: =SUM(F20:L20) -> 24238.059 | O20: =+'P-43'!$F$9 -> 6
A21: ARQUIN21 | B21: SI | C21: 44 | D21: =+VLOOKUP("Partida:",'P-44'!$A$7:$G$7,2,FALSE) -> Revoque Grueso impermeable Exterior hasta 3.00 m - Incl. Azotado hidrófugo | E21: =+'P-44'!$C$9 -> m2 | F21: =+VLOOKUP(F$7,'P-44'!$F11:$G65540,2,FALSE) -> 4009.2266 | I21: =+VLOOKUP(I$7,'P-44'!$F11:$G65540,2,FALSE) -> 10647.256 | L21: =+VLOOKUP(L$7,'P-44'!$F11:$G65540,2,FALSE) -> 306.95467 | M21: =SUM(F21:L21) -> 14963.437 | O21: =+'P-44'!$F$9 -> 11.5
A22: ARQUIN21 | B22: SI | C22: 45 | D22: =+VLOOKUP("Partida:",'P-45'!$A$7:$G$7,2,FALSE) -> Revoque Grueso impermeable Exterior a mas de 3.00 m - Incl. Azotado hidrófugo | E22: =+'P-45'!$C$9 -> m2 | F22: =+VLOOKUP(F$7,'P-45'!$F11:$G65540,2,FALSE) -> 4009.2266 | I22: =+VLOOKUP(I$7,'P-45'!$F11:$G65540,2,FALSE) -> 15305.431 | L22: =+VLOOKUP(L$7,'P-45'!$F11:$G65540,2,FALSE) -> 769.31526 | M22: =SUM(F22:L22) -> 20083.973 | O22: =+'P-45'!$F$9 -> 8
A23: ARQUIN21 | B23: SI | C23: 46 | D23: =+VLOOKUP("Partida:",'P-46'!$A$7:$G$7,2,FALSE) -> Contrapiso HHRP | E23: =+'P-46'!$C$9 -> m3 | F23: =+VLOOKUP(F$7,'P-46'!$F11:$G65534,2,FALSE) -> 67465.639 | I23: =+VLOOKUP(I$7,'P-46'!$F11:$G65534,2,FALSE) -> 89504.217 | L23: =+VLOOKUP(L$7,'P-46'!$F11:$G65540,2,FALSE) -> 2317.4207 | M23: =SUM(F23:L23) -> 159287.28 | O23: =+'P-46'!$F$9 -> 1.4
A24: ARQUIN21 | B24: SI | C24: 47 | D24: =+VLOOKUP("Partida:",'P-47'!$A$7:$G$7,2,FALSE) -> Carpeta MC 1:3 (e: 2cm) | E24: =+'P-47'!$C$9 -> m2 | F24: =+VLOOKUP(F$7,'P-47'!$F11:$G65533,2,FALSE) -> 3388.608 | I24: =+VLOOKUP(I$7,'P-47'!$F11:$G65533,2,FALSE) -> 7554.2906 | L24: =+VLOOKUP(L$7,'P-47'!$F11:$G65533,2,FALSE) -> 216.2926 | M24: =SUM(F24:L24) -> 11159.191 | O24: =+'P-47'!$F$9 -> 15
A25: ARQUIN21 | B25: SI | C25: 48 | D25: =+VLOOKUP("Partida:",'P-48'!$A$7:$G$7,2,FALSE) -> Carpeta monolítico h = 7 cm | E25: =+'P-48'!$C$9 -> m2 | F25: =+VLOOKUP(F$7,'P-48'!$F11:$G65536,2,FALSE) -> 6968.0306 | I25: =+VLOOKUP(I$7,'P-48'!$F11:$G65536,2,FALSE) -> 10126.741 | L25: =+VLOOKUP(L$7,'P-48'!$F11:$G65536,2,FALSE) -> 120.04692 | M25: =SUM(F25:L25) -> 17214.819 | O25: =+'P-48'!$F$9 -> 35
A26: ARQUIN21 | B26: SI | C26: 49 | D26: =+VLOOKUP("Partida:",'P-49'!$A$7:$G$7,2,FALSE) -> Carpeta hidrófuga (e: 2 cm) | E26: =+'P-49'!$C$9 -> m2 | F26: =+VLOOKUP(F$7,'P-49'!$F11:$G65537,2,FALSE) -> 4048.0752 | I26: =+VLOOKUP(I$7,'P-49'!$F11:$G65537,2,FALSE) -> 7554.2906 | L26: =+VLOOKUP(L$7,'P-49'!$F11:$G65537,2,FALSE) -> 216.2926 | M26: =SUM(F26:L26) -> 11818.658 | O26: =+'P-49'!$F$9 -> 15
A27: ARQUIN21 | B27: SI | C27: 50 | D27: =+VLOOKUP("Partida:",'P-50'!$A$7:$G$7,2,FALSE) -> Cemento alisado o cilindrado (e: 3 cm) | E27: =+'P-50'!$C$9 -> m2 | F27: =+VLOOKUP(F$7,'P-50'!$F11:$G65538,2,FALSE) -> 4066.3296 | I27: =+VLOOKUP(I$7,'P-50'!$F11:$G65538,2,FALSE) -> 10118.034 | L27: =+VLOOKUP(L$7,'P-50'!$F11:$G65538,2,FALSE) -> 282.12078 | M27: =SUM(F27:L27) -> 14466.484 | O27: =+'P-50'!$F$9 -> 11.5
A28: ARQUIN21 | B28: SI | C28: 51 | D28: =+VLOOKUP("Partida:",'P-51'!$A$7:$G$7,2,FALSE) -> Látex interior para paredes (incl. enduido) | E28: =+'P-51'!$C$9 -> m2 | F28: =+VLOOKUP(F$7,'P-51'!$F11:$G65539,2,FALSE) -> 2923.7665 | I28: =+VLOOKUP(I$7,'P-51'!$F12:$G65539,2,FALSE) -> 7626.9744 | L28: =+VLOOKUP(L$7,'P-51'!$F11:$G65539,2,FALSE) -> 174.89809 | M28: =SUM(F28:L28) -> 10725.639 | O28: =+'P-51'!$F$9 -> 22
A29: ARQUIN21 | B29: SI | C29: 52 | D29: =+VLOOKUP("Partida:",'P-52'!$A$7:$G$7,2,FALSE) -> látex para cielorrasos (incl. enduido) | E29: =+'P-52'!$C$9 -> m2 | F29: =+VLOOKUP(F$7,'P-52'!$F11:$G65541,2,FALSE) -> 2923.7665 | I29: =+VLOOKUP(I$7,'P-52'!$F13:$G65540,2,FALSE) -> 8652.5811 | L29: =+VLOOKUP(L$7,'P-52'!$F11:$G65541,2,FALSE) -> 241.06769 | M29: =SUM(F29:L29) -> 11817.415 | O29: =+'P-52'!$F$9 -> 17.5
A30: ARQUIN21 | B30: SI | C30: 53 | D30: =+VLOOKUP("Partida:",'P-53'!$A$7:$G$7,2,FALSE) -> látex exterior para paredes hasta 3.00 m de altura | E30: =+'P-53'!$C$9 -> m2 | F30: =+VLOOKUP(F$7,'P-53'!$F11:$G65536,2,FALSE) -> 1824.9263 | I30: =+VLOOKUP(I$7,'P-53'!$F14:$G65541,2,FALSE) -> 5543.6837 | L30: =+VLOOKUP(L$7,'P-53'!$F11:$G65536,2,FALSE) -> 124.12123 | M30: =SUM(F30:L30) -> 7492.7312 | O30: =+'P-53'!$F$9 -> 15.5
A31: ARQUIN21 | B31: SI | C31: 53 bis | D31: =+VLOOKUP("Partida:",'P-53 bis'!$A$7:$G$7,2,FALSE) -> látex exterior para paredes a más 3.00 m de altura | E31: =+'P-53'!$C$9 -> m2 | F31: =+VLOOKUP(F$7,'P-53 bis'!$F12:$G65537,2,FALSE) -> 1824.9263 | I31: =+VLOOKUP(I$7,'P-53 bis'!$F15:$G65542,2,FALSE) -> 14504.13 | L31: =+VLOOKUP(L$7,'P-53 bis'!$F12:$G65537,2,FALSE) -> 234.44231 | M31: =SUM(F31:L31) -> 16563.498 | O31: =+'P-53 bis'!$F$9 -> 15.5
A32: ARQUIN21 | B32: SI | C32: 54 | D32: =+VLOOKUP("Partida:",'P-54'!$A$7:$G$7,2,FALSE) -> Esmalte sintético sobre carpintería metálica , herrería (cuando es vacio x lleno contemplar MAT al 60%) | E32: =+'P-54'!$C$9 -> m2 | F32: =+VLOOKUP(F$7,'P-54'!$F11:$G65536,2,FALSE) -> 2585.0849 | I32: =+VLOOKUP(I$7,'P-54'!$F15:$G65542,2,FALSE) -> 10740.887 | L32: =+VLOOKUP(L$7,'P-54'!$F11:$G65536,2,FALSE) -> 240.48488 | M32: =SUM(F32:L32) -> 13566.457 | O32: =+'P-54'!$F$9 -> 8
A33: ARQUIN21 | B33: SI | C33: 55 | D33: =+VLOOKUP("Partida:",'P-55'!$A$7:$G$7,2,FALSE) -> Revestimiento plastico texturado tipo Quimtex fino | E33: =+'P-55'!$C$9 -> m2 | F33: =+VLOOKUP(F$7,'P-55'!$F11:$G65541,2,FALSE) -> 6000.929 | I33: =+VLOOKUP(I$7,'P-55'!$F16:$G65543,2,FALSE) -> 11240.7 | L33: =+VLOOKUP(L$7,'P-55'!$F11:$G65541,2,FALSE) -> 181.69279 | M33: =SUM(F33:L33) -> 17423.322 | O33: =+'P-55'!$F$9 -> 20
A34: ARQUIN21 | B34: SI | C34: 56 | D34: =+VLOOKUP("Partida:",'P-56'!$A$7:$G$7,2,FALSE) -> Colocación porcelanato en pisos (no incluye baños) | E34: =+'P-56'!$C$9 -> m2 | F34: =+VLOOKUP(F$7,'P-56'!$F10:$G65540,2,FALSE) -> 7156.2986 | I34: =+VLOOKUP(I$7,'P-56'!$F18:$G65545,2,FALSE) -> 11647.705 | L34: =+VLOOKUP(L$7,'P-56'!$F10:$G65540,2,FALSE) -> 225.81275 | M34: =SUM(F34:L34) -> 19029.817 | O34: =+'P-56'!$F$9 -> 13
A35: ARQUIN21 | B35: SI | C35: 57 | D35: =+VLOOKUP("Partida:",'P-57'!$A$7:$G$7,2,FALSE) -> Revestimiento porcelanato en paredes y piso baños | E35: =+'P-57'!$C$9 -> m2 | F35: =+VLOOKUP(F$7,'P-57'!$F10:$G65541,2,FALSE) -> 7156.2986 | I35: =+VLOOKUP(I$7,'P-57'!$F19:$G65546,2,FALSE) -> 15142.017 | L35: =+VLOOKUP(L$7,'P-57'!$F10:$G65541,2,FALSE) -> 293.55657 | M35: =SUM(F35:L35) -> 22591.872 | O35: =+'P-57'!$F$9 -> 10
A36: ARQUIN21 | B36: SI | C36: 58 | D36: =+VLOOKUP("Partida:",'P-58'!$A$7:$G$7,2,FALSE) -> Colocacion de zocalo porcelanato | E36: =+'P-58'!$C$9 -> ml | F36: =+VLOOKUP(F$7,'P-58'!$F11:$G65541,2,FALSE) -> 1066.3432 | I36: =+VLOOKUP(I$7,'P-58'!$F11:$G65541,2,FALSE) -> 5047.339 | L36: =+VLOOKUP(L$7,'P-58'!$F11:$G65541,2,FALSE) -> 97.85219 | M36: =SUM(F36:L36) -> 6211.5344 | O36: =+'P-58'!$F$9 -> 30
A37: ARQUIN22 | B37: SI | C37: 59 | D37: =+VLOOKUP("Partida:",'P-59'!$A$7:$G$7,2,FALSE) -> Látex interior satinado para paredes | E37: =+'P-59'!$C$9 -> m2 | F37: =+VLOOKUP(F$7,'P-59'!$F11:$G65536,2,FALSE) -> 5093.055 | I37: =+VLOOKUP(I$7,'P-59'!$F12:$G65542,2,FALSE) -> 13765.47 | L37: =+VLOOKUP(L$7,'P-59'!$F11:$G65536,2,FALSE) -> 331.59136 | M37: =SUM(F37:L37) -> 19190.116 | O37: =+'P-59'!$F$9 -> 11
A38: ARQUIN23 | B38: SI | C38: 60 | D38: =+VLOOKUP("Partida:",'P-60'!$A$7:$G$7,2,FALSE) -> Cielorraso Durlock - Junta Tomada STD | E38: =+'P-60'!$C$9 -> m2 | F38: =+VLOOKUP(F$7,'P-60'!$F12:$G65537,2,FALSE) -> 10671.937 | I38: =+VLOOKUP(I$7,'P-60'!$F13:$G65543,2,FALSE) -> 15938.965 | L38: =+VLOOKUP(L$7,'P-60'!$F12:$G65537,2,FALSE) -> 263.73013 | M38: =SUM(F38:L38) -> 26874.632 | O38: =+'P-60'!$F$9 -> 9.5
A39: ARQUIN24 | B39: SI | C39: 61 | D39: =+VLOOKUP("Partida:",'P-61'!$A$7:$G$7,2,FALSE) -> Cielorraso Durlock - Junta Tomada RH | E39: =+'P-61'!$C$9 -> m2 | F39: =+VLOOKUP(F$7,'P-61'!$F13:$G65538,2,FALSE) -> 14660.055 | I39: =+VLOOKUP(I$7,'P-61'!$F14:$G65544,2,FALSE) -> 15938.965 | L39: =+VLOOKUP(L$7,'P-61'!$F13:$G65538,2,FALSE) -> 263.73013 | M39: =SUM(F39:L39) -> 30862.75 | O39: =+'P-61'!$F$9 -> 9.5
A40: ARQUIN25 | B40: SI | C40: 62 | D40: =+VLOOKUP("Partida:",'P-62'!$A$7:$G$7,2,FALSE) -> Cielorraso Durlock - Junta Tomada RF | E40: =+'P-62'!$C$9 -> m2 | F40: =+VLOOKUP(F$7,'P-62'!$F14:$G65539,2,FALSE) -> 13890.957 | I40: =+VLOOKUP(I$7,'P-62'!$F15:$G65545,2,FALSE) -> 15938.965 | L40: =+VLOOKUP(L$7,'P-62'!$F14:$G65539,2,FALSE) -> 263.73013 | M40: =SUM(F40:L40) -> 30093.652 | O40: =+'P-62'!$F$9 -> 9.5
A41: ARQUIN26 | B41: SI | C41: 63 | D41: =+VLOOKUP("Partida:",'P-63'!$A$7:$G$7,2,FALSE) -> Cielorraso Desmontable 60x60 - sin provision | E41: =+'P-63'!$C$9 -> m2 | F41: =+VLOOKUP(F$7,'P-63'!$F15:$G65540,2,FALSE) -> 5516.6996 | I41: =+VLOOKUP(I$7,'P-63'!$F16:$G65546,2,FALSE) -> 15142.017 | L41: =+VLOOKUP(L$7,'P-63'!$F15:$G65540,2,FALSE) -> 250.54362 | M41: =SUM(F41:L41) -> 20909.26 | O41: =+'P-63'!$F$9 -> 10
B42: SI | C42: 63 bis | D42: =+VLOOKUP("Partida:",'P-63 bis'!$A$7:$G$7,2,FALSE) -> Cielorraso Desmontable 60x60 - incluye placa Deco Vinyl | E42: =+'P-63 bis'!$C$9 -> m2 | F42: =+VLOOKUP(F$7,'P-63 bis'!$F17:$G65542,2,FALSE) -> 27431.696 | I42: =+VLOOKUP(I$7,'P-63 bis'!$F18:$G65548,2,FALSE) -> 15142.017 | L42: =+VLOOKUP(L$7,'P-63 bis'!$F17:$G65542,2,FALSE) -> 250.54362 | M42: =SUM(F42:L42) -> 42824.257 | O42: =+'P-63 bis'!$F$9 -> 10
A43: ARQUIN27 | B43: SI | C43: 64 | D43: =+VLOOKUP("Partida:",'P-64'!$A$7:$G$7,2,FALSE) -> Pared Durlock - Simple | E43: =+'P-64'!$C$9 -> m2 | F43: =+VLOOKUP(F$7,'P-64'!$F11:$G65536,2,FALSE) -> 16385.365 | I43: =+VLOOKUP(I$7,'P-64'!$F18:$G65548,2,FALSE) -> 21631.453 | L43: =+VLOOKUP(L$7,'P-64'!$F17:$G65542,2,FALSE) -> 347.90531 | M43: =SUM(F43:L43) -> 38364.723 | O43: =+'P-64'!$F$9 -> 7
A44: ARQUIN28 | B44: SI | C44: 65 | D44: =+VLOOKUP("Partida:",'P-65'!$A$7:$G$7,2,FALSE) -> Pared Durlock - Doble placa STD ambas caras y asilación lana de vidrio | E44: =+'P-65'!$C$9 -> m2 | F44: =+VLOOKUP(F$7,'P-65'!$F12:$G65538,2,FALSE) -> 30235.033 | I44: =+VLOOKUP(I$7,'P-65'!$F20:$G65550,2,FALSE) -> 25236.695 | L44: =+VLOOKUP(L$7,'P-65'!$F19:$G65544,2,FALSE) -> 405.88953 | M44: =SUM(F44:L44) -> 55877.617 | O44: =+'P-65'!$F$9 -> 6
A45: ARQUIN29 | B45: SI | C45: 66 | D45: =+VLOOKUP("Partida:",'P-66'!$A$7:$G$7,2,FALSE) -> Medio tabique espesor total 8,5 cm | E45: =+'P-66'!$C$9 -> m2 | F45: =+VLOOKUP(F$7,'P-66'!$F13:$G65539,2,FALSE) -> 11458.429 | I45: =+VLOOKUP(I$7,'P-66'!$F21:$G65551,2,FALSE) -> 13765.47 | L45: =+VLOOKUP(L$7,'P-65'!$F20:$G65545,2,FALSE) -> 405.88953 | M45: =SUM(F45:L45) -> 25629.789 | O45: =+'P-66'!$F$9 -> 11
A46: ARQUIN30 | B46: SI | C46: 67 | D46: =+VLOOKUP("Partida:",'P-67'!$A$7:$G$7,2,FALSE) -> Esmalte sintetico para paredes | E46: =+'P-67'!$C$9 -> m2 | F46: =+VLOOKUP(F$7,'P-67'!$F11:$G65538,2,FALSE) -> 2867.72 | I46: =+VLOOKUP(I$7,'P-67'!$F11:$G65538,2,FALSE) -> 7571.0084 | L46: =+VLOOKUP(L$7,'P-67'!$F11:$G65538,2,FALSE) -> 96.193952 | M46: =SUM(F46:L46) -> 10534.922 | O46: =+'P-67'!$F$9 -> 20
A47: ARQUIN31 | B47: SI | C47: 68 | D47: =+VLOOKUP("Partida:",'P-68'!$A$7:$G$7,2,FALSE) -> Ladrillo Klimablock 27 x 19 x 30 cm | E47: =+'P-68'!$C$9 -> m2 | F47: =+VLOOKUP(F$7,'P-68'!$F11:$G65538,2,FALSE) -> 3673.9149 | I47: =+VLOOKUP(I$7,'P-68'!$F11:$G65538,2,FALSE) -> 9785.8452 | L47: =+VLOOKUP(L$7,'P-68'!$F11:$G65538,2,FALSE) -> 235.33191 | M47: =SUM(F47:L47) -> 13695.092 | O47: =+'P-68'!$F$9 -> 15
A48: ARQUIN33 | B48: SI | C48: 70 | D48: =+VLOOKUP("Partida:",'P-70'!$A$7:$G$7,2,FALSE) -> Impermeabilización de cubierta transitable sobre carpeta horizontal con membrana Geotextil de 4mm, a soplete. | E48: =+'P-70'!$C$9 -> m2 | F48: =+VLOOKUP(F$7,'P-70'!$F10:$G65542,2,FALSE) -> 9769.1538 | I48: =+VLOOKUP(I$7,'P-70'!$F10:$G65542,2,FALSE) -> 5871.5071 | L48: =+VLOOKUP(L$7,'P-70'!$F10:$G65542,2,FALSE) -> 32.180227 | M48: =SUM(F48:L48) -> 15672.841 | O48: =+'P-70'!$F$9 -> 25
A49: ARQUIN34 | B49: SI | C49: 71 | D49: =+VLOOKUP("Partida:",'P-71'!$A$7:$G$7,2,FALSE) -> Impermeabilización de cubierta con Malla no tejida de poliester y pintura poliuretánica | E49: =+'P-71'!$C$9 -> m2 | F49: =+VLOOKUP(F$7,'P-71'!$F10:$G65541,2,FALSE) -> 7823.6499 | I49: =+VLOOKUP(I$7,'P-71'!$F10:$G65541,2,FALSE) -> 2935.7536 | L49: =+VLOOKUP(L$7,'P-71'!$F10:$G65541,2,FALSE) -> 37.276481 | M49: =SUM(F49:L49) -> 10796.68 | O49: =+'P-71'!$F$9 -> 50
A50: ARQUIN35 | B50: SI | C50: 72 | D50: =+VLOOKUP("Partida:",'P-72'!$A$7:$G$7,2,FALSE) -> Revoque Exterior 3 en 1 hasta 3,00 m | E50: =+'P-72'!$C$9 -> m2 | F50: =+VLOOKUP(F$7,'P-72'!$F11:$G65534,2,FALSE) -> 12898.27 | I50: =+VLOOKUP(I$7,'P-72'!$F11:$G65534,2,FALSE) -> 6934.6011 | L50: =+VLOOKUP(L$7,'P-72'!$F11:$G65534,2,FALSE) -> 1253.0947 | M50: =SUM(F50:L50) -> 21085.966 | O50: =+'P-72'!$F$9 -> 35
A51: ARQUIN36 | B51: SI | C51: 73 | D51: =+VLOOKUP("Partida:",'P-73'!$A$7:$G$7,2,FALSE) -> Pintura sobre pared existente | E51: =+'P-73'!$C$9 -> m2 | F51: =+VLOOKUP(F$7,'P-73'!$F11:$G65535,2,FALSE) -> 2207.5713 | I51: =+VLOOKUP(I$7,'P-73'!$F12:$G65535,2,FALSE) -> 4296.3549 | L51: =+VLOOKUP(L$7,'P-73'!$F11:$G65535,2,FALSE) -> 96.193952 | M51: =SUM(F51:L51) -> 6600.1201 | O51: =+'P-73'!$F$9 -> 20
A52: ARQUIN37 | B52: SI | C52: 74 | D52: =+VLOOKUP("Partida:",'P-74'!$A$7:$G$7,2,FALSE) -> Impermeabilizacion sobre ladrillo | E52: =+'P-74'!$C$9 -> m2 | F52: =+VLOOKUP(F$7,'P-74'!$F11:$G65533,2,FALSE) -> 2089.0826 | I52: =+VLOOKUP(I$7,'P-74'!$F13:$G65536,2,FALSE) -> 5047.339 | L52: =+VLOOKUP(L$7,'P-74'!$F11:$G65533,2,FALSE) -> 62.127468 | M52: =SUM(F52:L52) -> 7198.5491 | O52: =+'P-74'!$F$9 -> 30
A53: ARQUIN38 | B53: SI | C53: 75 | D53: ladrillo cerámico 12 x 19 x 33 cm - PORTANTE | E53: =+'P-74'!$C$9 -> m2 | F53: =+VLOOKUP(F$7,'P-75'!$F11:$G65539,2,FALSE) -> 14279.307 | I53: =+VLOOKUP(I$7,'P-75'!$F11:$G65539,2,FALSE) -> 10094.678 | L53: =+VLOOKUP(L$7,'P-75'!$F11:$G65539,2,FALSE) -> 235.33191 | M53: =SUM(F53:L53) -> 24609.317 | O53: =+'P-75'!$F$9 -> 15
A54: ARQUIN41 | B54: SI | C54: 113 | D54: =+VLOOKUP("Partida:",'P-113'!$A$7:$G$7,2,FALSE) -> Impermeabilizacion de azotea con pintura asfaltica / Barrera de vapor | E54: m2 | F54: =+VLOOKUP(F$7,'P-113'!$F11:$G65539,2,FALSE) -> 1256.6125 | I54: =+VLOOKUP(I$7,'P-113'!$F11:$G65539,2,FALSE) -> 1834.846 | L54: =+VLOOKUP(L$7,'P-113'!$F11:$G65539,2,FALSE) -> 10.056321 | M54: =SUM(F54:L54) -> 3101.5148 | O54: =+'P-113'!$F$9 -> 80
A55: ARQUIN42 | B55: SI | C55: 114 | D55: =+VLOOKUP("Partida:",'P-114'!$A$7:$G$7,2,FALSE) -> Babeta en Azotea con membrana Geotextil Ormiflex de 4mm, a soplete. | E55: m | F55: =+VLOOKUP(F$7,'P-114'!$F11:$G65542,2,FALSE) -> 4402.5269 | I55: =+VLOOKUP(I$7,'P-114'!$F11:$G65542,2,FALSE) -> 2446.4613 | L55: =+VLOOKUP(L$7,'P-114'!$F11:$G65542,2,FALSE) -> 13.408428 | M55: =SUM(F55:L55) -> 6862.3966 | O55: =+'P-114'!$F$9 -> 60
A56: ARQUIN43 | B56: NO | C56: 115 | D56: =+VLOOKUP("Partida:",'P-115'!$A$7:$G$7,2,FALSE) -> Revoque Grueso Exterior S/hidrofugo hasta 3.00 m | E56: m2 | F56: =+VLOOKUP(F$7,'P-115'!$F11:$G65536,2,FALSE) -> 2919.7378 | I56: =+VLOOKUP(I$7,'P-115'!$F11:$G65536,2,FALSE) -> 9785.8452 | L56: =+VLOOKUP(L$7,'P-115'!$F11:$G65536,2,FALSE) -> 0 | M56: =SUM(F56:L56) -> 12705.583 | O56: =+'P-115'!$F$9 -> 15
A57: ARQUIN44 | B57: SI | C57: 116 | D57: =+VLOOKUP("Partida:",'P-116'!$A$7:$G$7,2,FALSE) -> Cielorraso Desmontable 120x60 - incluye placa | E57: m2 | F57: =+VLOOKUP(F$7,'P-116'!$F11:$G65537,2,FALSE) -> 14768.589 | I57: =+VLOOKUP(I$7,'P-116'!$F11:$G65537,2,FALSE) -> 12618.347 | L57: =+VLOOKUP(L$7,'P-116'!$F12:$G65537,2,FALSE) -> 208.78635 | M57: =SUM(F57:L57) -> 27595.722 | O57: =+'P-116'!$F$9 -> 12
A58: ARQUIN45 | B58: SI | C58: 117 | D58: =+VLOOKUP("Partida:",'P-117'!$A$7:$G$7,2,FALSE) -> Perfil buña Z / Cantonera | E58: ml | F58: =+VLOOKUP(F$7,'P-117'!$F11:$G65536,2,FALSE) -> 1062.8718 | I58: =+VLOOKUP(I$7,'P-117'!$F11:$G65536,2,FALSE) -> 5728.4731 | L58: =+VLOOKUP(L$7,'P-117'!$F13:$G65538,2,FALSE) -> 167.02908 | M58: =SUM(F58:L58) -> 6958.374 | O58: =+'P-117'!$F$9 -> 15
A59: ARQUIN46 | B59: SI | C59: 118 | D59: =+VLOOKUP("Partida:",'P-118'!$A$7:$G$7,2,FALSE) -> Bloque de Hormigon 10 x 19 x 39 | E59: m2 | F59: =+VLOOKUP(F$7,'P-118'!$F11:$G65537,2,FALSE) -> 11007.236 | I59: =+VLOOKUP(I$7,'P-118'!$F11:$G65537,2,FALSE) -> 11441.09 | L59: =+VLOOKUP(L$7,'P-118'!$F11:$G65537,2,FALSE) -> 306.95467 | M59: =SUM(F59:L59) -> 22755.28 | O59: =+'P-118'!$F$9 -> 11.5
A60: ARQUIN47 | B60: SI | C60: 119 | D60: =+VLOOKUP("Partida:",'P-119'!$A$7:$G$7,2,FALSE) -> Bloque de Hormigon 19 x 19 x 39 | E60: m2 | F60: =+VLOOKUP(F$7,'P-119'!$F12:$G65538,2,FALSE) -> 15699.181 | I60: =+VLOOKUP(I$7,'P-119'!$F12:$G65538,2,FALSE) -> 11441.09 | L60: =+VLOOKUP(L$7,'P-119'!$F12:$G65538,2,FALSE) -> 306.95467 | M60: =SUM(F60:L60) -> 27447.225 | O60: =+'P-119'!$F$9 -> 11.5
A61: ARQUIN48 | B61: SI | C61: 120 | D61: =+VLOOKUP("Partida:",'P-120'!$A$7:$G$7,2,FALSE) -> BOCA ILUMINACIÓN | E61: ml | F61: =+VLOOKUP(F$7,'P-120'!$F13:$G65540,2,FALSE) -> 17867.355 | I61: =+VLOOKUP(I$7,'P-120'!$F13:$G65540,2,FALSE) -> 45165.439 | L61: =+VLOOKUP(L$7,'P-120'!$F13:$G65541,2,FALSE) -> 1667.318 | M61: =SUM(F61:L61) -> 64700.113 | O61: =+'P-120'!$F$9 -> 3.25
A62: ARQUIN49 | B62: SI | C62: 121 | D62: =+VLOOKUP("Partida:",'P-121'!$A$7:$G$7,2,FALSE) -> BOCA TOMACORRIENTE | E62: ml | F62: =+VLOOKUP(F$7,'P-121'!$F14:$G65544,2,FALSE) -> 14804.664 | I62: =+VLOOKUP(I$7,'P-121'!$F14:$G65541,2,FALSE) -> 45165.439 | L62: =+VLOOKUP(L$7,'P-121'!$F14:$G65542,2,FALSE) -> 1667.318 | M62: =SUM(F62:L62) -> 61637.422 | O62: =+'P-121'!$F$9 -> 3.25
A63: ARQUIN50 | B63: SI | C63: 122 | D63: =+VLOOKUP("Partida:",'P-122'!$A$7:$G$7,2,FALSE) -> BANDEJA PORTACABLES 200 | E63: ml | F63: =+VLOOKUP(F$7,'P-122'!$F15:$G65543,2,FALSE) -> 17891.691 | I63: =+'Sub CONTRATOS'!E44 -> 9545.7249 | L63: =+VLOOKUP(L$7,'P-122'!$F15:$G65541,2,FALSE) -> 0 | M63: =SUM(F63:L63) -> 27437.416 | O63: =+'P-122'!$F$9 -> 12
A64: ARQUIN51 | B64: NO | C64: 123 | D64: =+VLOOKUP("Partida:",'P-123'!$A$7:$G$7,2,FALSE) -> COLUMNA HORMIGÓN RÚSTICO 85 kg/m3 | E64: m3 | M64: =SUM(F64:L64) -> 0
A65: ARQUIN52 | B65: NO | C65: 124 | D65: =+VLOOKUP("Partida:",'P-124'!$A$7:$G$7,2,FALSE) -> COLUMNA HORMIGÓN VISTO | E65: m3 | M65: =SUM(F65:L65) -> 0
B66: NO | C66: 125 | D66: Viga de hormigon rustico 180 kg/m3 | M66: =SUM(F66:L66) -> 0
B67: NO | C67: 126 | D67: Viga | M67: =SUM(F67:L67) -> 0
B68: NO | C68: 127 | D68: Losa de hormigon rustico | M68: =SUM(F68:L68) -> 0
B69: NO | C69: 128 | D69: Losa | M69: =SUM(F69:L69) -> 0
B70: NO | C70: 129 | D70: Tabique de hormigon rustico 80 kg/m3 | M70: =SUM(F70:L70) -> 0
B71: NO | C71: 130 | D71: Tabique de hormigon visto 80 kg/m3 | M71: =SUM(F71:L71) -> 0
B72: NO | C72: 131 | D72: Escalera de hormigon rustico 75 kg/m3 | M72: =SUM(F72:L72) -> 0
B73: NO | C73: 132 | D73: Bases asiladas 60 kg/m3 | M73: =SUM(F73:L73) -> 0
B74: NO | C74: 133 | D74: Vigas de fundacion 60 kg/m3 | M74: =SUM(F74:L74) -> 0
B75: SI | C75: 134 | D75: =+VLOOKUP("Partida:",'P-134'!$A$7:$G$7,2,FALSE) -> Revoque grueso para interiores | E75: m2 | F75: =+VLOOKUP(F$7,'P-134'!$F10:$G65555,2,FALSE) -> 1531.6544 | I75: =+VLOOKUP(I$7,'P-134'!$F10:$G65552,2,FALSE) -> 7309.5852 | L75: =+VLOOKUP(L$7,'P-134'!$F10:$G65555,2,FALSE) -> 158.79529 | M75: =SUM(F75:L75) -> 9000.0348 | O75: =+'P-134'!$F$9 -> 18
B76: SI | C76: 135 | D76: Revoque fino a la cal | E76: m2 | F76: =+VLOOKUP(F$7,'P-135'!$F11:$G65556,2,FALSE) -> 1203.662 | I76: =+VLOOKUP(I$7,'P-135'!$F11:$G65553,2,FALSE) -> 13604.827 | L76: =+VLOOKUP(L$7,'P-135'!$F11:$G65556,2,FALSE) -> 423.95205 | M76: =SUM(F76:L76) -> 15232.441 | O76: =+'P-135'!$F$9 -> 9
B77: SI | C77: 136 | D77: =+VLOOKUP("Partida:",'P-136'!$A$7:$G$7,2,FALSE) -> Carpeta cal reforzada (e: 1,5 cm) | E77: m2 | F77: =+VLOOKUP(F$7,'P-136'!$F12:$G65554,2,FALSE) -> 2717.5179 | I77: =+VLOOKUP(I$7,'P-136'!$F12:$G65554,2,FALSE) -> 7814.7833 | L77: =+VLOOKUP(L$7,'P-136'!$F12:$G65554,2,FALSE) -> 223.75096 | M77: =SUM(F77:L77) -> 10756.052 | O77: =+'P-136'!$F$9 -> 14.5
B78: SI | C78: 137 | D78: =+VLOOKUP("Partida:",'P-137'!$A$7:$G$7,2,FALSE) -> Látex interior para paredes (enduido parcial) | E78: m2 | F78: =+VLOOKUP(F$7,'P-137'!$F13:$G65560,2,FALSE) -> 2272.0787 | I78: =+VLOOKUP(I$7,'P-137'!$F13:$G65560,2,FALSE) -> 4296.3549 | L78: =+VLOOKUP(L$7,'P-137'!$F13:$G65560,2,FALSE) -> 96.193952 | M78: =SUM(F78:L78) -> 6664.6275 | O78: =+'P-137'!$F$9 -> 20
B79: NO | C79: 138 | D79: Pared simple con aislacion de lana de vidrio
B80: NO | C80: 139 | D80: Yeso pared
B81: NO | C81: 140 | D81: Yeso en cielorraso
B82: NO | C82: 141 | D82: Cemento alisado
B83: NO | C83: 142 | D83: =+VLOOKUP("Partida:",'P-72'!$A$7:$G$7,2,FALSE) -> Revoque Exterior 3 en 1 hasta 3,00 m
B84: NO | C84: 143 | D84: REVOQUE 2 EN 1 hasta 3,00 m
B85: NO | C85: 144 | D85: REVOQUE 2 EN 1 a mas 3,00 m
B86: NO | C86: 145 | D86: Muro retak
B87: SI | C87: 146 | D87: =+VLOOKUP("Partida:",'P-146'!$A$7:$G$7,2,FALSE) -> Látex interior para paredes (s/enduido) | E87: m2 | F87: =+VLOOKUP(F$7,'P-146'!$F13:$G65569,2,FALSE) -> 2141.693 | I87: =+VLOOKUP(I$7,'P-146'!$F19:$G65569,2,FALSE) -> 3437.0839 | L87: =+VLOOKUP(L$7,'P-146'!$F11:$G65569,2,FALSE) -> 76.955162 | M87: =SUM(F87:L87) -> 5655.732 | O87: =+'P-146'!$F$9 -> 25
A88: ARQUIN49 | B88: SI | C88: 147 | D88: =+VLOOKUP("Partida:",'P-147'!$A$7:$G$7,2,FALSE) -> BOCA ILUMINACIÓN LOSA (Profunda) | E88: u | F88: =+VLOOKUP(F$7,'P-147'!$F11:$G65570,2,FALSE) -> 20340.181 | I88: =+VLOOKUP(I$7,'P-147'!$F11:$G65567,2,FALSE) -> 45165.439 | L88: =+VLOOKUP(L$7,'P-147'!$F11:$G65568,2,FALSE) -> 1667.318 | M88: =SUM(F88:L88) -> 67172.938 | O88: =+'P-147'!$F$9 -> 3.25
A89: ARQUIN49 | B89: SI | C89: 148 | D89: =+VLOOKUP("Partida:",'P-148'!$A$7:$G$7,2,FALSE) -> BOCA TOMACORRIENTE ESPECIAL | E89: u | F89: =+VLOOKUP(F$7,'P-148'!$F11:$G65571,2,FALSE) -> 34429.495 | I89: =+VLOOKUP(I$7,'P-148'!$F11:$G65568,2,FALSE) -> 45165.439 | L89: =+VLOOKUP(L$7,'P-147'!$F11:$G65569,2,FALSE) -> 1667.318 | M89: =SUM(F89:L89) -> 81262.252 | O89: =+'P-148'!$F$9 -> 3.25
A90: ARQUIN49 | B90: SI | C90: 148 | D90: =+VLOOKUP("Partida:",'P-149'!$A$7:$G$7,2,FALSE) -> BOCA VACIA C/CABLE TESTIGO | E90: u | F90: =+VLOOKUP(F$7,'P-149'!$F11:$G65572,2,FALSE) -> 12087.904 | I90: =+VLOOKUP(I$7,'P-149'!$F11:$G65569,2,FALSE) -> 29357.536 | L90: =+VLOOKUP(L$7,'P-149'!$F11:$G65570,2,FALSE) -> 1083.7567 | M90: =SUM(F90:L90) -> 42529.197 | O90: =+'P-149'!$F$9 -> 5

Sheet Rend. Equipos
A2: EQUIPOS
B3: Fecha: | C3: 45631
H5: 360
A6: Código | B6: DESCRIPCION | C6: P unit | D6: Cant | E6: Costo (referencial) | G6: Años | H6: Dias | I6: $ x dia | J6: % Deprec.
A7: *ANDAM05 | B7: ANDAMIO TUBULAR DE UNO A TRES CUERPOS | E7: =+SUM(E8:E10) -> 1028123.1 | G7: 5 | H7: =+G7*$H$5 -> 1800 | I7: =+E7/H7 -> 571.17949 | J7: =+I7/E7 -> 0.00055555556
B8: Andamio reforzado tubular 2,5 mts | C8: =VLOOKUP(B8,'Precio Equipos'!B:C,2,0) -> 237068.27 | D8: 3 | E8: =+C8*D8 -> 711204.81
B9: Tablon Para Andamio 2,5 M Metalico Antideslizante Tca Duroll | C9: =VLOOKUP(B9,'Precio Equipos'!B:C,2,0) -> 94209.625 | D9: 2 | E9: =+C9*D9 -> 188419.25
B10: Rueda para andamio giratoria c/freno | C10: =VLOOKUP(B10,'Precio Equipos'!B:C,2,0) -> 32124.755 | D10: 4 | E10: =+C10*D10 -> 128499.02
A11: EQALBA | B11: EQUIPO DE ALBAÑILERIA, carpetas, ladrillo | E11: =+SUM(E12:E31) -> 2470106.6 | G11: 3 | H11: =+G11*$H$5 -> 1080 | I11: =+E11/H11 -> 2287.1357 | J11: =+I11/E11 -> 0.00092592593
B12: REGLA ALUMINIO 6,00MTS | C12: =VLOOKUP(B12,'Precio Equipos'!B:C,2,0) -> 238945.46 | D12: 2 | E12: =+C12*D12 -> 477890.91
B13: Amoladora 4 1/2 850 w - BOSCH | C13: =VLOOKUP(B13,'Precio Equipos'!B:C,2,0) -> 137903.31 | D13: 1 | E13: =+C13*D13 -> 137903.31
B14: Rotopercutor RPK-32KA - BAROVO (5 kg) | C14: =VLOOKUP(B14,'Precio Equipos'!B:C,2,0) -> 180879.68 | D14: 1 | E14: =+C14*D14 -> 180879.68
B15: Sierra circular 7 1/4 - BOSCH | C15: =VLOOKUP(B15,'Precio Equipos'!B:C,2,0) -> 396998.4 | D15: 1 | E15: =+C15*D15 -> 396998.4
B16: Nivel Laser Dewalt Auto.alc.30mt 4p | C16: =VLOOKUP(B16,'Precio Equipos'!B:C,2,0) -> 832041.76 | D16: 0.5 | E16: =+C16*D16 -> 416020.88
B17: PALA FORJADA ANCHA - Gherardi | C17: =VLOOKUP(B17,'Precio Equipos'!B:C,2,0) -> 53370.69 | D17: 2 | E17: =+C17*D17 -> 106741.38
B18: PALA FORJADA DE PUNTA - Gherardi | C18: =VLOOKUP(B18,'Precio Equipos'!B:C,2,0) -> 53370.69 | D18: 2 | E18: =+C18*D18 -> 106741.38
B19: Carretilla Duroll 100 Litros Chapa 16 Profesional Rueda Maciza | C19: =VLOOKUP(B19,'Precio Equipos'!B:C,2,0) -> 107853.34 | D19: 1 | E19: =+C19*D19 -> 107853.34
B20: RUEDA MACIZA CARRETILLA C100DU | C20: =VLOOKUP(B20,'Precio Equipos'!B:C,2,0) -> 15556.499 | D20: 1 | E20: =+C20*D20 -> 15556.499
B21: FRATACHO DE ALGARROBO DE 30 CM | C21: =VLOOKUP(B21,'Precio Equipos'!B:C,2,0) -> 4646.285 | D21: 6 | E21: =+C21*D21 -> 27877.71
B22: Llana de yesero 12 x 30 cm | C22: =VLOOKUP(B22,'Precio Equipos'!B:C,2,0) -> 13904.259 | D22: 2 | E22: =+C22*D22 -> 27808.517
B23: CUCHARA ALBAÑIL FORJADA 6″ | C23: =VLOOKUP(B23,'Precio Equipos'!B:C,2,0) -> 18146.757 | D23: 2 | E23: =+C23*D23 -> 36293.514
... B31: Rodillo de bronce para cementista grande 17 cm | C31: =VLOOKUP(B31,'Precio Equipos'!B:C,2,0) -> 72426.909 | D31: 1 | E31: =+C31*D31 -> 72426.909
A32: EQCERAMI | B32: EQUIPO PARA COLOCACION DE CERAMICA | E32: =+SUM(E33:E46) -> 1424056.6 | G32: 1.5 | H32: =+G32*$H$5 -> 540 | I32: =+E32/H32 -> 2637.1418 | J32: =+I32/E32 -> 0.0018518519
B33: Amoladora 4 1/2 850 w - BOSCH | C33: =VLOOKUP(B33,'Precio Equipos'!B:C,2,0) -> 137903.31 | D33: 1 | E33: =+C33*D33 -> 137903.31
B34: MEZCLADOR ELECTRICO 2V. 50HZ 1200W | C34: =VLOOKUP(B34,'Precio Equipos'!B:C,2,0) -> 143732.28 | D34: 1 | E34: =+C34*D34 -> 143732.28
B35: Nivel Laser Dewalt Auto.alc.30mt 4p | C35: =VLOOKUP(B35,'Precio Equipos'!B:C,2,0) -> 832041.76 | D35: 1 | E35: =+C35*D35 -> 832041.76
B36: Rodillera de seguridad goma espuma | C36: =VLOOKUP(B36,'Precio Equipos'!B:C,2,0) -> 6903.8056 | D36: 3 | E36: =+C36*D36 -> 20711.417
B37: Martillo Maza De Goma | C37: =VLOOKUP(B37,'Precio Equipos'!B:C,2,0) -> 8898.892 | D37: 1 | E37: =+C37*D37 -> 8898.892
B38: LLANA DENTADA DE 12 X 12 CMS | C38: =VLOOKUP(B38,'Precio Equipos'!B:C,2,0) -> 13983.677 | D38: 2 | E38: =+C38*D38 -> 27967.355
B39: CUCHARA ALBAÑIL FORJADA 6″ | C39: =VLOOKUP(B39,'Precio Equipos'!B:C,2,0) -> 18146.757 | D39: 2 | E39: =+C39*D39 -> 36293.514
B40: BALDE ALBAÑIL PLÁSTICO – MANIJA PLÁSTICA – BAE | C40: =VLOOKUP(B40,'Precio Equipos'!B:C,2,0) -> 2097.2847 | D40: 6 | E40: =+C40*D40 -> 12583.708
B41: Lapiz carpintero 18 cm | C41: =VLOOKUP(B41,'Precio Equipos'!B:C,2,0) -> 1387.6932 | D41: 12 | E41: =+C41*D41 -> 16652.318
B42: CHOCLA PARA ALBAÑIL C/RECIPIENTE CON TIZA - DUROLL | C42: =VLOOKUP(B42,'Precio Equipos'!B:C,2,0) -> 4206.1727 | D42: 1 | E42: =+C42*D42 -> 4206.1727
B43: CINTA METRICA 510 RETROFLEX 10MTS - Evel | C43: =VLOOKUP(B43,'Precio Equipos'!B:C,2,0) -> 26993.867 | D43: 1 | E43: =+C43*D43 -> 26993.867
B44: Metro madera | C44: =VLOOKUP(B44,'Precio Equipos'!B:C,2,0) -> 4852.6243 | D44: 1 | E44: =+C44*D44 -> 4852.6243
... B46: RODEL RUEDITA 8MM P/C 1958 | C46: =VLOOKUP(B46,'Precio Equipos'!B:C,2,0) -> 39721.703 | D46: 3 | E46: =+C46*D46 -> 119165.11
A47: *EQUIP09 | B47: EQUIPO PARA INSTALACION ELECTRICA | E47: =+SUM(E48:E61) -> 2734071.2 | G47: 1.5 | H47: =+G47*$H$5 -> 540 | I47: =+E47/H47 -> 5063.0948 | J47: =+I47/E47 -> 0.0018518519
B48: Amoladora 4 1/2 850 w - BOSCH | C48: =VLOOKUP(B48,'Precio Equipos'!B:C,2,0) -> 137903.31 | D48: 1 | E48: =+C48*D48 -> 137903.31
B49: Rotopercutor RPK-32KA - BAROVO (5 kg) | C49: =VLOOKUP(B49,'Precio Equipos'!B:C,2,0) -> 180879.68 | D49: 1 | E49: =+C49*D49 -> 180879.68
B50: Taladro Percutor/Atornillador de 1/2″ (13mm) Inalámbrico 20V + 2 Baterías + Cargador + Maletín | C50: =VLOOKUP(B50,'Precio Equipos'!B:C,2,0) -> 555611 | D50: 1 | E50: =+C50*D50 -> 555611
B51: Nivel Laser Dewalt Auto.alc.30mt 4p | C51: =VLOOKUP(B51,'Precio Equipos'!B:C,2,0) -> 832041.76 | D51: 1 | E51: =+C51*D51 -> 832041.76
B52: Set de herramientas profesional duroll - S88PD | C52: =VLOOKUP(B52,'Precio Equipos'!B:C,2,0) -> 248336.44 | D52: 1 | E52: =+C52*D52 -> 248336.44
B53: TESTER 8EN1 AC/DC 6/380V | C53: =VLOOKUP(B53,'Precio Equipos'!B:C,2,0) -> 12314.379 | D53: 1 | E53: =+C53*D53 -> 12314.379
B54: Pinza amperométrica digital | C54: =VLOOKUP(B54,'Precio Equipos'!B:C,2,0) -> 14574.461 | D54: 1 | E54: =+C54*D54 -> 14574.461
B55: CINTA PASACABLE ALMA DE ACERO X 10MTS | C55: =VLOOKUP(B55,'Precio Equipos'!B:C,2,0) -> 6946.8561 | D55: 1 | E55: =+C55*D55 -> 6946.8561
B56: CINTA PASACABLE ALMA DE ACERO X 15 MTS | C56: =VLOOKUP(B56,'Precio Equipos'!B:C,2,0) -> 9385.7055 | D56: 1 | E56: =+C56*D56 -> 9385.7055
B57: CINTA METRICA 510 RETROFLEX 10MTS - Evel | C57: =VLOOKUP(B57,'Precio Equipos'!B:C,2,0) -> 26993.867 | D57: 2 | E57: =+C57*D57 -> 53987.733
B58: Set 6 Destornilladores Bahco Aislados 1000v | C58: =VLOOKUP(B58,'Precio Equipos'!B:C,2,0) -> 58068.715 | D58: 3 | E58: =+C58*D58 -> 174206.14
B59: NIVEL DE ALUMINIO X 50CM - SOLA | C59: =VLOOKUP(B59,'Precio Equipos'!B:C,2,0) -> 32054.263 | D59: 1 | E59: =+C59*D59 -> 32054.263
... B61: PINZA P.CURVA 1000V 160MM | C61: =VLOOKUP(B61,'Precio Equipos'!B:C,2,0) -> 118104.55 | D61: 2 | E61: =+C61*D61 -> 236209.1
A62: *EQUIPIN | B62: EQUIPO PARA PINTAR | E62: =+SUM(E63:E70) -> 1241010.7 | G62: 2 | H62: =+G62*$H$5 -> 720 | I62: =+E62/H62 -> 1723.626 | J62: =+I62/E62 -> 0.0013888889
B63: Lijadora Orbital de Palma Bosch GSS 140-1A | C63: =VLOOKUP(B63,'Precio Equipos'!B:C,2,0) -> 220003.08 | D63: 3 | E63: =+C63*D63 -> 660009.25
B64: PISTOLA DE CALOR BOSCH GHG180 | C64: =VLOOKUP(B64,'Precio Equipos'!B:C,2,0) -> 222728.18 | D64: 1 | E64: =+C64*D64 -> 222728.18
B65: Equipo De Pintar Hvlp Pistola Máquina Adiabatic Ec2000 | C65: =VLOOKUP(B65,'Precio Equipos'!B:C,2,0) -> 401156.67 | D65: 0.33333333 | E65: =+C65*D65 -> 133718.89
B66: Llana Plástica 12 x 25 cm | C66: =VLOOKUP(B66,'Precio Equipos'!B:C,2,0) -> 12916.221 | D66: 5 | E66: =+C66*D66 -> 64581.105
B67: Llana de yesero 12 x 30 cm | C67: =VLOOKUP(B67,'Precio Equipos'!B:C,2,0) -> 13904.259 | D67: 5 | E67: =+C67*D67 -> 69521.293
B68: Espátula de pintor N° 15 | C68: =VLOOKUP(B68,'Precio Equipos'!B:C,2,0) -> 5933.349 | D68: 10 | E68: =+C68*D68 -> 59333.49
B69: Cepillo de acero - El Galgo | C69: =VLOOKUP(B69,'Precio Equipos'!B:C,2,0) -> 8660.9133 | D69: 1 | E69: =+C69*D69 -> 8660.9133
B70: Pistola Aplicadora Silicona Profesional 9″ | C70: =VLOOKUP(B70,'Precio Equipos'!B:C,2,0) -> 11228.786 | D70: 2 | E70: =+C70*D70 -> 22457.572
A71: EQPLOME | B71: EQUIPO PARA PLOMERIA | E71: =+SUM(E72:E83) -> 2058254 | G71: 2 | H71: =+G71*$H$5 -> 720 | I71: =+E71/H71 -> 2858.6861 | J71: =+I71/E71 -> 0.0013888889
B72: Termofusora 1800 w - 220 v s/ boquilla | C72: =VLOOKUP(B72,'Precio Equipos'!B:C,2,0) -> 294158.54 | D72: 1 | E72: =+C72*D72 -> 294158.54
B73: Amoladora 4 1/2 850 w - BOSCH | C73: =VLOOKUP(B73,'Precio Equipos'!B:C,2,0) -> 137903.31 | D73: 1 | E73: =+C73*D73 -> 137903.31
B74: Rotopercutor RPK-32KA - BAROVO (5 kg) | C74: =VLOOKUP(B74,'Precio Equipos'!B:C,2,0) -> 180879.68 | D74: 1 | E74: =+C74*D74 -> 180879.68
B75: Nivel Laser Dewalt Auto.alc.30mt 4p | C75: =VLOOKUP(B75,'Precio Equipos'!B:C,2,0) -> 832041.76 | D75: 1 | E75: =+C75*D75 -> 832041.76
B76: PALA FORJADA ANCHA - Gherardi | C76: =VLOOKUP(B76,'Precio Equipos'!B:C,2,0) -> 53370.69 | D76: 2 | E76: =+C76*D76 -> 106741.38
B77: PALA FORJADA DE PUNTA - Gherardi | C77: =VLOOKUP(B77,'Precio Equipos'!B:C,2,0) -> 53370.69 | D77: 2 | E77: =+C77*D77 -> 106741.38
B78: MAZA PARA ALBAÑIL 2″1/2 KG | C78: =VLOOKUP(B78,'Precio Equipos'!B:C,2,0) -> 19515.279 | D78: 2 | E78: =+C78*D78 -> 39030.557
B79: CORTA HIERRO CHATO 30CM | C79: =VLOOKUP(B79,'Precio Equipos'!B:C,2,0) -> 8539.6503 | D79: 2 | E79: =+C79*D79 -> 17079.301
B80: CUCHARA ALBAÑIL FORJADA 6″ | C80: =VLOOKUP(B80,'Precio Equipos'!B:C,2,0) -> 18146.757 | D80: 2 | E80: =+C80*D80 -> 36293.514
B81: CINTA METRICA 510 RETROFLEX 10MTS - Evel | C81: =VLOOKUP(B81,'Precio Equipos'!B:C,2,0) -> 26993.867 | D81: 1 | E81: =+C81*D81 -> 26993.867
B82: NIVEL DE ALUMINIO X 50CM - SOLA | C82: =VLOOKUP(B82,'Precio Equipos'!B:C,2,0) -> 32054.263 | D82: 1 | E82: =+C82*D82 -> 32054.263
B83: Set de herramientas profesional duroll - S88PD | C83: =VLOOKUP(B83,'Precio Equipos'!B:C,2,0) -> 248336.44 | D83: 1 | E83: =+C83*D83 -> 248336.44
B84: EQUIPO MOVIMIENTO DE TIERRA MANUAL | E84: =+SUM(E85:E90) -> 823493.85 | G84: 1 | H84: =+G84*$H$5 -> 360 | I84: =+E84/H84 -> 2287.4829 | J84: =+I84/E84 -> 0.0027777778
B85: Carretilla Duroll 100 Litros Chapa 16 Profesional Rueda Maciza | C85: =VLOOKUP(B85,'Precio Equipos'!B:C,2,0) -> 107853.34 | D85: 3 | E85: =+C85*D85 -> 323560.02
B86: RUEDA MACIZA CARRETILLA C100DU | C86: =VLOOKUP(B86,'Precio Equipos'!B:C,2,0) -> 15556.499 | D86: 3 | E86: =+C86*D86 -> 46669.498
B87: PALA FORJADA ANCHA - Gherardi | C87: =VLOOKUP(B87,'Precio Equipos'!B:C,2,0) -> 53370.69 | D87: 3 | E87: =+C87*D87 -> 160112.07
B88: PALA FORJADA DE PUNTA - Gherardi | C88: =VLOOKUP(B88,'Precio Equipos'!B:C,2,0) -> 53370.69 | D88: 3 | E88: =+C88*D88 -> 160112.07
B89: PALA FORJADA POCERO | C89: =VLOOKUP(B89,'Precio Equipos'!B:C,2,0) -> 53690.724 | D89: 2 | E89: =+C89*D89 -> 107381.45
B90: CABO PARA PALA 0.70 MTS.EMPUÑADURA METAL X UNIDAD | C90: =VLOOKUP(B90,'Precio Equipos'!B:C,2,0) -> 3207.3432 | D90: =+SUM(D87:D89) -> 8 | E90: =+C90*D90 -> 25658.746
A91: *EQUIP02 | B91: EQUIPO PARA HORMIGON | E91: =+SUM(E92:E112) -> 3739856.7 | G91: 1.5 | H91: =+G91*$H$5 -> 540 | I91: =+E91/H91 -> 6925.6605 | J91: =+I91/E91 -> 0.0018518519
B92: Amoladora 4 1/2 850 w - BOSCH | C92: =VLOOKUP(B92,'Precio Equipos'!B:C,2,0) -> 137903.31 | D92: 1 | E92: =+C92*D92 -> 137903.31
B93: Sierra circular 7 1/4 - BOSCH | C93: =VLOOKUP(B93,'Precio Equipos'!B:C,2,0) -> 396998.4 | D93: 1 | E93: =+C93*D93 -> 396998.4
B94: Rotopercutor RPK-32KA - BAROVO (5 kg) | C94: =VLOOKUP(B94,'Precio Equipos'!B:C,2,0) -> 180879.68 | D94: 1 | E94: =+C94*D94 -> 180879.68
B95: Vibrador de hormigón | C95: =VLOOKUP(B95,'Precio Equipos'!B:C,2,0) -> 1090691 | D95: =1/3 -> 0.33333333 | E95: =+C95*D95 -> 363563.68
B96: Nivel Laser Dewalt Auto.alc.30mt 4p | C96: =VLOOKUP(B96,'Precio Equipos'!B:C,2,0) -> 832041.76 | D96: 1 | E96: =+C96*D96 -> 832041.76
B97: MAZA PARA ALBAÑIL 2″1/2 KG | C97: =VLOOKUP(B97,'Precio Equipos'!B:C,2,0) -> 19515.279 | D97: 1 | E97: =+C97*D97 -> 19515.279
B98: CORTA HIERRO CHATO 30CM | C98: =VLOOKUP(B98,'Precio Equipos'!B:C,2,0) -> 8539.6503 | D98: 1 | E98: =+C98*D98 -> 8539.6503
B99: BARRETA SACA CLAVO 19 X 500 | C99: =VLOOKUP(B99,'Precio Equipos'!B:C,2,0) -> 16440.93 | D99: 1 | E99: =+C99*D99 -> 16440.93
B100: BARRETA SACA CLAVO 22X1000 | C100: =VLOOKUP(B100,'Precio Equipos'!B:C,2,0) -> 51198.256 | D100: 1 | E100: =+C100*D100 -> 51198.256
B101: DOBLADORA PARA HIERRO 6mm a 10mm Con Palanca Regulable | C101: =VLOOKUP(B101,'Precio Equipos'!B:C,2,0) -> 65209.346 | D101: 1 | E101: =+C101*D101 -> 65209.346
B102: DOBLADORA PARA HIERRO 12mm a 20mm Sin Palanca Regulable | C102: =VLOOKUP(B102,'Precio Equipos'!B:C,2,0) -> 88032.832 | D102: 1 | E102: =+C102*D102 -> 88032.832
B103: DOBLADORA PARA HIERRO 25mm Sin Palanca Regulable Reforzada | C103: =VLOOKUP(B103,'Precio Equipos'!B:C,2,0) -> 119763.33 | D103: 1 | E103: =+C103*D103 -> 119763.33
B104: MASCARA FOTOSENSIBLE | C104: =VLOOKUP(B104,'Precio Equipos'!B:C,2,0) -> 53027.866 | D104: 1 | E104: =+C104*D104 -> 53027.866
B105: Soldadora inverter ESAB LHN 240i Plus amarilla y negra 50Hz/60Hz 220V | C105: =VLOOKUP(B105,'Precio Equipos'!B:C,2,0) -> 1002877.3 | D105: 1 | E105: =+C105*D105 -> 1002877.3
B106: Tenaza 3 puntos | C106: =VLOOKUP(B106,'Precio Equipos'!B:C,2,0) -> 24263.281 | D106: 3 | E106: =+C106*D106 -> 72789.844
B107: Martillo Galponero Loro 500gr Cabo Largo 48cm | C107: =VLOOKUP(B107,'Precio Equipos'!B:C,2,0) -> 47886.089 | D107: 3 | E107: =+C107*D107 -> 143658.27
... B112: NIVEL DE ALUMINIO X 50CM - SOLA | C112: =VLOOKUP(B112,'Precio Equipos'!B:C,2,0) -> 32054.263 | D112: 1 | E112: =+C112*D112 -> 32054.263
A113: TROMPO | B113: Hormigonera De 150 Litros 1hp Con Rueda Maciza | E113: =+SUM(E114:E116) -> 689222.3 | G113: 2 | H113: =+G113*$H$5 -> 720 | I113: =+E113/H113 -> 957.2532 | J113: =+I113/E113 -> 0.0013888889
B114: Hormigonera De 150 Litros 1hp Con Rueda Maciza | C114: =VLOOKUP(B114,'Precio Equipos'!B:C,2,0) -> 499025.69 | D114: 1 | E114: =+C114*D114 -> 499025.69
B115: REPUESTO MOTOR HORMIGONERA 1HP CLASICO | C115: =VLOOKUP(B115,'Precio Equipos'!B:C,2,0) -> 151447.94 | D115: 1 | E115: =+C115*D115 -> 151447.94
...

Sheet Precio Equipos
G1: DÓLAR USD | H1: DÓLAR MEP
B2: PRECIOS DE EQUIPOS | F2: 45631 | G2: 1033 | H2: 1075
H3: 13277.8 | I3: 45292
B4: DESCRIPCION | C4: P. Unit | D4: Fecha | E4: Proveedor | H4: 17149.9 | I4: 45566
A5: 1 | B5: IZAJE, TRASLADO Y ALTURA | H5: =+H4/H3 -> 1.2916221
A6: 1.01 | B6: Andamio reforzado tubular 2,5 mts | C6: =+H6*$H$5 -> 237068.27 | E6: Abrafer WEB | H6: =222087.1/1.21 -> 183543.06 | I6: 45299
A7: 1.02 | B7: Tablon Para Andamio 2,5 M Metalico Antideslizante Tca Duroll | C7: =+H7*$H$5 -> 94209.625 | E7: Abrafer WEB | H7: =88256.19/1.21 -> 72939 | I7: 45299
A8: 1.03 | B8: Rueda para andamio giratoria c/freno | C8: =+H8*$H$5 -> 32124.755 | E8: Abrafer WEB | H8: =30094.68/1.21 -> 24871.636 | I8: 45299
A9: 1.04 | B9: Carretilla Duroll 100 Litros Chapa 16 Profesional Rueda Maciza | C9: =+H9*$H$5 -> 107853.34 | E9: Abrafer WEB | H9: =101037.71/1.21 -> 83502.24 | I9: 45303
A10: 1.05 | B10: RUEDA MACIZA CARRETILLA C100DU | C10: =+H10*$H$5 -> 15556.499 | E10: Abrafer WEB | H10: =14573.43/1.21 -> 12044.157 | I10: 45303
A11: 1.06 | B11: ESCALERA GLOSS ALUMINIO ARTICULADA 4 X 4 ESCALONES HASTA 150KG | C11: =+H11*$H$5 -> 201885.25 | E11: Abrafer WEB | H11: =189127.42/1.21 -> 156303.65 | I11: 45303
A12: 1.07 | B12: ESCALERA MADERA PINTOR 8 ESCALONES | C12: =+H12*$H$5 -> 72091.109 | E12: Abrafer WEB | H12: =67535.42/1.21 -> 55814.397 | I12: 45299
A13: 1.08 | B13: Kit Complementario Silleta Descensor Conector Soga X 50 Mts | C13: =+H13*$H$5 -> 683705.75 | E13: Mercado Libre | H13: =640500/1.21 -> 529338.84 | I13: 45327
A14: 1.09 | B14: Balancin | C14: =+F14*$G$2 -> 10476479 | D14: 45631 | E14: Leiten | F14: 10141.8
A15: 2 | B15: HERRAMIENTAS ELECTRICAS
A16: 2.01 | B16: Amoladora 4 1/2 850 w - BOSCH | C16: =+H16*$H$5 -> 137903.31 | E16: Abrafer WEB | H16: =129188.72/1.21 -> 106767.54 | I16: 45303
A17: 2.02 | B17: AMOLADORA BOSCH 7″ GWS 22-180 2200W | C17: =+H17*$H$5 -> 452946.11 | E17: Abrafer WEB | H17: =424322.87/1.21 -> 350680.06 | I17: 45327
A18: 2.03 | B18: Rotopercutor RPK-32KA - BAROVO (5 kg) | C18: =+H18*$H$5 -> 180879.68 | E18: Abrafer WEB | H18: =169449.26/1.21 -> 140040.71 | I18: 45303
A19: 2.04 | B19: Termofusora 1800 w - 220 v s/ boquilla | C19: =+H19*$H$5 -> 294158.54 | E19: Abrafer WEB | H19: =275569.64/1.21 -> 227743.5 | I19: 45307
A20: 2.05 | B20: Sierra circular 7 1/4 - BOSCH | C20: =+H20*$H$5 -> 396998.4 | E20: Abrafer WEB | H20: =371910.69/1.21 -> 307364.21 | I20: 45303
A21: 2.06 | B21: Nivel Laser Dewalt Auto.alc.30mt 4p | C21: =+H21*$H$5 -> 832041.76 | E21: Abrafer WEB | H21: =779462.14/1.21 -> 644183.59 | I21: 45327
A22: 2.07 | B22: Taladro Percutor/Atornillador de 1/2″ (13mm) Inalámbrico 20V + 2 Baterías + Cargador + Maletín | C22: =+H22*$H$5 -> 555611 | E22: Abrafer WEB | H22: =520500/1.21 -> 430165.29 | I22: 45327
A23: 2.08 | B23: Vibrador de hormigón | C23: =+H23*$H$5 -> 1090691 | E23: Abrafer WEB | H23: =1021766.47/1.21 -> 844435.1 | I23: 45303
A24: 2.09 | B24: MEZCLADOR ELECTRICO 2V. 50HZ 1200W | C24: =+H24*$H$5 -> 143732.28 | E24: Abrafer WEB | H24: 111280.45 | I24: 45303
A25: 2.1 | B25: Equipo De Pintar Hvlp Pistola Máquina Adiabatic Ec2000 | C25: =+H25*$H$5 -> 401156.67 | E25: Abrafer WEB | H25: =375806.18/1.21 -> 310583.62 | I25: 45327
A26: 2.11 | B26: PISTOLA DE CALOR BOSCH GHG180 | C26: =+H26*$H$5 -> 222728.18 | E26: Abrafer WEB | H26: =208653.21/1.21 -> 172440.67 | I26: 45327
A27: 2.12 | B27: Lijadora Orbital de Palma Bosch GSS 140-1A | C27: =+H27*$H$5 -> 220003.08 | E27: Abrafer WEB | H27: =206100.32/1.21 -> 170330.84 | I27: 45327
A28: 2.13 | B28: Soldadora inverter ESAB LHN 240i Plus amarilla y negra 50Hz/60Hz 220V | C28: =+H28*$H$5 -> 1002877.3 | E28: Mercado Libre | H28: =939502/1.21 -> 776447.93 | I28: 45327
A29: 2.14 | B29: MASCARA FOTOSENSIBLE | C29: =+H29*$H$5 -> 53027.866 | E29: Abrafer WEB | H29: =49676.85/1.21 -> 41055.248 | I29: 45327
A30: 2.15 | B30: Sierra de metal de banco gco 220 | C30: =+H30*$H$5 -> 549290.39 | E30: Abrafer WEB | H30: =514578.81/1.21 -> 425271.74 | I30: 45327
A31: 2.16 | B31: Martillo demoledor MPK-125K | C31: =+H31*$H$5 -> 886390.57 | E31: Abrafer WEB | H31: =830376.46/1.21 -> 686261.54 | I31: 45327
A32: 2.17 | B32: Hormigonera De 150 Litros 1hp Con Rueda Maciza | C32: =+H32*$H$5 -> 499025.69 | E32: Abrafer WEB | H32: =467490.52/1.21 -> 386355.8 | I32: 45303
A33: 2.18 | B33: REPUESTO MOTOR HORMIGONERA 1HP CLASICO | C33: =+H33*$H$5 -> 151447.94 | E33: Abrafer WEB | H33: =141877.42/1.21 -> 117254.07 | I33: 45303
A34: 2.19 | B34: Correa | C34: =+H34*$H$5 -> 12916.221 | E34: Abrafer WEB | H34: 10000 | I34: 45303
A35: 3 | B35: HERRAMIENTAS
A36: 3.01 | B36: Set de herramientas profesional duroll - S88PD | C36: =+H36*$H$5 -> 248336.44 | E36: Abrafer WEB | H36: =232643.19/1.21 -> 192267.1 | I36: 45303
A37: 3.02 | B37: CORTADORA CERAMICA PROFESIONAL 1200MM (PORCELANATO HASTA 16MM) | C37: =+H37*$H$5 -> 537162.92 | E37: Abrafer WEB | H37: =503217.72/1.21 -> 415882.41 | I37: 45303
A38: 3.03 | B38: REGLA ALUMINIO 6,00MTS | C38: =+H38*$H$5 -> 238945.46 | E38: Abrafer WEB | H38: =223845.66/1.21 -> 184996.41 | I38: 45303
A39: 3.04 | B39: PALA FORJADA ANCHA - Gherardi | C39: =+H39*$H$5 -> 53370.69 | E39: Abrafer WEB | H39: =49998.01/1.21 -> 41320.669 | I39: 45303
A40: 3.05 | B40: PALA FORJADA DE PUNTA - Gherardi | C40: =+H40*$H$5 -> 53370.69 | E40: Abrafer WEB | H40: =49998.01/1.21 -> 41320.669 | I40: 45303
A41: 3.06 | B41: PALA FORJADA POCERO | C41: =+H41*$H$5 -> 53690.724 | E41: Abrafer WEB | H41: =50297.82/1.21 -> 41568.446 | I41: 45327
A42: 3.07 | B42: CABO PARA PALA 0.70 MTS.EMPUÑADURA METAL X UNIDAD | C42: =+H42*$H$5 -> 3207.3432 | E42: Abrafer WEB | H42: =3004.66/1.21 -> 2483.1901 | I42: 45327
A43: 3.08 | B43: FRATACHO DE ALGARROBO DE 30 CM | C43: =+H43*$H$5 -> 4646.285 | E43: Abrafer WEB | H43: =4352.67/1.21 -> 3597.2479 | I43: 45303
A44: 3.09 | B44: CUCHARA ALBAÑIL FORJADA 6″ | C44: =+H44*$H$5 -> 18146.757 | E44: Abrafer WEB | H44: =17000/1.21 -> 14049.587 | I44: 45303
A45: 3.1 | B45: PLOMADA PARA ALBAÑIL 500GRS | C45: =+H45*$H$5 -> 5823.7319 | E45: Abrafer WEB | H45: =5455.71/1.21 -> 4508.8512 | I45: 45303
A46: 3.11 | B46: CHOCLA PARA ALBAÑIL C/RECIPIENTE CON TIZA - DUROLL | C46: =+H46*$H$5 -> 4206.1727 | E46: Abrafer WEB | H46: =3940.37/1.21 -> 3256.5041 | I46: 45303
A47: 3.12 | B47: MAZA PARA ALBAÑIL 2″1/2 KG | C47: =+H47*$H$5 -> 19515.279 | E47: Abrafer WEB | H47: =18282.04/1.21 -> 15109.124 | I47: 45303
A48: 3.13 | B48: CORTA HIERRO CHATO 30CM | C48: =+H48*$H$5 -> 8539.6503 | E48: Abrafer WEB | H48: =8000/1.21 -> 6611.5702 | I48: 45303
A49: 3.14 | B49: BALDE ALBAÑIL PLÁSTICO – MANIJA PLÁSTICA – BAE | C49: =+H49*$H$5 -> 2097.2847 | E49: Abrafer WEB | H49: =1964.75/1.21 -> 1623.7603 | I49: 45303
A50: 3.15 | B50: NIVEL DE ALUMINIO X 50CM - SOLA | C50: =+H50*$H$5 -> 32054.263 | E50: Abrafer WEB | H50: =24817.06 -> 24817.06 | I50: 45303
A51: 3.16 | B51: Rodillera de seguridad goma espuma | C51: =+H51*$H$5 -> 6903.8056 | E51: Abrafer WEB | H51: 5345.0661 | I51: 45303
A52: 3.17 | B52: Martillo Maza De Goma | C52: =+H52*$H$5 -> 8898.892 | E52: Abrafer WEB | H52: 6889.7025 | I52: 45303
A53: 3.18 | B53: LLANA DENTADA DE 12 X 12 CMS | C53: =+H53*$H$5 -> 13983.677 | E53: Abrafer WEB | H53: 10826.446 | I53: 45303
A54: 3.19 | B54: Lapiz carpintero 18 cm | C54: =+H54*$H$5 -> 1387.6932 | E54: Abrafer WEB | H54: =1300/1.21 -> 1074.3802 | I54: 45303
A55: 3.2 | B55: CINTA METRICA 510 RETROFLEX 10MTS - Evel | C55: =+H55*$H$5 -> 26993.867 | E55: Abrafer WEB | H55: =25288.03/1.21 -> 20899.198 | I55: 45303
A56: 3.21 | B56: Llana de yesero 12 x 30 cm | C56: =+H56*$H$5 -> 13904.259 | E56: Prestigio WEB | H56: =13025.6/1.21 -> 10764.959 | I56: 45303
A57: 3.22 | B57: Llana Plástica 12 x 25 cm | C57: =+H57*$H$5 -> 12916.221 | E57: Prestigio WEB | H57: =10000 -> 10000 | I57: 45304
A58: 3.23 | B58: Espátula de pintor N° 15 | C58: =+H58*$H$5 -> 5933.349 | E58: Prestigio WEB | H58: =5558.4/1.21 -> 4593.719 | I58: 45305
A59: 3.24 | B59: Cepillo de acero - El Galgo | C59: =+H59*$H$5 -> 8660.9133 | E59: Prestigio WEB | H59: =8113.6/1.21 -> 6705.4545 | I59: 45306
A60: 3.25 | B60: Tenaza 3 puntos | C60: =+H60*$H$5 -> 24263.281 | E60: Abrafer WEB | H60: =22730/1.21 -> 18785.124 | I60: 45303
A61: 3.26 | B61: Martillo Galponero Loro 500gr Cabo Largo 48cm | C61: =+H61*$H$5 -> 47886.089 | E61: Mercado Libre | H61: =44860/1.21 -> 37074.38 | I61: 45327
A62: 3.27 | B62: CARTUCHERA T32 CLAVERA SIMPLE 2 BOLSILLO | C62: =+H62*$H$5 -> 21774.08 | E62: Abrafer WEB | H62: =20398.1/1.21 -> 16857.934 | I62: 45303
A63: 3.28 | B63: Metro madera | C63: =+H63*$H$5 -> 4852.6243 | E63: Abrafer WEB | H63: =4545.97/1.21 -> 3757 | I63: 45303
A64: 3.29 | B64: Rodillo de bronce para cementista grande 17 cm | C64: =+H64*$H$5 -> 72426.909 | E64: Abrafer WEB | H64: =67850/1.21 -> 56074.38 | I64: 45303
A65: 3.3 | B65: RODEL RUEDITA 8MM P/C 1958 | C65: =+H65*$H$5 -> 39721.703 | E65: Abrafer WEB | H65: =37211.55/1.21 -> 30753.347 | I65: 45327
A66: 3.31 | B66: Pinza amperométrica digital | C66: =+H66*$H$5 -> 14574.461 | E66: Abrafer WEB | H66: =13653.45/1.21 -> 11283.843 | I66: 45327
A67: 3.32 | B67: TESTER 8EN1 AC/DC 6/380V | C67: =+H67*$H$5 -> 12314.379 | E67: Abrafer WEB | H67: =11536.19/1.21 -> 9534.0413 | I67: 45327
A68: 3.33 | B68: CINTA PASACABLE ALMA DE ACERO X 10MTS | C68: =+H68*$H$5 -> 6946.8561 | E68: Abrafer WEB | H68: =6507.86/1.21 -> 5378.3967 | I68: 45327
A69: 3.34 | B69: CINTA PASACABLE ALMA DE ACERO X 15 MTS | C69: =+H69*$H$5 -> 9385.7055 | E69: Abrafer WEB | H69: =8792.59/1.21 -> 7266.6033 | I69: 45327
A70: 3.35 | B70: Set 6 Destornilladores Bahco Aislados 1000v | C70: =+H70*$H$5 -> 58068.715 | E70: Abrafer WEB | H70: =54399.15/1.21 -> 44957.975 | I70: 45327
A71: 3.36 | B71: ALICATE UNIVERSAL | C71: =+H71*$H$5 -> 119810.18 | E71: Abrafer WEB | H71: =112238.96/1.21 -> 92759.471 | I71: 45327
A72: 3.37 | B72: PINZA P.CURVA 1000V 160MM | C72: =+H72*$H$5 -> 118104.55 | E72: Abrafer WEB | H72: =110641.11/1.21 -> 91438.934 | I72: 45327
A73: 3.38 | B73: Pistola Aplicadora Silicona Profesional 9″ | C73: =+H73*$H$5 -> 11228.786 | E73: Abrafer WEB | H73: =10519.2/1.21 -> 8693.5537 | I73: 45327
A74: 3.39 | B74: DOBLADORA PARA HIERRO 6mm a 10mm Con Palanca Regulable | C74: =+H74*$H$5 -> 65209.346 | E74: Abrafer WEB | H74: =61088.54/1.21 -> 50486.397 | I74: 45327
A75: 3.4 | B75: DOBLADORA PARA HIERRO 12mm a 20mm Sin Palanca Regulable | C75: =+H75*$H$5 -> 88032.832 | E75: Abrafer WEB | H75: =82469.73/1.21 -> 68156.802 | I75: 45327
A76: 3.41 | B76: DOBLADORA PARA HIERRO 25mm Sin Palanca Regulable Reforzada | C76: =+H76*$H$5 -> 119763.33 | E76: Abrafer WEB | H76: =112195.07/1.21 -> 92723.198 | I76: 45327
A77: 3.42 | B77: BARRETA SACA CLAVO 22X1000 | C77: =+H77*$H$5 -> 51198.256 | E77: Abrafer WEB | H77: =47962.86/1.21 -> 39638.727 | I77: 45327
A78: 3.43 | B78: BARRETA SACA CLAVO 19 X 500 | C78: =+H78*$H$5 -> 16440.93 | E78: Abrafer WEB | H78: =15401.97/1.21 -> 12728.901 | I78: 45327
A79: 3.44 | B79: Kit 4 Escuadra Magnetica 4″ Kushiro | C79: =+H79*$H$5 -> 28394.508 | E79: Abrafer WEB | H79: =26600.16/1.21 -> 21983.603 | I79: 45327
A80: 3.45 | B80: Serruchin Para Durlock Con Mango Plastico | C80: =+H80*$H$5 -> 6232.1407 | E80: Abrafer WEB | H80: =5838.31/1.21 -> 4825.0496 | I80: 45327
A81: 3.46 | B81: CUTTER TRAPEZOIDAL ALUMINIO | C81: =+H81*$H$5 -> 4504.6335 | E81: Abrafer WEB | H81: =4219.97/1.21 -> 3487.5785 | I81: 45327
A82: 3.47 | B82: Soplete Techista Con Manguera 50mm Garrafas 10kg Brogas | C82: =+H82*$H$5 -> 22416.582 | E82: Mercado Libre | H82: =21000/1.21 -> 17355.372 | I82: 45327
A83: 3.48 | B83: Garrafa x 10 kg - Vacia | C83: =+H83*$H$5 -> 80059.221 | E83: Mercado Libre | H83: =75000/1.21 -> 61983.471 | I83: 45327
A84: 3.49 | B84: Tijera Hojalatero Aviacion Recta 10 | C84: =+H84*$H$5 -> 10408.766 | E84: Abrafer WEB | H84: =9751/1.21 -> 8058.6777 | I84: 45327
A85: 4 | B85: ALQUILER EQUIPOS Y MAQUINARIAS | F85: USD
A86: 4.01 | B86: FRATACHADORA MASTERPAC PMT36H - Alq. X dia | C86: =+F86*$G$2 -> 61876.7 | D86: 45631 | E86: Leiten | F86: 59.9
A87: 4.02 | B87: FRATACHADORA MASALTA MT24-2 - Alq. X dia | C87: =+F87*$G$2 -> 72723.2 | D87: 45631 | E87: Leiten | F87: 70.4
A88: 4.03 | B88: MARTILLO HIDRAULICO PARA BOBCAT
A89: 4.04 | B89: Maquina revocadora Revoque/Yeso - Alq. X mes | C89: =1230000 -> 1230000 | D89: 45631 | E89: TODO PROYECTABLE
A90: 4.05 | B90: MINI CARGADORA Bobcat S570 (c/ operario y combustible) - Alq. X dia | C90: =+F90*$G$2 -> 309900 | E90: LP VIAL | F90: 300 | H90: =+K90*$G$2 -> 0 | I90: 45201
A91: 4.06 | B91: Pala y retro 310J (c/ operario y combustible) - Alq. X dia | C91: =+F91*$G$2 -> 464850 | E91: LP VIAL | F91: 450 | H91: =+K91*$G$2 -> 0 | I91: 45201
A92: 4.07 | B92: Pala cargadora frontal (2 m) 936 - (c/ operario y combustible) - Alq. X dia | C92: =+F92*$G$2 -> 506170 | E92: LP VIAL | F92: 490 | H92: =+K92*$G$2 -> 0 | I92: 45201
A93: 4.08 | B93: Pala cargadora frontal (3 m) 950 - (c/ operario y combustible) - Alq. X dia | C93: =+F93*$G$2 -> 588810 | E93: LP VIAL | F93: 570 | H93: =+K93*$G$2 -> 0 | I93: 45201
A94: 4.09 | B94: Compactador pata de cabra 612H - (c/operario y combustible) - Alq. X dia | C94: =+F94*$G$2 -> 568150 | E94: LP VIAL | F94: 550 | H94: =+K94*$G$2 -> 0 | I94: 45201
A95: 4.1 | B95: Excavador sobre orugas PC-200 - (c/operario y combustible) - Alq. X dia | C95: =+F95*$G$2 -> 878050 | E95: LP VIAL | F95: 850 | H95: =+K95*$G$2 -> 0 | I95: 45201
A96: 4.11 | B96: Motoniveladora 120H - (c/operario y combustible) - Alq. X dia | C96: =+F96*$G$2 -> 929700 | E96: LP VIAL | F96: 900 | H96: =+K96*$G$2 -> 0 | I96: 45201
A97: 4.12 | B97: Camion chasis volcador 170E22 - (c/ operario y combustible) - Alq. X dia | C97: =+F97*$G$2 -> 258250 | E97: LP VIAL | F97: 250 | H97: =+K97*$G$2 -> 0 | I97: 45201
A98: 4.13 | B98: Camion Batea o Tatu 170E22 - (c/ operario y combustible) - Alq. X dia | C98: =+F98*$G$2 -> 402870 | E98: LP VIAL | F98: 390 | H98: =+K98*$G$2 -> 0 | I98: 45201
A99: 4.14 | B99: Combustible bobcat (36 lts) | C99: =+C102*36 -> 40428 | H99: =+H102*36 -> 36000
A100: 4.15 | B100: Combustible Pala y Retro (60 lts) | C100: =+C102*60 -> 67380 | H100: =+H102*60 -> 60000
...

Sheet Mano de Obra
A3: MANO DE OBRA
C4: Fecha: | D4: 45627
A7: Código | B7: DESCRIPCION | C7: Salario (Día) | D7: Prestaciones Sociales | G7: COSTO Jornal
A8: *AYUDAN1 | B8: AYUDANTE | C8: =+$G$12 -> 60860.581 | D8: 0 | F8: CAPATAZ | G8: 147709.44
A9: AYUDANTE | B9: AYUDANTE ALBAÑIL | C9: =+$G$12 -> 60860.581 | D9: 0 | F9: ESPECIALIZADO | G9: 85927.097
A10: AYAR | B10: AYUDANTE ARMADOR | C10: =+$G$12 -> 60860.581 | D10: 0 | F10: OFICIAL | G10: 76955.08
A11: AYUCARP | B11: AYUDANTE CARPINTERO | C11: =+$G$12 -> 60860.581 | D11: 0 | F11: MEDIO OFICIAL | G11: 65493.072
A12: AYELECT | B12: AYUDANTE ELECTRICISTA | C12: =+$G$12 -> 60860.581 | D12: 0 | F12: AYUDANTE | G12: 60860.581
A13: AYPLOMER | B13: AYUDANTE PLOMERO | C13: =+$G$12 -> 60860.581 | D13: 0
A14: MOFAL | B14: MEDIO OFICIAL ALBAÑIL | C14: =+$G$11 -> 65493.072 | D14: 0 | F14: SOBRESTANTE | G14: 3009340.6
A15: MEDARM | B15: MEDIO OFICIAL ARMADOR | C15: =+$G$11 -> 65493.072 | D15: 0 | F15: JEFE DE OBRA | G15: 4372210.6
A16: MEDOFCAR | B16: MEDIO OFICIAL CARPINTERO | C16: =+$G$11 -> 65493.072 | D16: 0 | F16: COORD OBRAS | G16: 5273644.1
A17: MEDPINTO | B17: MEDIO OFICIAL PINTOR | C17: =+$G$11 -> 65493.072 | D17: 0 | F17: CAPATAZ | G17: 3545026.5
A18: OFCOLOCA | B18: OFICIAL COLOCADOR | C18: =+$G$9 -> 85927.097 | D18: 0
A19: OFAL | B19: OFICIAL ESPECIALIZADO ALBAÑIL | C19: =+$G$9 -> 85927.097 | D19: 0
A20: OFAR | B20: OFICIAL ESPECIALIZADO ARMADOR | C20: =+$G$9 -> 85927.097 | D20: 0
A21: OFICARPI | B21: OFICIAL ESPECIALIZADO CARPINTERO | C21: =+$G$9 -> 85927.097 | D21: 0
A22: OFELECT | B22: OFICIAL ESPECIALIZADO ELECTRICISTA | C22: =+$G$9 -> 85927.097 | D22: 0
A23: OFINST | B23: OFICIAL ESPECIALIZADO INSTALADOR | C23: =+$G$9 -> 85927.097 | D23: 0
A24: OFPINTOR | B24: OFICIAL ESPECIALIZADO PINTOR | C24: =+$G$9 -> 85927.097 | D24: 0
A25: OFPLOMER | B25: OFICIAL ESPECIALIZADO PLOMERO | C25: =+$G$9 -> 85927.097 | D25: 0
A26: *TOPOGRA | B26: TOPOGRAFO | C26: =+G9*2 -> 171854.19 | D26: 0
B28: 0 | C28: 0 | D28: 0

Sheet Sub CONTRATOS
J2: CAC OCT 24 | N2: CAC OCT 24 | O2: Retroactivo oct.
A3: SUBCONTRATOS | H3: CAC sep 22 | I3: 1541.9 | J3: =+$O$3 -> 10902.632 | K3: =+J3/I3+$K$2 -> 7.0709073 | M3: 1.04 | N3: 10483.3 | O3: =+M3*N3 -> 10902.632
H4: CAC jul 22 | I4: 1322.6 | J4: =+$O$3 -> 10902.632 | K4: =+J4/I4+$K$2 -> 8.2433328
A7: RUBRO | B7: TAREA | C7: CONTRATISTA | D7: U | E7: PU | F7: FECHA | H7: CAC nov 22 | I7: 1815.7 | J7: =+$O$3 -> 10902.632 | K7: =+J7/I7+$K$2 -> 6.0046439
A8: Colocacion | B8: Ceramico en pisos y pared | C8: Zotelo | D8: m2 | E8: =+H8*$K$3 -> 14141.815 | F8: 45631 | H8: 2000 | I8: 44835
A9: Colocacion | B9: Porcelanato en piso | C9: Zotelo | D9: m2 | E9: =+H9*$K$3 -> 12727.633 | F9: 45631 | H9: 1800 | I9: 44835
A10: Pintura | B10: Latex Mate | C10: Lionel | D10: m2 | E10: =+H10*$K$7 -> 4803.7152 | F10: 45631 | H10: 800 | I10: 44896
A11: Pintura | B11: Latex Mate s/ Pared + Enduido | C11: Lionel | D11: m2 | E11: =+H11*$K$7 -> 6004.6439 | F11: 45631 | H11: 1000 | I11: 44896
A12: Pintura | B12: Latex Mate s/ Cielorraso + Enduido | C12: Lionel | D12: m2 | E12: =+H12*$K$7 -> 6004.6439 | F12: 45631 | H12: 1000 | I12: 44896
A13: Pintura | B13: Latex Satinado s/ Pared + Enduido | C13: Lionel | D13: m2 | E13: =+H13*$K$7 -> 12009.288 | F13: 45631 | H13: 2000 | I13: 44896
A14: Pintura | B14: Latex Satinado s/ Cielorraso + Enduido | C14: Lionel | D14: m2 | E14: =+H14*$K$7 -> 12009.288 | F14: 45631 | H14: 2000 | I14: 44896
A15: Pintura | B15: Esmalte Sintetico | C15: Lionel | D15: m2 | E15: =+H15*$K$7 -> 7806.0371 | F15: 45631 | H15: 1300 | I15: 44896
A16: Pintura | B16: Esmalte sintetico en Herrerias | C16: Lionel | D16: m2 | E16: =+H16*$K$7 -> 7806.0371 | F16: 45631 | H16: 1300 | I16: 44896
A17: Pintura | B17: Tarquini | C17: Lionel | D17: m2 | E17: =+H17*$K$7 -> 9006.9659 | F17: 45631 | H17: 1500 | I17: 45017
A18: Durlock | B18: Tabique simple | C18: Mario Silva | D18: m2 | E18: =+H18*$K$4 -> 20608.332 | F18: 45631 | H18: 2500 | I18: 44774 | J18: Neogen
A19: Durlock | B19: Tabique simple, doble placa | C19: Mario Silva | D19: m2 | E19: =+H19*$K$4 -> 0 | F19: 45631
A20: Durlock | B20: Medio Forro | C20: Mario Silva | D20: m2 | E20: =+H20*$K$4 -> 14837.999 | F20: 45631 | H20: 1800 | I20: 44774 | J20: Neogen | K20: =+H20/H18 -> 0.72
A21: Durlock | B21: Cielorraso Junta Tomada | C21: Mario Silva | D21: m2 | E21: =+H21*$K$4 -> 14837.999 | F21: 45631 | H21: 1800 | I21: 44774 | J21: Neogen
A22: Durlock | B22: Cielorraso Desmontable | C22: Mario Silva | D22: m2 | E22: =+H22*$K$4 -> 13189.333 | F22: 45631 | H22: 1600 | I22: 44774 | J22: Neogen | K22: =+H22/H21 -> 0.88888889
A23: Durlock | B23: Cajon cielorraso | C23: Mario Silva | D23: m2 | E23: =+H23*$K$4 -> 16486.666 | F23: 45631 | H23: 2000 | I23: 44774 | J23: Neogen
A24: Techos | B24: Cubierta Metalica c/Aislacion | C24: Acevedo | D24: m2 | E24: =+H24*K7 -> 42032.508 | F24: 45631 | H24: 7000 | I24: 45279 | J24: HUA
A25: Techos | B25: Babeta | C25: Acevedo | D25: ml | E25: 0 | F25: 45631
A26: Techos | B26: Banda Soler | C26: Acevedo | D26: ml | E26: 0 | F26: 45631
A27: Techos | B27: Canaleta | C27: Acevedo | D27: ml | E27: 0 | F27: 45631
A28: Techos | B28: Cumbrera | C28: Acevedo | D28: ml | E28: 0 | F28: 45631
A29: Yeso | B29: Cielorraso aplicado yeso | C29: Miguel Galleguillo | D29: m2 | E29: =+H29*$K$7 -> 9607.4303 | F29: 45631 | H29: 1600 | I29: 44890
A30: Yeso | B30: Cielorraso armado yeso | C30: Jorge Yesero (CDR) | D30: m2 | E30: =+H30*$K$7 -> 15011.61 | F30: 45631 | H30: 2500 | I30: 44890 | K30: CDR
A31: Yeso | B31: Aristas | C31: Miguel Galleguillo | D31: ml | E31: =+E29*0.5 -> 4803.7152 | F31: 45631 | H31: 750 | I31: 44890 | J31: =+H31/H29 -> 0.46875 | M31: Cielorraso armado CDR | N31: 220000 | O31: 60 | P31: =+N31/O31 -> 3666.6667 | Q31: =+P31/2 -> 1833.3333
A32: Yeso | B32: Enlucidos en paredes | C32: Miguel Galleguillo | D32: m2 | E32: =+E29 -> 9607.4303 | F32: 45631 | M32: Buña | O32: 70
A33: Yeso | B33: Buñas | C33: Jorge Yesero (CDR) | D33: ml | E33: =+E31 -> 4803.7152 | F33: 45631 | H33: 750 | I33: 44890 | K33: CDR
B34: Enduido Tabiques | C34: Fredi Austral | D34: m2 | F34: 45631 | H34: 500 | I34: 44593
B35: Enduido Cielorraso | C35: Fredi Austral | D35: m2 | F35: 45631 | H35: 450 | I35: 44593
F36: 45631
F37: 45631 | L37: 45597
F38: 45631 | H38: =+K3 -> 7.0709073 | L38: AAIERIC | M38: 1
A39: Electrico | B39: Cableado x boca | C39: Demian | D39: u | E39: =+H39*$H$38 -> 10606.361 | F39: 45631 | H39: 1500 | I39: 44835 | L39: 15156 | M39: =+L39/$M$38 -> 15156 | N39: =+E39/M39 -> 0.69981268
A40: Electrico | B40: Cableado x bandeja (cable 4x10mm x ml) | C40: Demian | D40: ml | E40: =+H40*$H$38 -> 10606.361 | F40: 45631 | H40: 1500 | I40: 44835 | M40: =+L40/$M$38 -> 0 | N40: =+E40/M40 -> #DIV/0!
A41: Electrico | B41: Cañeria PVC (x boca) | C41: Demian | D41: u | E41: =+H41*$H$38 -> 21212.722 | F41: 45631 | H41: 3000 | I41: 44835 | L41: 31184 | M41: =+L41/$M$38 -> 31184 | N41: =+E41/M41 -> 0.68024378
A42: Electrico | B42: Cañeria Metalica (x boca) | C42: Demian | D42: u | E42: =+H42*$H$38 -> 21212.722 | F42: 45631 | H42: 3000 | I42: 44835 | L42: 31184 | M42: =+L42/$M$38 -> 31184 | N42: =+E42/M42 -> 0.68024378
A43: Electrico | B43: Cañeria EXT | C43: Demian | D43: ml | E43: =+H43*$H$38 -> 21212.722 | F43: 45631 | H43: 3000 | I43: 44835 | L43: 28325 | M43: =+L43/$M$38 -> 28325 | N43: =+E43/M43 -> 0.74890457
A44: Electrico | B44: Bandeja 450/600 (xml) | C44: Demian | D44: ml | E44: =+H44*$H$38 -> 9545.7249 | F44: 45631 | H44: 1350 | I44: 44835 | L44: 15326 | M44: =+L44/$M$38 -> 15326 | N44: =+E44/M44 -> 0.62284516
A45: Electrico | B45: Cablecanal (x ml) | C45: Demian | D45: ml | E45: =+H45*$H$38 -> 0 | F45: 45631 | H45: 0 | I45: 44835 | M45: =+L45/$M$38 -> 0 | N45: =+E45/M45 -> #DIV/0!
A46: Electrico | B46: Colocacion Interruptores / Tomas | C46: Demian | D46: u | E46: =+H46*$H$38 -> 3535.4537 | F46: 45631 | H46: 500 | I46: 44835 | L46: 11000 | M46: =+L46/$M$38 -> 11000 | N46: =+E46/M46 -> 0.32140488
A47: Electrico | B47: Colocacion de fichas / tomas de Telefono o TV | C47: Demian | D47: u | E47: =+H47*$H$38 -> 3535.4537 | F47: 45631 | H47: 500 | I47: 44835 | L47: 11000 | M47: =+L47/$M$38 -> 11000 | N47: =+E47/M47 -> 0.32140488
A48: Electrico | B48: Colocacion de Artefactos tipo (aplique, extractores, campanillas, etc) | C48: Demian | D48: u | E48: =+H48*$H$38 -> 10606.361 | F48: 45631 | H48: 1500 | I48: 44835 | L48: 5132 | M48: =+L48/$M$38 -> 5132 | N48: =+E48/M48 -> 2.066711
A49: Electrico | B49: Armado de Tablero de Bombas | C49: Demian | D49: u | E49: =+H49*$H$38 -> 141418.15 | F49: 45631 | H49: 20000 | I49: 44835 | L49: 246410 | M49: =+L49/$M$38 -> 246410 | N49: =+E49/M49 -> 0.57391399
A50: Electrico | B50: Portero Electrico hasta 2m | C50: Demian | D50: u | E50: =+H50*$H$38 -> 31819.083 | F50: 45631 | H50: =+H41+H39 -> 4500 | I50: 44835 | M50: =+L50/$M$38 -> 0 | N50: =+E50/M50 -> #DIV/0!
A51: Electrico | B51: Cableado estructurado Red / Telefono / TV | C51: Demian | D51: ml | E51: =+H51*$H$38 -> 10606.361 | F51: 45631 | H51: 1500 | I51: 44835 | M51: =+L51/$M$38 -> 0 | N51: =+E51/M51 -> #DIV/0!
A52: Electrico | B52: Colocacion Y armado de Tableros 1ID + 1 TM + 1 PAT | C52: Demian | D52: u | E52: =+H52*$H$38 -> 141418.15 | F52: 45631 | H52: 20000 | I52: 44835 | L52: 246410 | M52: =+L52/$M$38 -> 246410 | N52: =+E52/M52 -> 0.57391399
A53: Electrico | B53: Interruptor Diferencial Bipolar | C53: Demian | D53: u | E53: =+H53*$H$38 -> 31819.083 | F53: 45631 | H53: =+H41+H39 -> 4500 | I53: 44835 | L53: 44737 | M53: =+L53/$M$38 -> 44737 | N53: =+E53/M53 -> 0.71124758
A54: Electrico | B54: Interruptor Diferencial Tetrapolar | C54: Demian | D54: u | E54: =+H54*$H$38 -> 63638.166 | F54: 45631 | H54: =+H53*2 -> 9000 | I54: 44835 | L54: 77020 | M54: =+L54/$M$38 -> 77020 | N54: =+E54/M54 -> 0.82625508
A55: Electrico | B55: Interruptor Termomagnetico Bipolar | C55: Demian | D55: u | E55: =+H55*$H$38 -> 31819.083 | F55: 45631 | H55: =+H53 -> 4500 | I55: 44835 | L55: 44737 | M55: =+L55/$M$38 -> 44737 | N55: =+E55/M55 -> 0.71124758
A56: Electrico | B56: Interruptor Termomagnetico Tetrapolar | C56: Demian | D56: u | E56: =+H56*$H$38 -> 63638.166 | F56: 45631 | H56: =+H53*2 -> 9000 | I56: 44835 | L56: 77020 | M56: =+L56/$M$38 -> 77020 | N56: =+E56/M56 -> 0.82625508
A57: Electrico | B57: Automatico de bomba | C57: Demian | D57: u | E57: =+H57*$H$38 -> 42425.444 | F57: 45631 | H57: =+H39+H41+H48 -> 6000 | I57: 44835 | M57: =+L57/$M$38 -> 0 | N57: =+E57/M57 -> #DIV/0!
A58: Electrico | B58: Acometida Trifasica + 50Kw | C58: Demian | D58: gl | E58: =+H58*$H$38 -> 0 | F58: 45631 | H58: 0 | I58: 44835 | M58: =+L58/$M$38 -> 0 | N58: =+E58/M58 -> #DIV/0!
A59: Electrico | B59: Puesta a tierra: Jabalina + caja de inspeccion | C59: Demian | D59: u | E59: =+H59*$H$38 -> 49496.351 | F59: 45631 | H59: 7000 | I59: 44835 | L59: 92361 | M59: =+L59/$M$38 -> 92361 | N59: =+E59/M59 -> 0.53590099
B60: Cable subterraneo (1 boca cada 5 metros) | C60: Demian | D60: b | E60: =+H60*$H$38 -> 24748.176 | F60: 45631 | H60: 3500 | I60: 44835 | L60: 32890 | M60: =+L60/$M$38 -> 32890 | N60: =+E60/M60 -> 0.75245289
B63: Tablero seccional hasta 8 polos | L63: 17584 | M63: =+L63/$M$38 -> 17584 | P63: 47989 | Q63: =P63/$Q$38 -> #DIV/0!
B64: Tablero secicional de 8 a 36 polos | L64: 70345 | M64: =+L64/$M$38 -> 70345 | P64: 191984 | Q64: =P64/$Q$38 -> #DIV/0!
B65: Tablero seccional de 36 a 54 polos | L65: 105513 | M65: =+L65/$M$38 -> 105513 | P65: 287963 | Q65: =P65/$Q$38 -> #DIV/0!

Sheet Materiales
A3: PRECIOS UNITARIOS POR MATERIAL
D4: 45536
A7: Código | B7: DESCRIPCION | C7: UNIDAD | D7: Costo Material | E7: Proveedor
A8: *AGREG02 | B8: ARENA LAVADA | C8: m3 | D8: 32399.77 | E8: Cutuli Hnos | F8: 45625 | G8: BOLSÓN
B9: Piedra Partida | C9: m3 | D9: 56202.3 | E9: Cutuli Hnos | F9: 45625 | G9: BOLSÓN
B10: Cascote | C10: m3 | D10: 34246.8 | E10: Cutuli Hnos | F10: 45625 | G10: BOLSÓN
A11: *AGREG01 | B11: Cemento Portland x 50kg | C11: Bol | D11: 7809.48 | E11: Cutuli Hnos | F11: 45625 | G11: CEMENTO AVELLANEDA
A12: AGREG11 | B12: Cal Comun x 25kg | C12: bol | D12: 3837.96 | E12: Cutuli Hnos | F12: 45625
A13: CALMILAG | B13: cal milagro | C13: bol | D13: 10936.8 | E13: Cutuli Hnos | F13: 45625
A14: FE06 | B14: Barra de Acero Aleteado - 6mm x 12m | C14: u | D14: 3424.53 | E14: Cutuli Hnos | F14: 45625
B15: Barra de Acero Aleteado - 8mm x 12m | C15: u | D15: 6017.04 | E15: Cutuli Hnos | F15: 45625
B16: Barra de Acero Aleteado - 10mm x 12m | C16: u | D16: 9272.75 | E16: Cutuli Hnos | F16: 45625
B17: Barra de Acero Aleteado - 12mm x 12m | C17: u | D17: 13312.25 | E17: Cutuli Hnos | F17: 45625
B18: Barra de Acero Aleteado - 16mm x 12m | C18: u | D18: 23236.16 | E18: Cutuli Hnos | F18: 45625
B19: Barra de Acero Aleteado - 20mm x 12m | C19: u | D19: 36391.64 | E19: Cutuli Hnos | F19: 45625
B20: Barra de Acero Aleteado - 25mm x 12m | C20: u | D20: 56794.12 | E20: Cutuli Hnos | F20: 45625
A21: LADVISTA | B21: ladrillo a la vista 1 cara | C21: u | D21: 233.44 | E21: Cutuli Hnos | F21: 45625 | G21: 1/2 VISTA MDQ
A22: *LADRI03 | B22: LADRILLO CERAMICO 8 x 18 x 33 cm | C22: u | D22: 292.32 | E22: Cutuli Hnos | F22: 45625
A23: LADRI12 | B23: LADRILLO CERAMICO 12 x 18 x 33 cm | C23: u | D23: 365.4 | E23: Cutuli Hnos | F23: 45625
A24: LADRI181 | B24: LADRILLO CERAMICO 18 x 18 x 33 cm | C24: u | D24: 519.12 | E24: Cutuli Hnos | F24: 45625
A25: LADRIC | B25: Ladrillo Comun 12.5 x 5.5 x 25 | C25: u | D25: 132.3 | E25: Cutuli Hnos | F25: 45625
A26: LADRI182 | B26: Ladrillo hueco ceramico 12x19x33 - Portante | C26: u | D26: 563.22 | E26: Cutuli Hnos | F26: 45625
B27: Ladrillo hueco ceramico 18x19x33 - Portante | C27: u | D27: 694.26 | E27: Cutuli Hnos | F27: 45625
B28: Ladrillo Ceramico Kilablock 27 x 18 x 33 | C28: u
B29: Bloque de Hormigon 19 x 19 x 39 | C29: u | D29: 1016.6 | E29: Cutuli Hnos | F29: 45625
B30: Bloque de Hormigon 10 x 19 x 39 | C30: u | D30: 682.52 | E30: Cutuli Hnos | F30: 45625 | I30: Precio x 25 kg | J30: kg | K30: Precio x 30 kg | L30: kg
B31: Bloque de Hormigon 39 x 19 x 19 - simil pieda | C31: u
A32: *AGREG11 | B32: Adhesivo Klaukol Porcellanato Fluido x 30Kg | C32: bol | D32: =+K32 -> 18802.512 | E32: Cutuli Hnos | F32: 45625 | G32: WEBER FORTE PORCELLANATO X 25 KG | I32: 15668.76 | J32: 25 | K32: =+L32*I32/J32 -> 18802.512 | L32: 30
B33: Adhesivo Klaukol Impermeable Petenciado x 30Kg | C33: bol | D33: =+K33 -> 29811.732 | E33: Cutuli Hnos | F33: 45625 | G33: WEBER SUPLER FLEX 25 KG | I33: 24843.11 | J33: 25 | K33: =+L33*I33/J33 -> 29811.732 | L33: 30
A34: AGREG07 | B34: Aditivo Hidrofugo en pasta - Ceresita x 1kg | C34: kg | D34: =25122.56/20 -> 1256.128 | E34: Cutuli Hnos | F34: 45625 | G34: CERESITA X 20 LTS
A35: PINT015 | B35: Yeso Tuyango x 30kg | C35: b | D35: 9639 | E35: Cutuli Hnos | F35: 45625
B36: Pastina Klaukol x 1kg - Alta performance | C36: u | D36: =6428.7/2 -> 3214.35 | E36: Cutuli Hnos | F36: 45625 | G36: Prestige nieve
B37: Revoque Cementicio Exterior 3en1 | C37: bol | D37: 7534.8 | E37: Cutuli Hnos | F37: 45625 | G37: PROMEX E X 30
B38: Malla SIMA Q335 (8mm) | C38: u | D38: 126755.8 | E38: Cutuli Hnos | F38: 45625
B39: Malla SIMA Q188 (6mm) | C39: u | D39: 69985.79 | E39: Cutuli Hnos | F39: 45625
B40: Malla SIMA Q92 (4.2mm) | C40: u
B41: Alambre de Fardo | C41: kg | D41: 2302.02 | E41: Cutuli Hnos | F41: 45625 | G41: Alambre N°16
B42: Sika Poro Plus x 10 kg | C42: b | D42: =305000/1.21 -> 252066.12 | E42: ML | F42: 45631 | G42: https://articulo.mercadolibre.com.ar/MLA-1239468887-sika-poro-plus-espumigeno-para-hormigon-10-kg-_JM#polycard_client=search-nordic&position=11&search_layout=grid&type=item&tracking_id=c5802d9e-4804-403a-958c-824dd473f5b4
B44: Solera 70mm x 2.60m | C44: u | D44: 2932.93 | E44: Cutuli Hnos | F44: 45625
B45: Montante 69mm x 2.60m | C45: u | D45: 3295.47 | E45: Cutuli Hnos | F45: 45625
B46: Solera 35mm x 2.60m | C46: u | D46: 2147.85 | E46: Cutuli Hnos | F46: 45625
B47: Montante 34mm x 2.60m | C47: u | D47: 2468.66 | E47: Cutuli Hnos | F47: 45625
B48: Tornillo T1 - Aguja | C48: u | D48: =19787.84/1.21/500 -> 32.707174 | E48: CMP online | F48: 45631
B49: Tornillo T2 - Aguja | C49: u | D49: =18726.79/1.21/900 -> 17.196318 | E49: CMP online | F49: 45631
B50: Tornillo T3 - Aguja | C50: u | D50: =20025.61/1.21/400 -> 41.375227 | E50: CMP online | F50: 45631
B51: Fijacion completa del 8 | C51: u | D51: =7976.2/1.21/100 -> 65.919008 | E51: CMP online | F51: 45631
B52: Cinta Entramada - 90m | C52: u | D52: 4042.71 | E52: Cutuli Hnos | F52: 45625
B53: Cinta de Papel - 75m | C53: u | D53: 5920.61 | E53: Cutuli Hnos | F53: 45625 | G53: Pegue la de 150 m entramada
B54: Masilla x 32kg | C54: u | D54: 26872.02 | E54: Cutuli Hnos | F54: 45625
B55: Placa Roca de Yeso 1220 x 2440 - 12.5mm - STD | C55: u | D55: 10022.96 | E55: Cutuli Hnos | F55: 45625
B56: Placa Roca de Yeso 1220 x 2440 - 12.5mm - RH | C56: u | D56: 16160.1 | E56: Cutuli Hnos | F56: 45625
B57: Placa Roca de Yeso 1220 x 2440 - 12.5mm - RF | C57: u | D57: 14217.87 | E57: Cutuli Hnos | F57: 45625
B58: Cantonera x 2.60 | C58: u | D58: 1421.47 | E58: Cutuli Hnos | F58: 45625
B59: Buña Z x 2.60m | C59: u | D59: 2351.29 | E59: Cutuli Hnos | F59: 45625
B60: Lana De Vidrio 40mm X 21,6m2 Alta Densidad | C60: u | D60: 97970.9 | E60: Cutuli Hnos | F60: 45625 | G60: Rolac plata cubierta 1,20 x 18 x 50 mm
B61: Perfil Perimetral x 3.05 | C61: u | D61: =2989.38/1.21 -> 2470.562 | E61: CMP online | F61: 45631
B62: Larguero x 3.66 | C62: u | D62: =4712.54/1.21 -> 3894.6612 | E62: CMP online | F62: 45631
B63: Travesaño x 1.22 | C63: u | D63: =1527.23/1.21 -> 1262.1736 | E63: CMP online | F63: 45631
B64: Travesaño x 0.60 | C64: u | D64: =783.17/1.21 -> 647.24793 | E64: CMP online | F64: 45631 | H64: =106331.96*(1-0.28) -> 76559.011 | I64: =+H64/J65 -> 114838.52
B65: Lana De Vidrio Acustiver Ar400 50mm x 21,6m2 | C65: rol | D65: =+I64 -> 114838.52 | E65: Galvylam | F65: 45555 | H65: =1.2*12 -> 14.4 | I65: 21.6 | J65: =+H65/I65 -> 0.66666667
B66: Placa Decovinyl Liso 60x60 | C66: u | D66: =+M66 -> 6538.6116 | E66: ML | F66: 45631 | I66: 0.6 | J66: 0.6 | K66: =+I66*J66 -> 0.36 | L66: =21977/1.21 -> 18162.81 | M66: =+K66*L66 -> 6538.6116
B67: Alambre galvanizado N°14 x kg | C67: u | D67: =2993.96/1.21 -> 2474.3471 | E67: CMP online | F67: 45631
B68: Placa Decovinyl Liso 120x60 | C68: u | D68: 4751.7079 | E68: ML | F68: 45350 | G68: no tengo coti
A70: PINT001 | B70: Latex Loxon Interior Sherwin Williams Mate Bco x 20lts | C70: B | D70: 120622.23 | E70: Prestigio | F70: 45642
B71: Latex Loxon Interior Sherwin Williams Satinado Bco x 20lts | C71: u | D71: =287500/1.21 -> 237603.31 | E71: Prestigio Web | F71: 45654
B72: Latex Loxon Exterior Sherwin Williams Mate Bco x 20lts | C72: u | D72: 105657.74 | E72: Prestigio | F72: 45642
A73: ESMALTES | B73: Esmalte sintetico brillante Albalux Blanco x 4lts | C73: b | D73: 28011.57 | E73: Prestigio | F73: 45642
A74: ESMALTES | B74: Esmalte sintetico semi mate Albalux Blanco x 4lts | C74: b | D74: 28011.57 | E74: Prestigio | F74: 45642
A75: ESMALTES | B75: Esmalte sintetico satinado Satinol Blanco x 4lts | C75: b | D75: 28011.57 | E75: Prestigio | F75: 45642
A76: PINT010 | B76: Enduido Interior x 20lts | C76: B | D76: 18735.77 | E76: Prestigio | F76: 45642 | G76: COVER
B77: Recuplast Tradicional Blanco x 20 lts | C77: u | D77: =150268/1.21 -> 124188.43 | E77: Prestigio Web | F77: 45654
B78: Pintura Asfaltica Asfasol x18ts | C78: b | D78: 32845.78 | E78: Cutuli Hnos | F78: 45625
B79: Revear Marble - Medio x 30kg | C79: u
B80: Quimtex Romano Fino x 27 kg | C80: u | D80: =69011/1.21 -> 57033.884 | E80: Quimtex | F80: 45509
B81: Quimtex base cuarzo 18 lts | C81: u | D81: =113000/1.21 -> 93388.43 | E81: Quimtex | F81: 45509
B82: Membrana Geotextil Ormiflex 4mm - (35kg) x10m | C82: u | D82: 70192.21 | E82: Cutuli Hnos | F82: 45625 | G82: Membrana EMAPI W450
B83: Membrana Geotextil Ormiflex 4mm -(codigo 52) c/aluminio | C83: u
B84: Membrana Geotextil Ormiflex 4mm -(codigo 10) c/aluminio | C84: u
B85: Venda SikaTEX 75 - Rollo | C85: u | D85: =80000/1.21 -> 66115.702 | E85: Prestifio Web | F85: 45654
A86: PINT014 | B86: Fijador al Aguarras x 4lts | C86: B | D86: =52050.7/1.21 -> 43017.107 | E86: Prestigio WEB | F86: 45523
B87: Fijador al agua x 20 lts | C87: b | D87: 30467.49 | E87: Prestigio | F87: 45642 | G87: PRINZ
A88: PINT016 | B88: Aguarras Hydrarras Hydra x 18lts | C88: b | D88: 26907.33 | E88: Prestigio | F88: 45642
A89: PINT011 | B89: Lija 180 al agua x 10u | C89: u | D89: =566.14*10 -> 5661.4 | E89: Prestigio | F89: 45642
A90: PINT012 | B90: Cinta de Papel 36 mm x 40m | C90: u | D90: 3293.01 | E90: Prestigio | F90: 45642 | G90: 48 mm
A91: PINT013 | B91: Trapo | C91: u | D91: 735.06 | E91: Prestigio | F91: 45642
B92: Impregnante p/ Ladrillos Brikol 20 L - Semi Satinado | C92: u | D92: =240923.25/1.21 -> 199110.12 | E92: Prestigio WEB | F92: 45654 | G92: SikaGuard
B93: Rodillo de lana pelo corto antigota N°22 - El Galgo | C93: u | D93: 6678.36 | E93: Prestigio | F93: 45642
B94: Rodillo de lana pelo largo N°22 - El Galgo | C94: u | D94: =+D93 -> 6678.36 | E94: Prestigio | F94: 45642
B95: Pincel N° 20 - El Galgo | C95: u | D95: 5282.24 | E95: Prestigio | F95: 45642 | G95: N25
B96: Rollo de cartón corrugado 0,90 x 25 mts | C96: u | D96: 7427.6 | E96: Prestigio | F96: 45642
B97: Llana Plástica 12 x 25 cm | C97: u | D97: =15216/1.21 -> 12575.207 | E97: Prestigio WEB | F97: 45654
A99: CLAVO25 | B99: CLAVOS DE 21/2" X 12 | C99: KG | D99: =34082.69/16 -> 2130.1681 | E99: Cutuli Hnos | F99: 45625
A100: FENOLICO | B100: FENOLICO 18MM. COMUN 1.22 x 2.40 | C100: UD | D100: 26322.68 | E100: Newton | F100: 45583
A101: FENOLMEL | B101: FENOLICO 18MM. LAMINADO MELAMINICO | C101: M2 | D101: 51752.74 | E101: Newton | F101: 45602
A102: PUNTA3X3 | B102: tirante 3x3 para puntal 3.66 | C102: ml | D102: =+D103/3.66 -> 1213.73 | E102: Newton | F102: 45583
A103: TIRAN3X6 | B103: tirante 3x6 3.66 | C103: un | D103: =1213.73*3.66 -> 4442.2518 | E103: Newton | F103: 45583
A107: ACEROEST | B107: ACERO ESTRUCTURAL POR KILO | C107: KGF | D107: 1269.26 | E107: Cutuli Hnos | F107: 45625
A108: HORH30 | B108: Hormigon Elaborado H30 | C108: m3 | D108: 137000 | E108: Horcrisa | F108: 45616
B109: Traslado de Bomba | C109: gl | D109: 500000 | E109: Horcrisa | F109: 45616
B110: Bombeo | C110: m3 | D110: 5000 | E110: Horcrisa | F110: 45616
...

Sheet P-32
F2: Fecha: | G2: Completar…
A3: ANALISIS DE PRECIO UNITARIO
F4: Partida N°: | G4: 32
A5: Obra: | B5: Completar…
A6: Cliente: | B6: Completar… | F6: Código de Obra: | G6: Completar…
A7: Partida: | B7: Movimiento de suelos para bases c/ aporte de tosca (e: 40 cm en 2 capas de 20 cm)
C8: Unidad: | E8: Cantidad: | F8: Rendimiento:
C9: m3 | E9: 100 | F9: 25 | G9: m3/dia | J9: =65*0.4 -> 26 | L9: 120 | M9: 0.4 | N9: =+L9*M9 -> 48
A10: 1.- MATERIALES | L10: 60 | M10: 0.4 | N10: =+L10*M10 -> 24
A11: Código | B11: Descripción | C11: Unidad | D11: Cantidad | E11: Costo $ | F11: % Desp. | G11: Total $ | H11: Cant. x Obra
B12: Aporte de Tosca | C12: m3 | D12: 1 | E12: =VLOOKUP(B12,Materiales!$B$8:$D$118,3,FALSE) -> 9811.2872 | F12: 30 | G12: =+D12*E12*((F12+100)/100) -> 12754.673 | H12: =+D12*$E$9 -> 100
F13: Total Materiales: | G13: =SUM(G12:G12) -> 12754.673 | M13: 250 | N13: 0.5 | O13: =+M13*N13 -> 125
F14: Unitario Materiales: | G14: =+G13 -> 12754.673 | M14: 250 | N14: 0.4 | O14: =+M14*N14 -> 100
A15: 2.- EQUIPOS
A16: Código | B16: Descripción | D16: Cantidad | E16: Tarifa $ | F16: % Deprec. | G16: Total $
B17: Pala y retro 310J (c/ operario y combustible) - Alq. X dia | C17: d | D17: 1 | E17: =VLOOKUP(B17,'Rend. Equipos'!$B$7:$E$222,4,FALSE) -> 464850 | F17: 1 | G17: =+E17*D17*F17 -> 464850
B18: Combustible Retroexcav (96 lts) | C18: d | D18: 0 | E18: =VLOOKUP(B18,'Rend. Equipos'!$B$7:$E$222,4,FALSE) -> 107808 | F18: 1 | G18: =+E18*D18*F18 -> 0
B19: Camion chasis volcador 170E22 - (c/ operario y combustible) - Alq. X dia | C19: d | D19: 1 | E19: =VLOOKUP(B19,'Rend. Equipos'!$B$7:$E$222,4,FALSE) -> 258250 | F19: 1 | G19: =+E19*D19*F19 -> 258250
B20: Compactador pata de cabra 612H - (c/operario y combustible) - Alq. X dia | C20: d | D20: 0.25 | E20: =VLOOKUP(B20,'Rend. Equipos'!$B$7:$E$222,4,FALSE) -> 568150 | F20: 1 | G20: =+E20*D20*F20 -> 142037.5
F21: Total Equipos: | G21: =SUM(G17:G20) -> 865137.5
F22: Unitario Equipos: | G22: =+G21/F9 -> 34605.5
A23: 3.- MANO DE OBRA
A24: Código | B24: Descripción | C24: Unidad | D24: Cantidad | E24: Salario $ | G24: Total $
A25: OFAL | B25: OFICIAL ESPECIALIZADO ALBAÑIL | C25: j | D25: 1 | E25: =VLOOKUP(B25,'Mano de Obra'!$B$8:$C$100,2,FALSE) -> 85927.097 | G25: =+E25*D25 -> 85927.097
A26: MOFAL | B26: MEDIO OFICIAL ALBAÑIL | C26: j | D26: 1 | E26: =VLOOKUP(B26,'Mano de Obra'!$B$8:$C$100,2,FALSE) -> 65493.072 | G26: =+E26*D26 -> 65493.072
F27: Total Mano de Obra Menor: | G27: =SUM(G25:G26) -> 151420.17
F28: Grado de dificultad | G28: 1
F29: Total Mano de Obra: | G29: =+G28*G27 -> 151420.17
F30: Unitario Mano de Obra: | G30: =+G29/F9 -> 6056.8068
F34: Costo Directo por Unidad: | G34: =+G30+G22+G14 -> 53416.98
E35: Gastos Generales: | F35: =+RESUMEN!$I$2 -> 0 | G35: =IF(F35=0,0,F35*G34) -> 0
E36: Beneficio: | F36: =+RESUMEN!$I$3 -> 0 | G36: =IF(F36=0,0,F36*G34) -> 0
F37: PRECIO UNITARIO: | G37: =SUM(G34:G36) -> 53416.98

Sheet P-33
F2: Fecha: | G2: Completar …
A3: ANALISIS DE PRECIO UNITARIO
F4: Partida N°: | G4: 33
A5: Obra: | B5: Completar …
A6: Cliente: | B6: Completar … | F6: Código de Obra: | G6: Completar …
A7: Partida: | B7: Ladrillo común 12,5 x 5,5 x 25 (e:15 cm)
C8: Unidad: | E8: Cantidad: | F8: Rendimiento:
C9: m2 | E9: 100 | F9: 7 | G9: m2/dia
A10: 1.- MATERIALES | L10: 7
A11: Código | B11: Descripción | C11: Unidad | D11: Cantidad | E11: Costo $ | F11: % Desp. | G11: Total $ | H11: Cant. x Obra | L11: para 1 m2
A12: *AGREG01 | B12: Cemento Portland x 50kg | C12: bol | D12: 0.15 | E12: =VLOOKUP(B12,Materiales!$B$8:$D$118,3,FALSE) -> 7809.48 | F12: 10 | G12: =+D12*E12*((F12+100)/100) -> 1288.5642 | H12: =+D12*$E$9 -> 15 | I12: =+G12/4 -> 322.14105 | L12: 7.5 | M12: 50 | N12: =+L12/M12 -> 0.15
A13: AGREG11 | B13: Cal Comun x 25kg | C13: bol | D13: 0.3 | E13: =VLOOKUP(B13,Materiales!$B$8:$D$118,3,FALSE) -> 3837.96 | F13: 10 | G13: =+D13*E13*((F13+100)/100) -> 1266.5268 | H13: =+D13*$E$9 -> 30 | I13: =+G13/4 -> 316.6317 | L13: 7.5 | M13: 25 | N13: =+L13/M13 -> 0.3
A14: FE06 | B14: Barra de Acero Aleteado - 6mm x 12m | C14: u | D14: 0.17 | E14: =VLOOKUP(B14,Materiales!$B$8:$D$118,3,FALSE) -> 3424.53 | F14: 10 | G14: =+D14*E14*((F14+100)/100) -> 640.38711 | H14: =+D14*$E$9 -> 17 | I14: =+G14/4 -> 160.09678
A15: LADRIC | B15: Ladrillo Comun 12.5 x 5.5 x 25 | C15: u | D15: 60 | E15: =VLOOKUP(B15,Materiales!$B$8:$D$118,3,FALSE) -> 132.3 | F15: 5 | G15: =+D15*E15*((F15+100)/100) -> 8334.9 | H15: =+D15*$E$9 -> 6000 | I15: =+G15/4 -> 2083.725 | L15: 60 | M15: 1 | N15: =+L15/M15 -> 60
A16: *AGREG02 | B16: ARENA LAVADA | C16: m3 | D16: 0.035 | E16: =VLOOKUP(B16,Materiales!$B$8:$D$118,3,FALSE) -> 32399.77 | F16: 10 | G16: =+D16*E16*((F16+100)/100) -> 1247.3911 | H16: =+D16*$E$9 -> 3.5 | I16: =+G16/4 -> 311.84779 | L16: 0.035 | M16: 1 | N16: =+L16/M16 -> 0.035
B17: Consumibles (discos, alambre, maderas, etc.) | C17: gl | D17: 0.01 | E17: =+SUM(G12:G16) -> 12777.769 | F17: 3 | G17: =+D17*E17*((F17+100)/100) -> 131.61102 | H17: =+D17*$E$9 -> 1 | I17: =+G17/4 -> 32.902756
F18: Total Materiales: | G18: =SUM(G12:G17) -> 12909.38 | H18: =+G18/2 -> 6454.6901
F19: Unitario Materiales: | G19: =+G18 -> 12909.38
A20: 2.- EQUIPOS
A21: Código | B21: Descripción | C21: Unidad | D21: Cantidad | E21: Tarifa $ | F21: % Deprec. | G21: Total $
A22: EQALBA | B22: EQUIPO DE ALBAÑILERIA, carpetas, ladrillo | C22: gl | D22: 1 | E22: =VLOOKUP(B22,'Rend. Equipos'!$B$7:$E$222,4,FALSE) -> 2470106.6 | F22: =VLOOKUP(B22,'Rend. Equipos'!$B$6:$L$166,MATCH($F$21,'Rend. Equipos'!$B$6:$L$6,0),0) -> 0.00092592593 | G22: =+E22*D22*F22 -> 2287.1357
A23: *ANDAM05 | B23: ANDAMIO TUBULAR DE UNO A TRES CUERPOS | C23: gl | D23: 0.5 | E23: =VLOOKUP(B23,'Rend. Equipos'!$B$7:$E$222,4,FALSE) -> 1028123.1 | F23: =VLOOKUP(B23,'Rend. Equipos'!$B$6:$L$166,MATCH($F$21,'Rend. Equipos'!$B$6:$L$6,0),0) -> 0.00055555556 | G23: =+E23*D23*F23 -> 285.58975
A24: TROMPO | B24: Hormigonera De 150 Litros 1hp Con Rueda Maciza | C24: u | D24: 1 | E24: =VLOOKUP(B24,'Rend. Equipos'!$B$7:$E$222,4,FALSE) -> 689222.3 | F24: =VLOOKUP(B24,'Rend. Equipos'!$B$6:$L$166,MATCH($F$21,'Rend. Equipos'!$B$6:$L$6,0),0) -> 0.0013888889 | G24: =+E24*D24*F24 -> 957.2532
F25: Total Equipos: | G25: =SUM(G22:G24) -> 3529.9787
F26: Unitario Equipos: | G26: =+G25/F9 -> 504.28267
A27: 3.- MANO DE OBRA
A28: Código | B28: Descripción | C28: Unidad | D28: Cantidad | E28: Salario $ | G28: Total $
A29: OFAL | B29: OFICIAL ESPECIALIZADO ALBAÑIL | C29: j | D29: 1 | E29: =VLOOKUP(B29,'Mano de Obra'!$B$8:$C$100,2,FALSE) -> 85927.097 | G29: =+E29*D29 -> 85927.097
A30: AYUDANTE | B30: AYUDANTE ALBAÑIL | C30: j | D30: 1 | E30: =VLOOKUP(B30,'Mano de Obra'!$B$8:$C$100,2,FALSE) -> 60860.581 | G30: =+E30*D30 -> 60860.581
F31: Total Mano de Obra Menor: | G31: =SUM(G29:G30) -> 146787.68
F32: Grado de dificultad | G32: 1
F33: Total Mano de Obra: | G33: =+G32*G31 -> 146787.68
F34: Unitario Mano de Obra: | G34: =+G33/F9 -> 20969.668
E36: Costo Directo por Unidad: | G36: =+G34+G26+G19 -> 34383.331
E37: Gastos Generales: | F37: =+RESUMEN!$I$2 -> 0 | G37: =IF(F37=0,0,F37*G36) -> 0
E38: Beneficio: | F38: =+RESUMEN!$I$3 -> 0 | G38: =IF(F38=0,0,F38*G36) -> 0
F39: PRECIO UNITARIO: | G39: =SUM(G36:G38) -> 34383.331

Sheet P-34
F2: Fecha: | G2: Completar …
A3: ANALISIS DE PRECIO UNITARIO
F4: Partida N°: | G4: 34
A5: Obra: | B5: Completar …
A6: Cliente: | B6: Completar … | F6: Código de Obra: | G6: Completar …
A7: Partida: | B7: Ladrillo cerámico 8 x 18 x 33 cm
C8: Unidad: | E8: Cantidad: | F8: Rendimiento:
B9: (10 lts mezcla x m2) | C9: m2 | E9: 100 | F9: 15 | G9: m2/dia
A10: 1.- MATERIALES
A11: Código | B11: Descripción | C11: Unidad | D11: Cantidad | E11: Costo $ | F11: % Desp. | G11: Total $ | H11: Cant. x Obra | J11: Para 1 m2
A12: *LADRI03 | B12: LADRILLO CERAMICO 8 x 18 x 33 cm | C12: u | D12: 15 | E12: =VLOOKUP(B12,Materiales!$B$8:$D$118,3,FALSE) -> 292.32 | F12: 5 | G12: =+D12*E12*((F12+100)/100) -> 4604.04 | H12: =+D12*$E$9 -> 1500 | J12: 15.5
A13: FE06 | B13: Barra de Acero Aleteado - 6mm x 12m | C13: u | D13: 0.17 | E13: =VLOOKUP(B13,Materiales!$B$8:$D$118,3,FALSE) -> 3424.53 | F13: 10 | G13: =+D13*E13*((F13+100)/100) -> 640.38711 | H13: =+D13*$E$9 -> 17
A14: *AGREG02 | B14: ARENA LAVADA | C14: m3 | D14: 0.012 | E14: =VLOOKUP(B14,Materiales!$B$8:$D$118,3,FALSE) -> 32399.77 | F14: 10 | G14: =+D14*E14*((F14+100)/100) -> 427.67696 | H14: =+D14*$E$9 -> 1.2 | J14: 0.012
A15: AGREG11 | B15: Cal Comun x 25kg | C15: bol | D15: 0.1 | E15: =VLOOKUP(B15,Materiales!$B$8:$D$118,3,FALSE) -> 3837.96 | F15: 10 | G15: =+D15*E15*((F15+100)/100) -> 422.1756 | H15: =+D15*$E$9 -> 10 | J15: 2.5 | K15: 25 | L15: =+J15/K15 -> 0.1
A16: *AGREG01 | B16: Cemento Portland x 50kg | C16: bol | D16: 0.05 | E16: =VLOOKUP(B16,Materiales!$B$8:$D$118,3,FALSE) -> 7809.48 | F16: 10 | G16: =+D16*E16*((F16+100)/100) -> 429.5214 | H16: =+D16*$E$9 -> 5 | J16: 2.6 | K16: 50 | L16: =+J16/K16 -> 0.052
B17: Consumibles (discos, alambre, maderas, etc.) | C17: gl | D17: 0.01 | E17: =+SUM(G12:G16) -> 6523.8011 | F17: 3 | G17: =+D17*E17*((F17+100)/100) -> 67.195151 | H17: =+D17*$E$9 -> 1
F18: Total Materiales: | G18: =SUM(G12:G17) -> 6590.9962
F19: Unitario Materiales: | G19: =+G18 -> 6590.9962
A20: 2.- EQUIPOS
A21: Código | B21: Descripción | C21: Unidad | D21: Cantidad | E21: Tarifa $ | F21: % Deprec. | G21: Total $
A22: EQALBA | B22: EQUIPO DE ALBAÑILERIA, carpetas, ladrillo | C22: gl | D22: 1 | E22: =VLOOKUP(B22,'Rend. Equipos'!$B$7:$E$222,4,FALSE) -> 2470106.6 | F22: =VLOOKUP(B22,'Rend. Equipos'!$B$6:$L$166,MATCH($F$21,'Rend. Equipos'!$B$6:$L$6,0),0) -> 0.00092592593 | G22: =+E22*D22*F22 -> 2287.1357
A23: *ANDAM05 | B23: ANDAMIO TUBULAR DE UNO A TRES CUERPOS | C23: gl | D23: 0.5 | E23: =VLOOKUP(B23,'Rend. Equipos'!$B$7:$E$222,4,FALSE) -> 1028123.1 | F23: =VLOOKUP(B23,'Rend. Equipos'!$B$6:$L$166,MATCH($F$21,'Rend. Equipos'!$B$6:$L$6,0),0) -> 0.00055555556 | G23: =+E23*D23*F23 -> 285.58975
A24: TROMPO | B24: Hormigonera De 150 Litros 1hp Con Rueda Maciza | C24: u | D24: 1 | E24: =VLOOKUP(B24,'Rend. Equipos'!$B$7:$E$222,4,FALSE) -> 689222.3 | F24: =VLOOKUP(B24,'Rend. Equipos'!$B$6:$L$166,MATCH($F$21,'Rend. Equipos'!$B$6:$L$6,0),0) -> 0.0013888889 | G24: =+E24*D24*F24 -> 957.2532
F25: Total Equipos: | G25: =SUM(G22:G24) -> 3529.9787
F26: Unitario Equipos: | G26: =+G25/F9 -> 235.33191
A27: 3.- MANO DE OBRA
A28: Código | B28: Descripción | C28: Unidad | D28: Cantidad | E28: Salario $ | G28: Total $
A29: OFAL | B29: OFICIAL ESPECIALIZADO ALBAÑIL | C29: j | D29: 1 | E29: =VLOOKUP(B29,'Mano de Obra'!$B$8:$C$100,2,FALSE) -> 85927.097 | G29: =+E29*D29 -> 85927.097
A30: AYUDANTE | B30: AYUDANTE ALBAÑIL | C30: j | D30: 1 | E30: =VLOOKUP(B30,'Mano de Obra'!$B$8:$C$100,2,FALSE) -> 60860.581 | G30: =+E30*D30 -> 60860.581
F31: Total Mano de Obra Menor: | G31: =SUM(G29:G30) -> 146787.68
F32: Grado de dificultad | G32: 1
F33: Total Mano de Obra: | G33: =+G32*G31 -> 146787.68
F34: Unitario Mano de Obra: | G34: =+G33/F9 -> 9785.8452
F36: Costo Directo por Unidad: | G36: =+G34+G26+G19 -> 16612.173
E37: Gastos Generales: | F37: =+RESUMEN!$I$2 -> 0 | G37: =IF(F37=0,0,F37*G36) -> 0
E38: Beneficio: | F38: =+RESUMEN!$I$3 -> 0 | G38: =IF(F38=0,0,F38*G36) -> 0
F39: PRECIO UNITARIO: | G39: =SUM(G36:G38) -> 16612.173

Sheet P-35
F2: Fecha: | G2: Completar …
A3: ANALISIS DE PRECIO UNITARIO
F4: Partida N°: | G4: 35
A5: Obra: | B5: Completar …
A6: Cliente: | B6: Completar … | F6: Código de Obra: | G6: Completar …
A7: Partida: | B7: Ladrillo cerámico 12 x 18 x 33 cm
C8: Unidad: | E8: Cantidad: | F8: Rendimiento:
B9: (15 lts mezcla x m2) | C9: m2 | E9: 100 | F9: 15 | G9: m2/dia
A10: 1.- MATERIALES
A11: Código | B11: Descripción | C11: Unidad | D11: Cantidad | E11: Costo $ | F11: % Desp. | G11: Total $ | H11: Cant. x Obra
A12: FE06 | B12: Barra de Acero Aleteado - 6mm x 12m | C12: u | D12: 0.17 | E12: =VLOOKUP(B12,Materiales!$B$8:$D$118,3,FALSE) -> 3424.53 | F12: 10 | G12: =+D12*E12*((F12+100)/100) -> 640.38711 | H12: =+D12*$E$9 -> 17 | M12: lt | N12: lts
A13: LADRI12 | B13: LADRILLO CERAMICO 12 x 18 x 33 cm | C13: u | D13: 15 | E13: =VLOOKUP(B13,Materiales!$B$8:$D$118,3,FALSE) -> 365.4 | F13: 5 | G13: =+D13*E13*((F13+100)/100) -> 5755.05 | H13: =+D13*$E$9 -> 1500 | M13: 10 | N13: 15
A14: AGREG11 | B14: Cal Comun x 25kg | C14: bol | D14: 0.15 | E14: =VLOOKUP(B14,Materiales!$B$8:$D$118,3,FALSE) -> 3837.96 | F14: 10 | G14: =+D14*E14*((F14+100)/100) -> 633.2634 | H14: =+D14*$E$9 -> 15 | K14: ARENA LAVADA | L14: m3 | M14: 0.012 | N14: =+$N$13*M14/$M$13 -> 0.018
A15: *AGREG01 | B15: Cemento Portland x 50kg | C15: bol | D15: 0.075 | E15: =VLOOKUP(B15,Materiales!$B$8:$D$118,3,FALSE) -> 7809.48 | F15: 10 | G15: =+D15*E15*((F15+100)/100) -> 644.2821 | H15: =+D15*$E$9 -> 7.5 | K15: Cal Comun x 25kg | L15: bol | M15: 0.1 | N15: =+$N$13*M15/$M$13 -> 0.15
A16: *AGREG02 | B16: ARENA LAVADA | C16: m3 | D16: 0.018 | E16: =VLOOKUP(B16,Materiales!$B$8:$D$118,3,FALSE) -> 32399.77 | F16: 10 | G16: =+D16*E16*((F16+100)/100) -> 641.51545 | H16: =+D16*$E$9 -> 1.8 | K16: Cemento Portland x 50kg | L16: bol | M16: 0.05 | N16: =+$N$13*M16/$M$13 -> 0.075
B17: Consumibles (discos, alambre, maderas, etc.) | C17: gl | D17: 0.01 | E17: =+SUM(G12:G16) -> 8314.4981 | F17: 3 | G17: =+D17*E17*((F17+100)/100) -> 85.63933 | H17: =+D17*$E$9 -> 1
F18: Total Materiales: | G18: =SUM(G12:G16) -> 8314.4981
F19: Unitario Materiales: | G19: =+G18 -> 8314.4981
A20: 2.- EQUIPOS
A21: Código | B21: Descripción | C21: Unidad | D21: Cantidad | E21: Tarifa $ | F21: % Deprec. | G21: Total $
A22: EQALBA | B22: EQUIPO DE ALBAÑILERIA, carpetas, ladrillo | C22: gl | D22: 1 | E22: =VLOOKUP(B22,'Rend. Equipos'!$B$7:$E$222,4,FALSE) -> 2470106.6 | F22: =VLOOKUP(B22,'Rend. Equipos'!$B$6:$L$166,MATCH($F$21,'Rend. Equipos'!$B$6:$L$6,0),0) -> 0.00092592593 | G22: =+E22*D22*F22 -> 2287.1357 | J22: 60105.537
A23: *ANDAM05 | B23: ANDAMIO TUBULAR DE UNO A TRES CUERPOS | C23: gl | D23: 0.5 | E23: =VLOOKUP(B23,'Rend. Equipos'!$B$7:$E$222,4,FALSE) -> 1028123.1 | F23: =VLOOKUP(B23,'Rend. Equipos'!$B$6:$L$166,MATCH($F$21,'Rend. Equipos'!$B$6:$L$6,0),0) -> 0.00055555556 | G23: =+E23*D23*F23 -> 285.58975
A24: TROMPO | B24: Hormigonera De 150 Litros 1hp Con Rueda Maciza | C24: u | D24: 1 | E24: =VLOOKUP(B24,'Rend. Equipos'!$B$7:$E$222,4,FALSE) -> 689222.3 | F24: =VLOOKUP(B24,'Rend. Equipos'!$B$6:$L$166,MATCH($F$21,'Rend. Equipos'!$B$6:$L$6,0),0) -> 0.0013888889 | G24: =+E24*D24*F24 -> 957.2532
F25: Total Equipos: | G25: =SUM(G22:G24) -> 3529.9787 | J25: 0.02
F26: Unitario Equipos: | G26: =+G25/F9 -> 235.33191 | J26: =+J22*J25 -> 1202.1107
A27: 3.- MANO DE OBRA | J27: =+J26/F9 -> 80.140716
A28: Código | B28: Descripción | D28: Cantidad | E28: Salario $ | G28: Total $
A29: OFAL | B29: OFICIAL ESPECIALIZADO ALBAÑIL | D29: 1 | E29: =VLOOKUP(B29,'Mano de Obra'!$B$8:$C$100,2,FALSE) -> 85927.097 | G29: =+E29*D29 -> 85927.097
A30: AYUDANTE | B30: AYUDANTE ALBAÑIL | D30: 1 | E30: =VLOOKUP(B30,'Mano de Obra'!$B$8:$C$100,2,FALSE) -> 60860.581 | G30: =+E30*D30 -> 60860.581
F31: Total Mano de Obra Menor: | G31: =SUM(G29:G30) -> 146787.68
F32: Grado de dificultad | G32: 1
F33: Total Mano de Obra: | G33: =+G32*G31 -> 146787.68
F34: Unitario Mano de Obra: | G34: =+G33/F9 -> 9785.8452
F36: Costo Directo por Unidad: | G36: =+G34+G26+G19 -> 18335.675
E37: Gastos Generales: | F37: =+RESUMEN!$I$2 -> 0 | G37: =IF(F37=0,0,F37*G36) -> 0
E38: Beneficio: | F38: =+RESUMEN!$I$3 -> 0 | G38: =IF(F38=0,0,F38*G36) -> 0
F39: PRECIO UNITARIO: | G39: =SUM(G36:G38) -> 18335.675

Sheet P-36
F2: Fecha: | G2: Completar …
A3: ANALISIS DE PRECIO UNITARIO
F4: Partida N°: | G4: 36
A5: Obra: | B5: Completar …
A6: Cliente: | B6: Completar … | F6: Código de Obra: | G6: Completar …
A7: Partida: | B7: Ladrillo cerámico 18 x 18 x 33 cm
C8: Unidad: | E8: Cantidad: | F8: Rendimiento:
B9: (20 lts mezcla x m2) | C9: m2 | E9: 100 | F9: 15 | G9: m2/dia
A10: 1.- MATERIALES
A11: Código | B11: Descripción | C11: Unidad | D11: Cantidad | E11: Costo $ | F11: % Desp. | G11: Total $ | H11: Cant. x Obra
A12: LADRI181 | B12: LADRILLO CERAMICO 18 x 18 x 33 cm | C12: u | D12: 15 | E12: =VLOOKUP(B12,Materiales!$B$8:$D$118,3,FALSE) -> 519.12 | F12: 5 | G12: =+D12*E12*((F12+100)/100) -> 8176.14 | H12: =+D12*$E$9 -> 1500 | M12: lt | N12: lt
A13: FE06 | B13: Barra de Acero Aleteado - 6mm x 12m | C13: u | D13: 0.17 | E13: =VLOOKUP(B13,Materiales!$B$8:$D$118,3,FALSE) -> 3424.53 | F13: 10 | G13: =+D13*E13*((F13+100)/100) -> 640.38711 | H13: =+D13*$E$9 -> 17 | M13: 10 | N13: 20
A14: AGREG11 | B14: Cal Comun x 25kg | C14: bol | D14: 0.2 | E14: =VLOOKUP(B14,Materiales!$B$8:$D$118,3,FALSE) -> 3837.96 | F14: 10 | G14: =+D14*E14*((F14+100)/100) -> 844.3512 | H14: =+D14*$E$9 -> 20 | K14: Cal Comun x 25kg | L14: bol | M14: 0.1 | N14: =+$N$13*M14/$M$13 -> 0.2
A15: *AGREG01 | B15: Cemento Portland x 50kg | C15: bol | D15: 0.1 | E15: =VLOOKUP(B15,Materiales!$B$8:$D$118,3,FALSE) -> 7809.48 | F15: 10 | G15: =+D15*E15*((F15+100)/100) -> 859.0428 | H15: =+D15*$E$9 -> 10 | K15: Cemento Portland x 50kg | L15: bol | M15: 0.05 | N15: =+$N$13*M15/$M$13 -> 0.1
A16: *AGREG02 | B16: ARENA LAVADA | C16: m3 | D16: 0.024 | E16: =VLOOKUP(B16,Materiales!$B$8:$D$118,3,FALSE) -> 32399.77 | F16: 10 | G16: =+D16*E16*((F16+100)/100) -> 855.35393 | H16: =+D16*$E$9 -> 2.4 | K16: ARENA LAVADA | L16: m3 | M16: 0.012 | N16: =+$N$13*M16/$M$13 -> 0.024
B17: Consumibles (discos, alambre, maderas, etc.) | C17: gl | D17: 0.01 | E17: =+SUM(G12:G16) -> 11375.275 | F17: 3 | G17: =+D17*E17*((F17+100)/100) -> 117.16533 | H17: =+D17*$E$9 -> 1
F18: Total Materiales: | G18: =SUM(G12:G17) -> 11492.44
F19: Unitario Materiales: | G19: =+G18 -> 11492.44
A20: 2.- EQUIPOS
A21: Código | B21: Descripción | C21: Unidad | D21: Cantidad | E21: Tarifa $ | F21: % Deprec. | G21: Total $
A22: EQALBA | B22: EQUIPO DE ALBAÑILERIA, carpetas, ladrillo | C22: gl | D22: 1 | E22: =VLOOKUP(B22,'Rend. Equipos'!$B$7:$E$222,4,FALSE) -> 2470106.6 | F22: =VLOOKUP(B22,'Rend. Equipos'!$B$6:$L$166,MATCH($F$21,'Rend. Equipos'!$B$6:$L$6,0),0) -> 0.00092592593 | G22: =+E22*D22*F22 -> 2287.1357
A23: *ANDAM05 | B23: ANDAMIO TUBULAR DE UNO A TRES CUERPOS | C23: gl | D23: 0.5 | E23: =VLOOKUP(B23,'Rend. Equipos'!$B$7:$E$222,4,FALSE) -> 1028123.1 | F23: =VLOOKUP(B23,'Rend. Equipos'!$B$6:$L$166,MATCH($F$21,'Rend. Equipos'!$B$6:$L$6,0),0) -> 0.00055555556 | G23: =+E23*D23*F23 -> 285.58975
A24: TROMPO | B24: Hormigonera De 150 Litros 1hp Con Rueda Maciza | C24: u | D24: 1 | E24: =VLOOKUP(B24,'Rend. Equipos'!$B$7:$E$222,4,FALSE) -> 689222.3 | F24: =VLOOKUP(B24,'Rend. Equipos'!$B$6:$L$166,MATCH($F$21,'Rend. Equipos'!$B$6:$L$6,0),0) -> 0.0013888889 | G24: =+E24*D24*F24 -> 957.2532
F25: Total Equipos: | G25: =SUM(G22:G24) -> 3529.9787
F26: Unitario Equipos: | G26: =+G25/F9 -> 235.33191
A27: 3.- MANO DE OBRA
A28: Código | B28: Descripción | C28: Unidad | D28: Cantidad | E28: Salario $ | G28: Total $
A29: OFAL | B29: OFICIAL ESPECIALIZADO ALBAÑIL | C29: j | D29: 1 | E29: =VLOOKUP(B29,'Mano de Obra'!$B$8:$C$100,2,FALSE) -> 85927.097 | G29: =+E29*D29 -> 85927.097
A30: AYUDANTE | B30: AYUDANTE ALBAÑIL | C30: j | D30: 1 | E30: =VLOOKUP(B30,'Mano de Obra'!$B$8:$C$100,2,FALSE) -> 60860.581 | G30: =+E30*D30 -> 60860.581
F31: Total Mano de Obra Menor: | G31: =SUM(G29:G30) -> 146787.68
F32: Grado de dificultad | G32: 1
F33: Total Mano de Obra: | G33: =+G32*G31 -> 146787.68
F34: Unitario Mano de Obra: | G34: =+G33/F9 -> 9785.8452
F36: Costo Directo por Unidad: | G36: =+G34+G26+G19 -> 21513.617
E37: Gastos Generales: | F37: =+RESUMEN!$I$2 -> 0 | G37: =IF(F37=0,0,F37*G36) -> 0
E38: Beneficio: | F38: =+RESUMEN!$I$3 -> 0 | G38: =IF(F38=0,0,F38*G36) -> 0
F39: PRECIO UNITARIO: | G39: =SUM(G36:G38) -> 21513.617

Sheet P-37
F2: Fecha: | G2: Completar …
A3: ANALISIS DE PRECIO UNITARIO
F4: Partida N°: | G4: 37
A5: Obra: | B5: Completar …
A6: Cliente: | B6: Completar … | F6: Código de Obra: | G6: Completar …
A7: Partida: | B7: Pared DOBLE Comun / 5 / LHC 08 - (ladrillo a la vista)
C8: Unidad: | E8: Cantidad: | F8: Rendimiento:
C9: m2 | E9: 100 | F9: 4 | G9: m2/dia
A10: 1.- MATERIALES
A11: Código | B11: Descripción | C11: Unidad | D11: Cantidad | E11: Costo $ | F11: % Desp. | G11: Total $ | H11: Cant. x Obra
B12: Mamposteria LHC 08
A13: AGREG11 | B13: LADRILLO CERAMICO 8 x 18 x 33 cm | C13: u | D13: 15 | E13: =VLOOKUP(B13,Materiales!$B$8:$D$118,3,FALSE) -> 292.32 | F13: 5 | G13: =+D13*E13*((F13+100)/100) -> 4604.04 | H13: =+D13*$E$9 -> 1500 | I13: 7.3 | J13: 25 | K13: =+I13/J13 -> 0.292
A14: *AGREG01 | B14: Barra de Acero Aleteado - 6mm x 12m | C14: u | D14: 0.17 | E14: =VLOOKUP(B14,Materiales!$B$8:$D$118,3,FALSE) -> 3424.53 | F14: 10 | G14: =+D14*E14*((F14+100)/100) -> 640.38711 | H14: =+D14*$E$9 -> 17 | I14: 7.5 | J14: 50 | K14: =+I14/J14 -> 0.15
A15: *AGREG02 | B15: ARENA LAVADA | C15: m3 | D15: 0.012 | E15: =VLOOKUP(B15,Materiales!$B$8:$D$118,3,FALSE) -> 32399.77 | F15: 10 | G15: =+D15*E15*((F15+100)/100) -> 427.67696 | H15: =+D15*$E$9 -> 1.2 | I15: 0.04 | J15: 1 | K15: =+I15/J15 -> 0.04
A16: LADVISTA | B16: Cal Comun x 25kg | C16: bol | D16: 0.1 | E16: =VLOOKUP(B16,Materiales!$B$8:$D$118,3,FALSE) -> 3837.96 | F16: 10 | G16: =+D16*E16*((F16+100)/100) -> 422.1756 | H16: =+D16*$E$9 -> 10
A17: FE06 | B17: Cemento Portland x 50kg | C17: bol | D17: 0.05 | E17: =VLOOKUP(B17,Materiales!$B$8:$D$118,3,FALSE) -> 7809.48 | F17: 10 | G17: =+D17*E17*((F17+100)/100) -> 429.5214 | H17: =+D17*$E$9 -> 5
B18: Azotado hidrófugo + pintura asfáltica
A19: *AGREG02 | B19: ARENA LAVADA | C19: m3 | D19: 0.006 | E19: =VLOOKUP(B19,Materiales!$B$8:$D$118,3,FALSE) -> 32399.77 | F19: 10 | G19: =+D19*E19*((F19+100)/100) -> 213.83848 | H19: =+D19*$E$9 -> 0.6
A20: AGREG07 | B20: Aditivo Hidrofugo en pasta - Ceresita x 1kg | C20: kg | D20: 0.1 | E20: =VLOOKUP(B20,Materiales!$B$8:$D$118,3,FALSE) -> 1256.128 | F20: 5 | G20: =+D20*E20*((F20+100)/100) -> 131.89344 | H20: =+D20*$E$9 -> 10
A21: *AGREG01 | B21: Cemento Portland x 50kg | C21: bol | D21: 0.054 | E21: =VLOOKUP(B21,Materiales!$B$8:$D$118,3,FALSE) -> 7809.48 | F21: 10 | G21: =+D21*E21*((F21+100)/100) -> 463.88311 | H21: =+D21*$E$9 -> 5.4
B22: Pintura Asfaltica Asfasol x18ts | C22: b | D22: =1/36 -> 0.027777778 | E22: =VLOOKUP(B22,Materiales!$B$8:$D$118,3,FALSE) -> 32845.78 | F22: 10 | G22: =+D22*E22*((F22+100)/100) -> 1003.6211 | H22: =+D22*$E$9 -> 2.7777778 | I22: Rend. 0,50 lts x m2
A23: PINT016 | B23: Aguarras Hydrarras Hydra x 18lts | C23: b | D23: 0.005 | E23: =VLOOKUP(B23,Materiales!$B$8:$D$118,3,FALSE) -> 26907.33 | F23: 5 | G23: =+D23*E23*((F23+100)/100) -> 141.26348 | H23: =+D23*$E$9 -> 0.5
B24: Rodillo de lana pelo largo N°22 - El Galgo | C24: u | D24: 0.01 | E24: =VLOOKUP(B24,Materiales!$B$8:$D$118,3,FALSE) -> 6678.36 | F24: 5 | G24: =+D24*E24*((F24+100)/100) -> 70.12278 | H24: =+D24*$E$9 -> 1
B25: Pared ladrillo a la vista
A26: *AGREG01 | B26: Cemento Portland x 50kg | C26: bol | D26: 0.15 | E26: =VLOOKUP(B26,Materiales!$B$8:$D$118,3,FALSE) -> 7809.48 | F26: 10 | G26: =+D26*E26*((F26+100)/100) -> 1288.5642 | H26: =+D26*$E$9 -> 15
A27: AGREG11 | B27: Cal Comun x 25kg | C27: bol | D27: 0.3 | E27: =VLOOKUP(B27,Materiales!$B$8:$D$118,3,FALSE) -> 3837.96 | F27: 10 | G27: =+D27*E27*((F27+100)/100) -> 1266.5268 | H27: =+D27*$E$9 -> 30
A28: FE06 | B28: Barra de Acero Aleteado - 6mm x 12m | C28: u | D28: 0.17 | E28: =VLOOKUP(B28,Materiales!$B$8:$D$118,3,FALSE) -> 3424.53 | F28: 10 | G28: =+D28*E28*((F28+100)/100) -> 640.38711 | H28: =+D28*$E$9 -> 17
A29: LADVISTA | B29: ladrillo a la vista 1 cara | C29: u | D29: 60 | E29: =VLOOKUP(B29,Materiales!$B$8:$D$118,3,FALSE) -> 233.44 | F29: 5 | G29: =+D29*E29*((F29+100)/100) -> 14706.72 | H29: =+D29*$E$9 -> 6000
A30: *AGREG02 | B30: ARENA LAVADA | C30: m3 | D30: 0.035 | E30: =VLOOKUP(B30,Materiales!$B$8:$D$118,3,FALSE) -> 32399.77 | F30: 10 | G30: =+D30*E30*((F30+100)/100) -> 1247.3911 | H30: =+D30*$E$9 -> 3.5
B31: Consumibles
B32: Consumibles (discos, alambre, maderas, etc.) | C32: gl | D32: 0.01 | E32: =+SUM(G13:G30) -> 27698.013 | F32: 3 | G32: =+D32*E32*((F32+100)/100) -> 285.28953 | H32: =+D32*$E$9 -> 1
F33: Total Materiales: | G33: =SUM(G13:G32) -> 27983.302
F34: Unitario Materiales: | G34: =+G33 -> 27983.302
A35: 2.- EQUIPOS
A36: Código | B36: Descripción | C36: Unidad | D36: Cantidad | E36: Tarifa $ | F36: % Deprec. | G36: Total $
A37: EQALBA | B37: EQUIPO DE ALBAÑILERIA, carpetas, ladrillo | C37: gl | D37: 1 | E37: =VLOOKUP(B37,'Rend. Equipos'!$B$7:$E$222,4,FALSE) -> 2470106.6 | F37: =VLOOKUP(B37,'Rend. Equipos'!$B$6:$L$166,MATCH($F$36,'Rend. Equipos'!$B$6:$L$6,0),0) -> 0.00092592593 | G37: =+E37*D37*F37 -> 2287.1357
A38: *ANDAM05 | B38: ANDAMIO TUBULAR DE UNO A TRES CUERPOS | C38: gl | D38: 0.5 | E38: =VLOOKUP(B38,'Rend. Equipos'!$B$7:$E$222,4,FALSE) -> 1028123.1 | F38: =VLOOKUP(B38,'Rend. Equipos'!$B$6:$L$166,MATCH($F$36,'Rend. Equipos'!$B$6:$L$6,0),0) -> 0.00055555556 | G38: =+E38*D38*F38 -> 285.58975
A39: TROMPO | B39: Hormigonera De 150 Litros 1hp Con Rueda Maciza | C39: u | D39: 1 | E39: =VLOOKUP(B39,'Rend. Equipos'!$B$7:$E$222,4,FALSE) -> 689222.3 | F39: =VLOOKUP(B39,'Rend. Equipos'!$B$6:$L$166,MATCH($F$36,'Rend. Equipos'!$B$6:$L$6,0),0) -> 0.0013888889 | G39: =+E39*D39*F39 -> 957.2532
F40: Total Equipos: | G40: =SUM(G37:G39) -> 3529.9787
F41: Unitario Equipos: | G41: =+G40/F9 -> 882.49467
A42: 3.- MANO DE OBRA | J42: horas x m2 | K42: Azotado | L42: Lh | M42: L comun | N42: Subtotla horas | O42: horas | P42: m2 x dia
A43: Código | B43: Descripción | C43: Unidad | D43: Cantidad | E43: Salario $ | G43: Total $ | J43: Oficial | K43: 0.25 | L43: 0.5 | M43: 1 | N43: =+SUM(K43:M43) -> 1.75 | O43: 7 | P43: =+O43/N43 -> 4
A44: OFAL | B44: OFICIAL ESPECIALIZADO ALBAÑIL | C44: j | D44: 1 | E44: =VLOOKUP(B44,'Mano de Obra'!$B$8:$C$100,2,FALSE) -> 85927.097 | G44: =+E44*D44 -> 85927.097 | J44: Ayudante | K44: 0.1 | L44: 0.5 | M44: 1 | N44: =+SUM(K44:M44) -> 1.6 | O44: 7 | P44: =+O44/N44 -> 4.375 | Q44: =+P43/P44 -> 0.91428571
A45: AYUDANTE | B45: AYUDANTE ALBAÑIL | C45: j | D45: 0.91 | E45: =VLOOKUP(B45,'Mano de Obra'!$B$8:$C$100,2,FALSE) -> 60860.581 | G45: =+E45*D45 -> 55383.129
F46: Total Mano de Obra Menor: | G46: =SUM(G44:G45) -> 141310.23
F47: Grado de dificultad | G47: 1
F48: Total Mano de Obra: | G48: =+G47*G46 -> 141310.23
F49: Unitario Mano de Obra: | G49: =+G48/F9 -> 35327.556
F51: Costo Directo por Unidad: | G51: =+G49+G41+G34 -> 64193.353
E52: Gastos Generales: | F52: =+RESUMEN!$I$2 -> 0 | G52: =IF(F52=0,0,F52*G51) -> 0
E53: Beneficio: | F53: =+RESUMEN!$I$3 -> 0 | G53: =IF(F53=0,0,F53*G51) -> 0
F54: PRECIO UNITARIO: | G54: =SUM(G51:G53) -> 64193.353

Sheet P-38
F2: Fecha: | G2: Completar …
A3: ANALISIS DE PRECIO UNITARIO
F4: Partida N°: | G4: 38
A5: Obra: | B5: Completar …
A6: Cliente: | B6: Completar … | F6: Código de Obra: | G6: Completar …
A7: Partida: | B7: Ladrillo hueco portante 12 x 19 x 33
C8: Unidad: | E8: Cantidad: | F8: Rendimiento:
B9: (15 lts mezcla x m2) | C9: m2 | E9: 100 | F9: 15 | G9: m2/dia
A10: 1.- MATERIALES
A11: Código | B11: Descripción | C11: Unidad | D11: Cantidad | E11: Costo $ | F11: % Desp. | G11: Total $ | H11: Cant. x Obra
A12: LADRI182 | B12: Ladrillo hueco ceramico 12x19x33 - Portante | C12: u | D12: 15 | E12: =VLOOKUP(B12,Materiales!$B$8:$D$118,3,FALSE) -> 563.22 | F12: 5 | G12: =+D12*E12*((F12+100)/100) -> 8870.715 | H12: =+D12*$E$9 -> 1500
A13: FE06 | B13: Barra de Acero Aleteado - 6mm x 12m | C13: u | D13: 0.17 | E13: =VLOOKUP(B13,Materiales!$B$8:$D$118,3,FALSE) -> 3424.53 | F13: 10 | G13: =+D13*E13*((F13+100)/100) -> 640.38711 | H13: =+D13*$E$9 -> 17
A14: AGREG11 | B14: Cal Comun x 25kg | C14: bol | D14: 0.15 | E14: =VLOOKUP(B14,Materiales!$B$8:$D$118,3,FALSE) -> 3837.96 | F14: 10 | G14: =+D14*E14*((F14+100)/100) -> 633.2634 | H14: =+D14*$E$9 -> 15
A15: *AGREG01 | B15: Cemento Portland x 50kg | C15: bol | D15: 0.075 | E15: =VLOOKUP(B15,Materiales!$B$8:$D$118,3,FALSE) -> 7809.48 | F15: 10 | G15: =+D15*E15*((F15+100)/100) -> 644.2821 | H15: =+D15*$E$9 -> 7.5
A16: *AGREG02 | B16: ARENA LAVADA | C16: m3 | D16: 0.018 | E16: =VLOOKUP(B16,Materiales!$B$8:$D$118,3,FALSE) -> 32399.77 | F16: 10 | G16: =+D16*E16*((F16+100)/100) -> 641.51545 | H16: =+D16*$E$9 -> 1.8
B17: Consumibles (discos, alambre, maderas, etc.) | C17: gl | D17: 0.01 | E17: =+SUM(G12:G16) -> 11430.163 | F17: 3 | G17: =+D17*E17*((F17+100)/100) -> 117.73068 | H17: =+D17*$E$9 -> 1 | J17: =+G17*100 -> 11773.068
F18: Total Materiales: | G18: =SUM(G12:G17) -> 11547.894
F19: Unitario Materiales: | G19: =+G18 -> 11547.894
A20: 2.- EQUIPOS
A21: Código | B21: Descripción | C21: Unidad | D21: Cantidad | E21: Tarifa $ | F21: % Deprec. | G21: Total $
A22: EQALBA | B22: EQUIPO DE ALBAÑILERIA, carpetas, ladrillo | C22: gl | D22: 1 | E22: =VLOOKUP(B22,'Rend. Equipos'!$B$7:$E$222,4,FALSE) -> 2470106.6 | F22: =VLOOKUP(B22,'Rend. Equipos'!$B$6:$L$166,MATCH($F$21,'Rend. Equipos'!$B$6:$L$6,0),0) -> 0.00092592593 | G22: =+E22*D22*F22 -> 2287.1357
A23: *ANDAM05 | B23: ANDAMIO TUBULAR DE UNO A TRES CUERPOS | C23: gl | D23: 0.5 | E23: =VLOOKUP(B23,'Rend. Equipos'!$B$7:$E$222,4,FALSE) -> 1028123.1 | F23: =VLOOKUP(B23,'Rend. Equipos'!$B$6:$L$166,MATCH($F$21,'Rend. Equipos'!$B$6:$L$6,0),0) -> 0.00055555556 | G23: =+E23*D23*F23 -> 285.58975
A24: TROMPO | B24: Hormigonera De 150 Litros 1hp Con Rueda Maciza | C24: u | D24: 1 | E24: =VLOOKUP(B24,'Rend. Equipos'!$B$7:$E$222,4,FALSE) -> 689222.3 | F24: =VLOOKUP(B24,'Rend. Equipos'!$B$6:$L$166,MATCH($F$21,'Rend. Equipos'!$B$6:$L$6,0),0) -> 0.0013888889 | G24: =+E24*D24*F24 -> 957.2532
F25: Total Equipos: | G25: =SUM(G22:G24) -> 3529.9787
F26: Unitario Equipos: | G26: =+G25/F9 -> 235.33191
A27: 3.- MANO DE OBRA
A28: Código | B28: Descripción | C28: Unidad | D28: Cantidad | E28: Salario $ | G28: Total $
A29: OFAL | B29: OFICIAL ESPECIALIZADO ALBAÑIL | C29: j | D29: 1 | E29: =VLOOKUP(B29,'Mano de Obra'!$B$8:$C$100,2,FALSE) -> 85927.097 | G29: =+E29*D29 -> 85927.097
A30: AYUDANTE | B30: AYUDANTE ALBAÑIL | C30: j | D30: 1 | E30: =VLOOKUP(B30,'Mano de Obra'!$B$8:$C$100,2,FALSE) -> 60860.581 | G30: =+E30*D30 -> 60860.581
F31: Total Mano de Obra Menor: | G31: =SUM(G29:G30) -> 146787.68
F32: Grado de dificultad | G32: 1
F33: Total Mano de Obra: | G33: =+G32*G31 -> 146787.68
F34: Unitario Mano de Obra: | G34: =+G33/F9 -> 9785.8452
F36: Costo Directo por Unidad: | G36: =+G34+G26+G19 -> 21569.071
E37: Gastos Generales: | F37: =+RESUMEN!$I$2 -> 0 | G37: =IF(F37=0,0,F37*G36) -> 0
E38: Beneficio: | F38: =+RESUMEN!$I$3 -> 0 | G38: =IF(F38=0,0,F38*G36) -> 0
F39: PRECIO UNITARIO: | G39: =SUM(G36:G38) -> 21569.071

Sheet P-39
F2: Fecha: | G2: Completar …
A3: ANALISIS DE PRECIO UNITARIO
F4: Partida N°: | G4: 39
A5: Obra: | B5: Completar …
A6: Cliente: | B6: Completar … | F6: Código de Obra: | G6: Completar …
A7: Partida: | B7: Amure puertas tipo (0,90 x 2,00 m)
C8: Unidad: | E8: Cantidad: | F8: Rendimiento: | J8: Ancho | K8: Largo | L8: e Tabique | M8: m3 mezcla
B9: (0,03 m3 de mezcla de concreto) | C9: u | E9: 100 | F9: 2 | G9: U/dia | J9: 0.05 | K9: =2+1+2 -> 5 | L9: 0.12 | M9: =+J9*K9*L9 -> 0.03
A10: 1.- MATERIALES
A11: Código | B11: Descripción | C11: Unidad | D11: Cantidad | E11: Costo $ | F11: % Desp. | G11: Total $ | H11: Cant. x Obra
A12: *AGREG02 | B12: ARENA LAVADA | C12: m3 | D12: =+P16 -> 0.036 | E12: =VLOOKUP(B12,Materiales!$B$8:$D$118,3,FALSE) -> 32399.77 | F12: 10 | G12: =+D12*E12*((F12+100)/100) -> 1283.0309 | H12: =+D12*$E$9 -> 3.6
A13: *AGREG01 | B13: Cemento Portland x 50kg | C13: bol | D13: =+P15 -> 0.324 | E13: =VLOOKUP(B13,Materiales!$B$8:$D$118,3,FALSE) -> 7809.48 | F13: 10 | G13: =+D13*E13*((F13+100)/100) -> 2783.2987 | H13: =+D13*$E$9 -> 32.4 | O13: Para m3 | P13: Para
F14: Total Materiales: | G14: =SUM(G12:G13) -> 4066.3296 | M14: Para 2 cm espesor | N14: U comercial | O14: 0.02 | P14: =+M9 -> 0.03
F15: Unitario Materiales: | G15: =+G14 -> 4066.3296 | L15: Cemento | M15: 10.8 | N15: 50 | O15: =+M15/N15 -> 0.216 | P15: =+O15*P14/O14 -> 0.324
A16: 2.- EQUIPOS | L16: Arena | M16: 0.024 | N16: 1 | O16: =+M16/N16 -> 0.024 | P16: =+O16*P14/O14 -> 0.036
A17: Código | B17: Descripción | C17: Unidad | D17: Cantidad | E17: Tarifa $ | F17: % Deprec. | G17: Total $
A18: EQALBA | B18: EQUIPO DE ALBAÑILERIA, carpetas, ladrillo | C18: gl | D18: 0.25 | E18: =VLOOKUP(B18,'Rend. Equipos'!$B$7:$E$222,4,FALSE) -> 2470106.6 | F18: =VLOOKUP(B18,'Rend. Equipos'!$B$6:$L$166,MATCH($F$17,'Rend. Equipos'!$B$6:$L$6,0),0) -> 0.00092592593 | G18: =+E18*D18*F18 -> 571.78394
A19: TROMPO | B19: Hormigonera De 150 Litros 1hp Con Rueda Maciza | C19: u | D19: 0.25 | E19: =VLOOKUP(B19,'Rend. Equipos'!$B$7:$E$222,4,FALSE) -> 689222.3 | F19: =VLOOKUP(B19,'Rend. Equipos'!$B$6:$L$166,MATCH($F$17,'Rend. Equipos'!$B$6:$L$6,0),0) -> 0.0013888889 | G19: =+E19*D19*F19 -> 239.3133
F20: Total Equipos: | G20: =SUM(G18:G19) -> 811.09724
F21: Unitario Equipos: | G21: =+G20/F9 -> 405.54862
A22: 3.- MANO DE OBRA
A23: Código | B23: Descripción | C23: Unidad | D23: Cantidad | E23: Salario $ | G23: Total $
A24: AYUDANTE | B24: AYUDANTE ALBAÑIL | C24: j | D24: 0.75 | E24: =VLOOKUP(B24,'Mano de Obra'!$B$8:$C$100,2,FALSE) -> 60860.581 | G24: =+E24*D24 -> 45645.436
A25: OFAL | B25: OFICIAL ESPECIALIZADO ALBAÑIL | C25: j | D25: 0.75 | E25: =VLOOKUP(B25,'Mano de Obra'!$B$8:$C$100,2,FALSE) -> 85927.097 | G25: =+E25*D25 -> 64445.323
F26: Total Mano de Obra Menor: | G26: =SUM(G24:G25) -> 110090.76
F27: Grado de dificultad | G27: 1
F28: Total Mano de Obra: | G28: =+G27*G26 -> 110090.76
F29: Unitario Mano de Obra: | G29: =+G28/F9 -> 55045.379
F31: Costo Directo por Unidad: | G31: =+G29+G21+G15 -> 59517.257
E32: Gastos Generales: | F32: =+RESUMEN!$I$2 -> 0 | G32: =IF(F32=0,0,F32*G31) -> 0
E33: Beneficio: | F33: =+RESUMEN!$I$3 -> 0 | G33: =IF(F33=0,0,F33*G31) -> 0
F34: PRECIO UNITARIO: | G34: =SUM(G31:G33) -> 59517.257

Sheet P-40
F2: Fecha: | G2: Completar …
A3: ANALISIS DE PRECIO UNITARIO
F4: Partida N°: | G4: 40
A5: Obra: | B5: Completar …
A6: Cliente: | B6: Completar … | F6: Código de Obra: | G6: Completar …
A7: Partida: | B7: Amure Premarcos | K7: Ancho | L7: h | M7: m2 | N7: e tabiq | O7: carga | P7: m3 | R7: Perim
C8: Unidad: | E8: Cantidad: | F8: Rendimiento: | J8: Premarco 1 | K8: 2.4 | L8: 2.3 | M8: =+K8*L8 -> 5.52 | N8: 0.05 | O8: 0.05 | P8: =+((K8*2)+(L8*2))*N8*O8 -> 0.0235 | R8: =+K8*2+L8*2 -> 9.4
B9: (0,0125 m3 de mezcla de concreto) | C9: u | E9: 100 | F9: 4 | G9: U/dia | J9: Premarco 2 | K9: 1.6 | L9: 1.2 | M9: =+K9*L9 -> 1.92 | N9: 0.05 | O9: 0.05 | P9: =+((K9*2)+(L9*2))*N9*O9 -> 0.014 | R9: =+K9*2+L9*2 -> 5.6
A10: 1.- MATERIALES | J10: Premarco 3 | K10: 0.6 | L10: 1.2 | M10: =+K10*L10 -> 0.72 | N10: 0.05 | O10: 0.05 | P10: =+((K10*2)+(L10*2))*N10*O10 -> 0.009 | R10: =+K10*2+L10*2 -> 3.6
A11: Código | B11: Descripción | C11: Unidad | D11: Cantidad | E11: Costo $ | F11: % Desp. | G11: Total $ | H11: Cant. x Obra | J11: Premarco 4 | K11: 1 | L11: 1.2 | M11: =+K11*L11 -> 1.2 | N11: 0.05 | O11: 0.05 | P11: =+((K11*2)+(L11*2))*N11*O11 -> 0.011 | R11: =+K11*2+L11*2 -> 4.4
A12: *AGREG02 | B12: ARENA LAVADA | C12: m3 | D12: =+U17 -> 0.0138 | E12: =VLOOKUP(B12,Materiales!$B$8:$D$118,3,FALSE) -> 32399.77 | F12: 5 | G12: =+D12*E12*((F12+100)/100) -> 469.47267 | H12: =+D12*$E$9 -> 1.38 | M12: =AVERAGE(M8:M11,0) -> 1.872 | P12: =AVERAGE(P8:P11,0) -> 0.0115 | Q12: m3 mezcla | R12: =AVERAGE(R8:R11,0) -> 4.6
A13: *AGREG01 | B13: Cemento Portland x 50kg | C13: bol | D13: =+U16 -> 0.1242 | E13: =VLOOKUP(B13,Materiales!$B$8:$D$118,3,FALSE) -> 7809.48 | F13: 5 | G13: =+D13*E13*((F13+100)/100) -> 1018.4343 | H13: =+D13*$E$9 -> 12.42
F14: Total Materiales: | G14: =SUM(G12:G13) -> 1487.907 | T14: Para m3 | U14: Para
F15: Unitario Materiales: | G15: =+G14 -> 1487.907 | R15: Para 2 cm espesor | S15: U comercial | T15: 0.02 | U15: =+P12 -> 0.0115
A16: 2.- EQUIPOS | Q16: Cemento | R16: 10.8 | S16: 50 | T16: =+R16/S16 -> 0.216 | U16: =+T16*U15/T15 -> 0.1242
A17: Código | B17: Descripción | C17: Unidad | D17: Cantidad | E17: Tarifa $ | F17: % Deprec. | G17: Total $ | Q17: Arena | R17: 0.024 | S17: 1 | T17: =+R17/S17 -> 0.024 | U17: =+T17*U15/T15 -> 0.0138
A18: EQALBA | B18: EQUIPO DE ALBAÑILERIA, carpetas, ladrillo | C18: gl | D18: 0.25 | E18: =VLOOKUP(B18,'Rend. Equipos'!$B$7:$E$222,4,FALSE) -> 2470106.6 | F18: =VLOOKUP(B18,'Rend. Equipos'!$B$6:$L$166,MATCH($F$17,'Rend. Equipos'!$B$6:$L$6,0),0) -> 0.00092592593 | G18: =+E18*D18*F18 -> 571.78394
A19: TROMPO | B19: Hormigonera De 150 Litros 1hp Con Rueda Maciza | C19: u | D19: 0.25 | E19: =VLOOKUP(B19,'Rend. Equipos'!$B$7:$E$222,4,FALSE) -> 689222.3 | F19: =VLOOKUP(B19,'Rend. Equipos'!$B$6:$L$166,MATCH($F$17,'Rend. Equipos'!$B$6:$L$6,0),0) -> 0.0013888889 | G19: =+E19*D19*F19 -> 239.3133
F20: Total Equipos: | G20: =SUM(G18:G19) -> 811.09724
F21: Unitario Equipos: | G21: =+G20/F9 -> 202.77431
A22: 3.- MANO DE OBRA
A23: Código | B23: Descripción | C23: Unidad | D23: Cantidad | E23: Salario $ | G23: Total $
A24: AYUDANTE | B24: AYUDANTE ALBAÑIL | C24: j | D24: 1 | E24: =VLOOKUP(B24,'Mano de Obra'!$B$8:$C$100,2,FALSE) -> 60860.581 | G24: =+E24*D24 -> 60860.581
A25: OFAL | B25: OFICIAL ESPECIALIZADO ALBAÑIL | C25: j | D25: 1 | E25: =VLOOKUP(B25,'Mano de Obra'!$B$8:$C$100,2,FALSE) -> 85927.097 | G25: =+E25*D25 -> 85927.097
F26: Total Mano de Obra Menor: | G26: =SUM(G24:G25) -> 146787.68
F27: Grado de dificultad | G27: 1
F28: Total Mano de Obra: | G28: =+G27*G26 -> 146787.68
F29: Unitario Mano de Obra: | G29: =+G28/F9 -> 36696.919
F31: Costo Directo por Unidad: | G31: =+G29+G21+G15 -> 38387.601
E32: Gastos Generales: | F32: =+RESUMEN!$I$2 -> 0 | G32: =IF(F32=0,0,F32*G31) -> 0
E33: Beneficio: | F33: =+RESUMEN!$I$3 -> 0 | G33: =IF(F33=0,0,F33*G31) -> 0
F34: PRECIO UNITARIO: | G34: =SUM(G31:G33) -> 38387.601

Sheet P-41
F2: Fecha: | G2: Completar …
A3: ANALISIS DE PRECIO UNITARIO
F4: Partida N°: | G4: 41
A5: Obra: | B5: Completar …
A6: Cliente: | B6: Completar … | F6: Código de Obra: | G6: Completar …
A7: Partida: | B7: Amure barandas (insertos c/1,00 m)
C8: Unidad: | E8: Cantidad: | F8: Rendimiento:
C9: ml | E9: 100 | F9: 5 | G9: ml/dia
A10: 1.- MATERIALES
A11: Código | B11: Descripción | C11: Unidad | D11: Cantidad | E11: Costo $ | F11: % Desp. | G11: Total $ | J11: Cada inserto | N11: 1.25
A12: *AGREG02 | B12: ARENA LAVADA | C12: m3 | D12: =+N19 -> 0.0018 | E12: =VLOOKUP(B12,Materiales!$B$8:$D$118,3,FALSE) -> 32399.77 | F12: 10 | G12: =+D12*E12*((F12+100)/100) -> 64.151545 | J12: Ancho | K12: prof | L12: h | M12: m3 mezcla | N12: m3 mezcla x ml
A13: *AGREG01 | B13: Cemento Portland x 50kg | C13: bol | D13: =+N18 -> 0.0162 | E13: =VLOOKUP(B13,Materiales!$B$8:$D$118,3,FALSE) -> 7809.48 | F13: 10 | G13: =+D13*E13*((F13+100)/100) -> 139.16493 | J13: 0.1 | K13: 0.12 | L13: 0.1 | M13: =+J13*K13*L13 -> 0.0012 | N13: =+M13*N11 -> 0.0015
B14: Consumibles (discos, alambre, maderas, etc.) | C14: gl | D14: 0.5 | E14: =+SUM(G12:G13) -> 203.31648 | F14: 3 | G14: =+D14*E14*((F14+100)/100) -> 104.70799
F15: Total Materiales: | G15: =SUM(G12:G14) -> 308.02446
F16: Unitario Materiales: | G16: =+G15 -> 308.02446 | M16: Para m3 | N16: Para
A17: 2.- EQUIPOS | K17: Para 2 cm espesor | L17: U comercial | M17: 0.02 | N17: =+N13 -> 0.0015
A18: Código | B18: Descripción | C18: Unidad | D18: Cantidad | E18: Tarifa $ | F18: % Deprec. | G18: Total $ | J18: Cemento | K18: 10.8 | L18: 50 | M18: =+K18/L18 -> 0.216 | N18: =+M18*N17/M17 -> 0.0162
A19: *EQUIP04 | B19: EQUIPO DE ALBAÑILERIA, carpetas, ladrillo | C19: gl | D19: 0.5 | E19: =VLOOKUP(B19,'Rend. Equipos'!$B$7:$E$222,4,FALSE) -> 2470106.6 | F19: =VLOOKUP(B19,'Rend. Equipos'!$B$6:$L$166,MATCH($F$18,'Rend. Equipos'!$B$6:$L$6,0),0) -> 0.00092592593 | G19: =+E19*D19*F19 -> 1143.5679 | J19: Arena | K19: 0.024 | L19: 1 | M19: =+K19/L19 -> 0.024 | N19: =+M19*N17/M17 -> 0.0018
A20: TROMPO | B20: Hormigonera De 150 Litros 1hp Con Rueda Maciza | C20: u | D20: 0.25 | E20: =VLOOKUP(B20,'Rend. Equipos'!$B$7:$E$222,4,FALSE) -> 689222.3 | F20: =VLOOKUP(B20,'Rend. Equipos'!$B$6:$L$166,MATCH($F$18,'Rend. Equipos'!$B$6:$L$6,0),0) -> 0.0013888889 | G20: =+E20*D20*F20 -> 239.3133
F21: Total Equipos: | G21: =SUM(G19:G20) -> 1382.8812
F22: Unitario Equipos: | G22: =+G21/F9 -> 276.57623
A23: 3.- MANO DE OBRA
A24: Código | B24: Descripción | D24: Cantidad | E24: Salario $ | G24: Total $
A25: AYUDANTE | B25: AYUDANTE ALBAÑIL | D25: 1 | E25: =VLOOKUP(B25,'Mano de Obra'!$B$8:$C$100,2,FALSE) -> 60860.581 | G25: =+E25*D25 -> 60860.581
A26: OFAL | B26: OFICIAL ESPECIALIZADO ALBAÑIL | D26: 1 | E26: =VLOOKUP(B26,'Mano de Obra'!$B$8:$C$100,2,FALSE) -> 85927.097 | G26: =+E26*D26 -> 85927.097
F27: Total Mano de Obra Menor: | G27: =SUM(G25:G26) -> 146787.68
F28: Grado de dificultad | G28: 1
F29: Total Mano de Obra: | G29: =+G28*G27 -> 146787.68
F30: Unitario Mano de Obra: | G30: =+G29/F9 -> 29357.536
F32: Costo Directo por Unidad: | G32: =+G30+G22+G16 -> 29942.136
E33: Gastos Generales: | F33: =+RESUMEN!$I$2 -> 0 | G33: =IF(F33=0,0,F33*G32) -> 0
E34: Beneficio: | F34: =+RESUMEN!$I$3 -> 0 | G34: =IF(F34=0,0,F34*G32) -> 0
F35: PRECIO UNITARIO: | G35: =SUM(G32:G34) -> 29942.136

Sheet P-42
F2: Fecha: | G2: Completar …
A3: ANALISIS DE PRECIO UNITARIO
F4: Partida N°: | G4: 42
A5: Obra: | B5: Completar …
A6: Cliente: | B6: Completar … | F6: Código de Obra: | G6: Completar …
A7: Partida: | B7: Azotado hidrófugo
C8: Unidad: | E8: Cantidad: | F8: Rendimiento:
C9: m2 | E9: 100 | F9: 28 | G9: m2/dia
A10: 1.- MATERIALES | M10: e: 0,5 cm
A11: Código | B11: Descripción | C11: Unidad | D11: Cantidad | E11: Costo $ | F11: % Desp. | G11: Total $ | H11: Cant. x Obra | J11: Proporciones | K11: Cant | L11: Un | M11: Para 1 m2 | N11: Medidas comerciales
A12: *AGREG02 | B12: ARENA LAVADA | C12: m3 | D12: 0.006 | E12: =VLOOKUP(B12,Materiales!$B$8:$D$118,3,FALSE) -> 32399.77 | F12: 10 | G12: =+D12*E12*((F12+100)/100) -> 213.83848 | H12: =+D12*$E$9 -> 0.6 | J12: 3 | K12: 0.006 | L12: m3 | M12: =+K12/N12 -> 0.006 | N12: 1
A13: AGREG07 | B13: Aditivo Hidrofugo en pasta - Ceresita x 1kg | C13: kg | D13: 0.1 | E13: =VLOOKUP(B13,Materiales!$B$8:$D$118,3,FALSE) -> 1256.128 | F13: 5 | G13: =+D13*E13*((F13+100)/100) -> 131.89344 | H13: =+D13*$E$9 -> 10 | K13: 0.1 | L13: kg | M13: =+K13/N13 -> 0.1 | N13: 1 | P13: de 175 a 200 gr x cm de espesor
A14: *AGREG01 | B14: Cemento Portland x 50kg | C14: Bol | D14: 0.054 | E14: =VLOOKUP(B14,Materiales!$B$8:$D$118,3,FALSE) -> 7809.48 | F14: 10 | G14: =+D14*E14*((F14+100)/100) -> 463.88311 | H14: =+D14*$E$9 -> 5.4 | J14: 1 | K14: 2.7 | L14: kg | M14: =+K14/N14 -> 0.054 | N14: 50
F15: Total Materiales: | G15: =SUM(G12:G14) -> 809.61503
F16: Unitario Materiales: | G16: =+G15 -> 809.61503
A17: 2.- EQUIPOS
A18: Código | B18: Descripción | C18: Unidad | D18: Cantidad | E18: Tarifa $ | F18: % Deprec. | G18: Total $
A19: *ANDAM05 | B19: ANDAMIO TUBULAR DE UNO A TRES CUERPOS | C19: gl | D19: 0.5 | E19: =VLOOKUP(B19,'Rend. Equipos'!$B$7:$E$222,4,FALSE) -> 1028123.1 | F19: =VLOOKUP(B19,'Rend. Equipos'!$B$6:$L$166,MATCH($F$18,'Rend. Equipos'!$B$6:$L$6,0),0) -> 0.00055555556 | G19: =+E19*D19*F19 -> 285.58975
A20: EQALBA | B20: EQUIPO DE ALBAÑILERIA, carpetas, ladrillo | C20: gl | D20: 1 | E20: =VLOOKUP(B20,'Rend. Equipos'!$B$7:$E$222,4,FALSE) -> 2470106.6 | F20: =VLOOKUP(B20,'Rend. Equipos'!$B$6:$L$166,MATCH($F$18,'Rend. Equipos'!$B$6:$L$6,0),0) -> 0.00092592593 | G20: =+E20*D20*F20 -> 2287.1357
A21: TROMPO | B21: Hormigonera De 150 Litros 1hp Con Rueda Maciza | C21: u | D21: 1 | E21: =VLOOKUP(B21,'Rend. Equipos'!$B$7:$E$222,4,FALSE) -> 689222.3 | F21: =VLOOKUP(B21,'Rend. Equipos'!$B$6:$L$166,MATCH($F$18,'Rend. Equipos'!$B$6:$L$6,0),0) -> 0.0013888889 | G21: =+E21*D21*F21 -> 957.2532
F22: Total Equipos: | G22: =SUM(G19:G21) -> 3529.9787
F23: Unitario Equipos: | G23: =+G22/F9 -> 126.07067
A24: 3.- MANO DE OBRA
A25: Código | B25: Descripción | C25: Unidad | D25: Cantidad | E25: Salario $ | G25: Total $ | J25: horas x m2 | K25: horas | L25: m2/d
A26: AYUDANTE | B26: AYUDANTE ALBAÑIL | C26: j | D26: 0.4 | E26: =VLOOKUP(B26,'Mano de Obra'!$B$8:$C$100,2,FALSE) -> 60860.581 | G26: =+E26*D26 -> 24344.232 | J26: 0.25 | K26: 7 | L26: =+K26/J26 -> 28
A27: OFAL | B27: OFICIAL ESPECIALIZADO ALBAÑIL | C27: j | D27: 1 | E27: =VLOOKUP(B27,'Mano de Obra'!$B$8:$C$100,2,FALSE) -> 85927.097 | G27: =+E27*D27 -> 85927.097 | J27: 0.1 | K27: 7 | L27: =+K27/J27 -> 70 | M27: =+J27/J26 -> 0.4
F28: Total Mano de Obra Menor: | G28: =SUM(G26:G27) -> 110271.33
F29: Grado de dificultad | G29: 1
F30: Total Mano de Obra: | G30: =+G29*G28 -> 110271.33
F31: Unitario Mano de Obra: | G31: =+G30/F9 -> 3938.2618
F33: Costo Directo por Unidad: | G33: =+G31+G23+G16 -> 4873.9475
E34: Gastos Generales: | F34: 0 | G34: =IF(F34=0,0,F34*G33) -> 0
E35: Beneficio: | F35: 0 | G35: =IF(F35=0,0,F35*G33) -> 0
F36: PRECIO UNITARIO: | G36: =SUM(G33:G35) -> 4873.9475

Sheet P-43
F2: Fecha: | G2: Completar …
A3: ANALISIS DE PRECIO UNITARIO
F4: Partida N°: | G4: 43
A5: Obra: | B5: Completar …
A6: Cliente: | B6: Completar … | F6: Código de Obra: | G6: Completar …
A7: Partida: | B7: Interior jaharro a la cal + Enlucido a la cal
C8: Unidad: | E8: Cantidad: | F8: Rendimiento:
C9: m2 | E9: 100 | F9: 6 | G9: m2/dia
A10: 1.- MATERIALES
A11: Código | B11: Descripción | C11: Unidad | D11: Cantidad | E11: Costo $ | F11: % Desp. | G11: Total $ | H11: Cant. x Obra
B12: Revoque grueso para interiores
A13: *AGREG02 | B13: ARENA LAVADA | C13: m3 | D13: 0.017 | E13: =VLOOKUP(B13,Materiales!$B$8:$D$118,3,FALSE) -> 32399.77 | F13: 10 | G13: =+D13*E13*((F13+100)/100) -> 605.8757 | H13: =+D13*$E$9 -> 1.7
A14: AGREG11 | B14: Cal Comun x 25kg | C14: bol | D14: 0.144 | E14: =VLOOKUP(B14,Materiales!$B$8:$D$118,3,FALSE) -> 3837.96 | F14: 10 | G14: =+D14*E14*((F14+100)/100) -> 607.93286 | H14: =+D14*$E$9 -> 14.4
A15: *AGREG01 | B15: Cemento Portland x 50kg | C15: bol | D15: 0.037 | E15: =VLOOKUP(B15,Materiales!$B$8:$D$118,3,FALSE) -> 7809.48 | F15: 10 | G15: =+D15*E15*((F15+100)/100) -> 317.84584 | H15: =+D15*$E$9 -> 3.7
B16: Revoque fino a la cal
A17: *AGREG02 | B17: ARENA LAVADA | C17: m3 | D17: 0.01 | E17: =VLOOKUP(B17,Materiales!$B$8:$D$118,3,FALSE) -> 32399.77 | F17: 10 | G17: =+D17*E17*((F17+100)/100) -> 356.39747 | H17: =+D17*$E$9 -> 1
A18: AGREG11 | B18: cal milagro | C18: bol | D18: 0.064 | E18: =VLOOKUP(B18,Materiales!$B$8:$D$118,3,FALSE) -> 10936.8 | F18: 10 | G18: =+D18*E18*((F18+100)/100) -> 769.95072 | H18: =+D18*$E$9 -> 6.4
A19: *AGREG01 | B19: Cemento Portland x 50kg | C19: bol | D19: 0.009 | E19: =VLOOKUP(B19,Materiales!$B$8:$D$118,3,FALSE) -> 7809.48 | F19: 10 | G19: =+D19*E19*((F19+100)/100) -> 77.313852 | H19: =+D19*$E$9 -> 0.9
F20: Total Materiales: | G20: =SUM(G12:G19) -> 2735.3164
F21: Unitario Materiales: | G21: =+G20 -> 2735.3164
A22: 2.- EQUIPOS
A23: Código | B23: Descripción | C23: Unidad | D23: Cantidad | E23: Tarifa $ | F23: % Deprec. | G23: Total $
A24: *ANDAM05 | B24: ANDAMIO TUBULAR DE UNO A TRES CUERPOS | C24: gl | D24: 0.5 | E24: =VLOOKUP(B24,'Rend. Equipos'!$B$7:$E$222,4,FALSE) -> 1028123.1 | F24: =VLOOKUP(B24,'Rend. Equipos'!$B$6:$L$166,MATCH($F$23,'Rend. Equipos'!$B$6:$L$6,0),0) -> 0.00055555556 | G24: =+E24*D24*F24 -> 285.58975
A25: EQALBA | B25: EQUIPO DE ALBAÑILERIA, carpetas, ladrillo | C25: gl | D25: 1 | E25: =VLOOKUP(B25,'Rend. Equipos'!$B$7:$E$222,4,FALSE) -> 2470106.6 | F25: =VLOOKUP(B25,'Rend. Equipos'!$B$6:$L$166,MATCH($F$23,'Rend. Equipos'!$B$6:$L$6,0),0) -> 0.00092592593 | G25: =+E25*D25*F25 -> 2287.1357
A26: TROMPO | B26: Hormigonera De 150 Litros 1hp Con Rueda Maciza | C26: u | D26: 1 | E26: =VLOOKUP(B26,'Rend. Equipos'!$B$7:$E$222,4,FALSE) -> 689222.3 | F26: =VLOOKUP(B26,'Rend. Equipos'!$B$6:$L$166,MATCH($F$23,'Rend. Equipos'!$B$6:$L$6,0),0) -> 0.0013888889 | G26: =+E26*D26*F26 -> 957.2532
F27: Total Equipos: | G27: =SUM(G24:G26) -> 3529.9787
F28: Unitario Equipos: | G28: =+G27/F9 -> 588.32978
A29: 3.- MANO DE OBRA
A30: Código | B30: Descripción | C30: Unidad | D30: Cantidad | E30: Salario $ | G30: Total $ | I30: M.O Chandias | J30: Grueso | K30: Fino | L30: Horas | M30: H x dia | N30: Rend.
A31: AYUDANTE | B31: AYUDANTE ALBAÑIL | C31: j | D31: 0.65 | E31: =VLOOKUP(B31,'Mano de Obra'!$B$8:$C$100,2,FALSE) -> 60860.581 | G31: =+E31*D31 -> 39559.378 | I31: Ayudante | J31: 0.25 | K31: 0.45 | L31: =+J31+K31 -> 0.7 | M31: 7 | N31: =+M31/L31 -> 10
A32: OFAL | B32: OFICIAL ESPECIALIZADO ALBAÑIL | C32: j | D32: 1 | E32: =VLOOKUP(B32,'Mano de Obra'!$B$8:$C$100,2,FALSE) -> 85927.097 | G32: =+E32*D32 -> 85927.097 | I32: Oficial | J32: 0.35 | K32: 0.8 | L32: =+J32+K32 -> 1.15 | M32: 7 | N32: =+M32/L32 -> 6.0869565 | O32: =+N32/N31 -> 0.60869565
F33: Total Mano de Obra Menor: | G33: =SUM(G31:G32) -> 125486.47
F34: Grado de dificultad | G34: 1
F35: Total Mano de Obra: | G35: =+G34*G33 -> 125486.47
F36: Unitario Mano de Obra: | G36: =+G35/F9 -> 20914.412
F38: Costo Directo por Unidad: | G38: =+G36+G28+G21 -> 24238.059
E39: Gastos Generales: | F39: =+RESUMEN!$I$2 -> 0 | G39: =IF(F39=0,0,F39*G38) -> 0
E40: Beneficio: | F40: =+RESUMEN!$I$3 -> 0 | G40: =IF(F40=0,0,F40*G38) -> 0
F41: PRECIO UNITARIO: | G41: =SUM(G38:G40) -> 24238.059

Sheet P-44
F2: Fecha: | G2: Completar…
A3: ANALISIS DE PRECIO UNITARIO
F4: Partida N°: | G4: 44
A5: Obra: | B5: Completar…
A6: Cliente: | B6: Completar… | F6: Código de Obra: | G6: Completar…
A7: Partida: | B7: Revoque Grueso impermeable Exterior hasta 3.00 m - Incl. Azotado hidrófugo
C8: Unidad: | E8: Cantidad: | F8: Rendimiento:
C9: m2 | E9: 100 | F9: 11.5 | G9: m2/dia
A10: 1.- MATERIALES
A11: Código | B11: Descripción | C11: Unidad | D11: Cantidad | E11: Costo $ | F11: % Desp. | G11: Total $ | H11: Cant. x Obra
B12: Azotado hidrofugo (5 lts/m2)
A13: *AGREG02 | B13: ARENA LAVADA | C13: m3 | D13: 0.006 | E13: =VLOOKUP(B13,Materiales!$B$8:$D$118,3,FALSE) -> 32399.77 | F13: 10 | G13: =+D13*E13*((F13+100)/100) -> 213.83848 | H13: =+D13*$E$9 -> 0.6
A14: AGREG07 | B14: Aditivo Hidrofugo en pasta - Ceresita x 1kg | C14: kg | D14: 0.1 | E14: =VLOOKUP(B14,Materiales!$B$8:$D$118,3,FALSE) -> 1256.128 | F14: 5 | G14: =+D14*E14*((F14+100)/100) -> 131.89344 | H14: =+D14*$E$9 -> 10
A15: *AGREG01 | B15: Cemento Portland x 50kg | C15: bol | D15: 0.054 | E15: =VLOOKUP(B15,Materiales!$B$8:$D$118,3,FALSE) -> 7809.48 | F15: 10 | G15: =+D15*E15*((F15+100)/100) -> 463.88311 | H15: =+D15*$E$9 -> 5.4
B16: Revoque grueso (15 lts/m2)
A17: *AGREG02 | B17: ARENA LAVADA | C17: m3 | D17: 0.02 | E17: =VLOOKUP(B17,Materiales!$B$8:$D$118,3,FALSE) -> 32399.77 | F17: 10 | G17: =+D17*E17*((F17+100)/100) -> 712.79494 | H17: =+D17*$E$9 -> 2
A18: AGREG11 | B18: Cal Comun x 25kg | C18: bol | D18: 0.06 | E18: =VLOOKUP(B18,Materiales!$B$8:$D$118,3,FALSE) -> 3837.96 | F18: 10 | G18: =+D18*E18*((F18+100)/100) -> 253.30536 | H18: =+D18*$E$9 -> 6
A19: *AGREG01 | B19: Cemento Portland x 50kg | C19: bol | D19: 0.26 | E19: =VLOOKUP(B19,Materiales!$B$8:$D$118,3,FALSE) -> 7809.48 | F19: 10 | G19: =+D19*E19*((F19+100)/100) -> 2233.5113 | H19: =+D19*$E$9 -> 26
F20: Total Materiales: | G20: =SUM(G12:G19) -> 4009.2266
F21: Unitario Materiales: | G21: =+G20 -> 4009.2266
A22: 2.- EQUIPOS
A23: Código | B23: Descripción | C23: Unidad | D23: Cantidad | E23: Tarifa $ | F23: % Deprec. | G23: Total $
A24: *ANDAM05 | B24: ANDAMIO TUBULAR DE UNO A TRES CUERPOS | C24: gl | D24: 0.5 | E24: =VLOOKUP(B24,'Rend. Equipos'!$B$7:$E$222,4,FALSE) -> 1028123.1 | F24: =VLOOKUP(B24,'Rend. Equipos'!$B$6:$L$166,MATCH($F$23,'Rend. Equipos'!$B$6:$L$6,0),0) -> 0.00055555556 | G24: =+E24*D24*F24 -> 285.58975
A25: EQALBA | B25: EQUIPO DE ALBAÑILERIA, carpetas, ladrillo | C25: gl | D25: 1 | E25: =VLOOKUP(B25,'Rend. Equipos'!$B$7:$E$222,4,FALSE) -> 2470106.6 | F25: =VLOOKUP(B25,'Rend. Equipos'!$B$6:$L$166,MATCH($F$23,'Rend. Equipos'!$B$6:$L$6,0),0) -> 0.00092592593 | G25: =+E25*D25*F25 -> 2287.1357
A26: TROMPO | B26: Hormigonera De 150 Litros 1hp Con Rueda Maciza | C26: u | D26: 1 | E26: =VLOOKUP(B26,'Rend. Equipos'!$B$7:$E$222,4,FALSE) -> 689222.3 | F26: =VLOOKUP(B26,'Rend. Equipos'!$B$6:$L$166,MATCH($F$23,'Rend. Equipos'!$B$6:$L$6,0),0) -> 0.0013888889 | G26: =+E26*D26*F26 -> 957.2532
F27: Total Equipos: | G27: =SUM(G24:G26) -> 3529.9787
F28: Unitario Equipos: | G28: =+G27/F9 -> 306.95467
A29: 3.- MANO DE OBRA
A30: Código | B30: Descripción | C30: Unidad | D30: Cantidad | E30: Salario $ | G30: Total $
A31: OFAL | B31: OFICIAL ESPECIALIZADO ALBAÑIL | C31: j | D31: 1 | E31: =VLOOKUP(B31,'Mano de Obra'!$B$8:$C$100,2,FALSE) -> 85927.097 | G31: =+E31*D31 -> 85927.097
A32: AYUDANTE | B32: AYUDANTE ALBAÑIL | C32: j | D32: 0.6 | E32: =VLOOKUP(B32,'Mano de Obra'!$B$8:$C$100,2,FALSE) -> 60860.581 | G32: =+E32*D32 -> 36516.348
F33: Total Mano de Obra Menor: | G33: =SUM(G31:G32) -> 122443.45
F34: Grado de dificultad | G34: 1
F35: Total Mano de Obra: | G35: =+G34*G33 -> 122443.45
F36: Unitario Mano de Obra: | G36: =+G35/F9 -> 10647.256
F38: Costo Directo por Unidad: | G38: =+G36+G28+G21 -> 14963.437
E39: Gastos Generales: | F39: =+RESUMEN!$I$2 -> 0 | G39: =IF(F39=0,0,F39*G38) -> 0
E40: Beneficio: | F40: =+RESUMEN!$I$3 -> 0 | G40: =IF(F40=0,0,F40*G38) -> 0
F41: PRECIO UNITARIO: | G41: =SUM(G38:G40) -> 14963.437

Sheet P-45
F2: Fecha: | G2: Completar…
A3: ANALISIS DE PRECIO UNITARIO
F4: Partida N°: | G4: 45
A5: Obra: | B5: Completar…
A6: Cliente: | B6: Completar… | F6: Código de Obra: | G6: Completar…
A7: Partida: | B7: Revoque Grueso impermeable Exterior a mas de 3.00 m - Incl. Azotado hidrófugo
C8: Unidad: | E8: Cantidad: | F8: Rendimiento:
C9: m2 | E9: 100 | F9: 8 | G9: m2/dia
A10: 1.- MATERIALES
A11: Código | B11: Descripción | C11: Unidad | D11: Cantidad | E11: Costo $ | F11: % Desp. | G11: Total $ | H11: Cant. x Obra
B12: Azotado hidrofugo (5 lts/m2)
A13: *AGREG02 | B13: ARENA LAVADA | C13: m3 | D13: 0.006 | E13: =VLOOKUP(B13,Materiales!$B$8:$D$118,3,FALSE) -> 32399.77 | F13: 10 | G13: =+D13*E13*((F13+100)/100) -> 213.83848 | H13: =+D13*$E$9 -> 0.6
A14: AGREG07 | B14: Aditivo Hidrofugo en pasta - Ceresita x 1kg | C14: kg | D14: 0.1 | E14: =VLOOKUP(B14,Materiales!$B$8:$D$118,3,FALSE) -> 1256.128 | F14: 5 | G14: =+D14*E14*((F14+100)/100) -> 131.89344 | H14: =+D14*$E$9 -> 10
A15: *AGREG01 | B15: Cemento Portland x 50kg | C15: bol | D15: 0.054 | E15: =VLOOKUP(B15,Materiales!$B$8:$D$118,3,FALSE) -> 7809.48 | F15: 10 | G15: =+D15*E15*((F15+100)/100) -> 463.88311 | H15: =+D15*$E$9 -> 5.4
B16: Revoque grueso (15 lts/m2)
A17: *AGREG02 | B17: ARENA LAVADA | C17: m3 | D17: 0.02 | E17: =VLOOKUP(B17,Materiales!$B$8:$D$118,3,FALSE) -> 32399.77 | F17: 10 | G17: =+D17*E17*((F17+100)/100) -> 712.79494 | H17: =+D17*$E$9 -> 2
A18: AGREG11 | B18: Cal Comun x 25kg | C18: bol | D18: 0.06 | E18: =VLOOKUP(B18,Materiales!$B$8:$D$118,3,FALSE) -> 3837.96 | F18: 10 | G18: =+D18*E18*((F18+100)/100) -> 253.30536 | H18: =+D18*$E$9 -> 6
A19: *AGREG01 | B19: Cemento Portland x 50kg | C19: bol | D19: 0.26 | E19: =VLOOKUP(B19,Materiales!$B$8:$D$118,3,FALSE) -> 7809.48 | F19: 10 | G19: =+D19*E19*((F19+100)/100) -> 2233.5113 | H19: =+D19*$E$9 -> 26
F20: Total Materiales: | G20: =SUM(G12:G19) -> 4009.2266
F21: Unitario Materiales: | G21: =+G20 -> 4009.2266
A22: 2.- EQUIPOS
A23: Código | B23: Descripción | C23: Unidad | D23: Cantidad | E23: Tarifa $ | F23: % Deprec. | G23: Total $
A24: BALANCIN | B24: Balancin | C24: gl | D24: 1 | E24: =VLOOKUP(B24,'Rend. Equipos'!$B$7:$E$222,4,FALSE) -> 10476479 | F24: =VLOOKUP(B24,'Rend. Equipos'!$B$6:$L$166,MATCH($F$23,'Rend. Equipos'!$B$6:$L$6,0),0) -> 0.00027777778 | G24: =+E24*D24*F24 -> 2910.1332
A25: *ANDAM05 | B25: ANDAMIO TUBULAR DE UNO A TRES CUERPOS | C25: gl | D25: 0 | E25: =VLOOKUP(B25,'Rend. Equipos'!$B$7:$E$222,4,FALSE) -> 1028123.1 | F25: =VLOOKUP(B25,'Rend. Equipos'!$B$6:$L$166,MATCH($F$23,'Rend. Equipos'!$B$6:$L$6,0),0) -> 0.00055555556 | G25: =+E25*D25*F25 -> 0
A26: EQALBA | B26: EQUIPO DE ALBAÑILERIA, carpetas, ladrillo | C26: gl | D26: 1 | E26: =VLOOKUP(B26,'Rend. Equipos'!$B$7:$E$222,4,FALSE) -> 2470106.6 | F26: =VLOOKUP(B26,'Rend. Equipos'!$B$6:$L$166,MATCH($F$23,'Rend. Equipos'!$B$6:$L$6,0),0) -> 0.00092592593 | G26: =+E26*D26*F26 -> 2287.1357
A27: TROMPO | B27: Hormigonera De 150 Litros 1hp Con Rueda Maciza | C27: u | D27: 1 | E27: =VLOOKUP(B27,'Rend. Equipos'!$B$7:$E$222,4,FALSE) -> 689222.3 | F27: =VLOOKUP(B27,'Rend. Equipos'!$B$6:$L$166,MATCH($F$23,'Rend. Equipos'!$B$6:$L$6,0),0) -> 0.0013888889 | G27: =+E27*D27*F27 -> 957.2532
F28: Total Equipos: | G28: =SUM(G24:G27) -> 6154.5221
F29: Unitario Equipos: | G29: =+G28/F9 -> 769.31526
A30: 3.- MANO DE OBRA
A31: Código | B31: Descripción | C31: Unidad | D31: Cantidad | E31: Salario $ | G31: Total $ | I31: M.O Chandias | J31: Azotado | K31: Revoque | L31: Horas | M31: Costo h balancin | N31: Horas | O31: H x dia | P31: Rend.
A32: OFAL | B32: OFICIAL ESPECIALIZADO ALBAÑIL | C32: j | D32: 1 | E32: =VLOOKUP(B32,'Mano de Obra'!$B$8:$C$100,2,FALSE) -> 85927.097 | G32: =+E32*D32 -> 85927.097 | I32: OF | J32: 0.25 | K32: 0.35 | L32: =+SUM(J32:K32) -> 0.6 | M32: 1.5 | N32: =+L32*M32 -> 0.9 | O32: 7 | P32: =+O32/N32 -> 7.7777778
A33: AYUDANTE | B33: AYUDANTE ALBAÑIL | C33: j | D33: 0.6 | E33: =VLOOKUP(B33,'Mano de Obra'!$B$8:$C$100,2,FALSE) -> 60860.581 | G33: =+E33*D33 -> 36516.348 | I33: AY | J33: 0.1 | K33: 0.25 | L33: =+SUM(J33:K33) -> 0.35 | M33: 1 | N33: =+L33*M33 -> 0.35 | O33: 7 | P33: =+O33/N33 -> 20 | Q33: =+L33/L32 -> 0.58333333
F34: Total Mano de Obra Menor: | G34: =SUM(G32:G33) -> 122443.45
F35: Grado de dificultad | G35: 1
F36: Total Mano de Obra: | G36: =+G35*G34 -> 122443.45
F37: Unitario Mano de Obra: | G37: =+G36/F9 -> 15305.431
F39: Costo Directo por Unidad: | G39: =+G37+G29+G21 -> 20083.973
E40: Gastos Generales: | F40: =+RESUMEN!$I$2 -> 0 | G40: =IF(F40=0,0,F40*G39) -> 0
E41: Beneficio: | F41: =+RESUMEN!$I$3 -> 0 | G41: =IF(F41=0,0,F41*G39) -> 0
F42: PRECIO UNITARIO: | G42: =SUM(G39:G41) -> 20083.973

Sheet P-46
F2: Fecha: | G2: Completar…
A3: ANALISIS DE PRECIO UNITARIO
F4: Partida N°: | G4: 46
A5: Obra: | B5: Completar…
A6: Cliente: | B6: Completar… | F6: Código de Obra: | G6: Completar…
A7: Partida: | B7: Contrapiso HHRP
C8: Unidad: | E8: Cantidad: | F8: Rendimiento:
C9: m3 | E9: 100 | F9: 1.4 | G9: m3/dia | N9: 1 | O9: =+N9/0.08 -> 12.5
A10: 1.- MATERIALES | N10: =+O10*N9/O9 -> 0.08 | O10: 1
A11: Código | B11: Descripción | C11: Unidad | D11: Cantidad | E11: Costo $ | F11: % Desp. | G11: Total $ | H11: Cant. x Obra | J11: Para 1 m3 | N11: Para 8 cm
A12: *AGREG01 | B12: Cemento Portland x 50kg | C12: bol | D12: 0.748 | E12: =VLOOKUP(B12,Materiales!$B$8:$D$118,3,FALSE) -> 7809.48 | F12: 10 | G12: =+D12*E12*((F12+100)/100) -> 6425.6401 | H12: =+D12*$E$9 -> 74.8 | J12: 38.4 | K12: 50 | L12: =+J12/K12 -> 0.768 | N12: =+J12*$N$10 -> 3.072 | O12: 50 | P12: =+N12/O12 -> 0.06144
A13: AGREG11 | B13: Cal Comun x 25kg | C13: bol | D13: 3.24 | E13: =VLOOKUP(B13,Materiales!$B$8:$D$118,3,FALSE) -> 3837.96 | F13: 10 | G13: =+D13*E13*((F13+100)/100) -> 13678.489 | H13: =+D13*$E$9 -> 324 | J13: 81 | K13: 25 | L13: =+J13/K13 -> 3.24 | N13: =+J13*$N$10 -> 6.48 | O13: 25 | P13: =+N13/O13 -> 0.2592
B14: Cascote | C14: m3 | D14: 0.77 | E14: =VLOOKUP(B14,Materiales!$B$8:$D$118,3,FALSE) -> 34246.8 | F14: 10 | G14: =+D14*E14*((F14+100)/100) -> 29007.04 | H14: =+D14*$E$9 -> 77 | J14: 0.77 | K14: 1 | L14: =+J14/K14 -> 0.77 | N14: =+J14*$N$10 -> 0.0616 | O14: 1 | P14: =+N14/O14 -> 0.0616
A15: *AGREG02 | B15: ARENA LAVADA | C15: m3 | D15: 0.515 | E15: =VLOOKUP(B15,Materiales!$B$8:$D$118,3,FALSE) -> 32399.77 | F15: 10 | G15: =+D15*E15*((F15+100)/100) -> 18354.47 | H15: =+D15*$E$9 -> 51.5 | J15: 0.515 | K15: 1 | L15: =+J15/K15 -> 0.515 | N15: =+J15*$N$10 -> 0.0412 | O15: 1 | P15: =+N15/O15 -> 0.0412
F16: Total Materiales: | G16: =SUM(G12:G15) -> 67465.639
F17: Unitario Materiales: | G17: =+G16 -> 67465.639
A18: 2.- EQUIPOS
A19: Código | B19: Descripción | C19: Unidad | D19: Cantidad | E19: Tarifa $ | F19: % Deprec. | G19: Total $
A20: TROMPO | B20: Hormigonera De 150 Litros 1hp Con Rueda Maciza | C20: u | D20: 1 | E20: =VLOOKUP(B20,'Rend. Equipos'!$B$7:$E$222,4,FALSE) -> 689222.3 | F20: =VLOOKUP(B20,'Rend. Equipos'!$B$6:$L$166,MATCH($F$19,'Rend. Equipos'!$B$6:$L$6,0),0) -> 0.0013888889 | G20: =+E20*D20*F20 -> 957.2532
A21: EQALBA | B21: EQUIPO DE ALBAÑILERIA, carpetas, ladrillo | C21: gl | D21: 1 | E21: =VLOOKUP(B21,'Rend. Equipos'!$B$7:$E$222,4,FALSE) -> 2470106.6 | F21: =VLOOKUP(B21,'Rend. Equipos'!$B$6:$L$166,MATCH($F$19,'Rend. Equipos'!$B$6:$L$6,0),0) -> 0.00092592593 | G21: =+E21*D21*F21 -> 2287.1357
F22: Total Equipos: | G22: =SUM(G20:G21) -> 3244.3889
F23: Unitario Equipos: | G23: =+G22/F9 -> 2317.4207
A24: 3.- MANO DE OBRA | P24: =+O9 -> 12.5
A25: Código | B25: Descripción | C25: Unidad | D25: Cantidad | E25: Salario $ | G25: Total $ | J25: M.O Chandias | K25: Horas | L25: H x dia | M25: Rend. | P25: m3 x dia
A26: AYUDANTE | B26: AYUDANTE ALBAÑIL | C26: j | D26: 1 | E26: =VLOOKUP(B26,'Mano de Obra'!$B$8:$C$100,2,FALSE) -> 60860.581 | G26: =+E26*D26 -> 60860.581 | J26: AY | K26: 0.4 | L26: 7 | M26: =+L26/K26 -> 17.5 | P26: =+M26/P24 -> 1.4
A27: OFAL | B27: OFICIAL ESPECIALIZADO ALBAÑIL | C27: j | D27: 0.75 | E27: =VLOOKUP(B27,'Mano de Obra'!$B$8:$C$100,2,FALSE) -> 85927.097 | G27: =+E27*D27 -> 64445.323 | J27: OF | K27: 0.3 | L27: 7 | M27: =+L27/K27 -> 23.333333 | N27: =+M26/M27 -> 0.75
F28: Total Mano de Obra Menor: | G28: =SUM(G26:G27) -> 125305.9
F29: Grado de dificultad | G29: 1
F30: Total Mano de Obra: | G30: =+G29*G28 -> 125305.9
F31: Unitario Mano de Obra: | G31: =+G30/F9 -> 89504.217
F33: Costo Directo por Unidad: | G33: =+G31+G23+G17 -> 159287.28
E34: Gastos Generales: | F34: =+RESUMEN!$I$2 -> 0 | G34: =IF(F34=0,0,F34*G33) -> 0
E35: Beneficio: | F35: =+RESUMEN!$I$3 -> 0 | G35: =IF(F35=0,0,F35*G33) -> 0
F36: PRECIO UNITARIO: | G36: =SUM(G33:G35) -> 159287.28

Sheet P-47
F2: Fecha: | G2: Completar…
A3: ANALISIS DE PRECIO UNITARIO
F4: Partida N°: | G4: 47
A5: Obra: | B5: Completar…
A6: Cliente: | B6: Completar… | F6: Código de Obra: | G6: Completar…
A7: Partida: | B7: Carpeta MC 1:3 (e: 2cm)
C8: Unidad: | E8: Cantidad: | F8: Rendimiento:
C9: m2 | E9: 100 | F9: 15 | G9: m2/dia | J9: 2 | K9: 2.5
A10: 1.- MATERIALES | J10: e: 2 cm | K10: e: 2,5 cm
A11: Código | B11: Descripción | C11: Unidad | D11: Cantidad | E11: Costo $ | F11: % Desp. | G11: Total $ | H11: Cant. x Obra | J11: x m2 | K11: x m2 | L11: U comerc | M11: Cant
A12: *AGREG01 | B12: Cemento Portland x 50kg | C12: bol | D12: 0.27 | E12: =VLOOKUP(B12,Materiales!$B$8:$D$118,3,FALSE) -> 7809.48 | F12: 10 | G12: =+D12*E12*((F12+100)/100) -> 2319.4156 | H12: =+D12*$E$9 -> 27 | J12: 10.8 | K12: =+J12*K9/J9 -> 13.5 | L12: 50 | M12: =+K12/L12 -> 0.27
A13: *AGREG02 | B13: ARENA LAVADA | C13: m3 | D13: 0.03 | E13: =VLOOKUP(B13,Materiales!$B$8:$D$118,3,FALSE) -> 32399.77 | F13: 10 | G13: =+D13*E13*((F13+100)/100) -> 1069.1924 | H13: =+D13*$E$9 -> 3 | J13: 0.024 | K13: =+J13*K9/J9 -> 0.03 | L13: 1 | M13: =+K13/L13 -> 0.03
F14: Total Materiales: | G14: =SUM(G12:G13) -> 3388.608
F15: Unitario Materiales: | G15: =+G14 -> 3388.608
A16: 2.- EQUIPOS
A17: Código | B17: Descripción | C17: Unidad | D17: Cantidad | E17: Tarifa $ | F17: % Deprec. | G17: Total $
A18: TROMPO | B18: Hormigonera De 150 Litros 1hp Con Rueda Maciza | C18: u | D18: 1 | E18: =VLOOKUP(B18,'Rend. Equipos'!$B$7:$E$222,4,FALSE) -> 689222.3 | F18: =VLOOKUP(B18,'Rend. Equipos'!$B$6:$L$166,MATCH($F$17,'Rend. Equipos'!$B$6:$L$6,0),0) -> 0.0013888889 | G18: =+E18*D18*F18 -> 957.2532
A19: EQALBA | B19: EQUIPO DE ALBAÑILERIA, carpetas, ladrillo | C19: gl | D19: 1 | E19: =VLOOKUP(B19,'Rend. Equipos'!$B$7:$E$222,4,FALSE) -> 2470106.6 | F19: =VLOOKUP(B19,'Rend. Equipos'!$B$6:$L$166,MATCH($F$17,'Rend. Equipos'!$B$6:$L$6,0),0) -> 0.00092592593 | G19: =+E19*D19*F19 -> 2287.1357
F20: Total Equipos: | G20: =SUM(G18:G19) -> 3244.3889
F21: Unitario Equipos: | G21: =+G20/F9 -> 216.2926
A22: 3.- MANO DE OBRA
A23: Código | B23: Descripción | C23: Unidad | D23: Cantidad | E23: Salario $ | G23: Total $ | I23: h/m2 | J23: horas x dia | K23: m2/d
A24: AYUDANTE | B24: AYUDANTE ALBAÑIL | C24: j | D24: 0.45 | E24: =VLOOKUP(B24,'Mano de Obra'!$B$8:$C$100,2,FALSE) -> 60860.581 | G24: =+E24*D24 -> 27387.261 | I24: 0.25 | J24: 8 | K24: =+J24/I24 -> 32 | L24: =+I24/I25 -> 0.45454545
A25: OFAL | B25: OFICIAL ESPECIALIZADO ALBAÑIL | C25: j | D25: 1 | E25: =VLOOKUP(B25,'Mano de Obra'!$B$8:$C$100,2,FALSE) -> 85927.097 | G25: =+E25*D25 -> 85927.097 | I25: 0.55 | J25: 8 | K25: =+J25/I25 -> 14.545455
F26: Total Mano de Obra Menor: | G26: =SUM(G24:G25) -> 113314.36
F27: Grado de dificultad | G27: 1
F28: Total Mano de Obra: | G28: =+G27*G26 -> 113314.36
F29: Unitario Mano de Obra: | G29: =+G28/F9 -> 7554.2906
F31: Costo Directo por Unidad: | G31: =+G29+G21+G15 -> 11159.191
E32: Gastos Generales: | F32: =+RESUMEN!$I$2 -> 0 | G32: =IF(F32=0,0,F32*G31) -> 0
E33: Beneficio: | F33: =+RESUMEN!$I$3 -> 0 | G33: =IF(F33=0,0,F33*G31) -> 0
F34: PRECIO UNITARIO: | G34: =SUM(G31:G33) -> 11159.191

Sheet P-48
F2: Fecha: | G2: Completar..
A3: ANALISIS DE PRECIO UNITARIO
F4: Partida N°: | G4: 48
A5: Obra: | B5: Completar..
A6: Cliente: | B6: Completar.. | F6: Código de Obra: | G6: Completar..
A7: Partida: | B7: Carpeta monolítico h = 7 cm
C8: Unidad: | E8: Cantidad: | F8: Rendimiento: | K8: m3 | L8: h | M8: m2
C9: m2 | E9: 100 | F9: 35 | G9: m2/dia | K9: 1 | L9: 0.07 | M9: =+K9/L9 -> 14.285714
A10: 1.- MATERIALES
A11: Código | B11: Descripción | C11: Unidad | D11: Cantidad | E11: Costo $ | F11: % Desp. | G11: Total $ | H11: Cant. x Obra | K11: Para 1 m3 | L11: Para 1 m2
A12: *AGREG02 | B12: ARENA LAVADA | C12: m3 | D12: =+L12 -> 0.0595 | E12: =VLOOKUP(B12,Materiales!$B$8:$D$118,3,FALSE) -> 32399.77 | F12: 10 | G12: =+D12*E12*((F12+100)/100) -> 2120.5649 | H12: =+D12*$E$9 -> 5.95 | K12: 0.85 | L12: =+K12/$M$9 -> 0.0595
A13: *AGREG01 | B13: Cemento Portland x 50kg | C13: bol | D13: =+L13 -> 0.42 | E13: =VLOOKUP(B13,Materiales!$B$8:$D$118,3,FALSE) -> 7809.48 | F13: 10 | G13: =+D13*E13*((F13+100)/100) -> 3607.9798 | H13: =+D13*$E$9 -> 42 | K13: 6 | L13: =+K13/$M$9 -> 0.42
A14: AGREG11 | B14: Cal Comun x 25kg | C14: bol | D14: =+L14 -> 0.14 | E14: =VLOOKUP(B14,Materiales!$B$8:$D$118,3,FALSE) -> 3837.96 | F14: 10 | G14: =+D14*E14*((F14+100)/100) -> 591.04584 | H14: =+D14*$E$9 -> 14 | K14: 2 | L14: =+K14/$M$9 -> 0.14
B15: Sika Poro Plus x 10 kg | C15: bal | D15: =+L15 -> 0.00245 | E15: =VLOOKUP(B15,Materiales!$B$8:$D$118,3,FALSE) -> 252066.12 | F15: 5 | G15: =+D15*E15*((F15+100)/100) -> 648.44008 | H15: =+D15*$E$9 -> 0.245 | K15: 0.035 | L15: =+K15/$M$9 -> 0.00245
F16: Total Materiales: | G16: =SUM(G12:G15) -> 6968.0306
F17: Unitario Materiales: | G17: =+G16 -> 6968.0306
A18: 2.- EQUIPOS
A19: Código | B19: Descripción | C19: Unidad | D19: Cantidad | E19: Tarifa $ | F19: % Deprec. | G19: Total $
A20: TROMPO | B20: Hormigonera De 150 Litros 1hp Con Rueda Maciza | C20: u | D20: 2 | E20: =VLOOKUP(B20,'Rend. Equipos'!$B$7:$E$222,4,FALSE) -> 689222.3 | F20: =VLOOKUP(B20,'Rend. Equipos'!$B$6:$L$166,MATCH($F$19,'Rend. Equipos'!$B$6:$L$6,0),0) -> 0.0013888889 | G20: =+E20*D20*F20 -> 1914.5064
A21: EQALBA | B21: EQUIPO DE ALBAÑILERIA, carpetas, ladrillo | C21: gl | D21: 1 | E21: =VLOOKUP(B21,'Rend. Equipos'!$B$7:$E$222,4,FALSE) -> 2470106.6 | F21: =VLOOKUP(B21,'Rend. Equipos'!$B$6:$L$166,MATCH($F$19,'Rend. Equipos'!$B$6:$L$6,0),0) -> 0.00092592593 | G21: =+E21*D21*F21 -> 2287.1357
F22: Total Equipos: | G22: =SUM(G20:G21) -> 4201.6421
F23: Unitario Equipos: | G23: =+G22/F9 -> 120.04692
A24: 3.- MANO DE OBRA
A25: Código | B25: Descripción | C25: Unidad | D25: Cantidad | E25: Salario $ | G25: Total $
A26: AYUDANTE | B26: AYUDANTE ALBAÑIL | C26: j | D26: 3 | E26: =VLOOKUP(B26,'Mano de Obra'!$B$8:$C$100,2,FALSE) -> 60860.581 | G26: =+E26*D26 -> 182581.74
A27: OFAL | B27: OFICIAL ESPECIALIZADO ALBAÑIL | C27: j | D27: 2 | E27: =VLOOKUP(B27,'Mano de Obra'!$B$8:$C$100,2,FALSE) -> 85927.097 | G27: =+E27*D27 -> 171854.19
F28: Total Mano de Obra Menor: | G28: =SUM(G26:G27) -> 354435.94
F29: Grado de dificultad | G29: 1
F30: Total Mano de Obra: | G30: =+G29*G28 -> 354435.94
F31: Unitario Mano de Obra: | G31: =+G30/F9 -> 10126.741
F33: Costo Directo por Unidad: | G33: =+G31+G23+G17 -> 17214.819
E34: Gastos Generales: | F34: =+RESUMEN!$I$2 -> 0 | G34: =IF(F34=0,0,F34*G33) -> 0
E35: Beneficio: | F35: =+RESUMEN!$I$3 -> 0 | G35: =IF(F35=0,0,F35*G33) -> 0
F36: PRECIO UNITARIO: | G36: =SUM(G33:G35) -> 17214.819

Sheet P-49
F2: Fecha: | G2: Completar..
A3: ANALISIS DE PRECIO UNITARIO | S3: 25 | T3: kg
F4: Partida N°: | G4: 49 | S4: 13.5
A5: Obra: | B5: Completar… | S5: =+S3/S4 -> 1.8518519
A6: Cliente: | B6: Completar… | F6: Código de Obra: | G6: Completar…
A7: Partida: | B7: Carpeta hidrófuga (e: 2 cm)
C8: Unidad: | E8: Cantidad: | F8: Rendimiento:
C9: m2 | E9: 100 | F9: 15 | G9: m2/dia | J9: 2 | K9: 2.5
A10: 1.- MATERIALES | J10: e: 2 cm | K10: e: 2,5 cm
A11: Código | B11: Descripción | C11: Unidad | D11: Cantidad | E11: Costo $ | F11: % Desp. | G11: Total $ | H11: Cant. x Obra | J11: x m2 | K11: x m2 | L11: U comerc | M11: Cant
A12: AGREG07 | B12: Aditivo Hidrofugo en pasta - Ceresita x 1kg | C12: kg | D12: 0.5 | E12: =VLOOKUP(B12,Materiales!$B$8:$D$118,3,FALSE) -> 1256.128 | F12: 5 | G12: =+D12*E12*((F12+100)/100) -> 659.4672 | H12: =+D12*$E$9 -> 50 | J12: =0.2*2 -> 0.4 | K12: =+J12*$K$9/$J$9 -> 0.5 | L12: 1 | M12: =+K12/L12 -> 0.5 | N12: de 175 a 200 gr x cm de espesor | O12: 2 | P12: 2.5
A13: *AGREG02 | B13: ARENA LAVADA | C13: m3 | D13: 0.03 | E13: =VLOOKUP(B13,Materiales!$B$8:$D$118,3,FALSE) -> 32399.77 | F13: 10 | G13: =+D13*E13*((F13+100)/100) -> 1069.1924 | H13: =+D13*$E$9 -> 3 | J13: 0.024 | K13: =+J13*$K$9/$J$9 -> 0.03 | L13: 1 | M13: =+K13/L13 -> 0.03 | O13: e: 2 cm | P13: e: 2,5 cm
A14: *AGREG01 | B14: Cemento Portland x 50kg | C14: bol | D14: 0.27 | E14: =VLOOKUP(B14,Materiales!$B$8:$D$118,3,FALSE) -> 7809.48 | F14: 10 | G14: =+D14*E14*((F14+100)/100) -> 2319.4156 | H14: =+D14*$E$9 -> 27 | J14: 10.8 | K14: =+J14*$K$9/$J$9 -> 13.5 | L14: 50 | M14: =+K14/L14 -> 0.27 | O14: x m2 | P14: x m2 | Q14: U comerc | R14: Cant
F15: Total Materiales: | G15: =SUM(G12:G14) -> 4048.0752 | O15: 10.8 | P15: =+O15*P12/O12 -> 13.5 | Q15: 50 | R15: =+P15/Q15 -> 0.27
F16: Unitario Materiales: | G16: =+G15 -> 4048.0752 | O16: 0.024 | P16: =+O16*P12/O12 -> 0.03 | Q16: 1 | R16: =+P16/Q16 -> 0.03
A17: 2.- EQUIPOS
A18: Código | B18: Descripción | C18: Unidad | D18: Cantidad | E18: Tarifa $ | F18: % Deprec. | G18: Total $
A19: TROMPO | B19: Hormigonera De 150 Litros 1hp Con Rueda Maciza | C19: u | D19: 1 | E19: =VLOOKUP(B19,'Rend. Equipos'!$B$7:$E$222,4,FALSE) -> 689222.3 | F19: =VLOOKUP(B19,'Rend. Equipos'!$B$6:$L$166,MATCH($F$18,'Rend. Equipos'!$B$6:$L$6,0),0) -> 0.0013888889 | G19: =+E19*D19*F19 -> 957.2532
A20: EQALBA | B20: EQUIPO DE ALBAÑILERIA, carpetas, ladrillo | C20: gl | D20: 1 | E20: =VLOOKUP(B20,'Rend. Equipos'!$B$7:$E$222,4,FALSE) -> 2470106.6 | F20: =VLOOKUP(B20,'Rend. Equipos'!$B$6:$L$166,MATCH($F$18,'Rend. Equipos'!$B$6:$L$6,0),0) -> 0.00092592593 | G20: =+E20*D20*F20 -> 2287.1357
F21: Total Equipos: | G21: =SUM(G19:G20) -> 3244.3889
F22: Unitario Equipos: | G22: =+G21/F9 -> 216.2926
A23: 3.- MANO DE OBRA
A24: Código | B24: Descripción | C24: Unidad | D24: Cantidad | E24: Salario $ | G24: Total $ | J24: h/m2 | K24: horas x dia | L24: m2/d
A25: OFAL | B25: OFICIAL ESPECIALIZADO ALBAÑIL | C25: j | D25: 1 | E25: =VLOOKUP(B25,'Mano de Obra'!$B$8:$C$100,2,FALSE) -> 85927.097 | G25: =+E25*D25 -> 85927.097 | J25: 0.55 | K25: 8 | L25: =+K25/J25 -> 14.545455
A26: AYUDANTE | B26: AYUDANTE ALBAÑIL | C26: j | D26: 0.45 | E26: =VLOOKUP(B26,'Mano de Obra'!$B$8:$C$100,2,FALSE) -> 60860.581 | G26: =+E26*D26 -> 27387.261 | J26: 0.25 | K26: 8 | L26: =+K26/J26 -> 32 | M26: =+J26/J25 -> 0.45454545
F27: Total Mano de Obra Menor: | G27: =SUM(G25:G26) -> 113314.36
F28: Grado de dificultad | G28: 1
F29: Total Mano de Obra: | G29: =+G27*G28 -> 113314.36
F30: Unitario Mano de Obra: | G30: =+G29/F9 -> 7554.2906
F32: Costo Directo por Unidad: | G32: =+G16+G22+G30 -> 11818.658
E33: Gastos Generales: | F33: =+RESUMEN!$I$2 -> 0 | G33: =IF(F33=0,0,F33*G32) -> 0
E34: Beneficio: | F34: =+RESUMEN!$I$3 -> 0 | G34: =IF(F34=0,0,F34*G32) -> 0
F35: PRECIO UNITARIO: | G35: =SUM(G32:G34) -> 11818.658

Sheet P-50
F2: Fecha: | G2: Completar..
A3: ANALISIS DE PRECIO UNITARIO
F4: Partida N°: | G4: 50
A5: Obra: | B5: Completar..
A6: Cliente: | B6: Completar.. | F6: Código de Obra: | G6: Completar..
A7: Partida: | B7: Cemento alisado o cilindrado (e: 3 cm)
C8: Unidad: | E8: Cantidad: | F8: Rendimiento:
C9: m2 | E9: 100 | F9: 11.5 | G9: m2/dia | J9: 2 | K9: 3
A10: 1.- MATERIALES | J10: e: 2 cm | K10: e: 2,5 cm
A11: Código | B11: Descripción | C11: Unidad | D11: Cantidad | E11: Costo $ | F11: % Desp. | G11: Total $ | H11: Cant. x Obra | J11: x m2 | K11: x m2 | L11: U comerc | M11: Cant
A12: *AGREG01 | B12: Cemento Portland x 50kg | C12: bol | D12: 0.324 | E12: =VLOOKUP(B12,Materiales!$B$8:$D$118,3,FALSE) -> 7809.48 | F12: 10 | G12: =+D12*E12*((F12+100)/100) -> 2783.2987 | H12: =+D12*$E$9 -> 32.4 | J12: 10.8 | K12: =+J12*$K$9/$J$9 -> 16.2 | L12: 50 | M12: =+K12/L12 -> 0.324 | O12: 2 | P12: 2.5
A13: *AGREG02 | B13: ARENA LAVADA | C13: m3 | D13: 0.036 | E13: =VLOOKUP(B13,Materiales!$B$8:$D$118,3,FALSE) -> 32399.77 | F13: 10 | G13: =+D13*E13*((F13+100)/100) -> 1283.0309 | H13: =+D13*$E$9 -> 3.6 | J13: 0.024 | K13: =+J13*$K$9/$J$9 -> 0.036 | L13: 1 | M13: =+K13/L13 -> 0.036 | O13: e: 2 cm | P13: e: 2,5 cm
F14: Total Materiales: | G14: =SUM(G12:G13) -> 4066.3296 | O14: x m2 | P14: x m2 | Q14: U comerc | R14: Cant
F15: Unitario Materiales: | G15: =+G14 -> 4066.3296 | O15: 10.8 | P15: =+O15*P12/O12 -> 13.5 | Q15: 50 | R15: =+P15/Q15 -> 0.27
A16: 2.- EQUIPOS | O16: 0.024 | P16: =+O16*P12/O12 -> 0.03 | Q16: 1 | R16: =+P16/Q16 -> 0.03
A17: Código | B17: Descripción | C17: Unidad | D17: Cantidad | E17: Tarifa $ | F17: % Deprec. | G17: Total $
A18: TROMPO | B18: Hormigonera De 150 Litros 1hp Con Rueda Maciza | C18: u | D18: 1 | E18: =VLOOKUP(B18,'Rend. Equipos'!$B$7:$E$222,4,FALSE) -> 689222.3 | F18: =VLOOKUP(B18,'Rend. Equipos'!$B$6:$L$166,MATCH($F$17,'Rend. Equipos'!$B$6:$L$6,0),0) -> 0.0013888889 | G18: =+E18*D18*F18 -> 957.2532
A19: EQALBA | B19: EQUIPO DE ALBAÑILERIA, carpetas, ladrillo | C19: u | D19: 1 | E19: =VLOOKUP(B19,'Rend. Equipos'!$B$7:$E$222,4,FALSE) -> 2470106.6 | F19: =VLOOKUP(B19,'Rend. Equipos'!$B$6:$L$166,MATCH($F$17,'Rend. Equipos'!$B$6:$L$6,0),0) -> 0.00092592593 | G19: =+E19*D19*F19 -> 2287.1357
B20: Rodillo de bronce para cementista grande 17 cm | C20: u | D20: 1 | E20: =VLOOKUP(B20,'Rend. Equipos'!$B$7:$E$222,4,FALSE) -> 72426.909 | F20: =VLOOKUP(B20,'Rend. Equipos'!$B$6:$L$166,MATCH($F$17,'Rend. Equipos'!$B$6:$L$6,0),0) -> 0 | G20: =+E20*D20*F20 -> 0
F21: Total Equipos: | G21: =SUM(G18:G20) -> 3244.3889
F22: Unitario Equipos: | G22: =+G21/F9 -> 282.12078
A23: 3.- MANO DE OBRA
A24: Código | B24: Descripción | C24: Unidad | D24: Cantidad | E24: Salario $ | G24: Total $ | I24: h x m2 | J24: h x dia | K24: m2/dia
A25: AYUDANTE | B25: AYUDANTE ALBAÑIL | C25: j | D25: 0.5 | E25: =VLOOKUP(B25,'Mano de Obra'!$B$8:$C$100,2,FALSE) -> 60860.581 | G25: =+E25*D25 -> 30430.29 | I25: 0.3 | J25: 7 | K25: =+J25/I25 -> 23.333333
A26: OFAL | B26: OFICIAL ESPECIALIZADO ALBAÑIL | C26: j | D26: 1 | E26: =VLOOKUP(B26,'Mano de Obra'!$B$8:$C$100,2,FALSE) -> 85927.097 | G26: =+E26*D26 -> 85927.097 | I26: 0.6 | J26: 7 | K26: =+J26/I26 -> 11.666667
F27: Total Mano de Obra Menor: | G27: =SUM(G25:G26) -> 116357.39
F28: Grado de dificultad | G28: 1
F29: Total Mano de Obra: | G29: =+G27*G28 -> 116357.39
F30: Unitario Mano de Obra: | G30: =+G29/F9 -> 10118.034
F32: Costo Directo por Unidad: | G32: =+G15+G22+G30 -> 14466.484
E33: Gastos Generales: | F33: =+RESUMEN!$I$2 -> 0 | G33: =IF(F33=0,0,F33*G32) -> 0
E34: Beneficio: | F34: =+RESUMEN!$I$3 -> 0 | G34: =IF(F34=0,0,F34*G32) -> 0
F35: PRECIO UNITARIO: | G35: =SUM(G32:G34) -> 14466.484

Sheet P-51
F2: Fecha: | G2: Completar …
A3: ANALISIS DE PRECIO UNITARIO
F4: Partida N°: | G4: 51
A5: Obra: | B5: Completar …
A6: Cliente: | B6: Completar … | F6: Código de Obra: | G6: Completar …
A7: Partida: | B7: Látex interior para paredes (incl. enduido)
C8: Unidad: | E8: Cantidad: | F8: Rendimiento:
C9: m2 | E9: 2500 | F9: 22 | G9: m2/dia
A10: 1.- MATERIALES | K10: VERA
A11: Código | B11: Descripción | C11: Unidad | D11: Cantidad | E11: Costo $ | F11: % Desp. | G11: Total $ | H11: Cant. x Obra | K11: 2651
A12: PINT014 | B12: Fijador al agua x 20 lts | C12: b | D12: 0.004 | E12: =VLOOKUP(B12,Materiales!$B$8:$D$118,3,FALSE) -> 30467.49 | F12: 5 | G12: =+D12*E12*((F12+100)/100) -> 127.96346 | H12: =+D12*$E$9 -> 10 | K12: =+D12*$K$11 -> 10.604
A13: PINT010 | B13: Enduido Interior x 20lts | C13: b | D13: 0.03 | E13: =VLOOKUP(B13,Materiales!$B$8:$D$118,3,FALSE) -> 18735.77 | F13: 10 | G13: =+D13*E13*((F13+100)/100) -> 618.28041 | H13: =+D13*$E$9 -> 75 | K13: =+D13*$K$11 -> 79.53
A14: PINT001 | B14: Latex Loxon Interior Sherwin Williams Mate Bco x 20lts | C14: b | D14: 0.0125 | E14: =VLOOKUP(B14,Materiales!$B$8:$D$118,3,FALSE) -> 120622.23 | F14: 10 | G14: =+D14*E14*((F14+100)/100) -> 1658.5557 | H14: =+D14*$E$9 -> 31.25 | K14: =+D14*$K$11 -> 33.1375
A15: PINT015 | B15: Yeso Tuyango x 30kg | C15: b | D15: 0.0025 | E15: =VLOOKUP(B15,Materiales!$B$8:$D$118,3,FALSE) -> 9639 | F15: 5 | G15: =+D15*E15*((F15+100)/100) -> 25.302375 | H15: =+D15*$E$9 -> 6.25 | K15: =+D15*$K$11 -> 6.6275
A16: PINT013 | B16: Trapo | C16: u | D16: 0.03 | E16: =VLOOKUP(B16,Materiales!$B$8:$D$118,3,FALSE) -> 735.06 | F16: 5 | G16: =+D16*E16*((F16+100)/100) -> 23.15439 | H16: =+D16*$E$9 -> 75 | K16: =+D16*$K$11 -> 79.53 | M16: =+SUM(G12:G14) -> 2404.7995 | N16: Pintura
A17: PINT012 | B17: Cinta de Papel 36 mm x 40m | C17: u | D17: 0.05 | E17: =VLOOKUP(B17,Materiales!$B$8:$D$118,3,FALSE) -> 3293.01 | F17: 10 | G17: =+D17*E17*((F17+100)/100) -> 181.11555 | H17: =+D17*$E$9 -> 125 | K17: =+D17*$K$11 -> 132.55 | M17: =+SUM(G15:G21) -> 518.96702 | N17: Consumibles
A18: PINT011 | B18: Lija 180 al agua x 10u | C18: u | D18: 0.025 | E18: =VLOOKUP(B18,Materiales!$B$8:$D$118,3,FALSE) -> 5661.4 | F18: 5 | G18: =+D18*E18*((F18+100)/100) -> 148.61175 | H18: =+D18*$E$9 -> 62.5 | K18: =+D18*$K$11 -> 66.275 | M18: =+M17/M16 -> 0.21580469 | N18: % incidencia
B19: Rodillo de lana pelo corto antigota N°22 - El Galgo | C19: u | D19: 0.005 | E19: =VLOOKUP(B19,Materiales!$B$8:$D$118,3,FALSE) -> 6678.36 | F19: 5 | G19: =+D19*E19*((F19+100)/100) -> 35.06139 | H19: =+D19*$E$9 -> 12.5 | K19: =+D19*$K$11 -> 13.255
B20: Pincel N° 20 - El Galgo | C20: u | D20: 0.005 | E20: =VLOOKUP(B20,Materiales!$B$8:$D$118,3,FALSE) -> 5282.24 | F20: 5 | G20: =+D20*E20*((F20+100)/100) -> 27.73176 | H20: =+D20*$E$9 -> 12.5 | K20: =+D20*$K$11 -> 13.255
B21: Rollo de cartón corrugado 0,90 x 25 mts | C21: u | D21: 0.01 | E21: =VLOOKUP(B21,Materiales!$B$8:$D$118,3,FALSE) -> 7427.6 | F21: 5 | G21: =+D21*E21*((F21+100)/100) -> 77.9898 | H21: =+D21*$E$9 -> 25 | K21: =+D21*$K$11 -> 26.51
F22: Total Materiales: | G22: =SUM(G12:G21) -> 2923.7665
F23: Unitario Materiales: | G23: =+G22 -> 2923.7665 | J23: =+G23*E9 -> 7309416.4
A24: 2.- EQUIPOS
A25: Código | B25: Descripción | D25: Cantidad | E25: Costo $ | F25: % Deprec. | G25: Total $ | H25: Obra
B26: ESCALERA MADERA PINTOR 8 ESCALONES | C26: u | D26: 2 | E26: =VLOOKUP(B26,'Rend. Equipos'!$B$7:$E$222,4,FALSE) -> 72091.109 | F26: =VLOOKUP(B26,'Rend. Equipos'!$B$6:$L$166,MATCH($F$25,'Rend. Equipos'!$B$6:$L$6,0),0) -> 0.0027777778 | G26: =+D26*E26*F26 -> 400.50616 | H26: =+D26*$E$9*F26/$F$9 -> 0.63131313 | K26: =+F26*$K$11*D26 -> 14.727778
A27: *EQUIPIN | B27: EQUIPO PARA PINTAR | C27: gl | D27: 2 | E27: =VLOOKUP(B27,'Rend. Equipos'!$B$7:$E$222,4,FALSE) -> 1241010.7 | F27: =VLOOKUP(B27,'Rend. Equipos'!$B$6:$L$166,MATCH($F$25,'Rend. Equipos'!$B$6:$L$6,0),0) -> 0.0013888889 | G27: =+D27*E27*F27 -> 3447.2519 | H27: =+D27*$E$9*F27/$F$9 -> 0.31565657 | K27: =+F27*$K$11*D27 -> 7.3638889
F28: Total Equipos: | G28: =SUM(G26:G27) -> 3847.7581
F29: Unitario Equipos: | G29: =+G28/F9 -> 174.89809 | J29: =+G29*E9 -> 437245.24 | K29: =+G29*K11 -> 463654.85
A30: 3.- MANO DE OBRA
A31: Código | B31: Descripción | D31: Cantidad | E31: Salario $ | G31: Total $
A32: OFPINTOR | B32: OFICIAL ESPECIALIZADO PINTOR | C32: j | D32: 1 | E32: =VLOOKUP(B32,'Mano de Obra'!$B$8:$C$100,2,FALSE) -> 85927.097 | G32: =+E32*D32 -> 85927.097
A33: MEDPINTO | B33: MEDIO OFICIAL PINTOR | C33: j | D33: 1.25 | E33: =VLOOKUP(B33,'Mano de Obra'!$B$8:$C$100,2,FALSE) -> 65493.072 | G33: =+E33*D33 -> 81866.34 | L33: h x m2 | M33: horas x dia | N33: m2 / dia
F34: Total Mano de Obra Menor: | G34: =SUM(G32:G33) -> 167793.44 | K34: Chandias | L34: 0.3 | M34: 7 | N34: =+M34/L34 -> 23.333333
F35: Grado de dificultad | G35: 1
F36: Total Mano de Obra: | G36: =+G35*G34 -> 167793.44
F37: Unitario Mano de Obra: | G37: =+G36/F9 -> 7626.9744 | J37: =+G37*E9 -> 19067436
F39: Costo Directo por Unidad: | G39: =+G37+G29+G23 -> 10725.639
E40: Gastos Generales: | F40: =+RESUMEN!$I$2 -> 0 | G40: =IF(F40=0,0,F40*G39) -> 0 | J40: =+SUM(J23:J37) -> 26814098
E41: Beneficio: | F41: =+RESUMEN!$I$3 -> 0 | G41: =IF(F41=0,0,F41*G39) -> 0
F42: PRECIO UNITARIO: | G42: =SUM(G39:G41) -> 10725.639

Sheet P-52
F2: Fecha: | G2: Completar …
A3: ANALISIS DE PRECIO UNITARIO
F4: Partida N°: | G4: 52
A5: Obra: | B5: Completar …
A6: Cliente: | B6: Completar … | F6: Código de Obra: | G6: Completar …
A7: Partida: | B7: látex para cielorrasos (incl. enduido)
C8: Unidad: | E8: Cantidad: | F8: Rendimiento:
C9: m2 | E9: 100 | F9: 17.5 | G9: m2/dia
A10: 1.- MATERIALES
A11: Código | B11: Descripción | C11: Unidad | D11: Cantidad | E11: Costo $ | F11: % Desp. | G11: Total $ | H11: Cant. x Obra
A12: PINT014 | B12: Fijador al agua x 20 lts | C12: b | D12: 0.004 | E12: =VLOOKUP(B12,Materiales!$B$8:$D$118,3,FALSE) -> 30467.49 | F12: 5 | G12: =+D12*E12*((F12+100)/100) -> 127.96346 | H12: =+D12*$E$9 -> 0.4
A13: PINT010 | B13: Enduido Interior x 20lts | C13: b | D13: 0.03 | E13: =VLOOKUP(B13,Materiales!$B$8:$D$118,3,FALSE) -> 18735.77 | F13: 10 | G13: =+D13*E13*((F13+100)/100) -> 618.28041 | H13: =+D13*$E$9 -> 3
A14: PINT001 | B14: Latex Loxon Interior Sherwin Williams Mate Bco x 20lts | C14: b | D14: 0.0125 | E14: =VLOOKUP(B14,Materiales!$B$8:$D$118,3,FALSE) -> 120622.23 | F14: 10 | G14: =+D14*E14*((F14+100)/100) -> 1658.5557 | H14: =+D14*$E$9 -> 1.25
A15: PINT015 | B15: Yeso Tuyango x 30kg | C15: b | D15: 0.0025 | E15: =VLOOKUP(B15,Materiales!$B$8:$D$118,3,FALSE) -> 9639 | F15: 5 | G15: =+D15*E15*((F15+100)/100) -> 25.302375 | H15: =+D15*$E$9 -> 0.25
A16: PINT013 | B16: Trapo | C16: u | D16: 0.03 | E16: =VLOOKUP(B16,Materiales!$B$8:$D$118,3,FALSE) -> 735.06 | F16: 5 | G16: =+D16*E16*((F16+100)/100) -> 23.15439 | H16: =+D16*$E$9 -> 3
A17: PINT012 | B17: Cinta de Papel 36 mm x 40m | C17: u | D17: 0.05 | E17: =VLOOKUP(B17,Materiales!$B$8:$D$118,3,FALSE) -> 3293.01 | F17: 10 | G17: =+D17*E17*((F17+100)/100) -> 181.11555 | H17: =+D17*$E$9 -> 5
A18: PINT011 | B18: Lija 180 al agua x 10u | C18: u | D18: 0.025 | E18: =VLOOKUP(B18,Materiales!$B$8:$D$118,3,FALSE) -> 5661.4 | F18: 5 | G18: =+D18*E18*((F18+100)/100) -> 148.61175 | H18: =+D18*$E$9 -> 2.5
B19: Rodillo de lana pelo corto antigota N°22 - El Galgo | C19: u | D19: 0.005 | E19: =VLOOKUP(B19,Materiales!$B$8:$D$118,3,FALSE) -> 6678.36 | F19: 5 | G19: =+D19*E19*((F19+100)/100) -> 35.06139 | H19: =+D19*$E$9 -> 0.5
B20: Pincel N° 20 - El Galgo | C20: u | D20: 0.005 | E20: =VLOOKUP(B20,Materiales!$B$8:$D$118,3,FALSE) -> 5282.24 | F20: 5 | G20: =+D20*E20*((F20+100)/100) -> 27.73176 | H20: =+D20*$E$9 -> 0.5
B21: Rollo de cartón corrugado 0,90 x 25 mts | C21: u | D21: 0.01 | E21: =VLOOKUP(B21,Materiales!$B$8:$D$118,3,FALSE) -> 7427.6 | F21: 5 | G21: =+D21*E21*((F21+100)/100) -> 77.9898 | H21: =+D21*$E$9 -> 1
F22: Total Materiales: | G22: =SUM(G12:G21) -> 2923.7665
F23: Unitario Materiales: | G23: =+G22 -> 2923.7665
A24: 2.- EQUIPOS
A25: Código | B25: Descripción | C25: Unidad | D25: Cantidad | E25: Tarifa $ | F25: % Deprec. | G25: Total $ | H25: Cant. x Obra
A26: *ANDAM05 | B26: ANDAMIO TUBULAR DE UNO A TRES CUERPOS | C26: gl | D26: 1 | E26: =VLOOKUP(B26,'Rend. Equipos'!$B$7:$E$222,4,FALSE) -> 1028123.1 | F26: =VLOOKUP(B26,'Rend. Equipos'!$B$6:$L$166,MATCH($F$25,'Rend. Equipos'!$B$6:$L$6,0),0) -> 0.00055555556 | G26: =+E26*D26*F26 -> 571.17949 | H26: =+D26*$E$9*F26/$F$9 -> 0.0031746032
B27: ESCALERA MADERA PINTOR 8 ESCALONES | C27: u | D27: 1 | E27: =VLOOKUP(B27,'Rend. Equipos'!$B$7:$E$222,4,FALSE) -> 72091.109 | F27: =VLOOKUP(B27,'Rend. Equipos'!$B$6:$L$166,MATCH($F$25,'Rend. Equipos'!$B$6:$L$6,0),0) -> 0.0027777778 | G27: =+E27*D27*F27 -> 200.25308 | H27: =+D27*$E$9*F27/$F$9 -> 0.015873016
A28: *EQUIPIN | B28: EQUIPO PARA PINTAR | C28: gl | D28: 2 | E28: =VLOOKUP(B28,'Rend. Equipos'!$B$7:$E$222,4,FALSE) -> 1241010.7 | F28: =VLOOKUP(B28,'Rend. Equipos'!$B$6:$L$166,MATCH($F$25,'Rend. Equipos'!$B$6:$L$6,0),0) -> 0.0013888889 | G28: =+E28*D28*F28 -> 3447.2519 | H28: =+D28*$E$9*F28/$F$9 -> 0.015873016
F29: Total Equipos: | G29: =SUM(G26:G28) -> 4218.6845
F30: Unitario Equipos: | G30: =+G29/F9 -> 241.06769
A31: 3.- MANO DE OBRA
A32: Código | B32: Descripción | C32: Unidad | D32: Cantidad | E32: Salario $ | G32: Total $
A33: MEDPINTO | B33: MEDIO OFICIAL PINTOR | C33: j | D33: 1 | E33: =VLOOKUP(B33,'Mano de Obra'!$B$8:$C$100,2,FALSE) -> 65493.072 | G33: =+E33*D33 -> 65493.072
A34: OFPINTOR | B34: OFICIAL ESPECIALIZADO PINTOR | C34: j | D34: 1 | E34: =VLOOKUP(B34,'Mano de Obra'!$B$8:$C$100,2,FALSE) -> 85927.097 | G34: =+E34*D34 -> 85927.097 | J34: h x m2 | K34: horas x dia
F35: Total Mano de Obra Menor: | G35: =SUM(G33:G34) -> 151420.17 | I35: Chandias | J35: 0.4 | K35: 7 | L35: =+K35/J35 -> 17.5
F36: Grado de dificultad | G36: 1
F37: Total Mano de Obra: | G37: =+G36*G35 -> 151420.17
F38: Unitario Mano de Obra: | G38: =+G37/F9 -> 8652.5811
F40: Costo Directo por Unidad: | G40: =+G38+G30+G23 -> 11817.415
E41: Gastos Generales: | F41: =+RESUMEN!$I$2 -> 0 | G41: =IF(F41=0,0,F41*G40) -> 0
E42: Beneficio: | F42: =+RESUMEN!$I$3 -> 0 | G42: =IF(F42=0,0,F42*G40) -> 0
F43: PRECIO UNITARIO: | G43: =SUM(G40:G42) -> 11817.415

Sheet P-53
F2: Fecha: | G2: Completar …
A3: ANALISIS DE PRECIO UNITARIO
F4: Partida N°: | G4: 53
A5: Obra: | B5: Completar …
A6: Cliente: | B6: Completar … | F6: Código de Obra: | G6: Completar …
A7: Partida: | B7: látex exterior para paredes hasta 3.00 m de altura
C8: Unidad: | E8: Cantidad: | F8: Rendimiento:
C9: m2 | E9: 100 | F9: 15.5 | G9: m2/dia
A10: 1.- MATERIALES
A11: Código | B11: Descripción | C11: Unidad | D11: Cantidad | E11: Costo $ | F11: % Desp. | G11: Total $ | H11: Cant. x Obra
A12: PINT014 | B12: Fijador al agua x 20 lts | C12: b | D12: 0.004 | E12: =VLOOKUP(B12,Materiales!$B$8:$D$118,3,FALSE) -> 30467.49 | F12: 5 | G12: =+D12*E12*((F12+100)/100) -> 127.96346 | H12: =+D12*$E$9 -> 0.4 | M12: =+SUM(G12:G13) -> 1580.7574 | N12: Pintura
A13: PINT001 | B13: Latex Loxon Exterior Sherwin Williams Mate Bco x 20lts | C13: b | D13: 0.0125 | E13: =VLOOKUP(B13,Materiales!$B$8:$D$118,3,FALSE) -> 105657.74 | F13: 10 | G13: =+D13*E13*((F13+100)/100) -> 1452.7939 | H13: =+D13*$E$9 -> 1.25 | M13: =+SUM(G14:G19) -> 244.16889 | N13: Consumibles
A14: PINT013 | B14: Trapo | C14: u | D14: 0.01 | E14: =VLOOKUP(B14,Materiales!$B$8:$D$118,3,FALSE) -> 735.06 | F14: 5 | G14: =+D14*E14*((F14+100)/100) -> 7.71813 | H14: =+D14*$E$9 -> 1 | M14: =+M13/M12 -> 0.15446323 | N14: % incidencia
A15: PINT012 | B15: Cinta de Papel 36 mm x 40m | C15: u | D15: 0.01 | E15: =VLOOKUP(B15,Materiales!$B$8:$D$118,3,FALSE) -> 3293.01 | F15: 10 | G15: =+D15*E15*((F15+100)/100) -> 36.22311 | H15: =+D15*$E$9 -> 1
A16: PINT011 | B16: Lija 180 al agua x 10u | C16: u | D16: 0.01 | E16: =VLOOKUP(B16,Materiales!$B$8:$D$118,3,FALSE) -> 5661.4 | F16: 5 | G16: =+D16*E16*((F16+100)/100) -> 59.4447 | H16: =+D16*$E$9 -> 1
B17: Rodillo de lana pelo largo N°22 - El Galgo | C17: u | D17: 0.005 | E17: =VLOOKUP(B17,Materiales!$B$8:$D$118,3,FALSE) -> 6678.36 | F17: 5 | G17: =+D17*E17*((F17+100)/100) -> 35.06139 | H17: =+D17*$E$9 -> 0.5
B18: Pincel N° 20 - El Galgo | C18: u | D18: 0.005 | E18: =VLOOKUP(B18,Materiales!$B$8:$D$118,3,FALSE) -> 5282.24 | F18: 5 | G18: =+D18*E18*((F18+100)/100) -> 27.73176 | H18: =+D18*$E$9 -> 0.5
B19: Rollo de cartón corrugado 0,90 x 25 mts | C19: u | D19: 0.01 | E19: =VLOOKUP(B19,Materiales!$B$8:$D$118,3,FALSE) -> 7427.6 | F19: 5 | G19: =+D19*E19*((F19+100)/100) -> 77.9898 | H19: =+D19*$E$9 -> 1
F20: Total Materiales: | G20: =SUM(G12:G19) -> 1824.9263
F21: Unitario Materiales: | G21: =+G20 -> 1824.9263
A22: 2.- EQUIPOS
A23: Código | B23: Descripción | C23: Unidad | D23: Cantidad | E23: Tarifa $ | F23: % Deprec. | G23: Total $ | H23: Cant. x Obra
A24: *ESCALE1 | B24: ESCALERA MADERA PINTOR 8 ESCALONES | C24: gl | D24: 1 | E24: =VLOOKUP(B24,'Rend. Equipos'!$B$7:$E$222,4,FALSE) -> 72091.109 | F24: =VLOOKUP(B24,'Rend. Equipos'!$B$6:$L$166,MATCH($F$23,'Rend. Equipos'!$B$6:$L$6,0),0) -> 0.0027777778 | G24: =+E24*D24*F24 -> 200.25308 | H24: =+D24*$E$9*F24/$F$9 -> 0.017921147
A25: *EQUIPIN | B25: EQUIPO PARA PINTAR | C25: u | D25: 1 | E25: =VLOOKUP(B25,'Rend. Equipos'!$B$7:$E$222,4,FALSE) -> 1241010.7 | F25: =VLOOKUP(B25,'Rend. Equipos'!$B$6:$L$166,MATCH($F$23,'Rend. Equipos'!$B$6:$L$6,0),0) -> 0.0013888889 | G25: =+E25*D25*F25 -> 1723.626 | H25: =+D25*$E$9*F25/$F$9 -> 0.0089605735
F26: Total Equipos: | G26: =SUM(G24:G25) -> 1923.879
F27: Unitario Equipos: | G27: =+G26/F9 -> 124.12123
A28: 3.- MANO DE OBRA
A29: Código | B29: Descripción | C29: Unidad | D29: Cantidad | E29: Salario $ | G29: Total $ | K29: h x m2 | L29: horas x dia
A30: OFPINTOR | B30: OFICIAL ESPECIALIZADO PINTOR | C30: j | D30: 1 | E30: =VLOOKUP(B30,'Mano de Obra'!$B$8:$C$100,2,FALSE) -> 85927.097 | G30: =+E30*D30 -> 85927.097 | J30: Chandias | K30: 0.45 | L30: 7 | M30: =+L30/K30 -> 15.555556
F31: Total Mano de Obra Menor: | G31: =SUM(G30:G30) -> 85927.097
F32: Grado de dificultad | G32: 1
F33: Total Mano de Obra: | G33: =+G32*G31 -> 85927.097
F34: Unitario Mano de Obra: | G34: =+G33/F9 -> 5543.6837
F36: Costo Directo por Unidad: | G36: =+G34+G27+G21 -> 7492.7312
E37: Gastos Generales: | F37: =+RESUMEN!$I$2 -> 0 | G37: =IF(F37=0,0,F37*G36) -> 0
E38: Beneficio: | F38: =+RESUMEN!$I$3 -> 0 | G38: =IF(F38=0,0,F38*G36) -> 0
F39: PRECIO UNITARIO: | G39: =SUM(G36:G38) -> 7492.7312

Sheet P-53 bis
F2: Fecha: | G2: Completar …
A3: ANALISIS DE PRECIO UNITARIO
F4: Partida N°: | G4: 53
A5: Obra: | B5: Completar …
A6: Cliente: | B6: Completar … | F6: Código de Obra: | G6: Completar …
A7: Partida: | B7: látex exterior para paredes a más 3.00 m de altura
C8: Unidad: | E8: Cantidad: | F8: Rendimiento:
C9: m2 | E9: 100 | F9: 15.5 | G9: m2/dia
A10: 1.- MATERIALES
A11: Código | B11: Descripción | C11: Unidad | D11: Cantidad | E11: Costo $ | F11: % Desp. | G11: Total $ | H11: Cant. x Obra
A12: PINT014 | B12: Fijador al agua x 20 lts | C12: b | D12: 0.004 | E12: =VLOOKUP(B12,Materiales!$B$8:$D$118,3,FALSE) -> 30467.49 | F12: 5 | G12: =+D12*E12*((F12+100)/100) -> 127.96346 | H12: =+D12*$E$9 -> 0.4 | M12: =+SUM(G12:G13) -> 1580.7574 | N12: Pintura
A13: PINT001 | B13: Latex Loxon Exterior Sherwin Williams Mate Bco x 20lts | C13: b | D13: 0.0125 | E13: =VLOOKUP(B13,Materiales!$B$8:$D$118,3,FALSE) -> 105657.74 | F13: 10 | G13: =+D13*E13*((F13+100)/100) -> 1452.7939 | H13: =+D13*$E$9 -> 1.25 | M13: =+SUM(G14:G19) -> 244.16889 | N13: Consumibles
A14: PINT013 | B14: Trapo | C14: u | D14: 0.01 | E14: =VLOOKUP(B14,Materiales!$B$8:$D$118,3,FALSE) -> 735.06 | F14: 5 | G14: =+D14*E14*((F14+100)/100) -> 7.71813 | H14: =+D14*$E$9 -> 1 | M14: =+M13/M12 -> 0.15446323 | N14: % incidencia
A15: PINT012 | B15: Cinta de Papel 36 mm x 40m | C15: u | D15: 0.01 | E15: =VLOOKUP(B15,Materiales!$B$8:$D$118,3,FALSE) -> 3293.01 | F15: 10 | G15: =+D15*E15*((F15+100)/100) -> 36.22311 | H15: =+D15*$E$9 -> 1
A16: PINT011 | B16: Lija 180 al agua x 10u | C16: u | D16: 0.01 | E16: =VLOOKUP(B16,Materiales!$B$8:$D$118,3,FALSE) -> 5661.4 | F16: 5 | G16: =+D16*E16*((F16+100)/100) -> 59.4447 | H16: =+D16*$E$9 -> 1
B17: Rodillo de lana pelo largo N°22 - El Galgo | C17: u | D17: 0.005 | E17: =VLOOKUP(B17,Materiales!$B$8:$D$118,3,FALSE) -> 6678.36 | F17: 5 | G17: =+D17*E17*((F17+100)/100) -> 35.06139 | H17: =+D17*$E$9 -> 0.5
B18: Pincel N° 20 - El Galgo | C18: u | D18: 0.005 | E18: =VLOOKUP(B18,Materiales!$B$8:$D$118,3,FALSE) -> 5282.24 | F18: 5 | G18: =+D18*E18*((F18+100)/100) -> 27.73176 | H18: =+D18*$E$9 -> 0.5
B19: Rollo de cartón corrugado 0,90 x 25 mts | C19: u | D19: 0.01 | E19: =VLOOKUP(B19,Materiales!$B$8:$D$118,3,FALSE) -> 7427.6 | F19: 5 | G19: =+D19*E19*((F19+100)/100) -> 77.9898 | H19: =+D19*$E$9 -> 1
F20: Total Materiales: | G20: =SUM(G12:G19) -> 1824.9263
F21: Unitario Materiales: | G21: =+G20 -> 1824.9263
A22: 2.- EQUIPOS
A23: Código | B23: Descripción | C23: Unidad | D23: Cantidad | E23: Tarifa $ | F23: % Deprec. | G23: Total $
A24: SILLETA | B24: Kit Complementario Silleta Descensor Conector Soga X 50 Mts | C24: u | D24: 0.75 | E24: =VLOOKUP(B24,'Rend. Equipos'!$B$7:$E$222,4,FALSE) -> 683705.75 | F24: =VLOOKUP(B24,'Rend. Equipos'!$B$6:$L$166,MATCH($F$23,'Rend. Equipos'!$B$6:$L$6,0),0) -> 0.0027777778 | G24: =+E24*D24*F24 -> 1424.387
A25: *ANDAM05 | B25: ANDAMIO TUBULAR DE UNO A TRES CUERPOS | C25: gl | D25: 0.5 | E25: =VLOOKUP(B25,'Rend. Equipos'!$B$7:$E$222,4,FALSE) -> 1028123.1 | F25: =VLOOKUP(B25,'Rend. Equipos'!$B$6:$L$166,MATCH($F$23,'Rend. Equipos'!$B$6:$L$6,0),0) -> 0.00055555556 | G25: =+E25*D25*F25 -> 285.58975
A26: *ESCALE1 | B26: ESCALERA MADERA PINTOR 8 ESCALONES | C26: gl | D26: 1 | E26: =VLOOKUP(B26,'Rend. Equipos'!$B$7:$E$222,4,FALSE) -> 72091.109 | F26: =VLOOKUP(B26,'Rend. Equipos'!$B$6:$L$166,MATCH($F$23,'Rend. Equipos'!$B$6:$L$6,0),0) -> 0.0027777778 | G26: =+E26*D26*F26 -> 200.25308
A27: *EQUIPIN | B27: EQUIPO PARA PINTAR | C27: u | D27: 1 | E27: =VLOOKUP(B27,'Rend. Equipos'!$B$7:$E$222,4,FALSE) -> 1241010.7 | F27: =VLOOKUP(B27,'Rend. Equipos'!$B$6:$L$166,MATCH($F$23,'Rend. Equipos'!$B$6:$L$6,0),0) -> 0.0013888889 | G27: =+E27*D27*F27 -> 1723.626
F28: Total Equipos: | G28: =SUM(G24:G27) -> 3633.8558
F29: Unitario Equipos: | G29: =+G28/F9 -> 234.44231
A30: 3.- MANO DE OBRA
A31: Código | B31: Descripción | C31: Unidad | D31: Cantidad | E31: Salario $ | G31: Total $ | K31: h x m2 | L31: horas x dia
A32: MEDPINTO | B32: MEDIO OFICIAL PINTOR | C32: j | D32: 1 | E32: =VLOOKUP(B32,'Mano de Obra'!$B$8:$C$100,2,FALSE) -> 65493.072 | G32: =+E32*D32 -> 65493.072 | J32: Chandias | K32: 0.45 | L32: 7 | M32: =+L32/K32 -> 15.555556
A33: OFPINTOR | B33: OFICIAL ESPECIALIZADO PINTOR | C33: j | D33: 1.5 | E33: =VLOOKUP(B33,'Mano de Obra'!$B$8:$C$100,2,FALSE) -> 85927.097 | G33: =+E33*D33 -> 128890.65 | H33: horas extras x silleta
A34: MOFAL | B34: AYUDANTE | C34: j | D34: 0.5 | E34: =VLOOKUP(B34,'Mano de Obra'!$B$8:$C$100,2,FALSE) -> 60860.581 | G34: =+E34*D34 -> 30430.29
F35: Total Mano de Obra Menor: | G35: =SUM(G32:G34) -> 224814.01
F36: Grado de dificultad | G36: 1
F37: Total Mano de Obra: | G37: =+G36*G35 -> 224814.01
F38: Unitario Mano de Obra: | G38: =+G37/F9 -> 14504.13
F40: Costo Directo por Unidad: | G40: =+G38+G29+G21 -> 16563.498
E41: Gastos Generales: | F41: =+RESUMEN!$I$2 -> 0 | G41: =IF(F41=0,0,F41*G40) -> 0
E42: Beneficio: | F42: =+RESUMEN!$I$3 -> 0 | G42: =IF(F42=0,0,F42*G40) -> 0
F43: PRECIO UNITARIO: | G43: =SUM(G40:G42) -> 16563.498

Sheet P-54
F2: Fecha: | G2: Completar …
A3: ANALISIS DE PRECIO UNITARIO
F4: Partida N°: | G4: 54 | L4: =6*7 -> 42 | M4: *
A5: Obra: | B5: Completar …
A6: Cliente: | B6: Completar … | F6: Código de Obra: | G6: Completar …
A7: Partida: | B7: Esmalte sintético sobre carpintería metálica , herrería (cuando es vacio x lleno contemplar MAT al 60%)
C8: Unidad: | E8: Cantidad: | F8: Rendimiento: | Q8: 2
C9: m2 | E9: 1 | F9: 8 | G9: m2/dia | H9: =+E9/F9 -> 0.125 | P9: mlperim | Q9: Ambas caras
A10: 1.- MATERIALES | L10: Puerta tipo | M10: perim | N10: 0.9 | O10: 2.05 | P10: =+N10+O10+O10 -> 5 | Q10: =+P10*Q8 -> 10 | R10: ml de cinta x 5m2
A11: Código | B11: Descripción | C11: Unidad | D11: Cantidad | E11: Costo $ | F11: % Desp. | G11: Total $ | H11: Cant. x Obra | M11: sup marc | N11: 0.25 | P11: =+P10 -> 5 | Q11: =+N11*P11 -> 1.25
A12: ESMALTES | B12: Esmalte sintetico satinado Satinol Blanco x 4lts | C12: b | D12: 0.0625 | E12: =VLOOKUP(B12,Materiales!$B$8:$D$118,3,FALSE) -> 28011.57 | F12: 10 | G12: =+D12*E12*((F12+100)/100) -> 1925.7954 | H12: =+D12*$E$9 -> 0.0625 | M12: hojas | N12: 0.9 | O12: 2 | P12: =+N12*O12 -> 1.8 | Q12: =+P12*Q8 -> 3.6 | R12: =+Q11+Q12 -> 4.85 | S12: x puerta
A13: PINT016 | B13: Aguarras Hydrarras Hydra x 18lts | C13: b | D13: 0.005 | E13: =VLOOKUP(B13,Materiales!$B$8:$D$118,3,FALSE) -> 26907.33 | F13: 10 | G13: =+D13*E13*((F13+100)/100) -> 147.99032 | H13: =+D13*$E$9 -> 0.005 | R13: 100 | S13: m2
A14: PINT013 | B14: Trapo | C14: u | D14: 0.01 | E14: =VLOOKUP(B14,Materiales!$B$8:$D$118,3,FALSE) -> 735.06 | F14: 5 | G14: =+D14*E14*((F14+100)/100) -> 7.71813 | H14: =+D14*$E$9 -> 0.01 | J14: 2 | K14: imprimacion | R14: =+R13/R12 -> 20.618557 | S14: puertas
A15: PINT012 | B15: Cinta de Papel 36 mm x 40m | C15: u | D15: 0.05 | E15: =VLOOKUP(B15,Materiales!$B$8:$D$118,3,FALSE) -> 3293.01 | F15: 10 | G15: =+D15*E15*((F15+100)/100) -> 181.11555 | H15: =+D15*$E$9 -> 0.05 | J15: 0.5 | K15: x dia
A16: PINT011 | B16: Lija 180 al agua x 10u | C16: u | D16: 0.02 | E16: =VLOOKUP(B16,Materiales!$B$8:$D$118,3,FALSE) -> 5661.4 | F16: 5 | G16: =+D16*E16*((F16+100)/100) -> 118.8894 | H16: =+D16*$E$9 -> 0.02 | J16: 14 | K16: d
B17: Rodillo de lana pelo largo N°22 - El Galgo | C17: u | D17: 0.01 | E17: =VLOOKUP(B17,Materiales!$B$8:$D$118,3,FALSE) -> 6678.36 | F17: 5 | G17: =+D17*E17*((F17+100)/100) -> 70.12278 | H17: =+D17*$E$9 -> 0.01
B18: Pincel N° 20 - El Galgo | C18: u | D18: 0.01 | E18: =VLOOKUP(B18,Materiales!$B$8:$D$118,3,FALSE) -> 5282.24 | F18: 5 | G18: =+D18*E18*((F18+100)/100) -> 55.46352 | H18: =+D18*$E$9 -> 0.01
B19: Rollo de cartón corrugado 0,90 x 25 mts | C19: u | D19: 0.01 | E19: =VLOOKUP(B19,Materiales!$B$8:$D$118,3,FALSE) -> 7427.6 | F19: 5 | G19: =+D19*E19*((F19+100)/100) -> 77.9898 | H19: =+D19*$E$9 -> 0.01
F20: Total Materiales: | G20: =SUM(G12:G19) -> 2585.0849
F21: Unitario Materiales: | G21: =+G20 -> 2585.0849 | M21: 12 a 15 litros x mano
A22: 2.- EQUIPOS | M22: litros | N22: m2 x 3 manos
A23: Código | B23: Descripción | C23: Unidad | D23: Cantidad | E23: Tarifa $ | F23: % Deprec. | G23: Total $ | M23: 1 | N23: =12/3 -> 4
A24: *ESCALE1 | B24: ESCALERA MADERA PINTOR 8 ESCALONES | C24: gl | D24: 1 | E24: =VLOOKUP(B24,'Rend. Equipos'!$B$7:$E$222,4,FALSE) -> 72091.109 | F24: =VLOOKUP(B24,'Rend. Equipos'!$B$6:$L$166,MATCH($F$23,'Rend. Equipos'!$B$6:$L$6,0),0) -> 0.0027777778 | G24: =+E24*D24*F24 -> 200.25308 | M24: 4 | N24: =M24*N23/M23 -> 16 | O24: =1/N24 -> 0.0625
A25: *EQUIPIN | B25: EQUIPO PARA PINTAR | C25: u | D25: 1 | E25: =VLOOKUP(B25,'Rend. Equipos'!$B$7:$E$222,4,FALSE) -> 1241010.7 | F25: =VLOOKUP(B25,'Rend. Equipos'!$B$6:$L$166,MATCH($F$23,'Rend. Equipos'!$B$6:$L$6,0),0) -> 0.0013888889 | G25: =+E25*D25*F25 -> 1723.626
F26: Total Equipos: | G26: =SUM(G24:G25) -> 1923.879
F27: Unitario Equipos: | G27: =+G26/F9 -> 240.48488
A28: 3.- MANO DE OBRA | J28: h/m2 | K28: h/d | L28: m/d
A29: Código | B29: Descripción | C29: Unidad | D29: Cantidad | E29: Salario $ | G29: Total $ | I29: M.O Chandias | J29: 0.9 | K29: 7 | L29: =+K29/J29 -> 7.7777778
A30: OFPINTOR | B30: OFICIAL ESPECIALIZADO PINTOR | C30: j | D30: 1 | E30: =VLOOKUP(B30,'Mano de Obra'!$B$8:$C$100,2,FALSE) -> 85927.097 | G30: =+E30*D30 -> 85927.097
F31: Total Mano de Obra Menor: | G31: =SUM(G30:G30) -> 85927.097
F32: Grado de dificultad | G32: 1
F33: Total Mano de Obra: | G33: =+G32*G31 -> 85927.097
F34: Unitario Mano de Obra: | G34: =+G33/F9 -> 10740.887
F36: Costo Directo por Unidad: | G36: =+G34+G27+G21 -> 13566.457
E37: Gastos Generales: | F37: =+RESUMEN!$I$2 -> 0 | G37: =IF(F37=0,0,F37*G36) -> 0
E38: Beneficio: | F38: =+RESUMEN!$I$3 -> 0 | G38: =IF(F38=0,0,F38*G36) -> 0
F39: PRECIO UNITARIO: | G39: =SUM(G36:G38) -> 13566.457

Sheet P-55
F2: Fecha: | G2: Completar..
A3: ANALISIS DE PRECIO UNITARIO
F4: Partida N°: | G4: 55 | K4: MAIZ
A5: Obra: | B5: Completar .. | J5: m2 | K5: 770
A6: Cliente: | B6: Completar .. | F6: Código de Obra: | G6: Completar .. | J6: base | K6: 5
A7: Partida: | B7: Revestimiento plastico texturado tipo Quimtex fino | J7: kg base | K7: =+K6*20 -> 100
C8: Unidad: | E8: Cantidad: | F8: Rendimiento: | J8: kg/m2 | K8: 0.2 | M8: 1 | N8: 5
C9: m2 | E9: 1000 | F9: 20 | G9: m2/dia | J9: Balde/m2 | K9: =+N11 -> 0.011111111 | M9: 18 | N9: =+M9*N8/M8 -> 90
A10: 1.- MATERIALES | J10: tarquini | K10: 55
A11: Código | B11: Descripción | C11: Unidad | D11: Cantidad | E11: Costo $ | F11: % Desp. | G11: Total $ | H11: Cant. x Obra | J11: kg tarquini | K11: =+K10*27 -> 1485 | N11: =1/N9 -> 0.011111111
B12: Quimtex Romano Fino x 27 kg | C12: u | D12: 0.0741 | E12: =VLOOKUP(B12,Materiales!$B$8:$D$118,3,FALSE) -> 57033.884 | F12: 10 | G12: =+D12*E12*((F12+100)/100) -> 4648.8319 | H12: =+D12*$E$9 -> 74.1 | J12: kg/m2 | K12: 2
B13: Quimtex base cuarzo 18 lts | C13: u | D13: 0.0111 | E13: =VLOOKUP(B13,Materiales!$B$8:$D$118,3,FALSE) -> 93388.43 | F13: 10 | G13: =+D13*E13*((F13+100)/100) -> 1140.2727 | H13: =+D13*$E$9 -> 11.1 | J13: Balde/m2 | K13: =+K12/27 -> 0.074074074
B14: Llana Plástica 12 x 25 cm | C14: u | D14: 0.01 | E14: =VLOOKUP(B14,Materiales!$B$8:$D$118,3,FALSE) -> 12575.207 | F14: 10 | G14: =+D14*E14*((F14+100)/100) -> 138.32727 | H14: =+D14*$E$9 -> 10
B15: Rodillo de lana pelo largo N°22 - El Galgo | C15: u | D15: 0.005 | E15: =VLOOKUP(B15,Materiales!$B$8:$D$118,3,FALSE) -> 6678.36 | F15: 5 | G15: =+D15*E15*((F15+100)/100) -> 35.06139 | H15: =+D15*$E$9 -> 5
B16: Trapo | C16: u | D16: 0.005 | E16: =VLOOKUP(B16,Materiales!$B$8:$D$118,3,FALSE) -> 735.06 | F16: 5 | G16: =+D16*E16*((F16+100)/100) -> 3.859065 | H16: =+D16*$E$9 -> 5
B17: Cinta de Papel 36 mm x 40m | C17: u | D17: 0.01 | E17: =VLOOKUP(B17,Materiales!$B$8:$D$118,3,FALSE) -> 3293.01 | F17: 5 | G17: =+D17*E17*((F17+100)/100) -> 34.576605 | H17: =+D17*$E$9 -> 10
F18: Total Materiales: | G18: =SUM(G12:G17) -> 6000.929
F19: Unitario Materiales: | G19: =+G18 -> 6000.929
A20: 2.- EQUIPOS
A21: Código | B21: Descripción | C21: Unidad | D21: Cantidad | E21: Tarifa $ | F21: % Deprec. | G21: Total $
A22: SILLETA | B22: Kit Complementario Silleta Descensor Conector Soga X 50 Mts | C22: u | D22: 0.75 | E22: =VLOOKUP(B22,'Rend. Equipos'!$B$7:$E$222,4,FALSE) -> 683705.75 | F22: =VLOOKUP(B22,'Rend. Equipos'!$B$6:$L$166,MATCH($F$21,'Rend. Equipos'!$B$6:$L$6,0),0) -> 0.0027777778 | G22: =+E22*D22*F22 -> 1424.387
A23: *ANDAM05 | B23: ANDAMIO TUBULAR DE UNO A TRES CUERPOS | C23: gl | D23: 0.5 | E23: =VLOOKUP(B23,'Rend. Equipos'!$B$7:$E$222,4,FALSE) -> 1028123.1 | F23: =VLOOKUP(B23,'Rend. Equipos'!$B$6:$L$166,MATCH($F$21,'Rend. Equipos'!$B$6:$L$6,0),0) -> 0.00055555556 | G23: =+E23*D23*F23 -> 285.58975
A24: *ESCALE1 | B24: ESCALERA MADERA PINTOR 8 ESCALONES | C24: u | D24: 1 | E24: =VLOOKUP(B24,'Rend. Equipos'!$B$7:$E$222,4,FALSE) -> 72091.109 | F24: =VLOOKUP(B24,'Rend. Equipos'!$B$6:$L$166,MATCH($F$21,'Rend. Equipos'!$B$6:$L$6,0),0) -> 0.0027777778 | G24: =+E24*D24*F24 -> 200.25308
A25: *EQUIPIN | B25: EQUIPO PARA PINTAR | C25: gl | D25: 1 | E25: =VLOOKUP(B25,'Rend. Equipos'!$B$7:$E$222,4,FALSE) -> 1241010.7 | F25: =VLOOKUP(B25,'Rend. Equipos'!$B$6:$L$166,MATCH($F$21,'Rend. Equipos'!$B$6:$L$6,0),0) -> 0.0013888889 | G25: =+E25*D25*F25 -> 1723.626
F26: Total Equipos: | G26: =SUM(G22:G25) -> 3633.8558
F27: Unitario Equipos: | G27: =+G26/F9 -> 181.69279
A28: 3.- MANO DE OBRA
A29: Código | B29: Descripción | C29: Unidad | D29: Cantidad | E29: Salario $ | G29: Total $
A30: MEDPINTO | B30: MEDIO OFICIAL PINTOR | C30: j | D30: 1 | E30: =VLOOKUP(B30,'Mano de Obra'!$B$8:$C$100,2,FALSE) -> 65493.072 | G30: =+E30*D30 -> 65493.072
A31: OFPINTOR | B31: OFICIAL ESPECIALIZADO PINTOR | C31: j | D31: 1.5 | E31: =VLOOKUP(B31,'Mano de Obra'!$B$8:$C$100,2,FALSE) -> 85927.097 | G31: =+E31*D31 -> 128890.65 | H31: horas extras x silleta
A32: MOFAL | B32: AYUDANTE | C32: j | D32: 0.5 | E32: =VLOOKUP(B32,'Mano de Obra'!$B$8:$C$100,2,FALSE) -> 60860.581 | G32: =+E32*D32 -> 30430.29
F33: Total Mano de Obra Menor: | G33: =SUM(G30:G32) -> 224814.01
F34: Grado de dificultad | G34: 1
F35: Total Mano de Obra: | G35: =+G34*G33 -> 224814.01
F36: Unitario Mano de Obra: | G36: =+G35/F9 -> 11240.7
F38: Costo Directo por Unidad: | G38: =+G36+G27+G19 -> 17423.322
E39: Gastos Generales: | F39: =+RESUMEN!$I$2 -> 0 | G39: =IF(F39=0,0,F39*G38) -> 0
E40: Beneficio: | F40: =+RESUMEN!$I$3 -> 0 | G40: =IF(F40=0,0,F40*G38) -> 0
F41: PRECIO UNITARIO: | G41: =SUM(G38:G40) -> 17423.322

Sheet P-56
F2: Fecha: | G2: Completar …
A3: ANALISIS DE PRECIO UNITARIO
F4: Partida N°: | G4: 56
A5: Obra: | B5: Completar …
A6: Cliente: | B6: Completar … | F6: Código de Obra: | G6: Completar …
A7: Partida: | B7: Colocación porcelanato en pisos (no incluye baños)
C8: Unidad: | E8: Cantidad: | F8: Rendimiento:
C9: m2 | E9: 100 | F9: 13 | G9: m2/dia
A10: 1.- MATERIALES
A11: Código | B11: Descripción | C11: Unidad | D11: Cantidad | E11: Costo $ | F11: % Desp. | G11: Total $ | H11: Cant. x Obra | J11: Depto tipo
A12: *AGREG11 | B12: Adhesivo Klaukol Porcellanato Fluido x 30Kg | C12: bol | D12: 0.2 | E12: =VLOOKUP(B12,Materiales!$B$8:$D$118,3,FALSE) -> 18802.512 | F12: 20 | G12: =+D12*E12*((F12+100)/100) -> 4512.6029 | H12: =+D12*$E$9 -> 20 | J12: =5*3 -> 15 | K12: Estar
A13: *AGREG11 | B13: Pastina Klaukol x 1kg - Alta performance | C13: bol | D13: 0.2 | E13: =VLOOKUP(B13,Materiales!$B$8:$D$118,3,FALSE) -> 3214.35 | F13: 5 | G13: =+D13*E13*((F13+100)/100) -> 675.0135 | H13: =+D13*$E$9 -> 20 | J13: 9 | K13: Habitacion
B14: Disco Diamantado Aliafor Turbo Fino TRF | C14: u | D14: =1/250 -> 0.004 | E14: =VLOOKUP(B14,Materiales!$B$8:$D$212,3,FALSE) -> 20237 | F14: 5 | G14: =+D14*E14*((F14+100)/100) -> 84.9954 | H14: =+D14*$E$9 -> 0.4 | J14: 9 | K14: Habitacion
B15: Arco y cuña niveladores porcelanatos x 150 un | C15: bol | D15: =6/150 -> 0.04 | E15: =VLOOKUP(B15,Materiales!$B$8:$D$212,3,FALSE) -> 44669.421 | F15: 5 | G15: =+D15*E15*((F15+100)/100) -> 1876.1157 | H15: =+D15*$E$9 -> 4 | J15: 9 | K15: Habitacion
A16: PINT013 | B16: Trapo | C16: u | D16: 0.01 | E16: =VLOOKUP(B16,Materiales!$B$8:$D$212,3,FALSE) -> 735.06 | F16: 3 | G16: =+D16*E16*((F16+100)/100) -> 7.571118 | H16: =+D16*$E$9 -> 1 | J16: 5 | K16: Paso y cocina
F17: Total Materiales: | G17: =SUM(G12:G16) -> 7156.2986 | J17: =+SUM(J12:J16) -> 47 | K17: m2
F18: Unitario Materiales: | G18: =+G17 -> 7156.2986 | J18: 3 | K18: dias
A19: 2.- EQUIPOS | J19: =+J17/J18 -> 15.666667 | K19: m2 x dia
A20: Código | B20: Descripción | C20: Unidad | D20: Cantidad | E20: Tarifa $ | F20: % Deprec. | G20: Total $
A21: EQCERAMI | B21: EQUIPO PARA COLOCACION DE CERAMICA | C21: gl | D21: 1 | E21: =VLOOKUP(B21,'Rend. Equipos'!$B$7:$E$222,4,FALSE) -> 1424056.6 | F21: =VLOOKUP(B21,'Rend. Equipos'!$B$6:$L$166,MATCH($F$20,'Rend. Equipos'!$B$6:$L$6,0),0) -> 0.0018518519 | G21: =+E21*D21*F21 -> 2637.1418
B22: CORTADORA CERAMICA PROFESIONAL 1200MM (PORCELANATO HASTA 16MM) | C22: u | D22: 1 | E22: =VLOOKUP(B22,'Rend. Equipos'!$B$7:$E$222,4,FALSE) -> 537162.92 | F22: =VLOOKUP(B22,'Rend. Equipos'!$B$6:$L$166,MATCH($F$20,'Rend. Equipos'!$B$6:$L$6,0),0) -> 0.00055555556 | G22: =+E22*D22*F22 -> 298.42384
F23: Total Equipos: | G23: =SUM(G21:G22) -> 2935.5657
F24: Unitario Equipos: | G24: =+G23/F9 -> 225.81275
A25: 3.- MANO DE OBRA
A26: Código | B26: Descripción | C26: Unidad | D26: Cantidad | E26: Salario $ | G26: Total $
A27: MOFAL | B27: MEDIO OFICIAL ALBAÑIL | C27: j | D27: 1 | E27: =VLOOKUP(B27,'Mano de Obra'!$B$8:$C$100,2,FALSE) -> 65493.072 | G27: =+E27*D27 -> 65493.072
A28: OFCOLOCA | B28: OFICIAL COLOCADOR | C28: j | D28: 1 | E28: =VLOOKUP(B28,'Mano de Obra'!$B$8:$C$100,2,FALSE) -> 85927.097 | G28: =+E28*D28 -> 85927.097
F29: Total Mano de Obra Menor: | G29: =SUM(G27:G28) -> 151420.17
F30: Grado de dificultad | G30: 1
F31: Total Mano de Obra: | G31: =+G30*G29 -> 151420.17
F32: Unitario Mano de Obra: | G32: =+G31/F9 -> 11647.705
F34: Costo Directo por Unidad: | G34: =+G32+G24+G18 -> 19029.817
E35: Gastos Generales: | F35: =+RESUMEN!$I$2 -> 0 | G35: =IF(F35=0,0,F35*G34) -> 0
E36: Beneficio: | F36: =+RESUMEN!$I$3 -> 0 | G36: =IF(F36=0,0,F36*G34) -> 0
F37: PRECIO UNITARIO: | G37: =SUM(G34:G36) -> 19029.817

Sheet P-57
F2: Fecha: | G2: Completar …
A3: ANALISIS DE PRECIO UNITARIO
F4: Partida N°: | G4: 57
A5: Obra: | B5: Completar …
A6: Cliente: | B6: Completar … | F6: Código de Obra: | G6: Completar …
A7: Partida: | B7: Revestimiento porcelanato en paredes y piso baños
C8: Unidad: | E8: Cantidad: | F8: Rendimiento: | L8: Largo | M8: Ancho
C9: m2 | E9: 100 | F9: 10 | G9: m2/dia | K9: Paredes | L9: 2.2 | M9: 1.5 | N9: =+L9*2+M9*2 -> 7.4 | O9: 2.4 | P9: =+N9*O9 -> 17.76 | Q9: Paredes
A10: 1.- MATERIALES | P10: =+L9*M9*1.1 -> 3.63 | Q10: Piso
A11: Código | B11: Descripción | C11: Unidad | D11: Cantidad | E11: Costo $ | F11: % Desp. | G11: Total $ | H11: Cant. x Obra | P11: =+P9+P10 -> 21.39 | Q11: Total
A12: *AGREG11 | B12: Adhesivo Klaukol Porcellanato Fluido x 30Kg | C12: bol | D12: 0.2 | E12: =VLOOKUP(B12,Materiales!$B$8:$D$212,3,FALSE) -> 18802.512 | F12: 20 | G12: =+D12*E12*((F12+100)/100) -> 4512.6029 | H12: =+D12*$E$9 -> 20 | P12: 3 | Q12: dias
A13: *AGREG11 | B13: Pastina Klaukol x 1kg - Alta performance | C13: bol | D13: 0.2 | E13: =VLOOKUP(B13,Materiales!$B$8:$D$212,3,FALSE) -> 3214.35 | F13: 5 | G13: =+D13*E13*((F13+100)/100) -> 675.0135 | H13: =+D13*$E$9 -> 20 | P13: =+P11/P12 -> 7.13 | Q13: m2 x dia
B14: Disco Diamantado Aliafor Turbo Fino TRF | C14: u | D14: =1/250 -> 0.004 | E14: =VLOOKUP(B14,Materiales!$B$8:$D$212,3,FALSE) -> 20237 | F14: 5 | G14: =+D14*E14*((F14+100)/100) -> 84.9954 | H14: =+D14*$E$9 -> 0.4
B15: Arco y cuña niveladores porcelanatos x 150 un | C15: bol | D15: =6/150 -> 0.04 | E15: =VLOOKUP(B15,Materiales!$B$8:$D$212,3,FALSE) -> 44669.421 | F15: 5 | G15: =+D15*E15*((F15+100)/100) -> 1876.1157 | H15: =+D15*$E$9 -> 4
A16: PINT013 | B16: Trapo | C16: u | D16: 0.01 | E16: =VLOOKUP(B16,Materiales!$B$8:$D$212,3,FALSE) -> 735.06 | F16: 3 | G16: =+D16*E16*((F16+100)/100) -> 7.571118 | H16: =+D16*$E$9 -> 1
F17: Total Materiales: | G17: =SUM(G12:G16) -> 7156.2986
F18: Unitario Materiales: | G18: =+G17 -> 7156.2986
A19: 2.- EQUIPOS
A20: Código | B20: Descripción | C20: Unidad | D20: Cantidad | E20: Tarifa $ | F20: % Deprec. | G20: Total $
A21: EQCERAMI | B21: EQUIPO PARA COLOCACION DE CERAMICA | C21: gl | D21: 1 | E21: =VLOOKUP(B21,'Rend. Equipos'!$B$7:$E$222,4,FALSE) -> 1424056.6 | F21: =VLOOKUP(B21,'Rend. Equipos'!$B$6:$L$166,MATCH($F$20,'Rend. Equipos'!$B$6:$L$6,0),0) -> 0.0018518519 | G21: =+E21*D21*F21 -> 2637.1418
B22: CORTADORA CERAMICA PROFESIONAL 1200MM (PORCELANATO HASTA 16MM) | C22: u | D22: 1 | E22: =VLOOKUP(B22,'Rend. Equipos'!$B$7:$E$222,4,FALSE) -> 537162.92 | F22: =VLOOKUP(B22,'Rend. Equipos'!$B$6:$L$166,MATCH($F$20,'Rend. Equipos'!$B$6:$L$6,0),0) -> 0.00055555556 | G22: =+E22*D22*F22 -> 298.42384
F23: Total Equipos: | G23: =SUM(G21:G22) -> 2935.5657
F24: Unitario Equipos: | G24: =+G23/F9 -> 293.55657
A25: 3.- MANO DE OBRA
A26: Código | B26: Descripción | C26: Unidad | D26: Cantidad | E26: Salario $ | G26: Total $
A27: MOFAL | B27: MEDIO OFICIAL ALBAÑIL | C27: j | D27: 1 | E27: =VLOOKUP(B27,'Mano de Obra'!$B$8:$C$100,2,FALSE) -> 65493.072 | G27: =+E27*D27 -> 65493.072
A28: OFCOLOCA | B28: OFICIAL COLOCADOR | C28: j | D28: 1 | E28: =VLOOKUP(B28,'Mano de Obra'!$B$8:$C$100,2,FALSE) -> 85927.097 | G28: =+E28*D28 -> 85927.097
F29: Total Mano de Obra Menor: | G29: =SUM(G27:G28) -> 151420.17
F30: Grado de dificultad | G30: 1
F31: Total Mano de Obra: | G31: =+G30*G29 -> 151420.17
F32: Unitario Mano de Obra: | G32: =+G31/F9 -> 15142.017
F34: Costo Directo por Unidad: | G34: =+G32+G24+G18 -> 22591.872
E35: Gastos Generales: | F35: =+RESUMEN!$I$2 -> 0 | G35: =IF(F35=0,0,F35*G34) -> 0
E36: Beneficio: | F36: =+RESUMEN!$I$3 -> 0 | G36: =IF(F36=0,0,F36*G34) -> 0
F37: PRECIO UNITARIO: | G37: =SUM(G34:G36) -> 22591.872

Sheet P-58
F2: Fecha: | G2: Completar.. | J2: Depto tipo | K2: A | L2: B | M2: ml
A3: ANALISIS DE PRECIO UNITARIO | J3: Estar | K3: 5 | L3: 3 | M3: =+K3*2+L3*2 -> 16
F4: Partida N°: | G4: 58 | J4: Habitacion | K4: 3 | L4: 3 | M4: =+K4*2+L4*2 -> 12
A5: Obra: | B5: Completar | J5: Habitacion | K5: 3 | L5: 3 | M5: =+K5*2+L5*2 -> 12
A6: Cliente: | B6: Completar | F6: Código de Obra: | G6: Completar | J6: Habitacion | K6: 3 | L6: 3 | M6: =+K6*2+L6*2 -> 12
A7: Partida: | B7: Colocacion de zocalo porcelanato | J7: Paso | K7: 3 | L7: 1 | M7: =+K7*2+L7 -> 7
C8: Unidad: | E8: Cantidad: | F8: Rendimiento: | J8: Cocina | K8: 4 | L8: 1 | M8: =+K8+L8*2 -> 6
C9: ml | E9: 100 | F9: 30 | G9: ml/dia | M9: =+SUM(M3:M8) -> 65 | N9: ml
A10: 1.- MATERIALES | M10: 2 | N10: d
A11: Código | B11: Descripción | C11: Unidad | D11: Cantidad | E11: Costo $ | F11: % Desp. | G11: Total $ | H11: Cant. x Obra | K11: m2 | L11: ml | M11: =+M9/M10 -> 32.5 | N11: m2 x dia
A12: *AGREG11 | B12: Adhesivo Klaukol Porcellanato Fluido x 30Kg | C12: bol | D12: 0.04 | E12: =VLOOKUP(B12,Materiales!$B$8:$D$212,3,FALSE) -> 18802.512 | F12: 20 | G12: =+D12*E12*((F12+100)/100) -> 902.52058 | H12: =+D12*$E$9 -> 4 | K12: 0.2 | L12: 1 | N12: bolsa | O12: 0.2 | P12: 1
A13: *AGREG11 | B13: Pastina Klaukol x 1kg - Alta performance | C13: bol | D13: =0.04 -> 0.04 | E13: =VLOOKUP(B13,Materiales!$B$8:$D$212,3,FALSE) -> 3214.35 | F13: 5 | G13: =+D13*E13*((F13+100)/100) -> 135.0027 | H13: =+D13*$E$9 -> 4 | K13: 1 | L13: =+K13*L12/K12 -> 5 | O13: =+P13*O12/P12 -> 0.04 | P13: 0.2
B14: Disco Diamantado Aliafor Turbo Fino TRF | C14: u | D14: =1/1000 -> 0.001 | E14: =VLOOKUP(B14,Materiales!$B$8:$D$212,3,FALSE) -> 20237 | F14: 5 | G14: =+D14*E14*((F14+100)/100) -> 21.24885 | H14: =+D14*$E$9 -> 0.1
B15: Arco y cuña niveladores porcelanatos x 150 un | C15: bol | D15: 0 | E15: =VLOOKUP(B15,Materiales!$B$8:$D$212,3,FALSE) -> 44669.421 | F15: 0 | G15: =+D15*E15*((F15+100)/100) -> 0 | H15: =+D15*$E$9 -> 0 | K15: Pegamento
A16: PINT013 | B16: Trapo | C16: u | D16: 0.01 | E16: =VLOOKUP(B16,Materiales!$B$8:$D$212,3,FALSE) -> 735.06 | F16: 3 | G16: =+D16*E16*((F16+100)/100) -> 7.571118 | H16: =+D16*$E$9 -> 1 | J16: m2 | K16: 1 | L16: 5
F17: Total Materiales: | G17: =SUM(G12:G16) -> 1066.3432 | J17: ml | K17: =+L12 -> 1 | L17: =+K17*L16/K16 -> 5
F18: Unitario Materiales: | G18: =+G17 -> 1066.3432
A19: 2.- EQUIPOS
A20: Código | B20: Descripción | C20: Unidad | D20: Cantidad | E20: Tarifa $ | F20: % Deprec. | G20: Total $
A21: EQCERAMI | B21: EQUIPO PARA COLOCACION DE CERAMICA | C21: gl | D21: 1 | E21: =VLOOKUP(B21,'Rend. Equipos'!$B$7:$E$222,4,FALSE) -> 1424056.6 | F21: =VLOOKUP(B21,'Rend. Equipos'!$B$6:$L$166,MATCH($F$20,'Rend. Equipos'!$B$6:$L$6,0),0) -> 0.0018518519 | G21: =+E21*D21*F21 -> 2637.1418
B22: CORTADORA CERAMICA PROFESIONAL 1200MM (PORCELANATO HASTA 16MM) | C22: u | D22: 1 | E22: =VLOOKUP(B22,'Rend. Equipos'!$B$7:$E$222,4,FALSE) -> 537162.92 | F22: =VLOOKUP(B22,'Rend. Equipos'!$B$6:$L$166,MATCH($F$20,'Rend. Equipos'!$B$6:$L$6,0),0) -> 0.00055555556 | G22: =+E22*D22*F22 -> 298.42384
F23: Total Equipos: | G23: =SUM(G21:G22) -> 2935.5657
F24: Unitario Equipos: | G24: =+G23/F9 -> 97.85219
A25: 3.- MANO DE OBRA
A26: Código | B26: Descripción | C26: Unidad | D26: Cantidad | E26: Salario $ | G26: Total $
A27: MOFAL | B27: MEDIO OFICIAL ALBAÑIL | C27: j | D27: 1 | E27: =VLOOKUP(B27,'Mano de Obra'!$B$8:$C$100,2,FALSE) -> 65493.072 | G27: =+E27*D27 -> 65493.072
A28: OFCOLOCA | B28: OFICIAL COLOCADOR | C28: j | D28: 1 | E28: =VLOOKUP(B28,'Mano de Obra'!$B$8:$C$100,2,FALSE) -> 85927.097 | G28: =+E28*D28 -> 85927.097
F29: Total Mano de Obra Menor: | G29: =SUM(G27:G28) -> 151420.17
F30: Grado de dificultad | G30: 1
F31: Total Mano de Obra: | G31: =+G30*G29 -> 151420.17
F32: Unitario Mano de Obra: | G32: =+G31/F9 -> 5047.339
F34: Costo Directo por Unidad: | G34: =+G32+G24+G18 -> 6211.5344
E35: Gastos Generales: | F35: =+RESUMEN!$I$2 -> 0 | G35: =IF(F35=0,0,F35*G34) -> 0
E36: Beneficio: | F36: =+RESUMEN!$I$3 -> 0 | G36: =IF(F36=0,0,F36*G34) -> 0
F37: PRECIO UNITARIO: | G37: =SUM(G34:G36) -> 6211.5344

Sheet P-59
F2: Fecha: | G2: Completar..
A3: ANALISIS DE PRECIO UNITARIO
F4: Partida N°: | G4: 59
A5: Obra: | B5: Completar
A6: Cliente: | B6: Completar | F6: Código de Obra: | G6: Completar
A7: Partida: | B7: Látex interior satinado para paredes
C8: Unidad: | E8: Cantidad: | F8: Rendimiento:
C9: m2 | E9: 100 | F9: 11 | G9: m2/dia
A10: 1.- MATERIALES
A11: Código | B11: Descripción | C11: Unidad | D11: Cantidad | E11: Costo $ | F11: % Desp. | G11: Total $ | H11: Cant. x Obra
A12: PINT014 | B12: Fijador al agua x 20 lts | C12: b | D12: 0.004 | E12: =VLOOKUP(B12,Materiales!$B$8:$D$118,3,FALSE) -> 30467.49 | F12: 5 | G12: =+D12*E12*((F12+100)/100) -> 127.96346 | H12: =+D12*$E$9 -> 0.4
A13: PINT010 | B13: Enduido Interior x 20lts | C13: b | D13: 0.05 | E13: =VLOOKUP(B13,Materiales!$B$8:$D$118,3,FALSE) -> 18735.77 | F13: 10 | G13: =+D13*E13*((F13+100)/100) -> 1030.4674 | H13: =+D13*$E$9 -> 5 | J13: 2 m2 x litros | L13: 1 | M13: 1
A14: PINT001 | B14: Latex Loxon Interior Sherwin Williams Satinado Bco x 20lts | C14: b | D14: 0.0125 | E14: =VLOOKUP(B14,Materiales!$B$8:$D$118,3,FALSE) -> 237603.31 | F14: 10 | G14: =+D14*E14*((F14+100)/100) -> 3267.0455 | H14: =+D14*$E$9 -> 1.25 | L14: 20 | M14: =+L14*M13/L13 -> 20
A15: PINT015 | B15: Yeso Tuyango x 30kg | C15: b | D15: 0.0025 | E15: =VLOOKUP(B15,Materiales!$B$8:$D$118,3,FALSE) -> 9639 | F15: 5 | G15: =+D15*E15*((F15+100)/100) -> 25.302375 | H15: =+D15*$E$9 -> 0.25
A16: PINT013 | B16: Trapo | C16: u | D16: 0.03 | E16: =VLOOKUP(B16,Materiales!$B$8:$D$118,3,FALSE) -> 735.06 | F16: 5 | G16: =+D16*E16*((F16+100)/100) -> 23.15439 | H16: =+D16*$E$9 -> 3 | M16: 0.05
A17: PINT012 | B17: Cinta de Papel 36 mm x 40m | C17: u | D17: 0.05 | E17: =VLOOKUP(B17,Materiales!$B$8:$D$118,3,FALSE) -> 3293.01 | F17: 10 | G17: =+D17*E17*((F17+100)/100) -> 181.11555 | H17: =+D17*$E$9 -> 5
A18: PINT011 | B18: Lija 180 al agua x 10u | C18: u | D18: 0.05 | E18: =VLOOKUP(B18,Materiales!$B$8:$D$118,3,FALSE) -> 5661.4 | F18: 5 | G18: =+D18*E18*((F18+100)/100) -> 297.2235 | H18: =+D18*$E$9 -> 5
B19: Rodillo de lana pelo corto antigota N°22 - El Galgo | C19: u | D19: 0.005 | E19: =VLOOKUP(B19,Materiales!$B$8:$D$118,3,FALSE) -> 6678.36 | F19: 5 | G19: =+D19*E19*((F19+100)/100) -> 35.06139 | H19: =+D19*$E$9 -> 0.5
B20: Pincel N° 20 - El Galgo | C20: u | D20: 0.005 | E20: =VLOOKUP(B20,Materiales!$B$8:$D$118,3,FALSE) -> 5282.24 | F20: 5 | G20: =+D20*E20*((F20+100)/100) -> 27.73176 | H20: =+D20*$E$9 -> 0.5
B21: Rollo de cartón corrugado 0,90 x 25 mts | C21: u | D21: 0.01 | E21: =VLOOKUP(B21,Materiales!$B$8:$D$118,3,FALSE) -> 7427.6 | F21: 5 | G21: =+D21*E21*((F21+100)/100) -> 77.9898 | H21: =+D21*$E$9 -> 1
F22: Total Materiales: | G22: =SUM(G12:G21) -> 5093.055
F23: Unitario Materiales: | G23: =+G22 -> 5093.055
A24: 2.- EQUIPOS
A25: Código | B25: Descripción | C25: Unidad | D25: Cantidad | E25: Tarifa $ | F25: % Deprec. | G25: Total $
A26: *ESCALE1 | B26: ESCALERA MADERA PINTOR 8 ESCALONES | C26: u | D26: 1 | E26: =VLOOKUP(B26,'Rend. Equipos'!$B$7:$E$222,4,FALSE) -> 72091.109 | F26: =VLOOKUP(B26,'Rend. Equipos'!$B$6:$L$166,MATCH($F$25,'Rend. Equipos'!$B$6:$L$6,0),0) -> 0.0027777778 | G26: =+E26*D26*F26 -> 200.25308
A27: *EQUIPIN | B27: EQUIPO PARA PINTAR | C27: gl | D27: 2 | E27: =VLOOKUP(B27,'Rend. Equipos'!$B$7:$E$222,4,FALSE) -> 1241010.7 | F27: =VLOOKUP(B27,'Rend. Equipos'!$B$6:$L$166,MATCH($F$25,'Rend. Equipos'!$B$6:$L$6,0),0) -> 0.0013888889 | G27: =+E27*D27*F27 -> 3447.2519
F28: Total Equipos: | G28: =SUM(G26:G27) -> 3647.505
F29: Unitario Equipos: | G29: =+G28/F9 -> 331.59136
A30: 3.- MANO DE OBRA
A31: Código | B31: Descripción | C31: Unidad | D31: Cantidad | E31: Salario $ | G31: Total $
A32: OFPINTOR | B32: OFICIAL ESPECIALIZADO PINTOR | C32: j | D32: 1 | E32: =VLOOKUP(B32,'Mano de Obra'!$B$8:$C$100,2,FALSE) -> 85927.097 | G32: =+E32*D32 -> 85927.097
A33: MEDPINTO | B33: MEDIO OFICIAL PINTOR | C33: j | D33: 1 | E33: =VLOOKUP(B33,'Mano de Obra'!$B$8:$C$100,2,FALSE) -> 65493.072 | G33: =+E33*D33 -> 65493.072
F34: Total Mano de Obra Menor: | G34: =SUM(G32:G33) -> 151420.17
F35: Grado de dificultad | G35: 1
F36: Total Mano de Obra: | G36: =+G35*G34 -> 151420.17
F37: Unitario Mano de Obra: | G37: =+G36/F9 -> 13765.47
F39: Costo Directo por Unidad: | G39: =+G37+G29+G23 -> 19190.116
E40: Gastos Generales: | F40: =+RESUMEN!$I$2 -> 0 | G40: =IF(F40=0,0,F40*G39) -> 0
E41: Beneficio: | F41: =+RESUMEN!$I$3 -> 0 | G41: =IF(F41=0,0,F41*G39) -> 0
F42: PRECIO UNITARIO: | G42: =SUM(G39:G41) -> 19190.116

Sheet P-60
F2: Fecha: | G2: Completar..
A3: ANALISIS DE PRECIO UNITARIO
F4: Partida N°: | G4: 60
A5: Obra: | B5: Completar
A6: Cliente: | B6: Completar | F6: Código de Obra: | G6: Completar..
A7: Partida: | B7: Cielorraso Durlock - Junta Tomada STD
C8: Unidad: | E8: Cantidad: | F8: Rendimiento:
C9: m2 | E9: 100 | F9: 9.5 | G9: m2/dia
A10: 1.- MATERIALES
A11: Código | B11: Descripción | C11: Unidad | D11: Cantidad | E11: Costo $ | F11: % Desp. | G11: Total $ | H11: Cant. x Obra
B12: Solera 35mm x 2.60m | C12: u | D12: =1.1/2.6*1.2 -> 0.50769231 | E12: =VLOOKUP(B12,Materiales!$B$8:$D$118,3,FALSE) -> 2147.85 | F12: 10 | G12: =+D12*E12*((F12+100)/100) -> 1199.4916 | H12: =+D12*$E$9 -> 50.769231 | K12: 1.1
B13: Montante 34mm x 2.60m | C13: u | D13: =3.2/2.6 -> 1.2307692 | E13: =VLOOKUP(B13,Materiales!$B$8:$D$118,3,FALSE) -> 2468.66 | F13: 10 | G13: =+D13*E13*((F13+100)/100) -> 3342.1858 | H13: =+D13*$E$9 -> 123.07692 | K13: =+K12/2.6 -> 0.42307692
