Workbook
Name \0: #REF!
Name \0: #REF!
Name \0: #REF!
Name \0: #REF!
Name \0: #REF!
Name \c: #REF!
Name \c: #REF!
Name \E: #REF!
Name \E: #REF!
Name \i: #REF!
Name \j: #REF!
Name \m: #REF!
Name \P: #REF!
Name \P: #REF!
Name \P: #REF!
Name \r: #N/A
Name \x: #REF!
Name \z: #REF!
Name __________ben1: #REF!
Name __________ben1: #REF!
Name __________ben1: #REF!
Name __________ben1: #REF!
Name __________ben10: #REF!
Name __________ben10: #REF!
Name __________ben10: #REF!
Name __________ben15: #REF!
Name __________ben15: #REF!
Name __________ben15: #REF!
Name __________BEN2: #REF!
Name __________BEN2: #REF!
Name __________BEN2: [1]Beneficios!$C$3
Name __________BEN2: #REF!
Name __________BEN2: [1]Beneficios!$C$3
Name __________BEN2: #REF!
Name __________BEN2: #REF!
Name __________BEN2: [1]Beneficios!$C$3
Name __________BEN2: #REF!
Name __________ben20: #REF!
Name __________ben20: #REF!
Name __________ben20: #REF!
Name __________ben25: #REF!
Name __________ben25: #REF!
Name __________ben25: #REF!
Name __________BEN3: #REF!
Name __________BEN3: #REF!
Name __________BEN3: #REF!
Name __________BEN4: #REF!
Name __________BEN4: #REF!
Name __________BEN4: #REF!
Name __________ben5: #REF!
Name __________ben5: #REF!
Name __________ben5: #REF!
Name _________ben1: #REF!
Name _________ben1: #REF!
Name _________ben1: #REF!
Name _________ben10: #REF!
Name _________ben10: #REF!
Name _________ben10: #REF!
Name _________ben15: #REF!
Name _________ben15: #REF!

Sheet Cotizaciones
I1: =+GGBB!H2 -> 45846
B2: Descripcion | C2: Un | D2: P unit | E2: Proveedor | F2: Fecha | H2: DÓLAR BNA | I2: DÓLAR MEP
B3: PRELIMINARES | H3: =+GGBB!G4 -> 1280 | I3: =+GGBB!H4 -> 1276
B4: C. CIN. T101 ESP 0,50 MM (C25) | C4: m2 | D4: =13142.74/1.21 -> 10861.769 | E4: CMP Web | F4: 45785
B5: Peril UPN 100 x 12 m | C5: bar | D5: =328085.32/1.21 -> 271144.89 | E5: CMP Web | F5: 45785
B6: Tubo estructural 40 x 40 x 2, Largo 6 metros | C6: bar | D6: =28463.74/1.21 -> 23523.752 | E6: CMP Web | F6: 45785
B7: Riel Roma 174 e: 2,1 mm. 53 x 60 x 6000 | C7: bar | D7: =103323.57/1.21 -> 85391.38 | E7: CMP Web | F7: 45785
B8: Carro acero 174 4 ruedas puertas portones Ø45mm | C8: u | D8: =13957.04/1.21 -> 11534.744 | E8: CMP Web | F8: 45785
B9: PLACA CEMENTICIA CONSTRUCCION SECO SUPERBOARD ESTRUCTURAL BORDE RECTO 10MM X 1200MM X 2400MM | C9: u | D9: =57320.11/1.21 -> 47371.992 | E9: CMP Web | F9: 45785
B10: CHAPA LISA GALVANIZADA C27 - 1,22 x 2,00 m | C10: u | D10: =20659.53/1.21 -> 17073.992 | E10: CMP Web | F10: 45785
B11: CHAPA LISA GALVANIZADA C27 - 1,22 x 2,44 m | C11: u | D11: =25162.26/1.21 -> 20795.256 | E11: CMP Web | F11: 45785
B12: CHAPA LISA GALVANIZADA C25 - 1,22 x 2,00 m | C12: u | D12: =24100.79/1.21 -> 19918.008 | E12: CMP Web | F12: 45785
B13: CHAPA LISA GALVANIZADA C25 - 1,22 x 2,44 m | C13: u | D13: =29391.17/1.21 -> 24290.223 | E13: CMP Web | F13: 45785
B14: CHAPA LISA GALVANIZADA C22 - 1,22 x 2,44 m | C14: u | D14: =41709.52/1.21 -> 34470.678 | E14: CMP Web | F14: 45785
B15: CHAPA LISA PREP C25 - 1,22 x 2,44 m | C15: u | D15: =46496.8/1.21 -> 38427.107 | E15: CMP Web | F15: 45785 | H15: =+D15/D13 -> 1.5819989
B16: PERFIL ANGULO ALAS IGUALES ESTRUCTURAL ACERO 6M X 5/8" X 1/8 | C16: u | D16: =12473.83/1.21 -> 10308.95 | E16: CMP Web | F16: 45785
B17: Zócalo Contramarco Curvo Atenneas 7.5cm x 15mm MDF Prepintado Blanco 2.75m | C17: tira | D17: =5615/1.21 -> 4640.4959 | E17: GUALA | F17: 45846
B18: Sikaflex®-1A Sellador Poliuretano Color Gris 300ml | C18: u | D18: =29859.05/1.21 -> 24676.901 | E18: ABRAFER WEB | F18: 45845
B19: Babeta amure gris C25 Des. 200mm x 2.44m | C19: tira | D19: 21485.39 | E19: CMP Web | F19: 45845
B20: MADERA
B21: Precio fenolico comun e: 18 mm | C21: placa | D21: 26393.8 | E21: NEWTON | F21: 45782
B22: Precio fenolico visto e: 18 mm | C22: placa | D22: =61746/1.21 -> 51029.752 | E22: ML | F22: 45785
B23: Tabla 4 x 1 x 3,6 Saligna bruto | C23: u | D23: =133124.28/60 -> 2218.738 | E23: NEWTON | F23: 45782
B24: Tirante 3 x 3 x 3,6 Saligna bruto | C24: u | D24: =149764.94/30 -> 4992.1647 | E24: NEWTON | F24: 45782
B25: HORMIGON
B26: H30 6.12 Gunitado | C26: m3 | D26: 148900 | E26: FENOMIX | F26: 45785
B27: H30 6.20 | C27: m3 | D27: 125000 | E27: FENOMIX | F27: 45832
B28: H13 6.20 | C28: m3 | D28: 115100 | E28: FENOMIX | F28: 45785
B29: Acarreo | C29: gl | D29: 533000 | E29: FENOMIX | F29: 45832
B30: Bombeo | C30: m3 | D30: 5330 | E30: FENOMIX | F30: 45832
B31: Super | C31: m3 | D31: 1500 | E31: FENOMIX | F31: 45832
B32: Hidrofugo
B33: HIERRO CONSTRUCCION
B34: Hierro del 6 | C34: kg | D34: 1769.41 | E34: NUQLEA | F34: 45800 | H34: =+D34/D41 -> 1.3216487
B35: Hierro del 8 | C35: kg | D35: 1641.01 | E35: NUQLEA | F35: 45800 | H35: =+D35/D42 -> 1.2605797
B36: Hierro del 10 | C36: kg | D36: 1610.19 | E36: NUQLEA | F36: 45800 | H36: =+D36/D43 -> 1.2369046
B37: Hierro del 12 | C37: kg | D37: 1569.1 | E37: NUQLEA | F37: 45800 | H37: =+D37/D44 -> 1.2136752
B38: Hierro del 16 | C38: kg | D38: 1537 | E38: NUQLEA | F38: 45800 | H38: =+D38/D45 -> 1.203687
B39: Hierro del 20 | C39: kg | D39: 1526.73 | E39: NUQLEA | F39: 45800 | H39: =+D39/D46 -> 1.1956442
B40: Hierro del 25 | C40: kg | D40: 1526.73 | E40: NUQLEA | F40: 45800 | H40: =+D40/D47 -> 1.1956442
B41: Hierro del 6 | C41: kg | D41: 1338.79 | E41: CUTULI HNOS | F41: 45825
B42: Hierro del 8 | C42: kg | D42: 1301.79 | E42: CUTULI HNOS | F42: 45825
B43: Hierro del 10 | C43: kg | D43: 1301.79 | E43: CUTULI HNOS | F43: 45825
B44: Hierro del 12 | C44: kg | D44: 1292.85 | E44: CUTULI HNOS | F44: 45825
B45: Hierro del 16 | C45: kg | D45: 1276.91 | E45: CUTULI HNOS | F45: 45825
B46: Hierro del 20 | C46: kg | D46: 1276.91 | E46: CUTULI HNOS | F46: 45825
B47: Hierro del 25 | C47: kg | D47: 1276.91 | E47: CUTULI HNOS | F47: 45825
B48: BAÑOS
B49: Baño portatil / Ducha | C49: u | D49: 80000 | E49: BATH | F49: 45845
B50: Traslado flete entrega/ retiro | C50: u | D50: 20000 | E50: BATH | F50: 45845
B51: CORRALON
B52: Telgopor 1 x 1 x 20 mm densidad 20 kg | C52: u | D52: 3538.08 | E52: CUTULI HNOS | F52: 45786
B53: Malla de fibra 5 x 5 90 gr, rollo 1 x 50 mts | C53: rol | D53: 42850.08 | E53: CUTULI HNOS | F53: 45786
B54: Liston refractario 230 x 65 x 19 | C54: u | D54: =8900/1.21/10 -> 735.53719 | E54: ML | F54: 45811
B55: Yeso Knauf MP 40/75 Proyectable x 25 kg | C55: bol | D55: 7524.72 | E55: CUTULI HNOS | F55: 45786
B56: Guardacanto yesero 2,60 mts | C56: u | D56: 1566 | E56: CUTULI HNOS | F56: 45786
B57: PA-MAX PUENTE DE ADHERENCIA 20LT | C57: tac | D57: 152600 | E57: TODO PROYECT WEB | F57: 45811 | H57: 150 m2/balde
B58: BUÑA Z PERIMETRAL - Largo 2,60 mt | C58: un | D58: 2212.06 | E58: CUTULI HNOS | F58: 45786
B59: Malla N° 4 Liv 15 x 15 3 x 2 mt | C59: un | D59: 10716.59 | E59: CUTULI HNOS | F59: 45786
B60: Rollo Polietileno negro 2x50 mt x 200mic | C60: rol | D60: 27000 | E60: CUTULI HNOS | F60: 45786
B61: MEMBRANA C/GEOTEXTIL W450 | C61: rol | D61: 57227.91 | E61: CUTULI HNOS | F61: 45786
B62: BOLSON DE PIEDRA PARTIDA 6/20 | C62: bol | D62: 57141 | E62: CUTULI HNOS | F62: 45786
B63: Malla Q188 15 x 15 6 mm 6x2,40 | C63: u | D63: 74988.34 | E63: CUTULI HNOS | F63: 45786
B64: WEBER REFRACTARIO X 10KG (rend. 0,5 m2) | C64: bol | D64: 18900 | E64: CUTULI HNOS | F64: 45786
B65: CEMENTO AVELLANEDA x 50 KG | C65: bol | D65: 7809.92 | E65: CUTULI HNOS | F65: 45786
B66: Cal comun hidrat x 25 kg | C66: bol | D66: =3897.52 -> 3897.52 | E66: CUTULI HNOS | F66: 45786
B67: Weber climamur termoaislante x 7 kg (rinde 1 m2) | C67: bol | D67: =23489/1.21 -> 19412.397 | E67: ML | F67: 45785
B68: Weberprim celublock x 30 kg (3 kg/m2) | C68: bol | D68: 7081.2 | E68: CUTULI HNOS | F68: 45771
B69: MERCADO LIBRE
B70: Sika WaterBars V-15, largo 15 mts | C70: rol | E70: SIKA MAIPU
B71: Sika WaterBars V-20, largo 15 mts | C71: rol | E71: SIKA MAIPU
B72: Tapa Y Marco Para Tanque De Hormigón Poliéster 52 X 52 Cm | C72: u | E72: ML
B73: Varilla Guardacanto L Aluminio Cromo Mate 1663 12 Mm Atrim | C73: u | D73: =22360.76/1.21 -> 18479.967 | E73: DECO TURNER | F73: 45811
B74: REJILLAS
B75: Rejilla De Ventilacion 20 X 20 Fija - Retorno / Extraccion | C75: u | D75: =22000/1.21 -> 18181.818 | E75: ML | F75: 45785
B76: Caño Ventilación Corrugado Aluminio 4 Pulgadas X 1 Metro | C76: ml | D76: =8436.22/1.21 -> 6972.0826 | E76: ML | F76: 45785
B77: Rejilla de ventilación fija 60 x 25 cm - Sala de maquinas de Asc. | C77: u | D77: =51021.1/1.21 -> 42166.198 | E77: SUREF WEB | F77: 45785 | G77: https://surefsuministros.mercadoshops.com.ar/MLA-1315412695-rejilla-de-ventilacion-60x25-fija-retorno-extraccion-_JM?gad_source=1&gclid=CjwKCAjwuMC2BhA7EiwAmJKRrBsF7v-jNZTqJpTBzXJ5xCG9oqcQTWkgAttZaEZuAUMNY4ZB49ecMBoCDdgQAvD_BwE
B78: Termostato ambiente 0-55°C | C78: u | D78: 65000 | E78: VALAIRE | F78: 45750
B79: Forzador de aire 22 m3/m - Sala de maquinas de Asc. | C79: u | D79: 163642 | E79: VALAIRE | F79: 45750
B80: ELECTRICIDAD | I80: Base pres | K80: 16700.7 | L80: 45505
B81: Cable Subterraneo 1x50mm² Violeta PVC IMSA | C81: ml | D81: =+H81*$K$83 -> 10647.354 | E81: PELBA WEB | F81: 45814 | H81: =11974/1.21 -> 9895.8678 | I81: 45654 | K81: 17375.7 | L81: 45597
B82: M SUBTERRANEO N IRAM 5X16 MM2 | C82: ml | D82: =+H82*$K$83 -> 18677.339 | E82: CASTELAO | F82: 45814 | H82: 17359.1 | I82: 45636 | K82: 18695.2 | L82: 45778
B83: M SUBTERRANEO N.IRAM 5X10 MM2 | C83: ml | D83: =+H83*$K$83 -> 12168.035 | E83: CASTELAO | F83: 45814 | H83: 11309.22 | I83: 45636 | K83: =+K82/K81 -> 1.0759394 | L83: CAC MAT
B84: M SUBTERRANEO N IRAM 5X 6 MM2 | C84: ml | D84: =+H84*$K$83 -> 6493.4771 | E84: CASTELAO | F84: 45814 | H84: 6035.17 | I84: 45636 | K84: =+K82/K80 -> 1.1194261 | L84: CAC MAT
B85: Cable Subterraneo 3x10mm² Violeta PVC IMSA | C85: ml | D85: =+H85*$K$83 -> 7374.1862 | E85: PELBA WEB | F85: 45814 | H85: =8293/1.21 -> 6853.719 | I85: 45654
B86: M SUBTERRANEO N IRAM 3X 6.00 MM2 | C86: ml | D86: =+H86*$K$83 -> 3978.9637 | E86: CASTELAO | F86: 45814 | H86: 3698.13 | I86: 45636
B87: M SUBTERRANEO N IRAM 3X 4.00 MM2 | C87: ml | D87: =+H87*$K$83 -> 2895.6434 | E87: CASTELAO | F87: 45814 | H87: 2691.27 | I87: 45636
B88: M SUBTERRANEO N IRAM 3X 2.50 MM2 | C88: ml | D88: =+H88*$K$83 -> 1908.8133 | E88: CASTELAO | F88: 45814 | H88: 1774.09 | I88: 45636
B89: M SUBTERRANEO N IRAM 1X 120MM2 | C89: ml | D89: =+H89*$K$83 -> 22097.051 | E89: CASTELAO | F89: 45814 | H89: 20537.45 | I89: 45636
B90: Cable Cobre desnudo 1x25mm² | C90: ml | D90: =+H90*$K$83 -> 4801.713 | E90: PELBA WEB | F90: 45814 | H90: =5400/1.21 -> 4462.8099 | I90: 45654
B91: RLLOX100M 1X16 MM VD/ AM N.IRAM | C91: rol | D91: =+H91*$K$83 -> 288766.92 | E91: CASTELAO | F91: 45814 | H91: 268385.86 | I91: 45636
B92: RLLOX100M 1X 2,5MM NEGRO N.IRAM | C92: rol | D92: =+H92*$K$83 -> 45833.877 | E92: CASTELAO | F92: 45814 | H92: 42598.94 | I92: 45636
B93: RLLOX100M 1X 1,5MM NEGRO N.IRAM | C93: rol | D93: =+H93*$K$83 -> 28477.232 | E93: CASTELAO | F93: 45814 | H93: 26467.32 | I93: 45636
B94: RLLOX100M 1X 4,0MM NEGRO N.IRAM | C94: rol | D94: =+H94*$K$83 -> 71572.004 | E94: CASTELAO | F94: 45814 | H94: 66520.48 | I94: 45636
B95: RLLOX100M 1X 6,0MM NEGRO N.IRAM | C95: rol | D95: =+H95*$K$83 -> 103147.91 | E95: PELBA WEB | F95: 45814 | H95: =1160*100/1.21 -> 95867.769 | I95: 45654
B96: Cable unipolar 10 mm N.IRAM | C96: ml | D96: =+H96*$K$83 -> 1780.1906 | E96: PELBA WEB | F96: 45814 | H96: =2002/1.21 -> 1654.5455 | I96: 45654
B97: CONDUWELD JAB ST 3/4 1.5M | C97: u | D97: =+H97*$K$83 -> 29030.943 | E97: CASTELAO | F97: 45814 | H97: 26981.95 | I97: 45636
B98: CONDUWELD TOMACABLE 3 | C98: u | D98: =+H98*$K$83 -> 18112.396 | E98: CASTELAO | F98: 45814 | H98: 16834.03 | I98: 45636
B99: CAJA INSPECCION 15 x 15 PVC | C99: u | D99: =+H99*$K$83 -> 1167.9968 | E99: CASTELAO | F99: 45814 | H99: 1085.56 | I99: 45636
B100: INT. TERMOMAGNETICO E9 2X10A 4,5KA | C100: u | D100: =+H100*$K$83 -> 16986.63 | E100: CASTELAO | F100: 45814 | H100: 15787.72 | I100: 45636
...

Sheet SUBCONTRATOS
J2: 10331 | K2: 45292 | M2: DÓLAR BNA | N2: DÓLAR MEP
B3: Descripcion | C3: Un | D3: Precio | E3: Fecha | F3: Contratista | H3: Pres. BASE ENE | J3: 16253.5 | K3: 45748 | M3: =+GGBB!G4 -> 1280 | N3: =+GGBB!H4 -> 1276
B4: GESTOR ELECTRICO | J4: =+J3/J2 -> 1.5732746 | K4: CAC
B5: Proyecto instalacion electrica | C5: gl | D5: =+H5*$J$4 -> 1274352.4 | E5: 45748 | F5: IGT | H5: 810000 | I5: 45356
B6: Baja de suministros | C6: gl | D6: =+H6*$J$4 -> 51918.062 | E6: 45749 | F6: IGT | H6: 33000 | I6: 45356
B7: Corte por demolicion | C7: gl | D7: =+H7*$J$4 -> 116422.32 | E7: 45750 | F7: IGT | H7: 74000 | I7: 45356
B8: Instalacion electrica desenergizada | C8: gl | D8: =+H8*$J$4 -> 143167.99 | E8: 45751 | F8: IGT | H8: 91000 | I8: 45356
B9: Traslado de alumbrado publico | C9: gl | D9: =+H9*$J$4 -> 121142.15 | E9: 45752 | F9: IGT | H9: 77000 | I9: 45356
B10: Factibilidad y renovacion | C10: gl | D10: =+H10*$J$4 -> 259590.31 | E10: 45753 | F10: IGT | H10: 165000 | I10: 45356
B11: Gestion suministros luz de obra | C11: gl | D11: =+H11*$J$4 -> 157327.46 | E11: 45754 | F11: IGT | H11: 100000 | I11: 45356
B12: Sala de medidores / Camara transformadora | C12: gl | D12: =+H12*$J$4 -> 550646.11 | E12: 45755 | F12: IGT | H12: 350000 | I12: 45356
B13: Certificados
B14: Luz de Obra | C14: u | D14: =+H14*$J$4 -> 113275.77 | E14: 45757 | F14: IGT | H14: 72000 | I14: 45356
B15: Servicios grales T1 | C15: u | D15: =+H15*$J$4 -> 113275.77 | E15: 45758 | F15: IGT | H15: 72000 | I15: 45356
B16: Servicios grales T2 | C16: u | D16: =+H16*$J$4 -> 166767.11 | E16: 45759 | F16: IGT | H16: 106000 | I16: 45356
B17: Residencial | C17: u | D17: =+H17*$J$4 -> 78663.731 | E17: 45760 | F17: IGT | H17: 50000 | I17: 45356
B18: Medicion PAT luz de obra | C18: u | D18: =+H18*$J$4 -> 99116.3 | E18: 45761 | F18: IGT | H18: 63000 | I18: 45356
B19: Medicion PAT adicional c/u tableros | C19: u | D19: =+H19*$J$4 -> 49558.15 | E19: 45762 | F19: IGT | H19: 31500 | I19: 45356
B20: ENSAYOS HORMIGON
B21: Ensayo probeta 15 x 30 x un | C21: gl | D21: =(38800+(22000/2))/1.21 -> 41157.025 | E21: 45756 | F21: INTI
B22: MOVIMIENTO DE SUELOS | I22: M.O Ago-24 | J22: 10084.9
B23: Excavación por m3 | C23: m3 | D23: 19500 | E23: 45783 | F23: CELSI VIAL | I23: M.O. Abr 25 | J23: 12755.3 | L23: 0.665 | M23: Cargas
B24: Desmonte y aporte de tosca | C24: m2 | D24: =+H24/600 -> 21120 | E24: 45790 | F24: CELSI VIAL | G24: Polo Palermo (600 m2) | H24: 12672000 | J24: =+J23/J22+K24 -> 1.3447919 | K24: 0.08 | L24: 0.9 | M24: Subcontrato
B25: Desmonte y aporte de tosca | C25: m2 | D25: =+H25/180 -> 23552.222 | E25: 45652 | F25: CELSI VIAL | G25: VL 572 (180 m2) | H25: =3854000*1.1 -> 4239400
B26: Maquina 6 tn | C26: d | D26: 528000 | E26: 45833 | F26: CELSI VIAL
B27: Viaje camión | C27: d | D27: 140000 | E27: 45833 | F27: CELSI VIAL
B28: Traslado de maquina | C28: u | D28: 80000 | E28: 45833 | F28: CELSI VIAL
B29: PROYECTABLE | H29: Base Agosto 24 | L29: Cargas sociales
B30: Monolitico | C30: m2 | D30: =+L30 -> 9100.0957 | E30: 45748 | F30: JUAN VAZQUEZ | H30: 4500 | I30: 45510 | J30: =+H30*$J$24 -> 6051.5636 | L30: =+J30/$L$23 -> 9100.0957
B31: Alivianado | C31: m2 | D31: =+L31 -> 8088.9739 | E31: 45748 | F31: JUAN VAZQUEZ | H31: 4000 | I31: 45510 | J31: =+H31*$J$24 -> 5379.1677 | L31: =+J31/$L$23 -> 8088.9739
B32: Yeso | C32: m2 | D32: =+L32 -> 12252.549 | E32: 45748 | F32: JUAN VAZQUEZ | H32: 8200 | I32: 45510 | J32: =+H32*$J$24 -> 11027.294 | L32: =+J32/$L$24 -> 12252.549
B33: Arista / Buña | C33: ml | D33: =+L33 -> 13144.583 | E33: 45748 | F33: JUAN VAZQUEZ | H33: 6500 | I33: 45510 | J33: =+H33*$J$24 -> 8741.1475 | L33: =+J33/$L$23 -> 13144.583
B34: Cantonera | C34: u | D34: =+L34 -> 13144.583 | E34: 45748 | F34: JUAN VAZQUEZ | H34: 6500 | I34: 45510 | J34: =+H34*$J$24 -> 8741.1475 | L34: =+J34/$L$23 -> 13144.583
B35: Revoque 3 en 1 | C35: m2 | D35: =+L35 -> 22244.678 | E35: 45748 | F35: JUAN VAZQUEZ | H35: 11000 | I35: 45510 | J35: =+H35*$J$24 -> 14792.711 | L35: =+J35/$L$23 -> 22244.678
B36: Buña en revoque | C36: ml | D36: =+L36 -> 11122.339 | E36: 45748 | F36: JUAN VAZQUEZ | H36: 5500 | I36: 45510 | J36: =+H36*$J$24 -> 7396.3555 | L36: =+J36/$L$23 -> 11122.339
B37: TARQUINI
B38: Revestimiento plastico | C38: m2 | D38: =+L38 -> 10111.217 | E38: 45748 | F38: CRISTIAN CAPONE | H38: 5000 | I38: 45510 | J38: =+H38*$J$24 -> 6723.9596 | L38: =+J38/$L$23 -> 10111.217
B39: Revestimiento plastico | C39: m2 | D39: =+L39 -> 14155.704 | E39: 45748 | F39: CRISTIAN CAPONE | G39: 15% plus altura + 25% menor rendimiento | H39: =+H38*1.4 -> 7000 | I39: 45510 | J39: =+H39*$J$24 -> 9413.5434 | L39: =+J39/$L$23 -> 14155.704 | M39: 15% plus altura + 25% menor rendimiento
B40: AA.CC - PREINSTALACIONES | G40: 40
B41: Preinstalacion MAT | C41: u | D41: =+G41/$G$40 -> 247500 | E41: 45840 | F41: GUILLERMO ERBA | G41: 9900000
B42: Preinstalacion M.O | C42: u | D42: =+G42/$G$40 -> 230000 | E42: 45840 | F42: GUILLERMO ERBA | G42: 9200000
B43: Instalacion y puesta en marcha | C43: u | D43: =+G43/$G$40 -> 0 | F43: GUILLERMO ERBA
B44: INSTALACION ELECTRICA | G44: Precios WEB | H44: 45778
B45: Canalización | C45: b | D45: =+G45*0.7 -> 30114.7 | E45: 45778 | F45: AAIERIC | G45: 43021
B46: Cableado | C46: b | D46: =+G46*0.7 -> 13192.2 | E46: 45778 | F46: AAIERIC | G46: 18846
B47: Boca completa | D47: =+D45+D46 -> 43306.9 | E47: 45778 | F47: AAIERIC
B48: Boca completa de ilum/toma + punto/toma | C48: b | D48: =+G48*0.7 -> 53617.2 | E48: 45778 | F48: AAIERIC | G48: 76596
B49: Conexión de punto y toma | C49: b | D49: =+G49*0.7 -> 9575.3 | E49: 45778 | F49: AAIERIC | G49: 13679
B50: Colocación artefacto | C50: u | D50: =+G50*0.7 -> 14693.7 | E50: 45778 | F50: AAIERIC | G50: 20991
B51: Colocación extractor de aire en baño | C51: u | D51: =+G51*0.5 -> 59550 | E51: 45778 | F51: ELECTRO INSTALADOR | G51: 119100
B52: Colocación Campana tipo Spar | C52: u | D52: =+G52*0.5 -> 84800 | E52: 45778 | F52: ELECTRO INSTALADOR | G52: 169600
B53: Luz de emergencia | C53: u | D53: =+G53*0.7 -> 22610 | E53: 45778 | F53: ELECTRO INSTALADOR | G53: 32300
B54: Tablero seccional de 8 a 36 polos | C54: u | D54: =+G54*0.45 -> 289506.6 | E54: 45778 | F54: AAIERIC | G54: 643348
B55: Tablero seccional de 36 a 54 polos | C55: u | D55: =+G55*0.45 -> 434240.1 | E55: 45778 | F55: AAIERIC | G55: 964978
B56: Bandeja portacable 300 mm | C56: u | D56: =+G56*0.7 -> 26460 | E56: 45778 | F56: ELECTRO INSTALADOR | G56: 37800
B57: Tendido de cable subterraneo | C57: ml | D57: =+G57*0.7 -> 26831 | E57: 45778 | F57: AAIERIC | G57: 38330
B58: Gabinete 4 medidores | C58: u | D58: =+G58*0.7 -> 428925 | E58: 45778 | F58: AAIERIC | G58: 612750 | O58: RVG 1553 | P58: UF
B59: Gabinete 1 medidor trif | C59: u | D59: =+G59*0.7 -> 112571.9 | E59: 45778 | F59: AAIERIC | G59: 160817 | O59: PB | P59: 80
B60: Caño de acometida | C60: u | D60: =+G60*0.7 -> 112571.9 | E60: 45778 | F60: AAIERIC | G60: 160817 | K60: 45383 | L60: 7803.5 | O60: 2º | P60: 75
B61: Caja de toma | C61: u | D61: =+G61*0.7 -> 160878.2 | E61: 45778 | F61: AAIERIC | G61: 229826 | K61: 45748 | L61: 12755.3 | O61: 3º | P61: 80
B62: PAT de Servicio | C62: u | D62: =+G62*0.7 -> 80397.1 | E62: 45778 | F62: AAIERIC | G62: 114853 | L62: =+L61/L60 -> 1.6345614 | M62: =+P63/T70 -> 0.38265306 | O62: 3º | P62: 65
B63: CALEFACCION | H63: 45385 | J63: dólar mep abril | K63: Cotización de peña | L63: ACT. CAC M.O | M63: Incidencia de obra | P63: =+SUM(P59:P62) -> 300
B64: Piso radiante + caldera | C64: gl | D64: =+M64 -> 10758083 | E64: 45748 | F64: ARIAS | H64: 17200 | I64: usd | J64: 1000 | K64: =+H64*J64 -> 17200000 | L64: =+K64*L62 -> 28114456 | M64: =+L64*M62 -> 10758083
G65: 1 | O65: Peña | P65: A | Q65: B | R65: m2 | S65: Rep | T65: m2
B66: Tendido de cañerías | C66: u | D66: =+$D$64/$G$65*G66 -> 9144370.4 | E66: 45748 | F66: ARIAS | G66: 0.85 | H66: =+D66/4 -> 2286092.6 | I66: x UF promedio | K66: m2 | L66: =+T70 -> 784 | O66: P1 | P66: 47 | Q66: 47 | R66: =+SUM(P66:Q66) -> 94 | S66: 1 | T66: =+R66*S66 -> 94 | V66: =2*S66 -> 2
B67: Montaje de radiadores | C67: u | D67: =+$D$64/$G$65*G67 -> 0 | G67: 0 | H67: =+D67/81 -> 0 | K67: x m2 | L67: =+L64/L66 -> 35860.276 | O67: P2 a 7 | P67: 47 | Q67: 47 | R67: =+SUM(P67:Q67) -> 94 | S67: 6 | T67: =+R67*S67 -> 564 | V67: =2*S67 -> 12
B68: Puesta en marcha de caldera | C68: u | D68: =+$D$64/$G$65*G68 -> 1613712.4 | E68: 45748 | F68: ARIAS | G68: 0.15 | H68: =+D68/4 -> 403428.1 | I68: x caldera | O68: P8 | P68: 36 | Q68: 47 | R68: =+SUM(P68:Q68) -> 83 | S68: 1 | T68: =+R68*S68 -> 83 | V68: =2*S68 -> 2
H69: 10483.3 | I69: Base M.O. sep 24 | O69: P9 | P69: 43 | R69: =+SUM(P69:Q69) -> 43 | S69: 1 | T69: =+R69*S69 -> 43 | V69: =1*S69 -> 1
H70: 12755.3 | I70: Base M.O. abr 25 | T70: =+SUM(T66:T69) -> 784 | V70: =+SUM(V66:V69) -> 17
B71: DEPRESION DE NAPAS | H71: =+H70/H69 -> 1.2167256 | I71: Act. Estimada
B72: Perforación completa | C72: gl | D72: =+H72 -> 3163486.7 | E72: 45748 | F72: Claudio Pizzutto | G72: 2600000 | H72: =+G72*$H$71 -> 3163486.7
B73: Total de Obra (2 perforaciones) | C73: gl | D73: =+H73 -> 6326973.4 | E73: 45748 | F73: Claudio Pizzutto | G73: =+G72*2 -> 5200000 | H73: =+G73*$H$71 -> 6326973.4
B74: IMPERMEBAILIZACION | I74: =1/1.5 -> 0.66666667 | J74: Cargas sociales
B75: Colocación de membrana | C75: m2 | D75: =+I75 -> 12775.619 | E75: 45748 | F75: CARLOS BURGO | G75: 7000 | H75: =+G75*$H$71 -> 8517.0795 | I75: =+H75/I74 -> 12775.619
B76: Juntas (perimetral/vertical/etc.) | C76: ml | D76: =+H76 -> 29809.778 | E76: 45748 | F76: HIDROTECNICA | G76: 24500 | H76: =+G76*$H$71 -> 29809.778
B77: Impermeabilización (tabiques/losa) | C77: m2 | D77: =+H77 -> 14600.708 | E77: 45748 | F77: HIDROTECNICA | G77: 12000 | H77: =+G77*$H$71 -> 14600.708
B78: Bajo recorrdio | C78: gl | D78: =+H78 -> 1041517.2 | E78: 45748 | F78: HIDROTECNICA | G78: 856000 | H78: =+G78*$H$71 -> 1041517.2
B79: HORMIGON GUNITADO
B80: Servicio de gunitado, fratazado y fieltrado | C80: m2 | D80: 14150 | E80: 45777 | F80: Gunix | H80: =+D80/0.15 -> 94333.333
B81: Movimiento de bomba y limpieza | C81: gl | D81: 90000 | E81: 45777 | F81: Gunix
B82: ANCLAJES DE SUBMURACION | H82: =+H80+H81 -> 94333.333 | I82: x m3
B83: Anclajes | C83: ml | D83: 40000 | E83: 45777 | F83: CIMA
B84: GESTOR GAS
B85: Prefactibilidad | C85: gl | D85: 450000 | E85: 45779 | F85: Ezequiel Mendoza | M85: =+SUM(L86) -> 5760970.2 | N85: =+M85+D91 -> 61950970
B86: Parcial | C86: gl | D86: 550000 | E86: 45779 | F86: Ezequiel Mendoza | H86: 730 bolsas cemento | J86: 730 | K86: 7891.74 | L86: =+J86*K86 -> 5760970.2
B87: Final | C87: gl | D87: 400000 | E87: 45779 | F87: Ezequiel Mendoza | M87: =+SUM(L88:L91) -> 19437121 | N87: =+M87+D90 -> 78473121
B88: Habilitación | C88: gl | D88: 1500000 | J88: 1310 | K88: 7891.74 | L88: =+J88*K88 -> 10338179
B89: MICROPILOTES | I89: 12 | J89: 56 | K89: 14040.44 | L89: =+J89*K89 -> 786264.64
B90: MP IRS | C90: gl | D90: 59036000 | E90: 45803 | F90: PILOTES Y ANCLAJES | H90: 1310 bolsas cemento, 56 Ø12, 120 Ø16, 140 Ø20 | I90: 16 | J90: 120 | K90: 24503.33 | L90: =+J90*K90 -> 2940399.6
B91: MP IU | C91: gl | D91: 56190000 | E91: 45803 | F91: PILOTES Y ANCLAJES | I91: 20 | J91: 140 | K91: 38373.41 | L91: =+J91*K91 -> 5372277.4
B92: Movilización | C92: gl | D92: 950000 | E92: 45803 | F92: PERFOSUR SRL | M92: =+SUM(L93:L95) -> 9703977.8 | N92: =+M92+D93+D92 -> 45003978
B93: Perforación | C93: gl | D93: 34350000 | E93: 45803 | F93: PERFOSUR SRL | H93: 1100 bolsas cemento, 24 Ø12, 28 Ø16 | J93: 1100 | K93: 7891.74 | L93: =+J93*K93 -> 8680914
I94: 12 | J94: 24 | K94: 14040.44 | L94: =+J94*K94 -> 336970.56 | O94: 10.65 | P94: =+O94*J94 -> 255.6
I95: 16 | J95: 28 | K95: 24503.33 | L95: =+J95*K95 -> 686093.24 | O95: 18.94 | P95: =+O95*J95 -> 530.32
P96: =+SUM(P94:P95) -> 785.92
P97: 800

Sheet APU 06.25
A1: , | K1: Mes: | L1: JUNIO
K2: Año: | L2: 2025
K3: Revisado: | L3: MC
C5: ANALISIS DE PRECIO UNITARIO
C7: RESUMEN
E8: PRECIO UNITARIO
E9: Unitario Materiales: | H9: Unitario Mano de Obra: | K9: Unitario Equipos: | M9: RENDIMIENTO
A10: CODIGO | B10: PARTIDA | C10: DETALLE | E10: MAT | H10: MO | K10: EQUIPOS | L10: TOTAL | M10: u/dia
B11: 32 | C11: Movimiento de suelos para bases c/ aporte de tosca (e: 40 cm en 2 capas de 20 cm) | D11: m3 | E11: 12754.673 | H11: 6652.371 | K11: 40200 | L11: =+SUM(E11:K11) -> 59607.044 | M11: 25
A12: ARQUIN21 | B12: 33 | C12: Ladrillo común 12,5 x 5,5 x 25 (e:15 cm) | D12: m2 | E12: 14000.877 | H12: 23059.662 | K12: 548.10112 | L12: =+SUM(E12:K12) -> 37608.641 | M12: 7
A13: ARQUIN21 | B13: 34 | C13: Ladrillo cerámico 8 x 18 x 33 cm | D13: m2 | E13: 10053.788 | H13: 10761.176 | K13: 255.78052 | L13: =+SUM(E13:K13) -> 21070.744 | M13: 15
A14: ARQUIN21 | B14: 35 | C14: Ladrillo cerámico 12 x 18 x 33 cm | D14: m2 | E14: 12465.038 | H14: 10761.176 | K14: 255.78052 | L14: =+SUM(E14:K14) -> 23481.994 | M14: 15
A15: ARQUIN21 | B15: 36 | C15: Ladrillo cerámico 18 x 18 x 33 cm | D15: m2 | E15: 17538.995 | H15: 10761.176 | K15: 255.78052 | L15: =+SUM(E15:K15) -> 28555.952 | M15: 15
A16: ARQUIN21 | B16: 37 | C16: Pared DOBLE Comun / 5 / LHC 08 - (ladrillo a la vista) | D16: m2 | E16: 31798.204 | H16: 38841.498 | K16: 959.17696 | L16: =+SUM(E16:K16) -> 71598.879 | M16: 4
A17: ARQUIN21 | B17: 38 | C17: Ladrillo hueco portante 12 x 19 x 33 | D17: m2 | E17: 18207.26 | H17: 10761.176 | K17: 255.78052 | L17: =+SUM(E17:K17) -> 29224.217 | M17: 15
A18: ARQUIN21 | B18: 39 | C18: Amure puertas tipo (0,90 x 2,00 m) | D18: u | E18: 4104.3832 | H18: 60531.614 | K18: 440.78781 | L18: =+SUM(E18:K18) -> 65076.785 | M18: 2
A19: ARQUIN21 | B19: 40 | C19: Amure Premarcos | D19: u | E19: 1501.8311 | H19: 40354.409 | K19: 220.3939 | L19: =+SUM(E19:K19) -> 42076.634 | M19: 4
A20: ARQUIN21 | B20: 41 | C20: Amure barandas (insertos c/1,00 m) | D20: ml | E20: 310.90703 | H20: 32283.527 | K20: 300.60867 | L20: =+SUM(E20:K20) -> 32895.043 | M20: 5
A21: ARQUIN21 | B21: 42 | C21: Azotado hidrófugo | D21: m2 | E21: 827.27861 | H21: 4324.0478 | K21: 137.02528 | L21: =+SUM(E21:K21) -> 5288.3517 | M21: 28
A22: ARQUIN21 | B22: 43 | C22: Interior jaharro a la cal + Enlucido a la cal | D22: m2 | E22: 2891.2175 | H22: 22980.577 | K22: 639.45131 | L22: =+SUM(E22:K22) -> 26511.246 | M22: 6
A23: ARQUIN21 | B23: 44 | C23: Revoque Grueso impermeable Exterior hasta 3.00 m - Incl. Azotado hidrófugo | D23: m2 | E23: 4061.1651 | H23: 11697.516 | K23: 333.62677 | L23: =+SUM(E23:K23) -> 16092.308 | M23: 11.5
... A28: ARQUIN21 | B28: 49 | C28: Carpeta hidrófuga (e: 2 cm) | D28: m2 | E28: 4136.3931 | H28: 8295.6908 | K28: 235.08683 | L28: =+SUM(E28:K28) -> 12667.171 | M28: 15
A29: ARQUIN21 | B29: 50 | C29: Cemento alisado o cilindrado (e: 3 cm) | D29: m2 | E29: 4104.3832 | H29: 11112.816 | K29: 306.635 | L29: =+SUM(E29:K29) -> 15523.834 | M29: 11.5 | U29: perim | V29: h
A30: ARQUIN21 | B30: 51 | C30: Látex interior para paredes (incl. enduido) | D30: m2 | E30: 4251.3982 | H30: 8379.1959 | K30: 190.09545 | L30: =+SUM(E30:K30) -> 12820.69 | M30: 22 | Q30: Living | R30: 8 | S30: 4 | T30: =+R30*S30 -> 32 | U30: =+R30*2+S30*2 -> 24 | V30: 4.5 | W30: =+U30*V30 -> 108
A31: ARQUIN21 | B31: 52 | C31: látex para cielorrasos (incl. enduido) | D31: m2 | E31: 4251.3982 | H31: 9503.3872 | K31: 262.01469 | L31: =+SUM(E31:K31) -> 14016.8 | M31: 17.5 | Q31: Cocina | R31: 3 | S31: 5 | T31: =+R31*S31 -> 15 | U31: =+R31*2+S31*2 -> 16 | V31: 1 | W31: =+U31*V31 -> 16
A32: ARQUIN21 | B32: 53 | C32: látex exterior para paredes hasta 3.00 m de altura | D32: m2 | E32: 2901.8567 | H32: 6075.9444 | K32: 134.90645 | L32: =+SUM(E32:K32) -> 9112.7075 | M32: 15.5 | Q32: Dormitori | R32: 6 | S32: 4 | T32: =+R32*S32 -> 24 | U32: =+R32*2+S32*2 -> 20 | V32: 4.5 | W32: =+U32*V32 -> 90
A33: ARQUIN22 | B33: 53 bis | C33: látex exterior para paredes a más 3.00 m de altura | D33: m2 | E33: 2901.8567 | H33: 15936.651 | K33: 254.81362 | L33: =+SUM(E33:K33) -> 19093.322 | M33: 15.5 | Q33: Dormitori | R33: 3 | S33: 4 | T33: =+R33*S33 -> 12 | U33: =+R33*2+S33*2 -> 14 | V33: 2 | W33: =+U33*V33 -> 28
A34: ARQUIN21 | B34: 54 | C34: Esmalte sintético sobre carpintería metálica , herrería (cuando es vacio x lleno contemplar MAT al 60%) | D34: m2 | E34: 4460.7312 | H34: 11772.142 | K34: 261.38124 | L34: =+SUM(E34:K34) -> 16494.255 | M34: 8 | Q34: Baño | R34: 3 | S34: 2 | T34: =+R34*S34 -> 6 | U34: =+R34*2+S34*2 -> 10 | V34: 1 | W34: =+U34*V34 -> 10 | Z34: =+Z36*1.35 -> 6356.9568
A35: ARQUIN21 | B35: 55 | C35: Revestimiento plastico texturado tipo Quimtex fino | D35: m2 | E35: 6929.178 | H35: 12350.905 | K35: 197.48055 | L35: =+SUM(E35:K35) -> 19477.563 | M35: 20 | Q35: Baño | R35: 1.5 | S35: 2 | T35: =+R35*S35 -> 3 | U35: =+R35*2+S35*2 -> 7 | V35: 1 | W35: =+U35*V35 -> 7
A36: ARQUIN21 | B36: 56 | C36: Colocación porcelanato en pisos (no incluye baños) | D36: m2 | E36: 6932.2708 | H36: 12793.021 | K36: 245.43421 | L36: =+SUM(E36:K36) -> 19970.726 | M36: 13 | T36: =+SUM(T30:T35) -> 92 | W36: =+SUM(W30:W35) -> 259 | Y36: =+T36+W36 -> 351 | Z36: =+H80 -> 4708.8569 | AA36: =+Y36*Z36 -> 1652808.8
A37: ARQUIN21 | B37: 57 | C37: Revestimiento porcelanato en paredes y piso baños | D37: m2 | E37: 6932.2708 | H37: 16630.928 | K37: 319.06447 | L37: =+SUM(E37:K37) -> 23882.263 | M37: 10 | Y37: =+Y36 -> 351 | Z37: 2126.0865 | AA37: =+Y37*Z37 -> 746256.36
A38: ARQUIN21 | B38: 58 | C38: Colocacion de zocalo porcelanato | D38: ml | E38: 1001.4972 | H38: 5543.6425 | K38: 106.35482 | L38: =+SUM(E38:K38) -> 6651.4946 | M38: 30
A39: ARQUIN22 | B39: 59 | C39: Látex interior satinado para paredes | D39: m2 | E39: 6691.9788 | H39: 15119.025 | K39: 360.40421 | L39: =+SUM(E39:K39) -> 22171.408 | M39: 11 | AA39: =+AA36+AA37 -> 2399065.1
A40: ARQUIN23 | B40: 60 | C40: Cielorraso Durlock - Junta Tomada STD | D40: m2 | E40: 10667.045 | H40: 17506.24 | K40: 286.64634 | L40: =+SUM(E40:K40) -> 28459.931 | M40: 9.5
A41: ARQUIN24 | B41: 61 | C41: Cielorraso Durlock - Junta Tomada RH | D41: m2 | E41: 14748.7 | H41: 17506.24 | K41: 286.64634 | L41: =+SUM(E41:K41) -> 32541.586 | M41: 9.5
A42: ARQUIN25 | B42: 62 | C42: Cielorraso Durlock - Junta Tomada RF | D42: m2 | E42: 13947.896 | H42: 17506.24 | K42: 286.64634 | L42: =+SUM(E42:K42) -> 31740.781 | M42: 9.5
A43: ARQUIN26 | B43: 63 | C43: Cielorraso Desmontable 60x60 - sin provision | D43: m2 | E43: 6636.1994 | H43: 16630.928 | K43: 272.31402 | L43: =+SUM(E43:K43) -> 23539.441 | M43: 10
B44: 63 bis | C44: Cielorraso Desmontable 60x60 - incluye placa Deco Vinyl | D44: m2 | E44: 33199.927 | H44: 16630.928 | K44: 272.31402 | L44: =+SUM(E44:K44) -> 50103.169 | M44: 10
A45: ARQUIN27 | B45: 64 | C45: Pared Durlock - Simple | D45: m2 | E45: 16393.937 | H45: 23758.468 | K45: 378.13572 | L45: =+SUM(E45:K45) -> 40530.54 | M45: 7
A46: ARQUIN28 | B46: 65 | C46: Pared Durlock - Doble placa STD ambas caras y asilación lana de vidrio | D46: m2 | E46: 28944.105 | H46: 27718.213 | K46: 441.15834 | L46: =+SUM(E46:K46) -> 57103.476 | M46: 6
A47: ARQUIN29 | B47: 66 | C47: Medio tabique espesor total 8,5 cm | D47: m2 | E47: 11507.597 | H47: 15119.025 | K47: 441.15834 | L47: =+SUM(E47:K47) -> 27067.78 | M47: 11
A48: ARQUIN30 | B48: 67 | C48: Esmalte sintetico para paredes | D48: m2 | E48: 4981.3709 | H48: 8315.4638 | K48: 104.5525 | L48: =+SUM(E48:K48) -> 13401.387 | M48: 20
A49: ARQUIN31 | B49: 68 | C49: Ladrillo Klimablock 27 x 19 x 30 cm | D49: m2 | E49: 3751.4788 | H49: 10761.176 | K49: 255.78052 | L49: =+SUM(E49:K49) -> 14768.435 | M49: 15
A50: ARQUIN33 | B50: 70 | C50: Impermeabilización de cubierta transitable sobre carpeta horizontal con membrana Geotextil de 4mm, a soplete. | D50: m2 | E50: 8716.8187 | H50: 6456.7055 | K50: 34.976452 | L50: =+SUM(E50:K50) -> 15208.501 | M50: 25
A51: ARQUIN34 | B51: 71 | C51: Impermeabilización de cubierta con Malla no tejida de poliester y pintura poliuretánica | D51: m2 | E51: 8638.6331 | H51: 3228.3527 | K51: 40.515533 | L51: =+SUM(E51:K51) -> 11907.501 | M51: 50
A52: ARQUIN35 | B52: 72 | C52: Revoque Exterior 3 en 1 hasta 3,00 m | D52: m2 | E52: 13018.852 | H52: 7633.4293 | K52: 1260.1909 | L52: =+SUM(E52:K52) -> 21912.472 | M52: 35
A53: ARQUIN36 | B53: 73 | C53: Pintura sobre pared existente | D53: m2 | E53: 2616.1485 | H53: 4708.8569 | K53: 104.5525 | L53: =+SUM(E53:K53) -> 7429.5579 | M53: 20
A54: ARQUIN37 | B54: 74 | C54: Impermeabilizacion sobre ladrillo | D54: m2 | E54: 2454.0124 | H54: 5543.6425 | K54: 67.525888 | L54: =+SUM(E54:K54) -> 8065.1808 | M54: 30
A55: ARQUIN38 | B55: 75 | C55: ladrillo cerámico 12 x 19 x 33 cm - PORTANTE | D55: m2 | E55: 22250.605 | H55: 11087.285 | K55: 255.78052 | L55: =+SUM(E55:K55) -> 33593.671 | M55: 15
A56: ARQUIN41 | B56: 113 | C56: Impermeabilizacion de azotea con pintura asfaltica / Barrera de vapor | D56: m2 | E56: 1392.6098 | H56: 2017.7205 | K56: 10.930141 | L56: =+SUM(E56:K56) -> 3421.2604 | M56: 80
... A65: ARQUIN50 | B65: 122 | C65: BANDEJA PORTACABLES 200 | D65: ml | E65: 18848.235 | H65: 11167.816 | K65: 0 | L65: =+SUM(E65:K65) -> 30016.05 | M65: 12
A66: ARQUIN51 | B66: 123 | C66: COLUMNA HORMIGÓN RÚSTICO 85 kg/m3 | D66: m3 | L66: =+SUM(E66:K66) -> 0
A67: ARQUIN52 | B67: 124 | C67: COLUMNA HORMIGÓN VISTO | D67: m3 | L67: =+SUM(E67:K67) -> 0
A68: ARQUIN53 | B68: 125 | C68: Viga de hormigon rustico 180 kg/m3 | L68: =+SUM(E68:K68) -> 0
A69: ARQUIN54 | B69: 126 | C69: Viga | L69: =+SUM(E69:K69) -> 0
A70: ARQUIN55 | B70: 127 | C70: Losa de hormigon rustico | L70: =+SUM(E70:K70) -> 0
A71: ARQUIN56 | B71: 128 | C71: Losa | L71: =+SUM(E71:K71) -> 0
A72: ARQUIN57 | B72: 129 | C72: Tabique de hormigon rustico 80 kg/m3 | L72: =+SUM(E72:K72) -> 0
A73: ARQUIN58 | B73: 130 | C73: Tabique de hormigon visto 80 kg/m3 | L73: =+SUM(E73:K73) -> 0
A74: ARQUIN59 | B74: 131 | C74: Escalera de hormigon rustico 75 kg/m3 | L74: =+SUM(E74:K74) -> 0
A75: ARQUIN60 | B75: 132 | C75: Bases asiladas 60 kg/m3 | L75: =+SUM(E75:K75) -> 0
A76: ARQUIN61 | B76: 133 | C76: Vigas de fundacion 60 kg/m3 | L76: =+SUM(E76:K76) -> 0
A77: ARQUIN62 | B77: 134 | C77: Revoque grueso para interiores | D77: m2 | E77: 1553.2761 | H77: 8033.7507 | K77: 172.59343 | L77: =+SUM(E77:K77) -> 9759.6202 | M77: 18
A78: ARQUIN63 | B78: 135 | C78: Revoque fino a la cal | D78: m2 | E78: 1337.9415 | H78: 14946.826 | K78: 460.79036 | L78: =+SUM(E78:K78) -> 16745.558 | M78: 9
A79: ARQUIN64 | B79: 136 | C79: Carpeta cal reforzada (e: 1,5 cm) | D79: m2 | E79: 2755.4985 | H79: 8581.7491 | K79: 243.19327 | L79: =+SUM(E79:K79) -> 11580.441 | M79: 14.5
A80: ARQUIN65 | B80: 137 | C80: Látex interior para paredes (enduido parcial) | D80: m2 | E80: 2880.1573 | H80: 4708.8569 | K80: 104.5525 | L80: =+SUM(E80:K80) -> 7693.5667 | M80: 20
A81: ARQUIN66 | B81: 138 | C81: Pared simple con aislacion de lana de vidrio | L81: =+SUM(E81:K81) -> 0
A82: ARQUIN67 | B82: 139 | C82: Yeso pared | L82: =+SUM(E82:K82) -> 0
A83: ARQUIN68 | B83: 140 | C83: Yeso en cielorraso | L83: =+SUM(E83:K83) -> 0
A84: ARQUIN69 | B84: 141 | C84: Cemento alisado | L84: =+SUM(E84:K84) -> 0
A85: ARQUIN70 | B85: 142 | C85: Revoque Exterior 3 en 1 hasta 3,00 m | L85: =+SUM(E85:K85) -> 0
A86: ARQUIN71 | B86: 143 | C86: REVOQUE 2 EN 1 hasta 3,00 m | L86: =+SUM(E86:K86) -> 0
A87: ARQUIN72 | B87: 144 | C87: REVOQUE 2 EN 1 a mas 3,00 m | L87: =+SUM(E87:K87) -> 0
A88: ARQUIN73 | B88: 145 | C88: Muro retak | L88: =+SUM(E88:K88) -> 0
A89: ARQUIN74 | B89: 146 | C89: Látex interior para paredes (s/enduido) | D89: m2 | E89: 2664.568 | H89: 3767.0855 | K89: 83.641998 | L89: =+SUM(E89:K89) -> 6515.2955 | M89: 25
B90: 147 | C90: BOCA ILUMINACIÓN LOSA (Profunda) | D90: u | E90: 18798.888 | H90: 49666.965 | K90: 1812.1957 | L90: =+SUM(E90:K90) -> 70278.049 | M90: 3.25
B91: 148 | C91: BOCA TOMACORRIENTE ESPECIAL | D91: u | E91: 34095.002 | H91: 49666.965 | K91: 1812.1957 | L91: =+SUM(E91:K91) -> 85574.163 | M91: 3.25
B92: 149 | C92: BOCA VACIA C/CABLE TESTIGO | D92: u | E92: 10558 | H92: 32283.527 | K92: 1177.9272 | L92: =+SUM(E92:K92) -> 44019.454 | M92: 5

Sheet P.MO 06.25
A1: COSTO M.O. | B1: 45809 | F1: Carga Manual
A3: Costo Real (B+N) | B3: Jornal | C3: Mensual | D3: Hora | E3: Dif real / teorico | F3: Mano Jornal | G3: Hora Uocra
A4: ESPECIALIZADO | B4: 94177.138 | C4: 2260251.3 | D4: 11772.142 | E4: 1.1585236 | F4: 59355.621 | G4: 5121.2727 | I4: =+B4/F4 -> 1.5866591
A5: OFICIAL | B5: 84612.513 | C5: 2030700.3 | D5: 10576.564 | E5: 1.1076363 | F5: 51821.351 | G5: 4402.9091 | I5: =+B5/F5 -> 1.6327732
A6: MEDIO OFICIAL | B6: 72132.138 | C6: 1731171.3 | D6: 9016.5173 | E6: 1.0989982 | F6: 43355.923 | G6: 4062.1818 | I6: =+B6/F6 -> 1.6637205
A7: AYUDANTE | B7: 67240.499 | C7: 1613772 | D7: 8405.0624 | E7: 1.1023505 | F7: 40254.783 | G7: 3748.5 | I7: =+B7/F7 -> 1.6703729
A9: SOBRESTANTE | B9: 147568.59 | C9: 3246508.9 | D9: 18446.073 | F9: 2265320.2
A10: JEFE DE OBRA | B10: 214394.06 | C10: 4716669.4 | D10: 26799.258 | F10: 3290107.9
A11: COORD OBRAS | B11: 258581.93 | C11: 5688802.4 | D11: 32322.741 | F11: 4314895.6
A12: CAPATAZ | B12: 161430.42 | C12: 3874330.1 | D12: 20178.803 | F12: 2804682.1 | G12: 5121.2727

Sheet INFO.
C2: USD | F2: DÓLAR MEP
B3: VALOR ESTIMADO REFERENCIA COSTO | F3: =+GGBB!H4 -> 1276 | G3: =+F6/F3 -> 1460381.2
D4: Coef Complej
C5: m2 | D5: 1 | E5: USD/ m2
B6: SUPERFICIE CUBIERTA | C6: =+ROUNDUP(F20,0) -> 1452 | D6: =+C3*D5 -> 0 | E6: =+F32 -> 1005.7722 | F6: =+E6*F3*C6 -> 1.8634464e+09 | G6: Valor estimado precio de venta
B8: Lote | E8: 1 | F8: SS
B9: Pisada | E9: 0.25 | F9: Patios
E10: 0.5 | F10: Balcones y semicubiertos
B11: Superficie | C11: Cubierto | D11: Semicubierto | E11: % | F11: Subtotal
B12: SS | C12: 24 | E12: =+D12*$E$8 -> 0 | F12: =+C12+E12 -> 24
B13: PB | C13: 65 | D13: 137 | E13: =+D13*$E$10 -> 68.5 | F13: =+C13+E13 -> 133.5
B14: PB (patio) | D14: 51.5 | E14: =+D14*$E$9 -> 12.875 | F14: =+C14+E14 -> 12.875
B15: P 1º a 5° | C15: 175 | D15: =11+10.5 -> 21.5 | E15: =+D15*$E$10 -> 10.75 | F15: =+C15+E15 -> 185.75 | G15: 4
C16: =+C15*G15 -> 700 | D16: =+D15*G15 -> 86 | E16: =+E15*G15 -> 43 | F16: =+C16+E16 -> 743
B17: P 6° | C17: 160 | D17: =11+16 -> 27 | E17: =+D17*$E$10 -> 13.5 | F17: =+C17+E17 -> 173.5
B18: P 7° | C18: 111 | D18: =32+16 -> 48 | E18: =+D18*$E$10 -> 24 | F18: =+C18+E18 -> 135
B19: PLANTA TECHOS | C19: 22 | D19: 89 | E19: =+D19*$E$9 -> 22.25 | F19: =+C19+E19 -> 44.25
C20: =SUM(C12:C19) -> 1257 | D20: =SUM(D12:D19) -> 460 | E20: =SUM(E12:E19) -> 194.875 | F20: =SUM(F12:F19) -> 1451.875
H21: usd/m2
B22: OBRA CIVIL | E22: 0.7 | F22: =+'01'!W213 -> 1540618531 | G22: =+F22/F3 -> 1207381.3 | H22: =+G22/C6 -> 831.52982
B23: PROVISIONES | E23: =1-E22 -> 0.3 | F23: =+G23*F22 -> 6.6026508e+08 | G23: =+E23/E22 -> 0.42857143
F24: =+F23+F22 -> 2.2008836e+09
B25: ARQ CLARIN
B26: 45800 | C26: Fecha
B28: (se toma MODELO 6 Vivienda en altura) | C28: m2 | D28: $/ m2
B29: VALOR ESTIMADO REFERENCIA COSTO | C29: =+C6 -> 1452 | D29: 1833379 | F29: =+D29*C29 -> 2662066308 | G29: Valor estimado precio de venta
D30: usd/m2 | F30: =+F29/F3 -> 2086258.9 | G30: USD
D31: =+D29/F3 -> 1436.8174 | F31: =+F30/C29 -> 1436.8174 | G31: usd/m2
F32: =+F31*E22 -> 1005.7722 | G32: usd/m2 sin provisiones

Sheet 01
F1: OK | G1: Listo | V1: DÓLAR BNA | W1: DÓLAR MEP
F2: IN | G2: Estimado | V2: =+GGBB!G4 -> 1280 | W2: =+GGBB!H4 -> 1276
F3: C | G3: Chekear (Inventado)
F4: R | G4: Sin hacer/revisar | V4: 45817
C5: OBRA: EDIFICIO CHIVILCOY 2171 | F5: MATERIAL | I5: M. DE OBRA | N5: MATERIAL | P5: M. DE OBRA | T5: =+GGBB!F61 -> 1.3564677
C6: PRESUPUESTO OBRA CIVIL | T6: 1.1
B7: E | C7: Descripción | D7: U | E7: Cant | F7: Otro | G7: Corralón | H7: Total | I7: Otro | J7: Albañil | K7: Total | L7: EQUIPOS | M7: P.Unit | N7: Otro | O7: Corralón | P7: Otro | Q7: Albañil | R7: EQUIPOS | S7: Total | T7: Subtotal | U7: P unit | V7: Subtotal
A8: 1 | C8: TAREAS PRELIMINARES | T8: =SUM(S9:S17) -> 17207623 | W8: =SUM(V9:V17) -> 23341592 | X8: =+W8/$W$213 -> 0.015150793
A9: 1.01 | B9: OK | C9: Limpieza y preparación del terreno - No cotiza | D9: gl | E9: 0 | H9: =F9+G9 -> 0 | K9: =I9+J9 -> 0 | M9: =H9+K9+L9 -> 0 | N9: =F9*E9 -> 0 | O9: =G9*E9 -> 0 | P9: =I9*E9 -> 0 | Q9: =J9*E9 -> 0 | R9: =+L9*E9 -> 0 | S9: =SUM(N9:R9) -> 0 | U9: =+ROUNDUP(M9*$T$5,0) -> 0 | V9: =+U9*E9 -> 0
A10: 1.02 | B10: OK | C10: Topógrafo - Visita de obra replanteo | D10: un | E10: 4 | F10: =+Tareas!H8 -> 0 | G10: =+Tareas!I8 -> 25000 | H10: =F10+G10 -> 25000 | I10: =+Tareas!Q8 -> 214394.06 | J10: =+Tareas!R8 -> 67240.499 | K10: =I10+J10 -> 281634.56 | L10: =+(H10+K10)*0.015 -> 4599.5184 | M10: =H10+K10+L10 -> 311234.08 | N10: =F10*E10 -> 0 | O10: =G10*E10 -> 100000 | P10: =I10*E10 -> 857576.25 | Q10: =J10*E10 -> 268962 | R10: =+L10*E10 -> 18398.074 | S10: =SUM(N10:R10) -> 1244936.3 | U10: =+ROUNDUP(M10*$T$5,0) -> 422179 | V10: =+U10*E10 -> 1688716
A11: 1.03 | B11: OK | C11: Cartel de Obra - No cotiza | D11: gl | E11: 1 | H11: =F11+G11 -> 0 | K11: =I11+J11 -> 0 | M11: =H11+K11+L11 -> 0 | N11: =F11*E11 -> 0 | O11: =G11*E11 -> 0 | P11: =I11*E11 -> 0 | Q11: =J11*E11 -> 0 | R11: =+L11*E11 -> 0 | S11: =SUM(N11:R11) -> 0 | U11: =+ROUNDUP(M11*$T$5,0) -> 0 | V11: =+U11*E11 -> 0
A12: 1.04 | B12: OK | C12: Cerco de obra perimetral - En chapa C25 + Concertina + Porton corredizo | D12: ml | E12: 10 | F12: =+Tareas!H12 -> 98815.568 | G12: =+Tareas!I12 -> 0 | H12: =F12+G12 -> 98815.568 | I12: =+Tareas!Q12 -> 0 | J12: =+Tareas!R12 -> 111992.57 | K12: =I12+J12 -> 111992.57 | L12: =+(H12+K12)*0.015 -> 3162.1221 | M12: =H12+K12+L12 -> 213970.27 | N12: =F12*E12 -> 988155.68 | O12: =G12*E12 -> 0 | P12: =I12*E12 -> 0 | Q12: =J12*E12 -> 1119925.7 | R12: =+L12*E12 -> 31621.221 | S12: =SUM(N12:R12) -> 2139702.7 | U12: =+ROUNDUP(M12*$T$5,0) -> 290244 | V12: =+U12*E12 -> 2902440
A13: 1.05 | B13: OK | C13: Obrador, pañol y ducha | D13: gl | E13: 1 | F13: =+Tareas!H23 -> 2270625.2 | G13: =+Tareas!I23 -> 300000 | H13: =F13+G13 -> 2570625.2 | I13: =+Tareas!Q23 -> 1000000 | J13: =+Tareas!R23 -> 5023936.4 | K13: =I13+J13 -> 6023936.4 | L13: =+(H13+K13)*0.015 -> 128918.42 | M13: =H13+K13+L13 -> 8723480 | N13: =F13*E13 -> 2270625.2 | O13: =G13*E13 -> 300000 | P13: =I13*E13 -> 1000000 | Q13: =J13*E13 -> 5023936.4 | R13: =+L13*E13 -> 128918.42 | S13: =SUM(N13:R13) -> 8723480 | U13: =+ROUNDUP(M13*$T$5,0) -> 11833120 | V13: =+U13*E13 -> 11833120
A14: 1.06 | B14: OK | C14: Alquiler de baños quimicos y duchas portatiles | D14: mes | E14: 4 | F14: =+Tareas!H47 -> 0 | G14: =+Tareas!I47 -> 0 | H14: =F14+G14 -> 0 | I14: =+Tareas!Q47 -> 260000 | J14: =+Tareas!R47 -> 0 | K14: =I14+J14 -> 260000 | M14: =H14+K14+L14 -> 260000 | N14: =F14*E14 -> 0 | O14: =G14*E14 -> 0 | P14: =I14*E14 -> 1040000 | Q14: =J14*E14 -> 0 | R14: =+L14*E14 -> 0 | S14: =SUM(N14:R14) -> 1040000 | U14: =+ROUNDUP(M14*$T$5,0) -> 352682 | V14: =+U14*E14 -> 1410728
A15: 1.07 | B15: OK | C15: Conexión pilar y luz de obra + Tablero de obra | D15: gl | E15: 1 | F15: =+Tareas!H52 -> 1290000 | G15: =+Tareas!I52 -> 100000 | H15: =F15+G15 -> 1390000 | I15: =+Tareas!Q52 -> 0 | J15: =+Tareas!R52 -> 661285.32 | K15: =I15+J15 -> 661285.32 | L15: =+(H15+K15)*0.015 -> 30769.28 | M15: =H15+K15+L15 -> 2082054.6 | N15: =F15*E15 -> 1290000 | O15: =G15*E15 -> 100000 | P15: =I15*E15 -> 0 | Q15: =J15*E15 -> 661285.32 | R15: =+L15*E15 -> 30769.28 | S15: =SUM(N15:R15) -> 2082054.6 | U15: =+ROUNDUP(M15*$T$5,0) -> 2824240 | V15: =+U15*E15 -> 2824240
A16: 1.08 | B16: OK | C16: Conexión agua de obra, tanque + bomba | D16: gl | E16: 1 | F16: =+Tareas!H59 -> 936000 | G16: =+Tareas!I59 -> 0 | H16: =F16+G16 -> 936000 | I16: =+Tareas!Q59 -> 0 | J16: =+Tareas!R59 -> 536368.95 | K16: =I16+J16 -> 536368.95 | L16: =+(H16+K16)*0.015 -> 22085.534 | M16: =H16+K16+L16 -> 1494454.5 | N16: =F16*E16 -> 936000 | O16: =G16*E16 -> 0 | P16: =I16*E16 -> 0 | Q16: =J16*E16 -> 536368.95 | R16: =+L16*E16 -> 22085.534 | S16: =SUM(N16:R16) -> 1494454.5 | U16: =+ROUNDUP(M16*$T$5,0) -> 2027180 | V16: =+U16*E16 -> 2027180
A17: 1.09 | B17: OK | C17: Tramite luz de obra, certificado luz de obra (2) y medición PAT | D17: gl | E17: 1 | F17: =+Tareas!H69 -> 0 | G17: =+Tareas!I69 -> 0 | H17: =F17+G17 -> 0 | I17: =+Tareas!Q69 -> 482995.31 | J17: =+Tareas!R69 -> 0 | K17: =I17+J17 -> 482995.31 | M17: =H17+K17+L17 -> 482995.31 | N17: =F17*E17 -> 0 | O17: =G17*E17 -> 0 | P17: =I17*E17 -> 482995.31 | Q17: =J17*E17 -> 0 | R17: =+L17*E17 -> 0 | S17: =SUM(N17:R17) -> 482995.31 | U17: =+ROUNDUP(M17*$T$5,0) -> 655168 | V17: =+U17*E17 -> 655168
A18: 2 | C18: MOVIMIENTO DE TIERRA, COMPACTACION Y RELLENO | T18: =SUM(S19:S22) -> 12400628 | W18: =SUM(V19:V22) -> 16821282 | X18: =+W18/$W$213 -> 0.010918525
A19: 2.01 | B19: OK | C19: Retiro de suelo vegetal e: 50 cm, aporte y compactación de tosca e: 40 cm (dos capas de 20 cm) | D19: m2 | E19: =+Exc.!G53 -> 219 | F19: =+Tareas!H74 -> 0 | G19: =+Tareas!I74 -> 0 | H19: =F19+G19 -> 0 | I19: =+Tareas!Q74 -> 25907.444 | J19: =+Tareas!R74 -> 3070.3424 | K19: =I19+J19 -> 28977.787 | M19: =H19+K19+L19 -> 28977.787 | N19: =F19*E19 -> 0 | O19: =G19*E19 -> 0 | P19: =I19*E19 -> 5673730.3 | Q19: =J19*E19 -> 672404.99 | R19: =+L19*E19 -> 0 | S19: =SUM(N19:R19) -> 6346135.3 | U19: =+ROUNDUP(M19*$T$5,0) -> 39308 | V19: =+U19*E19 -> 8608452
A20: 2.02 | B20: OK | C20: Excavación para cámara transformadora | D20: m3 | E20: =+Exc.!I6 -> 100 | F20: =+Tareas!H77 -> 0 | G20: =+Tareas!I77 -> 0 | H20: =F20+G20 -> 0 | I20: =+Tareas!Q77 -> 24440 | J20: =+Tareas!R77 -> 6724.0499 | K20: =I20+J20 -> 31164.05 | L20: =+(H20+K20)*0.015 -> 467.46075 | M20: =H20+K20+L20 -> 31631.511 | N20: =F20*E20 -> 0 | O20: =G20*E20 -> 0 | P20: =I20*E20 -> 2444000 | Q20: =J20*E20 -> 672404.99 | R20: =+L20*E20 -> 46746.075 | S20: =SUM(N20:R20) -> 3163151.1 | U20: =+ROUNDUP(M20*$T$5,0) -> 42908 | V20: =+U20*E20 -> 4290800
A21: 2.03 | B21: OK | C21: Excavación manual para tensores y vigas de fundación | D21: m3 | E21: =+Exc.!I8 -> 43 | H21: =F21+G21 -> 0 | J21: =+'P.MO 06.25'!B7 -> 67240.499 | K21: =I21+J21 -> 67240.499 | M21: =H21+K21+L21 -> 67240.499 | N21: =F21*E21 -> 0 | O21: =G21*E21 -> 0 | P21: =I21*E21 -> 0 | Q21: =J21*E21 -> 2891341.5 | R21: =+L21*E21 -> 0 | S21: =SUM(N21:R21) -> 2891341.5 | U21: =+ROUNDUP(M21*$T$5,0) -> 91210 | V21: =+U21*E21 -> 3922030
A22: 2.04 | B22: OK | C22: Demolición y retiro de fundaciones existentes - No cotiza | D22: gl | E22: 0 | H22: =F22+G22 -> 0 | K22: =I22+J22 -> 0 | M22: =H22+K22+L22 -> 0 | N22: =F22*E22 -> 0 | O22: =G22*E22 -> 0 | P22: =I22*E22 -> 0 | Q22: =J22*E22 -> 0 | R22: =+L22*E22 -> 0 | S22: =SUM(N22:R22) -> 0 | U22: =+ROUNDUP(M22*$T$5,0) -> 0 | V22: =+U22*E22 -> 0
A23: 3 | C23: ESTRUCTURA RESISTENTE | T23: =SUM(S24:S45) -> 3.3368577e+08 | W23: =SUM(V24:V45) -> 452634152 | X23: =+W23/$W$213 -> 0.29380028 | Y23: M.O HA | Z23: =+SUM(P24:R41,Q19:R21)-P25 -> 1.3371847e+08
A24: 3.01 | B24: OK | C24: Hormigón de limpieza - e: 10 cm | D24: m3 | E24: 3 | F24: =+Tareas!H83 -> 120430 | G24: =+Tareas!I83 -> 0 | H24: =F24+G24 -> 120430 | I24: =+Tareas!Q83 -> 0 | J24: =+Tareas!R83 -> 155041.22 | K24: =I24+J24 -> 155041.22 | L24: =+(H24+K24)*0.015 -> 4132.0683 | M24: =H24+K24+L24 -> 279603.29 | N24: =F24*E24 -> 361290 | O24: =G24*E24 -> 0 | P24: =I24*E24 -> 0 | Q24: =J24*E24 -> 465123.66 | R24: =+L24*E24 -> 12396.205 | S24: =SUM(N24:R24) -> 838809.86 | U24: =+ROUNDUP(M24*$T$5,0) -> 379273 | V24: =+U24*E24 -> 1137819 | Y24: S/cargas | Z24: =+Z23/AA24 -> 83574041 | AA24: 1.6
A25: 3.02 | B25: OK | C25: Micropilotes Ø 20 cm | D25: gl | E25: 1 | F25: =+Tareas!H88 -> 11090041 | G25: =+Tareas!I88 -> 0 | H25: =F25+G25 -> 11090041 | I25: =+Tareas!Q88 -> 34350000 | J25: =+Tareas!R88 -> 2460301.5 | K25: =I25+J25 -> 36810301 | L25: =+(H25+K25)*0.015 -> 718505.14 | M25: =H25+K25+L25 -> 48618848 | N25: =F25*E25 -> 11090041 | O25: =G25*E25 -> 0 | P25: =I25*E25 -> 34350000 | Q25: =J25*E25 -> 2460301.5 | R25: =+L25*E25 -> 718505.14 | S25: =SUM(N25:R25) -> 48618848 | U25: =+ROUNDUP(M25*$T$5,0) -> 65949899 | V25: =+U25*E25 -> 65949899 | Y25: Meses | Z25: =+Z24/Z26 -> 8.1451198
A26: 3.03 | B26: OK | C26: Platea - H30 (110 kg/m3 de hierro) | D26: m3 | E26: =+'H°A° '!O4 -> 7 | F26: =+'H°A° '!F47 -> 357146.17 | H26: =F26+G26 -> 357146.17 | I26: =+'MO HA AING'!C5 -> 222927.96 | K26: =I26+J26 -> 222927.96 | L26: =+(H26+K26)*0.015 -> 8701.1119 | M26: =H26+K26+L26 -> 588775.24 | N26: =F26*E26 -> 2500023.2 | O26: =G26*E26 -> 0 | P26: =I26*E26 -> 1560495.7 | Q26: =J26*E26 -> 0 | R26: =+L26*E26 -> 60907.784 | S26: =SUM(N26:R26) -> 4121426.7 | U26: =+ROUNDUP(M26*$T$5,0) -> 798655 | V26: =+U26*E26 -> 5590585 | Y26: Cuadrilla (9) | Z26: =9*'P.MO 06.25'!F5*22 -> 10260628
A27: 3.04 | B27: OK | C27: Zapata corrida tabique - H30 (180 kg/m3 de hierro) | D27: m3 | E27: =+'H°A° '!O5 -> 4 | F27: =+'H°A° '!F48 -> 537813.29 | H27: =F27+G27 -> 537813.29 | I27: =+'MO HA AING'!C6 -> 323084 | K27: =I27+J27 -> 323084 | L27: =+(H27+K27)*0.015 -> 12913.459 | M27: =H27+K27+L27 -> 873810.75 | N27: =F27*E27 -> 2151253.2 | O27: =G27*E27 -> 0 | P27: =I27*E27 -> 1292336 | Q27: =J27*E27 -> 0 | R27: =+L27*E27 -> 51653.837 | S27: =SUM(N27:R27) -> 3495243 | U27: =+ROUNDUP(M27*$T$5,0) -> 1185297 | V27: =+U27*E27 -> 4741188
A28: 3.05 | B28: OK | C28: Bases aisladas - H30 (110 kg/m3 de hierro) | D28: m3 | E28: =+'H°A° '!O6 -> 2 | F28: =+'H°A° '!F49 -> 357146.17 | H28: =F28+G28 -> 357146.17 | I28: =+'MO HA AING'!C5 -> 222927.96 | K28: =I28+J28 -> 222927.96 | L28: =+(H28+K28)*0.015 -> 8701.1119 | M28: =H28+K28+L28 -> 588775.24 | N28: =F28*E28 -> 714292.34 | O28: =G28*E28 -> 0 | P28: =I28*E28 -> 445855.92 | Q28: =J28*E28 -> 0 | R28: =+L28*E28 -> 17402.224 | S28: =SUM(N28:R28) -> 1177550.5 | U28: =+ROUNDUP(M28*$T$5,0) -> 798655 | V28: =+U28*E28 -> 1597310
A29: 3.06 | B29: OK | C29: Cabezales - H30 (130 kg/m3 de hierro) | D29: m3 | E29: =+'H°A° '!O7 -> 11 | F29: =+'H°A° '!F50 -> 392586.17 | H29: =F29+G29 -> 392586.17 | I29: =+'MO HA AING'!C5 -> 222927.96 | K29: =I29+J29 -> 222927.96 | L29: =+(H29+K29)*0.015 -> 9232.7119 | M29: =H29+K29+L29 -> 624746.84 | N29: =F29*E29 -> 4318447.9 | O29: =G29*E29 -> 0 | P29: =I29*E29 -> 2452207.6 | Q29: =J29*E29 -> 0 | R29: =+L29*E29 -> 101559.83 | S29: =SUM(N29:R29) -> 6872215.3 | U29: =+ROUNDUP(M29*$T$5,0) -> 847449 | V29: =+U29*E29 -> 9321939
A30: 3.07 | B30: OK | C30: Viga de fundación - H30 (180 kg/m3 de hierro) | D30: m3 | E30: =+'H°A° '!O8 -> 9 | F30: =+'H°A° '!F51 -> 537813.29 | H30: =F30+G30 -> 537813.29 | I30: =+'MO HA AING'!C6 -> 323084 | K30: =I30+J30 -> 323084 | L30: =+(H30+K30)*0.015 -> 12913.459 | M30: =H30+K30+L30 -> 873810.75 | N30: =F30*E30 -> 4840319.6 | O30: =G30*E30 -> 0 | P30: =I30*E30 -> 2907756 | Q30: =J30*E30 -> 0 | R30: =+L30*E30 -> 116221.13 | S30: =SUM(N30:R30) -> 7864296.7 | U30: =+ROUNDUP(M30*$T$5,0) -> 1185297 | V30: =+U30*E30 -> 10667673
A31: 3.08 | B31: OK | C31: Tabique submuración - H30 (90 kg/m3 de hierro) | D31: m3 | E31: =+'H°A° '!O9 -> 9 | F31: =+'H°A° '!F52 -> 394401.89 | H31: =F31+G31 -> 394401.89 | I31: =+'MO HA AING'!D72 -> 392678.73 | K31: =I31+J31 -> 392678.73 | L31: =+(H31+K31)*0.015 -> 11806.209 | M31: =H31+K31+L31 -> 798886.83 | N31: =F31*E31 -> 3549617 | O31: =G31*E31 -> 0 | P31: =I31*E31 -> 3534108.6 | Q31: =J31*E31 -> 0 | R31: =+L31*E31 -> 106255.88 | S31: =SUM(N31:R31) -> 7189981.5 | U31: =+ROUNDUP(M31*$T$5,0) -> 1083665 | V31: =+U31*E31 -> 9752985 | Y31: $ x m3 | Z31: =+Z24/AA31 -> 284265.44 | AA31: =+SUM(E31:E40) -> 294
A32: 3.09 | B32: OK | C32: Puntales de compresión/codales - H30 (120 kg/m3) | D32: m3 | E32: 1 | F32: =+'H°A° '!F53 -> 542036.05 | H32: =F32+G32 -> 542036.05 | I32: =+'MO HA AING'!D47 -> 362209.61 | K32: =I32+J32 -> 362209.61 | L32: =+(H32+K32)*0.015 -> 13563.685 | M32: =H32+K32+L32 -> 917809.34 | N32: =F32*E32 -> 542036.05 | O32: =G32*E32 -> 0 | P32: =I32*E32 -> 362209.61 | Q32: =J32*E32 -> 0 | R32: =+L32*E32 -> 13563.685 | S32: =SUM(N32:R32) -> 917809.34 | U32: =+ROUNDUP(M32*$T$5,0) -> 1244979 | V32: =+U32*E32 -> 1244979
A33: 3.1 | B33: OK | C33: Columna - H30 (240 kg/m3 de hierro) | D33: m3 | E33: =+'H°A° '!O12 -> 32 | F33: =+'H°A° '!F55 -> 648356.05 | H33: =F33+G33 -> 648356.05 | I33: =+'MO HA AING'!D47 -> 362209.61 | K33: =I33+J33 -> 362209.61 | L33: =+(H33+K33)*0.015 -> 15158.485 | M33: =H33+K33+L33 -> 1025724.1 | N33: =F33*E33 -> 20747394 | O33: =G33*E33 -> 0 | P33: =I33*E33 -> 11590707 | Q33: =J33*E33 -> 0 | R33: =+L33*E33 -> 485071.52 | S33: =SUM(N33:R33) -> 32823173 | U33: =+ROUNDUP(M33*$T$5,0) -> 1391362 | V33: =+U33*E33 -> 44523584
A34: 3.11 | B34: OK | C34: Tabiques - H30 (120 kg/m3 de hierro) | D34: m3 | E34: =+'H°A° '!O13 -> 30 | F34: =+'H°A° '!F56 -> 447561.89 | H34: =F34+G34 -> 447561.89 | I34: =+'MO HA AING'!D72 -> 392678.73 | K34: =I34+J34 -> 392678.73 | L34: =+(H34+K34)*0.015 -> 12603.609 | M34: =H34+K34+L34 -> 852844.23 | N34: =F34*E34 -> 13426857 | O34: =G34*E34 -> 0 | P34: =I34*E34 -> 11780362 | Q34: =J34*E34 -> 0 | R34: =+L34*E34 -> 378108.28 | S34: =SUM(N34:R34) -> 25585327 | U34: =+ROUNDUP(M34*$T$5,0) -> 1156856 | V34: =+U34*E34 -> 34705680
A35: 3.12 | B35: OK | C35: Viga H° Visto - H30 (120 kg/m3 de hierro) | D35: m3 | E35: =+'H°A° '!O14 -> 7 | F35: =+'H°A° '!F57 -> 466389.3 | H35: =F35+G35 -> 466389.3 | I35: =+'MO HA AING'!D99 -> 629584.36 | J35: =+I35*0.25 -> 157396.09 | K35: =I35+J35 -> 786980.44 | L35: =+(H35+K35)*0.015 -> 18800.546 | M35: =H35+K35+L35 -> 1272170.3 | N35: =F35*E35 -> 3264725.1 | O35: =G35*E35 -> 0 | P35: =I35*E35 -> 4407090.5 | Q35: =J35*E35 -> 1101772.6 | R35: =+L35*E35 -> 131603.82 | S35: =SUM(N35:R35) -> 8905192 | U35: =+ROUNDUP(M35*$T$5,0) -> 1725658 | V35: =+U35*E35 -> 12079606
A36: 3.13 | B36: OK | C36: Viga apeo s/PB - H30 (180 kg/m3 de hierro) | D36: m3 | E36: =+'H°A° '!O15 -> 12 | F36: =+'H°A° '!F58 -> 578369.51 | H36: =F36+G36 -> 578369.51 | I36: =+'MO HA AING'!D99 -> 629584.36 | J36: =+I36*0.25 -> 157396.09 | K36: =I36+J36 -> 786980.44 | L36: =+(H36+K36)*0.015 -> 20480.249 | M36: =H36+K36+L36 -> 1385830.2 | N36: =F36*E36 -> 6940434.1 | O36: =G36*E36 -> 0 | P36: =I36*E36 -> 7555012.3 | Q36: =J36*E36 -> 1888753.1 | R36: =+L36*E36 -> 245762.99 | S36: =SUM(N36:R36) -> 16629962 | U36: =+ROUNDUP(M36*$T$5,0) -> 1879834 | V36: =+U36*E36 -> 22558008
A37: 3.14 | B37: OK | C37: Viga - H30 (120 kg/m3 de hierro) | D37: m3 | E37: =+'H°A° '!O16 -> 41 | F37: =+'H°A° '!F59 -> 472049.51 | H37: =F37+G37 -> 472049.51 | I37: =+'MO HA AING'!D99 -> 629584.36 | K37: =I37+J37 -> 629584.36 | L37: =+(H37+K37)*0.015 -> 16524.508 | M37: =H37+K37+L37 -> 1118158.4 | N37: =F37*E37 -> 19354030 | O37: =G37*E37 -> 0 | P37: =I37*E37 -> 25812959 | Q37: =J37*E37 -> 0 | R37: =+L37*E37 -> 677504.83 | S37: =SUM(N37:R37) -> 45844493 | U37: =+ROUNDUP(M37*$T$5,0) -> 1516746 | V37: =+U37*E37 -> 62186586
A38: 3.15 | B38: OK | C38: Losa - H30 (95 kg/m3 de hierro) | D38: m3 | E38: =+'H°A° '!O17 -> 135 | F38: =+'H°A° '!F60 -> 361563.22 | H38: =F38+G38 -> 361563.22 | I38: =+'MO HA AING'!D123 -> 253632.45 | K38: =I38+J38 -> 253632.45 | L38: =+(H38+K38)*0.015 -> 9227.9351 | M38: =H38+K38+L38 -> 624423.61 | N38: =F38*E38 -> 48811035 | O38: =G38*E38 -> 0 | P38: =I38*E38 -> 34240381 | Q38: =J38*E38 -> 0 | R38: =+L38*E38 -> 1245771.2 | S38: =SUM(N38:R38) -> 84297187 | U38: =+ROUNDUP(M38*$T$5,0) -> 847011 | V38: =+U38*E38 -> 114346485
A39: 3.16 | B39: OK | C39: Losa H° Visto - H30 (95 kg/m3 de hierro) | D39: m3 | E39: =+'H°A° '!O18 -> 13 | F39: =+'H°A° '!F61 -> 367994.55 | H39: =F39+G39 -> 367994.55 | I39: =+'MO HA AING'!D123 -> 253632.45 | J39: =+I39*0.25 -> 63408.113 | K39: =I39+J39 -> 317040.56 | L39: =+(H39+K39)*0.015 -> 10275.527 | M39: =H39+K39+L39 -> 695310.64 | N39: =F39*E39 -> 4783929.2 | O39: =G39*E39 -> 0 | P39: =I39*E39 -> 3297221.9 | Q39: =J39*E39 -> 824305.46 | R39: =+L39*E39 -> 133581.85 | S39: =SUM(N39:R39) -> 9039038.3 | U39: =+ROUNDUP(M39*$T$5,0) -> 943167 | V39: =+U39*E39 -> 12261171
A40: 3.17 | B40: OK | C40: Escalera - H30 (105 kg/m3) | D40: m3 | E40: =+'H°A° '!O19 -> 14 | F40: =+'H°A° '!F62 -> 404870.23 | H40: =F40+G40 -> 404870.23 | I40: =+'MO HA AING'!D148 -> 370454.15 | K40: =I40+J40 -> 370454.15 | L40: =+(H40+K40)*0.015 -> 11629.866 | M40: =H40+K40+L40 -> 786954.25 | N40: =F40*E40 -> 5668183.3 | O40: =G40*E40 -> 0 | P40: =I40*E40 -> 5186358.1 | Q40: =J40*E40 -> 0 | R40: =+L40*E40 -> 162818.12 | S40: =SUM(N40:R40) -> 11017359 | U40: =+ROUNDUP(M40*$T$5,0) -> 1067479 | V40: =+U40*E40 -> 14944706
A41: 3.18 | B41: OK | C41: Viga alero - H30 (120 kg/m3 de hierro) | D41: m3 | E41: =+'H°A° '!O20 -> 2 | F41: =+'H°A° '!F63 -> 466389.3 | H41: =F41+G41 -> 466389.3 | I41: =+'MO HA AING'!D99 -> 629584.36 | J41: =+I41*0.25 -> 157396.09 | K41: =I41+J41 -> 786980.44 | L41: =+(H41+K41)*0.015 -> 18800.546 | M41: =H41+K41+L41 -> 1272170.3 | N41: =F41*E41 -> 932778.6 | O41: =G41*E41 -> 0 | P41: =I41*E41 -> 1259168.7 | Q41: =J41*E41 -> 314792.18 | R41: =+L41*E41 -> 37601.092 | S41: =SUM(N41:R41) -> 2544340.6 | U41: =+ROUNDUP(M41*$T$5,0) -> 1725658 | V41: =+U41*E41 -> 3451316
A42: 3.19 | B42: OK | C42: Sistema de apuntalamiento y reapuntalamiento | D42: gl | E42: 1 | H42: =F42+G42 -> 0 | K42: =I42+J42 -> 0 | L42: =+'ENCOFRADO '!G151 -> 10584988 | M42: =H42+K42+L42 -> 10584988 | N42: =F42*E42 -> 0 | O42: =G42*E42 -> 0 | P42: =I42*E42 -> 0 | Q42: =J42*E42 -> 0 | R42: =+L42*E42 -> 10584988 | S42: =SUM(N42:R42) -> 10584988 | U42: =+ROUNDUP(M42*$T$5,0) -> 14358195 | V42: =+U42*E42 -> 14358195
A43: 3.2 | B43: OK | C43: Ensayos de Hormigon por etapas de hormigonado | D43: u | E43: =+'H°A° '!S43 -> 13 | H43: =F43+G43 -> 0 | I43: =+'H°A° '!S44 -> 246942.15 | K43: =I43+J43 -> 246942.15 | M43: =H43+K43+L43 -> 246942.15 | N43: =F43*E43 -> 0 | O43: =G43*E43 -> 0 | P43: =I43*E43 -> 3210247.9 | Q43: =J43*E43 -> 0 | R43: =+L43*E43 -> 0 | S43: =SUM(N43:R43) -> 3210247.9 | U43: =+ROUNDUP(M43*$T$5,0) -> 334970 | V43: =+U43*E43 -> 4354610
A44: 3.21 | B44: OK | C44: Permiso de estacionamiento de bomba de hormigón a contramano | D44: gl | E44: =+GGBB!R12 -> 3 | F44: 55000 | H44: =F44+G44 -> 55000 | K44: =I44+J44 -> 0 | M44: =H44+K44+L44 -> 55000 | N44: =F44*E44 -> 165000 | O44: =G44*E44 -> 0 | P44: =I44*E44 -> 0 | Q44: =J44*E44 -> 0 | R44: =+L44*E44 -> 0 | S44: =SUM(N44:R44) -> 165000 | U44: =+ROUNDUP(M44*$T$5,0) -> 74606 | V44: =+U44*E44 -> 223818
A45: 3.22 | B45: OK | C45: Picado de medianeras para columnas y vigas - Cotizado solo para PB, 1P, NO contempla picado en CT | D45: m2 | E45: =+Computo!H49 -> 65 | F45: =+Tareas!H96 -> 4615.3846 | G45: =+Tareas!I96 -> 4615.3846 | H45: =F45+G45 -> 9230.7692 | I45: =+Tareas!Q96 -> 0 | J45: =+Tareas!R96 -> 20224.016 | K45: =I45+J45 -> 20224.016 | L45: =+(H45+K45)*0.015 -> 441.82178 | M45: =H45+K45+L45 -> 29896.607 | N45: =F45*E45 -> 300000 | O45: =G45*E45 -> 300000 | P45: =I45*E45 -> 0 | Q45: =J45*E45 -> 1314561.1 | R45: =+L45*E45 -> 28718.416 | S45: =SUM(N45:R45) -> 1943279.5 | U45: =+ROUNDUP(M45*$T$5,0) -> 40554 | V45: =+U45*E45 -> 2636010
A46: 4 | C46: MAMPOSTERÍA | T46: =SUM(S47:S52) -> 59733584 | W46: =SUM(V47:V52) -> 81027653 | X46: =+W46/$W$213 -> 0.052594235
A47: 4.01 | B47: OK | C47: Muro tipo 1 (interiores, divisorio de locales) e: 10 cm - Ladrillo hueco 08 x 18 x 33 | D47: m2 | E47: =+MAMP.!L218 -> 437 | G47: =+'APU 06.25'!E13 -> 10053.788 | H47: =F47+G47 -> 10053.788 | J47: =+'APU 06.25'!H13 -> 10761.176 | K47: =I47+J47 -> 10761.176 | L47: =+'APU 06.25'!K13 -> 255.78052 | M47: =H47+K47+L47 -> 21070.744 | N47: =F47*E47 -> 0 | O47: =G47*E47 -> 4393505.4 | P47: =I47*E47 -> 0 | Q47: =J47*E47 -> 4702633.8 | R47: =+L47*E47 -> 111776.09 | S47: =SUM(N47:R47) -> 9207915.3 | U47: =+ROUNDUP(M47*$T$5,0) -> 28582 | V47: =+U47*E47 -> 12490334
A48: 4.02 | B48: OK | C48: Muro tipo 2 y 3 (medianera, caja de escaleras y ascensor) e: 15 cm - Ladrillo hueco portante 12 x 19 x 33 | D48: m2 | E48: =+MAMP.!N218 -> 723 | G48: =+'APU 06.25'!E17 -> 18207.26 | H48: =F48+G48 -> 18207.26 | J48: =+'APU 06.25'!H17 -> 10761.176 | K48: =I48+J48 -> 10761.176 | L48: =+'APU 06.25'!K17 -> 255.78052 | M48: =H48+K48+L48 -> 29224.217 | N48: =F48*E48 -> 0 | O48: =G48*E48 -> 13163849 | P48: =I48*E48 -> 0 | Q48: =J48*E48 -> 7780330.1 | R48: =+L48*E48 -> 184929.32 | S48: =SUM(N48:R48) -> 21129109 | U48: =+ROUNDUP(M48*$T$5,0) -> 39642 | V48: =+U48*E48 -> 28661166
A49: 4.03 | B49: OK | C49: Muro tipo 4 (divisorio de unidades y fachadas) e: 15 cm - Ladrillo hueco 12 x 18 x 33 | D49: m2 | E49: =+MAMP.!M218 -> 1008 | G49: =+'APU 06.25'!E14 -> 12465.038 | H49: =F49+G49 -> 12465.038 | J49: =+'APU 06.25'!H14 -> 10761.176 | K49: =I49+J49 -> 10761.176 | L49: =+'APU 06.25'!K14 -> 255.78052 | M49: =H49+K49+L49 -> 23481.994 | N49: =F49*E49 -> 0 | O49: =G49*E49 -> 12564758 | P49: =I49*E49 -> 0 | Q49: =J49*E49 -> 10847265 | R49: =+L49*E49 -> 257826.77 | S49: =SUM(N49:R49) -> 23669850 | U49: =+ROUNDUP(M49*$T$5,0) -> 31853 | V49: =+U49*E49 -> 32107824
A50: 4.04 | B50: OK | C50: Enchape medianeras existentes - Contemplamos picado zonas sueltas y enchape con ladrillo comun para PB y 1° | D50: m2 | E50: =+MAMP.!O218 -> 199 | G50: =+'APU 06.25'!E17/3 -> 6069.0868 | H50: =F50+G50 -> 6069.0868 | J50: =+'APU 06.25'!H17/2 -> 5380.5879 | K50: =I50+J50 -> 5380.5879 | L50: =+'APU 06.25'!K13 -> 255.78052 | M50: =H50+K50+L50 -> 11705.455 | N50: =F50*E50 -> 0 | O50: =G50*E50 -> 1207748.3 | P50: =I50*E50 -> 0 | Q50: =J50*E50 -> 1070737 | R50: =+L50*E50 -> 50900.324 | S50: =SUM(N50:R50) -> 2329385.6 | U50: =+ROUNDUP(M50*$T$5,0) -> 15879 | V50: =+U50*E50 -> 3159921
A51: 4.05 | B51: IN | C51: Muro de tabique seco ignifugo | D51: m2 | E51: =+MAMP.!Q218 -> 34 | F51: =+'APU 06.25'!E46 -> 28944.105 | H51: =F51+G51 -> 28944.105 | I51: =+'APU 06.25'!H46 -> 27718.213 | K51: =I51+J51 -> 27718.213 | L51: =+'APU 06.25'!K46 -> 441.15834 | M51: =H51+K51+L51 -> 57103.476 | N51: =F51*E51 -> 984099.57 | O51: =G51*E51 -> 0 | P51: =I51*E51 -> 942419.23 | Q51: =J51*E51 -> 0 | R51: =+L51*E51 -> 14999.384 | S51: =SUM(N51:R51) -> 1941518.2 | U51: =+ROUNDUP(M51*$T$5,0) -> 77460 | V51: =+U51*E51 -> 2633640
A52: 4.06 | B52: OK | C52: Vigas de encadenado - En muros de PB, incl. excavación y armado | D52: ml | E52: =+Computo!C13 -> 24 | F52: =+Tareas!H101 -> 23405.012 | G52: =+Tareas!I101 -> 0 | H52: =F52+G52 -> 23405.012 | I52: =+Tareas!Q101 -> 0 | J52: =+Tareas!R101 -> 36357.144 | K52: =I52+J52 -> 36357.144 | L52: =(H52+K52)*0.015 -> 896.43233 | M52: =H52+K52+L52 -> 60658.588 | N52: =F52*E52 -> 561720.28 | O52: =G52*E52 -> 0 | P52: =I52*E52 -> 0 | Q52: =J52*E52 -> 872571.45 | R52: =+L52*E52 -> 21514.376 | S52: =SUM(N52:R52) -> 1455806.1 | U52: =+ROUNDUP(M52*$T$5,0) -> 82282 | V52: =+U52*E52 -> 1974768
A53: 5 | C53: AISLACIONES | T53: =SUM(S54:S59) -> 12211793 | W53: =SUM(V54:V59) -> 16565561 | X53: =+W53/$W$213 -> 0.010752539
A54: 5.01 | B54: OK | C54: Aislación hidrófuga horizontal (baños) - Inc. membrana geotextil y 35% en concepto de babetas | D54: m2 | E54: =+Locales!AD100 -> 79 | F54: =+G54*0.35 -> 3050.8865 | G54: =+'APU 06.25'!E50 -> 8716.8187 | H54: =F54+G54 -> 11767.705 | I54: =+J54*0.35 -> 4471.4668 | J54: =+SUBCONTRATOS!D75 -> 12775.619 | K54: =I54+J54 -> 17247.086 | L54: =+'APU 06.25'!K50 -> 34.976452 | M54: =H54+K54+L54 -> 29049.768 | N54: =F54*E54 -> 241020.04 | O54: =G54*E54 -> 688628.68 | P54: =I54*E54 -> 353245.87 | Q54: =J54*E54 -> 1009273.9 | R54: =+L54*E54 -> 2763.1397 | S54: =SUM(N54:R54) -> 2294931.7 | U54: =+ROUNDUP(M54*$T$5,0) -> 39406 | V54: =+U54*E54 -> 3113074
A55: 5.02 | B55: OK | C55: Cajón hidrófugo - Muros de PB | D55: ml | E55: =+MAMP.!U41 -> 113 | G55: =+'APU 06.25'!E21 -> 827.27861 | H55: =F55+G55 -> 827.27861 | J55: =+'APU 06.25'!H21 -> 4324.0478 | K55: =I55+J55 -> 4324.0478 | L55: =+'APU 06.25'!K21 -> 137.02528 | M55: =H55+K55+L55 -> 5288.3517 | N55: =F55*E55 -> 0 | O55: =G55*E55 -> 93482.483 | P55: =I55*E55 -> 0 | Q55: =J55*E55 -> 488617.4 | R55: =+L55*E55 -> 15483.857 | S55: =SUM(N55:R55) -> 597583.74 | U55: =+ROUNDUP(M55*$T$5,0) -> 7174 | V55: =+U55*E55 -> 810662
A56: 5.03 | B56: OK | C56: Azotado hidrófugo - Sobre contrapiso en vereda y PB | D56: m2 | E56: =+Locales!AF100 -> 207 | G56: =+'APU 06.25'!E21 -> 827.27861 | H56: =F56+G56 -> 827.27861 | J56: =+'APU 06.25'!H21 -> 4324.0478 | K56: =I56+J56 -> 4324.0478 | L56: =+'APU 06.25'!K21 -> 137.02528 | M56: =H56+K56+L56 -> 5288.3517 | N56: =F56*E56 -> 0 | O56: =G56*E56 -> 171246.67 | P56: =I56*E56 -> 0 | Q56: =J56*E56 -> 895077.89 | R56: =+L56*E56 -> 28364.233 | S56: =SUM(N56:R56) -> 1094688.8 | U56: =+ROUNDUP(M56*$T$5,0) -> 7174 | V56: =+U56*E56 -> 1485018
A57: 5.04 | B57: OK | C57: Aislación térmica en terrazas, eps e:2,00 cm | D57: m2 | E57: =+Locales!AH100 -> 165 | G57: =+Cotizaciones!D52 -> 3538.08 | H57: =F57+G57 -> 3538.08 | K57: =I57+J57 -> 0 | M57: =H57+K57+L57 -> 3538.08 | N57: =F57*E57 -> 0 | O57: =G57*E57 -> 583783.2 | P57: =I57*E57 -> 0 | Q57: =J57*E57 -> 0 | R57: =+L57*E57 -> 0 | S57: =SUM(N57:R57) -> 583783.2 | U57: =+ROUNDUP(M57*$T$5,0) -> 4800 | V57: =+U57*E57 -> 792000
A58: 5.05 | B58: OK | C58: Barrera de vapor | D58: m2 | E58: =+Locales!AG100 -> 165 | G58: =+'APU 06.25'!E56 -> 1392.6098 | H58: =F58+G58 -> 1392.6098 | J58: =+'APU 06.25'!H56 -> 2017.7205 | K58: =I58+J58 -> 2017.7205 | L58: =+'APU 06.25'!K56 -> 10.930141 | M58: =H58+K58+L58 -> 3421.2604 | N58: =F58*E58 -> 0 | O58: =G58*E58 -> 229780.61 | P58: =I58*E58 -> 0 | Q58: =J58*E58 -> 332923.88 | R58: =+L58*E58 -> 1803.4733 | S58: =SUM(N58:R58) -> 564507.96 | U58: =+ROUNDUP(M58*$T$5,0) -> 4641 | V58: =+U58*E58 -> 765765
A59: 5.06 | B59: OK | C59: Membrana asfaltica geotextil 4mm - Balcones y azotea - Inc. 20% en concepto de babetas | D59: m2 | E59: =+Locales!AI100 -> 274 | F59: =+G59*0.2 -> 1743.3637 | G59: =+'APU 06.25'!E50 -> 8716.8187 | H59: =F59+G59 -> 10460.182 | I59: =+J59*0.2 -> 2555.1239 | J59: =+SUBCONTRATOS!D75 -> 12775.619 | K59: =I59+J59 -> 15330.743 | L59: =+'APU 06.25'!K50 -> 34.976452 | M59: =H59+K59+L59 -> 25825.902 | N59: =F59*E59 -> 477681.67 | O59: =G59*E59 -> 2388408.3 | P59: =I59*E59 -> 700103.94 | Q59: =J59*E59 -> 3500519.7 | R59: =+L59*E59 -> 9583.5479 | S59: =SUM(N59:R59) -> 7076297.2 | U59: =+ROUNDUP(M59*$T$5,0) -> 35033 | V59: =+U59*E59 -> 9599042
A60: 6 | C60: CUBIERTAS | T60: =SUM(S61:S61) -> 1090677.6 | W60: =SUM(V61:V61) -> 1479500 | X60: =+W60/$W$213 -> 0.00096032858
A61: 6.01 | B61: OK | C61: Babeta de chapa galvanizada en medianeras | D61: ml | E61: =25+9.5+9.5 -> 44 | F61: =+Tareas!H117 -> 16294.998 | G61: =+Tareas!I117 -> 0 | H61: =F61+G61 -> 16294.998 | I61: =+Tareas!Q117 -> 0 | J61: =+Tareas!R117 -> 8126.8023 | K61: =I61+J61 -> 8126.8023 | L61: =+(H61+K61)*0.015 -> 366.327 | M61: =H61+K61+L61 -> 24788.127 | N61: =F61*E61 -> 716979.9 | O61: =G61*E61 -> 0 | P61: =I61*E61 -> 0 | Q61: =J61*E61 -> 357579.3 | R61: =+L61*E61 -> 16118.388 | S61: =SUM(N61:R61) -> 1090677.6 | U61: =+ROUNDUP(M61*$T$5,0) -> 33625 | V61: =+U61*E61 -> 1479500
A62: 7 | C62: REVOQUES | T62: =SUM(S63:S70) -> 1.1177101e+08 | W62: =SUM(V63:V70) -> 151616626 | X62: =+W62/$W$213 -> 0.098412828
A63: 7.01 | B63: OK | C63: Revoque Grueso Impermeable Exterior | D63: m2 | E63: =+'Rev.'!J54 -> 663 | G63: =+'APU 06.25'!E23 -> 4061.1651 | H63: =F63+G63 -> 4061.1651 | J63: =+'APU 06.25'!H23 -> 11697.516 | K63: =I63+J63 -> 11697.516 | L63: =+'APU 06.25'!K23 -> 333.62677 | M63: =H63+K63+L63 -> 16092.308 | N63: =F63*E63 -> 0 | O63: =G63*E63 -> 2692552.5 | P63: =I63*E63 -> 0 | Q63: =J63*E63 -> 7755453.3 | R63: =+L63*E63 -> 221194.55 | S63: =SUM(N63:R63) -> 10669200 | U63: =+ROUNDUP(M63*$T$5,0) -> 21829 | V63: =+U63*E63 -> 14472627
A64: 7.02 | B64: OK | C64: Revoque Grueso Impermeable Exterior a mas de 3m - Medianero y fachadas | D64: m2 | E64: =+'Rev.'!J67 -> 1164 | G64: =+'APU 06.25'!E24 -> 4061.1651 | H64: =F64+G64 -> 4061.1651 | J64: =+'APU 06.25'!H24 -> 16815.18 | K64: =I64+J64 -> 16815.18 | L64: =+'APU 06.25'!K24 -> 863.36281 | M64: =H64+K64+L64 -> 21739.708 | N64: =F64*E64 -> 0 | O64: =G64*E64 -> 4727196.2 | P64: =I64*E64 -> 0 | Q64: =J64*E64 -> 19572869 | R64: =+L64*E64 -> 1004954.3 | S64: =SUM(N64:R64) -> 25305020 | U64: =+ROUNDUP(M64*$T$5,0) -> 29490 | V64: =+U64*E64 -> 34326360
A65: 7.03 | B65: OK | C65: Buña en revoque - Estimados ml en medianeras | D65: ml | E65: =+'Rev.'!J71 -> 500 | H65: =F65+G65 -> 0 | I65: =+SUBCONTRATOS!D36 -> 11122.339 | K65: =I65+J65 -> 11122.339 | M65: =H65+K65+L65 -> 11122.339 | N65: =F65*E65 -> 0 | O65: =G65*E65 -> 0 | P65: =I65*E65 -> 5561169.6 | Q65: =J65*E65 -> 0 | R65: =+L65*E65 -> 0 | S65: =SUM(N65:R65) -> 5561169.6 | U65: =+ROUNDUP(M65*$T$5,0) -> 15088 | V65: =+U65*E65 -> 7544000
A66: 7.04 | B66: OK | C66: Revoque Grueso Interior + fino | D66: m2 | E66: =+Locales!U100 -> 521 | G66: =+'APU 06.25'!E22 -> 2891.2175 | H66: =F66+G66 -> 2891.2175 | J66: =+'APU 06.25'!H22 -> 22980.577 | K66: =I66+J66 -> 22980.577 | L66: =+'APU 06.25'!K22 -> 639.45131 | M66: =H66+K66+L66 -> 26511.246 | N66: =F66*E66 -> 0 | O66: =G66*E66 -> 1506324.3 | P66: =I66*E66 -> 0 | Q66: =J66*E66 -> 11972881 | R66: =+L66*E66 -> 333154.13 | S66: =SUM(N66:R66) -> 13812359 | U66: =+ROUNDUP(M66*$T$5,0) -> 35962 | V66: =+U66*E66 -> 18736202
A67: 7.05 | B67: OK | C67: Yeso interior | D67: m2 | E67: =+Locales!Z100 -> 2180 | F67: =+Tareas!H123 -> 0 | G67: =+Tareas!I123 -> 5780.8669 | H67: =F67+G67 -> 5780.8669 | I67: =+Tareas!Q123 -> 12252.549 | J67: =+Tareas!R123 -> 0 | K67: =I67+J67 -> 12252.549 | L67: =+(H67+K67)*0.015 -> 270.50123 | M67: =H67+K67+L67 -> 18303.917 | N67: =F67*E67 -> 0 | O67: =G67*E67 -> 12602290 | P67: =I67*E67 -> 26710556 | Q67: =J67*E67 -> 0 | R67: =+L67*E67 -> 589692.69 | S67: =SUM(N67:R67) -> 39902538 | U67: =+ROUNDUP(M67*$T$5,0) -> 24829 | V67: =+U67*E67 -> 54127220
A68: 7.06 | B68: OK | C68: Arista en yeso | D68: ml | E68: =+Locales!AA100 -> 255 | F68: =+Tareas!H128 -> 0 | G68: =+Tareas!I128 -> 0 | H68: =F68+G68 -> 0 | I68: =+Tareas!Q128 -> 13144.583 | J68: =+Tareas!R128 -> 0 | K68: =I68+J68 -> 13144.583 | L68: =+(H68+K68)*0.015 -> 197.16874 | M68: =H68+K68+L68 -> 13341.751 | N68: =F68*E68 -> 0 | O68: =G68*E68 -> 0 | P68: =I68*E68 -> 3351868.6 | Q68: =J68*E68 -> 0 | R68: =+L68*E68 -> 50278.029 | S68: =SUM(N68:R68) -> 3402146.6 | U68: =+ROUNDUP(M68*$T$5,0) -> 18098 | V68: =+U68*E68 -> 4614990
A69: 7.07 | B69: OK | C69: Provisión y colocación de guardacanto yesero | D69: u | E69: =+Locales!AB100 -> 102 | F69: =+Tareas!H130 -> 0 | G69: =+Tareas!I130 -> 1658.1176 | H69: =F69+G69 -> 1658.1176 | I69: =+Tareas!Q130 -> 13917.793 | J69: =+Tareas!R130 -> 0 | K69: =I69+J69 -> 13917.793 | L69: =+(H69+K69)*0.015 -> 233.63867 | M69: =H69+K69+L69 -> 15809.55 | N69: =F69*E69 -> 0 | O69: =G69*E69 -> 169128 | P69: =I69*E69 -> 1419614.9 | Q69: =J69*E69 -> 0 | R69: =+L69*E69 -> 23831.144 | S69: =SUM(N69:R69) -> 1612574.1 | U69: =+ROUNDUP(M69*$T$5,0) -> 21446 | V69: =+U69*E69 -> 2187492
A70: 7.08 | B70: OK | C70: Revoque Grueso Impermeable Interior b/ revestimiento | D70: m2 | E70: =+Locales!X100 -> 715 | G70: =+'APU 06.25'!E23 -> 4061.1651 | H70: =F70+G70 -> 4061.1651 | J70: =+'APU 06.25'!H23 -> 11697.516 | K70: =I70+J70 -> 11697.516 | L70: =+'APU 06.25'!K23 -> 333.62677 | M70: =H70+K70+L70 -> 16092.308 | N70: =F70*E70 -> 0 | O70: =G70*E70 -> 2903733 | P70: =I70*E70 -> 0 | Q70: =J70*E70 -> 8363724.1 | R70: =+L70*E70 -> 238543.14 | S70: =SUM(N70:R70) -> 11506000 | U70: =+ROUNDUP(M70*$T$5,0) -> 21829 | V70: =+U70*E70 -> 15607735
A71: 8 | C71: CONTRAPISOS Y CARPETAS | T71: =SUM(S72:S79) -> 36751131 | W71: =SUM(V72:V79) -> 49852854 | X71: =+W71/$W$213 -> 0.032358986
A72: 8.01 | B72: OK | C72: Contrapiso de cascotes s/ss e: 15 cm | D72: m2 | E72: =+Locales!O100 -> 21 | G72: =+'APU 06.25'!E25*0.2 -> 13595.327 | H72: =F72+G72 -> 13595.327 | J72: =+'APU 06.25'!H25*0.2 -> 19696.193 | K72: =I72+J72 -> 19696.193 | L72: =+'APU 06.25'!K25*0.2 -> 503.75749 | M72: =H72+K72+L72 -> 33795.278 | N72: =F72*E72 -> 0 | O72: =G72*E72 -> 285501.86 | P72: =I72*E72 -> 0 | Q72: =J72*E72 -> 413620.06 | R72: =+L72*E72 -> 10578.907 | S72: =SUM(N72:R72) -> 709700.83 | U72: =+ROUNDUP(M72*$T$5,0) -> 45843 | V72: =+U72*E72 -> 962703
A73: 8.02 | B73: OK | C73: Contrapiso armado de H° pobre s/terreno natural e: 20 cm - Incluye film de polietileno | D73: m2 | E73: =+Locales!P100 -> 201 | F73: =+Tareas!H133 -> 28415.373 | G73: =+Tareas!I133 -> 2539.3792 | H73: =F73+G73 -> 30954.752 | I73: =+Tareas!Q133 -> 0 | J73: =+Tareas!R133 -> 8768.7309 | K73: =I73+J73 -> 8768.7309 | L73: =+(H73+K73)*0.015 -> 595.85225 | M73: =H73+K73+L73 -> 40319.335 | N73: =F73*E73 -> 5711490 | O73: =G73*E73 -> 510415.21 | P73: =I73*E73 -> 0 | Q73: =J73*E73 -> 1762514.9 | R73: =+L73*E73 -> 119766.3 | S73: =SUM(N73:R73) -> 8104186.4 | U73: =+ROUNDUP(M73*$T$5,0) -> 54692 | V73: =+U73*E73 -> 10993092
A74: 8.03 | B74: OK | C74: Contrapiso de cascotes en azoteas c/pendiente e: 15 cm | D74: m2 | E74: =+Locales!N100 -> 107 | G74: =+'APU 06.25'!E25*0.2 -> 13595.327 | H74: =F74+G74 -> 13595.327 | J74: =+'APU 06.25'!H25*0.2 -> 19696.193 | K74: =I74+J74 -> 19696.193 | L74: =+'APU 06.25'!K25*0.2 -> 503.75749 | M74: =H74+K74+L74 -> 33795.278 | N74: =F74*E74 -> 0 | O74: =G74*E74 -> 1454700 | P74: =I74*E74 -> 0 | Q74: =J74*E74 -> 2107492.7 | R74: =+L74*E74 -> 53902.052 | S74: =SUM(N74:R74) -> 3616094.7 | U74: =+ROUNDUP(M74*$T$5,0) -> 45843 | V74: =+U74*E74 -> 4905201
A75: 8.04 | B75: OK | C75: Contrapiso - Carpeta monolitico e: 6 cm | D75: m2 | E75: =+Locales!Q100 -> 850 | G75: =+'APU 06.25'!E27 -> 6717.8752 | H75: =F75+G75 -> 6717.8752 | J75: =+'APU 06.25'!H27 -> 11145.022 | K75: =I75+J75 -> 11145.022 | L75: =+'APU 06.25'!K27 -> 130.47811 | M75: =H75+K75+L75 -> 17993.375 | N75: =F75*E75 -> 0 | O75: =G75*E75 -> 5710194 | P75: =I75*E75 -> 0 | Q75: =J75*E75 -> 9473268.8 | R75: =+L75*E75 -> 110906.39 | S75: =SUM(N75:R75) -> 15294369 | U75: =+ROUNDUP(M75*$T$5,0) -> 24408 | V75: =+U75*E75 -> 20746800
A76: 8.05 | B76: OK | C76: Carpeta en PB, balcones, baños y azoteas e: 3,00 cm | D76: m2 | E76: =+Locales!R100 -> 365 | G76: =+'APU 06.25'!E26 -> 3420.3193 | H76: =F76+G76 -> 3420.3193 | J76: =+'APU 06.25'!H26 -> 8295.6908 | K76: =I76+J76 -> 8295.6908 | L76: =+'APU 06.25'!K26 -> 235.08683 | M76: =H76+K76+L76 -> 11951.097 | N76: =F76*E76 -> 0 | O76: =G76*E76 -> 1248416.6 | P76: =I76*E76 -> 0 | Q76: =J76*E76 -> 3027927.2 | R76: =+L76*E76 -> 85806.693 | S76: =SUM(N76:R76) -> 4362150.4 | U76: =+ROUNDUP(M76*$T$5,0) -> 16212 | V76: =+U76*E76 -> 5917380
A77: 8.06 | B77: OK | C77: Carpeta sobre membrana, e: 3,00 cm | D77: m2 | E77: =+Locales!S100 -> 357 | G77: =+'APU 06.25'!E26 -> 3420.3193 | H77: =F77+G77 -> 3420.3193 | J77: =+'APU 06.25'!H26 -> 8295.6908 | K77: =I77+J77 -> 8295.6908 | L77: =+'APU 06.25'!K26 -> 235.08683 | M77: =H77+K77+L77 -> 11951.097 | N77: =F77*E77 -> 0 | O77: =G77*E77 -> 1221054 | P77: =I77*E77 -> 0 | Q77: =J77*E77 -> 2961561.6 | R77: =+L77*E77 -> 83925.998 | S77: =SUM(N77:R77) -> 4266541.6 | U77: =+ROUNDUP(M77*$T$5,0) -> 16212 | V77: =+U77*E77 -> 5787684
A78: 8.07 | B78: R | C78: Banquinas para cocinas - N/A | D78: gl | E78: 0 | H78: =F78+G78 -> 0 | K78: =I78+J78 -> 0 | M78: =H78+K78+L78 -> 0 | N78: =F78*E78 -> 0 | O78: =G78*E78 -> 0 | P78: =I78*E78 -> 0 | Q78: =J78*E78 -> 0 | R78: =+L78*E78 -> 0 | S78: =SUM(N78:R78) -> 0 | U78: =+ROUNDUP(M78*$T$5,0) -> 0 | V78: =+U78*E78 -> 0
A79: 8.08 | B79: OK | C79: Banquinas para bombas, TT, etc. h: 15 cm | D79: gl | E79: 1 | F79: =+Tareas!H142 -> 0 | G79: =+Tareas!I142 -> 88498.55 | H79: =F79+G79 -> 88498.55 | I79: =+Tareas!Q142 -> 0 | J79: =+Tareas!R142 -> 303706.02 | K79: =I79+J79 -> 303706.02 | L79: =+(H79+K79)*0.015 -> 5883.0686 | M79: =H79+K79+L79 -> 398087.64 | N79: =F79*E79 -> 0 | O79: =G79*E79 -> 88498.55 | P79: =I79*E79 -> 0 | Q79: =J79*E79 -> 303706.02 | R79: =+L79*E79 -> 5883.0686 | S79: =SUM(N79:R79) -> 398087.64 | U79: =+ROUNDUP(M79*$T$5,0) -> 539994 | V79: =+U79*E79 -> 539994
A80: 9 | C80: ESCALERAS | T80: =SUM(S81:S83) -> 5878458.4 | W80: =SUM(V81:V83) -> 7973950 | X80: =+W80/$W$213 -> 0.0051758108
A81: 9.01 | B81: OK | C81: Provisión y ejecución de alisado de cemento en pedadas y alzadas | D81: gl | E81: 1 | F81: =+Tareas!H147 -> 427508.24 | G81: =+Tareas!I147 -> 0 | H81: =F81+G81 -> 427508.24 | I81: =+Tareas!Q147 -> 0 | J81: =+Tareas!R147 -> 2044758.2 | K81: =I81+J81 -> 2044758.2 | L81: =+(H81+K81)*0.015 -> 37083.997 | M81: =H81+K81+L81 -> 2509350.4 | N81: =F81*E81 -> 427508.24 | O81: =G81*E81 -> 0 | P81: =I81*E81 -> 0 | Q81: =J81*E81 -> 2044758.2 | R81: =+L81*E81 -> 37083.997 | S81: =SUM(N81:R81) -> 2509350.4 | U81: =+ROUNDUP(M81*$T$5,0) -> 3403853 | V81: =+U81*E81 -> 3403853
A82: 9.02 | B82: OK | C82: Provisión y colocación de nariz metálica en escalones | D82: gl | E82: 1 | F82: =+Tareas!H151 -> 463902.77 | G82: =+Tareas!I151 -> 0 | H82: =F82+G82 -> 463902.77 | I82: =+Tareas!Q151 -> 0 | J82: =+Tareas!R151 -> 1775796.2 | K82: =I82+J82 -> 1775796.2 | L82: =+(H82+K82)*0.015 -> 33595.485 | M82: =H82+K82+L82 -> 2273294.5 | N82: =F82*E82 -> 463902.77 | O82: =G82*E82 -> 0 | P82: =I82*E82 -> 0 | Q82: =J82*E82 -> 1775796.2 | R82: =+L82*E82 -> 33595.485 | S82: =SUM(N82:R82) -> 2273294.5 | U82: =+ROUNDUP(M82*$T$5,0) -> 3083651 | V82: =+U82*E82 -> 3083651
A83: 9.03 | B83: OK | C83: Zócalo de concreto en escalera - No incluye el ojo | D83: ml | E83: =+Computo!G201 -> 114 | G83: =+'APU 06.25'!E21 -> 827.27861 | H83: =F83+G83 -> 827.27861 | I83: =+J83 -> 4324.0478 | J83: =+'APU 06.25'!H21 -> 4324.0478 | K83: =I83+J83 -> 8648.0955 | L83: =+'APU 06.25'!K21 -> 137.02528 | M83: =H83+K83+L83 -> 9612.3994 | N83: =F83*E83 -> 0 | O83: =G83*E83 -> 94309.762 | P83: =I83*E83 -> 492941.45 | Q83: =J83*E83 -> 492941.45 | R83: =+L83*E83 -> 15620.882 | S83: =SUM(N83:R83) -> 1095813.5 | U83: =+ROUNDUP(M83*$T$5,0) -> 13039 | V83: =+U83*E83 -> 1486446
A84: 10 | C84: VENTILACIONES - PROVISION COTIZADA EN ITEM 26 | T84: =SUM(S85:S87) -> 4784536 | W84: =SUM(V85:V87) -> 6490073 | X84: =+W84/$W$213 -> 0.0042126411
A85: 10.01 | B85: OK | C85: Colocación de ventilación de conducto de humos. Inc. toma de aire en PB | D85: gl | E85: 1 | F85: =+Tareas!H157 -> 250000 | G85: =+Tareas!I157 -> 0 | H85: =F85+G85 -> 250000 | I85: =+Tareas!Q157 -> 0 | J85: =+Tareas!R157 -> 1663092.8 | K85: =I85+J85 -> 1663092.8 | L85: =(H85+K85)*0.015 -> 28696.391 | M85: =H85+K85+L85 -> 1941789.2 | N85: =F85*E85 -> 250000 | O85: =G85*E85 -> 0 | P85: =I85*E85 -> 0 | Q85: =J85*E85 -> 1663092.8 | R85: =+L85*E85 -> 28696.391 | S85: =SUM(N85:R85) -> 1941789.2 | U85: =+ROUNDUP(M85*$T$5,0) -> 2633975 | V85: =+U85*E85 -> 2633975
A86: 10.02 | B86: OK | C86: Colocación y montaje de conducto de ventilación en baños | D86: gl | E86: 1 | F86: =+Tareas!H160 -> 250000 | G86: =+Tareas!I160 -> 0 | H86: =F86+G86 -> 250000 | I86: =+Tareas!Q160 -> 0 | J86: =+Tareas!R160 -> 1663092.8 | K86: =I86+J86 -> 1663092.8 | L86: =(H86+K86)*0.015 -> 28696.391 | M86: =H86+K86+L86 -> 1941789.2 | N86: =F86*E86 -> 250000 | O86: =G86*E86 -> 0 | P86: =I86*E86 -> 0 | Q86: =J86*E86 -> 1663092.8 | R86: =+L86*E86 -> 28696.391 | S86: =SUM(N86:R86) -> 1941789.2 | U86: =+ROUNDUP(M86*$T$5,0) -> 2633975 | V86: =+U86*E86 -> 2633975
A87: 10.03 | B87: OK | C87: Colocación sombreretes en chapa prepintada C25 - Provisión en item 26 | D87: u | E87: 7 | F87: =+Tareas!H163 -> 31772.281 | G87: =+Tareas!I163 -> 0 | H87: =F87+G87 -> 31772.281 | I87: =+Tareas!Q163 -> 0 | J87: =+Tareas!R163 -> 95033.872 | K87: =I87+J87 -> 95033.872 | L87: =(H87+K87)*0.015 -> 1902.0923 | M87: =H87+K87+L87 -> 128708.25 | N87: =F87*E87 -> 222405.97 | O87: =G87*E87 -> 0 | P87: =I87*E87 -> 0 | Q87: =J87*E87 -> 665237.1 | R87: =+L87*E87 -> 13314.646 | S87: =SUM(N87:R87) -> 900957.72 | U87: =+ROUNDUP(M87*$T$5,0) -> 174589 | V87: =+U87*E87 -> 1222123
A88: 11 | C88: PISOS - PROVISION A CARGO DEL COMITENTE | T88: =SUM(S89:S95) -> 27324425 | W88: =SUM(V89:V95) -> 37065194 | X88: =+W88/$W$213 -> 0.024058645
A89: 11.01 | B89: OK | C89: Colocación de baldosas en palieres - Provisión a cargo del comitente | D89: m2 | E89: =+Locales!BE100 -> 101 | G89: =+'APU 06.25'!E36 -> 6932.2708 | H89: =F89+G89 -> 6932.2708 | J89: =+'APU 06.25'!H36 -> 12793.021 | K89: =I89+J89 -> 12793.021 | L89: =+'APU 06.25'!K36 -> 245.43421 | M89: =H89+K89+L89 -> 19970.726 | N89: =F89*E89 -> 0 | O89: =G89*E89 -> 700159.35 | P89: =I89*E89 -> 0 | Q89: =J89*E89 -> 1292095.1 | R89: =+L89*E89 -> 24788.855 | S89: =SUM(N89:R89) -> 2017043.4 | U89: =+ROUNDUP(M89*$T$5,0) -> 27090 | V89: =+U89*E89 -> 2736090
A90: 11.02 | B90: OK | C90: Colocación de porcelanato en UF - Provisión a cargo del comitente | D90: m2 | E90: =+Locales!BF100 -> 898 | G90: =+'APU 06.25'!E36 -> 6932.2708 | H90: =F90+G90 -> 6932.2708 | J90: =+'APU 06.25'!H36 -> 12793.021 | K90: =I90+J90 -> 12793.021 | L90: =+'APU 06.25'!K36 -> 245.43421 | M90: =H90+K90+L90 -> 19970.726 | N90: =F90*E90 -> 0 | O90: =G90*E90 -> 6225179.2 | P90: =I90*E90 -> 0 | Q90: =J90*E90 -> 11488133 | R90: =+L90*E90 -> 220399.92 | S90: =SUM(N90:R90) -> 17933712 | U90: =+ROUNDUP(M90*$T$5,0) -> 27090 | V90: =+U90*E90 -> 24326820
A91: 11.03 | B91: OK | C91: Colocación de porcelanato en baños - Provisión a cargo del comitente | D91: m2 | E91: =+Locales!BG100 -> 88 | G91: =+'APU 06.25'!E37 -> 6932.2708 | H91: =F91+G91 -> 6932.2708 | J91: =+'APU 06.25'!H37 -> 16630.928 | K91: =I91+J91 -> 16630.928 | L91: =+'APU 06.25'!K37 -> 319.06447 | M91: =H91+K91+L91 -> 23882.263 | N91: =F91*E91 -> 0 | O91: =G91*E91 -> 610039.83 | P91: =I91*E91 -> 0 | Q91: =J91*E91 -> 1463521.6 | R91: =+L91*E91 -> 28077.674 | S91: =SUM(N91:R91) -> 2101639.1 | U91: =+ROUNDUP(M91*$T$5,0) -> 32396 | V91: =+U91*E91 -> 2850848
A92: 11.04 | B92: OK | C92: Colocación de porcelanato en exterior - Provisión a cargo del comitente | D92: m2 | E92: =+Locales!BD100 -> 63 | G92: =+'APU 06.25'!E36 -> 6932.2708 | H92: =F92+G92 -> 6932.2708 | J92: =+'APU 06.25'!H36 -> 12793.021 | K92: =I92+J92 -> 12793.021 | L92: =+'APU 06.25'!K36 -> 245.43421 | M92: =H92+K92+L92 -> 19970.726 | N92: =F92*E92 -> 0 | O92: =G92*E92 -> 436733.06 | P92: =I92*E92 -> 0 | Q92: =J92*E92 -> 805960.34 | R92: =+L92*E92 -> 15462.355 | S92: =SUM(N92:R92) -> 1258155.8 | U92: =+ROUNDUP(M92*$T$5,0) -> 27090 | V92: =+U92*E92 -> 1706670
A93: 11.05 | B93: OK | C93: Provisión y colocación de sustrato - No cotiza | D93: m2 | E93: =+Locales!BI100 -> 25 | H93: =F93+G93 -> 0 | K93: =I93+J93 -> 0 | M93: =H93+K93+L93 -> 0 | N93: =F93*E93 -> 0 | O93: =G93*E93 -> 0 | P93: =I93*E93 -> 0 | Q93: =J93*E93 -> 0 | R93: =+L93*E93 -> 0 | S93: =SUM(N93:R93) -> 0 | U93: =+ROUNDUP(M93*$T$5,0) -> 0 | V93: =+U93*E93 -> 0
A94: 11.06 | B94: OK | C94: Provisión y ejecución de alisado de cemento rodillado | D94: m2 | E94: =+Locales!BH100 -> 27 | G94: =+'APU 06.25'!E29 -> 4104.3832 | H94: =F94+G94 -> 4104.3832 | J94: =+'APU 06.25'!H29 -> 11112.816 | K94: =I94+J94 -> 11112.816 | L94: =+'APU 06.25'!K29 -> 306.635 | M94: =H94+K94+L94 -> 15523.834 | N94: =F94*E94 -> 0 | O94: =G94*E94 -> 110818.35 | P94: =I94*E94 -> 0 | Q94: =J94*E94 -> 300046.04 | R94: =+L94*E94 -> 8279.1449 | S94: =SUM(N94:R94) -> 419143.53 | U94: =+ROUNDUP(M94*$T$5,0) -> 21058 | V94: =+U94*E94 -> 568566
A95: 11.07 | B95: OK | C95: Colocación de baldoson de vereda - Provisión a cargo del comitente | D95: m2 | E95: =+Locales!BJ100 -> 180 | G95: =+'APU 06.25'!E36 -> 6932.2708 | H95: =F95+G95 -> 6932.2708 | J95: =+'APU 06.25'!H36 -> 12793.021 | K95: =I95+J95 -> 12793.021 | L95: =+'APU 06.25'!K36 -> 245.43421 | M95: =H95+K95+L95 -> 19970.726 | N95: =F95*E95 -> 0 | O95: =G95*E95 -> 1247808.7 | P95: =I95*E95 -> 0 | Q95: =J95*E95 -> 2302743.8 | R95: =+L95*E95 -> 44178.158 | S95: =SUM(N95:R95) -> 3594730.7 | U95: =+ROUNDUP(M95*$T$5,0) -> 27090 | V95: =+U95*E95 -> 4876200
A96: 12 | C96: ZOCALOS Y SOLIAS - PROVISION A CARGO DEL COMITENTE | T96: =SUM(S97:S100) -> 11405978 | W96: =SUM(V97:V100) -> 15472374 | X96: =+W96/$W$213 -> 0.010042962
A97: 12.01 | B97: OK | C97: Provisión y colocación de zocalos de Madera (MDF) h: 5 cm | D97: ml | E97: =+Locales!BL100 -> 792 | F97: =+Tareas!H169 -> 4349.9864 | G97: =+Tareas!I169 -> 0 | H97: =F97+G97 -> 4349.9864 | I97: =+Tareas!Q169 -> 0 | J97: =+Tareas!R169 -> 5122.3554 | K97: =I97+J97 -> 5122.3554 | L97: =(H97+K97)*0.015 -> 142.08513 | M97: =H97+K97+L97 -> 9614.427 | N97: =F97*E97 -> 3445189.3 | O97: =G97*E97 -> 0 | P97: =I97*E97 -> 0 | Q97: =J97*E97 -> 4056905.5 | R97: =+L97*E97 -> 112531.42 | S97: =SUM(N97:R97) -> 7614626.2 | U97: =+ROUNDUP(M97*$T$5,0) -> 13042 | V97: =+U97*E97 -> 10329264
A98: 12.02 | B98: OK | C98: Colocación de zócalo de porcelanato en balcones UF - Provisión a cargo del comitente | D98: ml | E98: =+Locales!BN100 -> 282 | G98: =+'APU 06.25'!E38 -> 1001.4972 | H98: =F98+G98 -> 1001.4972 | J98: =+'APU 06.25'!H38 -> 5543.6425 | K98: =I98+J98 -> 5543.6425 | L98: =+'APU 06.25'!K38 -> 106.35482 | M98: =H98+K98+L98 -> 6651.4946 | N98: =F98*E98 -> 0 | O98: =G98*E98 -> 282422.21 | P98: =I98*E98 -> 0 | Q98: =J98*E98 -> 1563307.2 | R98: =+L98*E98 -> 29992.06 | S98: =SUM(N98:R98) -> 1875721.5 | U98: =+ROUNDUP(M98*$T$5,0) -> 9023 | V98: =+U98*E98 -> 2544486
A99: 12.03 | B99: OK | C99: Colocación de zócalo de porcelanato en espacios comunes - Provisión a cargo del comitente | D99: ml | E99: =+Locales!BO100 -> 263 | G99: =+'APU 06.25'!E38 -> 1001.4972 | H99: =F99+G99 -> 1001.4972 | J99: =+'APU 06.25'!H38 -> 5543.6425 | K99: =I99+J99 -> 5543.6425 | L99: =+'APU 06.25'!K38 -> 106.35482 | M99: =H99+K99+L99 -> 6651.4946 | N99: =F99*E99 -> 0 | O99: =G99*E99 -> 263393.76 | P99: =I99*E99 -> 0 | Q99: =J99*E99 -> 1457978 | R99: =+L99*E99 -> 27971.319 | S99: =SUM(N99:R99) -> 1749343.1 | U99: =+ROUNDUP(M99*$T$5,0) -> 9023 | V99: =+U99*E99 -> 2373049
A100: 12.04 | B100: OK | C100: Colocación de solia - Provisión a cargo del comitente | D100: ml | E100: =+Locales!BK100 -> 25 | G100: =+'APU 06.25'!E38 -> 1001.4972 | H100: =F100+G100 -> 1001.4972 | J100: =+'APU 06.25'!H38 -> 5543.6425 | K100: =I100+J100 -> 5543.6425 | L100: =+'APU 06.25'!K38 -> 106.35482 | M100: =H100+K100+L100 -> 6651.4946 | N100: =F100*E100 -> 0 | O100: =G100*E100 -> 25037.43 | P100: =I100*E100 -> 0 | Q100: =J100*E100 -> 138591.06 | R100: =+L100*E100 -> 2658.8706 | S100: =SUM(N100:R100) -> 166287.36 | U100: =+ROUNDUP(M100*$T$5,0) -> 9023 | V100: =+U100*E100 -> 225575
...

Sheet Tareas
H4: MATERIALES | Q4: MANO DE OBRA
H5: PU | J5: TOTAL | M5: =+'P.MO 06.25'!B4 -> 94177.138 | N5: =+'P.MO 06.25'!B5 -> 84612.513 | O5: =+'P.MO 06.25'!B6 -> 72132.138 | P5: =+'P.MO 06.25'!B7 -> 67240.499 | Q5: PU | S5: TOTAL
C6: Descripción | D6: U | E6: Cant | F6: OTRO | G6: CORRALON | H6: OTRO | I6: CORRALON | J6: OTRO | K6: CORRALON | L6: OTRO | M6: ES | N6: OF | O6: MED | P6: AY | Q6: OTRO | R6: ALB | S6: OTRO | T6: ALB
A7: =+'01'!A8 -> 1 | C7: =+'01'!C8 -> TAREAS PRELIMINARES
A8: =+'01'!A10 -> 1.02 | B8: =+'01'!B10 -> OK | C8: =+'01'!C10 -> Topógrafo - Visita de obra replanteo | D8: =+'01'!D10 -> un | E8: =+'01'!E10 -> 4 | H8: =+J8/E8 -> 0 | I8: =+K8/E8 -> 25000 | J8: =SUM(J9:J11) -> 0 | K8: =SUM(K9:K11) -> 100000 | Q8: =+U8/E8 -> 214394.06 | R8: =+V8/E8 -> 67240.499 | U8: =SUM(S9:S11) -> 857576.25 | V8: =SUM(T9:T11) -> 268962
C9: M.Obra topografo | D9: d | E9: =+E8 -> 4 | J9: =+F9*E9 -> 0 | K9: =+G9*E9 -> 0 | L9: =+'P.MO 06.25'!B10 -> 214394.06 | S9: =+L9*E9 -> 857576.25 | T9: =(+M9*$M$5+N9*$N$5+O9*$O$5+P9*$P$5)*E9 -> 0
C10: M.Obra ayudante | D10: d | E10: =+E8 -> 4 | J10: =+F10*E10 -> 0 | K10: =+G10*E10 -> 0 | P10: 1 | S10: =+L10*E10 -> 0 | T10: =(+M10*$M$5+N10*$N$5+O10*$O$5+P10*$P$5)*E10 -> 268962
C11: Consumibles | D11: gl | E11: =+E8 -> 4 | G11: 25000 | J11: =+F11*E11 -> 0 | K11: =+G11*E11 -> 100000 | S11: =+L11*E11 -> 0 | T11: =(+M11*$M$5+N11*$N$5+O11*$O$5+P11*$P$5)*E11 -> 0
A12: =+'01'!A12 -> 1.04 | B12: =+'01'!B12 -> OK | C12: =+'01'!C12 -> Cerco de obra perimetral - En chapa C25 + Concertina + Porton corredizo | D12: =+'01'!D12 -> ml | E12: =+'01'!E12 -> 10 | H12: =+J12/E12 -> 98815.568 | I12: =+K12/E12 -> 0 | J12: =+SUM(J13:J22) -> 988155.68 | K12: =+SUM(K13:K22) -> 0 | Q12: =+U12/E12 -> 0 | R12: =+V12/E12 -> 111992.57 | U12: =SUM(S13:S22) -> 0 | V12: =SUM(T13:T22) -> 1119925.7
C13: Chapa acanalada C25 | D13: m2 | E13: =+E12*2.5 -> 25 | F13: =+Cotizaciones!D4 -> 10861.769 | J13: =+F13*E13 -> 271544.21 | K13: =+G13*E13 -> 0 | S13: =+L13*E13 -> 0 | T13: =(+M13*$M$5+N13*$N$5+O13*$O$5+P13*$P$5)*E13 -> 0
C14: Perfiles UPN 100 | D14: un | E14: 1 | F14: =+Cotizaciones!D5 -> 271144.89 | J14: =+F14*E14 -> 271144.89 | K14: =+G14*E14 -> 0 | S14: =+L14*E14 -> 0 | T14: =(+M14*$M$5+N14*$N$5+O14*$O$5+P14*$P$5)*E14 -> 0
C15: Bastidor para porton corredizo - Perfil 40 x 40 x 2 | D15: u | E15: 2 | F15: =+Cotizaciones!D6 -> 23523.752 | J15: =+F15*E15 -> 47047.504 | K15: =+G15*E15 -> 0 | S15: =+L15*E15 -> 0 | T15: =(+M15*$M$5+N15*$N$5+O15*$O$5+P15*$P$5)*E15 -> 0
C16: Riel Roma 174 e: 2,1 mm. 53 x 60 x 6000 | D16: u | E16: 1 | F16: =+Cotizaciones!D7 -> 85391.38 | J16: =+F16*E16 -> 85391.38 | K16: =+G16*E16 -> 0 | S16: =+L16*E16 -> 0 | T16: =(+M16*$M$5+N16*$N$5+O16*$O$5+P16*$P$5)*E16 -> 0
C17: Carro acero 174 4 ruedas puertas portones Ø45mm | D17: u | E17: 2 | F17: =+Cotizaciones!D8 -> 11534.744 | J17: =+F17*E17 -> 23069.488 | K17: =+G17*E17 -> 0 | S17: =+L17*E17 -> 0 | T17: =(+M17*$M$5+N17*$N$5+O17*$O$5+P17*$P$5)*E17 -> 0
C18: Autoperforantes punta mecha 14 x 2 | D18: u | E18: =+E13*4.5 -> 112.5 | F18: 120 | J18: =+F18*E18 -> 13500 | K18: =+G18*E18 -> 0 | S18: =+L18*E18 -> 0 | T18: =(+M18*$M$5+N18*$N$5+O18*$O$5+P18*$P$5)*E18 -> 0
C19: Rollo Concertina | D19: rol | E19: 2 | F19: =50000/1.21 -> 41322.314 | J19: =+F19*E19 -> 82644.628 | K19: =+G19*E19 -> 0 | S19: =+L19*E19 -> 0 | T19: =(+M19*$M$5+N19*$N$5+O19*$O$5+P19*$P$5)*E19 -> 0
C20: Puntales 3 x 3 x 3,7 | D20: u | E20: 7 | F20: =+Cotizaciones!D24 -> 4992.1647 | J20: =+F20*E20 -> 34945.153 | K20: =+G20*E20 -> 0 | S20: =+L20*E20 -> 0 | T20: =(+M20*$M$5+N20*$N$5+O20*$O$5+P20*$P$5)*E20 -> 0
C21: Consumibles | D21: gl | E21: 0.2 | F21: =+SUM(J13:J19) -> 794342.11 | J21: =+F21*E21 -> 158868.42 | K21: =+G21*E21 -> 0 | S21: =+L21*E21 -> 0 | T21: =(+M21*$M$5+N21*$N$5+O21*$O$5+P21*$P$5)*E21 -> 0
C22: M.Obra | D22: d | E22: 5 | J22: =+F22*E22 -> 0 | K22: =+G22*E22 -> 0 | N22: 1 | O22: 1 | P22: 1 | S22: =+L22*E22 -> 0 | T22: =(+M22*$M$5+N22*$N$5+O22*$O$5+P22*$P$5)*E22 -> 1119925.7
A23: =+'01'!A13 -> 1.05 | B23: =+'01'!B13 -> OK | C23: =+'01'!C13 -> Obrador, pañol y ducha | D23: =+'01'!D13 -> gl | E23: =+'01'!E13 -> 1 | H23: =+J23/E23 -> 2270625.2 | I23: =+K23/E23 -> 300000 | J23: =+SUM(J24:J46) -> 2270625.2 | K23: =+SUM(K24:K46) -> 300000 | Q23: =+U23/E23 -> 1000000 | R23: =+V23/E23 -> 5023936.4 | U23: =SUM(S24:S46) -> 1000000 | V23: =SUM(T24:T46) -> 5023936.4 | AD23: 0.66
C24: Chapa acanalada C25 - Reutilizado (estimado 3 usos) | D24: m2 | E24: 30 | F24: =+Cotizaciones!D4/2 -> 5430.8843 | J24: =+F24*E24 -> 162926.53 | K24: =+G24*E24 -> 0 | S24: =+L24*E24 -> 0 | T24: =(+M24*$M$5+N24*$N$5+O24*$O$5+P24*$P$5)*E24 -> 0 | X24: Largo | Y24: Ancho | Z24: perim | AA24: h | AB24: m2 | AD24: Puntales
C25: Fenolico 1,22 x 2,44 - Reutilizado (estimado 3 usos) | D25: u | E25: =+AB33 -> 30 | F25: =+Cotizaciones!D21/2 -> 13196.9 | J25: =+F25*E25 -> 395907 | K25: =+G25*E25 -> 0 | S25: =+L25*E25 -> 0 | T25: =(+M25*$M$5+N25*$N$5+O25*$O$5+P25*$P$5)*E25 -> 0 | W25: Paredes | X25: 8 | Y25: 4 | Z25: =+X25 -> 8 | AA25: 2.4 | AB25: =+Z25*AA25 -> 19.2 | AD25: =+ROUNDUP(X25/$AD$23,0) -> 13 | AE25: =+AD25*AA25 -> 31.2 | AF25: =+ROUNDUP(AE25/3.7,0) -> 9
C26: Puntales 1 x 4 x 3,7 - Reutilizado (estimado 3 usos) | D26: u | E26: =+E27*2 -> 74 | F26: =+Cotizaciones!D23/2 -> 1109.369 | J26: =+F26*E26 -> 82093.306 | K26: =+G26*E26 -> 0 | S26: =+L26*E26 -> 0 | T26: =(+M26*$M$5+N26*$N$5+O26*$O$5+P26*$P$5)*E26 -> 0 | W26: Piso | X26: =+X25 -> 8 | Y26: 4 | AB26: =+X26*Y26 -> 32 | AD26: =+ROUNDUP(Y26/$AD$23,0) -> 7 | AE26: =+AD26*X26 -> 56 | AF26: =+ROUNDUP(AE26/3.7,0) -> 16
C27: Puntales 3 x 3 x 3,7 - Reutilizado (estimado 3 usos) | D27: u | E27: =+AF28 -> 37 | F27: =+Cotizaciones!D24/2 -> 2496.0823 | J27: =+F27*E27 -> 92355.046 | K27: =+G27*E27 -> 0 | S27: =+L27*E27 -> 0 | T27: =(+M27*$M$5+N27*$N$5+O27*$O$5+P27*$P$5)*E27 -> 0 | W27: Paredes interiores | X27: 3 | Y27: 3 | AA27: 2.4 | AB27: =+X27*Y27*AA27 -> 21.6 | AD27: =+ROUNDUP(Y27*3/$AD$23,0) -> 14 | AE27: =+AD27*X27 -> 42 | AF27: =+ROUNDUP(AE27/3.7,0) -> 12
C28: Flechas 3 x 6 x 3,7 - Reutilizado (estimado 3 usos) | D28: u | E28: 20 | F28: =+F27*2 -> 4992.1647 | J28: =+F28*E28 -> 99843.293 | K28: =+G28*E28 -> 0 | S28: =+L28*E28 -> 0 | T28: =(+M28*$M$5+N28*$N$5+O28*$O$5+P28*$P$5)*E28 -> 0 | W28: Galeria | AF28: =+SUM(AF25:AF27) -> 37
C29: Escalera | D29: gl | E29: 0 | F29: =+SUM(J26:J28) -> 274291.65 | J29: =+F29*E29 -> 0 | K29: =+G29*E29 -> 0 | S29: =+L29*E29 -> 0 | T29: =(+M29*$M$5+N29*$N$5+O29*$O$5+P29*$P$5)*E29 -> 0
C30: Flete madera | D30: u | E30: 2 | J30: =+F30*E30 -> 0 | K30: =+G30*E30 -> 0 | L30: 250000 | S30: =+L30*E30 -> 500000 | T30: =(+M30*$M$5+N30*$N$5+O30*$O$5+P30*$P$5)*E30 -> 0 | AB30: =+SUM(AB25:AB27) -> 72.8
C31: Materiales varios | D31: gl | E31: 1 | G31: 300000 | J31: =+F31*E31 -> 0 | K31: =+G31*E31 -> 300000 | S31: =+L31*E31 -> 0 | T31: =(+M31*$M$5+N31*$N$5+O31*$O$5+P31*$P$5)*E31 -> 0
C32: M.Obra carpinteros | D32: d | E32: 5 | J32: =+F32*E32 -> 0 | K32: =+G32*E32 -> 0 | N32: 1 | O32: 1 | P32: 2 | S32: =+L32*E32 -> 0 | T32: =(+M32*$M$5+N32*$N$5+O32*$O$5+P32*$P$5)*E32 -> 1456128.2 | U32: =+N32*$E32 -> 5 | V32: =+O32*$E32 -> 5 | W32: =+P32*$E32 -> 10 | AB32: =1.2*2.4 -> 2.88
C33: Rollo de cable TPR 3 x 2,5 | D33: rol | E33: 1 | F33: 250000 | J33: =+F33*E33 -> 250000 | K33: =+G33*E33 -> 0 | S33: =+L33*E33 -> 0 | T33: =(+M33*$M$5+N33*$N$5+O33*$O$5+P33*$P$5)*E33 -> 0 | AB33: =+ROUNDUP(AB30/AB32*1.15,0) -> 30 | AD33: =+SUM(AD25:AD32)*1.15 -> 39.1
C34: Zocalo E27 | D34: u | E34: 10 | F34: 500 | J34: =+F34*E34 -> 5000 | K34: =+G34*E34 -> 0 | S34: =+L34*E34 -> 0 | T34: =(+M34*$M$5+N34*$N$5+O34*$O$5+P34*$P$5)*E34 -> 0
C35: Lampara Led 12 w | D35: u | E35: =+E34 -> 10 | F35: 3000 | J35: =+F35*E35 -> 30000 | K35: =+G35*E35 -> 0 | S35: =+L35*E35 -> 0 | T35: =(+M35*$M$5+N35*$N$5+O35*$O$5+P35*$P$5)*E35 -> 0
C36: Mat. Elect. (tomas, enchufes, etc.) | D36: gl | E36: 0.5 | F36: =+SUM(J33:J35) -> 285000 | J36: =+F36*E36 -> 142500 | K36: =+G36*E36 -> 0 | S36: =+L36*E36 -> 0 | T36: =(+M36*$M$5+N36*$N$5+O36*$O$5+P36*$P$5)*E36 -> 0
C37: M.Obra elect | D37: d | E37: 3 | J37: =+F37*E37 -> 0 | K37: =+G37*E37 -> 0 | M37: 1 | N37: 1 | S37: =+L37*E37 -> 0 | T37: =(+M37*$M$5+N37*$N$5+O37*$O$5+P37*$P$5)*E37 -> 536368.95 | U37: =+N37*$E37 -> 3 | V37: =+O37*$E37 -> 0 | W37: =+P37*$E37 -> 0
C38: Materiales Sanit | D38: gl | E38: 1 | F38: 300000 | J38: =+F38*E38 -> 300000 | K38: =+G38*E38 -> 0 | S38: =+L38*E38 -> 0 | T38: =(+M38*$M$5+N38*$N$5+O38*$O$5+P38*$P$5)*E38 -> 0
C39: Inodoro | D39: u | E39: 2 | F39: 150000 | J39: =+F39*E39 -> 300000 | K39: =+G39*E39 -> 0 | S39: =+L39*E39 -> 0 | T39: =(+M39*$M$5+N39*$N$5+O39*$O$5+P39*$P$5)*E39 -> 0
C40: Mochila plastico | D40: u | E40: 2 | F40: 25000 | J40: =+F40*E40 -> 50000 | K40: =+G40*E40 -> 0 | S40: =+L40*E40 -> 0 | T40: =(+M40*$M$5+N40*$N$5+O40*$O$5+P40*$P$5)*E40 -> 0
C41: Bacha | D41: u | E41: 2 | F41: 30000 | J41: =+F41*E41 -> 60000 | K41: =+G41*E41 -> 0 | S41: =+L41*E41 -> 0 | T41: =(+M41*$M$5+N41*$N$5+O41*$O$5+P41*$P$5)*E41 -> 0
C42: Termo electrico 40 lts | D42: u | E42: 1 | F42: 300000 | J42: =+F42*E42 -> 300000 | K42: =+G42*E42 -> 0 | S42: =+L42*E42 -> 0 | T42: =(+M42*$M$5+N42*$N$5+O42*$O$5+P42*$P$5)*E42 -> 0
C43: M.Obra sanit | D43: d | E43: 4 | J43: =+F43*E43 -> 0 | K43: =+G43*E43 -> 0 | M43: 1 | N43: 1 | S43: =+L43*E43 -> 0 | T43: =(+M43*$M$5+N43*$N$5+O43*$O$5+P43*$P$5)*E43 -> 715158.6 | U43: =+N43*$E43 -> 4 | V43: =+O43*$E43 -> 0 | W43: =+P43*$E43 -> 0
C44: Mantenimiento | D44: mes | E44: =+GGBB!F4 -> 19 | J44: =+F44*E44 -> 0 | K44: =+G44*E44 -> 0 | N44: 0.5 | P44: 0.5 | S44: =+L44*E44 -> 0 | T44: =(+M44*$M$5+N44*$N$5+O44*$O$5+P44*$P$5)*E44 -> 1442603.6 | U44: =+N44*$E44 -> 9.5 | V44: =+O44*$E44 -> 0 | W44: =+P44*$E44 -> 9.5
C45: Flete madera | D45: u | E45: 2 | J45: =+F45*E45 -> 0 | K45: =+G45*E45 -> 0 | L45: 250000 | S45: =+L45*E45 -> 500000 | T45: =(+M45*$M$5+N45*$N$5+O45*$O$5+P45*$P$5)*E45 -> 0
C46: Desarmado | D46: d | E46: 3 | J46: =+F46*E46 -> 0 | K46: =+G46*E46 -> 0 | N46: 1 | O46: 1 | P46: 2 | S46: =+L46*E46 -> 0 | T46: =(+M46*$M$5+N46*$N$5+O46*$O$5+P46*$P$5)*E46 -> 873676.95 | U46: =+N46*$E46 -> 3 | V46: =+O46*$E46 -> 3 | W46: =+P46*$E46 -> 6
A47: =+'01'!A14 -> 1.06 | B47: =+'01'!B8 -> 0 | C47: =+'01'!C14 -> Alquiler de baños quimicos y duchas portatiles | D47: =+'01'!D14 -> mes | E47: =+'01'!E14 -> 4 | H47: =+J47/E47 -> 0 | I47: =+K47/E47 -> 0 | J47: =+SUM(J48:J51) -> 0 | K47: =+SUM(K48:K51) -> 0 | Q47: =+U47/E47 -> 260000 | R47: =+V47/E47 -> 0 | U47: =SUM(S48:S51) -> 1040000 | V47: =SUM(T48:T51) -> 0
C48: Alquiler de baños quimico | D48: mes | E48: =+$E$47 -> 4 | J48: =+F48*E48 -> 0 | K48: =+G48*E48 -> 0 | L48: =+Cotizaciones!D49 -> 80000 | S48: =+L48*E48 -> 320000 | T48: =(+M48*$M$5+N48*$N$5+O48*$O$5+P48*$P$5)*E48 -> 0
C49: Limpieza adicional | D49: mes | E49: =+$E$47 -> 4 | J49: =+F49*E49 -> 0 | K49: =+G49*E49 -> 0 | L49: =+Cotizaciones!D49 -> 80000 | S49: =+L49*E49 -> 320000 | T49: =(+M49*$M$5+N49*$N$5+O49*$O$5+P49*$P$5)*E49 -> 0
C50: Alquiler de modulo de ducha | D50: mes | E50: =+$E$47 -> 4 | J50: =+F50*E50 -> 0 | K50: =+G50*E50 -> 0 | L50: =+Cotizaciones!D49 -> 80000 | S50: =+L50*E50 -> 320000 | T50: =(+M50*$M$5+N50*$N$5+O50*$O$5+P50*$P$5)*E50 -> 0
C51: Fletes de entrega y retiro | D51: u | E51: 4 | J51: =+F51*E51 -> 0 | K51: =+G51*E51 -> 0 | L51: =+Cotizaciones!D50 -> 20000 | S51: =+L51*E51 -> 80000 | T51: =(+M51*$M$5+N51*$N$5+O51*$O$5+P51*$P$5)*E51 -> 0
A52: =+'01'!A15 -> 1.07 | B52: =+'01'!B15 -> OK | C52: =+'01'!C15 -> Conexión pilar y luz de obra + Tablero de obra | D52: =+'01'!D15 -> gl | E52: =+'01'!E15 -> 1 | H52: =+J52/E52 -> 1290000 | I52: =+K52/E52 -> 100000 | J52: =+SUM(J53:J58) -> 1290000 | K52: =+SUM(K53:K58) -> 100000 | Q52: =+U52/E52 -> 0 | R52: =+V52/E52 -> 661285.32 | U52: =SUM(S53:S58) -> 0 | V52: =SUM(T53:T58) -> 661285.32
C53: Pilar de obra, albañileria | D53: d | E53: 2 | G53: 50000 | J53: =+F53*E53 -> 0 | K53: =+G53*E53 -> 100000 | N53: 1 | P53: 1 | S53: =+L53*E53 -> 0 | T53: =(+M53*$M$5+N53*$N$5+O53*$O$5+P53*$P$5)*E53 -> 303706.02
C54: Kit medidor pilar Edenor Conextube | D54: gl | E54: 1 | F54: 150000 | J54: =+F54*E54 -> 150000 | K54: =+G54*E54 -> 0 | S54: =+L54*E54 -> 0 | T54: =(+M54*$M$5+N54*$N$5+O54*$O$5+P54*$P$5)*E54 -> 0
C55: Kit jabalina + caja + toma cable | D55: gl | E55: 1 | F55: 15000 | J55: =+F55*E55 -> 15000 | K55: =+G55*E55 -> 0 | S55: =+L55*E55 -> 0 | T55: =(+M55*$M$5+N55*$N$5+O55*$O$5+P55*$P$5)*E55 -> 0
C56: Cable subterraneo 5 x 10 mm2 | D56: mts | E56: 50 | F56: 16500 | J56: =+F56*E56 -> 825000 | K56: =+G56*E56 -> 0 | S56: =+L56*E56 -> 0 | T56: =(+M56*$M$5+N56*$N$5+O56*$O$5+P56*$P$5)*E56 -> 0
C57: Tablero de obra | D57: gl | E57: 1 | F57: 300000 | J57: =+F57*E57 -> 300000 | K57: =+G57*E57 -> 0 | S57: =+L57*E57 -> 0 | T57: =(+M57*$M$5+N57*$N$5+O57*$O$5+P57*$P$5)*E57 -> 0
C58: M.Obra elect | D58: d | E58: 2 | J58: =+F58*E58 -> 0 | K58: =+G58*E58 -> 0 | M58: 1 | N58: 1 | S58: =+L58*E58 -> 0 | T58: =(+M58*$M$5+N58*$N$5+O58*$O$5+P58*$P$5)*E58 -> 357579.3
A59: =+'01'!A16 -> 1.08 | B59: =+'01'!B16 -> OK | C59: =+'01'!C16 -> Conexión agua de obra, tanque + bomba | D59: =+'01'!D16 -> gl | E59: =+'01'!E16 -> 1 | H59: =+J59/E59 -> 936000 | I59: =+K59/E59 -> 0 | J59: =+SUM(J60:J68) -> 936000 | K59: =+SUM(K60:K68) -> 0 | Q59: =+U59/E59 -> 0 | R59: =+V59/E59 -> 536368.95 | U59: =SUM(S60:S68) -> 0 | V59: =SUM(T60:T68) -> 536368.95
C60: Tanque de Bombeo 500 lts (reutilizado) | D60: u | E60: 1 | F60: 200000 | J60: =+F60*E60 -> 200000 | K60: =+G60*E60 -> 0 | S60: =+L60*E60 -> 0 | T60: =(+M60*$M$5+N60*$N$5+O60*$O$5+P60*$P$5)*E60 -> 0
C61: Bomba pres (reutilizada) | D61: u | E61: 1 | F61: 200000 | J61: =+F61*E61 -> 200000 | K61: =+G61*E61 -> 0 | S61: =+L61*E61 -> 0 | T61: =(+M61*$M$5+N61*$N$5+O61*$O$5+P61*$P$5)*E61 -> 0
C62: Flotante mecanico 1" + boya | D62: u | E62: 1 | F62: 50000 | J62: =+F62*E62 -> 50000 | K62: =+G62*E62 -> 0 | S62: =+L62*E62 -> 0 | T62: =(+M62*$M$5+N62*$N$5+O62*$O$5+P62*$P$5)*E62 -> 0
C63: Flotante automatico | D63: u | E63: 1 | F63: 10000 | J63: =+F63*E63 -> 10000 | K63: =+G63*E63 -> 0 | S63: =+L63*E63 -> 0 | T63: =(+M63*$M$5+N63*$N$5+O63*$O$5+P63*$P$5)*E63 -> 0
C64: Caño 3/4" | D64: u | E64: =ROUNDUP((50+(3*7))/6,0) -> 12 | F64: 15000 | J64: =+F64*E64 -> 180000 | K64: =+G64*E64 -> 0 | S64: =+L64*E64 -> 0 | T64: =(+M64*$M$5+N64*$N$5+O64*$O$5+P64*$P$5)*E64 -> 0
C65: Val. esf doble media union 1" | D65: u | E65: 8 | F65: 15000 | J65: =+F65*E65 -> 120000 | K65: =+G65*E65 -> 0 | S65: =+L65*E65 -> 0 | T65: =(+M65*$M$5+N65*$N$5+O65*$O$5+P65*$P$5)*E65 -> 0
C66: Canilla de pvc | D66: u | E66: 10 | F66: 2000 | J66: =+F66*E66 -> 20000 | K66: =+G66*E66 -> 0 | S66: =+L66*E66 -> 0 | T66: =(+M66*$M$5+N66*$N$5+O66*$O$5+P66*$P$5)*E66 -> 0
C67: Desperdicio | D67: gl | E67: 0.2 | F67: =+SUM(J60:J66) -> 780000 | J67: =+F67*E67 -> 156000 | K67: =+G67*E67 -> 0 | S67: =+L67*E67 -> 0 | T67: =(+M67*$M$5+N67*$N$5+O67*$O$5+P67*$P$5)*E67 -> 0
C68: M.Obra sanit | D68: d | E68: 3 | J68: =+F68*E68 -> 0 | K68: =+G68*E68 -> 0 | M68: 1 | N68: 1 | S68: =+L68*E68 -> 0 | T68: =(+M68*$M$5+N68*$N$5+O68*$O$5+P68*$P$5)*E68 -> 536368.95
A69: =+'01'!A17 -> 1.09 | B69: =+'01'!B17 -> OK | C69: =+'01'!C17 -> Tramite luz de obra, certificado luz de obra (2) y medición PAT | D69: =+'01'!D17 -> gl | E69: =+'01'!E17 -> 1 | H69: =+J69/E69 -> 0 | I69: =+K69/E69 -> 0 | J69: =+SUM(J70:J72) -> 0 | K69: =+SUM(K70:K72) -> 0 | Q69: =+U69/E69 -> 482995.31 | R69: =+V69/E69 -> 0 | U69: =SUM(S70:S72) -> 482995.31 | V69: =SUM(T70:T72) -> 0
C70: Gestion suministro luz de obra | D70: u | E70: 1 | J70: =+F70*E70 -> 0 | K70: =+G70*E70 -> 0 | L70: =+SUBCONTRATOS!D11 -> 157327.46 | S70: =+L70*E70 -> 157327.46 | T70: =(+M70*$M$5+N70*$N$5+O70*$O$5+P70*$P$5)*E70 -> 0
C71: Luz de Obra | D71: u | E71: 2 | J71: =+F71*E71 -> 0 | K71: =+G71*E71 -> 0 | L71: =+SUBCONTRATOS!D14 -> 113275.77 | S71: =+L71*E71 -> 226551.54 | T71: =(+M71*$M$5+N71*$N$5+O71*$O$5+P71*$P$5)*E71 -> 0
C72: Medicion PAT luz de obra | D72: u | E72: 1 | J72: =+F72*E72 -> 0 | K72: =+G72*E72 -> 0 | L72: =+SUBCONTRATOS!D18 -> 99116.3 | S72: =+L72*E72 -> 99116.3 | T72: =(+M72*$M$5+N72*$N$5+O72*$O$5+P72*$P$5)*E72 -> 0
A73: =+'01'!A18 -> 2 | C73: =+'01'!C18 -> MOVIMIENTO DE TIERRA, COMPACTACION Y RELLENO
A74: =+'01'!A19 -> 2.01 | C74: =+'01'!C19 -> Retiro de suelo vegetal e: 50 cm, aporte y compactación de tosca e: 40 cm (dos capas de 20 cm) | D74: =+'01'!D19 -> m2 | E74: =+'01'!E19 -> 219 | H74: =+J74/E74 -> 0 | I74: =+K74/E74 -> 0 | J74: =+SUM(J75:J76) -> 0 | K74: =+SUM(K75:K76) -> 0 | Q74: =+U74/E74 -> 25907.444 | R74: =+V74/E74 -> 3070.3424 | U74: =SUM(S75:S76) -> 5673730.3 | V74: =SUM(T75:T76) -> 672404.99
C75: Subcontrato + 10% - Celsi VIAL | D75: m2 | E75: =+E74*1.1 -> 240.9 | J75: =+F75*E75 -> 0 | K75: =+G75*E75 -> 0 | L75: =+SUBCONTRATOS!D25 -> 23552.222 | S75: =+L75*E75 -> 5673730.3 | T75: =(+M75*$M$5+N75*$N$5+O75*$O$5+P75*$P$5)*E75 -> 0
C76: Ayuda de gremios | D76: d | E76: 5 | J76: =+F76*E76 -> 0 | K76: =+G76*E76 -> 0 | P76: 2 | S76: =+L76*E76 -> 0 | T76: =(+M76*$M$5+N76*$N$5+O76*$O$5+P76*$P$5)*E76 -> 672404.99
A77: =+'01'!A20 -> 2.02 | C77: =+'01'!C20 -> Excavación para cámara transformadora | D77: =+'01'!D20 -> m3 | E77: =+'01'!E20 -> 100 | H77: =+J77/E77 -> 0 | I77: =+K77/E77 -> 0 | J77: =+SUM(J78:J81) -> 0 | K77: =+SUM(K78:K81) -> 0 | Q77: =+U77/E77 -> 24440 | R77: =+V77/E77 -> 6724.0499 | U77: =SUM(S78:S81) -> 2444000 | V77: =SUM(T78:T81) -> 672404.99
C78: Maquina x dia | D78: d | E78: 3 | J78: =+F78*E78 -> 0 | K78: =+G78*E78 -> 0 | L78: =+SUBCONTRATOS!D26 -> 528000 | S78: =+L78*E78 -> 1584000 | T78: =(+M78*$M$5+N78*$N$5+O78*$O$5+P78*$P$5)*E78 -> 0
C79: Viajes camión | D79: u | E79: =+ROUNDUP(E77/20,0) -> 5 | J79: =+F79*E79 -> 0 | K79: =+G79*E79 -> 0 | L79: =+SUBCONTRATOS!D27 -> 140000 | S79: =+L79*E79 -> 700000 | T79: =(+M79*$M$5+N79*$N$5+O79*$O$5+P79*$P$5)*E79 -> 0
C80: Traslado | D80: u | E80: 2 | J80: =+F80*E80 -> 0 | K80: =+G80*E80 -> 0 | L80: =+SUBCONTRATOS!D28 -> 80000 | S80: =+L80*E80 -> 160000 | T80: =(+M80*$M$5+N80*$N$5+O80*$O$5+P80*$P$5)*E80 -> 0
C81: Ayuda de gremios / Perfilado | D81: d | E81: 5 | J81: =+F81*E81 -> 0 | K81: =+G81*E81 -> 0 | P81: 2 | S81: =+L81*E81 -> 0 | T81: =(+M81*$M$5+N81*$N$5+O81*$O$5+P81*$P$5)*E81 -> 672404.99
A82: =+'01'!A23 -> 3 | C82: =+'01'!C23 -> ESTRUCTURA RESISTENTE
A83: =+'01'!A24 -> 3.01 | B83: =+'01'!B24 -> OK | C83: =+'01'!C24 -> Hormigón de limpieza - e: 10 cm | D83: =+'01'!D24 -> m3 | E83: =+'01'!E24 -> 3 | H83: =+J83/E83 -> 120430 | I83: =+K83/E83 -> 0 | J83: =+SUM(J84:J87) -> 361290 | K83: =+SUM(K84:K87) -> 0 | Q83: =+U83/E83 -> 0 | R83: =+V83/E83 -> 155041.22 | U83: =SUM(S84:S87) -> 0 | V83: =SUM(T84:T87) -> 465123.66
C84: H13 | D84: m3 | E84: =+$E$83 -> 3 | F84: =+Cotizaciones!D28 -> 115100 | J84: =+F84*E84 -> 345300 | K84: =+G84*E84 -> 0 | S84: =+L84*E84 -> 0 | T84: =(+M84*$M$5+N84*$N$5+O84*$O$5+P84*$P$5)*E84 -> 0
C85: Bombeo | D85: m3 | E85: =+$E$83 -> 3 | F85: =+Cotizaciones!D30 -> 5330 | J85: =+F85*E85 -> 15990 | K85: =+G85*E85 -> 0 | S85: =+L85*E85 -> 0 | T85: =(+M85*$M$5+N85*$N$5+O85*$O$5+P85*$P$5)*E85 -> 0
C86: Bomba | D86: u | E86: 0 | F86: =+Cotizaciones!D29 -> 533000 | J86: =+F86*E86 -> 0 | K86: =+G86*E86 -> 0 | S86: =+L86*E86 -> 0 | T86: =(+M86*$M$5+N86*$N$5+O86*$O$5+P86*$P$5)*E86 -> 0
C87: M.O | D87: d | E87: 1 | J87: =+F87*E87 -> 0 | K87: =+G87*E87 -> 0 | M87: 1 | N87: 2 | P87: 3 | S87: =+L87*E87 -> 0 | T87: =(+M87*$M$5+N87*$N$5+O87*$O$5+P87*$P$5)*E87 -> 465123.66
A88: =+'01'!A25 -> 3.02 | B88: =+'01'!B25 -> OK | C88: =+'01'!C25 -> Micropilotes Ø 20 cm | D88: =+'01'!D25 -> gl | E88: =+'01'!E25 -> 1 | H88: =+J88/E88 -> 11090041 | I88: =+K88/E88 -> 0 | J88: =+SUM(J89:J95) -> 11090041 | K88: =+SUM(K89:K95) -> 0 | Q88: =+U88/E88 -> 34350000 | R88: =+V88/E88 -> 2460301.5 | U88: =SUM(S89:S95) -> 34350000 | V88: =SUM(T89:T95) -> 2460301.5
C89: Mano de Obra, perforacion e inyección | D89: gl | E89: 1 | J89: =+F89*E89 -> 0 | K89: =+G89*E89 -> 0 | L89: =+SUBCONTRATOS!D93 -> 34350000 | S89: =+L89*E89 -> 34350000 | T89: =(+M89*$M$5+N89*$N$5+O89*$O$5+P89*$P$5)*E89 -> 0
C90: Movilización | D90: gl | E90: 1 | J90: =+F90*E90 -> 0 | K90: =+G90*E90 -> 0 | L90: =+SUBCONTRATOS!D92 -> 950000 | T90: =(+M90*$M$5+N90*$N$5+O90*$O$5+P90*$P$5)*E90 -> 0
C91: Cemento | D91: bol | E91: =+SUBCONTRATOS!J93 -> 1100 | F91: =+Cotizaciones!D65 -> 7809.92 | J91: =+F91*E91 -> 8590912 | K91: =+G91*E91 -> 0 | S91: =+L91*E91 -> 0 | T91: =(+M91*$M$5+N91*$N$5+O91*$O$5+P91*$P$5)*E91 -> 0
C92: Hierro | D92: kg | E92: =+SUBCONTRATOS!P97 -> 800 | F92: =+Cotizaciones!D41 -> 1338.79 | J92: =+F92*E92 -> 1071032 | K92: =+G92*E92 -> 0 | S92: =+L92*E92 -> 0 | T92: =(+M92*$M$5+N92*$N$5+O92*$O$5+P92*$P$5)*E92 -> 0
C93: Volquetes p/barro | D93: u | E93: 6 | F93: 150000 | J93: =+F93*E93 -> 900000 | K93: =+G93*E93 -> 0 | S93: =+L93*E93 -> 0 | T93: =(+M93*$M$5+N93*$N$5+O93*$O$5+P93*$P$5)*E93 -> 0
C94: Consumibles | D94: gl | E94: 0.05 | F94: =+SUM(J89:K93) -> 10561944 | J94: =+F94*E94 -> 528097.2 | K94: =+G94*E94 -> 0 | S94: =+L94*E94 -> 0 | T94: =(+M94*$M$5+N94*$N$5+O94*$O$5+P94*$P$5)*E94 -> 0
C95: M.O cortado y doblado | D95: d | E95: 10 | J95: =+F95*E95 -> 0 | K95: =+G95*E95 -> 0 | M95: 1 | N95: 1 | P95: 1 | S95: =+L95*E95 -> 0 | T95: =(+M95*$M$5+N95*$N$5+O95*$O$5+P95*$P$5)*E95 -> 2460301.5
A96: =+'01'!A45 -> 3.22 | C96: =+'01'!C45 -> Picado de medianeras para columnas y vigas - Cotizado solo para PB, 1P, NO contempla picado en CT | D96: =+'01'!D45 -> m2 | E96: =+'01'!E45 -> 65 | H96: =+J96/E96 -> 4615.3846 | I96: =+K96/E96 -> 4615.3846 | J96: =SUM(J97:J99) -> 300000 | K96: =SUM(K97:K99) -> 300000 | Q96: =+U96/E96 -> 0 | R96: =+V96/E96 -> 20224.016 | U96: =SUM(S97:S99) -> 0 | V96: =SUM(T97:T99) -> 1314561.1
C97: Consumibles - Punta martillo | D97: gl | E97: 1 | G97: 300000 | J97: =+F97*E97 -> 0 | K97: =+G97*E97 -> 300000 | S97: =+L97*E97 -> 0 | T97: =(+M97*$M$5+N97*$N$5+O97*$O$5+P97*$P$5)*E97 -> 0
C98: Volquetes | D98: u | E98: =+ROUNDUP(E96*0.2/5,0) -> 3 | F98: 100000 | J98: =+F98*E98 -> 300000 | K98: =+G98*E98 -> 0 | S98: =+L98*E98 -> 0 | T98: =(+M98*$M$5+N98*$N$5+O98*$O$5+P98*$P$5)*E98 -> 0
C99: 12 | D99: d | E99: =+ROUNDUP(E96/C99,0) -> 6 | J99: =+F99*E99 -> 0 | K99: =+G99*E99 -> 0 | N99: 1 | P99: 2 | S99: =+L99*E99 -> 0 | T99: =(+M99*$M$5+N99*$N$5+O99*$O$5+P99*$P$5)*E99 -> 1314561.1
A100: =+'01'!A46 -> 4 | C100: =+'01'!C46 -> MAMPOSTERÍA
A101: =+'01'!A52 -> 4.06 | B101: =+'01'!B52 -> OK | C101: =+'01'!C52 -> Vigas de encadenado - En muros de PB, incl. excavación y armado | D101: =+'01'!D52 -> ml | E101: =+'01'!E52 -> 24 | H101: =+J101/E101 -> 23405.012 | I101: =+K101/E101 -> 0 | J101: =SUM(J102:J108) -> 561720.28 | Q101: =+U101/E101 -> 0 | R101: =+V101/E101 -> 36357.144 | U101: =SUM(S102:S108) -> 0 | V101: =SUM(T102:T108) -> 872571.45
C102: Excavación | D102: m3 | E102: =+Computo!H13 -> 3 | J102: =+F102*E102 -> 0 | K102: =+G102*E102 -> 0 | P102: 1 | S102: =+L102*E102 -> 0 | T102: =(+M102*$M$5+N102*$N$5+O102*$O$5+P102*$P$5)*E102 -> 201721.5 | X102: =+P102*$E102/$E$101 -> 0.125
C103: Volquete | D103: u | E103: =+ROUNDUP(E102/5,0) -> 1 | F103: 100000 | J103: =+F103*E103 -> 100000 | K103: =+G103*E103 -> 0 | S103: =+L103*E103 -> 0 | T103: =(+M103*$M$5+N103*$N$5+O103*$O$5+P103*$P$5)*E103 -> 0
...

Sheet GGBB
H2: 45846 | O2: 24
F3: MESES | G3: DÓLAR BNA | H3: DÓLAR MEP | M3: Descrip | N3: Mes | O3: Total Dias
B4: GASTOS GENERALES y BENEFICIO | F4: =+ROUNDUP(N21,0) -> 19 | G4: 1280 | H4: 1276 | M4: Prelim | N4: 0.5 | O4: =+N4*$O$2 -> 12 | Q4: Syh permanente
M5: Micropilotes | N5: 2 | O5: =+N5*$O$2 -> 48 | Q5: =+ROUNDUP(SUM(N6),0) -> 1
B6: Gastos Grales de obra en items | C6: Un | D6: Meses | E6: Cant | F6: Precio Unit | G6: Subtotal | H6: =SUM(G7:G10) -> 3040000 | M6: Subsuelo y VF | N6: 1 | O6: =+N6*$O$2 -> 24
B7: Oficina en obra (6x3 c/AA) | C7: mes | D7: =+$F$4 -> 19 | E7: 0 | F7: =E7*I7+J7 -> 0 | G7: =+F7*D7*E7 -> 0 | M7: Losa sobre PB | N7: 1 | O7: =+N7*$O$2 -> 24
B8: Obrador 6x3 s/AA | C8: mes | D8: =+$F$4 -> 19 | E8: 0 | F8: =E8*I8+J8 -> 0 | G8: =+F8*D8*E8 -> 0 | M8: Losa sobre 1 | N8: 0.75 | O8: =+N8*$O$2 -> 18
B9: Pañol (6x3) | C9: mes | D9: =+$F$4 -> 19 | E9: 0 | F9: 180000 | G9: =+F9*D9*E9 -> 0 | M9: Losa sobre 2 | N9: 0.75 | O9: =+N9*$O$2 -> 18
B10: Baños | C10: mes | D10: =+$F$4 -> 19 | E10: 2 | F10: 80000 | G10: =+F10*D10*E10 -> 3040000 | M10: Losa sobre 3 | N10: 0.75 | O10: =+N10*$O$2 -> 18
B11: Gastos Grales de obra en items | H11: =SUM(G12:G19) -> 39866835 | M11: Losa sobre 4 | N11: 0.75 | O11: =+N11*$O$2 -> 18 | P11: Inicio mamposteria | Q11: Meses H° | R11: Estacionamiento en contramano
B12: HyS permanente | C12: mes | D12: =+Q5 -> 1 | E12: 1 | G12: =+F12*D12*E12 -> 0 | J12: =+'P.MO 06.25'!C9/2 -> 1623254.5 | K12: =+J12*D12*E12 -> 1623254.5 | M12: Losa sobre 5 | N12: 0.75 | O12: =+N12*$O$2 -> 18 | Q12: =+SUM(N6:N15) -> 7.5 | R12: =+ROUNDUP(Q12/3,0) -> 3
B13: HyS | C13: mes | D13: =+$F$4 -> 19 | E13: 1 | G13: =+F13*D13*E13 -> 0 | J13: 300000 | K13: =+J13*D13*E13 -> 5700000 | M13: Losa sobre 6 | N13: 0.75 | O13: =+N13*$O$2 -> 18
B14: Energía de obra | C14: mes | D14: =+$F$4 -> 19 | E14: 0.5 | F14: 200000 | G14: =+F14*D14*E14 -> 1900000 | M14: Losa sobre 7 | N14: 0.5 | O14: =+N14*$O$2 -> 12
B15: Agua de obra | C15: mes | D15: =+$F$4 -> 19 | E15: 1 | F15: 300000 | G15: =+F15*D15*E15 -> 5700000 | M15: Losa Techos | N15: 0.5 | O15: =+N15*$O$2 -> 12
B16: Internet | C16: mes | D16: =+$F$4 -> 19 | E16: 1 | F16: 75000 | G16: =+F16*D16*E16 -> 1425000 | M16: Mampostería | N16: 2 | O16: =+N16*$O$2 -> 48
B17: Alquiler cerco de obra chapa | C17: mes | D17: =+$F$4 -> 19 | E17: 0 | F17: 10000 | G17: =+F17*D17*E17 -> 0 | M17: Revoques, contrap y carp | N17: 2 | O17: =+N17*$O$2 -> 48
B18: Proyecto Ejecutivo | C18: mes | D18: =+$F$4 -> 19 | E18: 0 | F18: =+'P.MO 06.25'!C9 -> 3246508.9 | G18: =+F18*D18*E18 -> 0 | M18: Colocación | N18: 2 | O18: =+N18*$O$2 -> 48
B19: Proyecto (50%) | C19: mes | D19: =+$F$4 -> 19 | E19: 0.5 | F19: =+'P.MO 06.25'!C9 -> 3246508.9 | G19: =+F19*D19*E19 -> 30841835 | M19: Pintura | N19: 2 | O19: =+N19*$O$2 -> 48
B20: Gastos Directos | H20: =SUM(G21:G30) -> 89942566 | M20: Terminaciones | N20: 1 | O20: =+N20*$O$2 -> 24
B21: Coordinacion de obra | C21: mes | D21: =+$F$4 -> 19 | E21: 0.15 | F21: =+'P.MO 06.25'!C11 -> 5688802.4 | G21: =+F21*D21*E21 -> 16213087 | N21: =SUM(N4:N20) -> 19 | O21: =SUM(O4:O20) -> 456
B22: Jefe de obra | C22: mes | D22: =+$F$4 -> 19 | E22: 0.2 | F22: =+'P.MO 06.25'!C10 -> 4716669.4 | G22: =+F22*D22*E22 -> 17923344
B23: Sobrestante | C23: mes | D23: =+$F$4 -> 19 | E23: 1 | G23: =+F23*D23*E23 -> 0 | J23: =+'P.MO 06.25'!C9 -> 3246508.9 | K23: =+J23*D23*E23 -> 61683669
B24: Administrativo en obra | C24: mes | D24: =+$F$4 -> 19 | E24: 0 | F24: =+J23 -> 3246508.9 | G24: =+F24*D24*E24 -> 0
B25: Capataz | C25: mes | D25: =+$F$4 -> 19 | E25: 0.5 | F25: =+'P.MO 06.25'!C12 -> 3874330.1 | G25: =+F25*D25*E25 -> 36806136
B26: Logistica | C26: mes | D26: =+$F$4 -> 19 | E26: 1 | F26: 500000 | G26: =+F26*D26*E26 -> 9500000
B27: Vehiculo obra | C27: mes | D27: =+$F$4 -> 19 | E27: 1 | F27: =F26 -> 500000 | G27: =+F27*D27*E27 -> 9500000
B28: Mov y viaticos | C28: mes | D28: =+$F$4 -> 19 | E28: 1 | G28: =+F28*D28*E28 -> 0 | J28: =F26 -> 500000 | K28: =+J28*D28*E28 -> 9500000
B29: UOCRA | C29: mes | D29: =+$F$4 -> 19 | E29: 1 | G29: =+F29*D29*E29 -> 0
B30: Pañolero/Sereno | C30: mes | D30: =+$F$4 -> 19 | E30: 1 | J30: =+'P.MO 06.25'!C7/2 -> 806885.99 | K30: =+J30*D30*E30 -> 15330834
B31: Equipos | H31: =SUM(G32:G36) -> 0
B32: Bobcat | C32: mes | F32: 130000 | G32: =+F32*D32 -> 0
B33: Camion limpieza | C33: mes | F33: 100000 | G33: =+F33*D33 -> 0
B34: Tijera electrica 12 | C34: mes | F34: 33600 | G34: =+F34*D34 -> 0
B35: JLG | C35: mes | F35: 89000 | G35: =+F35*D35 -> 0
B36: Grua 20ton | C36: mes | F36: 70000 | G36: =+F36*D36 -> 0
B37: Gastos Indirectos | H37: =SUM(G38:G42) -> 94164835
B38: Admin (50%Compras - 50%RRHH) | C38: mes | D38: =+$F$4 -> 19 | E38: 0.5 | F38: ='P.MO 06.25'!C9 -> 3246508.9 | G38: =+F38*D38*E38 -> 30841835
B39: Seguros | C39: gl | D39: =+D38 -> 19 | E39: 1 | F39: 250000 | G39: =+F39*D39 -> 4750000
B40: IIBB (monto venta obra gris) | C40: gl | D40: 0.04 | E40: 0.7 | F40: 1550000000 | G40: =+F40*D40*E40 -> 43400000
B41: Imp cheque | C41: gl | D41: =1.2/100 -> 0.012 | E41: =+E40 -> 0.7 | F41: =+F40*1.15 -> 1.7825e+09 | G41: =+F41*D41*E41 -> 14973000
B42: Contrato | C42: gl | D42: 1 | E42: 1 | F42: 200000 | G42: =+F42*D42*E42 -> 200000
G43: =SUM(G7:G42) -> 2.2701424e+08 | H43: =SUM(H6:H42) -> 2.2701424e+08 | K43: =SUM(K6:K42) -> 93837758 | L43: =+H43+K43 -> 3.2085199e+08
B44: Monto puesto en Ayuda de gremio que no se eroga | K44: Imputados en pres | L44: Total GGBB
B45: Total de Gastos Generales | H45: =+H44+H43 -> 2.2701424e+08 | L45: =+L43/G53 -> 0.28250277
B47: Otro | G47: =+'01'!N213 -> 2.8879873e+08 | H47: =+G47/$H$4 -> 226331.29
B48: Corralon | G48: =+'01'!O213 -> 92826298 | H48: =+G48/$H$4 -> 72747.882
B49: Subcontratos | G49: =+'01'!P213 -> 5.0875886e+08 | H49: =+G49/$H$4 -> 398713.84
B50: Mano de obra | G50: =+'01'!Q213 -> 2.1954745e+08 | H50: =+G50/$H$4 -> 172059.13
B51: Equipos | G51: =+'01'!R213 -> 25816814 | H51: =+G51/$H$4 -> 20232.613
A53: A | G53: =SUM(G47:G52) -> 1.1357481e+09 | H53: =SUM(H47:H52) -> 890084.76
J54: =+G53-G51 -> 1.1099313e+09
B55: GG | F55: =+H45/G53 -> 0.19988079 | G55: =+F55*$G$53 -> 2.2701424e+08 | H55: =+G55/$H$4 -> 177910.84 | J55: =+J54*K55 -> 33297940 | K55: 0.03
B56: Equipos | E56: 3 | F56: =+G56/G53 -> 0.0065869586 | G56: =+J56 -> 7481126 | H56: =+G56/$H$4 -> 5862.9514 | J56: =+J55-G51 -> 7481126
B57: Imprevistos + Negociación | E57: 5 | F57: 0.05 | G57: =+F57*$G$53 -> 56787407 | H57: =+G57/$H$4 -> 44504.238
B58: Beneficio | E58: 9 | F58: 0.1 | G58: =+F58*$G$53 -> 1.1357481e+08 | H58: =+G58/$H$4 -> 89008.476
A59: B | F59: =SUM(F55:F58) -> 0.35646775 | G59: =SUM(G55:G58) -> 4.0485758e+08 | H59: =+G59/$H$4 -> 317286.51
A61: K | F61: =1+F59 -> 1.3564677 | G61: =+G53*F61 -> 1.5406057e+09
A63: A+B | G63: =+G53+G59 -> 1.5406057e+09 | H63: =+G63/$H$4 -> 1207371.3

Sheet Locales
J2: H Promedio | N2: ALBAÑILERIA | U2: REVOQUES | AD2: AISLACIONES | AL2: CIELORRASOS | AW2: CARPINTERIAS | BD2: PISOS (m2) | BL2: ZOCALOS (ml) | BQ2: TERMINACIONES | CB2: ELECTRICIDAD | CZ2: ART SANITARIO | DE2: GRIFERIAS
J3: H a revisar | N3: CONTRAPISOS | Q3: CARPETAS | U3: CEMENTICIO | Z3: YESO | AL3: SECO | AR3: YESO | AU3: H°A° | AW3: Puertas | BB3: Ventanas | BQ3: REV | BT3: PAREDES | BW3: CIELORRASO | CB3: ARTEFACTOS ILUM | CE3: TENSION | CV3: MBT
J4: Revisar | N4: C1 | O4: C2 | P4: C3 | Q4: C4 | R4: C5 | S4: C6 | U4: R1 | V4: R2 | W4: R3 | X4: R4 | Y4: R5 | Z4: R6 | AA4: R7 | AB4: R8 | AD4: A1 | AE4: A1.1 | AF4: A2 | AG4: A3 | AH4: A4 | AI4: A5 | AJ4: A5.1 | AL4: C1 | AM4: C2 | AN4: C3 | AO4: C4 | AP4: C5 | AQ4: C6 | AR4: C7 | AS4: C8 | AT4: C9 | AU4: C10 | AW4: P1 | AX4: P2 | AY4: P3 | AZ4: P4 | BA4: P5 | BB4: PM | BD4: P1 | BE4: P2 | BF4: P3 | BG4: P4 | BH4: P5 | BI4: P6 | BJ4: P7 | BK4: S1 | BL4: Z1 | BM4: Z2 | BN4: Z3 | BO4: Z4 | BQ4: RV1 | BR4: RV2 | BS4: RV3 | BT4: PI1 | BU4: PI2 | BV4: PI4 | BW4: PCI1 | BX4: PCI2 | BY4: PCI3 | BZ4: PCI4 | CB4: AI1 | CC4: AI2 | CD4: AI3 | CE4: IL1 | CF4: IL2 | CG4: IL3 | CH4: IL4 | CI4: IL5 | CJ4: IL6 | CK4: IL7 | CL4: IL8 | CM4: IL9 | CN4: IL10 | CO4: IL11 | CP4: IL12 | CQ4: IL13 | CR4: IL14 | CS4: IL15 | CT4: IL16 | CU4: IL17 | CV4: BT1 | CW4: BT2 | CX4: BT3 | CZ4: IS1 | DA4: IS2 | DB4: IS3 | DC4: IS4 | DD4: IS5 | DE4: IS6 | DF4: IS7 | DG4: IS8 | DH4: IS9 | DI4: IS10
J5: Revisado | N5: MC | O5: MC | P5: MC | Q5: MC | R5: MC | S5: MC | U5: MC | V5: MC | W5: MC | X5: MC | Y5: MC | Z5: MC | AA5: MC | AB5: MC | AD5: MC | AE5: MC | AF5: MC | AG5: MC | AH5: MC | AI5: MC | AJ5: MC | AL5: MC | AM5: MC | AN5: MC | AO5: MC | AP5: MC | AQ5: MC | AR5: MC | AS5: MC | AT5: MC | AU5: MC | AW5: MC | AX5: MC | AY5: MC | AZ5: MC | BA5: MC | BB5: MC | BD5: MC | BE5: MC | BF5: MC | BG5: MC | BH5: MC | BI5: MC | BJ5: MC | BK5: MC | BL5: MC | BM5: MC | BN5: MC | BO5: MC | BQ5: MC | BR5: MC | BS5: MC | BT5: MC | BU5: MC | BV5: MC | BW5: MC | BX5: MC | BY5: MC | BZ5: MC
C6: CHIVILCOY 2171 | N6: Contrapiso alivianado c/ pendiente en azotea | O6: Contrapiso s/ss | P6: Contrapiso armado s/ suelo nat | Q6: Monolitico | R6: Carpeta | S6: Carpeta s/ membrana | U6: Revoque 2 en 1 | V6: Aristas (esq. Metalico) | W6: Cantonera en revoque | X6: Grueso bajo reves | Y6: Revoque 3 en 1 | Z6: Yeso | AA6: Aristas (esq. Metalico) | AB6: Cantoneras | AD6: Aislacion Horizontal en Baños | AE6: Babeta | AF6: Aislaciòn hidrofuga sobre contrapiso | AG6: Barrera de vapor (pintura asfaltica) | AH6: Aislaciòn termica EPS | AI6: Membrana geotextil - Balcones y azotea | AJ6: Babeta | AL6: Suspendido placa STD | AM6: Suspendido placa RH | AN6: Buña "Z" Durlock | AO6: Cantonera dk | AP6: Cajòn durlock | AQ6: Garganta | AR6: Yeso aplicado | AS6: Buña de Yeso | AT6: Arista | AU6: Hormigon visto / Maquillaje | AW6: Puerta placa F30 de 90cm (acceso a UF) | AX6: Pueras F60 | AY6: Puerta placa MDF (blanco semi mate) | AZ6: Puerta de chapa (espacios comunes) | BA6: Frente ascensor | BB6: Premarco | BD6: Porcelanato exterior | BE6: Palieres / Terrazas | BF6: Porcelanato en UF | BG6: Porcelanato en baños | BH6: Alisado de cemento rodillado | BI6: Sustrato | BJ6: Baldosas 40x40 | BK6: Solia de entrada | BL6: MDF Pintado | BM6: Concreto | BN6: Porcelanato UF | BO6: Porcelanato | BQ6: Revestimiento cocina | BR6: Revestimiento baño | BS6: Revestimiento texturado con llana metalica | BT6: Latex interior color a definir enduido completo | BU6: Latex interior color a definir enduido parcial | BV6: Latex interior color a definir s/ enduido | BW6: Latex interior color a definir enduido completo | BX6: Latex interior color a definir enduido parcial | BY6: Revestimiento plastico | BZ6: Latex exterior color a definir s/ enduido | CB6: Extractor | CC6: Espacio comun/balcones | CD6: Luz de emergencia | CE6: Boca ilum losa | CF6: Boca ilum pared | CG6: Caja para led | CH6: Pulsador | CI6: Tecla 1 mod | CJ6: Tecla 2 mod | CK6: Tecla 3 mod | CL6: Tomas simple | CM6: Toma doble | CN6: Toma encapsulado | CO6: Toma Esp. Anafe/Horno | CP6: Toma A/A | CQ6: Tablero 1 amb | CR6: Tablero 2/3 amb | CS6: Tablero SG | CT6: Tablero TSFM | CU6: Tablero TSBT | CV6: Pulsador timbre | CW6: Boca de Portero | CX6: Boca TV | CZ6: Indoro Roca monaco | DA6: Bidet Roca monaco | DB6: Bacha de losa Roca | DC6: Bañera Roca | DD6: Bacha A.I Johnson | DE6: Accesorios de Baño FV alerce o similar | DF6: Griferia de lavarotio FV alerce o similar | DG6: Griferia de bidet 3 agujeros con tapita FV alerce o similar | DH6: Griferia de ducha FV alerce o similar | DI6: Griferia de cocina FV alerce o similar
A7: PLANTA | B7: Nº | C7: LOCAL | D7: Largo | E7: Ancho | F7: SUP | G7: perim unit | H7: vacio | I7: perim real | J7: H | K7: H r | L7: aux | N7: m2 | O7: m2 | P7: m2 | Q7: m2 | R7: m2 | S7: m2 | U7: m2 | V7: ml | W7: un | X7: m2 | Y7: m2 | Z7: m2 | AA7: ml | AB7: un | AD7: m2 | AE7: ml | AF7: m2 | AG7: m2 | AH7: m2 | AI7: m2 | AJ7: ml | AL7: m2 | AM7: m2 | AN7: ml | AO7: ml | AP7: ml | AQ7: ml | AR7: m2 | AS7: ml | AT7: ml | AU7: m2 | AW7: u | AX7: u | AY7: u | AZ7: u | BA7: u | BB7: u | BD7: m2 | BE7: m2 | BF7: m2 | BG7: m2 | BH7: m2 | BI7: m2 | BJ7: m2 | BK7: ml | BL7: ml | BM7: ml | BN7: ml | BO7: ml | BQ7: m2 | BR7: m2 | BS7: m2 | BT7: m2 | BU7: m2 | BV7: m2 | BW7: m2 | BX7: m2 | BY7: m2 | BZ7: m2 | CB7: un | CC7: un | CD7: un | CE7: un | CF7: un | CG7: un | CH7: un | CI7: un | CJ7: un | CK7: un | CL7: un | CM7: un | CN7: un | CO7: un | CP7: un | CQ7: un | CR7: un | CS7: un | CT7: un | CU7: un | CV7: un | CW7: un | CX7: un | CZ7: un | DA7: un | DB7: un | DC7: un | DD7: un | DE7: un | DF7: un | DG7: un | DH7: un | DI7: un
A8: Subsuelo | B8: 1 | C8: CT | D8: 5 | E8: 4.13 | F8: =D8*E8 -> 20.65 | G8: =+D8*2+E8*2 -> 18.26 | I8: =+G8-H8 -> 18.26 | J8: 3.5 | O8: =+F8 -> 20.65 | U8: =+I8*J8 -> 63.91 | AU8: =+F8 -> 20.65 | BV8: =+I8*J8 -> 63.91 | BZ8: =+F8 -> 20.65
A9: PB | B9: 2 | C9: Vereda | D9: 8.1 | E9: 3.2 | F9: =D9*E9 -> 25.92 | G9: =+D9*2+E9*2 -> 22.6 | H9: 0 | I9: =+G9-H9 -> 22.6 | L9: =7.5*1.4 -> 10.5 | P9: =+F9 -> 25.92 | AF9: =+F9 -> 25.92 | AU9: =+L9 -> 10.5 | BJ9: =+F9 -> 25.92 | BZ9: =+L9 -> 10.5 | CC9: 3 | CF9: 3
B10: 3 | C10: Acceso cocheras exterior | D10: 4.03 | E10: 3 | F10: =D10*E10 -> 12.09 | G10: =+D10*2+E10*2 -> 14.06 | H10: =+D11+E10*2 -> 9.73 | I10: =+G10-H10 -> 4.33 | J10: 3 | P10: =+F10 -> 12.09 | AF10: =+F10 -> 12.09 | AU10: =+F10 -> 12.09 | BJ10: =+F10 -> 12.09 | BZ10: =+F10 -> 12.09 | CC10: 1 | CE10: 1
B11: 4 | C11: Medidores de luz | D11: 3.73 | E11: 0.4 | F11: =D11*E11 -> 1.492 | G11: =+D11*2+E11*2 -> 8.26 | H11: =+D11 -> 3.73 | I11: =+G11-H11 -> 4.53 | J11: 3 | P11: =+F11 -> 1.492 | AF11: =+F11 -> 1.492 | AU11: =+F11 -> 1.492 | BH11: =+F11 -> 1.492 | BZ11: =+F11 -> 1.492 | CM11: 1
B12: 5 | C12: Ingreso vehicular | D12: =13.04-D13 -> 6.9 | E12: 4.13 | F12: =D12*E12 -> 28.497 | G12: =+D12*2+E12*2 -> 22.06 | H12: =+E12*2 -> 8.26 | I12: =+G12-H12 -> 13.8 | J12: 3 | P12: =+F12 -> 28.497 | AF12: =+F12 -> 28.497 | AU12: =+F12 -> 28.497 | BJ12: =+F12 -> 28.497 | BZ12: =+F12 -> 28.497 | CC12: 2 | CE12: 2 | CM12: 1 | CS12: 1
B13: 6 | C13: Ingreso vehicular s/cielorraso | D13: 6.14 | E13: 4.13 | F13: =D13*E13 -> 25.3582 | G13: =+D13*2+E13*2 -> 20.54 | H13: =+E13*2 -> 8.26 | I13: =+G13-H13 -> 12.28 | J13: 3 | P13: =+F13 -> 25.3582 | AF13: =+F13 -> 25.3582 | BJ13: =+F13 -> 25.3582 | CC13: 2 | CF13: 2 | CM13: 1
B14: 7 | C14: Espacio guardacoche | D14: 7.93 | E14: 7.76 | F14: =D14*E14 -> 61.5368 | G14: =+D14*2+E14*2 -> 31.38 | H14: =+E14+E12 -> 11.89 | I14: =+G14-H14 -> 19.49 | J14: 3 | L14: =7.45*1.5 -> 11.175 | P14: =+F14 -> 61.5368 | AF14: =+F14 -> 61.5368 | AU14: =+F14+L14 -> 72.7118 | BJ14: =+F14 -> 61.5368 | BZ14: =+F14+L14 -> 72.7118 | CC14: 4 | CE14: 4
B15: 8 | C15: Terreno absorbente | F15: 48.35 | G15: 27.98 | H15: =+E14 -> 7.76 | I15: =+G15-H15 -> 20.22 | J15: 3 | CC15: 2 | CF15: 2
B16: 9 | C16: Medidor de gas | D16: 1 | E16: 0.6 | F16: =D16*E16 -> 0.6 | G16: =+D16*2+E16*2 -> 3.2 | H16: =+D16 -> 1 | I16: =+G16-H16 -> 2.2 | J16: 3 | P16: =+F16 -> 0.6 | AF16: =+F16 -> 0.6 | AU16: =+F16 -> 0.6 | BH16: =+F16 -> 0.6
B17: 10 | C17: Paso | F17: 26.12 | G17: 40.61 | H17: 1.55 | I17: =+G17-H17 -> 39.06 | J17: 3 | L17: 4 | P17: =+F17 -> 26.12 | AF17: =+F17 -> 26.12 | AM17: =+L17 -> 4 | AN17: =+AM17 -> 4 | AO17: =+H17*2 -> 3.1 | AU17: =+F17-AM17 -> 22.12 | BA17: 1 | BJ17: =+F17 -> 26.12 | BW17: =+L17 -> 4 | BZ17: =+F17-BW17 -> 22.12 | CC17: 7 | CD17: 2 | CE17: 9 | CH17: 1 | CM17: 1
B18: 11 | C18: Esp. Pers. Mant. Frente | F18: 6.09 | G18: 11.1 | H18: 0 | I18: =+G18-H18 -> 11.1 | J18: 3 | P18: =+F18 -> 6.09 | U18: =+I18*J18 -> 33.3 | V18: =+W18*J18 -> 3 | W18: 1 | AF18: =+F18 -> 6.09 | AU18: =+F18 -> 6.09 | AZ18: 1 | BH18: =+F18 -> 6.09 | BM18: =+I18 -> 11.1 | BV18: =+I18*J18 -> 33.3 | BZ18: =+F18 -> 6.09 | CC18: 1 | CE18: 1 | CI18: 1 | CM18: 2
B19: 12 | C19: Sala tanques de bombeo | D19: 3.9 | E19: 1.81 | F19: =D19*E19 -> 7.059 | G19: =+D19*2+E19*2 -> 11.42 | H19: 0 | I19: =+G19-H19 -> 11.42 | J19: 3 | P19: =+F19 -> 7.059 | U19: =+I19*J19 -> 34.26 | V19: =+W19*J19 -> 0 | W19: 0 | AF19: =+F19 -> 7.059 | AU19: =+F19 -> 7.059 | AX19: 1 | BH19: =+F19 -> 7.059 | BM19: =+I19 -> 11.42 | BV19: =+I19*J19 -> 34.26 | BZ19: =+F19 -> 7.059 | CC19: 1 | CE19: 1 | CI19: 1 | CM19: 1 | CU19: 1
B20: 13 | C20: Esp. Pers. Mant. Escalera | F20: 2.89 | G20: 7.9 | H20: 0 | I20: =+G20-H20 -> 7.9 | J20: 3 | P20: =+F20 -> 2.89 | U20: =+I20*J20 -> 23.7 | V20: =+W20*J20 -> 3 | W20: 1 | AF20: =+F20 -> 2.89 | AU20: =+F20 -> 2.89 | AZ20: 1 | BH20: =+F20 -> 2.89 | BM20: =+I20 -> 7.9 | BV20: =+I20*J20 -> 23.7 | BZ20: =+F20 -> 2.89 | CC20: 1 | CE20: 1 | CI20: 1 | CM20: 1
B21: 14 | C21: Baño mantenimiento | D21: 2.24 | E21: 1.2 | F21: =D21*E21 -> 2.688 | G21: =+D21*2+E21*2 -> 6.88 | H21: 0 | I21: =+G21-H21 -> 6.88 | J21: 3 | K21: 2.3 | L21: =+J21-K21 -> 0.7 | P21: =+F21 -> 2.688 | X21: =+I21*J21 -> 20.64 | AF21: =+F21 -> 2.688 | AU21: =+F21 -> 2.688 | AZ21: 1 | BG21: =+F21 -> 2.688 | BR21: =+I21*K21 -> 15.824 | BV21: =+L21*I21 -> 4.816 | BZ21: =+F21 -> 2.688 | CC21: 1 | CE21: 1 | CI21: 1 | CM21: 1
B22: 15 | C22: Escalera | F22: 6.39 | G22: 13.48 | H22: 0 | I22: =+G22-H22 -> 13.48 | J22: 3 | U22: =+I22*J22 -> 40.44 | V22: =+W22*J22 -> 3 | W22: 1 | AF22: =+F22 -> 6.39 | AU22: =+F22 -> 6.39 | AX22: 1 | BV22: =+I22*J22 -> 40.44 | BZ22: =+F22 -> 6.39 | CC22: 2 | CD22: 1 | CE22: 2 | CH22: 1
A23: P 1 | B23: 16 | C23: Escalera | F23: 9.89 | G23: 13.1 | H23: 0 | I23: =+G23-H23 -> 13.1 | J23: 2.8 | L23: 2 | Q23: =+L23 -> 2 | U23: =+I23*J23 -> 36.68 | AU23: =+F23 -> 9.89 | AX23: 1 | BV23: =+I23*J23 -> 36.68 | BZ23: =+F23 -> 9.89 | CC23: 2 | CD23: 1 | CE23: 3 | CH23: 1
B24: 17 | C24: Hall ascensores | F24: 15.97 | G24: 30.86 | H24: 0 | I24: =+G24-H24 -> 30.86 | J24: 2.4 | L24: 1.1 | Q24: =+F24 -> 15.97 | Z24: =+I24*J24 -> 74.064 | AA24: =+AB24*J24 -> 9.6 | AB24: 4 | AL24: =+F24 -> 15.97 | AN24: =+G24 -> 30.86 | AO24: =+L24*2 -> 2.2 | BA24: 1 | BB24: 2 | BE24: =+F24 -> 15.97 | BO24: =+G24 -> 30.86 | BU24: =+I24*J24 -> 74.064 | BW24: =+F24 -> 15.97 | CC24: 7 | CD24: 2 | CE24: 9 | CH24: 3 | CM24: 1
B25: 18 | C25: A101 - Estar/Comedor/Cocina/Lav - Hall | D25: 2.35 | E25: 1.5 | F25: =D25*E25 -> 3.525 | G25: =+D25*2+E25*2 -> 7.7 | H25: =+E25+E26 -> 2.1 | I25: =+G25-H25 -> 5.6 | J25: 2.2 | Q25: =+F25 -> 3.525 | Z25: =+I25*J25 -> 12.32 | AA25: =+AB25*J25 -> 2.2 | AB25: 1 | AL25: =+F25 -> 3.525 | AN25: =+G25 -> 7.7 | AO25: =+E25 -> 1.5 | AW25: 1 | BF25: =+F25 -> 3.525 | BK25: 1 | BL25: =+I25 -> 5.6 | BU25: =+I25*J25 -> 12.32 | BW25: =+F25 -> 3.525 | CE25: 1 | CK25: 1
B26: 19 | C26: A101 - Estar/Comedor/Cocina/Lav - Cocina | D26: 2.63 | E26: 0.6 | F26: =D26*E26 -> 1.578 | G26: =+D26*2+E26*2 -> 6.46 | H26: =+D26+E26 -> 3.23 | I26: =+G26-H26 -> 3.23 | J26: 2.2 | K26: 0.9 | L26: 4.25 | Q26: =+F26 -> 1.578 | X26: =+I26*J26 -> 7.106 | AN26: =+G26 -> 6.46 | AP26: =+D26 -> 2.63 | BF26: =+F26 -> 1.578 | BL26: =+I26 -> 3.23 | BQ26: =+K26*L26 -> 3.825 | BT26: =+(I26*J26)-BQ26 -> 3.281 | BW26: =+AP26 -> 2.63 | CG26: 1 | CI26: 1 | CL26: 3 | CM26: 2 | CO26: 2 | CR26: 1 | CX26: 1
B27: 20 | C27: A101 - Estar/Comedor/Cocina/Lav - Estar | D27: 4.4 | E27: 4.13 | F27: =D27*E27 -> 18.172 | G27: =+D27*2+E27*2 -> 17.06 | H27: =+E27 -> 4.13 | I27: =+G27-H27 -> 12.93 | J27: 2.6 | Q27: =+F27 -> 18.172 | Z27: =+I27*J27 -> 33.618 | AA27: =+AB27*J27 -> 0 | AB27: 0 | AR27: =+F27 -> 18.172 | AS27: =+G27 -> 17.06 | BB27: 1 | BF27: =+F27 -> 18.172 | BL27: =+I27 -> 12.93 | BU27: =+I27*J27 -> 33.618 | BX27: =+F27 -> 18.172 | CE27: 2 | CK27: 1 | CM27: 4 | CP27: 1
B28: 21 | C28: A103 - Dormitorio | D28: 3.98 | E28: 2.51 | F28: =D28*E28 -> 9.9898 | G28: =+D28*2+E28*2 -> 12.98 | H28: 0 | I28: =+G28-H28 -> 12.98 | J28: 2.6 | Q28: =+F28 -> 9.9898 | Z28: =+I28*J28 -> 33.748 | AA28: =+AB28*J28 -> 2.6 | AB28: 1 | AR28: =+F28 -> 9.9898 | AS28: =+G28 -> 12.98 | AY28: 1 | BB28: 1 | BF28: =+F28 -> 9.9898 | BL28: =+I28 -> 12.98 | BU28: =+I28*J28 -> 33.748 | BX28: =+F28 -> 9.9898 | CE28: 1 | CI28: 1 | CM28: 3 | CP28: 1 | CX28: 1
B29: 22 | C29: A104 - Baño | F29: 3.04 | G29: 7.52 | H29: 0 | I29: =+G29-H29 -> 7.52 | J29: 2.3 | K29: 2.3 | R29: =+F29 -> 3.04 | S29: =+F29 -> 3.04 | X29: =+I29*J29 -> 17.296 | AD29: =+F29 -> 3.04 | AE29: =+G29 -> 7.52 | AM29: =+F29 -> 3.04 | AN29: =+G29 -> 7.52 | AY29: 1 | BB29: 1 | BG29: =+F29 -> 3.04 | BR29: =+I29*K29 -> 17.296 | BW29: =+F29 -> 3.04 | CE29: 1 | CF29: 1 | CJ29: 1 | CM29: 1
B30: 23 | C30: Balcon 2 amb CF | D30: 3.96 | E30: 1.4 | F30: =D30*E30 -> 5.544 | G30: =+D30*2+E30*2 -> 10.72 | H30: =+D30+(E30*2) -> 6.76 | I30: =+G30-H30 -> 3.96 | J30: 2.6 | R30: =+F30 -> 5.544 | S30: =+F30 -> 5.544 | AI30: =+F30 -> 5.544 | AJ30: =+G30 -> 10.72 | AU30: =+F30 -> 5.544 | BF30: =+F30 -> 5.544 | BN30: =+G30 -> 10.72 | BY30: =+F30 -> 5.544 | CC30: 1 | CF30: 1
B31: 24 | C31: A102 - Estar/Comedor/Cocina/Lav/Domitorio | F31: 23.33 | G31: 22.19 | H31: 0 | I31: =+G31-H31 -> 22.19 | J31: 2.6 | K31: 0.9 | L31: 3 | Q31: =+F31 -> 23.33 | X31: =+L31*J31 -> 7.8 | Z31: =+(I31*J31)-X31 -> 49.894 | AA31: =+AB31*J31 -> 5.2 | AB31: 2 | AN31: =(AP31*2)+(0.6*2) -> 5.6 | AP31: 2.2 | AR31: =+F31 -> 23.33 | AW31: 1 | BB31: 1 | BF31: =+F31 -> 23.33 | BK31: 1 | BL31: =+G31 -> 22.19 | BQ31: =+K31*L31 -> 2.7 | BT31: =(L31*J31)-BQ31 -> 5.1 | BU31: =+I31*J31-(BT31+BQ31) -> 49.894 | BW31: =+AP31 -> 2.2 | BX31: =+F31 -> 23.33 | CE31: 3 | CG31: 1 | CI31: 1 | CK31: 2 | CL31: 3 | CM31: 6 | CO31: 2 | CP31: 1 | CQ31: 1
B32: 25 | C32: A105 - Baño | F32: 3.06 | G32: 7.49 | H32: 0 | I32: =+G32-H32 -> 7.49 | J32: 2.3 | K32: 2.3 | R32: =+F32 -> 3.06 | S32: =+F32 -> 3.06 | X32: =+I32*J32 -> 17.227 | AD32: =+F32 -> 3.06 | AE32: =+G32 -> 7.49 | AM32: =+F32 -> 3.06 | AN32: =+G32 -> 7.49 | AY32: 1 | BG32: =+F32 -> 3.06 | BR32: =+I32*K32 -> 17.227 | BW32: =+F32 -> 3.06 | CB32: 1 | CE32: 1 | CF32: 1 | CK32: 1 | CM32: 1 | CX32: 1
B33: 26 | C33: Balcon mono CF | D33: 3.3 | E33: 1.4 | F33: =D33*E33 -> 4.62 | G33: =+D33*2+E33*2 -> 9.4 | H33: =+D33+(E33*2) -> 6.1 | I33: =+G33-H33 -> 3.3 | J33: 2.6 | R33: =+F33 -> 4.62 | S33: =+F33 -> 4.62 | AI33: =+F33 -> 4.62 | AJ33: =+G33 -> 9.4 | AU33: =+F33 -> 4.62 | BF33: =+F33 -> 4.62 | BN33: =+G33 -> 9.4 | BY33: =+F33 -> 4.62 | CC33: 1 | CF33: 1
B34: 27 | C34: Hall acceso 2 amb F | F34: 3.12 | G34: 7.7 | H34: 1.2 | I34: =+G34-H34 -> 6.5 | J34: 2.2 | Q34: =+F34 -> 3.12 | Z34: =+I34*J34 -> 14.3 | AA34: =+AB34*J34 -> 2.2 | AB34: 1 | AL34: =+F34 -> 3.12 | AN34: =+G34 -> 7.7 | AO34: =+H34 -> 1.2 | AW34: 1 | BF34: =+F34 -> 3.12 | BK34: 1 | BL34: =+G34 -> 7.7 | BU34: =+I34*J34 -> 14.3 | BW34: =+F34 -> 3.12 | CE34: 1 | CK34: 1 | CR34: 1
B35: 28 | C35: Cocina 2 amb F | D35: 2.83 | E35: 0.6 | F35: =D35*E35 -> 1.698 | G35: =+D35*2+E35*2 -> 6.86 | H35: =+D35 -> 2.83 | I35: =+G35-H35 -> 4.03 | J35: 2.2 | K35: 0.9 | Q35: =+F35 -> 1.698 | X35: =+I35*J35 -> 8.866 | AN35: =+G35 -> 6.86 | AP35: =+H35 -> 2.83 | BF35: =+F35 -> 1.698 | BL35: =+G35 -> 6.86 | BQ35: =+I35*K35 -> 3.627 | BT35: =+(I35*J35)-BQ35 -> 5.239 | BW35: =+AP35 -> 2.83 | CG35: 1 | CI35: 1 | CL35: 3 | CM35: 2 | CO35: 2
B36: 29 | C36: A106 - Estar/Comedor/Cocina/Lav. | D36: 4.4 | E36: 4.13 | F36: =D36*E36 -> 18.172 | G36: =+D36*2+E36*2 -> 17.06 | H36: =+E36 -> 4.13 | I36: =+G36-H36 -> 12.93 | J36: 2.6 | Q36: =+F36 -> 18.172 | Z36: =+I36*J36 -> 33.618 | AA36: =+AB36*J36 -> 5.2 | AB36: 2 | AR36: =+F36 -> 18.172 | AS36: =+G36 -> 17.06 | BB36: 1 | BF36: =+F36 -> 18.172 | BL36: =+G36 -> 17.06 | BU36: =+I36*J36 -> 33.618 | BX36: =+F36 -> 18.172 | CE36: 2 | CK36: 1 | CM36: 4 | CP36: 1 | CX36: 1
B37: 30 | C37: A107 - Baño F | F37: 3.18 | G37: 7.52 | H37: 0 | I37: =+G37-H37 -> 7.52 | J37: 2.3 | K37: 2.3 | R37: =+F37 -> 3.18 | S37: =+F37 -> 3.18 | X37: =+I37*J37 -> 17.296 | AD37: =+F37 -> 3.18 | AE37: =+G37 -> 7.52 | AM37: =+F37 -> 3.18 | AN37: =+G37 -> 7.52 | AY37: 1 | BB37: 1 | BG37: =+F37 -> 3.18 | BR37: =+I37*K37 -> 17.296 | BW37: =+F37 -> 3.18 | CE37: 1 | CF37: 1 | CJ37: 1 | CM37: 1
B38: 31 | C38: A106 - Dormitorio | D38: 3.98 | E38: 2.51 | F38: =D38*E38 -> 9.9898 | G38: =+D38*2+E38*2 -> 12.98 | I38: =+G38-H38 -> 12.98 | J38: 2.6 | Q38: =+F38 -> 9.9898 | Z38: =+I38*J38 -> 33.748 | AA38: =+AB38*J38 -> 2.6 | AB38: 1 | AR38: =+F38 -> 9.9898 | AS38: =+G38 -> 12.98 | AY38: 1 | BB38: 1 | BF38: =+F38 -> 9.9898 | BL38: =+G38 -> 12.98 | BU38: =+I38*J38 -> 33.748 | BX38: =+F38 -> 9.9898 | CE38: 1 | CI38: 1 | CM38: 3 | CP38: 1 | CX38: 1
B39: 32 | C39: Balcon 2 amb F | D39: 3.96 | E39: 1.3 | F39: =D39*E39 -> 5.148 | G39: =+D39*2+E39*2 -> 10.52 | H39: =+D39+(E39*2) -> 6.56 | I39: =+G39-H39 -> 3.96 | J39: 2.6 | R39: =+F39 -> 5.148 | S39: =+F39 -> 5.148 | AI39: =+F39 -> 5.148 | AJ39: =+G39 -> 10.52 | AU39: =+F39 -> 5.148 | BF39: =+F39 -> 5.148 | BN39: =+G39 -> 10.52 | BY39: =+F39 -> 5.148 | CC39: 1 | CF39: 1
B40: 33 | C40: A110 - Estar/Comedor/Cocina/Lav/Dormitorio | F40: 23.53 | G40: 22.25 | H40: 0 | I40: =+G40-H40 -> 22.25 | J40: 2.6 | K40: 0.9 | L40: 3 | Q40: =+F40 -> 23.53 | X40: =+L40*J40 -> 7.8 | Z40: =(I40*J40)-X40 -> 50.05 | AA40: =+AB40*J40 -> 5.2 | AB40: 2 | AN40: =(AP40*2)+(0.6*2) -> 5.6 | AP40: 2.2 | AR40: =+F40 -> 23.53 | AW40: 1 | BF40: =+F40 -> 23.53 | BK40: 1 | BL40: =+G40 -> 22.25 | BQ40: =+K40*L40 -> 2.7 | BT40: =(L40*J40)-BQ40 -> 5.1 | BU40: =+I40*J40-(BT40+BQ40) -> 50.05 | BW40: =+AP40 -> 2.2 | BX40: =+F40 -> 23.53 | CE40: 3 | CG40: 1 | CI40: 1 | CK40: 2 | CL40: 3 | CM40: 6 | CO40: 2 | CP40: 1 | CQ40: 1
B41: 34 | C41: A108 - Baño | F41: 3.07 | G41: 7.52 | H41: 0 | I41: =+G41-H41 -> 7.52 | J41: 2.3 | K41: 2.3 | R41: =+F41 -> 3.07 | S41: =+F41 -> 3.07 | X41: =+I41*J41 -> 17.296 | AD41: =+F41 -> 3.07 | AE41: =+G41 -> 7.52 | AM41: =+F41 -> 3.07 | AN41: =+G41 -> 7.52 | AY41: 1 | BB41: 1 | BG41: =+F41 -> 3.07 | BR41: =+I41*K41 -> 17.296 | BW41: =+F41 -> 3.07 | CB41: 1 | CE41: 1 | CF41: 1 | CK41: 1 | CM41: 1 | CX41: 1
B42: 35 | C42: Balcon mono CF | D42: 3.35 | E42: 1.3 | F42: =D42*E42 -> 4.355 | G42: =+D42*2+E42*2 -> 9.3 | H42: =+D42+(E42*2) -> 5.95 | I42: =+G42-H42 -> 3.35 | J42: 2.6 | R42: =+F42 -> 4.355 | S42: =+F42 -> 4.355 | AI42: =+F42 -> 4.355 | AJ42: =+G42 -> 9.3 | AU42: =+F42 -> 4.355 | BF42: =+F42 -> 4.355 | BN42: =+G42 -> 9.3 | BY42: =+F42 -> 4.355 | CC42: 1 | CF42: 1
C43: Repetición de 2° a 4° | L43: 3 | N43: =+SUM(N23:N42)*$L$43 -> 0 | O43: =+SUM(O23:O42)*$L$43 -> 0 | P43: =+SUM(P23:P42)*$L$43 -> 0 | Q43: =+SUM(Q23:Q42)*$L$43 -> 393.2238 | R43: =+SUM(R23:R42)*$L$43 -> 96.051 | S43: =+SUM(S23:S42)*$L$43 -> 96.051 | U43: =+SUM(U23:U42)*$L$43 -> 110.04 | V43: =+SUM(V23:V42)*$L$43 -> 0 | W43: =+SUM(W23:W42)*$L$43 -> 0 | X43: =+SUM(X23:X42)*$L$43 -> 302.061 | Y43: =+SUM(Y23:Y42)*$L$43 -> 0 | Z43: =+SUM(Z23:Z42)*$L$43 -> 1006.08 | AA43: =+SUM(AA23:AA42)*$L$43 -> 104.4 | AB43: =+SUM(AB23:AB42)*$L$43 -> 42 | AD43: =+SUM(AD23:AD42)*$L$43 -> 37.05 | AE43: =+SUM(AE23:AE42)*$L$43 -> 90.15 | AF43: =+SUM(AF23:AF42)*$L$43 -> 0 | AG43: =+SUM(AG23:AG42)*$L$43 -> 0 | AH43: =+SUM(AH23:AH42)*$L$43 -> 0 | AI43: =+SUM(AI23:AI42)*$L$43 -> 59.001 | AJ43: =+SUM(AJ23:AJ42)*$L$43 -> 119.82 | AL43: =+SUM(AL23:AL42)*$L$43 -> 67.845 | AM43: =+SUM(AM23:AM42)*$L$43 -> 37.05 | AN43: =+SUM(AN23:AN42)*$L$43 -> 302.49 | AO43: =+SUM(AO23:AO42)*$L$43 -> 14.7 | AP43: =+SUM(AP23:AP42)*$L$43 -> 29.58 | AQ43: =+SUM(AQ23:AQ42)*$L$43 -> 0 | AR43: =+SUM(AR23:AR42)*$L$43 -> 309.5508 | AS43: =+SUM(AS23:AS42)*$L$43 -> 180.24 | ... AU43: =+SUM(AU23:AU42)*$L$43 -> 88.671 | AW43: =+SUM(AW23:AW42)*$L$43 -> 12 | AX43: =+SUM(AX23:AX42)*$L$43 -> 3 | AY43: =+SUM(AY23:AY42)*$L$43 -> 18 | AZ43: =+SUM(AZ23:AZ42)*$L$43 -> 0 | BA43: =+SUM(BA23:BA42)*$L$43 -> 3 | BB43: =+SUM(BB23:BB42)*$L$43 -> 30 | BD43: =+SUM(BD23:BD42)*$L$43 -> 0 | BE43: =+SUM(BE23:BE42)*$L$43 -> 47.91 | BF43: =+SUM(BF23:BF42)*$L$43 -> 398.3148 | BG43: =+SUM(BG23:BG42)*$L$43 -> 37.05 | BH43: =+SUM(BH23:BH42)*$L$43 -> 0 | BI43: =+SUM(BI23:BI42)*$L$43 -> 0 | BJ43: =+SUM(BJ23:BJ42)*$L$43 -> 0 | BK43: =+SUM(BK23:BK42)*$L$43 -> 12 | ... BO43: =+SUM(BO23:BO42)*$L$43 -> 92.58 | BQ43: =+SUM(BQ23:BQ42)*$L$43 -> 38.556 | BR43: =+SUM(BR23:BR42)*$L$43 -> 207.345 | BS43: =+SUM(BS23:BS42)*$L$43 -> 0 | BT43: =+SUM(BT23:BT42)*$L$43 -> 56.16 | BU43: =+SUM(BU23:BU42)*$L$43 -> 1006.08 | BV43: =+SUM(BV23:BV42)*$L$43 -> 110.04 | BW43: =+SUM(BW23:BW42)*$L$43 -> 134.475 | BX43: =+SUM(BX23:BX42)*$L$43 -> 309.5508 | ... BZ43: =+SUM(BZ23:BZ42)*$L$43 -> 29.67 | CB43: =+SUM(CB23:CB42)*$L$43 -> 6 | CC43: =+SUM(CC23:CC42)*$L$43 -> 39 | CD43: =+SUM(CD23:CD42)*$L$43 -> 9 | CE43: =+SUM(CE23:CE42)*$L$43 -> 90 | CF43: =+SUM(CF23:CF42)*$L$43 -> 24 | CG43: =+SUM(CG23:CG42)*$L$43 -> 12 | CI43: =+SUM(CI23:CI42)*$L$43 -> 18 | CJ43: =+SUM(CJ23:CJ42)*$L$43 -> 6 | CK43: =+SUM(CK23:CK42)*$L$43 -> 30 | CL43: =+SUM(CL23:CL42)*$L$43 -> 36 | CM43: =+SUM(CM23:CM42)*$L$43 -> 105 | CN43: =+SUM(CN23:CN42)*$L$43 -> 0 | CO43: =+SUM(CO23:CO42)*$L$43 -> 24 | CP43: =+SUM(CP23:CP42)*$L$43 -> 18 | ... CX43: =+SUM(CX23:CX42)*$L$43 -> 18 | CZ43: =+SUM(CZ8:CZ42)*$L$43 -> 0 | DA43: =+SUM(DA8:DA42)*$L$43 -> 0 | DB43: =+SUM(DB8:DB42)*$L$43 -> 0 | DC43: =+SUM(DC8:DC42)*$L$43 -> 0 | DD43: =+SUM(DD8:DD42)*$L$43 -> 0 | DE43: =+SUM(DE8:DE42)*$L$43 -> 0 | DF43: =+SUM(DF8:DF42)*$L$43 -> 0 | DG43: =+SUM(DG8:DG42)*$L$43 -> 0 | ... DI43: =+SUM(DI8:DI42)*$L$43 -> 0
A44: P5 | B44: 35 | C44: Escalera | F44: 9.89 | G44: 13.1 | H44: 0 | I44: =+G44-H44 -> 13.1 | J44: 2.8 | L44: 2 | Q44: =+L44 -> 2 | U44: =+I44*J44 -> 36.68 | AU44: =+F44 -> 9.89 | AX44: 1 | BV44: =+I44*J44 -> 36.68 | BZ44: =+F44 -> 9.89 | CC44: 2 | CD44: 1 | CE44: 3 | CH44: 1
B45: 36 | C45: Hall ascensores | F45: 15.97 | G45: 30.86 | H45: 0 | I45: =+G45-H45 -> 30.86 | J45: 2.4 | L45: 1.1 | Q45: =+F45 -> 15.97 | Z45: =+I45*J45 -> 74.064 | AA45: =+AB45*J45 -> 9.6 | AB45: 4 | AL45: =+F45 -> 15.97 | AN45: =+G45 -> 30.86 | AO45: =+L45*2 -> 2.2 | BA45: 1 | BB45: 2 | BE45: =+F45 -> 15.97 | BO45: =+G45 -> 30.86 | BU45: =+I45*J45 -> 74.064 | BW45: =+F45 -> 15.97 | CC45: 7 | CD45: 2 | CE45: 9 | CH45: 3 | CM45: 1
B46: 37 | C46: A101 - Estar/Comedor/Cocina/Lav - Hall | D46: 2.35 | E46: 1.5 | F46: =D46*E46 -> 3.525 | G46: =+D46*2+E46*2 -> 7.7 | H46: =+E46+E47 -> 2.1 | I46: =+G46-H46 -> 5.6 | J46: 2.2 | Q46: =+F46 -> 3.525 | Z46: =+I46*J46 -> 12.32 | AA46: =+AB46*J46 -> 2.2 | AB46: 1 | AL46: =+F46 -> 3.525 | AN46: =+G46 -> 7.7 | AO46: =+E46 -> 1.5 | AW46: 1 | BF46: =+F46 -> 3.525 | BK46: 1 | BL46: =+I46 -> 5.6 | BU46: =+I46*J46 -> 12.32 | BW46: =+F46 -> 3.525 | CE46: 1 | CK46: 1
B47: 38 | C47: A101 - Estar/Comedor/Cocina/Lav - Cocina | D47: 2.63 | E47: 0.6 | F47: =D47*E47 -> 1.578 | G47: =+D47*2+E47*2 -> 6.46 | H47: =+D47+E47 -> 3.23 | I47: =+G47-H47 -> 3.23 | J47: 2.2 | K47: 0.9 | L47: 4.25 | Q47: =+F47 -> 1.578 | X47: =+I47*J47 -> 7.106 | AN47: =+G47 -> 6.46 | AP47: =+D47 -> 2.63 | BF47: =+F47 -> 1.578 | BL47: =+I47 -> 3.23 | BQ47: =+K47*L47 -> 3.825 | BT47: =+(I47*J47)-BQ47 -> 3.281 | BW47: =+AP47 -> 2.63 | CG47: 1 | CI47: 1 | CL47: 3 | CM47: 2 | CO47: 2 | CR47: 1 | CX47: 1
B48: 39 | C48: A101 - Estar/Comedor/Cocina/Lav - Estar | D48: 4.4 | E48: 4.13 | F48: =D48*E48 -> 18.172 | G48: =+D48*2+E48*2 -> 17.06 | H48: =+E48 -> 4.13 | I48: =+G48-H48 -> 12.93 | J48: 2.6 | Q48: =+F48 -> 18.172 | Z48: =+I48*J48 -> 33.618 | AA48: =+AB48*J48 -> 2.6 | AB48: 1 | AR48: =+F48 -> 18.172 | AS48: =+G48 -> 17.06 | BB48: 1 | BF48: =+F48 -> 18.172 | BL48: =+I48 -> 12.93 | BU48: =+I48*J48 -> 33.618 | BX48: =+F48 -> 18.172 | CE48: 2 | CK48: 1 | CM48: 4 | CP48: 1
B49: 40 | C49: A103 - Dormitorio | D49: 3.98 | E49: 2.51 | F49: =D49*E49 -> 9.9898 | G49: =+D49*2+E49*2 -> 12.98 | H49: 0 | I49: =+G49-H49 -> 12.98 | J49: 2.6 | Q49: =+F49 -> 9.9898 | Z49: =+I49*J49 -> 33.748 | AR49: =+F49 -> 9.9898 | AS49: =+G49 -> 12.98 | AY49: 1 | BB49: 1 | BF49: =+F49 -> 9.9898 | BL49: =+I49 -> 12.98 | BU49: =+I49*J49 -> 33.748 | BX49: =+F49 -> 9.9898 | CE49: 1 | CI49: 1 | CM49: 3 | CP49: 1 | CX49: 1
B50: 41 | C50: A104 - Baño | F50: 3.04 | G50: 7.52 | H50: 0 | I50: =+G50-H50 -> 7.52 | J50: 2.3 | K50: 2.3 | R50: =+F50 -> 3.04 | S50: =+F50 -> 3.04 | X50: =+I50*J50 -> 17.296 | AD50: =+F50 -> 3.04 | AE50: =+G50 -> 7.52 | AM50: =+F50 -> 3.04 | AN50: =+G50 -> 7.52 | AY50: 1 | BB50: 1 | BG50: =+F50 -> 3.04 | BR50: =+I50*K50 -> 17.296 | BW50: =+F50 -> 3.04 | CE50: 1 | CF50: 1 | CJ50: 1 | CM50: 1
B51: 42 | C51: Balcon 2 amb CF | D51: 3.96 | E51: 1.4 | F51: =D51*E51 -> 5.544 | G51: =+D51*2+E51*2 -> 10.72 | H51: =+D51+(E51*2) -> 6.76 | I51: =+G51-H51 -> 3.96 | J51: 2.6 | R51: =+F51 -> 5.544 | S51: =+F51 -> 5.544 | AI51: =+F51 -> 5.544 | AJ51: =+G51 -> 10.72 | AU51: =+F51 -> 5.544 | BF51: =+F51 -> 5.544 | BN51: =+G51 -> 10.72 | BY51: =+F51 -> 5.544 | CC51: 1 | CF51: 1
B52: 43 | C52: A102 - Estar/Comedor/Cocina/Lav/Domitorio | F52: 23.33 | G52: 22.19 | H52: 0 | I52: =+G52-H52 -> 22.19 | J52: 2.6 | K52: 0.9 | L52: 3 | Q52: =+F52 -> 23.33 | X52: =+L52*J52 -> 7.8 | Z52: =(I52*J52)-X52 -> 49.894 | AA52: =+AB52*J52 -> 5.2 | AB52: 2 | AN52: =(AP52*2)+(0.6*2) -> 5.6 | AP52: 2.2 | AR52: =+F52 -> 23.33 | AW52: 1 | BB52: 1 | BF52: =+F52 -> 23.33 | BK52: 1 | BL52: =+G52 -> 22.19 | BQ52: =+K52*L52 -> 2.7 | BT52: =(L52*J52)-BQ52 -> 5.1 | BU52: =+I52*J52-(BT52+BQ52) -> 49.894 | BW52: =+AP52 -> 2.2 | BX52: =+F52 -> 23.33 | CE52: 3 | CG52: 1 | CI52: 1 | CK52: 2 | CL52: 3 | CM52: 6 | CO52: 2 | CP52: 1 | CQ52: 1
B53: 44 | C53: A105 - Baño | F53: 3.06 | G53: 7.49 | H53: 0 | I53: =+G53-H53 -> 7.49 | J53: 2.3 | K53: 2.3 | R53: =+F53 -> 3.06 | S53: =+F53 -> 3.06 | X53: =+I53*J53 -> 17.227 | AD53: =+F53 -> 3.06 | AE53: =+G53 -> 7.49 | AM53: =+F53 -> 3.06 | AN53: =+G53 -> 7.49 | AY53: 1 | BG53: =+F53 -> 3.06 | BR53: =+I53*K53 -> 17.227 | BW53: =+F53 -> 3.06 | CB53: 1 | CE53: 1 | CF53: 1 | CK53: 1 | CM53: 1 | CX53: 1
B54: 45 | C54: Balcon mono CF | D54: 3.3 | E54: 1.4 | F54: =D54*E54 -> 4.62 | G54: =+D54*2+E54*2 -> 9.4 | H54: =+D54+(E54*2) -> 6.1 | I54: =+G54-H54 -> 3.3 | J54: 2.6 | R54: =+F54 -> 4.62 | S54: =+F54 -> 4.62 | AI54: =+F54 -> 4.62 | AJ54: =+G54 -> 9.4 | AU54: =+F54 -> 4.62 | BF54: =+F54 -> 4.62 | BN54: =+G54 -> 9.4 | BY54: =+F54 -> 4.62 | CC54: 1 | CF54: 1
B55: 46 | C55: Hall acceso 2 amb F | F55: 3.12 | G55: 7.7 | H55: 1.2 | I55: =+G55-H55 -> 6.5 | J55: 2.2 | Q55: =+F55 -> 3.12 | Z55: =+I55*J55 -> 14.3 | AA55: =+AB55*J55 -> 2.2 | AB55: 1 | AL55: =+F55 -> 3.12 | AN55: =+G55 -> 7.7 | AO55: =+H55 -> 1.2 | AW55: 1 | BF55: =+F55 -> 3.12 | BK55: 1 | BL55: =+I55 -> 6.5 | BU55: =+I55*J55 -> 14.3 | BW55: =+F55 -> 3.12 | CE55: 1 | CK55: 1 | CR55: 1
B56: 47 | C56: Cocina 2 amb F | D56: 2.83 | E56: 0.6 | F56: =D56*E56 -> 1.698 | G56: =+D56*2+E56*2 -> 6.86 | H56: =+D56 -> 2.83 | I56: =+G56-H56 -> 4.03 | J56: 2.2 | K56: 0.9 | L56: 3 | Q56: =+F56 -> 1.698 | X56: =+I56*J56 -> 8.866 | AN56: =+G56 -> 6.86 | AP56: =+H56 -> 2.83 | BF56: =+F56 -> 1.698 | BL56: =+I56 -> 4.03 | BQ56: =+K56*L56 -> 2.7 | BT56: =(I56*J56)-BQ56 -> 6.166 | BW56: =+AP56 -> 2.83 | CG56: 1 | CI56: 1 | CL56: 3 | CM56: 2 | CO56: 2
B57: 48 | C57: A109 - Estar/Comedor/Cocina/Lav F | D57: 4.4 | E57: 4.13 | F57: =D57*E57 -> 18.172 | G57: =+D57*2+E57*2 -> 17.06 | H57: =+E57 -> 4.13 | I57: =+G57-H57 -> 12.93 | J57: 2.6 | L57: 4.4 | Q57: =+F57 -> 18.172 | Z57: =+I57*J57 -> 33.618 | AA57: =+AB57*J57 -> 5.2 | AB57: 2 | AP57: =+L57 -> 4.4 | AR57: =+F57 -> 18.172 | AS57: =+G57 -> 17.06 | BB57: 1 | BF57: =+F57 -> 18.172 | BL57: =+I57 -> 12.93 | BU57: =+I57*J57 -> 33.618 | BW57: =+AP57 -> 4.4 | BX57: =+F57 -> 18.172 | CE57: 2 | CK57: 1 | CM57: 4 | CP57: 1 | CX57: 1
B58: 49 | C58: A107 - Baño F | F58: 3.18 | G58: 7.52 | H58: 0 | I58: =+G58-H58 -> 7.52 | J58: 2.3 | K58: 2.3 | R58: =+F58 -> 3.18 | S58: =+F58 -> 3.18 | X58: =+I58*J58 -> 17.296 | AD58: =+F58 -> 3.18 | AE58: =+G58 -> 7.52 | AM58: =+F58 -> 3.18 | AN58: =+G58 -> 7.52 | AY58: 1 | BB58: 1 | BG58: =+F58 -> 3.18 | BR58: =+I58*K58 -> 17.296 | BW58: =+F58 -> 3.18 | CE58: 1 | CF58: 1 | CJ58: 1 | CM58: 1
B59: 50 | C59: A106 - Dormitorio AL | D59: 3.98 | E59: 2.51 | F59: =D59*E59 -> 9.9898 | G59: =+D59*2+E59*2 -> 12.98 | H59: 0 | I59: =+G59-H59 -> 12.98 | J59: 2.6 | Q59: =+F59 -> 9.9898 | Z59: =+I59*J59 -> 33.748 | AA59: =+AB59*J59 -> 2.6 | AB59: 1 | AR59: =+F59 -> 9.9898 | AS59: =+G59 -> 12.98 | AY59: 1 | BB59: 1 | BF59: =+F59 -> 9.9898 | BL59: =+I59 -> 12.98 | BU59: =+I59*J59 -> 33.748 | BX59: =+F59 -> 9.9898 | CE59: 1 | CI59: 1 | CM59: 3 | CP59: 1 | CX59: 1
B60: 51 | C60: Balcon 2 amb F | D60: 3.96 | E60: 1.3 | F60: =D60*E60 -> 5.148 | G60: =+D60*2+E60*2 -> 10.52 | H60: =+D60+(E60*2) -> 6.56 | I60: =+G60-H60 -> 3.96 | J60: 2.6 | R60: =+F60 -> 5.148 | S60: =+F60 -> 5.148 | AI60: =+F60 -> 5.148 | AJ60: =+G60 -> 10.52 | BF60: =+F60 -> 5.148 | BN60: =+G60 -> 10.52 | BY60: 0 | CC60: 1 | CF60: 1
B61: 52 | C61: A110 - Estar/Comedor/Cocina/Lav/Dormitorio | F61: 23.53 | G61: 22.25 | H61: 0 | I61: =+G61-H61 -> 22.25 | J61: 2.6 | K61: 0.9 | L61: 3 | Q61: =+F61 -> 23.53 | X61: =+L61*J61 -> 7.8 | Z61: =(I61*J61)-X61 -> 50.05 | AA61: =+AB61*J61 -> 5.2 | AB61: 2 | AN61: =(AP61*2)+(0.6*2) -> 5.6 | AP61: 2.2 | AR61: =+F61 -> 23.53 | AW61: 1 | BB61: 1 | BF61: =+F61 -> 23.53 | BK61: 1 | BL61: =+G61 -> 22.25 | BQ61: =+L61*K61 -> 2.7 | BT61: =(L61*J61)-BQ61 -> 5.1 | BU61: =+I61*J61-(BT61+BQ61) -> 50.05 | BW61: =+AP61 -> 2.2 | BX61: =+F61 -> 23.53 | CE61: 3 | CG61: 1 | CI61: 1 | CK61: 2 | CL61: 3 | CM61: 6 | CO61: 2 | CP61: 1 | CQ61: 1
B62: 53 | C62: A108 - Baño | F62: 3.07 | G62: 7.52 | H62: 0 | I62: =+G62-H62 -> 7.52 | J62: 2.3 | K62: 2.3 | R62: =+F62 -> 3.07 | S62: =+F62 -> 3.07 | X62: =+I62*J62 -> 17.296 | AD62: =+F62 -> 3.07 | AE62: =+G62 -> 7.52 | AM62: =+F62 -> 3.07 | AN62: =+G62 -> 7.52 | AY62: 1 | BG62: =+F62 -> 3.07 | BR62: =+I62*K62 -> 17.296 | BW62: =+F62 -> 3.07 | CB62: 1 | CE62: 1 | CF62: 1 | CK62: 1 | CM62: 1 | CX62: 1
B63: 54 | C63: Balcon mono F | D63: 3.35 | E63: 1.3 | F63: =D63*E63 -> 4.355 | G63: =+D63*2+E63*2 -> 9.3 | H63: =+D63+(E63*2) -> 5.95 | I63: =+G63-H63 -> 3.35 | J63: 2.6 | R63: =+F63 -> 4.355 | S63: =+F63 -> 4.355 | AI63: =+F63 -> 4.355 | AJ63: =+G63 -> 9.3 | BF63: =+F63 -> 4.355 | BN63: =+G63 -> 9.3 | BY63: 0 | CC63: 1 | CF63: 1
A64: P6 | B64: 55 | C64: Escalera | F64: 9.89 | G64: 13.1 | H64: 0 | I64: =+G64-H64 -> 13.1 | J64: 2.8 | L64: 2 | Q64: =+L64 -> 2 | U64: =+I64*J64 -> 36.68 | AU64: =+F64 -> 9.89 | AX64: 1 | BV64: =+I64*J64 -> 36.68 | BZ64: =+F64 -> 9.89 | CC64: 2 | CD64: 1 | CE64: 3 | CH64: 1
B65: 56 | C65: Hall ascensores | F65: 12.25 | G65: 24.04 | H65: 0 | I65: =+G65-H65 -> 24.04 | J65: 2.4 | L65: 1.1 | Q65: =+F65 -> 12.25 | Z65: =+I65*J65 -> 57.696 | AA65: =+AB65*J65 -> 7.2 | AB65: 3 | AL65: =+F65 -> 12.25 | AN65: =+G65 -> 24.04 | AO65: =+L65*2 -> 2.2 | BA65: 1 | BB65: 2 | BE65: =+F65 -> 12.25 | BO65: =+G65 -> 24.04 | BU65: =+I65*J65 -> 57.696 | BW65: =+F65 -> 12.25 | CC65: 5 | CD65: 2 | CE65: 7 | CH65: 2 | CM65: 1
B66: 57 | C66: A201 - Estar/Comedor/Cocina/Lav - Hall | F66: 3.15 | G66: 7.72 | H66: 1.2 | I66: =+G66-H66 -> 6.52 | J66: 2.2 | Q66: =+F66 -> 3.15 | Z66: =+I66*J66 -> 14.344 | AA66: =+AB66*J66 -> 2.2 | AB66: 1 | AL66: =+F66 -> 3.15 | AN66: =+G66 -> 7.72 | AO66: =+H66 -> 1.2 | AW66: 1 | BF66: =+F66 -> 3.15 | BK66: 1 | BL66: =+I66 -> 6.52 | BU66: =+I66*J66 -> 14.344 | BW66: =+F66 -> 3.15 | CE66: 1 | CK66: 1
B67: 58 | C67: A201 - Estar/Comedor/Cocina/Lav - Cocina | D67: 2.83 | E67: 0.6 | F67: =D67*E67 -> 1.698 | G67: =+D67*2+E67*2 -> 6.86 | H67: =+D67 -> 2.83 | I67: =+G67-H67 -> 4.03 | J67: 2.2 | K67: 0.9 | Q67: =+F67 -> 1.698 | X67: =+I67*J67 -> 8.866 | AN67: =+G67 -> 6.86 | AP67: =+H67 -> 2.83 | BF67: =+F67 -> 1.698 | BL67: =+I67 -> 4.03 | BQ67: =+I67*K67 -> 3.627 | BT67: =(I67*J67)-BQ67 -> 5.239 | BW67: =+AP67 -> 2.83 | CG67: 1 | CI67: 1 | CL67: 3 | CM67: 2 | CO67: 2 | CR67: 1 | CX67: 1
B68: 59 | C68: A201 - Estar/Comedor/Cocina/Lav - Estar | D68: 4.4 | E68: 4.13 | F68: =D68*E68 -> 18.172 | G68: =+D68*2+E68*2 -> 17.06 | H68: =+E68 -> 4.13 | I68: =+G68-H68 -> 12.93 | J68: 2.6 | Q68: =+F68 -> 18.172 | Z68: =+I68*J68 -> 33.618 | AA68: =+AB68*J68 -> 5.2 | AB68: 2 | AR68: =+F68 -> 18.172 | AS68: =+G68 -> 17.06 | BB68: 1 | BF68: =+F68 -> 18.172 | BL68: =+I68 -> 12.93 | BU68: =+I68*J68 -> 33.618 | BX68: =+F68 -> 18.172 | CE68: 2 | CK68: 1 | CM68: 4 | CP68: 1
B69: 60 | C69: A203 - Dormitorio | D69: 3.98 | E69: 2.51 | F69: =D69*E69 -> 9.9898 | G69: =+D69*2+E69*2 -> 12.98 | H69: 0 | I69: =+G69-H69 -> 12.98 | J69: 2.6 | Q69: =+F69 -> 9.9898 | Z69: =+I69*J69 -> 33.748 | AA69: =+AB69*J69 -> 0 | AB69: 0 | AR69: =+F69 -> 9.9898 | AS69: =+G69 -> 12.98 | AY69: 1 | BB69: 1 | BF69: =+F69 -> 9.9898 | BL69: =+I69 -> 12.98 | BU69: =+I69*J69 -> 33.748 | BX69: =+F69 -> 9.9898 | CE69: 1 | CI69: 1 | CM69: 3 | CP69: 1 | CX69: 1
B70: 61 | C70: A204 - Baño | F70: 3.04 | G70: 7.52 | H70: 0 | I70: =+G70-H70 -> 7.52 | J70: 2.3 | K70: 2.3 | R70: =+F70 -> 3.04 | S70: =+F70 -> 3.04 | X70: =+I70*J70 -> 17.296 | AD70: =+F70 -> 3.04 | AE70: =+G70 -> 7.52 | AM70: =+F70 -> 3.04 | AN70: =+G70 -> 7.52 | AY70: 1 | BB70: 1 | BG70: =+F70 -> 3.04 | BR70: =+I70*K70 -> 17.296 | BW70: =+F70 -> 3.04 | CE70: 1 | CF70: 1 | CJ70: 1 | CM70: 1
B71: 62 | C71: Balcon 2 amb CF | D71: 3.96 | E71: 1.4 | F71: =D71*E71 -> 5.544 | G71: =+D71*2+E71*2 -> 10.72 | H71: =+D71+(E71*2) -> 6.76 | I71: =+G71-H71 -> 3.96 | J71: 2.6 | R71: =+F71 -> 5.544 | S71: =+F71 -> 5.544 | AI71: =+F71 -> 5.544 | AJ71: =+G71 -> 10.72 | BF71: =+F71 -> 5.544 | BN71: =+G71 -> 10.72 | CC71: 1 | CF71: 1
B72: 63 | C72: A202 - Estar/Comedor/Cocina/Lav/Domitorio | F72: 23.33 | G72: 22.19 | H72: 0 | I72: =+G72-H72 -> 22.19 | J72: 2.6 | K72: 0.9 | L72: 3 | Q72: =+F72 -> 23.33 | X72: =+L72*J72 -> 7.8 | Z72: =(I72*J72)-X72 -> 49.894 | AA72: =+AB72*J72 -> 5.2 | AB72: 2 | AN72: =(AP72*2)+(0.6*2) -> 5.6 | AP72: 2.2 | AR72: =+F72 -> 23.33 | AW72: 1 | BB72: 1 | BF72: =+F72 -> 23.33 | BK72: 1 | BL72: =+I72 -> 22.19 | BQ72: =+L72*K72 -> 2.7 | BT72: =(L72*J72)-BQ72 -> 5.1 | BU72: =+I72*J72-(BT72+BQ72) -> 49.894 | BW72: =+AP72 -> 2.2 | BX72: =+F72 -> 23.33 | CE72: 3 | CG72: 1 | CI72: 1 | CK72: 2 | CL72: 3 | CM72: 6 | CO72: 2 | CP72: 1 | CQ72: 1
B73: 64 | C73: A205 - Baño | F73: 3.05 | G73: 7.49 | H73: 0 | I73: =+G73-H73 -> 7.49 | J73: 2.3 | K73: 2.3 | R73: =+F73 -> 3.05 | S73: =+F73 -> 3.05 | X73: =+I73*J73 -> 17.227 | AD73: =+F73 -> 3.05 | AE73: =+G73 -> 7.49 | AM73: =+F73 -> 3.05 | AN73: =+G73 -> 7.49 | AY73: 1 | BG73: =+F73 -> 3.05 | BR73: =+I73*K73 -> 17.227 | BW73: =+F73 -> 3.05 | CB73: 1 | CE73: 1 | CF73: 1 | CK73: 1 | CM73: 1 | CX73: 1
B74: 65 | C74: Balcon mono CF | D74: 3.3 | E74: 1.4 | F74: =D74*E74 -> 4.62 | G74: =+D74*2+E74*2 -> 9.4 | H74: =+D74+(E74*2) -> 6.1 | I74: =+G74-H74 -> 3.3 | J74: 2.6 | R74: =+F74 -> 4.62 | S74: =+F74 -> 4.62 | AI74: =+F74 -> 4.62 | AJ74: =+G74 -> 9.4 | BF74: =+F74 -> 4.62 | BN74: =+G74 -> 9.4 | CC74: 1 | CF74: 1
B75: 66 | C75: Hall acceso / Cocina 3 amb F | F75: 6.58 | G75: 11.58 | H75: =+E76 -> 3.51 | I75: =+G75-H75 -> 8.07 | J75: 2.2 | K75: 0.9 | L75: 3.65 | Q75: =+F75 -> 6.58 | X75: =+I75*J75 -> 17.754 | AA75: =+AB75*J75 -> 6.6 | AB75: 3 | AL75: =+F75 -> 6.58 | AN75: =+G75 -> 11.58 | AO75: =+H75 -> 3.51 | AW75: 1 | BF75: =+F75 -> 6.58 | BK75: 1 | BL75: =+I75 -> 8.07 | BQ75: =+L75*K75 -> 3.285 | BT75: =(I75*J75)-BQ75 -> 14.469 | BW75: =+F75 -> 6.58 | CE75: 1 | CG75: 1 | CI75: 1 | CK75: 1 | CL75: 3 | CM75: 2 | CO75: 2 | CR75: 1
B76: 67 | C76: A208 - Estar/Comedor/Cocina/Lav. F | D76: 5 | E76: 3.51 | F76: =D76*E76 -> 17.55 | G76: =+D76*2+E76*2 -> 17.02 | H76: =+E76+H77 -> 4.68 | I76: =+G76-H76 -> 12.34 | J76: 2.6 | Q76: =+F76 -> 17.55 | Z76: =+I76*J76 -> 32.084 | AA76: =+AB76*J76 -> 5.2 | AB76: 2 | AR76: =+F76 -> 17.55 | AS76: =+G76 -> 17.02 | AT76: =+H77 -> 1.17 | BB76: 1 | BF76: =+F76 -> 17.55 | BL76: =+I76 -> 12.34 | BU76: =+I76*J76 -> 32.084 | BX76: =+F76 -> 17.55 | CE76: 2 | CI76: 1 | CM76: 3 | CP76: 1 | CX76: 1
B77: 68 | C77: A208 - Hall Dist. F | F77: 1.8 | G77: 5.64 | H77: 1.17 | I77: =+G77-H77 -> 4.47 | J77: 2.2 | Q77: =+F77 -> 1.8 | Z77: =+I77*J77 -> 9.834 | AA77: =+AB77*J77 -> 2.2 | AB77: 1 | AL77: =+F77 -> 1.8 | AN77: =+G77 -> 5.64 | BF77: =+F77 -> 1.8 | BL77: =+I77 -> 4.47 | BU77: =+I77*J77 -> 9.834 | BW77: =+F77 -> 1.8 | CE77: 1 | CI77: 1
B78: 69 | C78: A206 - Dormitorio AL | F78: 11.49 | G78: 15.14 | H78: 0 | I78: =+G78-H78 -> 15.14 | J78: 2.6 | L78: 2.81 | Q78: =+F78 -> 11.49 | Z78: =+I78*J78 -> 39.364 | AA78: =+AB78*J78 -> 2.6 | AB78: 1 | AN78: =(AP78*2)+(2*0.6) -> 6.82 | AP78: =+L78 -> 2.81 | AR78: =+F78 -> 11.49 | AS78: =+G78 -> 15.14 | AY78: 1 | BB78: 1 | BF78: =+F78 -> 11.49 | BL78: =+I78 -> 15.14 | BU78: =+I78*J78 -> 39.364 | BW78: =+AP78 -> 2.81 | BX78: =+F78 -> 11.49 | CE78: 1 | CM78: 3 | CP78: 1 | CX78: 1
B79: 70 | C79: A207 - Toil. | F79: 2.05 | G79: 6.16 | H79: 0 | I79: =+G79-H79 -> 6.16 | J79: 2.3 | K79: 2.3 | Q79: =+F79 -> 2.05 | X79: =+I79*J79 -> 14.168 | AM79: =+F79 -> 2.05 | AN79: =+G79 -> 6.16 | AY79: 1 | BB79: 1 | BG79: =+F79 -> 2.05 | BR79: =+I79*K79 -> 14.168 | BW79: =+F79 -> 2.05 | CF79: 1 | CI79: 1 | CM79: 1
B80: 71 | C80: A209 - Dormitorio F | D80: 3.6 | E80: 2.51 | F80: =D80*E80 -> 9.036 | G80: =+D80*2+E80*2 -> 12.22 | H80: 0 | I80: =+G80-H80 -> 12.22 | J80: 2.6 | Q80: =+F80 -> 9.036 | Z80: =+I80*J80 -> 31.772 | AA80: =+AB80*J80 -> 0 | AB80: 0 | AR80: =+F80 -> 9.036 | AS80: =+G80 -> 12.22 | AY80: 1 | BB80: 1 | BF80: =+F80 -> 9.036 | BL80: =+I80 -> 12.22 | BU80: =+I80*J80 -> 31.772 | BX80: =+F80 -> 9.036 | CE80: 1 | CM80: 3 | CP80: 1 | CX80: 1
B81: 72 | C81: A210 - Baño | D81: 2.31 | E81: 1.5 | F81: =D81*E81 -> 3.465 | G81: =+D81*2+E81*2 -> 7.62 | H81: 0 | I81: =+G81-H81 -> 7.62 | J81: 2.3 | K81: 2.3 | R81: =+F81 -> 3.465 | S81: =+F81 -> 3.465 | X81: =+I81*J81 -> 17.526 | AD81: =+F81 -> 3.465 | AE81: =+G81 -> 7.62 | AM81: =+F81 -> 3.465 | AN81: =+G81 -> 7.62 | AY81: 1 | BB81: 1 | BG81: =+F81 -> 3.465 | BR81: =+I81*K81 -> 17.526 | BW81: =+F81 -> 3.465 | CE81: 1 | CF81: 1 | CJ81: 1 | CM81: 1
B82: 73 | C82: Terraza | D82: 7.8 | E82: 1.85 | F82: =D82*E82 -> 14.43 | G82: =+D82*2+E82*2 -> 19.3 | H82: =+D82+(E82*2) -> 11.5 | I82: =+G82-H82 -> 7.8 | J82: 0 | R82: =+F82 -> 14.43 | S82: =+F82 -> 14.43 | AG82: =+F82 -> 14.43 | AH82: =+F82 -> 14.43 | AI82: =+F82 -> 14.43 | AJ82: =+G82 -> 19.3 | BF82: =+F82 -> 14.43 | BN82: =+G82 -> 19.3 | CC82: 2 | CF82: 2
A83: P7 | B83: 74 | C83: Escalera | F83: 9.89 | G83: 13.1 | I83: =+G83-H83 -> 13.1 | J83: 2.8 | L83: 2 | Q83: =+L83 -> 2 | U83: =+I83*J83 -> 36.68 | AU83: =+F83 -> 9.89 | AX83: 1 | BV83: =+I83*J83 -> 36.68 | BZ83: =+F83 -> 9.89 | CC83: 3 | CD83: 2 | CE83: 5 | CH83: 1
B84: 75 | C84: Hall ascensores | F84: 8.79 | G84: 17.78 | I84: =+G84-H84 -> 17.78 | J84: 2.4 | L84: 1.1 | Q84: =+F84 -> 8.79 | Z84: =+I84*J84 -> 42.672 | AA84: =+AB84*J84 -> 4.8 | AB84: 2 | AL84: =+F84 -> 8.79 | AN84: =+G84 -> 17.78 | AO84: =+L84*2 -> 2.2 | BA84: 1 | BB84: 2 | BE84: =+F84 -> 8.79 | BO84: =+G84 -> 17.78 | BU84: =+I84*J84 -> 42.672 | BW84: =+F84 -> 8.79 | CC84: 2 | CD84: 1 | CE84: 3 | CH84: 1 | CL84: 1
B85: 76 | C85: Terraza | D85: 3.85 | E85: 7.76 | F85: =D85*E85 -> 29.876 | G85: =+D85*2+E85*2 -> 23.22 | I85: =+G85-H85 -> 23.22 | R85: =+F85 -> 29.876 | S85: =+F85 -> 29.876 | AG85: =+F85 -> 29.876 | AH85: =+F85 -> 29.876 | AI85: =+F85 -> 29.876 | AJ85: =+G85 -> 23.22 | BF85: =+F85 -> 29.876 | BN85: =+G85 -> 23.22 | CC85: 2 | CF85: 2
B86: 77 | C86: A301 - Dormitorio | F86: 10.61 | G86: 15.64 | I86: =+G86-H86 -> 15.64 | J86: 2.6 | Q86: =+F86 -> 10.61 | Z86: =I86*J86 -> 40.664 | AA86: =+AB86*J86 -> 10.4 | AB86: 4 | AR86: =+F86 -> 10.61 | AS86: =+G86 -> 15.64 | AY86: 1 | BB86: 1 | BF86: =+F86 -> 10.61 | BL86: =+G86 -> 15.64 | BU86: =+I86*J86 -> 40.664 | BX86: =+F86 -> 10.61 | CE86: 1 | CJ86: 1 | CM86: 3 | CP86: 1 | CX86: 1
B87: 78 | C87: A302 - Estar/Comedor/Cocina/Lav. | F87: 20.34 | G87: 19.34 | I87: =+G87-H87 -> 19.34 | J87: 2.6 | K87: 0.9 | L87: 4.8 | Q87: =+F87 -> 20.34 | X87: =+L87*J87 -> 12.48 | Z87: =(I87*J87)-X87 -> 37.804 | AA87: =+AB87*J87 -> 7.8 | AB87: 3 | AR87: =+F87 -> 20.34 | AS87: =+G87 -> 19.34 | AW87: 1 | BB87: 2 | BF87: =+F87 -> 20.34 | BK87: 1 | BL87: =+G87 -> 19.34 | BQ87: =+K87*L87 -> 4.32 | BT87: =+L87*J87-BQ87 -> 8.16 | BU87: =+I87*J87-(BT87+BQ87) -> 37.804 | BX87: =+F87 -> 20.34 | CE87: 4 | CI87: 1 | CK87: 1 | CL87: 3 | CM87: =3+2 -> 5 | CO87: 2 | CP87: 1 | CR87: 1 | CX87: 1
B88: 79 | C88: A303 - Baño (c/ ducha) | D88: 1.5 | E88: 2.31 | F88: =D88*E88 -> 3.465 | G88: =+D88*2+E88*2 -> 7.62 | I88: =+G88-H88 -> 7.62 | J88: 2.3 | K88: 2.3 | R88: =+F88 -> 3.465 | S88: =+F88 -> 3.465 | X88: =+I88*J88 -> 17.526 | AD88: =+F88 -> 3.465 | AE88: =+G88 -> 7.62 | AM88: =+F88 -> 3.465 | AN88: =+G88 -> 7.62 | AY88: 1 | BB88: 1 | BG88: =+F88 -> 3.465 | BR88: =+I88*K88 -> 17.526 | BW88: =+F88 -> 3.465 | CE88: 1 | CF88: 1 | CJ88: 1 | CM88: 1
B89: 80 | C89: A304 - Toilete | F89: 2.18 | G89: 6.4 | I89: =+G89-H89 -> 6.4 | J89: 2.3 | K89: 2.3 | R89: =+F89 -> 2.18 | S89: =+F89 -> 2.18 | X89: =+I89*J89 -> 14.72 | AM89: =+F89 -> 2.18 | AN89: =+G89 -> 6.4 | AY89: 1 | BB89: 1 | BG89: =+F89 -> 2.18 | BR89: =+I89*K89 -> 14.72 | BW89: =+F89 -> 2.18 | CF89: 1 | CI89: 1 | CM89: 1
B90: 81 | C90: A305 - Baño (c/ducha) | D90: 1.5 | E90: 2.31 | F90: =D90*E90 -> 3.465 | G90: =+D90*2+E90*2 -> 7.62 | I90: =+G90-H90 -> 7.62 | J90: 2.3 | K90: 2.3 | R90: =+F90 -> 3.465 | S90: =+F90 -> 3.465 | X90: =+I90*J90 -> 17.526 | AD90: =+F90 -> 3.465 | AE90: =+G90 -> 7.62 | AM90: =+F90 -> 3.465 | AN90: =+G90 -> 7.62 | AY90: 1 | BB90: 1 | BG90: =+F90 -> 3.465 | BR90: =+I90*K90 -> 17.526 | BW90: =+F90 -> 3.465 | CE90: 1 | CF90: 1 | CJ90: 1 | CM90: 1
B91: 82 | C91: A306 - Toil. | F91: 2.32 | G91: 6.4 | I91: =+G91-H91 -> 6.4 | J91: 2.3 | K91: 2.3 | R91: =+F91 -> 2.32 | S91: =+F91 -> 2.32 | X91: =+I91*J91 -> 14.72 | AM91: =+F91 -> 2.32 | AN91: =+G91 -> 6.4 | AY91: 1 | BB91: 1 | BG91: =+F91 -> 2.32 | BR91: =+I91*K91 -> 14.72 | BW91: =+F91 -> 2.32 | CF91: 1 | CI91: 1 | CM91: 1
B92: 83 | C92: A307 - Dormitorio | F92: 10.6 | G92: 15.64 | I92: =+G92-H92 -> 15.64 | J92: 2.6 | Q92: =+F92 -> 10.6 | Z92: =+I92*J92 -> 40.664 | AA92: =+AB92*J92 -> 10.4 | AB92: 4 | AR92: =+F92 -> 10.6 | AS92: =+G92 -> 15.64 | AY92: 1 | BB92: 1 | BF92: =+F92 -> 10.6 | BL92: =+G92 -> 15.64 | BU92: =+I92*J92 -> 40.664 | BX92: =+F92 -> 10.6 | CE92: 1 | CJ92: 1 | CM92: 3 | CP92: 1 | CX92: 1
B93: 84 | C93: A308 - Estar/Comedor/Cocina/Lav. | F93: 20.8 | G93: 19.69 | I93: =+G93-H93 -> 19.69 | J93: 2.6 | K93: 0.9 | L93: 4.8 | Q93: =+F93 -> 20.8 | X93: =+L93*J93 -> 12.48 | Z93: =(I93*J93)-X93 -> 38.714 | AA93: =+AB93*J93 -> 10.4 | AB93: 4 | AR93: =+F93 -> 20.8 | AS93: =+G93 -> 19.69 | BB93: 1 | BF93: =+F93 -> 20.8 | BK93: 1 | BL93: =+G93 -> 19.69 | BQ93: =+K93*L93 -> 4.32 | BT93: =+L93*J93-BQ93 -> 8.16 | BU93: =+I93*J93-(BT93+BQ93) -> 38.714 | BX93: =+F93 -> 20.8 | CE93: 4 | CI93: 1 | CK93: 1 | CL93: 3 | CM93: =3+2 -> 5 | CO93: 2 | CP93: 1 | CR93: 1 | CX93: 1
B94: 85 | C94: Terraza | D94: 7.8 | E94: 1.85 | F94: =D94*E94 -> 14.43 | G94: =+D94*2+E94*2 -> 19.3 | I94: =+G94-H94 -> 19.3 | R94: =+F94 -> 14.43 | S94: =+F94 -> 14.43 | AG94: =+F94 -> 14.43 | AH94: =+F94 -> 14.43 | AI94: =+F94 -> 14.43 | AJ94: =+G94 -> 19.3 | BF94: =+F94 -> 14.43 | BN94: =+G94 -> 19.3 | CC94: 2 | CF94: 2
A95: P9 | B95: 86 | C95: Escalera | F95: 9.89 | G95: 13.1 | I95: =+G95-H95 -> 13.1 | J95: 3.2 | L95: 2 | Q95: =+L95 -> 2 | U95: =+I95*J95 -> 41.92 | AU95: =+F95 -> 9.89 | AX95: 1 | BV95: =+I95*J95 -> 41.92 | BZ95: =+F95 -> 9.89 | CC95: 2 | CD95: 1 | CE95: 3 | CH95: 1
B96: 87 | C96: A401 - Sala de maq. | D96: 3.6 | E96: 2.26 | F96: =D96*E96 -> 8.136 | G96: =+D96*2+E96*2 -> 11.72 | I96: =+G96-H96 -> 11.72 | J96: 2.2 | R96: =+F96 -> 8.136 | U96: =+I96*J96 -> 25.784 | V96: =+W96*J96 -> 4.4 | W96: 2 | AU96: =+F96 -> 8.136 | AX96: 1 | BH96: =+F96 -> 8.136 | BM96: =+I96 -> 11.72 | BV96: =+I96*J96 -> 25.784 | BZ96: =+F96 -> 8.136 | CC96: =+CE96 -> 1 | CE96: 1 | CM96: 1 | CT96: 1
B97: 88 | C97: Terraza | F97: =87-F98 -> 62.3 | G97: 66.01 | I97: =+G97-H97 -> 66.01 | N97: =+F97 -> 62.3 | R97: =+F97 -> 62.3 | S97: =+F97 -> 62.3 | AG97: =+F97 -> 62.3 | AH97: =+F97 -> 62.3 | AI97: =+F97 -> 62.3 | AJ97: =+G97 -> 66.01 | BD97: =+F97 -> 62.3 | BO97: =+I97 -> 66.01 | CC97: =+CF97 -> 4 | CF97: 4 | CN97: 1
B98: 89 | C98: Terraza verde | F98: 24.7 | G98: 23.43 | I98: =+G98-H98 -> 23.43 | N98: =+F98 -> 24.7 | R98: =+F98 -> 24.7 | S98: =+F98 -> 24.7 | AG98: =+F98 -> 24.7 | AH98: =+F98 -> 24.7 | AI98: =+F98 -> 24.7 | BI98: =+F98 -> 24.7
B99: 90 | C99: Techo SM | D99: 8.29 | E99: 2.3 | F99: =D99*E99 -> 19.067 | G99: =+D99*2+E99*2 -> 21.18 | N99: =+F99 -> 19.067 | R99: =+F99 -> 19.067 | S99: =+F99 -> 19.067 | AG99: =+F99 -> 19.067 | AH99: =+F99 -> 19.067 | AI99: =+F99 -> 19.067 | AJ99: =+G99 -> 21.18
N100: =ROUNDUP(SUM(N8:N99),0) -> 107 | O100: =ROUNDUP(SUM(O8:O99),0) -> 21 | P100: =ROUNDUP(SUM(P8:P99),0) -> 201 | Q100: =ROUNDUP(SUM(Q8:Q99),0) -> 850 | R100: =ROUNDUP(SUM(R8:R99),0) -> 365 | S100: =ROUNDUP(SUM(S8:S99),0) -> 357 | U100: =ROUNDUP(SUM(U8:U99),0) -> 521 | V100: =ROUNDUP(SUM(V8:V99),0) -> 14 | W100: =ROUNDUP(SUM(W8:W99),0) -> 5 | X100: =ROUNDUP(SUM(X8:X99),0) -> 715 | Y100: =ROUNDUP(SUM(Y8:Y99),0) -> 0 | Z100: =ROUNDUP(SUM(Z8:Z99),0) -> 2180 | AA100: =ROUNDUP(SUM(AA8:AA99),0) -> 255 | AB100: =ROUNDUP(SUM(AB8:AB99),0) -> 102 | AD100: =ROUNDUP(SUM(AD8:AD99),0) -> 79 | AE100: =ROUNDUP(SUM(AE8:AE99),0) -> 189 | AF100: =ROUNDUP(SUM(AF8:AF99),0) -> 207 | AG100: =ROUNDUP(SUM(AG8:AG99),0) -> 165 | AH100: =ROUNDUP(SUM(AH8:AH99),0) -> 165 | AI100: =ROUNDUP(SUM(AI8:AI99),0) -> 274 | AJ100: =ROUNDUP(SUM(AJ8:AJ99),0) -> 369 | AL100: =ROUNDUP(SUM(AL8:AL99),0) -> 146 | AM100: =ROUNDUP(SUM(AM8:AM99),0) -> 89 | AN100: =ROUNDUP(SUM(AN8:AN99),0) -> 652 | AO100: =ROUNDUP(SUM(AO8:AO99),0) -> 37 | AP100: =ROUNDUP(SUM(AP8:AP99),0) -> 62 | AQ100: =ROUNDUP(SUM(AQ8:AQ99),0) -> 0 | AR100: =ROUNDUP(SUM(AR8:AR99),0) -> 668 | AS100: =ROUNDUP(SUM(AS8:AS99),0) -> 446 | ... AU100: =ROUNDUP(SUM(AU8:AU99),0) -> 370 | AW100: =ROUNDUP(SUM(AW8:AW99),0) -> 24 | AX100: =ROUNDUP(SUM(AX8:AX99),0) -> 11 | AY100: =ROUNDUP(SUM(AY8:AY99),0) -> 43 | AZ100: =ROUNDUP(SUM(AZ8:AZ99),0) -> 3 | BA100: =ROUNDUP(SUM(BA8:BA99),0) -> 8 | BB100: =ROUNDUP(SUM(BB8:BB99),0) -> 72 | BD100: =ROUNDUP(SUM(BD8:BD99),0) -> 63 | BE100: =ROUNDUP(SUM(BE8:BE99),0) -> 101 | BF100: =ROUNDUP(SUM(BF8:BF99),0) -> 898 | BG100: =ROUNDUP(SUM(BG8:BG99),0) -> 88 | BH100: =ROUNDUP(SUM(BH8:BH99),0) -> 27 | BI100: =ROUNDUP(SUM(BI8:BI99),0) -> 25 | BJ100: =ROUNDUP(SUM(BJ8:BJ99),0) -> 180 | BK100: =ROUNDUP(SUM(BK8:BK99),0) -> 25 | ... BO100: =ROUNDUP(SUM(BO8:BO99),0) -> 263 | BQ100: =ROUNDUP(SUM(BQ8:BQ99),0) -> 82 | BR100: =ROUNDUP(SUM(BR8:BR99),0) -> 493 | BS100: =ROUNDUP(SUM(BS8:BS99),0) -> 0 | BT100: =ROUNDUP(SUM(BT8:BT99),0) -> 136 | BU100: =ROUNDUP(SUM(BU8:BU99),0) -> 2180 | BV100: =ROUNDUP(SUM(BV8:BV99),0) -> 525 | BW100: =ROUNDUP(SUM(BW8:BW99),0) -> 296 | BX100: =ROUNDUP(SUM(BX8:BX99),0) -> 668 | ... BZ100: =ROUNDUP(SUM(BZ8:BZ99),0) -> 281 | CB100: =ROUNDUP(SUM(CB8:CB99),0) -> 11 | CC100: =ROUNDUP(SUM(CC8:CC99),0) -> 119 | CD100: =ROUNDUP(SUM(CD8:CD99),0) -> 25 | CE100: =ROUNDUP(SUM(CE8:CE99),0) -> 222 | CF100: =ROUNDUP(SUM(CF8:CF99),0) -> 67 | CG100: =ROUNDUP(SUM(CG8:CG99),0) -> 23 | CH100: =ROUNDUP(SUM(CH8:CH99),0) -> 16 | CI100: =ROUNDUP(SUM(CI8:CI99),0) -> 45 | ... CX100: =ROUNDUP(SUM(CX8:CX99),0) -> 40 | CZ100: =ROUNDUP(SUM(CZ8:CZ82),0) -> 0 | DA100: =ROUNDUP(SUM(DA8:DA82),0) -> 0 | DB100: =ROUNDUP(SUM(DB8:DB82),0) -> 0 | DC100: =ROUNDUP(SUM(DC8:DC82),0) -> 0 | DD100: =ROUNDUP(SUM(DD8:DD82),0) -> 0 | DE100: =ROUNDUP(SUM(DE8:DE82),0) -> 0 | DF100: =ROUNDUP(SUM(DF8:DF82),0) -> 0 | DG100: =ROUNDUP(SUM(DG8:DG82),0) -> 0 | ... DI100: =ROUNDUP(SUM(DI8:DI82),0) -> 0
AE101: 0.15 | AJ101: 0.15
...

Sheet Computo
H2: 1.25
B3: Vigas de fundación | C3: Largo | D3: Ancho | E3: e | F3: m3 | G3: H°A° | H3: EXC.
B4: PB | G4: =+SUM(F5:F11) -> 2.1735 | H4: =+G4*H2 -> 2.716875
B5: Espacio de mantenimiento frente | C5: 1.5 | D5: 0.3 | E5: 0.3 | F5: =+C5*D5*E5 -> 0.135
B6: Espacio de mantenimiento frente | C6: 4.6 | D6: 0.3 | E6: 0.3 | F6: =+C6*D6*E6 -> 0.414
B7: Sala de tanques | C7: 5.8 | D7: 0.3 | E7: 0.3 | F7: =+C7*D7*E7 -> 0.522
B8: Espacio de mantenimiento CF | C8: 4 | D8: 0.3 | E8: 0.3 | F8: =+C8*D8*E8 -> 0.36
B9: Caja de escaleras | C9: 4.35 | D9: 0.3 | E9: 0.3 | F9: =+C9*D9*E9 -> 0.3915
B10: Baño Aux. | C10: 3.3 | D10: 0.3 | E10: 0.3 | F10: =+C10*D10*E10 -> 0.297
B11: Pasillo Aux. | C11: 0.6 | D11: 0.3 | E11: 0.3 | F11: =+C11*D11*E11 -> 0.054
C12: =+SUM(C4:C11) -> 24.15 | F12: =+SUM(F4:F11) -> 2.1735 | G12: =+SUM(G4:G11) -> 2.1735 | H12: =+SUM(H4:H11) -> 2.716875
C13: =+ROUND(C12,0) -> 24 | G13: =+ROUND(G12,0) -> 2 | H13: =+ROUND(H12,0) -> 3
B16: Picado de medianeras | C16: Largo | D16: h | E16: m2 | F16: REP | G16: m2 | H16: Subtotal
B17: PB | H17: =+SUM(G18:G38) -> 48.648
B18: C01 | C18: 0.7 | D18: 3.2 | E18: =+C18*D18 -> 2.24 | F18: 1 | G18: =+E18*F18 -> 2.24
B19: C03 | C19: 0.7 | D19: 3.2 | E19: =+C19*D19 -> 2.24 | F19: 1 | G19: =+E19*F19 -> 2.24
B20: C04 | C20: 0.7 | D20: 3.2 | E20: =+C20*D20 -> 2.24 | F20: 1 | G20: =+E20*F20 -> 2.24
B21: C06 | C21: 0.7 | D21: 3.2 | E21: =+C21*D21 -> 2.24 | F21: 1 | G21: =+E21*F21 -> 2.24
B22: C07 | C22: 0.7 | D22: 3.2 | E22: =+C22*D22 -> 2.24 | F22: 1 | G22: =+E22*F22 -> 2.24
B23: M5 | C23: 1.8 | D23: 3.2 | E23: =+C23*D23 -> 5.76 | F23: 1 | G23: =+E23*F23 -> 5.76
B24: M2 | C24: 1.3 | D24: 3.2 | E24: =+C24*D24 -> 4.16 | F24: 1 | G24: =+E24*F24 -> 4.16
B25: C09 | C25: 0.7 | D25: 3.2 | E25: =+C25*D25 -> 2.24 | F25: 1 | G25: =+E25*F25 -> 2.24
B26: C11 | C26: 0.8 | D26: 3.2 | E26: =+C26*D26 -> 2.56 | F26: 1 | G26: =+E26*F26 -> 2.56
B27: C13 | C27: 0.8 | D27: 3.2 | E27: =+C27*D27 -> 2.56 | F27: 1 | G27: =+E27*F27 -> 2.56
B28: C14 | C28: 0.8 | D28: 3.2 | E28: =+C28*D28 -> 2.56 | F28: 1 | G28: =+E28*F28 -> 2.56
B29: C16 | C29: 0.8 | D29: 3.2 | E29: =+C29*D29 -> 2.56 | F29: 1 | G29: =+E29*F29 -> 2.56
... B38: V030 | C38: 3.32 | D38: 0.45 | E38: =+C38*D38 -> 1.494 | F38: 1 | G38: =+E38*F38 -> 1.494
B39: 1P | H39: =+SUM(G40:G47) -> 15.89
B40: C04 | C40: 0.7 | D40: 1.5 | E40: =+C40*D40 -> 1.05 | F40: 1 | G40: =+E40*F40 -> 1.05
B41: C07 | C41: 0.7 | D41: 1.5 | E41: =+C41*D41 -> 1.05 | F41: 1 | G41: =+E41*F41 -> 1.05
B42: C14 | C42: 0.7 | D42: 1.5 | E42: =+C42*D42 -> 1.05 | F42: 1 | G42: =+E42*F42 -> 1.05
B43: C06 | C43: 0.7 | D43: 2.8 | E43: =+C43*D43 -> 1.96 | F43: 1 | G43: =+E43*F43 -> 1.96
B44: M5 | C44: 1.8 | D44: 2.8 | E44: =+C44*D44 -> 5.04 | F44: 1 | G44: =+E44*F44 -> 5.04
B45: M2 | C45: 1.3 | D45: 2.8 | E45: =+C45*D45 -> 3.64 | F45: 1 | G45: =+E45*F45 -> 3.64
B46: C13 | C46: 0.7 | D46: 1.5 | E46: =+C46*D46 -> 1.05 | F46: 1 | G46: =+E46*F46 -> 1.05
B47: C16 | C47: 0.7 | D47: 1.5 | E47: =+C47*D47 -> 1.05 | F47: 1 | G47: =+E47*F47 -> 1.05
H48: =SUM(H17:H47) -> 64.538
H49: =+ROUNDUP(H48,0) -> 65
B52: PINTURA PUERTAS
H53: 2
B54: Descripción | C54: Cant | D54: Ancho | E54: h | F54: Caras | G54: m2 hojas | H54: Perim | I54: ancho | J54: m2 marcos | K54: m2 | L54: Subtotal
B55: Placa MDF 0,80 m | C55: =+Locales!AY100 -> 43 | D55: 0.8 | E55: 2.05 | F55: 2 | G55: =+D55*E55*F55 -> 3.28 | H55: =+(E55*$H$53)+D55 -> 4.9 | I55: =0.15+0.04+0.04 -> 0.23 | J55: =+H55*I55 -> 1.127 | K55: =+G55+J55 -> 4.407 | L55: =+C55*K55 -> 189.501 | N55: =+C55*J55 -> 48.461
B56: Chapa F60 | C56: =+Locales!AX100 -> 11 | D56: 0.9 | E56: 2.05 | F56: 2 | G56: =+D56*E56*F56 -> 3.69 | H56: =+(E56*$H$53)+D56 -> 5 | I56: =0.15+0.04+0.04 -> 0.23 | J56: =+H56*I56 -> 1.15 | K56: =+G56+J56 -> 4.84 | L56: =+C56*K56 -> 53.24 | N56: =+C56*J56 -> 12.65
B57: Chapa F30 0,90 m | C57: =+Locales!AW100 -> 24 | D57: 0.9 | E57: 2.05 | F57: 2 | G57: =+D57*E57*F57 -> 3.69 | H57: =+(E57*$H$53)+D57 -> 5 | I57: =0.15+0.04+0.04 -> 0.23 | J57: =+H57*I57 -> 1.15 | K57: =+G57+J57 -> 4.84 | L57: =+C57*K57 -> 116.16 | N57: =+C57*J57 -> 27.6
B58: Chapa 0,80 m | C58: =+Locales!AZ100 -> 3 | D58: 0.8 | E58: 2.05 | F58: 2 | G58: =+D58*E58*F58 -> 3.28 | H58: =+(E58*$H$53)+D58 -> 4.9 | I58: =0.15+0.04+0.04 -> 0.23 | J58: =+H58*I58 -> 1.127 | K58: =+G58+J58 -> 4.407 | L58: =+C58*K58 -> 13.221 | N58: =+C58*J58 -> 3.381
B59: Puerta Ascensor | C59: =+Locales!BA100-1 -> 7 | D59: 0.9 | E59: 2.05 | F59: 1 | G59: =+D59*E59*F59 -> 1.845 | H59: =+(E59*$H$53)+D59 -> 5 | I59: =0.15+0.04+0.04 -> 0.23 | J59: =+H59*I59 -> 1.15 | K59: =+G59+J59 -> 2.995 | L59: =+C59*K59 -> 20.965 | N59: =+C59*J59 -> 8.05
C60: =SUM(C55:C59) -> 88 | L60: =SUM(L55:L59) -> 393.087 | N60: =SUM(N55:N59) -> 100.142 | O60: =+SUM(L60:N60) -> 493.229
B63: BARANDAS y HERRERIAS
C64: Cant | D64: Ancho | E64: h | F64: m2 | G64: Caras | H64: Subt | I64: Total
B65: PATIO INTERNO | J65: =+SUM(I66) -> 22.4
B66: Hueco 1º a 4º | C66: 4 | D66: 4 | E66: 0.7 | F66: =+D66*E66 -> 2.8 | G66: 2 | H66: =+F66*G66 -> 5.6 | I66: =+H66*C66 -> 22.4
B67: FRENTE | J67: =+SUM(I68:I70) -> 75.7
B68: Balcones Frente - 2º a 5º | C68: 4 | D68: 10.3 | E68: 0.6 | F68: =+D68*E68 -> 6.18 | G68: 2 | H68: =+F68*G68 -> 12.36 | I68: =+H68*C68 -> 49.44
B69: Balcones Frente - 6° | C69: 1 | D69: 7.8 | E69: 0.6 | F69: =+D69*E69 -> 4.68 | G69: 2 | H69: =+F69*G69 -> 9.36 | I69: =+H69*C69 -> 9.36
B70: Divisores | C70: 5 | D70: 1.3 | E70: 2.6 | F70: =+D70*E70 -> 3.38 | G70: 1 | H70: =+F70*G70 -> 3.38 | I70: =+H70*C70 -> 16.9
B71: FACHADA | J71: =+SUM(I72:I74) -> 40.072
B72: Med. Luz | C72: 1 | D72: 3.73 | E72: 2.2 | F72: =+D72*E72 -> 8.206 | G72: 2 | H72: =+F72*G72 -> 16.412 | I72: =+H72*C72 -> 16.412
B73: Porton | C73: 1 | D73: 3 | E73: 2.6 | F73: =+D73*E73 -> 7.8 | G73: 2 | H73: =+F73*G73 -> 15.6 | I73: =+H73*C73 -> 15.6
B74: PB | C74: 1 | D74: 1.55 | E74: 2.6 | F74: =+D74*E74 -> 4.03 | G74: 2 | H74: =+F74*G74 -> 8.06 | I74: =+H74*C74 -> 8.06
B75: CONTRAFRENTE | J75: =+SUM(I76:I78) -> 119.04
B76: Balcones CFrente - 1º a 6º | C76: 6 | D76: 10.5 | E76: 0.7 | F76: =+D76*E76 -> 7.35 | G76: 2 | H76: =+F76*G76 -> 14.7 | I76: =+H76*C76 -> 88.2
B77: Balcones CFrente - 4° | C77: 1 | D77: 9 | E77: 0.5 | F77: =+D77*E77 -> 4.5 | G77: 2 | H77: =+F77*G77 -> 9 | I77: =+H77*C77 -> 9
B78: Divisores | C78: 6 | D78: 1.4 | E78: 2.6 | F78: =+D78*E78 -> 3.64 | G78: 1 | H78: =+F78*G78 -> 3.64 | I78: =+H78*C78 -> 21.84
B79: ESCALERA | J79: =+SUM(I80:I83) -> 216
B80: Esc. PPAL - Pasamos externo | C80: 8 | D80: 1 | E80: 10 | F80: =+D80*E80 -> 10 | G80: 1 | H80: =+F80*G80 -> 10 | I80: =+H80*C80 -> 80
B81: Esc. PPAL - Pasamos interno | C81: 8 | D81: 1 | E81: 5 | F81: =+D81*E81 -> 5 | G81: 1 | H81: =+F81*G81 -> 5 | I81: =+H81*C81 -> 40
B82: Esc. SEC - Pasamos externo | C82: 8 | D82: 1 | E82: 8 | F82: =+D82*E82 -> 8 | G82: 1 | H82: =+F82*G82 -> 8 | I82: =+H82*C82 -> 64
B83: Esc. SEC - Pasamos interno | C83: 8 | D83: 1 | E83: 4 | F83: =+D83*E83 -> 4 | G83: 1 | H83: =+F83*G83 -> 4 | I83: =+H83*C83 -> 32
I84: =SUM(I65:I83) -> 473.212 | J84: =SUM(J65:J83) -> 473.212
B87: PROTECCIONES Y DEFENSAS
B89: Defensas frente y contrafrente
C90: Ml | D90: Cant | E90: Subtotal
B91: Frente | C91: 10 | D91: 2 | E91: =+C91*D91 -> 20
B92: Contrafrente | C92: 10 | D92: 2 | E92: =+C92*D92 -> 20
B93: Fachada lat | C93: 25 | D93: 4 | E93: =+C93*D93 -> 100
D94: =SUM(D91:D93) -> 8 | E94: =+SUM(E91:E93) -> 140
B96: BARANDAS
B97: FRENTE
B98: Balcones 1° a 4° | C98: 10 | D98: 6 | E98: =+D98*C98 -> 60
B99: CF
B100: Balcones 1° a 4° | C100: 10 | D100: 7 | E100: =+D100*C100 -> 70
E101: =+SUM(E98:E100) -> 130
B104: ATRIM VERTICAL
B106: Descripción | C106: ml | D106: Rep | E106: Subtotal
B107: PLANTA TIPO 1° a 5° | F107: =+SUM(E108:E115) -> 109
B108: Cocina A (2 amb) | C108: 0 | D108: 5 | E108: =+C108*D108 -> 0
B109: Cocina B (mono) | C109: 0 | D109: 5 | E109: =+C109*D109 -> 0
B110: Cocina C (mono) | C110: 0 | D110: 5 | E110: =+C110*D110 -> 0
B111: Cocina D (2 amb) | C111: 0 | D111: 5 | E111: =+C111*D111 -> 0
B112: Baños A (2 amb) | C112: =2.2+2.2+1 -> 5.4 | D112: 5 | E112: =+C112*D112 -> 27
B113: Baños B (mono) | C113: =2.2+2.2+1 -> 5.4 | D113: 5 | E113: =+C113*D113 -> 27
B114: Baños C (mono) | C114: =2.2+2.2+1 -> 5.4 | D114: 5 | E114: =+C114*D114 -> 27
B115: Baños D (dos amb) | C115: =2.2+2.2+1.2 -> 5.6 | D115: 5 | E115: =+C115*D115 -> 28
B116: PLANTA TIPO 6° | F116: =+SUM(E117:E123) -> 21.5
B117: Cocina A (2 amb) | C117: 0 | D117: 1 | E117: =+C117*D117 -> 0
B118: Cocina B (mono) | C118: 0 | D118: 1 | E118: =+C118*D118 -> 0
B119: Cocina C (2 amb) | C119: 2.6 | D119: 1 | E119: =+C119*D119 -> 2.6
B120: Baños A (2 amb) | C120: =2.2+2.2+1 -> 5.4 | D120: 1 | E120: =+C120*D120 -> 5.4
B121: Baños B (mono) | C121: =2.2+2.2+1 -> 5.4 | D121: 1 | E121: =+C121*D121 -> 5.4
B122: Baños C (2 amb) | C122: 2.2 | D122: 1 | E122: =+C122*D122 -> 2.2
...

Sheet INCEND
B1: NOTA: CANTIDADES SALEN DE COMPUTO AUXILIAR INCENDIO
K2: =+'P.MO 06.25'!B4 -> 94177.138 | L2: =+'P.MO 06.25'!B5 -> 84612.513 | M2: =+'P.MO 06.25'!B6 -> 72132.138 | N2: =+'P.MO 06.25'!B7 -> 67240.499 | O2: 1.5
B3: Descripción | C3: Un | D3: Cant | E3: P Unit | F3: Subtotal | I3: TAREA | J3: DIA | K3: ES | L3: OF | M3: MED | N3: AY | O3: GGBB
B4: Por tendido cañeria de incendio - (no incluye gabinetes, manguera, lanza y valvula) | G4: =+SUM(F5:F18) -> 3702330.1 | I4: Pintura | J4: 3 | N4: 2 | O4: =(+K4*$K$2+L4*$L$2+M4*$M$2+N4*$N$2)*J4 -> 403442.99
B5: CAÑO DE HIERRO GALVANIZADO 2" x 6,4 m | C5: tira | D5: 2 | E5: =VLOOKUP(B5,Cotizaciones!B:D,3,0) -> 213864.12 | F5: =+D5*E5 -> 427728.25 | I5: Tendido montante | J5: 7 | K5: 1 | M5: 1 | O5: =(+K5*$K$2+L5*$L$2+M5*$M$2+N5*$N$2)*J5 -> 1164164.9
B6: CAÑO DE HIERRO GALVANIZADO 2 1/2" x 6,4 m | C6: tira | D6: 8 | E6: =VLOOKUP(B6,Cotizaciones!B:D,3,0) -> 243957.3 | F6: =+D6*E6 -> 1951658.4 | I6: Amurado de gabinete | J6: 3 | K6: 1 | M6: 1 | O6: =(+K6*$K$2+L6*$L$2+M6*$M$2+N6*$N$2)*J6 -> 498927.83
B7: TEE REDUCCION GALVANIZADA 2 1/2" x 2" | C7: u | D7: 8 | E7: =VLOOKUP(B7,Cotizaciones!B:D,3,0) -> 21017.561 | F7: =+D7*E7 -> 168140.49 | I7: Colocación de mangueras | J7: 2 | K7: 1 | M7: 0.5 | O7: =(+K7*$K$2+L7*$L$2+M7*$M$2+N7*$N$2)*J7 -> 260486.41
B8: TEE GALVANIZADA 2 1/2" | C8: u | D8: 0 | E8: =VLOOKUP(B8,Cotizaciones!B:D,3,0) -> 23588.239 | F8: =+D8*E8 -> 0 | J8: =SUM(J4:J7) -> 15 | O8: =+SUM(O4:O7) -> 2327022.2
B9: CODO GALVANIZADO H-H 90° 2 1/2" | C9: u | D9: 4 | E9: =VLOOKUP(B9,Cotizaciones!B:D,3,0) -> 18240.035 | F9: =+D9*E9 -> 72960.138 | O9: =+O8*$O$2 -> 3490533.3 | P9: GGBB
B10: BUJE REDUCCION M - H 2 1/2" x 2" | C10: u | D10: 1 | E10: =VLOOKUP(B10,Cotizaciones!B:D,3,0) -> 8050.0172 | F10: =+D10*E10 -> 8050.0172
B11: CODO GALVANIZADO H-H 90° 2" | C11: u | D11: 1 | E11: =VLOOKUP(B11,Cotizaciones!B:D,3,0) -> 7526.1258 | F11: =+D11*E11 -> 7526.1258
B12: ROSCA CON TUERCA GALVANIZADA 2" | C12: u | D12: 8 | E12: =VLOOKUP(B12,Cotizaciones!B:D,3,0) -> 4907.0044 | F12: =+D12*E12 -> 39256.036
B13: CUPLA H - H GALVANIZADA 2 1/2" | C13: u | D13: =+D6 -> 8 | E13: =VLOOKUP(B13,Cotizaciones!B:D,3,0) -> 16504.372 | F13: =+D13*E13 -> 132034.98
B14: CUPLA H - H GALVANIZADA 2" | C14: u | D14: =+D5 -> 2 | E14: =VLOOKUP(B14,Cotizaciones!B:D,3,0) -> 6211.2478 | F14: =+D14*E14 -> 12422.496
B15: Esmalte sintetico 3 en 1 Bermellon x 4 lts | C15: tac | D15: 1 | E15: 100000 | F15: =+D15*E15 -> 100000
B16: Galvite | C16: tac | D16: 1 | E16: =+E15 -> 100000 | F16: =+D16*E16 -> 100000
B17: Rodillos y pinceles | C17: gl | D17: 0.2 | E17: =+SUM(E15:E16) -> 200000 | F17: =+D17*E17 -> 40000
B18: Desperdicio / Imprevistos / | C18: gl | D18: 0.21 | E18: =+SUM(F5:F17) -> 3059776.9 | F18: =+D18*E18 -> 642553.16
B19: BOCA GABINETE COMPLETA | G19: =+SUM(F20:F23) -> 3980380.6
B20: Válvula tipo teatro de 2" BSP x 1 3/4"INC. | C20: u | D20: 9 | E20: =VLOOKUP(B20,Cotizaciones!B:D,3,0) -> 51214.715 | F20: =+D20*E20 -> 460932.43
B21: Gabinete para manguera de 1 3/4" con puerta hierro angulo . s/vidrio 500 x 550 x 160 mm. | C21: u | D21: 9 | E21: =VLOOKUP(B21,Cotizaciones!B:D,3,0) -> 56938.712 | F21: =+D21*E21 -> 512448.41
B22: Manguera sintética RYL JET sello IRAM de 1 3/4" x 25 mts. | C22: u | D22: 9 | E22: =VLOOKUP(B22,Cotizaciones!B:D,3,0) -> 286985.31 | F22: =+D22*E22 -> 2582867.8
B23: Lanza de 1 3/4" con boquilla chorro PLENO Y NIEBLA regulable | C23: u | D23: 9 | E23: =VLOOKUP(B23,Cotizaciones!B:D,3,0) -> 47125.769 | F23: =+D23*E23 -> 424131.92
B24: IMPULSION COMPLETA | G24: =+SUM(F25:F26) -> 185687.18
B25: Válvula de Impulsión para Piso o Pared c/anilla giratoria de 2 1/2" | C25: u | D25: 1 | E25: =VLOOKUP(B25,Cotizaciones!B:D,3,0) -> 137686.19 | F25: =+D25*E25 -> 137686.19
B26: Tapa con inscripción BOMBEROS para pared | C26: u | D26: 1 | E26: =VLOOKUP(B26,Cotizaciones!B:D,3,0) -> 48000.991 | F26: =+D26*E26 -> 48000.991
F27: =+SUM(F4:F26) -> 7868397.9 | G27: =+SUM(G4:G26) -> 7868397.9

Sheet GAS
B3: NOTA: CANTIDADES SALEN DE COMPUTO AUXILIAR GAS / CH 2171_Computo gas
K4: =+'P.MO 06.25'!B4 -> 94177.138 | L4: =+'P.MO 06.25'!B5 -> 84612.513 | M4: =+'P.MO 06.25'!B6 -> 72132.138 | N4: =+'P.MO 06.25'!B7 -> 67240.499 | O4: 1.5
B5: Descripción | C5: Un | D5: Cant | E5: P Unit | F5: Subtotal | I5: TAREA | J5: DIA | K5: ES | L5: OF | M5: MED | N5: AY | O5: GGBB
B6: Tendido cañería | G6: =+SUM(F7:F43) -> 1540056.3 | I6: TENDIDO
B7: BZ TENARIS CANO EPOXI 11/4X6.40 MTS | C7: tira | D7: 1 | E7: =VLOOKUP(B7,Cotizaciones!B:D,3,0) -> 85882.267 | F7: =+D7*E7 -> 85882.267 | I7: Zanjeo PB Y tapado | J7: 3 | M7: 2 | O7: =(+K7*$K$4+L7*$L$4+M7*$M$4+N7*$N$4)*J7 -> 432792.83
B8: DEMA EPOXI TEE 11/4 | C8: u | D8: 4 | E8: =VLOOKUP(B8,Cotizaciones!B:D,3,0) -> 5407.9081 | F8: =+D8*E8 -> 21631.632 | I8: Tendido de cañerías | J8: 8 | K8: 1 | L8: 1 | M8: 1 | O8: =(+K8*$K$4+L8*$L$4+M8*$M$4+N8*$N$4)*J8 -> 2007374.3
B9: DEMA EPOXI CODO 90 HH 11/4 | C9: u | D9: 3 | E9: =VLOOKUP(B9,Cotizaciones!B:D,3,0) -> 3865.011 | F9: =+D9*E9 -> 11595.033 | I9: Armado de SM | J9: 2 | K9: 1 | L9: 1 | M9: 1 | O9: =(+K9*$K$4+L9*$L$4+M9*$M$4+N9*$N$4)*J9 -> 501843.58
B10: CB BRONCE BUJE RED 3/4X1/2 | C10: u | D10: 0 | E10: =VLOOKUP(B10,Cotizaciones!B:D,3,0) -> 1113.0378 | F10: =+D10*E10 -> 0 | I10: Armado de regulador y cuadro de medidores | J10: 1 | K10: 1 | L10: 1 | M10: 1 | O10: =(+K10*$K$4+L10*$L$4+M10*$M$4+N10*$N$4)*J10 -> 250921.79
B11: CB BRONCE BUJE RED 11/4X1 | C11: u | D11: 1 | E11: =VLOOKUP(B11,Cotizaciones!B:D,3,0) -> 4313.6239 | F11: =+D11*E11 -> 4313.6239 | I11: Amurado de gabinete | J11: 1 | L11: 1 | M11: 0.5 | O11: =(+K11*$K$4+L11*$L$4+M11*$M$4+N11*$N$4)*J11 -> 120678.58
B12: CB BRONCE BUJE RED 11/2X11/4 | C12: u | D12: 0 | E12: =VLOOKUP(B12,Cotizaciones!B:D,3,0) -> 3817.2823 | F12: =+D12*E12 -> 0 | J12: =SUM(J7:J11) -> 15 | O12: =+SUM(O7:O11) -> 3313611.1 | R12: =+G6 -> 1540056.3 | S12: MAT
B13: SUYAI ESFERICA P/GAS FORJADA 11/4 PASO TOTAL | C13: u | D13: 1 | E13: =VLOOKUP(B13,Cotizaciones!B:D,3,0) -> 94942.043 | F13: =+D13*E13 -> 94942.043 | O13: =+O12*$O$4 -> 4970416.6 | Q13: =+O13/R13 -> 0.7634494 | R13: =+O13+R12 -> 6510472.9 | S13: TOTAL
B14: FUSIOGAS TRANSICION HEMBRA 32 X 1 (203232) | C14: u | D14: 1 | E14: =VLOOKUP(B14,Cotizaciones!B:D,3,0) -> 4426.9741 | F14: =+D14*E14 -> 4426.9741
B15: FUSIOGAS TRANSICION HEMBRA 50 X 1 1/2 (203250) | C15: u | D15: 0 | E15: =VLOOKUP(B15,Cotizaciones!B:D,3,0) -> 14513.723 | F15: =+D15*E15 -> 0 | I15: COLOCACION
B16: SALUSTRI REGULADOR GAS GS-25 25 NM3/H APROBADO | C16: u | D16: 1 | E16: =VLOOKUP(B16,Cotizaciones!B:D,3,0) -> 139939.37 | F16: =+D16*E16 -> 139939.37 | I16: Colocación de calderas | J16: 0 | K16: 1 | O16: =(+K16*$K$4+L16*$L$4+M16*$M$4+N16*$N$4)*J16 -> 0
B17: FUSIOGAS TUBO 20 MM X 4.00 MTS (200020) | C17: tira | D17: 0 | E17: =VLOOKUP(B17,Cotizaciones!B:D,3,0) -> 11975.69 | F17: =+D17*E17 -> 0 | I17: Colocación de termos y armado de cuadro | J17: 2 | K17: 1 | M17: 1 | O17: =(+K17*$K$4+L17*$L$4+M17*$M$4+N17*$N$4)*J17 -> 332618.55
B18: FUSIOGAS TUBO 25 MM X 4.00 MTS (200025) | C18: tira | D18: 0 | E18: =VLOOKUP(B18,Cotizaciones!B:D,3,0) -> 15522.621 | F18: =+D18*E18 -> 0 | O18: =+SUM(O16:O17) -> 332618.55 | R18: =+G44 -> 43707.03 | S18: MAT
B19: FUSIOGAS TUBO 32 MM X 4.00 MTS (200032) | C19: tira | D19: 1 | E19: =VLOOKUP(B19,Cotizaciones!B:D,3,0) -> 23660.65 | F19: =+D19*E19 -> 23660.65 | O19: =+O18*$O$4 -> 498927.83 | Q19: =+O19/R19 -> 0.91945407 | R19: =+O19+R18 -> 542634.86 | S19: TOTAL
B20: FUSIOGAS TUBO 50 MM X 4.00 MTS (200050) | C20: tira | D20: 14 | E20: =VLOOKUP(B20,Cotizaciones!B:D,3,0) -> 34177.774 | F20: =+D20*E20 -> 478488.84
B21: FUSIOGAS CUPLA FUSION 20 MM (203020) | C21: u | D21: 0 | E21: =VLOOKUP(B21,Cotizaciones!B:D,3,0) -> 1073.1742 | F21: =+D21*E21 -> 0
B22: FUSIOGAS CUPLA FUSION 25 MM (203025) | C22: u | D22: 0 | E22: =VLOOKUP(B22,Cotizaciones!B:D,3,0) -> 1208.6673 | F22: =+D22*E22 -> 0
B23: FUSIOGAS CUPLA FUSION 32 MM (203032) | C23: u | D23: 3 | E23: =VLOOKUP(B23,Cotizaciones!B:D,3,0) -> 1372.2208 | F23: =+D23*E23 -> 4116.6624
B24: FUSIOGAS CUPLA FUSION 50 MM (203050) | C24: u | D24: 14 | E24: =VLOOKUP(B24,Cotizaciones!B:D,3,0) -> 6565.6081 | F24: =+D24*E24 -> 91918.513
B25: FUSIOGAS TEE FUSION 25 MM (202025) | C25: u | D25: 0 | E25: =VLOOKUP(B25,Cotizaciones!B:D,3,0) -> 2889.7365 | F25: =+D25*E25 -> 0
B26: FUSIOGAS TEE FUSION 32 MM (202032) | C26: u | D26: 0 | E26: =VLOOKUP(B26,Cotizaciones!B:D,3,0) -> 3803.3812 | F26: =+D26*E26 -> 0
B27: FUSIOGAS TEE FUSION 50 MM (202050) | C27: u | D27: 3 | E27: =VLOOKUP(B27,Cotizaciones!B:D,3,0) -> 13292.887 | F27: =+D27*E27 -> 39878.66
B28: FUSIOGAS CODO A 90 FUSION 20 MM (201020) | C28: u | D28: 0 | E28: =VLOOKUP(B28,Cotizaciones!B:D,3,0) -> 1428.0621 | F28: =+D28*E28 -> 0
B29: FUSIOGAS CODO A 90 FUSION 25 MM (201025) | C29: u | D29: 0 | E29: =VLOOKUP(B29,Cotizaciones!B:D,3,0) -> 1557.5837 | F29: =+D29*E29 -> 0
B30: FUSIOGAS CODO A 90 FUSION 32 MM (201032) | C30: u | D30: 4 | E30: =VLOOKUP(B30,Cotizaciones!B:D,3,0) -> 2394.2449 | F30: =+D30*E30 -> 9576.9795
B31: FUSIOGAS CODO A 90 FUSION 50 MM (201050) | C31: u | D31: 6 | E31: =VLOOKUP(B31,Cotizaciones!B:D,3,0) -> 9913.7916 | F31: =+D31*E31 -> 59482.75
... B39: FUSIOGAS LLAVE PASO C/MANIVELA Y ROSETA 20 MM (207 | C39: u | D39: 0 | E39: =VLOOKUP(B39,Cotizaciones!B:D,3,0) -> 15209.727 | F39: =+D39*E39 -> 0
B40: FUSIOGAS LLAVE PASO C/MANIVELA Y ROSETA 25 MM (207 | C40: u | E40: =VLOOKUP(B40,Cotizaciones!B:D,3,0) -> 15225.78 | F40: =+D40*E40 -> 0
B41: FUSIOGAS LLAVE PASO C/MANIVELA Y ROSETA 32 MM (207 | C41: u | D41: 3 | E41: =VLOOKUP(B41,Cotizaciones!B:D,3,0) -> 36808.069 | F41: =+D41*E41 -> 110424.21
B42: Gabinete para gas | C42: gl | D42: 1 | E42: 70000 | F42: =+D42*E42 -> 70000
B43: Consumibles y desperdicio (roscadas/brocas/etc.) | C43: gl | D43: 0.21 | E43: =+SUM(F7:F41) -> 1214922.5 | F43: =+D43*E43 -> 255133.73
B44: Colocación de artefactos | G44: =+SUM(F45:F49) -> 43707.03
B45: DINATECNICA EXTENSIBLE GAS 1/2 X 20-42 CM | C45: u | D45: 3 | E45: =VLOOKUP(B45,Cotizaciones!B:D,3,0) -> 11763.267 | F45: =+D45*E45 -> 35289.8
B46: DINATECNICA EXTENSIBLE GAS 3/4 X 20-42 CM | C46: u | D46: 0 | E46: =VLOOKUP(B46,Cotizaciones!B:D,3,0) -> 16928.292 | F46: =+D46*E46 -> 0
B47: DINATECNICA KIT CONEXION CALDERAS MIXTAS | C47: u | D47: 0 | E47: =VLOOKUP(B47,Cotizaciones!B:D,3,0) -> 80849.001 | F47: =+D47*E47 -> 0
B48: REJA VENTILACION 15X15 ESMALTADA (450731) | C48: u | D48: 1 | E48: =VLOOKUP(B48,Cotizaciones!B:D,3,0) -> 831.71191 | F48: =+D48*E48 -> 831.71191
B49: Consumibles y desperdicio (roscadas/brocas/etc.) | C49: gl | D49: 0.21 | E49: =+SUM(F45:F48) -> 36121.512 | F49: =+D49*E49 -> 7585.5176
G50: =SUM(G6:G49) -> 1583763.3

Sheet CALEFA
B2: NOTA: CANTIDADES SALEN DE COMPUTO AUXILIAR CALEFA
K3: =+'P.MO 06.25'!B4 -> 94177.138 | L3: =+'P.MO 06.25'!B5 -> 84612.513 | M3: =+'P.MO 06.25'!B6 -> 72132.138 | N3: =+'P.MO 06.25'!B7 -> 67240.499 | O3: 1.4
B4: Descripción | C4: Un | D4: Cant | E4: P Unit | F4: Subtotal | I4: TAREA | J4: DIA | K4: ES | L4: OF | M4: MED | N4: AY | O4: GGBB
B5: Tendido cañería | G5: =+SUM(F7:F18) -> 4230816.9
B6: PISO
B7: HIDROFLEX TUBO 16 MM ROLLO X 240 MTS (1504) | C7: rol | D7: 7 | E7: =VLOOKUP(B7,Cotizaciones!B:D,3,0) -> 204450.58 | F7: =+D7*E7 -> 1431154.1
B8: HIDROFLEX MEMBRANA TERMICA 1X20 MT ESP 10MM (8100) | C8: rol | D8: 18 | E8: =VLOOKUP(B8,Cotizaciones!B:D,3,0) -> 60978.66 | F8: =+D8*E8 -> 1097615.9
B9: HIDROFLEX CURVA TUBOS 16 MM (1670) | C9: u | D9: 38 | E9: =VLOOKUP(B9,Cotizaciones!B:D,3,0) -> 1327.8383 | F9: =+D9*E9 -> 50457.856
B10: HIDROFLEX PRECINTOS 200 MM X 100 UNIDADES (1880) | C10: paq | D10: 15 | E10: =VLOOKUP(B10,Cotizaciones!B:D,3,0) -> 4474.6598 | F10: =+D10*E10 -> 67119.896
B11: Rollo Polietileno negro 2x50 mt x 200mic | C11: rol | D11: 4 | E11: =VLOOKUP(B11,Cotizaciones!B:D,3,0) -> 27000 | F11: =+D11*E11 -> 108000
B12: Malla N° 4 Liv 15 x 15 3 x 2 mt | C12: u | D12: 60 | E12: =VLOOKUP(B12,Cotizaciones!B:D,3,0) -> 10716.59 | F12: =+D12*E12 -> 642995.4
B13: CONEXIÓN CALDERA
B14: H-3 TUBO AGUA CALIENTE 19X3.9X6 | C14: tira | D14: 8 | E14: 10000 | F14: =+D14*E14 -> 80000
B15: H-3 CODO ø19 MM.FUSION | C15: u | D15: 16 | E15: 600 | F15: =+D15*E15 -> 9600
B16: H-3 CODO ø19 MM.FUS-R.MET.H. | C16: u | D16: 8 | E16: =VLOOKUP(B16,Cotizaciones!B:D,3,0) -> 2090.7762 | F16: =+D16*E16 -> 16726.209
B17: H3 COVERTHOR BLANCO 3/8 X 5MM X 2.00 MT (3200) | C17: tira | D17: =+D14*3 -> 24 | E17: =VLOOKUP(B17,Cotizaciones!B:D,3,0) -> 917.14149 | F17: =+D17*E17 -> 22011.396
B18: Consumibles / Desperdicio | C18: gl | D18: 0.2 | E18: =+SUM(F7:F17) -> 3525680.7 | F18: =+D18*E18 -> 705136.15
B19: GABINETE, COLECTOR | G19: =+SUM(F20:F23) -> 1643547.6
B20: HIDROFLEX COLECTOR LUXUS CROMO 4 SAL.16 MM | C20: u | D20: 1 | E20: =VLOOKUP(B20,Cotizaciones!B:D,3,0) -> 285491.67 | F20: =+D20*E20 -> 285491.67
B21: HIDROFLEX COLECTOR LUXUS CROMO 5 SAL.16 MM | C21: u | D21: 3 | E21: =VLOOKUP(B21,Cotizaciones!B:D,3,0) -> 326160.39 | F21: =+D21*E21 -> 978481.18
B22: HIDROFLEX GABINETE P/COLECTOR 450 X 450 X 110 | C22: u | D22: 1 | E22: =VLOOKUP(B22,Cotizaciones!B:D,3,0) -> 78983.161 | F22: =+D22*E22 -> 78983.161
B23: HIDROFLEX GABINETE P/COLECTOR 600 X 450 X 110 | C23: u | D23: 3 | E23: =VLOOKUP(B23,Cotizaciones!B:D,3,0) -> 100197.18 | F23: =+D23*E23 -> 300591.53
F24: =+SUM(F5:F23) -> 5874364.4 | G24: =+SUM(G5:G23) -> 5874364.4

Sheet CLOACAL
K3: =+'P.MO 06.25'!B4 -> 94177.138 | L3: =+'P.MO 06.25'!B5 -> 84612.513 | M3: =+'P.MO 06.25'!B6 -> 72132.138 | N3: =+'P.MO 06.25'!B7 -> 67240.499 | O3: 1.5
B4: Descripción | C4: Un | D4: Cant | E4: P Unit | F4: Subtotal | I4: TAREA | J4: DIA | K4: ES | L4: OF | M4: MED | N4: AY | O4: GGBB
B5: MONO AMB | G5: =+SUM(F6:F47) -> 130431.68
B6: Ø 110
B7: AWA TUBO PPN CLOACAL ø.110X4.00 3/1035 | C7: tira | D7: 1 | E7: =VLOOKUP(B7,Cotizaciones!B:D,3,0) -> 15376.594 | F7: =+D7*E7 -> 15376.594
B8: AWA CODO MH 45*PPN CLOACAL.ø110 6/2004 | C8: Un | D8: 2 | E8: =VLOOKUP(B8,Cotizaciones!B:D,3,0) -> 2066.7612 | F8: =+D8*E8 -> 4133.5224
B9: AWA MANG/CUPLA PPN CLOAC.ø110 10/2016 | C9: Un | D9: 2 | E9: =VLOOKUP(B9,Cotizaciones!B:D,3,0) -> 2137.1599 | F9: =+D9*E9 -> 4274.3198
B10: AWA TAPA PPN CLOACAL ø.110 10/2036 | C10: Un | D10: 4 | E10: =VLOOKUP(B10,Cotizaciones!B:D,3,0) -> 1603.0206 | F10: =+D10*E10 -> 6412.0823
B11: Ø 63
B12: AWA TUBO PPN CLOACAL ø 63X4.00 10/1026 | C12: tira | D12: 0.5 | E12: =VLOOKUP(B12,Cotizaciones!B:D,3,0) -> 8313.6868 | F12: =+D12*E12 -> 4156.8434
B13: AWA CODO MH 90*PPN CLOACAL ø63 20/2007 | C13: un | D13: 0 | E13: =VLOOKUP(B13,Cotizaciones!B:D,3,0) -> 1014.4279 | F13: =+D13*E13 -> 0
B14: AWA CODO MH 45*PPN CLOACAL ø63 20/2003 | C14: Un | D14: 1 | E14: =VLOOKUP(B14,Cotizaciones!B:D,3,0) -> 960.65248 | F14: =+D14*E14 -> 960.65248
B15: AWA MANG/CUPLA PPN CLOAC.ø 63 20/2015 | C15: Un | D15: 1 | E15: =VLOOKUP(B15,Cotizaciones!B:D,3,0) -> 960.65248 | F15: =+D15*E15 -> 960.65248
B16: Ø 50
B17: AWA TUBO PPN CLOACAL ø 50X4.00 10/1017 | C17: tira | D17: 0.5 | E17: =VLOOKUP(B17,Cotizaciones!B:D,3,0) -> 6715.6586 | F17: =+D17*E17 -> 3357.8293
B18: AWA CODO MH 90*PPN CLOACAL ø50 20/2006 | C18: Un | D18: 2 | E18: =VLOOKUP(B18,Cotizaciones!B:D,3,0) -> 571.84027 | F18: =+D18*E18 -> 1143.6805
B19: AWA MANG/CUPLA PPN CLOAC.ø 50 20/2014 | C19: un | D19: 1 | E19: =VLOOKUP(B19,Cotizaciones!B:D,3,0) -> 723.32177 | F19: =+D19*E19 -> 723.32177
B20: AWA TAPA PPN CLOACAL ø 50 20/2037 | C20: Un | D20: 1 | E20: =VLOOKUP(B20,Cotizaciones!B:D,3,0) -> 586.21482 | F20: =+D20*E20 -> 586.21482
B21: Ø 40
B22: AWA TUBO PPN CLOACAL ø 40X4.00 10/1008 | C22: tira | D22: 1 | E22: =VLOOKUP(B22,Cotizaciones!B:D,3,0) -> 5296.1072 | F22: =+D22*E22 -> 5296.1072
B23: AWA CODO MH 90*PPN CLOACAL ø40 20/2005 | C23: Un | D23: 3 | E23: =VLOOKUP(B23,Cotizaciones!B:D,3,0) -> 432.16181 | F23: =+D23*E23 -> 1296.4854
B24: AWA CODO MH 45*PPN CLOACAL ø40 20/2001 | C24: Un | D24: 3 | E24: =VLOOKUP(B24,Cotizaciones!B:D,3,0) -> 399.55009 | F24: =+D24*E24 -> 1198.6503
B25: AWA MANG/CUPLA PPN CLOAC.ø 40 20/2013 | C25: Un | D25: 2 | E25: =VLOOKUP(B25,Cotizaciones!B:D,3,0) -> 658.67933 | F25: =+D25*E25 -> 1317.3587
B26: AWA TAPA PPN CLOACAL ø 40 20/2034 | C26: Un | D26: 1 | E26: =VLOOKUP(B26,Cotizaciones!B:D,3,0) -> 361.83842 | F26: =+D26*E26 -> 361.83842
B27: ACCESORIOS
B28: AWA GRAMPA RAPICLACK ø110 10/4170 | C28: Un | D28: =+D7*3 -> 3 | E28: =VLOOKUP(B28,Cotizaciones!B:D,3,0) -> 696.1543 | F28: =+D28*E28 -> 2088.4629
B29: AWA GRAMPA RAPICLACK ø 40-50-63 20/4167 | C29: un | D29: =+(D12+D17+D22)*3 -> 6 | E29: =VLOOKUP(B29,Cotizaciones!B:D,3,0) -> 424.1891 | F29: =+D29*E29 -> 2545.1346
B30: AWA BUJE RED.MH ø 63X50 20/2081 | C30: Un | D30: 1 | E30: =VLOOKUP(B30,Cotizaciones!B:D,3,0) -> 653.42875 | F30: =+D30*E30 -> 653.42875
B31: AWA BOCA ACCES.HOR.3 ACOM.ø110X63 4/2460 | C31: un | D31: 1 | E31: =VLOOKUP(B31,Cotizaciones!B:D,3,0) -> 4518.7195 | F31: =+D31*E31 -> 4518.7195
B32: AWA RAMAL 45*PPN CLOAC.ø 63X 63 20/2026 | C32: un | D32: 0 | E32: =VLOOKUP(B32,Cotizaciones!B:D,3,0) -> 2240.2995 | F32: =+D32*E32 -> 0
B33: AWA RAMAL 45*PPN CLOAC.ø110X 63 5/2024 | C33: un | D33: 1 | E33: =VLOOKUP(B33,Cotizaciones!B:D,3,0) -> 3362.0093 | F33: =+D33*E33 -> 3362.0093
B34: AWA RAMAL 45*PPN CLOAC.ø110X110 5/2023 | C34: un | D34: 1 | E34: =VLOOKUP(B34,Cotizaciones!B:D,3,0) -> 4732.896 | F34: =+D34*E34 -> 4732.896
B35: AWA RAMAL 90+ ø110X110 C/VENT. 2/2050 | C35: un | D35: 0 | E35: =VLOOKUP(B35,Cotizaciones!B:D,3,0) -> 6006.9588 | F35: =+D35*E35 -> 0
B36: AWA RAMAL 90+ ø110X 63 C/VENT. 2/2063 | C36: un | D36: 0 | E36: =VLOOKUP(B36,Cotizaciones!B:D,3,0) -> 7761.1919 | F36: =+D36*E36 -> 0
B37: AWA DISCO ANTIFILTRACION P/REJA 4/2077 | C37: un | D37: 3 | E37: 5000 | F37: =+D37*E37 -> 15000
B38: AWA SOPAPA BAÑERA VERTICAL BCE.CR.1/4128 | C38: un | D38: 0 | E38: =VLOOKUP(B38,Cotizaciones!B:D,3,0) -> 9528.6698 | F38: =+D38*E38 -> 0
B39: AWA ADAPT.SUPEREXCENT.INO.ø105"AC"4/2271 | C39: un | D39: 1 | E39: =VLOOKUP(B39,Cotizaciones!B:D,3,0) -> 4507.7019 | F39: =+D39*E39 -> 4507.7019
B40: AWA SIFON ROMPE ESPUMA PPN 1/7120 | C40: un | D40: 0 | E40: =VLOOKUP(B40,Cotizaciones!B:D,3,0) -> 9878.3824 | F40: =+D40*E40 -> 0
B41: AWA SOLUC.DESLIZ.AEROSOL 255 CM3 12/4023 | C41: un | D41: 1 | E41: =VLOOKUP(B41,Cotizaciones!B:D,3,0) -> 9863.9863 | F41: =+D41*E41 -> 9863.9863
B42: AWADUCT PILETA PATIO 7 ENT. C/SIFON 40X63 (2031) | C42: un | D42: 1 | E42: =VLOOKUP(B42,Cotizaciones!B:D,3,0) -> 6417.2898 | F42: =+D42*E42 -> 6417.2898
B43: AWA PORTAREJ.+REJA A*I*12X12 ø110 4/4002 | C43: un | D43: 0 | E43: =VLOOKUP(B43,Cotizaciones!B:D,3,0) -> 3704.4378 | F43: =+D43*E43 -> 0
B44: AWA PORTAREJ +TAPA A*I*15X15 ø110 4/4005 | C44: un | D44: 0 | E44: =VLOOKUP(B44,Cotizaciones!B:D,3,0) -> 4644.8303 | F44: =+D44*E44 -> 0
B45: AWA PILETA BALCON ø 63(M) 4/2062 | C45: un | D45: 1 | E45: =VLOOKUP(B45,Cotizaciones!B:D,3,0) -> 3447.2883 | F45: =+D45*E45 -> 3447.2883
B46: CONSUMIBLES | I46: Canaleteado | J46: 0.5 | M46: 1 | O46: =(+K46*$K$3+L46*$L$3+M46*$M$3+N46*$N$3)*J46 -> 36066.069 | R46: =+R48/T48 -> 0.3509731 | S46: =+S48/T48 -> 0.6490269
B47: CONSUMIBLES/DESPERDICIO/IMPREVISTO | C47: gl | D47: 0.2 | E47: =+SUM(F7:F45) -> 108693.07 | F47: =+D47*E47 -> 21738.614 | I47: Armado | J47: 0.75 | K47: 1 | M47: 1 | O47: =(+K47*$K$3+L47*$L$3+M47*$M$3+N47*$N$3)*J47 -> 124731.96 | R47: MAT | S47: MO | T47: TOTAL
F48: =+SUM(F6:F47) -> 130431.68 | G48: =+SUM(G5:G47) -> 130431.68 | O48: =+SUM(O45:O47) -> 160798.03 | P48: =+O48*$O$3 -> 241197.04 | Q48: GGBB | R48: =+G48 -> 130431.68 | S48: =+P48 -> 241197.04 | T48: =+SUM(R48:S48) -> 371628.72
F49: Cant UF | G49: 11 | O49: Cant UF | P49: 11
G50: =+G48*G49 -> 1434748.5 | P50: =+P48*P49 -> 2653167.4
B53: 2 AMB | G53: =+SUM(F54:F95) -> 192583.1
B54: Ø 110
B55: AWA TUBO PPN CLOACAL ø.110X4.00 3/1035 | C55: tira | D55: 2 | E55: =VLOOKUP(B55,Cotizaciones!B:D,3,0) -> 15376.594 | F55: =+D55*E55 -> 30753.188
B56: AWA CODO MH 45*PPN CLOACAL.ø110 6/2004 | C56: un | D56: 7 | E56: =VLOOKUP(B56,Cotizaciones!B:D,3,0) -> 2066.7612 | F56: =+D56*E56 -> 14467.328
B57: AWA MANG/CUPLA PPN CLOAC.ø110 10/2016 | C57: un | D57: =+D55 -> 2 | E57: =VLOOKUP(B57,Cotizaciones!B:D,3,0) -> 2137.1599 | F57: =+D57*E57 -> 4274.3198
B58: AWA TAPA PPN CLOACAL ø.110 10/2036 | C58: un | D58: 4 | E58: =VLOOKUP(B58,Cotizaciones!B:D,3,0) -> 1603.0206 | F58: =+D58*E58 -> 6412.0823
B59: Ø 63
B60: AWA TUBO PPN CLOACAL ø 63X4.00 10/1026 | C60: tira | D60: 0.5 | E60: =VLOOKUP(B60,Cotizaciones!B:D,3,0) -> 8313.6868 | F60: =+D60*E60 -> 4156.8434
B61: AWA CODO MH 90*PPN CLOACAL ø63 20/2007 | C61: un | D61: 0 | E61: =VLOOKUP(B61,Cotizaciones!B:D,3,0) -> 1014.4279 | F61: =+D61*E61 -> 0
B62: AWA CODO MH 45*PPN CLOACAL ø63 20/2003 | C62: Un | D62: 1 | E62: =VLOOKUP(B62,Cotizaciones!B:D,3,0) -> 960.65248 | F62: =+D62*E62 -> 960.65248
B63: AWA MANG/CUPLA PPN CLOAC.ø 63 20/2015 | C63: Un | D63: 1 | E63: =VLOOKUP(B63,Cotizaciones!B:D,3,0) -> 960.65248 | F63: =+D63*E63 -> 960.65248
B64: Ø 50
B65: AWA TUBO PPN CLOACAL ø 50X4.00 10/1017 | C65: tira | D65: 0.5 | E65: =VLOOKUP(B65,Cotizaciones!B:D,3,0) -> 6715.6586 | F65: =+D65*E65 -> 3357.8293
B66: AWA CODO MH 90*PPN CLOACAL ø50 20/2006 | C66: Un | D66: 2 | E66: =VLOOKUP(B66,Cotizaciones!B:D,3,0) -> 571.84027 | F66: =+D66*E66 -> 1143.6805
B67: AWA MANG/CUPLA PPN CLOAC.ø 50 20/2014 | C67: un | D67: 1 | E67: =VLOOKUP(B67,Cotizaciones!B:D,3,0) -> 723.32177 | F67: =+D67*E67 -> 723.32177
B68: AWA TAPA PPN CLOACAL ø 50 20/2037 | C68: Un | D68: 1 | E68: =VLOOKUP(B68,Cotizaciones!B:D,3,0) -> 586.21482 | F68: =+D68*E68 -> 586.21482
B69: Ø 40
B70: AWA TUBO PPN CLOACAL ø 40X4.00 10/1008 | C70: tira | D70: 1 | E70: =VLOOKUP(B70,Cotizaciones!B:D,3,0) -> 5296.1072 | F70: =+D70*E70 -> 5296.1072
B71: AWA CODO MH 90*PPN CLOACAL ø40 20/2005 | C71: Un | D71: 3 | E71: =VLOOKUP(B71,Cotizaciones!B:D,3,0) -> 432.16181 | F71: =+D71*E71 -> 1296.4854
B72: AWA CODO MH 45*PPN CLOACAL ø40 20/2001 | C72: Un | D72: 3 | E72: =VLOOKUP(B72,Cotizaciones!B:D,3,0) -> 399.55009 | F72: =+D72*E72 -> 1198.6503
B73: AWA MANG/CUPLA PPN CLOAC.ø 40 20/2013 | C73: Un | D73: 2 | E73: =VLOOKUP(B73,Cotizaciones!B:D,3,0) -> 658.67933 | F73: =+D73*E73 -> 1317.3587
B74: AWA TAPA PPN CLOACAL ø 40 20/2034 | C74: Un | D74: 1 | E74: =VLOOKUP(B74,Cotizaciones!B:D,3,0) -> 361.83842 | F74: =+D74*E74 -> 361.83842
B75: ACCESORIOS
B76: AWA GRAMPA RAPICLACK ø110 10/4170 | C76: Un | D76: =+D55*3 -> 6 | E76: =VLOOKUP(B76,Cotizaciones!B:D,3,0) -> 696.1543 | F76: =+D76*E76 -> 4176.9258
B77: AWA GRAMPA RAPICLACK ø 40-50-63 20/4167 | C77: un | D77: =+(D60+D65+D70)*3 -> 6 | E77: =VLOOKUP(B77,Cotizaciones!B:D,3,0) -> 424.1891 | F77: =+D77*E77 -> 2545.1346
B78: AWA BUJE RED.MH ø 63X50 20/2081 | C78: Un | D78: 1 | E78: =VLOOKUP(B78,Cotizaciones!B:D,3,0) -> 653.42875 | F78: =+D78*E78 -> 653.42875
B79: AWA BOCA ACCES.HOR.3 ACOM.ø110X63 4/2460 | C79: un | D79: 2 | E79: =VLOOKUP(B79,Cotizaciones!B:D,3,0) -> 4518.7195 | F79: =+D79*E79 -> 9037.439
B80: AWA RAMAL 45*PPN CLOAC.ø 63X 63 20/2026 | C80: un | D80: 0 | E80: =VLOOKUP(B80,Cotizaciones!B:D,3,0) -> 2240.2995 | F80: =+D80*E80 -> 0
B81: AWA RAMAL 45*PPN CLOAC.ø110X 63 5/2024 | C81: un | D81: 1 | E81: =VLOOKUP(B81,Cotizaciones!B:D,3,0) -> 3362.0093 | F81: =+D81*E81 -> 3362.0093
B82: AWA RAMAL 45*PPN CLOAC.ø110X110 5/2023 | C82: un | D82: 2 | E82: =VLOOKUP(B82,Cotizaciones!B:D,3,0) -> 4732.896 | F82: =+D82*E82 -> 9465.7919
B83: AWA RAMAL 90+ ø110X110 C/VENT. 2/2050 | C83: un | D83: 0 | E83: =VLOOKUP(B83,Cotizaciones!B:D,3,0) -> 6006.9588 | F83: =+D83*E83 -> 0
B84: AWA RAMAL 90+ ø110X 63 C/VENT. 2/2063 | C84: un | D84: 0 | E84: =VLOOKUP(B84,Cotizaciones!B:D,3,0) -> 7761.1919 | F84: =+D84*E84 -> 0
B85: AWA DISCO ANTIFILTRACION P/REJA 4/2077 | C85: un | D85: 2 | E85: 5000 | F85: =+D85*E85 -> 10000
B86: AWA SOPAPA BAÑERA VERTICAL BCE.CR.1/4128 | C86: un | D86: 0 | E86: =VLOOKUP(B86,Cotizaciones!B:D,3,0) -> 9528.6698 | F86: =+D86*E86 -> 0
B87: AWA ADAPT.SUPEREXCENT.INO.ø105"AC"4/2271 | C87: un | D87: 1 | E87: =VLOOKUP(B87,Cotizaciones!B:D,3,0) -> 4507.7019 | F87: =+D87*E87 -> 4507.7019
B88: AWA SIFON ROMPE ESPUMA PPN 1/7120 | C88: un | D88: 1 | E88: =VLOOKUP(B88,Cotizaciones!B:D,3,0) -> 9878.3824 | F88: =+D88*E88 -> 9878.3824
B89: AWA SOLUC.DESLIZ.AEROSOL 255 CM3 12/4023 | C89: un | D89: 2 | E89: =VLOOKUP(B89,Cotizaciones!B:D,3,0) -> 9863.9863 | F89: =+D89*E89 -> 19727.973
B90: AWADUCT PILETA PATIO 7 ENT. C/SIFON 40X63 (2031) | C90: un | D90: 1 | E90: =VLOOKUP(B90,Cotizaciones!B:D,3,0) -> 6417.2898 | F90: =+D90*E90 -> 6417.2898
B91: AWA PORTAREJ.+REJA A*I*12X12 ø110 4/4002 | C91: un | D91: 0 | E91: =VLOOKUP(B91,Cotizaciones!B:D,3,0) -> 3704.4378 | F91: =+D91*E91 -> 0
B92: AWA PORTAREJ +TAPA A*I*15X15 ø110 4/4005 | C92: un | D92: 0 | E92: =VLOOKUP(B92,Cotizaciones!B:D,3,0) -> 4644.8303 | F92: =+D92*E92 -> 0
B93: AWA PILETA BALCON ø 63(M) 4/2062 | C93: un | D93: 1 | E93: =VLOOKUP(B93,Cotizaciones!B:D,3,0) -> 3447.2883 | F93: =+D93*E93 -> 3447.2883 | I93: Replanteo | O93: =(+K93*$K$3+L93*$L$3+M93*$M$3+N93*$N$3)*J93 -> 0
B94: CONSUMIBLES | I94: Canaleteado | J94: 0.5 | M94: 1 | O94: =(+K94*$K$3+L94*$L$3+M94*$M$3+N94*$N$3)*J94 -> 36066.069 | R94: =+R96/T96 -> 0.38815803 | S94: =+S96/T96 -> 0.61184197
B95: CONSUMIBLES/DESPERDICIO/IMPREVISTO | C95: gl | D95: 0.2 | E95: =+SUM(F55:F93) -> 160485.92 | F95: =+D95*E95 -> 32097.184 | I95: Armado | J95: 1 | K95: 1 | M95: 1 | O95: =(+K95*$K$3+L95*$L$3+M95*$M$3+N95*$N$3)*J95 -> 166309.28 | R95: MAT | S95: MO | T95: TOTAL
F96: =+SUM(F54:F95) -> 192583.1 | G96: =+SUM(G53:G95) -> 192583.1 | O96: =+SUM(O93:O95) -> 202375.35 | P96: =+O96*$O$3 -> 303563.02 | Q96: GGBB | R96: =+G96 -> 192583.1 | S96: =+P96 -> 303563.02 | T96: =+SUM(R96:S96) -> 496146.12
F97: Cant UF | G97: 11 | O97: Cant UF | P97: 11
G98: =+G96*G97 -> 2118414.1 | P98: =+P96*P97 -> 3339193.2
B101: 2 AMB (c/2 baños) / 3 AMB | G101: =+SUM(F102:F143) -> 252155.07
B102: Ø 110
B103: AWA TUBO PPN CLOACAL ø.110X4.00 3/1035 | C103: tira | D103: 3 | E103: =VLOOKUP(B103,Cotizaciones!B:D,3,0) -> 15376.594 | F103: =+D103*E103 -> 46129.782
B104: AWA CODO MH 45*PPN CLOACAL.ø110 6/2004 | C104: un | D104: 7 | E104: =VLOOKUP(B104,Cotizaciones!B:D,3,0) -> 2066.7612 | F104: =+D104*E104 -> 14467.328
B105: AWA MANG/CUPLA PPN CLOAC.ø110 10/2016 | C105: un | D105: =+D103 -> 3 | E105: =VLOOKUP(B105,Cotizaciones!B:D,3,0) -> 2137.1599 | F105: =+D105*E105 -> 6411.4798
B106: AWA TAPA PPN CLOACAL ø.110 10/2036 | C106: un | D106: 6 | E106: =VLOOKUP(B106,Cotizaciones!B:D,3,0) -> 1603.0206 | F106: =+D106*E106 -> 9618.1234
...

Sheet PLU
K4: =+'P.MO 06.25'!B4 -> 94177.138 | L4: =+'P.MO 06.25'!B5 -> 84612.513 | M4: =+'P.MO 06.25'!B6 -> 72132.138 | N4: =+'P.MO 06.25'!B7 -> 67240.499 | O4: 1.5
B5: Descripción | C5: Un | D5: Cant | E5: P Unit | F5: Subtotal | I5: TAREA | J5: DIA | K5: ES | L5: OF | M5: MED | N5: AY | O5: GGBB
B6: Tendido caño pluvial en planta baja | G6: =+SUM(F7:F19) -> 460664.74
B7: Ø 110
B8: AWA TUBO PPN CLOACAL ø.110X4.00 3/1035 | C8: tira | D8: 15 | E8: =VLOOKUP(B8,Cotizaciones!B:D,3,0) -> 15376.594 | F8: =+D8*E8 -> 230648.91
B9: AWA CAÑO CAMARA PPN CLOACAL ø110 5/2065 | C9: Un | D9: 7 | E9: =VLOOKUP(B9,Cotizaciones!B:D,3,0) -> 4922.6056 | F9: =+D9*E9 -> 34458.239
B10: AWA CODO MH 90*PPN.CLOACAL ø110 12/2008 | C10: Un | D10: 7 | E10: =VLOOKUP(B10,Cotizaciones!B:D,3,0) -> 2245.1197 | F10: =+D10*E10 -> 15715.838
B11: AWA CODO MH 45*PPN CLOACAL.ø110 6/2004 | C11: Un | D11: 7 | E11: =VLOOKUP(B11,Cotizaciones!B:D,3,0) -> 2066.7612 | F11: =+D11*E11 -> 14467.328
B12: AWA RAMAL 45*PPN CLOAC.ø110X110 5/2023 | C12: Un | D12: 6 | E12: =VLOOKUP(B12,Cotizaciones!B:D,3,0) -> 4732.896 | F12: =+D12*E12 -> 28397.376
B13: BROCA METALICA 1/4 CJA X 100 | C13: un | D13: =+D14/100 -> 0.21 | E13: =VLOOKUP(B13,Cotizaciones!B:D,3,0) -> 76135.192 | F13: =+D13*E13 -> 15988.39
