Workbook
Name \0: #REF!
Name \0: #REF!
Name \c: #REF!
Name \c: #REF!
Name \E: #REF!
Name \E: #REF!
Name \i: #REF!
Name \j: #REF!
Name \m: #REF!
Name \P: #REF!
Name \P: #REF!
Name \P: #REF!
Name \P: #REF!
Name \P: #REF!
Name \P: #REF!
Name \P: #REF!
Name \P: #REF!
Name \P: #REF!
Name \P: #REF!
Name \P: #REF!
Name \P: #REF!
Name \P: #REF!
Name \P: #REF!
Name \P: #REF!
Name \r: #N/A
Name \x: #REF!
Name \z: #REF!
Name \z: #REF!
Name __________ben1: #REF!
Name __________ben1: #REF!
Name __________ben1: #REF!
Name __________ben1: #REF!
Name __________ben1: #REF!
Name __________ben1: #REF!
Name __________ben1: #REF!
Name __________ben1: #REF!
Name __________ben1: #REF!
Name __________ben1: #REF!
Name __________ben1: #REF!
Name __________ben1: #REF!
Name __________ben1: #REF!
Name __________ben1: #REF!
Name __________ben1: #REF!
Name __________ben1: #REF!
Name __________ben10: #REF!
Name __________ben10: #REF!
Name __________ben10: #REF!
Name __________ben10: #REF!
Name __________ben10: #REF!
Name __________ben10: #REF!
Name __________ben10: #REF!
Name __________ben10: #REF!
Name __________ben10: #REF!
Name __________ben10: #REF!
Name __________ben10: #REF!
Name __________ben10: #REF!
Name __________ben10: #REF!
Name __________ben10: #REF!
Name __________ben10: #REF!
Name __________ben10: #REF!

Sheet Resumen General
U1: Actualizado | V1: 46156
B3: OBRA: CHIVILCOY 2171
B4: RESUMEN DE OBRA
D5: 45962 | E5: 45992 | F5: 46023 | G5: 46054 | H5: 46082 | I5: 46113 | J5: 46143 | L5: Acum. Descontado | N5: Presupuesto #1 | O5: Presupuesto #2 | P5: Previsto | Q5: % Cert. Acum. | R5: Saldo Disponible | S5: Disponible % | T5: Rubro Completado
B6: Ingresos de Obra
B7: Ingresos por Certificados | D7: =SUM(VLOOKUP($B7,'Resumen Pto #1'!$B$5:$I$10,MATCH(D$5,'Resumen Pto #1'!$B$5:$I$5,0),0),VLOOKUP($B7,'Resumen Pto #2'!$B$5:$I$9,MATCH(D$5,'Resumen Pto #2'!$B$5:$I$5,0),0)) -> 0 | E7: =SUM(VLOOKUP($B7,'Resumen Pto #1'!$B$5:$I$10,MATCH(E$5,'Resumen Pto #1'!$B$5:$I$5,0),0),VLOOKUP($B7,'Resumen Pto #2'!$B$5:$I$9,MATCH(E$5,'Resumen Pto #2'!$B$5:$I$5,0),0)) -> 0 | F7: =SUM(VLOOKUP($B7,'Resumen Pto #1'!$B$5:$I$10,MATCH(F$5,'Resumen Pto #1'!$B$5:$I$5,0),0),VLOOKUP($B7,'Resumen Pto #2'!$B$5:$I$9,MATCH(F$5,'Resumen Pto #2'!$B$5:$I$5,0),0)) -> 0 | G7: =SUM(VLOOKUP($B7,'Resumen Pto #1'!$B$5:$I$10,MATCH(G$5,'Resumen Pto #1'!$B$5:$I$5,0),0),VLOOKUP($B7,'Resumen Pto #2'!$B$5:$I$9,MATCH(G$5,'Resumen Pto #2'!$B$5:$I$5,0),0)) -> 0 | H7: =SUM(VLOOKUP($B7,'Resumen Pto #1'!$B$5:$I$10,MATCH(H$5,'Resumen Pto #1'!$B$5:$I$5,0),0),VLOOKUP($B7,'Resumen Pto #2'!$B$5:$I$9,MATCH(H$5,'Resumen Pto #2'!$B$5:$I$5,0),0)) -> 120095631 | I7: =SUM(VLOOKUP($B7,'Resumen Pto #1'!$B$5:I$10,MATCH(I$5,'Resumen Pto #1'!$B$5:I$5,0),0),VLOOKUP($B7,'Resumen Pto #2'!$B$5:I$9,MATCH(I$5,'Resumen Pto #2'!$B$5:I$5,0),0)) -> 51205725 | J7: =SUM(VLOOKUP($B7,'Resumen Pto #1'!$B$5:J$10,MATCH(J$5,'Resumen Pto #1'!$B$5:J$5,0),0),VLOOKUP($B7,'Resumen Pto #2'!$B$5:J$9,MATCH(J$5,'Resumen Pto #2'!$B$5:J$5,0),0)) -> 0 | L7: =SUM(D7:K7) -> 1.7130136e+08 | N7: ='Resumen Pto #1'!N7 -> 3.903108e+08 | O7: ='Resumen Pto #2'!N7 -> 6.1109415e+08 | P7: =SUM(N7:O7) -> 1.001405e+09 | R7: =IF(Q7=100%,0,IF(OR(L7<>0,P7),P7-L7)) -> 8.301036e+08 | S7: =IF(OR(R7<0,P7),R7/P7,0%) -> 0.82893898 | T7: =IF(Q7=100%,IF(OR(K7<>0,P7),P7-K7),0) -> 0
B8: Total Ingresos de Obra | D8: =SUM(D7) -> 0 | E8: =SUM(E7) -> 0 | F8: =SUM(F7) -> 0 | G8: =SUM(G7) -> 0 | H8: =SUM(H7) -> 120095631 | I8: =SUM(I7) -> 51205725 | J8: =SUM(J7) -> 0 | L8: =SUM(L7) -> 1.7130136e+08 | N8: =SUM(N7) -> 3.903108e+08 | O8: =SUM(O7) -> 6.1109415e+08 | P8: =SUM(P7) -> 1.001405e+09 | R8: =SUM(R7) -> 8.301036e+08 | S8: =IF(OR(R8<0,P8),R8/P8,0%) -> 0.82893898 | T8: =SUM(T7) -> 0
B9: Actualización por CAC | D9: =SUM(VLOOKUP($B9,'Resumen Pto #1'!$B$5:$I$10,MATCH(D$5,'Resumen Pto #1'!$B$5:$I$5,0),0),VLOOKUP($B9,'Resumen Pto #2'!$B$5:$I$9,MATCH(D$5,'Resumen Pto #2'!$B$5:$I$5,0),0)) -> 0 | E9: =SUM(VLOOKUP($B9,'Resumen Pto #1'!$B$5:$I$10,MATCH(E$5,'Resumen Pto #1'!$B$5:$I$5,0),0),VLOOKUP($B9,'Resumen Pto #2'!$B$5:$I$9,MATCH(E$5,'Resumen Pto #2'!$B$5:$I$5,0),0)) -> 0 | F9: =SUM(VLOOKUP($B9,'Resumen Pto #1'!$B$5:$I$10,MATCH(F$5,'Resumen Pto #1'!$B$5:$I$5,0),0),VLOOKUP($B9,'Resumen Pto #2'!$B$5:$I$9,MATCH(F$5,'Resumen Pto #2'!$B$5:$I$5,0),0)) -> 0 | G9: =SUM(VLOOKUP($B9,'Resumen Pto #1'!$B$5:$I$10,MATCH(G$5,'Resumen Pto #1'!$B$5:$I$5,0),0),VLOOKUP($B9,'Resumen Pto #2'!$B$5:$I$9,MATCH(G$5,'Resumen Pto #2'!$B$5:$I$5,0),0)) -> 0 | H9: =SUM(VLOOKUP($B9,'Resumen Pto #1'!$B$5:$I$10,MATCH(H$5,'Resumen Pto #1'!$B$5:$I$5,0),0),VLOOKUP($B9,'Resumen Pto #2'!$B$5:$I$9,MATCH(H$5,'Resumen Pto #2'!$B$5:$I$5,0),0)) -> 21310936 | I9: =SUM(VLOOKUP($B9,'Resumen Pto #1'!$B$5:I$10,MATCH(I$5,'Resumen Pto #1'!$B$5:I$5,0),0),VLOOKUP($B9,'Resumen Pto #2'!$B$5:I$9,MATCH(I$5,'Resumen Pto #2'!$B$5:I$5,0),0)) -> 10072663 | J9: =SUM(VLOOKUP($B9,'Resumen Pto #1'!$B$5:J$10,MATCH(J$5,'Resumen Pto #1'!$B$5:J$5,0),0),VLOOKUP($B9,'Resumen Pto #2'!$B$5:J$9,MATCH(J$5,'Resumen Pto #2'!$B$5:J$5,0),0)) -> 0 | L9: =SUM(D9:K9) -> 31383599 | N9: ='[1]Resumen Pto #1'!X9 -> 0 | O9: ='[1]Resumen Pto #2'!X9 -> 0 | P9: =SUM(N9:O9) -> 0 | R9: =IF(Q9=100%,0,IF(P9=0,P9,P9-L9)) -> 0 | S9: =IF(OR(R9<0,P9),R9/P9,0%) -> 0 | T9: =IF(Q9=100%,IF(OR(K9<>0,P9),P9-K9),0) -> 0
B10: Total Ingresos de Obra | D10: =SUM(D9) -> 0 | E10: =SUM(E9) -> 0 | F10: =SUM(F9) -> 0 | G10: =SUM(G9) -> 0 | H10: =SUM(H9) -> 21310936 | I10: =SUM(I9) -> 10072663 | J10: =SUM(J9) -> 0 | L10: =SUM(L9) -> 31383599 | N10: =SUM(N9) -> 0 | O10: =SUM(O9) -> 0 | P10: =SUM(P9) -> 0 | R10: =SUM(R9) -> 0 | S10: =IF(OR(R10<0,P10),R10/P10,0%) -> 0 | T10: =SUM(T9) -> 0
B12: Costos de Obra
B13: Seguridad e Higiene | D13: ='Resumen Pto #1'!D15+'Resumen Pto #2'!D14 -> 0 | E13: ='Resumen Pto #1'!E15+'Resumen Pto #2'!E14 -> 0 | F13: ='Resumen Pto #1'!F15+'Resumen Pto #2'!F14 -> 0 | G13: ='Resumen Pto #1'!G15+'Resumen Pto #2'!G14 -> 517195 | H13: ='Resumen Pto #1'!H15+'Resumen Pto #2'!H14 -> 826285.91 | I13: ='Resumen Pto #1'!I15+'Resumen Pto #2'!I14 -> 517195 | J13: ='Resumen Pto #1'!J15+'Resumen Pto #2'!K14 -> 1195790 | L13: {=SUMPRODUCT($D13:$K13,TRANSPOSE('Indice CAC'!$E$12:$E$19))} -> 2519063.7 | N13: =IFERROR(VLOOKUP($B13&$C13,'Resumen Pto #1'!$B$13:$N$23,13,0),0) -> 4623254.5 | O13: =VLOOKUP($B13,'Resumen Pto #2'!$B$13:$N$30,12,0) -> 0 | P13: =SUM(N13:O13) -> 4623254.5 | R13: =IF(Q13=100%,0,IF(OR(L13<>0,P13),P13-L13,0)) -> 2104190.8 | S13: =IF(OR(R13<0,P13),R13/P13,0%) -> 0.45513194 | T13: =IF(Q13=100%,IF(OR(L13<>0,P13),P13-L13),0) -> 0
B14: Supervisión de Obra | D14: ='Resumen Pto #2'!D13 -> 0 | E14: ='Resumen Pto #2'!E13 -> 0 | F14: ='Resumen Pto #2'!F13 -> 0 | G14: ='Resumen Pto #2'!G13 -> 0 | H14: ='Resumen Pto #2'!H13+'Resumen Pto #1'!H24 -> 2800000 | I14: ='Resumen Pto #2'!I13+'Resumen Pto #1'!I24 -> 2867000 | J14: ='Resumen Pto #2'!K13+'Resumen Pto #1'!J24 -> 2850000 | L14: {=SUMPRODUCT($D14:$K14,TRANSPOSE('Indice CAC'!$E$12:$E$19))} -> 6991833.5 | N14: =VLOOKUP($B14&$C14,'Resumen Pto #1'!$B$13:$N$24,13,0) -> 32465089 | O14: =VLOOKUP($B14,'Resumen Pto #2'!$B$13:$N$30,12,0) -> 0 | P14: =SUM(N14:O14) -> 32465089 | R14: =IF(Q14=100%,0,IF(OR(L14<>0,P14),P14-L14,0)) -> 25473256 | S14: =IF(OR(R14<0,P14),R14/P14,0%) -> 0.78463532 | T14: =IF(Q14=100%,IF(OR(L14<>0,P14),P14-L14),0) -> 0
B15: Movilidad | D15: ='Resumen Pto #1'!D16+'Resumen Pto #2'!D15 -> 0 | E15: ='Resumen Pto #1'!E16+'Resumen Pto #2'!E15 -> 0 | F15: ='Resumen Pto #1'!F16+'Resumen Pto #2'!F15 -> 0 | G15: ='Resumen Pto #1'!G16+'Resumen Pto #2'!G15 -> 0 | H15: ='Resumen Pto #1'!H16+'Resumen Pto #2'!H15 -> 639742.64 | I15: ='Resumen Pto #1'!I16+'Resumen Pto #2'!I15 -> 716525.59 | J15: ='Resumen Pto #1'!J16+'Resumen Pto #2'!K15 -> 38016.53 | L15: {=SUMPRODUCT($D15:$K15,TRANSPOSE('Indice CAC'!$E$12:$E$19))} -> 1153083.2 | N15: =IFERROR(VLOOKUP($B15&$C15,'Resumen Pto #1'!$B$13:$N$23,13,0),0) -> 8000000 | O15: =VLOOKUP($B15,'Resumen Pto #2'!$B$13:$N$30,12,0) -> 0 | P15: =SUM(N15:O15) -> 8000000 | R15: =IF(Q15=100%,0,IF(OR(L15<>0,P15),P15-L15,0)) -> 6846916.8 | S15: =IF(OR(R15<0,P15),R15/P15,0%) -> 0.85586461 | T15: =IF(Q15=100%,IF(OR(L15<>0,P15),P15-L15),0) -> 0
B16: Preliminares | D16: ='Resumen Pto #1'!D13 -> 0 | E16: ='Resumen Pto #1'!E13 -> 0 | F16: ='Resumen Pto #1'!F13 -> 939182.1 | G16: ='Resumen Pto #1'!G13 -> 1539988.9 | H16: ='Resumen Pto #1'!H13 -> 3125044.3 | I16: ='Resumen Pto #1'!I13 -> 734909.88 | J16: ='Resumen Pto #1'!J13 -> 0 | L16: {=SUMPRODUCT($D16:$K16,TRANSPOSE('Indice CAC'!$E$12:$E$19))} -> 5329921.3 | N16: =VLOOKUP($B16,'Resumen Pto #1'!$B$13:$N$23,13,0) -> 14709293 | O16: =IFERROR(VLOOKUP($B16,'Resumen Pto #2'!$B$13:$N$30,12,0),0) -> 0 | P16: =SUM(N16:O16) -> 14709293 | R16: =IF(Q16=100%,0,IF(OR(L16<>0,P16),P16-L16,0)) -> 9379371.2 | S16: =IF(OR(R16<0,P16),R16/P16,0%) -> 0.63764938 | T16: =IF(Q16=100%,IF(OR(L16<>0,P16),P16-L16),0) -> 0
B17: Agrimensura | D17: ='Resumen Pto #1'!D14 -> 0 | E17: ='Resumen Pto #1'!E14 -> 0 | F17: ='Resumen Pto #1'!F14 -> 0 | G17: ='Resumen Pto #1'!G14 -> 0 | H17: ='Resumen Pto #1'!H14 -> 730000 | I17: ='Resumen Pto #1'!I14 -> 0 | J17: ='Resumen Pto #1'!J14 -> 0 | L17: {=SUMPRODUCT($D17:$K17,TRANSPOSE('Indice CAC'!$E$12:$E$19))} -> 610005.92 | N17: =VLOOKUP($B17,'Resumen Pto #1'!$B$13:$N$23,13,0) -> 1226538.2 | O17: =IFERROR(VLOOKUP($B17,'Resumen Pto #2'!$B$13:$N$30,12,0),0) -> 0 | P17: =SUM(N17:O17) -> 1226538.2 | R17: =IF(Q17=100%,0,IF(OR(L17<>0,P17),P17-L17,0)) -> 616532.32 | S17: =IF(OR(R17<0,P17),R17/P17,0%) -> 0.5026605 | T17: =IF(Q17=100%,IF(OR(L17<>0,P17),P17-L17),0) -> 0
B18: Excavación y Mov. de Suelos | D18: ='Resumen Pto #1'!D19 -> 0 | E18: ='Resumen Pto #1'!E19 -> 0 | F18: ='Resumen Pto #1'!F19 -> 0 | G18: ='Resumen Pto #1'!G19 -> 0 | H18: ='Resumen Pto #1'!H19 -> 0 | I18: ='Resumen Pto #1'!I19 -> 1310000 | J18: ='Resumen Pto #1'!J19 -> 0 | L18: {=SUMPRODUCT($D18:$K18,TRANSPOSE('Indice CAC'!$E$12:$E$19))} -> 1074687.2 | N18: =VLOOKUP($B18,'Resumen Pto #1'!$B$13:$N$23,13,0) -> 9462540.3 | O18: =IFERROR(VLOOKUP($B18,'Resumen Pto #2'!$B$13:$N$30,12,0),0) -> 0 | P18: =SUM(N18:O18) -> 9462540.3 | R18: =IF(Q18=100%,0,IF(OR(L18<>0,P18),P18-L18,0)) -> 8387853.1 | S18: =IF(OR(R18<0,P18),R18/P18,0%) -> 0.8864272 | T18: =IF(Q18=100%,IF(OR(L18<>0,P18),P18-L18),0) -> 0
B19: Hormigón | C19: MAT | D19: ='Resumen Pto #1'!D20 -> 0 | E19: ='Resumen Pto #1'!E20 -> 0 | F19: ='Resumen Pto #1'!F20 -> 0 | G19: ='Resumen Pto #1'!G20 -> 0 | H19: ='Resumen Pto #1'!H20 -> 20721536 | I19: ='Resumen Pto #1'!I20 -> 4488122.6 | J19: ='Resumen Pto #1'!J20 -> 13222352 | L19: {=SUMPRODUCT($D19:$K19,TRANSPOSE('Indice CAC'!$E$12:$E$19))} -> 31668388 | N19: ='Resumen Pto #1'!N20 -> 1.55289e+08 | O19: =IFERROR(VLOOKUP($B19,'Resumen Pto #2'!$B$13:$N$30,12,0),0) -> 0 | P19: =SUM(N19:O19) -> 1.55289e+08 | R19: =IF(Q19=100%,0,IF(OR(L19<>0,P19),P19-L19,0)) -> 1.2362062e+08 | S19: =IF(OR(R19<0,P19),R19/P19,0%) -> 0.79606806 | T19: =IF(Q19=100%,IF(OR(L19<>0,P19),P19-L19),0) -> 0
B20: Hormigón | C20: MO | D20: ='Resumen Pto #1'!D21 -> 0 | E20: ='Resumen Pto #1'!E21 -> 0 | F20: ='Resumen Pto #1'!F21 -> 0 | G20: ='Resumen Pto #1'!G21 -> 0 | H20: ='Resumen Pto #1'!H21 -> 19211836 | I20: ='Resumen Pto #1'!I21 -> 19661613 | J20: ='Resumen Pto #1'!J21 -> 30526436 | L20: {=SUMPRODUCT($D20:$K20,TRANSPOSE('Indice CAC'!$E$12:$E$19))} -> 56819928 | N20: ='Resumen Pto #1'!N21 -> 1.6857077e+08 | O20: =IFERROR(VLOOKUP($B20,'Resumen Pto #2'!$B$13:$N$30,12,0),0) -> 0 | P20: =SUM(N20:O20) -> 1.6857077e+08 | R20: =IF(Q20=100%,0,IF(OR(L20<>0,P20),P20-L20,0)) -> 1.1175085e+08 | S20: =IF(OR(R20<0,P20),R20/P20,0%) -> 0.66293132 | T20: =IF(Q20=100%,IF(OR(L20<>0,P20),P20-L20),0) -> 0
B21: Albañilería | C21: MAT | D21: ='Resumen Pto #1'!D17+'Resumen Pto #2'!D16 -> 0 | E21: ='Resumen Pto #1'!E17+'Resumen Pto #2'!E16 -> 0 | F21: ='Resumen Pto #1'!F17+'Resumen Pto #2'!F16 -> 0 | G21: ='Resumen Pto #1'!G17+'Resumen Pto #2'!G16 -> 48248.1 | H21: ='Resumen Pto #1'!H17+'Resumen Pto #2'!H16 -> 95942.03 | I21: ='Resumen Pto #1'!I17+'Resumen Pto #2'!I16 -> 371787.4 | J21: ='Resumen Pto #1'!J17+'Resumen Pto #2'!K16 -> 171269.97 | L21: {=SUMPRODUCT($D21:$K21,TRANSPOSE('Indice CAC'!$E$12:$E$19))} -> 564374.82 | N21: ='Resumen Pto #1'!N17 -> 1000000 | O21: =VLOOKUP($B21,'Resumen Pto #2'!$B$13:$N$30,12,0) -> 0 | P21: =SUM(N21:O21) -> 1000000 | R21: =IF(Q21=100%,0,IF(OR(L21<>0,P21),P21-L21,0)) -> 435625.18 | S21: =IF(OR(R21<0,P21),R21/P21,0%) -> 0.43562518 | T21: =IF(Q21=100%,IF(OR(L21<>0,P21),P21-L21),0) -> 0
B22: Albañilería | C22: MO | D22: ='Resumen Pto #1'!D18+'Resumen Pto #2'!D17 -> 0 | E22: ='Resumen Pto #1'!E18+'Resumen Pto #2'!E17 -> 0 | F22: ='Resumen Pto #1'!F18+'Resumen Pto #2'!F17 -> 0 | G22: ='Resumen Pto #1'!G18+'Resumen Pto #2'!G17 -> 0 | H22: ='Resumen Pto #1'!H18+'Resumen Pto #2'!H17 -> 0 | I22: ='Resumen Pto #1'!I18+'Resumen Pto #2'!I17 -> 2330315.7 | J22: ='Resumen Pto #1'!J18+'Resumen Pto #2'!K17 -> 0 | L22: {=SUMPRODUCT($D22:$K22,TRANSPOSE('Indice CAC'!$E$12:$E$19))} -> 1911725.5 | N22: ='Resumen Pto #1'!N18 -> 20558829 | O22: ='Resumen Pto #2'!N17 -> 1.5272197e+08 | P22: =SUM(N22:O22) -> 1.732808e+08 | R22: =IF(Q22=100%,0,IF(OR(L22<>0,P22),P22-L22,0)) -> 1.7136907e+08 | S22: =IF(OR(R22<0,P22),R22/P22,0%) -> 0.98896747 | T22: =IF(Q22=100%,IF(OR(L22<>0,P22),P22-L22),0) -> 0
B23: Durlock | C23: MAT | D23: ='Resumen Pto #2'!D18 -> 0 | E23: ='Resumen Pto #2'!E18 -> 0 | F23: ='Resumen Pto #2'!F18 -> 0 | G23: ='Resumen Pto #2'!G18 -> 0 | H23: ='Resumen Pto #2'!H18 -> 0 | I23: ='Resumen Pto #2'!I18 -> 0 | J23: ='Resumen Pto #2'!K18 -> 0 | L23: {=SUMPRODUCT($D23:$K23,TRANSPOSE('Indice CAC'!$E$12:$E$19))} -> 0 | N23: =IFERROR(VLOOKUP($B23,'Resumen Pto #1'!$B$13:$N$23,13,0),0) -> 0 | O23: =VLOOKUP($B23,'Resumen Pto #2'!$B$13:$N$30,12,0) -> 0 | P23: =SUM(N23:O23) -> 0 | R23: =IF(Q23=100%,0,IF(OR(L23<>0,P23),P23-L23,0)) -> 0 | S23: =IF(OR(R23<0,P23),R23/P23,0%) -> 0 | T23: =IF(Q23=100%,IF(OR(L23<>0,P23),P23-L23),0) -> 0
B24: Durlock | C24: MO | D24: ='Resumen Pto #2'!D19 -> 0 | E24: ='Resumen Pto #2'!E19 -> 0 | F24: ='Resumen Pto #2'!F19 -> 0 | G24: ='Resumen Pto #2'!G19 -> 0 | H24: ='Resumen Pto #2'!H19 -> 0 | I24: ='Resumen Pto #2'!I19 -> 0 | J24: ='Resumen Pto #2'!K19 -> 0 | L24: {=SUMPRODUCT($D24:$K24,TRANSPOSE('Indice CAC'!$E$12:$E$19))} -> 0 | N24: =IFERROR(VLOOKUP($B24,'Resumen Pto #1'!$B$13:$N$23,13,0),0) -> 0 | O24: ='Resumen Pto #2'!N19 -> 55470003 | P24: =SUM(N24:O24) -> 55470003 | R24: =IF(Q24=100%,0,IF(OR(L24<>0,P24),P24-L24,0)) -> 55470003 | S24: =IF(OR(R24<0,P24),R24/P24,0%) -> 1 | T24: =IF(Q24=100%,IF(OR(L24<>0,P24),P24-L24),0) -> 0
B25: Pintura | C25: MAT | D25: ='Resumen Pto #2'!D20 -> 0 | E25: ='Resumen Pto #2'!E20 -> 0 | F25: ='Resumen Pto #2'!F20 -> 0 | G25: ='Resumen Pto #2'!G20 -> 0 | H25: ='Resumen Pto #2'!H20 -> 0 | I25: ='Resumen Pto #2'!I20 -> 0 | J25: ='Resumen Pto #2'!K20 -> 0 | L25: {=SUMPRODUCT($D25:$K25,TRANSPOSE('Indice CAC'!$E$12:$E$19))} -> 0 | N25: =IFERROR(VLOOKUP($B25,'Resumen Pto #1'!$B$13:$N$23,13,0),0) -> 0 | O25: =VLOOKUP($B25,'Resumen Pto #2'!$B$13:$N$30,12,0) -> 0 | P25: =SUM(N25:O25) -> 0 | R25: =IF(Q25=100%,0,IF(OR(L25<>0,P25),P25-L25,0)) -> 0 | S25: =IF(OR(R25<0,P25),R25/P25,0%) -> 0 | T25: =IF(Q25=100%,IF(OR(L25<>0,P25),P25-L25),0) -> 0
B26: Pintura | C26: MO | D26: ='Resumen Pto #2'!D21 -> 0 | E26: ='Resumen Pto #2'!E21 -> 0 | F26: ='Resumen Pto #2'!F21 -> 0 | G26: ='Resumen Pto #2'!G21 -> 0 | H26: ='Resumen Pto #2'!H21 -> 0 | I26: ='Resumen Pto #2'!I21 -> 0 | J26: ='Resumen Pto #2'!K21 -> 0 | L26: {=SUMPRODUCT($D26:$K26,TRANSPOSE('Indice CAC'!$E$12:$E$19))} -> 0 | N26: =IFERROR(VLOOKUP($B26,'Resumen Pto #1'!$B$13:$N$23,13,0),0) -> 0 | O26: ='Resumen Pto #2'!N21 -> 60159232 | P26: =SUM(N26:O26) -> 60159232 | R26: =IF(Q26=100%,0,IF(OR(L26<>0,P26),P26-L26,0)) -> 60159232 | S26: =IF(OR(R26<0,P26),R26/P26,0%) -> 1 | T26: =IF(Q26=100%,IF(OR(L26<>0,P26),P26-L26),0) -> 0
B27: Revestimiento | C27: MAT | D27: ='Resumen Pto #2'!D22 -> 0 | E27: ='Resumen Pto #2'!E22 -> 0 | F27: ='Resumen Pto #2'!F22 -> 0 | G27: ='Resumen Pto #2'!G22 -> 0 | H27: ='Resumen Pto #2'!H22 -> 0 | I27: ='Resumen Pto #2'!I22 -> 0 | J27: ='Resumen Pto #2'!K22 -> 0 | L27: {=SUMPRODUCT($D27:$K27,TRANSPOSE('Indice CAC'!$E$12:$E$19))} -> 0 | N27: =IFERROR(VLOOKUP($B27,'Resumen Pto #1'!$B$13:$N$23,13,0),0) -> 0 | O27: =VLOOKUP($B27,'Resumen Pto #2'!$B$13:$N$30,12,0) -> 0 | P27: =SUM(N27:O27) -> 0 | R27: =IF(Q27=100%,0,IF(OR(L27<>0,P27),P27-L27,0)) -> 0 | S27: =IF(OR(R27<0,P27),R27/P27,0%) -> 0 | T27: =IF(Q27=100%,IF(OR(L27<>0,P27),P27-L27),0) -> 0
B28: Revestimiento | C28: MO | D28: ='Resumen Pto #2'!D23 -> 0 | E28: ='Resumen Pto #2'!E23 -> 0 | F28: ='Resumen Pto #2'!F23 -> 0 | G28: ='Resumen Pto #2'!G23 -> 0 | H28: ='Resumen Pto #2'!H23 -> 0 | I28: ='Resumen Pto #2'!I23 -> 0 | J28: ='Resumen Pto #2'!K23 -> 0 | L28: {=SUMPRODUCT($D28:$K28,TRANSPOSE('Indice CAC'!$E$12:$E$19))} -> 0 | N28: =IFERROR(VLOOKUP($B28,'Resumen Pto #1'!$B$13:$N$23,13,0),0) -> 0 | O28: ='Resumen Pto #2'!N23 -> 35274699 | P28: =SUM(N28:O28) -> 35274699 | R28: =IF(Q28=100%,0,IF(OR(L28<>0,P28),P28-L28,0)) -> 35274699 | S28: =IF(OR(R28<0,P28),R28/P28,0%) -> 1 | T28: =IF(Q28=100%,IF(OR(L28<>0,P28),P28-L28),0) -> 0
B29: Eléctrico | C29: MAT | D29: ='Resumen Pto #2'!D24 -> 0 | E29: ='Resumen Pto #2'!E24 -> 0 | F29: ='Resumen Pto #2'!F24 -> 0 | G29: ='Resumen Pto #2'!G24 -> 0 | H29: ='Resumen Pto #2'!H24 -> 0 | I29: ='Resumen Pto #2'!I24 -> 0 | J29: ='Resumen Pto #2'!K24 -> 0 | L29: {=SUMPRODUCT($D29:$K29,TRANSPOSE('Indice CAC'!$E$12:$E$19))} -> 0 | N29: =IFERROR(VLOOKUP($B29,'Resumen Pto #1'!$B$13:$N$23,13,0),0) -> 0 | O29: =VLOOKUP($B29,'Resumen Pto #2'!$B$13:$N$30,12,0) -> 0 | P29: =SUM(N29:O29) -> 0 | R29: =IF(Q29=100%,0,IF(OR(L29<>0,P29),P29-L29,0)) -> 0 | S29: =IF(OR(R29<0,P29),R29/P29,0%) -> 0 | T29: =IF(Q29=100%,IF(OR(L29<>0,P29),P29-L29),0) -> 0
B30: Eléctrico | C30: MO | D30: ='Resumen Pto #2'!D25 -> 0 | E30: ='Resumen Pto #2'!E25 -> 0 | F30: ='Resumen Pto #2'!F25 -> 0 | G30: ='Resumen Pto #2'!G25 -> 0 | H30: ='Resumen Pto #2'!H25 -> 0 | I30: ='Resumen Pto #2'!I25 -> 0 | J30: ='Resumen Pto #2'!K25 -> 0 | L30: {=SUMPRODUCT($D30:$K30,TRANSPOSE('Indice CAC'!$E$12:$E$19))} -> 0 | N30: =IFERROR(VLOOKUP($B30,'Resumen Pto #1'!$B$13:$N$23,13,0),0) -> 0 | O30: ='Resumen Pto #2'!N25 -> 64414415 | P30: =SUM(N30:O30) -> 64414415 | R30: =IF(Q30=100%,0,IF(OR(L30<>0,P30),P30-L30,0)) -> 64414415 | S30: =IF(OR(R30<0,P30),R30/P30,0%) -> 1 | T30: =IF(Q30=100%,IF(OR(L30<>0,P30),P30-L30),0) -> 0
B31: Sanitaria | C31: MAT | D31: ='Resumen Pto #2'!D26 -> 0 | E31: ='Resumen Pto #2'!E26 -> 0 | F31: ='Resumen Pto #2'!F26 -> 0 | G31: ='Resumen Pto #2'!G26 -> 0 | H31: ='Resumen Pto #2'!H26 -> 0 | I31: ='Resumen Pto #2'!I26 -> 0 | J31: ='Resumen Pto #2'!K26 -> 0 | L31: {=SUMPRODUCT($D31:$K31,TRANSPOSE('Indice CAC'!$E$12:$E$19))} -> 0 | N31: =IFERROR(VLOOKUP($B31,'Resumen Pto #1'!$B$13:$N$23,13,0),0) -> 0 | O31: =VLOOKUP($B31,'Resumen Pto #2'!$B$13:$N$30,12,0) -> 0 | P31: =SUM(N31:O31) -> 0 | R31: =IF(Q31=100%,0,IF(OR(L31<>0,P31),P31-L31,0)) -> 0 | S31: =IF(OR(R31<0,P31),R31/P31,0%) -> 0 | T31: =IF(Q31=100%,IF(OR(L31<>0,P31),P31-L31),0) -> 0
B32: Sanitaria | C32: MO | D32: ='Resumen Pto #2'!D27 -> 0 | E32: ='Resumen Pto #2'!E27 -> 0 | F32: ='Resumen Pto #2'!F27 -> 0 | G32: ='Resumen Pto #2'!G27 -> 0 | H32: ='Resumen Pto #2'!H27 -> 0 | I32: ='Resumen Pto #2'!I27 -> 0 | J32: ='Resumen Pto #2'!K27 -> 0 | L32: {=SUMPRODUCT($D32:$K32,TRANSPOSE('Indice CAC'!$E$12:$E$19))} -> 0 | N32: =IFERROR(VLOOKUP($B32,'Resumen Pto #1'!$B$13:$N$23,13,0),0) -> 0 | O32: ='Resumen Pto #2'!N27 -> 52462847 | P32: =SUM(N32:O32) -> 52462847 | R32: =IF(Q32=100%,0,IF(OR(L32<>0,P32),P32-L32,0)) -> 52462847 | S32: =IF(OR(R32<0,P32),R32/P32,0%) -> 1 | T32: =IF(Q32=100%,IF(OR(L32<>0,P32),P32-L32),0) -> 0
B33: Termomecánica | D33: ='Resumen Pto #2'!D28 -> 0 | E33: ='Resumen Pto #2'!E28 -> 0 | F33: ='Resumen Pto #2'!F28 -> 0 | G33: ='Resumen Pto #2'!G28 -> 0 | H33: ='Resumen Pto #2'!H28 -> 0 | I33: ='Resumen Pto #2'!I28 -> 0 | J33: ='Resumen Pto #2'!K28 -> 0 | L33: {=SUMPRODUCT($D33:$K33,TRANSPOSE('Indice CAC'!$E$12:$E$19))} -> 0 | N33: =IFERROR(VLOOKUP($B33,'Resumen Pto #1'!$B$13:$N$23,13,0),0) -> 0 | O33: ='Resumen Pto #2'!N28 -> 19100000 | P33: =SUM(N33:O33) -> 19100000 | R33: =IF(Q33=100%,0,IF(OR(L33<>0,P33),P33-L33,0)) -> 19100000 | S33: =IF(OR(R33<0,P33),R33/P33,0%) -> 1 | T33: =IF(Q33=100%,IF(OR(L33<>0,P33),P33-L33),0) -> 0
B34: Equipos | D34: ='Resumen Pto #1'!D22+'Resumen Pto #2'!D29 -> 0 | E34: ='Resumen Pto #1'!E22+'Resumen Pto #2'!E29 -> 0 | F34: ='Resumen Pto #1'!F22+'Resumen Pto #2'!F29 -> 0 | G34: ='Resumen Pto #1'!G22+'Resumen Pto #2'!G29 -> 0 | H34: ='Resumen Pto #1'!H22+'Resumen Pto #2'!H29 -> 0 | I34: ='Resumen Pto #1'!I22+'Resumen Pto #2'!I29 -> 0 | J34: ='Resumen Pto #1'!J22+'Resumen Pto #2'!K29 -> 702737.42 | L34: {=SUMPRODUCT($D34:$K34,TRANSPOSE('Indice CAC'!$E$12:$E$19))} -> 567140.81 | N34: =VLOOKUP($B34,'Resumen Pto #1'!$B$13:$N$23,13,0) -> 15976116 | O34: =VLOOKUP($B34,'Resumen Pto #2'!$B$13:$N$30,12,0) -> 0 | P34: =SUM(N34:O34) -> 15976116 | R34: =IF(Q34=100%,0,IF(OR(L34<>0,P34),P34-L34,0)) -> 15408975 | S34: =IF(OR(R34<0,P34),R34/P34,0%) -> 0.96450071 | T34: =IF(Q34=100%,IF(OR(L34<>0,P34),P34-L34),0) -> 0
B35: Gastos Generales Obra | D35: ='Resumen Pto #1'!D23+'Resumen Pto #2'!D30 -> 0 | E35: ='Resumen Pto #1'!E23+'Resumen Pto #2'!E30 -> 0 | F35: ='Resumen Pto #1'!F23+'Resumen Pto #2'!F30 -> 0 | G35: ='Resumen Pto #1'!G23+'Resumen Pto #2'!G30 -> 247000 | H35: ='Resumen Pto #1'!H23+'Resumen Pto #2'!H30 -> 227000 | I35: ='Resumen Pto #1'!I23+'Resumen Pto #2'!I30 -> 1101000 | J35: ='Resumen Pto #1'!J23+'Resumen Pto #2'!K30 -> 1520000 | L35: {=SUMPRODUCT($D35:$K35,TRANSPOSE('Indice CAC'!$E$12:$E$19))} -> 2529400.2 | N35: =VLOOKUP($B35,'Resumen Pto #1'!$B$13:$N$23,13,0) -> 3712405 | O35: =VLOOKUP($B35,'Resumen Pto #2'!$B$13:$N$30,12,0) -> 0 | P35: =SUM(N35:O35) -> 3712405 | R35: =IF(Q35=100%,0,IF(OR(L35<>0,P35),P35-L35,0)) -> 1183004.8 | S35: =IF(OR(R35<0,P35),R35/P35,0%) -> 0.31866264 | T35: =IF(Q35=100%,IF(OR(L35<>0,P35),P35-L35),0) -> 0
B36: Total Egresos de Obra | D36: =SUM(D13:D35) -> 0 | E36: =SUM(E13:E35) -> 0 | F36: =SUM(F13:F35) -> 939182.1 | G36: =SUM(G13:G35) -> 2352432 | H36: =SUM(H13:H35) -> 48377387 | I36: =SUM(I13:I35) -> 34098469 | J36: =SUM(J13:J35) -> 50226602 | L36: =SUM(L13:L35) -> 1.1173955e+08 | N36: =SUM(N13:N35) -> 4.3559384e+08 | O36: =SUM(O13:O35) -> 4.3960316e+08 | P36: =SUM(P13:P35) -> 8.7519701e+08 | R36: =IF(Q36=100%,0,IF(OR(L36<>0,P36),P36-L36)) -> 7.6345745e+08 | S36: =IF(OR(R36<0,P36),R36/P36,0%) -> 0.8723264 | T36: =SUM(T13:T35) -> 0
B38: Gastos Generales
B39: Gastos Directos | D39: =SUM(VLOOKUP($B39,'C. Gestión Pto #1'!$B$33:$H$33,MATCH(D$5,'C. Gestión Pto #1'!B19:H19,0),0),VLOOKUP($B39,'C. Gestión Pto #2'!$B$40:$H$40,MATCH(D$5,'C. Gestión Pto #2'!$B$26:$H$26,0),0)) -> 0 | E39: =SUM(VLOOKUP($B39,'C. Gestión Pto #1'!$B$33:$H$33,MATCH(E$5,'C. Gestión Pto #1'!C19:I19,0),0),VLOOKUP($B39,'C. Gestión Pto #2'!$B$40:$H$40,MATCH(E$5,'C. Gestión Pto #2'!$B$26:$H$26,0),0)) -> 0 | F39: =SUM(VLOOKUP($B39,'C. Gestión Pto #1'!$B$33:$H$33,MATCH(F$5,'C. Gestión Pto #1'!D19:J19,0),0),VLOOKUP($B39,'C. Gestión Pto #2'!$B$40:$H$40,MATCH(F$5,'C. Gestión Pto #2'!$B$26:$H$26,0),0)) -> 0 | G39: =SUM(VLOOKUP($B39,'C. Gestión Pto #1'!$B$33:$H$33,MATCH(G$5,'C. Gestión Pto #1'!E19:K19,0),0),VLOOKUP($B39,'C. Gestión Pto #2'!$B$40:$H$40,MATCH(G$5,'C. Gestión Pto #2'!$B$26:$H$26,0),0)) -> 0 | H39: =SUM(VLOOKUP($B39,'C. Gestión Pto #1'!$B$33:$L$33,MATCH(H$5,'C. Gestión Pto #1'!$B$19:L19,0),0),VLOOKUP($B39,'C. Gestión Pto #2'!$B$40:$H$40,MATCH(H$5,'C. Gestión Pto #2'!$B$26:$H$26,0),0)) -> 1521288.1 | I39: =SUM(VLOOKUP($B39,'C. Gestión Pto #1'!$B$33:$L$33,MATCH(I$5,'C. Gestión Pto #1'!$B$19:M19,0),0),VLOOKUP($B39,'C. Gestión Pto #2'!$B$40:$H$40,MATCH(I$5,'C. Gestión Pto #2'!$B$26:$H$26,0),0)) -> 1597596 | J39: =SUM(VLOOKUP($B39,'C. Gestión Pto #1'!$B$33:$L$33,MATCH(J$5,'C. Gestión Pto #1'!$B$19:L19,0),0),VLOOKUP($B39,'C. Gestión Pto #2'!$B$40:$I$40,MATCH(J$5,'C. Gestión Pto #2'!$B$26:$I$26,0),0)) -> 1736014.7 | L39: {=SUMPRODUCT($D39:$K39,TRANSPOSE('Indice CAC'!$E$12:$E$19))} -> 3982890.6 | P39: =SUM(GGBB!H6:H36) -> 1.328494e+08 | R39: =IF(Q39=100%,0,IF(OR(L39<>0,P39),P39-L39)) -> 1.2886651e+08 | S39: =IF(OR(R39<0,P39),R39/P39,0%) -> 0.97001951 | T39: =IF(Q39=100%,IF(OR(L39<>0,P39),P39-L39),0) -> 0
B40: Gastos Indirectos | D40: =SUM(VLOOKUP($B40,'C. Gestión Pto #1'!$B$39:$H$39,MATCH(D$5,'C. Gestión Pto #1'!B35:H35,0),0),VLOOKUP($B40,'C. Gestión Pto #2'!$B$46:$H$46,MATCH(D$5,'C. Gestión Pto #2'!$B$42:$H$42,0),0)) -> 0 | E40: =SUM(VLOOKUP($B40,'C. Gestión Pto #1'!$B$39:$H$39,MATCH(E$5,'C. Gestión Pto #1'!C35:I35,0),0),VLOOKUP($B40,'C. Gestión Pto #2'!$B$46:$H$46,MATCH(E$5,'C. Gestión Pto #2'!$B$42:$H$42,0),0)) -> 0 | F40: =SUM(VLOOKUP($B40,'C. Gestión Pto #1'!$B$39:$H$39,MATCH(F$5,'C. Gestión Pto #1'!D35:J35,0),0),VLOOKUP($B40,'C. Gestión Pto #2'!$B$46:$H$46,MATCH(F$5,'C. Gestión Pto #2'!$B$42:$H$42,0),0)) -> 0 | G40: =SUM(VLOOKUP($B40,'C. Gestión Pto #1'!$B$39:$H$39,MATCH(G$5,'C. Gestión Pto #1'!E35:K35,0),0),VLOOKUP($B40,'C. Gestión Pto #2'!$B$46:$H$46,MATCH(G$5,'C. Gestión Pto #2'!$B$42:$H$42,0),0)) -> 0 | H40: =SUM(VLOOKUP($B40,'C. Gestión Pto #1'!$B$39:$L$39,MATCH(H$5,'C. Gestión Pto #1'!$B$35:L35,0),0),VLOOKUP($B40,'C. Gestión Pto #2'!$B$46:$L$46,MATCH(H$5,'C. Gestión Pto #2'!$B$42:$L$42,0),0)) -> 1734248.2 | I40: =SUM(VLOOKUP($B40,'C. Gestión Pto #1'!$B$39:$L$39,MATCH(I$5,'C. Gestión Pto #1'!$B$35:M35,0),0),VLOOKUP($B40,'C. Gestión Pto #2'!$B$46:$L$46,MATCH(I$5,'C. Gestión Pto #2'!$B$42:$L$42,0),0)) -> 1886946.4 | J40: =SUM(VLOOKUP($B40,'C. Gestión Pto #1'!$B$39:$L$39,MATCH(J$5,'C. Gestión Pto #1'!$B$35:N35,0),0),VLOOKUP($B40,'C. Gestión Pto #2'!$B$46:$L$46,MATCH(J$5,'C. Gestión Pto #2'!$B$42:$L$42,0),0)) -> 1833735.9 | L40: {=SUMPRODUCT($D40:$K40,TRANSPOSE('Indice CAC'!$E$12:$E$19))} -> 4477085.8 | P40: =SUM(GGBB!H37:H42) -> 94164835 | R40: =IF(Q40=100%,0,IF(OR(L40<>0,P40),P40-L40)) -> 89687749 | S40: =IF(OR(R40<0,P40),R40/P40,0%) -> 0.9524548 | T40: =IF(Q40=100%,IF(OR(L40<>0,P40),P40-L40),0) -> 0
B41: Total Gastos Generales | D41: =SUM(D39:D40) -> 0 | E41: =SUM(E39:E40) -> 0 | F41: =SUM(F39:F40) -> 0 | G41: =SUM(G39:G40) -> 0 | H41: =SUM(H39:H40) -> 3255536.3 | I41: =SUM(I39:I40) -> 3484542.4 | J41: =SUM(J39:J40) -> 3569750.6 | L41: =SUM(L39:L40) -> 8459976.4 | N41: =SUM(N39:N40) -> 0 | O41: =SUM(O39:O40) -> 0 | P41: =SUM(P39:P40) -> 2.2701424e+08 | R41: =IF(Q41=100%,0,IF(OR(L41<>0,P41),P41-L41)) -> 2.1855426e+08 | S41: =IF(OR(R41<0,P41),R41/P41,0%) -> 0.96273372 | T41: =SUM(T39:T40) -> 0
B43: Total Egresos | D43: =D36+D41 -> 0 | E43: =E36+E41 -> 0 | F43: =F36+F41 -> 939182.1 | G43: =G36+G41 -> 2352432 | H43: =H36+H41 -> 51632923 | I43: =I36+I41 -> 37583012 | J43: =J36+J41 -> 53796353 | L43: =L36+L41 -> 1.2019953e+08 | N43: =N36+N41 -> 4.3559384e+08 | O43: =O36+O41 -> 4.3960316e+08 | P43: =P36+P41 -> 1.1022112e+09
B45: Resultado Operativo | D45: =SUM(D8,D10,-D43) -> 0 | E45: =SUM(E8,E10,-E43) -> 0 | F45: =SUM(F8,F10,-F43) -> -939182.1 | G45: =SUM(G8,G10,-G43) -> -2352432 | H45: =SUM(H8,H10,-H43) -> 89773643 | I45: =SUM(I8,I10,-I43) -> 23695377 | J45: =SUM(J8,J10,-J43) -> -53796353 | L45: =L8-L43 -> 51101828 | P45: =P8-P43 -> -1.0080629e+08
B46: Resultado Acumulado | D46: =D45 -> 0 | E46: =D46+E45 -> 0 | F46: =E46+F45 -> -939182.1 | G46: =F46+G45 -> -3291614.1 | H46: =G46+H45 -> 86482029 | I46: =H46+I45 -> 1.1017741e+08 | J46: =I46+J45 -> 56381053
B48: Resultado Operativo USD | D48: =D45/VLOOKUP(EOMONTH(DATE(2025,COLUMN(K1),1),0),'TC USD MEP'!$B:$C,2,0) -> 0 | E48: =E45/VLOOKUP(EOMONTH(DATE(2025,COLUMN(L1),1),0),'TC USD MEP'!$B:$C,2,0) -> 0 | F48: =F45/VLOOKUP(EOMONTH(DATE(2026,COLUMN(A1),1),0),'TC USD MEP'!$B:$C,2,0) -> -643.13445 | G48: =G45/VLOOKUP(EOMONTH(DATE(2026,COLUMN(B1),1),0),'TC USD MEP'!$B:$C,2,0) -> -1657.1791 | H48: =H45/VLOOKUP(EOMONTH(DATE(2026,COLUMN(C1),1),0),'TC USD MEP'!$B:$C,2,0) -> 63094.686 | I48: =I45/VLOOKUP(EOMONTH(DATE(2026,COLUMN(D1),1),0),'TC USD MEP'!$B:$C,2,0) -> 16427.402 | J48: =J45/VLOOKUP(EOMONTH(DATE(2026,COLUMN(E1),1),0),'TC USD MEP'!$B:$C,2,0) -> -37503.906
B49: Resultado Acumulado USD | D49: =D48 -> 0 | E49: =D49+E48 -> 0 | F49: =E49+F48 -> -643.13445 | G49: =F49+G48 -> -2300.3136 | H49: =G49+H48 -> 60794.373 | I49: =H49+I48 -> 77221.774 | J49: =I49+J48 -> 39717.868
P68: =P43+P45-P10 -> 1.001405e+09

Sheet Resumen Pto #1
S1: Actualizado | T1: 46156
B3: OBRA: CHIVILCOY 2171
B4: RESUMEN DE OBRA
D5: 45962 | E5: 45992 | F5: 46023 | G5: 46054 | H5: 46082 | I5: 46113 | J5: 46143 | L5: Acum. Descontado | N5: Previsto | O5: % Cert. Acum. | P5: Saldo Disponible | Q5: Disponible % | R5: Rubro Completado
B6: Ingresos de Obra
B7: Ingresos por certificados | D7: =SUMIFS(Certificados!$E$12:$E$21,Certificados!$A$12:$A$21,">="&DATE(2025,11,1),Certificados!$A$12:$A$21,"<="&DATE(2025,11,30),Certificados!$C$12:$C$21,"Pto 1") -> 0 | E7: =SUMIFS(Certificados!$E$12:$E$21,Certificados!$A$12:$A$21,">="&DATE(2025,12,1),Certificados!$A$12:$A$21,"<="&DATE(2025,12,31),Certificados!$C$12:$C$21,"Pto 1") -> 0 | F7: =SUMIFS(Certificados!$E$12:$E$21,Certificados!$A$12:$A$21,">="&DATE(2026,1,1),Certificados!$A$12:$A$21,"<="&DATE(2026,1,31),Certificados!$C$12:$C$21,"Pto 1") -> 0 | G7: =SUMIFS(Certificados!$E$12:$E$21,Certificados!$A$12:$A$21,">="&DATE(2026,2,1),Certificados!$A$12:$A$21,"<="&DATE(2026,2,29),Certificados!$C$12:$C$21,"Pto 1") -> 0 | H7: =SUMIFS(Certificados!$E$12:$E$21,Certificados!$A$12:$A$21,">="&DATE(2026,3,1),Certificados!$A$12:$A$21,"<="&DATE(2026,3,31),Certificados!$B$12:$B$21,"Pto 1") -> 120095631 | I7: =SUMIFS(Certificados!$E$12:$E$21,Certificados!$A$12:$A$21,">="&DATE(2026,4,1),Certificados!$A$12:$A$21,"<="&DATE(2026,4,30),Certificados!$B$12:$B$21,"Pto 1") -> 51205725 | J7: =SUMIFS(Certificados!$E$12:$E$21,Certificados!$A$12:$A$21,">="&DATE(2026,5,1),Certificados!$A$12:$A$21,"<="&DATE(2026,5,31),Certificados!$B$12:$B$21,"Pto 1") -> 0 | L7: =SUM(D7:I7) -> 1.7130136e+08 | N7: =SUM(Facturacion!E4:E4) -> 3.903108e+08 | P7: =IF(O7=100%,0,IF(OR(L7<>0,N7),N7-L7)) -> 2.1900944e+08 | Q7: =IF(OR(P7<0,N7),P7/N7,0%) -> 0.56111551 | R7: =IF(O7=100%,IF(OR(L7<>0,N7),N7-L7),0) -> 0
B8: Total Ingresos de Obra | D8: =SUM(D7) -> 0 | E8: =SUM(E7) -> 0 | F8: =SUM(F7) -> 0 | G8: =SUM(G7) -> 0 | H8: =SUM(H7) -> 120095631 | I8: =SUM(I7) -> 51205725 | J8: =SUM(J7) -> 0 | L8: =SUM(L7) -> 1.7130136e+08 | N8: =SUM(N7) -> 3.903108e+08 | P8: =SUM(P7) -> 2.1900944e+08 | Q8: =IF(OR(P8<0,N8),P8/N8,0%) -> 0.56111551 | R8: =SUM(R7) -> 0
B9: Actualización por CAC | D9: =SUMIFS(Certificados!$F$12:$F$21,Certificados!$A$12:$A$21,">="&DATE(2025,11,1),Certificados!$A$12:$A$21,"<="&DATE(2025,11,30),Certificados!$C$12:$C$21,"Pto. 1") -> 0 | E9: =SUMIFS(Certificados!$F$12:$F$21,Certificados!$A$12:$A$21,">="&DATE(2025,12,1),Certificados!$A$12:$A$21,"<="&DATE(2025,12,31),Certificados!$C$12:$C$21,"Pto. 1") -> 0 | F9: =SUMIFS(Certificados!$F$12:$F$21,Certificados!$A$12:$A$21,">="&DATE(2026,1,1),Certificados!$A$12:$A$21,"<="&DATE(2026,1,31),Certificados!$C$12:$C$21,"Pto. 1") -> 0 | G9: =SUMIFS(Certificados!$F$12:$F$21,Certificados!$A$12:$A$21,">="&DATE(2026,2,1),Certificados!$A$12:$A$21,"<="&DATE(2026,2,29),Certificados!$C$12:$C$21,"Pto. 1") -> 0 | H9: =SUMIFS(Certificados!$F$12:$F$21,Certificados!$A$12:$A$21,">="&DATE(2026,3,1),Certificados!$A$12:$A$21,"<="&DATE(2026,3,31),Certificados!$B$12:$B$21,"Pto 1") -> 21310936 | I9: =SUMIFS(Certificados!$F$12:$F$21,Certificados!$A$12:$A$21,">="&DATE(2026,4,1),Certificados!$A$12:$A$21,"<="&DATE(2026,4,30),Certificados!$B$12:$B$21,"Pto 1") -> 10072663 | J9: =SUMIFS(Certificados!$F$12:$F$21,Certificados!$A$12:$A$21,">="&DATE(2026,5,1),Certificados!$A$12:$A$21,"<="&DATE(2026,5,31),Certificados!$C$12:$C$21,"Pto 1") -> 0 | L9: =SUM(D9:I9) -> 31383599 | N9: 0 | O9: 0 | P9: =IF(O9=100%,0,IF(N9=0,N9,N9-L9)) -> 0 | Q9: =IF(OR(P9<0,N9),P9/N9,0%) -> 0 | R9: =IF(O9=100%,IF(OR(L9<>0,N9),N9-L9),0) -> 0
B10: Total Ingresos por CAC | D10: =SUM(D9) -> 0 | E10: =SUM(E9) -> 0 | F10: =SUM(F9) -> 0 | G10: =SUM(G9) -> 0 | H10: =SUM(H9) -> 21310936 | I10: =SUM(I9) -> 10072663 | J10: =SUM(J9) -> 0 | L10: =SUM(L9) -> 31383599 | N10: =SUM(N9) -> 0 | P10: =SUM(P9) -> 0 | Q10: =IF(OR(P10<0,N10),P10/N10,0%) -> 0 | R10: =SUM(R9) -> 0
B12: Costos de Obra
B13: Preliminares | D13: =IFERROR(VLOOKUP($B13&$C13,'C. Gestión Pto #1'!$B$4:H$16,MATCH(D$5,'C. Gestión Pto #1'!$B$4:H$4,0),FALSE),0) -> 0 | E13: =IFERROR(VLOOKUP($B13&$C13,'C. Gestión Pto #1'!$B$4:I$16,MATCH(E$5,'C. Gestión Pto #1'!$B$4:I$4,0),"FALSO"),0) -> 0 | F13: =IFERROR(VLOOKUP($B13&$C13,'C. Gestión Pto #1'!$B$4:J$16,MATCH(F$5,'C. Gestión Pto #1'!$B$4:J$4,0),"FALSO"),0) -> 939182.1 | G13: =IFERROR(VLOOKUP($B13&$C13,'C. Gestión Pto #1'!$B$4:K$16,MATCH(G$5,'C. Gestión Pto #1'!$B$4:K$4,0),"FALSO"),0) -> 1539988.9 | H13: =IFERROR(VLOOKUP($B13&$C13,'C. Gestión Pto #1'!$B$4:L$16,MATCH(H$5,'C. Gestión Pto #1'!$B$4:L$4,0),"FALSO"),0) -> 3125044.3 | I13: =IFERROR(VLOOKUP($B13&$C13,'C. Gestión Pto #1'!$B$4:M$16,MATCH(I$5,'C. Gestión Pto #1'!$B$4:M$4,0),"FALSO"),0) -> 734909.88 | J13: =IFERROR(VLOOKUP($B13&$C13,'C. Gestión Pto #1'!$B$4:N$16,MATCH(J$5,'C. Gestión Pto #1'!$B$4:N$4,0),"FALSO"),0) -> 0 | L13: {=SUMPRODUCT($D13:$K13,TRANSPOSE('Indice CAC'!$E$12:$E$19))} -> 5329921.3 | N13: =IF($C13="MAT",SUMIF('Preventivo Costo CH2171 '!$A$9:$A$57,$B13,'Preventivo Costo CH2171 '!$I$9:$I$57),IF($C13="MO",SUMIF('Preventivo Costo CH2171 '!$A$9:$A$57,$B13,'Preventivo Costo CH2171 '!$L$9:$L$57),SUMIF('Preventivo Costo CH2171 '!$A$9:$A$57,$B13,'Preventivo Costo CH2171 '!$N$9:$N$57))) -> 14709293 | P13: =IF(O13=100%,0,IF(OR(L13<>0,N13),N13-L13)) -> 9379371.2 | Q13: =IF(OR(P13<0,N13),P13/N13,0%) -> 0.63764938 | R13: =IF(O13=100%,IF(OR(L13<>0,N13),N13-L13),0) -> 0
B14: Agrimensura | D14: =IFERROR(VLOOKUP($B14&$C14,'C. Gestión Pto #1'!$B$4:H$16,MATCH(D$5,'C. Gestión Pto #1'!$B$4:H$4,0),FALSE),0) -> 0 | E14: =IFERROR(VLOOKUP($B14&$C14,'C. Gestión Pto #1'!$B$4:I$16,MATCH(E$5,'C. Gestión Pto #1'!$B$4:I$4,0),"FALSO"),0) -> 0 | F14: =IFERROR(VLOOKUP($B14&$C14,'C. Gestión Pto #1'!$B$4:J$16,MATCH(F$5,'C. Gestión Pto #1'!$B$4:J$4,0),"FALSO"),0) -> 0 | G14: =IFERROR(VLOOKUP($B14&$C14,'C. Gestión Pto #1'!$B$4:K$16,MATCH(G$5,'C. Gestión Pto #1'!$B$4:K$4,0),"FALSO"),0) -> 0 | H14: =IFERROR(VLOOKUP($B14&$C14,'C. Gestión Pto #1'!$B$4:L$16,MATCH(H$5,'C. Gestión Pto #1'!$B$4:L$4,0),"FALSO"),0) -> 730000 | I14: =IFERROR(VLOOKUP($B14&$C14,'C. Gestión Pto #1'!$B$4:M$16,MATCH(I$5,'C. Gestión Pto #1'!$B$4:M$4,0),"FALSO"),0) -> 0 | J14: =IFERROR(VLOOKUP($B14&$C14,'C. Gestión Pto #1'!$B$4:N$16,MATCH(J$5,'C. Gestión Pto #1'!$B$4:N$4,0),"FALSO"),0) -> 0 | L14: {=SUMPRODUCT($D14:$K14,TRANSPOSE('Indice CAC'!$E$12:$E$19))} -> 610005.92 | N14: =IF($C14="MAT",SUMIF('Preventivo Costo CH2171 '!$A$9:$A$57,$B14,'Preventivo Costo CH2171 '!$I$9:$I$57),IF($C14="MO",SUMIF('Preventivo Costo CH2171 '!$A$9:$A$57,$B14,'Preventivo Costo CH2171 '!$L$9:$L$57),SUMIF('Preventivo Costo CH2171 '!$A$9:$A$57,$B14,'Preventivo Costo CH2171 '!$N$9:$N$57))) -> 1226538.2 | P14: =IF(O14=100%,0,IF(OR(L14<>0,N14),N14-L14)) -> 616532.32 | Q14: =IF(OR(P14<0,N14),P14/N14,0%) -> 0.5026605 | R14: =IF(O14=100%,IF(OR(L14<>0,N14),N14-L14),0) -> 0
B15: Seguridad e Higiene | D15: =IFERROR(VLOOKUP($B15&$C15,'C. Gestión Pto #1'!$B$4:H$16,MATCH(D$5,'C. Gestión Pto #1'!$B$4:H$4,0),"FALSO"),0) -> 0 | E15: =IFERROR(VLOOKUP($B15&$C15,'C. Gestión Pto #1'!$B$4:I$16,MATCH(E$5,'C. Gestión Pto #1'!$B$4:I$4,0),"FALSO"),0) -> 0 | F15: =IFERROR(VLOOKUP($B15&$C15,'C. Gestión Pto #1'!$B$4:J$16,MATCH(F$5,'C. Gestión Pto #1'!$B$4:J$4,0),"FALSO"),0) -> 0 | G15: =IFERROR(VLOOKUP($B15&$C15,'C. Gestión Pto #1'!$B$4:K$16,MATCH(G$5,'C. Gestión Pto #1'!$B$4:K$4,0),"FALSO"),0) -> 517195 | H15: =IFERROR(VLOOKUP($B15&$C15,'C. Gestión Pto #1'!$B$4:L$16,MATCH(H$5,'C. Gestión Pto #1'!$B$4:L$4,0),"FALSO"),0) -> 826285.91 | I15: =IFERROR(VLOOKUP($B15&$C15,'C. Gestión Pto #1'!$B$4:M$16,MATCH(I$5,'C. Gestión Pto #1'!$B$4:M$4,0),"FALSO"),0) -> 517195 | J15: =IFERROR(VLOOKUP($B15&$C15,'C. Gestión Pto #1'!$B$4:N$16,MATCH(J$5,'C. Gestión Pto #1'!$B$4:N$4,0),"FALSO"),0) -> 1195790 | L15: {=SUMPRODUCT($D15:$K15,TRANSPOSE('Indice CAC'!$E$12:$E$19))} -> 2519063.7 | N15: =IF($C15="MAT",SUMIF('Preventivo Costo CH2171 '!$A$9:$A$57,$B15,'Preventivo Costo CH2171 '!$I$9:$I$57),IF($C15="MO",SUMIF('Preventivo Costo CH2171 '!$A$9:$A$57,$B15,'Preventivo Costo CH2171 '!$L$9:$L$57),SUMIF('Preventivo Costo CH2171 '!$A$9:$A$57,$B15,'Preventivo Costo CH2171 '!$N$9:$N$57))) -> 4623254.5 | P15: =IF(O15=100%,0,IF(OR(L15<>0,N15),N15-L15)) -> 2104190.8 | Q15: =IF(OR(P15<0,N15),P15/N15,0%) -> 0.45513194 | R15: =IF(O15=100%,IF(OR(L15<>0,N15),N15-L15),0) -> 0
B16: Movilidad | D16: =IFERROR(VLOOKUP($B16&$C16,'C. Gestión Pto #1'!$B$4:H$16,MATCH(D$5,'C. Gestión Pto #1'!$B$4:H$4,0),"FALSO"),0) -> 0 | E16: =IFERROR(VLOOKUP($B16&$C16,'C. Gestión Pto #1'!$B$4:I$16,MATCH(E$5,'C. Gestión Pto #1'!$B$4:I$4,0),"FALSO"),0) -> 0 | F16: =IFERROR(VLOOKUP($B16&$C16,'C. Gestión Pto #1'!$B$4:J$16,MATCH(F$5,'C. Gestión Pto #1'!$B$4:J$4,0),"FALSO"),0) -> 0 | G16: =IFERROR(VLOOKUP($B16&$C16,'C. Gestión Pto #1'!$B$4:K$16,MATCH(G$5,'C. Gestión Pto #1'!$B$4:K$4,0),"FALSO"),0) -> 0 | H16: =IFERROR(VLOOKUP($B16&$C16,'C. Gestión Pto #1'!$B$4:L$16,MATCH(H$5,'C. Gestión Pto #1'!$B$4:L$4,0),"FALSO"),0) -> 639742.64 | I16: =IFERROR(VLOOKUP($B16&$C16,'C. Gestión Pto #1'!$B$4:M$16,MATCH(I$5,'C. Gestión Pto #1'!$B$4:M$4,0),"FALSO"),0) -> 716525.59 | J16: =IFERROR(VLOOKUP($B16&$C16,'C. Gestión Pto #1'!$B$4:N$16,MATCH(J$5,'C. Gestión Pto #1'!$B$4:N$4,0),"FALSO"),0) -> 38016.53 | L16: {=SUMPRODUCT($D16:$K16,TRANSPOSE('Indice CAC'!$E$12:$E$19))} -> 1153083.2 | N16: =IF($C16="MAT",SUMIF('Preventivo Costo CH2171 '!$A$9:$A$57,$B16,'Preventivo Costo CH2171 '!$I$9:$I$57),IF($C16="MO",SUMIF('Preventivo Costo CH2171 '!$A$9:$A$57,$B16,'Preventivo Costo CH2171 '!$L$9:$L$57),SUMIF('Preventivo Costo CH2171 '!$A$9:$A$57,$B16,'Preventivo Costo CH2171 '!$N$9:$N$57))) -> 8000000 | P16: =IF(O16=100%,0,IF(OR(L16<>0,N16),N16-L16)) -> 6846916.8 | Q16: =IF(OR(P16<0,N16),P16/N16,0%) -> 0.85586461 | R16: =IF(O16=100%,IF(OR(L16<>0,N16),N16-L16),0) -> 0
B17: Albañilería | C17: MAT | D17: =IFERROR(VLOOKUP($B17&$C17,'C. Gestión Pto #1'!$B$4:H$16,MATCH(D$5,'C. Gestión Pto #1'!$B$4:H$4,0),"FALSO"),0) -> 0 | E17: =IFERROR(VLOOKUP($B17&$C17,'C. Gestión Pto #1'!$B$4:I$16,MATCH(E$5,'C. Gestión Pto #1'!$B$4:I$4,0),"FALSO"),0) -> 0 | F17: =IFERROR(VLOOKUP($B17&$C17,'C. Gestión Pto #1'!$B$4:J$16,MATCH(F$5,'C. Gestión Pto #1'!$B$4:J$4,0),"FALSO"),0) -> 0 | G17: =IFERROR(VLOOKUP($B17&$C17,'C. Gestión Pto #1'!$B$4:K$16,MATCH(G$5,'C. Gestión Pto #1'!$B$4:K$4,0),"FALSO"),0) -> 48248.1 | H17: =IFERROR(VLOOKUP($B17&$C17,'C. Gestión Pto #1'!$B$4:L$16,MATCH(H$5,'C. Gestión Pto #1'!$B$4:L$4,0),"FALSO"),0) -> 95942.03 | I17: =IFERROR(VLOOKUP($B17&$C17,'C. Gestión Pto #1'!$B$4:M$16,MATCH(I$5,'C. Gestión Pto #1'!$B$4:M$4,0),"FALSO"),0) -> 371787.4 | J17: =IFERROR(VLOOKUP($B17&$C17,'C. Gestión Pto #1'!$B$4:N$16,MATCH(J$5,'C. Gestión Pto #1'!$B$4:N$4,0),"FALSO"),0) -> 171269.97 | L17: {=SUMPRODUCT($D17:$K17,TRANSPOSE('Indice CAC'!$E$12:$E$19))} -> 564374.82 | N17: =IF($C17="MAT",SUMIF('Preventivo Costo CH2171 '!$A$9:$A$57,$B17,'Preventivo Costo CH2171 '!$I$9:$I$57),IF($C17="MO",SUMIF('Preventivo Costo CH2171 '!$A$9:$A$57,$B17,'Preventivo Costo CH2171 '!$L$9:$L$57),SUMIF('Preventivo Costo CH2171 '!$A$9:$A$57,$B17,'Preventivo Costo CH2171 '!$N$9:$N$57))) -> 1000000 | P17: =IF(O17=100%,0,IF(OR(L17<>0,N17),N17-L17)) -> 435625.18 | Q17: =IF(OR(P17<0,N17),P17/N17,0%) -> 0.43562518 | R17: =IF(O17=100%,IF(OR(L17<>0,N17),N17-L17),0) -> 0
B18: Albañilería | C18: MO | D18: =IFERROR(VLOOKUP($B18&$C18,'C. Gestión Pto #1'!$B$4:H$16,MATCH(D$5,'C. Gestión Pto #1'!$B$4:H$4,0),"FALSO"),0) -> 0 | E18: =IFERROR(VLOOKUP($B18&$C18,'C. Gestión Pto #1'!$B$4:I$16,MATCH(E$5,'C. Gestión Pto #1'!$B$4:I$4,0),"FALSO"),0) -> 0 | F18: =IFERROR(VLOOKUP($B18&$C18,'C. Gestión Pto #1'!$B$4:J$16,MATCH(F$5,'C. Gestión Pto #1'!$B$4:J$4,0),"FALSO"),0) -> 0 | G18: =IFERROR(VLOOKUP($B18&$C18,'C. Gestión Pto #1'!$B$4:K$16,MATCH(G$5,'C. Gestión Pto #1'!$B$4:K$4,0),"FALSO"),0) -> 0 | H18: =IFERROR(VLOOKUP($B18&$C18,'C. Gestión Pto #1'!$B$4:L$16,MATCH(H$5,'C. Gestión Pto #1'!$B$4:L$4,0),"FALSO"),0) -> 0 | I18: =IFERROR(VLOOKUP($B18&$C18,'C. Gestión Pto #1'!$B$4:M$16,MATCH(I$5,'C. Gestión Pto #1'!$B$4:M$4,0),"FALSO"),0) -> 2330315.7 | J18: =IFERROR(VLOOKUP($B18&$C18,'C. Gestión Pto #1'!$B$4:N$16,MATCH(J$5,'C. Gestión Pto #1'!$B$4:N$4,0),"FALSO"),0) -> 0 | L18: {=SUMPRODUCT($D18:$K18,TRANSPOSE('Indice CAC'!$E$12:$E$19))} -> 1911725.5 | N18: =IF($C18="MAT",SUMIF('Preventivo Costo CH2171 '!$A$9:$A$57,$B18,'Preventivo Costo CH2171 '!$I$9:$I$57),IF($C18="MO",SUMIF('Preventivo Costo CH2171 '!$A$9:$A$57,$B18,'Preventivo Costo CH2171 '!$L$9:$L$57),SUMIF('Preventivo Costo CH2171 '!$A$9:$A$57,$B18,'Preventivo Costo CH2171 '!$N$9:$N$57))) -> 20558829 | P18: =IF(O18=100%,0,IF(OR(L18<>0,N18),N18-L18)) -> 18647104 | Q18: =IF(OR(P18<0,N18),P18/N18,0%) -> 0.90701195 | R18: =IF(O18=100%,IF(OR(L18<>0,N18),N18-L18),0) -> 0
B19: Excavación y Mov. de Suelos | D19: =IFERROR(VLOOKUP($B19&$C19,'C. Gestión Pto #1'!$B$4:H$16,MATCH(D$5,'C. Gestión Pto #1'!$B$4:H$4,0),"FALSO"),0) -> 0 | E19: =IFERROR(VLOOKUP($B19&$C19,'C. Gestión Pto #1'!$B$4:I$16,MATCH(E$5,'C. Gestión Pto #1'!$B$4:I$4,0),"FALSO"),0) -> 0 | F19: =IFERROR(VLOOKUP($B19&$C19,'C. Gestión Pto #1'!$B$4:J$16,MATCH(F$5,'C. Gestión Pto #1'!$B$4:J$4,0),"FALSO"),0) -> 0 | G19: =IFERROR(VLOOKUP($B19&$C19,'C. Gestión Pto #1'!$B$4:K$16,MATCH(G$5,'C. Gestión Pto #1'!$B$4:K$4,0),"FALSO"),0) -> 0 | H19: =IFERROR(VLOOKUP($B19&$C19,'C. Gestión Pto #1'!$B$4:L$16,MATCH(H$5,'C. Gestión Pto #1'!$B$4:L$4,0),"FALSO"),0) -> 0 | I19: =IFERROR(VLOOKUP($B19&$C19,'C. Gestión Pto #1'!$B$4:M$16,MATCH(I$5,'C. Gestión Pto #1'!$B$4:M$4,0),"FALSO"),0) -> 1310000 | J19: =IFERROR(VLOOKUP($B19&$C19,'C. Gestión Pto #1'!$B$4:N$16,MATCH(J$5,'C. Gestión Pto #1'!$B$4:N$4,0),"FALSO"),0) -> 0 | L19: {=SUMPRODUCT($D19:$K19,TRANSPOSE('Indice CAC'!$E$12:$E$19))} -> 1074687.2 | N19: =IF($C19="MAT",SUMIF('Preventivo Costo CH2171 '!$A$9:$A$57,$B19,'Preventivo Costo CH2171 '!$I$9:$I$57),IF($C19="MO",SUMIF('Preventivo Costo CH2171 '!$A$9:$A$57,$B19,'Preventivo Costo CH2171 '!$L$9:$L$57),SUMIF('Preventivo Costo CH2171 '!$A$9:$A$57,$B19,'Preventivo Costo CH2171 '!$N$9:$N$57))) -> 9462540.3 | P19: =IF(O19=100%,0,IF(OR(L19<>0,N19),N19-L19)) -> 8387853.1 | Q19: =IF(OR(P19<0,N19),P19/N19,0%) -> 0.8864272 | R19: =IF(O19=100%,IF(OR(L19<>0,N19),N19-L19),0) -> 0
B20: Hormigón | C20: MAT | D20: =IFERROR(VLOOKUP($B20&$C20,'C. Gestión Pto #1'!$B$4:H$16,MATCH(D$5,'C. Gestión Pto #1'!$B$4:H$4,0),"FALSO"),0) -> 0 | E20: =IFERROR(VLOOKUP($B20&$C20,'C. Gestión Pto #1'!$B$4:I$16,MATCH(E$5,'C. Gestión Pto #1'!$B$4:I$4,0),"FALSO"),0) -> 0 | F20: =IFERROR(VLOOKUP($B20&$C20,'C. Gestión Pto #1'!$B$4:J$16,MATCH(F$5,'C. Gestión Pto #1'!$B$4:J$4,0),"FALSO"),0) -> 0 | G20: =IFERROR(VLOOKUP($B20&$C20,'C. Gestión Pto #1'!$B$4:K$16,MATCH(G$5,'C. Gestión Pto #1'!$B$4:K$4,0),"FALSO"),0) -> 0 | H20: =IFERROR(VLOOKUP($B20&$C20,'C. Gestión Pto #1'!$B$4:L$16,MATCH(H$5,'C. Gestión Pto #1'!$B$4:L$4,0),"FALSO"),0) -> 20721536 | I20: =IFERROR(VLOOKUP($B20&$C20,'C. Gestión Pto #1'!$B$4:M$16,MATCH(I$5,'C. Gestión Pto #1'!$B$4:M$4,0),"FALSO"),0) -> 4488122.6 | J20: =IFERROR(VLOOKUP($B20&$C20,'C. Gestión Pto #1'!$B$4:N$16,MATCH(J$5,'C. Gestión Pto #1'!$B$4:N$4,0),"FALSO"),0) -> 13222352 | L20: {=SUMPRODUCT($D20:$K20,TRANSPOSE('Indice CAC'!$E$12:$E$19))} -> 31668388 | N20: =IF($C20="MAT",SUMIF('Preventivo Costo CH2171 '!$A$9:$A$57,$B20,'Preventivo Costo CH2171 '!$I$9:$I$57),IF($C20="MO",SUMIF('Preventivo Costo CH2171 '!$A$9:$A$57,$B20,'Preventivo Costo CH2171 '!$L$9:$L$57),SUMIF('Preventivo Costo CH2171 '!$A$9:$A$57,$B20,'Preventivo Costo CH2171 '!$N$9:$N$57))) -> 1.55289e+08 | P20: =IF(O20=100%,0,IF(OR(L20<>0,N20),N20-L20)) -> 1.2362062e+08 | Q20: =IF(OR(P20<0,N20),P20/N20,0%) -> 0.79606806 | R20: =IF(O20=100%,IF(OR(L20<>0,N20),N20-L20),0) -> 0
B21: Hormigón | C21: MO | D21: =IFERROR(VLOOKUP($B21&$C21,'C. Gestión Pto #1'!$B$4:H$16,MATCH(D$5,'C. Gestión Pto #1'!$B$4:H$4,0),"FALSO"),0) -> 0 | E21: =IFERROR(VLOOKUP($B21&$C21,'C. Gestión Pto #1'!$B$4:I$16,MATCH(E$5,'C. Gestión Pto #1'!$B$4:I$4,0),"FALSO"),0) -> 0 | F21: =IFERROR(VLOOKUP($B21&$C21,'C. Gestión Pto #1'!$B$4:J$16,MATCH(F$5,'C. Gestión Pto #1'!$B$4:J$4,0),"FALSO"),0) -> 0 | G21: =IFERROR(VLOOKUP($B21&$C21,'C. Gestión Pto #1'!$B$4:K$16,MATCH(G$5,'C. Gestión Pto #1'!$B$4:K$4,0),"FALSO"),0) -> 0 | H21: =IFERROR(VLOOKUP($B21&$C21,'C. Gestión Pto #1'!$B$4:L$16,MATCH(H$5,'C. Gestión Pto #1'!$B$4:L$4,0),"FALSO"),0) -> 19211836 | I21: =IFERROR(VLOOKUP($B21&$C21,'C. Gestión Pto #1'!$B$4:M$16,MATCH(I$5,'C. Gestión Pto #1'!$B$4:M$4,0),"FALSO"),0) -> 19661613 | J21: =IFERROR(VLOOKUP($B21&$C21,'C. Gestión Pto #1'!$B$4:N$16,MATCH(J$5,'C. Gestión Pto #1'!$B$4:N$4,0),"FALSO"),0) -> 30526436 | L21: {=SUMPRODUCT($D21:$K21,TRANSPOSE('Indice CAC'!$E$12:$E$19))} -> 56819928 | N21: =IF($C21="MAT",SUMIF('Preventivo Costo CH2171 '!$A$9:$A$57,$B21,'Preventivo Costo CH2171 '!$I$9:$I$57),IF($C21="MO",SUMIF('Preventivo Costo CH2171 '!$A$9:$A$57,$B21,'Preventivo Costo CH2171 '!$L$9:$L$57),SUMIF('Preventivo Costo CH2171 '!$A$9:$A$57,$B21,'Preventivo Costo CH2171 '!$N$9:$N$57))) -> 1.6857077e+08 | P21: =IF(O21=100%,0,IF(OR(L21<>0,N21),N21-L21)) -> 1.1175085e+08 | Q21: =IF(OR(P21<0,N21),P21/N21,0%) -> 0.66293132 | R21: =IF(O21=100%,IF(OR(L21<>0,N21),N21-L21),0) -> 0
B22: Equipos | D22: =IFERROR(VLOOKUP($B22&$C22,'C. Gestión Pto #1'!$B$4:H$16,MATCH(D$5,'C. Gestión Pto #1'!$B$4:H$4,0),"FALSO"),0) -> 0 | E22: =IFERROR(VLOOKUP($B22&$C22,'C. Gestión Pto #1'!$B$4:I$16,MATCH(E$5,'C. Gestión Pto #1'!$B$4:I$4,0),"FALSO"),0) -> 0 | F22: =IFERROR(VLOOKUP($B22&$C22,'C. Gestión Pto #1'!$B$4:J$16,MATCH(F$5,'C. Gestión Pto #1'!$B$4:J$4,0),"FALSO"),0) -> 0 | G22: =IFERROR(VLOOKUP($B22&$C22,'C. Gestión Pto #1'!$B$4:K$16,MATCH(G$5,'C. Gestión Pto #1'!$B$4:K$4,0),"FALSO"),0) -> 0 | H22: =IFERROR(VLOOKUP($B22&$C22,'C. Gestión Pto #1'!$B$4:L$16,MATCH(H$5,'C. Gestión Pto #1'!$B$4:L$4,0),"FALSO"),0) -> 0 | I22: =IFERROR(VLOOKUP($B22&$C22,'C. Gestión Pto #1'!$B$4:M$16,MATCH(I$5,'C. Gestión Pto #1'!$B$4:M$4,0),"FALSO"),0) -> 0 | J22: =IFERROR(VLOOKUP($B22&$C22,'C. Gestión Pto #1'!$B$4:N$16,MATCH(J$5,'C. Gestión Pto #1'!$B$4:N$4,0),"FALSO"),0) -> 702737.42 | L22: {=SUMPRODUCT($D22:$K22,TRANSPOSE('Indice CAC'!$E$12:$E$19))} -> 567140.81 | N22: =IF($C22="MAT",SUMIF('Preventivo Costo CH2171 '!$A$9:$A$57,$B22,'Preventivo Costo CH2171 '!$I$9:$I$57),IF($C22="MO",SUMIF('Preventivo Costo CH2171 '!$A$9:$A$57,$B22,'Preventivo Costo CH2171 '!$L$9:$L$57),SUM('Preventivo Costo CH2171 '!M9:M57))) -> 15976116 | P22: =IF(O22=100%,0,IF(OR(L22<>0,N22),N22-L22)) -> 15408975 | Q22: =IF(OR(P22<0,N22),P22/N22,0%) -> 0.96450071 | R22: =IF(O22=100%,IF(OR(L22<>0,N22),N22-L22),0) -> 0
B23: Gastos Generales Obra | D23: =IFERROR(VLOOKUP($B23&$C23,'C. Gestión Pto #1'!$B$4:H$16,MATCH(D$5,'C. Gestión Pto #1'!$B$4:H$4,0),"FALSO"),0) -> 0 | E23: =IFERROR(VLOOKUP($B23&$C23,'C. Gestión Pto #1'!$B$4:I$16,MATCH(E$5,'C. Gestión Pto #1'!$B$4:I$4,0),"FALSO"),0) -> 0 | F23: =IFERROR(VLOOKUP($B23&$C23,'C. Gestión Pto #1'!$B$4:J$16,MATCH(F$5,'C. Gestión Pto #1'!$B$4:J$4,0),"FALSO"),0) -> 0 | G23: =IFERROR(VLOOKUP($B23&$C23,'C. Gestión Pto #1'!$B$4:K$16,MATCH(G$5,'C. Gestión Pto #1'!$B$4:K$4,0),"FALSO"),0) -> 247000 | H23: =IFERROR(VLOOKUP($B23&$C23,'C. Gestión Pto #1'!$B$4:L$16,MATCH(H$5,'C. Gestión Pto #1'!$B$4:L$4,0),"FALSO"),0) -> 227000 | I23: =IFERROR(VLOOKUP($B23&$C23,'C. Gestión Pto #1'!$B$4:M$16,MATCH(I$5,'C. Gestión Pto #1'!$B$4:M$4,0),"FALSO"),0) -> 1101000 | J23: =IFERROR(VLOOKUP($B23&$C23,'C. Gestión Pto #1'!$B$4:N$16,MATCH(J$5,'C. Gestión Pto #1'!$B$4:N$4,0),"FALSO"),0) -> 1520000 | L23: {=SUMPRODUCT($D23:$K23,TRANSPOSE('Indice CAC'!$E$12:$E$19))} -> 2529400.2 | N23: =IF($C23="MAT",SUMIF('Preventivo Costo CH2171 '!$A$9:$A$57,$B23,'Preventivo Costo CH2171 '!$I$9:$I$57),IF($C23="MO",SUMIF('Preventivo Costo CH2171 '!$A$9:$A$57,$B23,'Preventivo Costo CH2171 '!$L$9:$L$57),SUMIF('Preventivo Costo CH2171 '!$A$9:$A$57,$B23,'Preventivo Costo CH2171 '!$N$9:$N$57))) -> 3712405 | P23: =IF(O23=100%,0,IF(OR(L23<>0,N23),N23-L23)) -> 1183004.8 | Q23: =IF(OR(P23<0,N23),P23/N23,0%) -> 0.31866264 | R23: =IF(O23=100%,IF(OR(L23<>0,N23),N23-L23),0) -> 0
B24: Supervisión de Obra | D24: =IFERROR(VLOOKUP($B24&$C24,'C. Gestión Pto #1'!$B$4:H$16,MATCH(D$5,'C. Gestión Pto #1'!$B$4:H$4,0),"FALSO"),0) -> 0 | E24: =IFERROR(VLOOKUP($B24&$C24,'C. Gestión Pto #1'!$B$4:I$16,MATCH(E$5,'C. Gestión Pto #1'!$B$4:I$4,0),"FALSO"),0) -> 0 | F24: =IFERROR(VLOOKUP($B24&$C24,'C. Gestión Pto #1'!$B$4:J$16,MATCH(F$5,'C. Gestión Pto #1'!$B$4:J$4,0),"FALSO"),0) -> 0 | G24: =IFERROR(VLOOKUP($B24&$C24,'C. Gestión Pto #1'!$B$4:K$16,MATCH(G$5,'C. Gestión Pto #1'!$B$4:K$4,0),"FALSO"),0) -> 0 | H24: =IFERROR(VLOOKUP($B24&$C24,'C. Gestión Pto #1'!$B$4:L$16,MATCH(H$5,'C. Gestión Pto #1'!$B$4:L$4,0),"FALSO"),0) -> 2800000 | I24: =IFERROR(VLOOKUP($B24&$C24,'C. Gestión Pto #1'!$B$4:M$16,MATCH(I$5,'C. Gestión Pto #1'!$B$4:M$4,0),"FALSO"),0) -> 2867000 | J24: =IFERROR(VLOOKUP($B24&$C24,'C. Gestión Pto #1'!$B$4:N$16,MATCH(J$5,'C. Gestión Pto #1'!$B$4:N$4,0),"FALSO"),0) -> 2850000 | L24: {=SUMPRODUCT($D24:$K24,TRANSPOSE('Indice CAC'!$E$12:$E$19))} -> 6991833.5 | N24: =IF($C24="MAT",SUMIF('Preventivo Costo CH2171 '!$A$9:$A$57,$B24,'Preventivo Costo CH2171 '!$I$9:$I$57),IF($C24="MO",SUMIF('Preventivo Costo CH2171 '!$A$9:$A$57,$B24,'Preventivo Costo CH2171 '!$L$9:$L$57),SUMIF('Preventivo Costo CH2171 '!$A$9:$A$57,$B24,'Preventivo Costo CH2171 '!$N$9:$N$57))) -> 32465089 | P24: =IF(O24=100%,0,IF(OR(L24<>0,N24),N24-L24)) -> 25473256 | Q24: =IF(OR(P24<0,N24),P24/N24,0%) -> 0.78463532 | R24: =IF(O24=100%,IF(OR(L24<>0,N24),N24-L24),0) -> 0
B25: Total Egresos de Obra | D25: =SUM(D13:D24) -> 0 | E25: =SUM(E13:E24) -> 0 | F25: =SUM(F13:F24) -> 939182.1 | G25: =SUM(G13:G24) -> 2352432 | H25: =SUM(H13:H24) -> 48377387 | I25: =SUM(I13:I24) -> 34098469 | J25: =SUM(J13:J24) -> 50226602 | L25: =SUM(L13:L24) -> 1.1173955e+08 | N25: =SUM(N13:N24) -> 4.3559384e+08 | P25: =IF(O25=100%,0,IF(OR(L25<>0,N25),N25-L25)) -> 3.2385429e+08 | Q25: =IF(OR(P25<0,N25),P25/N25,0%) -> 0.74347766 | R25: =SUM(R13:R23) -> 0
B27: Resultado Operativo | D27: =SUM(D8,D10,-D25) -> 0 | E27: =SUM(E8,E10,-E25) -> 0 | F27: =SUM(F8,F10,-F25) -> -939182.1 | G27: =SUM(G8,G10,-G25) -> -2352432 | H27: =SUM(H8,H10,-H25) -> 93029180 | I27: =SUM(I8,I10,-I25) -> 27179919 | J27: =SUM(J8,J10,-J25) -> -50226602 | L27: =SUM(L8,-L25) -> 59561804 | N27: =SUM(N8,-N25) -> -45283042
B28: Resultado Acumulado | D28: =D27 -> 0 | E28: =E27+D28 -> 0 | F28: =F27+E28 -> -939182.1 | G28: =G27+F28 -> -3291614.1 | H28: =H27+G28 -> 89737566 | I28: =I27+H28 -> 1.1691748e+08 | J28: =J27+I28 -> 66690883

Sheet Resumen Pto #2
S1: Actualizado | T1: 46156
B3: OBRA: CHIVILCOY 2171
B4: RESUMEN DE OBRA
D5: 45962 | E5: 45992 | F5: 46023 | G5: 46054 | H5: 46082 | I5: 46113 | J5: 46143 | L5: Acum. Descontado | N5: Previsto | O5: % Cert. Acum. | P5: Saldo Disponible | Q5: Disponible % | R5: Rubro Completado
B6: Ingresos de Obra
B7: Ingresos por certificados | D7: =SUMIFS(Certificados!$E$12:$E$21,Certificados!$A$12:$A$21,">="&DATE(2025,11,1),Certificados!$A$12:$A$21,"<="&DATE(2025,11,30),Certificados!$C$12:$C$21,"Pto. 2") -> 0 | E7: =SUMIFS(Certificados!$E$12:$E$21,Certificados!$A$12:$A$21,">="&DATE(2025,12,1),Certificados!$A$12:$A$21,"<="&DATE(2025,12,31),Certificados!$C$12:$C$21,"Pto. 2") -> 0 | F7: =SUMIFS(Certificados!$E$12:$E$21,Certificados!$A$12:$A$21,">="&DATE(2026,1,1),Certificados!$A$12:$A$21,"<="&DATE(2026,1,31),Certificados!$C$12:$C$21,"Pto. 2") -> 0 | G7: =SUMIFS(Certificados!$E$12:$E$21,Certificados!$A$12:$A$21,">="&DATE(2026,2,1),Certificados!$A$12:$A$21,"<="&DATE(2026,2,29),Certificados!$C$12:$C$21,"Pto. 2") -> 0 | H7: =SUMIFS(Certificados!$E$12:$E$21,Certificados!$A$12:$A$21,">="&DATE(2026,3,1),Certificados!$A$12:$A$21,"<="&DATE(2026,3,31),Certificados!$B$12:$B$21,"Pto 2") -> 0 | I7: =SUMIFS(Certificados!$E$12:$E$21,Certificados!$A$12:$A$21,">="&DATE(2026,4,1),Certificados!$A$12:$A$21,"<="&DATE(2026,4,30),Certificados!$B$12:$B$21,"Pto 2") -> 0 | J7: =SUMIFS(Certificados!$E$12:$E$21,Certificados!$A$12:$A$21,">="&DATE(2026,5,1),Certificados!$A$12:$A$21,"<="&DATE(2026,5,31),Certificados!$B$12:$B$21,"Pto 2") -> 0 | L7: =SUM(D7:K7) -> 0 | N7: =SUM(Facturacion!E5:E5) -> 6.1109415e+08 | P7: =IF(O7=100%,0,IF(OR(L7<>0,N7),N7-L7)) -> 6.1109415e+08 | Q7: =IF(OR(P7<0,N7),P7/N7,0%) -> 1 | R7: =IF(O7=100%,IF(OR(#REF!<>0,N7),N7-#REF!),0) -> 0
B8: Total Ingresos de Obra | D8: =SUM(D7) -> 0 | E8: =SUM(E7) -> 0 | F8: =SUM(F7) -> 0 | G8: =SUM(G7) -> 0 | H8: =SUM(H7) -> 0 | I8: =SUM(I7) -> 0 | J8: =SUM(J7) -> 0 | L8: =SUM(L7) -> 0 | N8: =SUM(N7) -> 6.1109415e+08 | P8: =SUM(P7) -> 6.1109415e+08 | Q8: =IF(OR(P8<0,N8),P8/N8,0%) -> 1 | R8: =SUM(R7) -> 0
B9: Actualización por CAC | D9: =SUMIFS(Certificados!$F$12:$F$21,Certificados!$A$12:$A$21,">="&DATE(2025,11,1),Certificados!$A$12:$A$21,"<="&DATE(2025,11,30),Certificados!$C$12:$C$21,"Pto. 2") -> 0 | E9: =SUMIFS(Certificados!$F$12:$F$21,Certificados!$A$12:$A$21,">="&DATE(2025,12,1),Certificados!$A$12:$A$21,"<="&DATE(2025,12,31),Certificados!$C$12:$C$21,"Pto. 2") -> 0 | F9: =SUMIFS(Certificados!$F$12:$F$21,Certificados!$A$12:$A$21,">="&DATE(2026,1,1),Certificados!$A$12:$A$21,"<="&DATE(2026,1,31),Certificados!$C$12:$C$21,"Pto. 2") -> 0 | G9: =SUMIFS(Certificados!$F$12:$F$21,Certificados!$A$12:$A$21,">="&DATE(2026,2,1),Certificados!$A$12:$A$21,"<="&DATE(2026,2,29),Certificados!$C$12:$C$21,"Pto. 2") -> 0 | H9: =SUMIFS(Certificados!$F$12:$F$21,Certificados!$A$12:$A$21,">="&DATE(2026,3,1),Certificados!$A$12:$A$21,"<="&DATE(2026,3,31),Certificados!$B$12:$B$21,"Pto 2") -> 0 | I9: =SUMIFS(Certificados!$F$12:$F$21,Certificados!$A$12:$A$21,">="&DATE(2026,4,1),Certificados!$A$12:$A$21,"<="&DATE(2026,4,30),Certificados!$B$12:$B$21,"Pto 2") -> 0 | J9: =SUMIFS(Certificados!$F$12:$F$21,Certificados!$A$12:$A$21,">="&DATE(2026,5,1),Certificados!$A$12:$A$21,"<="&DATE(2026,5,31),Certificados!$B$12:$B$21,"Pto 2") -> 0 | L9: =SUM(D9:K9) -> 0 | N9: 0 | O9: 0 | P9: =IF(O9=100%,0,IF(N9=0,N9,N9-L9)) -> 0 | Q9: =IF(OR(P9<0,N9),P9/N9,0%) -> 0 | R9: =IF(O9=100%,IF(OR(#REF!<>0,N9),N9-#REF!),0) -> 0
B10: Total Ingresos por CAC | D10: =SUM(D9) -> 0 | E10: =SUM(E9) -> 0 | F10: =SUM(F9) -> 0 | G10: =SUM(G9) -> 0 | H10: =SUM(H9) -> 0 | I10: =SUM(I9) -> 0 | J10: =SUM(J9) -> 0 | L10: =SUM(L9) -> 0 | N10: =SUM(N9) -> 0 | P10: =SUM(P9) -> 0 | Q10: =IF(OR(P10<0,N10),P10/N10,0%) -> 0 | R10: =SUM(R9) -> 0
B12: Costos de Obra
B13: Supervisión de Obra | D13: =IFERROR(VLOOKUP($B13&$C13,'C. Gestión Pto #2'!$B$4:C$22,MATCH(D$5,'C. Gestión Pto #2'!$B$4:C$4,0),FALSE),0) -> 0 | E13: =IFERROR(VLOOKUP($B13&$C13,'C. Gestión Pto #2'!$B$4:D$22,MATCH(E$5,'C. Gestión Pto #2'!$B$4:D$4,0),FALSE),0) -> 0 | F13: =IFERROR(VLOOKUP($B13&$C13,'C. Gestión Pto #2'!$B$4:E$22,MATCH(F$5,'C. Gestión Pto #2'!$B$4:E$4,0),FALSE),0) -> 0 | G13: =IFERROR(VLOOKUP($B13&$C13,'C. Gestión Pto #2'!$B$4:F$22,MATCH(G$5,'C. Gestión Pto #2'!$B$4:F$4,0),FALSE),0) -> 0 | H13: =IFERROR(VLOOKUP($B13&$C13,'C. Gestión Pto #2'!$B$4:G$22,MATCH(H$5,'C. Gestión Pto #2'!$B$4:G$4,0),FALSE),0) -> 0 | I13: =IFERROR(VLOOKUP($B13&$C13,'C. Gestión Pto #2'!$B$4:H$22,MATCH(I$5,'C. Gestión Pto #2'!$B$4:H$4,0),FALSE),0) -> 0 | J13: =IFERROR(VLOOKUP($B13&$C13,'C. Gestión Pto #2'!$B$4:I$22,MATCH(J$5,'C. Gestión Pto #2'!$B$4:I$4,0),FALSE),0) -> 0 | L13: {=SUMPRODUCT($D13:$K13,TRANSPOSE('Indice CAC'!$E$12:$E$19))} -> 0 | N13: =IF(C13="MAT",SUMIF('Preventivo Costo CH2171 '!$A$61:$A$224,$B13,'Preventivo Costo CH2171 '!$I$61:$I$224),IF(C13="MO",SUMIF('Preventivo Costo CH2171 '!$A$61:$A$224,$B13,'Preventivo Costo CH2171 '!$L$61:$L$224),SUMIF('Preventivo Costo CH2171 '!$A$61:$A$224,$B13,'Preventivo Costo CH2171 '!$N$61:$N$224))) -> 29218580 | P13: =IF(O13=100%,0,IF(OR(L13<>0,N13),N13-L13)) -> 29218580 | Q13: =IF(OR(P13<0,N13),P13/N13,0%) -> 1 | R13: =IF(O13=100%,IF(OR(#REF!<>0,N13),N13-#REF!),0) -> 0
B14: Seguridad e Higiene | D14: =IFERROR(VLOOKUP($B14&$C14,'C. Gestión Pto #2'!$B$4:C$22,MATCH(D$5,'C. Gestión Pto #2'!$B$4:C$4,0),FALSE),0) -> 0 | E14: =IFERROR(VLOOKUP($B14&$C14,'C. Gestión Pto #2'!$B$4:D$22,MATCH(E$5,'C. Gestión Pto #2'!$B$4:D$4,0),FALSE),0) -> 0 | F14: =IFERROR(VLOOKUP($B14&$C14,'C. Gestión Pto #2'!$B$4:E$22,MATCH(F$5,'C. Gestión Pto #2'!$B$4:E$4,0),FALSE),0) -> 0 | G14: =IFERROR(VLOOKUP($B14&$C14,'C. Gestión Pto #2'!$B$4:F$22,MATCH(G$5,'C. Gestión Pto #2'!$B$4:F$4,0),FALSE),0) -> 0 | H14: =IFERROR(VLOOKUP($B14&$C14,'C. Gestión Pto #2'!$B$4:G$22,MATCH(H$5,'C. Gestión Pto #2'!$B$4:G$4,0),FALSE),0) -> 0 | I14: =IFERROR(VLOOKUP($B14&$C14,'C. Gestión Pto #2'!$B$4:H$22,MATCH(I$5,'C. Gestión Pto #2'!$B$4:H$4,0),FALSE),0) -> 0 | J14: =IFERROR(VLOOKUP($B14&$C14,'C. Gestión Pto #2'!$B$4:I$22,MATCH(J$5,'C. Gestión Pto #2'!$B$4:I$4,0),FALSE),0) -> 0 | L14: {=SUMPRODUCT($D14:$K14,TRANSPOSE('Indice CAC'!$E$12:$E$19))} -> 0 | N14: =IF(C14="MAT",SUMIF('Preventivo Costo CH2171 '!$A$61:$A$224,$B14,'Preventivo Costo CH2171 '!$I$61:$I$224),IF(C14="MO",SUMIF('Preventivo Costo CH2171 '!$A$61:$A$224,$B14,'Preventivo Costo CH2171 '!$L$61:$L$224),SUMIF('Preventivo Costo CH2171 '!$A$61:$A$224,$B14,'Preventivo Costo CH2171 '!$N$61:$N$224))) -> 2700000 | P14: =IF(O14=100%,0,IF(OR(L14<>0,N14),N14-L14)) -> 2700000 | Q14: =IF(OR(P14<0,N14),P14/N14,0%) -> 1 | R14: =IF(O14=100%,IF(OR(#REF!<>0,N14),N14-#REF!),0) -> 0
B15: Movilidad | D15: =IFERROR(VLOOKUP($B15&$C15,'C. Gestión Pto #2'!$B$4:C$22,MATCH(D$5,'C. Gestión Pto #2'!$B$4:C$4,0),FALSE),0) -> 0 | E15: =IFERROR(VLOOKUP($B15&$C15,'C. Gestión Pto #2'!$B$4:D$22,MATCH(E$5,'C. Gestión Pto #2'!$B$4:D$4,0),FALSE),0) -> 0 | F15: =IFERROR(VLOOKUP($B15&$C15,'C. Gestión Pto #2'!$B$4:E$22,MATCH(F$5,'C. Gestión Pto #2'!$B$4:E$4,0),FALSE),0) -> 0 | G15: =IFERROR(VLOOKUP($B15&$C15,'C. Gestión Pto #2'!$B$4:F$22,MATCH(G$5,'C. Gestión Pto #2'!$B$4:F$4,0),FALSE),0) -> 0 | H15: =IFERROR(VLOOKUP($B15&$C15,'C. Gestión Pto #2'!$B$4:G$22,MATCH(H$5,'C. Gestión Pto #2'!$B$4:G$4,0),FALSE),0) -> 0 | I15: =IFERROR(VLOOKUP($B15&$C15,'C. Gestión Pto #2'!$B$4:H$22,MATCH(I$5,'C. Gestión Pto #2'!$B$4:H$4,0),FALSE),0) -> 0 | J15: =IFERROR(VLOOKUP($B15&$C15,'C. Gestión Pto #2'!$B$4:I$22,MATCH(J$5,'C. Gestión Pto #2'!$B$4:I$4,0),FALSE),0) -> 0 | L15: {=SUMPRODUCT($D15:$K15,TRANSPOSE('Indice CAC'!$E$12:$E$19))} -> 0 | N15: =IF(C15="MAT",SUMIF('Preventivo Costo CH2171 '!$A$61:$A$224,$B15,'Preventivo Costo CH2171 '!$I$61:$I$224),IF(C15="MO",SUMIF('Preventivo Costo CH2171 '!$A$61:$A$224,$B15,'Preventivo Costo CH2171 '!$L$61:$L$224),SUMIF('Preventivo Costo CH2171 '!$A$61:$A$224,$B15,'Preventivo Costo CH2171 '!$N$61:$N$224))) -> 7200000 | P15: =IF(O15=100%,0,IF(OR(L15<>0,N15),N15-L15)) -> 7200000 | Q15: =IF(OR(P15<0,N15),P15/N15,0%) -> 1 | R15: =IF(O15=100%,IF(OR(#REF!<>0,N15),N15-#REF!),0) -> 0
B16: Albañilería | C16: MAT | D16: =IFERROR(VLOOKUP($B16&$C16,'C. Gestión Pto #2'!$B$4:C$22,MATCH(D$5,'C. Gestión Pto #2'!$B$4:C$4,0),FALSE),0) -> 0 | E16: =IFERROR(VLOOKUP($B16&$C16,'C. Gestión Pto #2'!$B$4:D$22,MATCH(E$5,'C. Gestión Pto #2'!$B$4:D$4,0),FALSE),0) -> 0 | F16: =IFERROR(VLOOKUP($B16&$C16,'C. Gestión Pto #2'!$B$4:E$22,MATCH(F$5,'C. Gestión Pto #2'!$B$4:E$4,0),FALSE),0) -> 0 | G16: =IFERROR(VLOOKUP($B16&$C16,'C. Gestión Pto #2'!$B$4:F$22,MATCH(G$5,'C. Gestión Pto #2'!$B$4:F$4,0),FALSE),0) -> 0 | H16: =IFERROR(VLOOKUP($B16&$C16,'C. Gestión Pto #2'!$B$4:G$22,MATCH(H$5,'C. Gestión Pto #2'!$B$4:G$4,0),FALSE),0) -> 0 | I16: =IFERROR(VLOOKUP($B16&$C16,'C. Gestión Pto #2'!$B$4:H$22,MATCH(I$5,'C. Gestión Pto #2'!$B$4:H$4,0),FALSE),0) -> 0 | J16: =IFERROR(VLOOKUP($B16&$C16,'C. Gestión Pto #2'!$B$4:I$22,MATCH(J$5,'C. Gestión Pto #2'!$B$4:I$4,0),FALSE),0) -> 0 | L16: {=SUMPRODUCT($D16:$K16,TRANSPOSE('Indice CAC'!$E$12:$E$19))} -> 0 | N16: =IF(C16="MAT",SUMIF('Preventivo Costo CH2171 '!$A$61:$A$224,$B16,'Preventivo Costo CH2171 '!$I$61:$I$224),IF(C16="MO",SUMIF('Preventivo Costo CH2171 '!$A$61:$A$224,$B16,'Preventivo Costo CH2171 '!$L$61:$L$224),SUMIF('Preventivo Costo CH2171 '!$A$61:$A$224,$B16,'Preventivo Costo CH2171 '!$N$61:$N$224))) -> 70873304 | P16: =IF(O16=100%,0,IF(OR(L16<>0,N16),N16-L16)) -> 70873304 | Q16: =IF(OR(P16<0,N16),P16/N16,0%) -> 1 | R16: =IF(O16=100%,IF(OR(#REF!<>0,N16),N16-#REF!),0) -> 0
B17: Albañilería | C17: MO | D17: =IFERROR(VLOOKUP($B17&$C17,'C. Gestión Pto #2'!$B$4:C$22,MATCH(D$5,'C. Gestión Pto #2'!$B$4:C$4,0),FALSE),0) -> 0 | E17: =IFERROR(VLOOKUP($B17&$C17,'C. Gestión Pto #2'!$B$4:D$22,MATCH(E$5,'C. Gestión Pto #2'!$B$4:D$4,0),FALSE),0) -> 0 | F17: =IFERROR(VLOOKUP($B17&$C17,'C. Gestión Pto #2'!$B$4:E$22,MATCH(F$5,'C. Gestión Pto #2'!$B$4:E$4,0),FALSE),0) -> 0 | G17: =IFERROR(VLOOKUP($B17&$C17,'C. Gestión Pto #2'!$B$4:F$22,MATCH(G$5,'C. Gestión Pto #2'!$B$4:F$4,0),FALSE),0) -> 0 | H17: =IFERROR(VLOOKUP($B17&$C17,'C. Gestión Pto #2'!$B$4:G$22,MATCH(H$5,'C. Gestión Pto #2'!$B$4:G$4,0),FALSE),0) -> 0 | I17: =IFERROR(VLOOKUP($B17&$C17,'C. Gestión Pto #2'!$B$4:H$22,MATCH(I$5,'C. Gestión Pto #2'!$B$4:H$4,0),FALSE),0) -> 0 | J17: =IFERROR(VLOOKUP($B17&$C17,'C. Gestión Pto #2'!$B$4:I$22,MATCH(J$5,'C. Gestión Pto #2'!$B$4:I$4,0),FALSE),0) -> 0 | L17: {=SUMPRODUCT($D17:$K17,TRANSPOSE('Indice CAC'!$E$12:$E$19))} -> 0 | N17: =IF(C17="MAT",SUMIF('Preventivo Costo CH2171 '!$A$61:$A$224,$B17,'Preventivo Costo CH2171 '!$I$61:$I$224),IF(C17="MO",SUMIF('Preventivo Costo CH2171 '!$A$61:$A$224,$B17,'Preventivo Costo CH2171 '!$L$61:$L$224),SUMIF('Preventivo Costo CH2171 '!$A$61:$A$224,$B17,'Preventivo Costo CH2171 '!$N$61:$N$224))) -> 1.5272197e+08 | P17: =IF(O17=100%,0,IF(OR(L17<>0,N17),N17-L17)) -> 1.5272197e+08 | Q17: =IF(OR(P17<0,N17),P17/N17,0%) -> 1 | R17: =IF(O17=100%,IF(OR(#REF!<>0,N17),N17-#REF!),0) -> 0
B18: Durlock | C18: MAT | D18: =IFERROR(VLOOKUP($B18&$C18,'C. Gestión Pto #2'!$B$4:C$22,MATCH(D$5,'C. Gestión Pto #2'!$B$4:C$4,0),FALSE),0) -> 0 | E18: =IFERROR(VLOOKUP($B18&$C18,'C. Gestión Pto #2'!$B$4:D$22,MATCH(E$5,'C. Gestión Pto #2'!$B$4:D$4,0),FALSE),0) -> 0 | F18: =IFERROR(VLOOKUP($B18&$C18,'C. Gestión Pto #2'!$B$4:E$22,MATCH(F$5,'C. Gestión Pto #2'!$B$4:E$4,0),FALSE),0) -> 0 | G18: =IFERROR(VLOOKUP($B18&$C18,'C. Gestión Pto #2'!$B$4:F$22,MATCH(G$5,'C. Gestión Pto #2'!$B$4:F$4,0),FALSE),0) -> 0 | H18: =IFERROR(VLOOKUP($B18&$C18,'C. Gestión Pto #2'!$B$4:G$22,MATCH(H$5,'C. Gestión Pto #2'!$B$4:G$4,0),FALSE),0) -> 0 | I18: =IFERROR(VLOOKUP($B18&$C18,'C. Gestión Pto #2'!$B$4:H$22,MATCH(I$5,'C. Gestión Pto #2'!$B$4:H$4,0),FALSE),0) -> 0 | J18: =IFERROR(VLOOKUP($B18&$C18,'C. Gestión Pto #2'!$B$4:I$22,MATCH(J$5,'C. Gestión Pto #2'!$B$4:I$4,0),FALSE),0) -> 0 | L18: {=SUMPRODUCT($D18:$K18,TRANSPOSE('Indice CAC'!$E$12:$E$19))} -> 0 | N18: =IF(C18="MAT",SUMIF('Preventivo Costo CH2171 '!$A$61:$A$224,$B18,'Preventivo Costo CH2171 '!$I$61:$I$224),IF(C18="MO",SUMIF('Preventivo Costo CH2171 '!$A$61:$A$224,$B18,'Preventivo Costo CH2171 '!$L$61:$L$224),SUMIF('Preventivo Costo CH2171 '!$A$61:$A$224,$B18,'Preventivo Costo CH2171 '!$N$61:$N$224))) -> 21396457 | P18: =IF(O18=100%,0,IF(OR(L18<>0,N18),N18-L18)) -> 21396457 | Q18: =IF(OR(P18<0,N18),P18/N18,0%) -> 1 | R18: =IF(O18=100%,IF(OR(#REF!<>0,N18),N18-#REF!),0) -> 0
B19: Durlock | C19: MO | D19: =IFERROR(VLOOKUP($B19&$C19,'C. Gestión Pto #2'!$B$4:C$22,MATCH(D$5,'C. Gestión Pto #2'!$B$4:C$4,0),FALSE),0) -> 0 | E19: =IFERROR(VLOOKUP($B19&$C19,'C. Gestión Pto #2'!$B$4:D$22,MATCH(E$5,'C. Gestión Pto #2'!$B$4:D$4,0),FALSE),0) -> 0 | F19: =IFERROR(VLOOKUP($B19&$C19,'C. Gestión Pto #2'!$B$4:E$22,MATCH(F$5,'C. Gestión Pto #2'!$B$4:E$4,0),FALSE),0) -> 0 | G19: =IFERROR(VLOOKUP($B19&$C19,'C. Gestión Pto #2'!$B$4:F$22,MATCH(G$5,'C. Gestión Pto #2'!$B$4:F$4,0),FALSE),0) -> 0 | H19: =IFERROR(VLOOKUP($B19&$C19,'C. Gestión Pto #2'!$B$4:G$22,MATCH(H$5,'C. Gestión Pto #2'!$B$4:G$4,0),FALSE),0) -> 0 | I19: =IFERROR(VLOOKUP($B19&$C19,'C. Gestión Pto #2'!$B$4:H$22,MATCH(I$5,'C. Gestión Pto #2'!$B$4:H$4,0),FALSE),0) -> 0 | J19: =IFERROR(VLOOKUP($B19&$C19,'C. Gestión Pto #2'!$B$4:I$22,MATCH(J$5,'C. Gestión Pto #2'!$B$4:I$4,0),FALSE),0) -> 0 | L19: {=SUMPRODUCT($D19:$K19,TRANSPOSE('Indice CAC'!$E$12:$E$19))} -> 0 | N19: =IF(C19="MAT",SUMIF('Preventivo Costo CH2171 '!$A$61:$A$224,$B19,'Preventivo Costo CH2171 '!$I$61:$I$224),IF(C19="MO",SUMIF('Preventivo Costo CH2171 '!$A$61:$A$224,$B19,'Preventivo Costo CH2171 '!$L$61:$L$224),SUMIF('Preventivo Costo CH2171 '!$A$61:$A$224,$B19,'Preventivo Costo CH2171 '!$N$61:$N$224))) -> 55470003 | P19: =IF(O19=100%,0,IF(OR(L19<>0,N19),N19-L19)) -> 55470003 | Q19: =IF(OR(P19<0,N19),P19/N19,0%) -> 1 | R19: =IF(O19=100%,IF(OR(#REF!<>0,N19),N19-#REF!),0) -> 0
B20: Pintura | C20: MAT | D20: =IFERROR(VLOOKUP($B20&$C20,'C. Gestión Pto #2'!$B$4:C$22,MATCH(D$5,'C. Gestión Pto #2'!$B$4:C$4,0),FALSE),0) -> 0 | E20: =IFERROR(VLOOKUP($B20&$C20,'C. Gestión Pto #2'!$B$4:D$22,MATCH(E$5,'C. Gestión Pto #2'!$B$4:D$4,0),FALSE),0) -> 0 | F20: =IFERROR(VLOOKUP($B20&$C20,'C. Gestión Pto #2'!$B$4:E$22,MATCH(F$5,'C. Gestión Pto #2'!$B$4:E$4,0),FALSE),0) -> 0 | G20: =IFERROR(VLOOKUP($B20&$C20,'C. Gestión Pto #2'!$B$4:F$22,MATCH(G$5,'C. Gestión Pto #2'!$B$4:F$4,0),FALSE),0) -> 0 | H20: =IFERROR(VLOOKUP($B20&$C20,'C. Gestión Pto #2'!$B$4:G$22,MATCH(H$5,'C. Gestión Pto #2'!$B$4:G$4,0),FALSE),0) -> 0 | I20: =IFERROR(VLOOKUP($B20&$C20,'C. Gestión Pto #2'!$B$4:H$22,MATCH(I$5,'C. Gestión Pto #2'!$B$4:H$4,0),FALSE),0) -> 0 | J20: =IFERROR(VLOOKUP($B20&$C20,'C. Gestión Pto #2'!$B$4:I$22,MATCH(J$5,'C. Gestión Pto #2'!$B$4:I$4,0),FALSE),0) -> 0 | L20: {=SUMPRODUCT($D20:$K20,TRANSPOSE('Indice CAC'!$E$12:$E$19))} -> 0 | N20: =IF(C20="MAT",SUMIF('Preventivo Costo CH2171 '!$A$61:$A$224,$B20,'Preventivo Costo CH2171 '!$I$61:$I$224),IF(C20="MO",SUMIF('Preventivo Costo CH2171 '!$A$61:$A$224,$B20,'Preventivo Costo CH2171 '!$L$61:$L$224),SUMIF('Preventivo Costo CH2171 '!$A$61:$A$224,$B20,'Preventivo Costo CH2171 '!$N$61:$N$224))) -> 29509901 | P20: =IF(O20=100%,0,IF(OR(L20<>0,N20),N20-L20)) -> 29509901 | Q20: =IF(OR(P20<0,N20),P20/N20,0%) -> 1 | R20: =IF(O20=100%,IF(OR(#REF!<>0,N20),N20-#REF!),0) -> 0
B21: Pintura | C21: MO | D21: =IFERROR(VLOOKUP($B21&$C21,'C. Gestión Pto #2'!$B$4:C$22,MATCH(D$5,'C. Gestión Pto #2'!$B$4:C$4,0),FALSE),0) -> 0 | E21: =IFERROR(VLOOKUP($B21&$C21,'C. Gestión Pto #2'!$B$4:D$22,MATCH(E$5,'C. Gestión Pto #2'!$B$4:D$4,0),FALSE),0) -> 0 | F21: =IFERROR(VLOOKUP($B21&$C21,'C. Gestión Pto #2'!$B$4:E$22,MATCH(F$5,'C. Gestión Pto #2'!$B$4:E$4,0),FALSE),0) -> 0 | G21: =IFERROR(VLOOKUP($B21&$C21,'C. Gestión Pto #2'!$B$4:F$22,MATCH(G$5,'C. Gestión Pto #2'!$B$4:F$4,0),FALSE),0) -> 0 | H21: =IFERROR(VLOOKUP($B21&$C21,'C. Gestión Pto #2'!$B$4:G$22,MATCH(H$5,'C. Gestión Pto #2'!$B$4:G$4,0),FALSE),0) -> 0 | I21: =IFERROR(VLOOKUP($B21&$C21,'C. Gestión Pto #2'!$B$4:H$22,MATCH(I$5,'C. Gestión Pto #2'!$B$4:H$4,0),FALSE),0) -> 0 | J21: =IFERROR(VLOOKUP($B21&$C21,'C. Gestión Pto #2'!$B$4:I$22,MATCH(J$5,'C. Gestión Pto #2'!$B$4:I$4,0),FALSE),0) -> 0 | L21: {=SUMPRODUCT($D21:$K21,TRANSPOSE('Indice CAC'!$E$12:$E$19))} -> 0 | N21: =IF(C21="MAT",SUMIF('Preventivo Costo CH2171 '!$A$61:$A$224,$B21,'Preventivo Costo CH2171 '!$I$61:$I$224),IF(C21="MO",SUMIF('Preventivo Costo CH2171 '!$A$61:$A$224,$B21,'Preventivo Costo CH2171 '!$L$61:$L$224),SUMIF('Preventivo Costo CH2171 '!$A$61:$A$224,$B21,'Preventivo Costo CH2171 '!$N$61:$N$224))) -> 60159232 | P21: =IF(O21=100%,0,IF(OR(L21<>0,N21),N21-L21)) -> 60159232 | Q21: =IF(OR(P21<0,N21),P21/N21,0%) -> 1 | R21: =IF(O21=100%,IF(OR(#REF!<>0,N21),N21-#REF!),0) -> 0
B22: Revestimiento | C22: MAT | D22: =IFERROR(VLOOKUP($B22&$C22,'C. Gestión Pto #2'!$B$4:C$22,MATCH(D$5,'C. Gestión Pto #2'!$B$4:C$4,0),FALSE),0) -> 0 | E22: =IFERROR(VLOOKUP($B22&$C22,'C. Gestión Pto #2'!$B$4:D$22,MATCH(E$5,'C. Gestión Pto #2'!$B$4:D$4,0),FALSE),0) -> 0 | F22: =IFERROR(VLOOKUP($B22&$C22,'C. Gestión Pto #2'!$B$4:E$22,MATCH(F$5,'C. Gestión Pto #2'!$B$4:E$4,0),FALSE),0) -> 0 | G22: =IFERROR(VLOOKUP($B22&$C22,'C. Gestión Pto #2'!$B$4:F$22,MATCH(G$5,'C. Gestión Pto #2'!$B$4:F$4,0),FALSE),0) -> 0 | H22: =IFERROR(VLOOKUP($B22&$C22,'C. Gestión Pto #2'!$B$4:G$22,MATCH(H$5,'C. Gestión Pto #2'!$B$4:G$4,0),FALSE),0) -> 0 | I22: =IFERROR(VLOOKUP($B22&$C22,'C. Gestión Pto #2'!$B$4:H$22,MATCH(I$5,'C. Gestión Pto #2'!$B$4:H$4,0),FALSE),0) -> 0 | J22: =IFERROR(VLOOKUP($B22&$C22,'C. Gestión Pto #2'!$B$4:I$22,MATCH(J$5,'C. Gestión Pto #2'!$B$4:I$4,0),FALSE),0) -> 0 | L22: {=SUMPRODUCT($D22:$K22,TRANSPOSE('Indice CAC'!$E$12:$E$19))} -> 0 | N22: =IF(C22="MAT",SUMIF('Preventivo Costo CH2171 '!$A$61:$A$224,$B22,'Preventivo Costo CH2171 '!$I$61:$I$224),IF(C22="MO",SUMIF('Preventivo Costo CH2171 '!$A$61:$A$224,$B22,'Preventivo Costo CH2171 '!$L$61:$L$224),SUMIF('Preventivo Costo CH2171 '!$A$61:$A$224,$B22,'Preventivo Costo CH2171 '!$N$61:$N$224))) -> 17485064 | P22: =IF(O22=100%,0,IF(OR(L22<>0,N22),N22-L22)) -> 17485064 | Q22: =IF(OR(P22<0,N22),P22/N22,0%) -> 1 | R22: =IF(O22=100%,IF(OR(#REF!<>0,N22),N22-#REF!),0) -> 0
B23: Revestimiento | C23: MO | D23: =IFERROR(VLOOKUP($B23&$C23,'C. Gestión Pto #2'!$B$4:C$22,MATCH(D$5,'C. Gestión Pto #2'!$B$4:C$4,0),FALSE),0) -> 0 | E23: =IFERROR(VLOOKUP($B23&$C23,'C. Gestión Pto #2'!$B$4:D$22,MATCH(E$5,'C. Gestión Pto #2'!$B$4:D$4,0),FALSE),0) -> 0 | F23: =IFERROR(VLOOKUP($B23&$C23,'C. Gestión Pto #2'!$B$4:E$22,MATCH(F$5,'C. Gestión Pto #2'!$B$4:E$4,0),FALSE),0) -> 0 | G23: =IFERROR(VLOOKUP($B23&$C23,'C. Gestión Pto #2'!$B$4:F$22,MATCH(G$5,'C. Gestión Pto #2'!$B$4:F$4,0),FALSE),0) -> 0 | H23: =IFERROR(VLOOKUP($B23&$C23,'C. Gestión Pto #2'!$B$4:G$22,MATCH(H$5,'C. Gestión Pto #2'!$B$4:G$4,0),FALSE),0) -> 0 | I23: =IFERROR(VLOOKUP($B23&$C23,'C. Gestión Pto #2'!$B$4:H$22,MATCH(I$5,'C. Gestión Pto #2'!$B$4:H$4,0),FALSE),0) -> 0 | J23: =IFERROR(VLOOKUP($B23&$C23,'C. Gestión Pto #2'!$B$4:I$22,MATCH(J$5,'C. Gestión Pto #2'!$B$4:I$4,0),FALSE),0) -> 0 | L23: {=SUMPRODUCT($D23:$K23,TRANSPOSE('Indice CAC'!$E$12:$E$19))} -> 0 | N23: =IF(C23="MAT",SUMIF('Preventivo Costo CH2171 '!$A$61:$A$224,$B23,'Preventivo Costo CH2171 '!$I$61:$I$224),IF(C23="MO",SUMIF('Preventivo Costo CH2171 '!$A$61:$A$224,$B23,'Preventivo Costo CH2171 '!$L$61:$L$224),SUMIF('Preventivo Costo CH2171 '!$A$61:$A$224,$B23,'Preventivo Costo CH2171 '!$N$61:$N$224))) -> 35274699 | P23: =IF(O23=100%,0,IF(OR(L23<>0,N23),N23-L23)) -> 35274699 | Q23: =IF(OR(P23<0,N23),P23/N23,0%) -> 1 | R23: =IF(O23=100%,IF(OR(#REF!<>0,N23),N23-#REF!),0) -> 0
B24: Eléctrico | C24: MAT | D24: =IFERROR(VLOOKUP($B24&$C24,'C. Gestión Pto #2'!$B$4:C$22,MATCH(D$5,'C. Gestión Pto #2'!$B$4:C$4,0),FALSE),0) -> 0 | E24: =IFERROR(VLOOKUP($B24&$C24,'C. Gestión Pto #2'!$B$4:D$22,MATCH(E$5,'C. Gestión Pto #2'!$B$4:D$4,0),FALSE),0) -> 0 | F24: =IFERROR(VLOOKUP($B24&$C24,'C. Gestión Pto #2'!$B$4:E$22,MATCH(F$5,'C. Gestión Pto #2'!$B$4:E$4,0),FALSE),0) -> 0 | G24: =IFERROR(VLOOKUP($B24&$C24,'C. Gestión Pto #2'!$B$4:F$22,MATCH(G$5,'C. Gestión Pto #2'!$B$4:F$4,0),FALSE),0) -> 0 | H24: =IFERROR(VLOOKUP($B24&$C24,'C. Gestión Pto #2'!$B$4:G$22,MATCH(H$5,'C. Gestión Pto #2'!$B$4:G$4,0),FALSE),0) -> 0 | I24: =IFERROR(VLOOKUP($B24&$C24,'C. Gestión Pto #2'!$B$4:H$22,MATCH(I$5,'C. Gestión Pto #2'!$B$4:H$4,0),FALSE),0) -> 0 | J24: =IFERROR(VLOOKUP($B24&$C24,'C. Gestión Pto #2'!$B$4:I$22,MATCH(J$5,'C. Gestión Pto #2'!$B$4:I$4,0),FALSE),0) -> 0 | L24: {=SUMPRODUCT($D24:$K24,TRANSPOSE('Indice CAC'!$E$12:$E$19))} -> 0 | N24: =IF(C24="MAT",SUMIF('Preventivo Costo CH2171 '!$A$61:$A$224,$B24,'Preventivo Costo CH2171 '!$I$61:$I$224),IF(C24="MO",SUMIF('Preventivo Costo CH2171 '!$A$61:$A$224,$B24,'Preventivo Costo CH2171 '!$L$61:$L$224),SUMIF('Preventivo Costo CH2171 '!$A$61:$A$224,$B24,'Preventivo Costo CH2171 '!$N$61:$N$224))) -> 37575178 | P24: =IF(O24=100%,0,IF(OR(L24<>0,N24),N24-L24)) -> 37575178 | Q24: =IF(OR(P24<0,N24),P24/N24,0%) -> 1 | R24: =IF(O24=100%,IF(OR(#REF!<>0,N24),N24-#REF!),0) -> 0
B25: Eléctrico | C25: MO | D25: =IFERROR(VLOOKUP($B25&$C25,'C. Gestión Pto #2'!$B$4:C$22,MATCH(D$5,'C. Gestión Pto #2'!$B$4:C$4,0),FALSE),0) -> 0 | E25: =IFERROR(VLOOKUP($B25&$C25,'C. Gestión Pto #2'!$B$4:D$22,MATCH(E$5,'C. Gestión Pto #2'!$B$4:D$4,0),FALSE),0) -> 0 | F25: =IFERROR(VLOOKUP($B25&$C25,'C. Gestión Pto #2'!$B$4:E$22,MATCH(F$5,'C. Gestión Pto #2'!$B$4:E$4,0),FALSE),0) -> 0 | G25: =IFERROR(VLOOKUP($B25&$C25,'C. Gestión Pto #2'!$B$4:F$22,MATCH(G$5,'C. Gestión Pto #2'!$B$4:F$4,0),FALSE),0) -> 0 | H25: =IFERROR(VLOOKUP($B25&$C25,'C. Gestión Pto #2'!$B$4:G$22,MATCH(H$5,'C. Gestión Pto #2'!$B$4:G$4,0),FALSE),0) -> 0 | I25: =IFERROR(VLOOKUP($B25&$C25,'C. Gestión Pto #2'!$B$4:H$22,MATCH(I$5,'C. Gestión Pto #2'!$B$4:H$4,0),FALSE),0) -> 0 | J25: =IFERROR(VLOOKUP($B25&$C25,'C. Gestión Pto #2'!$B$4:I$22,MATCH(J$5,'C. Gestión Pto #2'!$B$4:I$4,0),FALSE),0) -> 0 | L25: {=SUMPRODUCT($D25:$K25,TRANSPOSE('Indice CAC'!$E$12:$E$19))} -> 0 | N25: =IF(C25="MAT",SUMIF('Preventivo Costo CH2171 '!$A$61:$A$224,$B25,'Preventivo Costo CH2171 '!$I$61:$I$224),IF(C25="MO",SUMIF('Preventivo Costo CH2171 '!$A$61:$A$224,$B25,'Preventivo Costo CH2171 '!$L$61:$L$224),SUMIF('Preventivo Costo CH2171 '!$A$61:$A$224,$B25,'Preventivo Costo CH2171 '!$N$61:$N$224))) -> 64414415 | P25: =IF(O25=100%,0,IF(OR(L25<>0,N25),N25-L25)) -> 64414415 | Q25: =IF(OR(P25<0,N25),P25/N25,0%) -> 1 | R25: =IF(O25=100%,IF(OR(#REF!<>0,N25),N25-#REF!),0) -> 0
B26: Sanitaria | C26: MAT | D26: =IFERROR(VLOOKUP($B26&$C26,'C. Gestión Pto #2'!$B$4:C$22,MATCH(D$5,'C. Gestión Pto #2'!$B$4:C$4,0),FALSE),0) -> 0 | E26: =IFERROR(VLOOKUP($B26&$C26,'C. Gestión Pto #2'!$B$4:D$22,MATCH(E$5,'C. Gestión Pto #2'!$B$4:D$4,0),FALSE),0) -> 0 | F26: =IFERROR(VLOOKUP($B26&$C26,'C. Gestión Pto #2'!$B$4:E$22,MATCH(F$5,'C. Gestión Pto #2'!$B$4:E$4,0),FALSE),0) -> 0 | G26: =IFERROR(VLOOKUP($B26&$C26,'C. Gestión Pto #2'!$B$4:F$22,MATCH(G$5,'C. Gestión Pto #2'!$B$4:F$4,0),FALSE),0) -> 0 | H26: =IFERROR(VLOOKUP($B26&$C26,'C. Gestión Pto #2'!$B$4:G$22,MATCH(H$5,'C. Gestión Pto #2'!$B$4:G$4,0),FALSE),0) -> 0 | I26: =IFERROR(VLOOKUP($B26&$C26,'C. Gestión Pto #2'!$B$4:H$22,MATCH(I$5,'C. Gestión Pto #2'!$B$4:H$4,0),FALSE),0) -> 0 | J26: =IFERROR(VLOOKUP($B26&$C26,'C. Gestión Pto #2'!$B$4:I$22,MATCH(J$5,'C. Gestión Pto #2'!$B$4:I$4,0),FALSE),0) -> 0 | L26: {=SUMPRODUCT($D26:$K26,TRANSPOSE('Indice CAC'!$E$12:$E$19))} -> 0 | N26: =IF(C26="MAT",SUMIF('Preventivo Costo CH2171 '!$A$61:$A$224,$B26,'Preventivo Costo CH2171 '!$I$61:$I$224),IF(C26="MO",SUMIF('Preventivo Costo CH2171 '!$A$61:$A$224,$B26,'Preventivo Costo CH2171 '!$L$61:$L$224),SUMIF('Preventivo Costo CH2171 '!$A$61:$A$224,$B26,'Preventivo Costo CH2171 '!$N$61:$N$224))) -> 25266705 | P26: =IF(O26=100%,0,IF(OR(L26<>0,N26),N26-L26)) -> 25266705 | Q26: =IF(OR(P26<0,N26),P26/N26,0%) -> 1 | R26: =IF(O26=100%,IF(OR(#REF!<>0,N26),N26-#REF!),0) -> 0
B27: Sanitaria | C27: MO | D27: =IFERROR(VLOOKUP($B27&$C27,'C. Gestión Pto #2'!$B$4:C$22,MATCH(D$5,'C. Gestión Pto #2'!$B$4:C$4,0),FALSE),0) -> 0 | E27: =IFERROR(VLOOKUP($B27&$C27,'C. Gestión Pto #2'!$B$4:D$22,MATCH(E$5,'C. Gestión Pto #2'!$B$4:D$4,0),FALSE),0) -> 0 | F27: =IFERROR(VLOOKUP($B27&$C27,'C. Gestión Pto #2'!$B$4:E$22,MATCH(F$5,'C. Gestión Pto #2'!$B$4:E$4,0),FALSE),0) -> 0 | G27: =IFERROR(VLOOKUP($B27&$C27,'C. Gestión Pto #2'!$B$4:F$22,MATCH(G$5,'C. Gestión Pto #2'!$B$4:F$4,0),FALSE),0) -> 0 | H27: =IFERROR(VLOOKUP($B27&$C27,'C. Gestión Pto #2'!$B$4:G$22,MATCH(H$5,'C. Gestión Pto #2'!$B$4:G$4,0),FALSE),0) -> 0 | I27: =IFERROR(VLOOKUP($B27&$C27,'C. Gestión Pto #2'!$B$4:H$22,MATCH(I$5,'C. Gestión Pto #2'!$B$4:H$4,0),FALSE),0) -> 0 | J27: =IFERROR(VLOOKUP($B27&$C27,'C. Gestión Pto #2'!$B$4:I$22,MATCH(J$5,'C. Gestión Pto #2'!$B$4:I$4,0),FALSE),0) -> 0 | L27: {=SUMPRODUCT($D27:$K27,TRANSPOSE('Indice CAC'!$E$12:$E$19))} -> 0 | N27: =IF(C27="MAT",SUMIF('Preventivo Costo CH2171 '!$A$61:$A$224,$B27,'Preventivo Costo CH2171 '!$I$61:$I$224),IF(C27="MO",SUMIF('Preventivo Costo CH2171 '!$A$61:$A$224,$B27,'Preventivo Costo CH2171 '!$L$61:$L$224),SUMIF('Preventivo Costo CH2171 '!$A$61:$A$224,$B27,'Preventivo Costo CH2171 '!$N$61:$N$224))) -> 52462847 | P27: =IF(O27=100%,0,IF(OR(L27<>0,N27),N27-L27)) -> 52462847 | Q27: =IF(OR(P27<0,N27),P27/N27,0%) -> 1 | R27: =IF(O27=100%,IF(OR(#REF!<>0,N27),N27-#REF!),0) -> 0
B28: Termomecánica | D28: =IFERROR(VLOOKUP($B28&$C28,'C. Gestión Pto #2'!$B$4:C$22,MATCH(D$5,'C. Gestión Pto #2'!$B$4:C$4,0),FALSE),0) -> 0 | E28: =IFERROR(VLOOKUP($B28&$C28,'C. Gestión Pto #2'!$B$4:D$22,MATCH(E$5,'C. Gestión Pto #2'!$B$4:D$4,0),FALSE),0) -> 0 | F28: =IFERROR(VLOOKUP($B28&$C28,'C. Gestión Pto #2'!$B$4:E$22,MATCH(F$5,'C. Gestión Pto #2'!$B$4:E$4,0),FALSE),0) -> 0 | G28: =IFERROR(VLOOKUP($B28&$C28,'C. Gestión Pto #2'!$B$4:F$22,MATCH(G$5,'C. Gestión Pto #2'!$B$4:F$4,0),FALSE),0) -> 0 | H28: =IFERROR(VLOOKUP($B28&$C28,'C. Gestión Pto #2'!$B$4:G$22,MATCH(H$5,'C. Gestión Pto #2'!$B$4:G$4,0),FALSE),0) -> 0 | I28: =IFERROR(VLOOKUP($B28&$C28,'C. Gestión Pto #2'!$B$4:H$22,MATCH(I$5,'C. Gestión Pto #2'!$B$4:H$4,0),FALSE),0) -> 0 | J28: =IFERROR(VLOOKUP($B28&$C28,'C. Gestión Pto #2'!$B$4:I$22,MATCH(J$5,'C. Gestión Pto #2'!$B$4:I$4,0),FALSE),0) -> 0 | L28: {=SUMPRODUCT($D28:$K28,TRANSPOSE('Indice CAC'!$E$12:$E$19))} -> 0 | N28: =IF(C28="MAT",SUMIF('Preventivo Costo CH2171 '!$A$61:$A$224,$B28,'Preventivo Costo CH2171 '!$I$61:$I$224),IF(C28="MO",SUMIF('Preventivo Costo CH2171 '!$A$61:$A$224,$B28,'Preventivo Costo CH2171 '!$L$61:$L$224),SUMIF('Preventivo Costo CH2171 '!$A$61:$A$224,$B28,'Preventivo Costo CH2171 '!$N$61:$N$224))) -> 19100000 | P28: =IF(O28=100%,0,IF(OR(L28<>0,N28),N28-L28)) -> 19100000 | Q28: =IF(OR(P28<0,N28),P28/N28,0%) -> 1
B29: Equipos | D29: =IFERROR(VLOOKUP($B29&$C29,'C. Gestión Pto #2'!$B$4:C$22,MATCH(D$5,'C. Gestión Pto #2'!$B$4:C$4,0),FALSE),0) -> 0 | E29: =IFERROR(VLOOKUP($B29&$C29,'C. Gestión Pto #2'!$B$4:D$22,MATCH(E$5,'C. Gestión Pto #2'!$B$4:D$4,0),FALSE),0) -> 0 | F29: =IFERROR(VLOOKUP($B29&$C29,'C. Gestión Pto #2'!$B$4:E$22,MATCH(F$5,'C. Gestión Pto #2'!$B$4:E$4,0),FALSE),0) -> 0 | G29: =IFERROR(VLOOKUP($B29&$C29,'C. Gestión Pto #2'!$B$4:F$22,MATCH(G$5,'C. Gestión Pto #2'!$B$4:F$4,0),FALSE),0) -> 0 | H29: =IFERROR(VLOOKUP($B29&$C29,'C. Gestión Pto #2'!$B$4:G$22,MATCH(H$5,'C. Gestión Pto #2'!$B$4:G$4,0),FALSE),0) -> 0 | I29: =IFERROR(VLOOKUP($B29&$C29,'C. Gestión Pto #2'!$B$4:H$22,MATCH(I$5,'C. Gestión Pto #2'!$B$4:H$4,0),FALSE),0) -> 0 | J29: =IFERROR(VLOOKUP($B29&$C29,'C. Gestión Pto #2'!$B$4:I$22,MATCH(J$5,'C. Gestión Pto #2'!$B$4:I$4,0),FALSE),0) -> 0 | L29: {=SUMPRODUCT($D29:$K29,TRANSPOSE('Indice CAC'!$E$12:$E$19))} -> 0 | N29: =IF(C29="MAT",SUMIF('Preventivo Costo CH2171 '!$A$61:$A$224,$B29,'Preventivo Costo CH2171 '!$I$61:$I$224),IF(C29="MO",SUMIF('Preventivo Costo CH2171 '!$A$61:$A$224,$B29,'Preventivo Costo CH2171 '!$L$61:$L$224),SUM('Preventivo Costo CH2171 '!$M$61:$M$224))) -> 9840752.7 | P29: =IF(O29=100%,0,IF(OR(L29<>0,N29),N29-L29)) -> 9840752.7 | Q29: =IF(OR(P29<0,N29),P29/N29,0%) -> 1 | R29: =IF(O29=100%,IF(OR(#REF!<>0,N29),N29-#REF!),0) -> 0
B30: Gastos Generales Obra | D30: =IFERROR(VLOOKUP($B30&$C30,'C. Gestión Pto #2'!$B$4:C$22,MATCH(D$5,'C. Gestión Pto #2'!$B$4:C$4,0),FALSE),0) -> 0 | E30: =IFERROR(VLOOKUP($B30&$C30,'C. Gestión Pto #2'!$B$4:D$22,MATCH(E$5,'C. Gestión Pto #2'!$B$4:D$4,0),FALSE),0) -> 0 | F30: =IFERROR(VLOOKUP($B30&$C30,'C. Gestión Pto #2'!$B$4:E$22,MATCH(F$5,'C. Gestión Pto #2'!$B$4:E$4,0),FALSE),0) -> 0 | G30: =IFERROR(VLOOKUP($B30&$C30,'C. Gestión Pto #2'!$B$4:F$22,MATCH(G$5,'C. Gestión Pto #2'!$B$4:F$4,0),FALSE),0) -> 0 | H30: =IFERROR(VLOOKUP($B30&$C30,'C. Gestión Pto #2'!$B$4:G$22,MATCH(H$5,'C. Gestión Pto #2'!$B$4:G$4,0),FALSE),0) -> 0 | I30: =IFERROR(VLOOKUP($B30&$C30,'C. Gestión Pto #2'!$B$4:H$22,MATCH(I$5,'C. Gestión Pto #2'!$B$4:H$4,0),FALSE),0) -> 0 | J30: =IFERROR(VLOOKUP($B30&$C30,'C. Gestión Pto #2'!$B$4:I$22,MATCH(J$5,'C. Gestión Pto #2'!$B$4:I$4,0),FALSE),0) -> 0 | L30: {=SUMPRODUCT($D30:$K30,TRANSPOSE('Indice CAC'!$E$12:$E$19))} -> 0 | N30: =IF(C30="MAT",SUMIF('Preventivo Costo CH2171 '!$A$61:$A$224,$B30,'Preventivo Costo CH2171 '!$I$61:$I$224),IF(C30="MO",SUMIF('Preventivo Costo CH2171 '!$A$61:$A$224,$B30,'Preventivo Costo CH2171 '!$L$61:$L$224),SUMIF('Preventivo Costo CH2171 '!$A$61:$A$224,$B30,'Preventivo Costo CH2171 '!$N$61:$N$224))) -> 2405164.5 | P30: =IF(O30=100%,0,IF(OR(L30<>0,N30),N30-L30)) -> 2405164.5 | Q30: =IF(OR(P30<0,N30),P30/N30,0%) -> 1
B31: Total Egresos de Obra | D31: =SUM(D13:D29) -> 0 | E31: =SUM(E13:E29) -> 0 | F31: =SUM(F13:F29) -> 0 | G31: =SUM(G13:G29) -> 0 | H31: =SUM(H13:H29) -> 0 | I31: =SUM(I13:I29) -> 0 | J31: =SUM(J13:J29) -> 0 | L31: =SUM(L13:L29) -> 0 | N31: =SUM(N13:N30) -> 6.9307427e+08 | P31: =IF(O31=100%,0,IF(OR(L31<>0,N31),N31-L31)) -> 6.9307427e+08 | Q31: =IF(OR(P31<0,N31),P31/N31,0%) -> 1 | R31: =SUM(R16:R29) -> 0
B33: Resultado Operativo | D33: =SUM(D8,D10,-D31) -> 0 | E33: =SUM(E8,E10,-E31) -> 0 | F33: =SUM(F8,F10,-F31) -> 0 | G33: =SUM(G8,G10,-G31) -> 0 | H33: =SUM(H8,H10,-H31) -> 0 | I33: =SUM(I8,I10,-I31) -> 0 | J33: =SUM(J8,J10,-J31) -> 0 | L33: =SUM(L8,-L31) -> 0 | N33: =SUM(N8,-N31) -> -81980118
B34: Resultado Acumulado | D34: =D33 -> 0 | E34: =E33+D34 -> 0 | F34: =F33+E34 -> 0 | G34: =G33+F34 -> 0 | H34: =H33+G34 -> 0 | I34: =I33+H34 -> 0 | J34: =J33+I34 -> 0

Sheet Facturacion
A1: Obra:
B3: O.C. | C3: COD | D3: Descripcion | E3: Importe | F3: IVA | G3: Total | K3: 0.2 | L3: =E4*K3 -> 78062160 | M3: =L3 -> 78062160 | N3: a Facturar
B4: Pto 1 | C4: P1B65 | D4: Presupuesto 1 Preliminar Y Hormigon | E4: ='Preventivo Vta CH2171 '!G59*65% -> 3.903108e+08 | F4: =+E4*0.105 -> 40982634 | G4: =E4+F4 -> 4.3129343e+08 | M4: =SUM(E9:E10) -> 56902642 | N4: Facturado
B5: Pto 2 | C5: P2B65 | D5: Presupuesto 2 - Albañilería/Inst. | E5: ='Preventivo Vta CH2171 '!G228*65% -> 6.1109415e+08 | F5: =+E5*0.105 -> 64164886 | G5: =E5+F5 -> 6.7525904e+08 | M5: =M3-M4 -> 21159518 | N5: Pendiente
D6: Totales | E6: =SUM(E4:E5) -> 1.001405e+09 | F6: =SUM(F4:F5) -> 1.0514752e+08 | G6: =SUM(G4:G5) -> 1.1065525e+09
K7: Según Banco
A8: Fecha | B8: Factura | C8: O.C. | D8: Descripcion | E8: Importe | F8: CAC | G8: IVA | H8: Total | L8: Retenciones | M8: Total
A9: 46111 | B9: 0003-00000834 | C9: P1B65 | D9: Presupuesto 1 - Anticipo | E9: =35000000/('Indice CAC'!C15/'Indice CAC'!C6) -> 29725261 | F9: =E9*(('Indice CAC'!$C$15/'Indice CAC'!$C$6)-1) -> 5274739.1 | G9: =(E9+F9)*0.105 -> 3675000 | H9: =SUM(E9:G9) -> 38675000 | I9: Pto 1
A10: 46136 | B10: 0003-00000852 | C10: P1B65 | D10: Presupuesto 1 - Anticipo | E10: =32000000/('Indice CAC'!C15/'Indice CAC'!C6) -> 27177381 | F10: =E10*(('Indice CAC'!$C$15/'Indice CAC'!$C$6)-1) -> 4822618.6 | G10: =(F10+E10)*0.105 -> 3360000 | H10: =SUM(E10:G10) -> 35360000 | I10: Pto 1
A11: 46163 | B11: 0003-00000564 | C11: P1B65 | D11: Presupuesto 1 - Anticipo | E11: =M5 -> 21159518 | F11: =E11*(('Indice CAC'!C15/'Indice CAC'!C6)-1) -> 3754750.4 | G11: =(F11+E11)*0.105 -> 2615998.2 | H11: =SUM(E11:G11) -> 27530267 | I11: Pto 1
G12: =(F12+E12)*0.105 -> 0 | H12: =SUM(E12:G12) -> 0 | I12: Pto 1
G13: =(F13+E13)*0.105 -> 0 | H13: =SUM(E13:G13) -> 0 | I13: Pto 1
G14: =(F14+E14)*0.105 -> 0 | H14: =SUM(E14:G14) -> 0 | I14: Pto 2
G15: =SUM(E15:F15)*0.105 -> 0 | H15: =SUM(E15:G15) -> 0 | I15: Pto 1
G16: =SUM(E16:F16)*0.105 -> 0 | H16: =SUM(E16:G16) -> 0 | I16: Pto 2
G17: =SUM(E17:F17)*0.105 -> 0 | H17: =SUM(E17:G17) -> 0 | I17: Pto 1
G18: =(F18+E18)*0.105 -> 0 | H18: =SUM(E18:G18) -> 0 | I18: Pto 1
G19: =(F19+E19)*0.105 -> 0 | H19: =SUM(E19:G19) -> 0 | I19: Pto 1
G20: =(F20+E20)*0.105 -> 0 | H20: =SUM(E20:G20) -> 0 | I20: Pto 2
G21: =(F21+E21)*0.105 -> 0 | H21: =SUM(E21:G21) -> 0 | I21: Pto 1
G22: =(F22+E22)*0.105 -> 0 | H22: =SUM(E22:G22) -> 0 | I22: Pto 2
G23: =(F23+E23)*0.105 -> 0 | H23: =SUM(E23:G23) -> 0 | I23: Pto 1
G24: =(F24+E24)*0.105 -> 0 | H24: =SUM(E24:G24) -> 0 | I24: Pto 2
G25: =(F25+E25)*0.105 -> 0 | H25: =SUM(E25:G25) -> 0
G26: =(F26+E26)*0.105 -> 0 | H26: =SUM(E26:G26) -> 0
G27: =(F27+E27)*0.105 -> 0 | H27: =SUM(E27:G27) -> 0
G28: =(F28+E28)*0.105 -> 0 | H28: =SUM(E28:G28) -> 0
G29: =(F29+E29)*0.105 -> 0 | H29: =SUM(E29:G29) -> 0
G30: =(F30+E30)*0.105 -> 0 | H30: =SUM(E30:G30) -> 0
G31: =(F31+E31)*0.105 -> 0 | H31: =SUM(E31:G31) -> 0
G32: =(F32+E32)*0.105 -> 0 | H32: =SUM(E32:G32) -> 0
G33: =(F33+E33)*0.105 -> 0 | H33: =SUM(E33:G33) -> 0
H35: =SUM(E35:G35) -> 0
D36: Totales | E36: =SUM(E9:E35) -> 78062160 | F36: =SUM(F9:F35) -> 13852108 | G36: =SUM(G9:G35) -> 9650998.2 | H36: =SUM(H9:H35) -> 1.0156527e+08 | M36: =SUM(L9:M35) -> 0
H38: 1400
H39: =+H36/H38 -> 72546.619 | L39: Por Cobrar | M39: =+M36-H36 -> -1.0156527e+08
D40: Total Presupuestado | E40: =SUM(E4:E5) -> 1.001405e+09
D41: Total Facturado | E41: =SUMIF($B$9:$B$22,"0003-*",$E$9:$E$22) -> 78062160
D42: Total Sin Facturar | E42: =SUMIF($B$9:$B$22,"",$E$9:$E$22) -> 0
D43: Pendiente de Facturar | E43: =E40-E41-E42 -> 9.2334279e+08
C46: Facturación Según O. C. Aprobadas
C48: O.C. | D48: Descripcion | E48: Facturado | F48: Pendiente
C49: P1B65 | D49: Presupuesto 1 Preliminar Y Hormigon | E49: =SUMIF($C$9:$C$35,C49,$E$9:$E$35) -> 78062160 | F49: =SUMIF($C$4:$C$5,C49,$E$4:$E$5)-E49 -> 3.1224864e+08
C50: P2B65 | D50: Presupuesto 2 - Albañilería/Inst. | E50: =SUMIF($C$9:$C$35,C50,$E$9:$E$35) -> 0 | F50: =SUMIF($C$4:$C$5,C50,$E$4:$E$5)-E50 -> 6.1109415e+08
E52: =SUM(E49:E51) -> 78062160 | F52: =SUM(F49:F51) -> 9.2334279e+08

Sheet Certificados
A1: Obra: CHIVILCOY 2171
I2: ='Indice CAC'!C6 -> 16521.3 | K2: CAC Base 05-2025
B3: O.C. | C3: COD | D3: Descripcion | E3: Importe | F3: IVA | G3: Total
B4: Pto 1 | C4: P1B65 | D4: Presupuesto 1 Preliminar Y Hormigon | E4: ='Preventivo Vta CH2171 '!G59*65% -> 3.903108e+08 | F4: =+E4*0.105 -> 40982634 | G4: =E4+F4 -> 4.3129343e+08 | J4: 0.2 | K4: Anticipo Pto. 1 | L4: Para revisar - considerando que el fideicomiso realizará compras de material grandes
B5: Pto 1 | C5: P1N35 | D5: Presupuesto 1 Preliminar Y Hormigon | E5: ='Preventivo Vta CH2171 '!G59*35% -> 2.1016735e+08 | F5: 0 | G5: =E5+F5 -> 2.1016735e+08
B6: Pto 2 | C6: P2B65 | D6: Presupuesto 2 - Albañilería/Inst. | E6: ='Preventivo Vta CH2171 '!G228*65% -> 6.1109415e+08 | F6: =+E6*0.105 -> 64164886 | G6: =E6+F6 -> 6.7525904e+08 | J6: 0.4 | K6: Anticipo Pto. 2
B7: Pto 2 | C7: P2N35 | D7: Presupuesto 2 - Albañilería/Inst. | E7: ='Preventivo Vta CH2171 '!G228*35% -> 3.290507e+08 | F7: 0 | G7: =E7+F7 -> 3.290507e+08
B8: Gdes | C8: GDN | D8: Presupuesto Gtos Desarrollo | E8: ='AING Gtos Desarrollo'!AF19 -> 104981.39 | F8: 0 | G8: =E8+F8 -> 104981.39
D9: Totales | E9: =SUM(E4:E7) -> 1540623004 | F9: =SUM(F4:F7) -> 1.0514752e+08 | G9: =SUM(G4:G7) -> 1.6457705e+09
K10: CERT. - B | L10: Fecha | M10: Pagos
A11: Fecha | B11: O.C. | C11: COD | D11: Descripcion | E11: Importe | F11: CAC | G11: IVA | H11: Total | J11: usd | K11: =SUM(K12:K21) -> 65481.126
A12: 46082 | B12: Pto 1 | C12: P1B65 | D12: Presupuesto 1 - Anticipo | E12: =E4*$J$4 -> 78062160 | F12: =E12*((_xlfn.XLOOKUP(DATE(2026,2,1),'Indice CAC'!$B$6:$B$24,'Indice CAC'!$C$6:$C$24)/$I$2)-1) -> 13852108 | G12: =(F12+E12)*0.105 -> 9650998.2 | H12: =SUM(E12:G12) -> 1.0156527e+08
A13: 46082 | B13: Pto 1 | C13: P1N35 | D13: Presupuesto 1 - Anticipo | E13: =E5*$J$4 -> 42033471 | F13: =E13*((_xlfn.XLOOKUP(DATE(2026,2,1),'Indice CAC'!$B$6:$B$24,'Indice CAC'!$C$6:$C$24)/$I$2)-1) -> 7458827.5 | G13: 0 | H13: =SUM(E13:G13) -> 49492298 | J13: =_xlfn.XLOOKUP($A13,'TC USD MEP'!B:B,'TC USD MEP'!C:C,0) -> 1419.54 | K13: =$H13/$J13 -> 34865.026
A14: 46082 | B14: Gdes | C14: GDN | D14: Presupuesto Gtos Des. - Cert. #1 | E14: 0 | F14: 0 | G14: 0 | H14: =SUM(E14:G14) -> 0 | J14: =_xlfn.XLOOKUP($A14,'TC USD MEP'!B:B,'TC USD MEP'!C:C,0) -> 1419.54 | K14: =_xlfn.XLOOKUP($A14,'AING Gtos Desarrollo'!$K$5:$AE$5,'AING Gtos Desarrollo'!$K$19:$AE$19,0) -> 5249.0695
A15: 46142 | B15: Pto 1 | C15: P1B65 | D15: Presupuesto 1 - Cert. #1 | E15: =51205725.464*65% -> 33283722 | F15: =E15*((_xlfn.XLOOKUP($A12,'Indice CAC'!$B$6:$B$24,'Indice CAC'!$C$6:$C$24)/$I$2)-1) -> 6547230.9 | G15: =(F15+E15)*0.105 -> 4182250 | H15: =SUM(E15:G15) -> 44013203
A16: 46142 | B16: Pto 1 | C16: P1N35 | D16: Presupuesto 1 - Cert. #1 | E16: =51205725.464*35% -> 17922004 | F16: =E16*((_xlfn.XLOOKUP($A13,'Indice CAC'!$B$6:$B$24,'Indice CAC'!$C$6:$C$24)/$I$2)-1) -> 3525432 | G16: 0 | H16: =SUM(E16:G16) -> 21447436 | J16: =_xlfn.XLOOKUP($A16,'TC USD MEP'!B:B,'TC USD MEP'!C:C,0) -> 1442.43 | K16: =$H16/$J16 -> 14868.961
A17: 46142 | B17: Gdes | C17: GDN | D17: Presupuesto Gtos Des. - Cert. #2 | G17: 0 | H17: =SUM(E17:G17) -> 0 | J17: =_xlfn.XLOOKUP($A17,'TC USD MEP'!B:B,'TC USD MEP'!C:C,0) -> 1442.43 | K17: =_xlfn.XLOOKUP(EOMONTH($A17,-1)+1,'AING Gtos Desarrollo'!$K$5:$AE$5,'AING Gtos Desarrollo'!$K$19:$AE$19,0) -> 5249.0695
A18: 46175 | B18: Pto 1 | C18: P1B65 | D18: Presupuesto 1 - Cert. #2 | E18: =55124362*0.65 -> 35830835 | F18: =13252495*0.65 -> 8614121.8 | G18: =(F18+E18)*0.105 -> 4666720.5 | H18: =SUM(E18:G18) -> 49111678
A19: 46175 | B19: Pto 1 | C19: P1N35 | D19: Presupuesto 1 - Cert. #2 | E19: =55124362*0.35 -> 19293527 | F19: =13252495*0.35 -> 4638373.2 | G19: 0 | H19: =SUM(E19:G19) -> 23931900
A20: 46175 | B20: Gdes | C20: GDN | D20: Presupuesto Gtos Des. - Cert. #3 | K20: 5249
D22: Totales | E22: =SUM(E12:E21) -> 2.2642572e+08 | F22: =SUM(F12:F21) -> 44636094 | G22: =SUM(G12:G21) -> 18499969 | H22: =SUM(H12:H21) -> 2.8956178e+08 | K22: =SUM(K12:K21) -> 65481.126 | M22: =SUM(M12:M21) -> 0
K24: Por Cobrar - Contab. B | M24: =K22-M22 -> 65481.126
D25: Total Presupuestado | E25: =SUM(E4:E7) -> 1540623004
D26: Total Facturado | E26: =SUMIF($B$12:$B$21,"0003-*",$E$12:$E$21) -> 0 | M26: 52882.143
D27: Total Sin Facturar | E27: =SUMIF($B$12:$B$21,"",$E$12:$E$21) -> 0 | M27: =+M24+M26 -> 118363.27
D28: Pendiente de Facturar | E28: =E25-E26-E27 -> 1540623004 | M28: =20000000/1400 -> 14285.714
M29: =M27+M28 -> 132648.98
C30: O.C. | D30: Descripcion | E30: Certificado | F30: Pendiente | G30: Facturable | M30: 150000
C31: P1B65 | D31: Presupuesto 1 Preliminar Y Hormigon | E31: =SUMIF($C$12:$C$21,C31,$E$12:$E$21) -> 1.4717672e+08 | F31: =SUMIF($C$4:$C$7,C31,$E$4:$E$7)-E31 -> 2.4313408e+08 | G31: =+E31 -> 1.4717672e+08 | M31: =+M29-M30 -> -17351.017
C32: P1N35 | D32: Presupuesto 1 Preliminar Y Hormigon | E32: =SUMIF($C$12:$C$21,C32,$E$12:$E$21) -> 79249001 | F32: =SUMIF($C$4:$C$7,C32,$E$4:$E$7)-E32 -> 1.3091835e+08
C33: P2B65 | D33: Presupuesto 2 - Albañilería/Inst. | E33: =SUMIF($C$12:$C$21,C33,$E$12:$E$21) -> 0 | F33: =SUMIF($C$4:$C$7,C33,$E$4:$E$7)-E33 -> 6.1109415e+08 | G33: =+E33 -> 0
C34: P2N35 | D34: Presupuesto 2 - Albañilería/Inst. | E34: =SUMIF($C$12:$C$21,C34,$E$12:$E$21) -> 0 | F34: =SUMIF($C$4:$C$7,C34,$E$4:$E$7)-E34 -> 3.290507e+08
E37: =SUM(E31:E36) -> 2.2642572e+08 | F37: =SUM(F31:F36) -> 1.3141973e+09 | G37: =SUM(G31:G36) -> 1.4717672e+08
C40: O.C. | D40: Descripcion | E40: Certificado | F40: Pendiente | G40: Facturable
C41: GDN | D41: Presupuesto Gtos Desarrollo | E41: =SUMIF($C$12:$C$21,C41,$K$12:$K$21) -> 15747.139 | F41: =SUMIF($C$4:$C$8,C41,$E$4:$E$8)-E41 -> 89234.251
E42: =SUMIF($B$12:$B$21,C42,$E$12:$E$21) -> 0 | F42: =SUMIF($C$4:$C$7,C42,$E$4:$E$7)-E42 -> 0
E44: =SUM(E41:E43) -> 15747.139 | F44: =SUM(F41:F43) -> 89234.251 | G44: =SUM(G41:G43) -> 0

Sheet Contratistas
A1: CHIVILCOY
A2: CONTRATISTAS
A4: CLAUDIO BALACLAV | D4: GESTOR ELECTRICO
A5: Fecha | B5: Observacion | C5: Pagos | D5: CAC | E5: Presupuesto
B6: Presupuesto Aprobado | E6: 1040000
A7: 46079 | B7: Anticipo | C7: 520000
A8: 46125 | B8: Saldo | C8: 520000
C10: =SUM(C7:C9) -> 1040000 | D10: =SUM(D9:D9) -> 0 | E10: =SUM(E6:E9) -> 1040000 | F10: =+E10-C10 -> 0
A12: ALEJANDRO ARDILES | D12: AGRIMENSOR
A13: Fecha | B13: Observacion | C13: Pagos | D13: CAC | E13: Presupuesto
A14: 46066 | B14: Presupuesto Aprobado | E14: 680000
A15: 46086 | B15: Alejandro Ardiles - Agrimensor | C15: 380000
A16: 46106 | B16: Alejandro Ardiles - Agrimensor | C16: 350000
C18: =SUM(C15:C17) -> 730000 | D18: =SUM(D17:D17) -> 0 | E18: =SUM(E14:E17) -> 680000 | F18: =+E18-C18 -> -50000
D20: MICROPILOTES | G20: 0.23152321 | H20: 0.76847679
A21: Fecha | B21: Observacion | C21: Pagos | D21: CAC | E21: Presupuesto | G21: MAT | H21: MO
A22: 46084 | B22: Presupuesto Aprobado | E22: 55937600
A23: 46094 | B23: Anticipo 30% - Fact. 1-1478 | C23: 16781280
A24: 46142 | B24: Cert. #1 - Efectivo | C24: 10000000
A25: 46142 | B25: Cert. #1 - Fact. 1-1506 | C25: =16837217.6-C24 -> 6837217.6 | D25: 492422.92
A26: 46163 | B26: Cert. #2 - Fact. 1-1513 | C26: =17791840-D26 -> 17139093 | D26: 652746.66 | G26: =SUM(C26:D26)*G20 -> 4119223.9 | H26: =SUM(C26:D26)*H20 -> 13672616
A27: 46162 | B27: Cert. #2 - Efectivo | C27: 5000000 | H27: =SUM(C27:D27)*H20 -> 3842383.9
A28: 46162 | B28: Descuento | C28: 180009
C30: =SUM(C22:C29) -> 55937600 | D30: =SUM(D29:D29) -> 0 | E30: =SUM(E22:E29) -> 55937600 | F30: =+E30-C30 -> 0.060000002
A32: CELSI VIAL
A33: Fecha | B33: Observacion | C33: Pagos | D33: CAC | E33: Presupuesto
B34: Certificado | C34: 1310000 | E34: 1310000
C36: =SUM(C34:C35) -> 1310000 | D36: =SUM(D35:D35) -> 0 | E36: =SUM(E34:E35) -> 1310000 | F36: =+E36-C36 -> 0

Sheet Horm M.O.
A1: MANO DE OBRA | O1: T | P1: Trabajado
A2: Costo Real | O2: P | P2: Presupuesto
C4: Días x Quincena | H4: Especializado | I4: Oficial | J4: 1/2 Oficial | K4: Ayudante | L4: Total | M4: Subtotal | P4: Personal por día
C5: ESP | D5: OF | E5: 1/2 Of | F5: Ayu | P5: Días | Q5: ESP | R5: OF | S5: 1/2 Of | T5: Ayu | U5: Tot
H6: 117452.66 | I6: 97866.77 | J6: 83614.94 | K6: 78291.042 | L6: 46023
H7: 119406.33 | I7: 99479.558 | J7: 84948.749 | K7: 79490.602 | L7: 46054
H8: 122445.79 | I8: 102029.07 | J8: 87100.47 | K8: 81453.719 | L8: 46082
H9: 128780.87 | I9: 106995.86 | J9: 91265.842 | K9: 85242.812 | L9: 46113
H10: 131727.59 | I10: 109491.85 | J10: 93345.065 | K10: 87239.917 | L10: 46143
A11: 46054 | B11: 1Q | C11: 0 | D11: 0 | E11: 0 | F11: 5 | H11: =C11*H$7 -> 0 | I11: =D11*I$7 -> 0 | J11: =E11*J$7 -> 0 | K11: =F11*K$7 -> 397453.01 | L11: =SUM(H11:K11) -> 397453.01 | M11: =L11 -> 397453.01 | N11: T | P11: 13 | Q11: =C11/P11 -> 0 | R11: =D11/P11 -> 0 | S11: =E11/P11 -> 0 | T11: =F11/P11 -> 0.38461538 | U11: =SUM(Q11:T11) -> 0.38461538
A12: 46054 | B12: 2Q | C12: 0 | D12: 0 | E12: 0 | F12: 0 | H12: =C12*H$7 -> 0 | I12: =D12*I$7 -> 0 | J12: =E12*J$7 -> 0 | K12: =F12*K$7 -> 0 | L12: =SUM(H12:K12) -> 0 | M12: =L12 -> 0 | N12: T | P12: 14 | Q12: =C12/P12 -> 0 | R12: =D12/P12 -> 0 | S12: =E12/P12 -> 0 | T12: =F12/P12 -> 0 | U12: =SUM(Q12:T12) -> 0
A13: 46082 | B13: 1Q | C13: 12.5 | D13: 21 | E13: 0 | F13: 0 | H13: =C13*H$8 -> 1530572.4 | I13: =D13*I$8 -> 2142610.4 | J13: =E13*J$8 -> 0 | K13: =F13*K$8 -> 0 | L13: =SUM(H13:K13) -> 3673182.8 | M13: =L13 -> 3673182.8 | N13: T | P13: 12 | Q13: =C13/P13 -> 1.0416667 | R13: =D13/P13 -> 1.75 | S13: =E13/P13 -> 0 | T13: =F13/P13 -> 0 | U13: =SUM(Q13:T13) -> 2.7916667
A14: 46082 | B14: 2Q | C14: 7 | D14: 17.5 | E14: 0 | F14: 0 | H14: =C14*H$8 -> 857120.53 | I14: =D14*I$8 -> 1785508.7 | J14: =E14*J$8 -> 0 | K14: =F14*K$8 -> 0 | L14: =SUM(H14:K14) -> 2642629.2 | M14: =L14 -> 2642629.2 | N14: T | P14: 13 | Q14: =C14/P14 -> 0.53846154 | R14: =D14/P14 -> 1.3461538 | S14: =E14/P14 -> 0 | T14: =F14/P14 -> 0 | U14: =SUM(Q14:T14) -> 1.8846154
A15: 46113 | B15: 1Q | C15: 11 | D15: 16 | E15: 0 | F15: 0 | H15: =C15*H$9 -> 1416589.5 | I15: =D15*I$9 -> 1711933.8 | J15: =E15*J$9 -> 0 | K15: =F15*K$9 -> 0 | L15: =SUM(H15:K15) -> 3128523.3 | M15: =L15 -> 3128523.3 | N15: T | P15: 13 | Q15: =C15/P15 -> 0.84615385 | R15: =D15/P15 -> 1.2307692 | S15: =E15/P15 -> 0 | T15: =F15/P15 -> 0 | U15: =SUM(Q15:T15) -> 2.0769231
A16: 46113 | B16: 2Q | C16: 15 | D16: 12 | E16: 0 | F16: 0 | H16: =C16*H$9 -> 1931713 | I16: =D16*I$9 -> 1283950.3 | J16: =E16*J$9 -> 0 | K16: =F16*K$9 -> 0 | L16: =SUM(H16:K16) -> 3215663.3 | M16: =L16 -> 3215663.3 | N16: T | P16: 13 | Q16: =C16/P16 -> 1.1538462 | R16: =D16/P16 -> 0.92307692 | S16: =E16/P16 -> 0 | T16: =F16/P16 -> 0 | U16: =SUM(Q16:T16) -> 2.0769231
A17: 46143 | B17: 1Q | C17: 12.5 | D17: 22.5 | E17: 10 | F17: 11 | H17: =C17*H$10 -> 1646594.8 | I17: =D17*I$10 -> 2463566.6 | J17: =E17*J$10 -> 933450.65 | K17: =F17*K$10 -> 959639.09 | L17: =SUM(H17:K17) -> 6003251.2 | M17: =L17 -> 6003251.2 | N17: T | P17: 12 | Q17: =C17/P17 -> 1.0416667 | R17: =D17/P17 -> 1.875 | S17: =E17/P17 -> 0.83333333 | T17: =F17/P17 -> 0.91666667 | U17: =SUM(Q17:T17) -> 4.6666667
A18: 46143 | B18: 2Q | C18: 11 | D18: 36 | E18: 6.5 | F18: 10 | H18: =C18*H$10 -> 1449003.5 | I18: =D18*I$10 -> 3941706.5 | J18: =E18*J$10 -> 606742.92 | K18: =F18*K$10 -> 872399.17 | L18: =SUM(H18:K18) -> 6869852.1 | M18: =L18 -> 6869852.1 | N18: T | P18: 12 | Q18: =C18/P18 -> 0.91666667 | R18: =D18/P18 -> 3 | S18: =E18/P18 -> 0.54166667 | T18: =F18/P18 -> 0.83333333 | U18: =SUM(Q18:T18) -> 5.2916667
L20: =SUM(L11:L19) -> 25930555 | M20: =SUM(M11:M19) -> 25930555 | P20: =SUM(P11:P19) -> 102 | Q20: =SUM(Q11:Q19) -> 5.5384615 | R20: =SUM(R11:R19) -> 10.125 | S20: =SUM(S11:S19) -> 1.375 | T20: =SUM(T11:T19) -> 2.1346154 | U20: =SUM(U11:U19) -> 19.173077
L23: Total T | M23: =SUM(M11:M19) -> 25930555
L24: Total P
M25: =+M24+M23 -> 25930555

Sheet Alba M.O. 
A1: MANO DE OBRA | O1: T | P1: Trabajado
A2: Costo Real | O2: P | P2: Presupuesto
C4: Días x Quincena | H4: Especializado | I4: Oficial | J4: 1/2 Oficial | K4: Ayudante | L4: Total | M4: Subtotal | P4: Personal por día
C5: ESP | D5: OF | E5: 1/2 Of | F5: Ayu | P5: Días | Q5: ESP | R5: OF | S5: 1/2 Of | T5: Ayu | U5: Tot
H6: 117452.66 | I6: 97866.77 | J6: 83614.94 | K6: 78291.042 | L6: 46023
H7: 119406.33 | I7: 99479.558 | J7: 84948.749 | K7: 79490.602 | L7: 46054
H8: 122445.79 | I8: 102029.07 | J8: 87100.47 | K8: 81453.719 | L8: 46082
H9: 128780.87 | I9: 106995.86 | J9: 91265.842 | K9: 85242.812 | L9: 46113
H10: 131727.59 | I10: 109491.85 | J10: 93345.065 | K10: 87239.917 | L10: 46143
A11: 46113 | B11: 1Q | C11: 0 | D11: 12 | E11: 0 | F11: 0 | H11: =C11*H$9 -> 0 | I11: =D11*I$8 -> 1224348.8 | J11: =E11*J$8 -> 0 | K11: =F11*K$8 -> 0 | L11: =SUM(H11:K11) -> 1224348.8 | M11: =L11 -> 1224348.8 | N11: T | P11: 13 | Q11: =C11/P11 -> 0 | R11: =D11/P11 -> 0.92307692 | S11: =E11/P11 -> 0 | T11: =F11/P11 -> 0 | U11: =SUM(Q11:T11) -> 0.92307692
A12: 46113 | B12: 2Q | C12: 0 | D12: 8 | E12: 0 | F12: 0 | H12: =C12*H$9 -> 0 | I12: =D12*I$9 -> 855966.9 | J12: =E12*J$9 -> 0 | K12: =F12*K$9 -> 0 | L12: =SUM(H12:K12) -> 855966.9 | M12: =L12 -> 855966.9 | N12: T | P12: 13 | Q12: =C12/P12 -> 0 | R12: =D12/P12 -> 0.61538462 | S12: =E12/P12 -> 0 | T12: =F12/P12 -> 0 | U12: =SUM(Q12:T12) -> 0.61538462
L14: =SUM(L11:L13) -> 2080315.7 | M14: =SUM(M11:M13) -> 2080315.7 | P14: =SUM(P11:P13) -> 26 | Q14: =SUM(Q11:Q13) -> 0 | R14: =SUM(R11:R13) -> 1.5384615 | S14: =SUM(S11:S13) -> 0 | T14: =SUM(T11:T13) -> 0 | U14: =SUM(U11:U13) -> 1.5384615
L17: Total T | M17: =SUM(M11:M13) -> 2080315.7
L18: Total P
M19: =+M18+M17 -> 2080315.7

Sheet Elect M.O.
A1: MANO DE OBRA | O1: T | P1: Trabajado
A2: Costo Real | O2: P | P2: Presupuesto
C4: Días x Quincena | H4: Especializado | I4: Oficial | J4: 1/2 Oficial | K4: Ayudante | L4: Total | M4: Subtotal | P4: Personal por día
C5: ESP | D5: OF | E5: 1/2 Of | F5: Ayu | P5: Días | Q5: ESP | R5: OF | S5: 1/2 Of | T5: Ayu | U5: Tot
H6: 117452.66 | I6: 97866.77 | J6: 83614.94 | K6: 78291.042 | L6: 46023
H7: 119406.33 | I7: 99479.558 | J7: 84948.749 | K7: 79490.602 | L7: 46054
H8: 122445.79 | I8: 102029.07 | J8: 87100.47 | K8: 81453.719 | L8: 46082
A9: 46054 | B9: 1Q | H9: =C9*H$7 -> 0 | I9: =D9*I$7 -> 0 | J9: =E9*J$7 -> 0 | K9: =F9*K$7 -> 0 | L9: =SUM(H9:K9) -> 0 | M9: =L9 -> 0 | N9: T | P9: 13 | Q9: =C9/P9 -> 0 | R9: =D9/P9 -> 0 | S9: =E9/P9 -> 0 | T9: =F9/P9 -> 0 | U9: =SUM(Q9:T9) -> 0
A10: 46054 | B10: 2Q | H10: =C10*H$7 -> 0 | I10: =D10*I$7 -> 0 | J10: =E10*J$7 -> 0 | K10: =F10*K$7 -> 0 | L10: =SUM(H10:K10) -> 0 | M10: =L10 -> 0 | N10: T | P10: 14 | Q10: =C10/P10 -> 0 | R10: =D10/P10 -> 0 | S10: =E10/P10 -> 0 | T10: =F10/P10 -> 0 | U10: =SUM(Q10:T10) -> 0
A11: 46082 | B11: 1Q | H11: =C11*H$8 -> 0 | I11: =D11*I$8 -> 0 | J11: =E11*J$8 -> 0 | K11: =F11*K$8 -> 0 | L11: =SUM(H11:K11) -> 0 | M11: =L11 -> 0 | N11: T | P11: 12 | Q11: =C11/P11 -> 0 | R11: =D11/P11 -> 0 | S11: =E11/P11 -> 0 | T11: =F11/P11 -> 0 | U11: =SUM(Q11:T11) -> 0
A12: 46082 | B12: 2Q | H12: =C12*H$8 -> 0 | I12: =D12*I$8 -> 0 | J12: =E12*J$8 -> 0 | K12: =F12*K$8 -> 0 | L12: =SUM(H12:K12) -> 0 | M12: =L12 -> 0 | N12: T | P12: 13 | Q12: =C12/P12 -> 0 | R12: =D12/P12 -> 0 | S12: =E12/P12 -> 0 | T12: =F12/P12 -> 0 | U12: =SUM(Q12:T12) -> 0
L14: =SUM(L9:L13) -> 0 | M14: =SUM(M9:M13) -> 0
L17: Total T | M17: =SUM(M9:M13) -> 0
L18: Total P
M19: =+M18+M17 -> 0

Sheet GGBB
H2: 45846 | O2: 24
F3: MESES | G3: DÓLAR BNA | H3: DÓLAR MEP | M3: Descrip | N3: Mes | O3: Total Dias
B4: GASTOS GENERALES y BENEFICIO | F4: =+ROUNDUP(N21,0) -> 19 | G4: 1280 | H4: 1276 | M4: Prelim | N4: 0.5 | O4: =+N4*$O$2 -> 12 | Q4: Syh permanente
M5: Micropilotes | N5: 2 | O5: =+N5*$O$2 -> 48 | Q5: =+ROUNDUP(SUM(N6),0) -> 1
B6: Gastos Grales de obra en items | C6: Un | D6: Meses | E6: Cant | F6: Precio Unit | G6: Subtotal | H6: =SUM(G7:G10) -> 3040000 | M6: Subsuelo y VF | N6: 1 | O6: =+N6*$O$2 -> 24
B7: Oficina en obra (6x3 c/AA) | C7: mes | D7: =+$F$4 -> 19 | E7: 0 | F7: =E7*I7+J7 -> 0 | G7: =+F7*D7*E7 -> 0 | M7: Losa sobre PB | N7: 1 | O7: =+N7*$O$2 -> 24
B8: Obrador 6x3 s/AA | C8: mes | D8: =+$F$4 -> 19 | E8: 0 | F8: =E8*I8+J8 -> 0 | G8: =+F8*D8*E8 -> 0 | M8: Losa sobre 1 | N8: 0.75 | O8: =+N8*$O$2 -> 18
B9: Pañol (6x3) | C9: mes | D9: =+$F$4 -> 19 | E9: 0 | F9: 180000 | G9: =+F9*D9*E9 -> 0 | M9: Losa sobre 2 | N9: 0.75 | O9: =+N9*$O$2 -> 18
B10: Baños | C10: mes | D10: =+$F$4 -> 19 | E10: 2 | F10: 80000 | G10: =+F10*D10*E10 -> 3040000 | M10: Losa sobre 3 | N10: 0.75 | O10: =+N10*$O$2 -> 18
B11: Gastos Grales de obra en items | H11: =SUM(G12:G19) -> 39866835 | M11: Losa sobre 4 | N11: 0.75 | O11: =+N11*$O$2 -> 18 | P11: Inicio mamposteria | Q11: Meses H° | R11: Estacionamiento en contramano
B12: HyS permanente | C12: mes | D12: =+Q5 -> 1 | E12: 1 | G12: =+F12*D12*E12 -> 0 | J12: =+'[7]P.MO 06.25'!C9/2 -> 1623254.5 | K12: =+J12*D12*E12 -> 1623254.5 | M12: Losa sobre 5 | N12: 0.75 | O12: =+N12*$O$2 -> 18 | Q12: =+SUM(N6:N15) -> 7.5 | R12: =+ROUNDUP(Q12/3,0) -> 3
B13: HyS | C13: mes | D13: =+$F$4 -> 19 | E13: 1 | G13: =+F13*D13*E13 -> 0 | J13: 300000 | K13: =+J13*D13*E13 -> 5700000 | M13: Losa sobre 6 | N13: 0.75 | O13: =+N13*$O$2 -> 18
B14: Energía de obra | C14: mes | D14: =+$F$4 -> 19 | E14: 0.5 | F14: 200000 | G14: =+F14*D14*E14 -> 1900000 | M14: Losa sobre 7 | N14: 0.5 | O14: =+N14*$O$2 -> 12
B15: Agua de obra | C15: mes | D15: =+$F$4 -> 19 | E15: 1 | F15: 300000 | G15: =+F15*D15*E15 -> 5700000 | M15: Losa Techos | N15: 0.5 | O15: =+N15*$O$2 -> 12
B16: Internet | C16: mes | D16: =+$F$4 -> 19 | E16: 1 | F16: 75000 | G16: =+F16*D16*E16 -> 1425000 | M16: Mampostería | N16: 2 | O16: =+N16*$O$2 -> 48
B17: Alquiler cerco de obra chapa | C17: mes | D17: =+$F$4 -> 19 | E17: 0 | F17: 10000 | G17: =+F17*D17*E17 -> 0 | M17: Revoques, contrap y carp | N17: 2 | O17: =+N17*$O$2 -> 48
B18: Proyecto Ejecutivo | C18: mes | D18: =+$F$4 -> 19 | E18: 0 | F18: =+'[7]P.MO 06.25'!C9 -> 3246508.9 | G18: =+F18*D18*E18 -> 0 | M18: Colocación | N18: 2 | O18: =+N18*$O$2 -> 48
B19: Proyecto (50%) | C19: mes | D19: =+$F$4 -> 19 | E19: 0.5 | F19: =+'[7]P.MO 06.25'!C9 -> 3246508.9 | G19: =+F19*D19*E19 -> 30841835 | M19: Pintura | N19: 2 | O19: =+N19*$O$2 -> 48
B20: Gastos Directos | H20: =SUM(G21:G30) -> 89942566 | M20: Terminaciones | N20: 1 | O20: =+N20*$O$2 -> 24
B21: Coordinacion de obra | C21: mes | D21: =+$F$4 -> 19 | E21: 0.15 | F21: =+'[7]P.MO 06.25'!C11 -> 5688802.4 | G21: =+F21*D21*E21 -> 16213087 | N21: =SUM(N4:N20) -> 19 | O21: =SUM(O4:O20) -> 456
B22: Jefe de obra | C22: mes | D22: =+$F$4 -> 19 | E22: 0.2 | F22: =+'[7]P.MO 06.25'!C10 -> 4716669.4 | G22: =+F22*D22*E22 -> 17923344
B23: Sobrestante | C23: mes | D23: =+$F$4 -> 19 | E23: 1 | G23: =+F23*D23*E23 -> 0 | J23: =+'[7]P.MO 06.25'!C9 -> 3246508.9 | K23: =+J23*D23*E23 -> 61683669
B24: Administrativo en obra | C24: mes | D24: =+$F$4 -> 19 | E24: 0 | F24: =+J23 -> 3246508.9 | G24: =+F24*D24*E24 -> 0
B25: Capataz | C25: mes | D25: =+$F$4 -> 19 | E25: 0.5 | F25: =+'[7]P.MO 06.25'!C12 -> 3874330.1 | G25: =+F25*D25*E25 -> 36806136
B26: Logistica | C26: mes | D26: =+$F$4 -> 19 | E26: 1 | F26: 500000 | G26: =+F26*D26*E26 -> 9500000
B27: Vehiculo obra | C27: mes | D27: =+$F$4 -> 19 | E27: 1 | F27: =F26 -> 500000 | G27: =+F27*D27*E27 -> 9500000
B28: Mov y viaticos | C28: mes | D28: =+$F$4 -> 19 | E28: 1 | G28: =+F28*D28*E28 -> 0 | J28: =F26 -> 500000 | K28: =+J28*D28*E28 -> 9500000
B29: UOCRA | C29: mes | D29: =+$F$4 -> 19 | E29: 1 | G29: =+F29*D29*E29 -> 0
B30: Pañolero/Sereno | C30: mes | D30: =+$F$4 -> 19 | E30: 1 | J30: =+'[7]P.MO 06.25'!C7/2 -> 806885.99 | K30: =+J30*D30*E30 -> 15330834
B31: Equipos | H31: =SUM(G32:G36) -> 0
B32: Bobcat | C32: mes | F32: 130000 | G32: =+F32*D32 -> 0
B33: Camion limpieza | C33: mes | F33: 100000 | G33: =+F33*D33 -> 0
B34: Tijera electrica 12 | C34: mes | F34: 33600 | G34: =+F34*D34 -> 0
B35: JLG | C35: mes | F35: 89000 | G35: =+F35*D35 -> 0
B36: Grua 20ton | C36: mes | F36: 70000 | G36: =+F36*D36 -> 0
B37: Gastos Indirectos | H37: =SUM(G38:G42) -> 94164835
B38: Admin (50%Compras - 50%RRHH) | C38: mes | D38: =+$F$4 -> 19 | E38: 0.5 | F38: ='[7]P.MO 06.25'!C9 -> 3246508.9 | G38: =+F38*D38*E38 -> 30841835
B39: Seguros | C39: gl | D39: =+D38 -> 19 | E39: 1 | F39: 250000 | G39: =+F39*D39 -> 4750000
B40: IIBB (monto venta obra gris) | C40: gl | D40: 0.04 | E40: 0.7 | F40: 1550000000 | G40: =+F40*D40*E40 -> 43400000
B41: Imp cheque | C41: gl | D41: =1.2/100 -> 0.012 | E41: =+E40 -> 0.7 | F41: =+F40*1.15 -> 1.7825e+09 | G41: =+F41*D41*E41 -> 14973000
B42: Contrato | C42: gl | D42: 1 | E42: 1 | F42: 200000 | G42: =+F42*D42*E42 -> 200000
G43: =SUM(G7:G42) -> 2.2701424e+08 | H43: =SUM(H6:H42) -> 2.2701424e+08 | K43: =SUM(K6:K42) -> 93837758 | L43: =+H43+K43 -> 3.2085199e+08
B44: Monto puesto en Ayuda de gremio que no se eroga | K44: Imputados en pres | L44: Total GGBB
B45: Total de Gastos Generales | H45: =+H44+H43 -> 2.2701424e+08 | L45: =+L43/G53 -> 0.28250185
B47: Otro | G47: =+'[7]01'!N213 -> 2.8879873e+08 | H47: =+G47/$H$4 -> 226331.29
B48: Corralon | G48: =+'[7]01'!O213 -> 92831284 | H48: =+G48/$H$4 -> 72751.79
B49: Subcontratos | G49: =+'[7]01'!P213 -> 5.0875751e+08 | H49: =+G49/$H$4 -> 398712.78
B50: Mano de obra | G50: =+'[7]01'!Q213 -> 2.1954745e+08 | H50: =+G50/$H$4 -> 172059.13
B51: Equipos | G51: =+'[7]01'!R213 -> 25816869 | H51: =+G51/$H$4 -> 20232.656
A53: A | G53: =SUM(G47:G52) -> 1.1357518e+09 | H53: =SUM(H47:H52) -> 890087.65
J54: =+G53-G51 -> 1.109935e+09
B55: GG | F55: =+H45/G53 -> 0.19988014 | G55: =+F55*$G$53 -> 2.2701424e+08 | H55: =+G55/$H$4 -> 177910.84 | J55: =+J54*K55 -> 33298049 | K55: 0.03
B56: Equipos | E56: 3 | F56: =+G56/G53 -> 0.0065869852 | G56: =+J56 -> 7481180.5 | H56: =+G56/$H$4 -> 5862.9941 | J56: =+J55-G51 -> 7481180.5
B57: Imprevistos + Negociación | E57: 5 | F57: 0.05 | G57: =+F57*$G$53 -> 56787592 | H57: =+G57/$H$4 -> 44504.382
B58: Beneficio | E58: 9 | F58: 0.1 | G58: =+F58*$G$53 -> 1.1357518e+08 | H58: =+G58/$H$4 -> 89008.765
A59: B | F59: =SUM(F55:F58) -> 0.35646712 | G59: =SUM(G55:G58) -> 4.0485819e+08 | H59: =+G59/$H$4 -> 317286.98
A61: K | F61: =1+F59 -> 1.3564671 | G61: =+G53*F61 -> 1.54061e+09
A63: A+B | G63: =+G53+G59 -> 1.54061e+09 | H63: =+G63/$H$4 -> 1207374.6

Sheet Preventivo Vta CH2171 
F1: DÓLAR BNA | G1: DÓLAR MEP
F2: =+[8]GGBB!G4 -> 1280 | G2: =+[8]GGBB!H4 -> 1276
F4: 45817
B5: OBRA: EDIFICIO CHIVILCOY 2171
B6: PRESUPUESTO OBRA CIVIL
B7: Descripción | C7: U | D7: Cant | E7: P unit | F7: Subtotal
A8: 1 | B8: TAREAS PRELIMINARES | G8: =SUM(F9:F17) -> 23341584 | H8: =+G8/$G$228 -> 0.024827647
A9: 1.01 | B9: Limpieza y preparación del terreno - No cotiza | C9: gl | D9: 0 | E9: 0 | F9: =+E9*D9 -> 0
A10: 1.02 | B10: Topógrafo - Visita de obra replanteo | C10: un | D10: 4 | E10: 422179 | F10: =+E10*D10 -> 1688716
A11: 1.03 | B11: Cartel de Obra - No cotiza | C11: gl | D11: 1 | E11: 0 | F11: =+E11*D11 -> 0
A12: 1.04 | B12: Cerco de obra perimetral - En chapa C25 + Concertina + Porton corredizo | C12: ml | D12: 10 | E12: 290244 | F12: =+E12*D12 -> 2902440
A13: 1.05 | B13: Obrador, pañol y ducha | C13: gl | D13: 1 | E13: 11833114 | F13: =+E13*D13 -> 11833114
A14: 1.06 | B14: Alquiler de baños quimicos y duchas portatiles | C14: mes | D14: 4 | E14: 352682 | F14: =+E14*D14 -> 1410728
A15: 1.07 | B15: Conexión pilar y luz de obra + Tablero de obra | C15: gl | D15: 1 | E15: 2824239 | F15: =+E15*D15 -> 2824239
A16: 1.08 | B16: Conexión agua de obra, tanque + bomba | C16: gl | D16: 1 | E16: 2027179 | F16: =+E16*D16 -> 2027179
A17: 1.09 | B17: Tramite luz de obra, certificado luz de obra (2) y medición PAT | C17: gl | D17: 1 | E17: 655168 | F17: =+E17*D17 -> 655168
A18: 2 | B18: MOVIMIENTO DE TIERRA, COMPACTACION Y RELLENO | G18: =SUM(F19:F22) -> 16821282 | H18: =+G18/$G$228 -> 0.017892224
A19: 2.01 | B19: Retiro de suelo vegetal e: 50 cm, aporte y compactación de tosca e: 40 cm (dos capas de 20 cm) | C19: m2 | D19: 219 | E19: 39308 | F19: =+E19*D19 -> 8608452
A20: 2.02 | B20: Excavación para cámara transformadora | C20: m3 | D20: 100 | E20: 42908 | F20: =+E20*D20 -> 4290800
A21: 2.03 | B21: Excavación manual para tensores y vigas de fundación | C21: m3 | D21: 43 | E21: 91210 | F21: =+E21*D21 -> 3922030
A22: 2.04 | B22: Demolición y retiro de fundaciones existentes - No cotiza | C22: gl | D22: 0 | E22: 0 | F22: =+E22*D22 -> 0
A23: 3 | B23: ESTRUCTURA RESISTENTE | G23: =SUM(F24:F45) -> 452634067 | H23: =+G23/$G$228 -> 0.48145141
A24: 3.01 | B24: Hormigón de limpieza - e: 10 cm | C24: m3 | D24: 3 | E24: 379273 | F24: =+E24*D24 -> 1137819
A25: 3.02 | B25: Micropilotes Ø 20 cm | C25: gl | D25: 1 | E25: 65949869 | F25: =+E25*D25 -> 65949869
A26: 3.03 | B26: Platea - H30 (110 kg/m3 de hierro) | C26: m3 | D26: 7 | E26: 798655 | F26: =+E26*D26 -> 5590585
A27: 3.04 | B27: Zapata corrida tabique - H30 (180 kg/m3 de hierro) | C27: m3 | D27: 4 | E27: 1185296 | F27: =+E27*D27 -> 4741184
A28: 3.05 | B28: Bases aisladas - H30 (110 kg/m3 de hierro) | C28: m3 | D28: 2 | E28: 798655 | F28: =+E28*D28 -> 1597310
A29: 3.06 | B29: Cabezales - H30 (130 kg/m3 de hierro) | C29: m3 | D29: 11 | E29: 847449 | F29: =+E29*D29 -> 9321939
A30: 3.07 | B30: Viga de fundación - H30 (180 kg/m3 de hierro) | C30: m3 | D30: 9 | E30: 1185296 | F30: =+E30*D30 -> 10667664
A31: 3.08 | B31: Tabique submuración - H30 (90 kg/m3 de hierro) | C31: m3 | D31: 9 | E31: 1083664 | F31: =+E31*D31 -> 9752976
A32: 3.09 | B32: Puntales de compresión/codales - H30 (120 kg/m3) | C32: m3 | D32: 1 | E32: 1244979 | F32: =+E32*D32 -> 1244979
A33: 3.1 | B33: Columna - H30 (240 kg/m3 de hierro) | C33: m3 | D33: 32 | E33: 1391362 | F33: =+E33*D33 -> 44523584
A34: 3.11 | B34: Tabiques - H30 (120 kg/m3 de hierro) | C34: m3 | D34: 30 | E34: 1156856 | F34: =+E34*D34 -> 34705680
A35: 3.12 | B35: Viga H° Visto - H30 (120 kg/m3 de hierro) | C35: m3 | D35: 7 | E35: 1725658 | F35: =+E35*D35 -> 12079606
... A45: 3.22 | B45: Picado de medianeras para columnas y vigas - Cotizado solo para PB, 1P, NO contempla picado en CT | C45: m2 | D45: 65 | E45: 40554 | F45: =+E45*D45 -> 2636010
A46: 24 | B46: AYUDA DE GREMIOS | G46: =SUM(F47:F55) -> 56861052 | H46: =+G46/$G$228 -> 0.060481161
A47: 24.01 | B47: Sereno | C47: mes | D47: 10 | E47: 1094515 | F47: =+E47*D47 -> 10945150
A48: 24.02 | B48: Tecnico de seguridad & higiene permanente en Obra | C48: mes | D48: 1 | E48: 2201892 | F48: =+E48*D48 -> 2201892
A49: 24.03 | B49: Higiene y seguridad Res 51 | C49: mes | D49: 10 | E49: 406941 | F49: =+E49*D49 -> 4069410
A50: 24.04 | B50: Protecciones y defensas | C50: gl | D50: 1 | E50: 13322590 | F50: =+E50*D50 -> 13322590
A51: 24.05 | B51: Ayuda de gremios | C51: mes | D51: 10 | E51: 973794 | F51: =+E51*D51 -> 9737940
A52: 24.06 | B52: Limpieza periódica | C52: mes | D52: 10 | E52: 883525 | F52: =+E52*D52 -> 8835250
A53: 24.07 | B53: Limpieza final de Obra | C53: gl | D53: 0 | E53: 6243068 | F53: =+E53*D53 -> 0
A54: 24.08 | B54: Fletes | C54: mes | D54: 10 | E54: 406941 | F54: =+E54*D54 -> 4069410
A55: 24.09 | B55: Volquetes | C55: mes | D55: 10 | E55: 367941 | F55: =+E55*D55 -> 3679410
A56: 25 | B56: JEFATURA DE OBRA | G56: =SUM(F57:F58) -> 50820170 | H56: =+G56/$G$228 -> 0.054055681
A57: 25.01 | B57: Proyecto Ejecutivo y Supervisión profesional de Obra | C57: mes | D57: 10 | E57: 4403783 | F57: =+E57*D57 -> 44037830
A58: 25.02 | B58: Movilidad y viaticos | C58: mes | D58: 10 | E58: 678234 | F58: =+E58*D58 -> 6782340
A59: A | B59: PTO 01 SUBTOTAL SIN IVA | F59: =SUM(F8:F58) -> 600478155 | G59: =SUM(G8:G58) -> 600478155 | J59: PTO 01 | K59: =SUM(#REF!) -> #REF! | L59: =+K59-G59 -> #REF!
A61: 4 | B61: MAMPOSTERÍA | G61: =SUM(F62:F67) -> 81027619 | H61: =+G61/$G$228 -> 0.086186314
A62: 4.01 | B62: Muro tipo 1 (interiores, divisorio de locales) e: 10 cm - Ladrillo hueco 08 x 18 x 33 | C62: m2 | D62: 437 | E62: 28582 | F62: =+E62*D62 -> 12490334
A63: 4.02 | B63: Muro tipo 2 y 3 (medianera, caja de escaleras y ascensor) e: 15 cm - Ladrillo hueco portante 12 x 19 x 33 | C63: m2 | D63: 723 | E63: 39642 | F63: =+E63*D63 -> 28661166
A64: 4.03 | B64: Muro tipo 4 (divisorio de unidades y fachadas) e: 15 cm - Ladrillo hueco 12 x 18 x 33 | C64: m2 | D64: 1008 | E64: 31853 | F64: =+E64*D64 -> 32107824
A65: 4.04 | B65: Enchape medianeras existentes - Contemplamos picado zonas sueltas y enchape con ladrillo comun para PB y 1° | C65: m2 | D65: 199 | E65: 15879 | F65: =+E65*D65 -> 3159921
A66: 4.05 | B66: Muro de tabique seco ignifugo | C66: m2 | D66: 34 | E66: 77459 | F66: =+E66*D66 -> 2633606
A67: 4.06 | B67: Vigas de encadenado - En muros de PB, incl. excavación y armado | C67: ml | D67: 24 | E67: 82282 | F67: =+E67*D67 -> 1974768
A68: 5 | B68: AISLACIONES | G68: =SUM(F69:F74) -> 16565287 | H68: =+G68/$G$228 -> 0.017619931
A69: 5.01 | B69: Aislación hidrófuga horizontal (baños) - Inc. membrana geotextil y 35% en concepto de babetas | C69: m2 | D69: 79 | E69: 39406 | F69: =+E69*D69 -> 3113074
A70: 5.02 | B70: Cajón hidrófugo - Muros de PB | C70: ml | D70: 113 | E70: 7174 | F70: =+E70*D70 -> 810662
A71: 5.03 | B71: Azotado hidrófugo - Sobre contrapiso en vereda y PB | C71: m2 | D71: 207 | E71: 7174 | F71: =+E71*D71 -> 1485018
A72: 5.04 | B72: Aislación térmica en terrazas, eps e:2,00 cm | C72: m2 | D72: 165 | E72: 4800 | F72: =+E72*D72 -> 792000
A73: 5.05 | B73: Barrera de vapor | C73: m2 | D73: 165 | E73: 4641 | F73: =+E73*D73 -> 765765
A74: 5.06 | B74: Membrana asfaltica geotextil 4mm - Balcones y azotea - Inc. 20% en concepto de babetas | C74: m2 | D74: 274 | E74: 35032 | F74: =+E74*D74 -> 9598768
A75: 6 | B75: CUBIERTAS | G75: =SUM(F76:F76) -> 1479500 | H75: =+G75/$G$228 -> 0.0015736937
A76: 6.01 | B76: Babeta de chapa galvanizada en medianeras | C76: ml | D76: 44 | E76: 33625 | F76: =+E76*D76 -> 1479500
A77: 7 | B77: REVOQUES | G77: =SUM(F78:F85) -> 151616626 | H77: =+G77/$G$228 -> 0.16126943
A78: 7.01 | B78: Revoque Grueso Impermeable Exterior | C78: m2 | D78: 663 | E78: 21829 | F78: =+E78*D78 -> 14472627
A79: 7.02 | B79: Revoque Grueso Impermeable Exterior a mas de 3m - Medianero y fachadas | C79: m2 | D79: 1164 | E79: 29490 | F79: =+E79*D79 -> 34326360
A80: 7.03 | B80: Buña en revoque - Estimados ml en medianeras | C80: ml | D80: 500 | E80: 15088 | F80: =+E80*D80 -> 7544000
A81: 7.04 | B81: Revoque Grueso Interior + fino | C81: m2 | D81: 521 | E81: 35962 | F81: =+E81*D81 -> 18736202
A82: 7.05 | B82: Yeso interior | C82: m2 | D82: 2180 | E82: 24829 | F82: =+E82*D82 -> 54127220
A83: 7.06 | B83: Arista en yeso | C83: ml | D83: 255 | E83: 18098 | F83: =+E83*D83 -> 4614990
A84: 7.07 | B84: Provisión y colocación de guardacanto yesero | C84: u | D84: 102 | E84: 21446 | F84: =+E84*D84 -> 2187492
A85: 7.08 | B85: Revoque Grueso Impermeable Interior b/ revestimiento | C85: m2 | D85: 715 | E85: 21829 | F85: =+E85*D85 -> 15607735
A86: 8 | B86: CONTRAPISOS Y CARPETAS | G86: =SUM(F87:F94) -> 49859719 | H86: =+G86/$G$228 -> 0.053034082
A87: 8.01 | B87: Contrapiso de cascotes s/ss e: 15 cm | C87: m2 | D87: 21 | E87: 45843 | F87: =+E87*D87 -> 962703
A88: 8.02 | B88: Contrapiso armado de H° pobre s/terreno natural e: 20 cm - Incluye film de polietileno | C88: m2 | D88: 201 | E88: 54692 | F88: =+E88*D88 -> 10993092
A89: 8.03 | B89: Contrapiso de cascotes en azoteas c/pendiente e: 15 cm | C89: m2 | D89: 107 | E89: 45843 | F89: =+E89*D89 -> 4905201
A90: 8.04 | B90: Contrapiso - Carpeta monolitico e: 6 cm | C90: m2 | D90: 850 | E90: 24408 | F90: =+E90*D90 -> 20746800
A91: 8.05 | B91: Carpeta en PB, balcones, baños y azoteas e: 3,00 cm | C91: m2 | D91: 365 | E91: 16212 | F91: =+E91*D91 -> 5917380
A92: 8.06 | B92: Carpeta sobre membrana, e: 3,00 cm | C92: m2 | D92: 357 | E92: 16212 | F92: =+E92*D92 -> 5787684
A93: 8.07 | B93: Banquinas para cocinas - N/A | C93: gl | D93: 0 | E93: 0 | F93: =+E93*D93 -> 0
A94: 8.08 | B94: Banquinas para bombas, TT, etc. h: 15 cm | C94: gl | D94: 1 | E94: 546859 | F94: =+E94*D94 -> 546859
A95: 9 | B95: ESCALERAS | G95: =SUM(F96:F98) -> 7973948 | H95: =+G95/$G$228 -> 0.0084816164
A96: 9.01 | B96: Provisión y ejecución de alisado de cemento en pedadas y alzadas | C96: gl | D96: 1 | E96: 3403852 | F96: =+E96*D96 -> 3403852
A97: 9.02 | B97: Provisión y colocación de nariz metálica en escalones | C97: gl | D97: 1 | E97: 3083650 | F97: =+E97*D97 -> 3083650
A98: 9.03 | B98: Zócalo de concreto en escalera - No incluye el ojo | C98: ml | D98: 114 | E98: 13039 | F98: =+E98*D98 -> 1486446
A99: 10 | B99: VENTILACIONES - PROVISION COTIZADA EN ITEM 26 | G99: =SUM(F100:F102) -> 6490071 | H99: =+G99/$G$228 -> 0.0069032671
A100: 10.01 | B100: Colocación de ventilación de conducto de humos. Inc. toma de aire en PB | C100: gl | D100: 1 | E100: 2633974 | F100: =+E100*D100 -> 2633974
A101: 10.02 | B101: Colocación y montaje de conducto de ventilación en baños | C101: gl | D101: 1 | E101: 2633974 | F101: =+E101*D101 -> 2633974
A102: 10.03 | B102: Colocación sombreretes en chapa prepintada C25 - Provisión en item 26 | C102: u | D102: 7 | E102: 174589 | F102: =+E102*D102 -> 1222123
A103: 11 | B103: PISOS - PROVISION A CARGO DEL COMITENTE | G103: =SUM(F104:F110) -> 37065194 | H103: =+G103/$G$228 -> 0.039424982
A104: 11.01 | B104: Colocación de baldosas en palieres - Provisión a cargo del comitente | C104: m2 | D104: 101 | E104: 27090 | F104: =+E104*D104 -> 2736090
A105: 11.02 | B105: Colocación de porcelanato en UF - Provisión a cargo del comitente | C105: m2 | D105: 898 | E105: 27090 | F105: =+E105*D105 -> 24326820
A106: 11.03 | B106: Colocación de porcelanato en baños - Provisión a cargo del comitente | C106: m2 | D106: 88 | E106: 32396 | F106: =+E106*D106 -> 2850848
A107: 11.04 | B107: Colocación de porcelanato en exterior - Provisión a cargo del comitente | C107: m2 | D107: 63 | E107: 27090 | F107: =+E107*D107 -> 1706670
A108: 11.05 | B108: Provisión y colocación de sustrato - No cotiza | C108: m2 | D108: 25 | E108: 0 | F108: =+E108*D108 -> 0
A109: 11.06 | B109: Provisión y ejecución de alisado de cemento rodillado | C109: m2 | D109: 27 | E109: 21058 | F109: =+E109*D109 -> 568566
A110: 11.07 | B110: Colocación de baldoson de vereda - Provisión a cargo del comitente | C110: m2 | D110: 180 | E110: 27090 | F110: =+E110*D110 -> 4876200
A111: 12 | B111: ZOCALOS Y SOLIAS - PROVISION A CARGO DEL COMITENTE | G111: =SUM(F112:F115) -> 15472374 | H111: =+G111/$G$228 -> 0.016457436
...

Sheet Preventivo Costo CH2171 
Q3: DÓLAR BNA | R3: DÓLAR MEP
Q4: =+[8]GGBB!G4 -> 1280 | R4: =+[8]GGBB!H4 -> 1276
C5: OBRA: EDIFICIO CHIVILCOY 2171 | G5: MATERIAL | J5: M. DE OBRA
C6: PRESUPUESTO OBRA CIVIL | Q6: 45817
C7: Descripción | D7: U | E7: Cant | F7: P.Unit | G7: Otro | H7: Corralon | I7: Total MAT | J7: Otro | K7: Albañil | L7: Total MO | M7: EQUIPOS | N7: Total
B8: 1 | C8: TAREAS PRELIMINARES
A9: Preliminares | B9: 1.01 | C9: Limpieza y preparación del terreno - No cotiza | D9: gl | E9: 0 | F9: 0 | G9: 0 | H9: 0 | I9: =SUM(G9:H9) -> 0 | J9: 0 | K9: 0 | L9: =SUM(J9:K9) -> 0 | M9: 0 | N9: =SUM(I9,L9) -> 0
A10: Agrimensura | B10: 1.02 | C10: Topógrafo - Visita de obra replanteo | D10: un | E10: 4 | F10: 311234.08 | G10: 0 | H10: 100000 | I10: =SUM(G10:H10) -> 100000 | J10: 857576.25 | K10: 268962 | L10: =SUM(J10:K10) -> 1126538.2 | M10: 18398.074 | N10: =SUM(I10,L10) -> 1226538.2
A11: Preliminares | B11: 1.03 | C11: Cartel de Obra - No cotiza | D11: gl | E11: 1 | F11: 0 | G11: 0 | H11: 0 | I11: =SUM(G11:H11) -> 0 | J11: 0 | K11: 0 | L11: =SUM(J11:K11) -> 0 | M11: 0 | N11: =SUM(I11,L11) -> 0
A12: Preliminares | B12: 1.04 | C12: Cerco de obra perimetral - En chapa C25 + Concertina + Porton corredizo | D12: ml | E12: 10 | F12: 213970.27 | G12: 988155.68 | H12: 0 | I12: =SUM(G12:H12) -> 988155.68 | J12: 0 | K12: 1119925.7 | L12: =SUM(J12:K12) -> 1119925.7 | M12: 31621.221 | N12: =SUM(I12,L12) -> 2108081.4
A13: Preliminares | B13: 1.05 | C13: Obrador, pañol y ducha | D13: gl | E13: 1 | F13: 8723480 | G13: 2270625.2 | H13: 300000 | I13: =SUM(G13:H13) -> 2570625.2 | J13: 1000000 | K13: 5023936.4 | L13: =SUM(J13:K13) -> 6023936.4 | M13: 128918.42 | N13: =SUM(I13,L13) -> 8594561.5
A14: Gastos Generales Obra | B14: 1.06 | C14: Alquiler de baños quimicos y duchas portatiles | D14: mes | E14: 4 | F14: 260000 | G14: 0 | H14: 0 | I14: =SUM(G14:H14) -> 0 | J14: 1040000 | K14: 0 | L14: =SUM(J14:K14) -> 1040000 | M14: 0 | N14: =SUM(I14,L14) -> 1040000
A15: Preliminares | B15: 1.07 | C15: Conexión pilar y luz de obra + Tablero de obra | D15: gl | E15: 1 | F15: 2082054.6 | G15: 1290000 | H15: 100000 | I15: =SUM(G15:H15) -> 1390000 | J15: 0 | K15: 661285.32 | L15: =SUM(J15:K15) -> 661285.32 | M15: 30769.28 | N15: =SUM(I15,L15) -> 2051285.3
A16: Preliminares | B16: 1.08 | C16: Conexión agua de obra, tanque + bomba | D16: gl | E16: 1 | F16: 1494454.5 | G16: 936000 | H16: 0 | I16: =SUM(G16:H16) -> 936000 | J16: 0 | K16: 536368.95 | L16: =SUM(J16:K16) -> 536368.95 | M16: 22085.534 | N16: =SUM(I16,L16) -> 1472369
A17: Preliminares | B17: 1.09 | C17: Tramite luz de obra, certificado luz de obra (2) y medición PAT | D17: gl | E17: 1 | F17: 482995.31 | G17: 0 | H17: 0 | I17: =SUM(G17:H17) -> 0 | J17: 482995.31 | K17: 0 | L17: =SUM(J17:K17) -> 482995.31 | M17: 0 | N17: =SUM(I17,L17) -> 482995.31
B18: 2 | C18: MOVIMIENTO DE TIERRA, COMPACTACION Y RELLENO
A19: Excavación y Mov. de Suelos | B19: 2.01 | C19: Retiro de suelo vegetal e: 50 cm, aporte y compactación de tosca e: 40 cm (dos capas de 20 cm) | D19: m2 | E19: 219 | F19: 28977.787 | G19: 0 | H19: 0 | I19: =SUM(G19:H19) -> 0 | J19: 5673730.3 | K19: 672404.99 | L19: =SUM(J19:K19) -> 6346135.3 | M19: 0 | N19: =SUM(I19,L19) -> 6346135.3
A20: Excavación y Mov. de Suelos | B20: 2.02 | C20: Excavación para cámara transformadora | D20: m3 | E20: 100 | F20: 31631.511 | G20: 0 | H20: 0 | I20: =SUM(G20:H20) -> 0 | J20: 2444000 | K20: 672404.99 | L20: =SUM(J20:K20) -> 3116405 | M20: 46746.075 | N20: =SUM(I20,L20) -> 3116405
A21: Hormigón | B21: 2.03 | C21: Excavación manual para tensores y vigas de fundación | D21: m3 | E21: 43 | F21: 67240.499 | G21: 0 | H21: 0 | I21: =SUM(G21:H21) -> 0 | J21: 0 | K21: 2891341.5 | L21: =SUM(J21:K21) -> 2891341.5 | M21: 0 | N21: =SUM(I21,L21) -> 2891341.5
A22: Excavación y Mov. de Suelos | B22: 2.04 | C22: Demolición y retiro de fundaciones existentes - No cotiza | D22: gl | E22: 0 | F22: 0 | G22: 0 | H22: 0 | I22: =SUM(G22:H22) -> 0 | J22: 0 | K22: 0 | L22: =SUM(J22:K22) -> 0 | M22: 0 | N22: =SUM(I22,L22) -> 0
B23: 3 | C23: ESTRUCTURA RESISTENTE
A24: Hormigón | B24: 3.01 | C24: Hormigón de limpieza - e: 10 cm | D24: m3 | E24: 3 | F24: 279603.29 | G24: 361290 | H24: 0 | I24: =SUM(G24:H24) -> 361290 | J24: 0 | K24: 465123.66 | L24: =SUM(J24:K24) -> 465123.66 | M24: 12396.205 | N24: =SUM(I24,L24) -> 826413.66
A25: Hormigón | B25: 3.02 | C25: Micropilotes Ø 20 cm | D25: gl | E25: 1 | F25: 48618848 | G25: 11090041 | H25: 0 | I25: =SUM(G25:H25) -> 11090041 | J25: 34350000 | K25: 2460301.5 | L25: =SUM(J25:K25) -> 36810301 | M25: 718505.14 | N25: =SUM(I25,L25) -> 47900343 | P25: =I25/N25 -> 0.23152321 | Q25: =L25/N25 -> 0.76847679
A26: Hormigón | B26: 3.03 | C26: Platea - H30 (110 kg/m3 de hierro) | D26: m3 | E26: 7 | F26: 588775.24 | G26: 2500023.2 | H26: 0 | I26: =SUM(G26:H26) -> 2500023.2 | J26: 1560495.7 | K26: 0 | L26: =SUM(J26:K26) -> 1560495.7 | M26: 60907.784 | N26: =SUM(I26,L26) -> 4060518.9
A27: Hormigón | B27: 3.04 | C27: Zapata corrida tabique - H30 (180 kg/m3 de hierro) | D27: m3 | E27: 4 | F27: 873810.75 | G27: 2151253.2 | H27: 0 | I27: =SUM(G27:H27) -> 2151253.2 | J27: 1292336 | K27: 0 | L27: =SUM(J27:K27) -> 1292336 | M27: 51653.837 | N27: =SUM(I27,L27) -> 3443589.2
A28: Hormigón | B28: 3.05 | C28: Bases aisladas - H30 (110 kg/m3 de hierro) | D28: m3 | E28: 2 | F28: 588775.24 | G28: 714292.34 | H28: 0 | I28: =SUM(G28:H28) -> 714292.34 | J28: 445855.92 | K28: 0 | L28: =SUM(J28:K28) -> 445855.92 | M28: 17402.224 | N28: =SUM(I28,L28) -> 1160148.3
A29: Hormigón | B29: 3.06 | C29: Cabezales - H30 (130 kg/m3 de hierro) | D29: m3 | E29: 11 | F29: 624746.84 | G29: 4318447.9 | H29: 0 | I29: =SUM(G29:H29) -> 4318447.9 | J29: 2452207.6 | K29: 0 | L29: =SUM(J29:K29) -> 2452207.6 | M29: 101559.83 | N29: =SUM(I29,L29) -> 6770655.4
A30: Hormigón | B30: 3.07 | C30: Viga de fundación - H30 (180 kg/m3 de hierro) | D30: m3 | E30: 9 | F30: 873810.75 | G30: 4840319.6 | H30: 0 | I30: =SUM(G30:H30) -> 4840319.6 | J30: 2907756 | K30: 0 | L30: =SUM(J30:K30) -> 2907756 | M30: 116221.13 | N30: =SUM(I30,L30) -> 7748075.6
B31: 3.08 | C31: Tabique submuración - H30 (90 kg/m3 de hierro) | D31: m3 | E31: 9 | F31: 798886.83 | G31: 3549617 | H31: 0 | I31: =SUM(G31:H31) -> 3549617 | J31: 3534108.6 | K31: 0 | L31: =SUM(J31:K31) -> 3534108.6 | M31: 106255.88 | N31: =SUM(I31,L31) -> 7083725.6
A32: Hormigón | B32: 3.09 | C32: Puntales de compresión/codales - H30 (120 kg/m3) | D32: m3 | E32: 1 | F32: 917809.34 | G32: 542036.05 | H32: 0 | I32: =SUM(G32:H32) -> 542036.05 | J32: 362209.61 | K32: 0 | L32: =SUM(J32:K32) -> 362209.61 | M32: 13563.685 | N32: =SUM(I32,L32) -> 904245.66
A33: Hormigón | B33: 3.1 | C33: Columna - H30 (240 kg/m3 de hierro) | D33: m3 | E33: 32 | F33: 1025724.1 | G33: 20747394 | H33: 0 | I33: =SUM(G33:H33) -> 20747394 | J33: 11590707 | K33: 0 | L33: =SUM(J33:K33) -> 11590707 | M33: 485071.52 | N33: =SUM(I33,L33) -> 32338101
A34: Hormigón | B34: 3.11 | C34: Tabiques - H30 (120 kg/m3 de hierro) | D34: m3 | E34: 30 | F34: 852844.23 | G34: 13426857 | H34: 0 | I34: =SUM(G34:H34) -> 13426857 | J34: 11780362 | K34: 0 | L34: =SUM(J34:K34) -> 11780362 | M34: 378108.28 | N34: =SUM(I34,L34) -> 25207219
A35: Hormigón | B35: 3.12 | C35: Viga H° Visto - H30 (120 kg/m3 de hierro) | D35: m3 | E35: 7 | F35: 1272170.3 | G35: 3264725.1 | H35: 0 | I35: =SUM(G35:H35) -> 3264725.1 | J35: 4407090.5 | K35: 1101772.6 | L35: =SUM(J35:K35) -> 5508863.1 | M35: 131603.82 | N35: =SUM(I35,L35) -> 8773588.2
A36: Hormigón | B36: 3.13 | C36: Viga apeo s/PB - H30 (180 kg/m3 de hierro) | D36: m3 | E36: 12 | F36: 1385830.2 | G36: 6940434.1 | H36: 0 | I36: =SUM(G36:H36) -> 6940434.1 | J36: 7555012.3 | K36: 1888753.1 | L36: =SUM(J36:K36) -> 9443765.3 | M36: 245762.99 | N36: =SUM(I36,L36) -> 16384199
A37: Hormigón | B37: 3.14 | C37: Viga - H30 (120 kg/m3 de hierro) | D37: m3 | E37: 41 | F37: 1118158.4 | G37: 19354030 | H37: 0 | I37: =SUM(G37:H37) -> 19354030 | J37: 25812959 | K37: 0 | L37: =SUM(J37:K37) -> 25812959 | M37: 677504.83 | N37: =SUM(I37,L37) -> 45166988
A38: Hormigón | B38: 3.15 | C38: Losa - H30 (95 kg/m3 de hierro) | D38: m3 | E38: 135 | F38: 624423.61 | G38: 48811035 | H38: 0 | I38: =SUM(G38:H38) -> 48811035 | J38: 34240381 | K38: 0 | L38: =SUM(J38:K38) -> 34240381 | M38: 1245771.2 | N38: =SUM(I38,L38) -> 83051416
A39: Hormigón | B39: 3.16 | C39: Losa H° Visto - H30 (95 kg/m3 de hierro) | D39: m3 | E39: 13 | F39: 695310.64 | G39: 4783929.2 | H39: 0 | I39: =SUM(G39:H39) -> 4783929.2 | J39: 3297221.9 | K39: 824305.46 | L39: =SUM(J39:K39) -> 4121527.3 | M39: 133581.85 | N39: =SUM(I39,L39) -> 8905456.5
A40: Hormigón | B40: 3.17 | C40: Escalera - H30 (105 kg/m3) | D40: m3 | E40: 14 | F40: 786954.25 | G40: 5668183.3 | H40: 0 | I40: =SUM(G40:H40) -> 5668183.3 | J40: 5186358.1 | K40: 0 | L40: =SUM(J40:K40) -> 5186358.1 | M40: 162818.12 | N40: =SUM(I40,L40) -> 10854541
A41: Hormigón | B41: 3.18 | C41: Viga alero - H30 (120 kg/m3 de hierro) | D41: m3 | E41: 2 | F41: 1272170.3 | G41: 932778.6 | H41: 0 | I41: =SUM(G41:H41) -> 932778.6 | J41: 1259168.7 | K41: 314792.18 | L41: =SUM(J41:K41) -> 1573960.9 | M41: 37601.092 | N41: =SUM(I41,L41) -> 2506739.5
A42: Hormigón | B42: 3.19 | C42: Sistema de apuntalamiento y reapuntalamiento | D42: gl | E42: 1 | F42: 10584988 | G42: 0 | H42: 0 | I42: =SUM(G42:H42) -> 0 | J42: 0 | K42: 0 | L42: =SUM(J42:K42) -> 0 | M42: 10584988 | N42: =SUM(I42,L42) -> 0
A43: Hormigón | B43: 3.2 | C43: Ensayos de Hormigon por etapas de hormigonado | D43: u | E43: 13 | F43: 246942.15 | G43: 0 | H43: 0 | I43: =SUM(G43:H43) -> 0 | J43: 3210247.9 | K43: 0 | L43: =SUM(J43:K43) -> 3210247.9 | M43: 0 | N43: =SUM(I43,L43) -> 3210247.9
... A45: Hormigón | B45: 3.22 | C45: Picado de medianeras para columnas y vigas - Cotizado solo para PB, 1P, NO contempla picado en CT | D45: m2 | E45: 65 | F45: 29896.607 | G45: 300000 | H45: 300000 | I45: =SUM(G45:H45) -> 600000 | J45: 0 | K45: 1314561.1 | L45: =SUM(J45:K45) -> 1314561.1 | M45: 28718.416 | N45: =SUM(I45,L45) -> 1914561.1
B46: 24 | C46: AYUDA DE GREMIOS
A47: Albañilería | B47: 24.01 | C47: Sereno | D47: mes | E47: 10 | F47: 806885.99 | G47: 0 | H47: 0 | I47: =SUM(G47:H47) -> 0 | J47: =E47*F47 -> 8068859.9 | K47: 0 | L47: =SUM(J47:K47) -> 8068859.9 | M47: 0 | N47: =SUM(I47,L47) -> 8068859.9 | P47: Gastos generales
A48: Seguridad e Higiene | B48: 24.02 | C48: Tecnico de seguridad & higiene permanente en Obra | D48: mes | E48: 1 | F48: 1623254.5 | G48: 0 | H48: 0 | I48: =SUM(G48:H48) -> 0 | J48: =E48*F48 -> 1623254.5 | K48: 0 | L48: =SUM(J48:K48) -> 1623254.5 | M48: 0 | N48: =SUM(I48,L48) -> 1623254.5
A49: Seguridad e Higiene | B49: 24.03 | C49: Higiene y seguridad Res 51 | D49: mes | E49: 10 | F49: 300000 | G49: 0 | H49: 0 | I49: =SUM(G49:H49) -> 0 | J49: =E49*F49 -> 3000000 | K49: 0 | L49: =SUM(J49:K49) -> 3000000 | M49: 0 | N49: =SUM(I49,L49) -> 3000000
A50: Hormigón | B50: 24.04 | C50: Protecciones y defensas | D50: gl | E50: 1 | F50: 9821535.3 | G50: =E50*'01'!F204 -> 4076935.9 | H50: 0 | I50: =SUM(G50:H50) -> 4076935.9 | J50: =E50*'01'!I204 -> 600000 | K50: =E50*'01'!Q204 -> 4999453.5 | L50: =SUM(J50:K50) -> 5599453.5 | M50: =E50*'01'!R204 -> 145145.84 | N50: =SUM(I50,L50) -> 9676389.4
A51: Albañilería | B51: 24.05 | C51: Ayuda de gremios | D51: mes | E51: 10 | F51: 717889.74 | G51: 0 | H51: =$E$51*'01'!G205 -> 500000 | I51: =SUM(G51:H51) -> 500000 | J51: 0 | K51: =E51*'01'!J205 -> 6572805.3 | L51: =SUM(J51:K51) -> 6572805.3 | M51: =10*'01'!L205 -> 106092.08 | N51: =SUM(I51,L51) -> 7072805.3
A52: Albañilería | B52: 24.06 | C52: Limpieza periódica | D52: mes | E52: 10 | F52: 651342.14 | G52: 0 | H52: =10*'01'!G206 -> 500000 | I52: =SUM(G52:H52) -> 500000 | J52: 0 | K52: =10*'01'!J206 -> 5917163.9 | L52: =SUM(J52:K52) -> 5917163.9 | M52: =10*'01'!L206 -> 96257.458 | N52: =SUM(I52,L52) -> 6417163.9
A53: Movilidad | B53: 24.08 | C53: Fletes | D53: mes | E53: 10 | F53: 300000 | G53: 0 | H53: 0 | I53: =SUM(G53:H53) -> 0 | J53: =E53*'01'!I208 -> 3000000 | K53: 0 | L53: =SUM(J53:K53) -> 3000000 | M53: 0 | N53: =SUM(I53,L53) -> 3000000
A54: Gastos Generales Obra | B54: 24.09 | C54: Volquetes | D54: mes | E54: 10 | F54: 271249.11 | G54: =E54*'01'!F209 -> 2000000 | H54: 0 | I54: =SUM(G54:H54) -> 2000000 | J54: 0 | K54: =E54*'01'!J209 -> 672404.99 | L54: =SUM(J54:K54) -> 672404.99 | M54: =10*'01'!L209 -> 40086.075 | N54: =SUM(I54,L54) -> 2672405
B55: 25 | C55: JEFATURA DE OBRA
A56: Supervisión de Obra | B56: 25.01 | C56: Proyecto Ejecutivo y Supervisión profesional de Obra | D56: mes | E56: 10 | F56: 3246508.9 | G56: 0 | H56: 0 | I56: =SUM(G56:H56) -> 0 | J56: =E56*'01'!I211 -> 32465089 | K56: 0 | L56: =SUM(J56:K56) -> 32465089 | M56: 0 | N56: =SUM(I56,L56) -> 32465089
A57: Movilidad | B57: 25.02 | C57: Movilidad y viaticos | D57: mes | E57: 10 | F57: 500000 | G57: 0 | H57: 0 | I57: =SUM(G57:H57) -> 0 | J57: =E57*'01'!I212 -> 5000000 | K57: 0 | L57: =SUM(J57:K57) -> 5000000 | M57: 0 | N57: =SUM(I57,L57) -> 5000000
B58: A | C58: PTO 01 SUBTOTAL SIN IVA | P58: PTO 01 | Q58: =SUM(#REF!) -> #REF! | R58: =+Q58-#REF! -> #REF!
R59: =Q59-P59 -> 0
B60: 4 | C60: MAMPOSTERÍA
A61: Albañilería | B61: 4.01 | C61: Muro tipo 1 (interiores, divisorio de locales) e: 10 cm - Ladrillo hueco 08 x 18 x 33 | D61: m2 | E61: 437 | F61: 21070.744 | G61: 0 | H61: 4393505.4 | I61: =SUM(G61:H61) -> 4393505.4 | J61: 0 | K61: 4702633.8 | L61: =SUM(J61:K61) -> 4702633.8 | M61: 111776.09 | N61: =SUM(I61,L61) -> 9096139.2
A62: Albañilería | B62: 4.02 | C62: Muro tipo 2 y 3 (medianera, caja de escaleras y ascensor) e: 15 cm - Ladrillo hueco portante 12 x 19 x 33 | D62: m2 | E62: 723 | F62: 29224.217 | G62: 0 | H62: 13163849 | I62: =SUM(G62:H62) -> 13163849 | J62: 0 | K62: 7780330.1 | L62: =SUM(J62:K62) -> 7780330.1 | M62: 184929.32 | N62: =SUM(I62,L62) -> 20944179
A63: Albañilería | B63: 4.03 | C63: Muro tipo 4 (divisorio de unidades y fachadas) e: 15 cm - Ladrillo hueco 12 x 18 x 33 | D63: m2 | E63: 1008 | F63: 23481.994 | G63: 0 | H63: 12564758 | I63: =SUM(G63:H63) -> 12564758 | J63: 0 | K63: 10847265 | L63: =SUM(J63:K63) -> 10847265 | M63: 257826.77 | N63: =SUM(I63,L63) -> 23412023
A64: Albañilería | B64: 4.04 | C64: Enchape medianeras existentes - Contemplamos picado zonas sueltas y enchape con ladrillo comun para PB y 1° | D64: m2 | E64: 199 | F64: 11705.455 | G64: 0 | H64: 1207748.3 | I64: =SUM(G64:H64) -> 1207748.3 | J64: 0 | K64: 1070737 | L64: =SUM(J64:K64) -> 1070737 | M64: 50900.324 | N64: =SUM(I64,L64) -> 2278485.3
A65: Albañilería | B65: 4.05 | C65: Muro de tabique seco ignifugo | D65: m2 | E65: 34 | F65: 57103.476 | G65: 984099.57 | H65: 0 | I65: =SUM(G65:H65) -> 984099.57 | J65: 942419.23 | K65: 0 | L65: =SUM(J65:K65) -> 942419.23 | M65: 14999.384 | N65: =SUM(I65,L65) -> 1926518.8
A66: Albañilería | B66: 4.06 | C66: Vigas de encadenado - En muros de PB, incl. excavación y armado | D66: ml | E66: 24 | F66: 60658.588 | G66: 561720.28 | H66: 0 | I66: =SUM(G66:H66) -> 561720.28 | J66: 0 | K66: 872571.45 | L66: =SUM(J66:K66) -> 872571.45 | M66: 21514.376 | N66: =SUM(I66,L66) -> 1434291.7
B67: 5 | C67: AISLACIONES
A68: Albañilería | B68: 5.01 | C68: Aislación hidrófuga horizontal (baños) - Inc. membrana geotextil y 35% en concepto de babetas | D68: m2 | E68: 79 | F68: 29049.768 | G68: 241020.04 | H68: 688628.68 | I68: =SUM(G68:H68) -> 929648.72 | J68: 353245.87 | K68: 1009273.9 | L68: =SUM(J68:K68) -> 1362519.8 | M68: 2763.1397 | N68: =SUM(I68,L68) -> 2292168.5
A69: Albañilería | B69: 5.02 | C69: Cajón hidrófugo - Muros de PB | D69: ml | E69: 113 | F69: 5288.3517 | G69: 0 | H69: 93482.483 | I69: =SUM(G69:H69) -> 93482.483 | J69: 0 | K69: 488617.4 | L69: =SUM(J69:K69) -> 488617.4 | M69: 15483.857 | N69: =SUM(I69,L69) -> 582099.88
A70: Albañilería | B70: 5.03 | C70: Azotado hidrófugo - Sobre contrapiso en vereda y PB | D70: m2 | E70: 207 | F70: 5288.3517 | G70: 0 | H70: 171246.67 | I70: =SUM(G70:H70) -> 171246.67 | J70: 0 | K70: 895077.89 | L70: =SUM(J70:K70) -> 895077.89 | M70: 28364.233 | N70: =SUM(I70,L70) -> 1066324.6
A71: Albañilería | B71: 5.04 | C71: Aislación térmica en terrazas, eps e:2,00 cm | D71: m2 | E71: 165 | F71: 3538.08 | G71: 0 | H71: 583783.2 | I71: =SUM(G71:H71) -> 583783.2 | J71: 0 | K71: 0 | L71: =SUM(J71:K71) -> 0 | M71: 0 | N71: =SUM(I71,L71) -> 583783.2
A72: Albañilería | B72: 5.05 | C72: Barrera de vapor | D72: m2 | E72: 165 | F72: 3421.2604 | G72: 0 | H72: 229780.61 | I72: =SUM(G72:H72) -> 229780.61 | J72: 0 | K72: 332923.88 | L72: =SUM(J72:K72) -> 332923.88 | M72: 1803.4733 | N72: =SUM(I72,L72) -> 562704.49
A73: Albañilería | B73: 5.06 | C73: Membrana asfaltica geotextil 4mm - Balcones y azotea - Inc. 20% en concepto de babetas | D73: m2 | E73: 274 | F73: 25825.902 | G73: 477681.67 | H73: 2388408.3 | I73: =SUM(G73:H73) -> 2866090 | J73: 700103.94 | K73: 3500519.7 | L73: =SUM(J73:K73) -> 4200623.6 | M73: 9583.5479 | N73: =SUM(I73,L73) -> 7066713.6
B74: 6 | C74: CUBIERTAS
A75: Albañilería | B75: 6.01 | C75: Babeta de chapa galvanizada en medianeras | D75: ml | E75: 44 | F75: 24788.127 | G75: 716979.9 | H75: 0 | I75: =SUM(G75:H75) -> 716979.9 | J75: 0 | K75: 357579.3 | L75: =SUM(J75:K75) -> 357579.3 | M75: 16118.388 | N75: =SUM(I75,L75) -> 1074559.2
B76: 7 | C76: REVOQUES
A77: Albañilería | B77: 7.01 | C77: Revoque Grueso Impermeable Exterior | D77: m2 | E77: 663 | F77: 16092.308 | G77: 0 | H77: 2692552.5 | I77: =SUM(G77:H77) -> 2692552.5 | J77: 0 | K77: 7755453.3 | L77: =SUM(J77:K77) -> 7755453.3 | M77: 221194.55 | N77: =SUM(I77,L77) -> 10448006
A78: Albañilería | B78: 7.02 | C78: Revoque Grueso Impermeable Exterior a mas de 3m - Medianero y fachadas | D78: m2 | E78: 1164 | F78: 21739.708 | G78: 0 | H78: 4727196.2 | I78: =SUM(G78:H78) -> 4727196.2 | J78: 0 | K78: 19572869 | L78: =SUM(J78:K78) -> 19572869 | M78: 1004954.3 | N78: =SUM(I78,L78) -> 24300065
A79: Albañilería | B79: 7.03 | C79: Buña en revoque - Estimados ml en medianeras | D79: ml | E79: 500 | F79: 11122.339 | G79: 0 | H79: 0 | I79: =SUM(G79:H79) -> 0 | J79: 5561169.6 | K79: 0 | L79: =SUM(J79:K79) -> 5561169.6 | M79: 0 | N79: =SUM(I79,L79) -> 5561169.6
A80: Albañilería | B80: 7.04 | C80: Revoque Grueso Interior + fino | D80: m2 | E80: 521 | F80: 26511.246 | G80: 0 | H80: 1506324.3 | I80: =SUM(G80:H80) -> 1506324.3 | J80: 0 | K80: 11972881 | L80: =SUM(J80:K80) -> 11972881 | M80: 333154.13 | N80: =SUM(I80,L80) -> 13479205
A81: Durlock | B81: 7.05 | C81: Yeso interior | D81: m2 | E81: 2180 | F81: 18303.917 | G81: 0 | H81: 12602290 | I81: =SUM(G81:H81) -> 12602290 | J81: 26710556 | K81: 0 | L81: =SUM(J81:K81) -> 26710556 | M81: 589692.69 | N81: =SUM(I81,L81) -> 39312846
A82: Durlock | B82: 7.06 | C82: Arista en yeso | D82: ml | E82: 255 | F82: 13341.751 | G82: 0 | H82: 0 | I82: =SUM(G82:H82) -> 0 | J82: 3351868.6 | K82: 0 | L82: =SUM(J82:K82) -> 3351868.6 | M82: 50278.029 | N82: =SUM(I82,L82) -> 3351868.6
A83: Durlock | B83: 7.07 | C83: Provisión y colocación de guardacanto yesero | D83: u | E83: 102 | F83: 15809.55 | G83: 0 | H83: 169128 | I83: =SUM(G83:H83) -> 169128 | J83: 1419614.9 | K83: 0 | L83: =SUM(J83:K83) -> 1419614.9 | M83: 23831.144 | N83: =SUM(I83,L83) -> 1588742.9
A84: Albañilería | B84: 7.08 | C84: Revoque Grueso Impermeable Interior b/ revestimiento | D84: m2 | E84: 715 | F84: 16092.308 | G84: 0 | H84: 2903733 | I84: =SUM(G84:H84) -> 2903733 | J84: 0 | K84: 8363724.1 | L84: =SUM(J84:K84) -> 8363724.1 | M84: 238543.14 | N84: =SUM(I84,L84) -> 11267457
B85: 8 | C85: CONTRAPISOS Y CARPETAS
A86: Albañilería | B86: 8.01 | C86: Contrapiso de cascotes s/ss e: 15 cm | D86: m2 | E86: 21 | F86: 33795.278 | G86: 0 | H86: 285501.86 | I86: =SUM(G86:H86) -> 285501.86 | J86: 0 | K86: 413620.06 | L86: =SUM(J86:K86) -> 413620.06 | M86: 10578.907 | N86: =SUM(I86,L86) -> 699121.92
A87: Albañilería | B87: 8.02 | C87: Contrapiso armado de H° pobre s/terreno natural e: 20 cm - Incluye film de polietileno | D87: m2 | E87: 201 | F87: 40319.335 | G87: 5711490 | H87: 510415.21 | I87: =SUM(G87:H87) -> 6221905.2 | J87: 0 | K87: 1762514.9 | L87: =SUM(J87:K87) -> 1762514.9 | M87: 119766.3 | N87: =SUM(I87,L87) -> 7984420.1
A88: Albañilería | B88: 8.03 | C88: Contrapiso de cascotes en azoteas c/pendiente e: 15 cm | D88: m2 | E88: 107 | F88: 33795.278 | G88: 0 | H88: 1454700 | I88: =SUM(G88:H88) -> 1454700 | J88: 0 | K88: 2107492.7 | L88: =SUM(J88:K88) -> 2107492.7 | M88: 53902.052 | N88: =SUM(I88,L88) -> 3562192.6
A89: Albañilería | B89: 8.04 | C89: Contrapiso - Carpeta monolitico e: 6 cm | D89: m2 | E89: 850 | F89: 17993.375 | G89: 0 | H89: 5710194 | I89: =SUM(G89:H89) -> 5710194 | J89: 0 | K89: 9473268.8 | L89: =SUM(J89:K89) -> 9473268.8 | M89: 110906.39 | N89: =SUM(I89,L89) -> 15183463
A90: Albañilería | B90: 8.05 | C90: Carpeta en PB, balcones, baños y azoteas e: 3,00 cm | D90: m2 | E90: 365 | F90: 11951.097 | G90: 0 | H90: 1248416.6 | I90: =SUM(G90:H90) -> 1248416.6 | J90: 0 | K90: 3027927.2 | L90: =SUM(J90:K90) -> 3027927.2 | M90: 85806.693 | N90: =SUM(I90,L90) -> 4276343.7
A91: Albañilería | B91: 8.06 | C91: Carpeta sobre membrana, e: 3,00 cm | D91: m2 | E91: 357 | F91: 11951.097 | G91: 0 | H91: 1221054 | I91: =SUM(G91:H91) -> 1221054 | J91: 0 | K91: 2961561.6 | L91: =SUM(J91:K91) -> 2961561.6 | M91: 83925.998 | N91: =SUM(I91,L91) -> 4182615.6
A92: Albañilería | B92: 8.07 | C92: Banquinas para cocinas - N/A | D92: gl | E92: 0 | F92: 0 | G92: 0 | H92: 0 | I92: =SUM(G92:H92) -> 0 | J92: 0 | K92: 0 | L92: =SUM(J92:K92) -> 0 | M92: 0 | N92: =SUM(I92,L92) -> 0
A93: Albañilería | B93: 8.08 | C93: Banquinas para bombas, TT, etc. h: 15 cm | D93: gl | E93: 1 | F93: 403148.91 | G93: 0 | H93: 93485.024 | I93: =SUM(G93:H93) -> 93485.024 | J93: 0 | K93: 303706.02 | L93: =SUM(J93:K93) -> 303706.02 | M93: 5957.8657 | N93: =SUM(I93,L93) -> 397191.05
B94: 9 | C94: ESCALERAS
A95: Albañilería | B95: 9.01 | C95: Provisión y ejecución de alisado de cemento en pedadas y alzadas | D95: gl | E95: 1 | F95: 2509350.4 | G95: 427508.24 | H95: 0 | I95: =SUM(G95:H95) -> 427508.24 | J95: 0 | K95: 2044758.2 | L95: =SUM(J95:K95) -> 2044758.2 | M95: 37083.997 | N95: =SUM(I95,L95) -> 2472266.4
A96: Albañilería | B96: 9.02 | C96: Provisión y colocación de nariz metálica en escalones | D96: gl | E96: 1 | F96: 2273294.5 | G96: 463902.77 | H96: 0 | I96: =SUM(G96:H96) -> 463902.77 | J96: 0 | K96: 1775796.2 | L96: =SUM(J96:K96) -> 1775796.2 | M96: 33595.485 | N96: =SUM(I96,L96) -> 2239699
A97: Albañilería | B97: 9.03 | C97: Zócalo de concreto en escalera - No incluye el ojo | D97: ml | E97: 114 | F97: 9612.3994 | G97: 0 | H97: 94309.762 | I97: =SUM(G97:H97) -> 94309.762 | J97: 492941.45 | K97: 492941.45 | L97: =SUM(J97:K97) -> 985882.89 | M97: 15620.882 | N97: =SUM(I97,L97) -> 1080192.7
B98: 10 | C98: VENTILACIONES - PROVISION COTIZADA EN ITEM 26
A99: Albañilería | B99: 10.01 | C99: Colocación de ventilación de conducto de humos. Inc. toma de aire en PB | D99: gl | E99: 1 | F99: 1941789.2 | G99: 250000 | H99: 0 | I99: =SUM(G99:H99) -> 250000 | J99: 0 | K99: 1663092.8 | L99: =SUM(J99:K99) -> 1663092.8 | M99: 28696.391 | N99: =SUM(I99,L99) -> 1913092.8
A100: Albañilería | B100: 10.02 | C100: Colocación y montaje de conducto de ventilación en baños | D100: gl | E100: 1 | F100: 1941789.2 | G100: 250000 | H100: 0 | I100: =SUM(G100:H100) -> 250000 | J100: 0 | K100: 1663092.8 | L100: =SUM(J100:K100) -> 1663092.8 | M100: 28696.391 | N100: =SUM(I100,L100) -> 1913092.8
A101: Albañilería | B101: 10.03 | C101: Colocación sombreretes en chapa prepintada C25 - Provisión en item 26 | D101: u | E101: 7 | F101: 128708.25 | G101: 222405.97 | H101: 0 | I101: =SUM(G101:H101) -> 222405.97 | J101: 0 | K101: 665237.1 | L101: =SUM(J101:K101) -> 665237.1 | M101: 13314.646 | N101: =SUM(I101,L101) -> 887643.07
B102: 11 | C102: PISOS - PROVISION A CARGO DEL COMITENTE
A103: Revestimiento | B103: 11.01 | C103: Colocación de baldosas en palieres - Provisión a cargo del comitente | D103: m2 | E103: 101 | F103: 19970.726 | G103: 0 | H103: 700159.35 | I103: =SUM(G103:H103) -> 700159.35 | J103: 0 | K103: 1292095.1 | L103: =SUM(J103:K103) -> 1292095.1 | M103: 24788.855 | N103: =SUM(I103,L103) -> 1992254.5
...

Sheet 01
F1: OK | G1: Listo | V1: DÓLAR BNA | W1: DÓLAR MEP
F2: IN | G2: Estimado | V2: =+[9]GGBB!G4 -> 1280 | W2: =+[9]GGBB!H4 -> 1276
F3: C | G3: Chekear (Inventado)
F4: R | G4: Sin hacer/revisar | V4: 45817
C5: OBRA: EDIFICIO CHIVILCOY 2171 | F5: MATERIAL | I5: M. DE OBRA | N5: MATERIAL | P5: M. DE OBRA | T5: =+[9]GGBB!F61 -> 1.3564671
C6: PRESUPUESTO OBRA CIVIL | T6: 1.1
B7: E | C7: Descripción | D7: U | E7: Cant | F7: Otro | G7: Corralón | H7: Total | I7: Otro | J7: Albañil | K7: Total | L7: EQUIPOS | M7: P.Unit | N7: Otro | O7: Corralón | P7: Otro | Q7: Albañil | R7: EQUIPOS | S7: Total | T7: Subtotal | U7: P unit | V7: Subtotal
A8: 1 | C8: TAREAS PRELIMINARES | T8: =SUM(S9:S17) -> 17207623 | W8: =SUM(V9:V17) -> 23341584 | X8: =+W8/$W$213 -> 0.015150744
A9: 1.01 | B9: OK | C9: Limpieza y preparación del terreno - No cotiza | D9: gl | E9: 0 | H9: =F9+G9 -> 0 | K9: =I9+J9 -> 0 | M9: =H9+K9+L9 -> 0 | N9: =F9*E9 -> 0 | O9: =G9*E9 -> 0 | P9: =I9*E9 -> 0 | Q9: =J9*E9 -> 0 | R9: =+L9*E9 -> 0 | S9: =SUM(N9:R9) -> 0 | U9: =+ROUNDUP(M9*$T$5,0) -> 0 | V9: =+U9*E9 -> 0
A10: 1.02 | B10: OK | C10: Topógrafo - Visita de obra replanteo | D10: un | E10: 4 | F10: =+[9]Tareas!H8 -> 0 | G10: =+[9]Tareas!I8 -> 25000 | H10: =F10+G10 -> 25000 | I10: =+[9]Tareas!Q8 -> 214394.06 | J10: =+[9]Tareas!R8 -> 67240.499 | K10: =I10+J10 -> 281634.56 | L10: =+(H10+K10)*0.015 -> 4599.5184 | M10: =H10+K10+L10 -> 311234.08 | N10: =F10*E10 -> 0 | O10: =G10*E10 -> 100000 | P10: =I10*E10 -> 857576.25 | Q10: =J10*E10 -> 268962 | R10: =+L10*E10 -> 18398.074 | S10: =SUM(N10:R10) -> 1244936.3 | U10: =+ROUNDUP(M10*$T$5,0) -> 422179 | V10: =+U10*E10 -> 1688716
A11: 1.03 | B11: OK | C11: Cartel de Obra - No cotiza | D11: gl | E11: 1 | H11: =F11+G11 -> 0 | K11: =I11+J11 -> 0 | M11: =H11+K11+L11 -> 0 | N11: =F11*E11 -> 0 | O11: =G11*E11 -> 0 | P11: =I11*E11 -> 0 | Q11: =J11*E11 -> 0 | R11: =+L11*E11 -> 0 | S11: =SUM(N11:R11) -> 0 | U11: =+ROUNDUP(M11*$T$5,0) -> 0 | V11: =+U11*E11 -> 0
A12: 1.04 | B12: OK | C12: Cerco de obra perimetral - En chapa C25 + Concertina + Porton corredizo | D12: ml | E12: 10 | F12: =+[9]Tareas!H12 -> 98815.568 | G12: =+[9]Tareas!I12 -> 0 | H12: =F12+G12 -> 98815.568 | I12: =+[9]Tareas!Q12 -> 0 | J12: =+[9]Tareas!R12 -> 111992.57 | K12: =I12+J12 -> 111992.57 | L12: =+(H12+K12)*0.015 -> 3162.1221 | M12: =H12+K12+L12 -> 213970.27 | N12: =F12*E12 -> 988155.68 | O12: =G12*E12 -> 0 | P12: =I12*E12 -> 0 | Q12: =J12*E12 -> 1119925.7 | R12: =+L12*E12 -> 31621.221 | S12: =SUM(N12:R12) -> 2139702.7 | U12: =+ROUNDUP(M12*$T$5,0) -> 290244 | V12: =+U12*E12 -> 2902440
A13: 1.05 | B13: OK | C13: Obrador, pañol y ducha | D13: gl | E13: 1 | F13: =+[9]Tareas!H23 -> 2270625.2 | G13: =+[9]Tareas!I23 -> 300000 | H13: =F13+G13 -> 2570625.2 | I13: =+[9]Tareas!Q23 -> 1000000 | J13: =+[9]Tareas!R23 -> 5023936.4 | K13: =I13+J13 -> 6023936.4 | L13: =+(H13+K13)*0.015 -> 128918.42 | M13: =H13+K13+L13 -> 8723480 | N13: =F13*E13 -> 2270625.2 | O13: =G13*E13 -> 300000 | P13: =I13*E13 -> 1000000 | Q13: =J13*E13 -> 5023936.4 | R13: =+L13*E13 -> 128918.42 | S13: =SUM(N13:R13) -> 8723480 | U13: =+ROUNDUP(M13*$T$5,0) -> 11833114 | V13: =+U13*E13 -> 11833114
A14: 1.06 | B14: OK | C14: Alquiler de baños quimicos y duchas portatiles | D14: mes | E14: 4 | F14: =+[9]Tareas!H47 -> 0 | G14: =+[9]Tareas!I47 -> 0 | H14: =F14+G14 -> 0 | I14: =+[9]Tareas!Q47 -> 260000 | J14: =+[9]Tareas!R47 -> 0 | K14: =I14+J14 -> 260000 | M14: =H14+K14+L14 -> 260000 | N14: =F14*E14 -> 0 | O14: =G14*E14 -> 0 | P14: =I14*E14 -> 1040000 | Q14: =J14*E14 -> 0 | R14: =+L14*E14 -> 0 | S14: =SUM(N14:R14) -> 1040000 | U14: =+ROUNDUP(M14*$T$5,0) -> 352682 | V14: =+U14*E14 -> 1410728
A15: 1.07 | B15: OK | C15: Conexión pilar y luz de obra + Tablero de obra | D15: gl | E15: 1 | F15: =+[9]Tareas!H52 -> 1290000 | G15: =+[9]Tareas!I52 -> 100000 | H15: =F15+G15 -> 1390000 | I15: =+[9]Tareas!Q52 -> 0 | J15: =+[9]Tareas!R52 -> 661285.32 | K15: =I15+J15 -> 661285.32 | L15: =+(H15+K15)*0.015 -> 30769.28 | M15: =H15+K15+L15 -> 2082054.6 | N15: =F15*E15 -> 1290000 | O15: =G15*E15 -> 100000 | P15: =I15*E15 -> 0 | Q15: =J15*E15 -> 661285.32 | R15: =+L15*E15 -> 30769.28 | S15: =SUM(N15:R15) -> 2082054.6 | U15: =+ROUNDUP(M15*$T$5,0) -> 2824239 | V15: =+U15*E15 -> 2824239
A16: 1.08 | B16: OK | C16: Conexión agua de obra, tanque + bomba | D16: gl | E16: 1 | F16: =+[9]Tareas!H59 -> 936000 | G16: =+[9]Tareas!I59 -> 0 | H16: =F16+G16 -> 936000 | I16: =+[9]Tareas!Q59 -> 0 | J16: =+[9]Tareas!R59 -> 536368.95 | K16: =I16+J16 -> 536368.95 | L16: =+(H16+K16)*0.015 -> 22085.534 | M16: =H16+K16+L16 -> 1494454.5 | N16: =F16*E16 -> 936000 | O16: =G16*E16 -> 0 | P16: =I16*E16 -> 0 | Q16: =J16*E16 -> 536368.95 | R16: =+L16*E16 -> 22085.534 | S16: =SUM(N16:R16) -> 1494454.5 | U16: =+ROUNDUP(M16*$T$5,0) -> 2027179 | V16: =+U16*E16 -> 2027179
A17: 1.09 | B17: OK | C17: Tramite luz de obra, certificado luz de obra (2) y medición PAT | D17: gl | E17: 1 | F17: =+[9]Tareas!H69 -> 0 | G17: =+[9]Tareas!I69 -> 0 | H17: =F17+G17 -> 0 | I17: =+[9]Tareas!Q69 -> 482995.31 | J17: =+[9]Tareas!R69 -> 0 | K17: =I17+J17 -> 482995.31 | M17: =H17+K17+L17 -> 482995.31 | N17: =F17*E17 -> 0 | O17: =G17*E17 -> 0 | P17: =I17*E17 -> 482995.31 | Q17: =J17*E17 -> 0 | R17: =+L17*E17 -> 0 | S17: =SUM(N17:R17) -> 482995.31 | U17: =+ROUNDUP(M17*$T$5,0) -> 655168 | V17: =+U17*E17 -> 655168
A18: 2 | C18: MOVIMIENTO DE TIERRA, COMPACTACION Y RELLENO | T18: =SUM(S19:S22) -> 12400628 | W18: =SUM(V19:V22) -> 16821282 | X18: =+W18/$W$213 -> 0.010918493
A19: 2.01 | B19: OK | C19: Retiro de suelo vegetal e: 50 cm, aporte y compactación de tosca e: 40 cm (dos capas de 20 cm) | D19: m2 | E19: =+[9]Exc.!G53 -> 219 | F19: =+[9]Tareas!H74 -> 0 | G19: =+[9]Tareas!I74 -> 0 | H19: =F19+G19 -> 0 | I19: =+[9]Tareas!Q74 -> 25907.444 | J19: =+[9]Tareas!R74 -> 3070.3424 | K19: =I19+J19 -> 28977.787 | M19: =H19+K19+L19 -> 28977.787 | N19: =F19*E19 -> 0 | O19: =G19*E19 -> 0 | P19: =I19*E19 -> 5673730.3 | Q19: =J19*E19 -> 672404.99 | R19: =+L19*E19 -> 0 | S19: =SUM(N19:R19) -> 6346135.3 | U19: =+ROUNDUP(M19*$T$5,0) -> 39308 | V19: =+U19*E19 -> 8608452
A20: 2.02 | B20: OK | C20: Excavación para cámara transformadora | D20: m3 | E20: =+[9]Exc.!I6 -> 100 | F20: =+[9]Tareas!H77 -> 0 | G20: =+[9]Tareas!I77 -> 0 | H20: =F20+G20 -> 0 | I20: =+[9]Tareas!Q77 -> 24440 | J20: =+[9]Tareas!R77 -> 6724.0499 | K20: =I20+J20 -> 31164.05 | L20: =+(H20+K20)*0.015 -> 467.46075 | M20: =H20+K20+L20 -> 31631.511 | N20: =F20*E20 -> 0 | O20: =G20*E20 -> 0 | P20: =I20*E20 -> 2444000 | Q20: =J20*E20 -> 672404.99 | R20: =+L20*E20 -> 46746.075 | S20: =SUM(N20:R20) -> 3163151.1 | U20: =+ROUNDUP(M20*$T$5,0) -> 42908 | V20: =+U20*E20 -> 4290800
A21: 2.03 | B21: OK | C21: Excavación manual para tensores y vigas de fundación | D21: m3 | E21: =+[9]Exc.!I8 -> 43 | H21: =F21+G21 -> 0 | J21: =+'[9]P.MO 06.25'!B7 -> 67240.499 | K21: =I21+J21 -> 67240.499 | M21: =H21+K21+L21 -> 67240.499 | N21: =F21*E21 -> 0 | O21: =G21*E21 -> 0 | P21: =I21*E21 -> 0 | Q21: =J21*E21 -> 2891341.5 | R21: =+L21*E21 -> 0 | S21: =SUM(N21:R21) -> 2891341.5 | U21: =+ROUNDUP(M21*$T$5,0) -> 91210 | V21: =+U21*E21 -> 3922030
A22: 2.04 | B22: OK | C22: Demolición y retiro de fundaciones existentes - No cotiza | D22: gl | E22: 0 | H22: =F22+G22 -> 0 | K22: =I22+J22 -> 0 | M22: =H22+K22+L22 -> 0 | N22: =F22*E22 -> 0 | O22: =G22*E22 -> 0 | P22: =I22*E22 -> 0 | Q22: =J22*E22 -> 0 | R22: =+L22*E22 -> 0 | S22: =SUM(N22:R22) -> 0 | U22: =+ROUNDUP(M22*$T$5,0) -> 0 | V22: =+U22*E22 -> 0
A23: 3 | C23: ESTRUCTURA RESISTENTE | T23: =SUM(S24:S45) -> 3.3368577e+08 | W23: =SUM(V24:V45) -> 452634067 | X23: =+W23/$W$213 -> 0.29379937 | Y23: M.O HA | Z23: =+SUM(P24:R41,Q19:R21)-P25 -> 1.3371847e+08
A24: 3.01 | B24: OK | C24: Hormigón de limpieza - e: 10 cm | D24: m3 | E24: 3 | F24: =+[9]Tareas!H83 -> 120430 | G24: =+[9]Tareas!I83 -> 0 | H24: =F24+G24 -> 120430 | I24: =+[9]Tareas!Q83 -> 0 | J24: =+[9]Tareas!R83 -> 155041.22 | K24: =I24+J24 -> 155041.22 | L24: =+(H24+K24)*0.015 -> 4132.0683 | M24: =H24+K24+L24 -> 279603.29 | N24: =F24*E24 -> 361290 | O24: =G24*E24 -> 0 | P24: =I24*E24 -> 0 | Q24: =J24*E24 -> 465123.66 | R24: =+L24*E24 -> 12396.205 | S24: =SUM(N24:R24) -> 838809.86 | U24: =+ROUNDUP(M24*$T$5,0) -> 379273 | V24: =+U24*E24 -> 1137819 | Y24: S/cargas | Z24: =+Z23/AA24 -> 83574041 | AA24: 1.6
A25: 3.02 | B25: OK | C25: Micropilotes Ø 20 cm | D25: gl | E25: 1 | F25: =+[9]Tareas!H88 -> 11090041 | G25: =+[9]Tareas!I88 -> 0 | H25: =F25+G25 -> 11090041 | I25: =+[9]Tareas!Q88 -> 34350000 | J25: =+[9]Tareas!R88 -> 2460301.5 | K25: =I25+J25 -> 36810301 | L25: =+(H25+K25)*0.015 -> 718505.14 | M25: =H25+K25+L25 -> 48618848 | N25: =F25*E25 -> 11090041 | O25: =G25*E25 -> 0 | P25: =I25*E25 -> 34350000 | Q25: =J25*E25 -> 2460301.5 | R25: =+L25*E25 -> 718505.14 | S25: =SUM(N25:R25) -> 48618848 | U25: =+ROUNDUP(M25*$T$5,0) -> 65949869 | V25: =+U25*E25 -> 65949869 | Y25: Meses | Z25: =+Z24/Z26 -> 8.1451198
A26: 3.03 | B26: OK | C26: Platea - H30 (110 kg/m3 de hierro) | D26: m3 | E26: =+'[9]H°A° '!O4 -> 7 | F26: =+'[9]H°A° '!F47 -> 357146.17 | H26: =F26+G26 -> 357146.17 | I26: =+'[9]MO HA AING'!C5 -> 222927.96 | K26: =I26+J26 -> 222927.96 | L26: =+(H26+K26)*0.015 -> 8701.1119 | M26: =H26+K26+L26 -> 588775.24 | N26: =F26*E26 -> 2500023.2 | O26: =G26*E26 -> 0 | P26: =I26*E26 -> 1560495.7 | Q26: =J26*E26 -> 0 | R26: =+L26*E26 -> 60907.784 | S26: =SUM(N26:R26) -> 4121426.7 | U26: =+ROUNDUP(M26*$T$5,0) -> 798655 | V26: =+U26*E26 -> 5590585 | Y26: Cuadrilla (9) | Z26: =9*'[9]P.MO 06.25'!F5*22 -> 10260628
A27: 3.04 | B27: OK | C27: Zapata corrida tabique - H30 (180 kg/m3 de hierro) | D27: m3 | E27: =+'[9]H°A° '!O5 -> 4 | F27: =+'[9]H°A° '!F48 -> 537813.29 | H27: =F27+G27 -> 537813.29 | I27: =+'[9]MO HA AING'!C6 -> 323084 | K27: =I27+J27 -> 323084 | L27: =+(H27+K27)*0.015 -> 12913.459 | M27: =H27+K27+L27 -> 873810.75 | N27: =F27*E27 -> 2151253.2 | O27: =G27*E27 -> 0 | P27: =I27*E27 -> 1292336 | Q27: =J27*E27 -> 0 | R27: =+L27*E27 -> 51653.837 | S27: =SUM(N27:R27) -> 3495243 | U27: =+ROUNDUP(M27*$T$5,0) -> 1185296 | V27: =+U27*E27 -> 4741184
A28: 3.05 | B28: OK | C28: Bases aisladas - H30 (110 kg/m3 de hierro) | D28: m3 | E28: =+'[9]H°A° '!O6 -> 2 | F28: =+'[9]H°A° '!F49 -> 357146.17 | H28: =F28+G28 -> 357146.17 | I28: =+'[9]MO HA AING'!C5 -> 222927.96 | K28: =I28+J28 -> 222927.96 | L28: =+(H28+K28)*0.015 -> 8701.1119 | M28: =H28+K28+L28 -> 588775.24 | N28: =F28*E28 -> 714292.34 | O28: =G28*E28 -> 0 | P28: =I28*E28 -> 445855.92 | Q28: =J28*E28 -> 0 | R28: =+L28*E28 -> 17402.224 | S28: =SUM(N28:R28) -> 1177550.5 | U28: =+ROUNDUP(M28*$T$5,0) -> 798655 | V28: =+U28*E28 -> 1597310
A29: 3.06 | B29: OK | C29: Cabezales - H30 (130 kg/m3 de hierro) | D29: m3 | E29: =+'[9]H°A° '!O7 -> 11 | F29: =+'[9]H°A° '!F50 -> 392586.17 | H29: =F29+G29 -> 392586.17 | I29: =+'[9]MO HA AING'!C5 -> 222927.96 | K29: =I29+J29 -> 222927.96 | L29: =+(H29+K29)*0.015 -> 9232.7119 | M29: =H29+K29+L29 -> 624746.84 | N29: =F29*E29 -> 4318447.9 | O29: =G29*E29 -> 0 | P29: =I29*E29 -> 2452207.6 | Q29: =J29*E29 -> 0 | R29: =+L29*E29 -> 101559.83 | S29: =SUM(N29:R29) -> 6872215.3 | U29: =+ROUNDUP(M29*$T$5,0) -> 847449 | V29: =+U29*E29 -> 9321939
A30: 3.07 | B30: OK | C30: Viga de fundación - H30 (180 kg/m3 de hierro) | D30: m3 | E30: =+'[9]H°A° '!O8 -> 9 | F30: =+'[9]H°A° '!F51 -> 537813.29 | H30: =F30+G30 -> 537813.29 | I30: =+'[9]MO HA AING'!C6 -> 323084 | K30: =I30+J30 -> 323084 | L30: =+(H30+K30)*0.015 -> 12913.459 | M30: =H30+K30+L30 -> 873810.75 | N30: =F30*E30 -> 4840319.6 | O30: =G30*E30 -> 0 | P30: =I30*E30 -> 2907756 | Q30: =J30*E30 -> 0 | R30: =+L30*E30 -> 116221.13 | S30: =SUM(N30:R30) -> 7864296.7 | U30: =+ROUNDUP(M30*$T$5,0) -> 1185296 | V30: =+U30*E30 -> 10667664
A31: 3.08 | B31: OK | C31: Tabique submuración - H30 (90 kg/m3 de hierro) | D31: m3 | E31: =+'[9]H°A° '!O9 -> 9 | F31: =+'[9]H°A° '!F52 -> 394401.89 | H31: =F31+G31 -> 394401.89 | I31: =+'[9]MO HA AING'!D72 -> 392678.73 | K31: =I31+J31 -> 392678.73 | L31: =+(H31+K31)*0.015 -> 11806.209 | M31: =H31+K31+L31 -> 798886.83 | N31: =F31*E31 -> 3549617 | O31: =G31*E31 -> 0 | P31: =I31*E31 -> 3534108.6 | Q31: =J31*E31 -> 0 | R31: =+L31*E31 -> 106255.88 | S31: =SUM(N31:R31) -> 7189981.5 | U31: =+ROUNDUP(M31*$T$5,0) -> 1083664 | V31: =+U31*E31 -> 9752976 | Y31: $ x m3 | Z31: =+Z24/AA31 -> 284265.44 | AA31: =+SUM(E31:E40) -> 294
A32: 3.09 | B32: OK | C32: Puntales de compresión/codales - H30 (120 kg/m3) | D32: m3 | E32: 1 | F32: =+'[9]H°A° '!F53 -> 542036.05 | H32: =F32+G32 -> 542036.05 | I32: =+'[9]MO HA AING'!D47 -> 362209.61 | K32: =I32+J32 -> 362209.61 | L32: =+(H32+K32)*0.015 -> 13563.685 | M32: =H32+K32+L32 -> 917809.34 | N32: =F32*E32 -> 542036.05 | O32: =G32*E32 -> 0 | P32: =I32*E32 -> 362209.61 | Q32: =J32*E32 -> 0 | R32: =+L32*E32 -> 13563.685 | S32: =SUM(N32:R32) -> 917809.34 | U32: =+ROUNDUP(M32*$T$5,0) -> 1244979 | V32: =+U32*E32 -> 1244979
A33: 3.1 | B33: OK | C33: Columna - H30 (240 kg/m3 de hierro) | D33: m3 | E33: =+'[9]H°A° '!O12 -> 32 | F33: =+'[9]H°A° '!F55 -> 648356.05 | H33: =F33+G33 -> 648356.05 | I33: =+'[9]MO HA AING'!D47 -> 362209.61 | K33: =I33+J33 -> 362209.61 | L33: =+(H33+K33)*0.015 -> 15158.485 | M33: =H33+K33+L33 -> 1025724.1 | N33: =F33*E33 -> 20747394 | O33: =G33*E33 -> 0 | P33: =I33*E33 -> 11590707 | Q33: =J33*E33 -> 0 | R33: =+L33*E33 -> 485071.52 | S33: =SUM(N33:R33) -> 32823173 | U33: =+ROUNDUP(M33*$T$5,0) -> 1391362 | V33: =+U33*E33 -> 44523584
A34: 3.11 | B34: OK | C34: Tabiques - H30 (120 kg/m3 de hierro) | D34: m3 | E34: =+'[9]H°A° '!O13 -> 30 | F34: =+'[9]H°A° '!F56 -> 447561.89 | H34: =F34+G34 -> 447561.89 | I34: =+'[9]MO HA AING'!D72 -> 392678.73 | K34: =I34+J34 -> 392678.73 | L34: =+(H34+K34)*0.015 -> 12603.609 | M34: =H34+K34+L34 -> 852844.23 | N34: =F34*E34 -> 13426857 | O34: =G34*E34 -> 0 | P34: =I34*E34 -> 11780362 | Q34: =J34*E34 -> 0 | R34: =+L34*E34 -> 378108.28 | S34: =SUM(N34:R34) -> 25585327 | U34: =+ROUNDUP(M34*$T$5,0) -> 1156856 | V34: =+U34*E34 -> 34705680
A35: 3.12 | B35: OK | C35: Viga H° Visto - H30 (120 kg/m3 de hierro) | D35: m3 | E35: =+'[9]H°A° '!O14 -> 7 | F35: =+'[9]H°A° '!F57 -> 466389.3 | H35: =F35+G35 -> 466389.3 | I35: =+'[9]MO HA AING'!D99 -> 629584.36 | J35: =+I35*0.25 -> 157396.09 | K35: =I35+J35 -> 786980.44 | L35: =+(H35+K35)*0.015 -> 18800.546 | M35: =H35+K35+L35 -> 1272170.3 | N35: =F35*E35 -> 3264725.1 | O35: =G35*E35 -> 0 | P35: =I35*E35 -> 4407090.5 | Q35: =J35*E35 -> 1101772.6 | R35: =+L35*E35 -> 131603.82 | S35: =SUM(N35:R35) -> 8905192 | U35: =+ROUNDUP(M35*$T$5,0) -> 1725658 | V35: =+U35*E35 -> 12079606
A36: 3.13 | B36: OK | C36: Viga apeo s/PB - H30 (180 kg/m3 de hierro) | D36: m3 | E36: =+'[9]H°A° '!O15 -> 12 | F36: =+'[9]H°A° '!F58 -> 578369.51 | H36: =F36+G36 -> 578369.51 | I36: =+'[9]MO HA AING'!D99 -> 629584.36 | J36: =+I36*0.25 -> 157396.09 | K36: =I36+J36 -> 786980.44 | L36: =+(H36+K36)*0.015 -> 20480.249 | M36: =H36+K36+L36 -> 1385830.2 | N36: =F36*E36 -> 6940434.1 | O36: =G36*E36 -> 0 | P36: =I36*E36 -> 7555012.3 | Q36: =J36*E36 -> 1888753.1 | R36: =+L36*E36 -> 245762.99 | S36: =SUM(N36:R36) -> 16629962 | U36: =+ROUNDUP(M36*$T$5,0) -> 1879834 | V36: =+U36*E36 -> 22558008
A37: 3.14 | B37: OK | C37: Viga - H30 (120 kg/m3 de hierro) | D37: m3 | E37: =+'[9]H°A° '!O16 -> 41 | F37: =+'[9]H°A° '!F59 -> 472049.51 | H37: =F37+G37 -> 472049.51 | I37: =+'[9]MO HA AING'!D99 -> 629584.36 | K37: =I37+J37 -> 629584.36 | L37: =+(H37+K37)*0.015 -> 16524.508 | M37: =H37+K37+L37 -> 1118158.4 | N37: =F37*E37 -> 19354030 | O37: =G37*E37 -> 0 | P37: =I37*E37 -> 25812959 | Q37: =J37*E37 -> 0 | R37: =+L37*E37 -> 677504.83 | S37: =SUM(N37:R37) -> 45844493 | U37: =+ROUNDUP(M37*$T$5,0) -> 1516746 | V37: =+U37*E37 -> 62186586
A38: 3.15 | B38: OK | C38: Losa - H30 (95 kg/m3 de hierro) | D38: m3 | E38: =+'[9]H°A° '!O17 -> 135 | F38: =+'[9]H°A° '!F60 -> 361563.22 | H38: =F38+G38 -> 361563.22 | I38: =+'[9]MO HA AING'!D123 -> 253632.45 | K38: =I38+J38 -> 253632.45 | L38: =+(H38+K38)*0.015 -> 9227.9351 | M38: =H38+K38+L38 -> 624423.61 | N38: =F38*E38 -> 48811035 | O38: =G38*E38 -> 0 | P38: =I38*E38 -> 34240381 | Q38: =J38*E38 -> 0 | R38: =+L38*E38 -> 1245771.2 | S38: =SUM(N38:R38) -> 84297187 | U38: =+ROUNDUP(M38*$T$5,0) -> 847011 | V38: =+U38*E38 -> 114346485
A39: 3.16 | B39: OK | C39: Losa H° Visto - H30 (95 kg/m3 de hierro) | D39: m3 | E39: =+'[9]H°A° '!O18 -> 13 | F39: =+'[9]H°A° '!F61 -> 367994.55 | H39: =F39+G39 -> 367994.55 | I39: =+'[9]MO HA AING'!D123 -> 253632.45 | J39: =+I39*0.25 -> 63408.113 | K39: =I39+J39 -> 317040.56 | L39: =+(H39+K39)*0.015 -> 10275.527 | M39: =H39+K39+L39 -> 695310.64 | N39: =F39*E39 -> 4783929.2 | O39: =G39*E39 -> 0 | P39: =I39*E39 -> 3297221.9 | Q39: =J39*E39 -> 824305.46 | R39: =+L39*E39 -> 133581.85 | S39: =SUM(N39:R39) -> 9039038.3 | U39: =+ROUNDUP(M39*$T$5,0) -> 943167 | V39: =+U39*E39 -> 12261171
A40: 3.17 | B40: OK | C40: Escalera - H30 (105 kg/m3) | D40: m3 | E40: =+'[9]H°A° '!O19 -> 14 | F40: =+'[9]H°A° '!F62 -> 404870.23 | H40: =F40+G40 -> 404870.23 | I40: =+'[9]MO HA AING'!D148 -> 370454.15 | K40: =I40+J40 -> 370454.15 | L40: =+(H40+K40)*0.015 -> 11629.866 | M40: =H40+K40+L40 -> 786954.25 | N40: =F40*E40 -> 5668183.3 | O40: =G40*E40 -> 0 | P40: =I40*E40 -> 5186358.1 | Q40: =J40*E40 -> 0 | R40: =+L40*E40 -> 162818.12 | S40: =SUM(N40:R40) -> 11017359 | U40: =+ROUNDUP(M40*$T$5,0) -> 1067478 | V40: =+U40*E40 -> 14944692
A41: 3.18 | B41: OK | C41: Viga alero - H30 (120 kg/m3 de hierro) | D41: m3 | E41: =+'[9]H°A° '!O20 -> 2 | F41: =+'[9]H°A° '!F63 -> 466389.3 | H41: =F41+G41 -> 466389.3 | I41: =+'[9]MO HA AING'!D99 -> 629584.36 | J41: =+I41*0.25 -> 157396.09 | K41: =I41+J41 -> 786980.44 | L41: =+(H41+K41)*0.015 -> 18800.546 | M41: =H41+K41+L41 -> 1272170.3 | N41: =F41*E41 -> 932778.6 | O41: =G41*E41 -> 0 | P41: =I41*E41 -> 1259168.7 | Q41: =J41*E41 -> 314792.18 | R41: =+L41*E41 -> 37601.092 | S41: =SUM(N41:R41) -> 2544340.6 | U41: =+ROUNDUP(M41*$T$5,0) -> 1725658 | V41: =+U41*E41 -> 3451316
A42: 3.19 | B42: OK | C42: Sistema de apuntalamiento y reapuntalamiento | D42: gl | E42: 1 | H42: =F42+G42 -> 0 | K42: =I42+J42 -> 0 | L42: =+'[9]ENCOFRADO '!G151 -> 10584988 | M42: =H42+K42+L42 -> 10584988 | N42: =F42*E42 -> 0 | O42: =G42*E42 -> 0 | P42: =I42*E42 -> 0 | Q42: =J42*E42 -> 0 | R42: =+L42*E42 -> 10584988 | S42: =SUM(N42:R42) -> 10584988 | U42: =+ROUNDUP(M42*$T$5,0) -> 14358189 | V42: =+U42*E42 -> 14358189
A43: 3.2 | B43: OK | C43: Ensayos de Hormigon por etapas de hormigonado | D43: u | E43: =+'[9]H°A° '!S43 -> 13 | H43: =F43+G43 -> 0 | I43: =+'[9]H°A° '!S44 -> 246942.15 | K43: =I43+J43 -> 246942.15 | M43: =H43+K43+L43 -> 246942.15 | N43: =F43*E43 -> 0 | O43: =G43*E43 -> 0 | P43: =I43*E43 -> 3210247.9 | Q43: =J43*E43 -> 0 | R43: =+L43*E43 -> 0 | S43: =SUM(N43:R43) -> 3210247.9 | U43: =+ROUNDUP(M43*$T$5,0) -> 334969 | V43: =+U43*E43 -> 4354597
A44: 3.21 | B44: OK | C44: Permiso de estacionamiento de bomba de hormigón a contramano | D44: gl | E44: =+[9]GGBB!R12 -> 3 | F44: 55000 | H44: =F44+G44 -> 55000 | K44: =I44+J44 -> 0 | M44: =H44+K44+L44 -> 55000 | N44: =F44*E44 -> 165000 | O44: =G44*E44 -> 0 | P44: =I44*E44 -> 0 | Q44: =J44*E44 -> 0 | R44: =+L44*E44 -> 0 | S44: =SUM(N44:R44) -> 165000 | U44: =+ROUNDUP(M44*$T$5,0) -> 74606 | V44: =+U44*E44 -> 223818
A45: 3.22 | B45: OK | C45: Picado de medianeras para columnas y vigas - Cotizado solo para PB, 1P, NO contempla picado en CT | D45: m2 | E45: =+[9]Computo!H49 -> 65 | F45: =+[9]Tareas!H96 -> 4615.3846 | G45: =+[9]Tareas!I96 -> 4615.3846 | H45: =F45+G45 -> 9230.7692 | I45: =+[9]Tareas!Q96 -> 0 | J45: =+[9]Tareas!R96 -> 20224.016 | K45: =I45+J45 -> 20224.016 | L45: =+(H45+K45)*0.015 -> 441.82178 | M45: =H45+K45+L45 -> 29896.607 | N45: =F45*E45 -> 300000 | O45: =G45*E45 -> 300000 | P45: =I45*E45 -> 0 | Q45: =J45*E45 -> 1314561.1 | R45: =+L45*E45 -> 28718.416 | S45: =SUM(N45:R45) -> 1943279.5 | U45: =+ROUNDUP(M45*$T$5,0) -> 40554 | V45: =+U45*E45 -> 2636010
A46: 4 | C46: MAMPOSTERÍA | T46: =SUM(S47:S52) -> 59733584 | W46: =SUM(V47:V52) -> 81027619 | X46: =+W46/$W$213 -> 0.05259406
A47: 4.01 | B47: OK | C47: Muro tipo 1 (interiores, divisorio de locales) e: 10 cm - Ladrillo hueco 08 x 18 x 33 | D47: m2 | E47: =+[9]MAMP.!L218 -> 437 | G47: =+'[9]APU 06.25'!E13 -> 10053.788 | H47: =F47+G47 -> 10053.788 | J47: =+'[9]APU 06.25'!H13 -> 10761.176 | K47: =I47+J47 -> 10761.176 | L47: =+'[9]APU 06.25'!K13 -> 255.78052 | M47: =H47+K47+L47 -> 21070.744 | N47: =F47*E47 -> 0 | O47: =G47*E47 -> 4393505.4 | P47: =I47*E47 -> 0 | Q47: =J47*E47 -> 4702633.8 | R47: =+L47*E47 -> 111776.09 | S47: =SUM(N47:R47) -> 9207915.3 | U47: =+ROUNDUP(M47*$T$5,0) -> 28582 | V47: =+U47*E47 -> 12490334
A48: 4.02 | B48: OK | C48: Muro tipo 2 y 3 (medianera, caja de escaleras y ascensor) e: 15 cm - Ladrillo hueco portante 12 x 19 x 33 | D48: m2 | E48: =+[9]MAMP.!N218 -> 723 | G48: =+'[9]APU 06.25'!E17 -> 18207.26 | H48: =F48+G48 -> 18207.26 | J48: =+'[9]APU 06.25'!H17 -> 10761.176 | K48: =I48+J48 -> 10761.176 | L48: =+'[9]APU 06.25'!K17 -> 255.78052 | M48: =H48+K48+L48 -> 29224.217 | N48: =F48*E48 -> 0 | O48: =G48*E48 -> 13163849 | P48: =I48*E48 -> 0 | Q48: =J48*E48 -> 7780330.1 | R48: =+L48*E48 -> 184929.32 | S48: =SUM(N48:R48) -> 21129109 | U48: =+ROUNDUP(M48*$T$5,0) -> 39642 | V48: =+U48*E48 -> 28661166
A49: 4.03 | B49: OK | C49: Muro tipo 4 (divisorio de unidades y fachadas) e: 15 cm - Ladrillo hueco 12 x 18 x 33 | D49: m2 | E49: =+[9]MAMP.!M218 -> 1008 | G49: =+'[9]APU 06.25'!E14 -> 12465.038 | H49: =F49+G49 -> 12465.038 | J49: =+'[9]APU 06.25'!H14 -> 10761.176 | K49: =I49+J49 -> 10761.176 | L49: =+'[9]APU 06.25'!K14 -> 255.78052 | M49: =H49+K49+L49 -> 23481.994 | N49: =F49*E49 -> 0 | O49: =G49*E49 -> 12564758 | P49: =I49*E49 -> 0 | Q49: =J49*E49 -> 10847265 | R49: =+L49*E49 -> 257826.77 | S49: =SUM(N49:R49) -> 23669850 | U49: =+ROUNDUP(M49*$T$5,0) -> 31853 | V49: =+U49*E49 -> 32107824
A50: 4.04 | B50: OK | C50: Enchape medianeras existentes - Contemplamos picado zonas sueltas y enchape con ladrillo comun para PB y 1° | D50: m2 | E50: =+[9]MAMP.!O218 -> 199 | G50: =+'[9]APU 06.25'!E17/3 -> 6069.0868 | H50: =F50+G50 -> 6069.0868 | J50: =+'[9]APU 06.25'!H17/2 -> 5380.5879 | K50: =I50+J50 -> 5380.5879 | L50: =+'[9]APU 06.25'!K13 -> 255.78052 | M50: =H50+K50+L50 -> 11705.455 | N50: =F50*E50 -> 0 | O50: =G50*E50 -> 1207748.3 | P50: =I50*E50 -> 0 | Q50: =J50*E50 -> 1070737 | R50: =+L50*E50 -> 50900.324 | S50: =SUM(N50:R50) -> 2329385.6 | U50: =+ROUNDUP(M50*$T$5,0) -> 15879 | V50: =+U50*E50 -> 3159921
A51: 4.05 | B51: IN | C51: Muro de tabique seco ignifugo | D51: m2 | E51: =+[9]MAMP.!Q218 -> 34 | F51: =+'[9]APU 06.25'!E46 -> 28944.105 | H51: =F51+G51 -> 28944.105 | I51: =+'[9]APU 06.25'!H46 -> 27718.213 | K51: =I51+J51 -> 27718.213 | L51: =+'[9]APU 06.25'!K46 -> 441.15834 | M51: =H51+K51+L51 -> 57103.476 | N51: =F51*E51 -> 984099.57 | O51: =G51*E51 -> 0 | P51: =I51*E51 -> 942419.23 | Q51: =J51*E51 -> 0 | R51: =+L51*E51 -> 14999.384 | S51: =SUM(N51:R51) -> 1941518.2 | U51: =+ROUNDUP(M51*$T$5,0) -> 77459 | V51: =+U51*E51 -> 2633606
A52: 4.06 | B52: OK | C52: Vigas de encadenado - En muros de PB, incl. excavación y armado | D52: ml | E52: =+[9]Computo!C13 -> 24 | F52: =+[9]Tareas!H101 -> 23405.012 | G52: =+[9]Tareas!I101 -> 0 | H52: =F52+G52 -> 23405.012 | I52: =+[9]Tareas!Q101 -> 0 | J52: =+[9]Tareas!R101 -> 36357.144 | K52: =I52+J52 -> 36357.144 | L52: =(H52+K52)*0.015 -> 896.43233 | M52: =H52+K52+L52 -> 60658.588 | N52: =F52*E52 -> 561720.28 | O52: =G52*E52 -> 0 | P52: =I52*E52 -> 0 | Q52: =J52*E52 -> 872571.45 | R52: =+L52*E52 -> 21514.376 | S52: =SUM(N52:R52) -> 1455806.1 | U52: =+ROUNDUP(M52*$T$5,0) -> 82282 | V52: =+U52*E52 -> 1974768
A53: 5 | C53: AISLACIONES | T53: =SUM(S54:S59) -> 12211793 | W53: =SUM(V54:V59) -> 16565287 | X53: =+W53/$W$213 -> 0.01075233
A54: 5.01 | B54: OK | C54: Aislación hidrófuga horizontal (baños) - Inc. membrana geotextil y 35% en concepto de babetas | D54: m2 | E54: =+[9]Locales!AD100 -> 79 | F54: =+G54*0.35 -> 3050.8865 | G54: =+'[9]APU 06.25'!E50 -> 8716.8187 | H54: =F54+G54 -> 11767.705 | I54: =+J54*0.35 -> 4471.4668 | J54: =+[9]SUBCONTRATOS!D75 -> 12775.619 | K54: =I54+J54 -> 17247.086 | L54: =+'[9]APU 06.25'!K50 -> 34.976452 | M54: =H54+K54+L54 -> 29049.768 | N54: =F54*E54 -> 241020.04 | O54: =G54*E54 -> 688628.68 | P54: =I54*E54 -> 353245.87 | Q54: =J54*E54 -> 1009273.9 | R54: =+L54*E54 -> 2763.1397 | S54: =SUM(N54:R54) -> 2294931.7 | U54: =+ROUNDUP(M54*$T$5,0) -> 39406 | V54: =+U54*E54 -> 3113074
A55: 5.02 | B55: OK | C55: Cajón hidrófugo - Muros de PB | D55: ml | E55: =+[9]MAMP.!U41 -> 113 | G55: =+'[9]APU 06.25'!E21 -> 827.27861 | H55: =F55+G55 -> 827.27861 | J55: =+'[9]APU 06.25'!H21 -> 4324.0478 | K55: =I55+J55 -> 4324.0478 | L55: =+'[9]APU 06.25'!K21 -> 137.02528 | M55: =H55+K55+L55 -> 5288.3517 | N55: =F55*E55 -> 0 | O55: =G55*E55 -> 93482.483 | P55: =I55*E55 -> 0 | Q55: =J55*E55 -> 488617.4 | R55: =+L55*E55 -> 15483.857 | S55: =SUM(N55:R55) -> 597583.74 | U55: =+ROUNDUP(M55*$T$5,0) -> 7174 | V55: =+U55*E55 -> 810662
A56: 5.03 | B56: OK | C56: Azotado hidrófugo - Sobre contrapiso en vereda y PB | D56: m2 | E56: =+[9]Locales!AF100 -> 207 | G56: =+'[9]APU 06.25'!E21 -> 827.27861 | H56: =F56+G56 -> 827.27861 | J56: =+'[9]APU 06.25'!H21 -> 4324.0478 | K56: =I56+J56 -> 4324.0478 | L56: =+'[9]APU 06.25'!K21 -> 137.02528 | M56: =H56+K56+L56 -> 5288.3517 | N56: =F56*E56 -> 0 | O56: =G56*E56 -> 171246.67 | P56: =I56*E56 -> 0 | Q56: =J56*E56 -> 895077.89 | R56: =+L56*E56 -> 28364.233 | S56: =SUM(N56:R56) -> 1094688.8 | U56: =+ROUNDUP(M56*$T$5,0) -> 7174 | V56: =+U56*E56 -> 1485018
A57: 5.04 | B57: OK | C57: Aislación térmica en terrazas, eps e:2,00 cm | D57: m2 | E57: =+[9]Locales!AH100 -> 165 | G57: =+[9]Cotizaciones!D52 -> 3538.08 | H57: =F57+G57 -> 3538.08 | K57: =I57+J57 -> 0 | M57: =H57+K57+L57 -> 3538.08 | N57: =F57*E57 -> 0 | O57: =G57*E57 -> 583783.2 | P57: =I57*E57 -> 0 | Q57: =J57*E57 -> 0 | R57: =+L57*E57 -> 0 | S57: =SUM(N57:R57) -> 583783.2 | U57: =+ROUNDUP(M57*$T$5,0) -> 4800 | V57: =+U57*E57 -> 792000
A58: 5.05 | B58: OK | C58: Barrera de vapor | D58: m2 | E58: =+[9]Locales!AG100 -> 165 | G58: =+'[9]APU 06.25'!E56 -> 1392.6098 | H58: =F58+G58 -> 1392.6098 | J58: =+'[9]APU 06.25'!H56 -> 2017.7205 | K58: =I58+J58 -> 2017.7205 | L58: =+'[9]APU 06.25'!K56 -> 10.930141 | M58: =H58+K58+L58 -> 3421.2604 | N58: =F58*E58 -> 0 | O58: =G58*E58 -> 229780.61 | P58: =I58*E58 -> 0 | Q58: =J58*E58 -> 332923.88 | R58: =+L58*E58 -> 1803.4733 | S58: =SUM(N58:R58) -> 564507.96 | U58: =+ROUNDUP(M58*$T$5,0) -> 4641 | V58: =+U58*E58 -> 765765
A59: 5.06 | B59: OK | C59: Membrana asfaltica geotextil 4mm - Balcones y azotea - Inc. 20% en concepto de babetas | D59: m2 | E59: =+[9]Locales!AI100 -> 274 | F59: =+G59*0.2 -> 1743.3637 | G59: =+'[9]APU 06.25'!E50 -> 8716.8187 | H59: =F59+G59 -> 10460.182 | I59: =+J59*0.2 -> 2555.1239 | J59: =+[9]SUBCONTRATOS!D75 -> 12775.619 | K59: =I59+J59 -> 15330.743 | L59: =+'[9]APU 06.25'!K50 -> 34.976452 | M59: =H59+K59+L59 -> 25825.902 | N59: =F59*E59 -> 477681.67 | O59: =G59*E59 -> 2388408.3 | P59: =I59*E59 -> 700103.94 | Q59: =J59*E59 -> 3500519.7 | R59: =+L59*E59 -> 9583.5479 | S59: =SUM(N59:R59) -> 7076297.2 | U59: =+ROUNDUP(M59*$T$5,0) -> 35032 | V59: =+U59*E59 -> 9598768
A60: 6 | C60: CUBIERTAS | T60: =SUM(S61:S61) -> 1090677.6 | W60: =SUM(V61:V61) -> 1479500 | X60: =+W60/$W$213 -> 0.00096032579
A61: 6.01 | B61: OK | C61: Babeta de chapa galvanizada en medianeras | D61: ml | E61: =25+9.5+9.5 -> 44 | F61: =+[9]Tareas!H117 -> 16294.998 | G61: =+[9]Tareas!I117 -> 0 | H61: =F61+G61 -> 16294.998 | I61: =+[9]Tareas!Q117 -> 0 | J61: =+[9]Tareas!R117 -> 8126.8023 | K61: =I61+J61 -> 8126.8023 | L61: =+(H61+K61)*0.015 -> 366.327 | M61: =H61+K61+L61 -> 24788.127 | N61: =F61*E61 -> 716979.9 | O61: =G61*E61 -> 0 | P61: =I61*E61 -> 0 | Q61: =J61*E61 -> 357579.3 | R61: =+L61*E61 -> 16118.388 | S61: =SUM(N61:R61) -> 1090677.6 | U61: =+ROUNDUP(M61*$T$5,0) -> 33625 | V61: =+U61*E61 -> 1479500
A62: 7 | C62: REVOQUES | T62: =SUM(S63:S70) -> 1.1177101e+08 | W62: =SUM(V63:V70) -> 151616626 | X62: =+W62/$W$213 -> 0.098412542
A63: 7.01 | B63: OK | C63: Revoque Grueso Impermeable Exterior | D63: m2 | E63: =+'[9]Rev.'!J54 -> 663 | G63: =+'[9]APU 06.25'!E23 -> 4061.1651 | H63: =F63+G63 -> 4061.1651 | J63: =+'[9]APU 06.25'!H23 -> 11697.516 | K63: =I63+J63 -> 11697.516 | L63: =+'[9]APU 06.25'!K23 -> 333.62677 | M63: =H63+K63+L63 -> 16092.308 | N63: =F63*E63 -> 0 | O63: =G63*E63 -> 2692552.5 | P63: =I63*E63 -> 0 | Q63: =J63*E63 -> 7755453.3 | R63: =+L63*E63 -> 221194.55 | S63: =SUM(N63:R63) -> 10669200 | U63: =+ROUNDUP(M63*$T$5,0) -> 21829 | V63: =+U63*E63 -> 14472627
A64: 7.02 | B64: OK | C64: Revoque Grueso Impermeable Exterior a mas de 3m - Medianero y fachadas | D64: m2 | E64: =+'[9]Rev.'!J67 -> 1164 | G64: =+'[9]APU 06.25'!E24 -> 4061.1651 | H64: =F64+G64 -> 4061.1651 | J64: =+'[9]APU 06.25'!H24 -> 16815.18 | K64: =I64+J64 -> 16815.18 | L64: =+'[9]APU 06.25'!K24 -> 863.36281 | M64: =H64+K64+L64 -> 21739.708 | N64: =F64*E64 -> 0 | O64: =G64*E64 -> 4727196.2 | P64: =I64*E64 -> 0 | Q64: =J64*E64 -> 19572869 | R64: =+L64*E64 -> 1004954.3 | S64: =SUM(N64:R64) -> 25305020 | U64: =+ROUNDUP(M64*$T$5,0) -> 29490 | V64: =+U64*E64 -> 34326360
A65: 7.03 | B65: OK | C65: Buña en revoque - Estimados ml en medianeras | D65: ml | E65: =+'[9]Rev.'!J71 -> 500 | H65: =F65+G65 -> 0 | I65: =+[9]SUBCONTRATOS!D36 -> 11122.339 | K65: =I65+J65 -> 11122.339 | M65: =H65+K65+L65 -> 11122.339 | N65: =F65*E65 -> 0 | O65: =G65*E65 -> 0 | P65: =I65*E65 -> 5561169.6 | Q65: =J65*E65 -> 0 | R65: =+L65*E65 -> 0 | S65: =SUM(N65:R65) -> 5561169.6 | U65: =+ROUNDUP(M65*$T$5,0) -> 15088 | V65: =+U65*E65 -> 7544000
A66: 7.04 | B66: OK | C66: Revoque Grueso Interior + fino | D66: m2 | E66: =+[9]Locales!U100 -> 521 | G66: =+'[9]APU 06.25'!E22 -> 2891.2175 | H66: =F66+G66 -> 2891.2175 | J66: =+'[9]APU 06.25'!H22 -> 22980.577 | K66: =I66+J66 -> 22980.577 | L66: =+'[9]APU 06.25'!K22 -> 639.45131 | M66: =H66+K66+L66 -> 26511.246 | N66: =F66*E66 -> 0 | O66: =G66*E66 -> 1506324.3 | P66: =I66*E66 -> 0 | Q66: =J66*E66 -> 11972881 | R66: =+L66*E66 -> 333154.13 | S66: =SUM(N66:R66) -> 13812359 | U66: =+ROUNDUP(M66*$T$5,0) -> 35962 | V66: =+U66*E66 -> 18736202
A67: 7.05 | B67: OK | C67: Yeso interior | D67: m2 | E67: =+[9]Locales!Z100 -> 2180 | F67: =+[9]Tareas!H123 -> 0 | G67: =+[9]Tareas!I123 -> 5780.8669 | H67: =F67+G67 -> 5780.8669 | I67: =+[9]Tareas!Q123 -> 12252.549 | J67: =+[9]Tareas!R123 -> 0 | K67: =I67+J67 -> 12252.549 | L67: =+(H67+K67)*0.015 -> 270.50123 | M67: =H67+K67+L67 -> 18303.917 | N67: =F67*E67 -> 0 | O67: =G67*E67 -> 12602290 | P67: =I67*E67 -> 26710556 | Q67: =J67*E67 -> 0 | R67: =+L67*E67 -> 589692.69 | S67: =SUM(N67:R67) -> 39902538 | U67: =+ROUNDUP(M67*$T$5,0) -> 24829 | V67: =+U67*E67 -> 54127220
A68: 7.06 | B68: OK | C68: Arista en yeso | D68: ml | E68: =+[9]Locales!AA100 -> 255 | F68: =+[9]Tareas!H128 -> 0 | G68: =+[9]Tareas!I128 -> 0 | H68: =F68+G68 -> 0 | I68: =+[9]Tareas!Q128 -> 13144.583 | J68: =+[9]Tareas!R128 -> 0 | K68: =I68+J68 -> 13144.583 | L68: =+(H68+K68)*0.015 -> 197.16874 | M68: =H68+K68+L68 -> 13341.751 | N68: =F68*E68 -> 0 | O68: =G68*E68 -> 0 | P68: =I68*E68 -> 3351868.6 | Q68: =J68*E68 -> 0 | R68: =+L68*E68 -> 50278.029 | S68: =SUM(N68:R68) -> 3402146.6 | U68: =+ROUNDUP(M68*$T$5,0) -> 18098 | V68: =+U68*E68 -> 4614990
A69: 7.07 | B69: OK | C69: Provisión y colocación de guardacanto yesero | D69: u | E69: =+[9]Locales!AB100 -> 102 | F69: =+[9]Tareas!H130 -> 0 | G69: =+[9]Tareas!I130 -> 1658.1176 | H69: =F69+G69 -> 1658.1176 | I69: =+[9]Tareas!Q130 -> 13917.793 | J69: =+[9]Tareas!R130 -> 0 | K69: =I69+J69 -> 13917.793 | L69: =+(H69+K69)*0.015 -> 233.63867 | M69: =H69+K69+L69 -> 15809.55 | N69: =F69*E69 -> 0 | O69: =G69*E69 -> 169128 | P69: =I69*E69 -> 1419614.9 | Q69: =J69*E69 -> 0 | R69: =+L69*E69 -> 23831.144 | S69: =SUM(N69:R69) -> 1612574.1 | U69: =+ROUNDUP(M69*$T$5,0) -> 21446 | V69: =+U69*E69 -> 2187492
A70: 7.08 | B70: OK | C70: Revoque Grueso Impermeable Interior b/ revestimiento | D70: m2 | E70: =+[9]Locales!X100 -> 715 | G70: =+'[9]APU 06.25'!E23 -> 4061.1651 | H70: =F70+G70 -> 4061.1651 | J70: =+'[9]APU 06.25'!H23 -> 11697.516 | K70: =I70+J70 -> 11697.516 | L70: =+'[9]APU 06.25'!K23 -> 333.62677 | M70: =H70+K70+L70 -> 16092.308 | N70: =F70*E70 -> 0 | O70: =G70*E70 -> 2903733 | P70: =I70*E70 -> 0 | Q70: =J70*E70 -> 8363724.1 | R70: =+L70*E70 -> 238543.14 | S70: =SUM(N70:R70) -> 11506000 | U70: =+ROUNDUP(M70*$T$5,0) -> 21829 | V70: =+U70*E70 -> 15607735
A71: 8 | C71: CONTRAPISOS Y CARPETAS | T71: =SUM(S72:S79) -> 36756192 | W71: =SUM(V72:V79) -> 49859719 | X71: =+W71/$W$213 -> 0.032363348
A72: 8.01 | B72: OK | C72: Contrapiso de cascotes s/ss e: 15 cm | D72: m2 | E72: =+[9]Locales!O100 -> 21 | G72: =+'[9]APU 06.25'!E25*0.2 -> 13595.327 | H72: =F72+G72 -> 13595.327 | J72: =+'[9]APU 06.25'!H25*0.2 -> 19696.193 | K72: =I72+J72 -> 19696.193 | L72: =+'[9]APU 06.25'!K25*0.2 -> 503.75749 | M72: =H72+K72+L72 -> 33795.278 | N72: =F72*E72 -> 0 | O72: =G72*E72 -> 285501.86 | P72: =I72*E72 -> 0 | Q72: =J72*E72 -> 413620.06 | R72: =+L72*E72 -> 10578.907 | S72: =SUM(N72:R72) -> 709700.83 | U72: =+ROUNDUP(M72*$T$5,0) -> 45843 | V72: =+U72*E72 -> 962703
A73: 8.02 | B73: OK | C73: Contrapiso armado de H° pobre s/terreno natural e: 20 cm - Incluye film de polietileno | D73: m2 | E73: =+[9]Locales!P100 -> 201 | F73: =+[9]Tareas!H133 -> 28415.373 | G73: =+[9]Tareas!I133 -> 2539.3792 | H73: =F73+G73 -> 30954.752 | I73: =+[9]Tareas!Q133 -> 0 | J73: =+[9]Tareas!R133 -> 8768.7309 | K73: =I73+J73 -> 8768.7309 | L73: =+(H73+K73)*0.015 -> 595.85225 | M73: =H73+K73+L73 -> 40319.335 | N73: =F73*E73 -> 5711490 | O73: =G73*E73 -> 510415.21 | P73: =I73*E73 -> 0 | Q73: =J73*E73 -> 1762514.9 | R73: =+L73*E73 -> 119766.3 | S73: =SUM(N73:R73) -> 8104186.4 | U73: =+ROUNDUP(M73*$T$5,0) -> 54692 | V73: =+U73*E73 -> 10993092
A74: 8.03 | B74: OK | C74: Contrapiso de cascotes en azoteas c/pendiente e: 15 cm | D74: m2 | E74: =+[9]Locales!N100 -> 107 | G74: =+'[9]APU 06.25'!E25*0.2 -> 13595.327 | H74: =F74+G74 -> 13595.327 | J74: =+'[9]APU 06.25'!H25*0.2 -> 19696.193 | K74: =I74+J74 -> 19696.193 | L74: =+'[9]APU 06.25'!K25*0.2 -> 503.75749 | M74: =H74+K74+L74 -> 33795.278 | N74: =F74*E74 -> 0 | O74: =G74*E74 -> 1454700 | P74: =I74*E74 -> 0 | Q74: =J74*E74 -> 2107492.7 | R74: =+L74*E74 -> 53902.052 | S74: =SUM(N74:R74) -> 3616094.7 | U74: =+ROUNDUP(M74*$T$5,0) -> 45843 | V74: =+U74*E74 -> 4905201
A75: 8.04 | B75: OK | C75: Contrapiso - Carpeta monolitico e: 6 cm | D75: m2 | E75: =+[9]Locales!Q100 -> 850 | G75: =+'[9]APU 06.25'!E27 -> 6717.8752 | H75: =F75+G75 -> 6717.8752 | J75: =+'[9]APU 06.25'!H27 -> 11145.022 | K75: =I75+J75 -> 11145.022 | L75: =+'[9]APU 06.25'!K27 -> 130.47811 | M75: =H75+K75+L75 -> 17993.375 | N75: =F75*E75 -> 0 | O75: =G75*E75 -> 5710194 | P75: =I75*E75 -> 0 | Q75: =J75*E75 -> 9473268.8 | R75: =+L75*E75 -> 110906.39 | S75: =SUM(N75:R75) -> 15294369 | U75: =+ROUNDUP(M75*$T$5,0) -> 24408 | V75: =+U75*E75 -> 20746800
A76: 8.05 | B76: OK | C76: Carpeta en PB, balcones, baños y azoteas e: 3,00 cm | D76: m2 | E76: =+[9]Locales!R100 -> 365 | G76: =+'[9]APU 06.25'!E26 -> 3420.3193 | H76: =F76+G76 -> 3420.3193 | J76: =+'[9]APU 06.25'!H26 -> 8295.6908 | K76: =I76+J76 -> 8295.6908 | L76: =+'[9]APU 06.25'!K26 -> 235.08683 | M76: =H76+K76+L76 -> 11951.097 | N76: =F76*E76 -> 0 | O76: =G76*E76 -> 1248416.6 | P76: =I76*E76 -> 0 | Q76: =J76*E76 -> 3027927.2 | R76: =+L76*E76 -> 85806.693 | S76: =SUM(N76:R76) -> 4362150.4 | U76: =+ROUNDUP(M76*$T$5,0) -> 16212 | V76: =+U76*E76 -> 5917380
A77: 8.06 | B77: OK | C77: Carpeta sobre membrana, e: 3,00 cm | D77: m2 | E77: =+[9]Locales!S100 -> 357 | G77: =+'[9]APU 06.25'!E26 -> 3420.3193 | H77: =F77+G77 -> 3420.3193 | J77: =+'[9]APU 06.25'!H26 -> 8295.6908 | K77: =I77+J77 -> 8295.6908 | L77: =+'[9]APU 06.25'!K26 -> 235.08683 | M77: =H77+K77+L77 -> 11951.097 | N77: =F77*E77 -> 0 | O77: =G77*E77 -> 1221054 | P77: =I77*E77 -> 0 | Q77: =J77*E77 -> 2961561.6 | R77: =+L77*E77 -> 83925.998 | S77: =SUM(N77:R77) -> 4266541.6 | U77: =+ROUNDUP(M77*$T$5,0) -> 16212 | V77: =+U77*E77 -> 5787684
A78: 8.07 | B78: R | C78: Banquinas para cocinas - N/A | D78: gl | E78: 0 | H78: =F78+G78 -> 0 | K78: =I78+J78 -> 0 | M78: =H78+K78+L78 -> 0 | N78: =F78*E78 -> 0 | O78: =G78*E78 -> 0 | P78: =I78*E78 -> 0 | Q78: =J78*E78 -> 0 | R78: =+L78*E78 -> 0 | S78: =SUM(N78:R78) -> 0 | U78: =+ROUNDUP(M78*$T$5,0) -> 0 | V78: =+U78*E78 -> 0
A79: 8.08 | B79: OK | C79: Banquinas para bombas, TT, etc. h: 15 cm | D79: gl | E79: 1 | F79: =+[9]Tareas!H142 -> 0 | G79: =+[9]Tareas!I142 -> 93485.024 | H79: =F79+G79 -> 93485.024 | I79: =+[9]Tareas!Q142 -> 0 | J79: =+[9]Tareas!R142 -> 303706.02 | K79: =I79+J79 -> 303706.02 | L79: =+(H79+K79)*0.015 -> 5957.8657 | M79: =H79+K79+L79 -> 403148.91 | N79: =F79*E79 -> 0 | O79: =G79*E79 -> 93485.024 | P79: =I79*E79 -> 0 | Q79: =J79*E79 -> 303706.02 | R79: =+L79*E79 -> 5957.8657 | S79: =SUM(N79:R79) -> 403148.91 | U79: =+ROUNDUP(M79*$T$5,0) -> 546859 | V79: =+U79*E79 -> 546859
A80: 9 | C80: ESCALERAS | T80: =SUM(S81:S83) -> 5878458.4 | W80: =SUM(V81:V83) -> 7973948 | X80: =+W80/$W$213 -> 0.0051757945
A81: 9.01 | B81: OK | C81: Provisión y ejecución de alisado de cemento en pedadas y alzadas | D81: gl | E81: 1 | F81: =+[9]Tareas!H147 -> 427508.24 | G81: =+[9]Tareas!I147 -> 0 | H81: =F81+G81 -> 427508.24 | I81: =+[9]Tareas!Q147 -> 0 | J81: =+[9]Tareas!R147 -> 2044758.2 | K81: =I81+J81 -> 2044758.2 | L81: =+(H81+K81)*0.015 -> 37083.997 | M81: =H81+K81+L81 -> 2509350.4 | N81: =F81*E81 -> 427508.24 | O81: =G81*E81 -> 0 | P81: =I81*E81 -> 0 | Q81: =J81*E81 -> 2044758.2 | R81: =+L81*E81 -> 37083.997 | S81: =SUM(N81:R81) -> 2509350.4 | U81: =+ROUNDUP(M81*$T$5,0) -> 3403852 | V81: =+U81*E81 -> 3403852
A82: 9.02 | B82: OK | C82: Provisión y colocación de nariz metálica en escalones | D82: gl | E82: 1 | F82: =+[9]Tareas!H151 -> 463902.77 | G82: =+[9]Tareas!I151 -> 0 | H82: =F82+G82 -> 463902.77 | I82: =+[9]Tareas!Q151 -> 0 | J82: =+[9]Tareas!R151 -> 1775796.2 | K82: =I82+J82 -> 1775796.2 | L82: =+(H82+K82)*0.015 -> 33595.485 | M82: =H82+K82+L82 -> 2273294.5 | N82: =F82*E82 -> 463902.77 | O82: =G82*E82 -> 0 | P82: =I82*E82 -> 0 | Q82: =J82*E82 -> 1775796.2 | R82: =+L82*E82 -> 33595.485 | S82: =SUM(N82:R82) -> 2273294.5 | U82: =+ROUNDUP(M82*$T$5,0) -> 3083650 | V82: =+U82*E82 -> 3083650
A83: 9.03 | B83: OK | C83: Zócalo de concreto en escalera - No incluye el ojo | D83: ml | E83: =+[9]Computo!G201 -> 114 | G83: =+'[9]APU 06.25'!E21 -> 827.27861 | H83: =F83+G83 -> 827.27861 | I83: =+J83 -> 4324.0478 | J83: =+'[9]APU 06.25'!H21 -> 4324.0478 | K83: =I83+J83 -> 8648.0955 | L83: =+'[9]APU 06.25'!K21 -> 137.02528 | M83: =H83+K83+L83 -> 9612.3994 | N83: =F83*E83 -> 0 | O83: =G83*E83 -> 94309.762 | P83: =I83*E83 -> 492941.45 | Q83: =J83*E83 -> 492941.45 | R83: =+L83*E83 -> 15620.882 | S83: =SUM(N83:R83) -> 1095813.5 | U83: =+ROUNDUP(M83*$T$5,0) -> 13039 | V83: =+U83*E83 -> 1486446
A84: 10 | C84: VENTILACIONES - PROVISION COTIZADA EN ITEM 26 | T84: =SUM(S85:S87) -> 4784536 | W84: =SUM(V85:V87) -> 6490071 | X84: =+W84/$W$213 -> 0.0042126276
A85: 10.01 | B85: OK | C85: Colocación de ventilación de conducto de humos. Inc. toma de aire en PB | D85: gl | E85: 1 | F85: =+[9]Tareas!H157 -> 250000 | G85: =+[9]Tareas!I157 -> 0 | H85: =F85+G85 -> 250000 | I85: =+[9]Tareas!Q157 -> 0 | J85: =+[9]Tareas!R157 -> 1663092.8 | K85: =I85+J85 -> 1663092.8 | L85: =(H85+K85)*0.015 -> 28696.391 | M85: =H85+K85+L85 -> 1941789.2 | N85: =F85*E85 -> 250000 | O85: =G85*E85 -> 0 | P85: =I85*E85 -> 0 | Q85: =J85*E85 -> 1663092.8 | R85: =+L85*E85 -> 28696.391 | S85: =SUM(N85:R85) -> 1941789.2 | U85: =+ROUNDUP(M85*$T$5,0) -> 2633974 | V85: =+U85*E85 -> 2633974
A86: 10.02 | B86: OK | C86: Colocación y montaje de conducto de ventilación en baños | D86: gl | E86: 1 | F86: =+[9]Tareas!H160 -> 250000 | G86: =+[9]Tareas!I160 -> 0 | H86: =F86+G86 -> 250000 | I86: =+[9]Tareas!Q160 -> 0 | J86: =+[9]Tareas!R160 -> 1663092.8 | K86: =I86+J86 -> 1663092.8 | L86: =(H86+K86)*0.015 -> 28696.391 | M86: =H86+K86+L86 -> 1941789.2 | N86: =F86*E86 -> 250000 | O86: =G86*E86 -> 0 | P86: =I86*E86 -> 0 | Q86: =J86*E86 -> 1663092.8 | R86: =+L86*E86 -> 28696.391 | S86: =SUM(N86:R86) -> 1941789.2 | U86: =+ROUNDUP(M86*$T$5,0) -> 2633974 | V86: =+U86*E86 -> 2633974
A87: 10.03 | B87: OK | C87: Colocación sombreretes en chapa prepintada C25 - Provisión en item 26 | D87: u | E87: 7 | F87: =+[9]Tareas!H163 -> 31772.281 | G87: =+[9]Tareas!I163 -> 0 | H87: =F87+G87 -> 31772.281 | I87: =+[9]Tareas!Q163 -> 0 | J87: =+[9]Tareas!R163 -> 95033.872 | K87: =I87+J87 -> 95033.872 | L87: =(H87+K87)*0.015 -> 1902.0923 | M87: =H87+K87+L87 -> 128708.25 | N87: =F87*E87 -> 222405.97 | O87: =G87*E87 -> 0 | P87: =I87*E87 -> 0 | Q87: =J87*E87 -> 665237.1 | R87: =+L87*E87 -> 13314.646 | S87: =SUM(N87:R87) -> 900957.72 | U87: =+ROUNDUP(M87*$T$5,0) -> 174589 | V87: =+U87*E87 -> 1222123
A88: 11 | C88: PISOS - PROVISION A CARGO DEL COMITENTE | T88: =SUM(S89:S95) -> 27324425 | W88: =SUM(V89:V95) -> 37065194 | X88: =+W88/$W$213 -> 0.024058575
A89: 11.01 | B89: OK | C89: Colocación de baldosas en palieres - Provisión a cargo del comitente | D89: m2 | E89: =+[9]Locales!BE100 -> 101 | G89: =+'[9]APU 06.25'!E36 -> 6932.2708 | H89: =F89+G89 -> 6932.2708 | J89: =+'[9]APU 06.25'!H36 -> 12793.021 | K89: =I89+J89 -> 12793.021 | L89: =+'[9]APU 06.25'!K36 -> 245.43421 | M89: =H89+K89+L89 -> 19970.726 | N89: =F89*E89 -> 0 | O89: =G89*E89 -> 700159.35 | P89: =I89*E89 -> 0 | Q89: =J89*E89 -> 1292095.1 | R89: =+L89*E89 -> 24788.855 | S89: =SUM(N89:R89) -> 2017043.4 | U89: =+ROUNDUP(M89*$T$5,0) -> 27090 | V89: =+U89*E89 -> 2736090
A90: 11.02 | B90: OK | C90: Colocación de porcelanato en UF - Provisión a cargo del comitente | D90: m2 | E90: =+[9]Locales!BF100 -> 898 | G90: =+'[9]APU 06.25'!E36 -> 6932.2708 | H90: =F90+G90 -> 6932.2708 | J90: =+'[9]APU 06.25'!H36 -> 12793.021 | K90: =I90+J90 -> 12793.021 | L90: =+'[9]APU 06.25'!K36 -> 245.43421 | M90: =H90+K90+L90 -> 19970.726 | N90: =F90*E90 -> 0 | O90: =G90*E90 -> 6225179.2 | P90: =I90*E90 -> 0 | Q90: =J90*E90 -> 11488133 | R90: =+L90*E90 -> 220399.92 | S90: =SUM(N90:R90) -> 17933712 | U90: =+ROUNDUP(M90*$T$5,0) -> 27090 | V90: =+U90*E90 -> 24326820
A91: 11.03 | B91: OK | C91: Colocación de porcelanato en baños - Provisión a cargo del comitente | D91: m2 | E91: =+[9]Locales!BG100 -> 88 | G91: =+'[9]APU 06.25'!E37 -> 6932.2708 | H91: =F91+G91 -> 6932.2708 | J91: =+'[9]APU 06.25'!H37 -> 16630.928 | K91: =I91+J91 -> 16630.928 | L91: =+'[9]APU 06.25'!K37 -> 319.06447 | M91: =H91+K91+L91 -> 23882.263 | N91: =F91*E91 -> 0 | O91: =G91*E91 -> 610039.83 | P91: =I91*E91 -> 0 | Q91: =J91*E91 -> 1463521.6 | R91: =+L91*E91 -> 28077.674 | S91: =SUM(N91:R91) -> 2101639.1 | U91: =+ROUNDUP(M91*$T$5,0) -> 32396 | V91: =+U91*E91 -> 2850848
A92: 11.04 | B92: OK | C92: Colocación de porcelanato en exterior - Provisión a cargo del comitente | D92: m2 | E92: =+[9]Locales!BD100 -> 63 | G92: =+'[9]APU 06.25'!E36 -> 6932.2708 | H92: =F92+G92 -> 6932.2708 | J92: =+'[9]APU 06.25'!H36 -> 12793.021 | K92: =I92+J92 -> 12793.021 | L92: =+'[9]APU 06.25'!K36 -> 245.43421 | M92: =H92+K92+L92 -> 19970.726 | N92: =F92*E92 -> 0 | O92: =G92*E92 -> 436733.06 | P92: =I92*E92 -> 0 | Q92: =J92*E92 -> 805960.34 | R92: =+L92*E92 -> 15462.355 | S92: =SUM(N92:R92) -> 1258155.8 | U92: =+ROUNDUP(M92*$T$5,0) -> 27090 | V92: =+U92*E92 -> 1706670
A93: 11.05 | B93: OK | C93: Provisión y colocación de sustrato - No cotiza | D93: m2 | E93: =+[9]Locales!BI100 -> 25 | H93: =F93+G93 -> 0 | K93: =I93+J93 -> 0 | M93: =H93+K93+L93 -> 0 | N93: =F93*E93 -> 0 | O93: =G93*E93 -> 0 | P93: =I93*E93 -> 0 | Q93: =J93*E93 -> 0 | R93: =+L93*E93 -> 0 | S93: =SUM(N93:R93) -> 0 | U93: =+ROUNDUP(M93*$T$5,0) -> 0 | V93: =+U93*E93 -> 0
A94: 11.06 | B94: OK | C94: Provisión y ejecución de alisado de cemento rodillado | D94: m2 | E94: =+[9]Locales!BH100 -> 27 | G94: =+'[9]APU 06.25'!E29 -> 4104.3832 | H94: =F94+G94 -> 4104.3832 | J94: =+'[9]APU 06.25'!H29 -> 11112.816 | K94: =I94+J94 -> 11112.816 | L94: =+'[9]APU 06.25'!K29 -> 306.635 | M94: =H94+K94+L94 -> 15523.834 | N94: =F94*E94 -> 0 | O94: =G94*E94 -> 110818.35 | P94: =I94*E94 -> 0 | Q94: =J94*E94 -> 300046.04 | R94: =+L94*E94 -> 8279.1449 | S94: =SUM(N94:R94) -> 419143.53 | U94: =+ROUNDUP(M94*$T$5,0) -> 21058 | V94: =+U94*E94 -> 568566
A95: 11.07 | B95: OK | C95: Colocación de baldoson de vereda - Provisión a cargo del comitente | D95: m2 | E95: =+[9]Locales!BJ100 -> 180 | G95: =+'[9]APU 06.25'!E36 -> 6932.2708 | H95: =F95+G95 -> 6932.2708 | J95: =+'[9]APU 06.25'!H36 -> 12793.021 | K95: =I95+J95 -> 12793.021 | L95: =+'[9]APU 06.25'!K36 -> 245.43421 | M95: =H95+K95+L95 -> 19970.726 | N95: =F95*E95 -> 0 | O95: =G95*E95 -> 1247808.7 | P95: =I95*E95 -> 0 | Q95: =J95*E95 -> 2302743.8 | R95: =+L95*E95 -> 44178.158 | S95: =SUM(N95:R95) -> 3594730.7 | U95: =+ROUNDUP(M95*$T$5,0) -> 27090 | V95: =+U95*E95 -> 4876200
A96: 12 | C96: ZOCALOS Y SOLIAS - PROVISION A CARGO DEL COMITENTE | T96: =SUM(S97:S100) -> 11405978 | W96: =SUM(V97:V100) -> 15472374 | X96: =+W96/$W$213 -> 0.010042933
A97: 12.01 | B97: OK | C97: Provisión y colocación de zocalos de Madera (MDF) h: 5 cm | D97: ml | E97: =+[9]Locales!BL100 -> 792 | F97: =+[9]Tareas!H169 -> 4349.9864 | G97: =+[9]Tareas!I169 -> 0 | H97: =F97+G97 -> 4349.9864 | I97: =+[9]Tareas!Q169 -> 0 | J97: =+[9]Tareas!R169 -> 5122.3554 | K97: =I97+J97 -> 5122.3554 | L97: =(H97+K97)*0.015 -> 142.08513 | M97: =H97+K97+L97 -> 9614.427 | N97: =F97*E97 -> 3445189.3 | O97: =G97*E97 -> 0 | P97: =I97*E97 -> 0 | Q97: =J97*E97 -> 4056905.5 | R97: =+L97*E97 -> 112531.42 | S97: =SUM(N97:R97) -> 7614626.2 | U97: =+ROUNDUP(M97*$T$5,0) -> 13042 | V97: =+U97*E97 -> 10329264
A98: 12.02 | B98: OK | C98: Colocación de zócalo de porcelanato en balcones UF - Provisión a cargo del comitente | D98: ml | E98: =+[9]Locales!BN100 -> 282 | G98: =+'[9]APU 06.25'!E38 -> 1001.4972 | H98: =F98+G98 -> 1001.4972 | J98: =+'[9]APU 06.25'!H38 -> 5543.6425 | K98: =I98+J98 -> 5543.6425 | L98: =+'[9]APU 06.25'!K38 -> 106.35482 | M98: =H98+K98+L98 -> 6651.4946 | N98: =F98*E98 -> 0 | O98: =G98*E98 -> 282422.21 | P98: =I98*E98 -> 0 | Q98: =J98*E98 -> 1563307.2 | R98: =+L98*E98 -> 29992.06 | S98: =SUM(N98:R98) -> 1875721.5 | U98: =+ROUNDUP(M98*$T$5,0) -> 9023 | V98: =+U98*E98 -> 2544486
A99: 12.03 | B99: OK | C99: Colocación de zócalo de porcelanato en espacios comunes - Provisión a cargo del comitente | D99: ml | E99: =+[9]Locales!BO100 -> 263 | G99: =+'[9]APU 06.25'!E38 -> 1001.4972 | H99: =F99+G99 -> 1001.4972 | J99: =+'[9]APU 06.25'!H38 -> 5543.6425 | K99: =I99+J99 -> 5543.6425 | L99: =+'[9]APU 06.25'!K38 -> 106.35482 | M99: =H99+K99+L99 -> 6651.4946 | N99: =F99*E99 -> 0 | O99: =G99*E99 -> 263393.76 | P99: =I99*E99 -> 0 | Q99: =J99*E99 -> 1457978 | R99: =+L99*E99 -> 27971.319 | S99: =SUM(N99:R99) -> 1749343.1 | U99: =+ROUNDUP(M99*$T$5,0) -> 9023 | V99: =+U99*E99 -> 2373049
A100: 12.04 | B100: OK | C100: Colocación de solia - Provisión a cargo del comitente | D100: ml | E100: =+[9]Locales!BK100 -> 25 | G100: =+'[9]APU 06.25'!E38 -> 1001.4972 | H100: =F100+G100 -> 1001.4972 | J100: =+'[9]APU 06.25'!H38 -> 5543.6425 | K100: =I100+J100 -> 5543.6425 | L100: =+'[9]APU 06.25'!K38 -> 106.35482 | M100: =H100+K100+L100 -> 6651.4946 | N100: =F100*E100 -> 0 | O100: =G100*E100 -> 25037.43 | P100: =I100*E100 -> 0 | Q100: =J100*E100 -> 138591.06 | R100: =+L100*E100 -> 2658.8706 | S100: =SUM(N100:R100) -> 166287.36 | U100: =+ROUNDUP(M100*$T$5,0) -> 9023 | V100: =+U100*E100 -> 225575
...

Sheet AING Gtos Desarrollo
F1: DÓLAR BNA | G1: DÓLAR MEP
F2: 1066.5 | G2: 1170
F4: 46063 | K4: CERTIFICACION MENSUAL
B5: OBRA: EDIFICIO GDR 3760 | L5: 46082 | M5: 46113 | N5: 46143 | O5: 46174 | P5: 46204 | Q5: 46235 | R5: 46266 | S5: 46296 | T5: 46327 | U5: 46357 | V5: 46388 | W5: 46419 | X5: 46447 | Y5: 46478 | Z5: 46508 | AA5: 46539 | AB5: 46569 | AC5: 46600 | AD5: 46631 | AE5: 46661
B6: GASTOS DESARROLLO AING | K6: MES 0 | L6: MES 1 | M6: MES 2 | N6: MES 3 | O6: MES 4 | P6: MES 5 | Q6: MES 6 | R6: MES 7 | S6: MES 8 | T6: MES 9 | U6: MES 10 | V6: MES 11 | W6: MES 12 | X6: MES 13 | Y6: MES 14 | Z6: MES 15 | AA6: MES 16 | AB6: MES 17 | AC6: MES 18 | AD6: MES 19 | AE6: MES 20
B7: Descripción | C7: U | D7: Cant | E7: P unit | F7: Subtotal
A8: 1 | B8: ='[10]Estructura De Costos'!B20 -> Descripcion | G8: =SUM(F9:F17) -> 307445.5 | H8: =+G8/$G$18 -> 1
A9: 1.01 | B9: ='[10]Estructura De Costos'!B21 -> Proyecto | C9: gl | D9: 1 | E9: ='[10]Estructura De Costos'!D21 -> 22496.012 | F9: =+E9*D9 -> 22496.012 | L9: 0.025 | M9: 0.025 | N9: 0.025 | O9: 0.025 | P9: 0.025 | Q9: 0.025 | R9: 0.025 | S9: 0.025 | T9: 0.025 | U9: 0.025 | V9: 0.025 | W9: 0.025 | X9: 0.025 | Y9: 0.025 | Z9: 0.025 | AA9: 0.025 | AB9: 0.025 | AC9: 0.025 | AD9: 0.025 | AE9: 0.025 | AF9: =SUM(L9:AE9) -> 0.5
A10: 1.02 | B10: ='[10]Estructura De Costos'!B22 -> Direccion | C10: gl | D10: 1 | E10: ='[10]Estructura De Costos'!D22 -> 44992.025 | F10: =+E10*D10 -> 44992.025 | L10: 0.05 | M10: =$L$10 -> 0.05 | N10: =$L$10 -> 0.05 | O10: =$L$10 -> 0.05 | P10: =$L$10 -> 0.05 | Q10: =$L$10 -> 0.05 | R10: =$L$10 -> 0.05 | S10: =$L$10 -> 0.05 | T10: =$L$10 -> 0.05 | ... AE10: =$L$10 -> 0.05 | AF10: =SUM(L10:AE10) -> 1
A11: 1.03 | B11: ='[10]Estructura De Costos'!B23 -> Honorarios Desarrollo | C11: gl | D11: 1 | E11: ='[10]Estructura De Costos'!D23 -> 14997.342 | F11: =+E11*D11 -> 14997.342 | L11: 0.05 | M11: =$L$10 -> 0.05 | N11: =$L$10 -> 0.05 | O11: =$L$10 -> 0.05 | P11: =$L$10 -> 0.05 | Q11: =$L$10 -> 0.05 | R11: =$L$10 -> 0.05 | S11: =$L$10 -> 0.05 | T11: =$L$10 -> 0.05 | ... AE11: =$L$10 -> 0.05 | AF11: =SUM(L11:AE11) -> 1
A12: 1.04 | B12: ='[10]Estructura De Costos'!B24 -> Gastos Admin. Fideicomiso | C12: gl | D12: 1 | E12: ='[10]Estructura De Costos'!D24 -> 67488.037 | F12: =+E12*D12 -> 67488.037 | L12: 0.025 | M12: 0.025 | N12: 0.025 | O12: 0.025 | P12: 0.025 | Q12: 0.025 | R12: 0.025 | S12: 0.025 | T12: 0.025 | U12: 0.025 | V12: 0.025 | W12: 0.025 | X12: 0.025 | Y12: 0.025 | Z12: 0.025 | AA12: 0.025 | AB12: 0.025 | AC12: 0.025 | AD12: 0.025 | AE12: 0.025 | AF12: =SUM(L12:AE12) -> 0.5
A13: 1.05 | B13: ='[10]Estructura De Costos'!B25 -> Derecho Construccion | C13: gl | D13: 1 | E13: ='[10]Estructura De Costos'!D25 -> 22496.012 | F13: =+E13*D13 -> 22496.012
A14: 1.06 | B14: ='[10]Estructura De Costos'!B26 -> Gestion Municipal | C14: gl | D14: 1 | E14: ='[10]Estructura De Costos'!D26 -> 14997.342 | F14: =+E14*D14 -> 14997.342
A15: 1.07 | B15: ='[10]Estructura De Costos'!B27 -> Fee Ventas | C15: gl | D15: 1 | E15: ='[10]Estructura De Costos'!D27 -> 44992.025 | F15: =+E15*D15 -> 44992.025
A16: 1.08 | B16: ='[10]Estructura De Costos'!B28 -> Marketing | C16: gl | D16: 1 | E16: ='[10]Estructura De Costos'!D28 -> 0 | F16: =+E16*D16 -> 0
A17: 1.09 | B17: ='[10]Estructura De Costos'!B29 -> Imprevistos | C17: gl | D17: 1 | E17: ='[10]Estructura De Costos'!D29 -> 74986.708 | F17: =+E17*D17 -> 74986.708 | AF17: =SUM(L17:AE17) -> 0
B18: SUBTOTAL SIN IVA | F18: =SUM(F8:F17) -> 307445.5 | G18: =SUM(G8:G17) -> 307445.5 | H18: =+G18/$G$18 -> 1
K19: PTO AING | L19: =+SUMPRODUCT($F$9:$F$17,L9:L17) -> 5249.0695 | M19: =+SUMPRODUCT($F$9:$F$17,M9:M17) -> 5249.0695 | N19: =+SUMPRODUCT($F$9:$F$17,N9:N17) -> 5249.0695 | O19: =+SUMPRODUCT($F$9:$F$17,O9:O17) -> 5249.0695 | P19: =+SUMPRODUCT($F$9:$F$17,P9:P17) -> 5249.0695 | Q19: =+SUMPRODUCT($F$9:$F$17,Q9:Q17) -> 5249.0695 | R19: =+SUMPRODUCT($F$9:$F$17,R9:R17) -> 5249.0695 | S19: =+SUMPRODUCT($F$9:$F$17,S9:S17) -> 5249.0695 | ... AE19: =+SUMPRODUCT($F$9:$F$17,AE9:AE17) -> 5249.0695 | AF19: =SUM(L19:AE19) -> 104981.39
B20: Gestion de compras provisiones | D20: 0.05 | E20: ='[10]Estructura De Costos'!D16 -> 380016 | F20: =+E20*D20 -> 19000.8 | K20: ACUMULADO | L20: =+L19 -> 5249.0695 | M20: =+L20+M19 -> 10498.139 | N20: =+M20+N19 -> 15747.209 | O20: =+N20+O19 -> 20996.278 | P20: =+O20+P19 -> 26245.348 | Q20: =+P20+Q19 -> 31494.417 | R20: =+Q20+R19 -> 36743.487 | S20: =+R20+S19 -> 41992.556 | T20: =+S20+T19 -> 47241.626 | ... AE20: =+AD20+AE19 -> 104981.39
L21: =L20/$G$18 -> 0.017073171 | M21: =M20/$G$18 -> 0.034146341 | N21: =N20/$G$18 -> 0.051219512 | O21: =O20/$G$18 -> 0.068292683 | P21: =P20/$G$18 -> 0.085365854 | Q21: =Q20/$G$18 -> 0.10243902 | R21: =R20/$G$18 -> 0.1195122 | S21: =S20/$G$18 -> 0.13658537 | ... AE21: =AE20/$G$18 -> 0.34146341

Sheet Indice CAC
B4: CAC - Pto. General
B5: Escala de tiempo | C5: Valores | D5: Previsión | E5: Indice
B6: 45778 | C6: 16521.3 | E6: =$C$6/C6 -> 1
B7: 45809 | C7: 16643.4 | E7: =$C$6/C7 -> 0.99266376
B8: 45839 | C8: 16939.5 | E8: =$C$6/C8 -> 0.97531214
B9: 45870 | C9: 17187.6 | E9: =$C$6/C9 -> 0.96123368
B10: 45901 | C10: 17762.3 | E10: =$C$6/C10 -> 0.93013292
B11: 45931 | C11: 18172.8 | E11: =$C$6/C11 -> 0.90912242
B12: 45962 | C12: 18534.9 | E12: =$C$6/C12 -> 0.8913617
B13: 45992 | C13: 18776.5 | E13: =$C$6/C13 -> 0.87989242
B14: 46023 | C14: 19209.4 | E14: =$C$6/C14 -> 0.8600633
B15: 46054 | C15: 19453 | E15: =$C$6/C15 -> 0.84929317
B16: 46082 | C16: 19771.2 | D16: 19771.2 | E16: =$C$6/C16 -> 0.83562454
B17: 46113 | C17: 20138.793 | D17: 20138.793 | E17: =$C$6/C17 -> 0.82037189
B18: 46143 | C18: 20471.346 | D18: 20471.346 | E18: =$C$6/C18 -> 0.80704512
B19: 46174 | C19: 20471.346 | D19: 20471.346 | E19: =$C$6/C19 -> 0.80704512

Sheet C. Gestión Pto #1
B1: OBRA: CHIVILCOY 2171 | J1: Actualizado | K1: 46174
B2: CUADRO DE GESTIÓN CONSOLIDADO - Pto. #1
B4: Cuenta | C4: 45962 | D4: 45992 | E4: 46023 | F4: 46054 | G4: 46082 | H4: 46113 | I4: 46143
B5: Seguridad e Higiene | F5: 517195 | G5: 826285.91 | H5: 517195 | I5: 1195790
B6: Supervisión de Obra | G6: 2800000 | H6: 2867000 | I6: 2850000
B7: Agrimensura | G7: =SUM(Contratistas!C15:C16) -> 730000
B8: Preliminares | E8: 939182.1 | F8: =1019988.94+Contratistas!C7 -> 1539988.9 | G8: 3125044.3 | H8: =214909.88+Contratistas!C8 -> 734909.88
B9: Movilidad | G9: 639742.64 | H9: 716525.59 | I9: 38016.53
B10: Excavación y Mov. de Suelos | H10: =Contratistas!C34 -> 1310000
B11: HormigónMAT | G11: =16836280+(Contratistas!C23*Contratistas!G20) -> 20721536 | H11: =475908.53+(SUM(Contratistas!C24:D25)*Contratistas!G20) -> 4488122.6 | I11: {=12023059.99+SUM(Contratistas!C27:C28*Contratistas!G20)} -> 13222352
B12: HormigónMO | G12: =SUM(Contratistas!C23*Contratistas!H20)+SUM('Horm M.O.'!M13:M14) -> 19211836 | H12: =SUM(Contratistas!C24:D25)*Contratistas!H20+SUM('Horm M.O.'!M15:M16) -> 19661613 | I12: {=13672616.05+SUM(Contratistas!C27:C28*Contratistas!H20)+SUM('Horm M.O.'!M17:M18)} -> 30526436
B13: AlbañileríaMAT | F13: 48248.1 | G13: 95942.03 | H13: 371787.4 | I13: 171269.97
B14: AlbañileríaMO | H14: =250000+SUM('Alba M.O. '!M11:M12) -> 2330315.7
B15: Gastos Generales Obra | F15: 247000 | G15: 227000 | H15: 1101000 | I15: 1520000
B16: Equipos | I16: 702737.42
B17: Total | C17: =SUM(C5:C16) -> 0 | D17: =SUM(D5:D16) -> 0 | E17: =SUM(E5:E16) -> 939182.1 | F17: =SUM(F5:F16) -> 2352432 | G17: =SUM(G5:G16) -> 48377387 | H17: =SUM(H5:H16) -> 34098469 | I17: =SUM(I5:I16) -> 50226602
B19: Gtos Directos | C19: 45962 | D19: 45992 | E19: 46023 | F19: 46054 | G19: 46082 | H19: 46113 | I19: 46143
B20: Oficina en obra (6x3 c/AA)
B21: Obrador 6x3 s/AA
B22: Pañol (6x3)
B23: Baños
B24: HyS permanente
B25: Energía de obra
B26: Agua de obra
B27: Proyecto (50%) | G27: 1259725.3 | H27: 1330802 | I27: 994750.57
B28: Coordinacion de obra | G28: 261562.8 | H28: 266794 | I28: 271596.2
B29: Sobrestante
B30: Capataz
B31: Logistica
B32: Vehiculo obra | I32: 469667.89
B33: Gastos Directos | C33: =SUM(C20:C32) -> 0 | D33: =SUM(D20:D32) -> 0 | E33: =SUM(E20:E32) -> 0 | F33: =SUM(F20:F32) -> 0 | G33: =SUM(G20:G32) -> 1521288.1 | H33: =SUM(H20:H32) -> 1597596 | I33: =SUM(I20:I32) -> 1736014.7
B35: Gtos Indirectos | C35: 45962 | D35: 45992 | E35: 46023 | F35: 46054 | G35: 46082 | H35: 46113 | I35: 46143
B36: Payroll - Socios | G36: 625000.05 | H36: 625000.05 | I36: 625000
B37: Intereses Financiamiento
B38: Payroll - Administración | G38: 1109248.1 | H38: 1261946.3 | I38: 1208735.9
B39: Gastos Indirectos | C39: =SUM(C36:C38) -> 0 | D39: =SUM(D36:D38) -> 0 | E39: =SUM(E36:E38) -> 0 | F39: =SUM(F36:F38) -> 0 | G39: =SUM(G36:G38) -> 1734248.2 | H39: =SUM(H36:H38) -> 1886946.4 | I39: =SUM(I36:I38) -> 1833735.9

Sheet C. Gestión Pto #2
B1: OBRA: CHIVILCOY 2171 | J1: Actualizado | K1: 46133
B2: CUADRO DE GESTIÓN CONSOLIDADO - Pto. #2
B4: Cuenta | C4: 45962 | D4: 45992 | E4: 46023 | F4: 46054 | G4: 46082 | H4: 46113 | I4: 46143
B5: Supervisión de Obra
B6: Seguridad e Higiene
B7: Movilidad
B8: AlbañileríaMAT
B9: AlbañileríaMO
B10: DurlockMAT
B11: DurlockMO
B12: RevestimientoMAT
B13: RevestimientoMO
B14: PinturaMAT
B15: PinturaMO
B16: EléctricoMAT
... B22: Equipos
B23: Total | C23: =SUM(C5:C22) -> 0 | D23: =SUM(D5:D22) -> 0 | E23: =SUM(E5:E22) -> 0 | F23: =SUM(F5:F22) -> 0 | G23: =SUM(G5:G22) -> 0 | H23: =SUM(H5:H22) -> 0 | I23: =SUM(I5:I22) -> 0
B26: Gtos Directos | C26: 45962 | D26: 45992 | E26: 46023 | F26: 46054 | G26: 46082 | H26: 46113 | I26: 46143
