Workbook
Name \0: #REF!
Name \0: #REF!
Name \0: #REF!
Name \c: #REF!
Name \c: #REF!
Name \E: #REF!
Name \E: #REF!
Name \i: #REF!
Name \j: #REF!
Name \m: #REF!
Name \P: #REF!
Name \P: #REF!
Name \P: #REF!
Name \P: #REF!
Name \P: #REF!
Name \r: #N/A
Name \x: #REF!
Name \z: #REF!
Name __________ben1: #REF!
Name __________ben1: #REF!
Name __________ben1: #REF!
Name __________ben1: #REF!
Name __________ben1: #REF!
Name __________ben1: #REF!
Name __________ben10: #REF!
Name __________ben10: #REF!
Name __________ben10: #REF!
Name __________ben10: #REF!
Name __________ben10: #REF!
Name __________ben15: #REF!
Name __________ben15: #REF!
Name __________ben15: #REF!
Name __________ben15: #REF!
Name __________BEN2: #REF!
Name __________BEN2: #REF!
Name __________BEN2: #REF!
Name __________BEN2: #REF!
Name __________ben20: #REF!
Name __________ben20: #REF!
Name __________ben20: #REF!
Name __________ben20: #REF!
Name __________ben20: #REF!
Name __________ben25: #REF!
Name __________ben25: #REF!
Name __________ben25: #REF!
Name __________ben25: #REF!
Name __________ben25: #REF!
Name __________BEN3: #REF!
Name __________BEN3: #REF!
Name __________BEN3: #REF!
Name __________BEN3: #REF!
Name __________BEN3: #REF!
Name __________BEN4: #REF!
Name __________BEN4: #REF!
Name __________BEN4: #REF!
Name __________BEN4: #REF!
Name __________ben5: #REF!
Name __________ben5: #REF!
Name __________ben5: #REF!
Name __________ben5: #REF!

Sheet AING SALV4140 03
F1: DÓLAR BNA | G1: DÓLAR MEP
F2: =+GGBB!G4 -> 1005 | G2: =+GGBB!H4 -> 1170
F4: 45590
B5: OBRA: EDIFICIO EL SALVADOR 4140
B6: PRESUPUESTO OBRA CIVIL
B7: Descripción | C7: U | D7: Cant | E7: P unit | F7: Subtotal
A8: 1 | B8: TAREAS PRELIMINARES | G8: =SUM(F9:F18) -> 24784163 | H8: =+G8/$G$218 -> 0.018338605
A9: 1.01 | B9: Limpieza y preparación del terreno - No cotiza | C9: gl | D9: 0 | E9: 0 | F9: =+E9*D9 -> 0
A10: 1.02 | B10: Topógrafo - Visita de obra replanteo | C10: un | D10: 3 | E10: 379588 | F10: =+E10*D10 -> 1138764
A11: 1.03 | B11: Cartel de Obra - No cotiza | C11: gl | D11: 0 | E11: 0 | F11: =+E11*D11 -> 0
A12: 1.04 | B12: Cerco de obra perimetral - En chapa C25 + Concertina + Porton corredizo | C12: ml | D12: 11 | E12: 141220 | F12: =+E12*D12 -> 1553420
A13: 1.05 | B13: Obrador colgante, pañol y ducha | C13: gl | D13: 1 | E13: 7548771 | F13: =+E13*D13 -> 7548771
A14: 1.06 | B14: Alquiler de baños quimicos y duchas portatiles | C14: mes | D14: 3 | E14: 392028 | F14: =+E14*D14 -> 1176084
A15: 1.07 | B15: Conexión pilar y luz de obra + Tablero de obra | C15: gl | D15: 1 | E15: 1731320 | F15: =+E15*D15 -> 1731320
A16: 1.08 | B16: Conexión agua de obra, tanque + bomba | C16: gl | D16: 1 | E16: 1405632 | F16: =+E16*D16 -> 1405632
A17: 1.09 | B17: Tramite luz de obra, certificado luz de obra (2) y medición PAT | C17: gl | D17: 1 | E17: 426487 | F17: =+E17*D17 -> 426487
A18: 1.1 | B18: Sistema de depresión de napas | C18: gl | D18: 1 | E18: 9803685 | F18: =+E18*D18 -> 9803685
A19: 2 | B19: MOVIMIENTO DE TIERRA, COMPACTACION Y RELLENO | G19: =SUM(F20:F22) -> 42017464 | H19: =+G19/$G$218 -> 0.031090082
A20: 2.01 | B20: Excavación a maquina para submuración y subsuelo | C20: m3 | D20: 1266 | E20: 33090 | F20: =+E20*D20 -> 41891940
A21: 2.02 | B21: Demolición y retiro de fundaciones existentes - No cotiza | C21: gl | D21: 0 | E21: 0 | F21: =+E21*D21 -> 0
A22: 2.03 | B22: Excavación manual para pozo de achique y bombeo | C22: m3 | D22: 2 | E22: 62762 | F22: =+E22*D22 -> 125524
A23: 3 | B23: ESTRUCTURA RESISTENTE | G23: =SUM(F24:F42) -> 477142865 | H23: =+G23/$G$218 -> 0.35305346
A24: 26.01 | B24: Hierro c/ corte y doblado | C24: kg | D24: 71835 | E24: 1676 | F24: =+E24*D24 -> 120395460
A25: 26.02 | B25: H° - inc hidrofugo, bombeo, piedra 6/12 | C25: m3 | D25: 641 | E25: 161742 | F25: =+E25*D25 -> 103676622
A26: 3.01 | B26: Hormigón de limpieza - e: 10 cm | C26: m3 | D26: 35 | E26: 314478 | F26: =+E26*D26 -> 11006730
A27: 3.02 | B27: Tabique submuración - H30 hidrófugo (95 kg/m3 de hierro) | C27: m3 | D27: 40 | E27: 482909 | F27: =+E27*D27 -> 19316360
A28: 3.03 | B28: Zapata corrida tabique - H30 hidrófugo (120 kg/m3) | C28: m3 | D28: 28 | E28: 394283 | F28: =+E28*D28 -> 11039924
A29: 3.04 | B29: Platea - H30 hidrófugo (95 kg/m3 de hierro) | C29: m3 | D29: 179 | E29: 193197 | F29: =+E29*D29 -> 34582263
A30: 3.05 | B30: Rampa - H30 (120 kg/m3 de hierro) | C30: m3 | D30: 10 | E30: 416850 | F30: =+E30*D30 -> 4168500
A31: 3.06 | B31: Losa maciza - H30 (110 kg/m3 de hierro) | C31: m3 | D31: 177 | E31: 285821 | F31: =+E31*D31 -> 50590317
A32: 3.07 | B32: Vigas - H30 (140 kg/m3 de hierro) | C32: m3 | D32: 65 | E32: 710813 | F32: =+E32*D32 -> 46202845
A33: 3.08 | B33: Vigas de H° visto - H30 (140 kg/m3 de hierro) | C33: m3 | D33: 12 | E33: 826182 | F33: =+E33*D33 -> 9914184
A34: 3.09 | B34: Tabiques - H30 (120 kg/m3 de hierro) | C34: m3 | D34: 28 | E34: 482909 | F34: =+E34*D34 -> 13521452
A35: 3.1 | B35: Columna - H30 (240 Kg/m3 de hierro) | C35: m3 | D35: 54 | E35: 426874 | F35: =+E35*D35 -> 23051196
... A42: 3.17 | B42: Picado de medianeras para columnas y vigas - Cotizado solo para PB y 1P, No contempla picado en SS | C42: m2 | D42: 93 | E42: 24580 | F42: =+E42*D42 -> 2285940
A43: 4 | B43: ALBAÑILERIA | G43: =SUM(F44:F51) -> 54302890 | H43: =+G43/$G$218 -> 0.040180467
A44: 4.01 | B44: Muro tipo 1 (interiores, divisorio de locales) e: 10 cm - Ladrillo hueco 08 x 18 x 33 | C44: m2 | D44: 819 | E44: 18993 | F44: =+E44*D44 -> 15555267
A45: 4.02 | B45: Muro tipo 2 y 3 (medianera, caja de escaleras y ascensor) e: 15 cm - Ladrillo hueco portante 12 x 19 x 33 | C45: m2 | D45: 612 | E45: 25172 | F45: =+E45*D45 -> 15405264
A46: 4.03 | B46: Muro tipo 4 (divisorio de unidades y fachas) e: 15 cm - Ladrillo hueco 12 x 18 x 33 | C46: m2 | D46: 636 | E46: 21109 | F46: =+E46*D46 -> 13425324
A47: 4.04 | B47: Enchape medianeras existentes - Contemplamos picado zonas sueltas y enchape con ladrillo comun para PB | C47: m2 | D47: 195 | E47: 15092 | F47: =+E47*D47 -> 2942940
A48: 4.05 | B48: Mamposteria cribada de ladrillo visto en balcones | C48: m2 | D48: 30.054 | E48: 67420 | F48: =+E48*D48 -> 2026240.7
A49: 4.06 | B49: Bloque de H° con masillado de hormigon | C49: m2 | D49: 24 | E49: 54908 | F49: =+E49*D49 -> 1317792
A50: 4.07 | B50: Cordón de hormigón en umbrales carpinterías | C50: ml | D50: 81 | E50: 30989 | F50: =+E50*D50 -> 2510109
A51: 4.08 | B51: Pozo de bombeo pluvial y cloacal | C51: gl | D51: 1 | E51: 1119953 | F51: =+E51*D51 -> 1119953
A52: 5 | B52: AISLACIONES | G52: =SUM(F53:F59) -> 35966419 | H52: =+G52/$G$218 -> 0.026612718
A53: 5.01 | B53: Aislación hidrófuga horizontal (baños) - Inc. membrana geotextil y 35% en concepto de babetas | C53: m2 | D53: 139.05 | E53: 21800 | F53: =+E53*D53 -> 3031290
A54: 5.02 | B54: Azotado hidrofugo - Sobre medianeras existentes | C54: m2 | D54: 300 | E54: 5376 | F54: =+E54*D54 -> 1612800
A55: 5.03 | B55: Azotado hidrofugo - Contrapiso de vereda | C55: m2 | D55: 48 | E55: 5376 | F55: =+E55*D55 -> 258048
A56: 5.04 | B56: Aislación térmica en terrazas, eps e:2,00 cm | C56: m2 | D56: 262 | E56: 4403 | F56: =+E56*D56 -> 1153586
A57: 5.05 | B57: Barrera de vapor | C57: m2 | D57: 510 | E57: 3578 | F57: =+E57*D57 -> 1824780
A58: 5.06 | B58: Membrana asfaltica geotextil 4mm - Balcones y azotea - Inc. 20% en concepto de babetas | C58: m2 | D58: 510 | E58: 21800 | F58: =+E58*D58 -> 11118000
A59: 5.07 | B59: Impermeabilización de subsuelo | C59: gl | D59: 1 | E59: 16967915 | F59: =+E59*D59 -> 16967915
A60: 6 | B60: CUBIERTAS | G60: =SUM(F61:F61) -> 2433900 | H60: =+G60/$G$218 -> 0.0018009214
A61: 6.02 | B61: Babeta de chapa galvanizada en medianeras | C61: ml | D61: 60 | E61: 40565 | F61: =+E61*D61 -> 2433900
A62: 7 | B62: REVOQUES | G62: =SUM(F63:F70) -> 1.3639056e+08 | H62: =+G62/$G$218 -> 0.10091979
A63: 7.01 | B63: Revoque Grueso Impermeable Exterior proyectable | C63: m2 | D63: 678.252 | E63: 16571 | F63: =+E63*D63 -> 11239314
A64: 7.02 | B64: Revoque Grueso Impermeable Exterior a mas de 3m proyectable - Medianero y fachadas | C64: m2 | D64: 876.0812 | E64: 22183 | F64: =+E64*D64 -> 19434109
A65: 7.03 | B65: Buña en revoque | C65: ml | D65: 182 | E65: 10806 | F65: =+E65*D65 -> 1966692
A66: 7.04 | B66: Revoque Grueso Interior + fino | C66: m2 | D66: 995.8511 | E66: 26530 | F66: =+E66*D66 -> 26419930
A67: 7.05 | B67: Yeso interior | C67: m2 | D67: 2514.897 | E67: 22566 | F67: =+E67*D67 -> 56751166
A68: 7.06 | B68: Arista en yeso | C68: ml | D68: 509.9 | E68: 12771 | F68: =+E68*D68 -> 6511932.9
A69: 7.07 | B69: Provisión y colocación de guardacanto yesero | C69: u | D69: 198 | E69: 14947 | F69: =+E69*D69 -> 2959506
A70: 7.08 | B70: Revoque Grueso Impermeable Interior b/ revestimiento | C70: m2 | D70: 670.322 | E70: 16571 | F70: =+E70*D70 -> 11107906
A71: 8 | B71: CONTRAPISOS Y CARPETAS | G71: =SUM(F72:F79) -> 44788107 | H71: =+G71/$G$218 -> 0.033140171
A72: 8.01 | B72: Contrapiso de cascotes en SS e: 15 cm | C72: m2 | D72: 104 | E72: 31920 | F72: =+E72*D72 -> 3319680
A73: 8.02 | B73: Contrapiso de cascote s/terreno natural e: 20 cm - Incluye film de polietileno | C73: m2 | D73: 48 | E73: 37268 | F73: =+E73*D73 -> 1788864
A74: 8.03 | B74: Contrapiso de cascotes en azoteas c/pendiente e: 15 cm | C74: m2 | D74: 235 | E74: 32410 | F74: =+E74*D74 -> 7616350
A75: 8.04 | B75: Contrapiso - Carpeta monolitico e: 7 cm | C75: m2 | D75: 878 | E75: 19006 | F75: =+E75*D75 -> 16687268
A76: 8.05 | B76: Carpeta en PB y balcones, baños y azoteas e: 3,00 cm | C76: m2 | D76: 564 | E76: 12439 | F76: =+E76*D76 -> 7015596
A77: 8.06 | B77: Carpeta sobre membrana | C77: m2 | D77: 438 | E77: 12439 | F77: =+E77*D77 -> 5448282
A78: 8.07 | B78: Banquinas para cocinas | C78: gl | D78: 1 | E78: 2426924 | F78: =+E78*D78 -> 2426924
A79: 8.08 | B79: Banquinas para bombas y tanques en SB | C79: gl | D79: 1 | E79: 485143 | F79: =+E79*D79 -> 485143
A80: 9 | B80: ESCALERAS | G80: =SUM(F81:F84) -> 5769056.6 | H80: =+G80/$G$218 -> 0.0042687118
A81: 9.01 | B81: Cemento alisado arrodillado en escaleras | C81: gl | D81: 1 | E81: 2024643 | F81: =+E81*D81 -> 2024643
A82: 9.02 | B82: Provisión nariz escalera, hierro angulo 5/8 x 1/8" | C82: ml | D82: 122 | E82: 18814 | F82: =+E82*D82 -> 2295308
A83: 9.03 | B83: Zócalo de concreto | C83: ml | D83: 155 | E83: 5376 | F83: =+E83*D83 -> 833280
A84: 9.04 | B84: Provisión y colocación de Rodapie/ Zócalo rampante en placa cementicia | C84: ml | D84: 31.2 | E84: 19738 | F84: =+E84*D84 -> 615825.6
A85: 10 | B85: VENTILACIONES | G85: =SUM(F86:F89) -> 4669278 | H85: =+G85/$G$218 -> 0.00345495
A86: 10.01 | B86: Ventilación Conducto Humos. Incluye toma de aire en PB - No aplica s/proyecto | C86: gl | D86: 0 | E86: 0 | F86: =+E86*D86 -> 0
A87: 10.02 | B87: Ventilación Baños - En caño Ø 110 | C87: gl | D87: 1 | E87: 2199545 | F87: =+E87*D87 -> 2199545
A88: 10.03 | B88: Colocación de rejillas de inyección y extracción - No aplica s/proyecto | C88: un | D88: 0 | E88: 0 | F88: =+E88*D88 -> 0
A89: 10.04 | B89: Sombreretes en chapa prepintada C25 | C89: u | D89: 7 | E89: 352819 | F89: =+E89*D89 -> 2469733
A90: 11 | B90: PISOS - PROVISION A CARGO DEL COMITENTE | G90: =SUM(F91:F97) -> 48040802 | H90: =+G90/$G$218 -> 0.035546945
A91: 11.01 | B91: Colocación de travertino en hall PB - Provisión a cargo del comitente | C91: m2 | D91: 30 | E91: 21948 | F91: =+E91*D91 -> 658440
A92: 11.02 | B92: Colocación de porcelanato en paliers, terraza y espacios comunes - Provisión a cargo del comitente | C92: m2 | D92: 185 | E92: 21948 | F92: =+E92*D92 -> 4060380
A93: 11.03 | B93: Colocación de porcelanato en UF - Provisión a cargo del comitente | C93: m2 | D93: 942 | E93: 21948 | F93: =+E93*D93 -> 20675016
A94: 11.04 | B94: Colocación de porcelanato en baños - Provisión a cargo del comitente | C94: m2 | D94: 110 | E94: 25799 | F94: =+E94*D94 -> 2837890
A95: 11.05 | B95: Provisión y ejecución de alisado de cemento rodillado | C95: m2 | D95: 128 | E95: 16080 | F95: =+E95*D95 -> 2058240
A96: 11.06 | B96: Colocación de baldoson de vereda - Provisión a cargo del comitente | C96: m2 | D96: 48 | E96: 21948 | F96: =+E96*D96 -> 1053504
A97: 11.07 | B97: Provisión y ejecución de pavimento e: 18 cm, incluye malla Q188 | C97: m2 | D97: 226 | E97: 73882 | F97: =+E97*D97 -> 16697332
A98: 12 | B98: ZOCALOS Y SOLIAS - PROVISION A CARGO DEL COMITENTE | G98: =SUM(F99:F103) -> 11022518 | H98: =+G98/$G$218 -> 0.008155918
A99: =+A98+0.01 -> 12.01 | B99: Provisión y colocación de zocalos de Madera (MDF) h: 7 cm | C99: ml | D99: 779 | E99: 7422 | F99: =+E99*D99 -> 5781738
A100: 12.02 | B100: Zócalo de concreto | C100: ml | D100: 155 | E100: 5376 | F100: =+E100*D100 -> 833280
A101: 12.03 | B101: Colocación de zocalo de porcelanico - Provisión a cargo del comitente | C101: ml | D101: 37 | E101: 7052 | F101: =+E101*D101 -> 260924
A102: 12.04 | B102: Colocación de zocalo de porcelanato en palieres - Provisión a cargo del comitente | C102: ml | D102: 433 | E102: 7052 | F102: =+E102*D102 -> 3053516
A103: 12.05 | B103: Colocación de zocalo de porcelanato en terraza y espacios comunes - Provisión a cargo del comitente | C103: ml | D103: 155 | E103: 7052 | F103: =+E103*D103 -> 1093060
A104: 13 | B104: REVESTIMIENTOS - PROVISION A CARGO DEL COMITENTE | G104: =SUM(F105:F108) -> 19433086 | H104: =+G104/$G$218 -> 0.01437917
A105: 13.01 | B105: Revestimiento en baños - Provisión a cargo del comitente | C105: m2 | D105: 511 | E105: 25799 | F105: =+E105*D105 -> 13183289
A106: 13.02 | B106: Revestimiento en cocinas - Provisión a cargo del comitente | C106: m2 | D106: 40 | E106: 25799 | F106: =+E106*D106 -> 1031960
A107: 13.03 | B107: Revestimiento tejuela exterior - Provisión a cargo del comitente | C107: m2 | D107: 147.601 | E107: 29881 | F107: =+E107*D107 -> 4410465.5
...

Sheet INFO.
C2: USD | F2: DÓLAR MEP
B3: VALOR ESTIMADO REFERENCIA COSTO | F3: =+GGBB!H4 -> 1170
D4: Coef Complej
C5: m2 | D5: 1 | E5: USD/ m2
B6: SUPERFICIE CUBIERTA | C6: =+F18 -> 1618.5 | D6: =+C3*D5 -> 0 | E6: =+F30 -> 972.38077 | F6: =+E6*F3*C6 -> 1.841344e+09 | G6: Valor estimado precio de venta
B8: Lote | C8: 344 | D8: m2 | E8: 0.75 | F8: SS
B9: Pisada | C9: 284 | D9: m2 | E9: 0.25 | F9: Patios
E10: 0.5 | F10: Balcones y semicubiertos
B11: Superficie | C11: Cubierto | D11: Semicubierto | E11: % | F11: Subtotal
B12: SS | C12: 0 | D12: 344 | E12: =+D12*$E$8 -> 258 | F12: =+C12+E12 -> 258
B13: PB | C13: 214 | D13: 130 | E13: =+D13*$E$9 -> 32.5 | F13: =+C13+E13 -> 246.5
B14: P 1º | C14: 251 | D14: 30 | E14: =+D14*$E$10 -> 15 | F14: =+C14+E14 -> 266 | G14: 2 | H14: planta tipo
B15: P 2° a 3° | C15: =+C14*G14 -> 502 | D15: =+D14*G14 -> 60 | E15: =+D15*$E$10 -> 30 | F15: =+C15+E15 -> 532
B16: P 4º | C16: 234 | D16: 47 | E16: =+D16*$E$10 -> 23.5 | F16: =+C16+E16 -> 257.5
B17: P Azotea | D17: 234 | E17: =+D17*$E$9 -> 58.5 | F17: =+C17+E17 -> 58.5
C18: =SUM(C12:C17) -> 1201 | D18: =SUM(D12:D17) -> 845 | E18: =SUM(E12:E17) -> 417.5 | F18: =SUM(F12:F17) -> 1618.5
H19: usd/m2
B20: OBRA CIVIL | E20: 0.7 | F20: =+'01'!W216 -> 1.1274028e+09 | G20: =+F20/F3 -> 963592.1 | H20: =+G20/C6 -> 595.3612
B21: PROVISIONES | E21: =1-E20 -> 0.3 | F21: =+G21*F20 -> 4.8317261e+08 | G21: =+E21/E20 -> 0.42857143
F22: =+F21+F20 -> 1.6105754e+09
B23: ARQ CLARIN
B24: 45588 | C24: Fecha | J24: Inc. | L24: =1+0.12+0.15 -> 1.27
I25: Electricidad | J25: 0.09 | K25: =+J25*F6 -> 1.6572096e+08 | L25: =+$L$24*K25 -> 2.1046562e+08
B26: (se toma MODELO 6 Vivienda en altura) | C26: m2 | D26: $/ m2 | I26: Sanitaria s/ calef | J26: 0.08 | K26: =+J26*F6 -> 1.4730752e+08 | L26: =+$L$24*K26 -> 1.8708055e+08
B27: VALOR ESTIMADO REFERENCIA COSTO | C27: =+C6 -> 1618.5 | D27: 1625265 | F27: =+D27*C27 -> 2.6304914e+09 | G27: Valor estimado precio de venta
D28: usd/m2 | F28: =+F27/F3 -> 2248283.2 | G28: USD
D29: =+D27/F3 -> 1389.1154 | F29: =+F28/C27 -> 1389.1154 | G29: usd/m2
F30: =+F29*E20 -> 972.38077 | G30: usd/m2 sin provisiones

Sheet 01
F1: OK | G1: Listo | V1: DÓLAR BNA | W1: DÓLAR MEP
F2: IN | G2: Estimado | V2: =+GGBB!G4 -> 1005 | W2: =+GGBB!H4 -> 1170
F3: C | G3: Chekear (Inventado)
F4: R | G4: Sin hacer/revisar | T4: 1 | V4: 45590
C5: OBRA: EDIFICIO EL SALVADOR 4140 | F5: MATERIAL | I5: M. DE OBRA | N5: MATERIAL | P5: M. DE OBRA | T5: =+GGBB!F66 -> 1.2568826
C6: PRESUPUESTO OBRA CIVIL | T6: 1.1
C7: Descripción | D7: U | E7: Cant | F7: Otro | G7: Corralón | H7: Total | I7: Otro | J7: Albañil | K7: Total | L7: EQUIPOS | M7: P.Unit | N7: Otro | O7: Corralón | P7: Otro | Q7: Albañil | R7: EQUIPOS | S7: Total | T7: Subtotal | U7: P unit | V7: Subtotal
A8: 1 | B8: E | C8: TAREAS PRELIMINARES | T8: =SUM(S9:S18) -> 19718747 | W8: =SUM(V9:V18) -> 24784163 | X8: =+W8/$W$216 -> 0.021983415 | Y8: =+W8 -> 24784163
A9: 1.01 | B9: OK | C9: Limpieza y preparación del terreno - No cotiza | D9: gl | E9: 0 | H9: =F9+G9 -> 0 | K9: =I9+J9 -> 0 | M9: =H9+K9+L9 -> 0 | N9: =F9*E9 -> 0 | O9: =G9*E9 -> 0 | P9: =I9*E9 -> 0 | Q9: =J9*E9 -> 0 | R9: =+L9*E9 -> 0 | S9: =SUM(N9:R9) -> 0 | U9: =+ROUNDUP(M9*$T$5,0) -> 0 | V9: =+U9*E9 -> 0
A10: 1.02 | B10: OK | C10: Topógrafo - Visita de obra replanteo | D10: un | E10: 3 | F10: =+Tareas!H8 -> 0 | G10: =+Tareas!I8 -> 41666.667 | H10: =F10+G10 -> 41666.667 | I10: =+Tareas!Q8 -> 172653.21 | J10: =+Tareas!R8 -> 83223.729 | K10: =I10+J10 -> 255876.94 | L10: =+(H10+K10)*0.015 -> 4463.1541 | M10: =H10+K10+L10 -> 302006.76 | N10: =F10*E10 -> 0 | O10: =G10*E10 -> 125000 | P10: =I10*E10 -> 517959.62 | Q10: =J10*E10 -> 249671.19 | R10: =+L10*E10 -> 13389.462 | S10: =SUM(N10:R10) -> 906020.27 | U10: =+ROUNDUP(M10*$T$5,0) -> 379588 | V10: =+U10*E10 -> 1138764
A11: 1.03 | B11: OK | C11: Cartel de Obra - No cotiza | D11: gl | E11: 0 | H11: =F11+G11 -> 0 | K11: =I11+J11 -> 0 | M11: =H11+K11+L11 -> 0 | N11: =F11*E11 -> 0 | O11: =G11*E11 -> 0 | P11: =I11*E11 -> 0 | Q11: =J11*E11 -> 0 | R11: =+L11*E11 -> 0 | S11: =SUM(N11:R11) -> 0 | U11: =+ROUNDUP(M11*$T$5,0) -> 0 | V11: =+U11*E11 -> 0
A12: 1.04 | B12: OK | C12: Cerco de obra perimetral - En chapa C25 + Concertina + Porton corredizo | D12: ml | E12: 11 | F12: =+Tareas!H12 -> 79773.183 | G12: =+Tareas!I12 -> 0 | H12: =F12+G12 -> 79773.183 | I12: =+Tareas!Q12 -> 0 | J12: =+Tareas!R12 -> 30923.374 | K12: =I12+J12 -> 30923.374 | L12: =+(H12+K12)*0.015 -> 1660.4484 | M12: =H12+K12+L12 -> 112357.01 | N12: =F12*E12 -> 877505.01 | O12: =G12*E12 -> 0 | P12: =I12*E12 -> 0 | Q12: =J12*E12 -> 340157.11 | R12: =+L12*E12 -> 18264.932 | S12: =SUM(N12:R12) -> 1235927.1 | U12: =+ROUNDUP(M12*$T$5,0) -> 141220 | V12: =+U12*E12 -> 1553420
A13: 1.05 | B13: OK | C13: Obrador colgante, pañol y ducha | D13: gl | E13: 1 | F13: =+Tareas!H22 -> 2300856.7 | G13: =+Tareas!I22 -> 100000 | H13: =F13+G13 -> 2400856.7 | I13: =+Tareas!Q22 -> 500000 | J13: =+Tareas!R22 -> 3016332.5 | K13: =I13+J13 -> 3516332.5 | L13: =+(H13+K13)*0.015 -> 88757.838 | M13: =H13+K13+L13 -> 6005947 | N13: =F13*E13 -> 2300856.7 | O13: =G13*E13 -> 100000 | P13: =I13*E13 -> 500000 | Q13: =J13*E13 -> 3016332.5 | R13: =+L13*E13 -> 88757.838 | S13: =SUM(N13:R13) -> 6005947 | U13: =+ROUNDUP(M13*$T$5,0) -> 7548771 | V13: =+U13*E13 -> 7548771
A14: 1.06 | B14: OK | C14: Alquiler de baños quimicos y duchas portatiles | D14: mes | E14: 3 | H14: =F14+G14 -> 0 | I14: =+Cotizaciones!D46*4 -> 295488.56 | J14: =+(Cotizaciones!D47*2*2)/'01'!E14 -> 16416.031 | K14: =I14+J14 -> 311904.59 | M14: =H14+K14+L14 -> 311904.59 | N14: =F14*E14 -> 0 | O14: =G14*E14 -> 0 | P14: =I14*E14 -> 886465.68 | Q14: =J14*E14 -> 49248.093 | R14: =+L14*E14 -> 0 | S14: =SUM(N14:R14) -> 935713.77 | U14: =+ROUNDUP(M14*$T$5,0) -> 392028 | V14: =+U14*E14 -> 1176084
A15: 1.07 | B15: OK | C15: Conexión pilar y luz de obra + Tablero de obra | D15: gl | E15: 1 | F15: =+Tareas!H44 -> 795578.51 | G15: =+Tareas!I44 -> 50000 | H15: =F15+G15 -> 845578.51 | I15: =+Tareas!Q44 -> 0 | J15: =+Tareas!R44 -> 511535.56 | K15: =I15+J15 -> 511535.56 | L15: =+(H15+K15)*0.015 -> 20356.711 | M15: =H15+K15+L15 -> 1377470.8 | N15: =F15*E15 -> 795578.51 | O15: =G15*E15 -> 50000 | P15: =I15*E15 -> 0 | Q15: =J15*E15 -> 511535.56 | R15: =+L15*E15 -> 20356.711 | S15: =SUM(N15:R15) -> 1377470.8 | U15: =+ROUNDUP(M15*$T$5,0) -> 1731320 | V15: =+U15*E15 -> 1731320
A16: 1.08 | B16: OK | C16: Conexión agua de obra, tanque + bomba | D16: gl | E16: 1 | F16: =+Tareas!H51 -> 680400 | G16: =+Tareas!I51 -> 0 | H16: =F16+G16 -> 680400 | I16: =+Tareas!Q51 -> 0 | J16: =+Tareas!R51 -> 421419.89 | K16: =I16+J16 -> 421419.89 | L16: =+(H16+K16)*0.015 -> 16527.298 | M16: =H16+K16+L16 -> 1118347.2 | N16: =F16*E16 -> 680400 | O16: =G16*E16 -> 0 | P16: =I16*E16 -> 0 | Q16: =J16*E16 -> 421419.89 | R16: =+L16*E16 -> 16527.298 | S16: =SUM(N16:R16) -> 1118347.2 | U16: =+ROUNDUP(M16*$T$5,0) -> 1405632 | V16: =+U16*E16 -> 1405632
A17: 1.09 | B17: OK | C17: Tramite luz de obra, certificado luz de obra (2) y medición PAT | D17: gl | E17: 1 | F17: =+Tareas!H61 -> 0 | G17: =+Tareas!I61 -> 0 | H17: =F17+G17 -> 0 | I17: =+Tareas!Q61 -> 339320.84 | J17: =+Tareas!R61 -> 0 | K17: =I17+J17 -> 339320.84 | M17: =H17+K17+L17 -> 339320.84 | N17: =F17*E17 -> 0 | O17: =G17*E17 -> 0 | P17: =I17*E17 -> 339320.84 | Q17: =J17*E17 -> 0 | R17: =+L17*E17 -> 0 | S17: =SUM(N17:R17) -> 339320.84 | U17: =+ROUNDUP(M17*$T$5,0) -> 426487 | V17: =+U17*E17 -> 426487
A18: 1.1 | B18: OK | C18: Sistema de depresión de napas | D18: gl | E18: 1 | H18: =F18+G18 -> 0 | I18: =+SUBCONTRATOS!D67 -> 7800000 | K18: =I18+J18 -> 7800000 | M18: =H18+K18+L18 -> 7800000 | N18: =F18*E18 -> 0 | O18: =G18*E18 -> 0 | P18: =I18*E18 -> 7800000 | Q18: =J18*E18 -> 0 | R18: =+L18*E18 -> 0 | S18: =SUM(N18:R18) -> 7800000 | U18: =+ROUNDUP(M18*$T$5,0) -> 9803685 | V18: =+U18*E18 -> 9803685
A19: 2 | C19: MOVIMIENTO DE TIERRA, COMPACTACION Y RELLENO | T19: =SUM(S20:S22) -> 33429552 | W19: =SUM(V20:V22) -> 42017464 | X19: =+W19/$W$216 -> 0.037269258 | Y19: =+W19 -> 42017464
A20: 2.01 | B20: OK | C20: Excavación a maquina para submuración y subsuelo | D20: m3 | E20: =+'H°A° '!H69 -> 1266 | F20: =+Tareas!H66 -> 0 | G20: =+Tareas!I66 -> 0 | H20: =F20+G20 -> 0 | I20: =+Tareas!Q66 -> 18400 | J20: =+Tareas!R66 -> 7809.62 | K20: =I20+J20 -> 26209.62 | L20: =+J20*0.015 -> 117.1443 | M20: =H20+K20+L20 -> 26326.764 | N20: =F20*E20 -> 0 | O20: =G20*E20 -> 0 | P20: =I20*E20 -> 23294400 | Q20: =J20*E20 -> 9886979 | R20: =+L20*E20 -> 148304.68 | S20: =SUM(N20:R20) -> 33329684 | U20: =+ROUNDUP(M20*$T$5,0) -> 33090 | V20: =+U20*E20 -> 41891940
A21: 2.02 | B21: OK | C21: Demolición y retiro de fundaciones existentes - No cotiza | D21: gl | E21: 0 | H21: =F21+G21 -> 0 | K21: =I21+J21 -> 0 | M21: =H21+K21+L21 -> 0 | N21: =F21*E21 -> 0 | O21: =G21*E21 -> 0 | P21: =I21*E21 -> 0 | Q21: =J21*E21 -> 0 | R21: =+L21*E21 -> 0 | S21: =SUM(N21:R21) -> 0 | U21: =+ROUNDUP(M21*$T$5,0) -> 0 | V21: =+U21*E21 -> 0
A22: 2.03 | B22: OK | C22: Excavación manual para pozo de achique y bombeo | D22: m3 | E22: =+'H°A° '!H87 -> 2 | H22: =F22+G22 -> 0 | J22: =+'P.MO 09.24'!B7 -> 49934.237 | K22: =I22+J22 -> 49934.237 | M22: =H22+K22+L22 -> 49934.237 | N22: =F22*E22 -> 0 | O22: =G22*E22 -> 0 | P22: =I22*E22 -> 0 | Q22: =J22*E22 -> 99868.474 | R22: =+L22*E22 -> 0 | S22: =SUM(N22:R22) -> 99868.474 | U22: =+ROUNDUP(M22*$T$5,0) -> 62762 | V22: =+U22*E22 -> 125524 | AB22: m3
A23: 3 | C23: ESTRUCTURA RESISTENTE | T23: =SUM(S24:S40) -> 2.0134759e+08 | W23: =SUM(V24:V40) -> 253070783 | X23: =+W23/$W$216 -> 0.22447238 | Y23: =+W23 -> 253070783 | AA23: =+SUM(P24:Q39)+Q20 -> 1.5859354e+08
A24: 3.01 | B24: OK | C24: Hormigón de limpieza - e: 10 cm | D24: m3 | E24: =+'H°A° '!E93 -> 35 | F24: =+Cotizaciones!D23+Cotizaciones!D27 -> 120430 | G24: =+Cotizaciones!D26*5/'01'!E24 -> 76142.857 | H24: =F24+G24 -> 196572.86 | J24: =+'P.MO 09.24'!B7 -> 49934.237 | K24: =I24+J24 -> 49934.237 | L24: =+(H24+K24)*0.015 -> 3697.6064 | M24: =H24+K24+L24 -> 250204.7 | N24: =F24*E24 -> 4215050 | O24: =G24*E24 -> 2665000 | P24: =I24*E24 -> 0 | Q24: =J24*E24 -> 1747698.3 | R24: =+L24*E24 -> 129416.22 | S24: =SUM(N24:R24) -> 8757164.5 | U24: =+ROUNDUP(M24*$T$5,0) -> 314478 | V24: =+U24*E24 -> 11006730 | Z24: EL SALVADOR 4041 | AA24: =+AA23/Z25 -> 1.0572902e+08 | AB24: 607 | AC24: =+AA24/AB24 -> 174182.91 | AD24: =+AC24/AC26 -> 0.76640478
A25: 3.02 | B25: OK | C25: Tabique submuración - H30 hidrófugo (95 kg/m3 de hierro) | D25: m3 | E25: =+'H°A° '!M5 -> 40 | F25: =+'H°A° '!F47 -> 70843.446 | H25: =F25+G25 -> 70843.446 | I25: =+'MO HA AING'!D72 -> 307690.19 | K25: =I25+J25 -> 307690.19 | L25: =+(H25+K25)*0.015 -> 5678.0046 | M25: =H25+K25+L25 -> 384211.64 | N25: =F25*E25 -> 2833737.8 | O25: =G25*E25 -> 0 | P25: =I25*E25 -> 12307608 | Q25: =J25*E25 -> 0 | R25: =+L25*E25 -> 227120.18 | S25: =SUM(N25:R25) -> 15368466 | U25: =+ROUNDUP(M25*$T$5,0) -> 482909 | V25: =+U25*E25 -> 19316360 | Z25: 1.5
A26: 3.03 | B26: OK | C26: Zapata corrida tabique - H30 hidrófugo (120 kg/m3) | D26: m3 | E26: =+'H°A° '!M7 -> 28 | F26: =+'H°A° '!F46 -> 55068.822 | H26: =F26+G26 -> 55068.822 | I26: =+'MO HA AING'!C6 -> 253994.14 | K26: =I26+J26 -> 253994.14 | L26: =+(H26+K26)*0.015 -> 4635.9445 | M26: =H26+K26+L26 -> 313698.91 | N26: =F26*E26 -> 1541927 | O26: =G26*E26 -> 0 | P26: =I26*E26 -> 7111836 | Q26: =J26*E26 -> 0 | R26: =+L26*E26 -> 129806.45 | S26: =SUM(N26:R26) -> 8783569.5 | U26: =+ROUNDUP(M26*$T$5,0) -> 394283 | V26: =+U26*E26 -> 11039924 | Z26: MNS 2920 | AA26: 75000000 | AB26: 330 | AC26: =+AA26/AB26 -> 227272.73
A27: 3.04 | B27: OK | C27: Platea - H30 hidrófugo (95 kg/m3 de hierro) | D27: m3 | E27: =+'H°A° '!M6 -> 179 | F27: =+'H°A° '!F50 -> 2471.4098 | H27: =F27+G27 -> 2471.4098 | I27: =+'MO HA AING'!C5*0.85 -> 148967.56 | K27: =I27+J27 -> 148967.56 | L27: =+(H27+K27)*0.015 -> 2271.5846 | M27: =H27+K27+L27 -> 153710.56 | N27: =F27*E27 -> 442382.35 | O27: =G27*E27 -> 0 | P27: =I27*E27 -> 26665194 | Q27: =J27*E27 -> 0 | R27: =+L27*E27 -> 406613.65 | S27: =SUM(N27:R27) -> 27514190 | U27: =+ROUNDUP(M27*$T$5,0) -> 193197 | V27: =+U27*E27 -> 34582263
A28: 3.05 | B28: OK | C28: Rampa - H30 (120 kg/m3 de hierro) | D28: m3 | E28: =+'H°A° '!M4 -> 10 | F28: =+'H°A° '!F52 -> 40150.005 | H28: =F28+G28 -> 40150.005 | I28: =+'MO HA AING'!D123 -> 191068.28 | J28: =+I28*0.5 -> 95534.142 | K28: =I28+J28 -> 286602.43 | L28: =+(H28+K28)*0.015 -> 4901.2865 | M28: =H28+K28+L28 -> 331653.72 | N28: =F28*E28 -> 401500.05 | O28: =G28*E28 -> 0 | P28: =I28*E28 -> 1910682.8 | Q28: =J28*E28 -> 955341.42 | R28: =+L28*E28 -> 49012.865 | S28: =SUM(N28:R28) -> 3316537.2 | U28: =+ROUNDUP(M28*$T$5,0) -> 416850 | V28: =+U28*E28 -> 4168500
A29: 3.06 | B29: OK | C29: Losa maciza - H30 (110 kg/m3 de hierro) | D29: m3 | E29: =+'H°A° '!M8 -> 177 | F29: =+'H°A° '!F51 -> 32975.501 | H29: =F29+G29 -> 32975.501 | I29: =+'MO HA AING'!D123 -> 191068.28 | K29: =I29+J29 -> 191068.28 | L29: =+(H29+K29)*0.015 -> 3360.6568 | M29: =H29+K29+L29 -> 227404.44 | N29: =F29*E29 -> 5836663.8 | O29: =G29*E29 -> 0 | P29: =I29*E29 -> 33819086 | Q29: =J29*E29 -> 0 | R29: =+L29*E29 -> 594836.25 | S29: =SUM(N29:R29) -> 40250586 | U29: =+ROUNDUP(M29*$T$5,0) -> 285821 | V29: =+U29*E29 -> 50590317
A30: 3.07 | B30: OK | C30: Vigas - H30 (140 kg/m3 de hierro) | D30: m3 | E30: =+'H°A° '!M9 -> 65 | F30: =+'H°A° '!F53 -> 94228.958 | H30: =F30+G30 -> 94228.958 | I30: =+'MO HA AING'!D99 -> 462949.29 | K30: =I30+J30 -> 462949.29 | L30: =+(H30+K30)*0.015 -> 8357.6737 | M30: =H30+K30+L30 -> 565535.92 | N30: =F30*E30 -> 6124882.3 | O30: =G30*E30 -> 0 | P30: =I30*E30 -> 30091704 | Q30: =J30*E30 -> 0 | R30: =+L30*E30 -> 543248.79 | S30: =SUM(N30:R30) -> 36759835 | U30: =+ROUNDUP(M30*$T$5,0) -> 710813 | V30: =+U30*E30 -> 46202845
A31: 3.08 | B31: OK | C31: Vigas de H° visto - H30 (140 kg/m3 de hierro) | D31: m3 | E31: =+'H°A° '!M13 -> 12 | F31: =+'H°A° '!F54 -> 92072.317 | H31: =F31+G31 -> 92072.317 | I31: =+'MO HA AING'!D99 -> 462949.29 | J31: =+I31*0.2 -> 92589.858 | K31: =I31+J31 -> 555539.15 | L31: =+(H31+K31)*0.015 -> 9714.172 | M31: =H31+K31+L31 -> 657325.64 | N31: =F31*E31 -> 1104867.8 | O31: =G31*E31 -> 0 | P31: =I31*E31 -> 5555391.5 | Q31: =J31*E31 -> 1111078.3 | R31: =+L31*E31 -> 116570.06 | S31: =SUM(N31:R31) -> 7887907.6 | U31: =+ROUNDUP(M31*$T$5,0) -> 826182 | V31: =+U31*E31 -> 9914184
A32: 3.09 | B32: OK | C32: Tabiques - H30 (120 kg/m3 de hierro) | D32: m3 | E32: =+'H°A° '!M10 -> 28 | F32: =+'H°A° '!F55 -> 70843.446 | H32: =F32+G32 -> 70843.446 | I32: =+'MO HA AING'!D72 -> 307690.19 | K32: =I32+J32 -> 307690.19 | L32: =+(H32+K32)*0.015 -> 5678.0046 | M32: =H32+K32+L32 -> 384211.64 | N32: =F32*E32 -> 1983616.5 | O32: =G32*E32 -> 0 | P32: =I32*E32 -> 8615325.4 | Q32: =J32*E32 -> 0 | R32: =+L32*E32 -> 158984.13 | S32: =SUM(N32:R32) -> 10757926 | U32: =+ROUNDUP(M32*$T$5,0) -> 482909 | V32: =+U32*E32 -> 13521452
A33: 3.1 | B33: OK | C33: Columna - H30 (240 Kg/m3 de hierro) | D33: m3 | E33: =+'H°A° '!M11 -> 54 | F33: =+'H°A° '!F57 -> 60951.379 | H33: =F33+G33 -> 60951.379 | I33: =+'MO HA AING'!D47 -> 273658.45 | K33: =I33+J33 -> 273658.45 | L33: =+(H33+K33)*0.015 -> 5019.1474 | M33: =H33+K33+L33 -> 339628.98 | N33: =F33*E33 -> 3291374.5 | O33: =G33*E33 -> 0 | P33: =I33*E33 -> 14777556 | Q33: =J33*E33 -> 0 | R33: =+L33*E33 -> 271033.96 | S33: =SUM(N33:R33) -> 18339965 | U33: =+ROUNDUP(M33*$T$5,0) -> 426874 | V33: =+U33*E33 -> 23051196
A34: 3.11 | B34: OK | C34: Escaleras - H30 (105 kg/m3 de hierro) | D34: m3 | E34: =+'H°A° '!M12 -> 11 | F34: =+'H°A° '!F60 -> 68185.041 | H34: =F34+G34 -> 68185.041 | I34: =+'MO HA AING'!D148 -> 283180.32 | K34: =I34+J34 -> 283180.32 | L34: =+(H34+K34)*0.015 -> 5270.4803 | M34: =H34+K34+L34 -> 356635.84 | N34: =F34*E34 -> 750035.45 | O34: =G34*E34 -> 0 | P34: =I34*E34 -> 3114983.5 | Q34: =J34*E34 -> 0 | R34: =+L34*E34 -> 57975.284 | S34: =SUM(N34:R34) -> 3922994.2 | U34: =+ROUNDUP(M34*$T$5,0) -> 448250 | V34: =+U34*E34 -> 4930750
A35: 3.12 | B35: OK | C35: Tabiques tanques de H° - H30 (120 kg/m3 de hierro) | D35: m3 | E35: =+'H°A° '!M14 -> 3 | F35: =+'H°A° '!F55 -> 70843.446 | H35: =F35+G35 -> 70843.446 | I35: =+'MO HA AING'!D72 -> 307690.19 | K35: =I35+J35 -> 307690.19 | L35: =+(H35+K35)*0.015 -> 5678.0046 | M35: =H35+K35+L35 -> 384211.64 | N35: =F35*E35 -> 212530.34 | O35: =G35*E35 -> 0 | P35: =I35*E35 -> 923070.58 | Q35: =J35*E35 -> 0 | R35: =+L35*E35 -> 17034.014 | S35: =SUM(N35:R35) -> 1152634.9 | U35: =+ROUNDUP(M35*$T$5,0) -> 482909 | V35: =+U35*E35 -> 1448727
A36: 3.13 | B36: OK | C36: Junta de impermeabilización de PVC - Sika Waterbars v15 x 15mts o similar | D36: ml | E36: 240 | F36: =+Cotizaciones!I498 -> 24772.727 | H36: =F36+G36 -> 24772.727 | K36: =I36+J36 -> 0 | M36: =H36+K36+L36 -> 24772.727 | N36: =F36*E36 -> 5945454.5 | O36: =G36*E36 -> 0 | P36: =I36*E36 -> 0 | Q36: =J36*E36 -> 0 | R36: =+L36*E36 -> 0 | S36: =SUM(N36:R36) -> 5945454.5 | U36: =+ROUNDUP(M36*$T$5,0) -> 31137 | V36: =+U36*E36 -> 7472880
A37: 3.14 | B37: OK | C37: Sistema de apuntalamiento y reapuntalamiento | D37: gl | E37: 1 | H37: =F37+G37 -> 0 | K37: =I37+J37 -> 0 | L37: =+'ENCOFRADO '!G148 -> 8822750 | M37: =H37+K37+L37 -> 8822750 | N37: =F37*E37 -> 0 | O37: =G37*E37 -> 0 | P37: =I37*E37 -> 0 | Q37: =J37*E37 -> 0 | R37: =+L37*E37 -> 8822750 | S37: =SUM(N37:R37) -> 8822750 | U37: =+ROUNDUP(M37*$T$5,0) -> 11089161 | V37: =+U37*E37 -> 11089161
A38: 3.15 | B38: OK | C38: Ensayos de Hormigon por etapas de hormigonado | D38: u | E38: =+'H°A° '!P34 -> 14 | F38: =+'H°A° '!T40 -> 123492.86 | H38: =F38+G38 -> 123492.86 | K38: =I38+J38 -> 0 | M38: =H38+K38+L38 -> 123492.86 | N38: =F38*E38 -> 1728900 | O38: =G38*E38 -> 0 | P38: =I38*E38 -> 0 | Q38: =J38*E38 -> 0 | R38: =+L38*E38 -> 0 | S38: =SUM(N38:R38) -> 1728900 | U38: =+ROUNDUP(M38*$T$5,0) -> 155217 | V38: =+U38*E38 -> 2173038
A39: 3.16 | B39: OK | C39: Permiso de estacionamiento de bomba de hormigón a contramano | D39: gl | E39: =+GGBB!R12 -> 4 | F39: 55000 | H39: =F39+G39 -> 55000 | K39: =I39+J39 -> 0 | M39: =H39+K39+L39 -> 55000 | N39: =F39*E39 -> 220000 | O39: =G39*E39 -> 0 | P39: =I39*E39 -> 0 | Q39: =J39*E39 -> 0 | R39: =+L39*E39 -> 0 | S39: =SUM(N39:R39) -> 220000 | U39: =+ROUNDUP(M39*$T$5,0) -> 69129 | V39: =+U39*E39 -> 276516
A40: 3.17 | B40: OK | C40: Picado de medianeras para columnas y vigas - Cotizado solo para PB y 1P, No contempla picado en SS | D40: m2 | E40: =+Computo!F53 -> 93 | F40: =+Tareas!H70 -> 3440.8602 | G40: =+Tareas!I70 -> 1612.9032 | H40: =F40+G40 -> 5053.7634 | I40: =+Tareas!Q70 -> 0 | J40: =+Tareas!R70 -> 14213.223 | K40: =I40+J40 -> 14213.223 | L40: =+(H40+K40)*0.015 -> 289.0048 | M40: =H40+K40+L40 -> 19555.992 | N40: =F40*E40 -> 320000 | O40: =G40*E40 -> 150000 | P40: =I40*E40 -> 0 | Q40: =J40*E40 -> 1321829.8 | R40: =+L40*E40 -> 26877.447 | S40: =SUM(N40:R40) -> 1818707.2 | U40: =+ROUNDUP(M40*$T$5,0) -> 24580 | V40: =+U40*E40 -> 2285940
A41: 4 | C41: ALBAÑILERIA | T41: =SUM(S42:S49) -> 43203971 | W41: =SUM(V42:V49) -> 54302890 | X41: =+W41/$W$216 -> 0.048166362 | Y41: =+W41 -> 54302890
A42: 4.01 | B42: OK | C42: Muro tipo 1 (interiores, divisorio de locales) e: 10 cm - Ladrillo hueco 08 x 18 x 33 | D42: m2 | E42: =+Mampostería!L3 -> 819 | G42: =+'APU 09.24'!E13 -> 6545.2009 | H42: =F42+G42 -> 6545.2009 | J42: =+'APU 09.24'!H13 -> 8336.4857 | K42: =I42+J42 -> 8336.4857 | L42: =+'APU 09.24'!K13 -> 229.16796 | M42: =H42+K42+L42 -> 15110.855 | N42: =F42*E42 -> 0 | O42: =G42*E42 -> 5360519.6 | P42: =I42*E42 -> 0 | Q42: =J42*E42 -> 6827581.8 | R42: =+L42*E42 -> 187688.56 | S42: =SUM(N42:R42) -> 12375790 | U42: =+ROUNDUP(M42*$T$5,0) -> 18993 | V42: =+U42*E42 -> 15555267
A43: 4.02 | B43: OK | C43: Muro tipo 2 y 3 (medianera, caja de escaleras y ascensor) e: 15 cm - Ladrillo hueco portante 12 x 19 x 33 | D43: m2 | E43: =+Mampostería!M3 -> 612 | G43: =+'APU 09.24'!E17 -> 11461.565 | H43: =F43+G43 -> 11461.565 | J43: =+'APU 09.24'!H17 -> 8336.4857 | K43: =I43+J43 -> 8336.4857 | L43: =+'APU 09.24'!K17 -> 229.16796 | M43: =H43+K43+L43 -> 20027.219 | N43: =F43*E43 -> 0 | O43: =G43*E43 -> 7014478.1 | P43: =I43*E43 -> 0 | Q43: =J43*E43 -> 5101929.2 | R43: =+L43*E43 -> 140250.79 | S43: =SUM(N43:R43) -> 12256658 | U43: =+ROUNDUP(M43*$T$5,0) -> 25172 | V43: =+U43*E43 -> 15405264
A44: 4.03 | B44: OK | C44: Muro tipo 4 (divisorio de unidades y fachas) e: 15 cm - Ladrillo hueco 12 x 18 x 33 | D44: m2 | E44: =+Mampostería!N3 -> 636 | G44: =+'APU 09.24'!E14 -> 8229.0499 | H44: =F44+G44 -> 8229.0499 | J44: =+'APU 09.24'!H14 -> 8336.4857 | K44: =I44+J44 -> 8336.4857 | L44: =+'APU 09.24'!K14 -> 229.16796 | M44: =H44+K44+L44 -> 16794.704 | N44: =F44*E44 -> 0 | O44: =G44*E44 -> 5233675.8 | P44: =I44*E44 -> 0 | Q44: =J44*E44 -> 5302004.9 | R44: =+L44*E44 -> 145750.83 | S44: =SUM(N44:R44) -> 10681431 | U44: =+ROUNDUP(M44*$T$5,0) -> 21109 | V44: =+U44*E44 -> 13425324
A45: 4.04 | B45: OK | C45: Enchape medianeras existentes - Contemplamos picado zonas sueltas y enchape con ladrillo comun para PB | D45: m2 | E45: =+Mampostería!P3 -> 195 | G45: =+'APU 09.24'!E12/2 -> 5807.159 | H45: =F45+G45 -> 5807.159 | J45: =+'APU 09.24'!H12/3 -> 5954.6326 | K45: =I45+J45 -> 5954.6326 | L45: =+'APU 09.24'!K12/2 -> 245.5371 | M45: =H45+K45+L45 -> 12007.329 | N45: =F45*E45 -> 0 | O45: =G45*E45 -> 1132396 | P45: =I45*E45 -> 0 | Q45: =J45*E45 -> 1161153.4 | R45: =+L45*E45 -> 47879.735 | S45: =SUM(N45:R45) -> 2341429.1 | U45: =+ROUNDUP(M45*$T$5,0) -> 15092 | V45: =+U45*E45 -> 2942940
A46: 4.05 | B46: IN | C46: Mamposteria cribada de ladrillo visto en balcones | D46: m2 | E46: =+Computo!H185 -> 30.054 | F46: =+G46*0.5 -> 5807.159 | G46: =+'APU 09.24'!E12 -> 11614.318 | H46: =F46+G46 -> 17421.477 | I46: =+J46 -> 17863.898 | J46: =+'APU 09.24'!H12 -> 17863.898 | K46: =I46+J46 -> 35727.796 | L46: =+'APU 09.24'!K12 -> 491.07421 | M46: =H46+K46+L46 -> 53640.347 | N46: =F46*E46 -> 174528.36 | O46: =G46*E46 -> 349056.71 | P46: =I46*E46 -> 536881.59 | Q46: =J46*E46 -> 536881.59 | R46: =+L46*E46 -> 14758.744 | S46: =SUM(N46:R46) -> 1612107 | U46: =+ROUNDUP(M46*$T$5,0) -> 67420 | V46: =+U46*E46 -> 2026240.7
A47: 4.06 | B47: IN | C47: Bloque de H° con masillado de hormigon | D47: m2 | E47: =+Mampostería!O3 -> 24 | F47: =+G47 -> 14352.05 | G47: =+'APU 09.24'!E62 -> 14352.05 | H47: =F47+G47 -> 28704.1 | I47: =+J47*0.5 -> 4894.075 | J47: =+'APU 09.24'!H62 -> 9788.1501 | K47: =I47+J47 -> 14682.225 | L47: =+'APU 09.24'!K62 -> 298.91474 | M47: =H47+K47+L47 -> 43685.24 | N47: =F47*E47 -> 344449.2 | O47: =G47*E47 -> 344449.2 | P47: =I47*E47 -> 117457.8 | Q47: =J47*E47 -> 234915.6 | R47: =+L47*E47 -> 7173.9537 | S47: =SUM(N47:R47) -> 1048445.8 | U47: =+ROUNDUP(M47*$T$5,0) -> 54908 | V47: =+U47*E47 -> 1317792
A48: 4.07 | B48: IN | C48: Cordón de hormigón en umbrales carpinterías | D48: ml | E48: =9*9 -> 81 | F48: =+Tareas!H75 -> 17364.128 | G48: =+Tareas!I75 -> 0 | H48: =F48+G48 -> 17364.128 | I48: =+Tareas!Q75 -> 0 | J48: =+Tareas!R75 -> 6926.499 | K48: =I48+J48 -> 6926.499 | L48: =+(H48+K48)*0.015 -> 364.3594 | M48: =H48+K48+L48 -> 24654.986 | N48: =F48*E48 -> 1406494.4 | O48: =G48*E48 -> 0 | P48: =I48*E48 -> 0 | Q48: =J48*E48 -> 561046.42 | R48: =+L48*E48 -> 29513.112 | S48: =SUM(N48:R48) -> 1997053.9 | U48: =+ROUNDUP(M48*$T$5,0) -> 30989 | V48: =+U48*E48 -> 2510109
A49: 4.08 | B49: IN | C49: Pozo de bombeo pluvial y cloacal | D49: gl | E49: 1 | F49: =+Tareas!H81 -> 451217.95 | G49: =+Tareas!I81 -> 0 | H49: =F49+G49 -> 451217.95 | I49: =+Tareas!Q81 -> 0 | J49: =+Tareas!R81 -> 426669.72 | K49: =I49+J49 -> 426669.72 | L49: =+(H49+K49)*0.015 -> 13168.315 | M49: =H49+K49+L49 -> 891055.98 | N49: =F49*E49 -> 451217.95 | O49: =G49*E49 -> 0 | P49: =I49*E49 -> 0 | Q49: =J49*E49 -> 426669.72 | R49: =+L49*E49 -> 13168.315 | S49: =SUM(N49:R49) -> 891055.98 | U49: =+ROUNDUP(M49*$T$5,0) -> 1119953 | V49: =+U49*E49 -> 1119953
A50: 5 | C50: AISLACIONES | T50: =SUM(S51:S57) -> 28614597 | W50: =SUM(V51:V57) -> 35966419 | X50: =+W50/$W$216 -> 0.031902014 | Y50: =+W50 -> 35966419
A51: 5.01 | B51: OK | C51: Aislación hidrófuga horizontal (baños) - Inc. membrana geotextil y 35% en concepto de babetas | D51: m2 | E51: =+Locales!AA147 -> 139.05 | G51: =+'APU 09.24'!E50 -> 9809.5604 | H51: =F51+G51 -> 9809.5604 | I51: =+J51*0.5 -> 2500.9457 | J51: =+'APU 09.24'!H50 -> 5001.8914 | K51: =I51+J51 -> 7502.8371 | L51: =+'APU 09.24'!K50 -> 31.337345 | M51: =H51+K51+L51 -> 17343.735 | N51: =F51*E51 -> 0 | O51: =G51*E51 -> 1364019.4 | P51: =I51*E51 -> 347756.5 | Q51: =J51*E51 -> 695513 | R51: =+L51*E51 -> 4357.4578 | S51: =SUM(N51:R51) -> 2411646.3 | U51: =+ROUNDUP(M51*$T$5,0) -> 21800 | V51: =+U51*E51 -> 3031290
A52: 5.02 | B52: OK | C52: Azotado hidrofugo - Sobre medianeras existentes | D52: m2 | E52: 300 | G52: =+'APU 09.24'!E21 -> 758.10738 | H52: =F52+G52 -> 758.10738 | J52: =+'APU 09.24'!H21 -> 3395.9551 | K52: =I52+J52 -> 3395.9551 | L52: =+'APU 09.24'!K21 -> 122.76855 | M52: =H52+K52+L52 -> 4276.831 | N52: =F52*E52 -> 0 | O52: =G52*E52 -> 227432.21 | P52: =I52*E52 -> 0 | Q52: =J52*E52 -> 1018786.5 | R52: =+L52*E52 -> 36830.566 | S52: =SUM(N52:R52) -> 1283049.3 | U52: =+ROUNDUP(M52*$T$5,0) -> 5376 | V52: =+U52*E52 -> 1612800
A53: 5.03 | B53: OK | C53: Azotado hidrofugo - Contrapiso de vereda | D53: m2 | E53: =+Locales!AB144 -> 48 | G53: =+'APU 09.24'!E21 -> 758.10738 | H53: =F53+G53 -> 758.10738 | J53: =+'APU 09.24'!H21 -> 3395.9551 | K53: =I53+J53 -> 3395.9551 | L53: =+'APU 09.24'!K21 -> 122.76855 | M53: =H53+K53+L53 -> 4276.831 | N53: =F53*E53 -> 0 | O53: =G53*E53 -> 36389.154 | P53: =I53*E53 -> 0 | Q53: =J53*E53 -> 163005.85 | R53: =+L53*E53 -> 5892.8905 | S53: =SUM(N53:R53) -> 205287.89 | U53: =+ROUNDUP(M53*$T$5,0) -> 5376 | V53: =+U53*E53 -> 258048
A54: 5.04 | B54: OK | C54: Aislación térmica en terrazas, eps e:2,00 cm | D54: m2 | E54: =+Locales!AC144 -> 262 | G54: =+Cotizaciones!D49 -> 3502.8 | H54: =F54+G54 -> 3502.8 | K54: =I54+J54 -> 0 | M54: =H54+K54+L54 -> 3502.8 | N54: =F54*E54 -> 0 | O54: =G54*E54 -> 917733.6 | P54: =I54*E54 -> 0 | Q54: =J54*E54 -> 0 | R54: =+L54*E54 -> 0 | S54: =SUM(N54:R54) -> 917733.6 | U54: =+ROUNDUP(M54*$T$5,0) -> 4403 | V54: =+U54*E54 -> 1153586
A55: 5.05 | B55: OK | C55: Barrera de vapor | D55: m2 | E55: =+Locales!AD147 -> 510 | G55: =+'APU 09.24'!E56 -> 1273.3407 | H55: =F55+G55 -> 1273.3407 | J55: =+'APU 09.24'!H56 -> 1563.0911 | K55: =I55+J55 -> 1563.0911 | L55: =+'APU 09.24'!K56 -> 9.7929202 | M55: =H55+K55+L55 -> 2846.2247 | N55: =F55*E55 -> 0 | O55: =G55*E55 -> 649403.77 | P55: =I55*E55 -> 0 | Q55: =J55*E55 -> 797176.44 | R55: =+L55*E55 -> 4994.3893 | S55: =SUM(N55:R55) -> 1451574.6 | U55: =+ROUNDUP(M55*$T$5,0) -> 3578 | V55: =+U55*E55 -> 1824780
A56: 5.06 | B56: OK | C56: Membrana asfaltica geotextil 4mm - Balcones y azotea - Inc. 20% en concepto de babetas | D56: m2 | E56: =+Locales!AD147 -> 510 | G56: =+'APU 09.24'!E50 -> 9809.5604 | H56: =F56+G56 -> 9809.5604 | I56: =+J56*0.5 -> 2500.9457 | J56: =+'APU 09.24'!H50 -> 5001.8914 | K56: =I56+J56 -> 7502.8371 | L56: =+'APU 09.24'!K50 -> 31.337345 | M56: =H56+K56+L56 -> 17343.735 | N56: =F56*E56 -> 0 | O56: =G56*E56 -> 5002875.8 | P56: =I56*E56 -> 1275482.3 | Q56: =J56*E56 -> 2550964.6 | R56: =+L56*E56 -> 15982.046 | S56: =SUM(N56:R56) -> 8845304.8 | U56: =+ROUNDUP(M56*$T$5,0) -> 21800 | V56: =+U56*E56 -> 11118000
A57: 5.07 | B57: OK | C57: Impermeabilización de subsuelo | D57: gl | E57: 1 | H57: =F57+G57 -> 0 | I57: 13500000 | K57: =I57+J57 -> 13500000 | M57: =H57+K57+L57 -> 13500000 | N57: =F57*E57 -> 0 | O57: =G57*E57 -> 0 | P57: =I57*E57 -> 13500000 | Q57: =J57*E57 -> 0 | R57: =+L57*E57 -> 0 | S57: =SUM(N57:R57) -> 13500000 | U57: =+ROUNDUP(M57*$T$5,0) -> 16967915 | V57: =+U57*E57 -> 16967915
A58: 6 | C58: CUBIERTAS | T58: =SUM(S59:S59) -> 1936418.4 | W58: =SUM(V59:V59) -> 2433900 | X58: =+W58/$W$216 -> 0.0021588558 | Y58: =+W58 -> 2433900
A59: 6.02 | B59: OK | C59: Babeta de chapa galvanizada en medianeras | D59: ml | E59: 60 | F59: =+Tareas!H95 -> 13939.394 | G59: =+Tareas!I95 -> 0 | H59: =F59+G59 -> 13939.394 | I59: =+Tareas!Q95 -> 0 | J59: =+Tareas!R95 -> 4329.904 | K59: =I59+J59 -> 4329.904 | L59: =+H59+K59*(0.015) -> 14004.342 | M59: =H59+K59+L59 -> 32273.64 | N59: =F59*E59 -> 836363.64 | O59: =G59*E59 -> 0 | P59: =I59*E59 -> 0 | Q59: =J59*E59 -> 259794.24 | R59: =+L59*E59 -> 840260.55 | S59: =SUM(N59:R59) -> 1936418.4 | U59: =+ROUNDUP(M59*$T$5,0) -> 40565 | V59: =+U59*E59 -> 2433900
A60: 7 | C60: REVOQUES | T60: =SUM(S61:S68) -> 1.0851119e+08 | W60: =SUM(V61:V68) -> 1.3639056e+08 | X60: =+W60/$W$216 -> 0.12097767 | Y60: =+W60 -> 1.3639056e+08
A61: 7.01 | B61: R | C61: Revoque Grueso Impermeable Exterior proyectable | D61: m2 | E61: =+Computo!J260 -> 678.252 | G61: =+'APU 09.24'!E23 -> 3747.8693 | H61: =F61+G61 -> 3747.8693 | J61: =+'APU 09.24'!H23 -> 9136.834 | K61: =I61+J61 -> 9136.834 | L61: =+'APU 09.24'!K23 -> 298.91474 | M61: =H61+K61+L61 -> 13183.618 | N61: =F61*E61 -> 0 | O61: =G61*E61 -> 2541999.9 | P61: =I61*E61 -> 0 | Q61: =J61*E61 -> 6197075.9 | R61: =+L61*E61 -> 202739.52 | S61: =SUM(N61:R61) -> 8941815.3 | U61: =+ROUNDUP(M61*$T$5,0) -> 16571 | V61: =+U61*E61 -> 11239314
A62: 7.02 | B62: R | C62: Revoque Grueso Impermeable Exterior a mas de 3m proyectable - Medianero y fachadas | D62: m2 | E62: =+Computo!H233 -> 876.0812 | G62: =+'APU 09.24'!E24 -> 3747.8693 | H62: =F62+G62 -> 3747.8693 | J62: =+'APU 09.24'!H24 -> 13134.199 | K62: =I62+J62 -> 13134.199 | L62: =+'APU 09.24'!K24 -> 766.41029 | M62: =H62+K62+L62 -> 17648.478 | N62: =F62*E62 -> 0 | O62: =G62*E62 -> 3283437.9 | P62: =I62*E62 -> 0 | Q62: =J62*E62 -> 11506625 | R62: =+L62*E62 -> 671437.65 | S62: =SUM(N62:R62) -> 15461500 | U62: =+ROUNDUP(M62*$T$5,0) -> 22183 | V62: =+U62*E62 -> 19434109
A63: 7.03 | C63: Buña en revoque | D63: ml | E63: =+Computo!F264 -> 182 | H63: =F63+G63 -> 0 | J63: =+SUBCONTRATOS!D32 -> 8597.4065 | K63: =I63+J63 -> 8597.4065 | M63: =H63+K63+L63 -> 8597.4065 | N63: =F63*E63 -> 0 | O63: =G63*E63 -> 0 | P63: =I63*E63 -> 0 | Q63: =J63*E63 -> 1564728 | R63: =+L63*E63 -> 0 | S63: =SUM(N63:R63) -> 1564728 | U63: =+ROUNDUP(M63*$T$5,0) -> 10806 | V63: =+U63*E63 -> 1966692
A64: 7.04 | B64: R | C64: Revoque Grueso Interior + fino | D64: m2 | E64: =+Locales!Y144 -> 995.8511 | G64: =+'APU 09.24'!E22 -> 2606.0756 | H64: =F64+G64 -> 2606.0756 | J64: =+'APU 09.24'!H22 -> 17928.384 | K64: =I64+J64 -> 17928.384 | L64: =+'APU 09.24'!K22 -> 572.91991 | M64: =H64+K64+L64 -> 21107.379 | N64: =F64*E64 -> 0 | O64: =G64*E64 -> 2595263.2 | P64: =I64*E64 -> 0 | Q64: =J64*E64 -> 17854001 | R64: =+L64*E64 -> 570542.92 | S64: =SUM(N64:R64) -> 21019807 | U64: =+ROUNDUP(M64*$T$5,0) -> 26530 | V64: =+U64*E64 -> 26419930
A65: 7.05 | B65: R | C65: Yeso interior | D65: m2 | E65: =+Locales!U144 -> 2514.897 | F65: =+Tareas!H101 -> 0 | G65: =+Tareas!I101 -> 5135.3399 | H65: =F65+G65 -> 5135.3399 | I65: =+Tareas!Q101 -> 12817.952 | J65: =+Tareas!R101 -> 0 | K65: =I65+J65 -> 12817.952 | M65: =H65+K65+L65 -> 17953.291 | N65: =F65*E65 -> 0 | O65: =G65*E65 -> 12914851 | P65: =I65*E65 -> 32235828 | Q65: =J65*E65 -> 0 | R65: =+L65*E65 -> 0 | S65: =SUM(N65:R65) -> 45150679 | U65: =+ROUNDUP(M65*$T$5,0) -> 22566 | V65: =+U65*E65 -> 56751166
A66: 7.06 | B66: R | C66: Arista en yeso | D66: ml | E66: =+Locales!V144 -> 509.9 | F66: =+Tareas!H106 -> 0 | G66: =+Tareas!I106 -> 0 | H66: =F66+G66 -> 0 | I66: =+Tareas!Q106 -> 10160.571 | J66: =+Tareas!R106 -> 0 | K66: =I66+J66 -> 10160.571 | M66: =H66+K66+L66 -> 10160.571 | N66: =F66*E66 -> 0 | O66: =G66*E66 -> 0 | P66: =I66*E66 -> 5180875.3 | Q66: =J66*E66 -> 0 | R66: =+L66*E66 -> 0 | S66: =SUM(N66:R66) -> 5180875.3 | U66: =+ROUNDUP(M66*$T$5,0) -> 12771 | V66: =+U66*E66 -> 6511932.9
A67: 7.07 | B67: R | C67: Provisión y colocación de guardacanto yesero | D67: u | E67: =+Locales!W144 -> 198 | F67: =+Tareas!H108 -> 0 | G67: =+Tareas!I108 -> 1217.7455 | H67: =F67+G67 -> 1217.7455 | I67: =+Tareas!Q108 -> 10673.732 | J67: =+Tareas!R108 -> 0 | K67: =I67+J67 -> 10673.732 | M67: =H67+K67+L67 -> 11891.477 | N67: =F67*E67 -> 0 | O67: =G67*E67 -> 241113.6 | P67: =I67*E67 -> 2113398.8 | Q67: =J67*E67 -> 0 | R67: =+L67*E67 -> 0 | S67: =SUM(N67:R67) -> 2354512.4 | U67: =+ROUNDUP(M67*$T$5,0) -> 14947 | V67: =+U67*E67 -> 2959506
A68: 7.08 | B68: R | C68: Revoque Grueso Impermeable Interior b/ revestimiento | D68: m2 | E68: =+Locales!X144 -> 670.322 | G68: =+'APU 09.24'!E23 -> 3747.8693 | H68: =F68+G68 -> 3747.8693 | J68: =+'APU 09.24'!H23 -> 9136.834 | K68: =I68+J68 -> 9136.834 | L68: =+'APU 09.24'!K23 -> 298.91474 | M68: =H68+K68+L68 -> 13183.618 | N68: =F68*E68 -> 0 | O68: =G68*E68 -> 2512279.3 | P68: =I68*E68 -> 0 | Q68: =J68*E68 -> 6124620.8 | R68: =+L68*E68 -> 200369.12 | S68: =SUM(N68:R68) -> 8837269.2 | U68: =+ROUNDUP(M68*$T$5,0) -> 16571 | V68: =+U68*E68 -> 11107906
A69: 8 | C69: CONTRAPISOS Y CARPETAS | T69: =SUM(S70:S77) -> 35633227 | W69: =SUM(V70:V77) -> 44788107 | X69: =+W69/$W$216 -> 0.039726803 | Y69: =+W69 -> 44788107
A70: 8.01 | B70: OK | C70: Contrapiso de cascotes en SS e: 15 cm | D70: m2 | E70: =+Locales!Q144 -> 104 | G70: =+'APU 09.24'!E25*0.15 -> 9763.519 | H70: =F70+G70 -> 9763.519 | J70: =+'APU 09.24'!H25*0.2 -> 15181.289 | K70: =I70+J70 -> 15181.289 | L70: =+'APU 09.24'!K25*0.2 -> 451.34429 | M70: =H70+K70+L70 -> 25396.152 | N70: =F70*E70 -> 0 | O70: =G70*E70 -> 1015406 | P70: =I70*E70 -> 0 | Q70: =J70*E70 -> 1578854.1 | R70: =+L70*E70 -> 46939.806 | S70: =SUM(N70:R70) -> 2641199.8 | U70: =+ROUNDUP(M70*$T$5,0) -> 31920 | V70: =+U70*E70 -> 3319680
A71: 8.02 | B71: OK | C71: Contrapiso de cascote s/terreno natural e: 20 cm - Incluye film de polietileno | D71: m2 | E71: =+Locales!P144 -> 48 | F71: 500 | G71: =+'APU 09.24'!E25*0.2 -> 13018.025 | H71: =F71+G71 -> 13518.025 | I71: =+F71 -> 500 | J71: =+'APU 09.24'!H25*0.2 -> 15181.289 | K71: =I71+J71 -> 15681.289 | L71: =+'APU 09.24'!K25*0.2 -> 451.34429 | M71: =H71+K71+L71 -> 29650.659 | N71: =F71*E71 -> 24000 | O71: =G71*E71 -> 624865.22 | P71: =I71*E71 -> 24000 | Q71: =J71*E71 -> 728701.87 | R71: =+L71*E71 -> 21664.526 | S71: =SUM(N71:R71) -> 1423231.6 | U71: =+ROUNDUP(M71*$T$5,0) -> 37268 | V71: =+U71*E71 -> 1788864
A72: 8.03 | B72: OK | C72: Contrapiso de cascotes en azoteas c/pendiente e: 15 cm | D72: m2 | E72: =+Locales!O144 -> 235 | G72: =+'APU 09.24'!E25*0.18 -> 11716.223 | H72: =F72+G72 -> 11716.223 | J72: =+'APU 09.24'!H25*0.18 -> 13663.16 | K72: =I72+J72 -> 13663.16 | L72: =+'APU 09.24'!K25*0.18 -> 406.20986 | M72: =H72+K72+L72 -> 25785.593 | N72: =F72*E72 -> 0 | O72: =G72*E72 -> 2753312.4 | P72: =I72*E72 -> 0 | Q72: =J72*E72 -> 3210842.6 | R72: =+L72*E72 -> 95459.318 | S72: =SUM(N72:R72) -> 6059614.3 | U72: =+ROUNDUP(M72*$T$5,0) -> 32410 | V72: =+U72*E72 -> 7616350
A73: 8.04 | B73: OK | C73: Contrapiso - Carpeta monolitico e: 7 cm | D73: m2 | E73: =+Locales!N144 -> 878 | G73: =+'APU 09.24'!E27 -> 6431.8162 | H73: =F73+G73 -> 6431.8162 | J73: =+'APU 09.24'!H27 -> 8572.2517 | K73: =I73+J73 -> 8572.2517 | L73: =+'APU 09.24'!K27 -> 116.90258 | M73: =H73+K73+L73 -> 15120.97 | N73: =F73*E73 -> 0 | O73: =G73*E73 -> 5647134.6 | P73: =I73*E73 -> 0 | Q73: =J73*E73 -> 7526437 | R73: =+L73*E73 -> 102640.47 | S73: =SUM(N73:R73) -> 13276212 | U73: =+ROUNDUP(M73*$T$5,0) -> 19006 | V73: =+U73*E73 -> 16687268
A74: 8.05 | B74: OK | C74: Carpeta en PB y balcones, baños y azoteas e: 3,00 cm | D74: m2 | E74: =+Locales!R144 -> 564 | G74: =+'APU 09.24'!E26 -> 3180.0905 | H74: =F74+G74 -> 3180.0905 | J74: =+'APU 09.24'!H26 -> 6505.5637 | K74: =I74+J74 -> 6505.5637 | L74: =+'APU 09.24'!K26 -> 210.62734 | M74: =H74+K74+L74 -> 9896.2815 | N74: =F74*E74 -> 0 | O74: =G74*E74 -> 1793571.1 | P74: =I74*E74 -> 0 | Q74: =J74*E74 -> 3669137.9 | R74: =+L74*E74 -> 118793.82 | S74: =SUM(N74:R74) -> 5581502.8 | U74: =+ROUNDUP(M74*$T$5,0) -> 12439 | V74: =+U74*E74 -> 7015596
A75: 8.06 | B75: OK | C75: Carpeta sobre membrana | D75: m2 | E75: =+Locales!S144 -> 438 | G75: =+'APU 09.24'!E26 -> 3180.0905 | H75: =F75+G75 -> 3180.0905 | J75: =+'APU 09.24'!H26 -> 6505.5637 | K75: =I75+J75 -> 6505.5637 | L75: =+'APU 09.24'!K26 -> 210.62734 | M75: =H75+K75+L75 -> 9896.2815 | N75: =F75*E75 -> 0 | O75: =G75*E75 -> 1392879.7 | P75: =I75*E75 -> 0 | Q75: =J75*E75 -> 2849436.9 | R75: =+L75*E75 -> 92254.773 | S75: =SUM(N75:R75) -> 4334571.3 | U75: =+ROUNDUP(M75*$T$5,0) -> 12439 | V75: =+U75*E75 -> 5448282
A76: 8.07 | B76: R | C76: Banquinas para cocinas | D76: gl | E76: 1 | F76: =+Tareas!H111 -> 1076227.7 | G76: =+Tareas!I111 -> 0 | H76: =F76+G76 -> 1076227.7 | I76: =+Tareas!Q111 -> 0 | J76: =+Tareas!R111 -> 826143.61 | K76: =I76+J76 -> 826143.61 | L76: =+(H76+K76)*0.015 -> 28535.569 | M76: =H76+K76+L76 -> 1930906.8 | N76: =F76*E76 -> 1076227.7 | O76: =G76*E76 -> 0 | P76: =I76*E76 -> 0 | Q76: =J76*E76 -> 826143.61 | R76: =+L76*E76 -> 28535.569 | S76: =SUM(N76:R76) -> 1930906.8 | U76: =+ROUNDUP(M76*$T$5,0) -> 2426924 | V76: =+U76*E76 -> 2426924
A77: 8.08 | B77: R | C77: Banquinas para bombas y tanques en SB | D77: gl | E77: 1 | F77: =+Tareas!H116 -> 215055.5 | G77: =+Tareas!I116 -> 0 | H77: =F77+G77 -> 215055.5 | I77: =+Tareas!Q116 -> 0 | J77: =+Tareas!R116 -> 165228.72 | K77: =I77+J77 -> 165228.72 | L77: =+(H77+K77)*0.015 -> 5704.2633 | M77: =H77+K77+L77 -> 385988.48 | N77: =F77*E77 -> 215055.5 | O77: =G77*E77 -> 0 | P77: =I77*E77 -> 0 | Q77: =J77*E77 -> 165228.72 | R77: =+L77*E77 -> 5704.2633 | S77: =SUM(N77:R77) -> 385988.48 | U77: =+ROUNDUP(M77*$T$5,0) -> 485143 | V77: =+U77*E77 -> 485143
A78: 9 | C78: ESCALERAS | T78: =SUM(S79:S82) -> 4659674.1 | W78: =SUM(V79:V82) -> 5769056.6 | X78: =+W78/$W$216 -> 0.0051171212 | Y78: =+W78 -> 5769056.6
A79: 9.01 | B79: R | C79: Cemento alisado arrodillado en escaleras | D79: gl | E79: 1 | F79: =+Tareas!H122 -> 0 | G79: =+Tareas!I122 -> 203505.44 | H79: =F79+G79 -> 203505.44 | I79: =+Tareas!Q122 -> 0 | J79: =+Tareas!R122 -> 1383533.8 | K79: =I79+J79 -> 1383533.8 | L79: =+(H79+K79)*0.015 -> 23805.589 | M79: =H79+K79+L79 -> 1610844.9 | N79: =F79*E79 -> 0 | O79: =G79*E79 -> 203505.44 | P79: =I79*E79 -> 0 | Q79: =J79*E79 -> 1383533.8 | R79: =+L79*E79 -> 23805.589 | S79: =SUM(N79:R79) -> 1610844.9 | U79: =+ROUNDUP(M79*$T$5,0) -> 2024643 | V79: =+U79*E79 -> 2024643
A80: 9.02 | B80: R | C80: Provisión nariz escalera, hierro angulo 5/8 x 1/8" | D80: ml | E80: =+Computo!H128 -> 122 | F80: =+Tareas!H125 -> 2447.0972 | G80: =+Tareas!I125 -> 0 | H80: =F80+G80 -> 2447.0972 | I80: =+Tareas!Q125 -> 0 | J80: =+Tareas!R125 -> 12299.733 | K80: =I80+J80 -> 12299.733 | L80: =+(H80+K80)*0.015 -> 221.20245 | M80: =H80+K80+L80 -> 14968.033 | N80: =F80*E80 -> 298545.86 | O80: =G80*E80 -> 0 | P80: =I80*E80 -> 0 | Q80: =J80*E80 -> 1500567.4 | R80: =+L80*E80 -> 26986.699 | S80: =SUM(N80:R80) -> 1826100 | U80: =+ROUNDUP(M80*$T$5,0) -> 18814 | V80: =+U80*E80 -> 2295308
A81: 9.03 | B81: R | C81: Zócalo de concreto | D81: ml | E81: =+Locales!BT144 -> 155 | G81: =+'APU 09.24'!E21 -> 758.10738 | H81: =F81+G81 -> 758.10738 | J81: =+'APU 09.24'!H21 -> 3395.9551 | K81: =I81+J81 -> 3395.9551 | L81: =+'APU 09.24'!K21 -> 122.76855 | M81: =H81+K81+L81 -> 4276.831 | N81: =F81*E81 -> 0 | O81: =G81*E81 -> 117506.64 | P81: =I81*E81 -> 0 | Q81: =J81*E81 -> 526373.04 | R81: =+L81*E81 -> 19029.126 | S81: =SUM(N81:R81) -> 662908.81 | U81: =+ROUNDUP(M81*$T$5,0) -> 5376 | V81: =+U81*E81 -> 833280
A82: 9.04 | B82: R | C82: Provisión y colocación de Rodapie/ Zócalo rampante en placa cementicia | D82: ml | E82: =+Computo!E131 -> 31.2 | F82: =+Tareas!H130 -> 7086.2111 | G82: =+Tareas!I130 -> 0 | H82: =F82+G82 -> 7086.2111 | I82: =+Tareas!Q130 -> 0 | J82: =+Tareas!R130 -> 10591.585 | K82: =I82+J82 -> 10591.585 | L82: =+(H82+K82)*0.015 -> 265.16694 | M82: =H82+K82+L82 -> 17942.963 | N82: =F82*E82 -> 221089.79 | O82: =G82*E82 -> 0 | P82: =I82*E82 -> 0 | Q82: =J82*E82 -> 330457.45 | R82: =+L82*E82 -> 8273.2085 | S82: =SUM(N82:R82) -> 559820.44 | U82: =+ROUNDUP(M82*$T$6,0) -> 19738 | V82: =+U82*E82 -> 615825.6
A83: 10 | C83: VENTILACIONES | T83: =SUM(S84:S87) -> 3714963.5 | W83: =SUM(V84:V87) -> 4669278 | X83: =+W83/$W$216 -> 0.0041416237 | Y83: =+W83 -> 4669278
A84: 10.01 | B84: R | C84: Ventilación Conducto Humos. Incluye toma de aire en PB - No aplica s/proyecto | D84: gl | E84: 0 | H84: =F84+G84 -> 0 | K84: =I84+J84 -> 0 | M84: =H84+K84+L84 -> 0 | N84: =F84*E84 -> 0 | O84: =G84*E84 -> 0 | P84: =I84*E84 -> 0 | Q84: =J84*E84 -> 0 | R84: =+L84*E84 -> 0 | S84: =SUM(N84:R84) -> 0 | U84: =+ROUNDUP(M84*$T$5,0) -> 0 | V84: =+U84*E84 -> 0
A85: 10.02 | B85: R | C85: Ventilación Baños - En caño Ø 110 | D85: gl | E85: 1 | F85: 700000 | H85: =F85+G85 -> 700000 | I85: =+F85*1.5 -> 1050000 | K85: =I85+J85 -> 1050000 | M85: =H85+K85+L85 -> 1750000 | N85: =F85*E85 -> 700000 | O85: =G85*E85 -> 0 | P85: =I85*E85 -> 1050000 | Q85: =J85*E85 -> 0 | R85: =+L85*E85 -> 0 | S85: =SUM(N85:R85) -> 1750000 | U85: =+ROUNDUP(M85*$T$5,0) -> 2199545 | V85: =+U85*E85 -> 2199545
A86: 10.03 | B86: R | C86: Colocación de rejillas de inyección y extracción - No aplica s/proyecto | D86: un | E86: 0 | H86: =F86+G86 -> 0 | K86: =I86+J86 -> 0 | M86: =H86+K86+L86 -> 0 | N86: =F86*E86 -> 0 | O86: =G86*E86 -> 0 | P86: =I86*E86 -> 0 | Q86: =J86*E86 -> 0 | R86: =+L86*E86 -> 0 | S86: =SUM(N86:R86) -> 0 | U86: =+ROUNDUP(M86*$T$5,0) -> 0 | V86: =+U86*E86 -> 0
A87: 10.04 | B87: R | C87: Sombreretes en chapa prepintada C25 | D87: u | E87: 7 | F87: =+COVE!L32 -> 225038.88 | H87: =F87+G87 -> 225038.88 | I87: =+COVE!T32 -> 55670.194 | K87: =I87+J87 -> 55670.194 | M87: =H87+K87+L87 -> 280709.07 | N87: =F87*E87 -> 1575272.1 | O87: =G87*E87 -> 0 | P87: =I87*E87 -> 389691.36 | Q87: =J87*E87 -> 0 | R87: =+L87*E87 -> 0 | S87: =SUM(N87:R87) -> 1964963.5 | U87: =+ROUNDUP(M87*$T$5,0) -> 352819 | V87: =+U87*E87 -> 2469733
A88: 11 | C88: PISOS - PROVISION A CARGO DEL COMITENTE | T88: =SUM(S89:S95) -> 38221919 | W88: =SUM(V89:V95) -> 48040802 | X88: =+W88/$W$216 -> 0.042611925 | Y88: =+W88 -> 48040802
A89: 11.01 | B89: OK | C89: Colocación de travertino en hall PB - Provisión a cargo del comitente | D89: m2 | E89: =+Locales!BJ144 -> 30 | G89: =+'APU 09.24'!E36 -> 7250.1087 | H89: =F89+G89 -> 7250.1087 | J89: =+'APU 09.24'!H36 -> 9992.0862 | K89: =I89+J89 -> 9992.0862 | L89: =+'APU 09.24'!K36 -> 219.89813 | M89: =H89+K89+L89 -> 17462.093 | N89: =F89*E89 -> 0 | O89: =G89*E89 -> 217503.26 | P89: =I89*E89 -> 0 | Q89: =J89*E89 -> 299762.58 | R89: =+L89*E89 -> 6596.9439 | S89: =SUM(N89:R89) -> 523862.79 | U89: =+ROUNDUP(M89*$T$5,0) -> 21948 | V89: =+U89*E89 -> 658440
A90: 11.02 | B90: OK | C90: Colocación de porcelanato en paliers, terraza y espacios comunes - Provisión a cargo del comitente | D90: m2 | E90: =+Locales!BM144 -> 185 | G90: =+'APU 09.24'!E36 -> 7250.1087 | H90: =F90+G90 -> 7250.1087 | J90: =+'APU 09.24'!H36 -> 9992.0862 | K90: =I90+J90 -> 9992.0862 | L90: =+'APU 09.24'!K36 -> 219.89813 | M90: =H90+K90+L90 -> 17462.093 | N90: =F90*E90 -> 0 | O90: =G90*E90 -> 1341270.1 | P90: =I90*E90 -> 0 | Q90: =J90*E90 -> 1848535.9 | R90: =+L90*E90 -> 40681.154 | S90: =SUM(N90:R90) -> 3230487.2 | U90: =+ROUNDUP(M90*$T$5,0) -> 21948 | V90: =+U90*E90 -> 4060380
A91: 11.03 | B91: OK | C91: Colocación de porcelanato en UF - Provisión a cargo del comitente | D91: m2 | E91: =+Locales!BK144 -> 942 | G91: =+'APU 09.24'!E36 -> 7250.1087 | H91: =F91+G91 -> 7250.1087 | J91: =+'APU 09.24'!H36 -> 9992.0862 | K91: =I91+J91 -> 9992.0862 | L91: =+'APU 09.24'!K36 -> 219.89813 | M91: =H91+K91+L91 -> 17462.093 | N91: =F91*E91 -> 0 | O91: =G91*E91 -> 6829602.4 | P91: =I91*E91 -> 0 | Q91: =J91*E91 -> 9412545.2 | R91: =+L91*E91 -> 207144.04 | S91: =SUM(N91:R91) -> 16449292 | U91: =+ROUNDUP(M91*$T$5,0) -> 21948 | V91: =+U91*E91 -> 20675016
A92: 11.04 | B92: OK | C92: Colocación de porcelanato en baños - Provisión a cargo del comitente | D92: m2 | E92: =+Locales!BL144 -> 110 | G92: =+'APU 09.24'!E37 -> 7250.1087 | H92: =F92+G92 -> 7250.1087 | J92: =+'APU 09.24'!H37 -> 12989.712 | K92: =I92+J92 -> 12989.712 | L92: =+'APU 09.24'!K37 -> 285.86757 | M92: =H92+K92+L92 -> 20525.688 | N92: =F92*E92 -> 0 | O92: =G92*E92 -> 797511.95 | P92: =I92*E92 -> 0 | Q92: =J92*E92 -> 1428868.3 | R92: =+L92*E92 -> 31445.432 | S92: =SUM(N92:R92) -> 2257825.7 | U92: =+ROUNDUP(M92*$T$5,0) -> 25799 | V92: =+U92*E92 -> 2837890
A93: 11.05 | B93: OK | C93: Provisión y ejecución de alisado de cemento rodillado | D93: m2 | E93: =+Locales!BN144 -> 128 | G93: =+'APU 09.24'!E29 -> 3816.1086 | H93: =F93+G93 -> 3816.1086 | J93: =+'APU 09.24'!H29 -> 8702.6232 | K93: =I93+J93 -> 8702.6232 | L93: =+'APU 09.24'!K29 -> 274.73131 | M93: =H93+K93+L93 -> 12793.463 | N93: =F93*E93 -> 0 | O93: =G93*E93 -> 488461.91 | P93: =I93*E93 -> 0 | Q93: =J93*E93 -> 1113935.8 | R93: =+L93*E93 -> 35165.607 | S93: =SUM(N93:R93) -> 1637563.3 | U93: =+ROUNDUP(M93*$T$5,0) -> 16080 | V93: =+U93*E93 -> 2058240
A94: 11.06 | B94: OK | C94: Colocación de baldoson de vereda - Provisión a cargo del comitente | D94: m2 | E94: =+Locales!BP144 -> 48 | G94: =+'APU 09.24'!E36 -> 7250.1087 | H94: =F94+G94 -> 7250.1087 | J94: =+'APU 09.24'!H36 -> 9992.0862 | K94: =I94+J94 -> 9992.0862 | L94: =+'APU 09.24'!K36 -> 219.89813 | M94: =H94+K94+L94 -> 17462.093 | N94: =F94*E94 -> 0 | O94: =G94*E94 -> 348005.22 | P94: =I94*E94 -> 0 | Q94: =J94*E94 -> 479620.14 | R94: =+L94*E94 -> 10555.11 | S94: =SUM(N94:R94) -> 838180.46 | U94: =+ROUNDUP(M94*$T$5,0) -> 21948 | V94: =+U94*E94 -> 1053504
A95: 11.07 | B95: IN | C95: Provisión y ejecución de pavimento e: 18 cm, incluye malla Q188 | D95: m2 | E95: =+Locales!BI144 -> 226 | F95: =+Tareas!H135 -> 44376.422 | G95: =+Tareas!I135 -> 0 | H95: =F95+G95 -> 44376.422 | I95: =+Tareas!Q135 -> 1659.292 | J95: =+Tareas!R135 -> 11877.483 | K95: =I95+J95 -> 13536.775 | L95: =(H95+K95)*0.015 -> 868.69795 | M95: =H95+K95+L95 -> 58781.895 | N95: =F95*E95 -> 10029071 | O95: =G95*E95 -> 0 | P95: =I95*E95 -> 375000 | Q95: =J95*E95 -> 2684311.2 | R95: =+L95*E95 -> 196325.74 | S95: =SUM(N95:R95) -> 13284708 | U95: =+ROUNDUP(M95*$T$5,0) -> 73882 | V95: =+U95*E95 -> 16697332
A96: 12 | C96: ZOCALOS Y SOLIAS - PROVISION A CARGO DEL COMITENTE | T96: =SUM(S97:S101) -> 8769049.6 | W96: =SUM(V97:V101) -> 11022518 | X96: =+W96/$W$216 -> 0.0097769124 | Y96: =+W96 -> 11022518
A97: =+A96+0.01 -> 12.01 | B97: IN | C97: Provisión y colocación de zocalos de Madera (MDF) h: 7 cm | D97: ml | E97: =+Locales!BQ144 -> 779 | F97: =+Tareas!H148 -> 3132.2314 | G97: =+Tareas!I148 -> 0 | H97: =F97+G97 -> 3132.2314 | I97: =+Tareas!Q148 -> 0 | J97: =+Tareas!R148 -> 2684.8882 | K97: =I97+J97 -> 2684.8882 | L97: =(H97+K97)*0.015 -> 87.256795 | M97: =H97+K97+L97 -> 5904.3764 | N97: =F97*E97 -> 2440008.3 | O97: =G97*E97 -> 0 | P97: =I97*E97 -> 0 | Q97: =J97*E97 -> 2091527.9 | R97: =+L97*E97 -> 67973.043 | S97: =SUM(N97:R97) -> 4599509.3 | U97: =+ROUNDUP(M97*$T$5,0) -> 7422 | V97: =+U97*E97 -> 5781738
A98: 12.02 | B98: OK | C98: Zócalo de concreto | D98: ml | E98: =+Locales!BT144 -> 155 | G98: =+'APU 09.24'!E21 -> 758.10738 | H98: =F98+G98 -> 758.10738 | J98: =+'APU 09.24'!H21 -> 3395.9551 | K98: =I98+J98 -> 3395.9551 | L98: =+'APU 09.24'!K21 -> 122.76855 | M98: =H98+K98+L98 -> 4276.831 | N98: =F98*E98 -> 0 | O98: =G98*E98 -> 117506.64 | P98: =I98*E98 -> 0 | Q98: =J98*E98 -> 526373.04 | R98: =+L98*E98 -> 19029.126 | S98: =SUM(N98:R98) -> 662908.81 | U98: =+ROUNDUP(M98*$T$5,0) -> 5376 | V98: =+U98*E98 -> 833280
A99: 12.03 | B99: OK | C99: Colocación de zocalo de porcelanico - Provisión a cargo del comitente | D99: ml | E99: =+Locales!BR144 -> 37 | G99: =+'APU 09.24'!E38 -> 1185.4173 | H99: =F99+G99 -> 1185.4173 | J99: =+'APU 09.24'!H38 -> 4329.904 | K99: =I99+J99 -> 4329.904 | L99: =+'APU 09.24'!K38 -> 95.289189 | M99: =H99+K99+L99 -> 5610.6105 | N99: =F99*E99 -> 0 | O99: =G99*E99 -> 43860.441 | P99: =I99*E99 -> 0 | Q99: =J99*E99 -> 160206.45 | R99: =+L99*E99 -> 3525.7 | S99: =SUM(N99:R99) -> 207592.59 | U99: =+ROUNDUP(M99*$T$5,0) -> 7052 | V99: =+U99*E99 -> 260924
A100: 12.04 | B100: OK | C100: Colocación de zocalo de porcelanato en palieres - Provisión a cargo del comitente | D100: ml | E100: =+Locales!BS144 -> 433 | G100: =+'APU 09.24'!E38 -> 1185.4173 | H100: =F100+G100 -> 1185.4173 | J100: =+'APU 09.24'!H38 -> 4329.904 | K100: =I100+J100 -> 4329.904 | L100: =+'APU 09.24'!K38 -> 95.289189 | M100: =H100+K100+L100 -> 5610.6105 | N100: =F100*E100 -> 0 | O100: =G100*E100 -> 513285.7 | P100: =I100*E100 -> 0 | Q100: =J100*E100 -> 1874848.4 | R100: =+L100*E100 -> 41260.219 | S100: =SUM(N100:R100) -> 2429394.3 | U100: =+ROUNDUP(M100*$T$5,0) -> 7052 | V100: =+U100*E100 -> 3053516
...

Sheet Tareas
H4: MATERIALES | Q4: MANO DE OBRA
H5: PU | J5: TOTAL | M5: =+'P.MO 09.24'!B4 -> 75113.048 | N5: =+'P.MO 09.24'!B5 -> 65360.248 | O5: =+'P.MO 09.24'!B6 -> 54784.072 | P5: =+'P.MO 09.24'!B7 -> 49934.237 | Q5: PU | S5: TOTAL
C6: Descripción | D6: U | E6: Cant | F6: OTRO | G6: CORRALON | H6: OTRO | I6: CORRALON | J6: OTRO | K6: CORRALON | L6: OTRO | M6: ES | N6: OF | O6: MED | P6: AY | Q6: OTRO | R6: ALB | S6: OTRO | T6: ALB
A7: =+'01'!A8 -> 1 | C7: =+'01'!C8 -> TAREAS PRELIMINARES
A8: =+'01'!A10 -> 1.02 | B8: =+'01'!B10 -> OK | C8: =+'01'!C10 -> Topógrafo - Visita de obra replanteo | D8: =+'01'!D10 -> un | E8: =+'01'!E10 -> 3 | H8: =+J8/E8 -> 0 | I8: =+K8/E8 -> 41666.667 | J8: =SUM(J9:J11) -> 0 | K8: =SUM(K9:K11) -> 125000 | Q8: =+U8/E8 -> 172653.21 | R8: =+V8/E8 -> 83223.729 | U8: =SUM(S9:S11) -> 517959.62 | V8: =SUM(T9:T11) -> 249671.19
C9: M.Obra topografo | D9: d | E9: =+E8 -> 3 | J9: =+F9*E9 -> 0 | K9: =+G9*E9 -> 0 | L9: =+'P.MO 09.24'!B10 -> 172653.21 | S9: =+L9*E9 -> 517959.62 | T9: =(+M9*$M$5+N9*$N$5+O9*$O$5+P9*$P$5)*E9 -> 0
C10: M.Obra ayudante | D10: d | E10: =+E8 -> 3 | J10: =+F10*E10 -> 0 | K10: =+G10*E10 -> 0 | S10: =+L10*E10 -> 0 | T10: =(+M10*$M$5+N10*$N$5+O10*$O$5+P10*$P$5)*E10 -> 0
C11: Consumibles | D11: gl | E11: 5 | G11: 25000 | J11: =+F11*E11 -> 0 | K11: =+G11*E11 -> 125000 | P11: 1 | S11: =+L11*E11 -> 0 | T11: =(+M11*$M$5+N11*$N$5+O11*$O$5+P11*$P$5)*E11 -> 249671.19
A12: =+'01'!A12 -> 1.04 | B12: =+'01'!B12 -> OK | C12: =+'01'!C12 -> Cerco de obra perimetral - En chapa C25 + Concertina + Porton corredizo | D12: =+'01'!D12 -> ml | E12: =+'01'!E12 -> 11 | H12: =+J12/E12 -> 79773.183 | I12: =+K12/E12 -> 0 | J12: =+SUM(J13:J21) -> 877505.01 | K12: =+SUM(K13:K21) -> 0 | Q12: =+U12/E12 -> 0 | R12: =+V12/E12 -> 30923.374 | U12: =SUM(S13:S21) -> 0 | V12: =SUM(T13:T21) -> 340157.11
C13: Chapa acanalada C25 | D13: m2 | E13: =+E12*2.5 -> 27.5 | F13: =+Cotizaciones!D4 -> 10599.983 | J13: =+F13*E13 -> 291499.55 | K13: =+G13*E13 -> 0 | S13: =+L13*E13 -> 0 | T13: =(+M13*$M$5+N13*$N$5+O13*$O$5+P13*$P$5)*E13 -> 0
C14: Perfiles UPN 100 | D14: un | E14: 1 | F14: =+Cotizaciones!D5 -> 267019.02 | J14: =+F14*E14 -> 267019.02 | K14: =+G14*E14 -> 0 | S14: =+L14*E14 -> 0 | T14: =(+M14*$M$5+N14*$N$5+O14*$O$5+P14*$P$5)*E14 -> 0
C15: Bastidor para porton corredizo - Perfil 40 x 40 x 2 | D15: u | E15: 2 | F15: =+Cotizaciones!D6 -> 26250.62 | J15: =+F15*E15 -> 52501.24 | K15: =+G15*E15 -> 0 | S15: =+L15*E15 -> 0 | T15: =(+M15*$M$5+N15*$N$5+O15*$O$5+P15*$P$5)*E15 -> 0
C16: Riel Roma 174 e: 2,1 mm. 53 x 60 x 6000 | D16: u | E16: 1 | F16: =+Cotizaciones!D7 -> 81509.95 | J16: =+F16*E16 -> 81509.95 | K16: =+G16*E16 -> 0 | S16: =+L16*E16 -> 0 | T16: =(+M16*$M$5+N16*$N$5+O16*$O$5+P16*$P$5)*E16 -> 0
C17: Carro acero 174 4 ruedas puertas portones Ø45mm | D17: u | E17: 2 | F17: =+Cotizaciones!D8 -> 12131.562 | J17: =+F17*E17 -> 24263.124 | K17: =+G17*E17 -> 0 | S17: =+L17*E17 -> 0 | T17: =(+M17*$M$5+N17*$N$5+O17*$O$5+P17*$P$5)*E17 -> 0
C18: Autoperforantes punta mecha 14 x 2 | D18: u | E18: =+E13*4.5 -> 123.75 | F18: 120 | J18: =+F18*E18 -> 14850 | K18: =+G18*E18 -> 0 | S18: =+L18*E18 -> 0 | T18: =(+M18*$M$5+N18*$N$5+O18*$O$5+P18*$P$5)*E18 -> 0
C19: Rollo Concertina | D19: rol | E19: 1 | F19: =38000/1.21 -> 31404.959 | J19: =+F19*E19 -> 31404.959 | K19: =+G19*E19 -> 0 | S19: =+L19*E19 -> 0 | T19: =(+M19*$M$5+N19*$N$5+O19*$O$5+P19*$P$5)*E19 -> 0
C20: Consumibles | D20: gl | E20: 0.15 | F20: =+SUM(J13:J19) -> 763047.83 | J20: =+F20*E20 -> 114457.18 | K20: =+G20*E20 -> 0 | S20: =+L20*E20 -> 0 | T20: =(+M20*$M$5+N20*$N$5+O20*$O$5+P20*$P$5)*E20 -> 0
C21: M.Obra | D21: d | E21: 2 | J21: =+F21*E21 -> 0 | K21: =+G21*E21 -> 0 | N21: 1 | O21: 1 | P21: 1 | S21: =+L21*E21 -> 0 | T21: =(+M21*$M$5+N21*$N$5+O21*$O$5+P21*$P$5)*E21 -> 340157.11
A22: =+'01'!A13 -> 1.05 | B22: =+'01'!B13 -> OK | C22: =+'01'!C13 -> Obrador colgante, pañol y ducha | D22: =+'01'!D13 -> gl | E22: =+'01'!E13 -> 1 | H22: =+J22/E22 -> 2300856.7 | I22: =+K22/E22 -> 100000 | J22: =+SUM(J23:J43) -> 2300856.7 | K22: =+SUM(K23:K43) -> 100000 | Q22: =+U22/E22 -> 500000 | R22: =+V22/E22 -> 3016332.5 | U22: =SUM(S23:S43) -> 500000 | V22: =SUM(T23:T43) -> 3016332.5 | AD22: 0.66
C23: Chapa acanalada C25 - Reutilizado (estimado 3 usos) | D23: m2 | E23: 35 | F23: =+Cotizaciones!D4/2 -> 5299.9917 | J23: =+F23*E23 -> 185499.71 | K23: =+G23*E23 -> 0 | S23: =+L23*E23 -> 0 | T23: =(+M23*$M$5+N23*$N$5+O23*$O$5+P23*$P$5)*E23 -> 0 | X23: Largo | Y23: Ancho | Z23: perim | AA23: h | AB23: m2 | AD23: Puntales
C24: Fenolico 1,22 x 2,44 - Reutilizado (estimado 3 usos) | D24: u | E24: =+AB32 -> 33 | F24: =+Cotizaciones!D18/2 -> 13161.34 | J24: =+F24*E24 -> 434324.22 | K24: =+G24*E24 -> 0 | S24: =+L24*E24 -> 0 | T24: =(+M24*$M$5+N24*$N$5+O24*$O$5+P24*$P$5)*E24 -> 0 | W24: Paredes | X24: 10 | Y24: 3.6 | Z24: =+X24 -> 10 | AA24: 2.4 | AB24: =+Z24*AA24 -> 24 | AD24: =+ROUNDUP(X24/$AD$22,0) -> 16 | AE24: =+AD24*AA24 -> 38.4 | AF24: =+ROUNDUP(AE24/3.7,0) -> 11
C25: Puntales 1 x 4 x 3,7 - Reutilizado (estimado 3 usos) | D25: u | E25: =+E26*2 -> 80 | F25: =+Cotizaciones!D20/2 -> 970.974 | J25: =+F25*E25 -> 77677.92 | K25: =+G25*E25 -> 0 | S25: =+L25*E25 -> 0 | T25: =(+M25*$M$5+N25*$N$5+O25*$O$5+P25*$P$5)*E25 -> 0 | W25: Piso | X25: =+X24 -> 10 | Y25: 3.6 | AB25: =+X25*Y25 -> 36 | AD25: =+ROUNDUP(Y25/$AD$22,0) -> 6 | AE25: =+AD25*X25 -> 60 | AF25: =+ROUNDUP(AE25/3.7,0) -> 17
C26: Puntales 3 x 3 x 3,7 - Reutilizado (estimado 3 usos) | D26: u | E26: =+AF27 -> 40 | F26: =+Cotizaciones!D21/2 -> 2184.714 | J26: =+F26*E26 -> 87388.56 | K26: =+G26*E26 -> 0 | S26: =+L26*E26 -> 0 | T26: =(+M26*$M$5+N26*$N$5+O26*$O$5+P26*$P$5)*E26 -> 0 | W26: Paredes interiores | X26: 3 | Y26: 3 | AA26: 2.4 | AB26: =+X26*Y26*AA26 -> 21.6 | AD26: =+ROUNDUP(Y26*3/$AD$22,0) -> 14 | AE26: =+AD26*X26 -> 42 | AF26: =+ROUNDUP(AE26/3.7,0) -> 12
C27: Flechas 3 x 6 x 3,7 - Reutilizado (estimado 3 usos) | D27: u | E27: 20 | F27: =+F26*2 -> 4369.428 | J27: =+F27*E27 -> 87388.56 | K27: =+G27*E27 -> 0 | S27: =+L27*E27 -> 0 | T27: =(+M27*$M$5+N27*$N$5+O27*$O$5+P27*$P$5)*E27 -> 0 | W27: Galeria | AF27: =+SUM(AF24:AF26) -> 40
C28: Escalera | D28: gl | E28: 0.5 | F28: =+SUM(J25:J27) -> 252455.04 | J28: =+F28*E28 -> 126227.52 | K28: =+G28*E28 -> 0 | S28: =+L28*E28 -> 0 | T28: =(+M28*$M$5+N28*$N$5+O28*$O$5+P28*$P$5)*E28 -> 0
C29: Flete madera | D29: u | E29: 2 | J29: =+F29*E29 -> 0 | K29: =+G29*E29 -> 0 | L29: 250000 | S29: =+L29*E29 -> 500000 | T29: =(+M29*$M$5+N29*$N$5+O29*$O$5+P29*$P$5)*E29 -> 0 | AB29: =+SUM(AB24:AB26) -> 81.6
C30: Materiales varios | D30: gl | E30: 1 | G30: 100000 | J30: =+F30*E30 -> 0 | K30: =+G30*E30 -> 100000 | S30: =+L30*E30 -> 0 | T30: =(+M30*$M$5+N30*$N$5+O30*$O$5+P30*$P$5)*E30 -> 0
C31: M.Obra carpinteros | D31: d | E31: 5 | J31: =+F31*E31 -> 0 | K31: =+G31*E31 -> 0 | M31: 1 | N31: 1 | O31: 1 | P31: 1 | S31: =+L31*E31 -> 0 | T31: =(+M31*$M$5+N31*$N$5+O31*$O$5+P31*$P$5)*E31 -> 1225958 | AB31: =1.2*2.4 -> 2.88
C32: Rollo de cable TPR 3 x 2,5 | D32: rol | E32: 1 | F32: =260000/1.21 -> 214876.03 | J32: =+F32*E32 -> 214876.03 | K32: =+G32*E32 -> 0 | S32: =+L32*E32 -> 0 | T32: =(+M32*$M$5+N32*$N$5+O32*$O$5+P32*$P$5)*E32 -> 0 | AB32: =+ROUNDUP(AB29/AB31*1.15,0) -> 33 | AD32: =+SUM(AD24:AD31)*1.15 -> 41.4
C33: Zocalo E27 | D33: u | E33: 10 | F33: =4475/1.21/10 -> 369.83471 | J33: =+F33*E33 -> 3698.3471 | K33: =+G33*E33 -> 0 | S33: =+L33*E33 -> 0 | T33: =(+M33*$M$5+N33*$N$5+O33*$O$5+P33*$P$5)*E33 -> 0
C34: Lampara Led 12 w | D34: u | E34: =+E33 -> 10 | F34: =14300/1.21/5 -> 2363.6364 | J34: =+F34*E34 -> 23636.364 | K34: =+G34*E34 -> 0 | S34: =+L34*E34 -> 0 | T34: =(+M34*$M$5+N34*$N$5+O34*$O$5+P34*$P$5)*E34 -> 0
C35: Mat. Elect. (tomas, enchufes, etc.) | D35: gl | E35: 0.25 | F35: =+SUM(J32:J34) -> 242210.74 | J35: =+F35*E35 -> 60552.686 | K35: =+G35*E35 -> 0 | S35: =+L35*E35 -> 0 | T35: =(+M35*$M$5+N35*$N$5+O35*$O$5+P35*$P$5)*E35 -> 0
C36: M.Obra elect | D36: d | E36: 3 | J36: =+F36*E36 -> 0 | K36: =+G36*E36 -> 0 | M36: 1 | N36: 1 | S36: =+L36*E36 -> 0 | T36: =(+M36*$M$5+N36*$N$5+O36*$O$5+P36*$P$5)*E36 -> 421419.89
C37: Materiales Sanit | D37: gl | E37: 1 | F37: 500000 | J37: =+F37*E37 -> 500000 | K37: =+G37*E37 -> 0 | S37: =+L37*E37 -> 0 | T37: =(+M37*$M$5+N37*$N$5+O37*$O$5+P37*$P$5)*E37 -> 0
C38: Inodoro | D38: u | E38: 2 | F38: 100000 | J38: =+F38*E38 -> 200000 | K38: =+G38*E38 -> 0 | S38: =+L38*E38 -> 0 | T38: =(+M38*$M$5+N38*$N$5+O38*$O$5+P38*$P$5)*E38 -> 0
C39: Mochila plastico | D39: u | E39: 2 | F39: 25000 | J39: =+F39*E39 -> 50000 | K39: =+G39*E39 -> 0 | S39: =+L39*E39 -> 0 | T39: =(+M39*$M$5+N39*$N$5+O39*$O$5+P39*$P$5)*E39 -> 0
C40: Bacha | D40: u | E40: 2 | F40: =30000/1.21 -> 24793.388 | J40: =+F40*E40 -> 49586.777 | K40: =+G40*E40 -> 0 | S40: =+L40*E40 -> 0 | T40: =(+M40*$M$5+N40*$N$5+O40*$O$5+P40*$P$5)*E40 -> 0
C41: Termo electrico 40 lts | D41: u | E41: 1 | F41: 200000 | J41: =+F41*E41 -> 200000 | K41: =+G41*E41 -> 0 | S41: =+L41*E41 -> 0 | T41: =(+M41*$M$5+N41*$N$5+O41*$O$5+P41*$P$5)*E41 -> 0
C42: M.Obra sanit | D42: d | E42: 4 | J42: =+F42*E42 -> 0 | K42: =+G42*E42 -> 0 | M42: 1 | N42: 1 | S42: =+L42*E42 -> 0 | T42: =(+M42*$M$5+N42*$N$5+O42*$O$5+P42*$P$5)*E42 -> 561893.19
C43: Mantenimiento | D43: mes | E43: =+GGBB!F4 -> 14 | J43: =+F43*E43 -> 0 | K43: =+G43*E43 -> 0 | N43: 0.5 | P43: 0.5 | S43: =+L43*E43 -> 0 | T43: =(+M43*$M$5+N43*$N$5+O43*$O$5+P43*$P$5)*E43 -> 807061.4
A44: =+'01'!A15 -> 1.07 | B44: =+'01'!B15 -> OK | C44: =+'01'!C15 -> Conexión pilar y luz de obra + Tablero de obra | D44: =+'01'!D15 -> gl | E44: =+'01'!E15 -> 1 | H44: =+J44/E44 -> 795578.51 | I44: =+K44/E44 -> 50000 | J44: =+SUM(J45:J50) -> 795578.51 | K44: =+SUM(K45:K50) -> 50000 | Q44: =+U44/E44 -> 0 | R44: =+V44/E44 -> 511535.56 | U44: =SUM(S45:S50) -> 0 | V44: =SUM(T45:T50) -> 511535.56
C45: Pilar de obra, albañileria | D45: d | E45: 2 | G45: 25000 | J45: =+F45*E45 -> 0 | K45: =+G45*E45 -> 50000 | N45: 1 | P45: 1 | S45: =+L45*E45 -> 0 | T45: =(+M45*$M$5+N45*$N$5+O45*$O$5+P45*$P$5)*E45 -> 230588.97
C46: Kit medidor pilar Edenor Conextube | D46: gl | E46: 1 | F46: 150000 | J46: =+F46*E46 -> 150000 | K46: =+G46*E46 -> 0 | S46: =+L46*E46 -> 0 | T46: =(+M46*$M$5+N46*$N$5+O46*$O$5+P46*$P$5)*E46 -> 0
C47: Kit jabalina + caja + toma cable | D47: gl | E47: 1 | F47: 15000 | J47: =+F47*E47 -> 15000 | K47: =+G47*E47 -> 0 | S47: =+L47*E47 -> 0 | T47: =(+M47*$M$5+N47*$N$5+O47*$O$5+P47*$P$5)*E47 -> 0
C48: Cable subterraneo 5 x 10 mm2 | D48: mts | E48: 20 | F48: =20000/1.21 -> 16528.926 | J48: =+F48*E48 -> 330578.51 | K48: =+G48*E48 -> 0 | S48: =+L48*E48 -> 0 | T48: =(+M48*$M$5+N48*$N$5+O48*$O$5+P48*$P$5)*E48 -> 0
C49: Tablero de obra | D49: gl | E49: 1 | F49: 300000 | J49: =+F49*E49 -> 300000 | K49: =+G49*E49 -> 0 | S49: =+L49*E49 -> 0 | T49: =(+M49*$M$5+N49*$N$5+O49*$O$5+P49*$P$5)*E49 -> 0
C50: M.Obra elect | D50: d | E50: 2 | J50: =+F50*E50 -> 0 | K50: =+G50*E50 -> 0 | M50: 1 | N50: 1 | S50: =+L50*E50 -> 0 | T50: =(+M50*$M$5+N50*$N$5+O50*$O$5+P50*$P$5)*E50 -> 280946.59
A51: =+'01'!A16 -> 1.08 | B51: =+'01'!B16 -> OK | C51: =+'01'!C16 -> Conexión agua de obra, tanque + bomba | D51: =+'01'!D16 -> gl | E51: =+'01'!E16 -> 1 | H51: =+J51/E51 -> 680400 | I51: =+K51/E51 -> 0 | J51: =+SUM(J52:J60) -> 680400 | K51: =+SUM(K52:K60) -> 0 | Q51: =+U51/E51 -> 0 | R51: =+V51/E51 -> 421419.89 | U51: =SUM(S52:S60) -> 0 | V51: =SUM(T52:T60) -> 421419.89
C52: Tanque de Bombeo 500 lts (reutilizado) | D52: u | E52: 1 | F52: 150000 | J52: =+F52*E52 -> 150000 | K52: =+G52*E52 -> 0 | S52: =+L52*E52 -> 0 | T52: =(+M52*$M$5+N52*$N$5+O52*$O$5+P52*$P$5)*E52 -> 0
C53: Bomba pres (reutilizada) | D53: u | E53: 1 | F53: 200000 | J53: =+F53*E53 -> 200000 | K53: =+G53*E53 -> 0 | S53: =+L53*E53 -> 0 | T53: =(+M53*$M$5+N53*$N$5+O53*$O$5+P53*$P$5)*E53 -> 0
C54: Flotante mecanico 1" + boya | D54: u | E54: 1 | F54: 50000 | J54: =+F54*E54 -> 50000 | K54: =+G54*E54 -> 0 | S54: =+L54*E54 -> 0 | T54: =(+M54*$M$5+N54*$N$5+O54*$O$5+P54*$P$5)*E54 -> 0
C55: Flotante automatico | D55: u | E55: 1 | F55: 10000 | J55: =+F55*E55 -> 10000 | K55: =+G55*E55 -> 0 | S55: =+L55*E55 -> 0 | T55: =(+M55*$M$5+N55*$N$5+O55*$O$5+P55*$P$5)*E55 -> 0
C56: Caño 3/4" | D56: u | E56: =60/6 -> 10 | F56: 10000 | J56: =+F56*E56 -> 100000 | K56: =+G56*E56 -> 0 | S56: =+L56*E56 -> 0 | T56: =(+M56*$M$5+N56*$N$5+O56*$O$5+P56*$P$5)*E56 -> 0
C57: Val. esf doble media union 1" | D57: u | E57: 3 | F57: 15000 | J57: =+F57*E57 -> 45000 | K57: =+G57*E57 -> 0 | S57: =+L57*E57 -> 0 | T57: =(+M57*$M$5+N57*$N$5+O57*$O$5+P57*$P$5)*E57 -> 0
C58: Canilla de pvc | D58: u | E58: 6 | F58: 2000 | J58: =+F58*E58 -> 12000 | K58: =+G58*E58 -> 0 | S58: =+L58*E58 -> 0 | T58: =(+M58*$M$5+N58*$N$5+O58*$O$5+P58*$P$5)*E58 -> 0
C59: Desperdicio | D59: gl | E59: 0.2 | F59: =+SUM(J52:J58) -> 567000 | J59: =+F59*E59 -> 113400 | K59: =+G59*E59 -> 0 | S59: =+L59*E59 -> 0 | T59: =(+M59*$M$5+N59*$N$5+O59*$O$5+P59*$P$5)*E59 -> 0
C60: M.Obra sanit | D60: d | E60: 3 | J60: =+F60*E60 -> 0 | K60: =+G60*E60 -> 0 | M60: 1 | N60: 1 | S60: =+L60*E60 -> 0 | T60: =(+M60*$M$5+N60*$N$5+O60*$O$5+P60*$P$5)*E60 -> 421419.89
A61: =+'01'!A17 -> 1.09 | B61: =+'01'!B17 -> OK | C61: =+'01'!C17 -> Tramite luz de obra, certificado luz de obra (2) y medición PAT | D61: =+'01'!D17 -> gl | E61: =+'01'!E17 -> 1 | H61: =+J61/E61 -> 0 | I61: =+K61/E61 -> 0 | J61: =+SUM(J62:J64) -> 0 | K61: =+SUM(K62:K64) -> 0 | Q61: =+U61/E61 -> 339320.84 | R61: =+V61/E61 -> 0 | U61: =SUM(S62:S63) -> 339320.84 | V61: =SUM(T62:T63) -> 0
C62: Gestion suministro luz de obra | D62: u | E62: 1 | J62: =+F62*E62 -> 0 | K62: =+G62*E62 -> 0 | L62: =+SUBCONTRATOS!D11 -> 139065.92 | S62: =+L62*E62 -> 139065.92 | T62: =(+M62*$M$5+N62*$N$5+O62*$O$5+P62*$P$5)*E62 -> 0
C63: Luz de Obra | D63: u | E63: 2 | J63: =+F63*E63 -> 0 | K63: =+G63*E63 -> 0 | L63: =+SUBCONTRATOS!D14 -> 100127.46 | S63: =+L63*E63 -> 200254.92 | T63: =(+M63*$M$5+N63*$N$5+O63*$O$5+P63*$P$5)*E63 -> 0
C64: Medicion PAT luz de obra | D64: u | E64: 1 | J64: =+F64*E64 -> 0 | K64: =+G64*E64 -> 0 | L64: =+SUBCONTRATOS!D18 -> 87611.528 | S64: =+L64*E64 -> 87611.528 | T64: =(+M64*$M$5+N64*$N$5+O64*$O$5+P64*$P$5)*E64 -> 0
A65: =+'01'!A19 -> 2 | C65: =+'01'!C19 -> MOVIMIENTO DE TIERRA, COMPACTACION Y RELLENO
A66: =+'01'!A20 -> 2.01 | B66: =+'01'!#REF! -> #REF! | C66: =+'01'!C20 -> Excavación a maquina para submuración y subsuelo | D66: =+'01'!D20 -> m3 | E66: =+'01'!E20 -> 1266 | H66: =+J66/E66 -> 0 | I66: =+K66/E66 -> 0 | J66: =+SUM(J67:J68) -> 0 | K66: =+SUM(K67:K68) -> 0 | Q66: =+U66/E66 -> 18400 | R66: =+V66/E66 -> 7809.62 | U66: =SUM(S67:S68) -> 23294400 | V66: =SUM(T67:T68) -> 9886979
C67: Subcontrato + 10% - Celsi VIAL | D67: gl | E67: =+E66*1.15 -> 1455.9 | J67: =+F67*E67 -> 0 | K67: =+G67*E67 -> 0 | L67: =+SUBCONTRATOS!D23 -> 16000 | S67: =+L67*E67 -> 23294400 | T67: =(+M67*$M$5+N67*$N$5+O67*$O$5+P67*$P$5)*E67 -> 0
C68: Ayuda de gremios | D68: d | E68: =3*22 -> 66 | J68: =+F68*E68 -> 0 | K68: =+G68*E68 -> 0 | P68: 3 | S68: =+L68*E68 -> 0 | T68: =(+M68*$M$5+N68*$N$5+O68*$O$5+P68*$P$5)*E68 -> 9886979
A69: =+'01'!A23 -> 3 | C69: =+'01'!C23 -> ESTRUCTURA RESISTENTE
A70: =+'01'!A40 -> 3.17 | C70: =+'01'!C40 -> Picado de medianeras para columnas y vigas - Cotizado solo para PB y 1P, No contempla picado en SS | D70: =+'01'!D40 -> m2 | E70: =+'01'!E40 -> 93 | H70: =+J70/E70 -> 3440.8602 | I70: =+K70/E70 -> 1612.9032 | J70: =SUM(J71:J73) -> 320000 | K70: =SUM(K71:K73) -> 150000 | Q70: =+U70/E70 -> 0 | R70: =+V70/E70 -> 14213.223 | U70: =SUM(S71:S73) -> 0 | V70: =SUM(T71:T73) -> 1321829.8
C71: Consumibles - Punta martillo | D71: gl | E71: 1 | G71: 150000 | J71: =+F71*E71 -> 0 | K71: =+G71*E71 -> 150000 | S71: =+L71*E71 -> 0 | T71: =(+M71*$M$5+N71*$N$5+O71*$O$5+P71*$P$5)*E71 -> 0
C72: Volquetes | D72: u | E72: =+ROUNDUP(E70*0.2/5,0) -> 4 | F72: 80000 | J72: =+F72*E72 -> 320000 | K72: =+G72*E72 -> 0 | S72: =+L72*E72 -> 0 | T72: =(+M72*$M$5+N72*$N$5+O72*$O$5+P72*$P$5)*E72 -> 0
C73: 12 | D73: d | E73: =+ROUNDUP(E70/C73,0) -> 8 | J73: =+F73*E73 -> 0 | K73: =+G73*E73 -> 0 | N73: 1 | P73: 2 | S73: =+L73*E73 -> 0 | T73: =(+M73*$M$5+N73*$N$5+O73*$O$5+P73*$P$5)*E73 -> 1321829.8
A74: =+'01'!A41 -> 4 | C74: =+'01'!C41 -> ALBAÑILERIA
A75: =+'01'!A48 -> 4.07 | B75: =+'01'!B48 -> IN | C75: =+'01'!C48 -> Cordón de hormigón en umbrales carpinterías | D75: =+'01'!D48 -> ml | E75: =+'01'!E48 -> 81 | H75: =+J75/E75 -> 17364.128 | I75: =+K75/E75 -> 0 | J75: =SUM(J76:J80) -> 1406494.4 | K75: =SUM(K76:K80) -> 0 | Q75: =+U75/E75 -> 0 | R75: =+V75/E75 -> 6926.499 | U75: =SUM(S76:S80) -> 0 | V75: =SUM(T76:T80) -> 561046.42
C76: Taco quimico Fischer | D76: u | E76: 8 | F76: 50000 | J76: =+F76*E76 -> 400000 | K76: =+G76*E76 -> 0 | S76: =+L76*E76 -> 0 | T76: =(+M76*$M$5+N76*$N$5+O76*$O$5+P76*$P$5)*E76 -> 0
C77: Hierro del 6 | D77: u | E77: =+ROUNDUP(E75*2.5*2.66,0) -> 539 | F77: =+Cotizaciones!D38 -> 1416.57 | J77: =+F77*E77 -> 763531.23 | K77: =+G77*E77 -> 0 | S77: =+L77*E77 -> 0 | T77: =(+M77*$M$5+N77*$N$5+O77*$O$5+P77*$P$5)*E77 -> 0
C78: H° | D78: m3 | E78: =+ROUNDUP(E75*0.1*0.1,0) -> 1 | F78: =+Cotizaciones!D23 -> 115100 | J78: =+F78*E78 -> 115100 | K78: =+G78*E78 -> 0 | S78: =+L78*E78 -> 0 | T78: =(+M78*$M$5+N78*$N$5+O78*$O$5+P78*$P$5)*E78 -> 0
C79: Consumibles | D79: gl | E79: 0.1 | F79: =+SUM(J76:J78) -> 1278631.2 | J79: =+F79*E79 -> 127863.12 | K79: =+G79*E79 -> 0 | S79: =+L79*E79 -> 0 | T79: =(+M79*$M$5+N79*$N$5+O79*$O$5+P79*$P$5)*E79 -> 0
C80: M.Obra | D80: d | E80: 4 | J80: =+F80*E80 -> 0 | K80: =+G80*E80 -> 0 | N80: 1 | P80: 1.5 | S80: =+L80*E80 -> 0 | T80: =(+M80*$M$5+N80*$N$5+O80*$O$5+P80*$P$5)*E80 -> 561046.42
A81: =+'01'!A49 -> 4.08 | B81: =+'01'!B49 -> IN | C81: =+'01'!C49 -> Pozo de bombeo pluvial y cloacal | D81: =+'01'!D49 -> gl | E81: =+'01'!E49 -> 1 | H81: =+J81/E81 -> 451217.95 | I81: =+K81/E81 -> 0 | J81: =SUM(J82:J88) -> 451217.95 | K81: =SUM(K82:K88) -> 0 | Q81: =+U81/E81 -> 0 | R81: =+V81/E81 -> 426669.72 | U81: =SUM(S82:S88) -> 0 | V81: =SUM(T82:T88) -> 426669.72
C82: H° | D82: m3 | E82: =+Computo!G208 -> 1.002 | F82: =+Cotizaciones!D24 -> 125000 | J82: =+F82*E82 -> 125250 | K82: =+G82*E82 -> 0 | S82: =+L82*E82 -> 0 | T82: =(+M82*$M$5+N82*$N$5+O82*$O$5+P82*$P$5)*E82 -> 0
C83: Fenolico | D83: u | E83: =+Computo!E210 -> 3.0905671 | F83: =+Cotizaciones!D18 -> 26322.68 | J83: =+F83*E83 -> 81352.008 | K83: =+G83*E83 -> 0 | S83: =+L83*E83 -> 0 | T83: =(+M83*$M$5+N83*$N$5+O83*$O$5+P83*$P$5)*E83 -> 0
C84: Hierro del 6 | D84: kg | E84: =+E82*90 -> 90.18 | F84: =+Cotizaciones!D38 -> 1416.57 | J84: =+F84*E84 -> 127746.28 | K84: =+G84*E84 -> 0 | S84: =+L84*E84 -> 0 | T84: =(+M84*$M$5+N84*$N$5+O84*$O$5+P84*$P$5)*E84 -> 0
C85: Consumibles | D85: gl | E85: 0.2 | F85: =+SUM(J82:J84) -> 334348.29 | J85: =+F85*E85 -> 66869.658 | K85: =+G85*E85 -> 0 | S85: =+L85*E85 -> 0 | T85: =(+M85*$M$5+N85*$N$5+O85*$O$5+P85*$P$5)*E85 -> 0
C86: Impermeabilizazión - Sika monotop 107 | D86: bol | E86: 1 | F86: 50000 | J86: =+F86*E86 -> 50000 | K86: =+G86*E86 -> 0 | S86: =+L86*E86 -> 0 | T86: =(+M86*$M$5+N86*$N$5+O86*$O$5+P86*$P$5)*E86 -> 0
C87: M.Obra imper | D87: d | E87: 1 | J87: =+F87*E87 -> 0 | K87: =+G87*E87 -> 0 | N87: 1 | S87: =+L87*E87 -> 0 | T87: =(+M87*$M$5+N87*$N$5+O87*$O$5+P87*$P$5)*E87 -> 65360.248
C88: M.Obra | D88: d | E88: 4 | J88: =+F88*E88 -> 0 | K88: =+G88*E88 -> 0 | N88: 1 | P88: 0.5 | S88: =+L88*E88 -> 0 | T88: =(+M88*$M$5+N88*$N$5+O88*$O$5+P88*$P$5)*E88 -> 361309.47
A89: =+'01'!A50 -> 5 | C89: =+'01'!C50 -> AISLACIONES
A90: =+'01'!A57 -> 5.07 | B90: =+'01'!B57 -> OK | C90: =+'01'!C57 -> Impermeabilización de subsuelo | D90: =+'01'!D57 -> gl | E90: =+'01'!E57 -> 1 | H90: =+J90/E90 -> 52237.326 | I90: =+K90/E90 -> 0 | J90: =SUM(J91:J93) -> 52237.326 | K90: =SUM(K91:K93) -> 0 | Q90: =+U90/E90 -> 0 | R90: =+V90/E90 -> 200160.33 | U90: =SUM(S91:S93) -> 0 | V90: =SUM(T91:T93) -> 200160.33
C91: Weber Imper G x 25 kg | D91: bol | E91: =+ROUNDUP((E90*2*3)/25,0) -> 1 | F91: =20000/1.21 -> 16528.926 | J91: =+F91*E91 -> 16528.926 | K91: =+G91*E91 -> 0 | S91: =+L91*E91 -> 0 | T91: =(+M91*$M$5+N91*$N$5+O91*$O$5+P91*$P$5)*E91 -> 0
C92: Malla de fibra 5 x 5 90 gr, rollo 1 x 50 mts | D92: rol | E92: 1 | F92: =VLOOKUP(C92,Cotizaciones!B:D,3,0) -> 35708.4 | J92: =+F92*E92 -> 35708.4 | K92: =+G92*E92 -> 0 | S92: =+L92*E92 -> 0 | T92: =(+M92*$M$5+N92*$N$5+O92*$O$5+P92*$P$5)*E92 -> 0
C93: 35 | D93: d | E93: 2 | J93: =+F93*E93 -> 0 | K93: =+G93*E93 -> 0 | M93: 1 | P93: 0.5 | S93: =+L93*E93 -> 0 | T93: =(+M93*$M$5+N93*$N$5+O93*$O$5+P93*$P$5)*E93 -> 200160.33
A94: =+'01'!A58 -> 6 | C94: =+'01'!C58 -> CUBIERTAS | D94: =+'01'!D58 -> 0 | E94: =+'01'!E58 -> 0
A95: =+'01'!A59 -> 6.02 | C95: =+'01'!C59 -> Babeta de chapa galvanizada en medianeras | D95: =+'01'!D59 -> ml | E95: =+'01'!E59 -> 60 | H95: =+J95/E95 -> 13939.394 | I95: =+K95/E95 -> 0 | J95: =SUM(J96:J99) -> 836363.64 | K95: =SUM(K96:K99) -> 0 | Q95: =+U95/E95 -> 0 | R95: =+V95/E95 -> 4329.904 | U95: =SUM(S96:S99) -> 0 | V95: =SUM(T96:T99) -> 259794.24
C96: Babeta | D96: u | E96: =+ROUNDUP(E95/2.44*1.1,0) -> 28 | F96: =20000/1.21 -> 16528.926 | J96: =+F96*E96 -> 462809.92 | K96: =+G96*E96 -> 0 | S96: =+L96*E96 -> 0 | T96: =(+M96*$M$5+N96*$N$5+O96*$O$5+P96*$P$5)*E96 -> 0
C97: Sellador / Silicona (rinde 5 mts) | D97: u | E97: =+E95/5 -> 12 | F97: =30000/1.21 -> 24793.388 | J97: =+F97*E97 -> 297520.66 | K97: =+G97*E97 -> 0 | S97: =+L97*E97 -> 0 | T97: =(+M97*$M$5+N97*$N$5+O97*$O$5+P97*$P$5)*E97 -> 0
C98: Consumibles | D98: gl | E98: 0.1 | F98: =+SUM(J96:J97) -> 760330.58 | J98: =+F98*E98 -> 76033.058 | K98: =+G98*E98 -> 0 | S98: =+L98*E98 -> 0 | T98: =(+M98*$M$5+N98*$N$5+O98*$O$5+P98*$P$5)*E98 -> 0
C99: M.Obra | D99: d | E99: 2 | J99: =+F99*E99 -> 0 | K99: =+G99*E99 -> 0 | M99: 1 | O99: 1 | S99: =+L99*E99 -> 0 | T99: =(+M99*$M$5+N99*$N$5+O99*$O$5+P99*$P$5)*E99 -> 259794.24
A100: =+'01'!A60 -> 7 | C100: =+'01'!C60 -> REVOQUES
A101: =+'01'!A65 -> 7.05 | B101: =+'01'!B65 -> R | C101: =+'01'!C65 -> Yeso interior | D101: =+'01'!D65 -> m2 | E101: =+'01'!E65 -> 2514.897 | H101: =+J101/E101 -> 0 | I101: =+K101/E101 -> 5135.3399 | J101: =SUM(J102:J105) -> 0 | K101: =SUM(K102:K105) -> 12914851 | Q101: =+U101/E101 -> 12817.952 | R101: =+V101/E101 -> 0 | U101: =SUM(S102:S105) -> 32235828 | V101: =SUM(T102:T105) -> 0
C102: Yeso Knauf MP 40/75 Proyectable x 25 kg - (17 kg/m2) | D102: bol | E102: =+ROUNDUP(E101*17/25*1.05,0) -> 1796 | G102: =+Cotizaciones!D53 -> 6694.38 | J102: =+F102*E102 -> 0 | K102: =+G102*E102 -> 12023106 | S102: =+L102*E102 -> 0 | T102: =(+M102*$M$5+N102*$N$5+O102*$O$5+P102*$P$5)*E102 -> 0
C103: PA-MAX PUENTE DE ADHERENCIA 20LT (150 m2/tac) - Contemplo el 20% de los m2 | D103: tac | E103: =+ROUND(E101/5/150*1.05,0) -> 4 | G103: =+Cotizaciones!D55 -> 124738 | J103: =+F103*E103 -> 0 | K103: =+G103*E103 -> 498952 | S103: =+L103*E103 -> 0 | T103: =(+M103*$M$5+N103*$N$5+O103*$O$5+P103*$P$5)*E103 -> 0
...

Sheet GGBB
H2: 45590 | O2: 22
F3: MESES | G3: DÓLAR BNA | H3: DÓLAR MEP | M3: Descrip | N3: Mes | O3: Total Dias
B4: GASTOS GENERALES y BENEFICIO | F4: 14 | G4: 1005 | H4: 1170 | M4: Prelim | N4: 0.75 | O4: =+N4*$O$2 -> 16.5 | Q4: Syh permanente
M5: Mov de suelos y excav. + micro | N5: 2.5 | O5: =+N5*$O$2 -> 55 | Q5: =+ROUNDUP(SUM(N4:N5),0) -> 4
B6: Gastos Grales de obra en items | C6: U | D6: Cant | F6: Precio Unit | G6: Subtotal | H6: =SUM(G7:G10) -> 0 | M6: Fundac | N6: 0 | O6: =+N6*$O$2 -> 0
B7: Oficina en obra (6x3 c/AA) | C7: mes | D7: =+$F$4 -> 14 | E7: 0 | F7: =E7*I7+J7 -> 0 | G7: =+F7*D7*E7 -> 0 | M7: Losa sobre PB | N7: 1 | O7: =+N7*$O$2 -> 22
B8: Obrador 6x3 s/AA | C8: mes | D8: =+$F$4 -> 14 | E8: 0 | F8: =E8*I8+J8 -> 0 | G8: =+F8*D8*E8 -> 0 | M8: Losa sobre 1 | N8: 1 | O8: =+N8*$O$2 -> 22
B9: Pañol (6x3) | C9: mes | D9: =+$F$4 -> 14 | E9: 1 | F9: =E9*I9+J9 -> 0 | G9: =+F9*D9*E9 -> 0 | M9: Losa sobre 2 | N9: 0.75 | O9: =+N9*$O$2 -> 16.5
B10: Baños | C10: mes | D10: =+$F$4 -> 14 | E10: 2 | F10: =E10*I10+J10 -> 0 | G10: =+F10*D10*E10 -> 0 | M10: Losa sobre 3 | N10: 0.75 | O10: =+N10*$O$2 -> 16.5 | P10: Inicio mamposteria
B11: Gastos Grales de obra en items | H11: =SUM(G12:G18) -> 16192179 | M11: Losa sobre 4 | N11: 0.75 | O11: =+N11*$O$2 -> 16.5 | Q11: Meses H° | R11: Estacionamiento en contramano
B12: HyS permanente | C12: mes | D12: 4 | E12: 1 | G12: =+F12*D12*E12 -> 0 | J12: =+'P.MO 09.24'!C9 -> 2578960.6 | K12: =+J12*D12*E12 -> 10315842 | M12: Techo escalera y sobrerecorrido | N12: 0.5 | O12: =+N12*$O$2 -> 11 | Q12: =+SUM(N4:N12) -> 8 | R12: =+Q12/2 -> 4
B13: HyS | C13: mes | D13: =+$F$4 -> 14 | E13: 1 | G13: =+F13*D13*E13 -> 0 | J13: 150000 | K13: =+J13*D13*E13 -> 2100000 | M13: Mampostería | N13: 2 | O13: =+N13*$O$2 -> 44
B14: Energía de obra | C14: mes | D14: =+F4 -> 14 | E14: 0.5 | F14: 200000 | G14: =+F14*D14*E14 -> 1400000 | I14: =+G14/$H$4 -> 1196.5812 | M14: Revoques, contrap y carp | N14: 2 | O14: =+N14*$O$2 -> 44 | P14: =+SUM(N13:N14) -> 4
B15: Agua de obra | C15: mes | D15: =+$F$4 -> 14 | E15: 1 | F15: 25000 | G15: =+F15*D15*E15 -> 350000 | M15: Amures | N15: 0 | O15: =+N15*$O$2 -> 0
B16: Alquiler cerco de obra chapa | C16: mes | D16: =+$F$4 -> 14 | E16: 0 | F16: 10000 | G16: =+F16*D16*E16 -> 0 | M16: Colocación | N16: 2 | O16: =+N16*$O$2 -> 44
B17: Proyecto Ejecutivo | C17: mes | D17: =+$F$4 -> 14 | E17: 0 | F17: =+'P.MO 09.24'!C9 -> 2578960.6 | G17: =+F17*D17*E17 -> 0 | M17: Pintura | N17: 2 | O17: =+N17*$O$2 -> 44
B18: Proyecto (50%) | C18: mes | D18: =+$F$4 -> 14 | E18: 0.4 | F18: =+'P.MO 09.24'!C9 -> 2578960.6 | G18: =+F18*D18*E18 -> 14442179 | I18: =+G18/$H$4 -> 12343.743 | M18: Terminaciones | N18: 0 | O18: =+L18*$O$2 -> 0
B19: Gastos Directos | H19: =SUM(G20:G30) -> 38913603 | N19: =SUM(N4:N18) -> 16 | O19: =SUM(O4:O18) -> 352
B20: Coordinacion de obra | C20: mes | D20: =+$F$4 -> 14 | E20: 0.15 | F20: =+'P.MO 09.24'!C11 -> 4680364.1 | G20: =+F20*D20*E20 -> 9828764.6 | I20: =+G20/$H$4 -> 8400.6535
B21: Jefe de obra | C21: mes | D21: =+$F$4 -> 14 | E21: 1 | G21: =+F21*D21*E21 -> 0 | J21: =+'P.MO 09.24'!C10 -> 3798370.6 | K21: =+J21*D21*E21 -> 53177188
B22: Sobrestante | C22: mes | D22: =+$F$4 -> 14 | E22: 0 | F22: =+'P.MO 09.24'!C9 -> 2578960.6 | G22: =+F22*D22*E22 -> 0
B23: Administrativo en obra | C23: mes | D23: =+$F$4 -> 14 | E23: 0 | F23: =+F22 -> 2578960.6 | G23: =+F23*D23*E23 -> 0
B24: Capataz | C24: mes | D24: =+$F$4 -> 14 | E24: 0.5 | F24: =+'P.MO 09.24'!C12 -> 3154977 | G24: =+F24*D24*E24 -> 22084839 | I24: =+G24/$H$4 -> 18875.931
B25: Logistica | C25: mes | D25: =+$F$4 -> 14 | E25: 0.5 | F25: 500000 | G25: =+F25*D25*E25 -> 3500000 | I25: =+G25/$H$4 -> 2991.453
B26: Vehiculo obra | C26: mes | D26: =+$F$4 -> 14 | E26: 0.5 | F26: =F25 -> 500000 | G26: =+F26*D26*E26 -> 3500000 | I26: =+G26/$H$4 -> 2991.453
B27: Mov y viaticos | C27: mes | D27: =+$F$4 -> 14 | E27: 1 | G27: =+F27*D27*E27 -> 0 | J27: =F25 -> 500000 | K27: =+J27*D27*E27 -> 7000000
B28: UOCRA | C28: mes | D28: =+$F$4 -> 14 | E28: 1 | G28: =+F28*D28*E28 -> 0
B29: Pañolero/Sereno | C29: mes | D29: =+$F$4 -> 14 | E29: 1 | J29: =+'P.MO 09.24'!C7 -> 1198421.7 | K29: =+J29*D29*E29 -> 16777904
B31: Equipos | H31: =SUM(G32:G40) -> 0
B32: Bobcat | C32: mes | D32: 0 | F32: 130000 | G32: =+F32*D32 -> 0
B33: Camion limpieza | C33: mes | D33: 0 | F33: 100000 | G33: =+F33*D33 -> 0
B34: Tijera electrica 12 | C34: mes | F34: 33600 | G34: =+F34*D34 -> 0
B35: JLG | C35: mes | F35: 89000 | G35: =+F35*D35 -> 0
B36: Grua 20ton | C36: mes | F36: 70000 | G36: =+F36*D36 -> 0
B41: Gastos Indirectos | H41: =SUM(G42:G47) -> 58713324
B42: Admin (50%Compras - 50%RRHH) | C42: mes | D42: =+$F$4 -> 14 | E42: 0.5 | F42: ='P.MO 09.24'!C9 -> 2578960.6 | G42: =+F42*D42*E42 -> 18052724 | I42: =+G42/$H$4 -> 15429.679
B43: Seguros | C43: gl | D43: =+D42 -> 14 | E43: 1 | F43: 250000 | G43: =+F43*D43 -> 3500000 | I43: =+G43/$H$4 -> 2991.453
B44: IIBB (monto venta obra gris) | C44: gl | D44: 0.04 | E44: 0.6 | F44: 1145000000 | G44: =+F44*D44*E44 -> 27480000 | I44: =+G44/$H$4 -> 23487.179
B45: Imp cheque | C45: gl | D45: =1.2/100 -> 0.012 | E45: =+E44 -> 0.6 | F45: =+F44*1.15 -> 1316750000 | G45: =+F45*D45*E45 -> 9480600 | I45: =+G45/$H$4 -> 8103.0769
B46: Contrato | C46: gl | D46: 1 | E46: 1 | F46: 200000 | G46: =+F46*D46*E46 -> 200000 | I46: =+G46/$H$4 -> 170.94017
G48: =SUM(G7:G47) -> 1.1381911e+08 | H48: =SUM(H6:H47) -> 1.1381911e+08 | I48: =SUM(I6:I47) -> 96982.142 | K48: =SUM(K6:K47) -> 89370934 | L48: =+K48+G64 -> 3.1980562e+08 | M48: =+L48/N19 -> 19987851
B49: Monto puesto en Ayuda de gremio que no se eroga
B50: Total de Gastos Generales | G50: =+G49+H48 -> 1.1381911e+08
B52: Otro | G52: =+'01'!N216 -> 1.5263579e+08 | I52: =+G52/$H$4 -> 130457.94
B53: Corralon | G53: =+'01'!O216 -> 89943825 | I53: =+G53/$H$4 -> 76875.064
B54: Subcontratos | G54: =+'01'!P216 -> 4.6615773e+08 | I54: =+G54/$H$4 -> 398425.41
B55: Mano de obra | G55: =+'01'!Q216 -> 1.677708e+08 | I55: =+G55/$H$4 -> 143393.85
B56: Equipos | G56: =+'01'!R216 -> 20534738 | I56: =+G56/$H$4 -> 17551.058
A58: A | G58: =SUM(G52:G57) -> 8.9704289e+08 | I58: =SUM(I52:I57) -> 766703.32
B60: GG | F60: =+G50/G58 -> 0.12688257 | G60: =+F60*$G$58 -> 1.1381911e+08 | I60: =+G60/$H$4 -> 97281.288
B61: Equipos | E61: 3 | F61: 0 | G61: =+F61*$G$58 -> 0 | I61: =+G61/$H$4 -> 0
B62: Imprevistos + Negciacion | E62: 5 | F62: 0.03 | G62: =+F62*$G$58 -> 26911287 | I62: =+G62/$H$4 -> 23001.1 | L62: 987276976
B63: Beneficio | E63: 9 | F63: 0.1 | G63: =+F63*$G$58 -> 89704289 | I63: =+G63/$H$4 -> 76670.332 | L63: =+'01'!Y216 -> 1.1274028e+09
A64: B | F64: =SUM(F60:F63) -> 0.25688257 | G64: =SUM(G60:G63) -> 2.3043468e+08 | I64: =+G64/$H$4 -> 196952.72 | L64: =+L63-L62 -> 1.4012578e+08
A66: K | F66: =1+F64 -> 1.2568826 | G66: =+G58*F66 -> 1.1274776e+09
L67: 1.1381953e+09
A68: A+B | G68: =+G58+G64 -> 1.1274776e+09 | I68: =+G68/$H$4 -> 963656.04
F70: =+G71/G58 -> 0.033443217
F71: =+G71/G66 -> 0.026608068 | G71: 30000000
I72: =+I63+I62+I20 -> 108072.09

Sheet Locales
J2: H Promedio | N2: CARPETAS / CONTRAPISOS | AA2: AISLACIONES | AF2: CIELORRASOS | AP2: CARPINTERIAS | BI2: PISOS (m2) | BQ2: ZOCALOS (ml) | CE2: ELECTRICIDAD | CW2: ART SANITARIO | DB2: GRIFERIAS
J3: H a revisar | U3: REVOQUES | AP3: Puertas | AX3: Ventanas | BV3: REV | BX3: PAREDES | CA3: CIELORRASO | CE3: ARTEFACTOS ILUM | CJ3: BOCAS
J4: Revisar | N4: A2 | O4: A3 | Q4: A3 | R4: A4 | S4: A5 | U4: R1 | V4: C | W4: C | X4: R2 | Y4: R5 | AA4: A1 | AD4: A2 | AF4: C1 | AG4: C2 | AH4: C3 | AI4: C4 | AK4: C5 | AL4: C6 | AM4: C7 | AN4: C8 | AP4: P1 | AQ4: P2 | AS4: P3 | AT4: P4 | AV4: P5 | AW4: P5 | AX4: V1 | AY4: V2 | AZ4: V3 | BA4: V4 | BB4: V5 | BC4: V6 | BD4: V7 | BE4: V8 | BF4: V9 | BG4: V10 | BI4: P1 | BJ4: P2 | BK4: P3 | BL4: P4 | BM4: P5 | BN4: P6 | BO4: P7 | BP4: P8 | BQ4: Z1 | BR4: Z2 | BS4: Z3 | BT4: Z4 | BV4: PI3 | BW4: PI4 | BX4: PI1 | BZ4: PI2 | CA4: PCI1 | CB4: PCI2 | CE4: AE1 | CF4: AE2 | CG4: AE3 | CH4: AE4 | CI4: AE5 | CJ4: IL1 | CK4: IL2 | CL4: IL3 | CM4: IL4 | CN4: IL5 | CO4: IL6 | CP4: IL7 | CQ4: IL8 | CR4: IL9 | CS4: IL10 | CT4: IL11 | CU4: IL12
J5: Revisado | N5: MC | O5: MC | Q5: MC | R5: MC | S5: MC | U5: MC | V5: MC | W5: MC | X5: MC | Y5: MC | AA5: MC | AD5: MC | AP5: MC | AQ5: MC | AS5: MC | AT5: MC | AV5: MC | AW5: MC | AX5: MC | AY5: MC | AZ5: MC | BA5: MC | BB5: MC | BC5: MC | BD5: MC | BE5: MC | BF5: MC | BG5: MC | BQ5: MC | BR5: MC | BT5: MC | BV5: MC | BW5: MC | BX5: MC | BZ5: MC | CA5: MC | CB5: MC | CG5: MC | CH5: MC | CI5: MC | CJ5: MC | CL5: MC | CN5: MC | CO5: MC | CP5: MC | CR5: MC | CT5: MC | CU5: MC | CW5: MC | CX5: MC | CY5: MC | DA5: MC | DB5: MC | DC5: MC | DD5: MC | DE5: MC | DF5: MC
C6: EL SALVADOR 4140 | N6: Monolitico e: 6,00 cm | O6: Contrapiso c/ pend. s/azotea | P6: Contrapiso s/ suelo nat | Q6: Contrapiso s/ Platea | R6: Carpeta | S6: Carpeta s/ membrana | U6: Yeso | V6: Aristas | W6: Cantoneras | X6: Bajo revestimiento | Y6: Revoque Grueso y Fino a la cal | AA6: Aislacion Horizontal en Baños | AB6: Aislaciòn sobre contrapiso | AC6: Aislaciòn termica EPS | AD6: Membrana geotextil - Balcones y azotea | AF6: Suspendido placa STD | AG6: Suspendido placa RH | AH6: Buña "Z" Durlock | AI6: Cajòn durlock | AJ6: Garganta | AK6: Yeso aplicado | AL6: Buña | AM6: Arista | AN6: Hormigon visto / Maquillaje | AP6: Puerta placa F30 de 90cm ancho | AQ6: Puerta placa MDF | AR6: Puerta de chapa | AS6: Puerta de chapa F60 | AT6: Puerta de chapa F60 para gabinetes de medidores de gas y luz | AU6: Frente ascensor | AV6: Frente de Baulera | AW6: Frentes de Placard | AX6: Ventana de aluminio anodizado 2,60m | AY6: Ventana de aluminio anodizado 2m | AZ6: Ventana de aluminio anodizado 2,80m | BA6: Ventana de aluminio anodizado 2,10m | BB6: Ventana de aluminio anodizado 2,50m | BC6: Ventana de aluminio anodizado 1,40m | BD6: Ventana de aluminio anodizado 0,50m | BE6: Ventana de aluminio anodizado 0,60m | BF6: Ventana de aluminio anodizado 2,85m | BG6: Ventana de aluminio anodizado 2,25m | BI6: Pavimento | BJ6: Travertino Hall | BK6: Porcelanato en UF | BL6: Porcelanato en baños | BM6: Porcelanato en espacio comun | BN6: Alisado de cemento rodillado | BO6: Sustrato | BP6: Baldosones | BQ6: Madera | BR6: Travertino | BS6: Porcelanato | BT6: Zocalo de material h: 10 cm | BV6: Revestimiento cocina | BW6: Revestimiento baño | BX6: Latex interior blanco s/ enduido | BY6: Latex interior blanco enduido parcial | BZ6: Latex interior blanco enduido completo | CA6: Latex cielorraso blanco s/enduido | CB6: Latex cielorraso blanco enduido parcial | CC6: Latex cielorraso blanco enduido completo | CE6: Extractor | CF6: Fotocelula | CG6: Sensor de movimiento | CH6: Toma de emergencia | CI6: Artefacto en espacio comun y balcon | CJ6: Boca ilum | CK6: Caja para led | CL6: Tecla | CM6: Pulsador timbre | CN6: Tomas simple | CO6: Toma doble | CP6: Toma A/A | CQ6: Termostato | CR6: Boca TV | CS6: Portero elecrico | CT6: Boca cctv | CU6: Tablero TSBT | CW6: Indoro Roca monaco | CX6: Bidet Roca monaco | CY6: Bacha de apoyar roca | CZ6: Bañadera Roca | DA6: Pileta de cocina | DB6: Accesorios de Baño FV alerce o similar | DC6: Griferia de lavarotio FV alerce o similar | DD6: Griferia de bidet 3 agujeros con tapita FV alerce o similar | DE6: Griferia de ducha FV alerce o similar | DF6: Griferia de cocina FV alerce o similar
A7: PLANTA | B7: Nº | C7: LOCAL | D7: Largo | E7: Ancho | F7: SUP | G7: perim unit | H7: vacio | I7: perim real | J7: H | K7: H r | L7: aux | N7: m2 | O7: m2 | P7: m2 | Q7: m2 | R7: m2 | S7: m2 | U7: m2 | V7: ml | W7: u | X7: m2 | Y7: m2 | AA7: m2 | AB7: m2 | AC7: m2 | AD7: m2 | AF7: m2 | AG7: m2 | AH7: ml | AI7: ml | AJ7: ml | AK7: m2 | AL7: ml | AM7: ml | AN7: m2 | AP7: u | AQ7: u | AR7: u | AS7: u | AT7: u | AU7: u | AV7: u | AW7: u | AX7: u | AY7: u | AZ7: u | BA7: u | BB7: u | BC7: u | BD7: u | BE7: u | BF7: u | BG7: u | BI7: m2 | BJ7: m2 | BK7: m2 | BM7: m2 | BN7: m2 | BP7: m2 | BQ7: ml | BR7: ml | BS7: ml | BT7: ml | BV7: m2 | BW7: m2 | BX7: m2 | BY7: m2 | BZ7: m2 | CA7: m2 | CB7: m2 | CC7: m2 | CH7: un | CI7: un | CJ7: un | CL7: un | CW7: un | CX7: un | CY7: un | CZ7: un | DA7: un | DB7: un | DC7: un | DD7: un | DE7: un | DF7: un
A8: Subsuelo | B8: 1 | C8: Cocheras | D8: 0 | E8: 0 | F8: 172.88 | G8: 63.68 | H8: =1.57+3.3 -> 4.87 | I8: =+G8-H8 -> 58.81 | J8: 2.93 | Y8: =$I8*$J8 -> 172.3133 | AN8: =+F8 -> 172.88 | BI8: =$F8 -> 172.88 | BX8: =+I8*J8 -> 172.3133 | CA8: =+F8 -> 172.88 | CG8: 3 | CH8: 5 | CI8: =+CJ8 -> 6 | CJ8: 6 | CN8: 1 | CT8: 1
B9: 2 | C9: Pallier | D9: 0 | E9: 0 | F9: 9.08 | G9: 16.07 | H9: =4.4+1.6 -> 6 | I9: =+G9-H9 -> 10.07 | J9: 2.93 | Q9: =$F9 -> 9.08 | Y9: =$I9*$J9 -> 29.5051 | AN9: =+F9 -> 9.08 | AU9: 1 | BN9: =$F9 -> 9.08 | BX9: =$I9*$J9 -> 29.5051 | CA9: =+F9 -> 9.08 | CG9: 1 | CH9: 1 | CI9: =+CJ9 -> 2 | CJ9: 2
B10: 3 | C10: Pasillo Baulera | D10: 0 | E10: 0 | F10: 32.65 | G10: 42.31 | H10: =+SUM(H11:H20)+1.26 -> 16.44 | I10: =+G10-H10 -> 25.87 | J10: 2.93 | Q10: =$F10 -> 32.65 | Y10: =$I10*$J10 -> 75.7991 | AN10: =+F10 -> 32.65 | BN10: =$F10 -> 32.65 | BX10: =$I10*$J10 -> 75.7991 | CA10: =+F10 -> 32.65 | CG10: 3 | CH10: 2 | CI10: =+CJ10 -> 7 | CJ10: 7 | CN10: 2
B11: 4 | C11: Baulera 1 | D11: 2.19 | E11: 1.41 | F11: =D11*E11 -> 3.0879 | G11: =+D11*2+E11*2 -> 7.2 | H11: 1.41 | I11: =+G11-H11 -> 5.79 | J11: 2.93 | Q11: =$F11 -> 3.0879 | Y11: =$I11*$J11 -> 16.9647 | AN11: =+F11 -> 3.0879 | AV11: 1 | BN11: =$F11 -> 3.0879 | BX11: =$I11*$J11 -> 16.9647 | CA11: =+F11 -> 3.0879
B12: 5 | C12: Baulera 2 | D12: 2.19 | E12: 1.41 | F12: =D12*E12 -> 3.0879 | G12: =+D12*2+E12*2 -> 7.2 | H12: 1.41 | I12: =+G12-H12 -> 5.79 | J12: 2.93 | Q12: =$F12 -> 3.0879 | Y12: =$I12*$J12 -> 16.9647 | AN12: =+F12 -> 3.0879 | AV12: 1 | BN12: =$F12 -> 3.0879 | BX12: =$I12*$J12 -> 16.9647 | CA12: =+F12 -> 3.0879
B13: 6 | C13: Baulera 3 | D13: 2.19 | E13: 1.41 | F13: =D13*E13 -> 3.0879 | G13: =+D13*2+E13*2 -> 7.2 | H13: 1.41 | I13: =+G13-H13 -> 5.79 | J13: 2.93 | Q13: =$F13 -> 3.0879 | Y13: =$I13*$J13 -> 16.9647 | AN13: =+F13 -> 3.0879 | AV13: 1 | BN13: =$F13 -> 3.0879 | BX13: =$I13*$J13 -> 16.9647 | CA13: =+F13 -> 3.0879
B14: 7 | C14: Baulera 4 | D14: 1.95 | E14: 1.59 | F14: =D14*E14 -> 3.1005 | G14: =+D14*2+E14*2 -> 7.08 | H14: 1.59 | I14: =+G14-H14 -> 5.49 | J14: 2.93 | Q14: =$F14 -> 3.1005 | Y14: =$I14*$J14 -> 16.0857 | AN14: =+F14 -> 3.1005 | AV14: 1 | BN14: =$F14 -> 3.1005 | BX14: =$I14*$J14 -> 16.0857 | CA14: =+F14 -> 3.1005
B15: 8 | C15: Baulera 5 | D15: 1.95 | E15: 1.59 | F15: =D15*E15 -> 3.1005 | G15: =+D15*2+E15*2 -> 7.08 | H15: 1.59 | I15: =+G15-H15 -> 5.49 | J15: 2.93 | Q15: =$F15 -> 3.1005 | Y15: =$I15*$J15 -> 16.0857 | AN15: =+F15 -> 3.1005 | AV15: 1 | BN15: =$F15 -> 3.1005 | BX15: =$I15*$J15 -> 16.0857 | CA15: =+F15 -> 3.1005
B16: 9 | C16: Baulera 6 | D16: 1.95 | E16: 1.59 | F16: =D16*E16 -> 3.1005 | G16: =+D16*2+E16*2 -> 7.08 | H16: 1.59 | I16: =+G16-H16 -> 5.49 | J16: 2.93 | Q16: =$F16 -> 3.1005 | Y16: =$I16*$J16 -> 16.0857 | AN16: =+F16 -> 3.1005 | AV16: 1 | BN16: =$F16 -> 3.1005 | BX16: =$I16*$J16 -> 16.0857 | CA16: =+F16 -> 3.1005
B17: 10 | C17: Baulera 7 | D17: 1.95 | E17: 1.59 | F17: =D17*E17 -> 3.1005 | G17: =+D17*2+E17*2 -> 7.08 | H17: 1.95 | I17: =+G17-H17 -> 5.13 | J17: 2.93 | Q17: =$F17 -> 3.1005 | Y17: =$I17*$J17 -> 15.0309 | AN17: =+F17 -> 3.1005 | AV17: 1 | BN17: =$F17 -> 3.1005 | BX17: =$I17*$J17 -> 15.0309 | CA17: =+F17 -> 3.1005
B18: 11 | C18: Baulera 8 | D18: 2.19 | E18: 1.41 | F18: =D18*E18 -> 3.0879 | G18: =+D18*2+E18*2 -> 7.2 | H18: 1.41 | I18: =+G18-H18 -> 5.79 | J18: 2.93 | Q18: =$F18 -> 3.0879 | Y18: =$I18*$J18 -> 16.9647 | AN18: =+F18 -> 3.0879 | AV18: 1 | BN18: =$F18 -> 3.0879 | BX18: =$I18*$J18 -> 16.9647 | CA18: =+F18 -> 3.0879
B19: 12 | C19: Baulera 9 | D19: 2.19 | E19: 1.41 | F19: =D19*E19 -> 3.0879 | G19: =+D19*2+E19*2 -> 7.2 | H19: 1.41 | I19: =+G19-H19 -> 5.79 | J19: 2.93 | Q19: =$F19 -> 3.0879 | Y19: =$I19*$J19 -> 16.9647 | AN19: =+F19 -> 3.0879 | AV19: 1 | BN19: =$F19 -> 3.0879 | BX19: =$I19*$J19 -> 16.9647 | CA19: =+F19 -> 3.0879
B20: 13 | C20: Baulera 10 | D20: 2.19 | E20: 1.41 | F20: =D20*E20 -> 3.0879 | G20: =+D20*2+E20*2 -> 7.2 | H20: 1.41 | I20: =+G20-H20 -> 5.79 | J20: 2.93 | Q20: =$F20 -> 3.0879 | Y20: =$I20*$J20 -> 16.9647 | AN20: =+F20 -> 3.0879 | AV20: 1 | BN20: =$F20 -> 3.0879 | BX20: =$I20*$J20 -> 16.9647 | CA20: =+F20 -> 3.0879
B21: 14 | C21: Auxiliar | D21: 0 | E21: 0 | F21: 9.74 | G21: 14.47 | H21: 0 | I21: =+G21-H21 -> 14.47 | J21: 2.93 | Q21: =$F21 -> 9.74 | Y21: =$I21*$J21 -> 42.3971 | AN21: =+F21 -> 9.74 | AR21: 1 | BM21: =+F21 -> 9.74 | BX21: =$I21*$J21 -> 42.3971 | CA21: =+F21 -> 9.74 | CI21: =+CJ21 -> 2 | CJ21: 2 | CL21: 1 | CO21: 1 | CR21: 1 | CS21: 1 | CT21: 1
B22: 15 | C22: Camara Transformadora | D22: 5 | E22: 3.65 | F22: =D22*E22 -> 18.25 | G22: 17.3 | H22: 0 | I22: =+G22-H22 -> 17.3 | J22: 2.93 | Q22: =$F22 -> 18.25 | Y22: =$I22*$J22 -> 50.689 | AN22: =+F22 -> 18.25 | BN22: =$F22 -> 18.25 | BX22: =$I22*$J22 -> 50.689 | CA22: =+F22 -> 18.25
B23: 16 | C23: Baño | D23: 1.2 | E23: 2.18 | F23: =D23*E23 -> 2.616 | G23: 6.76 | H23: 0 | I23: =+G23-H23 -> 6.76 | J23: 2.2 | K23: 2.2 | Q23: =$F23 -> 2.616 | R23: =$F23 -> 2.616 | X23: =+I23*K23 -> 14.872 | AN23: =+F23 -> 2.616 | AQ23: 1 | BL23: =+F23 -> 2.616 | BW23: =+I23*K23 -> 14.872 | CC23: =+F23 -> 2.616 | CI23: 1 | CJ23: 1 | CL23: 1 | CN23: 1 | CW23: 1 | CY23: 1 | DB23: 1 | DC23: 1
C24: SALA BOMBEO | F24: 7.7 | G24: 14.85 | H24: 3.08 | I24: =+G24-H24 -> 11.77 | J24: 2.93 | Y24: =$I24*$J24 -> 34.4861 | AN24: =+F24 -> 7.7 | BN24: =+F24 -> 7.7 | BX24: =$I24*$J24 -> 34.4861 | CA24: =+F24 -> 7.7 | CH24: 1 | CJ24: 2 | CL24: 1
C25: ESCALERA | F25: 9 | G25: 13.74 | H25: =1.25+1.55 -> 2.8 | I25: =+G25-H25 -> 10.94 | J25: 2.93 | Y25: =$I25*$J25 -> 32.0542 | AN25: =+F25 -> 9 | BT25: =+I25 -> 10.94 | BX25: =$I25*$J25 -> 32.0542 | CA25: =+F25 -> 9 | CG25: 1 | CH25: 1 | CI25: 2 | CJ25: 2
A26: PB | C26: Vereda | D26: 3 | E26: 10 | F26: =D26*E26 -> 30 | G26: =+D26*2+E26*2 -> 26 | H26: =+G26 -> 26 | I26: =+G26-H26 -> 0 | J26: 3.2 | P26: =$F26 -> 30 | AB26: =+F26 -> 30 | AG26: =1.3*9.14 -> 11.882 | AH26: =1.3*2+9.14*2 -> 20.88 | BP26: =+F26 -> 30 | CC26: =+AG26 -> 11.882 | CI26: 3 | CJ26: 3 | CT26: 1
C27: Acceso cocheras | D27: 3.1 | E27: 3.3 | F27: =D27*E27 -> 10.23 | G27: =+D27*2+E27*2 -> 12.8 | H27: =2.85*2 -> 5.7 | I27: =+G27-H27 -> 7.1 | J27: 3.2 | P27: =$F27 -> 10.23 | AB27: =+F27 -> 10.23 | AN27: =+F27 -> 10.23 | BP27: =+F27 -> 10.23 | CA27: =+F27 -> 10.23 | CG27: 1 | CI27: 1 | CJ27: 1 | CT27: 2
B28: 17 | C28: Rampa | D28: 0 | E28: 0 | F28: 52.38 | G28: 39.01 | H28: =2.85*2 -> 5.7 | I28: =+G28-H28 -> 33.31 | J28: =AVERAGE(3,6) -> 4.5 | Y28: =$I28*$J28 -> 149.895 | AN28: =8.52*3.3 -> 28.116 | AT28: 1 | BI28: =+F28 -> 52.38 | BT28: =$G28 -> 39.01 | BX28: =+I28*J28 -> 149.895 | CA28: =8.52*3.3 -> 28.116 | CG28: 1 | CH28: =+CJ28 -> 5 | CJ28: 5
B29: 18 | C29: Entrada | D29: 2.3 | E29: 3 | F29: =D29*E29 -> 6.9 | G29: 11.17 | H29: =(2.05*2) -> 4.1 | I29: =+G29-H29 -> 7.07 | J29: 3.2 | P29: =$F29 -> 6.9 | AB29: =+F29 -> 6.9 | AG29: =+F29 -> 6.9 | AH29: =+G29 -> 11.17 | AT29: 1 | BP29: =+F29 -> 6.9 | CC29: =+F29 -> 6.9 | CI29: 4 | CJ29: 4 | CT29: 2
B30: 19 | C30: Hall ingreso | D30: 0 | E30: 0 | F30: 29.36 | G30: 39.38 | H30: =2.05+1.2 -> 3.25 | I30: =+G30-H30 -> 36.13 | J30: 3.2 | N30: =+F30 -> 29.36 | U30: =$I30*$J30 -> 115.616 | V30: =+W30*J30 -> 22.4 | W30: 7 | AF30: =+F30 -> 29.36 | AH30: =+G30 -> 39.38 | AS30: 1 | AU30: 1 | BJ30: =$F30 -> 29.36 | BR30: =$I30 -> 36.13 | BY30: =+I30*J30 -> 115.616 | CC30: =+F30 -> 29.36 | CG30: 2 | CH30: 2 | CI30: 9 | CJ30: 9 | CK30: 3 | CM30: 1 | CO30: 1 | CT30: 1
C31: ESCALERA | F31: 9 | G31: 13.74 | H31: =1.25+1.55 -> 2.8 | I31: =+G31-H31 -> 10.94 | J31: 3.2 | V31: =+W31*J31 -> 3.2 | W31: 1 | Y31: =+I31*J31 -> 35.008 | AN31: =+F31 -> 9 | BT31: =+I31 -> 10.94 | BY31: =+I31*J31 -> 35.008 | CA31: =+F31 -> 9
B32: 20 | C32: Local Comercial | D32: 10.79 | E32: 3.74 | F32: =D32*E32 -> 40.3546 | G32: 25.05 | H32: 3.54 | I32: =+G32-H32 -> 21.51 | J32: 3.2 | N32: =+F32 -> 40.3546 | U32: =$I32*$J32 -> 68.832 | AF32: =+F32 -> 40.3546 | AH32: =+G32 -> 25.05 | BT32: =$I32 -> 21.51 | BY32: =+I32*J32 -> 68.832 | CC32: =+F32 -> 40.3546 | CJ32: 10 | CL32: 1 | CO32: 9 | CR32: 1 | CT32: 3
B33: 21 | C33: Baño Comercial | D33: 2.94 | E33: 1.52 | F33: =D33*E33 -> 4.4688 | G33: 8.92 | H33: 0 | I33: =+G33-H33 -> 8.92 | J33: 3.2 | K33: 3.2 | R33: =+F33 -> 4.4688 | S33: =+F33 -> 4.4688 | X33: =$I33*$J33 -> 28.544 | AN33: =+F33 -> 4.4688 | AQ33: 1 | BL33: =$F33 -> 4.4688 | BT33: =$I33 -> 8.92 | BW33: =+I33*K33 -> 28.544 | CC33: =+$F33 -> 4.4688 | CJ33: 2 | CL33: 1 | CN33: 1 | CW33: 2 | CY33: 1 | DC33: 1
B34: 22 | C34: Hall Dto. PB | D34: 0 | E34: 0 | F34: 7.06 | G34: 15.39 | H34: =1.2+3.6+2.25 -> 7.05 | I34: =+G34-H34 -> 8.34 | J34: 2.4 | N34: =+F34 -> 7.06 | U34: =$I34*$J34 -> 20.016 | V34: =+W34*J34 -> 4.8 | W34: 2 | AF34: =$F34 -> 7.06 | AH34: =$G34 -> 15.39 | AP34: 1 | BK34: =+F34 -> 7.06 | BQ34: =+I34 -> 8.34 | BY34: =+I34*J34 -> 20.016 | CC34: =+$F34 -> 7.06 | CJ34: 1 | CL34: 1 | CO34: 1 | CP34: 1 | CQ34: 1 | CS34: 1
B35: 23 | C35: Cocina Dto. PB | D35: 0 | E35: 0 | F35: 11.79 | G35: 16.19 | H35: =2.28+1.2 -> 3.48 | I35: =+G35-H35 -> 12.71 | J35: 2.4 | K35: 0.6 | L35: =5.25+3.6 -> 8.85 | N35: =+F35 -> 11.79 | U35: =+I35*J35-X35 -> 9.264 | V35: =+W35*J35 -> 14.4 | W35: 6 | X35: =+L35*J35 -> 21.24 | AF35: =$F35 -> 11.79 | AH35: =$G35 -> 16.19 | AI35: 3.6 | BK35: =+F35 -> 11.79 | BQ35: =+I35 -> 12.71 | BV35: =+K35*L35 -> 5.31 | BY35: =+I35*J35-BV35 -> 25.194 | CC35: =+$F35 -> 11.79 | CJ35: 8 | CK35: 2 | CL35: 2 | CN35: 1 | CO35: 8 | DA35: 1 | DF35: 1
B36: 24 | C36: Lavadero Dto. PB | D36: 2.94 | E36: 1.5 | F36: =D36*E36 -> 4.41 | G36: 9.15 | I36: =+G36-H36 -> 9.15 | J36: 2.4 | K36: 0.6 | L36: =2.7+2.3 -> 5 | N36: =+F36 -> 4.41 | U36: =+I36*J36-X36 -> 9.96 | V36: =+W36*J36 -> 2.4 | W36: 1 | X36: =+L36*J36 -> 12 | AF36: =$F36 -> 4.41 | AH36: =$G36 -> 9.15 | BC36: 1 | BK36: =+F36 -> 4.41 | BQ36: =+I36 -> 9.15 | BV36: =+K36*L36 -> 3 | BY36: =+I36*J36-BV36 -> 18.96 | CC36: =+$F36 -> 4.41 | CJ36: 1 | CL36: 1 | CN36: 2 | CO36: 2
B37: 25 | C37: living Dto. PB | D37: 6.12 | E37: 3.59 | F37: =D37*E37 -> 21.9708 | G37: 19.41 | H37: =3.59 -> 3.59 | I37: =+G37-H37 -> 15.82 | J37: 3 | N37: =+F37 -> 21.9708 | U37: =$I37*$J37 -> 47.46 | V37: =+W37*J37 -> 6 | W37: 2 | AK37: =$F37 -> 21.9708 | AL37: =+G37 -> 19.41 | AX37: 1 | BK37: =+F37 -> 21.9708 | BQ37: =+I37 -> 15.82 | BY37: =+I37*J37 -> 47.46 | CB37: =+$F37 -> 21.9708 | CJ37: 4 | CL37: 2 | CO37: 5 | CR37: 3
B38: 26 | C38: Toillette Dto. PB | D38: 1.17 | E38: 2.43 | F38: =D38*E38 -> 2.8431 | G38: 7.19 | I38: =+G38-H38 -> 7.19 | J38: 2.2 | K38: 2.2 | R38: =+F38 -> 2.8431 | S38: =+F38 -> 2.8431 | X38: =+I38*K38 -> 15.818 | AA38: =+F38 -> 2.8431 | AF38: =$F38 -> 2.8431 | AH38: =+G38 -> 7.19 | AQ38: 1 | BL38: =+F38 -> 2.8431 | BW38: =+I38*K38 -> 15.818 | CC38: =+$F38 -> 2.8431 | CE38: 1 | CJ38: 2 | CL38: 1 | CN38: 1 | CW38: 1 | CY38: 1 | DB38: 1 | DC38: 1
B39: 27 | C39: Paso Dorm Dto. PB | D39: 0 | E39: 0 | F39: 7.85 | G39: 17.63 | I39: =+G39-H39 -> 17.63 | J39: 2.4 | N39: =+F39 -> 7.85 | U39: =$I39*$J39 -> 42.312 | V39: =+W39*J39 -> 9.6 | W39: 4 | AF39: =$F39 -> 7.85 | AH39: =+G39 -> 17.63 | AQ39: 1 | BK39: =+F39 -> 7.85 | BQ39: =+I39 -> 17.63 | BY39: =+I39*J39 -> 42.312 | CC39: =+$F39 -> 7.85 | CJ39: 4 | CL39: 2 | CO39: 2
B40: 28 | C40: Placard Paso Dorm Dto. PB | D40: 1.18 | E40: 0.6 | F40: =D40*E40 -> 0.708 | G40: 3.56 | I40: =+G40-H40 -> 3.56 | J40: 3 | N40: =+F40 -> 0.708 | U40: =$I40*$J40 -> 10.68 | AK40: =$F40 -> 0.708 | AW40: 1 | BK40: =+F40 -> 0.708 | BY40: =+I40*J40 -> 10.68 | CB40: =+$F40 -> 0.708
B41: 29 | C41: Dorm 1 Dto. PB | D41: 2.48 | E41: 3.41 | F41: =D41*E41 -> 8.4568 | G41: 11.78 | I41: =+G41-H41 -> 11.78 | J41: 3 | N41: =+F41 -> 8.4568 | U41: =$I41*$J41 -> 35.34 | V41: =+W41*J41 -> 3 | W41: 1 | AK41: =$F41 -> 8.4568 | AL41: =$G41 -> 11.78 | AQ41: 1 | BA41: 1 | BK41: =+F41 -> 8.4568 | BQ41: =+I41 -> 11.78 | BY41: =+I41*J41 -> 35.34 | CB41: =+$F41 -> 8.4568 | CJ41: 1 | CL41: 2 | CO41: 3 | CP41: 1 | CR41: 1
B42: 30 | C42: Placard Dorm 1 Dto. PB | D42: 0.6 | E42: 1.7 | F42: =D42*E42 -> 1.02 | G42: 4.6 | I42: =+G42-H42 -> 4.6 | J42: 3 | N42: =+F42 -> 1.02 | U42: =$I42*$J42 -> 13.8 | AK42: =$F42 -> 1.02 | AW42: 1 | BK42: =+F42 -> 1.02 | BY42: =+I42*J42 -> 13.8 | CB42: =+$F42 -> 1.02
B43: 31 | C43: Balcon Dto. PB | D43: 0 | E43: 0 | F43: 8.91 | G43: 12.42 | H43: 3.96 | I43: =+G43-H43 -> 8.46 | J43: 3 | R43: =+F43 -> 8.91 | S43: =+F43 -> 8.91 | AD43: =+F43 -> 8.91 | BK43: =+F43 -> 8.91 | BQ43: =+I43 -> 8.46 | CI43: 4 | CJ43: 4
B44: 32 | C44: Baño Dto. PB | D44: 0 | E44: 0 | F44: 4.28 | G44: 9.08 | I44: =+G44-H44 -> 9.08 | J44: 2.2 | K44: 2.2 | R44: =+F44 -> 4.28 | S44: =+F44 -> 4.28 | X44: =+I44*J44 -> 19.976 | AA44: =+F44 -> 4.28 | AG44: =$F44 -> 4.28 | AH44: =$G44 -> 9.08 | AQ44: 1 | BL44: =+F44 -> 4.28 | BW44: =$I44*$K44 -> 19.976 | CC44: =+$F44 -> 4.28 | CE44: 1 | CJ44: 2 | CL44: 1 | CN44: 1 | CW44: 1 | CX44: 1 | CY44: 1 | CZ44: 1 | DB44: 1 | DC44: 1 | DD44: 1 | DE44: 1
B45: 33 | C45: Dorm 2 Dto. PB | D45: 3.3 | E45: 3.04 | F45: =D45*E45 -> 10.032 | G45: =+D45*2+E45*2 -> 12.68 | I45: =+G45-H45 -> 12.68 | J45: 3 | N45: =+F45 -> 10.032 | U45: =$I45*$J45 -> 38.04 | V45: =+W45*J45 -> 3 | W45: 1 | AK45: =$F45 -> 10.032 | AL45: =$G45 -> 12.68 | AQ45: 1 | BF45: 1 | BK45: =+F45 -> 10.032 | BQ45: =+I45 -> 12.68 | BY45: =+I45*J45 -> 38.04 | CB45: =+$F45 -> 10.032 | CJ45: 1 | CL45: 2 | CO45: 3 | CP45: 1 | CR45: 1
B46: 34 | C46: Placard Dorm 2 Dto. PB | D46: 0.6 | E46: 1.96 | F46: =D46*E46 -> 1.176 | G46: =+D46*2+E46*2 -> 5.12 | H46: 1.96 | I46: =+G46-H46 -> 3.16 | J46: 3 | N46: =+F46 -> 1.176 | U46: =$I46*$J46 -> 9.48 | AK46: =$F46 -> 1.176 | AW46: 1 | BK46: =+F46 -> 1.176 | BY46: =+I46*J46 -> 9.48 | CB46: =+$F46 -> 1.176
B47: 30 | C47: Dorm Principal Dto. PB | D47: 3.3 | E47: 2.81 | F47: =D47*E47 -> 9.273 | G47: =+D47*2+E47*2 -> 12.22 | H47: 2.26 | I47: =+G47-H47 -> 9.96 | J47: 3 | N47: =+F47 -> 9.273 | U47: =$I47*$J47 -> 29.88 | V47: =+W47*J47 -> 6 | W47: 2 | AK47: =$F47 -> 9.273 | AL47: =$G47 -> 12.22 | AQ47: 1 | BG47: 1 | BK47: =+F47 -> 9.273 | BQ47: =+I47 -> 9.96 | BY47: =+I47*J47 -> 29.88 | CB47: =+$F47 -> 9.273 | CJ47: 1 | CL47: 3 | CO47: 3 | CP47: 1 | CR47: 1
B48: 32 | C48: Placard Dorm Principal Dto. PB | D48: 1.58 | E48: 0.46 | F48: =D48*E48 -> 0.7268 | G48: =+D48*2+E48*2 -> 4.08 | H48: 1.58 | I48: =+G48-H48 -> 2.5 | J48: 3 | N48: =+F48 -> 0.7268 | U48: =$I48*$J48 -> 7.5 | AK48: =$F48 -> 0.7268 | AW48: 1 | BK48: =+F48 -> 0.7268 | BY48: =+I48*J48 -> 7.5 | CB48: =+$F48 -> 0.7268
B49: 31 | C49: Placard Dorm Principal Dto. PB | D49: 1.58 | E49: 0.37 | F49: =D49*E49 -> 0.5846 | G49: =+D49*2+E49*2 -> 3.9 | H49: 1.58 | I49: =+G49-H49 -> 2.32 | J49: 3 | N49: =+F49 -> 0.5846 | U49: =$I49*$J49 -> 6.96 | AK49: =$F49 -> 0.5846 | AW49: 1 | BK49: =+F49 -> 0.5846 | BY49: =+I49*J49 -> 6.96 | CB49: =+$F49 -> 0.5846
B50: 32 | C50: Paso Dorm Principal Dto. PB | D50: 1.58 | E50: 0.87 | F50: =D50*E50 -> 1.3746 | G50: =+D50*2+E50*2 -> 4.9 | H50: 0 | I50: =+G50-H50 -> 4.9 | J50: 3 | N50: =+F50 -> 1.3746 | U50: =$I50*$J50 -> 14.7 | V50: =+W50*J50 -> 6 | W50: 2 | AK50: =$F50 -> 1.3746 | AL50: =$G50 -> 4.9 | BK50: =+F50 -> 1.3746 | BQ50: =+I50 -> 4.9 | BY50: =+I50*J50 -> 14.7 | CB50: =+$F50 -> 1.3746 | CJ50: 1
B51: 33 | C51: Baño Dorm Principal Dto. PB | D51: 0 | E51: 0 | F51: 3.88 | G51: 8.16 | H51: 0 | I51: =+G51-H51 -> 8.16 | J51: 2.2 | R51: =+F51 -> 3.88 | S51: =+F51 -> 3.88 | X51: =+I51*J51 -> 17.952 | AA51: =+F51 -> 3.88 | AG51: =$F51 -> 3.88 | AH51: =$I51 -> 8.16 | AQ51: 1 | BL51: =+F51 -> 3.88 | BW51: =$I51*$J51 -> 17.952 | CC51: =+$F51 -> 3.88 | CE51: 1 | CJ51: 3 | CL51: 1 | CN51: 1 | CW51: 1 | CX51: 1 | CY51: 1 | CZ51: 1 | DB51: 1 | DC51: 1 | DD51: 1 | DE51: 1
C52: Semicubierto/Balcon Dto. PB | D52: 3.38 | E52: 1 | F52: =D52*E52 -> 3.38 | G52: =+D52*2+E52*2 -> 8.76 | H52: 2.78 | I52: =+G52-H52 -> 5.98 | J52: 3 | R52: =+F52 -> 3.38 | S52: =+F52 -> 3.38 | AD52: =+F52 -> 3.38 | AG52: 16 | AH52: 25 | BK52: =+G52 -> 8.76 | BS52: =+I52 -> 5.98 | CC52: =+AG52 -> 16 | CI52: 3 | CJ52: 3 | CO52: 1
C53: Patio / Jardin | F53: 59.28 | G53: 31.67 | H53: =+H52 -> 2.78 | I53: =+G53-H53 -> 28.89 | J53: 3 | R53: =+F53 -> 59.28 | S53: =+F53 -> 59.28 | AD53: =+F53 -> 59.28 | BK53: =+G53 -> 31.67 | BS53: =+I53 -> 28.89 | CF53: 1 | CI53: 5 | CJ53: 5
A54: P 1 a P3 | B54: 34 | C54: Pallier | D54: 0 | E54: 0 | F54: 13.1 | G54: 23.73 | H54: 1.29 | I54: =+G54-H54 -> 22.44 | J54: 2.6 | N54: =$F54 -> 13.1 | U54: =+I54*J54 -> 58.344 | AF54: =$F54 -> 13.1 | AH54: =+G54 -> 23.73 | AJ54: 1.6 | AU54: 1 | BM54: =+F54 -> 13.1 | BS54: =+I54 -> 22.44 | BY54: =+I54*J54 -> 58.344 | CC54: =+F54 -> 13.1 | CG54: 4 | CH54: 1 | CI54: 4 | CJ54: 4 | CM54: 4 | CO54: 1
C55: Escalera | D55: 4.37 | E55: 2.5 | F55: =+D55*E55 -> 10.925 | G55: =+D55*2+E55*2 -> 13.74 | H55: =+H54 -> 1.29 | I55: =+G55-H55 -> 12.45 | J55: 2.6 | V55: =+W55*J55 -> 18.2 | W55: 7 | Y55: =+I55*J55 -> 32.37 | AN55: =+F55 -> 10.925 | BT55: =+I55 -> 12.45 | BX55: =+I55*J55 -> 32.37 | CA55: =+F55 -> 10.925 | CG55: 1 | CH55: 1 | CI55: 2 | CJ55: 2
B56: 35 | C56: Hall 1amb A | D56: 2.56 | E56: 1.1 | F56: =D56*E56 -> 2.816 | G56: 7.33 | H56: 1.1 | I56: =+G56-H56 -> 6.23 | J56: 2.4 | N56: =$F56 -> 2.816 | U56: =$I56*$J56 -> 14.952 | V56: =+W56*J56 -> 7.2 | W56: 3 | AF56: =+F56 -> 2.816 | AH56: =$G56 -> 7.33 | AP56: 1 | BK56: =+F56 -> 2.816 | BQ56: =+I56 -> 6.23 | BY56: =+I56*J56 -> 14.952 | CC56: =+F56 -> 2.816 | CJ56: 2 | CL56: 3 | CS56: 1 | CU56: 1
B57: 36 | C57: Placard Hall 1amb A | D57: 1.2 | E57: 0.62 | F57: =D57*E57 -> 0.744 | G57: 3.63 | H57: 1.2 | I57: =+G57-H57 -> 2.43 | J57: 2.4 | N57: =$F57 -> 0.744 | U57: =$I57*$J57 -> 5.832 | W57: 0 | AF57: =+F57 -> 0.744 | AH57: =$G57 -> 3.63 | AW57: 1 | BK57: =+F57 -> 0.744 | BY57: =+I57*J57 -> 5.832 | CC57: =+F57 -> 0.744
B58: 37 | C58: Baño 1amb A | D58: 0 | E58: 0 | F58: 4.51 | G58: 9.79 | H58: 0 | I58: =+G58-H58 -> 9.79 | J58: 2.2 | K58: 2.2 | R58: =$F58 -> 4.51 | S58: =$F58 -> 4.51 | X58: =$I58*$J58 -> 21.538 | AA58: =$F58 -> 4.51 | AG58: =+F58 -> 4.51 | AH58: =+G58 -> 9.79 | AQ58: 1 | BL58: =+F58 -> 4.51 | BW58: =+K58*I58 -> 21.538 | CC58: =+F58 -> 4.51 | CE58: 1 | CJ58: 3 | CL58: 1 | CN58: 1 | CW58: 1 | CX58: 1 | CY58: 1 | DB58: 1 | DC58: 1 | DD58: 1 | DE58: 1
B59: 38 | C59: Cocina 1amb A | D59: 1.9 | E59: 3.59 | F59: =D59*E59 -> 6.821 | G59: 10.95 | H59: =3.6+1.1 -> 4.7 | I59: =+G59-H59 -> 6.25 | J59: 2.4 | K59: 0.6 | L59: 3.07 | N59: =$F59 -> 6.821 | U59: =+(I59*J59)-X59 -> 7.632 | X59: =+L59*J59 -> 7.368 | AF59: =+F59 -> 6.821 | AH59: =$G59 -> 10.95 | AI59: 3.6 | BK59: =+F59 -> 6.821 | BQ59: =+I59 -> 6.25 | BV59: =+L59*K59 -> 1.842 | BY59: =+I59*J59-BV59 -> 13.158 | CC59: =+F59 -> 6.821 | CJ59: 3 | CK59: 1 | CN59: 2 | CO59: 5 | DA59: 1 | DF59: 1
B60: 39 | C60: Living 1amb A | D60: 0 | E60: 0 | F60: 17.47 | G60: 17.11 | H60: 3.6 | I60: =+G60-H60 -> 13.51 | J60: 2.6 | N60: =$F60 -> 17.47 | U60: =$I60*$J60 -> 35.126 | V60: =+W60*J60 -> 7.8 | W60: 3 | AK60: =+F60 -> 17.47 | AL60: =+F60 -> 17.47 | BB60: 1 | BK60: =+F60 -> 17.47 | BQ60: =+I60 -> 13.51 | BY60: =+I60*J60 -> 35.126 | CB60: =+F60 -> 17.47 | CJ60: 2 | CL60: 2 | CN60: 1 | CO60: 5 | CP60: 1 | CQ60: 1 | CR60: 1
B61: 40 | C61: Balcon 1amb A | D61: 1.4 | E61: 3.48 | F61: =D61*E61 -> 4.872 | G61: 9.75 | H61: 0 | I61: =+G61-H61 -> 9.75 | J61: 2.2 | R61: =$F61 -> 4.872 | S61: =$F61 -> 4.872 | AD61: =$F61 -> 4.872 | AG61: =+F61 -> 4.872 | AH61: =+G61 -> 9.75 | BK61: =+F61 -> 4.872 | BS61: =+I61 -> 9.75 | CC61: =+F61 -> 4.872 | CI61: 1 | CJ61: 1
B62: 41 | C62: Hall 3amb A | D62: 1.15 | E62: 1.73 | F62: =D62*E62 -> 1.9895 | G62: 5.77 | H62: 1.15 | I62: =+G62-H62 -> 4.62 | J62: 2.4 | N62: =$F62 -> 1.9895 | U62: =+$I62*$J62 -> 11.088 | V62: =+W62*J62 -> 2.4 | W62: 1 | AF62: =+F62 -> 1.9895 | AH62: =$G62 -> 5.77 | AP62: 1 | BK62: =+F62 -> 1.9895 | BQ62: =+I62 -> 4.62 | BY62: =+I62*J62 -> 11.088 | CC62: =+F62 -> 1.9895 | CJ62: 1 | CL62: 1 | CS62: 1 | CU62: 1
B63: 42 | C63: Cocina 3amb A | D63: 3.25 | E63: 3 | F63: =D63*E63 -> 9.75 | G63: 12.49 | H63: =3+1.15 -> 4.15 | I63: =+G63-H63 -> 8.34 | J63: 2.4 | K63: 0.6 | L63: 3.25 | N63: =$F63 -> 9.75 | U63: =+(I63*J63)-X63 -> 12.216 | X63: =+L63*J63 -> 7.8 | AF63: =+F63 -> 9.75 | AH63: =$G63 -> 12.49 | AI63: 3 | BD63: 1 | BK63: =$F63 -> 9.75 | BQ63: =+I63 -> 8.34 | BV63: =+L63*K63 -> 1.95 | BY63: =+I63*J63-BV63 -> 18.066 | CC63: =+F63 -> 9.75 | CJ63: 6 | CK63: 1 | CL63: 1 | CN63: 2 | CO63: 5 | DA63: 1 | DF63: 1
B64: 43 | C64: Toillette 3amb A | D64: 2.97 | E64: 1.52 | F64: =D64*E64 -> 4.5144 | G64: 8.98 | I64: =+G64-H64 -> 8.98 | J64: 2.2 | K64: 2.2 | R64: =$F64 -> 4.5144 | S64: =$F64 -> 4.5144 | X64: =+$I64*$J64 -> 19.756 | AA64: =$F64 -> 4.5144 | AG64: =+F64 -> 4.5144 | AH64: =+G64 -> 8.98 | AQ64: 1 | BC64: 1 | BL64: =$F64 -> 4.5144 | BW64: =+I64*K64 -> 19.756 | CC64: =+F64 -> 4.5144 | CJ64: 2 | CL64: 1 | CN64: 3 | CO64: 1 | CW64: 1 | CX64: 1 | CY64: 1 | DB64: 1 | DC64: 1 | DD64: 1
B65: 44 | C65: Living 3amb A | D65: 6.47 | E65: 3 | F65: =D65*E65 -> 19.41 | G65: 18.93 | H65: 3 | I65: =+G65-H65 -> 15.93 | J65: 2.6 | N65: =$F65 -> 19.41 | U65: =+$I65*$J65 -> 41.418 | V65: =+W65*J65 -> 5.2 | W65: 2 | AK65: =+F65 -> 19.41 | AL65: =+G65 -> 18.93 | AY65: 1 | BK65: =$F65 -> 19.41 | BQ65: =+I65 -> 15.93 | BY65: =+I65*J65 -> 41.418 | CB65: =+F65 -> 19.41 | CJ65: 2 | CL65: 2 | CO65: 5 | CP65: 1 | CR65: 2
B66: 45 | C66: Paso 3amb A | D66: 2.55 | E66: 1 | F66: =D66*E66 -> 2.55 | G66: 7.1 | H66: 0.9 | I66: =+G66-H66 -> 6.2 | J66: 2.4 | N66: =$F66 -> 2.55 | U66: =+$I66*$J66 -> 14.88 | V66: =+W66*J66 -> 4.8 | W66: 2 | AG66: =+F66 -> 2.55 | AH66: =$G66 -> 7.1 | BK66: =$F66 -> 2.55 | BQ66: =+I66 -> 6.2 | BY66: =+I66*J66 -> 14.88 | CC66: =+F66 -> 2.55 | CJ66: 1 | CL66: 1 | CQ66: 1
B67: 46 | C67: Dorm 2 3amb A | D67: 0 | E67: 0 | F67: 8.12 | G67: 11.88 | H67: 1.69 | I67: =+G67-H67 -> 10.19 | J67: 2.6 | N67: =$F67 -> 8.12 | U67: =+$I67*$J67 -> 26.494 | V67: =+W67*J67 -> 5.2 | W67: 2 | AI67: 1 | AK67: =2.79*2.79 -> 7.7841 | AL67: =2.79*4 -> 11.16 | AQ67: 1 | AY67: 1 | BK67: =$F67 -> 8.12 | BQ67: =+I67 -> 10.19 | BY67: =+I67*J67 -> 26.494 | CB67: =+F67 -> 8.12 | CJ67: 1 | CL67: 1 | CO67: 3 | CP67: 1 | CR67: 1
B68: 47 | C68: Placard Dorm 2 3amb A | D68: 0.6 | E68: 1.69 | F68: =D68*E68 -> 1.014 | G68: 4.58 | H68: 1.69 | I68: =+G68-H68 -> 2.89 | J68: 2.6 | N68: =$F68 -> 1.014 | U68: =+$I68*$J68 -> 7.514 | AK68: =$F68 -> 1.014 | AW68: 1 | BK68: =$F68 -> 1.014 | BY68: =+I68*J68 -> 7.514 | CB68: =+F68 -> 1.014
B69: 48 | C69: Baño 3amb A | D69: 0 | E69: 0 | F69: 3.65 | G69: 7.9 | H69: 0 | I69: =+G69-H69 -> 7.9 | J69: 2.2 | K69: 2.2 | R69: =$F69 -> 3.65 | S69: =$F69 -> 3.65 | X69: =+$I69*$J69 -> 17.38 | AA69: =$F69 -> 3.65 | AG69: =+F69 -> 3.65 | AH69: =+G69 -> 7.9 | AQ69: 1 | BL69: =$F69 -> 3.65 | BW69: =+I69*K69 -> 17.38 | CC69: =+F69 -> 3.65 | CE69: 1 | CJ69: 2 | CL69: 1 | CN69: 1 | CW69: 1 | CX69: 1 | CY69: 1 | DB69: 1 | DC69: 1 | DD69: 1 | DE69: 1
B70: 49 | C70: Dorm Principal 3amb A | D70: 0 | E70: 0 | F70: 10.67 | G70: 15.21 | H70: 2.06 | I70: =+G70-H70 -> 13.15 | J70: 2.6 | N70: =$F70 -> 10.67 | U70: =+$I70*$J70 -> 34.19 | V70: =+W70*J70 -> 7.8 | W70: 3 | AF70: =1*1.5 -> 1.5 | AH70: =1.5*2+1*2 -> 5 | AI70: 1 | AK70: =3.27*2.79 -> 9.1233 | AL70: =3.27*2+2.79*2 -> 12.12 | AQ70: 1 | AY70: 1 | BK70: =$F70 -> 10.67 | BQ70: =+I70 -> 13.15 | BY70: =+I70*J70 -> 34.19 | CB70: =+F70 -> 10.67 | CJ70: 1 | CL70: 2 | CO70: 3 | CP70: 1 | CR70: 1
B71: 50 | C71: Vestuario 3amb A | D71: 1.43 | E71: 0.77 | F71: =D71*E71 -> 1.1011 | G71: 4.6 | H71: =+D71*2+E71 -> 3.63 | I71: =+G71-H71 -> 0.97 | J71: 2.6 | N71: =$F71 -> 1.1011 | U71: =+$I71*$J71 -> 2.522 | V71: =+W71*J71 -> 5.2 | W71: 2 | AG71: =+F71 -> 1.1011 | AH71: =+G71 -> 4.6 | BK71: =$F71 -> 1.1011 | BY71: =+I71*J71 -> 2.522 | CB71: =+F71 -> 1.1011 | CJ71: 1
B72: 51 | C72: Placard Vest 3amb A | D72: 1.43 | E72: 0.43 | F72: =D72*E72 -> 0.6149 | G72: 3.78 | H72: =+D72 -> 1.43 | I72: =+G72-H72 -> 2.35 | J72: 2.6 | N72: =$F72 -> 0.6149 | U72: =+$I72*$J72 -> 6.11 | AK72: =$F72 -> 0.6149 | AW72: 1 | BK72: =$F72 -> 0.6149 | BY72: =+I72*J72 -> 6.11 | CB72: =+F72 -> 0.6149
B73: 52 | C73: Placard Vest 3amb A | D73: 1.43 | E73: 0.43 | F73: =D73*E73 -> 0.6149 | G73: 3.78 | H73: =+D73 -> 1.43 | I73: =+G73-H73 -> 2.35 | J73: 2.6 | N73: =$F73 -> 0.6149 | U73: =+$I73*$J73 -> 6.11 | AK73: =$F73 -> 0.6149 | AW73: 1 | BK73: =$F73 -> 0.6149 | BY73: =+I73*J73 -> 6.11 | CB73: =+F73 -> 0.6149
B74: 53 | C74: Balcon 3amb A | D74: 0 | E74: 0 | F74: 10.4 | G74: 16.52 | H74: 0 | I74: =+G74-H74 -> 16.52 | J74: 2.2 | R74: =$F74 -> 10.4 | S74: =$F74 -> 10.4 | AD74: =$F74 -> 10.4 | AG74: =+F74 -> 10.4 | AH74: =+G74 -> 16.52 | BK74: =$F74 -> 10.4 | BS74: =+I74 -> 16.52 | CC74: =+F74 -> 10.4 | CI74: =+CJ74 -> 3 | CJ74: 3 | CO74: 1
B75: 54 | C75: Hall 1amb B | D75: 2.56 | E75: 1.1 | F75: =D75*E75 -> 2.816 | G75: 7.33 | H75: =1.1+1.2 -> 2.3 | I75: =+G75-H75 -> 5.03 | J75: 2.4 | N75: =$F75 -> 2.816 | U75: =+$I75*$J75 -> 12.072 | V75: =+W75*J75 -> 4.8 | W75: 2 | AF75: =$F75 -> 2.816 | AH75: =$G75 -> 7.33 | AP75: 1 | BK75: =$F75 -> 2.816 | BQ75: =+I75 -> 5.03 | BY75: =+I75*J75 -> 12.072 | CC75: =+F75 -> 2.816 | CI75: 1 | CJ75: 2 | CL75: 3 | CS75: 1 | CU75: 1
B76: 55 | C76: Placard Hall 1amb B | D76: 1.2 | E76: 0.62 | F76: =D76*E76 -> 0.744 | G76: 3.63 | H76: =+D76 -> 1.2 | I76: =+G76-H76 -> 2.43 | J76: 2.4 | N76: =$F76 -> 0.744 | U76: =+$I76*$J76 -> 5.832 | AF76: =$F76 -> 0.744 | AH76: =$G76 -> 3.63 | AW76: 1 | BK76: =$F76 -> 0.744 | BY76: =+I76*J76 -> 5.832 | CC76: =+F76 -> 0.744
B77: 56 | C77: Baño 1amb B | D77: 0 | E77: 0 | F77: 4.51 | G77: 9.79 | H77: 0 | I77: =+G77-H77 -> 9.79 | J77: 2.2 | K77: 2.2 | R77: =$F77 -> 4.51 | S77: =$F77 -> 4.51 | X77: =+$I77*$J77 -> 21.538 | AA77: =$F77 -> 4.51 | AG77: =$F77 -> 4.51 | AH77: =$G77 -> 9.79 | AQ77: 1 | BL77: =$F77 -> 4.51 | BW77: =+I77*K77 -> 21.538 | CC77: =+F77 -> 4.51 | CE77: 1 | CJ77: 3 | CL77: 1 | CN77: 1 | CW77: 1 | CX77: 1 | CY77: 1 | DB77: 1 | DC77: 1 | DD77: 1 | DE77: 1
B78: 57 | C78: Cocina 1amb B | D78: 1.9 | E78: 3.59 | F78: =D78*E78 -> 6.821 | G78: 10.95 | H78: =3.6+1.1 -> 4.7 | I78: =+G78-H78 -> 6.25 | J78: 2.4 | K78: 0.6 | L78: 3.07 | N78: =$F78 -> 6.821 | U78: =(I78*J78)-X78 -> 7.632 | V78: =+W78*J78 -> 2.4 | W78: 1 | X78: =+L78*J78 -> 7.368 | AF78: =$F78 -> 6.821 | AH78: =$G78 -> 10.95 | AI78: 3.6 | BK78: =$F78 -> 6.821 | BQ78: =+I78 -> 6.25 | BV78: =+K78*L78 -> 1.842 | BY78: =+I78*J78-BV78 -> 13.158 | CC78: =+F78 -> 6.821 | CJ78: 3 | CK78: 1 | CN78: 3 | CO78: 4 | DA78: 1 | DF78: 1
B79: 58 | C79: Living 1amb B | D79: 0 | E79: 0 | F79: 17.47 | G79: 17.11 | H79: 3.6 | I79: =+G79-H79 -> 13.51 | J79: 2.6 | N79: =$F79 -> 17.47 | U79: =+$I79*$J79 -> 35.126 | V79: =+W79*J79 -> 7.8 | W79: 3 | AK79: =$F79 -> 17.47 | AL79: =+G79 -> 17.11 | BB79: 1 | BK79: =$F79 -> 17.47 | BQ79: =+I79 -> 13.51 | BY79: =+I79*J79 -> 35.126 | CB79: =+F79 -> 17.47 | CJ79: 2 | CL79: 2 | CN79: 1 | CO79: 5 | CP79: 1 | CQ79: 1 | CR79: 1
B80: 59 | C80: Balcon 1amb B | D80: 1.4 | E80: 3.48 | F80: =D80*E80 -> 4.872 | G80: 9.75 | I80: =+G80-H80 -> 9.75 | J80: 2.2 | R80: =$F80 -> 4.872 | S80: =$F80 -> 4.872 | AD80: =$F80 -> 4.872 | AG80: =$F80 -> 4.872 | AH80: =$I80 -> 9.75 | BK80: =$F80 -> 4.872 | BS80: =+I80 -> 9.75 | CC80: =+F80 -> 4.872 | CI80: 1 | CJ80: 1
B81: 60 | C81: Hall 3amb B | D81: 1.15 | E81: 1.73 | F81: =D81*E81 -> 1.9895 | G81: 5.77 | H81: 1.15 | I81: =+G81-H81 -> 4.62 | J81: 2.4 | N81: =$F81 -> 1.9895 | U81: =+$I81*$J81 -> 11.088 | V81: =+W81*J81 -> 2.4 | W81: 1 | AF81: =$F81 -> 1.9895 | AH81: =$G81 -> 5.77 | AP81: 1 | BK81: =$F81 -> 1.9895 | BQ81: =+I81 -> 4.62 | BY81: =+I81*J81 -> 11.088 | CC81: =+F81 -> 1.9895 | CJ81: 1 | CL81: 1 | CS81: 1 | CU81: 1
B82: 61 | C82: Cocina 3amb B | D82: 3.25 | E82: 3 | F82: =D82*E82 -> 9.75 | G82: 12.49 | H82: =+H81+3 -> 4.15 | I82: =+G82-H82 -> 8.34 | J82: 2.4 | K82: 0.6 | L82: =+D82 -> 3.25 | N82: =$F82 -> 9.75 | U82: =+(I82*J82)-X82 -> 12.216 | X82: =+L82*J82 -> 7.8 | AF82: =$F82 -> 9.75 | AH82: =$G82 -> 12.49 | AI82: 3 | BD82: 1 | BK82: =$F82 -> 9.75 | BQ82: =+I82 -> 8.34 | BV82: =+K82*L82 -> 1.95 | BY82: =+I82*J82-BV82 -> 18.066 | CC82: =+F82 -> 9.75 | CJ82: 6 | CK82: 1 | CL82: 1 | CN82: 2 | CO82: 5 | DA82: 1 | DF82: 1
B83: 62 | C83: Toillette 3amb B | D83: 2.97 | E83: 1.52 | F83: =D83*E83 -> 4.5144 | G83: 8.98 | H83: 2.06 | I83: =+G83-H83 -> 6.92 | J83: 2.2 | K83: 2.2 | R83: =$F83 -> 4.5144 | S83: =$F83 -> 4.5144 | X83: =+$I83*$J83 -> 15.224 | AA83: =$F83 -> 4.5144 | AG83: =$F83 -> 4.5144 | AH83: =$I83 -> 6.92 | AQ83: 1 | BC83: 1 | BL83: =$F83 -> 4.5144 | BW83: =+I83*K83 -> 15.224 | CC83: =+F83 -> 4.5144 | CJ83: 2 | CL83: 1 | CN83: 3 | CO83: 1 | CW83: 1 | CX83: 1 | CY83: 1 | DB83: 1 | DC83: 1 | DD83: 1
B84: 64 | C84: Living 3amb B | D84: 6.47 | E84: 3 | F84: =D84*E84 -> 19.41 | G84: 18.93 | H84: =3+0.9 -> 3.9 | I84: =+G84-H84 -> 15.03 | J84: 2.6 | N84: =$F84 -> 19.41 | U84: =+$I84*$J84 -> 39.078 | V84: =+W84*J84 -> 5.2 | W84: 2 | AK84: =$F84 -> 19.41 | AL84: =G84 -> 18.93 | AY84: 1 | BK84: =$F84 -> 19.41 | BQ84: =+I84 -> 15.03 | BY84: =+I84*J84 -> 39.078 | CB84: =+F84 -> 19.41 | CJ84: 2 | CL84: 2 | CO84: 5 | CP84: 1 | CR84: 2
B85: 65 | C85: Paso 3amb B | D85: 2.55 | E85: 1 | F85: =D85*E85 -> 2.55 | G85: 7.1 | H85: 0.9 | I85: =+G85-H85 -> 6.2 | J85: 2.4 | N85: =$F85 -> 2.55 | U85: =+$I85*$J85 -> 14.88 | V85: =+W85*J85 -> 4.8 | W85: 2 | AF85: =$F85 -> 2.55 | AH85: =$G85 -> 7.1 | BK85: =$F85 -> 2.55 | BQ85: =+I85 -> 6.2 | BY85: =+I85*J85 -> 14.88 | CC85: =+F85 -> 2.55 | CJ85: 1 | CL85: 1 | CQ85: 1
B86: 66 | C86: Dorm 2 3amb B | D86: 0 | E86: 0 | F86: 8.12 | G86: 11.88 | H86: 1.69 | I86: =+G86-H86 -> 10.19 | J86: 2.6 | N86: =$F86 -> 8.12 | U86: =+$I86*$J86 -> 26.494 | V86: =+W86*J86 -> 5.2 | W86: 2 | AI86: 1 | AK86: =2.79*2.79 -> 7.7841 | AL86: =2.79*4 -> 11.16 | AQ86: 1 | AY86: 1 | BK86: =$F86 -> 8.12 | BQ86: =+I86 -> 10.19 | BY86: =+I86*J86 -> 26.494 | CB86: =+F86 -> 8.12 | CJ86: 1 | CL86: 1 | CO86: 3 | CP86: 1 | CR86: 1
B87: 67 | C87: Placard Dorm 2 3amb B | D87: 0.6 | E87: 1.69 | F87: =D87*E87 -> 1.014 | G87: 4.58 | H87: =+E87 -> 1.69 | I87: =+G87-H87 -> 2.89 | J87: 2.6 | N87: =$F87 -> 1.014 | U87: =+$I87*$J87 -> 7.514 | AK87: =$F87 -> 1.014 | AW87: 1 | BK87: =$F87 -> 1.014 | BY87: =+I87*J87 -> 7.514 | CB87: =+F87 -> 1.014
B88: 68 | C88: Baño 3amb B | D88: 0 | E88: 0 | F88: 3.65 | G88: 7.9 | I88: =+G88-H88 -> 7.9 | J88: 2.2 | K88: 2.2 | R88: =$F88 -> 3.65 | S88: =$F88 -> 3.65 | X88: =+$I88*$J88 -> 17.38 | AA88: =$F88 -> 3.65 | AG88: =$F88 -> 3.65 | AH88: =$G88 -> 7.9 | AQ88: 1 | BL88: =$F88 -> 3.65 | BW88: =+I88*K88 -> 17.38 | CC88: =+F88 -> 3.65 | CE88: 1 | CJ88: 3 | CL88: 1 | CN88: 1 | CW88: 1 | CX88: 1 | CY88: 1 | DB88: 1 | DC88: 1 | DD88: 1 | DE88: 1
B89: 69 | C89: Dorm Principal 3amb B | D89: 0 | E89: 0 | F89: 10.67 | G89: 15.21 | I89: =+G89-H89 -> 15.21 | J89: 2.6 | N89: =$F89 -> 10.67 | U89: =+$I89*$J89 -> 39.546 | V89: =+W89*J89 -> 7.8 | W89: 3 | AF89: =1.5*1 -> 1.5 | AH89: =1.5*2+1*2 -> 5 | AI89: 1 | AK89: =2.79*3.27 -> 9.1233 | AL89: =2.79*2+3.27*2 -> 12.12 | AQ89: 1 | AY89: 1 | BK89: =$F89 -> 10.67 | BQ89: =+I89 -> 15.21 | BY89: =+I89*J89 -> 39.546 | CB89: =+F89 -> 10.67 | CJ89: 1 | CL89: 2 | CO89: 3 | CP89: 1 | CR89: 1
B90: 70 | C90: Vestuario 3amb B | D90: 1.43 | E90: 0.77 | F90: =D90*E90 -> 1.1011 | G90: 4.6 | H90: =+D90*2+E90 -> 3.63 | I90: =+G90-H90 -> 0.97 | J90: 2.6 | N90: =$F90 -> 1.1011 | U90: =+$I90*$J90 -> 2.522 | V90: =+W90*J90 -> 5.2 | W90: 2 | AK90: =$F90 -> 1.1011 | AL90: =$G90 -> 4.6 | BK90: =$F90 -> 1.1011 | BY90: =+I90*J90 -> 2.522 | CB90: =+F90 -> 1.1011 | CJ90: 1
B91: 71 | C91: Placard Vest 3amb B | D91: 1.43 | E91: 0.43 | F91: =D91*E91 -> 0.6149 | G91: 3.78 | H91: =+D91 -> 1.43 | I91: =+G91-H91 -> 2.35 | J91: 2.6 | N91: =$F91 -> 0.6149 | U91: =+$I91*$J91 -> 6.11 | AK91: =$F91 -> 0.6149 | AW91: 1 | BK91: =$F91 -> 0.6149 | BY91: =+I91*J91 -> 6.11 | CB91: =+F91 -> 0.6149
B92: 72 | C92: Placard Vest 3amb B | D92: 1.43 | E92: 0.43 | F92: =D92*E92 -> 0.6149 | G92: 3.78 | H92: =+D92 -> 1.43 | I92: =+G92-H92 -> 2.35 | J92: 2.6 | N92: =$F92 -> 0.6149 | U92: =+$I92*$J92 -> 6.11 | AK92: =$F92 -> 0.6149 | AW92: 1 | BK92: =$F92 -> 0.6149 | BY92: =+I92*J92 -> 6.11 | CB92: =+F92 -> 0.6149
B93: 73 | C93: Balcon 3amb B | D93: 0 | E93: 0 | F93: 10.4 | G93: 16.52 | I93: =+G93-H93 -> 16.52 | J93: 2.2 | R93: =$F93 -> 10.4 | S93: =$F93 -> 10.4 | AD93: =$F93 -> 10.4 | AG93: =$F93 -> 10.4 | AH93: =$G93 -> 16.52 | BK93: =$F93 -> 10.4 | BS93: =+I93 -> 16.52 | CC93: =+F93 -> 10.4 | CI93: =+CJ93 -> 3 | CJ93: 3 | CO93: 1
C94: Repeticion | F94: =+SUM(F54:F93)*$L$94 -> 494.5772 | L94: 2 | N94: =+SUM(N54:N93)*$L$94 -> 360.9416 | O94: =+SUM(O54:O93)*$L$94 -> 0 | P94: =+SUM(P54:P93)*$L$94 -> 0 | Q94: =+SUM(Q54:Q93)*$L$94 -> 0 | R94: =+SUM(R54:R93)*$L$94 -> 111.7856 | S94: =+SUM(S54:S93)*$L$94 -> 111.7856 | U94: =+SUM(U54:U93)*$L$94 -> 1021.296 | V94: =+SUM(V54:V93)*$L$94 -> 218.8 | W94: =+SUM(W54:W93)*$L$94 -> 86 | X94: =+SUM(X54:X93)*$L$94 -> 286.304 | Y94: =+SUM(Y54:Y93)*$L$94 -> 64.74 | AA94: =+SUM(AA54:AA93)*$L$94 -> 50.6976 | AB94: =+SUM(AB54:AB93)*$L$94 -> 0 | AC94: =+SUM(AC54:AC93)*$L$94 -> 0 | AD94: =+SUM(AD54:AD93)*$L$94 -> 61.088 | AF94: =+SUM(AF54:AF93)*$L$94 -> 125.782 | AG94: =+SUM(AG54:AG93)*$L$94 -> 119.0878 | AH94: =+SUM(AH54:AH93)*$L$94 -> 473.38 | AI94: =+SUM(AI54:AI93)*$L$94 -> 34.4 | AJ94: =+SUM(AJ54:AJ93)*$L$94 -> 3.2 | AK94: =+SUM(AK54:AK93)*$L$94 -> 226.327 | AL94: =+SUM(AL54:AL93)*$L$94 -> 247.2 | AM94: =+SUM(AM54:AM93)*$L$94 -> 0 | AN94: =+SUM(AN54:AN93)*$L$94 -> 21.85 | AP94: =+SUM(AP54:AP93)*$L$94 -> 8 | AQ94: =+SUM(AQ54:AQ93)*$L$94 -> 20 | AR94: =+SUM(AR54:AR93)*$L$94 -> 0 | AS94: =+SUM(AS54:AS93)*$L$94 -> 0 | AT94: =+SUM(AT54:AT93)*$L$94 -> 0 | AU94: =+SUM(AU54:AU93)*$L$94 -> 2 | AV94: =+SUM(AV54:AV93)*$L$94 -> 0 | AW94: =+SUM(AW54:AW93)*$L$94 -> 16 | ... BG94: =+SUM(BG54:BG93)*$L$94 -> 0 | BI94: =+SUM(BI54:BI93)*$L$94 -> 0 | BJ94: =+SUM(BJ54:BJ93)*$L$94 -> 0 | BK94: =+SUM(BK54:BK93)*$L$94 -> 395.8296 | BL94: =+SUM(BL54:BL93)*$L$94 -> 50.6976 | BM94: =+SUM(BM54:BM93)*$L$94 -> 26.2 | BN94: =+SUM(BN54:BN93)*$L$94 -> 0 | BO94: =+SUM(BO54:BO93)*$L$94 -> 0 | BP94: =+SUM(BP54:BP93)*$L$94 -> 0 | ... BT94: =+SUM(BT54:BT93)*$L$94 -> 24.9 | BV94: =+SUM(BV54:BV93)*$L$94 -> 15.168 | BW94: =+SUM(BW54:BW93)*$L$94 -> 225.632 | BX94: =+SUM(BX54:BX93)*$L$94 -> 64.74 | BY94: =+SUM(BY54:BY93)*$L$94 -> 1066.8 | BZ94: =+SUM(BZ54:BZ93)*$L$94 -> 0 | CA94: =+SUM(CA54:CA93)*$L$94 -> 21.85 | CB94: =+SUM(CB54:CB93)*$L$94 -> 236.0596 | CC94: =+SUM(CC54:CC93)*$L$94 -> 236.6676 | CE94: =+SUM(CE54:CE93)*$L$94 -> 8 | CF94: =+SUM(CF54:CF93)*$L$94 -> 0 | CG94: =+SUM(CG54:CG93)*$L$94 -> 10 | CH94: =+SUM(CH54:CH93)*$L$94 -> 4 | CI94: =+SUM(CI54:CI93)*$L$94 -> 30 | CJ94: =+SUM(CJ54:CJ93)*$L$94 -> 138 | CK94: =+SUM(CK54:CK93)*$L$94 -> 8 | CL94: =+SUM(CL54:CL93)*$L$94 -> 64 | ... CU94: =+SUM(CU54:CU93)*$L$94 -> 8 | CW94: =+SUM(CW54:CW93)*$L$94 -> 12 | CX94: =+SUM(CX54:CX93)*$L$94 -> 12 | CY94: =+SUM(CY54:CY93)*$L$94 -> 12 | CZ94: =+SUM(CZ54:CZ93)*$L$94 -> 0 | DA94: =+SUM(DA54:DA93)*$L$94 -> 8 | DB94: =+SUM(DB54:DB93)*$L$94 -> 12 | DC94: =+SUM(DC54:DC93)*$L$94 -> 12 | DD94: =+SUM(DD54:DD93)*$L$94 -> 12 | ... DF94: =+SUM(DF54:DF93)*$L$94 -> 8
A95: P 4 | B95: 74 | C95: Pallier | D95: 0 | E95: 0 | F95: 15.19 | G95: 23.06 | H95: 0 | I95: =+G95-H95 -> 23.06 | J95: 2.6 | N95: =F95 -> 15.19 | U95: =+I95*J95 -> 59.956 | AF95: =$F95 -> 15.19 | AJ95: 1.6 | AU95: 1 | BM95: =$F95 -> 15.19 | BS95: =+I95 -> 23.06 | BY95: =+I95*J95 -> 59.956 | CC95: =+F95 -> 15.19 | CG95: 3 | CH95: 1 | CI95: 2 | CJ95: 3 | CM95: 3 | CO95: 1
C96: Escalera | D96: 4.37 | E96: 2.5 | F96: =+D96*E96 -> 10.925 | G96: =+D96*2+E96*2 -> 13.74 | H96: =+H95 -> 0 | I96: =+G96-H96 -> 13.74 | J96: 2.6 | Y96: =+I96*J96 -> 35.724 | AN96: =+F96 -> 10.925 | BT96: =+I96 -> 13.74 | BX96: =+I96*J96 -> 35.724 | CA96: =+F96 -> 10.925 | CG96: 1 | CH96: 1 | CI96: 2 | CJ96: 2
B97: 75 | C97: Hall 1amb B | D97: 2.56 | E97: 1.1 | F97: =D97*E97 -> 2.816 | G97: 7.33 | H97: =+E97+D98 -> 2.3 | I97: =+G97-H97 -> 5.03 | J97: 2.4 | N97: =$F97 -> 2.816 | U97: =$I97*$J97 -> 12.072 | V97: =+W97*J97 -> 7.2 | W97: 3 | AF97: =$F97 -> 2.816 | AH97: =+I67 -> 10.19 | AP97: 1 | BK97: =$F97 -> 2.816 | BQ97: =+I97 -> 5.03 | BY97: =+I97*J97 -> 12.072 | CC97: =+F97 -> 2.816 | CJ97: 2 | CL97: 3 | CS97: 1 | CU97: 1
B98: 76 | C98: Placard Hall 1amb B | D98: 1.2 | E98: 0.62 | F98: =D98*E98 -> 0.744 | G98: 3.63 | H98: =+D98 -> 1.2 | I98: =+G98-H98 -> 2.43 | J98: 2.4 | N98: =$F98 -> 0.744 | U98: =$I98*$J98 -> 5.832 | AF98: =$F98 -> 0.744 | AW98: 1 | BK98: =$F98 -> 0.744 | BY98: =+I98*J98 -> 5.832 | CC98: =+F98 -> 0.744
B99: 77 | C99: Baño 1amb B | D99: 0 | E99: 0 | F99: 4.51 | G99: 9.79 | H99: 0 | I99: =+G99-H99 -> 9.79 | J99: 2.2 | K99: 2.2 | R99: =$F99 -> 4.51 | S99: =$F99 -> 4.51 | X99: =+I99*K99 -> 21.538 | AA99: =$F99 -> 4.51 | AG99: =$F99 -> 4.51 | AH99: =$G99 -> 9.79 | AQ99: 1 | BK99: =$F99 -> 4.51 | BL99: =$F99 -> 4.51 | BW99: =+I99*K99 -> 21.538 | CC99: =+F99 -> 4.51 | CE99: 1 | CJ99: 3 | CK99: 1 | CL99: 1 | CN99: 1 | CW99: 1 | CX99: 1 | CY99: 1 | DB99: 1 | DC99: 1 | DD99: 1 | DE99: 1
B100: 78 | C100: Cocina 1amb B | D100: 1.9 | E100: 3.6 | F100: =D100*E100 -> 6.84 | G100: 10.95 | H100: =+E100 -> 3.6 | I100: =+G100-H100 -> 7.35 | J100: 2.4 | K100: 0.6 | L100: =3.6-1.1 -> 2.5 | N100: =$F100 -> 6.84 | U100: =(I100*J100)-X100 -> 11.64 | X100: =+L100*J100 -> 6 | AG100: =$F100 -> 6.84 | AH100: =$G100 -> 10.95 | AI100: 3.6 | BK100: =$F100 -> 6.84 | BQ100: =+I100 -> 7.35 | BV100: =+K100*L100 -> 1.5 | BY100: =+I100*J100-BV100 -> 16.14 | CC100: =+F100 -> 6.84 | CJ100: 3 | CN100: 3 | CO100: 4 | DA100: 1 | DF100: 1
B101: 79 | C101: Living 1amb B | D101: 0 | E101: 0 | F101: 17.47 | G101: 17.11 | H101: =+E100 -> 3.6 | I101: =+G101-H101 -> 13.51 | J101: 2.6 | N101: =$F101 -> 17.47 | U101: =+I101*J101 -> 35.126 | V101: =+W101*J101 -> 7.8 | W101: 3 | AK101: =$F101 -> 17.47 | AL101: =$G101 -> 17.11 | BB101: 1 | BK101: =$F101 -> 17.47 | BQ101: =+I101 -> 13.51 | BY101: =+I101*J101 -> 35.126 | CB101: =+F101 -> 17.47 | CJ101: 2 | CL101: 2 | CN101: 1 | CO101: 5 | CP101: 1 | CQ101: 1 | CR101: 1
...

Sheet Computo
B2: Picado de medianeras
C3: Largo | D3: h | E3: m2 | F3: Subtotal | J3: MEDIANERAS enchape | K3: Largo | L3: h | M3: m2
B4: PB | F4: =+SUM(E5:E27) -> 48.3255 | J4: PB | N4: =+SUM(M5:M7) -> 130.248
B5: C01 | C5: 0.75 | D5: 3.3 | E5: =+C5*D5 -> 2.475 | J5: Lado A | K5: 20.22 | L5: 2.7 | M5: =+K5*L5 -> 54.594
B6: C02 | C6: 0.75 | D6: 3.3 | E6: =+C6*D6 -> 2.475 | J6: Lado B | K6: 19.44 | L6: 2.7 | M6: =+K6*L6 -> 52.488
B7: C03 | C7: 0.75 | D7: 3.3 | E7: =+C7*D7 -> 2.475 | J7: Fondo | K7: 8.58 | L7: 2.7 | M7: =+K7*L7 -> 23.166
B8: C04 | C8: 0.75 | D8: 3.3 | E8: =+C8*D8 -> 2.475 | J8: 1P | N8: =+SUM(M9:M11) -> 108.807
B9: C05 | C9: 0.75 | D9: 3.3 | E9: =+C9*D9 -> 2.475 | J9: Lado A | K9: 20.22 | L9: =2.8-0.5 -> 2.3 | M9: =+K9*L9 -> 46.506
B10: C06 | C10: 0.75 | D10: 3.3 | E10: =+C10*D10 -> 2.475 | J10: Lado B | K10: 19.44 | L10: =2.8-0.5 -> 2.3 | M10: =+K10*L10 -> 44.712
B11: C19 | C11: 0.75 | D11: 3.3 | E11: =+C11*D11 -> 2.475 | J11: Fondo | K11: 8.58 | L11: 2.05 | M11: =+K11*L11 -> 17.589
B12: C20 | C12: 0.75 | D12: 3.3 | E12: =+C12*D12 -> 2.475 | M12: =SUM(M4:M11) -> 239.055 | N12: =SUM(N4:N11) -> 239.055
B13: C21 | C13: 0.75 | D13: 3.3 | E13: =+C13*D13 -> 2.475
B14: C22 | C14: 0.75 | D14: 3.3 | E14: =+C14*D14 -> 2.475
B15: C23 | C15: 0.75 | D15: 3.3 | E15: =+C15*D15 -> 2.475
B16: C24 | C16: 0.75 | D16: 3.3 | E16: =+C16*D16 -> 2.475
B17: V201 | C17: 4.3 | D17: 0.45 | E17: =+C17*D17 -> 1.935
B18: V202 | C18: 5.07 | D18: 0.45 | E18: =+C18*D18 -> 2.2815
B19: V203 | C19: 5.1 | D19: 0.45 | E19: =+C19*D19 -> 2.295
B20: V204 | C20: 5 | D20: 0.45 | E20: =+C20*D20 -> 2.25
B21: V205 | C21: 3.8 | D21: 0.45 | E21: =+C21*D21 -> 1.71
B22: V206 | C22: 0.6 | D22: 0.45 | E22: =+C22*D22 -> 0.27
B23: V224 | C23: 4.3 | D23: 0.45 | E23: =+C23*D23 -> 1.935
B24: V225 | C24: 4.44 | D24: 0.45 | E24: =+C24*D24 -> 1.998
... B27: V228 | C27: 0.6 | D27: 0.45 | E27: =+C27*D27 -> 0.27
B28: PB | F28: =+SUM(E29:E57) -> 43.8255
B29: C01 | C29: 0.75 | D29: 2.8 | E29: =+C29*D29 -> 2.1
B30: C02 | C30: 0.75 | D30: 2.8 | E30: =+C30*D30 -> 2.1
B31: C03 | C31: 0.75 | D31: 2.8 | E31: =+C31*D31 -> 2.1
B32: C04 | C32: 0.75 | D32: 2.8 | E32: =+C32*D32 -> 2.1
B33: C05 | C33: 0.75 | D33: 2.8 | E33: =+C33*D33 -> 2.1
B34: C06 | C34: 0.75 | D34: 2.8 | E34: =+C34*D34 -> 2.1
B35: C19 | C35: 0.75 | D35: 2.8 | E35: =+C35*D35 -> 2.1
B36: C20 | C36: 0.75 | D36: 2.8 | E36: =+C36*D36 -> 2.1
B37: C21 | C37: 0.75 | D37: 2.8 | E37: =+C37*D37 -> 2.1
B38: C22 | C38: 0.75 | D38: 2.8 | E38: =+C38*D38 -> 2.1
B39: C23 | C39: 0.75 | D39: 2.8 | E39: =+C39*D39 -> 2.1
B40: C24 | C40: 0.75 | D40: 2.8 | E40: =+C40*D40 -> 2.1
... B51: V327 | C51: 0.6 | D51: 0.45 | E51: =+C51*D51 -> 0.27
F52: =SUM(F4:F51) -> 92.151
F53: =+ROUNDUP(F52,0) -> 93
B57: IMPERMEABILIZACION | C57: Ancho | D57: h | E57: m2
B58: BAJO RECORRIDO ASC.
B59: M1 | C59: 1.9 | D59: 1.5 | E59: =+C59*D59 -> 2.85
B60: M2 | C60: 1.5 | D60: 1.5 | E60: =+C60*D60 -> 2.25
B61: M3 | C61: 1.9 | D61: 1.5 | E61: =+C61*D61 -> 2.85
B62: M4 | C62: 1.5 | D62: 1.5 | E62: =+C62*D62 -> 2.25
B63: Base | C63: 1.9 | D63: 1.5 | E63: =+C63*D63 -> 2.85
B64: SUBSUELO
B65: Planta | C65: 330 | D65: 1 | E65: =+C65*D65 -> 330
B66: Submuración | C66: 88 | D66: 2.75 | E66: =+C66*D66 -> 242
E67: =+SUM(E59:E66) -> 585.05
B70: PINTURA PUERTAS
H71: 2
B72: Descripción | C72: Cant | D72: Ancho | E72: h | F72: Caras | G72: m2 hojas | H72: Perim | I72: ancho | J72: m2 marcos | K72: m2 | L72: Subtotal
B73: Placa MDF 0,80 m | C73: =+Locales!AQ144 -> 47 | D73: 0.9 | E73: 2.05 | F73: 2 | G73: =+D73*E73*F73 -> 3.69 | H73: =+(E73*$H$71)+D73 -> 5 | I73: =0.15+0.04+0.04 -> 0.23 | J73: =+H73*I73 -> 1.15 | K73: =+G73+J73 -> 4.84 | L73: =+C73*K73 -> 227.48
B74: Chapa F60 | C74: =+Locales!AS144 -> 2 | D74: 0.9 | E74: 2.05 | F74: 2 | G74: =+D74*E74*F74 -> 3.69 | H74: =+(E74*$H$71)+D74 -> 5 | I74: =0.15+0.04+0.04 -> 0.23 | J74: =+H74*I74 -> 1.15 | K74: =+G74+J74 -> 4.84 | L74: =+C74*K74 -> 9.68
B75: Chapa F30 0,90 m | C75: =+Locales!AP144 -> 16 | D75: 0.9 | E75: 2.05 | F75: 2 | G75: =+D75*E75*F75 -> 3.69 | H75: =+(E75*$H$71)+D75 -> 5 | I75: =0.15+0.04+0.04 -> 0.23 | J75: =+H75*I75 -> 1.15 | K75: =+G75+J75 -> 4.84 | L75: =+C75*K75 -> 77.44
B76: Chapa 0,80 m | C76: =+Locales!AR144 -> 5 | D76: 0.8 | E76: 2.05 | F76: 2 | G76: =+D76*E76*F76 -> 3.28 | H76: =+(E76*$H$71)+D76 -> 4.9 | I76: =0.15+0.04+0.04 -> 0.23 | J76: =+H76*I76 -> 1.127 | K76: =+G76+J76 -> 4.407 | L76: =+C76*K76 -> 22.035
B77: Puerta Ascensor | C77: =+Locales!AU144-1 -> 6 | D77: 0.9 | E77: 2.05 | F77: 1 | G77: =+D77*E77*F77 -> 1.845 | H77: =+(E77*$H$71)+D77 -> 5 | I77: =0.15+0.04+0.04 -> 0.23 | J77: =+H77*I77 -> 1.15 | K77: =+G77+J77 -> 2.995 | L77: =+C77*K77 -> 17.97
C78: =SUM(C73:C77) -> 76 | L78: =SUM(L73:L77) -> 354.605
B81: BARANDAS y HERRERIAS | C81: Cant | D81: Ancho | E81: h | F81: m2 | G81: Caras | H81: Subt | I81: Subtotal
B82: CONTRAFRENTE | J82: =+SUM(I83:I83) -> 88
B83: Balcones contrafrente 1º a 6º | C83: 4 | D83: 11 | E83: 1 | F83: =+D83*E83 -> 11 | G83: 2 | H83: =+F83*G83 -> 22 | I83: =+H83*C83 -> 88
B84: FRENTE | J84: =+SUM(I85:I85) -> 66
B85: Balcones Frente - 1º a 6º | C85: 4 | D85: 11 | E85: 0.75 | F85: =+D85*E85 -> 8.25 | G85: 2 | H85: =+F85*G85 -> 16.5 | I85: =+H85*C85 -> 66
B86: RETIROS | J86: =+SUM(I87:I87) -> 28.73
C87: 2 | D87: 8.45 | E87: 0.85 | F87: =+D87*E87 -> 7.1825 | G87: 2 | H87: =+F87*G87 -> 14.365 | I87: =+H87*C87 -> 28.73
B88: FACHADA | J88: =+SUM(I89) -> 14.82
B89: PB / PORTON | C89: 1 | D89: 2.85 | E89: 2.6 | F89: =+D89*E89 -> 7.41 | G89: 2 | H89: =+F89*G89 -> 14.82 | I89: =+H89*C89 -> 14.82
B90: PORTONES MEDIDORES | J90: =+SUM(I91:I92) -> 20.54
B91: Medidor luz | C91: 1 | D91: 1.6 | E91: 2.6 | F91: =+D91*E91 -> 4.16 | G91: 2 | H91: =+F91*G91 -> 8.32 | I91: =+H91*C91 -> 8.32
B92: Medidor gas | C92: 1 | D92: 2.35 | E92: 2.6 | F92: =+D92*E92 -> 6.11 | G92: 2 | H92: =+F92*G92 -> 12.22 | I92: =+H92*C92 -> 12.22
B93: ESCALERA | J93: =+SUM(I94:I98) -> 46.63
B94: Horizontales pasamanos largo | C94: =2*7 -> 14 | D94: 3 | E94: 0.05 | F94: =+D94*E94 -> 0.15 | G94: 4 | H94: =+F94*G94 -> 0.6 | I94: =+H94*C94 -> 8.4
B95: Horizontales pasamanos corto | C95: =2*7 -> 14 | D95: 1 | E95: 0.05 | F95: =+D95*E95 -> 0.05 | G95: 4 | H95: =+F95*G95 -> 0.2 | I95: =+H95*C95 -> 2.8
B96: Horizontales ojo | C96: =3*2*7 -> 42 | D96: 2.5 | E96: 0.05 | F96: =+D96*E96 -> 0.125 | G96: 4 | H96: =+F96*G96 -> 0.5 | I96: =+H96*C96 -> 21
B97: Verticales | C97: 2 | D97: 0.05 | E97: 18 | F97: =+D97*E97 -> 0.9 | G97: 4 | H97: =+F97*G97 -> 3.6 | I97: =+H97*C97 -> 7.2
B98: Escaleras terraza y gato | C98: 3 | D98: 2.41 | E98: 0.5 | F98: =+D98*E98 -> 1.205 | G98: 2 | H98: =+F98*G98 -> 2.41 | I98: =+H98*C98 -> 7.23
I99: =SUM(I82:I98) -> 264.72 | J99: =SUM(J82:J98) -> 264.72
B102: DEFENSAS
B104: Defensas frente y contrafrente
C105: Ml | D105: Cant | E105: Subtotal
B106: Frente | C106: 10 | D106: 1 | E106: =+C106*D106 -> 10
B107: Contrafrente | C107: 10 | D107: 1 | E107: =+C107*D107 -> 10
B108: Fachada lat | C108: 31 | D108: 2 | E108: =+C108*D108 -> 62
D109: =SUM(D106:D108) -> 4 | E109: =+SUM(E106:E108) -> 82
B111: BARANDAS
B112: FRENTE
B113: Balcones 1° a 4° | C113: 12 | D113: 4 | E113: =+D113*C113 -> 48
B114: Piso 5° | C114: 8.5 | D114: 1 | E114: =+D114*C114 -> 8.5
B115: CONTREFRENTE
B116: Balcones 1° a 4° | C116: 12 | D116: 4 | E116: =+D116*C116 -> 48
B117: Piso 5° | C117: 8.5 | D117: 1 | E117: =+D117*C117 -> 8.5
B118: SUBSUELO
B119: Rampa | C119: 16 | D119: 1 | E119: =+D119*C119 -> 16
E120: =+SUM(E113:E119) -> 129
I123: 0.26 | J123: 0.18
B124: NARICES METALICAS | C124: h | D124: alzada | E124: N° Alzadas | F124: Cant niveles | G124: Largo | H124: Ml | I124: m2 pedada | J124: m2 alzada total | K124: m2
B125: SS° | C125: 3.05 | D125: 0.175 | E125: =+ROUNDUP(C125/D125,0) -> 18 | F125: 1 | G125: 1.2 | H125: =+E125*F125*G125 -> 21.6 | I125: =+E125*G125*$I$123*F125 -> 5.616 | J125: =+E125*G125*$J$123*F125 -> 3.888 | K125: =+I125+J125 -> 9.504
B126: PB | C126: 3.2 | D126: 0.175 | E126: =+ROUNDUP(C126/D126,0) -> 19 | F126: 1 | G126: 1.2 | H126: =+E126*F126*G126 -> 22.8 | I126: =+E126*G126*$I$123*F126 -> 5.928 | J126: =+E126*G126*$J$123*F126 -> 4.104 | K126: =+I126+J126 -> 10.032
...

Sheet INCEND
B1: NOTA: CANTIDADES SALEN DE COMPUTO AUXILIAR INCENDIO | F1: 1.05
H2: 0.6 | I2: respecto a VL 572 | L2: =+'P.MO 09.24'!B4 -> 75113.048 | M2: =+'P.MO 09.24'!B5 -> 65360.248 | N2: =+'P.MO 09.24'!B6 -> 54784.072 | O2: =+'P.MO 09.24'!B7 -> 49934.237 | P2: 1.5
B3: Descripción | C3: Un | D3: Cant | E3: P Unit | F3: Punit ACT | G3: Subtotal | J3: TAREA | K3: DIA | L3: ES | M3: OF | N3: MED | O3: AY | P3: GGBB
B4: Por tendido cañeria de incendio - (no incluye gabinetes, manguera, lanza y valvula) | H4: =+SUM(G5:G17)*H2 -> 2093587.4 | J4: Pintura | K4: 2 | O4: 2 | P4: =(+L4*$L$2+M4*$M$2+N4*$N$2+O4*$O$2)*K4 -> 199736.95
B5: CAÑO DE HIERRO GALVANIZADO 2" x 6,4 m | C5: tira | D5: 1 | E5: =VLOOKUP(B5,Cotizaciones!B:D,3,0) -> 191048 | F5: =+E5*$F$1 -> 200600.4 | G5: =+D5*F5 -> 200600.4 | J5: Tendido montante | K5: 5 | L5: 1 | O5: 1 | P5: =(+L5*$L$2+M5*$M$2+N5*$N$2+O5*$O$2)*K5 -> 625236.43
B6: CAÑO DE HIERRO GALVANIZADO 2 1/2" x 6,4 m | C6: tira | D6: 8 | E6: =VLOOKUP(B6,Cotizaciones!B:D,3,0) -> 266426 | F6: =+E6*$F$1 -> 279747.3 | G6: =+D6*F6 -> 2237978.4 | J6: Amurado de gabinete | K6: 2 | L6: 1 | O6: 1 | P6: =(+L6*$L$2+M6*$M$2+N6*$N$2+O6*$O$2)*K6 -> 250094.57
B7: TEE REDUCCION GALVANIZADA 2 1/2" x 2" | C7: u | D7: 8 | E7: =VLOOKUP(B7,Cotizaciones!B:D,3,0) -> 18775.3 | F7: =+E7*$F$1 -> 19714.065 | G7: =+D7*F7 -> 157712.52 | J7: Colocación de mangueras | K7: 2 | L7: 1 | O7: 1 | P7: =(+L7*$L$2+M7*$M$2+N7*$N$2+O7*$O$2)*K7 -> 250094.57
B8: TEE GALVANIZADA 2 1/2" | C8: u | D8: 2 | E8: =VLOOKUP(B8,Cotizaciones!B:D,3,0) -> 16598 | F8: =+E8*$F$1 -> 17427.9 | G8: =+D8*F8 -> 34855.8 | K8: =SUM(K4:K7) -> 11 | P8: =+SUM(P4:P7) -> 1325162.5
B9: CODO GALVANIZADO H-H 90° 2 1/2" | C9: u | D9: 11 | E9: =VLOOKUP(B9,Cotizaciones!B:D,3,0) -> 13695 | F9: =+E9*$F$1 -> 14379.75 | G9: =+D9*F9 -> 158177.25 | P9: =+P8*$P$2 -> 1987743.8 | Q9: GGBB
B10: BUJE REDUCCION M - H 2 1/2" x 2" | C10: u | D10: 8 | E10: =VLOOKUP(B10,Cotizaciones!B:D,3,0) -> 7191.2 | F10: =+E10*$F$1 -> 7550.76 | G10: =+D10*F10 -> 60406.08
B11: CODO GALVANIZADO H-H 90° 2" | C11: u | D11: 8 | E11: =VLOOKUP(B11,Cotizaciones!B:D,3,0) -> 6723.2 | F11: =+E11*$F$1 -> 7059.36 | G11: =+D11*F11 -> 56474.88
B12: ROSCA CON TUERCA GALVANIZADA 2" Página 1 de 2 | C12: u | D12: 18 | E12: =VLOOKUP(B12,Cotizaciones!B:D,3,0) -> 4383.5 | F12: =+E12*$F$1 -> 4602.675 | G12: =+D12*F12 -> 82848.15
B13: CUPLA H - H GALVANIZADA 2 1/2" | C13: u | D13: 3 | E13: =VLOOKUP(B13,Cotizaciones!B:D,3,0) -> 11704.5 | F13: =+E13*$F$1 -> 12289.725 | G13: =+D13*F13 -> 36869.175
B14: CUPLA H - H GALVANIZADA 2" | C14: u | D14: 1 | E14: =VLOOKUP(B14,Cotizaciones!B:D,3,0) -> 5548.6 | F14: =+E14*$F$1 -> 5826.03 | G14: =+D14*F14 -> 5826.03
B15: Esmalte sintetico 3 en 1 Bermellon x 4 lts | C15: tac | D15: 1 | E15: 100000 | F15: =+E15*$F$1 -> 105000 | G15: =+D15*F15 -> 105000
B16: Rodillos y pinceles | C16: gl | D16: 1 | E16: =+E15*0.2 -> 20000 | F16: =+E16*$F$1 -> 21000 | G16: =+D16*F16 -> 21000
B17: Desperdicio / Imprevistos / | C17: gl | D17: 0.1 | E17: =+SUM(G5:G16) -> 3157748.7 | F17: =+E17*$F$1 -> 3315636.1 | G17: =+D17*F17 -> 331563.61
B18: BOCA GABINETE COMPLETA | H18: =+SUM(G19:G22) -> 1796299.7
B19: Válvula tipo teatro de 2" BSP x 1 3/4"INC. | C19: u | D19: 4 | E19: =VLOOKUP(B19,Cotizaciones!B:D,3,0) -> 46242 | F19: =+E19*$F$1 -> 48554.1 | G19: =+D19*F19 -> 194216.4
B20: Gabinete para manguera de 1 3/4" con puerta hierro angulo . s/vidrio 500 x 550 x 160 mm. | C20: u | D20: 4 | E20: =VLOOKUP(B20,Cotizaciones!B:D,3,0) -> 53050 | F20: =+E20*$F$1 -> 55702.5 | G20: =+D20*F20 -> 222810
B21: Manguera sintética RYL JET sello IRAM de 1 3/4" x 25 mts. | C21: u | D21: 4 | E21: =VLOOKUP(B21,Cotizaciones!B:D,3,0) -> 300752.1 | F21: =+E21*$F$1 -> 315789.71 | G21: =+D21*F21 -> 1263158.8
B22: Lanza de 1 3/4" con boquilla chorro PLENO Y NIEBLA regulable | C22: u | D22: 4 | E22: =VLOOKUP(B22,Cotizaciones!B:D,3,0) -> 27646.3 | F22: =+E22*$F$1 -> 29028.615 | G22: =+D22*F22 -> 116114.46
B23: IMPULSION COMPLETA | H23: =+SUM(G24:G25) -> 141426.49
B24: Válvula de Impulsión para Piso o Pared c/anilla giratoria de 2 1/2" | D24: 1 | E24: =VLOOKUP(B24,Cotizaciones!B:D,3,0) -> 78188.1 | F24: =+E24*$F$1 -> 82097.505 | G24: =+D24*F24 -> 82097.505
B25: Tapa con inscripción BOMBEROS para piso chapa antideslizante | D25: 1 | E25: =VLOOKUP(B25,Cotizaciones!B:D,3,0) -> 56503.8 | F25: =+E25*$F$1 -> 59328.99 | G25: =+D25*F25 -> 59328.99
G26: =+SUM(G4:G25) -> 5427038.5 | H26: =+SUM(H4:H25) -> 4031313.6

Sheet ELECT
F1: 45505 | G1: 16700.7
F2: 45536 | G2: 17016.6
G3: =+G2/G1 -> 1.0189154
C4: Especificacion | D4: Unid | E4: Cant | F4: P Unit | G4: P.ACT | H4: Subtotal
B5: TSG Tablero de servicios Generales | I5: =+SUM(H6:H28) -> 1524162.9
B6: ID interruptos diferencial
B7: STECK DIFERENCIAL 2X25A 30MA | C7: 2x16 A | D7: u | E7: 2 | F7: =VLOOKUP(B7,Cotizaciones!B:D,3,0) -> 26260.49 | G7: =+F7*$G$3 -> 26757.217 | H7: =+E7*G7 -> 53514.434
B8: STECK DIFERENCIAL 2X25A 30MA | C8: 2x20 A | D8: u | E8: 2 | F8: =VLOOKUP(B8,Cotizaciones!B:D,3,0) -> 26260.49 | G8: =+F8*$G$3 -> 26757.217 | H8: =+E8*G8 -> 53514.434
B9: STECK DIFERENCIAL 4X40A 30MA | C9: 4x40 A | D9: u | E9: 1 | F9: =VLOOKUP(B9,Cotizaciones!B:D,3,0) -> 50827.41 | G9: =+F9*$G$3 -> 51788.83 | H9: =+E9*G9 -> 51788.83
B10: STECK DIFERENCIAL 4X63A 30MA | C10: 4x63 A | D10: u | E10: 1 | F10: =VLOOKUP(B10,Cotizaciones!B:D,3,0) -> 61558.32 | G10: =+F10*$G$3 -> 62722.719 | H10: =+E10*G10 -> 62722.719
B11: Llave termomagnetica | G11: =+F11*$G$3 -> 0 | H11: =+E11*G11 -> 0
B12: STECK TM BIPOLAR 10A 6KA | C12: 2x10 A | D12: u | E12: 5 | F12: =VLOOKUP(B12,Cotizaciones!B:D,3,0) -> 7482.76 | G12: =+F12*$G$3 -> 7624.2992 | H12: =+E12*G12 -> 38121.496
B13: STECK TM BIPOLAR 16A 6KA | C13: 2x16 A | D13: u | E13: 10 | F13: =VLOOKUP(B13,Cotizaciones!B:D,3,0) -> 7482.76 | G13: =+F13*$G$3 -> 7624.2992 | H13: =+E13*G13 -> 76242.992
B14: STECK TM TETRAPOLAR 32A 6KA | C14: 4x32 A | D14: u | E14: 1 | F14: =VLOOKUP(B14,Cotizaciones!B:D,3,0) -> 15812.97 | G14: =+F14*$G$3 -> 16112.078 | H14: =+E14*G14 -> 16112.078
B15: STECK TM TETRAPOLAR 50A 6KA | C15: 4x50 A | D15: u | E15: 1 | F15: =VLOOKUP(B15,Cotizaciones!B:D,3,0) -> 16942.47 | G15: =+F15*$G$3 -> 17262.943 | H15: =+E15*G15 -> 17262.943
B16: GAB. IP65 SERIE 9000 600X900X225 | D16: u | E16: 1 | F16: =VLOOKUP(B16,Cotizaciones!B:D,3,0) -> 291510.24 | G16: =+F16*$G$3 -> 297024.27 | H16: =+E16*G16 -> 297024.27
B17: CONTRAF ABISAG CALADO 60BIP S9000 600X900 | D17: u | E17: 1 | F17: =VLOOKUP(B17,Cotizaciones!B:D,3,0) -> 104750.48 | G17: =+F17*$G$3 -> 106731.87 | H17: =+E17*G17 -> 106731.87
B18: RIEL DIN 35MM 1 METRO PERFOR. | D18: u | E18: 4 | F18: =VLOOKUP(B18,Cotizaciones!B:D,3,0) -> 5557.26 | G18: =+F18*$G$3 -> 5662.3777 | H18: =+E18*G18 -> 22649.511
B19: RIEL PORTA ELEMENTOS X 1 METRO | D19: u | E19: 4 | F19: =VLOOKUP(B19,Cotizaciones!B:D,3,0) -> 16022.49 | G19: =+F19*$G$3 -> 16325.561 | H19: =+E19*G19 -> 65302.246
B20: SOP REG P/CONTRAFRENTE PROF 225 X1 | D20: u | E20: 12 | F20: =VLOOKUP(B20,Cotizaciones!B:D,3,0) -> 10131.37 | G20: =+F20*$G$3 -> 10323.009 | H20: =+E20*G20 -> 123876.1
B21: INTERRUPTOR COMPACTO 4X125A S250 | C21: Contactos 4 x 125A | D21: u | E21: 1 | F21: =VLOOKUP(B21,Cotizaciones!B:D,3,0) -> 171683.7 | G21: =+F21*$G$3 -> 174931.16 | H21: =+E21*G21 -> 174931.16
B22: DISTRIBUIDOR TETRAP.160A 15 STD | C22: Distribuidor tetrapolar 160a | D22: u | E22: 1 | F22: =VLOOKUP(B22,Cotizaciones!B:D,3,0) -> 154788.57 | G22: =+F22*$G$3 -> 157716.45 | H22: =+E22*G22 -> 157716.45
B23: TERMINAL COBRE SCC 120-2 (5/8) | C23: Terminal de cobre 50mm | D23: u | E23: 10 | F23: =VLOOKUP(B23,Cotizaciones!B:D,3,0) -> 5230.67 | G23: =+F23*$G$3 -> 5329.6101 | H23: =+E23*G23 -> 53296.101
B24: Voltimetro Display Ojo de Buey 22 mm | C24: Ojo de buey panel | D24: u | E24: 3 | F24: =VLOOKUP(B24,Cotizaciones!B:D,3,0) -> 4061.9835 | G24: =+F24*$G$3 -> 4138.8174 | H24: =+E24*G24 -> 12416.452
B25: Bornera puesta a tierra | D25: u | E25: 1 | G25: =+F25*$G$3 -> 0 | H25: =+E25*G25 -> 0
B26: Rollo cable | C26: 1 x 6 mm | D26: u | E26: 1 | G26: =+F26*$G$3 -> 0 | H26: =+E26*G26 -> 0
B27: Seccion de cable | G27: =+F27*$G$3 -> 0 | H27: =+E27*G27 -> 0
B28: Consumibles, desperdicio | D28: gl | E28: 0.1 | F28: =+SUM(H7:H27) -> 1383224.1 | G28: =+F28*$G$3 -> 1409388.3 | H28: =+E28*G28 -> 140938.83
B29: TSBI Tablero Seccional Bomba Impulsora | I29: =+SUM(H30:H38) -> 651921.6
B30: STECK DIFERENCIAL 2X25A 30MA | C30: 2 x 20 A | D30: u | E30: 1 | F30: =VLOOKUP(B30,Cotizaciones!B:D,3,0) -> 26260.49 | G30: =+F30*$G$3 -> 26757.217 | H30: =+E30*G30 -> 26757.217
B31: STECK TM BIPOLAR 16A 6KA | C31: 2 x 16 | D31: u | E31: 2 | F31: =VLOOKUP(B31,Cotizaciones!B:D,3,0) -> 7482.76 | G31: =+F31*$G$3 -> 7624.2992 | H31: =+E31*G31 -> 15248.598
B32: STECK TM BIPOLAR 10A 6KA | C32: 2 x 10 | D32: u | E32: 1 | F32: =VLOOKUP(B32,Cotizaciones!B:D,3,0) -> 7482.76 | G32: =+F32*$G$3 -> 7624.2992 | H32: =+E32*G32 -> 7624.2992
B33: LC1D18M7 18A 7,5KW 1+1 220V | C33: 16 A nc/no 220V | D33: u | E33: 2 | F33: =VLOOKUP(B33,Cotizaciones!B:D,3,0) -> 97328.45 | G33: =+F33*$G$3 -> 99169.454 | H33: =+E33*G33 -> 198338.91
B34: ALTERNADOR 2 BOMBA DIGITAL 24/110/220VCA | C34: 3 A 220V | D34: u | E34: 1 | F34: =VLOOKUP(B34,Cotizaciones!B:D,3,0) -> 140783.76 | G34: =+F34*$G$3 -> 143446.74 | H34: =+E34*G34 -> 143446.74
B35: Voltimetro Display Ojo de Buey 22 mm | D35: u | E35: 1 | F35: =VLOOKUP(B35,Cotizaciones!B:D,3,0) -> 4061.9835 | G35: =+F35*$G$3 -> 4138.8174 | H35: =+E35*G35 -> 4138.8174
B36: GAB. IP65 SERIE 9000 450X450X225 | C36: 450 X 450 X 150 | D36: u | E36: 1 | F36: =VLOOKUP(B36,Cotizaciones!B:D,3,0) -> 128686.18 | G36: =+F36*$G$3 -> 131120.33 | H36: =+E36*G36 -> 131120.33
B37: CONTRAF ABISAG.CALADO 18BIP S9000 450X450 | C37: p/Gabinete Genrod S900 IP66 | D37: u | E37: 1 | F37: =VLOOKUP(B37,Cotizaciones!B:D,3,0) -> 63757.72 | G37: =+F37*$G$3 -> 64963.721 | H37: =+E37*G37 -> 64963.721
B38: Consumibles, desperdicio | D38: gl | E38: 0.1 | F38: =+SUM(H30:H37) -> 591638.63 | G38: =+F38*$G$3 -> 602829.69 | H38: =+E38*G38 -> 60282.969
B39: TS.ASC Tablero Ascensor | I39: =+SUM(H40:H45) -> 304564.37
B40: STECK TM TETRAPOLAR 32A 6KA | C40: 4x32A | D40: u | E40: 1 | F40: =VLOOKUP(B40,Cotizaciones!B:D,3,0) -> 15812.97 | G40: =+F40*$G$3 -> 16112.078 | H40: =+E40*G40 -> 16112.078
B41: STECK DIFERENCIAL 4X40A 30MA | C41: 4x40A | D41: u | E41: 1 | F41: =VLOOKUP(B41,Cotizaciones!B:D,3,0) -> 50827.41 | G41: =+F41*$G$3 -> 51788.83 | H41: =+E41*G41 -> 51788.83
B42: Voltimetro Display Ojo de Buey 22 mm | D42: u | E42: 3 | F42: =VLOOKUP(B42,Cotizaciones!B:D,3,0) -> 4061.9835 | G42: =+F42*$G$3 -> 4138.8174 | H42: =+E42*G42 -> 12416.452
B43: GAB. IP65 SERIE 9000 450X450X225 | C43: 450 X 450 X 150 | D43: u | E43: 1 | F43: =VLOOKUP(B43,Cotizaciones!B:D,3,0) -> 128686.18 | G43: =+F43*$G$3 -> 131120.33 | H43: =+E43*G43 -> 131120.33
B44: CONTRAF ABISAG.CALADO 18BIP S9000 450X450 | C44: p/Gabinete Genrod S900 IP66 | D44: u | E44: 1 | F44: =VLOOKUP(B44,Cotizaciones!B:D,3,0) -> 63757.72 | G44: =+F44*$G$3 -> 64963.721 | H44: =+E44*G44 -> 64963.721
B45: Consumibles, desperdicio | D45: gl | E45: 0.1 | F45: =+SUM(H40:H44) -> 276401.41 | G45: =+F45*$G$3 -> 281629.64 | H45: =+E45*G45 -> 28162.964
B46: TS BP Tablero S Bomba Presurizadora | G46: =+F46*$G$3 -> 0 | H46: =+E46*G46 -> 0 | I46: =+SUM(H47:H55) -> 540706.66
B47: STECK TM BIPOLAR 16A 6KA | C47: 2x16A | D47: u | E47: 2 | F47: =VLOOKUP(B47,Cotizaciones!B:D,3,0) -> 7482.76 | G47: =+F47*$G$3 -> 7624.2992 | H47: =+E47*G47 -> 15248.598
B48: STECK TM BIPOLAR 10A 6KA | C48: 2 x 10A | D48: u | E48: 1 | F48: =VLOOKUP(B48,Cotizaciones!B:D,3,0) -> 7482.76 | G48: =+F48*$G$3 -> 7624.2992 | H48: =+E48*G48 -> 7624.2992
B49: STECK DIFERENCIAL 2X25A 30MA | C49: 2x20A | D49: u | E49: 1 | F49: =VLOOKUP(B49,Cotizaciones!B:D,3,0) -> 26260.49 | G49: =+F49*$G$3 -> 26757.217 | H49: =+E49*G49 -> 26757.217
B50: Voltimetro Display Ojo de Buey 22 mm | D50: u | E50: 1 | F50: =VLOOKUP(B50,Cotizaciones!B:D,3,0) -> 4061.9835 | G50: =+F50*$G$3 -> 4138.8174 | H50: =+E50*G50 -> 4138.8174
B51: LC1D18M7 18A 7,5KW 1+1 220V | C51: 16 A nc/no 220V | D51: u | E51: 2 | F51: =VLOOKUP(B51,Cotizaciones!B:D,3,0) -> 97328.45 | G51: =+F51*$G$3 -> 99169.454 | H51: =+E51*G51 -> 198338.91
B52: ALTERNADOR 2 BOMBA DIGITAL 24/110/220VCA | C52: 3 A 220V | D52: u | E52: 1 | F52: =VLOOKUP(B52,Cotizaciones!B:D,3,0) -> 140783.76 | G52: =+F52*$G$3 -> 143446.74 | H52: =+E52*G52 -> 143446.74
B53: GAB. IP65 SERIE 9000 300X300X150 | C53: 300 X 300 X 150 | D53: u | E53: 1 | F53: =VLOOKUP(B53,Cotizaciones!B:D,3,0) -> 56497.68 | G53: =+F53*$G$3 -> 57566.355 | H53: =+E53*G53 -> 57566.355
B54: CONTRAF ABISAG.CALADO 10BIP S9000 300X300 | C54: p/Gabinete Genrod S900 IP66 | D54: u | E54: 1 | F54: =VLOOKUP(B54,Cotizaciones!B:D,3,0) -> 36889 | G54: =+F54*$G$3 -> 37586.769 | H54: =+E54*G54 -> 37586.769
B55: Consumibles, desperdicio | D55: gl | E55: 0.1 | F55: =+SUM(H47:H54) -> 490707.7 | G55: =+F55*$G$3 -> 499989.62 | H55: =+E55*G55 -> 49998.962
B56: TUF - Monofásico | I56: =+SUM(H57:H63) -> 178279.7 | L56: Mod | M56: Total
B57: STECK TM BIPOLAR 10A 6KA | C57: 2 x 10 | D57: u | E57: 1 | F57: =VLOOKUP(B57,Cotizaciones!B:D,3,0) -> 7482.76 | G57: =+F57*$G$3 -> 7624.2992 | H57: =+E57*G57 -> 7624.2992 | L57: 2 | M57: =+E57*L57 -> 2
B58: STECK TM BIPOLAR 16A 6KA | C58: 2 x 16 | D58: u | E58: 1 | F58: =VLOOKUP(B58,Cotizaciones!B:D,3,0) -> 7482.76 | G58: =+F58*$G$3 -> 7624.2992 | H58: =+E58*G58 -> 7624.2992 | L58: 2 | M58: =+E58*L58 -> 2
B59: STECK TM BIPOLAR 16A 6KA | C59: 2 x 20 | D59: u | E59: 2 | F59: =VLOOKUP(B59,Cotizaciones!B:D,3,0) -> 7482.76 | G59: =+F59*$G$3 -> 7624.2992 | H59: =+E59*G59 -> 15248.598 | L59: 2 | M59: =+E59*L59 -> 4
B60: STECK DIFERENCIAL 2X25A 30MA | C60: 2 x 40 | D60: u | E60: 2 | F60: =VLOOKUP(B60,Cotizaciones!B:D,3,0) -> 26260.49 | G60: =+F60*$G$3 -> 26757.217 | H60: =+E60*G60 -> 53514.434 | J60: Coloco 2 porque no tengo el precio de 2X40 | L60: 2 | M60: =+E60*L60 -> 4
B61: STECK DIFERENCIAL 2X25A 30MA | C61: 2 x 25 | D61: u | E61: 2 | F61: =VLOOKUP(B61,Cotizaciones!B:D,3,0) -> 26260.49 | G61: =+F61*$G$3 -> 26757.217 | H61: =+E61*G61 -> 53514.434 | L61: 2 | M61: =+E61*L61 -> 4
B62: CAJA EMB P/ TM 24 POLOS BC T/FUME | D62: u | E62: 1 | F62: =VLOOKUP(B62,Cotizaciones!B:D,3,0) -> 23817.65 | G62: =+F62*$G$3 -> 24268.17 | H62: =+E62*G62 -> 24268.17 | M62: =+SUM(M57:M61) -> 16
B63: Consumibles, desperdicio | D63: gl | E63: 0.1 | F63: =+SUM(H57:H62) -> 161794.23 | G63: =+F63*$G$3 -> 164854.63 | H63: =+E63*G63 -> 16485.463
B64: TUF -Trifásico | I64: =+SUM(H65:H73) -> 246945.71
B65: STECK DIFERENCIAL 4X40A 30MA | C65: 4 x 40 | D65: u | E65: 1 | F65: =VLOOKUP(B65,Cotizaciones!B:D,3,0) -> 50827.41 | G65: =+F65*$G$3 -> 51788.83 | H65: =+E65*G65 -> 51788.83 | L65: 4 | M65: =+E65*L65 -> 4
B66: STECK DIFERENCIAL 4X25A 30MA | C66: 4 x 20 | D66: u | E66: 1 | F66: =VLOOKUP(B66,Cotizaciones!B:D,3,0) -> 48568.42 | G66: =+F66*$G$3 -> 49487.11 | H66: =+E66*G66 -> 49487.11 | L66: 4 | M66: =+E66*L66 -> 4
B67: STECK DIFERENCIAL 2X25A 30MA | C67: 2 x 25 | D67: u | E67: 2 | F67: =VLOOKUP(B67,Cotizaciones!B:D,3,0) -> 26260.49 | G67: =+F67*$G$3 -> 26757.217 | H67: =+E67*G67 -> 53514.434 | L67: 2 | M67: =+E67*L67 -> 4
B68: STECK TM TETRAPOLAR 16A 6KA | C68: 4 x 16 | D68: u | E68: 1 | F68: =VLOOKUP(B68,Cotizaciones!B:D,3,0) -> 15812.97 | G68: =+F68*$G$3 -> 16112.078 | H68: =+E68*G68 -> 16112.078 | L68: 4 | M68: =+E68*L68 -> 4
B69: STECK TM BIPOLAR 16A 6KA | C69: 2 x 16 | D69: u | E69: 1 | F69: =VLOOKUP(B69,Cotizaciones!B:D,3,0) -> 7482.76 | G69: =+F69*$G$3 -> 7624.2992 | H69: =+E69*G69 -> 7624.2992 | L69: 2 | M69: =+E69*L69 -> 2
B70: STECK TM BIPOLAR 10A 6KA | C70: 2 x 10 | D70: u | E70: 1 | F70: =VLOOKUP(B70,Cotizaciones!B:D,3,0) -> 7482.76 | G70: =+F70*$G$3 -> 7624.2992 | H70: =+E70*G70 -> 7624.2992 | L70: 2 | M70: =+E70*L70 -> 2
B71: STECK TM BIPOLAR 16A 6KA | C71: 2 x 20 | D71: u | E71: 1 | F71: =VLOOKUP(B71,Cotizaciones!B:D,3,0) -> 7482.76 | G71: =+F71*$G$3 -> 7624.2992 | H71: =+E71*G71 -> 7624.2992 | L71: 2 | M71: =+E71*L71 -> 2
B72: CAJA EMB P/ TM 36 POLOS BC T/FUME | D72: u | E72: 1 | F72: =VLOOKUP(B72,Cotizaciones!B:D,3,0) -> 29772.22 | G72: =+F72*$G$3 -> 30335.373 | H72: =+E72*G72 -> 30335.373 | M72: =+SUM(M65:M71) -> 22
B73: Consumibles, desperdicio | D73: gl | E73: 0.1 | F73: =+SUM(H65:H72) -> 224110.72 | G73: =+F73*$G$3 -> 228349.86 | H73: =+E73*G73 -> 22834.986
B74: Puesta a tierra | I74: =+SUM(H75:H79) -> 1261512.2
B75: M COBRE DESNUDO 7H 25MM | C75: 1 x 25 desnudo | D75: ml | E75: 100 | F75: =VLOOKUP(B75,Cotizaciones!B:D,3,0) -> 8408.235 | G75: =+F75*$G$3 -> 8567.2799 | H75: =+E75*G75 -> 856727.99
B76: CONDUWELD JAB ST 3/4 1.5M | C76: Jabalina 3/4" x 1,5 m | D76: u | E76: 5 | F76: =VLOOKUP(B76,Cotizaciones!B:D,3,0) -> 34242.55 | G76: =+F76*$G$3 -> 34890.261 | H76: =+E76*G76 -> 174451.3
B77: CONDUWELD TOMACABLE 3 | D77: u | E77: 5 | F77: =VLOOKUP(B77,Cotizaciones!B:D,3,0) -> 21131.19 | G77: =+F77*$G$3 -> 21530.894 | H77: =+E77*G77 -> 107654.47
B78: CAJA INSPECCION 15 x 15 PVC | D78: u | E78: 5 | F78: =VLOOKUP(B78,Cotizaciones!B:D,3,0) -> 1182.98 | G78: =+F78*$G$3 -> 1205.3565 | H78: =+E78*G78 -> 6026.7826
B79: Consumibles, desperdicio | D79: gl | E79: 0.1 | F79: =+SUM(H75:H78) -> 1144860.5 | G79: =+F79*$G$3 -> 1166516 | H79: =+E79*G79 -> 116651.6
B80: ACOMETIDA | I80: =+SUM(H81:H89) -> 5844722.2 | M80: MONO | N80: TRI
B81: M SUBTERRANEO N IRAM 1X 120MM2 | C81: 1 x 120 | D81: ml | E81: 50 | F81: =VLOOKUP(B81,Cotizaciones!B:D,3,0) -> 26132.22 | G81: =+F81*$G$3 -> 26626.521 | H81: =+E81*G81 -> 1331326 | L81: SG | N81: 1
B82: Gabinete columna 4 modulos trifasico Edesur | D82: u | F82: =VLOOKUP(B82,Cotizaciones!B:D,3,0) -> 968320.03 | G82: =+F82*$G$3 -> 986636.17 | H82: =+E82*G82 -> 0 | L82: LOCAL | N82: 1
B83: Gabinete columna 2 modulos trifasico Edesur | D83: u | E83: 1 | F83: =VLOOKUP(B83,Cotizaciones!B:D,3,0) -> 490352.21 | G83: =+F83*$G$3 -> 499627.41 | H83: =+E83*G83 -> 499627.41 | L83: PB | M83: 1
B84: Gabinete columna 12 modulos monofasico Edesur | D84: u | E84: 0 | F84: =VLOOKUP(B84,Cotizaciones!B:D,3,0) -> 1536497.2 | G84: =+F84*$G$3 -> 1565560.6 | H84: =+E84*G84 -> 0 | L84: 1° a 3° | M84: =4*3 -> 12
B85: Gabinete columna 3 modulos monofasico Edesur | D85: u | E85: 6 | F85: =VLOOKUP(B85,Cotizaciones!B:D,3,0) -> 440053.56 | G85: =+F85*$G$3 -> 448377.34 | H85: =+E85*G85 -> 2690264 | L85: 4° | M85: 3
B86: Caja de toma y secc. 400A c/6 bases NH T3 | D86: u | E86: 1 | F86: =VLOOKUP(B86,Cotizaciones!B:D,3,0) -> 546855.75 | G86: =+F86*$G$3 -> 557199.73 | H86: =+E86*G86 -> 557199.73 | M86: =+SUM(M81:M85) -> 16 | N86: =+SUM(N81:N85) -> 2
B87: Fusible NH 00 63 A | D87: u | E87: =+O88 -> 22 | F87: =VLOOKUP(B87,Cotizaciones!B:D,3,0) -> 4958.6777 | G87: =+F87*$G$3 -> 5052.4729 | H87: =+E87*G87 -> 111154.4 | L87: Fusible | M87: 1 | N87: 3
B88: Fusible NH 02 a 125 A | D88: u | E88: 6 | F88: =VLOOKUP(B88,Cotizaciones!B:D,3,0) -> 18760.331 | G88: =+F88*$G$3 -> 19115.189 | H88: =+E88*G88 -> 114691.14 | M88: =+M86*M87 -> 16 | N88: =+N86*N87 -> 6 | O88: =+SUM(M88:N88) -> 22
B89: Consumibles, desperdicio | D89: u | E89: 0.1 | F89: =+SUM(H81:H88) -> 5304262.7 | G89: =+F89*$G$3 -> 5404594.9 | H89: =+E89*G89 -> 540459.49
B90: MONTANTE | I90: =+SUM(H91:H114) -> 5773133.1 | R90: 3 | S90: 5 | T90: 5 | U90: 5
B91: PARTE MECANICA / PLENO | K91: PISO | L91: Cant caños | M91: h | N91: Total m | Q91: Alim | R91: 3 X 10 | S91: 5 X 10 | T91: 5 x 4 | U91: 5 x 16
B92: CAÑOX3M RIGIDO 25MM PVC TUBE | D92: u | E92: =+N99/3 -> 50 | F92: =VLOOKUP(B92,Cotizaciones!B:D,3,0) -> 2000.78 | G92: =+F92*$G$3 -> 2038.6255 | H92: =+E92*G92 -> 101931.28 | K92: 1 | L92: 16 | M92: 3 | N92: =+L92*M92 -> 48 | Q92: SG | U92: =10+4+2 -> 16
B93: RIEL DE FIJAC.1.22 OLMAR | D93: u | E93: =ROUNDUP(M97/3,0) -> 6 | F93: =VLOOKUP(B93,Cotizaciones!B:D,3,0) -> 5522.38 | G93: =+F93*$G$3 -> 5626.8379 | H93: =+E93*G93 -> 33761.027 | K93: 2 | L93: 12 | M93: 3 | N93: =+L93*M93 -> 36 | Q93: BOMBAS PB | T93: 5
B94: BROCA METALICA 1/4 CJA X 100 | D94: u | E94: =+E93*6/100 -> 0.36 | F94: =VLOOKUP(B94,Cotizaciones!B:D,3,0) -> 77112 | G94: =+F94*$G$3 -> 78570.602 | H94: =+E94*G94 -> 28285.417 | K94: 3 | L94: 8 | M94: 3 | N94: =+L94*M94 -> 24 | Q94: LOCAL | R94: =4+6 -> 10
B95: VARILLA ROSCADA 1/4"X1MTC/BUL. | D95: u | E95: =E93 -> 6 | F95: =VLOOKUP(B95,Cotizaciones!B:D,3,0) -> 1197.81 | G95: =+F95*$G$3 -> 1220.467 | H95: =+E95*G95 -> 7322.8022 | K95: 4 | L95: 4 | M95: 3 | N95: =+L95*M95 -> 12 | Q95: PB | R95: =17+2+2 -> 21
B96: GRAMPA P/RIEL 1 | D96: u | E96: =+N99 -> 150 | F96: =VLOOKUP(B96,Cotizaciones!B:D,3,0) -> 778.4 | G96: =+F96*$G$3 -> 793.12373 | H96: =+E96*G96 -> 118968.56 | K96: AZ | L96: 1 | M96: 6 | N96: =+L96*M96 -> 6 | Q96: 1A | R96: =12+4+5+2 -> 23
B97: CAJA DE CONEXION 30X40X10 CH20 | D97: u | E97: 7 | F97: =VLOOKUP(B97,Cotizaciones!B:D,3,0) -> 18151.02 | G97: =+F97*$G$3 -> 18494.353 | H97: =+E97*G97 -> 129460.47 | M97: =SUM(M92:M101) -> 18 | N97: =SUM(N92:N96) -> 126 | Q97: 1B | R97: =12+4+6+2 -> 24
B98: CONECTOR 25MM PVC RIG IP54 TUBE | D98: u | E98: =+E92*2 -> 100 | F98: =VLOOKUP(B98,Cotizaciones!B:D,3,0) -> 258.57 | G98: =+F98*$G$3 -> 263.46095 | H98: =+E98*G98 -> 26346.095 | N98: =+N97*O98 -> 144.9 | O98: 1.15 | Q98: 1C | R98: =12+4+6+2 -> 24
B99: PARTE MECANICA / SUSP. PB | N99: 150 | Q99: 1D | R99: =12+4+8+2 -> 26
B100: CAÑOX3M RIGIDO 25MM PVC TUBE | D100: u | E100: =9*L92/3 -> 48 | F100: =VLOOKUP(B100,Cotizaciones!B:D,3,0) -> 2000.78 | G100: =+F100*$G$3 -> 2038.6255 | H100: =+E100*G100 -> 97854.024 | Q100: 2A | R100: =12+7+5+2 -> 26
...

Sheet Cotizaciones
I1: =+GGBB!H2 -> 45590
B2: Descripcion | C2: Un | D2: P unit | E2: Proveedor | F2: Fecha | H2: DÓLAR BNA | I2: DÓLAR MEP
B3: PRELIMINARES | H3: =+GGBB!G4 -> 1005 | I3: =+GGBB!H4 -> 1170
B4: C. CIN. T101 ESP 0,50 MM (C25) | C4: m2 | D4: =12825.98/1.21 -> 10599.983 | E4: CMP Web | F4: 45588
B5: Peril UPN 100 x 12 m | C5: bar | D5: =323093.01/1.21 -> 267019.02 | E5: CMP Web | F5: 45588
B6: Tubo estructural 40 x 40 x 2, Largo 6 metros | C6: bar | D6: =31763.25/1.21 -> 26250.62 | E6: CMP Web | F6: 45588
B7: Riel Roma 174 e: 2,1 mm. 53 x 60 x 6000 | C7: bar | D7: =98627.04/1.21 -> 81509.95 | E7: CMP Web | F7: 45588
B8: Carro acero 174 4 ruedas puertas portones Ø45mm | C8: u | D8: =14679.19/1.21 -> 12131.562 | E8: CMP Web | F8: 45588
B9: PLACA CEMENTICIA CONSTRUCCION SECO SUPERBOARD ESTRUCTURAL BORDE RECTO 10MM X 1200MM X 2400MM | C9: u | D9: =55733.05/1.21 -> 46060.372 | E9: CMP Web | F9: 45588
B10: CHAPA LISA GALVANIZADA C27 - 1,22 x 2,00 m | C10: u | D10: =21053.99/1.21 -> 17399.992 | E10: CMP Web | F10: 45588
B11: CHAPA LISA GALVANIZADA C27 - 1,22 x 2,44 m | C11: u | D11: =25642.6/1.21 -> 21192.231 | E11: CMP Web | F11: 45588
B12: CHAPA LISA GALVANIZADA C25 - 1,22 x 2,00 m | C12: u | D12: =24557.6/1.21 -> 20295.537 | E12: CMP Web | F12: 45588
B13: CHAPA LISA GALVANIZADA C25 - 1,22 x 2,44 m | C13: u | D13: =29947.27/1.21 -> 24749.81 | E13: CMP Web | F13: 45588
B14: CHAPA LISA GALVANIZADA C22 - 1,22 x 2,44 m | C14: u | D14: =42498.43/1.21 -> 35122.669 | E14: CMP Web | F14: 45588
B15: CHAPA LISA PREP C25 - 1,22 x 2,44 m | C15: u | D15: =45382.84/1.21 -> 37506.479 | E15: CMP Web | F15: 45588 | H15: =+D15/D13 -> 1.5154249
B16: PERFIL ANGULO ALAS IGUALES ESTRUCTURAL ACERO 6M X 5/8" X 1/8 | C16: u | D16: =12662.63/1.21 -> 10464.983 | E16: CMP Web | F16: 45588
B17: MADERA
B18: Precio fenolico comun e: 18 mm | C18: placa | D18: 26322.68 | E18: NEWTON | F18: 45586
B19: Precio fenolico visto e: 18 mm | C19: placa | D19: 51752.74 | E19: NEWTON | F19: 45586
B20: Tabla 4 x 1 x 3,6 Saligna bruto | C20: u | D20: =539.43*3.6 -> 1941.948 | E20: NEWTON | F20: 45586
B21: Tirante 3 x 3 x 3,6 Saligna bruto | C21: u | D21: =1213.73*3.6 -> 4369.428 | E21: NEWTON | F21: 45586
B22: HORMIGON
B23: H13 6.20 | C23: m3 | D23: 115100 | E23: FENOMIX | F23: 45566
B24: H30 6.20 | C24: m3 | D24: 125000 | E24: FENOMIX | F24: 45566
B25: Piedra 6/12 | C25: m3 | D25: =130100-D24 -> 5100 | E25: FENOMIX | F25: 45566
B26: Acarreo | C26: gl | D26: 533000 | E26: FENOMIX | F26: 45566
B27: Bombeo | C27: m3 | D27: 5330 | E27: FENOMIX | F27: 45566
B28: Super | C28: m3 | D28: 1500 | E28: FENOMIX | F28: 45566
B29: Hidrofugo | C29: m3 | D29: =147200-D24 -> 22200 | E29: FENOMIX | F29: 45566
B30: HIERRO CONSTRUCCION
B31: Hierro del 6 | C31: kg | D31: 1704.41 | E31: NUQLEA | F31: 45575 | H31: =+D31/D38 -> 1.203195
B32: Hierro del 8 | C32: kg | D32: 1585.51 | E32: NUQLEA | F32: 45575 | H32: =+D32/D39 -> 1.1718911
B33: Hierro del 10 | C33: kg | D33: 1559.02 | E33: NUQLEA | F33: 45575 | H33: =+D33/D40 -> 1.1523116
B34: Hierro del 12 | C34: kg | D34: 1522.98 | E34: NUQLEA | F34: 45575 | H34: =+D34/D41 -> 1.1327735
B35: Hierro del 16 | C35: kg | D35: 1492.12 | E35: NUQLEA | F35: 45575 | H35: =+D35/D42 -> 1.1275239
B36: Hierro del 20 | C36: kg | D36: 1483.53 | E36: NUQLEA | F36: 45575 | H36: =+D36/D43 -> 1.1211175
B37: Hierro del 25 | C37: kg | D37: =+D36 -> 1483.53 | E37: NUQLEA | F37: 45575 | H37: =+D37/D44 -> 1.1211175
B38: Hierro del 6 | C38: kg | D38: 1416.57 | E38: CORIFERSA | F38: 45572
B39: Hierro del 8 | C39: kg | D39: 1352.95 | E39: CORIFERSA | F39: 45572
B40: Hierro del 10 | C40: kg | D40: 1352.95 | E40: CORIFERSA | F40: 45572
B41: Hierro del 12 | C41: kg | D41: 1344.47 | E41: CORIFERSA | F41: 45572
B42: Hierro del 16 | C42: kg | D42: 1323.36 | E42: CORIFERSA | F42: 45572
B43: Hierro del 20 | C43: kg | D43: 1323.26 | E43: CORIFERSA | F43: 45572
B44: Hierro del 25 | C44: kg | D44: =+D43 -> 1323.26 | E44: CORIFERSA | F44: 45572
B45: BAÑOS | K45: Indice CAC
B46: Baño portatil / Ducha | C46: u | D46: =+G46*$K$48 -> 73872.14 | E46: BATH | F46: 45588 | G46: 60000 | H46: 45387 | J46: 45352 | K46: 11669
B47: Traslado flete entrega/ retiro | C47: u | D47: =+G47*$K$48 -> 12312.023 | E47: BATH | F47: 45588 | G47: 10000 | H47: 45387 | J47: 45536 | K47: 14366.9
B48: CORRALON | K48: =+K47/K46 -> 1.2312023
B49: Telgopor 1 x 1 x 20 mm densidad 20 kg | C49: u | D49: 3502.8 | E49: CUTULI HNOS | F49: 45572
B50: Malla de fibra 5 x 5 90 gr, rollo 1 x 50 mts | C50: rol | D50: 35708.4 | E50: CUTULI HNOS | F50: 45572
B51: Liston refractario 230 x 65 x 19 | C51: u | D51: 417.3 | E51: CUTULI HNOS | F51: 45461
B52: Weber refractaro x 10 kg | C52: bol | D52: 15474.06 | E52: CUTULI HNOS | F52: 45572
B53: Yeso Knauf MP 40/75 Proyectable x 25 kg | C53: bol | D53: 6694.38 | E53: CUTULI HNOS | F53: 45572
B54: Guardacanto yesero 2 mts | C54: u | D54: 1159.2 | E54: CUTULI HNOS | F54: 45572
B55: PA-MAX PUENTE DE ADHERENCIA 20LT | C55: tac | D55: 124738 | E55: TODO PROYECT WEB | F55: 45588 | H55: 150 m2/balde
B56: BUÑA Z PERIMETRAL - Largo 2,60 mt | C56: un | D56: 2532.6 | E56: CUTULI HNOS | F56: 45572
B57: Malla N° 4 Liv 15 x 15 3 x 2 mt | C57: un | D57: 10337.35 | E57: CUTULI HNOS | F57: 45572
B58: Rollo Polietileno negro 2x50 mt x 200mic | C58: rol | D58: 27000 | E58: CUTULI HNOS | F58: 45572
B59: MEMBRANA C/GEOTEXTIL W450 | C59: rol | D59: 70192.21 | E59: CUTULI HNOS | F59: 45572
B60: BOLSON DE PIEDRA PARTIDA 6/20 | C60: bol | D60: 53805.78 | E60: CUTULI HNOS | F60: 45572
B61: Malla Q188 15 x 15 6 mm 6x2,40 | C61: u | D61: 75473.12 | E61: CUTULI HNOS | F61: 45572
B62: WEBER REFRACTARIO X 10KG (rend. 0,5 m2) | C62: bol | D62: 15474.06 | E62: CUTULI HNOS | F62: 45572
B63: LISTON REFRACTARIO 230x65x19 | C63: u | D63: 417.3 | E63: CUTULI HNOS | F63: 45366
B64: CEMENTO AVELLANEDA x 50 KG | C64: bol | D64: 7233.47 | E64: CUTULI HNOS | F64: 45572
B65: MERCADO LIBRE
B66: Sika WaterStop V-20, largo 15 mts | C66: rol | D66: =494587/1.21 -> 408749.59 | E66: ML | F66: 45588
B67: Tapa Y Marco Para Tanque De Hormigón Poliéster 52 X 52 Cm | C67: u | D67: =140000/1.21 -> 115702.48 | E67: ML | F67: 45588
B68: Varilla Guardacanto L Aluminio Cromo Mate 1663 12 Mm Atrim | C68: u | D68: =18957/1.21 -> 15666.942 | E68: DECO TURNER | F68: 45588
B69: REJILLAS
B70: Rejilla De Ventilacion 20 X 20 Fija - Retorno / Extraccion | C70: u | D70: =26800/1.21 -> 22148.76 | E70: ML | F70: 45588
B71: Caño Ventilación Corrugado Aluminio 4 Pulgadas X 1 Metro | C71: ml | D71: =7204/1.21 -> 5953.719 | E71: FIHOS WEB | F71: 45588
B72: Rejilla de ventilación fija 60 x 25 cm - Sala de maquinas de Asc. | C72: u | D72: =58814/1.21 -> 48606.612 | E72: SUREF WEB | F72: 45588 | G72: https://surefsuministros.mercadoshops.com.ar/MLA-1315412695-rejilla-de-ventilacion-60x25-fija-retorno-extraccion-_JM?gad_source=1&gclid=CjwKCAjwuMC2BhA7EiwAmJKRrBsF7v-jNZTqJpTBzXJ5xCG9oqcQTWkgAttZaEZuAUMNY4ZB49ecMBoCDdgQAvD_BwE
B73: Forzador de aire 720 m3/h - Sala de maquinas de Asc. | C73: u | D73: =150282/1.21 -> 124200 | E73: CLIMA TECNICA WEB | F73: 45588 | G73: https://www.climatecnica.com/forzador-de-aire-galaxia-serie-fs.72.477.html?srsltid=AfmBOoryxth9SwwxLj2AQttxVSWHrXEIwj3NaKPSBTM43SyGmw8M9lI3
B74: ELECTRICIDAD
B75: M PRYSMIAN VALIO 1X 50 MM2 | C75: ml | D75: 31318.27 | E75: CASTELAO | F75: 45510
B76: M SUBTERRANEO N IRAM 5X16 MM2 | C76: ml | D76: 20265.34 | E76: CASTELAO | F76: 45510
B77: M SUBTERRANEO N.IRAM 5X10 MM2 | C77: ml | D77: 13067.1 | E77: CASTELAO | F77: 45510
B78: M SUBTERRANEO N IRAM 5X 6 MM2 | C78: ml | D78: 7679.26 | E78: CASTELAO | F78: 45510
B79: M PRYSMIAN VALIO 3X10.00 MM2 | C79: ml | D79: 19909.93 | E79: CASTELAO | F79: 45510
B80: M SUBTERRANEO N IRAM 3X 6.00 MM2 | C80: ml | D80: 4705.56 | E80: CASTELAO | F80: 45510
B81: M SUBTERRANEO N IRAM 3X 4.00 MM2 | C81: ml | D81: 3424.42 | E81: CASTELAO | F81: 45510
B82: M SUBTERRANEO N IRAM 3X 2.50 MM2 | C82: ml | D82: 2257.38 | E82: CASTELAO | F82: 45510
B83: M SUBTERRANEO N IRAM 1X 120MM2 | C83: ml | D83: 26132.22 | E83: CASTELAO | F83: 45510
B84: M COBRE DESNUDO 7H 25MM | C84: ml | D84: 8408.235 | E84: CASTELAO | F84: 45386
B85: RLLOX100M 1X16 MM VD/ AM N.IRAM | C85: rol | D85: 341499 | E85: CASTELAO | F85: 45510
B86: RLLOX100M 1X 2,5MM NEGRO N.IRAM | C86: rol | D86: 54203.67 | E86: CASTELAO | F86: 45510
... B88: RLLOX100M 1X 4,0MM NEGRO N.IRAM | C88: rol | D88: 84641.86 | E88: CASTELAO | F88: 45510
B89: RLLOX100M 1X 6,0MM NEGRO N.IRAM | C89: rol | D89: =160000/1.21 -> 132231.4 | E89: ML | F89: 45531
B90: Cable unipolar 10 mm N.IRAM | C90: ml | D90: =30000/1.21/10 -> 2479.3388 | E90: ML | F90: 45531
B91: CONDUWELD JAB ST 3/4 1.5M | C91: u | D91: 34242.55 | E91: CASTELAO | F91: 45510
B92: CONDUWELD TOMACABLE 3 | C92: u | D92: 21131.19 | E92: CASTELAO | F92: 45510
B93: CAJA INSPECCION 15 x 15 PVC | C93: u | D93: 1182.98 | E93: CASTELAO | F93: 45510
B94: INT. TERMOMAGNETICO E9 2X10A 4,5KA | C94: u | D94: 17891.14 | E94: CASTELAO | F94: 45510
B95: INT. TERMOMAGNETICO E9 2X16A 4,5KA | C95: u | D95: 17891.14 | E95: CASTELAO | F95: 45510
B96: INT. TERMOMAGNETICO E9 2X20A 4,5KA | C96: u | D96: 17891.14 | E96: CASTELAO | F96: 45510
B97: INT. TERMOMAGNETICO E9 2X32A 4,5KA | C97: u | D97: 22988.05 | E97: CASTELAO | F97: 45510
B98: INT. DIFERENCIAL E9 2X25A 30MA | C98: u | D98: 73476.75 | E98: CASTELAO | F98: 45510
B99: INT. DIFERENCIAL E9 2X40A 30MA | C99: u | D99: 80300.97 | E99: CASTELAO | F99: 45510
B100: CAJA EMB P/ TM 24 POLOS BC T/FUME | C100: u | D100: 23817.65 | E100: CASTELAO | F100: 45510
B101: INTERRUPTOR COMPACTO 4X125A S250 | C101: u | D101: 171683.7 | E101: CASTELAO | F101: 45510
...

Sheet SUBCONTRATOS
J2: 10331 | K2: 45292 | M2: DÓLAR BNA | N2: DÓLAR MEP
B3: Descripcion | C3: Un | D3: Precio | E3: Fecha | F3: Contratista | H3: Pres. BASE ENE | J3: 14366.9 | K3: 45536 | M3: =+GGBB!G4 -> 1005 | N3: =+GGBB!H4 -> 1170
B4: GESTOR ELECTRICO | J4: =+J3/J2 -> 1.3906592 | K4: CAC
B5: Proyecto instalacion electrica | C5: gl | D5: =+H5*$J$4 -> 1126433.9 | E5: 45511 | F5: IGT | H5: 810000 | I5: 45356
B6: Baja de suministros | C6: gl | D6: =+H6*$J$4 -> 45891.753 | E6: 45511 | F6: IGT | H6: 33000 | I6: 45356
B7: Corte por demolicion | C7: gl | D7: =+H7*$J$4 -> 102908.78 | E7: 45511 | F7: IGT | H7: 74000 | I7: 45356
B8: Instalacion electrica desenergizada | C8: gl | D8: =+H8*$J$4 -> 126549.99 | E8: 45511 | F8: IGT | H8: 91000 | I8: 45356
B9: Traslado de alumbrado publico | C9: gl | D9: =+H9*$J$4 -> 107080.76 | E9: 45511 | F9: IGT | H9: 77000 | I9: 45356
B10: Factibilidad y renovacion | C10: gl | D10: =+H10*$J$4 -> 229458.76 | E10: 45511 | F10: IGT | H10: 165000 | I10: 45356
B11: Gestion suministros luz de obra | C11: gl | D11: =+H11*$J$4 -> 139065.92 | E11: 45511 | F11: IGT | H11: 100000 | I11: 45356
B12: Sala de medidores / Camara transformadora | C12: gl | D12: =+H12*$J$4 -> 486730.71 | E12: 45511 | F12: IGT | H12: 350000 | I12: 45356
B13: Certificados
B14: Luz de Obra | C14: u | D14: =+H14*$J$4 -> 100127.46 | E14: 45511 | F14: IGT | H14: 72000 | I14: 45356
B15: Servicios grales T1 | C15: u | D15: =+H15*$J$4 -> 100127.46 | E15: 45511 | F15: IGT | H15: 72000 | I15: 45356
B16: Servicios grales T2 | C16: u | D16: =+H16*$J$4 -> 147409.87 | E16: 45511 | F16: IGT | H16: 106000 | I16: 45356
B17: Residencial | C17: u | D17: =+H17*$J$4 -> 69532.959 | E17: 45511 | F17: IGT | H17: 50000 | I17: 45356
B18: Medicion PAT luz de obra | C18: u | D18: =+H18*$J$4 -> 87611.528 | E18: 45511 | F18: IGT | H18: 63000 | I18: 45356
B19: Medicion PAT adicional c/u tableros | C19: u | D19: =+H19*$J$4 -> 43805.764 | E19: 45511 | F19: IGT | H19: 31500 | I19: 45356
B20: ENSAYOS HORMIGON
B21: Ensayo probeta 15 x 30 x un | C21: gl | D21: 33900 | E21: 45581 | F21: INTI
B22: MOVIMIENTO DE SUELOS | I22: 45383 | J22: 10084.9
B23: Desmonte, retiro, aporte y compactación e: 40 cm | C23: m3 | D23: 16000 | E23: 45572 | F23: CELSI VIAL | I23: 45536 | J23: 10483.3 | L23: 0.665
B24: Subtotal obra | C24: gl | D24: 20000000 | E24: 45572 | F24: CELSI VIAL | J24: =+J23/J22 -> 1.0395046
B25: PROYECTABLE | H25: Base Agosto 24 | J25: Act. Sep 24 | L25: Cargas sociales
B26: Monolitico | C26: m2 | D26: =+L26 -> 7034.2417 | E26: 45510 | F26: JUAN VAZQUEZ | H26: 4500 | I26: 45510 | J26: =+H26*$J$24 -> 4677.7707 | L26: =+J26/$L$23 -> 7034.2417
B27: Alivianado | C27: m2 | D27: =+L27 -> 6252.6593 | E27: 45510 | F27: JUAN VAZQUEZ | H27: 4000 | I27: 45510 | J27: =+H27*$J$24 -> 4158.0184 | L27: =+J27/$L$23 -> 6252.6593
B28: Yeso | C28: m2 | D28: =+L28 -> 12817.952 | E28: 45510 | F28: JUAN VAZQUEZ | H28: 8200 | I28: 45510 | J28: =+H28*$J$24 -> 8523.9378 | L28: =+J28/$L$23 -> 12817.952
B29: Arista / Buña | C29: ml | D29: =+L29 -> 10160.571 | E29: 45510 | F29: JUAN VAZQUEZ | H29: 6500 | I29: 45510 | J29: =+H29*$J$24 -> 6756.7799 | L29: =+J29/$L$23 -> 10160.571
B30: Cantonera | C30: u | D30: =+L30 -> 10160.571 | E30: 45510 | F30: JUAN VAZQUEZ | H30: 6500 | I30: 45510 | J30: =+H30*$J$24 -> 6756.7799 | L30: =+J30/$L$23 -> 10160.571
B31: Revoque 3 en 1 | C31: m2 | D31: =+L31 -> 17194.813 | E31: 45510 | F31: JUAN VAZQUEZ | H31: 11000 | I31: 45510 | J31: =+H31*$J$24 -> 11434.551 | L31: =+J31/$L$23 -> 17194.813
B32: Buña en revoque | C32: ml | D32: =+L32 -> 8597.4065 | E32: 45510 | F32: JUAN VAZQUEZ | H32: 5500 | I32: 45510 | J32: =+H32*$J$24 -> 5717.2753 | L32: =+J32/$L$23 -> 8597.4065
B33: TARQUINI | J33: =+H33*$J$24 -> 0 | L33: =+J33/$L$23 -> 0
B34: Revestimiento plastico | C34: m2 | D34: =+L34 -> 7815.8241 | E34: 45510 | F34: CRISTIAN CAPONE | H34: 5000 | I34: 45510 | J34: =+H34*$J$24 -> 5197.523 | L34: =+J34/$L$23 -> 7815.8241
B35: Revestimiento plastico | C35: m2 | D35: =+L35 -> 10942.154 | E35: 45510 | F35: CRISTIAN CAPONE | G35: 15% plus altura + 25% menor rendimiento | H35: =+H34*1.4 -> 7000 | I35: 45510 | J35: =+H35*$J$24 -> 7276.5322 | L35: =+J35/$L$23 -> 10942.154 | M35: 15% plus altura + 25% menor rendimiento
B36: AA.CC - PREINSTALACIONES | G36: 36
B37: Preinstalacion MAT | C37: u | D37: =+G37/$G$36 -> 375000 | E37: 45580 | F37: GUILLERMO ERBA | G37: 13500000
B38: Preinstalacion M.O | C38: u | D38: =+G38/$G$36 -> 213888.89 | E38: 45580 | F38: GUILLERMO ERBA | G38: 7700000
B39: Instalacion y puesta en marcha | C39: u | D39: =+G39/$G$36 -> 189000 | E39: 45580 | F39: GUILLERMO ERBA | G39: 6804000
B40: INSTALACION ELECTRICA | G40: Precios WEB
B41: Canalización | C41: b | D41: =+G41*0.7 -> 22868.3 | E41: 45536 | F41: AAIERIC | G41: 32669
B42: Cableado | C42: b | D42: =+G42*0.7 -> 10018.4 | E42: 45536 | F42: AAIERIC | G42: 14312
B43: Boca completa | D43: =+D41+D42 -> 32886.7 | E43: 45536 | F43: AAIERIC
B44: Boca completa de ilum/toma + punto/toma | C44: b | D44: =+G44*0.7 -> 40714.8 | E44: 45536 | F44: AAIERIC | G44: 58164
B45: Conexión de punto y toma | C45: b | D45: =+G45*0.7 -> 7270.9 | E45: 45536 | F45: AAIERIC | G45: 10387
B46: Colocación artefacto | C46: u | D46: =+G46*0.7 -> 11158 | E46: 45536 | F46: AAIERIC | G46: 15940
B47: Colocación extractor de aire en baño | C47: u | D47: =+G47*0.7 -> 64400 | E47: 45566 | F47: ELECTRO INSTALADOR | G47: 92000
B48: Colocación Campana tipo Spar | C48: u | D48: =+G48*0.7 -> 59850 | E48: 45566 | F48: ELECTRO INSTALADOR | G48: 85500
B49: Luz de emergencia | C49: u | D49: =+G49*0.7 -> 17500 | E49: 45566 | F49: ELECTRO INSTALADOR | G49: 25000
B50: Tablero seccional de 8 a 36 polos | C50: u | D50: =+G50*0.45 -> 219841.65 | E50: 45536 | F50: AAIERIC | G50: 488537
B51: Tablero seccional de 36 a 54 polos | C51: u | D51: =+G51*0.45 -> 329747.4 | E51: 45536 | F51: AAIERIC | G51: 732772
B52: Bandeja portacable 300 mm | C52: u | D52: =+G52*0.7 -> 22190 | E52: 45566 | F52: ELECTRO INSTALADOR | G52: 31700
B53: Tendido de cable subterraneo | C53: ml | D53: =+G53*0.7 -> 20374.9 | E53: 45536 | F53: AAIERIC | G53: 29107
B54: Gabinete 4 medidores | C54: u | D54: =+G54*0.7 -> 292642.7 | E54: 45536 | F54: AAIERIC | G54: 418061
B55: Gabinete 1 medidor trif | C55: u | D55: =+G55*0.7 -> 92822.1 | E55: 45536 | F55: AAIERIC | G55: 132603
B56: Caño de acometida | C56: u | D56: =+G56*0.7 -> 85483.3 | E56: 45536 | F56: AAIERIC | G56: 122119 | K56: 45383 | L56: 7803.5
B57: Caja de toma | C57: u | D57: =+G57*0.7 -> 122165.4 | E57: 45536 | F57: AAIERIC | G57: 174522 | K57: 45536 | L57: 10483.3
B58: PAT de Servicio | C58: u | D58: =+G58*0.7 -> 61050.5 | E58: 45536 | F58: AAIERIC | G58: 87215 | L58: =+L57/L56 -> 1.34341 | M58: 0.7
B59: CALEFACCION | H59: 45385 | J59: dólar mep abril | K59: Cotización de peña | L59: ACT. CAC M.O | M59: Incidencia de obra
B60: Piso radiante + caldera | C60: gl | D60: =+M60 -> 16174657 | F60: ARIAS | H60: 17200 | I60: usd | J60: 1000 | K60: =+H60*J60 -> 17200000 | L60: =+K60*L58 -> 23106652 | M60: =+L60*M58 -> 16174657
G61: 1
B62: Tendido de cañerías | C62: u | D62: =+$D$60/$G$61*G62 -> 8896061.1 | F62: ARIAS | G62: 0.55 | H62: =+D62/16 -> 556003.82 | I62: x UF promedio
B63: Montaje de radiadores | C63: u | D63: =+$D$60/$G$61*G63 -> 4852397 | G63: 0.3 | H63: =+D63/81 -> 59906.135 | I63: x radiador
B64: Puesta en marcha de caldera | C64: u | D64: =+$D$60/$G$61*G64 -> 2426198.5 | F64: ARIAS | G64: 0.15 | H64: =+D64/16 -> 151637.4 | I64: x caldera
B65: DEPRESION DE NAPAS
B66: Perforación completa | C66: gl | D66: 2600000 | E66: 45569 | F66: Claudio Pizzutto
B67: Total de Obra (3 perforaciones) | C67: gl | D67: =+D66*3 -> 7800000 | E67: 45569 | F67: Claudio Pizzutto

Sheet APU 09.24
A1: , | K1: Mes: | L1: SEPTIEMBRE
K2: Año: | L2: 2024
K3: Revisado: | L3: MC
C5: ANALISIS DE PRECIO UNITARIO
C7: RESUMEN
E8: PRECIO UNITARIO
E9: Unitario Materiales: | H9: Unitario Mano de Obra: | K9: Unitario Equipos: | M9: RENDIMIENTO
A10: CODIGO | B10: PARTIDA | C10: DETALLE | E10: MAT | H10: MO | K10: EQUIPOS | L10: TOTAL | M10: u/dia
B11: 32 | C11: Movimiento de suelos para bases c/ aporte de tosca (e: 40 cm en 2 capas de 20 cm) | D11: m3 | E11: 12754.673 | H11: 5195.8848 | K11: 33014.25 | L11: 50964.808 | M11: 25
A12: ARQUIN21 | B12: 33 | C12: Ladrillo común 12,5 x 5,5 x 25 (e:15 cm) | D12: m2 | E12: 11614.318 | H12: 17863.898 | K12: 491.07421 | L12: 29969.29 | M12: 7
A13: ARQUIN21 | B13: 34 | C13: Ladrillo cerámico 8 x 18 x 33 cm | D13: m2 | E13: 6545.2009 | H13: 8336.4857 | K13: 229.16796 | L13: 15110.855 | M13: 15
A14: ARQUIN21 | B14: 35 | C14: Ladrillo cerámico 12 x 18 x 33 cm | D14: m2 | E14: 8229.0499 | H14: 8336.4857 | K14: 229.16796 | L14: 16794.704 | M14: 15
A15: ARQUIN21 | B15: 36 | C15: Ladrillo cerámico 18 x 18 x 33 cm | D15: m2 | E15: 11365.579 | H15: 8336.4857 | K15: 229.16796 | L15: 19931.233 | M15: 15
A16: ARQUIN21 | B16: 37 | C16: Pared DOBLE Comun / 5 / LHC 08 - (ladrillo a la vista) | D16: m2 | E16: 24204.422 | H16: 30138.301 | K16: 859.37987 | L16: 55202.103 | M16: 4
A17: ARQUIN21 | B17: 38 | C17: Ladrillo hueco portante 12 x 19 x 33 | D17: m2 | E17: 11461.565 | H17: 8336.4857 | K17: 229.16796 | L17: 20027.219 | M17: 15
A18: ARQUIN21 | B18: 39 | C18: Amure puertas tipo (0,90 x 2,00 m) | D18: u | E18: 3816.1086 | H18: 46892.732 | K18: 394.92626 | L18: 51103.767 | M18: 2
A19: ARQUIN21 | B19: 40 | C19: Amure Premarcos | D19: u | E19: 1396.3488 | H19: 31261.821 | K19: 197.46313 | L19: 32855.633 | M19: 4
A20: ARQUIN21 | B20: 41 | C20: Amure barandas (insertos c/1,00 m) | D20: ml | E20: 289.07023 | H20: 25009.457 | K20: 269.33199 | L20: 25567.859 | M20: 5
A21: ARQUIN21 | B21: 42 | C21: Azotado hidrófugo | D21: m2 | E21: 758.10738 | H21: 3395.9551 | K21: 122.76855 | L21: 4276.831 | M21: 28
A22: ARQUIN21 | B22: 43 | C22: Interior jaharro a la cal + Enlucido a la cal | D22: m2 | E22: 2606.0756 | H22: 17928.384 | K22: 572.91991 | L22: 21107.379 | M22: 6
A23: ARQUIN21 | B23: 44 | C23: Revoque Grueso impermeable Exterior hasta 3.00 m - Incl. Azotado hidrófugo | D23: m2 | E23: 3747.8693 | H23: 9136.834 | K23: 298.91474 | L23: 13183.618 | M23: 11.5
... A28: ARQUIN21 | B28: 49 | C28: Carpeta hidrófuga (e: 2 cm) | D28: m2 | E28: 3790.5369 | H28: 6505.5637 | K28: 210.62734 | L28: 10506.728 | M28: 15
A29: ARQUIN21 | B29: 50 | C29: Cemento alisado o cilindrado (e: 3 cm) | D29: m2 | E29: 3816.1086 | H29: 8702.6232 | K29: 274.73131 | L29: 12793.463 | M29: 11.5 | U29: perim | V29: h
A30: ARQUIN21 | B30: 51 | C30: Látex interior para paredes (incl. enduido) | D30: m2 | E30: 3131.614 | H30: 6526.9608 | K30: 170.31706 | L30: 9828.8919 | M30: 22 | O30: =+H30 -> 6526.9608 | Q30: Living | R30: 8 | S30: 4 | T30: =+R30*S30 -> 32 | U30: =+R30*2+S30*2 -> 24 | V30: 4.5 | W30: =+U30*V30 -> 108
A31: ARQUIN21 | B31: 52 | C31: látex para cielorrasos (incl. enduido) | D31: m2 | E31: 3131.614 | H31: 7422.6926 | K31: 234.7535 | L31: 10789.06 | M31: 17.5 | Q31: Cocina | R31: 3 | S31: 5 | T31: =+R31*S31 -> 15 | U31: =+R31*2+S31*2 -> 16 | V31: 1 | W31: =+U31*V31 -> 16
A32: ARQUIN21 | B32: 53 | C32: látex exterior para paredes hasta 3.00 m de altura | D32: m2 | E32: 2048.3671 | H32: 4846.0031 | K32: 120.87017 | L32: 7015.2404 | M32: 15.5 | Q32: Dormitori | R32: 6 | S32: 4 | T32: =+R32*S32 -> 24 | U32: =+R32*2+S32*2 -> 20 | V32: 4.5 | W32: =+U32*V32 -> 90
A33: ARQUIN22 | B33: 53 bis | C33: látex exterior para paredes a más 3.00 m de altura | D33: m2 | E33: 2048.3671 | H33: 12414.243 | K33: 228.30166 | L33: 14690.912 | M33: 15.5 | Q33: Dormitori | R33: 3 | S33: 4 | T33: =+R33*S33 -> 12 | U33: =+R33*2+S33*2 -> 14 | V33: 2 | W33: =+U33*V33 -> 28
A34: ARQUIN21 | B34: 54 | C34: Esmalte sintético sobre carpintería metálica , herrería (cuando es vacio x lleno contemplar MAT al 60%) | D34: m2 | E34: 2856.3898 | H34: 9389.131 | K34: 234.18596 | L34: 12479.707 | M34: 8 | Q34: Baño | R34: 3 | S34: 2 | T34: =+R34*S34 -> 6 | U34: =+R34*2+S34*2 -> 10 | V34: 1 | W34: =+U34*V34 -> 10 | Z34: =+Z36*1.35 -> 5070.1308
A35: ARQUIN21 | B35: 55 | C35: Revestimiento plastico texturado tipo Quimtex fino | D35: m2 | E35: 6006.8024 | H35: 9621.0381 | K35: 176.93379 | L35: 15804.774 | M35: 20 | Q35: Baño | R35: 1.5 | S35: 2 | T35: =+R35*S35 -> 3 | U35: =+R35*2+S35*2 -> 7 | V35: 1 | W35: =+U35*V35 -> 7
A36: ARQUIN21 | B36: 56 | C36: Colocación porcelanato en pisos (no incluye baños) | D36: m2 | E36: 7250.1087 | H36: 9992.0862 | K36: 219.89813 | L36: 17462.093 | M36: 13 | O36: 100 | T36: =+SUM(T30:T35) -> 92 | W36: =+SUM(W30:W35) -> 259 | Y36: =+T36+W36 -> 351 | Z36: =+H80 -> 3755.6524 | AA36: =+Y36*Z36 -> 1318234
A37: ARQUIN21 | B37: 57 | C37: Revestimiento porcelanato en paredes y piso baños | D37: m2 | E37: 7250.1087 | H37: 12989.712 | K37: 285.86757 | L37: 20525.688 | M37: 10 | Y37: =+Y36 -> 351 | Z37: 2126.0865 | AA37: =+Y37*Z37 -> 746256.36
A38: ARQUIN21 | B38: 58 | C38: Colocacion de zocalo porcelanato | D38: ml | E38: 1185.4173 | H38: 4329.904 | K38: 95.289189 | L38: 5610.6105 | M38: 30
A39: ARQUIN22 | B39: 59 | C39: Látex interior satinado para paredes | D39: m2 | E39: 4937.8235 | H39: 11808.829 | K39: 322.90613 | L39: 17069.559 | M39: 11 | AA39: =+AA36+AA37 -> 2064490.4
A40: ARQUIN23 | B40: 60 | C40: Cielorraso Durlock - Junta Tomada STD | D40: m2 | E40: 9357.5318 | H40: 13673.381 | K40: 256.82236 | L40: 23287.735 | M40: 9.5
A41: ARQUIN24 | B41: 61 | C41: Cielorraso Durlock - Junta Tomada RH | D41: m2 | E41: 13094.31 | H41: 13673.381 | K41: 256.82236 | L41: 27024.513 | M41: 9.5
A42: ARQUIN25 | B42: 62 | C42: Cielorraso Durlock - Junta Tomada RF | D42: m2 | E42: 12376.33 | H42: 13673.381 | K42: 256.82236 | L42: 26306.534 | M42: 9.5
A43: ARQUIN26 | B43: 63 | C43: Cielorraso Desmontable 60x60 - sin provision | D43: m2 | E43: 5209.6482 | H43: 12989.712 | K43: 243.98124 | L43: 18443.341 | M43: 10
B44: 63 bis | C44: Cielorraso Desmontable 60x60 - incluye placa Deco Vinyl | D44: m2 | E44: 18685.986 | H44: 12989.712 | K44: 243.98124 | L44: 31919.679 | M44: 10
A45: ARQUIN27 | B45: 64 | C45: Pared Durlock - Simple | D45: m2 | E45: 14846.976 | H45: 18556.731 | K45: 338.79278 | L45: 33742.501 | M45: 7
A46: ARQUIN28 | B46: 65 | C46: Pared Durlock - Doble placa STD ambas caras y asilación lana de vidrio | D46: m2 | E46: 27949.061 | H46: 21649.52 | K46: 395.25824 | L46: 49993.839 | M46: 6
A47: ARQUIN29 | B47: 66 | C47: Medio tabique espesor total 8,5 cm | D47: m2 | E47: 10316.337 | H47: 11808.829 | K47: 395.25824 | L47: 22520.425 | M47: 11
A48: ARQUIN30 | B48: 67 | C48: Esmalte sintetico para paredes | D48: m2 | E48: 3172.0074 | H48: 6494.856 | K48: 93.674385 | L48: 9760.5377 | M48: 20
A49: ARQUIN31 | B49: 68 | C49: Ladrillo Klimablock 27 x 19 x 30 cm | D49: m2 | E49: 3518.7855 | H49: 8336.4857 | K49: 229.16796 | L49: 12084.439 | M49: 15
A50: ARQUIN33 | B50: 70 | C50: Impermeabilización de cubierta transitable sobre carpeta horizontal con membrana Geotextil de 4mm, a soplete. | D50: m2 | E50: 9809.5604 | H50: 5001.8914 | K50: 31.337345 | L50: 14842.789 | M50: 25
A51: ARQUIN34 | B51: 71 | C51: Impermeabilización de cubierta con Malla no tejida de poliester y pintura poliuretánica | D51: m2 | E51: 6559.4276 | H51: 2500.9457 | K51: 36.300114 | L51: 9096.6734 | M51: 50
A52: ARQUIN35 | B52: 72 | C52: Revoque Exterior 3 en 1 hasta 3,00 m | D52: m2 | E52: 12474.154 | H52: 5851.385 | K52: 502.14495 | L52: 18827.684 | M52: 35
A53: ARQUIN36 | B53: 73 | C53: Pintura sobre pared existente | D53: m2 | E53: 2145.154 | H53: 3755.6524 | K53: 93.674385 | L53: 5994.4808 | M53: 20
A54: ARQUIN37 | B54: 74 | C54: Impermeabilizacion sobre ladrillo | D54: m2 | E54: 2323.3295 | H54: 4329.904 | K54: 60.50019 | L54: 6713.7336 | M54: 30
A55: ARQUIN38 | B55: 75 | C55: ladrillo cerámico 12 x 19 x 33 cm - PORTANTE | D55: m2 | E55: 14152.446 | H55: 8659.808 | K55: 229.16796 | L55: 23041.422 | M55: 15
A56: ARQUIN41 | B56: 113 | C56: Impermeabilizacion de azotea con pintura asfaltica / Barrera de vapor | D56: m2 | E56: 1273.3407 | H56: 1563.0911 | K56: 9.7929202 | L56: 2846.2247 | M56: 80
... A64: ARQUIN49 | B64: 121 | C64: BOCA TOMACORRIENTE | D64: ml | E64: 11193.921 | H64: 38476.088 | K64: 1623.6467 | L64: 51293.655 | M64: 3.25
A65: ARQUIN50 | B65: 122 | C65: BANDEJA PORTACABLES 200 | D65: ml | E65: 16864.721 | H65: 8829.7652 | K65: 0 | L65: 25694.487
A66: ARQUIN51 | B66: 123 | C66: COLUMNA HORMIGÓN RÚSTICO 85 kg/m3 | D66: m3 | L66: 0
A67: ARQUIN52 | B67: 124 | C67: COLUMNA HORMIGÓN VISTO | D67: m3 | L67: 0
A68: ARQUIN53 | B68: 125 | C68: Viga de hormigon rustico 180 kg/m3 | L68: 0
A69: ARQUIN54 | B69: 126 | C69: Viga | L69: 0
A70: ARQUIN55 | B70: 127 | C70: Losa de hormigon rustico | L70: 0
A71: ARQUIN56 | B71: 128 | C71: Losa | L71: 0
A72: ARQUIN57 | B72: 129 | C72: Tabique de hormigon rustico 80 kg/m3 | L72: 0
A73: ARQUIN58 | B73: 130 | C73: Tabique de hormigon visto 80 kg/m3 | L73: 0
A74: ARQUIN59 | B74: 131 | C74: Escalera de hormigon rustico 75 kg/m3 | L74: 0
A75: ARQUIN60 | B75: 132 | C75: Bases asiladas 60 kg/m3 | L75: 0
A76: ARQUIN61 | B76: 133 | C76: Vigas de fundacion 60 kg/m3 | L76: 0
A77: ARQUIN62 | B77: 134 | C77: Revoque grueso para interiores | D77: m2 | E77: 1438.6355 | H77: 6253.5403 | K77: 154.63603 | L77: 7846.8118 | M77: 18
A78: ARQUIN63 | B78: 135 | C78: Revoque fino a la cal | D78: m2 | E78: 1167.4401 | H78: 11674.843 | K78: 412.84765 | L78: 13255.131 | M78: 9
A79: ARQUIN64 | B79: 136 | C79: Carpeta cal reforzada (e: 1,5 cm) | D79: m2 | E79: 2552.4395 | H79: 6729.8934 | K79: 217.89035 | L79: 9500.2233 | M79: 14.5
A80: ARQUIN65 | B80: 137 | C80: Látex interior para paredes (enduido parcial) | D80: m2 | E80: 2322.5572 | H80: 3755.6524 | K80: 93.674385 | L80: 6171.884 | M80: 20
A81: ARQUIN66 | B81: 138 | C81: Pared simple con aislacion de lana de vidrio
A82: ARQUIN67 | B82: 139 | C82: Yeso pared
A83: ARQUIN68 | B83: 140 | C83: Yeso en cielorraso
A84: ARQUIN69 | B84: 141 | C84: Cemento alisado
A85: ARQUIN70 | B85: 142 | C85: Revoque Exterior 3 en 1 hasta 3,00 m
A86: ARQUIN71 | B86: 143 | C86: REVOQUE 2 EN 1 hasta 3,00 m
A87: ARQUIN72 | B87: 144 | C87: REVOQUE 2 EN 1 a mas 3,00 m
A88: ARQUIN73 | B88: 145 | C88: Muro retak
A89: ARQUIN74 | B89: 146 | C89: Látex interior para paredes (s/enduido) | D89: m2 | E89: 2180.3602 | H89: 3004.5219 | K89: 74.939508 | L89: 5259.8217 | M89: 25

Sheet P.MO 09.24
A1: COSTO M.O. | B1: 45536 | F1: Carga Manual
A3: Costo Real (B+N) | B3: Jornal | C3: Mensual | D3: Hora | E3: Dif real / teorico | F3: Mano Jornal | G3: Hora Uocra
A4: ESPECIALIZADO | B4: 75113.048 | C4: 1802713.2 | D4: 9389.131 | E4: 1.175166 | F4: 47000 | G4: 3946 | H4: 31568
A5: OFICIAL | B5: 65360.248 | C5: 1568646 | D5: 8170.031 | E5: 1.0957161 | F5: 39000 | G5: 3362 | H5: 26896
A6: MEDIO OFICIAL | B6: 54784.072 | C6: 1314817.7 | D6: 6848.009 | E6: 1.0656136 | F6: 31500 | G6: 3100 | H6: 24800
A7: AYUDANTE | B7: 49934.237 | C7: 1198421.7 | D7: 6241.7797 | E7: 1.0478055 | F7: 28100 | G7: 2846 | H7: 22768
A9: SOBRESTANTE | B9: 117225.48 | C9: 2578960.6 | D9: 14653.185 | F9: 1800000
A10: JEFE DE OBRA | B10: 172653.21 | C10: 3798370.6 | D10: 21581.651 | F10: 2650000
A11: COORD OBRAS | B11: 212743.82 | C11: 4680364.1 | D11: 26592.978 | F11: 3550000
A12: CAPATAZ | B12: 131457.37 | C12: 3154977 | D12: 16432.172 | F12: 2300000 | G12: 3946

Sheet H°A° 
A1: COMPUTO HORMIGON
A2: Pego valores de computo auxiliar | B2: SV4140_Computo Hormigon_Rev01 | T2: 1.08
B3: Unidad | C3: Fund | D3: s/ss | E3: s/PB | F3: s/1º | G3: s/2º | H3: s/3º | I3: s/4º | J3: s/Esc | K3: s/rec | L3: s/techos | M3: Total m3 | N3: kg/m3 | O3: Total KG | Q3: SS/Fund | R3: De PB y superiores | S3: Precio Unit | T3: M.O
A4: RAMPA | B4: m3 | C4: 0 | D4: 9.61632 | E4: 0 | F4: 0 | G4: 0 | H4: 0 | I4: 0 | J4: 0 | K4: 0 | L4: 0 | M4: =+ROUNDUP(SUM(C4:L4),0) -> 10 | N4: 120 | O4: =+M4*N4 -> 1200 | Q4: =+SUM(C4:D4) -> 9.61632 | R4: =+SUM(E4:L4) -> 0 | S4: =+SUM('01'!K28) -> 286602.43 | T4: =+S4*$T$2 -> 309530.62 | U4: =+Q4*T4 -> 2976545.5
A5: Tabique de submuración | B5: m3 | C5: 39.589505 | D5: 0 | E5: 0 | F5: 0 | G5: 0 | H5: 0 | I5: 0 | J5: 0 | K5: 0 | L5: 0 | M5: =+ROUNDUP(SUM(C5:L5),0) -> 40 | N5: 90 | O5: =+M5*N5 -> 3600 | Q5: =+SUM(C5:D5) -> 39.589505 | R5: =+SUM(E5:L5) -> 0 | S5: =+'01'!I25 -> 307690.19 | T5: =+S5*$T$2 -> 332305.41 | U5: =+Q5*T5 -> 13155807
A6: Platea | B6: m3 | C6: 178.6169 | D6: 0 | E6: 0 | F6: 0 | G6: 0 | H6: 0 | I6: 0 | J6: 0 | K6: 0 | L6: 0 | M6: =+ROUNDUP(SUM(C6:L6),0) -> 179 | N6: 90 | O6: =+M6*N6 -> 16110 | Q6: =+SUM(C6:D6) -> 178.6169 | R6: =+SUM(E6:L6) -> 0 | S6: =+'01'!I27 -> 148967.56 | T6: =+S6*$T$2 -> 160884.97 | U6: =+Q6*T6 -> 28736775
A7: Zapata corrida tabique | B7: m3 | C7: 27.5392 | D7: 0 | E7: 0 | F7: 0 | G7: 0 | H7: 0 | I7: 0 | J7: 0 | K7: 0 | L7: 0 | M7: =+ROUNDUP(SUM(C7:L7),0) -> 28 | N7: 140 | O7: =+M7*N7 -> 3920 | Q7: =+SUM(C7:D7) -> 27.5392 | R7: =+SUM(E7:L7) -> 0 | S7: =+'01'!I26 -> 253994.14 | T7: =+S7*$T$2 -> 274313.67 | U7: =+Q7*T7 -> 7554379.1
A8: Losa | B8: m3 | C8: 0 | D8: 28.916796 | E8: 28.083324 | F8: 29.471976 | G8: 29.471976 | H8: 29.433384 | I8: 23.15334 | J8: 3.878496 | K8: 1.5498 | L8: 2.81946 | M8: =+ROUNDUP(SUM(C8:L8),0) -> 177 | N8: 120 | O8: =+M8*N8 -> 21240 | Q8: =+SUM(C8:D8) -> 28.916796 | R8: =+SUM(E8:L8) -> 147.86176 | S8: =+'01'!I29 -> 191068.28 | T8: =+S8*$T$2 -> 206353.75 | V8: =+R8*T8 -> 30511827
A9: Viga | B9: m3 | C9: 0 | D9: 21.41727 | E9: 12.44928 | F9: 7.14048 | G9: 7.14048 | H9: 7.1394 | I9: 6.85122 | J9: 1.746645 | K9: 0.08736 | L9: 0.74256 | M9: =+ROUNDUP(SUM(C9:L9),0) -> 65 | N9: 130 | O9: =+M9*N9 -> 8450 | Q9: =+SUM(C9:D9) -> 21.41727 | R9: =+SUM(E9:L9) -> 43.297425 | S9: =+'01'!I30 -> 462949.29 | T9: =+S9*$T$2 -> 499985.23 | V9: =+R9*T9 -> 21648073
A10: Tabiques | B10: m3 | C10: 0 | D10: 4.150638 | E10: 4.285788 | F10: 3.352452 | G10: 3.21468 | H10: 3.21468 | I10: 3.32949 | J10: 3.06099 | K10: 1.15182 | L10: 1.668075 | M10: =+ROUNDUP(SUM(C10:L10),0) -> 28 | N10: 140 | O10: =+M10*N10 -> 3920 | Q10: =+SUM(C10:D10) -> 4.150638 | R10: =+SUM(E10:L10) -> 23.277975 | S10: =+'01'!I32 -> 307690.19 | T10: =+S10*$T$2 -> 332305.41 | V10: =+R10*T10 -> 7735397
A11: Columna | B11: m3 | C11: 0 | D11: 10.158625 | E11: 10.06458 | F11: 7.56 | G11: 7.56 | H11: 7.56 | I11: 7.52115 | J11: 1.57734 | K11: 0.91125 | L11: 0.77625 | M11: =+ROUNDUP(SUM(C11:L11),0) -> 54 | N11: 190 | O11: =+M11*N11 -> 10260 | Q11: =+SUM(C11:D11) -> 10.158625 | R11: =+SUM(E11:L11) -> 43.53057 | S11: =+'01'!I33 -> 273658.45 | T11: =+S11*$T$2 -> 295551.13 | V11: =+R11*T11 -> 12865509
A12: Escaleras | B12: m3 | C12: 0 | D12: 1.7736 | E12: 1.974546 | F12: 1.71 | G12: 1.71 | H12: 1.71 | I12: 1.71 | J12: 0 | K12: 0 | L12: 0 | M12: =+ROUNDUP(SUM(C12:L12),0) -> 11 | N12: 105 | O12: =+M12*N12 -> 1155 | Q12: =+SUM(C12:D12) -> 1.7736 | R12: =+SUM(E12:L12) -> 8.814546 | S12: =+'01'!I34 -> 283180.32 | T12: =+S12*$T$2 -> 305834.74 | V12: =+R12*T12 -> 2695794.4
A13: Vigas balcon | B13: m3 | C13: 0 | D13: 0 | E13: 2.8314 | F13: 2.8314 | G13: 2.8314 | H13: 2.8314 | I13: 0 | J13: 0 | K13: 0 | L13: 0 | M13: =+ROUNDUP(SUM(C13:L13),0) -> 12 | N13: 130 | O13: =+M13*N13 -> 1560 | Q13: =+SUM(C13:D13) -> 0 | R13: =+SUM(E13:L13) -> 11.3256 | S13: =+SUM('01'!I31:J31) -> 555539.15 | T13: =+S13*$T$2 -> 599982.28 | V13: =+R13*T13 -> 6795159.3
A14: Tabique de tanques | B14: m3 | C14: 0 | D14: 0 | E14: 0 | F14: 0 | G14: 0 | H14: 0 | I14: 0 | J14: 0 | K14: 2.761815 | L14: 0 | M14: =+ROUNDUP(SUM(C14:L14),0) -> 3 | N14: 140 | O14: =+M14*N14 -> 420 | Q14: =+SUM(C14:D14) -> 0 | R14: =+SUM(E14:L14) -> 2.761815 | S14: =+'01'!I35 -> 307690.19 | T14: =+S14*$T$2 -> 332305.41 | V14: =+R14*T14 -> 917766.06
C15: =+SUM(C4:C14) -> 245.74561 | D15: =+SUM(D4:D14) -> 76.033249 | E15: =+SUM(E4:E14) -> 59.688918 | F15: =+SUM(F4:F14) -> 52.066308 | G15: =+SUM(G4:G14) -> 51.928536 | H15: =+SUM(H4:H14) -> 51.888864 | I15: =+SUM(I4:I14) -> 42.5652 | J15: =+SUM(J4:J14) -> 10.263471 | ... M15: =+SUM(M4:M14) -> 607 | O15: =+SUM(O4:O14) -> 71835 | Q15: =+SUM(C15:D15) -> 321.77885 | R15: =+SUM(R4:R14) -> 280.86969 | U15: =+SUM(U4:U14) -> 52423506 | V15: =+SUM(V4:V14) -> 83169526
T16: Excavacion | U16: =+'01'!Q20 -> 9886979 | V16: =+'01'!Q24 -> 1747698.3 | W16: H° Limp | X16: =+SUM(U15:V16) -> 1.4722771e+08
U17: =+U15+U16 -> 62310485 | V17: =+V15+V16 -> 84917225
U18: =+U17/1.5 -> 41540323 | V18: =+V17/1.5 -> 56611483
A19: HORMIGON
A20: Descripcion | B20: P UNIT | E20: Total hormigonadas | F20: Subtotal | G20: Total m3 | H20: Bomba x m3 | T20: 10
A21: H30 6.20 | B21: =VLOOKUP(A21,Cotizaciones!B:D,3,0) -> 125000 | E21: =+P34 -> 14 | F21: =+B23*E21 -> 7462000 | G21: =+M15 -> 607 | H21: =+F21/G21 -> 12293.245 | I21: Bomba | R21: M3 | S21: m3 x etapa | T21: Camiones x etapa
A22: Piedra 6/12 | B22: =VLOOKUP(A22,Cotizaciones!B:D,3,0) -> 5100 | H22: =+B24 -> 5330 | I22: Bombeo | O22: FUNDACIONES tabiques | P22: 3 | R22: =+C15-R23 -> 66.745605 | S22: =+R22/P22 -> 22.248535 | T22: =+ROUNDUP(S22/$T$20,0) -> 3
A23: Acarreo | B23: =VLOOKUP(A23,Cotizaciones!B:D,3,0) -> 533000 | H23: =+B25 -> 1500 | I23: Super | O23: PLATEA | P23: 2 | R23: =+M6 -> 179 | S23: =+R23/P23 -> 89.5 | T23: =+ROUNDUP(S23/$T$20,0) -> 9
A24: Bombeo | B24: =VLOOKUP(A24,Cotizaciones!B:D,3,0) -> 5330 | H24: =+B26 -> 130100 | I24: H30 6.12 | O24: S/SS | P24: 1 | R24: =+D15 -> 76.033249 | S24: =+R24/P24 -> 76.033249 | T24: =+ROUNDUP(S24/$T$20,0) -> 8
A25: Super | B25: =VLOOKUP(A25,Cotizaciones!B:D,3,0) -> 1500 | G25: 0.05 | H25: =+SUM(H22:H24)*G25 -> 6846.5 | I25: Desperdicio/corte | J25: H Pobre | K25: 120000 | L25: 34 | M25: =+K25*L25 -> 4080000 | O25: S/PB | P25: 1 | R25: =+E15 -> 59.688918 | S25: =+R25/P25 -> 59.688918 | T25: =+ROUNDUP(S25/$T$20,0) -> 6
A26: H30 6.12 | B26: =+B21+B22 -> 130100 | H26: =SUM(H21:H25) -> 156069.75 | I26: H30 | J26: H30 | K26: =H26 -> 156069.75 | L26: =+M15-L27 -> 388 | M26: =+H26*L26 -> 60555061 | O26: S/1 | P26: 1 | R26: =+F15 -> 52.066308 | S26: =+R26/P26 -> 52.066308 | T26: =+ROUNDUP(S26/$T$20,0) -> 6
A27: Hidrofugo | B27: =VLOOKUP(A27,Cotizaciones!B:D,3,0) -> 22200 | H27: =+H26+B27 -> 178269.75 | I27: H° Hidrófugo | J27: H30 hidrofugo | K27: =H27 -> 178269.75 | L27: =+SUM(M5:M6) -> 219 | M27: =+L27*H27 -> 39041074 | O27: S/2 | P27: 1 | R27: =+G15 -> 51.928536 | S27: =+R27/P27 -> 51.928536 | T27: =+ROUNDUP(S27/$T$20,0) -> 6
