Workbook
Name \0: #REF!
Name \0: #REF!
Name \0: #REF!
Name \c: #REF!
Name \c: #REF!
Name \E: #REF!
Name \E: #REF!
Name \i: #REF!
Name \j: #REF!
Name \m: #REF!
Name \P: #REF!
Name \P: #REF!
Name \P: #REF!
Name \P: #REF!
Name \P: #REF!
Name \P: #REF!
Name \P: #REF!
Name \P: #REF!
Name \P: #REF!
Name \P: #REF!
Name \P: #REF!
Name \P: #REF!
Name \P: #REF!
Name \P: #REF!
Name \P: #REF!
Name \P: #REF!
Name \P: #REF!
Name \P: #REF!
Name \P: #REF!
Name \P: #REF!
Name \r: #N/A
Name \x: #REF!
Name \z: #REF!
Name \z: #REF!
Name \z: #REF!
Name __________ben1: #REF!
Name __________ben1: #REF!
Name __________ben1: #REF!
Name __________ben1: #REF!
Name __________ben1: #REF!
Name __________ben1: #REF!
Name __________ben1: #REF!
Name __________ben1: #REF!
Name __________ben1: #REF!
Name __________ben1: #REF!
Name __________ben1: #REF!
Name __________ben1: #REF!
Name __________ben1: #REF!
Name __________ben1: #REF!
Name __________ben1: #REF!
Name __________ben1: #REF!
Name __________ben1: #REF!
Name __________ben1: #REF!
Name __________ben1: #REF!
Name __________ben1: #REF!
Name __________ben1: #REF!
Name __________ben10: #REF!
Name __________ben10: #REF!
Name __________ben10: #REF!
Name __________ben10: #REF!

Sheet HOJA DE OBRA
D1: OBRA: Edificio El Salvador 4140
A6: Cliente / Comitente:
A7: Facturacion
A8: Dirección / Jefe de la Obra:
A11: Fecha de Inicio : | D11: Duracion de Obra: | E11: 18 meses
A13: Presupuesto Aprobado : | D13: Fecha de Aprobacion:
A14: Orden de Compra CL : | D14: Nota de Pedido ARQ:
A16: Anticipo : | D16: Condiciones de Pago:
A17: Certifiaciones : | D17: Forma de Pago:
A18: Actualización CAC:
A20: Seguros :
A21: Caucion Anticipo
A22: Caucion Ejecucion
A23: Resp. Civil
A25: Programa S&H :
A26: Aviso de Obra :
A28: Descripcion de Tareas
A33: Contactos del cliente:
A34: Nombre | B34: TEL | C34: Rubro | D34: Mail de contacto
A39: Subcontratistas | B39: Rubro | C39: Inicio | D39: Presupuesto Aprobado | E39: Cerrado / Estimado
A44: Cuadrilla de Obra | B44: Categoría | D44: Observación
A52: Observaciones Particulares

Sheet Resumen General
AE1: Actualizado | AF1: 46133
B3: OBRA: GDR 3760
B4: RESUMEN DE OBRA
D5: 45627 | E5: 45658 | F5: 45689 | G5: 45717 | H5: 45748 | I5: 45778 | J5: 45809 | K5: 45839 | L5: 45870 | M5: 45901 | N5: 45931 | O5: 45962 | P5: 45992 | Q5: 46023 | R5: 46054 | S5: 46082 | T5: 46113 | V5: Acum. Descontado | X5: Presupuesto #1 | Y5: Presupuesto #2 | Z5: Previsto | AA5: % Cert. Acum. | AB5: Saldo Disponible | AC5: Disponible % | AD5: Rubro Completado
B6: Ingresos de Obra
B7: Ingresos por Certificados | D7: =SUM(VLOOKUP($B7,'Resumen Pto #1'!$B$5:$U$10,MATCH('Resumen General'!D$5,'Resumen Pto #1'!$B$5:$U$5,0),0),VLOOKUP($B7,'Resumen Pto #2'!$B$5:$U$10,MATCH('Resumen General'!D$5,'Resumen Pto #2'!$B$5:$U$5,0),0)) -> 0 | E7: =SUM(VLOOKUP($B7,'Resumen Pto #1'!$B$5:$U$10,MATCH('Resumen General'!E$5,'Resumen Pto #1'!$B$5:$U$5,0),0),VLOOKUP($B7,'Resumen Pto #2'!$B$5:$U$10,MATCH('Resumen General'!E$5,'Resumen Pto #2'!$B$5:$U$5,0),0)) -> 0 | F7: =SUM(VLOOKUP($B7,'Resumen Pto #1'!$B$5:$U$10,MATCH('Resumen General'!F$5,'Resumen Pto #1'!$B$5:$U$5,0),0),VLOOKUP($B7,'Resumen Pto #2'!$B$5:$U$10,MATCH('Resumen General'!F$5,'Resumen Pto #2'!$B$5:$U$5,0),0)) -> 2.8484761e+08 | G7: =SUM(VLOOKUP($B7,'Resumen Pto #1'!$B$5:$U$10,MATCH('Resumen General'!G$5,'Resumen Pto #1'!$B$5:$U$5,0),0),VLOOKUP($B7,'Resumen Pto #2'!$B$5:$U$10,MATCH('Resumen General'!G$5,'Resumen Pto #2'!$B$5:$U$5,0),0)) -> 27616485 | H7: =SUM(VLOOKUP($B7,'Resumen Pto #1'!$B$5:$U$10,MATCH('Resumen General'!H$5,'Resumen Pto #1'!$B$5:$U$5,0),0),VLOOKUP($B7,'Resumen Pto #2'!$B$5:$U$10,MATCH('Resumen General'!H$5,'Resumen Pto #2'!$B$5:$U$5,0),0)) -> 24319183 | I7: =SUM(VLOOKUP($B7,'Resumen Pto #1'!$B$5:$U$10,MATCH('Resumen General'!I$5,'Resumen Pto #1'!$B$5:$U$5,0),0),VLOOKUP($B7,'Resumen Pto #2'!$B$5:$U$10,MATCH('Resumen General'!I$5,'Resumen Pto #2'!$B$5:$U$5,0),0)) -> 47861818 | J7: =SUM(VLOOKUP($B7,'Resumen Pto #1'!$B$5:$U$10,MATCH('Resumen General'!J$5,'Resumen Pto #1'!$B$5:$U$5,0),0),VLOOKUP($B7,'Resumen Pto #2'!$B$5:$U$10,MATCH('Resumen General'!J$5,'Resumen Pto #2'!$B$5:$U$5,0),0)) -> 29875785 | K7: =SUM(VLOOKUP($B7,'Resumen Pto #1'!$B$5:$U$10,MATCH('Resumen General'!K$5,'Resumen Pto #1'!$B$5:$U$5,0),0),VLOOKUP($B7,'Resumen Pto #2'!$B$5:$U$10,MATCH('Resumen General'!K$5,'Resumen Pto #2'!$B$5:$U$5,0),0)) -> 67092674 | ... T7: =SUM(VLOOKUP($B7,'Resumen Pto #1'!$B$5:$U$10,MATCH('Resumen General'!T$5,'Resumen Pto #1'!$B$5:$U$5,0),0),VLOOKUP($B7,'Resumen Pto #2'!$B$5:$U$10,MATCH('Resumen General'!T$5,'Resumen Pto #2'!$B$5:$U$5,0),0)) -> 0 | V7: =SUM(D7:U7) -> 7.458795e+08 | X7: ='Resumen Pto #1'!X7 -> 500907720 | Y7: ='Resumen Pto #2'!X7 -> 8.4484525e+08 | Z7: =SUM(X7:Y7) -> 1345752968 | AA7: =SUM('Cert. Pto. 01'!V46,'Cert. Pto. 02'!V195)/SUM('Cert. Pto. 02'!L195+'Cert. Pto. 01'!L46) -> 0.57722683 | AB7: =IF(AA7=100%,0,IF(OR(V7<>0,Z7),Z7-V7)) -> 5.9987347e+08 | AC7: =IF(OR(AB7<0,Z7),AB7/Z7,0%) -> 0.44575303 | AD7: =IF(AA7=100%,IF(OR(U7<>0,Z7),Z7-U7),0) -> 0
B8: Total Ingresos de Obra | D8: =SUM(D7) -> 0 | E8: =SUM(E7) -> 0 | F8: =SUM(F7) -> 2.8484761e+08 | G8: =SUM(G7) -> 27616485 | H8: =SUM(H7) -> 24319183 | I8: =SUM(I7) -> 47861818 | J8: =SUM(J7) -> 29875785 | K8: =SUM(K7) -> 67092674 | ... T8: =SUM(T7) -> 0 | V8: =SUM(V7) -> 7.458795e+08 | X8: =SUM(X7) -> 500907720 | Y8: =SUM(Y7) -> 8.4484525e+08 | Z8: =SUM(Z7) -> 1345752968 | AB8: =SUM(AB7) -> 5.9987347e+08 | AC8: =IF(OR(AB8<0,Z8),AB8/Z8,0%) -> 0.44575303 | AD8: =SUM(AD7) -> 0
B9: Actualización por CAC | D9: =SUM(VLOOKUP($B9,'Resumen Pto #1'!$B$5:$U$10,MATCH('Resumen General'!D$5,'Resumen Pto #1'!$B$5:$U$5,0),0),VLOOKUP($B9,'Resumen Pto #2'!$B$5:$U$10,MATCH('Resumen General'!D$5,'Resumen Pto #2'!$B$5:$U$5,0),0)) -> 0 | E9: =SUM(VLOOKUP($B9,'Resumen Pto #1'!$B$5:$U$10,MATCH('Resumen General'!E$5,'Resumen Pto #1'!$B$5:$U$5,0),0),VLOOKUP($B9,'Resumen Pto #2'!$B$5:$U$10,MATCH('Resumen General'!E$5,'Resumen Pto #2'!$B$5:$U$5,0),0)) -> 0 | F9: =SUM(VLOOKUP($B9,'Resumen Pto #1'!$B$5:$U$10,MATCH('Resumen General'!F$5,'Resumen Pto #1'!$B$5:$U$5,0),0),VLOOKUP($B9,'Resumen Pto #2'!$B$5:$U$10,MATCH('Resumen General'!F$5,'Resumen Pto #2'!$B$5:$U$5,0),0)) -> 9200360.5 | G9: =SUM(VLOOKUP($B9,'Resumen Pto #1'!$B$5:$U$10,MATCH('Resumen General'!G$5,'Resumen Pto #1'!$B$5:$U$5,0),0),VLOOKUP($B9,'Resumen Pto #2'!$B$5:$U$10,MATCH('Resumen General'!G$5,'Resumen Pto #2'!$B$5:$U$5,0),0)) -> 891991.37 | H9: =SUM(VLOOKUP($B9,'Resumen Pto #1'!$B$5:$U$10,MATCH('Resumen General'!H$5,'Resumen Pto #1'!$B$5:$U$5,0),0),VLOOKUP($B9,'Resumen Pto #2'!$B$5:$U$10,MATCH('Resumen General'!H$5,'Resumen Pto #2'!$B$5:$U$5,0),0)) -> 1011953.2 | I9: =SUM(VLOOKUP($B9,'Resumen Pto #1'!$B$5:$U$10,MATCH('Resumen General'!I$5,'Resumen Pto #1'!$B$5:$U$5,0),0),VLOOKUP($B9,'Resumen Pto #2'!$B$5:$U$10,MATCH('Resumen General'!I$5,'Resumen Pto #2'!$B$5:$U$5,0),0)) -> 2796022.3 | J9: =SUM(VLOOKUP($B9,'Resumen Pto #1'!$B$5:$U$10,MATCH('Resumen General'!J$5,'Resumen Pto #1'!$B$5:$U$5,0),0),VLOOKUP($B9,'Resumen Pto #2'!$B$5:$U$10,MATCH('Resumen General'!J$5,'Resumen Pto #2'!$B$5:$U$5,0),0)) -> 2266306 | K9: =SUM(VLOOKUP($B9,'Resumen Pto #1'!$B$5:$U$10,MATCH('Resumen General'!K$5,'Resumen Pto #1'!$B$5:$U$5,0),0),VLOOKUP($B9,'Resumen Pto #2'!$B$5:$U$10,MATCH('Resumen General'!K$5,'Resumen Pto #2'!$B$5:$U$5,0),0)) -> 5622949.4 | ... T9: =SUM(VLOOKUP($B9,'Resumen Pto #1'!$B$5:$U$10,MATCH('Resumen General'!T$5,'Resumen Pto #1'!$B$5:$U$5,0),0),VLOOKUP($B9,'Resumen Pto #2'!$B$5:$U$10,MATCH('Resumen General'!T$5,'Resumen Pto #2'!$B$5:$U$5,0),0)) -> 0 | V9: =SUM(D9:U9) -> 79119888 | X9: ='Resumen Pto #1'!X9 -> 0 | Y9: ='Resumen Pto #2'!X9 -> 0 | Z9: =SUM(X9:Y9) -> 0 | AB9: =IF(AA9=100%,0,IF(Z9=0,Z9,Z9-V9)) -> 0 | AC9: =IF(OR(AB9<0,Z9),AB9/Z9,0%) -> 0 | AD9: =IF(AA9=100%,IF(OR(U9<>0,Z9),Z9-U9),0) -> 0
B10: Total Ingresos de Obra | D10: =SUM(D9) -> 0 | E10: =SUM(E9) -> 0 | F10: =SUM(F9) -> 9200360.5 | G10: =SUM(G9) -> 891991.37 | H10: =SUM(H9) -> 1011953.2 | I10: =SUM(I9) -> 2796022.3 | J10: =SUM(J9) -> 2266306 | K10: =SUM(K9) -> 5622949.4 | ... T10: =SUM(T9) -> 0 | V10: =SUM(V9) -> 79119888 | X10: =SUM(X9) -> 0 | Y10: =SUM(Y9) -> 0 | Z10: =SUM(Z9) -> 0 | AB10: =SUM(AB9) -> 0 | AC10: =IF(OR(AB10<0,Z10),AB10/Z10,0%) -> 0 | AD10: =SUM(AD9) -> 0
B12: Costos de Obra
B13: Seguridad e Higiene | D13: ='Resumen Pto #2'!D14 -> 0 | E13: ='Resumen Pto #2'!E14 -> 0 | F13: ='Resumen Pto #2'!F14 -> 240000 | G13: ='Resumen Pto #2'!G14 -> 1706000 | H13: ='Resumen Pto #2'!H14 -> 446700 | I13: ='Resumen Pto #2'!I14 -> 1707000 | J13: ='Resumen Pto #2'!J14 -> 3102500 | K13: ='Resumen Pto #2'!K14 -> 535650 | ... T13: ='Resumen Pto #2'!T14 -> 790000 | V13: {=SUMPRODUCT($D13:$U13,TRANSPOSE('Indice CAC'!$D$2:$D$19))} -> 13132520 | X13: 0 | Y13: ='Resumen Pto #2'!X14 -> 8568681.2 | Z13: =SUM(X13:Y13) -> 8568681.2 | AA13: =IF($C13="MAT",SUMIF('Cert. Pto. 02'!$A$10:$A$194,$B13,'Cert. Pto. 02'!$T$10:$T$194),IF($C13="MO",SUMIF('Cert. Pto. 02'!$A$10:$A$194,$B13,'Cert. Pto. 02'!$U$10:$U$194),SUMIF('Cert. Pto. 02'!$A$10:$A$194,$B13,'Cert. Pto. 02'!$V$10:$V$194)))/IF($C13="MAT",SUMIF('Cert. Pto. 02'!$A$10:$A$194,$B13,'Cert. Pto. 02'!$I$10:$I$194),IF('Resumen Pto #2'!$C13="MO",SUMIF('Cert. Pto. 02'!$A$10:$A$194,$B13,'Cert. Pto. 02'!$J$10:$J$194),SUMIF('Cert. Pto. 02'!$A$10:$A$194,$B13,'Cert. Pto. 02'!$K$10:$K$194))) -> 0.89584131 | AB13: =IF(AA13=100%,0,IF(OR(V13<>0,Z13),Z13-V13)) -> -4563838.8 | AC13: =IF(OR(AB13<0,Z13),AB13/Z13,0%) -> -0.53261859 | AD13: =IF(AA13=100%,IF(OR(V13<>0,Z13),Z13-V13),0) -> 0
B14: Supervisión de Obra | D14: ='Resumen Pto #2'!D13 -> 2128206 | E14: ='Resumen Pto #2'!E13 -> 2503867.6 | F14: ='Resumen Pto #2'!F13 -> 2666306.9 | G14: ='Resumen Pto #2'!G13 -> 2632626 | H14: ='Resumen Pto #2'!H13 -> 2612626 | I14: ='Resumen Pto #2'!I13 -> 2612626 | J14: ='Resumen Pto #2'!J13 -> 2770864 | K14: ='Resumen Pto #2'!K13 -> 2921847.5 | ... T14: ='Resumen Pto #2'!T13 -> 0 | V14: {=SUMPRODUCT($D14:$U14,TRANSPOSE('Indice CAC'!$D$2:$D$19))} -> 42358438 | X14: 0 | Y14: ='Resumen Pto #2'!X13 -> 74327580 | Z14: =SUM(X14:Y14) -> 74327580 | AA14: =IF($C14="MAT",SUMIF('Cert. Pto. 02'!$A$10:$A$194,$B14,'Cert. Pto. 02'!$T$10:$T$194),IF($C14="MO",SUMIF('Cert. Pto. 02'!$A$10:$A$194,$B14,'Cert. Pto. 02'!$U$10:$U$194),SUMIF('Cert. Pto. 02'!$A$10:$A$194,$B14,'Cert. Pto. 02'!$V$10:$V$194)))/IF($C14="MAT",SUMIF('Cert. Pto. 02'!$A$10:$A$194,$B14,'Cert. Pto. 02'!$I$10:$I$194),IF('Resumen Pto #2'!$C14="MO",SUMIF('Cert. Pto. 02'!$A$10:$A$194,$B14,'Cert. Pto. 02'!$J$10:$J$194),SUMIF('Cert. Pto. 02'!$A$10:$A$194,$B14,'Cert. Pto. 02'!$K$10:$K$194))) -> 0.65 | AB14: =IF(AA14=100%,0,IF(OR(V14<>0,Z14),Z14-V14)) -> 31969142 | AC14: =IF(OR(AB14<0,Z14),AB14/Z14,0%) -> 0.43011144 | AD14: =IF(AA14=100%,IF(OR(V14<>0,Z14),Z14-V14),0) -> 0
B15: Movilidad | D15: ='Resumen Pto #2'!D15 -> 0 | E15: ='Resumen Pto #2'!E15 -> 320000 | F15: ='Resumen Pto #2'!F15 -> 14684.62 | G15: ='Resumen Pto #2'!G15 -> 181198.83 | H15: ='Resumen Pto #2'!H15 -> 217418.9 | I15: ='Resumen Pto #2'!I15 -> 263908.65 | J15: ='Resumen Pto #2'!J15 -> 162641.49 | K15: ='Resumen Pto #2'!K15 -> 614099.15 | ... T15: ='Resumen Pto #2'!T15 -> 432348.34 | V15: {=SUMPRODUCT($D15:$U15,TRANSPOSE('Indice CAC'!$D$2:$D$19))} -> 7606944 | X15: 0 | Y15: ='Resumen Pto #2'!X15 -> 13600000 | Z15: =SUM(X15:Y15) -> 13600000 | AA15: =IF($C15="MAT",SUMIF('Cert. Pto. 02'!$A$10:$A$194,$B15,'Cert. Pto. 02'!$T$10:$T$194),IF($C15="MO",SUMIF('Cert. Pto. 02'!$A$10:$A$194,$B15,'Cert. Pto. 02'!$U$10:$U$194),SUMIF('Cert. Pto. 02'!$A$10:$A$194,$B15,'Cert. Pto. 02'!$V$10:$V$194)))/IF($C15="MAT",SUMIF('Cert. Pto. 02'!$A$10:$A$194,$B15,'Cert. Pto. 02'!$I$10:$I$194),IF('Resumen Pto #2'!$C15="MO",SUMIF('Cert. Pto. 02'!$A$10:$A$194,$B15,'Cert. Pto. 02'!$J$10:$J$194),SUMIF('Cert. Pto. 02'!$A$10:$A$194,$B15,'Cert. Pto. 02'!$K$10:$K$194))) -> 0.65 | AB15: =IF(AA15=100%,0,IF(OR(V15<>0,Z15),Z15-V15)) -> 5993056 | AC15: =IF(OR(AB15<0,Z15),AB15/Z15,0%) -> 0.44066588 | AD15: =IF(AA15=100%,IF(OR(V15<>0,Z15),Z15-V15),0) -> 0
B16: Preliminares | D16: ='Resumen Pto #1'!D13 -> 0 | E16: ='Resumen Pto #1'!E13 -> 0 | F16: ='Resumen Pto #1'!F13 -> 6949796.9 | G16: ='Resumen Pto #1'!G13 -> 4182183.8 | H16: ='Resumen Pto #1'!H13 -> 163926.85 | I16: ='Resumen Pto #1'!I13 -> 459869.25 | J16: ='Resumen Pto #1'!J13 -> 92816.22 | K16: ='Resumen Pto #1'!K13 -> 14628.44 | ... T16: ='Resumen Pto #1'!T13 -> 0 | V16: {=SUMPRODUCT($D16:$U16,TRANSPOSE('Indice CAC'!$D$2:$D$19))} -> 12879112 | X16: ='Resumen Pto #1'!X13 -> 12544454 | Y16: 0 | Z16: =SUM(X16:Y16) -> 12544454 | AA16: =IF($C16="MAT",SUMIF('Cert. Pto. 01'!$A$9:$A$45,$B16,'Cert. Pto. 01'!$T$9:$T$45),IF($C16="MO",SUMIF('Cert. Pto. 01'!$A$9:$A$45,$B16,'Cert. Pto. 01'!$U$9:$U$45),SUMIF('Cert. Pto. 01'!$A$9:$A$45,$B16,'Cert. Pto. 01'!$V$9:$V$45)))/IF($C16="MAT",SUMIF('Cert. Pto. 01'!$A$9:$A$45,$B16,'Cert. Pto. 01'!$I$9:$I$45),IF($C16="MO",SUMIF('Cert. Pto. 01'!$A$9:$A$45,$B16,'Cert. Pto. 01'!$J$9:$J$45),SUMIF('Cert. Pto. 01'!$A$9:$A$45,$B16,'Cert. Pto. 01'!$K$9:$K$45))) -> 1 | AB16: =IF(AA16=100%,0,IF(OR(V16<>0,Z16),Z16-V16)) -> 0 | AC16: =IF(OR(AB16<0,Z16),AB16/Z16,0%) -> 0 | AD16: =IF(AA16=100%,IF(OR(V16<>0,Z16),Z16-V16),0) -> -334657.85
B17: Agrimensura | D17: ='Resumen Pto #1'!D14 -> 110000 | E17: ='Resumen Pto #1'!E14 -> 0 | F17: ='Resumen Pto #1'!F14 -> 0 | G17: ='Resumen Pto #1'!G14 -> 0 | H17: ='Resumen Pto #1'!H14 -> 0 | I17: ='Resumen Pto #1'!I14 -> 0 | J17: ='Resumen Pto #1'!J14 -> 0 | K17: ='Resumen Pto #1'!K14 -> 0 | ... T17: ='Resumen Pto #1'!T14 -> 0 | V17: {=SUMPRODUCT($D17:$U17,TRANSPOSE('Indice CAC'!$D$2:$D$19))} -> 110000 | X17: ='Resumen Pto #1'!X14 -> 853792.28 | Y17: 0 | Z17: =SUM(X17:Y17) -> 853792.28 | AA17: =IF($C17="MAT",SUMIF('Cert. Pto. 01'!$A$9:$A$45,$B17,'Cert. Pto. 01'!$T$9:$T$45),IF($C17="MO",SUMIF('Cert. Pto. 01'!$A$9:$A$45,$B17,'Cert. Pto. 01'!$U$9:$U$45),SUMIF('Cert. Pto. 01'!$A$9:$A$45,$B17,'Cert. Pto. 01'!$V$9:$V$45)))/IF($C17="MAT",SUMIF('Cert. Pto. 01'!$A$9:$A$45,$B17,'Cert. Pto. 01'!$I$9:$I$45),IF($C17="MO",SUMIF('Cert. Pto. 01'!$A$9:$A$45,$B17,'Cert. Pto. 01'!$J$9:$J$45),SUMIF('Cert. Pto. 01'!$A$9:$A$45,$B17,'Cert. Pto. 01'!$K$9:$K$45))) -> 1 | AB17: =IF(AA17=100%,0,IF(OR(V17<>0,Z17),Z17-V17)) -> 0 | AC17: =IF(OR(AB17<0,Z17),AB17/Z17,0%) -> 0 | AD17: =IF(AA17=100%,IF(OR(V17<>0,Z17),Z17-V17),0) -> 743792.28
B18: Excavación y Mov. de Suelos | D18: ='Resumen Pto #1'!D15 -> 0 | E18: ='Resumen Pto #1'!E15 -> 0 | F18: ='Resumen Pto #1'!F15 -> 0 | G18: ='Resumen Pto #1'!G15 -> 1580000 | H18: ='Resumen Pto #1'!H15 -> 1580000 | I18: ='Resumen Pto #1'!I15 -> 2974000 | J18: ='Resumen Pto #1'!J15 -> 3640000 | K18: ='Resumen Pto #1'!K15 -> 1416000 | ... T18: ='Resumen Pto #1'!T15 -> 0 | V18: {=SUMPRODUCT($D18:$U18,TRANSPOSE('Indice CAC'!$D$2:$D$19))} -> 10416172 | X18: ='Resumen Pto #1'!X15 -> 22068905 | Y18: 0 | Z18: =SUM(X18:Y18) -> 22068905 | AA18: =IF($C18="MAT",SUMIF('Cert. Pto. 01'!$A$9:$A$45,$B18,'Cert. Pto. 01'!$T$9:$T$45),IF($C18="MO",SUMIF('Cert. Pto. 01'!$A$9:$A$45,$B18,'Cert. Pto. 01'!$U$9:$U$45),SUMIF('Cert. Pto. 01'!$A$9:$A$45,$B18,'Cert. Pto. 01'!$V$9:$V$45)))/IF($C18="MAT",SUMIF('Cert. Pto. 01'!$A$9:$A$45,$B18,'Cert. Pto. 01'!$I$9:$I$45),IF($C18="MO",SUMIF('Cert. Pto. 01'!$A$9:$A$45,$B18,'Cert. Pto. 01'!$J$9:$J$45),SUMIF('Cert. Pto. 01'!$A$9:$A$45,$B18,'Cert. Pto. 01'!$K$9:$K$45))) -> 1 | AB18: =IF(AA18=100%,0,IF(OR(V18<>0,Z18),Z18-V18)) -> 0 | AC18: =IF(OR(AB18<0,Z18),AB18/Z18,0%) -> 0 | AD18: =IF(AA18=100%,IF(OR(V18<>0,Z18),Z18-V18),0) -> 11652732
B19: Hormigón | C19: MAT | D19: ='Resumen Pto #1'!D16 -> 0 | E19: ='Resumen Pto #1'!E16 -> 0 | F19: ='Resumen Pto #1'!F16 -> 1227898.4 | G19: ='Resumen Pto #1'!G16 -> 21854353 | H19: ='Resumen Pto #1'!H16 -> 64397545 | I19: ='Resumen Pto #1'!I16 -> 43287475 | J19: ='Resumen Pto #1'!J16 -> 1606135.8 | K19: ='Resumen Pto #1'!K16 -> 33701586 | ... T19: ='Resumen Pto #1'!T16 -> 0 | V19: {=SUMPRODUCT($D19:$U19,TRANSPOSE('Indice CAC'!$D$2:$D$19))} -> 1.8021717e+08 | X19: ='Resumen Pto #1'!X16 -> 1.8107277e+08 | Y19: 0 | Z19: =SUM(X19:Y19) -> 1.8107277e+08 | AA19: =IF($C19="MAT",SUMIF('Cert. Pto. 01'!$A$9:$A$45,$B19,'Cert. Pto. 01'!$T$9:$T$45),IF('Resumen Pto #1'!$C19="MO",SUMIF('Cert. Pto. 01'!$A$9:$A$45,$B19,'Cert. Pto. 01'!$U$9:$U$45),SUMIF('Cert. Pto. 01'!$A$9:$A$45,$B19,'Cert. Pto. 01'!$V$9:$V$45)))/IF($C19="MAT",SUMIF('Cert. Pto. 01'!$A$9:$A$45,$B19,'Cert. Pto. 01'!$I$9:$I$45),IF('Resumen Pto #1'!$C19="MO",SUMIF('Cert. Pto. 01'!$A$9:$A$45,$B19,'Cert. Pto. 01'!$J$9:$J$45),SUMIF('Cert. Pto. 01'!$A$9:$A$45,'Resumen Pto #1'!$B19,'Cert. Pto. 01'!$K$9:$K$45))) -> 1 | AB19: =IF(AA19=100%,0,IF(OR(V19<>0,Z19),Z19-V19)) -> 0 | AC19: =IF(OR(AB19<0,Z19),AB19/Z19,0%) -> 0 | AD19: =IF(AA19=100%,IF(OR(V19<>0,Z19),Z19-V19),0) -> 855599.54
B20: Hormigón | C20: MO | D20: ='Resumen Pto #1'!D17 -> 0 | E20: ='Resumen Pto #1'!E17 -> 0 | F20: ='Resumen Pto #1'!F17 -> 2411850 | G20: ='Resumen Pto #1'!G17 -> 9206862.2 | H20: ='Resumen Pto #1'!H17 -> 10965040 | I20: ='Resumen Pto #1'!I17 -> 9710066.5 | J20: ='Resumen Pto #1'!J17 -> 8357133.4 | K20: ='Resumen Pto #1'!K17 -> 20959356 | ... T20: ='Resumen Pto #1'!T17 -> 0 | V20: {=SUMPRODUCT($D20:$U20,TRANSPOSE('Indice CAC'!$D$2:$D$19))} -> 1.0530015e+08 | X20: ='Resumen Pto #1'!X17 -> 1.4437802e+08 | Y20: 0 | Z20: =SUM(X20:Y20) -> 1.4437802e+08 | AA20: =IF($C20="MAT",SUMIF('Cert. Pto. 01'!$A$9:$A$45,$B20,'Cert. Pto. 01'!$T$9:$T$45),IF($C20="MO",SUMIF('Cert. Pto. 01'!$A$9:$A$45,$B20,'Cert. Pto. 01'!$U$9:$U$45),SUMIF('Cert. Pto. 01'!$A$9:$A$45,$B20,'Cert. Pto. 01'!$V$9:$V$45)))/IF($C20="MAT",SUMIF('Cert. Pto. 01'!$A$9:$A$45,$B20,'Cert. Pto. 01'!$I$9:$I$45),IF($C20="MO",SUMIF('Cert. Pto. 01'!$A$9:$A$45,$B20,'Cert. Pto. 01'!$J$9:$J$45),SUMIF('Cert. Pto. 01'!$A$9:$A$45,$B20,'Cert. Pto. 01'!$K$9:$K$45))) -> 1 | AB20: =IF(AA20=100%,0,IF(OR(V20<>0,Z20),Z20-V20)) -> 0 | AC20: =IF(OR(AB20<0,Z20),AB20/Z20,0%) -> 0 | AD20: =IF(AA20=100%,IF(OR(V20<>0,Z20),Z20-V20),0) -> 39077870
B21: Albañilería | C21: MAT | D21: 0 | E21: ='Resumen Pto #2'!E16 -> 0 | F21: ='Resumen Pto #2'!F16 -> 0 | G21: ='Resumen Pto #2'!G16 -> 0 | H21: ='Resumen Pto #2'!H16 -> 0 | I21: ='Resumen Pto #2'!I16 -> 0 | J21: ='Resumen Pto #2'!J16 -> 43528.94 | K21: ='Resumen Pto #2'!K16 -> 493967.79 | L21: ='Resumen Pto #2'!L16 -> 503642.81 | ... T21: ='Resumen Pto #2'!T16 -> 1587335.5 | V21: {=SUMPRODUCT($D21:$U21,TRANSPOSE('Indice CAC'!$D$2:$D$19))} -> 30259046 | X21: 0 | Y21: ='Resumen Pto #2'!X16 -> 65392825 | Z21: =SUM(X21:Y21) -> 65392825 | AA21: =IF($C21="MAT",SUMIF('Cert. Pto. 02'!$A$10:$A$194,$B21,'Cert. Pto. 02'!$T$10:$T$194),IF($C21="MO",SUMIF('Cert. Pto. 02'!$A$10:$A$194,$B21,'Cert. Pto. 02'!$U$10:$U$194),SUMIF('Cert. Pto. 02'!$A$10:$A$194,$B21,'Cert. Pto. 02'!$V$10:$V$194)))/IF($C21="MAT",SUMIF('Cert. Pto. 02'!$A$10:$A$194,$B21,'Cert. Pto. 02'!$I$10:$I$194),IF($C21="MO",SUMIF('Cert. Pto. 02'!$A$10:$A$194,$B21,'Cert. Pto. 02'!$J$10:$J$194),SUMIF('Cert. Pto. 02'!$A$10:$A$194,$B21,'Cert. Pto. 02'!$K$10:$K$194))) -> 0.31906124 | AB21: =IF(AA21=100%,0,IF(OR(V21<>0,Z21),Z21-V21)) -> 35133778 | AC21: =IF(OR(AB21<0,Z21),AB21/Z21,0%) -> 0.53727268 | AD21: =IF(AA21=100%,IF(OR(V21<>0,Z21),Z21-V21),0) -> 0
B22: Albañilería | C22: MO | D22: ='Resumen Pto #2'!D17 -> 0 | E22: ='Resumen Pto #2'!E17 -> 0 | F22: ='Resumen Pto #2'!F17 -> 725487 | G22: ='Resumen Pto #2'!G17 -> 3309015.8 | H22: ='Resumen Pto #2'!H17 -> 3592574 | I22: ='Resumen Pto #2'!I17 -> 3991998.7 | J22: ='Resumen Pto #2'!J17 -> 4723373.5 | K22: ='Resumen Pto #2'!K17 -> 6711151 | ... T22: ='Resumen Pto #2'!T17 -> 1829165 | V22: {=SUMPRODUCT($D22:$U22,TRANSPOSE('Indice CAC'!$D$2:$D$19))} -> 1.2817618e+08 | X22: 0 | Y22: ='Resumen Pto #2'!X17 -> 1.3257367e+08 | Z22: =SUM(X22:Y22) -> 1.3257367e+08 | AA22: =IF($C22="MAT",SUMIF('Cert. Pto. 02'!$A$10:$A$194,$B22,'Cert. Pto. 02'!$T$10:$T$194),IF($C22="MO",SUMIF('Cert. Pto. 02'!$A$10:$A$194,$B22,'Cert. Pto. 02'!$U$10:$U$194),SUMIF('Cert. Pto. 02'!$A$10:$A$194,$B22,'Cert. Pto. 02'!$V$10:$V$194)))/IF($C22="MAT",SUMIF('Cert. Pto. 02'!$A$10:$A$194,$B22,'Cert. Pto. 02'!$I$10:$I$194),IF($C22="MO",SUMIF('Cert. Pto. 02'!$A$10:$A$194,$B22,'Cert. Pto. 02'!$J$10:$J$194),SUMIF('Cert. Pto. 02'!$A$10:$A$194,$B22,'Cert. Pto. 02'!$K$10:$K$194))) -> 0.42958142 | AB22: =IF(AA22=100%,0,IF(OR(V22<>0,Z22),Z22-V22)) -> 4397491.4 | AC22: =IF(OR(AB22<0,Z22),AB22/Z22,0%) -> 0.033170172 | AD22: =IF(AA22=100%,IF(OR(V22<>0,Z22),Z22-V22),0) -> 0
B23: Durlock | C23: MAT | D23: 0 | E23: ='Resumen Pto #2'!E18 -> 0 | F23: ='Resumen Pto #2'!F18 -> 0 | G23: ='Resumen Pto #2'!G18 -> 0 | H23: ='Resumen Pto #2'!H18 -> 0 | I23: ='Resumen Pto #2'!I18 -> 0 | J23: ='Resumen Pto #2'!J18 -> 0 | K23: ='Resumen Pto #2'!K18 -> 0 | L23: ='Resumen Pto #2'!L18 -> 0 | ... T23: ='Resumen Pto #2'!T18 -> 0 | V23: {=SUMPRODUCT($D23:$U23,TRANSPOSE('Indice CAC'!$D$2:$D$19))} -> 7552799.6 | X23: 0 | Y23: ='Resumen Pto #2'!X18 -> 13489970 | Z23: =SUM(X23:Y23) -> 13489970 | AA23: =IF($C23="MAT",SUMIF('Cert. Pto. 02'!$A$10:$A$194,$B23,'Cert. Pto. 02'!$T$10:$T$194),IF($C23="MO",SUMIF('Cert. Pto. 02'!$A$10:$A$194,$B23,'Cert. Pto. 02'!$U$10:$U$194),SUMIF('Cert. Pto. 02'!$A$10:$A$194,$B23,'Cert. Pto. 02'!$V$10:$V$194)))/IF($C23="MAT",SUMIF('Cert. Pto. 02'!$A$10:$A$194,$B23,'Cert. Pto. 02'!$I$10:$I$194),IF($C23="MO",SUMIF('Cert. Pto. 02'!$A$10:$A$194,$B23,'Cert. Pto. 02'!$J$10:$J$194),SUMIF('Cert. Pto. 02'!$A$10:$A$194,$B23,'Cert. Pto. 02'!$K$10:$K$194))) -> 0.091870848 | AB23: =IF(AA23=100%,0,IF(OR(V23<>0,Z23),Z23-V23)) -> 5937170.7 | AC23: =IF(OR(AB23<0,Z23),AB23/Z23,0%) -> 0.4401174 | AD23: =IF(AA23=100%,IF(OR(V23<>0,Z23),Z23-V23),0) -> 0
B24: Durlock | C24: MO | D24: 0 | E24: ='Resumen Pto #2'!E19 -> 0 | F24: ='Resumen Pto #2'!F19 -> 0 | G24: ='Resumen Pto #2'!G19 -> 0 | H24: ='Resumen Pto #2'!H19 -> 0 | I24: ='Resumen Pto #2'!I19 -> 0 | J24: ='Resumen Pto #2'!J19 -> 0 | K24: ='Resumen Pto #2'!K19 -> 0 | L24: ='Resumen Pto #2'!L19 -> 0 | ... T24: ='Resumen Pto #2'!T19 -> 3175584 | V24: {=SUMPRODUCT($D24:$U24,TRANSPOSE('Indice CAC'!$D$2:$D$19))} -> 10896814 | X24: 0 | Y24: ='Resumen Pto #2'!X19 -> 38496186 | Z24: =SUM(X24:Y24) -> 38496186 | AA24: =IF($C24="MAT",SUMIF('Cert. Pto. 02'!$A$10:$A$194,$B24,'Cert. Pto. 02'!$T$10:$T$194),IF($C24="MO",SUMIF('Cert. Pto. 02'!$A$10:$A$194,$B24,'Cert. Pto. 02'!$U$10:$U$194),SUMIF('Cert. Pto. 02'!$A$10:$A$194,$B24,'Cert. Pto. 02'!$V$10:$V$194)))/IF($C24="MAT",SUMIF('Cert. Pto. 02'!$A$10:$A$194,$B24,'Cert. Pto. 02'!$I$10:$I$194),IF($C24="MO",SUMIF('Cert. Pto. 02'!$A$10:$A$194,$B24,'Cert. Pto. 02'!$J$10:$J$194),SUMIF('Cert. Pto. 02'!$A$10:$A$194,$B24,'Cert. Pto. 02'!$K$10:$K$194))) -> 0.045566874 | AB24: =IF(AA24=100%,0,IF(OR(V24<>0,Z24),Z24-V24)) -> 27599372 | AC24: =IF(OR(AB24<0,Z24),AB24/Z24,0%) -> 0.71693783 | AD24: =IF(AA24=100%,IF(OR(V24<>0,Z24),Z24-V24),0) -> 0
B25: Pintura | C25: MAT | D25: 0 | E25: ='Resumen Pto #2'!E20 -> 0 | F25: ='Resumen Pto #2'!F20 -> 0 | G25: ='Resumen Pto #2'!G20 -> 0 | H25: ='Resumen Pto #2'!H20 -> 0 | I25: ='Resumen Pto #2'!I20 -> 0 | J25: ='Resumen Pto #2'!J20 -> 0 | K25: ='Resumen Pto #2'!K20 -> 0 | L25: ='Resumen Pto #2'!L20 -> 0 | ... T25: ='Resumen Pto #2'!T20 -> 0 | V25: {=SUMPRODUCT($D25:$U25,TRANSPOSE('Indice CAC'!$D$2:$D$19))} -> 132350.95 | X25: 0 | Y25: ='Resumen Pto #2'!X20 -> 19488570 | Z25: =SUM(X25:Y25) -> 19488570 | AA25: =IF($C25="MAT",SUMIF('Cert. Pto. 02'!$A$10:$A$194,$B25,'Cert. Pto. 02'!$T$10:$T$194),IF($C25="MO",SUMIF('Cert. Pto. 02'!$A$10:$A$194,$B25,'Cert. Pto. 02'!$U$10:$U$194),SUMIF('Cert. Pto. 02'!$A$10:$A$194,$B25,'Cert. Pto. 02'!$V$10:$V$194)))/IF($C25="MAT",SUMIF('Cert. Pto. 02'!$A$10:$A$194,$B25,'Cert. Pto. 02'!$I$10:$I$194),IF($C25="MO",SUMIF('Cert. Pto. 02'!$A$10:$A$194,$B25,'Cert. Pto. 02'!$J$10:$J$194),SUMIF('Cert. Pto. 02'!$A$10:$A$194,$B25,'Cert. Pto. 02'!$K$10:$K$194))) -> 0 | AB25: =IF(AA25=100%,0,IF(OR(V25<>0,Z25),Z25-V25)) -> 19356219 | AC25: =IF(OR(AB25<0,Z25),AB25/Z25,0%) -> 0.99320879 | AD25: =IF(AA25=100%,IF(OR(V25<>0,Z25),Z25-V25),0) -> 0
B26: Pintura | C26: MO | D26: 0 | E26: ='Resumen Pto #2'!E21 -> 0 | F26: ='Resumen Pto #2'!F21 -> 0 | G26: ='Resumen Pto #2'!G21 -> 0 | H26: ='Resumen Pto #2'!H21 -> 0 | I26: ='Resumen Pto #2'!I21 -> 0 | J26: ='Resumen Pto #2'!J21 -> 0 | K26: ='Resumen Pto #2'!K21 -> 0 | L26: ='Resumen Pto #2'!L21 -> 0 | ... T26: ='Resumen Pto #2'!T21 -> 0 | V26: {=SUMPRODUCT($D26:$U26,TRANSPOSE('Indice CAC'!$D$2:$D$19))} -> 0 | X26: 0 | Y26: ='Resumen Pto #2'!X21 -> 40879545 | Z26: =SUM(X26:Y26) -> 40879545 | AA26: =IF($C26="MAT",SUMIF('Cert. Pto. 02'!$A$10:$A$194,$B26,'Cert. Pto. 02'!$T$10:$T$194),IF($C26="MO",SUMIF('Cert. Pto. 02'!$A$10:$A$194,$B26,'Cert. Pto. 02'!$U$10:$U$194),SUMIF('Cert. Pto. 02'!$A$10:$A$194,$B26,'Cert. Pto. 02'!$V$10:$V$194)))/IF($C26="MAT",SUMIF('Cert. Pto. 02'!$A$10:$A$194,$B26,'Cert. Pto. 02'!$I$10:$I$194),IF($C26="MO",SUMIF('Cert. Pto. 02'!$A$10:$A$194,$B26,'Cert. Pto. 02'!$J$10:$J$194),SUMIF('Cert. Pto. 02'!$A$10:$A$194,$B26,'Cert. Pto. 02'!$K$10:$K$194))) -> 0 | AB26: =IF(AA26=100%,0,IF(OR(V26<>0,Z26),Z26-V26)) -> 40879545 | AC26: =IF(OR(AB26<0,Z26),AB26/Z26,0%) -> 1 | AD26: =IF(AA26=100%,IF(OR(V26<>0,Z26),Z26-V26),0) -> 0
B27: Revestimiento | C27: MAT | D27: 0 | E27: ='Resumen Pto #2'!E22 -> 0 | F27: ='Resumen Pto #2'!F22 -> 0 | G27: ='Resumen Pto #2'!G22 -> 0 | H27: ='Resumen Pto #2'!H22 -> 0 | I27: ='Resumen Pto #2'!I22 -> 0 | J27: ='Resumen Pto #2'!J22 -> 0 | K27: ='Resumen Pto #2'!K22 -> 0 | L27: ='Resumen Pto #2'!L22 -> 0 | ... T27: ='Resumen Pto #2'!T22 -> 0 | V27: {=SUMPRODUCT($D27:$U27,TRANSPOSE('Indice CAC'!$D$2:$D$19))} -> 1690828.7 | X27: 0 | Y27: ='Resumen Pto #2'!X22 -> 13983960 | Z27: =SUM(X27:Y27) -> 13983960 | AA27: =IF($C27="MAT",SUMIF('Cert. Pto. 02'!$A$10:$A$194,$B27,'Cert. Pto. 02'!$T$10:$T$194),IF($C27="MO",SUMIF('Cert. Pto. 02'!$A$10:$A$194,$B27,'Cert. Pto. 02'!$U$10:$U$194),SUMIF('Cert. Pto. 02'!$A$10:$A$194,$B27,'Cert. Pto. 02'!$V$10:$V$194)))/IF($C27="MAT",SUMIF('Cert. Pto. 02'!$A$10:$A$194,$B27,'Cert. Pto. 02'!$I$10:$I$194),IF($C27="MO",SUMIF('Cert. Pto. 02'!$A$10:$A$194,$B27,'Cert. Pto. 02'!$J$10:$J$194),SUMIF('Cert. Pto. 02'!$A$10:$A$194,$B27,'Cert. Pto. 02'!$K$10:$K$194))) -> 0 | AB27: =IF(AA27=100%,0,IF(OR(V27<>0,Z27),Z27-V27)) -> 12293132 | AC27: =IF(OR(AB27<0,Z27),AB27/Z27,0%) -> 0.87908799 | AD27: =IF(AA27=100%,IF(OR(V27<>0,Z27),Z27-V27),0) -> 0
B28: Revestimiento | C28: MO | D28: 0 | E28: ='Resumen Pto #2'!E23 -> 0 | F28: ='Resumen Pto #2'!F23 -> 0 | G28: ='Resumen Pto #2'!G23 -> 0 | H28: ='Resumen Pto #2'!H23 -> 0 | I28: ='Resumen Pto #2'!I23 -> 0 | J28: ='Resumen Pto #2'!J23 -> 0 | K28: ='Resumen Pto #2'!K23 -> 0 | L28: ='Resumen Pto #2'!L23 -> 0 | ... T28: ='Resumen Pto #2'!T23 -> 0 | V28: {=SUMPRODUCT($D28:$U28,TRANSPOSE('Indice CAC'!$D$2:$D$19))} -> 1531929.8 | X28: 0 | Y28: ='Resumen Pto #2'!X23 -> 26733574 | Z28: =SUM(X28:Y28) -> 26733574 | AA28: =IF($C28="MAT",SUMIF('Cert. Pto. 02'!$A$10:$A$194,$B28,'Cert. Pto. 02'!$T$10:$T$194),IF($C28="MO",SUMIF('Cert. Pto. 02'!$A$10:$A$194,$B28,'Cert. Pto. 02'!$U$10:$U$194),SUMIF('Cert. Pto. 02'!$A$10:$A$194,$B28,'Cert. Pto. 02'!$V$10:$V$194)))/IF($C28="MAT",SUMIF('Cert. Pto. 02'!$A$10:$A$194,$B28,'Cert. Pto. 02'!$I$10:$I$194),IF($C28="MO",SUMIF('Cert. Pto. 02'!$A$10:$A$194,$B28,'Cert. Pto. 02'!$J$10:$J$194),SUMIF('Cert. Pto. 02'!$A$10:$A$194,$B28,'Cert. Pto. 02'!$K$10:$K$194))) -> 0 | AB28: =IF(AA28=100%,0,IF(OR(V28<>0,Z28),Z28-V28)) -> 25201645 | AC28: =IF(OR(AB28<0,Z28),AB28/Z28,0%) -> 0.94269641 | AD28: =IF(AA28=100%,IF(OR(V28<>0,Z28),Z28-V28),0) -> 0
B29: Eléctrico | C29: MAT | D29: 0 | E29: ='Resumen Pto #2'!E24 -> 0 | F29: ='Resumen Pto #2'!F24 -> 0 | G29: ='Resumen Pto #2'!G24 -> 0 | H29: ='Resumen Pto #2'!H24 -> 0 | I29: ='Resumen Pto #2'!I24 -> 0 | J29: ='Resumen Pto #2'!J24 -> 0 | K29: ='Resumen Pto #2'!K24 -> 299136.83 | L29: ='Resumen Pto #2'!L24 -> 1111962.1 | ... T29: ='Resumen Pto #2'!T24 -> 76388.01 | V29: {=SUMPRODUCT($D29:$U29,TRANSPOSE('Indice CAC'!$D$2:$D$19))} -> 4965352.9 | X29: 0 | Y29: ='Resumen Pto #2'!X24 -> 25092460 | Z29: =SUM(X29:Y29) -> 25092460 | AA29: =IF($C29="MAT",SUMIF('Cert. Pto. 02'!$A$10:$A$194,$B29,'Cert. Pto. 02'!$T$10:$T$194),IF($C29="MO",SUMIF('Cert. Pto. 02'!$A$10:$A$194,$B29,'Cert. Pto. 02'!$U$10:$U$194),SUMIF('Cert. Pto. 02'!$A$10:$A$194,$B29,'Cert. Pto. 02'!$V$10:$V$194)))/IF($C29="MAT",SUMIF('Cert. Pto. 02'!$A$10:$A$194,$B29,'Cert. Pto. 02'!$I$10:$I$194),IF($C29="MO",SUMIF('Cert. Pto. 02'!$A$10:$A$194,$B29,'Cert. Pto. 02'!$J$10:$J$194),SUMIF('Cert. Pto. 02'!$A$10:$A$194,$B29,'Cert. Pto. 02'!$K$10:$K$194))) -> 0.28984006 | AB29: =IF(AA29=100%,0,IF(OR(V29<>0,Z29),Z29-V29)) -> 20127107 | AC29: =IF(OR(AB29<0,Z29),AB29/Z29,0%) -> 0.80211773 | AD29: =IF(AA29=100%,IF(OR(V29<>0,Z29),Z29-V29),0) -> 0
B30: Eléctrico | C30: MO | D30: 0 | E30: ='Resumen Pto #2'!E25 -> 0 | F30: ='Resumen Pto #2'!F25 -> 0 | G30: ='Resumen Pto #2'!G25 -> 0 | H30: ='Resumen Pto #2'!H25 -> 0 | I30: ='Resumen Pto #2'!I25 -> 0 | J30: ='Resumen Pto #2'!J25 -> 0 | K30: ='Resumen Pto #2'!K25 -> 500000 | L30: ='Resumen Pto #2'!L25 -> 450000 | ... T30: ='Resumen Pto #2'!T25 -> 0 | V30: {=SUMPRODUCT($D30:$U30,TRANSPOSE('Indice CAC'!$D$2:$D$19))} -> 17814883 | X30: 0 | Y30: ='Resumen Pto #2'!X25 -> 41278489 | Z30: =SUM(X30:Y30) -> 41278489 | AA30: =IF($C30="MAT",SUMIF('Cert. Pto. 02'!$A$10:$A$194,$B30,'Cert. Pto. 02'!$T$10:$T$194),IF($C30="MO",SUMIF('Cert. Pto. 02'!$A$10:$A$194,$B30,'Cert. Pto. 02'!$U$10:$U$194),SUMIF('Cert. Pto. 02'!$A$10:$A$194,$B30,'Cert. Pto. 02'!$V$10:$V$194)))/IF($C30="MAT",SUMIF('Cert. Pto. 02'!$A$10:$A$194,$B30,'Cert. Pto. 02'!$I$10:$I$194),IF($C30="MO",SUMIF('Cert. Pto. 02'!$A$10:$A$194,$B30,'Cert. Pto. 02'!$J$10:$J$194),SUMIF('Cert. Pto. 02'!$A$10:$A$194,$B30,'Cert. Pto. 02'!$K$10:$K$194))) -> 0.33069101 | AB30: =IF(AA30=100%,0,IF(OR(V30<>0,Z30),Z30-V30)) -> 23463605 | AC30: =IF(OR(AB30<0,Z30),AB30/Z30,0%) -> 0.5684221 | AD30: =IF(AA30=100%,IF(OR(V30<>0,Z30),Z30-V30),0) -> 0
B31: Sanitaria | C31: MAT | D31: 0 | E31: ='Resumen Pto #2'!E26 -> 0 | F31: ='Resumen Pto #2'!F26 -> 0 | G31: ='Resumen Pto #2'!G26 -> 0 | H31: ='Resumen Pto #2'!H26 -> 0 | I31: ='Resumen Pto #2'!I26 -> 0 | J31: ='Resumen Pto #2'!J26 -> 0 | K31: ='Resumen Pto #2'!K26 -> 7851.24 | L31: ='Resumen Pto #2'!L26 -> 0 | ... T31: ='Resumen Pto #2'!T26 -> 633057 | V31: {=SUMPRODUCT($D31:$U31,TRANSPOSE('Indice CAC'!$D$2:$D$19))} -> 6425159.6 | X31: 0 | Y31: ='Resumen Pto #2'!X26 -> 32568315 | Z31: =SUM(X31:Y31) -> 32568315 | AA31: =IF($C31="MAT",SUMIF('Cert. Pto. 02'!$A$10:$A$194,$B31,'Cert. Pto. 02'!$T$10:$T$194),IF($C31="MO",SUMIF('Cert. Pto. 02'!$A$10:$A$194,$B31,'Cert. Pto. 02'!$U$10:$U$194),SUMIF('Cert. Pto. 02'!$A$10:$A$194,$B31,'Cert. Pto. 02'!$V$10:$V$194)))/IF($C31="MAT",SUMIF('Cert. Pto. 02'!$A$10:$A$194,$B31,'Cert. Pto. 02'!$I$10:$I$194),IF($C31="MO",SUMIF('Cert. Pto. 02'!$A$10:$A$194,$B31,'Cert. Pto. 02'!$J$10:$J$194),SUMIF('Cert. Pto. 02'!$A$10:$A$194,$B31,'Cert. Pto. 02'!$K$10:$K$194))) -> 0.21719598 | AB31: =IF(AA31=100%,0,IF(OR(V31<>0,Z31),Z31-V31)) -> 26143156 | AC31: =IF(OR(AB31<0,Z31),AB31/Z31,0%) -> 0.80271747 | AD31: =IF(AA31=100%,IF(OR(V31<>0,Z31),Z31-V31),0) -> 0
B32: Sanitaria | C32: MO | D32: 0 | E32: ='Resumen Pto #2'!E27 -> 0 | F32: ='Resumen Pto #2'!F27 -> 0 | G32: ='Resumen Pto #2'!G27 -> 0 | H32: ='Resumen Pto #2'!H27 -> 0 | I32: ='Resumen Pto #2'!I27 -> 0 | J32: ='Resumen Pto #2'!J27 -> 0 | K32: ='Resumen Pto #2'!K27 -> 0 | L32: ='Resumen Pto #2'!L27 -> 0 | ... T32: ='Resumen Pto #2'!T27 -> 0 | V32: {=SUMPRODUCT($D32:$U32,TRANSPOSE('Indice CAC'!$D$2:$D$19))} -> 16085672 | X32: 0 | Y32: ='Resumen Pto #2'!X27 -> 75115078 | Z32: =SUM(X32:Y32) -> 75115078 | AA32: =IF($C32="MAT",SUMIF('Cert. Pto. 02'!$A$10:$A$194,$B32,'Cert. Pto. 02'!$T$10:$T$194),IF($C32="MO",SUMIF('Cert. Pto. 02'!$A$10:$A$194,$B32,'Cert. Pto. 02'!$U$10:$U$194),SUMIF('Cert. Pto. 02'!$A$10:$A$194,$B32,'Cert. Pto. 02'!$V$10:$V$194)))/IF($C32="MAT",SUMIF('Cert. Pto. 02'!$A$10:$A$194,$B32,'Cert. Pto. 02'!$I$10:$I$194),IF($C32="MO",SUMIF('Cert. Pto. 02'!$A$10:$A$194,$B32,'Cert. Pto. 02'!$J$10:$J$194),SUMIF('Cert. Pto. 02'!$A$10:$A$194,$B32,'Cert. Pto. 02'!$K$10:$K$194))) -> 0.25606992 | AB32: =IF(AA32=100%,0,IF(OR(V32<>0,Z32),Z32-V32)) -> 59029405 | AC32: =IF(OR(AB32<0,Z32),AB32/Z32,0%) -> 0.78585295 | AD32: =IF(AA32=100%,IF(OR(V32<>0,Z32),Z32-V32),0) -> 0
B33: Equipos | D33: ='Resumen Pto #1'!D18 -> 58271.121 | E33: ='Resumen Pto #1'!E18+'Resumen Pto #2'!E28 -> 59559.523 | F33: ='Resumen Pto #1'!F18+'Resumen Pto #2'!F28 -> 64331.918 | G33: ='Resumen Pto #1'!G18+'Resumen Pto #2'!G28 -> 287221.2 | H33: ='Resumen Pto #1'!H18+'Resumen Pto #2'!H28 -> 290739.63 | I33: ='Resumen Pto #1'!I18+'Resumen Pto #2'!I28 -> 296307.18 | J33: ='Resumen Pto #1'!J18+'Resumen Pto #2'!J28 -> 346009.64 | K33: ='Resumen Pto #1'!K18+'Resumen Pto #2'!K28 -> 799574.25 | L33: ='Resumen Pto #1'!L18+'Resumen Pto #2'!L28 -> 631705.98 | ... T33: ='Resumen Pto #1'!T18+'Resumen Pto #2'!T28 -> 0 | V33: {=SUMPRODUCT($D33:$U33,TRANSPOSE('Indice CAC'!$D$2:$D$19))} -> 6788085.2 | X33: ='Resumen Pto #1'!X18 -> 13604196 | Y33: ='Resumen Pto #2'!X28 -> 7890286.6 | Z33: =SUM(X33:Y33) -> 21494483 | AA33: =AVERAGE('Cert. Pto. 01'!S48,'Cert. Pto. 02'!S196) -> 0.66328256 | AB33: =IF(AA33=100%,0,IF(OR(V33<>0,Z33),Z33-V33)) -> 14706398 | AC33: =IF(OR(AB33<0,Z33),AB33/Z33,0%) -> 0.68419407 | AD33: =IF(AA33=100%,IF(OR(V33<>0,Z33),Z33-V33),0) -> 0
B34: Gastos Generales Obra | D34: ='Resumen Pto #1'!D19 -> 12905.63 | E34: ='Resumen Pto #1'!E19 -> 0 | F34: ='Resumen Pto #1'!F19 -> 90000 | G34: ='Resumen Pto #1'!G19 -> 180000 | H34: ='Resumen Pto #1'!H19 -> 80000 | I34: ='Resumen Pto #1'!I19 -> 80000 | J34: ='Resumen Pto #1'!J19 -> 380000 | K34: ='Resumen Pto #1'!K19 -> 160000 | ... T34: ='Resumen Pto #1'!T19 -> 0 | V34: {=SUMPRODUCT($D34:$U34,TRANSPOSE('Indice CAC'!$D$2:$D$19))} -> 3563879 | X34: ='Resumen Pto #1'!X19 -> 5763772 | Y34: 0 | Z34: =SUM(X34:Y34) -> 5763772 | AA34: =IF($C34="MAT",SUMIF('Cert. Pto. 01'!$A$9:$A$45,$B34,'Cert. Pto. 01'!$T$9:$T$45),IF($C34="MO",SUMIF('Cert. Pto. 01'!$A$9:$A$45,$B34,'Cert. Pto. 01'!$U$9:$U$45),SUMIF('Cert. Pto. 01'!$A$9:$A$45,$B34,'Cert. Pto. 01'!$V$9:$V$45)))/IF($C34="MAT",SUMIF('Cert. Pto. 01'!$A$9:$A$45,$B34,'Cert. Pto. 01'!$I$9:$I$45),IF($C34="MO",SUMIF('Cert. Pto. 01'!$A$9:$A$45,$B34,'Cert. Pto. 01'!$J$9:$J$45),SUMIF('Cert. Pto. 01'!$A$9:$A$45,$B34,'Cert. Pto. 01'!$K$9:$K$45))) -> 1 | AB34: =IF(AA34=100%,0,IF(OR(V34<>0,Z34),Z34-V34)) -> 0 | AC34: =IF(OR(AB34<0,Z34),AB34/Z34,0%) -> 0 | AD34: =IF(AA34=100%,IF(OR(V34<>0,Z34),Z34-V34),0) -> 2199893
B35: Total Egresos de Obra | D35: =SUM(D13:D34) -> 2309382.8 | E35: =SUM(E13:E34) -> 2883427.1 | F35: =SUM(F13:F34) -> 14390356 | G35: =SUM(G13:G34) -> 45119461 | H35: =SUM(H13:H34) -> 84346570 | I35: =SUM(I13:I34) -> 65383252 | J35: =SUM(J13:J34) -> 25225003 | K35: =SUM(K13:K34) -> 69134848 | ... T35: =SUM(T13:T34) -> 8523877.9 | V35: =SUM(V13:V34) -> 6.0790348e+08 | X35: =SUM(X13:X34) -> 3.8028591e+08 | Y35: =SUM(Y13:Y34) -> 6.2947919e+08 | Z35: =SUM(Z13:Z34) -> 1.0097651e+09 | AA35: =SUM('Cert. Pto. 01'!V46,'Cert. Pto. 02'!V195)/SUM('Cert. Pto. 01'!L46,'Cert. Pto. 02'!L195) -> 0.57722683 | AB35: =IF(AA35=100%,0,IF(OR(V35<>0,Z35),Z35-V35)) -> 4.0186161e+08 | AC35: =IF(OR(AB35<0,Z35),AB35/Z35,0%) -> 0.39797535 | AD35: =SUM(AD13:AD34) -> 54195229
B37: Gastos Generales
B38: Gastos Directos | D38: =SUM('Resumen Pto #1'!D$23,'Resumen Pto #2'!D$32) -> 3175204.8 | E38: =SUM('Resumen Pto #1'!E$23,'Resumen Pto #2'!E$32) -> 2020935.7 | F38: =SUM('Resumen Pto #1'!F$23,'Resumen Pto #2'!F$32) -> 2883500.7 | G38: =SUM('Resumen Pto #1'!G$23,'Resumen Pto #2'!G$32) -> 2286455.7 | H38: =SUM('Resumen Pto #1'!H$23,'Resumen Pto #2'!H$32) -> 6273647.6 | I38: =SUM('Resumen Pto #1'!I$23,'Resumen Pto #2'!I$32) -> 1963509.9 | J38: =SUM('Resumen Pto #1'!J$23,'Resumen Pto #2'!J$32) -> 2816808 | K38: =SUM('Resumen Pto #1'!K$23,'Resumen Pto #2'!K$32) -> 2808099.8 | ... T38: =SUM('Resumen Pto #1'!T$23,'Resumen Pto #2'!T$32) -> 0 | V38: {=SUMPRODUCT($D38:$U38,TRANSPOSE('Indice CAC'!$D$2:$D$19))} -> 45619359 | X38: ='Resumen Pto #1'!X23 -> 60150532 | Y38: ='Resumen Pto #2'!X32 -> 32809381 | Z38: =SUM(X38:Y38) -> 92959913 | AA38: =AVERAGE('Cert. Pto. 01'!S48,'Cert. Pto. 02'!S196) -> 0.66328256 | AB38: =IF(AA38=100%,0,IF(OR(V38<>0,Z38),Z38-V38)) -> 47340554 | AC38: =IF(OR(AB38<0,Z38),AB38/Z38,0%) -> 0.50925772 | AD38: =IF(AA38=100%,IF(OR(V38<>0,Z38),Z38-V38),0) -> 0
B39: Gastos Indirectos | D39: =SUM('Resumen Pto #1'!D$24,'Resumen Pto #2'!D$33) -> 639132.78 | E39: =SUM('Resumen Pto #1'!E$24,'Resumen Pto #2'!E$33) -> 1825790.3 | F39: =SUM('Resumen Pto #1'!F$24,'Resumen Pto #2'!F$33) -> 1406464.9 | G39: =SUM('Resumen Pto #1'!G$24,'Resumen Pto #2'!G$33) -> 2714187.3 | H39: =SUM('Resumen Pto #1'!H$24,'Resumen Pto #2'!H$33) -> 2169029.3 | I39: =SUM('Resumen Pto #1'!I$24,'Resumen Pto #2'!I$33) -> 1800256.2 | J39: =SUM('Resumen Pto #1'!J$24,'Resumen Pto #2'!J$33) -> 2949259.1 | K39: =SUM('Resumen Pto #1'!K$24,'Resumen Pto #2'!K$33) -> 4175013.8 | ... T39: =SUM('Resumen Pto #1'!T$24,'Resumen Pto #2'!T$33) -> 0 | V39: {=SUMPRODUCT($D39:$U39,TRANSPOSE('Indice CAC'!$D$2:$D$19))} -> 38502555 | X39: ='Resumen Pto #1'!X24 -> 53546314 | Y39: ='Resumen Pto #2'!X33 -> 29207081 | Z39: =SUM(X39:Y39) -> 82753395 | AA39: =AVERAGE('Cert. Pto. 01'!S48,'Cert. Pto. 02'!S196) -> 0.66328256 | AB39: =IF(AA39=100%,0,IF(OR(V39<>0,Z39),Z39-V39)) -> 44250840 | AC39: =IF(OR(AB39<0,Z39),AB39/Z39,0%) -> 0.53473141 | AD39: =IF(AA39=100%,IF(OR(V39<>0,Z39),Z39-V39),0) -> 0
B40: Total Gastos Generales | D40: =SUM(D38:D39) -> 3814337.6 | E40: =SUM(E38:E39) -> 3846726 | F40: =SUM(F38:F39) -> 4289965.6 | G40: =SUM(G38:G39) -> 5000643 | H40: =SUM(H38:H39) -> 8442676.9 | I40: =SUM(I38:I39) -> 3763766.1 | J40: =SUM(J38:J39) -> 5766067.1 | K40: =SUM(K38:K39) -> 6983113.6 | ... T40: =SUM(T38:T39) -> 0 | V40: =SUM(V38:V39) -> 84121914 | X40: =SUM(X38:X39) -> 1.1369685e+08 | Y40: =SUM(Y38:Y39) -> 62016462 | Z40: =SUM(Z38:Z39) -> 1.7571331e+08 | AB40: =IF(AA40=100%,0,IF(OR(V40<>0,Z40),Z40-V40)) -> 91591394 | AC40: =IF(OR(AB40<0,Z40),AB40/Z40,0%) -> 0.52125473 | AD40: =SUM(AD38:AD39) -> 0
B42: Total Egresos | D42: =D35+D40 -> 6123720.3 | E42: =E35+E40 -> 6730153.1 | F42: =F35+F40 -> 18680321 | G42: =G35+G40 -> 50120104 | H42: =H35+H40 -> 92789247 | I42: =I35+I40 -> 69147018 | J42: =J35+J40 -> 30991070 | K42: =K35+K40 -> 76117962 | ... T42: =T35+T40 -> 8523877.9 | V42: =V35+V40 -> 6.920254e+08 | X42: =X35+X40 -> 4.9398275e+08 | Y42: =Y35+Y40 -> 6.9149565e+08 | Z42: =Z35+Z40 -> 1.1854784e+09
B44: Resultado Operativo | D44: =SUM(D8,D10,-D42) -> -6123720.3 | E44: =SUM(E8,E10,-E42) -> -6730153.1 | F44: =SUM(F8,F10,-F42) -> 2.7536765e+08 | G44: =SUM(G8,G10,-G42) -> -21611627 | H44: =SUM(H8,H10,-H42) -> -67458111 | I44: =SUM(I8,I10,-I42) -> -18489177 | J44: =SUM(J8,J10,-J42) -> 1151020.9 | K44: =SUM(K8,K10,-K42) -> -3402338 | ... T44: =SUM(T8,T10,-T42) -> -8523877.9 | V44: =V8-V42 -> 53854106 | Z44: =Z8-Z42 -> 1.6027457e+08
B45: Resultado Acumulado | D45: =D44 -> -6123720.3 | E45: =D45+E44 -> -12853873 | F45: =E45+F44 -> 2.6251378e+08 | G45: =F45+G44 -> 2.4090215e+08 | H45: =G45+H44 -> 1.7344404e+08 | I45: =H45+I44 -> 1.5495486e+08 | J45: =I45+J44 -> 1.5610588e+08 | K45: =J45+K44 -> 1.5270355e+08 | L45: =K45+L44 -> 1.6960522e+08 | ... T45: =S45+T44 -> 37288390
B47: Resultado Operativo USD | D47: =D44/VLOOKUP(EOMONTH(DATE(2024,COLUMN(L1),1),0),'TC USD MEP'!$B$6:$C$1808,2,0) -> -5232.1155 | E47: =E44/VLOOKUP(EOMONTH(DATE(2025,COLUMN(A1),1),0),'TC USD MEP'!$B$6:$C$1808,2,0) -> -5777.997 | F47: =F44/VLOOKUP(EOMONTH(DATE(2025,COLUMN(B1),1),0),'TC USD MEP'!$B$6:$C$1808,2,0) -> 224153.14 | G47: =G44/VLOOKUP(EOMONTH(DATE(2025,COLUMN(C1),1),0),'TC USD MEP'!$B$6:$C$1808,2,0) -> -16447.58 | H47: =H44/VLOOKUP(EOMONTH(DATE(2025,COLUMN(D1),1),0),'TC USD MEP'!$B$6:$C$1808,2,0) -> -57005.088 | I47: =I44/VLOOKUP(EOMONTH(DATE(2025,COLUMN(E1),1),0),'TC USD MEP'!$B$6:$C$1808,2,0) -> -15514.699 | J47: =J44/VLOOKUP(EOMONTH(DATE(2025,COLUMN(F1),1),0),'TC USD MEP'!$B$6:$C$1808,2,0) -> 950.39291 | K47: =K44/VLOOKUP(EOMONTH(DATE(2025,COLUMN(G1),1),0),'TC USD MEP'!$B$6:$C$1808,2,0) -> -2502.1607 | L47: =L44/VLOOKUP(EOMONTH(DATE(2025,COLUMN(H1),1),0),'TC USD MEP'!$B$6:$C$1808,2,0) -> 12452.057 | ... P47: =P44/VLOOKUP(EOMONTH(DATE(2025,COLUMN(L1),1),0),'TC USD MEP'!$B$6:$C$1808,2,0) -> -8861.2181 | Q47: =Q44/VLOOKUP(EOMONTH(DATE(2026,COLUMN(A1),1),0),'TC USD MEP'!$B$6:$C$1808,2,0) -> -7563.6391 | R47: =R44/VLOOKUP(EOMONTH(DATE(2026,COLUMN(B1),1),0),'TC USD MEP'!$B$6:$C$1808,2,0) -> -14612.535 | S47: =S44/VLOOKUP(EOMONTH(DATE(2026,COLUMN(C1),1),0),'TC USD MEP'!$B$6:$C$1808,2,0) -> 1908.7014 | T47: =T44/VLOOKUP(EOMONTH(DATE(2026,COLUMN(D1),1),0),'TC USD MEP'!$B$6:$C$1808,2,0) -> -5909.3876
B48: Resultado Acumulado USD | D48: =D45/VLOOKUP(EOMONTH(DATE(2024,COLUMN(L2),1),0),'TC USD MEP'!$B$6:$C$1808,2,0) -> -5232.1155 | E48: =E45/VLOOKUP(EOMONTH(DATE(2025,COLUMN(A2),1),0),'TC USD MEP'!$B$6:$C$1808,2,0) -> -11035.357 | F48: =F45/VLOOKUP(EOMONTH(DATE(2025,COLUMN(B2),1),0),'TC USD MEP'!$B$6:$C$1808,2,0) -> 213689.91 | G48: =G45/VLOOKUP(EOMONTH(DATE(2025,COLUMN(C2),1),0),'TC USD MEP'!$B$6:$C$1808,2,0) -> 183339.16 | H48: =H45/VLOOKUP(EOMONTH(DATE(2025,COLUMN(D2),1),0),'TC USD MEP'!$B$6:$C$1808,2,0) -> 146567.89 | I48: =I45/VLOOKUP(EOMONTH(DATE(2025,COLUMN(E2),1),0),'TC USD MEP'!$B$6:$C$1808,2,0) -> 130026.23 | J48: =J45/VLOOKUP(EOMONTH(DATE(2025,COLUMN(F2),1),0),'TC USD MEP'!$B$6:$C$1808,2,0) -> 128895.95 | K48: =K45/VLOOKUP(EOMONTH(DATE(2025,COLUMN(G2),1),0),'TC USD MEP'!$B$6:$C$1808,2,0) -> 112301.84 | L48: =L45/VLOOKUP(EOMONTH(DATE(2025,COLUMN(H2),1),0),'TC USD MEP'!$B$6:$C$1808,2,0) -> 124954.12 | ... P48: =P45/VLOOKUP(EOMONTH(DATE(2025,COLUMN(L2),1),0),'TC USD MEP'!$B$6:$C$1808,2,0) -> 50572.621 | Q48: =Q45/VLOOKUP(EOMONTH(DATE(2026,COLUMN(A2),1),0),'TC USD MEP'!$B$6:$C$1808,2,0) -> 43716.151 | R48: =R45/VLOOKUP(EOMONTH(DATE(2026,COLUMN(B2),1),0),'TC USD MEP'!$B$6:$C$1808,2,0) -> 30359.476 | S48: =S45/VLOOKUP(EOMONTH(DATE(2026,COLUMN(C2),1),0),'TC USD MEP'!$B$6:$C$1808,2,0) -> 32197.765 | T48: =T45/VLOOKUP(EOMONTH(DATE(2026,COLUMN(D2),1),0),'TC USD MEP'!$B$6:$C$1808,2,0) -> 25851.092
Z67: =Z42+Z44-Z10 -> 1345752968

Sheet Resumen Pto #1
AC1: Actualizado | AD1: 46133
B3: OBRA: GDR 3760
B4: RESUMEN DE OBRA
D5: 45627 | E5: 45658 | F5: 45689 | G5: 45717 | H5: 45748 | I5: 45778 | J5: 45809 | K5: 45839 | L5: 45870 | M5: 45901 | N5: 45931 | O5: 45962 | P5: 45992 | Q5: 46023 | R5: 46054 | S5: 46082 | T5: 46113 | V5: Acum. Descontado | X5: Previsto | Y5: % Cert. Acum. | Z5: Saldo Disponible | AA5: Disponible % | AB5: Rubro Completado
B6: Ingresos de Obra
B7: Ingresos por certificados | D7: =SUMIFS(Certificados!$E$12:$E$80,Certificados!$A$12:$A$80,">="&DATE(2024,12,1),Certificados!$A$12:$A$80,"<="&DATE(2024,12,31),Certificados!$C$12:$C$80,"Pto. 1") -> 0 | E7: =SUMIFS(Certificados!$E$12:$E$80,Certificados!$A$12:$A$80,">="&DATE(2025,1,1),Certificados!$A$12:$A$80,"<="&DATE(2025,1,31),Certificados!$C$12:$C$80,"Pto. 1") -> 0 | F7: =SUMIFS(Certificados!$E$12:$E$80,Certificados!$A$12:$A$80,">="&DATE(2025,2,1),Certificados!$A$12:$A$80,"<="&DATE(2025,2,28),Certificados!$C$12:$C$80,"Pto. 1") -> 200363088 | G7: =SUMIFS(Certificados!$E$12:$E$80,Certificados!$A$12:$A$80,">="&DATE(2025,3,1),Certificados!$A$12:$A$80,"<="&DATE(2025,3,31),Certificados!$C$12:$C$80,"Pto. 1") -> 19603686 | H7: =SUMIFS(Certificados!$E$12:$E$80,Certificados!$A$12:$A$80,">="&DATE(2025,4,1),Certificados!$A$12:$A$80,"<="&DATE(2025,4,30),Certificados!$C$12:$C$80,"Pto. 1") -> 16465959 | I7: =SUMIFS(Certificados!$E$12:$E$80,Certificados!$A$12:$A$80,">="&DATE(2025,5,1),Certificados!$A$12:$A$80,"<="&DATE(2025,5,31),Certificados!$C$12:$C$80,"Pto. 1") -> 38898523 | J7: =SUMIFS(Certificados!$E$12:$E$80,Certificados!$A$12:$A$80,">="&DATE(2025,6,1),Certificados!$A$12:$A$80,"<="&DATE(2025,6,30),Certificados!$C$12:$C$80,"Pto. 1") -> 21634404 | K7: =SUMIFS(Certificados!$E$12:$E$80,Certificados!$A$12:$A$80,">="&DATE(2025,7,1),Certificados!$A$12:$A$80,"<="&DATE(2025,7,31),Certificados!$C$12:$C$80,"Pto. 1") -> 56374940 | L7: =SUMIFS(Certificados!$E$12:$E$80,Certificados!$A$12:$A$80,">="&DATE(2025,8,1),Certificados!$A$12:$A$80,"<="&DATE(2025,8,31),Certificados!$C$12:$C$80,"Pto. 1") -> 33566952 | M7: =SUMIFS(Certificados!$E$12:$E$80,Certificados!$A$12:$A$80,">="&DATE(2025,9,1),Certificados!$A$12:$A$80,"<="&DATE(2025,9,30),Certificados!$C$12:$C$80,"Pto. 1") -> 20270753 | N7: =SUMIFS(Certificados!$E$12:$E$80,Certificados!$A$12:$A$80,">="&DATE(2025,10,1),Certificados!$A$12:$A$80,"<="&DATE(2025,10,30),Certificados!$C$12:$C$80,"Pto. 1") -> 15191867 | O7: =SUMIFS(Certificados!$E$12:$E$80,Certificados!$A$12:$A$80,">="&DATE(2025,11,1),Certificados!$A$12:$A$80,"<="&DATE(2025,11,30),Certificados!$C$12:$C$80,"Pto. 1") -> -9282491.1 | P7: =SUMIFS(Certificados!$E$12:$E$80,Certificados!$A$12:$A$80,">="&DATE(2025,12,1),Certificados!$A$12:$A$80,"<="&DATE(2025,12,31),Certificados!$C$12:$C$80,"Pto. 1") -> 0 | Q7: =SUMIFS(Certificados!$E$12:$E$80,Certificados!$A$12:$A$80,">="&DATE(2026,1,1),Certificados!$A$12:$A$80,"<="&DATE(2026,1,31),Certificados!$C$12:$C$80,"Pto. 1") -> 0 | R7: =SUMIFS(Certificados!$E$12:$E$80,Certificados!$A$12:$A$80,">="&DATE(2026,2,1),Certificados!$A$12:$A$80,"<="&DATE(2026,2,28),Certificados!$C$12:$C$80,"Pto. 1") -> 0 | S7: =SUMIFS(Certificados!$E$12:$E$80,Certificados!$A$12:$A$80,">="&DATE(2026,3,1),Certificados!$A$12:$A$80,"<="&DATE(2026,3,31),Certificados!$C$12:$C$80,"Pto. 1") -> 0 | T7: =SUMIFS(Certificados!$E$12:$E$80,Certificados!$A$12:$A$80,">="&DATE(2026,4,1),Certificados!$A$12:$A$80,"<="&DATE(2026,4,30),Certificados!$C$12:$C$80,"Pto. 1") -> 0 | V7: =SUM(D7:U7) -> 4.1308768e+08 | X7: =SUM(Facturacion!E4:E5) -> 500907720 | Y7: ='Cert. Pto. 01'!S46/'Cert. Pto. 01'!L46 -> 1 | Z7: =IF(Y7=100%,0,IF(OR(V7<>0,X7),X7-V7)) -> 0 | AA7: =IF(OR(Z7<0,X7),Z7/X7,0%) -> 0 | AB7: =IF(Y7=100%,IF(OR(V7<>0,X7),X7-V7),0) -> 87820039
B8: Total Ingresos de Obra | D8: =SUM(D7) -> 0 | E8: =SUM(E7) -> 0 | F8: =SUM(F7) -> 200363088 | G8: =SUM(G7) -> 19603686 | H8: =SUM(H7) -> 16465959 | I8: =SUM(I7) -> 38898523 | J8: =SUM(J7) -> 21634404 | K8: =SUM(K7) -> 56374940 | ... T8: =SUM(T7) -> 0 | V8: =SUM(V7) -> 4.1308768e+08 | X8: =SUM(X7) -> 500907720 | Z8: =SUM(Z7) -> 0 | AA8: =IF(OR(Z8<0,X8),Z8/X8,0%) -> 0 | AB8: =SUM(AB7) -> 87820039
B9: Actualización por CAC | D9: =SUMIFS(Certificados!$F$12:$F$80,Certificados!$A$12:$A$80,">="&DATE(2024,12,1),Certificados!$A$12:$A$80,"<="&DATE(2024,12,31),Certificados!$C$12:$C$80,"Pto. 1") -> 0 | E9: =SUMIFS(Certificados!$F$12:$F$80,Certificados!$A$12:$A$80,">="&DATE(2025,1,1),Certificados!$A$12:$A$80,"<="&DATE(2025,1,31),Certificados!$C$12:$C$80,"Pto. 1") -> 0 | F9: =SUMIFS(Certificados!$F$12:$F$80,Certificados!$A$12:$A$80,">="&DATE(2025,2,1),Certificados!$A$12:$A$80,"<="&DATE(2025,2,28),Certificados!$C$12:$C$80,"Pto. 1") -> 6471574.8 | G9: =SUMIFS(Certificados!$F$12:$F$80,Certificados!$A$12:$A$80,">="&DATE(2025,3,1),Certificados!$A$12:$A$80,"<="&DATE(2025,3,31),Certificados!$C$12:$C$80,"Pto. 1") -> 633184.08 | H9: =SUMIFS(Certificados!$F$12:$F$80,Certificados!$A$12:$A$80,">="&DATE(2025,4,1),Certificados!$A$12:$A$80,"<="&DATE(2025,4,30),Certificados!$C$12:$C$80,"Pto. 1") -> 685170.23 | I9: =SUMIFS(Certificados!$F$12:$F$80,Certificados!$A$12:$A$80,">="&DATE(2025,5,1),Certificados!$A$12:$A$80,"<="&DATE(2025,5,31),Certificados!$C$12:$C$80,"Pto. 1") -> 2272398.8 | J9: =SUMIFS(Certificados!$F$12:$F$80,Certificados!$A$12:$A$80,">="&DATE(2025,6,1),Certificados!$A$12:$A$80,"<="&DATE(2025,6,30),Certificados!$C$12:$C$80,"Pto. 1") -> 1641134.4 | K9: =SUMIFS(Certificados!$F$12:$F$80,Certificados!$A$12:$A$80,">="&DATE(2025,7,1),Certificados!$A$12:$A$80,"<="&DATE(2025,7,31),Certificados!$C$12:$C$80,"Pto. 1") -> 4724710 | L9: =SUMIFS(Certificados!$F$12:$F$80,Certificados!$A$12:$A$80,">="&DATE(2025,8,1),Certificados!$A$12:$A$80,"<="&DATE(2025,8,31),Certificados!$C$12:$C$80,"Pto. 1") -> 3460436.2 | M9: =SUMIFS(Certificados!$F$12:$F$80,Certificados!$A$12:$A$80,">="&DATE(2025,9,1),Certificados!$A$12:$A$80,"<="&DATE(2025,9,30),Certificados!$C$12:$C$80,"Pto. 1") -> 2417220.4 | N9: =SUMIFS(Certificados!$F$12:$F$80,Certificados!$A$12:$A$80,">="&DATE(2025,10,1),Certificados!$A$12:$A$80,"<="&DATE(2025,10,30),Certificados!$C$12:$C$80,"Pto. 1") -> 2380122 | O9: =SUMIFS(Certificados!$F$12:$F$80,Certificados!$A$12:$A$80,">="&DATE(2025,11,1),Certificados!$A$12:$A$80,"<="&DATE(2025,11,30),Certificados!$C$12:$C$80,"Pto. 1") -> 4748892.9 | P9: =SUMIFS(Certificados!$F$12:$F$80,Certificados!$A$12:$A$80,">="&DATE(2025,12,1),Certificados!$A$12:$A$80,"<="&DATE(2025,12,31),Certificados!$C$12:$C$80,"Pto. 1") -> 0 | Q9: =SUMIFS(Certificados!$F$12:$F$80,Certificados!$A$12:$A$80,">="&DATE(2026,1,1),Certificados!$A$12:$A$80,"<="&DATE(2026,1,31),Certificados!$C$12:$C$80,"Pto. 1") -> 0 | R9: =SUMIFS(Certificados!$F$12:$F$80,Certificados!$A$12:$A$80,">="&DATE(2026,2,1),Certificados!$A$12:$A$80,"<="&DATE(2026,2,28),Certificados!$C$12:$C$80,"Pto. 1") -> 0 | S9: =SUMIFS(Certificados!$F$12:$F$80,Certificados!$A$12:$A$80,">="&DATE(2026,3,1),Certificados!$A$12:$A$80,"<="&DATE(2026,3,31),Certificados!$C$12:$C$80,"Pto. 1") -> 0 | T9: =SUMIFS(Certificados!$F$12:$F$80,Certificados!$A$12:$A$80,">="&DATE(2026,4,1),Certificados!$A$12:$A$80,"<="&DATE(2026,4,30),Certificados!$C$12:$C$80,"Pto. 1") -> 0 | V9: =SUM(D9:U9) -> 29434844 | X9: 0 | Y9: 0 | Z9: =IF(Y9=100%,0,IF(X9=0,X9,X9-V9)) -> 0 | AA9: =IF(OR(Z9<0,X9),Z9/X9,0%) -> 0 | AB9: =IF(Y9=100%,IF(OR(V9<>0,X9),X9-V9),0) -> 0
B10: Total Ingresos por CAC | D10: =SUM(D9) -> 0 | E10: =SUM(E9) -> 0 | F10: =SUM(F9) -> 6471574.8 | G10: =SUM(G9) -> 633184.08 | H10: =SUM(H9) -> 685170.23 | I10: =SUM(I9) -> 2272398.8 | J10: =SUM(J9) -> 1641134.4 | K10: =SUM(K9) -> 4724710 | ... T10: =SUM(T9) -> 0 | V10: =SUM(V9) -> 29434844 | X10: =SUM(X9) -> 0 | Z10: =SUM(Z9) -> 0 | AA10: =IF(OR(Z10<0,X10),Z10/X10,0%) -> 0 | AB10: =SUM(AB9) -> 0
B12: Costos de Obra
B13: Preliminares | D13: =IFERROR(VLOOKUP($B13&$C13,'C. Gestión Pto #1'!$B$4:C$11,MATCH(D$5,'C. Gestión Pto #1'!$B$4:C$4,0),FALSE),0) -> 0 | E13: =IFERROR(VLOOKUP($B13&$C13,'C. Gestión Pto #1'!$B$4:D$11,MATCH(E$5,'C. Gestión Pto #1'!$B$4:D$4,0),FALSE),0) -> 0 | F13: =IFERROR(VLOOKUP($B13&$C13,'C. Gestión Pto #1'!$B$4:E$11,MATCH(F$5,'C. Gestión Pto #1'!$B$4:E$4,0),FALSE),0) -> 6949796.9 | G13: =IFERROR(VLOOKUP($B13&$C13,'C. Gestión Pto #1'!$B$4:F$11,MATCH(G$5,'C. Gestión Pto #1'!$B$4:F$4,0),FALSE),0) -> 4182183.8 | H13: =IFERROR(VLOOKUP($B13&$C13,'C. Gestión Pto #1'!$B$4:G$11,MATCH(H$5,'C. Gestión Pto #1'!$B$4:G$4,0),FALSE),0) -> 163926.85 | I13: =IFERROR(VLOOKUP($B13&$C13,'C. Gestión Pto #1'!$B$4:H$11,MATCH(I$5,'C. Gestión Pto #1'!$B$4:H$4,0),FALSE),0) -> 459869.25 | J13: =IFERROR(VLOOKUP($B13&$C13,'C. Gestión Pto #1'!$B$4:I$11,MATCH(J$5,'C. Gestión Pto #1'!$B$4:I$4,0),FALSE),0) -> 92816.22 | K13: =IFERROR(VLOOKUP($B13&$C13,'C. Gestión Pto #1'!$B$4:J$11,MATCH(K$5,'C. Gestión Pto #1'!$B$4:J$4,0),FALSE),0) -> 14628.44 | ... T13: =IFERROR(VLOOKUP($B13&$C13,'C. Gestión Pto #1'!$B$4:S$11,MATCH(T$5,'C. Gestión Pto #1'!$B$4:S$4,0),FALSE),0) -> 0 | V13: {=SUMPRODUCT($D13:$U13,TRANSPOSE('Indice CAC'!$D$2:$D$19))} -> 12879112 | X13: =IF($C13="MAT",SUMIF('P. Costo'!$A$8:$A$58,$B13,'P. Costo'!$I$8:$I$58),IF($C13="MO",SUMIF('P. Costo'!$A$8:$A$58,$B13,'P. Costo'!$L$8:$L$58),SUMIF('P. Costo'!$A$8:$A$58,$B13,'P. Costo'!$N$8:$N$58))) -> 12544454 | Y13: =IF($C13="MAT",SUMIF('Cert. Pto. 01'!$A$9:$A$45,'Resumen Pto #1'!$B13,'Cert. Pto. 01'!$T$9:$T$45),IF('Resumen Pto #1'!$C13="MO",SUMIF('Cert. Pto. 01'!$A$9:$A$45,'Resumen Pto #1'!$B13,'Cert. Pto. 01'!$U$9:$U$45),SUMIF('Cert. Pto. 01'!$A$9:$A$45,'Resumen Pto #1'!$B13,'Cert. Pto. 01'!$V$9:$V$45)))/IF($C13="MAT",SUMIF('Cert. Pto. 01'!$A$9:$A$45,'Resumen Pto #1'!$B13,'Cert. Pto. 01'!$I$9:$I$45),IF('Resumen Pto #1'!$C13="MO",SUMIF('Cert. Pto. 01'!$A$9:$A$45,'Resumen Pto #1'!$B13,'Cert. Pto. 01'!$J$9:$J$45),SUMIF('Cert. Pto. 01'!$A$9:$A$45,'Resumen Pto #1'!$B13,'Cert. Pto. 01'!$K$9:$K$45))) -> 1 | Z13: =IF(Y13=100%,0,IF(OR(V13<>0,X13),X13-V13)) -> 0 | AA13: =IF(OR(Z13<0,X13),Z13/X13,0%) -> 0 | AB13: =IF(Y13=100%,IF(OR(V13<>0,X13),X13-V13),0) -> -334657.85
B14: Agrimensura | D14: =IFERROR(VLOOKUP($B14&$C14,'C. Gestión Pto #1'!$B$4:C$11,MATCH(D$5,'C. Gestión Pto #1'!$B$4:C$4,0),FALSE),0) -> 110000 | E14: =IFERROR(VLOOKUP($B14&$C14,'C. Gestión Pto #1'!$B$4:D$11,MATCH(E$5,'C. Gestión Pto #1'!$B$4:D$4,0),FALSE),0) -> 0 | F14: =IFERROR(VLOOKUP($B14&$C14,'C. Gestión Pto #1'!$B$4:E$11,MATCH(F$5,'C. Gestión Pto #1'!$B$4:E$4,0),FALSE),0) -> 0 | G14: =IFERROR(VLOOKUP($B14&$C14,'C. Gestión Pto #1'!$B$4:F$11,MATCH(G$5,'C. Gestión Pto #1'!$B$4:F$4,0),FALSE),0) -> 0 | H14: =IFERROR(VLOOKUP($B14&$C14,'C. Gestión Pto #1'!$B$4:G$11,MATCH(H$5,'C. Gestión Pto #1'!$B$4:G$4,0),FALSE),0) -> 0 | I14: =IFERROR(VLOOKUP($B14&$C14,'C. Gestión Pto #1'!$B$4:H$11,MATCH(I$5,'C. Gestión Pto #1'!$B$4:H$4,0),FALSE),0) -> 0 | J14: =IFERROR(VLOOKUP($B14&$C14,'C. Gestión Pto #1'!$B$4:I$11,MATCH(J$5,'C. Gestión Pto #1'!$B$4:I$4,0),FALSE),0) -> 0 | K14: =IFERROR(VLOOKUP($B14&$C14,'C. Gestión Pto #1'!$B$4:J$11,MATCH(K$5,'C. Gestión Pto #1'!$B$4:J$4,0),FALSE),0) -> 0 | ... T14: =IFERROR(VLOOKUP($B14&$C14,'C. Gestión Pto #1'!$B$4:S$11,MATCH(T$5,'C. Gestión Pto #1'!$B$4:S$4,0),FALSE),0) -> 0 | V14: {=SUMPRODUCT($D14:$U14,TRANSPOSE('Indice CAC'!$D$2:$D$19))} -> 110000 | X14: =IF($C14="MAT",SUMIF('P. Costo'!$A$8:$A$58,$B14,'P. Costo'!$I$8:$I$58),IF($C14="MO",SUMIF('P. Costo'!$A$8:$A$58,$B14,'P. Costo'!$L$8:$L$58),SUMIF('P. Costo'!$A$8:$A$58,$B14,'P. Costo'!$N$8:$N$58))) -> 853792.28 | Y14: =IF($C14="MAT",SUMIF('Cert. Pto. 01'!$A$9:$A$45,'Resumen Pto #1'!$B14,'Cert. Pto. 01'!$T$9:$T$45),IF('Resumen Pto #1'!$C14="MO",SUMIF('Cert. Pto. 01'!$A$9:$A$45,'Resumen Pto #1'!$B14,'Cert. Pto. 01'!$U$9:$U$45),SUMIF('Cert. Pto. 01'!$A$9:$A$45,'Resumen Pto #1'!$B14,'Cert. Pto. 01'!$V$9:$V$45)))/IF($C14="MAT",SUMIF('Cert. Pto. 01'!$A$9:$A$45,'Resumen Pto #1'!$B14,'Cert. Pto. 01'!$I$9:$I$45),IF('Resumen Pto #1'!$C14="MO",SUMIF('Cert. Pto. 01'!$A$9:$A$45,'Resumen Pto #1'!$B14,'Cert. Pto. 01'!$J$9:$J$45),SUMIF('Cert. Pto. 01'!$A$9:$A$45,'Resumen Pto #1'!$B14,'Cert. Pto. 01'!$K$9:$K$45))) -> 1 | Z14: =IF(Y14=100%,0,IF(OR(V14<>0,X14),X14-V14)) -> 0 | AA14: =IF(OR(Z14<0,X14),Z14/X14,0%) -> 0 | AB14: =IF(Y14=100%,IF(OR(V14<>0,X14),X14-V14),0) -> 743792.28
B15: Excavación y Mov. de Suelos | D15: =IFERROR(VLOOKUP($B15&$C15,'C. Gestión Pto #1'!$B$4:C$11,MATCH(D$5,'C. Gestión Pto #1'!$B$4:C$4,0),FALSE),0) -> 0 | E15: =IFERROR(VLOOKUP($B15&$C15,'C. Gestión Pto #1'!$B$4:D$11,MATCH(E$5,'C. Gestión Pto #1'!$B$4:D$4,0),FALSE),0) -> 0 | F15: =IFERROR(VLOOKUP($B15&$C15,'C. Gestión Pto #1'!$B$4:E$11,MATCH(F$5,'C. Gestión Pto #1'!$B$4:E$4,0),FALSE),0) -> 0 | G15: =IFERROR(VLOOKUP($B15&$C15,'C. Gestión Pto #1'!$B$4:F$11,MATCH(G$5,'C. Gestión Pto #1'!$B$4:F$4,0),FALSE),0) -> 1580000 | H15: =IFERROR(VLOOKUP($B15&$C15,'C. Gestión Pto #1'!$B$4:G$11,MATCH(H$5,'C. Gestión Pto #1'!$B$4:G$4,0),FALSE),0) -> 1580000 | I15: =IFERROR(VLOOKUP($B15&$C15,'C. Gestión Pto #1'!$B$4:H$11,MATCH(I$5,'C. Gestión Pto #1'!$B$4:H$4,0),FALSE),0) -> 2974000 | J15: =IFERROR(VLOOKUP($B15&$C15,'C. Gestión Pto #1'!$B$4:I$11,MATCH(J$5,'C. Gestión Pto #1'!$B$4:I$4,0),FALSE),0) -> 3640000 | K15: =IFERROR(VLOOKUP($B15&$C15,'C. Gestión Pto #1'!$B$4:J$11,MATCH(K$5,'C. Gestión Pto #1'!$B$4:J$4,0),FALSE),0) -> 1416000 | ... T15: =IFERROR(VLOOKUP($B15&$C15,'C. Gestión Pto #1'!$B$4:S$11,MATCH(T$5,'C. Gestión Pto #1'!$B$4:S$4,0),FALSE),0) -> 0 | V15: {=SUMPRODUCT($D15:$U15,TRANSPOSE('Indice CAC'!$D$2:$D$19))} -> 10416172 | X15: =IF($C15="MAT",SUMIF('P. Costo'!$A$8:$A$58,$B15,'P. Costo'!$I$8:$I$58),IF($C15="MO",SUMIF('P. Costo'!$A$8:$A$58,$B15,'P. Costo'!$L$8:$L$58),SUMIF('P. Costo'!$A$8:$A$58,$B15,'P. Costo'!$N$8:$N$58))) -> 22068905 | Y15: =IF($C15="MAT",SUMIF('Cert. Pto. 01'!$A$9:$A$45,'Resumen Pto #1'!$B15,'Cert. Pto. 01'!$T$9:$T$45),IF('Resumen Pto #1'!$C15="MO",SUMIF('Cert. Pto. 01'!$A$9:$A$45,'Resumen Pto #1'!$B15,'Cert. Pto. 01'!$U$9:$U$45),SUMIF('Cert. Pto. 01'!$A$9:$A$45,'Resumen Pto #1'!$B15,'Cert. Pto. 01'!$V$9:$V$45)))/IF($C15="MAT",SUMIF('Cert. Pto. 01'!$A$9:$A$45,'Resumen Pto #1'!$B15,'Cert. Pto. 01'!$I$9:$I$45),IF('Resumen Pto #1'!$C15="MO",SUMIF('Cert. Pto. 01'!$A$9:$A$45,'Resumen Pto #1'!$B15,'Cert. Pto. 01'!$J$9:$J$45),SUMIF('Cert. Pto. 01'!$A$9:$A$45,'Resumen Pto #1'!$B15,'Cert. Pto. 01'!$K$9:$K$45))) -> 1 | Z15: =IF(Y15=100%,0,IF(OR(V15<>0,X15),X15-V15)) -> 0 | AA15: =IF(OR(Z15<0,X15),Z15/X15,0%) -> 0 | AB15: =IF(Y15=100%,IF(OR(V15<>0,X15),X15-V15),0) -> 11652732
B16: Hormigón | C16: MAT | D16: =IFERROR(VLOOKUP($B16&$C16,'C. Gestión Pto #1'!$B$4:C$11,MATCH(D$5,'C. Gestión Pto #1'!$B$4:C$4,0),FALSE),0) -> 0 | E16: =IFERROR(VLOOKUP($B16&$C16,'C. Gestión Pto #1'!$B$4:D$11,MATCH(E$5,'C. Gestión Pto #1'!$B$4:D$4,0),FALSE),0) -> 0 | F16: =IFERROR(VLOOKUP($B16&$C16,'C. Gestión Pto #1'!$B$4:E$11,MATCH(F$5,'C. Gestión Pto #1'!$B$4:E$4,0),FALSE),0) -> 1227898.4 | G16: =IFERROR(VLOOKUP($B16&$C16,'C. Gestión Pto #1'!$B$4:F$11,MATCH(G$5,'C. Gestión Pto #1'!$B$4:F$4,0),FALSE),0) -> 21854353 | H16: =IFERROR(VLOOKUP($B16&$C16,'C. Gestión Pto #1'!$B$4:G$11,MATCH(H$5,'C. Gestión Pto #1'!$B$4:G$4,0),FALSE),0) -> 64397545 | I16: =IFERROR(VLOOKUP($B16&$C16,'C. Gestión Pto #1'!$B$4:H$11,MATCH(I$5,'C. Gestión Pto #1'!$B$4:H$4,0),FALSE),0) -> 43287475 | J16: =IFERROR(VLOOKUP($B16&$C16,'C. Gestión Pto #1'!$B$4:I$11,MATCH(J$5,'C. Gestión Pto #1'!$B$4:I$4,0),FALSE),0) -> 1606135.8 | K16: =IFERROR(VLOOKUP($B16&$C16,'C. Gestión Pto #1'!$B$4:J$11,MATCH(K$5,'C. Gestión Pto #1'!$B$4:J$4,0),FALSE),0) -> 33701586 | ... T16: =IFERROR(VLOOKUP($B16&$C16,'C. Gestión Pto #1'!$B$4:S$11,MATCH(T$5,'C. Gestión Pto #1'!$B$4:S$4,0),FALSE),0) -> 0 | V16: {=SUMPRODUCT($D16:$U16,TRANSPOSE('Indice CAC'!$D$2:$D$19))} -> 1.8021717e+08 | X16: =IF($C16="MAT",SUMIF('P. Costo'!$A$8:$A$58,$B16,'P. Costo'!$I$8:$I$58),IF($C16="MO",SUMIF('P. Costo'!$A$8:$A$58,$B16,'P. Costo'!$L$8:$L$58),SUMIF('P. Costo'!$A$8:$A$58,$B16,'P. Costo'!$N$8:$N$58))) -> 1.8107277e+08 | Y16: =IF($C16="MAT",SUMIF('Cert. Pto. 01'!$A$9:$A$45,'Resumen Pto #1'!$B16,'Cert. Pto. 01'!$T$9:$T$45),IF('Resumen Pto #1'!$C16="MO",SUMIF('Cert. Pto. 01'!$A$9:$A$45,'Resumen Pto #1'!$B16,'Cert. Pto. 01'!$U$9:$U$45),SUMIF('Cert. Pto. 01'!$A$9:$A$45,'Resumen Pto #1'!$B16,'Cert. Pto. 01'!$V$9:$V$45)))/IF($C16="MAT",SUMIF('Cert. Pto. 01'!$A$9:$A$45,'Resumen Pto #1'!$B16,'Cert. Pto. 01'!$I$9:$I$45),IF('Resumen Pto #1'!$C16="MO",SUMIF('Cert. Pto. 01'!$A$9:$A$45,'Resumen Pto #1'!$B16,'Cert. Pto. 01'!$J$9:$J$45),SUMIF('Cert. Pto. 01'!$A$9:$A$45,'Resumen Pto #1'!$B16,'Cert. Pto. 01'!$K$9:$K$45))) -> 1 | Z16: =IF(Y16=100%,0,IF(OR(V16<>0,X16),X16-V16)) -> 0 | AA16: =IF(OR(Z16<0,X16),Z16/X16,0%) -> 0 | AB16: =IF(Y16=100%,IF(OR(V16<>0,X16),X16-V16),0) -> 855599.54
B17: Hormigón | C17: MO | D17: =IFERROR(VLOOKUP($B17&$C17,'C. Gestión Pto #1'!$B$4:C$11,MATCH(D$5,'C. Gestión Pto #1'!$B$4:C$4,0),FALSE),0) -> 0 | E17: =IFERROR(VLOOKUP($B17&$C17,'C. Gestión Pto #1'!$B$4:D$11,MATCH(E$5,'C. Gestión Pto #1'!$B$4:D$4,0),FALSE),0) -> 0 | F17: =IFERROR(VLOOKUP($B17&$C17,'C. Gestión Pto #1'!$B$4:E$11,MATCH(F$5,'C. Gestión Pto #1'!$B$4:E$4,0),FALSE),0) -> 2411850 | G17: =IFERROR(VLOOKUP($B17&$C17,'C. Gestión Pto #1'!$B$4:F$11,MATCH(G$5,'C. Gestión Pto #1'!$B$4:F$4,0),FALSE),0) -> 9206862.2 | H17: =IFERROR(VLOOKUP($B17&$C17,'C. Gestión Pto #1'!$B$4:G$11,MATCH(H$5,'C. Gestión Pto #1'!$B$4:G$4,0),FALSE),0) -> 10965040 | I17: =IFERROR(VLOOKUP($B17&$C17,'C. Gestión Pto #1'!$B$4:H$11,MATCH(I$5,'C. Gestión Pto #1'!$B$4:H$4,0),FALSE),0) -> 9710066.5 | J17: =IFERROR(VLOOKUP($B17&$C17,'C. Gestión Pto #1'!$B$4:I$11,MATCH(J$5,'C. Gestión Pto #1'!$B$4:I$4,0),FALSE),0) -> 8357133.4 | K17: =IFERROR(VLOOKUP($B17&$C17,'C. Gestión Pto #1'!$B$4:J$11,MATCH(K$5,'C. Gestión Pto #1'!$B$4:J$4,0),FALSE),0) -> 20959356 | ... T17: =IFERROR(VLOOKUP($B17&$C17,'C. Gestión Pto #1'!$B$4:S$11,MATCH(T$5,'C. Gestión Pto #1'!$B$4:S$4,0),FALSE),0) -> 0 | V17: {=SUMPRODUCT($D17:$U17,TRANSPOSE('Indice CAC'!$D$2:$D$19))} -> 1.0530015e+08 | X17: =IF($C17="MAT",SUMIF('P. Costo'!$A$8:$A$58,$B17,'P. Costo'!$I$8:$I$58),IF($C17="MO",SUMIF('P. Costo'!$A$8:$A$58,$B17,'P. Costo'!$L$8:$L$58),SUMIF('P. Costo'!$A$8:$A$58,$B17,'P. Costo'!$N$8:$N$58))) -> 1.4437802e+08 | Y17: =IF($C17="MAT",SUMIF('Cert. Pto. 01'!$A$9:$A$45,'Resumen Pto #1'!$B17,'Cert. Pto. 01'!$T$9:$T$45),IF('Resumen Pto #1'!$C17="MO",SUMIF('Cert. Pto. 01'!$A$9:$A$45,'Resumen Pto #1'!$B17,'Cert. Pto. 01'!$U$9:$U$45),SUMIF('Cert. Pto. 01'!$A$9:$A$45,'Resumen Pto #1'!$B17,'Cert. Pto. 01'!$V$9:$V$45)))/IF($C17="MAT",SUMIF('Cert. Pto. 01'!$A$9:$A$45,'Resumen Pto #1'!$B17,'Cert. Pto. 01'!$I$9:$I$45),IF('Resumen Pto #1'!$C17="MO",SUMIF('Cert. Pto. 01'!$A$9:$A$45,'Resumen Pto #1'!$B17,'Cert. Pto. 01'!$J$9:$J$45),SUMIF('Cert. Pto. 01'!$A$9:$A$45,'Resumen Pto #1'!$B17,'Cert. Pto. 01'!$K$9:$K$45))) -> 1 | Z17: =IF(Y17=100%,0,IF(OR(V17<>0,X17),X17-V17)) -> 0 | AA17: =IF(OR(Z17<0,X17),Z17/X17,0%) -> 0 | AB17: =IF(Y17=100%,IF(OR(V17<>0,X17),X17-V17),0) -> 39077870
B18: Equipos | D18: =IFERROR(VLOOKUP($B18&$C18,'C. Gestión Pto #1'!$B$4:C$11,MATCH(D$5,'C. Gestión Pto #1'!$B$4:C$4,0),FALSE),0) -> 58271.121 | E18: =IFERROR(VLOOKUP($B18&$C18,'C. Gestión Pto #1'!$B$4:D$11,MATCH(E$5,'C. Gestión Pto #1'!$B$4:D$4,0),FALSE),0) -> 59559.523 | F18: =IFERROR(VLOOKUP($B18&$C18,'C. Gestión Pto #1'!$B$4:E$11,MATCH(F$5,'C. Gestión Pto #1'!$B$4:E$4,0),FALSE),0) -> 64331.918 | G18: =IFERROR(VLOOKUP($B18&$C18,'C. Gestión Pto #1'!$B$4:F$11,MATCH(G$5,'C. Gestión Pto #1'!$B$4:F$4,0),FALSE),0) -> 287221.2 | H18: =IFERROR(VLOOKUP($B18&$C18,'C. Gestión Pto #1'!$B$4:G$11,MATCH(H$5,'C. Gestión Pto #1'!$B$4:G$4,0),FALSE),0) -> 290739.63 | I18: =IFERROR(VLOOKUP($B18&$C18,'C. Gestión Pto #1'!$B$4:H$11,MATCH(I$5,'C. Gestión Pto #1'!$B$4:H$4,0),FALSE),0) -> 296307.18 | J18: =IFERROR(VLOOKUP($B18&$C18,'C. Gestión Pto #1'!$B$4:I$11,MATCH(J$5,'C. Gestión Pto #1'!$B$4:I$4,0),FALSE),0) -> 346009.64 | K18: =IFERROR(VLOOKUP($B18&$C18,'C. Gestión Pto #1'!$B$4:J$11,MATCH(K$5,'C. Gestión Pto #1'!$B$4:J$4,0),FALSE),0) -> 799574.25 | ... T18: =IFERROR(VLOOKUP($B18&$C18,'C. Gestión Pto #1'!$B$4:S$11,MATCH(T$5,'C. Gestión Pto #1'!$B$4:S$4,0),FALSE),0) -> 0 | V18: {=SUMPRODUCT($D18:$U18,TRANSPOSE('Indice CAC'!$D$2:$D$19))} -> 3783726.2 | X18: =IF($C18="MAT",SUMIF('P. Costo'!$A$8:$A$58,$B18,'P. Costo'!$I$8:$I$58),IF($C18="MO",SUMIF('P. Costo'!$A$8:$A$58,$B18,'P. Costo'!$L$8:$L$58),SUM('P. Costo'!M59,-SUM('P. Costo'!M19:M27)))) -> 13604196 | Y18: ='Cert. Pto. 01'!S48 -> 1 | Z18: =IF(Y18=100%,0,IF(OR(V18<>0,X18),X18-V18)) -> 0 | AA18: =IF(OR(Z18<0,X18),Z18/X18,0%) -> 0 | AB18: =IF(Y18=100%,IF(OR(V18<>0,X18),X18-V18),0) -> 9820470.1
B19: Gastos Generales Obra | D19: =IFERROR(VLOOKUP($B19&$C19,'C. Gestión Pto #1'!$B$4:C$11,MATCH(D$5,'C. Gestión Pto #1'!$B$4:C$4,0),FALSE),0) -> 12905.63 | E19: =IFERROR(VLOOKUP($B19&$C19,'C. Gestión Pto #1'!$B$4:D$11,MATCH(E$5,'C. Gestión Pto #1'!$B$4:D$4,0),FALSE),0) -> 0 | F19: =IFERROR(VLOOKUP($B19&$C19,'C. Gestión Pto #1'!$B$4:E$11,MATCH(F$5,'C. Gestión Pto #1'!$B$4:E$4,0),FALSE),0) -> 90000 | G19: =IFERROR(VLOOKUP($B19&$C19,'C. Gestión Pto #1'!$B$4:F$11,MATCH(G$5,'C. Gestión Pto #1'!$B$4:F$4,0),FALSE),0) -> 180000 | H19: =IFERROR(VLOOKUP($B19&$C19,'C. Gestión Pto #1'!$B$4:G$11,MATCH(H$5,'C. Gestión Pto #1'!$B$4:G$4,0),FALSE),0) -> 80000 | I19: =IFERROR(VLOOKUP($B19&$C19,'C. Gestión Pto #1'!$B$4:H$11,MATCH(I$5,'C. Gestión Pto #1'!$B$4:H$4,0),FALSE),0) -> 80000 | J19: =IFERROR(VLOOKUP($B19&$C19,'C. Gestión Pto #1'!$B$4:I$11,MATCH(J$5,'C. Gestión Pto #1'!$B$4:I$4,0),FALSE),0) -> 380000 | K19: =IFERROR(VLOOKUP($B19&$C19,'C. Gestión Pto #1'!$B$4:J$11,MATCH(K$5,'C. Gestión Pto #1'!$B$4:J$4,0),FALSE),0) -> 160000 | ... T19: =IFERROR(VLOOKUP($B19&$C19,'C. Gestión Pto #1'!$B$4:S$11,MATCH(T$5,'C. Gestión Pto #1'!$B$4:S$4,0),FALSE),0) -> 0 | V19: {=SUMPRODUCT($D19:$U19,TRANSPOSE('Indice CAC'!$D$2:$D$19))} -> 3563879 | X19: =IF($C19="MAT",SUMIF('P. Costo'!$A$8:$A$58,$B19,'P. Costo'!$I$8:$I$58),IF($C19="MO",SUMIF('P. Costo'!$A$8:$A$58,$B19,'P. Costo'!$L$8:$L$58),SUMIF('P. Costo'!$A$8:$A$58,$B19,'P. Costo'!$N$8:$N$58))) -> 5763772 | Y19: =IF($C19="MAT",SUMIF('Cert. Pto. 01'!$A$9:$A$45,'Resumen Pto #1'!$B19,'Cert. Pto. 01'!$T$9:$T$45),IF($C19="MO",SUMIF('Cert. Pto. 01'!$A$9:$A$45,'Resumen Pto #1'!$B19,'Cert. Pto. 01'!$U$9:$U$45),SUMIF('Cert. Pto. 01'!$A$9:$A$45,'Resumen Pto #1'!$B19,'Cert. Pto. 01'!$V$9:$V$45)))/IF($C19="MAT",SUMIF('Cert. Pto. 01'!$A$9:$A$45,'Resumen Pto #1'!$B19,'Cert. Pto. 01'!$I$9:$I$45),IF($C19="MO",SUMIF('Cert. Pto. 01'!$A$9:$A$45,'Resumen Pto #1'!$B19,'Cert. Pto. 01'!$J$9:$J$45),SUMIF('Cert. Pto. 01'!$A$9:$A$45,'Resumen Pto #1'!$B19,'Cert. Pto. 01'!$K$9:$K$45))) -> 1 | Z19: =IF(Y19=100%,0,IF(OR(V19<>0,X19),X19-V19)) -> 0 | AA19: =IF(OR(Z19<0,X19),Z19/X19,0%) -> 0 | AB19: =IF(Y19=100%,IF(OR(V19<>0,X19),X19-V19),0) -> 2199893
B20: Total Egresos de Obra | D20: =SUM(D13:D19) -> 181176.75 | E20: =SUM(E13:E19) -> 59559.523 | F20: =SUM(F13:F19) -> 10743877 | G20: =SUM(G13:G19) -> 37290620 | H20: =SUM(H13:H19) -> 77477251 | I20: =SUM(I13:I19) -> 56807718 | J20: =SUM(J13:J19) -> 14422095 | K20: =SUM(K13:K19) -> 57051145 | ... T20: =SUM(T13:T19) -> 0 | V20: =SUM(V13:V19) -> 3.1627021e+08 | X20: =SUM(X13:X19) -> 3.8028591e+08 | Z20: =IF(Y20=100%,0,IF(OR(V20<>0,X20),X20-V20)) -> 64015699 | AA20: =IF(OR(Z20<0,X20),Z20/X20,0%) -> 0.16833571 | AB20: =SUM(AB13:AB19) -> 64015699
B22: Gastos Generales
B23: Gastos Directos | D23: =VLOOKUP($B23,'C. Gestión Pto #1'!$B$28:N$28,MATCH('Resumen Pto #1'!D$5,'C. Gestión Pto #1'!$B$14:N$14,0),0) -> 3175204.8 | E23: =VLOOKUP($B23,'C. Gestión Pto #1'!$B$28:O$28,MATCH('Resumen Pto #1'!E$5,'C. Gestión Pto #1'!$B$14:O$14,0),0) -> 2020935.7 | F23: =VLOOKUP($B23,'C. Gestión Pto #1'!$B$28:P$28,MATCH('Resumen Pto #1'!F$5,'C. Gestión Pto #1'!$B$14:P$14,0),0) -> 2883500.7 | G23: =VLOOKUP($B23,'C. Gestión Pto #1'!$B$28:P$28,MATCH('Resumen Pto #1'!G$5,'C. Gestión Pto #1'!$B$14:P$14,0),0) -> 2286455.7 | H23: =VLOOKUP($B23,'C. Gestión Pto #1'!$B$28:Q$28,MATCH('Resumen Pto #1'!H$5,'C. Gestión Pto #1'!$B$14:Q$14,0),0) -> 6273647.6 | I23: =VLOOKUP($B23,'C. Gestión Pto #1'!$B$28:R$28,MATCH('Resumen Pto #1'!I$5,'C. Gestión Pto #1'!$B$14:R$14,0),0) -> 1963509.9 | J23: =VLOOKUP($B23,'C. Gestión Pto #1'!$B$28:S$28,MATCH('Resumen Pto #1'!J$5,'C. Gestión Pto #1'!$B$14:S$14,0),0) -> 2816808 | K23: =VLOOKUP($B23,'C. Gestión Pto #1'!$B$28:T$28,MATCH('Resumen Pto #1'!K$5,'C. Gestión Pto #1'!$B$14:T$14,0),0) -> 2808099.8 | L23: =VLOOKUP($B23,'C. Gestión Pto #1'!$B$28:U$28,MATCH('Resumen Pto #1'!L$5,'C. Gestión Pto #1'!$B$14:U$14,0),0) -> 3875715.8 | M23: =VLOOKUP($B23,'C. Gestión Pto #1'!$B$28:V$28,MATCH('Resumen Pto #1'!M$5,'C. Gestión Pto #1'!$B$14:V$14,0),0) -> 5086371.5 | N23: =VLOOKUP($B23,'C. Gestión Pto #1'!$B$28:W$28,MATCH('Resumen Pto #1'!N$5,'C. Gestión Pto #1'!$B$14:W$14,0),0) -> 4395052.3 | ... Q23: =VLOOKUP($B23,'C. Gestión Pto #1'!$B$28:Z$28,MATCH('Resumen Pto #1'!Q$5,'C. Gestión Pto #1'!$B$14:Z$14,0),0) -> 0 | R23: =IFERROR(VLOOKUP($B23,'C. Gestión Pto #1'!$B$28:AA$28,MATCH('Resumen Pto #1'!R$5,'C. Gestión Pto #1'!$B$14:AA$14,0),0),0) -> 0 | S23: =IFERROR(VLOOKUP($B23,'C. Gestión Pto #1'!$B$28:AB$28,MATCH('Resumen Pto #1'!S$5,'C. Gestión Pto #1'!$B$14:AB$14,0),0),0) -> 0 | T23: =IFERROR(VLOOKUP($B23,'C. Gestión Pto #1'!$B$28:AC$28,MATCH('Resumen Pto #1'!T$5,'C. Gestión Pto #1'!$B$14:AC$14,0),0),0) -> 0 | V23: {=SUMPRODUCT($D23:$U23,TRANSPOSE('Indice CAC'!$D$2:$D$19))} -> 34625158 | X23: =SUM(GGBB!H6:H32)/17*11 -> 60150532 | Y23: ='Cert. Pto. 01'!S48 -> 1 | Z23: =IF(Y23=100%,0,IF(OR(V23<>0,X23),X23-V23)) -> 0 | AA23: =IF(OR(Z23<0,X23),Z23/X23,0%) -> 0 | AB23: =IF(Y23=100%,IF(OR(V23<>0,X23),X23-V23),0) -> 25525374
B24: Gastos Indirectos | D24: =VLOOKUP($B24,'C. Gestión Pto #1'!$B$34:N$34,MATCH('Resumen Pto #1'!D$5,'C. Gestión Pto #1'!$B$30:N$30,0),0) -> 639132.78 | E24: =VLOOKUP($B24,'C. Gestión Pto #1'!$B$34:O$34,MATCH('Resumen Pto #1'!E$5,'C. Gestión Pto #1'!$B$30:O$30,0),0) -> 1825790.3 | F24: =VLOOKUP($B24,'C. Gestión Pto #1'!$B$34:P$34,MATCH('Resumen Pto #1'!F$5,'C. Gestión Pto #1'!$B$30:P$30,0),0) -> 1406464.9 | G24: =VLOOKUP($B24,'C. Gestión Pto #1'!$B$34:P$34,MATCH('Resumen Pto #1'!G$5,'C. Gestión Pto #1'!$B$30:P$30,0),0) -> 2714187.3 | H24: =VLOOKUP($B24,'C. Gestión Pto #1'!$B$34:Q$34,MATCH('Resumen Pto #1'!H$5,'C. Gestión Pto #1'!$B$30:Q$30,0),0) -> 2169029.3 | I24: =VLOOKUP($B24,'C. Gestión Pto #1'!$B$34:R$34,MATCH('Resumen Pto #1'!I$5,'C. Gestión Pto #1'!$B$30:R$30,0),0) -> 1800256.2 | J24: =VLOOKUP($B24,'C. Gestión Pto #1'!$B$34:S$34,MATCH('Resumen Pto #1'!J$5,'C. Gestión Pto #1'!$B$30:S$30,0),0) -> 2949259.1 | K24: =VLOOKUP($B24,'C. Gestión Pto #1'!$B$34:T$34,MATCH('Resumen Pto #1'!K$5,'C. Gestión Pto #1'!$B$30:T$30,0),0) -> 4175013.8 | L24: =VLOOKUP($B24,'C. Gestión Pto #1'!$B$34:U$34,MATCH('Resumen Pto #1'!L$5,'C. Gestión Pto #1'!$B$30:U$30,0),0) -> 2235375.3 | M24: =VLOOKUP($B24,'C. Gestión Pto #1'!$B$34:V$34,MATCH('Resumen Pto #1'!M$5,'C. Gestión Pto #1'!$B$30:V$30,0),0) -> 3075477.6 | N24: =VLOOKUP($B24,'C. Gestión Pto #1'!$B$34:W$34,MATCH('Resumen Pto #1'!N$5,'C. Gestión Pto #1'!$B$30:W$30,0),0) -> 3414307.4 | ... Q24: =VLOOKUP($B24,'C. Gestión Pto #1'!$B$34:Z$34,MATCH('Resumen Pto #1'!Q$5,'C. Gestión Pto #1'!$B$30:Z$30,0),0) -> 0 | R24: =IFERROR(VLOOKUP($B24,'C. Gestión Pto #1'!$B$28:AA$28,MATCH('Resumen Pto #1'!R$5,'C. Gestión Pto #1'!$B$14:AA$14,0),0),0) -> 0 | S24: =IFERROR(VLOOKUP($B24,'C. Gestión Pto #1'!$B$28:AB$28,MATCH('Resumen Pto #1'!S$5,'C. Gestión Pto #1'!$B$14:AB$14,0),0),0) -> 0 | T24: =IFERROR(VLOOKUP($B24,'C. Gestión Pto #1'!$B$28:AC$28,MATCH('Resumen Pto #1'!T$5,'C. Gestión Pto #1'!$B$14:AC$14,0),0),0) -> 0 | V24: {=SUMPRODUCT($D24:$U24,TRANSPOSE('Indice CAC'!$D$2:$D$19))} -> 24175440 | X24: =SUM(GGBB!H42:H48)/17*11 -> 53546314 | Y24: ='Cert. Pto. 01'!S48 -> 1 | Z24: =IF(Y24=100%,0,IF(OR(V24<>0,X24),X24-V24)) -> 0 | AA24: =IF(OR(Z24<0,X24),Z24/X24,0%) -> 0 | AB24: =IF(Y24=100%,IF(OR(V24<>0,X24),X24-V24),0) -> 29370874
B25: Total Gastos Generales | D25: =SUM(D23:D24) -> 3814337.6 | E25: =SUM(E23:E24) -> 3846726 | F25: =SUM(F23:F24) -> 4289965.6 | G25: =SUM(G23:G24) -> 5000643 | H25: =SUM(H23:H24) -> 8442676.9 | I25: =SUM(I23:I24) -> 3763766.1 | J25: =SUM(J23:J24) -> 5766067.1 | K25: =SUM(K23:K24) -> 6983113.6 | ... T25: =SUM(T23:T24) -> 0 | V25: =SUM(V23:V24) -> 58800598 | X25: =SUM(X23:X24) -> 1.1369685e+08 | Z25: =IF(Y25=100%,0,IF(OR(V25<>0,X25),X25-V25)) -> 54896248 | AA25: =IF(OR(Z25<0,X25),Z25/X25,0%) -> 0.48283 | AB25: =SUM(AB23:AB24) -> 54896248
B27: Total Egresos | D27: =D20+D25 -> 3995514.3 | E27: =E20+E25 -> 3906285.5 | F27: =F20+F25 -> 15033843 | G27: =G20+G25 -> 42291263 | H27: =H20+H25 -> 85919928 | I27: =I20+I25 -> 60571484 | J27: =J20+J25 -> 20188162 | K27: =K20+K25 -> 64034258 | ... T27: =T20+T25 -> 0 | V27: =V20+V25 -> 3.750708e+08 | X27: =X20+X25 -> 4.9398275e+08
B29: Resultado Operativo | D29: =SUM(D8,D10,-D27) -> -3995514.3 | E29: =SUM(E8,E10,-E27) -> -3906285.5 | F29: =SUM(F8,F10,-F27) -> 1.9180082e+08 | G29: =SUM(G8,G10,-G27) -> -22054393 | H29: =SUM(H8,H10,-H27) -> -68768799 | I29: =SUM(I8,I10,-I27) -> -19400563 | J29: =SUM(J8,J10,-J27) -> 3087375.8 | K29: =SUM(K8,K10,-K27) -> -2934608.3 | ... T29: =SUM(T8,T10,-T27) -> 0 | V29: =SUM(V8,-V27) -> 38016877 | X29: =SUM(X8,-X27) -> 6924967.5
B30: Resultado Acumulado | D30: =D29 -> -3995514.3 | E30: =E29+D30 -> -7901799.8 | F30: =F29+E30 -> 1.8389902e+08 | G30: =G29+F30 -> 1.6184463e+08 | H30: =H29+G30 -> 93075828 | I30: =I29+H30 -> 73675266 | J30: =J29+I30 -> 76762642 | K30: =K29+J30 -> 73828033 | L30: =L29+K30 -> 91708081 | ... T30: =T29+S30 -> 32100235

Sheet Certificados
A1: Obra: GDR 3740
C3: O.C. | D3: Descripcion | E3: Importe | F3: IVA | G3: Total
C4: P1B70 | D4: Presupuesto 1 Preliminar Y Hormigon | E4: =500907720*0.7 -> 350635404 | F4: =+E4*0.105 -> 36816717 | G4: =E4+F4 -> 3.8745212e+08
C5: P1N30 | D5: Presupuesto 1 Preliminar Y Hormigon | E5: =500907720*0.3 -> 150272316 | F5: 0 | G5: =E5+F5 -> 150272316
C6: P2B70 | D6: Presupuesto 2 - Albañilería/Inst. | E6: =844845248*0.7 -> 5.9139167e+08 | F6: =+E6*0.105 -> 62096126 | G6: =E6+F6 -> 6.534878e+08
C7: P2N30 | D7: Presupuesto 2 - Albañilería/Inst. | E7: =844845248*0.3 -> 2.5345357e+08 | F7: 0 | G7: =E7+F7 -> 2.5345357e+08
C8: AD01N | D8: Adicionales 01 | E8: 96300019 | F8: 0 | G8: =E8+F8 -> 96300019
D9: Totales | E9: =SUM(E4:E8) -> 1442052987 | F9: =SUM(F4:F8) -> 98912843 | G9: =SUM(G4:G8) -> 1.5409658e+09
K10: CERT. - B | L10: Fecha | M10: Pagos
A11: Fecha | B11: COD | C11: O.C. | D11: Descripcion | E11: Importe | F11: CAC | G11: IVA | H11: Total | J11: usd | K11: =SUM(K12:K80) -> 361022.08
A12: 45689 | B12: P1B70 | C12: Pto. 1 | D12: Presupuesto 1 - Anticipo B70 | E12: =+E4*0.4 -> 1.4025416e+08 | F12: =Facturacion!$V$3*70% -> 4530102.4 | G12: =(F12+E12)*0.105 -> 15202348 | H12: =SUM(E12:G12) -> 1.5998661e+08
A13: 45689 | B13: P1N30 | C13: Pto. 1 | D13: Presupuesto 1 - Anticipo N30 | E13: =+E5*0.4 -> 60108926 | F13: =Facturacion!$V$3*30% -> 1941472.4 | G13: 0 | H13: =SUM(E13:G13) -> 62050399 | J13: 1164.79 | K13: =+H13/J13 -> 53271.748
A14: 45689 | B14: P2B70 | C14: Pto. 2 | D14: Presupuesto 2 - Anticipo B70 | E14: =E6*0.1 -> 59139167 | F14: =Facturacion!$V$4*70% -> 1910150 | G14: =(F14+E14)*0.105 -> 6410178.3 | H14: =SUM(E14:G14) -> 67459496
A15: 45689 | B15: P2N30 | C15: Pto. 2 | D15: Presupuesto 2 - Anticipo N30 | E15: =E7*0.1 -> 25345357 | F15: =Facturacion!$V$4*30% -> 818635.7 | G15: 0 | H15: =SUM(E15:G15) -> 26163993 | J15: 1164.79 | K15: =+H15/J15 -> 22462.412
A16: 45747 | B16: P1B70 | C16: Pto. 1 | D16: Presupuesto 1 - Certif. # 1 - B70 | E16: =19603686*0.7 -> 13722580 | F16: =Facturacion!$V$5*70% -> 443228.86 | G16: =(F16+E16)*0.105 -> 1487410 | H16: =SUM(E16:G16) -> 15653219
A17: 45747 | B17: P1N30 | C17: Pto. 1 | D17: Presupuesto 1 - Certif. # 1 - N30 | E17: =19603686*0.3 -> 5881105.8 | F17: =Facturacion!$V$5*30% -> 189955.22 | G17: 0 | H17: =SUM(E17:G17) -> 6071061 | J17: 1313.97 | K17: =+H17/J17 -> 4620.3955
A18: 45747 | B18: P2B70 | C18: Pto. 2 | D18: Presupuesto 2 - Certif. # 1 - B70 | E18: =8012799*0.7 -> 5608959.3 | F18: =Facturacion!$V$6*70% -> 181165.1 | G18: =(F18+E18)*0.105 -> 607963.06 | H18: =SUM(E18:G18) -> 6398087.5
A19: 45747 | B19: P2N30 | C19: Pto. 2 | D19: Presupuesto 2 - Certif. # 1 - N30 | E19: =8012799*0.3 -> 2403839.7 | F19: =Facturacion!$V$6*30% -> 77642.186 | G19: 0 | H19: =SUM(E19:G19) -> 2481481.9 | J19: 1313.97 | K19: =+H19/J19 -> 1888.5377
A20: 45747 | B20: GGN | C20: Pto. 3 | D20: Presupuesto 3 - Certif. #1 | K20: 7792
A21: 45777 | B21: P1B70 | C21: Pto. 1 | D21: Presupuesto 1 - Certif. # 2 - B70 | E21: =16465959*0.7 -> 11526171 | F21: =Facturacion!$V$7*70% -> 479619.16 | G21: =(F21+E21)*0.105 -> 1260608 | H21: =SUM(E21:G21) -> 13266398 | L21: 45751 | M21: 10000
A22: 45777 | B22: P1N30 | C22: Pto. 1 | D22: Presupuesto 1 - Certif. # 2 - N30 | E22: =16465959*0.3 -> 4939787.7 | F22: =Facturacion!$V$7*30% -> 205551.07 | G22: 0 | H22: =SUM(E22:G22) -> 5145338.8 | J22: 1183.37 | K22: =+H22/J22 -> 4348.0389 | L22: 45754 | M22: 13600
A23: 45777 | B23: P2B70 | C23: Pto. 2 | D23: Presupuesto 2 - Certif. # 2 - B70 | E23: =7853224*0.7 -> 5497256.8 | F23: =Facturacion!$V$8*70% -> 228748.09 | G23: =(F23+E23)*0.105 -> 601230.51 | H23: =SUM(E23:G23) -> 6327235.4 | L23: 45762 | M23: 4000
A24: 45777 | B24: P2N30 | C24: Pto. 2 | D24: Presupuesto 2 - Certif. # 2 - N30 | E24: =7853224*0.3 -> 2355967.2 | F24: =Facturacion!$V$8*30% -> 98034.898 | G24: 0 | H24: =SUM(E24:G24) -> 2454002.1 | J24: 1183.37 | K24: =+H24/J24 -> 2073.7403 | L24: 45786 | M24: 50000
A25: 45777 | B25: GGN | C25: Pto. 3 | D25: Presupuesto 3 - Certif. #2 | K25: 7792
A26: 45808 | B26: P1B70 | C26: Pto. 1 | D26: Presupuesto 1 - Certif. # 3 - B70 | E26: =38898523*0.7 -> 27228966 | F26: =Facturacion!$V$9*70% -> 1590679.2 | G26: =(F26+E26)*0.105 -> 3026062.8 | H26: =SUM(E26:G26) -> 31845708 | L26: 45787 | M26: 3000
A27: 45808 | B27: P1N30 | C27: Pto. 1 | D27: Presupuesto 1 - Certif. # 3 - N30 | E27: =38898523*0.3 -> 11669557 | F27: =Facturacion!$V$9*30% -> 681719.65 | G27: 0 | H27: =SUM(E27:G27) -> 12351277 | J27: 1191.72 | K27: =+H27/J27 -> 10364.244 | L27: 45793 | M27: 50000
A28: 45808 | B28: P2B70 | C28: Pto. 2 | D28: Presupuesto 2 - Certif. # 3 - B70 | E28: =8963295*0.7 -> 6274306.5 | F28: =Facturacion!$V$10*70% -> 366536.46 | G28: =(F28+E28)*0.105 -> 697288.51 | H28: =SUM(E28:G28) -> 7338131.5 | L28: 45831 | M28: 30000
A29: 45808 | B29: P2N30 | C29: Pto. 2 | D29: Presupuesto 2 - Certif. # 3 - N30 | E29: =8963295*0.3 -> 2688988.5 | F29: =Facturacion!$V$10*30% -> 157087.05 | G29: 0 | H29: =SUM(E29:G29) -> 2846075.6 | J29: 1191.72 | K29: =+H29/J29 -> 2388.2083 | L29: 45835 | M29: 3505
A30: 45808 | B30: GGN | C30: Pto. 3 | D30: Presupuesto 3 - Certif. #3 | K30: 7792
A31: 45838 | B31: P1B70 | C31: Pto. 1 | D31: Presupuesto 1 - Certif. # 4 - B70 | E31: =21634403.628*70% -> 15144083 | F31: =1641134.431*70% -> 1148794.1 | G31: =(F31+E31)*0.105 -> 1710752 | H31: =SUM(E31:G31) -> 18003629 | L31: 45877 | M31: 1200
A32: 45838 | B32: P1N30 | C32: Pto. 1 | D32: Presupuesto 1 - Certif. # 4 - N30 | E32: =21634403.628*30% -> 6490321.1 | F32: =1641134.431*30% -> 492340.33 | G32: 0 | H32: =SUM(E32:G32) -> 6982661.4 | J32: 1211.1 | K32: =+H32/J32 -> 5765.5531 | L32: 45891 | M32: 2650
A33: 45838 | B33: P2B70 | C33: Pto. 2 | D33: Presupuesto 2 - Certif. # 4 - B70 | E33: =8241381.396*70% -> 5768967 | F33: =625171.601*70% -> 437620.12 | G33: =(F33+E33)*0.105 -> 651691.65 | H33: =SUM(E33:G33) -> 6858278.7 | L33: 45959 | M33: 10000
A34: 45838 | B34: P2N30 | C34: Pto. 2 | D34: Presupuesto 2 - Certif. # 4 - N30 | E34: =8241381.396*30% -> 2472414.4 | F34: =625171.601*30% -> 187551.48 | G34: 0 | H34: =SUM(E34:G34) -> 2659965.9 | J34: 1211.1 | K34: =+H34/J34 -> 2196.3223 | L34: 45638 | M34: 14000
A35: 45838 | B35: GGN | C35: Pto. 3 | D35: Presupuesto 3 - Certif. #4 | K35: 7792
A36: 45869 | B36: P1B70 | C36: Pto. 1 | D36: Presupuesto 1 - Certif. # 5 - B70 | E36: =56374940*0.7 -> 39462458 | F36: =4724710*0.7 -> 3307297 | G36: =(F36+E36)*0.105 -> 4490824.3 | H36: =SUM(E36:G36) -> 47260579 | L36: 46002 | M36: 1200
A37: 45869 | B37: P1N30 | C37: Pto. 1 | D37: Presupuesto 1 - Certif. # 5 - N30 | E37: =56374940*0.3 -> 16912482 | F37: =4724710*0.3 -> 1417413 | G37: 0 | H37: =SUM(E37:G37) -> 18329895 | J37: 1359.76 | K37: =+H37/J37 -> 13480.243 | L37: 46002 | M37: 20000
A38: 45869 | B38: P2B70 | C38: Pto. 2 | D38: Presupuesto 2 - Certif. # 5 - B70 | E38: =10717734.43*0.7 -> 7502414.1 | F38: =898239.44*0.7 -> 628767.61 | G38: =(F38+E38)*0.105 -> 853774.08 | H38: =SUM(E38:G38) -> 8984955.8 | L38: 46003 | M38: 18000
A39: 45869 | B39: P2N30 | C39: Pto. 2 | D39: Presupuesto 2 - Certif. # 5 - N30 | E39: =10717734.43*0.3 -> 3215320.3 | F39: =898239.44*0.3 -> 269471.83 | G39: 0 | H39: =SUM(E39:G39) -> 3484792.2 | J39: 1359.76 | K39: =+H39/J39 -> 2562.7994 | L39: 46008 | M39: 34873
A40: 45869 | B40: GGN | C40: Pto. 3 | D40: Presupuesto 3 - Certif. #5 | K40: 7792 | L40: 46031 | M40: 5426
A41: 45900 | B41: P1B70 | C41: Pto. 1 | D41: Presupuesto 1 - Certif. # 6 - B70 | E41: =33566952.47*70% -> 23496867 | F41: =3460436.199*70% -> 2422305.3 | G41: =(F41+E41)*0.105 -> 2721513.1 | H41: =SUM(E41:G41) -> 28640685 | L41: 46071 | M41: 3000
A42: 45900 | B42: P1N30 | C42: Pto. 1 | D42: Presupuesto 1 - Certif. # 6 - N30 | E42: =33566952.47*30% -> 10070086 | F42: =3460436.199*30% -> 1038130.9 | G42: 0 | H42: =SUM(E42:G42) -> 11108217 | J42: 1357.34 | K42: =+H42/J42 -> 8183.8129
A43: 45900 | B43: P2B70 | C43: Pto. 2 | D43: Presupuesto 2 - Certif. # 6 - B70 | E43: =10175591.475*70% -> 7122914 | F43: =1049007.505*70% -> 734305.25 | G43: =(F43+E43)*0.105 -> 825008.03 | H43: =SUM(E43:G43) -> 8682227.3
A44: 45900 | B44: P2N30 | C44: Pto. 2 | D44: Presupuesto 2 - Certif. # 6 - N30 | E44: =10175591.475*30% -> 3052677.4 | F44: =1049007.505*30% -> 314702.25 | G44: 0 | H44: =SUM(E44:G44) -> 3367379.7 | J44: 1357.34 | K44: =+H44/J44 -> 2480.8668
A45: 45900 | B45: AD01N | C45: Adic | D45: Adicional 01 - Certif. #1 | E45: 2212945 | F45: 228134 | G45: 0 | H45: =SUM(E45:G45) -> 2441079 | J45: 1357.34 | K45: =+H45/J45 -> 1798.4285
A46: 45900 | B46: GGN | C46: Pto. 3 | D46: Presupuesto 3 - Certif. #6 | K46: 7792
A47: 45930 | B47: P1B70 | C47: Pto. 1 | D47: Presupuesto 1 - Certif. # 7 - B65 | E47: =20270753.4*0.65 -> 13175990 | F47: =2417220.42*0.65 -> 1571193.3 | G47: =(F47+E47)*0.105 -> 1548454.2 | H47: =SUM(E47:G47) -> 16295637
A48: 45930 | B48: P1N30 | C48: Pto. 1 | D48: Presupuesto 1 - Certif. # 7 - N35 | E48: =20270753.4*0.35 -> 7094763.7 | F48: =2417220.42*0.35 -> 846027.15 | G48: 0 | H48: =SUM(E48:G48) -> 7940790.8 | J48: 1494.02 | K48: =+H48/J48 -> 5315.0499
A49: 45930 | B49: P2B70 | C49: Pto. 2 | D49: Presupuesto 2 - Certif. # 7 - B65 | E49: =12720796.16*0.65 -> 8268517.5 | F49: =1516912.94*0.65 -> 985993.41 | G49: =(F49+E49)*0.105 -> 971723.65 | H49: =SUM(E49:G49) -> 10226235
A50: 45930 | B50: P2N30 | C50: Pto. 2 | D50: Presupuesto 2 - Certif. # 7 - N35 | E50: =12720796.16*0.35 -> 4452278.7 | F50: =1516912.94*0.35 -> 530919.53 | G50: 0 | H50: =SUM(E50:G50) -> 4983198.2 | J50: 1494.02 | K50: =+H50/J50 -> 3335.4294
A51: 45930 | B51: AD01N | C51: Adic | D51: Adicional 01 - Certif. #2 | E51: 23811290 | F51: 2839418 | G51: 0 | H51: =SUM(E51:G51) -> 26650708 | J51: 1494.02 | K51: =+H51/J51 -> 17838.254
A52: 45930 | B52: GGN | C52: Pto. 3 | D52: Presupuesto 3 - Certif. #7 | K52: 7792
A53: 45958 | B53: P1B70 | C53: Pto. 1 | D53: Presupuesto 1 - Certif. # 8 - B65 | E53: =15191867*0.65 -> 9874713.6 | F53: =2380122*0.65 -> 1547079.3 | G53: =(F53+E53)*0.105 -> 1199288.2 | H53: =SUM(E53:G53) -> 12621081
A54: 45958 | B54: P1N30 | C54: Pto. 1 | D54: Presupuesto 1 - Certif. # 8 - N35 | E54: =15191867*0.35 -> 5317153.4 | F54: =2380122*0.35 -> 833042.7 | G54: 0 | H54: =SUM(E54:G54) -> 6150196.1 | J54: 1477.87 | K54: =+H54/J54 -> 4161.5272
A55: 45958 | B55: P2B70 | C55: Pto. 2 | D55: Presupuesto 2 - Certif. # 8 - B65 | E55: =11023993*0.65 -> 7165595.5 | F55: =1727138*0.65 -> 1122639.7 | G55: =(F55+E55)*0.105 -> 870264.69 | H55: =SUM(E55:G55) -> 9158499.8
A56: 45958 | B56: P2N30 | C56: Pto. 2 | D56: Presupuesto 2 - Certif. # 8 - N35 | E56: =11023993*0.35 -> 3858397.5 | F56: =1727138*0.35 -> 604498.3 | G56: 0 | H56: =SUM(E56:G56) -> 4462895.8 | J56: 1477.87 | K56: =+H56/J56 -> 3019.8163
A57: 45958 | B57: AD01N | C57: Adic | D57: Adicional 01 - Certif. #3 | E57: 35176921 | F57: 5511198 | G57: 0 | H57: =SUM(E57:G57) -> 40688119 | J57: 1477.87 | K57: =+H57/J57 -> 27531.595
A58: 45958 | B58: GGN | C58: Pto. 3 | D58: Presupuesto 3 - Certif. #8 | K58: 7792
A59: 45988 | B59: P1B70 | C59: Pto. 1 | D59: Presupuesto 1 - Certif. # 9 - B65 | E59: =25893302.99616*0.65 -> 16830647 | F59: =4748892.876*0.65 -> 3086780.4 | G59: =(F59+E59)*0.105 -> 2091329.9 | H59: =SUM(E59:G59) -> 22008757
A60: 45988 | B60: P1N30 | C60: Pto. 1 | D60: Presupuesto 1 - Certif. # 9 - N35 | E60: =25893302.99616*0.35 -> 9062656 | F60: =4748892.876*0.35 -> 1662112.5 | G60: 0 | H60: =SUM(E60:G60) -> 10724769 | J60: 1481.82 | K60: =+H60/J60 -> 7237.565
A61: 45988 | B61: P2B70 | C61: Pto. 2 | D61: Presupuesto 2 - Certif. # 9 - B65 | E61: =17371057.7808*0.65 -> 11291188 | F61: =3185892.991*0.65 -> 2070830.4 | G61: =(F61+E61)*0.105 -> 1403011.9 | H61: =SUM(E61:G61) -> 14765030
A62: 45988 | B62: P2N30 | C62: Pto. 2 | D62: Presupuesto 2 - Certif. # 9 - N35 | E62: =17371057.7808*0.35 -> 6079870.2 | F62: =3185892.991*0.35 -> 1115062.5 | G62: 0 | H62: =SUM(E62:G62) -> 7194932.8 | J62: 1481.82 | K62: =+H62/J62 -> 4855.4701
A63: 45988 | B63: AD01N | C63: Adic | D63: Adicional 01 - Certif. #4 | E63: 32644303 | F63: 5987042 | G63: 0 | H63: =SUM(E63:G63) -> 38631345 | J63: 1481.82 | K63: =+H63/J63 -> 26070.201
A64: 45988 | B64: GGN | C64: Pto. 3 | D64: Presupuesto 3 - Certif. #9 | K64: 7792
A65: 45988 | B65: P1N30 | C65: Pto. 1 | D65: Deductivos Pto. 1 (Anticipo Pto. 1) | E65: -35175794 | F65: 0 | G65: 0 | H65: =SUM(E65:G65) -> -35175794 | J65: 1170.41 | K65: =+H65/J65 -> -30054.249
A66: 46017 | B66: P2B70 | C66: Pto. 2 | D66: Presupuesto 2 - Certif. # 10 - B60 | E66: =32994657.3*0.6 -> 19796794 | F66: =6829303.63*0.6 -> 4097582.2 | G66: =(F66+E66)*0.105 -> 2508909.5 | H66: =SUM(E66:G66) -> 26403286
A67: 46017 | B67: P2N30 | C67: Pto. 2 | D67: Presupuesto 2 - Certif. # 10 - N40 | E67: =32994657.3*0.4 -> 13197863 | F67: =6829303.63*0.4 -> 2731721.5 | G67: 0 | H67: =SUM(E67:G67) -> 15929584 | J67: 1486.11 | K67: =+H67/J67 -> 10718.981
A68: 46017 | B68: GGN | C68: Pto. 3 | D68: Presupuesto 3 - Certif. #10 | K68: 7792
A69: 46050 | B69: P2B70 | C69: Pto. 2 | D69: Presupuesto 2 - Certif. # 11 - B60 | E69: =37677411.9*60% -> 22606447 | F69: =8391323.26*60% -> 5034794 | G69: =(F69+E69)*0.105 -> 2902330.3 | H69: =SUM(E69:G69) -> 30543571
A70: 46050 | B70: P2N30 | C70: Pto. 2 | D70: Presupuesto 2 - Certif. # 11 - N40 | E70: =37677411.9*40% -> 15070965 | F70: =8391323.26*40% -> 3356529.3 | G70: 0 | H70: =SUM(E70:G70) -> 18427494 | J70: 1462.35 | K70: =+H70/J70 -> 12601.288
A71: 46050 | B71: GGN | C71: Pto. 3 | D71: Presupuesto 3 - Certif. #11 | K71: 7792
A72: 46080 | B72: P2B70 | C72: Pto. 2 | D72: Presupuesto 2 - Certif. # 12 - B60 | E72: =25158565.47*0.6 -> 15095139 | F72: =6312414*0.6 -> 3787448.4 | G72: =(F72+E72)*0.105 -> 1982671.7 | H72: =SUM(E72:G72) -> 20865259
A73: 46080 | B73: P2N30 | C73: Pto. 2 | D73: Presupuesto 2 - Certif. # 12 - N40 | E73: =25158565.47*0.4 -> 10063426 | F73: =6312414*0.4 -> 2524965.6 | G73: 0 | H73: =SUM(E73:G73) -> 12588392 | J73: 1419.54 | K73: =+H73/J73 -> 8867.9374
A74: 46080 | B74: GGN | C74: Pto. 3 | D74: Presupuesto 3 - Certif. #12 | K74: 7792
A75: 46108 | B75: P2B70 | C75: Pto. 2 | D75: Presupuesto 2 - Certif. # 13 - B60 | E75: =57396789.378*60% -> 34438074 | F75: =15311641.228*60% -> 9186984.7 | G75: =(F75+E75)*0.105 -> 4580631.1 | H75: =SUM(E75:G75) -> 48205689
A76: 46108 | B76: P2N30 | C76: Pto. 2 | D76: Presupuesto 2 - Certif. # 13 - N40 | E76: =57396789.378*40% -> 22958716 | F76: =15311641.228*40% -> 6124656.5 | G76: 0 | H76: =SUM(E76:G76) -> 29083372 | J76: 1429.73 | K76: =+H76/J76 -> 20341.863
A77: 46108 | B77: GGN | C77: Pto. 3 | D77: Presupuesto 3 - Certif. #13 | K77: 7792
D81: Totales | E81: =SUM(E12:E80) -> 8.3972496e+08 | F81: =SUM(F12:F80) -> 93685680 | G81: =SUM(G12:G80) -> 60605267 | H81: =SUM(H12:H80) -> 9.9401591e+08 | K81: =SUM(K12:K80) -> 361022.08 | M81: =SUM(M12:M80) -> 274454
K83: Por Cobrar | M83: =K81-M81 -> 86568.078
D84: Total Presupuestado | E84: =SUM(E4:E8) -> 1442052987
D85: Total Facturado | E85: =SUMIF($B$12:$B$80,"0003-*",$E$12:$E$80) -> 0
D86: Total Sin Facturar | E86: =SUMIF($B$12:$B$80,"",$E$12:$E$80) -> 0
D87: Pendiente de Facturar | E87: =E84-E85-E86 -> 1442052987
C89: O.C. | D89: Descripcion | E89: Certificado | F89: Pendiente | G89: Facturable
C90: P1B70 | D90: Presupuesto 1 Preliminar Y Hormigon | E90: =SUMIF($B$12:$B$80,C90,$E$12:$E$80) -> 3.1071664e+08 | F90: =SUMIF($C$4:$C$8,C90,$E$4:$E$8)-E90 -> 39918767 | G90: =+E90 -> 3.1071664e+08
C91: P1N30 | D91: Presupuesto 1 Preliminar Y Hormigon | E91: =SUMIF($B$12:$B$80,C91,$E$12:$E$80) -> 1.0237104e+08 | F91: =SUMIF($C$4:$C$8,C91,$E$4:$E$8)-E91 -> 47901271
C92: P2B70 | D92: Presupuesto 2 - Albañilería/Inst. | E92: =SUMIF($B$12:$B$80,C92,$E$12:$E$80) -> 2.1557574e+08 | F92: =SUMIF($C$4:$C$8,C92,$E$4:$E$8)-E92 -> 3.7581593e+08 | G92: =+E92 -> 2.1557574e+08
C93: P2N30 | D93: Presupuesto 2 - Albañilería/Inst. | E93: =SUMIF($B$12:$B$80,C93,$E$12:$E$80) -> 1.1721608e+08 | F93: =SUMIF($C$4:$C$8,C93,$E$4:$E$8)-E93 -> 1.3623749e+08
C94: AD01N | D94: Adicionales 01 | E94: =SUMIF($B$12:$B$80,C94,$E$12:$E$80) -> 93845459 | F94: =SUMIF($C$4:$C$8,C94,$E$4:$E$8)-E94 -> 2454560
E96: =SUM(E90:E95) -> 8.3972496e+08 | F96: =SUM(F90:F95) -> 6.0232803e+08 | G96: =SUM(G90:G95) -> 5.2629238e+08
G98: =+E96-G96 -> 3.1343258e+08

Sheet Facturacion
A1: Obra: GDR 3740 | S1: Ingresos Pendientes de facturación y cobro | Y1: CAC Base | Z1: 45627 | AA1: 15356.4
S2: Fecha | T2: Detalle | U2: Importe | V2: CAC | W2: Total | Z2: 45689 | AA2: 15852.4
C3: O.C. | D3: Descripcion | E3: Importe | F3: IVA | G3: Total | K3: 0.4 | L3: =SUM(E4:E5)*K3 -> 200363088 | M3: =Certificados!E12+Certificados!F12 -> 1.4478426e+08 | N3: a Facturar | S3: 45689 | T3: Anticipo Pto. 1 | U3: 200363088 | V3: =U3*(($AA$2/$AA$1)-1) -> 6471574.8 | W3: =SUM(U3:V3) -> 2.0683466e+08
C4: GDR3760-01-F | D4: Presupuesto 1 Preliminar Y Hormigon | E4: ='Preventivo Vta'!H46*70% -> 350635404 | F4: =+E4*0.105 -> 36816717 | G4: =E4+F4 -> 3.8745212e+08 | H4: =+E4*0.4 -> 1.4025416e+08 | M4: =+E12+E13+E14+E15+F12+F13+F14+F15+E20+F20 -> 1.1459384e+08 | N4: Facturado | S4: 45689 | T4: Anticipo Pto. 2 | U4: =SUM(E6:E7)*10% -> 84484525 | V4: =U4*(($AA$2/$AA$1)-1) -> 2728785.7 | W4: =SUM(U4:V4) -> 87213310
C5: GDR3760-01-N | D5: Presupuesto 1 Preliminar Y Hormigon | E5: ='Preventivo Vta'!H46*30% -> 150272316 | F5: 0 | G5: =E5+F5 -> 150272316 | H5: =+E5*0.4 -> 60108926 | M5: =M3-M4 -> 30190424 | S5: 45747 | T5: Cert. # 1 - Pto. 1 | U5: 19603686 | V5: 633184.08 | W5: =SUM(U5:V5) -> 20236870
C6: GDR3760-02-F | D6: Presupuesto 2 - Albañilería/Inst. | E6: ='Preventivo Vta'!H234*70% -> 5.9139167e+08 | F6: =+E6*0.105 -> 62096126 | G6: =E6+F6 -> 6.534878e+08 | S6: 45747 | T6: Cert. # 1 - Pto. 2 | U6: 8012798.9 | V6: 258807.29 | W6: =SUM(U6:V6) -> 8271606.2
C7: GDR3760-02-N | D7: Presupuesto 2 - Albañilería/Inst. | E7: ='Preventivo Vta'!H234*30% -> 2.5345357e+08 | F7: 0 | G7: =E7+F7 -> 2.5345357e+08 | S7: 45777 | T7: Cert. # 2 - Pto. 1 | U7: 16465959 | V7: 685170.23 | W7: =SUM(U7:V7) -> 17151130
F8: =+E8*0.105 -> 0 | G8: =E8+F8 -> 0 | S8: 45777 | T8: Cert. # 2 - Pto. 2 | U8: 7853224.3 | V8: 326782.99 | W8: =SUM(U8:V8) -> 8180007.3
D9: Totales | E9: =SUM(E4:E8) -> 1345752968 | F9: =SUM(F4:F8) -> 98912843 | G9: =SUM(G4:G8) -> 1.4446658e+09 | S9: 45808 | T9: Cert. # 3 - Pto. 1 | U9: 38898523 | V9: 2272398.8 | W9: =SUM(U9:V9) -> 41170922
K10: Según Banco | S10: 45808 | T10: Cert. # 3 - Pto. 2 | U10: 8963295.2 | V10: 523623.51 | W10: =SUM(U10:V10) -> 9486918.7
A11: Fecha | B11: Factura | C11: O.C. | D11: Descripcion | E11: Importe | F11: CAC | G11: IVA | H11: Total | L11: Retenciones | M11: Total | S11: 45838 | T11: Cert. # 4 - Pto. 1 | U11: 21634404 | V11: 1641134.4 | W11: =SUM(U11:V11) -> 23275538
A12: 45784 | B12: 0003-00000653 | C12: GDR3760-01-F | D12: Presupuesto 1 - Anticipo | E12: =44000000*0.97 -> 42680000 | F12: =44000000*0.03 -> 1320000 | G12: =(E12+F12)*0.105 -> 4620000 | H12: =SUM(E12:G12) -> 48620000 | I12: Pto 1 | K12: 45777 | M12: 23400000 | S12: 45838 | T12: Cert. # 4 - Pto. 2 | U12: 8241381.4 | V12: 625171.6 | W12: =SUM(U12:V12) -> 8866553
A13: 45838 | B13: 0003-00000683 | C13: GDR3760-01-F | D13: Presupuesto 1 - Anticipo | E13: =34000000*0.97 -> 32980000 | F13: =34000000*0.03 -> 1020000 | G13: =(F13+E13)*0.105 -> 3570000 | H13: =SUM(E13:G13) -> 37570000 | I13: Pto 1 | K13: 45783 | M13: 23700000 | S13: 45869 | T13: Cert. # 5 - Pto. 1 | U13: 56374940 | V13: 4724710 | W13: =SUM(U13:V13) -> 61099650
A14: 45866 | B14: 0003-00000699 | C14: GDR3760-01-F | D14: Presupuesto 1 - Anticipo | E14: =27500000*0.97 -> 26675000 | F14: =27500000*0.03 -> 825000 | G14: =(F14+E14)*0.105 -> 2887500 | H14: =SUM(E14:G14) -> 30387500 | I14: Pto 1 | K14: 45812 | M14: 17100000 | S14: 45869 | T14: Cert. # 5 - Pto. 2 | U14: 10717734 | V14: 898239.44 | W14: =SUM(U14:V14) -> 11615974
A15: 45869 | B15: 0003-00000704 | C15: GDR3760-01-F | D15: Presupuesto 1 - Anticipo | E15: =44066.5429864253*0.97 -> 42744.547 | F15: =44066.5429864253*0.03 -> 1321.9963 | G15: =(F15+E15)*0.105 -> 4626.987 | H15: 48693.53 | I15: Pto 1 | K15: 45826 | M15: 10000000 | S15: 45900 | T15: Cert. # 6 - Pto. 1 | U15: 33566952 | V15: 3460436.2 | W15: =SUM(U15:V15) -> 37027389
A16: 45869 | B16: 0003-00000704 | C16: GDR3760-01-F | D16: Presupuesto 1 - Certif. #1 | E16: 13722580 | F16: 443228.86 | G16: =(F16+E16)*0.105 -> 1487410 | H16: =SUM(E16:G16) -> 15653219 | I16: Pto 1 | K16: 45835 | M16: 12000000 | S16: 45900 | T16: Cert. # 6 - Pto. 2 | U16: 10175591 | V16: 1049007.5 | W16: =SUM(U16:V16) -> 11224599
A17: 45869 | B17: 0003-00000704 | C17: GDR3760-02-F | D17: Presupuesto 2 - Certif. #1 | E17: 5608959.3 | F17: 181165.1 | G17: =(F17+E17)*0.105 -> 607963.06 | H17: =SUM(E17:G17) -> 6398087.5 | I17: Pto 2 | K17: 45845 | M17: 20000000
A18: 45891 | B18: 0003-00000719 | C18: GDR3760-01-F | D18: Presupuesto 1 - Certif. #2 | E18: 11526171 | F18: 479619.16 | G18: =SUM(E18:F18)*0.105 -> 1260608 | H18: =SUM(E18:G18) -> 13266398 | I18: Pto 1 | K18: 45860 | M18: 10000000
A19: 45891 | B19: 0003-00000719 | C19: GDR3760-02-F | D19: Presupuesto 2 - Certif. #2 | E19: 5497256.8 | F19: 228748.09 | G19: =SUM(E19:F19)*0.105 -> 601230.51 | H19: =SUM(E19:G19) -> 6327235.4 | I19: Pto 2 | K19: 45869 | M19: 20000000
A20: 45897 | B20: 0003-00000721 | C20: GDR3760-01-F | D20: Presupuesto 1 - Anticipo | E20: =9049773.76*0.97 -> 8778280.5 | F20: =9049773.76*0.03 -> 271493.21 | G20: =SUM(E20:F20)*0.105 -> 950226.24 | H20: =SUM(E20:G20) -> 10000000 | I20: Pto 1 | K20: 45891 | L20: 353292.5 | M20: 19240341
A21: 45900 | B21: 0003-00000722 | C21: GDR3760-01-F | D21: Presupuesto 1 - Anticipo | E21: =30190423.67*0.97 -> 29284711 | F21: =30190423.67*0.03 -> 905712.71 | G21: =(F21+E21)*0.105 -> 3169994.5 | H21: =SUM(E21:G21) -> 33360418 | I21: Pto 1 | K21: 45898 | M21: 9820347.9 | U21: =SUM(U3:U20) -> 5.253561e+08
A22: 45900 | B22: 0003-00000723 | C22: GDR3760-01-F | D22: Presupuesto 1 - Certif. #3 | E22: 27228966 | F22: 1590679.2 | G22: 3026062.8 | H22: =SUM(E22:G22) -> 31845708 | I22: Pto 1 | K22: 45933 | L22: 188701.85 | M22: 10311298 | T22: Cobrado | U22: =(23400000+23700000+17100000)/1.105 -> 58099548 | W22: =SUM(W3:W21) -> 5.5165513e+08
A23: 45900 | B23: 0003-00000723 | C23: GDR3760-02-F | D23: Presupuesto 2 - Certif. #3 | E23: 6274306.5 | F23: 366536.46 | G23: 697288.51 | H23: =SUM(E23:G23) -> 7338131.5 | I23: Pto 2 | K23: 45945 | L23: 216787.33 | M23: 21760713 | T23: Total Pendiente | U23: =U21-U22 -> 4.6725656e+08
A24: 45930 | B24: 0003-00000736 | C24: GDR3760-01-F | D24: Presupuesto 1 - Certif. #4 | E24: 15144083 | F24: 1148794.1 | G24: =(F24+E24)*0.105 -> 1710752 | H24: =SUM(E24:G24) -> 18003629 | I24: Pto 1 | K24: 45953 | L24: 241817.52 | M24: 13118601
A25: 45930 | B25: 0003-00000736 | C25: GDR3760-02-F | D25: Presupuesto 2 - Certif. #4 | E25: 5768967 | F25: 437620.12 | G25: =(F25+E25)*0.105 -> 651691.65 | H25: =SUM(E25:G25) -> 6858278.7 | I25: Pto 2 | K25: 45959 | L25: 469244.84 | M25: 25530755
A26: 45959 | B26: 0003-00000754 | C26: GDR3760-01-F | D26: Presupuesto 1 - Certif. #5 | E26: 39462458 | F26: =4724710*0.7 -> 3307297 | G26: =(F26+E26)*0.105 -> 4490824.3 | H26: =SUM(E26:G26) -> 47260579 | I26: Pto 1 | K26: 45980 | M26: 6000000
A27: 45959 | B27: 0003-00000754 | C27: GDR3760-02-F | D27: Presupuesto 2 - Certif. #5 | E27: 7502414.1 | F27: =898239.44*0.7 -> 628767.61 | G27: =(F27+E27)*0.105 -> 853774.08 | H27: =SUM(E27:G27) -> 8984955.8 | I27: Pto 2 | K27: 45986 | L27: 382074.51 | M27: 20801765
A28: 46009 | B28: 0003-00000784 | C28: GDR3760-01-F | D28: Presupuesto 1 - Certif. #6 | E28: 23496867 | F28: =3460436.199*70% -> 2422305.3 | G28: =(F28+E28)*0.105 -> 2721513.1 | H28: =SUM(E28:G28) -> 28640685 | K28: 45995 | L28: 469997.04 | M28: 25571562
A29: 46009 | B29: 0003-00000784 | C29: GDR3760-02-F | D29: Presupuesto 2 - Certif. #6 | E29: 7122914 | F29: =1049007.505*70% -> 734305.25 | G29: =(F29+E29)*0.105 -> 825008.02 | H29: =SUM(E29:G29) -> 8682227.3 | K29: 46009 | L29: 565530.05 | M29: 30680005
A30: 46041 | B30: 0003-00000800 | C30: GDR3760-01-F | D30: Presupuesto 1 - Certif. # 7 | E30: 14189527 | F30: 1692054.3 | G30: 1667566.1 | H30: =SUM(E30:G30) -> 17549148 | K30: 46024 | M30: 20000000
A31: 46041 | B31: 0003-00000800 | C31: GDR3760-02-F | D31: Presupuesto 2 - Certif. # 7 | E31: 8268517.5 | F31: 985993.41 | G31: 971723.65 | H31: =SUM(E31:G31) -> 10226235 | K31: 46029 | L31: 674184.83 | M31: 16648728
A32: 46041 | B32: 0003-00000802 | C32: GDR3760-01-F | D32: Presupuesto 1 - Certif. # 8 | E32: 9874713.6 | F32: 1547079.3 | G32: 1199288.2 | H32: =SUM(E32:G32) -> 12621081 | K32: 46045 | M32: =48000000+658040.86 -> 48658041
A33: 46041 | B33: 0003-00000802 | C33: GDR3760-02-F | D33: Presupuesto 2 - Certif. # 8 | E33: 7165595.5 | F33: 1122639.7 | G33: 870264.69 | H33: =SUM(E33:G33) -> 9158499.8
A34: 46057 | B34: 0003-00000810 | C34: GDR3760-01-F | D34: Presupuesto 1 - Certif. # 9 | E34: 16830647 | F34: 3086780.4 | G34: 2091329.9 | H34: =SUM(E34:G34) -> 22008757
A35: 46057 | B35: 0003-00000810 | C35: GDR3760-02-F | D35: Presupuesto 2 - Certif. # 9 | E35: 11291188 | F35: 2070830.4 | G35: 1403011.9 | H35: =SUM(E35:G35) -> 14765030
A36: 46100 | B36: 0003-00000832 | C36: GDR3760-02-F | D36: Presupuesto 2 - Certif. # 10 | E36: 19796794 | F36: 4097582.2 | G36: 2508909.5 | H36: =SUM(E36:G36) -> 26403286
H38: =SUM(E38:G38) -> 0
D39: Totales | E39: =SUM(E12:E38) -> 3.9621366e+08 | F39: =SUM(F12:F38) -> 30915554 | G39: =SUM(G12:G38) -> 44848568 | H39: =SUM(H12:H38) -> 4.7197778e+08 | M39: =SUM(L12:M38) -> 4.0790379e+08
L42: Por Cobrar | M42: =+M39-H39 -> -64073996
D43: Total Presupuestado | E43: =SUM(E4:E8) -> 1345752968
D44: Total Facturado | E44: =SUMIF($B$12:$B$25,"0003-*",$E$12:$E$25) -> 2.3121203e+08
D45: Total Sin Facturar | E45: =SUMIF($B$12:$B$25,"",$E$12:$E$25) -> 0
D46: Pendiente de Facturar | E46: =E43-E44-E45 -> 1.1145409e+09
C49: Facturación Según O. C. Aprobadas
C51: O.C. | D51: Descripcion | E51: Facturado | F51: Pendiente
C52: GDR3760-01-F | D52: Presupuesto 1 Preliminar Y Hormigon | E52: =SUMIF($C$12:$C$38,C52,$E$12:$E$38) -> 3.1191675e+08 | F52: =SUMIF($C$4:$C$8,C52,$E$4:$E$8)-E52 -> 38718655
C53: GDR3760-01-N | D53: Presupuesto 1 Preliminar Y Hormigon | E53: =SUMIF($C$12:$C$38,C53,$E$12:$E$38) -> 0 | F53: =SUMIF($C$4:$C$8,C53,$E$4:$E$8)-E53 -> 150272316
C54: GDR3760-02-F | D54: Presupuesto 2 - Albañilería/Inst. | E54: =SUMIF($C$12:$C$38,C54,$E$12:$E$38) -> 84296913 | F54: =SUMIF($C$4:$C$8,C54,$E$4:$E$8)-E54 -> 5.0709476e+08
C55: GDR3760-02-N | D55: Presupuesto 2 - Albañilería/Inst. | E55: =SUMIF($C$12:$C$38,C55,$E$12:$E$38) -> 0 | F55: =SUMIF($C$4:$C$8,C55,$E$4:$E$8)-E55 -> 2.5345357e+08
E57: =SUM(E52:E56) -> 3.9621366e+08 | F57: =SUM(F52:F56) -> 9.4953931e+08
C60: Total de Certificados Aprobados y Facturables | E60: =Certificados!G96 -> 5.2629238e+08
C61: Saldo de Certificados Aprobados sin Facturar | E61: =+E60-E57 -> 1.3007872e+08

Sheet Resumen Pto #2
AC1: Actualizado | AD1: 46133
B3: OBRA: GDR 3760
B4: RESUMEN DE OBRA
D5: 45627 | E5: 45658 | F5: 45689 | G5: 45717 | H5: 45748 | I5: 45778 | J5: 45809 | K5: 45839 | L5: 45870 | M5: 45901 | N5: 45931 | O5: 45962 | P5: 45992 | Q5: 46023 | R5: 46054 | S5: 46082 | T5: 46113 | V5: Acum. Descontado | X5: Previsto | Y5: % Cert. Acum. | Z5: Saldo Disponible | AA5: Disponible % | AB5: Rubro Completado
B6: Ingresos de Obra
B7: Ingresos por certificados | D7: =SUMIFS(Certificados!$E$12:$E$80,Certificados!$A$12:$A$80,">="&DATE(2024,12,1),Certificados!$A$12:$A$80,"<="&DATE(2024,12,31),Certificados!$C$12:$C$80,"Pto. 2") -> 0 | E7: =SUMIFS(Certificados!$E$12:$E$80,Certificados!$A$12:$A$80,">="&DATE(2025,1,1),Certificados!$A$12:$A$80,"<="&DATE(2025,1,31),Certificados!$C$12:$C$80,"Pto. 2") -> 0 | F7: =SUMIFS(Certificados!$E$12:$E$80,Certificados!$A$12:$A$80,">="&DATE(2025,2,1),Certificados!$A$12:$A$80,"<="&DATE(2025,2,28),Certificados!$C$12:$C$80,"Pto. 2") -> 84484525 | G7: =SUMIFS(Certificados!$E$12:$E$80,Certificados!$A$12:$A$80,">="&DATE(2025,3,1),Certificados!$A$12:$A$80,"<="&DATE(2025,3,31),Certificados!$C$12:$C$80,"Pto. 2") -> 8012799 | H7: =SUMIFS(Certificados!$E$12:$E$80,Certificados!$A$12:$A$80,">="&DATE(2025,4,1),Certificados!$A$12:$A$80,"<="&DATE(2025,4,30),Certificados!$C$12:$C$80,"Pto. 2") -> 7853224 | I7: =SUMIFS(Certificados!$E$12:$E$80,Certificados!$A$12:$A$80,">="&DATE(2025,5,1),Certificados!$A$12:$A$80,"<="&DATE(2025,5,31),Certificados!$C$12:$C$80,"Pto. 2") -> 8963295 | J7: =SUMIFS(Certificados!$E$12:$E$80,Certificados!$A$12:$A$80,">="&DATE(2025,6,1),Certificados!$A$12:$A$80,"<="&DATE(2025,6,30),Certificados!$C$12:$C$80,"Pto. 2") -> 8241381.4 | K7: =SUMIFS(Certificados!$E$12:$E$80,Certificados!$A$12:$A$80,">="&DATE(2025,7,1),Certificados!$A$12:$A$80,"<="&DATE(2025,7,31),Certificados!$C$12:$C$80,"Pto. 2") -> 10717734 | L7: =SUMIFS(Certificados!$E$12:$E$80,Certificados!$A$12:$A$80,">="&DATE(2025,8,1),Certificados!$A$12:$A$80,"<="&DATE(2025,8,31),Certificados!$C$12:$C$80,"Pto. 2") -> 10175591 | M7: =SUMIFS(Certificados!$E$12:$E$80,Certificados!$A$12:$A$80,">="&DATE(2025,9,1),Certificados!$A$12:$A$80,"<="&DATE(2025,9,30),Certificados!$C$12:$C$80,"Pto. 2") -> 12720796 | N7: =SUMIFS(Certificados!$E$12:$E$80,Certificados!$A$12:$A$80,">="&DATE(2025,10,1),Certificados!$A$12:$A$80,"<="&DATE(2025,10,30),Certificados!$C$12:$C$80,"Pto. 2") -> 11023993 | O7: =SUMIFS(Certificados!$E$12:$E$80,Certificados!$A$12:$A$80,">="&DATE(2025,11,1),Certificados!$A$12:$A$80,"<="&DATE(2025,11,30),Certificados!$C$12:$C$80,"Pto. 2") -> 17371058 | P7: =SUMIFS(Certificados!$E$12:$E$80,Certificados!$A$12:$A$80,">="&DATE(2025,12,1),Certificados!$A$12:$A$80,"<="&DATE(2025,12,31),Certificados!$C$12:$C$80,"Pto. 2") -> 32994657 | Q7: =SUMIFS(Certificados!$E$12:$E$80,Certificados!$A$12:$A$80,">="&DATE(2026,1,1),Certificados!$A$12:$A$80,"<="&DATE(2026,1,31),Certificados!$C$12:$C$80,"Pto. 2") -> 37677412 | R7: =SUMIFS(Certificados!$E$12:$E$80,Certificados!$A$12:$A$80,">="&DATE(2026,2,1),Certificados!$A$12:$A$80,"<="&DATE(2026,2,28),Certificados!$C$12:$C$80,"Pto. 2") -> 25158565 | S7: =SUMIFS(Certificados!$E$12:$E$80,Certificados!$A$12:$A$80,">="&DATE(2026,3,1),Certificados!$A$12:$A$80,"<="&DATE(2026,3,31),Certificados!$C$12:$C$80,"Pto. 2") -> 57396789 | T7: =SUMIFS(Certificados!$E$12:$E$80,Certificados!$A$12:$A$80,">="&DATE(2026,4,1),Certificados!$A$12:$A$80,"<="&DATE(2026,4,30),Certificados!$C$12:$C$80,"Pto. 2") -> 0 | V7: =SUM(D7:U7) -> 3.3279182e+08 | X7: =SUM(Facturacion!E6:E7) -> 8.4484525e+08 | Y7: ='Cert. Pto. 02'!V195/'Cert. Pto. 02'!L195 -> 0.32656513 | Z7: =IF(Y7=100%,0,IF(OR(V7<>0,X7),X7-V7)) -> 5.1205343e+08 | AA7: =IF(OR(Z7<0,X7),Z7/X7,0%) -> 0.60609139 | AB7: =IF(Y7=100%,IF(OR(G7<>0,X7),X7-G7),0) -> 0
B8: Total Ingresos de Obra | D8: =SUM(D7) -> 0 | E8: =SUM(E7) -> 0 | F8: =SUM(F7) -> 84484525 | G8: =SUM(G7) -> 8012799 | H8: =SUM(H7) -> 7853224 | I8: =SUM(I7) -> 8963295 | J8: =SUM(J7) -> 8241381.4 | K8: =SUM(K7) -> 10717734 | ... T8: =SUM(T7) -> 0 | V8: =SUM(V7) -> 3.3279182e+08 | X8: =SUM(X7) -> 8.4484525e+08 | Z8: =SUM(Z7) -> 5.1205343e+08 | AA8: =IF(OR(Z8<0,X8),Z8/X8,0%) -> 0.60609139 | AB8: =SUM(AB7) -> 0
B9: Actualización por CAC | D9: =SUMIFS(Certificados!$F$12:$F$80,Certificados!$A$12:$A$80,">="&DATE(2024,12,1),Certificados!$A$12:$A$80,"<="&DATE(2024,12,31),Certificados!$C$12:$C$80,"Pto. 2") -> 0 | E9: =SUMIFS(Certificados!$F$12:$F$80,Certificados!$A$12:$A$80,">="&DATE(2025,1,1),Certificados!$A$12:$A$80,"<="&DATE(2025,1,31),Certificados!$C$12:$C$80,"Pto. 2") -> 0 | F9: =SUMIFS(Certificados!$F$12:$F$80,Certificados!$A$12:$A$80,">="&DATE(2025,2,1),Certificados!$A$12:$A$80,"<="&DATE(2025,2,28),Certificados!$C$12:$C$80,"Pto. 2") -> 2728785.7 | G9: =SUMIFS(Certificados!$F$12:$F$80,Certificados!$A$12:$A$80,">="&DATE(2025,3,1),Certificados!$A$12:$A$80,"<="&DATE(2025,3,31),Certificados!$C$12:$C$80,"Pto. 2") -> 258807.29 | H9: =SUMIFS(Certificados!$F$12:$F$80,Certificados!$A$12:$A$80,">="&DATE(2025,4,1),Certificados!$A$12:$A$80,"<="&DATE(2025,4,30),Certificados!$C$12:$C$80,"Pto. 2") -> 326782.99 | I9: =SUMIFS(Certificados!$F$12:$F$80,Certificados!$A$12:$A$80,">="&DATE(2025,5,1),Certificados!$A$12:$A$80,"<="&DATE(2025,5,31),Certificados!$C$12:$C$80,"Pto. 2") -> 523623.51 | J9: =SUMIFS(Certificados!$F$12:$F$80,Certificados!$A$12:$A$80,">="&DATE(2025,6,1),Certificados!$A$12:$A$80,"<="&DATE(2025,6,30),Certificados!$C$12:$C$80,"Pto. 2") -> 625171.6 | K9: =SUMIFS(Certificados!$F$12:$F$80,Certificados!$A$12:$A$80,">="&DATE(2025,7,1),Certificados!$A$12:$A$80,"<="&DATE(2025,7,31),Certificados!$C$12:$C$80,"Pto. 2") -> 898239.44 | L9: =SUMIFS(Certificados!$F$12:$F$80,Certificados!$A$12:$A$80,">="&DATE(2025,8,1),Certificados!$A$12:$A$80,"<="&DATE(2025,8,31),Certificados!$C$12:$C$80,"Pto. 2") -> 1049007.5 | M9: =SUMIFS(Certificados!$F$12:$F$80,Certificados!$A$12:$A$80,">="&DATE(2025,9,1),Certificados!$A$12:$A$80,"<="&DATE(2025,9,30),Certificados!$C$12:$C$80,"Pto. 2") -> 1516912.9 | N9: =SUMIFS(Certificados!$F$12:$F$80,Certificados!$A$12:$A$80,">="&DATE(2025,10,1),Certificados!$A$12:$A$80,"<="&DATE(2025,10,30),Certificados!$C$12:$C$80,"Pto. 2") -> 1727138 | O9: =SUMIFS(Certificados!$F$12:$F$80,Certificados!$A$12:$A$80,">="&DATE(2025,11,1),Certificados!$A$12:$A$80,"<="&DATE(2025,11,30),Certificados!$C$12:$C$80,"Pto. 2") -> 3185893 | P9: =SUMIFS(Certificados!$F$12:$F$80,Certificados!$A$12:$A$80,">="&DATE(2025,12,1),Certificados!$A$12:$A$80,"<="&DATE(2025,12,31),Certificados!$C$12:$C$80,"Pto. 2") -> 6829303.6 | Q9: =SUMIFS(Certificados!$F$12:$F$80,Certificados!$A$12:$A$80,">="&DATE(2026,1,1),Certificados!$A$12:$A$80,"<="&DATE(2026,1,31),Certificados!$C$12:$C$80,"Pto. 2") -> 8391323.3 | R9: =SUMIFS(Certificados!$F$12:$F$80,Certificados!$A$12:$A$80,">="&DATE(2026,2,1),Certificados!$A$12:$A$80,"<="&DATE(2026,2,28),Certificados!$C$12:$C$80,"Pto. 2") -> 6312414 | S9: =SUMIFS(Certificados!$F$12:$F$80,Certificados!$A$12:$A$80,">="&DATE(2026,3,1),Certificados!$A$12:$A$80,"<="&DATE(2026,3,31),Certificados!$C$12:$C$80,"Pto. 2") -> 15311641 | T9: =SUMIFS(Certificados!$F$12:$F$80,Certificados!$A$12:$A$80,">="&DATE(2026,4,1),Certificados!$A$12:$A$80,"<="&DATE(2026,4,30),Certificados!$C$12:$C$80,"Pto. 2") -> 0 | V9: =SUM(D9:U9) -> 49685044 | X9: 0 | Y9: 0 | Z9: =IF(Y9=100%,0,IF(X9=0,X9,X9-V9)) -> 0 | AA9: =IF(OR(Z9<0,X9),Z9/X9,0%) -> 0 | AB9: =IF(Y9=100%,IF(OR(G9<>0,X9),X9-G9),0) -> 0
B10: Total Ingresos por CAC | D10: =SUM(D9) -> 0 | E10: =SUM(E9) -> 0 | F10: =SUM(F9) -> 2728785.7 | G10: =SUM(G9) -> 258807.29 | H10: =SUM(H9) -> 326782.99 | I10: =SUM(I9) -> 523623.51 | J10: =SUM(J9) -> 625171.6 | K10: =SUM(K9) -> 898239.44 | ... T10: =SUM(T9) -> 0 | V10: =SUM(V9) -> 49685044 | X10: =SUM(X9) -> 0 | Z10: =SUM(Z9) -> 0 | AA10: =IF(OR(Z10<0,X10),Z10/X10,0%) -> 0 | AB10: =SUM(AB9) -> 0
B12: Costos de Obra
B13: Supervisión de Obra | D13: =IFERROR(VLOOKUP($B13&$C13,'C. Gestión Pto #2'!$B$4:C$22,MATCH(D$5,'C. Gestión Pto #2'!$B$4:C$4,0),FALSE),0) -> 2128206 | E13: =IFERROR(VLOOKUP($B13&$C13,'C. Gestión Pto #2'!$B$4:D$22,MATCH(E$5,'C. Gestión Pto #2'!$B$4:D$4,0),FALSE),0) -> 2503867.6 | F13: =IFERROR(VLOOKUP($B13&$C13,'C. Gestión Pto #2'!$B$4:E$22,MATCH(F$5,'C. Gestión Pto #2'!$B$4:E$4,0),FALSE),0) -> 2666306.9 | G13: =IFERROR(VLOOKUP($B13&$C13,'C. Gestión Pto #2'!$B$4:F$22,MATCH(G$5,'C. Gestión Pto #2'!$B$4:F$4,0),FALSE),0) -> 2632626 | H13: =IFERROR(VLOOKUP($B13&$C13,'C. Gestión Pto #2'!$B$4:G$22,MATCH(H$5,'C. Gestión Pto #2'!$B$4:G$4,0),FALSE),0) -> 2612626 | I13: =IFERROR(VLOOKUP($B13&$C13,'C. Gestión Pto #2'!$B$4:H$22,MATCH(I$5,'C. Gestión Pto #2'!$B$4:H$4,0),FALSE),0) -> 2612626 | J13: =IFERROR(VLOOKUP($B13&$C13,'C. Gestión Pto #2'!$B$4:I$22,MATCH(J$5,'C. Gestión Pto #2'!$B$4:I$4,0),FALSE),0) -> 2770864 | K13: =IFERROR(VLOOKUP($B13&$C13,'C. Gestión Pto #2'!$B$4:J$22,MATCH(K$5,'C. Gestión Pto #2'!$B$4:J$4,0),FALSE),0) -> 2921847.5 | ... P13: =IFERROR(VLOOKUP($B13&$C13,'C. Gestión Pto #2'!$B$4:O$22,MATCH(P$5,'C. Gestión Pto #2'!$B$4:O$4,0),FALSE),0) -> 4621659.2 | Q13: =IFERROR(VLOOKUP($B13&$C13,'C. Gestión Pto #2'!$B$4:Q$22,MATCH(Q$5,'C. Gestión Pto #2'!$B$4:Q$4,0),FALSE),0) -> 3186153.1 | R13: =IFERROR(VLOOKUP($B13&$C13,'C. Gestión Pto #2'!$B$4:R$22,MATCH(R$5,'C. Gestión Pto #2'!$B$4:R$4,0),FALSE),0) -> 3241244.9 | S13: =IFERROR(VLOOKUP($B13&$C13,'C. Gestión Pto #2'!$B$4:S$22,MATCH(S$5,'C. Gestión Pto #2'!$B$4:S$4,0),FALSE),0) -> 3115790.4 | T13: =IFERROR(VLOOKUP($B13&$C13,'C. Gestión Pto #2'!$B$4:T$22,MATCH(T$5,'C. Gestión Pto #2'!$B$4:T$4,0),FALSE),0) -> 0 | V13: {=SUMPRODUCT($D13:$U13,TRANSPOSE('Indice CAC'!$D$2:$D$19))} -> 42358438 | X13: =SUM(IF($C13="MAT",SUMIF('P. Costo'!$A$61:$A$233,$B13,'P. Costo'!$I$61:$I$163),IF($C13="MO",SUMIF('P. Costo'!$A$61:$A$233,$B13,'P. Costo'!$L$61:$L$233),SUMIF('P. Costo'!$A$61:$A$233,$B13,'P. Costo'!$N$61:$N$233))),IF($C13="MAT",SUMIF('P. Costo'!$A$8:$A$58,$B13,'P. Costo'!$I$8:$I$58),IF($C13="MO",SUMIF('P. Costo'!$A$8:$A$58,$B13,'P. Costo'!$L$8:$L$58),SUMIF('P. Costo'!$A$8:$A$58,$B13,'P. Costo'!$N$8:$N$58)))) -> 74327580 | Y13: =IF($C13="MAT",SUMIF('Cert. Pto. 02'!$A$10:$A$194,'Resumen Pto #2'!$B13,'Cert. Pto. 02'!$T$10:$T$194),IF($C13="MO",SUMIF('Cert. Pto. 02'!$A$10:$A$194,$B13,'Cert. Pto. 02'!$U$10:$U$194),SUMIF('Cert. Pto. 02'!$A$10:$A$194,$B13,'Cert. Pto. 02'!$V$10:$V$194)))/IF($C13="MAT",SUMIF('Cert. Pto. 02'!$A$10:$A$194,'Resumen Pto #2'!$B13,'Cert. Pto. 02'!$I$10:$I$194),IF('Resumen Pto #2'!$C13="MO",SUMIF('Cert. Pto. 02'!$A$10:$A$194,$B13,'Cert. Pto. 02'!$J$10:$J$194),SUMIF('Cert. Pto. 02'!$A$10:$A$194,$B13,'Cert. Pto. 02'!$K$10:$K$194))) -> 0.65 | Z13: =IF(Y13=100%,0,IF(OR(V13<>0,X13),X13-V13)) -> 31969142 | AA13: =IF(OR(Z13<0,X13),Z13/X13,0%) -> 0.43011144 | AB13: =IF(Y13=100%,IF(OR(G13<>0,X13),X13-G13),0) -> 0
B14: Seguridad e Higiene | D14: =IFERROR(VLOOKUP($B14&$C14,'C. Gestión Pto #2'!$B$4:C$22,MATCH(D$5,'C. Gestión Pto #2'!$B$4:C$4,0),FALSE),0) -> 0 | E14: =IFERROR(VLOOKUP($B14&$C14,'C. Gestión Pto #2'!$B$4:D$22,MATCH(E$5,'C. Gestión Pto #2'!$B$4:D$4,0),FALSE),0) -> 0 | F14: =IFERROR(VLOOKUP($B14&$C14,'C. Gestión Pto #2'!$B$4:E$22,MATCH(F$5,'C. Gestión Pto #2'!$B$4:E$4,0),FALSE),0) -> 240000 | G14: =IFERROR(VLOOKUP($B14&$C14,'C. Gestión Pto #2'!$B$4:F$22,MATCH(G$5,'C. Gestión Pto #2'!$B$4:F$4,0),FALSE),0) -> 1706000 | H14: =IFERROR(VLOOKUP($B14&$C14,'C. Gestión Pto #2'!$B$4:G$22,MATCH(H$5,'C. Gestión Pto #2'!$B$4:G$4,0),FALSE),0) -> 446700 | I14: =IFERROR(VLOOKUP($B14&$C14,'C. Gestión Pto #2'!$B$4:H$22,MATCH(I$5,'C. Gestión Pto #2'!$B$4:H$4,0),FALSE),0) -> 1707000 | J14: =IFERROR(VLOOKUP($B14&$C14,'C. Gestión Pto #2'!$B$4:I$22,MATCH(J$5,'C. Gestión Pto #2'!$B$4:I$4,0),FALSE),0) -> 3102500 | K14: =IFERROR(VLOOKUP($B14&$C14,'C. Gestión Pto #2'!$B$4:J$22,MATCH(K$5,'C. Gestión Pto #2'!$B$4:J$4,0),FALSE),0) -> 535650 | ... P14: =IFERROR(VLOOKUP($B14&$C14,'C. Gestión Pto #2'!$B$4:O$22,MATCH(P$5,'C. Gestión Pto #2'!$B$4:O$4,0),FALSE),0) -> 510175 | Q14: =IFERROR(VLOOKUP($B14&$C14,'C. Gestión Pto #2'!$B$4:Q$22,MATCH(Q$5,'C. Gestión Pto #2'!$B$4:Q$4,0),FALSE),0) -> 902278 | R14: =IFERROR(VLOOKUP($B14&$C14,'C. Gestión Pto #2'!$B$4:R$22,MATCH(R$5,'C. Gestión Pto #2'!$B$4:R$4,0),FALSE),0) -> 537124 | S14: =IFERROR(VLOOKUP($B14&$C14,'C. Gestión Pto #2'!$B$4:S$22,MATCH(S$5,'C. Gestión Pto #2'!$B$4:S$4,0),FALSE),0) -> 1685000 | T14: =IFERROR(VLOOKUP($B14&$C14,'C. Gestión Pto #2'!$B$4:T$22,MATCH(T$5,'C. Gestión Pto #2'!$B$4:T$4,0),FALSE),0) -> 790000 | V14: {=SUMPRODUCT($D14:$U14,TRANSPOSE('Indice CAC'!$D$2:$D$19))} -> 13132520 | X14: =SUM(IF($C14="MAT",SUMIF('P. Costo'!$A$61:$A$233,$B14,'P. Costo'!$I$61:$I$163),IF($C14="MO",SUMIF('P. Costo'!$A$61:$A$233,$B14,'P. Costo'!$L$61:$L$233),SUMIF('P. Costo'!$A$61:$A$233,$B14,'P. Costo'!$N$61:$N$233))),IF($C14="MAT",SUMIF('P. Costo'!$A$8:$A$58,$B14,'P. Costo'!$I$8:$I$58),IF($C14="MO",SUMIF('P. Costo'!$A$8:$A$58,$B14,'P. Costo'!$L$8:$L$58),SUMIF('P. Costo'!$A$8:$A$58,$B14,'P. Costo'!$N$8:$N$58)))) -> 8568681.2 | Y14: =IF($C14="MAT",SUMIF('Cert. Pto. 02'!$A$10:$A$194,'Resumen Pto #2'!$B14,'Cert. Pto. 02'!$T$10:$T$194),IF($C14="MO",SUMIF('Cert. Pto. 02'!$A$10:$A$194,$B14,'Cert. Pto. 02'!$U$10:$U$194),SUMIF('Cert. Pto. 02'!$A$10:$A$194,$B14,'Cert. Pto. 02'!$V$10:$V$194)))/IF($C14="MAT",SUMIF('Cert. Pto. 02'!$A$10:$A$194,'Resumen Pto #2'!$B14,'Cert. Pto. 02'!$I$10:$I$194),IF('Resumen Pto #2'!$C14="MO",SUMIF('Cert. Pto. 02'!$A$10:$A$194,$B14,'Cert. Pto. 02'!$J$10:$J$194),SUMIF('Cert. Pto. 02'!$A$10:$A$194,$B14,'Cert. Pto. 02'!$K$10:$K$194))) -> 0.89584131 | Z14: =IF(Y14=100%,0,IF(OR(V14<>0,X14),X14-V14)) -> -4563838.8 | AA14: =IF(OR(Z14<0,X14),Z14/X14,0%) -> -0.53261859 | AB14: =IF(Y14=100%,IF(OR(G14<>0,X14),X14-G14),0) -> 0
B15: Movilidad | D15: =IFERROR(VLOOKUP($B15&$C15,'C. Gestión Pto #2'!$B$4:C$22,MATCH(D$5,'C. Gestión Pto #2'!$B$4:C$4,0),FALSE),0) -> 0 | E15: =IFERROR(VLOOKUP($B15&$C15,'C. Gestión Pto #2'!$B$4:D$22,MATCH(E$5,'C. Gestión Pto #2'!$B$4:D$4,0),FALSE),0) -> 320000 | F15: =IFERROR(VLOOKUP($B15&$C15,'C. Gestión Pto #2'!$B$4:E$22,MATCH(F$5,'C. Gestión Pto #2'!$B$4:E$4,0),FALSE),0) -> 14684.62 | G15: =IFERROR(VLOOKUP($B15&$C15,'C. Gestión Pto #2'!$B$4:F$22,MATCH(G$5,'C. Gestión Pto #2'!$B$4:F$4,0),FALSE),0) -> 181198.83 | H15: =IFERROR(VLOOKUP($B15&$C15,'C. Gestión Pto #2'!$B$4:G$22,MATCH(H$5,'C. Gestión Pto #2'!$B$4:G$4,0),FALSE),0) -> 217418.9 | I15: =IFERROR(VLOOKUP($B15&$C15,'C. Gestión Pto #2'!$B$4:H$22,MATCH(I$5,'C. Gestión Pto #2'!$B$4:H$4,0),FALSE),0) -> 263908.65 | J15: =IFERROR(VLOOKUP($B15&$C15,'C. Gestión Pto #2'!$B$4:I$22,MATCH(J$5,'C. Gestión Pto #2'!$B$4:I$4,0),FALSE),0) -> 162641.49 | K15: =IFERROR(VLOOKUP($B15&$C15,'C. Gestión Pto #2'!$B$4:J$22,MATCH(K$5,'C. Gestión Pto #2'!$B$4:J$4,0),FALSE),0) -> 614099.15 | ... P15: =IFERROR(VLOOKUP($B15&$C15,'C. Gestión Pto #2'!$B$4:O$22,MATCH(P$5,'C. Gestión Pto #2'!$B$4:O$4,0),FALSE),0) -> 1084990.7 | Q15: =IFERROR(VLOOKUP($B15&$C15,'C. Gestión Pto #2'!$B$4:Q$22,MATCH(Q$5,'C. Gestión Pto #2'!$B$4:Q$4,0),FALSE),0) -> 1932601.6 | R15: =IFERROR(VLOOKUP($B15&$C15,'C. Gestión Pto #2'!$B$4:R$22,MATCH(R$5,'C. Gestión Pto #2'!$B$4:R$4,0),FALSE),0) -> 579958.77 | S15: =IFERROR(VLOOKUP($B15&$C15,'C. Gestión Pto #2'!$B$4:S$22,MATCH(S$5,'C. Gestión Pto #2'!$B$4:S$4,0),FALSE),0) -> 621749.04 | T15: =IFERROR(VLOOKUP($B15&$C15,'C. Gestión Pto #2'!$B$4:T$22,MATCH(T$5,'C. Gestión Pto #2'!$B$4:T$4,0),FALSE),0) -> 432348.34 | V15: {=SUMPRODUCT($D15:$U15,TRANSPOSE('Indice CAC'!$D$2:$D$19))} -> 7606944 | X15: =SUM(IF($C15="MAT",SUMIF('P. Costo'!$A$61:$A$233,$B15,'P. Costo'!$I$61:$I$163),IF($C15="MO",SUMIF('P. Costo'!$A$61:$A$233,$B15,'P. Costo'!$L$61:$L$233),SUMIF('P. Costo'!$A$61:$A$233,$B15,'P. Costo'!$N$61:$N$233))),IF($C15="MAT",SUMIF('P. Costo'!$A$8:$A$58,$B15,'P. Costo'!$I$8:$I$58),IF($C15="MO",SUMIF('P. Costo'!$A$8:$A$58,$B15,'P. Costo'!$L$8:$L$58),SUMIF('P. Costo'!$A$8:$A$58,$B15,'P. Costo'!$N$8:$N$58)))) -> 13600000 | Y15: =IF($C15="MAT",SUMIF('Cert. Pto. 02'!$A$10:$A$194,'Resumen Pto #2'!$B15,'Cert. Pto. 02'!$T$10:$T$194),IF($C15="MO",SUMIF('Cert. Pto. 02'!$A$10:$A$194,$B15,'Cert. Pto. 02'!$U$10:$U$194),SUMIF('Cert. Pto. 02'!$A$10:$A$194,$B15,'Cert. Pto. 02'!$V$10:$V$194)))/IF($C15="MAT",SUMIF('Cert. Pto. 02'!$A$10:$A$194,'Resumen Pto #2'!$B15,'Cert. Pto. 02'!$I$10:$I$194),IF('Resumen Pto #2'!$C15="MO",SUMIF('Cert. Pto. 02'!$A$10:$A$194,$B15,'Cert. Pto. 02'!$J$10:$J$194),SUMIF('Cert. Pto. 02'!$A$10:$A$194,$B15,'Cert. Pto. 02'!$K$10:$K$194))) -> 0.65 | Z15: =IF(Y15=100%,0,IF(OR(V15<>0,X15),X15-V15)) -> 5993056 | AA15: =IF(OR(Z15<0,X15),Z15/X15,0%) -> 0.44066588 | AB15: =IF(Y15=100%,IF(OR(G15<>0,X15),X15-G15),0) -> 0
B16: Albañilería | C16: MAT | D16: =IFERROR(VLOOKUP($B16&$C16,'C. Gestión Pto #2'!$B$4:C$22,MATCH(D$5,'C. Gestión Pto #2'!$B$4:C$4,0),FALSE),0) -> 0 | E16: =IFERROR(VLOOKUP($B16&$C16,'C. Gestión Pto #2'!$B$4:D$22,MATCH(E$5,'C. Gestión Pto #2'!$B$4:D$4,0),FALSE),0) -> 0 | F16: =IFERROR(VLOOKUP($B16&$C16,'C. Gestión Pto #2'!$B$4:E$22,MATCH(F$5,'C. Gestión Pto #2'!$B$4:E$4,0),FALSE),0) -> 0 | G16: =IFERROR(VLOOKUP($B16&$C16,'C. Gestión Pto #2'!$B$4:F$22,MATCH(G$5,'C. Gestión Pto #2'!$B$4:F$4,0),FALSE),0) -> 0 | H16: =IFERROR(VLOOKUP($B16&$C16,'C. Gestión Pto #2'!$B$4:G$22,MATCH(H$5,'C. Gestión Pto #2'!$B$4:G$4,0),FALSE),0) -> 0 | I16: =IFERROR(VLOOKUP($B16&$C16,'C. Gestión Pto #2'!$B$4:H$22,MATCH(I$5,'C. Gestión Pto #2'!$B$4:H$4,0),FALSE),0) -> 0 | J16: =IFERROR(VLOOKUP($B16&$C16,'C. Gestión Pto #2'!$B$4:I$22,MATCH(J$5,'C. Gestión Pto #2'!$B$4:I$4,0),FALSE),0) -> 43528.94 | K16: =IFERROR(VLOOKUP($B16&$C16,'C. Gestión Pto #2'!$B$4:J$22,MATCH(K$5,'C. Gestión Pto #2'!$B$4:J$4,0),FALSE),0) -> 493967.79 | ... P16: =IFERROR(VLOOKUP($B16&$C16,'C. Gestión Pto #2'!$B$4:O$22,MATCH(P$5,'C. Gestión Pto #2'!$B$4:O$4,0),FALSE),0) -> 1477363.5 | Q16: =IFERROR(VLOOKUP($B16&$C16,'C. Gestión Pto #2'!$B$4:Q$22,MATCH(Q$5,'C. Gestión Pto #2'!$B$4:Q$4,0),FALSE),0) -> 2864564.5 | R16: =IFERROR(VLOOKUP($B16&$C16,'C. Gestión Pto #2'!$B$4:R$22,MATCH(R$5,'C. Gestión Pto #2'!$B$4:R$4,0),FALSE),0) -> 6304561.6 | S16: =IFERROR(VLOOKUP($B16&$C16,'C. Gestión Pto #2'!$B$4:S$22,MATCH(S$5,'C. Gestión Pto #2'!$B$4:S$4,0),FALSE),0) -> 6343465.5 | T16: =IFERROR(VLOOKUP($B16&$C16,'C. Gestión Pto #2'!$B$4:T$22,MATCH(T$5,'C. Gestión Pto #2'!$B$4:T$4,0),FALSE),0) -> 1587335.5 | V16: {=SUMPRODUCT($D16:$U16,TRANSPOSE('Indice CAC'!$D$2:$D$19))} -> 30259046 | X16: =SUM(IF($C16="MAT",SUMIF('P. Costo'!$A$61:$A$233,$B16,'P. Costo'!$I$61:$I$163),IF($C16="MO",SUMIF('P. Costo'!$A$61:$A$233,$B16,'P. Costo'!$L$61:$L$233),SUMIF('P. Costo'!$A$61:$A$233,$B16,'P. Costo'!$N$61:$N$233))),IF($C16="MAT",SUMIF('P. Costo'!$A$8:$A$58,$B16,'P. Costo'!$I$8:$I$58),IF($C16="MO",SUMIF('P. Costo'!$A$8:$A$58,$B16,'P. Costo'!$L$8:$L$58),SUMIF('P. Costo'!$A$8:$A$58,$B16,'P. Costo'!$N$8:$N$58)))) -> 65392825 | Y16: =IF($C16="MAT",SUMIF('Cert. Pto. 02'!$A$10:$A$194,'Resumen Pto #2'!$B16,'Cert. Pto. 02'!$T$10:$T$194),IF($C16="MO",SUMIF('Cert. Pto. 02'!$A$10:$A$194,$B16,'Cert. Pto. 02'!$U$10:$U$194),SUMIF('Cert. Pto. 02'!$A$10:$A$194,$B16,'Cert. Pto. 02'!$V$10:$V$194)))/IF($C16="MAT",SUMIF('Cert. Pto. 02'!$A$10:$A$194,'Resumen Pto #2'!$B16,'Cert. Pto. 02'!$I$10:$I$194),IF('Resumen Pto #2'!$C16="MO",SUMIF('Cert. Pto. 02'!$A$10:$A$194,$B16,'Cert. Pto. 02'!$J$10:$J$194),SUMIF('Cert. Pto. 02'!$A$10:$A$194,$B16,'Cert. Pto. 02'!$K$10:$K$194))) -> 0.31906124 | Z16: =IF(Y16=100%,0,IF(OR(V16<>0,X16),X16-V16)) -> 35133778 | AA16: =IF(OR(Z16<0,X16),Z16/X16,0%) -> 0.53727268 | AB16: =IF(Y16=100%,IF(OR(G16<>0,X16),X16-G16),0) -> 0
B17: Albañilería | C17: MO | D17: =IFERROR(VLOOKUP($B17&$C17,'C. Gestión Pto #2'!$B$4:C$22,MATCH(D$5,'C. Gestión Pto #2'!$B$4:C$4,0),FALSE),0) -> 0 | E17: =IFERROR(VLOOKUP($B17&$C17,'C. Gestión Pto #2'!$B$4:D$22,MATCH(E$5,'C. Gestión Pto #2'!$B$4:D$4,0),FALSE),0) -> 0 | F17: =IFERROR(VLOOKUP($B17&$C17,'C. Gestión Pto #2'!$B$4:E$22,MATCH(F$5,'C. Gestión Pto #2'!$B$4:E$4,0),FALSE),0) -> 725487 | G17: =IFERROR(VLOOKUP($B17&$C17,'C. Gestión Pto #2'!$B$4:F$22,MATCH(G$5,'C. Gestión Pto #2'!$B$4:F$4,0),FALSE),0) -> 3309015.8 | H17: =IFERROR(VLOOKUP($B17&$C17,'C. Gestión Pto #2'!$B$4:G$22,MATCH(H$5,'C. Gestión Pto #2'!$B$4:G$4,0),FALSE),0) -> 3592574 | I17: =IFERROR(VLOOKUP($B17&$C17,'C. Gestión Pto #2'!$B$4:H$22,MATCH(I$5,'C. Gestión Pto #2'!$B$4:H$4,0),FALSE),0) -> 3991998.7 | J17: =IFERROR(VLOOKUP($B17&$C17,'C. Gestión Pto #2'!$B$4:I$22,MATCH(J$5,'C. Gestión Pto #2'!$B$4:I$4,0),FALSE),0) -> 4723373.5 | K17: =IFERROR(VLOOKUP($B17&$C17,'C. Gestión Pto #2'!$B$4:J$22,MATCH(K$5,'C. Gestión Pto #2'!$B$4:J$4,0),FALSE),0) -> 6711151 | ... P17: =IFERROR(VLOOKUP($B17&$C17,'C. Gestión Pto #2'!$B$4:O$22,MATCH(P$5,'C. Gestión Pto #2'!$B$4:O$4,0),FALSE),0) -> 20262005 | Q17: =IFERROR(VLOOKUP($B17&$C17,'C. Gestión Pto #2'!$B$4:Q$22,MATCH(Q$5,'C. Gestión Pto #2'!$B$4:Q$4,0),FALSE),0) -> 21581645 | R17: =IFERROR(VLOOKUP($B17&$C17,'C. Gestión Pto #2'!$B$4:R$22,MATCH(R$5,'C. Gestión Pto #2'!$B$4:R$4,0),FALSE),0) -> 21958232 | S17: =IFERROR(VLOOKUP($B17&$C17,'C. Gestión Pto #2'!$B$4:S$22,MATCH(S$5,'C. Gestión Pto #2'!$B$4:S$4,0),FALSE),0) -> 28378747 | T17: =IFERROR(VLOOKUP($B17&$C17,'C. Gestión Pto #2'!$B$4:T$22,MATCH(T$5,'C. Gestión Pto #2'!$B$4:T$4,0),FALSE),0) -> 1829165 | V17: {=SUMPRODUCT($D17:$U17,TRANSPOSE('Indice CAC'!$D$2:$D$19))} -> 1.2817618e+08 | X17: =SUM(IF($C17="MAT",SUMIF('P. Costo'!$A$61:$A$233,$B17,'P. Costo'!$I$61:$I$163),IF($C17="MO",SUMIF('P. Costo'!$A$61:$A$233,$B17,'P. Costo'!$L$61:$L$233),SUMIF('P. Costo'!$A$61:$A$233,$B17,'P. Costo'!$N$61:$N$233))),IF($C17="MAT",SUMIF('P. Costo'!$A$8:$A$58,$B17,'P. Costo'!$I$8:$I$58),IF($C17="MO",SUMIF('P. Costo'!$A$8:$A$58,$B17,'P. Costo'!$L$8:$L$58),SUMIF('P. Costo'!$A$8:$A$58,$B17,'P. Costo'!$N$8:$N$58)))) -> 1.3257367e+08 | Y17: =IF($C17="MAT",SUMIF('Cert. Pto. 02'!$A$10:$A$194,'Resumen Pto #2'!$B17,'Cert. Pto. 02'!$T$10:$T$194),IF($C17="MO",SUMIF('Cert. Pto. 02'!$A$10:$A$194,$B17,'Cert. Pto. 02'!$U$10:$U$194),SUMIF('Cert. Pto. 02'!$A$10:$A$194,$B17,'Cert. Pto. 02'!$V$10:$V$194)))/IF($C17="MAT",SUMIF('Cert. Pto. 02'!$A$10:$A$194,'Resumen Pto #2'!$B17,'Cert. Pto. 02'!$I$10:$I$194),IF('Resumen Pto #2'!$C17="MO",SUMIF('Cert. Pto. 02'!$A$10:$A$194,$B17,'Cert. Pto. 02'!$J$10:$J$194),SUMIF('Cert. Pto. 02'!$A$10:$A$194,$B17,'Cert. Pto. 02'!$K$10:$K$194))) -> 0.42958142 | Z17: =IF(Y17=100%,0,IF(OR(V17<>0,X17),X17-V17)) -> 4397491.4 | AA17: =IF(OR(Z17<0,X17),Z17/X17,0%) -> 0.033170172 | AB17: =IF(Y17=100%,IF(OR(G17<>0,X17),X17-G17),0) -> 0
B18: Durlock | C18: MAT | D18: =IFERROR(VLOOKUP($B18&$C18,'C. Gestión Pto #2'!$B$4:C$22,MATCH(D$5,'C. Gestión Pto #2'!$B$4:C$4,0),FALSE),0) -> 0 | E18: =IFERROR(VLOOKUP($B18&$C18,'C. Gestión Pto #2'!$B$4:D$22,MATCH(E$5,'C. Gestión Pto #2'!$B$4:D$4,0),FALSE),0) -> 0 | F18: =IFERROR(VLOOKUP($B18&$C18,'C. Gestión Pto #2'!$B$4:E$22,MATCH(F$5,'C. Gestión Pto #2'!$B$4:E$4,0),FALSE),0) -> 0 | G18: =IFERROR(VLOOKUP($B18&$C18,'C. Gestión Pto #2'!$B$4:F$22,MATCH(G$5,'C. Gestión Pto #2'!$B$4:F$4,0),FALSE),0) -> 0 | H18: =IFERROR(VLOOKUP($B18&$C18,'C. Gestión Pto #2'!$B$4:G$22,MATCH(H$5,'C. Gestión Pto #2'!$B$4:G$4,0),FALSE),0) -> 0 | I18: =IFERROR(VLOOKUP($B18&$C18,'C. Gestión Pto #2'!$B$4:H$22,MATCH(I$5,'C. Gestión Pto #2'!$B$4:H$4,0),FALSE),0) -> 0 | J18: =IFERROR(VLOOKUP($B18&$C18,'C. Gestión Pto #2'!$B$4:I$22,MATCH(J$5,'C. Gestión Pto #2'!$B$4:I$4,0),FALSE),0) -> 0 | K18: =IFERROR(VLOOKUP($B18&$C18,'C. Gestión Pto #2'!$B$4:J$22,MATCH(K$5,'C. Gestión Pto #2'!$B$4:J$4,0),FALSE),0) -> 0 | ... P18: =IFERROR(VLOOKUP($B18&$C18,'C. Gestión Pto #2'!$B$4:O$22,MATCH(P$5,'C. Gestión Pto #2'!$B$4:O$4,0),FALSE),0) -> 0 | Q18: =IFERROR(VLOOKUP($B18&$C18,'C. Gestión Pto #2'!$B$4:Q$22,MATCH(Q$5,'C. Gestión Pto #2'!$B$4:Q$4,0),FALSE),0) -> 7783423.7 | R18: =IFERROR(VLOOKUP($B18&$C18,'C. Gestión Pto #2'!$B$4:R$22,MATCH(R$5,'C. Gestión Pto #2'!$B$4:R$4,0),FALSE),0) -> 0 | S18: =IFERROR(VLOOKUP($B18&$C18,'C. Gestión Pto #2'!$B$4:S$22,MATCH(S$5,'C. Gestión Pto #2'!$B$4:S$4,0),FALSE),0) -> 1583421.5 | T18: =IFERROR(VLOOKUP($B18&$C18,'C. Gestión Pto #2'!$B$4:T$22,MATCH(T$5,'C. Gestión Pto #2'!$B$4:T$4,0),FALSE),0) -> 0 | V18: {=SUMPRODUCT($D18:$U18,TRANSPOSE('Indice CAC'!$D$2:$D$19))} -> 7552799.6 | X18: =IF($C18="MAT",SUMIF('P. Costo'!$A$61:$A$233,$B18,'P. Costo'!$I$61:$I$163),IF($C18="MO",SUMIF('P. Costo'!$A$61:$A$233,$B18,'P. Costo'!$L$61:$L$233),SUMIF('P. Costo'!$A$61:$A$233,$B18,'P. Costo'!$N$61:$N$233))) -> 13489970 | Y18: =IF($C18="MAT",SUMIF('Cert. Pto. 02'!$A$10:$A$194,'Resumen Pto #2'!$B18,'Cert. Pto. 02'!$T$10:$T$194),IF($C18="MO",SUMIF('Cert. Pto. 02'!$A$10:$A$194,$B18,'Cert. Pto. 02'!$U$10:$U$194),SUMIF('Cert. Pto. 02'!$A$10:$A$194,$B18,'Cert. Pto. 02'!$V$10:$V$194)))/IF($C18="MAT",SUMIF('Cert. Pto. 02'!$A$10:$A$194,'Resumen Pto #2'!$B18,'Cert. Pto. 02'!$I$10:$I$194),IF('Resumen Pto #2'!$C18="MO",SUMIF('Cert. Pto. 02'!$A$10:$A$194,$B18,'Cert. Pto. 02'!$J$10:$J$194),SUMIF('Cert. Pto. 02'!$A$10:$A$194,$B18,'Cert. Pto. 02'!$K$10:$K$194))) -> 0.091870848 | Z18: =IF(Y18=100%,0,IF(OR(V18<>0,X18),X18-V18)) -> 5937170.7 | AA18: =IF(OR(Z18<0,X18),Z18/X18,0%) -> 0.4401174 | AB18: =IF(Y18=100%,IF(OR(G18<>0,X18),X18-G18),0) -> 0
B19: Durlock | C19: MO | D19: =IFERROR(VLOOKUP($B19&$C19,'C. Gestión Pto #2'!$B$4:C$22,MATCH(D$5,'C. Gestión Pto #2'!$B$4:C$4,0),FALSE),0) -> 0 | E19: =IFERROR(VLOOKUP($B19&$C19,'C. Gestión Pto #2'!$B$4:D$22,MATCH(E$5,'C. Gestión Pto #2'!$B$4:D$4,0),FALSE),0) -> 0 | F19: =IFERROR(VLOOKUP($B19&$C19,'C. Gestión Pto #2'!$B$4:E$22,MATCH(F$5,'C. Gestión Pto #2'!$B$4:E$4,0),FALSE),0) -> 0 | G19: =IFERROR(VLOOKUP($B19&$C19,'C. Gestión Pto #2'!$B$4:F$22,MATCH(G$5,'C. Gestión Pto #2'!$B$4:F$4,0),FALSE),0) -> 0 | H19: =IFERROR(VLOOKUP($B19&$C19,'C. Gestión Pto #2'!$B$4:G$22,MATCH(H$5,'C. Gestión Pto #2'!$B$4:G$4,0),FALSE),0) -> 0 | I19: =IFERROR(VLOOKUP($B19&$C19,'C. Gestión Pto #2'!$B$4:H$22,MATCH(I$5,'C. Gestión Pto #2'!$B$4:H$4,0),FALSE),0) -> 0 | J19: =IFERROR(VLOOKUP($B19&$C19,'C. Gestión Pto #2'!$B$4:I$22,MATCH(J$5,'C. Gestión Pto #2'!$B$4:I$4,0),FALSE),0) -> 0 | K19: =IFERROR(VLOOKUP($B19&$C19,'C. Gestión Pto #2'!$B$4:J$22,MATCH(K$5,'C. Gestión Pto #2'!$B$4:J$4,0),FALSE),0) -> 0 | ... P19: =IFERROR(VLOOKUP($B19&$C19,'C. Gestión Pto #2'!$B$4:O$22,MATCH(P$5,'C. Gestión Pto #2'!$B$4:O$4,0),FALSE),0) -> 0 | Q19: =IFERROR(VLOOKUP($B19&$C19,'C. Gestión Pto #2'!$B$4:Q$22,MATCH(Q$5,'C. Gestión Pto #2'!$B$4:Q$4,0),FALSE),0) -> 0 | R19: =IFERROR(VLOOKUP($B19&$C19,'C. Gestión Pto #2'!$B$4:R$22,MATCH(R$5,'C. Gestión Pto #2'!$B$4:R$4,0),FALSE),0) -> 2400000 | S19: =IFERROR(VLOOKUP($B19&$C19,'C. Gestión Pto #2'!$B$4:S$22,MATCH(S$5,'C. Gestión Pto #2'!$B$4:S$4,0),FALSE),0) -> 7589829 | T19: =IFERROR(VLOOKUP($B19&$C19,'C. Gestión Pto #2'!$B$4:T$22,MATCH(T$5,'C. Gestión Pto #2'!$B$4:T$4,0),FALSE),0) -> 3175584 | V19: {=SUMPRODUCT($D19:$U19,TRANSPOSE('Indice CAC'!$D$2:$D$19))} -> 10896814 | X19: =IF($C19="MAT",SUMIF('P. Costo'!$A$61:$A$233,$B19,'P. Costo'!$I$61:$I$163),IF($C19="MO",SUMIF('P. Costo'!$A$61:$A$233,$B19,'P. Costo'!$L$61:$L$233),SUMIF('P. Costo'!$A$61:$A$233,$B19,'P. Costo'!$N$61:$N$233))) -> 38496186 | Y19: =IF($C19="MAT",SUMIF('Cert. Pto. 02'!$A$10:$A$194,'Resumen Pto #2'!$B19,'Cert. Pto. 02'!$T$10:$T$194),IF($C19="MO",SUMIF('Cert. Pto. 02'!$A$10:$A$194,$B19,'Cert. Pto. 02'!$U$10:$U$194),SUMIF('Cert. Pto. 02'!$A$10:$A$194,$B19,'Cert. Pto. 02'!$V$10:$V$194)))/IF($C19="MAT",SUMIF('Cert. Pto. 02'!$A$10:$A$194,'Resumen Pto #2'!$B19,'Cert. Pto. 02'!$I$10:$I$194),IF('Resumen Pto #2'!$C19="MO",SUMIF('Cert. Pto. 02'!$A$10:$A$194,$B19,'Cert. Pto. 02'!$J$10:$J$194),SUMIF('Cert. Pto. 02'!$A$10:$A$194,$B19,'Cert. Pto. 02'!$K$10:$K$194))) -> 0.045566874 | Z19: =IF(Y19=100%,0,IF(OR(V19<>0,X19),X19-V19)) -> 27599372 | AA19: =IF(OR(Z19<0,X19),Z19/X19,0%) -> 0.71693783 | AB19: =IF(Y19=100%,IF(OR(G19<>0,X19),X19-G19),0) -> 0
B20: Pintura | C20: MAT | D20: =IFERROR(VLOOKUP($B20&$C20,'C. Gestión Pto #2'!$B$4:C$22,MATCH(D$5,'C. Gestión Pto #2'!$B$4:C$4,0),FALSE),0) -> 0 | E20: =IFERROR(VLOOKUP($B20&$C20,'C. Gestión Pto #2'!$B$4:D$22,MATCH(E$5,'C. Gestión Pto #2'!$B$4:D$4,0),FALSE),0) -> 0 | F20: =IFERROR(VLOOKUP($B20&$C20,'C. Gestión Pto #2'!$B$4:E$22,MATCH(F$5,'C. Gestión Pto #2'!$B$4:E$4,0),FALSE),0) -> 0 | G20: =IFERROR(VLOOKUP($B20&$C20,'C. Gestión Pto #2'!$B$4:F$22,MATCH(G$5,'C. Gestión Pto #2'!$B$4:F$4,0),FALSE),0) -> 0 | H20: =IFERROR(VLOOKUP($B20&$C20,'C. Gestión Pto #2'!$B$4:G$22,MATCH(H$5,'C. Gestión Pto #2'!$B$4:G$4,0),FALSE),0) -> 0 | I20: =IFERROR(VLOOKUP($B20&$C20,'C. Gestión Pto #2'!$B$4:H$22,MATCH(I$5,'C. Gestión Pto #2'!$B$4:H$4,0),FALSE),0) -> 0 | J20: =IFERROR(VLOOKUP($B20&$C20,'C. Gestión Pto #2'!$B$4:I$22,MATCH(J$5,'C. Gestión Pto #2'!$B$4:I$4,0),FALSE),0) -> 0 | K20: =IFERROR(VLOOKUP($B20&$C20,'C. Gestión Pto #2'!$B$4:J$22,MATCH(K$5,'C. Gestión Pto #2'!$B$4:J$4,0),FALSE),0) -> 0 | ... P20: =IFERROR(VLOOKUP($B20&$C20,'C. Gestión Pto #2'!$B$4:O$22,MATCH(P$5,'C. Gestión Pto #2'!$B$4:O$4,0),FALSE),0) -> 0 | Q20: =IFERROR(VLOOKUP($B20&$C20,'C. Gestión Pto #2'!$B$4:Q$22,MATCH(Q$5,'C. Gestión Pto #2'!$B$4:Q$4,0),FALSE),0) -> 116399.22 | R20: =IFERROR(VLOOKUP($B20&$C20,'C. Gestión Pto #2'!$B$4:R$22,MATCH(R$5,'C. Gestión Pto #2'!$B$4:R$4,0),FALSE),0) -> 0 | S20: =IFERROR(VLOOKUP($B20&$C20,'C. Gestión Pto #2'!$B$4:S$22,MATCH(S$5,'C. Gestión Pto #2'!$B$4:S$4,0),FALSE),0) -> 46767.16 | T20: =IFERROR(VLOOKUP($B20&$C20,'C. Gestión Pto #2'!$B$4:T$22,MATCH(T$5,'C. Gestión Pto #2'!$B$4:T$4,0),FALSE),0) -> 0 | V20: {=SUMPRODUCT($D20:$U20,TRANSPOSE('Indice CAC'!$D$2:$D$19))} -> 132350.95 | X20: =IF($C20="MAT",SUMIF('P. Costo'!$A$61:$A$233,$B20,'P. Costo'!$I$61:$I$163),IF($C20="MO",SUMIF('P. Costo'!$A$61:$A$233,$B20,'P. Costo'!$L$61:$L$233),SUMIF('P. Costo'!$A$61:$A$233,$B20,'P. Costo'!$N$61:$N$233))) -> 19488570 | Y20: =IF($C20="MAT",SUMIF('Cert. Pto. 02'!$A$10:$A$194,'Resumen Pto #2'!$B20,'Cert. Pto. 02'!$T$10:$T$194),IF($C20="MO",SUMIF('Cert. Pto. 02'!$A$10:$A$194,$B20,'Cert. Pto. 02'!$U$10:$U$194),SUMIF('Cert. Pto. 02'!$A$10:$A$194,$B20,'Cert. Pto. 02'!$V$10:$V$194)))/IF($C20="MAT",SUMIF('Cert. Pto. 02'!$A$10:$A$194,'Resumen Pto #2'!$B20,'Cert. Pto. 02'!$I$10:$I$194),IF('Resumen Pto #2'!$C20="MO",SUMIF('Cert. Pto. 02'!$A$10:$A$194,$B20,'Cert. Pto. 02'!$J$10:$J$194),SUMIF('Cert. Pto. 02'!$A$10:$A$194,$B20,'Cert. Pto. 02'!$K$10:$K$194))) -> 0 | Z20: =IF(Y20=100%,0,IF(OR(V20<>0,X20),X20-V20)) -> 19356219 | AA20: =IF(OR(Z20<0,X20),Z20/X20,0%) -> 0.99320879 | AB20: =IF(Y20=100%,IF(OR(G20<>0,X20),X20-G20),0) -> 0
B21: Pintura | C21: MO | D21: =IFERROR(VLOOKUP($B21&$C21,'C. Gestión Pto #2'!$B$4:C$22,MATCH(D$5,'C. Gestión Pto #2'!$B$4:C$4,0),FALSE),0) -> 0 | E21: =IFERROR(VLOOKUP($B21&$C21,'C. Gestión Pto #2'!$B$4:D$22,MATCH(E$5,'C. Gestión Pto #2'!$B$4:D$4,0),FALSE),0) -> 0 | F21: =IFERROR(VLOOKUP($B21&$C21,'C. Gestión Pto #2'!$B$4:E$22,MATCH(F$5,'C. Gestión Pto #2'!$B$4:E$4,0),FALSE),0) -> 0 | G21: =IFERROR(VLOOKUP($B21&$C21,'C. Gestión Pto #2'!$B$4:F$22,MATCH(G$5,'C. Gestión Pto #2'!$B$4:F$4,0),FALSE),0) -> 0 | H21: =IFERROR(VLOOKUP($B21&$C21,'C. Gestión Pto #2'!$B$4:G$22,MATCH(H$5,'C. Gestión Pto #2'!$B$4:G$4,0),FALSE),0) -> 0 | I21: =IFERROR(VLOOKUP($B21&$C21,'C. Gestión Pto #2'!$B$4:H$22,MATCH(I$5,'C. Gestión Pto #2'!$B$4:H$4,0),FALSE),0) -> 0 | J21: =IFERROR(VLOOKUP($B21&$C21,'C. Gestión Pto #2'!$B$4:I$22,MATCH(J$5,'C. Gestión Pto #2'!$B$4:I$4,0),FALSE),0) -> 0 | K21: =IFERROR(VLOOKUP($B21&$C21,'C. Gestión Pto #2'!$B$4:J$22,MATCH(K$5,'C. Gestión Pto #2'!$B$4:J$4,0),FALSE),0) -> 0 | ... P21: =IFERROR(VLOOKUP($B21&$C21,'C. Gestión Pto #2'!$B$4:O$22,MATCH(P$5,'C. Gestión Pto #2'!$B$4:O$4,0),FALSE),0) -> 0 | Q21: =IFERROR(VLOOKUP($B21&$C21,'C. Gestión Pto #2'!$B$4:Q$22,MATCH(Q$5,'C. Gestión Pto #2'!$B$4:Q$4,0),FALSE),0) -> 0 | R21: =IFERROR(VLOOKUP($B21&$C21,'C. Gestión Pto #2'!$B$4:R$22,MATCH(R$5,'C. Gestión Pto #2'!$B$4:R$4,0),FALSE),0) -> 0 | S21: =IFERROR(VLOOKUP($B21&$C21,'C. Gestión Pto #2'!$B$4:S$22,MATCH(S$5,'C. Gestión Pto #2'!$B$4:S$4,0),FALSE),0) -> 0 | T21: =IFERROR(VLOOKUP($B21&$C21,'C. Gestión Pto #2'!$B$4:T$22,MATCH(T$5,'C. Gestión Pto #2'!$B$4:T$4,0),FALSE),0) -> 0 | V21: {=SUMPRODUCT($D21:$U21,TRANSPOSE('Indice CAC'!$D$2:$D$19))} -> 0 | X21: =IF($C21="MAT",SUMIF('P. Costo'!$A$61:$A$233,$B21,'P. Costo'!$I$61:$I$163),IF($C21="MO",SUMIF('P. Costo'!$A$61:$A$233,$B21,'P. Costo'!$L$61:$L$233),SUMIF('P. Costo'!$A$61:$A$233,$B21,'P. Costo'!$N$61:$N$233))) -> 40879545 | Y21: =IF($C21="MAT",SUMIF('Cert. Pto. 02'!$A$10:$A$194,'Resumen Pto #2'!$B21,'Cert. Pto. 02'!$T$10:$T$194),IF($C21="MO",SUMIF('Cert. Pto. 02'!$A$10:$A$194,$B21,'Cert. Pto. 02'!$U$10:$U$194),SUMIF('Cert. Pto. 02'!$A$10:$A$194,$B21,'Cert. Pto. 02'!$V$10:$V$194)))/IF($C21="MAT",SUMIF('Cert. Pto. 02'!$A$10:$A$194,'Resumen Pto #2'!$B21,'Cert. Pto. 02'!$I$10:$I$194),IF('Resumen Pto #2'!$C21="MO",SUMIF('Cert. Pto. 02'!$A$10:$A$194,$B21,'Cert. Pto. 02'!$J$10:$J$194),SUMIF('Cert. Pto. 02'!$A$10:$A$194,$B21,'Cert. Pto. 02'!$K$10:$K$194))) -> 0 | Z21: =IF(Y21=100%,0,IF(OR(V21<>0,X21),X21-V21)) -> 40879545 | AA21: =IF(OR(Z21<0,X21),Z21/X21,0%) -> 1 | AB21: =IF(Y21=100%,IF(OR(G21<>0,X21),X21-G21),0) -> 0
B22: Revestimiento | C22: MAT | D22: =IFERROR(VLOOKUP($B22&$C22,'C. Gestión Pto #2'!$B$4:C$22,MATCH(D$5,'C. Gestión Pto #2'!$B$4:C$4,0),FALSE),0) -> 0 | E22: =IFERROR(VLOOKUP($B22&$C22,'C. Gestión Pto #2'!$B$4:D$22,MATCH(E$5,'C. Gestión Pto #2'!$B$4:D$4,0),FALSE),0) -> 0 | F22: =IFERROR(VLOOKUP($B22&$C22,'C. Gestión Pto #2'!$B$4:E$22,MATCH(F$5,'C. Gestión Pto #2'!$B$4:E$4,0),FALSE),0) -> 0 | G22: =IFERROR(VLOOKUP($B22&$C22,'C. Gestión Pto #2'!$B$4:F$22,MATCH(G$5,'C. Gestión Pto #2'!$B$4:F$4,0),FALSE),0) -> 0 | H22: =IFERROR(VLOOKUP($B22&$C22,'C. Gestión Pto #2'!$B$4:G$22,MATCH(H$5,'C. Gestión Pto #2'!$B$4:G$4,0),FALSE),0) -> 0 | I22: =IFERROR(VLOOKUP($B22&$C22,'C. Gestión Pto #2'!$B$4:H$22,MATCH(I$5,'C. Gestión Pto #2'!$B$4:H$4,0),FALSE),0) -> 0 | J22: =IFERROR(VLOOKUP($B22&$C22,'C. Gestión Pto #2'!$B$4:I$22,MATCH(J$5,'C. Gestión Pto #2'!$B$4:I$4,0),FALSE),0) -> 0 | K22: =IFERROR(VLOOKUP($B22&$C22,'C. Gestión Pto #2'!$B$4:J$22,MATCH(K$5,'C. Gestión Pto #2'!$B$4:J$4,0),FALSE),0) -> 0 | ... P22: =IFERROR(VLOOKUP($B22&$C22,'C. Gestión Pto #2'!$B$4:O$22,MATCH(P$5,'C. Gestión Pto #2'!$B$4:O$4,0),FALSE),0) -> 0 | Q22: =IFERROR(VLOOKUP($B22&$C22,'C. Gestión Pto #2'!$B$4:Q$22,MATCH(Q$5,'C. Gestión Pto #2'!$B$4:Q$4,0),FALSE),0) -> 0 | R22: =IFERROR(VLOOKUP($B22&$C22,'C. Gestión Pto #2'!$B$4:R$22,MATCH(R$5,'C. Gestión Pto #2'!$B$4:R$4,0),FALSE),0) -> 0 | S22: =IFERROR(VLOOKUP($B22&$C22,'C. Gestión Pto #2'!$B$4:S$22,MATCH(S$5,'C. Gestión Pto #2'!$B$4:S$4,0),FALSE),0) -> 2012146.6 | T22: =IFERROR(VLOOKUP($B22&$C22,'C. Gestión Pto #2'!$B$4:T$22,MATCH(T$5,'C. Gestión Pto #2'!$B$4:T$4,0),FALSE),0) -> 0 | V22: {=SUMPRODUCT($D22:$U22,TRANSPOSE('Indice CAC'!$D$2:$D$19))} -> 1690828.7 | X22: =IF($C22="MAT",SUMIF('P. Costo'!$A$61:$A$233,$B22,'P. Costo'!$I$61:$I$163),IF($C22="MO",SUMIF('P. Costo'!$A$61:$A$233,$B22,'P. Costo'!$L$61:$L$233),SUMIF('P. Costo'!$A$61:$A$233,$B22,'P. Costo'!$N$61:$N$233))) -> 13983960 | Y22: =IF($C22="MAT",SUMIF('Cert. Pto. 02'!$A$10:$A$194,'Resumen Pto #2'!$B22,'Cert. Pto. 02'!$T$10:$T$194),IF($C22="MO",SUMIF('Cert. Pto. 02'!$A$10:$A$194,$B22,'Cert. Pto. 02'!$U$10:$U$194),SUMIF('Cert. Pto. 02'!$A$10:$A$194,$B22,'Cert. Pto. 02'!$V$10:$V$194)))/IF($C22="MAT",SUMIF('Cert. Pto. 02'!$A$10:$A$194,'Resumen Pto #2'!$B22,'Cert. Pto. 02'!$I$10:$I$194),IF('Resumen Pto #2'!$C22="MO",SUMIF('Cert. Pto. 02'!$A$10:$A$194,$B22,'Cert. Pto. 02'!$J$10:$J$194),SUMIF('Cert. Pto. 02'!$A$10:$A$194,$B22,'Cert. Pto. 02'!$K$10:$K$194))) -> 0 | Z22: =IF(Y22=100%,0,IF(OR(V22<>0,X22),X22-V22)) -> 12293132 | AA22: =IF(OR(Z22<0,X22),Z22/X22,0%) -> 0.87908799 | AB22: =IF(Y22=100%,IF(OR(G22<>0,X22),X22-G22),0) -> 0
B23: Revestimiento | C23: MO | D23: =IFERROR(VLOOKUP($B23&$C23,'C. Gestión Pto #2'!$B$4:C$22,MATCH(D$5,'C. Gestión Pto #2'!$B$4:C$4,0),FALSE),0) -> 0 | E23: =IFERROR(VLOOKUP($B23&$C23,'C. Gestión Pto #2'!$B$4:D$22,MATCH(E$5,'C. Gestión Pto #2'!$B$4:D$4,0),FALSE),0) -> 0 | F23: =IFERROR(VLOOKUP($B23&$C23,'C. Gestión Pto #2'!$B$4:E$22,MATCH(F$5,'C. Gestión Pto #2'!$B$4:E$4,0),FALSE),0) -> 0 | G23: =IFERROR(VLOOKUP($B23&$C23,'C. Gestión Pto #2'!$B$4:F$22,MATCH(G$5,'C. Gestión Pto #2'!$B$4:F$4,0),FALSE),0) -> 0 | H23: =IFERROR(VLOOKUP($B23&$C23,'C. Gestión Pto #2'!$B$4:G$22,MATCH(H$5,'C. Gestión Pto #2'!$B$4:G$4,0),FALSE),0) -> 0 | I23: =IFERROR(VLOOKUP($B23&$C23,'C. Gestión Pto #2'!$B$4:H$22,MATCH(I$5,'C. Gestión Pto #2'!$B$4:H$4,0),FALSE),0) -> 0 | J23: =IFERROR(VLOOKUP($B23&$C23,'C. Gestión Pto #2'!$B$4:I$22,MATCH(J$5,'C. Gestión Pto #2'!$B$4:I$4,0),FALSE),0) -> 0 | K23: =IFERROR(VLOOKUP($B23&$C23,'C. Gestión Pto #2'!$B$4:J$22,MATCH(K$5,'C. Gestión Pto #2'!$B$4:J$4,0),FALSE),0) -> 0 | ... P23: =IFERROR(VLOOKUP($B23&$C23,'C. Gestión Pto #2'!$B$4:O$22,MATCH(P$5,'C. Gestión Pto #2'!$B$4:O$4,0),FALSE),0) -> 0 | Q23: =IFERROR(VLOOKUP($B23&$C23,'C. Gestión Pto #2'!$B$4:Q$22,MATCH(Q$5,'C. Gestión Pto #2'!$B$4:Q$4,0),FALSE),0) -> 0 | R23: =IFERROR(VLOOKUP($B23&$C23,'C. Gestión Pto #2'!$B$4:R$22,MATCH(R$5,'C. Gestión Pto #2'!$B$4:R$4,0),FALSE),0) -> 1940600 | S23: =IFERROR(VLOOKUP($B23&$C23,'C. Gestión Pto #2'!$B$4:S$22,MATCH(S$5,'C. Gestión Pto #2'!$B$4:S$4,0),FALSE),0) -> 0 | T23: =IFERROR(VLOOKUP($B23&$C23,'C. Gestión Pto #2'!$B$4:T$22,MATCH(T$5,'C. Gestión Pto #2'!$B$4:T$4,0),FALSE),0) -> 0 | V23: {=SUMPRODUCT($D23:$U23,TRANSPOSE('Indice CAC'!$D$2:$D$19))} -> 1531929.8 | X23: =IF($C23="MAT",SUMIF('P. Costo'!$A$61:$A$233,$B23,'P. Costo'!$I$61:$I$163),IF($C23="MO",SUMIF('P. Costo'!$A$61:$A$233,$B23,'P. Costo'!$L$61:$L$233),SUMIF('P. Costo'!$A$61:$A$233,$B23,'P. Costo'!$N$61:$N$233))) -> 26733574 | Y23: =IF($C23="MAT",SUMIF('Cert. Pto. 02'!$A$10:$A$194,'Resumen Pto #2'!$B23,'Cert. Pto. 02'!$T$10:$T$194),IF($C23="MO",SUMIF('Cert. Pto. 02'!$A$10:$A$194,$B23,'Cert. Pto. 02'!$U$10:$U$194),SUMIF('Cert. Pto. 02'!$A$10:$A$194,$B23,'Cert. Pto. 02'!$V$10:$V$194)))/IF($C23="MAT",SUMIF('Cert. Pto. 02'!$A$10:$A$194,'Resumen Pto #2'!$B23,'Cert. Pto. 02'!$I$10:$I$194),IF('Resumen Pto #2'!$C23="MO",SUMIF('Cert. Pto. 02'!$A$10:$A$194,$B23,'Cert. Pto. 02'!$J$10:$J$194),SUMIF('Cert. Pto. 02'!$A$10:$A$194,$B23,'Cert. Pto. 02'!$K$10:$K$194))) -> 0 | Z23: =IF(Y23=100%,0,IF(OR(V23<>0,X23),X23-V23)) -> 25201645 | AA23: =IF(OR(Z23<0,X23),Z23/X23,0%) -> 0.94269641 | AB23: =IF(Y23=100%,IF(OR(G23<>0,X23),X23-G23),0) -> 0
B24: Eléctrico | C24: MAT | D24: =IFERROR(VLOOKUP($B24&$C24,'C. Gestión Pto #2'!$B$4:C$22,MATCH(D$5,'C. Gestión Pto #2'!$B$4:C$4,0),FALSE),0) -> 0 | E24: =IFERROR(VLOOKUP($B24&$C24,'C. Gestión Pto #2'!$B$4:D$22,MATCH(E$5,'C. Gestión Pto #2'!$B$4:D$4,0),FALSE),0) -> 0 | F24: =IFERROR(VLOOKUP($B24&$C24,'C. Gestión Pto #2'!$B$4:E$22,MATCH(F$5,'C. Gestión Pto #2'!$B$4:E$4,0),FALSE),0) -> 0 | G24: =IFERROR(VLOOKUP($B24&$C24,'C. Gestión Pto #2'!$B$4:F$22,MATCH(G$5,'C. Gestión Pto #2'!$B$4:F$4,0),FALSE),0) -> 0 | H24: =IFERROR(VLOOKUP($B24&$C24,'C. Gestión Pto #2'!$B$4:G$22,MATCH(H$5,'C. Gestión Pto #2'!$B$4:G$4,0),FALSE),0) -> 0 | I24: =IFERROR(VLOOKUP($B24&$C24,'C. Gestión Pto #2'!$B$4:H$22,MATCH(I$5,'C. Gestión Pto #2'!$B$4:H$4,0),FALSE),0) -> 0 | J24: =IFERROR(VLOOKUP($B24&$C24,'C. Gestión Pto #2'!$B$4:I$22,MATCH(J$5,'C. Gestión Pto #2'!$B$4:I$4,0),FALSE),0) -> 0 | K24: =IFERROR(VLOOKUP($B24&$C24,'C. Gestión Pto #2'!$B$4:J$22,MATCH(K$5,'C. Gestión Pto #2'!$B$4:J$4,0),FALSE),0) -> 299136.83 | ... P24: =IFERROR(VLOOKUP($B24&$C24,'C. Gestión Pto #2'!$B$4:O$22,MATCH(P$5,'C. Gestión Pto #2'!$B$4:O$4,0),FALSE),0) -> 911386.19 | Q24: =IFERROR(VLOOKUP($B24&$C24,'C. Gestión Pto #2'!$B$4:Q$22,MATCH(Q$5,'C. Gestión Pto #2'!$B$4:Q$4,0),FALSE),0) -> 976118.42 | R24: =IFERROR(VLOOKUP($B24&$C24,'C. Gestión Pto #2'!$B$4:R$22,MATCH(R$5,'C. Gestión Pto #2'!$B$4:R$4,0),FALSE),0) -> 210250.83 | S24: =IFERROR(VLOOKUP($B24&$C24,'C. Gestión Pto #2'!$B$4:S$22,MATCH(S$5,'C. Gestión Pto #2'!$B$4:S$4,0),FALSE),0) -> 574075.59 | T24: =IFERROR(VLOOKUP($B24&$C24,'C. Gestión Pto #2'!$B$4:T$22,MATCH(T$5,'C. Gestión Pto #2'!$B$4:T$4,0),FALSE),0) -> 76388.01 | V24: {=SUMPRODUCT($D24:$U24,TRANSPOSE('Indice CAC'!$D$2:$D$19))} -> 4965352.9 | X24: =IF($C24="MAT",SUMIF('P. Costo'!$A$61:$A$233,$B24,'P. Costo'!$I$61:$I$163),IF($C24="MO",SUMIF('P. Costo'!$A$61:$A$233,$B24,'P. Costo'!$L$61:$L$233),SUMIF('P. Costo'!$A$61:$A$233,$B24,'P. Costo'!$N$61:$N$233))) -> 25092460 | Y24: =IF($C24="MAT",SUMIF('Cert. Pto. 02'!$A$10:$A$194,'Resumen Pto #2'!$B24,'Cert. Pto. 02'!$T$10:$T$194),IF($C24="MO",SUMIF('Cert. Pto. 02'!$A$10:$A$194,$B24,'Cert. Pto. 02'!$U$10:$U$194),SUMIF('Cert. Pto. 02'!$A$10:$A$194,$B24,'Cert. Pto. 02'!$V$10:$V$194)))/IF($C24="MAT",SUMIF('Cert. Pto. 02'!$A$10:$A$194,'Resumen Pto #2'!$B24,'Cert. Pto. 02'!$I$10:$I$194),IF('Resumen Pto #2'!$C24="MO",SUMIF('Cert. Pto. 02'!$A$10:$A$194,$B24,'Cert. Pto. 02'!$J$10:$J$194),SUMIF('Cert. Pto. 02'!$A$10:$A$194,$B24,'Cert. Pto. 02'!$K$10:$K$194))) -> 0.28984006 | Z24: =IF(Y24=100%,0,IF(OR(V24<>0,X24),X24-V24)) -> 20127107 | AA24: =IF(OR(Z24<0,X24),Z24/X24,0%) -> 0.80211773 | AB24: =IF(Y24=100%,IF(OR(G24<>0,X24),X24-G24),0) -> 0
B25: Eléctrico | C25: MO | D25: =IFERROR(VLOOKUP($B25&$C25,'C. Gestión Pto #2'!$B$4:C$22,MATCH(D$5,'C. Gestión Pto #2'!$B$4:C$4,0),FALSE),0) -> 0 | E25: =IFERROR(VLOOKUP($B25&$C25,'C. Gestión Pto #2'!$B$4:D$22,MATCH(E$5,'C. Gestión Pto #2'!$B$4:D$4,0),FALSE),0) -> 0 | F25: =IFERROR(VLOOKUP($B25&$C25,'C. Gestión Pto #2'!$B$4:E$22,MATCH(F$5,'C. Gestión Pto #2'!$B$4:E$4,0),FALSE),0) -> 0 | G25: =IFERROR(VLOOKUP($B25&$C25,'C. Gestión Pto #2'!$B$4:F$22,MATCH(G$5,'C. Gestión Pto #2'!$B$4:F$4,0),FALSE),0) -> 0 | H25: =IFERROR(VLOOKUP($B25&$C25,'C. Gestión Pto #2'!$B$4:G$22,MATCH(H$5,'C. Gestión Pto #2'!$B$4:G$4,0),FALSE),0) -> 0 | I25: =IFERROR(VLOOKUP($B25&$C25,'C. Gestión Pto #2'!$B$4:H$22,MATCH(I$5,'C. Gestión Pto #2'!$B$4:H$4,0),FALSE),0) -> 0 | J25: =IFERROR(VLOOKUP($B25&$C25,'C. Gestión Pto #2'!$B$4:I$22,MATCH(J$5,'C. Gestión Pto #2'!$B$4:I$4,0),FALSE),0) -> 0 | K25: =IFERROR(VLOOKUP($B25&$C25,'C. Gestión Pto #2'!$B$4:J$22,MATCH(K$5,'C. Gestión Pto #2'!$B$4:J$4,0),FALSE),0) -> 500000 | ... P25: =IFERROR(VLOOKUP($B25&$C25,'C. Gestión Pto #2'!$B$4:O$22,MATCH(P$5,'C. Gestión Pto #2'!$B$4:O$4,0),FALSE),0) -> 3802812.5 | Q25: =IFERROR(VLOOKUP($B25&$C25,'C. Gestión Pto #2'!$B$4:Q$22,MATCH(Q$5,'C. Gestión Pto #2'!$B$4:Q$4,0),FALSE),0) -> 4355561 | R25: =IFERROR(VLOOKUP($B25&$C25,'C. Gestión Pto #2'!$B$4:R$22,MATCH(R$5,'C. Gestión Pto #2'!$B$4:R$4,0),FALSE),0) -> 2943587.5 | S25: =IFERROR(VLOOKUP($B25&$C25,'C. Gestión Pto #2'!$B$4:S$22,MATCH(S$5,'C. Gestión Pto #2'!$B$4:S$4,0),FALSE),0) -> 4066285 | T25: =IFERROR(VLOOKUP($B25&$C25,'C. Gestión Pto #2'!$B$4:T$22,MATCH(T$5,'C. Gestión Pto #2'!$B$4:T$4,0),FALSE),0) -> 0 | V25: {=SUMPRODUCT($D25:$U25,TRANSPOSE('Indice CAC'!$D$2:$D$19))} -> 17814883 | X25: =IF($C25="MAT",SUMIF('P. Costo'!$A$61:$A$233,$B25,'P. Costo'!$I$61:$I$163),IF($C25="MO",SUMIF('P. Costo'!$A$61:$A$233,$B25,'P. Costo'!$L$61:$L$233),SUMIF('P. Costo'!$A$61:$A$233,$B25,'P. Costo'!$N$61:$N$233))) -> 41278489 | Y25: =IF($C25="MAT",SUMIF('Cert. Pto. 02'!$A$10:$A$194,'Resumen Pto #2'!$B25,'Cert. Pto. 02'!$T$10:$T$194),IF($C25="MO",SUMIF('Cert. Pto. 02'!$A$10:$A$194,$B25,'Cert. Pto. 02'!$U$10:$U$194),SUMIF('Cert. Pto. 02'!$A$10:$A$194,$B25,'Cert. Pto. 02'!$V$10:$V$194)))/IF($C25="MAT",SUMIF('Cert. Pto. 02'!$A$10:$A$194,'Resumen Pto #2'!$B25,'Cert. Pto. 02'!$I$10:$I$194),IF('Resumen Pto #2'!$C25="MO",SUMIF('Cert. Pto. 02'!$A$10:$A$194,$B25,'Cert. Pto. 02'!$J$10:$J$194),SUMIF('Cert. Pto. 02'!$A$10:$A$194,$B25,'Cert. Pto. 02'!$K$10:$K$194))) -> 0.33069101 | Z25: =IF(Y25=100%,0,IF(OR(V25<>0,X25),X25-V25)) -> 23463605 | AA25: =IF(OR(Z25<0,X25),Z25/X25,0%) -> 0.5684221 | AB25: =IF(Y25=100%,IF(OR(G25<>0,X25),X25-G25),0) -> 0
B26: Sanitaria | C26: MAT | D26: =IFERROR(VLOOKUP($B26&$C26,'C. Gestión Pto #2'!$B$4:C$22,MATCH(D$5,'C. Gestión Pto #2'!$B$4:C$4,0),FALSE),0) -> 0 | E26: =IFERROR(VLOOKUP($B26&$C26,'C. Gestión Pto #2'!$B$4:D$22,MATCH(E$5,'C. Gestión Pto #2'!$B$4:D$4,0),FALSE),0) -> 0 | F26: =IFERROR(VLOOKUP($B26&$C26,'C. Gestión Pto #2'!$B$4:E$22,MATCH(F$5,'C. Gestión Pto #2'!$B$4:E$4,0),FALSE),0) -> 0 | G26: =IFERROR(VLOOKUP($B26&$C26,'C. Gestión Pto #2'!$B$4:F$22,MATCH(G$5,'C. Gestión Pto #2'!$B$4:F$4,0),FALSE),0) -> 0 | H26: =IFERROR(VLOOKUP($B26&$C26,'C. Gestión Pto #2'!$B$4:G$22,MATCH(H$5,'C. Gestión Pto #2'!$B$4:G$4,0),FALSE),0) -> 0 | I26: =IFERROR(VLOOKUP($B26&$C26,'C. Gestión Pto #2'!$B$4:H$22,MATCH(I$5,'C. Gestión Pto #2'!$B$4:H$4,0),FALSE),0) -> 0 | J26: =IFERROR(VLOOKUP($B26&$C26,'C. Gestión Pto #2'!$B$4:I$22,MATCH(J$5,'C. Gestión Pto #2'!$B$4:I$4,0),FALSE),0) -> 0 | K26: =IFERROR(VLOOKUP($B26&$C26,'C. Gestión Pto #2'!$B$4:J$22,MATCH(K$5,'C. Gestión Pto #2'!$B$4:J$4,0),FALSE),0) -> 7851.24 | ... P26: =IFERROR(VLOOKUP($B26&$C26,'C. Gestión Pto #2'!$B$4:O$22,MATCH(P$5,'C. Gestión Pto #2'!$B$4:O$4,0),FALSE),0) -> 4296617.5 | Q26: =IFERROR(VLOOKUP($B26&$C26,'C. Gestión Pto #2'!$B$4:Q$22,MATCH(Q$5,'C. Gestión Pto #2'!$B$4:Q$4,0),FALSE),0) -> 1787531.5 | R26: =IFERROR(VLOOKUP($B26&$C26,'C. Gestión Pto #2'!$B$4:R$22,MATCH(R$5,'C. Gestión Pto #2'!$B$4:R$4,0),FALSE),0) -> 675872.13 | S26: =IFERROR(VLOOKUP($B26&$C26,'C. Gestión Pto #2'!$B$4:S$22,MATCH(S$5,'C. Gestión Pto #2'!$B$4:S$4,0),FALSE),0) -> 402485.09 | T26: =IFERROR(VLOOKUP($B26&$C26,'C. Gestión Pto #2'!$B$4:T$22,MATCH(T$5,'C. Gestión Pto #2'!$B$4:T$4,0),FALSE),0) -> 633057 | V26: {=SUMPRODUCT($D26:$U26,TRANSPOSE('Indice CAC'!$D$2:$D$19))} -> 6425159.6 | X26: =IF($C26="MAT",SUMIF('P. Costo'!$A$61:$A$233,$B26,'P. Costo'!$I$61:$I$163),IF($C26="MO",SUMIF('P. Costo'!$A$61:$A$233,$B26,'P. Costo'!$L$61:$L$233),SUMIF('P. Costo'!$A$61:$A$233,$B26,'P. Costo'!$N$61:$N$233))) -> 32568315 | Y26: =IF($C26="MAT",SUMIF('Cert. Pto. 02'!$A$10:$A$194,'Resumen Pto #2'!$B26,'Cert. Pto. 02'!$T$10:$T$194),IF($C26="MO",SUMIF('Cert. Pto. 02'!$A$10:$A$194,$B26,'Cert. Pto. 02'!$U$10:$U$194),SUMIF('Cert. Pto. 02'!$A$10:$A$194,$B26,'Cert. Pto. 02'!$V$10:$V$194)))/IF($C26="MAT",SUMIF('Cert. Pto. 02'!$A$10:$A$194,'Resumen Pto #2'!$B26,'Cert. Pto. 02'!$I$10:$I$194),IF('Resumen Pto #2'!$C26="MO",SUMIF('Cert. Pto. 02'!$A$10:$A$194,$B26,'Cert. Pto. 02'!$J$10:$J$194),SUMIF('Cert. Pto. 02'!$A$10:$A$194,$B26,'Cert. Pto. 02'!$K$10:$K$194))) -> 0.21719598 | Z26: =IF(Y26=100%,0,IF(OR(V26<>0,X26),X26-V26)) -> 26143156 | AA26: =IF(OR(Z26<0,X26),Z26/X26,0%) -> 0.80271747 | AB26: =IF(Y26=100%,IF(OR(G26<>0,X26),X26-G26),0) -> 0
B27: Sanitaria | C27: MO | D27: =IFERROR(VLOOKUP($B27&$C27,'C. Gestión Pto #2'!$B$4:C$22,MATCH(D$5,'C. Gestión Pto #2'!$B$4:C$4,0),FALSE),0) -> 0 | E27: =IFERROR(VLOOKUP($B27&$C27,'C. Gestión Pto #2'!$B$4:D$22,MATCH(E$5,'C. Gestión Pto #2'!$B$4:D$4,0),FALSE),0) -> 0 | F27: =IFERROR(VLOOKUP($B27&$C27,'C. Gestión Pto #2'!$B$4:E$22,MATCH(F$5,'C. Gestión Pto #2'!$B$4:E$4,0),FALSE),0) -> 0 | G27: =IFERROR(VLOOKUP($B27&$C27,'C. Gestión Pto #2'!$B$4:F$22,MATCH(G$5,'C. Gestión Pto #2'!$B$4:F$4,0),FALSE),0) -> 0 | H27: =IFERROR(VLOOKUP($B27&$C27,'C. Gestión Pto #2'!$B$4:G$22,MATCH(H$5,'C. Gestión Pto #2'!$B$4:G$4,0),FALSE),0) -> 0 | I27: =IFERROR(VLOOKUP($B27&$C27,'C. Gestión Pto #2'!$B$4:H$22,MATCH(I$5,'C. Gestión Pto #2'!$B$4:H$4,0),FALSE),0) -> 0 | J27: =IFERROR(VLOOKUP($B27&$C27,'C. Gestión Pto #2'!$B$4:I$22,MATCH(J$5,'C. Gestión Pto #2'!$B$4:I$4,0),FALSE),0) -> 0 | K27: =IFERROR(VLOOKUP($B27&$C27,'C. Gestión Pto #2'!$B$4:J$22,MATCH(K$5,'C. Gestión Pto #2'!$B$4:J$4,0),FALSE),0) -> 0 | ... P27: =IFERROR(VLOOKUP($B27&$C27,'C. Gestión Pto #2'!$B$4:O$22,MATCH(P$5,'C. Gestión Pto #2'!$B$4:O$4,0),FALSE),0) -> 3912286.3 | Q27: =IFERROR(VLOOKUP($B27&$C27,'C. Gestión Pto #2'!$B$4:Q$22,MATCH(Q$5,'C. Gestión Pto #2'!$B$4:Q$4,0),FALSE),0) -> 4566137.9 | R27: =IFERROR(VLOOKUP($B27&$C27,'C. Gestión Pto #2'!$B$4:R$22,MATCH(R$5,'C. Gestión Pto #2'!$B$4:R$4,0),FALSE),0) -> 4327360.8 | S27: =IFERROR(VLOOKUP($B27&$C27,'C. Gestión Pto #2'!$B$4:S$22,MATCH(S$5,'C. Gestión Pto #2'!$B$4:S$4,0),FALSE),0) -> 6427831.2 | T27: =IFERROR(VLOOKUP($B27&$C27,'C. Gestión Pto #2'!$B$4:T$22,MATCH(T$5,'C. Gestión Pto #2'!$B$4:T$4,0),FALSE),0) -> 0 | V27: {=SUMPRODUCT($D27:$U27,TRANSPOSE('Indice CAC'!$D$2:$D$19))} -> 16085672 | X27: =IF($C27="MAT",SUMIF('P. Costo'!$A$61:$A$233,$B27,'P. Costo'!$I$61:$I$163),IF($C27="MO",SUMIF('P. Costo'!$A$61:$A$233,$B27,'P. Costo'!$L$61:$L$233),SUMIF('P. Costo'!$A$61:$A$233,$B27,'P. Costo'!$N$61:$N$233))) -> 75115078 | Y27: =IF($C27="MAT",SUMIF('Cert. Pto. 02'!$A$10:$A$194,'Resumen Pto #2'!$B27,'Cert. Pto. 02'!$T$10:$T$194),IF($C27="MO",SUMIF('Cert. Pto. 02'!$A$10:$A$194,$B27,'Cert. Pto. 02'!$U$10:$U$194),SUMIF('Cert. Pto. 02'!$A$10:$A$194,$B27,'Cert. Pto. 02'!$V$10:$V$194)))/IF($C27="MAT",SUMIF('Cert. Pto. 02'!$A$10:$A$194,'Resumen Pto #2'!$B27,'Cert. Pto. 02'!$I$10:$I$194),IF('Resumen Pto #2'!$C27="MO",SUMIF('Cert. Pto. 02'!$A$10:$A$194,$B27,'Cert. Pto. 02'!$J$10:$J$194),SUMIF('Cert. Pto. 02'!$A$10:$A$194,$B27,'Cert. Pto. 02'!$K$10:$K$194))) -> 0.25606992 | Z27: =IF(Y27=100%,0,IF(OR(V27<>0,X27),X27-V27)) -> 59029405 | AA27: =IF(OR(Z27<0,X27),Z27/X27,0%) -> 0.78585295 | AB27: =IF(Y27=100%,IF(OR(G27<>0,X27),X27-G27),0) -> 0
B28: Equipos | D28: =IFERROR(VLOOKUP($B28&$C28,'C. Gestión Pto #2'!$B$4:C$22,MATCH(D$5,'C. Gestión Pto #2'!$B$4:C$4,0),FALSE),0) -> 0 | E28: =IFERROR(VLOOKUP($B28&$C28,'C. Gestión Pto #2'!$B$4:D$22,MATCH(E$5,'C. Gestión Pto #2'!$B$4:D$4,0),FALSE),0) -> 0 | F28: =IFERROR(VLOOKUP($B28&$C28,'C. Gestión Pto #2'!$B$4:E$22,MATCH(F$5,'C. Gestión Pto #2'!$B$4:E$4,0),FALSE),0) -> 0 | G28: =IFERROR(VLOOKUP($B28&$C28,'C. Gestión Pto #2'!$B$4:F$22,MATCH(G$5,'C. Gestión Pto #2'!$B$4:F$4,0),FALSE),0) -> 0 | H28: =IFERROR(VLOOKUP($B28&$C28,'C. Gestión Pto #2'!$B$4:G$22,MATCH(H$5,'C. Gestión Pto #2'!$B$4:G$4,0),FALSE),0) -> 0 | I28: =IFERROR(VLOOKUP($B28&$C28,'C. Gestión Pto #2'!$B$4:H$22,MATCH(I$5,'C. Gestión Pto #2'!$B$4:H$4,0),FALSE),0) -> 0 | J28: =IFERROR(VLOOKUP($B28&$C28,'C. Gestión Pto #2'!$B$4:I$22,MATCH(J$5,'C. Gestión Pto #2'!$B$4:I$4,0),FALSE),0) -> 0 | K28: =IFERROR(VLOOKUP($B28&$C28,'C. Gestión Pto #2'!$B$4:J$22,MATCH(K$5,'C. Gestión Pto #2'!$B$4:J$4,0),FALSE),0) -> 0 | ... P28: =IFERROR(VLOOKUP($B28&$C28,'C. Gestión Pto #2'!$B$4:O$22,MATCH(P$5,'C. Gestión Pto #2'!$B$4:O$4,0),FALSE),0) -> 711547.44 | Q28: =IFERROR(VLOOKUP($B28&$C28,'C. Gestión Pto #2'!$B$4:Q$22,MATCH(Q$5,'C. Gestión Pto #2'!$B$4:Q$4,0),FALSE),0) -> 737537.19 | R28: =IFERROR(VLOOKUP($B28&$C28,'C. Gestión Pto #2'!$B$4:R$22,MATCH(R$5,'C. Gestión Pto #2'!$B$4:R$4,0),FALSE),0) -> 761316.76 | S28: =IFERROR(VLOOKUP($B28&$C28,'C. Gestión Pto #2'!$B$4:S$22,MATCH(S$5,'C. Gestión Pto #2'!$B$4:S$4,0),FALSE),0) -> 787253.61 | T28: =IFERROR(VLOOKUP($B28&$C28,'C. Gestión Pto #2'!$B$4:T$22,MATCH(T$5,'C. Gestión Pto #2'!$B$4:T$4,0),FALSE),0) -> 0 | V28: {=SUMPRODUCT($D28:$U28,TRANSPOSE('Indice CAC'!$D$2:$D$19))} -> 3004359 | X28: =IF($C28="MAT",SUMIF('P. Costo'!$A$61:$A$233,$B28,'P. Costo'!$I$61:$I$163),IF($C28="MO",SUMIF('P. Costo'!$A$61:$A$233,$B28,'P. Costo'!$L$61:$L$233),SUM('P. Costo'!M164,'P. Costo'!M234,'P. Costo'!M19:M27))) -> 7890286.6 | Y28: ='Cert. Pto. 02'!S196 -> 0.32656513 | Z28: =IF(Y28=100%,0,IF(OR(V28<>0,X28),X28-V28)) -> 4885927.6 | AA28: =IF(OR(Z28<0,X28),Z28/X28,0%) -> 0.61923322 | AB28: =IF(Y28=100%,IF(OR(G28<>0,X28),X28-G28),0) -> 0
B29: Total Egresos de Obra | D29: =SUM(D13:D28) -> 2128206 | E29: =SUM(E13:E28) -> 2823867.6 | F29: =SUM(F13:F28) -> 3646478.5 | G29: =SUM(G13:G28) -> 7828840.7 | H29: =SUM(H13:H28) -> 6869318.9 | I29: =SUM(I13:I28) -> 8575533.3 | J29: =SUM(J13:J28) -> 10802908 | K29: =SUM(K13:K28) -> 12083704 | ... T29: =SUM(T13:T28) -> 8523877.9 | V29: =SUM(V13:V28) -> 2.9163328e+08 | X29: =SUM(X13:X28) -> 6.2947919e+08 | Z29: =IF(Y29=100%,0,IF(OR(V29<>0,X29),X29-V29)) -> 3.3784591e+08 | AA29: =IF(OR(Z29<0,X29),Z29/X29,0%) -> 0.53670704 | AB29: =SUM(AB16:AB28) -> 0
B31: Gastos Generales
B32: Gastos Directos | D32: =VLOOKUP($B32,'C. Gestión Pto #2'!$B$40:L$40,MATCH('Resumen Pto #2'!D$5,'C. Gestión Pto #2'!$B$26:L$26,0),0) -> 0 | E32: =VLOOKUP($B32,'C. Gestión Pto #2'!$B$40:M$40,MATCH('Resumen Pto #2'!E$5,'C. Gestión Pto #2'!$B$26:M$26,0),0) -> 0 | F32: =VLOOKUP($B32,'C. Gestión Pto #2'!$B$40:N$40,MATCH('Resumen Pto #2'!F$5,'C. Gestión Pto #2'!$B$26:N$26,0),0) -> 0 | G32: =VLOOKUP($B32,'C. Gestión Pto #2'!$B$40:N$40,MATCH('Resumen Pto #2'!G$5,'C. Gestión Pto #2'!$B$26:N$26,0),0) -> 0 | H32: =VLOOKUP($B32,'C. Gestión Pto #2'!$B$40:N$40,MATCH('Resumen Pto #2'!H$5,'C. Gestión Pto #2'!$B$26:N$26,0),0) -> 0 | I32: =VLOOKUP($B32,'C. Gestión Pto #2'!$B$40:O$40,MATCH('Resumen Pto #2'!I$5,'C. Gestión Pto #2'!$B$26:O$26,0),0) -> 0 | J32: =VLOOKUP($B32,'C. Gestión Pto #2'!$B$40:Q$40,MATCH('Resumen Pto #2'!J$5,'C. Gestión Pto #2'!$B$26:Q$26,0),0) -> 0 | K32: =VLOOKUP($B32,'C. Gestión Pto #2'!$B$40:R$40,MATCH('Resumen Pto #2'!K$5,'C. Gestión Pto #2'!$B$26:R$26,0),0) -> 0 | L32: =VLOOKUP($B32,'C. Gestión Pto #2'!$B$40:S$40,MATCH('Resumen Pto #2'!L$5,'C. Gestión Pto #2'!$B$26:S$26,0),0) -> 0 | M32: =VLOOKUP($B32,'C. Gestión Pto #2'!$B$40:T$40,MATCH('Resumen Pto #2'!M$5,'C. Gestión Pto #2'!$B$26:T$26,0),0) -> 0 | N32: =VLOOKUP($B32,'C. Gestión Pto #2'!$B$40:U$40,MATCH('Resumen Pto #2'!N$5,'C. Gestión Pto #2'!$B$26:U$26,0),0) -> 0 | O32: =VLOOKUP($B32,'C. Gestión Pto #2'!$B$40:V$40,MATCH('Resumen Pto #2'!O$5,'C. Gestión Pto #2'!$B$26:V$26,0),0) -> 2897224.5 | P32: =VLOOKUP($B32,'C. Gestión Pto #2'!$B$40:W$40,MATCH('Resumen Pto #2'!P$5,'C. Gestión Pto #2'!$B$26:W$26,0),0) -> 4034621.5 | Q32: =VLOOKUP($B32,'C. Gestión Pto #2'!$B$40:X$40,MATCH('Resumen Pto #2'!Q$5,'C. Gestión Pto #2'!$B$26:X$26,0),0) -> 2054329.6 | ... T32: =VLOOKUP($B32,'C. Gestión Pto #2'!$B$40:AA$40,MATCH('Resumen Pto #2'!T$5,'C. Gestión Pto #2'!$B$26:AA$26,0),0) -> 0 | V32: {=SUMPRODUCT($D32:$U32,TRANSPOSE('Indice CAC'!$D$2:$D$19))} -> 10994202 | X32: =SUM(GGBB!H6:H32)/17*6 -> 32809381 | Y32: 0 | Z32: =IF(Y32=100%,0,IF(OR(V32<>0,X32),X32-V32)) -> 21815179 | AA32: =IF(OR(Z32<0,X32),Z32/X32,0%) -> 0.66490677 | AB32: =IF(Y32=100%,IF(OR(G32<>0,X32),X32-G32),0) -> 0
B33: Gastos Indirectos | D33: =VLOOKUP($B33,'C. Gestión Pto #2'!$B$46:L$46,MATCH('Resumen Pto #2'!D$5,'C. Gestión Pto #2'!$B$42:L$42,0),0) -> 0 | E33: =VLOOKUP($B33,'C. Gestión Pto #2'!$B$46:M$46,MATCH('Resumen Pto #2'!E$5,'C. Gestión Pto #2'!$B$42:M$42,0),0) -> 0 | F33: =VLOOKUP($B33,'C. Gestión Pto #2'!$B$46:N$46,MATCH('Resumen Pto #2'!F$5,'C. Gestión Pto #2'!$B$42:N$42,0),0) -> 0 | G33: =VLOOKUP($B33,'C. Gestión Pto #2'!$B$46:N$46,MATCH('Resumen Pto #2'!G$5,'C. Gestión Pto #2'!$B$42:N$42,0),0) -> 0 | H33: =VLOOKUP($B33,'C. Gestión Pto #2'!$B$46:N$46,MATCH('Resumen Pto #2'!H$5,'C. Gestión Pto #2'!$B$42:N$42,0),0) -> 0 | I33: =VLOOKUP($B33,'C. Gestión Pto #2'!$B$46:O$46,MATCH('Resumen Pto #2'!I$5,'C. Gestión Pto #2'!$B$42:O$42,0),0) -> 0 | J33: =VLOOKUP($B33,'C. Gestión Pto #2'!$B$46:Q$46,MATCH('Resumen Pto #2'!J$5,'C. Gestión Pto #2'!$B$42:Q$42,0),0) -> 0 | K33: =VLOOKUP($B33,'C. Gestión Pto #2'!$B$46:R$46,MATCH('Resumen Pto #2'!K$5,'C. Gestión Pto #2'!$B$42:R$42,0),0) -> 0 | L33: =VLOOKUP($B33,'C. Gestión Pto #2'!$B$46:S$46,MATCH('Resumen Pto #2'!L$5,'C. Gestión Pto #2'!$B$42:S$42,0),0) -> 0 | M33: =VLOOKUP($B33,'C. Gestión Pto #2'!$B$46:T$46,MATCH('Resumen Pto #2'!M$5,'C. Gestión Pto #2'!$B$42:T$42,0),0) -> 0 | N33: =VLOOKUP($B33,'C. Gestión Pto #2'!$B$46:U$46,MATCH('Resumen Pto #2'!N$5,'C. Gestión Pto #2'!$B$42:U$42,0),0) -> 0 | O33: =VLOOKUP($B33,'C. Gestión Pto #2'!$B$46:V$46,MATCH('Resumen Pto #2'!O$5,'C. Gestión Pto #2'!$B$42:V$42,0),0) -> 2992482.4 | P33: =VLOOKUP($B33,'C. Gestión Pto #2'!$B$46:W$46,MATCH('Resumen Pto #2'!P$5,'C. Gestión Pto #2'!$B$42:W$42,0),0) -> 4350156.4 | Q33: =VLOOKUP($B33,'C. Gestión Pto #2'!$B$46:X$46,MATCH('Resumen Pto #2'!Q$5,'C. Gestión Pto #2'!$B$42:X$42,0),0) -> 3484073.8 | ... T33: =VLOOKUP($B33,'C. Gestión Pto #2'!$B$46:AA$46,MATCH('Resumen Pto #2'!T$5,'C. Gestión Pto #2'!$B$42:AA$42,0),0) -> 0 | V33: {=SUMPRODUCT($D33:$U33,TRANSPOSE('Indice CAC'!$D$2:$D$19))} -> 14327115 | X33: =SUM(GGBB!H42:H48)/17*6 -> 29207081 | Y33: 0 | Z33: =IF(Y33=100%,0,IF(OR(V33<>0,X33),X33-V33)) -> 14879966 | AA33: =IF(OR(Z33<0,X33),Z33/X33,0%) -> 0.50946433 | AB33: =IF(Y33=100%,IF(OR(G33<>0,X33),X33-G33),0) -> 0
B34: Total Gastos Generales | D34: =SUM(D32:D33) -> 0 | E34: =SUM(E32:E33) -> 0 | F34: =SUM(F32:F33) -> 0 | G34: =SUM(G32:G33) -> 0 | H34: =SUM(H32:H33) -> 0 | I34: =SUM(I32:I33) -> 0 | J34: =SUM(J32:J33) -> 0 | K34: =SUM(K32:K33) -> 0 | ... T34: =SUM(T32:T33) -> 0 | V34: =SUM(V32:V33) -> 25321316 | X34: =SUM(X32:X33) -> 62016462 | Z34: =IF(Y34=100%,0,IF(OR(V34<>0,X34),X34-V34)) -> 36695145 | AA34: =IF(OR(Z34<0,X34),Z34/X34,0%) -> 0.59170008 | AB34: =SUM(AB32:AB33) -> 0
B36: Total Egresos | D36: =D29+D34 -> 2128206 | E36: =E29+E34 -> 2823867.6 | F36: =F29+F34 -> 3646478.5 | G36: =G29+G34 -> 7828840.7 | H36: =H29+H34 -> 6869318.9 | I36: =I29+I34 -> 8575533.3 | J36: =J29+J34 -> 10802908 | K36: =K29+K34 -> 12083704 | ... T36: =T29+T34 -> 8523877.9 | V36: =V29+V34 -> 3.1695459e+08 | X36: =X29+X34 -> 6.9149565e+08
B38: Resultado Operativo | D38: =SUM(D8,D10,-D36) -> -2128206 | E38: =SUM(E8,E10,-E36) -> -2823867.6 | F38: =SUM(F8,F10,-F36) -> 83566832 | G38: =SUM(G8,G10,-G36) -> 442765.64 | H38: =SUM(H8,H10,-H36) -> 1310688.1 | I38: =SUM(I8,I10,-I36) -> 911385.17 | J38: =SUM(J8,J10,-J36) -> -1936355 | K38: =SUM(K8,K10,-K36) -> -467729.66 | ... T38: =SUM(T8,T10,-T36) -> -8523877.9 | V38: =SUM(V8,-V36) -> 15837230 | X38: =SUM(X8,-X36) -> 1.533496e+08
B39: Resultado Acumulado | D39: =D38 -> -2128206 | E39: =E38+D39 -> -4952073.6 | F39: =F38+E39 -> 78614758 | G39: =G38+F39 -> 79057524 | H39: =H38+G39 -> 80368212 | I39: =I38+H39 -> 81279597 | J39: =J38+I39 -> 79343242 | K39: =K38+J39 -> 78875513 | L39: =L38+K39 -> 77897140 | ... T39: =T38+S39 -> 5188154.9

Sheet Cert. Pto. 01
K1: DÓLAR BNA | L1: DÓLAR MEP
K2: 1066.5 | L2: 1170
K4: 45667 | N4: Certificado | O4: 9 | S4: 45988
C5: OBRA: EDIFICIO GDR 3760
C6: PRESUPUESTO OBRA CIVIL 01 | N6: Avance | Q6: Importe | T6: Importe
C7: Descripción | D7: U | E7: Cant | F7: Materiales | G7: Mano de Obra | H7: P unit | I7: Materiales | J7: Mano de obra | K7: Subtotal | N7: Anterior | O7: Actual | P7: Acumulado | Q7: Anterior | R7: Actual | S7: Acumulado | T7: Material | U7: Mano de Obra | V7: Total
B8: 1 | C8: TAREAS PRELIMINARES | L8: =SUM(K9:K17) -> 19888202 | M8: =+L8/$L$46 -> 0.039704323
B9: 1.01 | C9: Limpieza y preparación del terreno - No cotiza | D9: gl | E9: 1 | F9: ='01 (2)'!H9*'01 (2)'!$T$5 -> 0 | G9: =H9-F9 -> 0 | H9: 0 | I9: =E9*F9 -> 0 | J9: =E9*G9 -> 0 | K9: =E9*H9 -> 0 | N9: 0 | P9: =SUM(N9:O9) -> 0 | Q9: =K9*N9 -> 0 | R9: =K9*O9 -> 0 | S9: =K9*P9 -> 0 | T9: =I9*P9 -> 0 | U9: =J9*P9 -> 0 | V9: =SUM(T9:U9) -> 0
A10: Agrimensura | B10: 1.02 | C10: Topógrafo - Visita de obra replanteo | D10: gl | E10: 3 | F10: ='01 (2)'!H10*'01 (2)'!$T$5 -> 33318.186 | G10: =H10-F10 -> 351662.81 | H10: 384981 | I10: =E10*F10 -> 99954.557 | J10: =E10*G10 -> 1054988.4 | K10: =E10*H10 -> 1154943 | N10: 0.33 | O10: 0.67 | P10: =SUM(N10:O10) -> 1 | Q10: =K10*N10 -> 381131.19 | R10: =K10*O10 -> 773811.81 | S10: =K10*P10 -> 1154943 | T10: =I10*P10 -> 99954.557 | U10: =J10*P10 -> 1054988.4 | V10: =SUM(T10:U10) -> 1154943
B11: 1.03 | C11: Cartel de Obra - No cotiza | D11: gl | E11: 1 | F11: ='01 (2)'!H11*'01 (2)'!$T$5 -> 0 | G11: =H11-F11 -> 0 | H11: 0 | I11: =E11*F11 -> 0 | J11: =E11*G11 -> 0 | K11: =E11*H11 -> 0 | N11: 0 | P11: =SUM(N11:O11) -> 0 | Q11: =K11*N11 -> 0 | R11: =K11*O11 -> 0 | S11: =K11*P11 -> 0 | T11: =I11*P11 -> 0 | U11: =J11*P11 -> 0 | V11: =SUM(T11:U11) -> 0
A12: Preliminares | B12: 1.04 | C12: Cerco de obra perimetral - En chapa C25 + Concertina + Porton corredizo | D12: ml | E12: 10 | F12: ='01 (2)'!H12*'01 (2)'!$T$5 -> 117720.75 | G12: =H12-F12 -> 139276.25 | H12: 256997 | I12: =E12*F12 -> 1177207.5 | J12: =E12*G12 -> 1392762.5 | K12: =E12*H12 -> 2569970 | N12: 0.75 | O12: 0.25 | P12: =SUM(N12:O12) -> 1 | Q12: =K12*N12 -> 1927477.5 | R12: =K12*O12 -> 642492.5 | S12: =K12*P12 -> 2569970 | T12: =I12*P12 -> 1177207.5 | U12: =J12*P12 -> 1392762.5 | V12: =SUM(T12:U12) -> 2569970
A13: Preliminares | B13: 1.05 | C13: Obrador, pañol y ducha. | D13: gl | E13: 1 | F13: ='01 (2)'!H13*'01 (2)'!$T$5 -> 2770506.7 | G13: =H13-F13 -> 7041825.3 | H13: 9812332 | I13: =E13*F13 -> 2770506.7 | J13: =E13*G13 -> 7041825.3 | K13: =E13*H13 -> 9812332 | N13: 0.85 | O13: 0.15 | P13: =SUM(N13:O13) -> 1 | Q13: =K13*N13 -> 8340482.2 | R13: =K13*O13 -> 1471849.8 | S13: =K13*P13 -> 9812332 | T13: =I13*P13 -> 2770506.7 | U13: =J13*P13 -> 7041825.3 | V13: =SUM(T13:U13) -> 9812332
A14: Gastos Generales Obra | B14: 1.06 | C14: Alquiler de baños quimicos y duchas portatiles | D14: mes | E14: 4 | F14: ='01 (2)'!H14*'01 (2)'!$T$5 -> 0 | G14: =H14-F14 -> 442847 | H14: 442847 | I14: =E14*F14 -> 0 | J14: =E14*G14 -> 1771388 | K14: =E14*H14 -> 1771388 | N14: 1 | P14: =SUM(N14:O14) -> 1 | Q14: =K14*N14 -> 1771388 | R14: =K14*O14 -> 0 | S14: =K14*P14 -> 1771388 | T14: =I14*P14 -> 0 | U14: =J14*P14 -> 1771388 | V14: =SUM(T14:U14) -> 1771388
A15: Preliminares | B15: 1.07 | C15: Conexión pilar y luz de obra + Tablero de obra | D15: gl | E15: 1 | F15: ='01 (2)'!H15*'01 (2)'!$T$5 -> 1452672.9 | G15: =H15-F15 -> 835309.1 | H15: 2287982 | I15: =E15*F15 -> 1452672.9 | J15: =E15*G15 -> 835309.1 | K15: =E15*H15 -> 2287982 | N15: 0.8 | O15: 0.2 | P15: =SUM(N15:O15) -> 1 | Q15: =K15*N15 -> 1830385.6 | R15: =K15*O15 -> 457596.4 | S15: =K15*P15 -> 2287982 | T15: =I15*P15 -> 1452672.9 | U15: =J15*P15 -> 835309.1 | V15: =SUM(T15:U15) -> 2287982
A16: Preliminares | B16: 1.08 | C16: Conexión agua de obra, tanque + bomba | D16: gl | E16: 1 | F16: ='01 (2)'!H16*'01 (2)'!$T$5 -> 913184.83 | G16: =H16-F16 -> 895033.17 | H16: 1808218 | I16: =E16*F16 -> 913184.83 | J16: =E16*G16 -> 895033.17 | K16: =E16*H16 -> 1808218 | N16: 0.2 | O16: 0.8 | P16: =SUM(N16:O16) -> 1 | Q16: =K16*N16 -> 361643.6 | R16: =K16*O16 -> 1446574.4 | S16: =K16*P16 -> 1808218 | T16: =I16*P16 -> 913184.83 | U16: =J16*P16 -> 895033.17 | V16: =SUM(T16:U16) -> 1808218
A17: Preliminares | B17: 1.09 | C17: Tramite luz de obra, certificado luz de obra (2) y medición PAT | D17: gl | E17: 1 | F17: ='01 (2)'!H17*'01 (2)'!$T$5 -> 0 | G17: =H17-F17 -> 483369 | H17: 483369 | I17: =E17*F17 -> 0 | J17: =E17*G17 -> 483369 | K17: =E17*H17 -> 483369 | N17: 0.7 | O17: 0.3 | P17: =SUM(N17:O17) -> 1 | Q17: =K17*N17 -> 338358.3 | R17: =K17*O17 -> 145010.7 | S17: =K17*P17 -> 483369 | T17: =I17*P17 -> 0 | U17: =J17*P17 -> 483369 | V17: =SUM(T17:U17) -> 483369
B18: 2 | C18: MOVIMIENTO DE TIERRA, COMPACTACION Y RELLENO | L18: =SUM(K19:K23) -> 29649894 | M18: =+L18/$L$46 -> 0.059192328
A19: Excavación y Mov. de Suelos | B19: 2.01 | C19: Excavación a maquina para submuración, subsuelo y fundaciones | D19: m3 | E19: 308 | F19: ='01 (2)'!H19*'01 (2)'!$T$5 -> 0 | G19: =H19-F19 -> 52801 | H19: 52801 | I19: =$E19*F19 -> 0 | J19: =$E19*G19 -> 16262708 | K19: =+H19*E19 -> 16262708 | N19: 1 | P19: =SUM(N19:O19) -> 1 | Q19: =K19*N19 -> 16262708 | R19: =K19*O19 -> 0 | S19: =K19*P19 -> 16262708 | T19: =I19*P19 -> 0 | U19: =J19*P19 -> 16262708 | V19: =SUM(T19:U19) -> 16262708
A20: Excavación y Mov. de Suelos | B20: 2.02 | C20: Perfilado manual de bases. Relleno y compactación de pozos | D20: gl | E20: 1 | F20: ='01 (2)'!H20*'01 (2)'!$T$5 -> 139936.38 | G20: =H20-F20 -> 11484780 | H20: 11624716 | I20: =$E20*F20 -> 139936.38 | J20: =$E20*G20 -> 11484780 | K20: =+H20*E20 -> 11624716 | N20: 1 | P20: =SUM(N20:O20) -> 1 | Q20: =K20*N20 -> 11624716 | R20: =K20*O20 -> 0 | S20: =K20*P20 -> 11624716 | T20: =I20*P20 -> 139936.38 | U20: =J20*P20 -> 11484780 | V20: =SUM(T20:U20) -> 11624716
A21: Excavación y Mov. de Suelos | B21: 2.03 | C21: Excavación manual para vigas de fundación | D21: m3 | E21: 15 | F21: ='01 (2)'!H21*'01 (2)'!$T$5 -> 34650.913 | G21: =H21-F21 -> 82847.087 | H21: 117498 | I21: =$E21*F21 -> 519763.7 | J21: =$E21*G21 -> 1242706.3 | K21: =+H21*E21 -> 1762470 | N21: 1 | P21: =SUM(N21:O21) -> 1 | Q21: =K21*N21 -> 1762470 | R21: =K21*O21 -> 0 | S21: =K21*P21 -> 1762470 | T21: =I21*P21 -> 519763.7 | U21: =J21*P21 -> 1242706.3 | V21: =SUM(T21:U21) -> 1762470
B22: 2.04 | C22: Aporte y compactación de suelo seleccionado, e: 40 cm (2 capas de 20 cm) - Cotizado Hº Pobre en item 8,02 | D22: m2 | E22: 0 | F22: ='01 (2)'!H22*'01 (2)'!$T$5 -> 0 | G22: =H22-F22 -> 28536 | H22: 28536 | I22: =$E22*F22 -> 0 | J22: =$E22*G22 -> 0 | K22: =+H22*E22 -> 0 | N22: 0 | P22: =SUM(N22:O22) -> 0 | Q22: =K22*N22 -> 0 | R22: =K22*O22 -> 0 | S22: =K22*P22 -> 0 | T22: =I22*P22 -> 0 | U22: =J22*P22 -> 0 | V22: =SUM(T22:U22) -> 0
B23: 2.05 | C23: Demolición de bases existentes - No cotiza | D23: gl | E23: 0 | F23: ='01 (2)'!H23*'01 (2)'!$T$5 -> 0 | G23: =H23-F23 -> 0 | H23: 0 | I23: =$E23*F23 -> 0 | J23: =$E23*G23 -> 0 | K23: =+H23*E23 -> 0 | N23: 0 | P23: =SUM(N23:O23) -> 0 | Q23: =K23*N23 -> 0 | R23: =K23*O23 -> 0 | S23: =K23*P23 -> 0 | T23: =I23*P23 -> 0 | U23: =J23*P23 -> 0 | V23: =SUM(T23:U23) -> 0
B24: 3 | C24: ESTRUCTURA RESISTENTE | L24: =SUM(K25:K45) -> 451369624 | M24: =+L24/$L$46 -> 0.90110335
A25: Hormigón | B25: 3.01 | C25: Hormigón de limpieza - e: 10 cm | D25: m3 | E25: 13 | F25: ='01 (2)'!H25*'01 (2)'!$T$5 -> 153396.93 | G25: =H25-F25 -> 139742.07 | H25: 293139 | I25: =$E25*F25 -> 1994160 | J25: =$E25*G25 -> 1816647 | K25: =+H25*E25 -> 3810807 | N25: 1 | P25: =SUM(N25:O25) -> 1 | Q25: =K25*N25 -> 3810807 | R25: =K25*O25 -> 0 | S25: =K25*P25 -> 3810807 | T25: =I25*P25 -> 1994160 | U25: =J25*P25 -> 1816647 | V25: =SUM(T25:U25) -> 3810807
A26: Hormigón | B26: 3.02 | C26: Pilotes de tracción Ø 20 cm - (120 kg/m3 de hierro) | D26: u | E26: 18 | F26: ='01 (2)'!H26*'01 (2)'!$T$5 -> 120706.18 | G26: =H26-F26 -> 339990.82 | H26: 460697 | I26: =$E26*F26 -> 2172711.3 | J26: =$E26*G26 -> 6119834.7 | K26: =+H26*E26 -> 8292546 | N26: 1 | P26: =SUM(N26:O26) -> 1 | Q26: =K26*N26 -> 8292546 | R26: =K26*O26 -> 0 | S26: =K26*P26 -> 8292546 | T26: =I26*P26 -> 2172711.3 | U26: =J26*P26 -> 6119834.7 | V26: =SUM(T26:U26) -> 8292546
A27: Hormigón | B27: 3.03 | C27: Tabique submuración - H35 (95 kg/m3 de hierro) | D27: m3 | E27: 12 | F27: ='01 (2)'!H27*'01 (2)'!$T$5 -> 535853.1 | G27: =H27-F27 -> 491825.9 | H27: 1027679 | I27: =$E27*F27 -> 6430237.2 | J27: =$E27*G27 -> 5901910.8 | K27: =+H27*E27 -> 12332148 | N27: 1 | P27: =SUM(N27:O27) -> 1 | Q27: =K27*N27 -> 12332148 | R27: =K27*O27 -> 0 | S27: =K27*P27 -> 12332148 | T27: =I27*P27 -> 6430237.2 | U27: =J27*P27 -> 5901910.8 | V27: =SUM(T27:U27) -> 12332148
A28: Hormigón | B28: 3.04 | C28: Zapata corrida tabique - H35 (120 kg/m3 de hierro) | D28: m3 | E28: 7 | F28: ='01 (2)'!H28*'01 (2)'!$T$5 -> 570669.33 | G28: =H28-F28 -> 389531.67 | H28: 960201 | I28: =$E28*F28 -> 3994685.3 | J28: =$E28*G28 -> 2726721.7 | K28: =+H28*E28 -> 6721407 | N28: 1 | P28: =SUM(N28:O28) -> 1 | Q28: =K28*N28 -> 6721407 | R28: =K28*O28 -> 0 | S28: =K28*P28 -> 6721407 | T28: =I28*P28 -> 3994685.3 | U28: =J28*P28 -> 2726721.7 | V28: =SUM(T28:U28) -> 6721407
A29: Hormigón | B29: 3.05 | C29: Platea - H35 (95 kg/m3 de hierro) | D29: m3 | E29: 38 | F29: ='01 (2)'!H29*'01 (2)'!$T$5 -> 444731.82 | G29: =H29-F29 -> 269542.18 | H29: 714274 | I29: =$E29*F29 -> 16899809 | J29: =$E29*G29 -> 10242603 | K29: =+H29*E29 -> 27142412 | N29: 1 | P29: =SUM(N29:O29) -> 1 | Q29: =K29*N29 -> 27142412 | R29: =K29*O29 -> 0 | S29: =K29*P29 -> 27142412 | T29: =I29*P29 -> 16899809 | U29: =J29*P29 -> 10242603 | V29: =SUM(T29:U29) -> 27142412
A30: Hormigón | B30: 3.06 | C30: Bases aisladas - (60 kg/m3 de hierro) | D30: m3 | E30: 51 | F30: ='01 (2)'!H30*'01 (2)'!$T$5 -> 366556.52 | G30: =H30-F30 -> 268369.48 | H30: 634926 | I30: =$E30*F30 -> 18694383 | J30: =$E30*G30 -> 13686843 | K30: =+H30*E30 -> 32381226 | N30: 1 | P30: =SUM(N30:O30) -> 1 | Q30: =K30*N30 -> 32381226 | R30: =K30*O30 -> 0 | S30: =K30*P30 -> 32381226 | T30: =I30*P30 -> 18694383 | U30: =J30*P30 -> 13686843 | V30: =SUM(T30:U30) -> 32381226
A31: Hormigón | B31: 3.07 | C31: Troncos de columnas - H35 (240 kg/m3 de hierro) | D31: m3 | E31: 16 | F31: ='01 (2)'!H31*'01 (2)'!$T$5 -> 846538.76 | G31: =H31-F31 -> 442746.24 | H31: 1289285 | I31: =$E31*F31 -> 13544620 | J31: =$E31*G31 -> 7083939.9 | K31: =+H31*E31 -> 20628560 | N31: 1 | P31: =SUM(N31:O31) -> 1 | Q31: =K31*N31 -> 20628560 | R31: =K31*O31 -> 0 | S31: =K31*P31 -> 20628560 | T31: =I31*P31 -> 13544620 | U31: =J31*P31 -> 7083939.9 | V31: =SUM(T31:U31) -> 20628560
A32: Hormigón | B32: 3.08 | C32: Viga de encadenado - H35 (180 kg/m3 de hierro) | D32: m3 | E32: 7 | F32: ='01 (2)'!H32*'01 (2)'!$T$5 -> 704684.12 | G32: =H32-F32 -> 391541.88 | H32: 1096226 | I32: =$E32*F32 -> 4932788.8 | J32: =$E32*G32 -> 2740793.2 | K32: =+H32*E32 -> 7673582 | N32: 1 | P32: =SUM(N32:O32) -> 1 | Q32: =K32*N32 -> 7673582 | R32: =K32*O32 -> 0 | S32: =K32*P32 -> 7673582 | T32: =I32*P32 -> 4932788.8 | U32: =J32*P32 -> 2740793.2 | V32: =SUM(T32:U32) -> 7673582
A33: Hormigón | B33: 3.09 | C33: Losa maciza - H35 (100 kg/m3 de hierro) | D33: m3 | E33: 90 | F33: ='01 (2)'!H33*'01 (2)'!$T$5 -> 496553.36 | G33: =H33-F33 -> 307469.64 | H33: 804023 | I33: =$E33*F33 -> 44689802 | J33: =$E33*G33 -> 27672268 | K33: =+H33*E33 -> 72362070 | N33: 0.1333 | O33: 0.8667 | P33: =SUM(N33:O33) -> 1 | Q33: =K33*N33 -> 9645863.9 | R33: =K33*O33 -> 62716206 | S33: =K33*P33 -> 72362070 | T33: =I33*P33 -> 44689802 | U33: =J33*P33 -> 27672268 | V33: =SUM(T33:U33) -> 72362070
A34: Hormigón | B34: 3.1 | C34: Losa maciza de Hº visto - H35 (100 kg/m3 de hierro) | D34: m3 | E34: 32 | F34: ='01 (2)'!H34*'01 (2)'!$T$5 -> 506115.01 | G34: =H34-F34 -> 382617.99 | H34: 888733 | I34: =$E34*F34 -> 16195680 | J34: =$E34*G34 -> 12243776 | K34: =+H34*E34 -> 28439456 | N34: 1.0028 | O34: -0.0028 | P34: =SUM(N34:O34) -> 1 | Q34: =K34*N34 -> 28519086 | R34: =K34*O34 -> -79630.477 | S34: =K34*P34 -> 28439456 | T34: =I34*P34 -> 16195680 | U34: =J34*P34 -> 12243776 | V34: =SUM(T34:U34) -> 28439456
A35: Hormigón | B35: 3.11 | C35: Vigas - H35 (180 kg/m3 de hierro) | D35: m3 | E35: 46 | F35: ='01 (2)'!H35*'01 (2)'!$T$5 -> 756873.91 | G35: =H35-F35 -> 737813.09 | H35: 1494687 | I35: =$E35*F35 -> 34816200 | J35: =$E35*G35 -> 33939402 | K35: =+H35*E35 -> 68755602 | N35: 0.5824 | O35: 0.4176 | P35: =SUM(N35:O35) -> 1 | Q35: =K35*N35 -> 40043263 | R35: =K35*O35 -> 28712339 | S35: =K35*P35 -> 68755602 | T35: =I35*P35 -> 34816200 | U35: =J35*P35 -> 33939402 | V35: =SUM(T35:U35) -> 68755602
A36: Hormigón | B36: 3.12 | C36: Vigas de H° visto - H35 (180 kg/m3 de hierro) | D36: m3 | E36: 31 | F36: ='01 (2)'!H36*'01 (2)'!$T$5 -> 753999.69 | G36: =H36-F36 -> 919385.31 | H36: 1673385 | I36: =$E36*F36 -> 23373990 | J36: =$E36*G36 -> 28500945 | K36: =+H36*E36 -> 51874935 | N36: 1 | P36: =SUM(N36:O36) -> 1 | Q36: =K36*N36 -> 51874935 | R36: =K36*O36 -> 0 | S36: =K36*P36 -> 51874935 | T36: =I36*P36 -> 23373990 | U36: =J36*P36 -> 28500945 | V36: =SUM(T36:U36) -> 51874935
A37: Hormigón | B37: 3.13 | C37: Tabiques - H35 (100 kg/m3 de hierro) | D37: m3 | E37: 24 | F37: ='01 (2)'!H37*'01 (2)'!$T$5 -> 547021 | G37: =H37-F37 -> 491993 | H37: 1039014 | I37: =$E37*F37 -> 13128504 | J37: =$E37*G37 -> 11807832 | K37: =+H37*E37 -> 24936336 | N37: 0.6519 | O37: 0.3481 | P37: =SUM(N37:O37) -> 1 | Q37: =K37*N37 -> 16255997 | R37: =K37*O37 -> 8680338.6 | S37: =K37*P37 -> 24936336 | T37: =I37*P37 -> 13128504 | U37: =J37*P37 -> 11807832 | V37: =SUM(T37:U37) -> 24936336
A38: Hormigón | B38: 3.14 | C38: Columna - H35 (180 Kg/m3 de hierro) | D38: m3 | E38: 39 | F38: ='01 (2)'!H38*'01 (2)'!$T$5 -> 712523.96 | G38: =H38-F38 -> 440736.04 | H38: 1153260 | I38: =$E38*F38 -> 27788435 | J38: =$E38*G38 -> 17188705 | K38: =+H38*E38 -> 44977140 | N38: 0.8189 | O38: 0.1811 | P38: =SUM(N38:O38) -> 1 | Q38: =K38*N38 -> 36831780 | R38: =K38*O38 -> 8145360.1 | S38: =K38*P38 -> 44977140 | T38: =I38*P38 -> 27788435 | U38: =J38*P38 -> 17188705 | V38: =SUM(T38:U38) -> 44977140
A39: Hormigón | B39: 3.16 | C39: Columna vista- H35 (180 Kg/m3 de hierro) | D39: m3 | E39: 4 | F39: ='01 (2)'!H39*'01 (2)'!$T$5 -> 724547.88 | G39: =H39-F39 -> 529616.12 | H39: 1254164 | I39: =$E39*F39 -> 2898191.5 | J39: =$E39*G39 -> 2118464.5 | K39: =+H39*E39 -> 5016656 | N39: 0.6325 | O39: 0.3675 | P39: =SUM(N39:O39) -> 1 | Q39: =K39*N39 -> 3173034.9 | R39: =K39*O39 -> 1843621.1 | S39: =K39*P39 -> 5016656 | T39: =I39*P39 -> 2898191.5 | U39: =J39*P39 -> 2118464.5 | V39: =SUM(T39:U39) -> 5016656
A40: Hormigón | B40: 3.17 | C40: Escaleras de Hº visto - H35 (105 kg/m3 de hierro) | D40: m3 | E40: 10 | F40: ='01 (2)'!H40*'01 (2)'!$T$5 -> 554645.97 | G40: =H40-F40 -> 556889.03 | H40: 1111535 | I40: =$E40*F40 -> 5546459.7 | J40: =$E40*G40 -> 5568890.3 | K40: =+H40*E40 -> 11115350 | N40: 0.564 | O40: 0.436 | P40: =SUM(N40:O40) -> 1 | Q40: =K40*N40 -> 6269057.4 | R40: =K40*O40 -> 4846292.6 | S40: =K40*P40 -> 11115350 | T40: =I40*P40 -> 5546459.7 | U40: =J40*P40 -> 5568890.3 | V40: =SUM(T40:U40) -> 11115350
A41: Hormigón | B41: 3.18 | C41: Tanques de HºAº - H35 (100 kg/m3 de hierro) - Tanque de reserva | D41: m3 | E41: 6 | F41: ='01 (2)'!H41*'01 (2)'!$T$5 -> 547021 | G41: =H41-F41 -> 491993 | H41: 1039014 | I41: =$E41*F41 -> 3282126 | J41: =$E41*G41 -> 2951958 | K41: =+H41*E41 -> 6234084 | N41: 0 | O41: 1 | P41: =SUM(N41:O41) -> 1 | Q41: =K41*N41 -> 0 | R41: =K41*O41 -> 6234084 | S41: =K41*P41 -> 6234084 | T41: =I41*P41 -> 3282126 | U41: =J41*P41 -> 2951958 | V41: =SUM(T41:U41) -> 6234084
A42: Hormigón | B42: 3.19 | C42: Sistema de apuntalamiento y reapuntalamiento | D42: gl | E42: 1 | F42: ='01 (2)'!H42*'01 (2)'!$T$5 -> 0 | G42: =H42-F42 -> 11272951 | H42: 11272951 | I42: =$E42*F42 -> 0 | J42: =$E42*G42 -> 11272951 | K42: =+H42*E42 -> 11272951 | N42: 0.65 | O42: 0.35 | P42: =SUM(N42:O42) -> 1 | Q42: =K42*N42 -> 7327418.2 | R42: =K42*O42 -> 3945532.8 | S42: =K42*P42 -> 11272951 | T42: =I42*P42 -> 0 | U42: =J42*P42 -> 11272951 | V42: =SUM(T42:U42) -> 11272951
A43: Hormigón | B43: 3.2 | C43: Ensayos de hormigon por etapas de hormigonado | D43: u | E43: 15 | F43: ='01 (2)'!H43*'01 (2)'!$T$5 -> 0 | G43: =H43-F43 -> 304811 | H43: 304811 | I43: =$E43*F43 -> 0 | J43: =$E43*G43 -> 4572165 | K43: =+H43*E43 -> 4572165 | N43: 0.8 | O43: 0.2 | P43: =SUM(N43:O43) -> 1 | Q43: =K43*N43 -> 3657732 | R43: =K43*O43 -> 914433 | S43: =K43*P43 -> 4572165 | T43: =I43*P43 -> 0 | U43: =J43*P43 -> 4572165 | V43: =SUM(T43:U43) -> 4572165
A44: Hormigón | B44: 3.21 | C44: Permiso de estacionamiento de bomba de hormigón a contramano | D44: gl | E44: 3 | F44: ='01 (2)'!H44*'01 (2)'!$T$5 -> 68288.513 | G44: =H44-F44 -> 0.48720434 | H44: 68289 | I44: =$E44*F44 -> 204865.54 | J44: =$E44*G44 -> 1.461613 | K44: =+H44*E44 -> 204867 | N44: 1 | P44: =SUM(N44:O44) -> 1 | Q44: =K44*N44 -> 204867 | R44: =K44*O44 -> 0 | S44: =K44*P44 -> 204867 | T44: =I44*P44 -> 204865.54 | U44: =J44*P44 -> 1.461613 | V44: =SUM(T44:U44) -> 204867
A45: Hormigón | B45: 3.22 | C45: Picado de medianeras para columnas y vigas - Cotizado para PB y 1P | D45: m2 | E45: 78 | F45: ='01 (2)'!H45*'01 (2)'!$T$5 -> 9397.437 | G45: =H45-F45 -> 24260.563 | H45: 33658 | I45: =$E45*F45 -> 733000.08 | J45: =$E45*G45 -> 1892323.9 | K45: =+H45*E45 -> 2625324 | N45: 1 | P45: =SUM(N45:O45) -> 1 | Q45: =K45*N45 -> 2625324 | R45: =K45*O45 -> 0 | S45: =K45*P45 -> 2625324 | T45: =I45*P45 -> 733000.08 | U45: =J45*P45 -> 1892323.9 | V45: =SUM(T45:U45) -> 2625324
C46: SUB TOTAL OBRA GRIS | K46: =SUM(K8:K45) -> 500907720 | L46: =SUM(L8:L45) -> 500907720 | M46: =+L46/$L$46 -> 1 | Q46: =+SUM(Q8:Q45) -> 3.7001181e+08 | R46: =+SUM(R8:R45) -> 1.3089591e+08 | S46: =+SUM(S8:S45) -> 500907720 | T46: =SUM(T9:T45) -> 2.4839388e+08 | U46: =SUM(U9:U45) -> 2.5251384e+08 | V46: =SUM(V9:V45) -> 500907720
S48: =S46/L46 -> 1
F49: 3 | G49: DEDUCTIVOS | L49: =SUM(K50:K53) -> -87820038 | M49: -0.17532179 | Z49: =+N47 -> 0
F50: =A35 -> Hormigón | G50: 3.1 | H50: Losa maciza de Hº visto - H35 (100 kg/m3 de hierro) | I50: 0 | J50: 888733 | K50: 0 | O50: 1 | P50: =+N50+O50 -> 1 | Q50: =+K50*N50 -> 0 | R50: =+K50*O50 -> 0 | S50: =+K50*P50 -> 0 | Z50: =+S54 -> -87820038
F51: =A34 -> Hormigón | G51: 3.09 | H51: Losa maciza - H35 (100 kg/m3 de hierro) | I51: -75.681 | J51: 804023 | K51: -60849265 | O51: 1 | P51: =+N51+O51 -> 1 | Q51: =+K51*N51 -> 0 | R51: =+K51*O51 -> -60849265 | S51: =+K51*P51 -> -60849265 | Z51: 93845459
F52: =A36 -> Hormigón | G52: 3.11 | H52: Vigas - H35 (180 kg/m3 de hierro) | I52: -13.8736 | J52: 1494687 | K52: -20736690 | O52: 1 | P52: =+N52+O52 -> 1 | Q52: =+K52*N52 -> 0 | R52: =+K52*O52 -> -20736690 | S52: =+K52*P52 -> -20736690 | Z52: =+Z49+Z50+Z51 -> 6025420.8
F53: =A42 -> Hormigón | G53: 3.18 | H53: Tanques de HºAº - H35 (100 kg/m3 de hierro) - Tanque de reserva | I53: -6 | J53: 1039014 | K53: -6234084 | O53: 1 | P53: =+N53+O53 -> 1 | Q53: =+K53*N53 -> 0 | R53: =+K53*O53 -> -6234084 | S53: =+K53*P53 -> -6234084
G54: SUBTOTAL DEDUCTIVOS PTO#1 | L54: =SUM(L49:L53) -> -87820038 | Q54: =SUM(Q51:Q53) -> 0 | R54: =SUM(R50:R53) -> -87820038 | S54: =SUM(S50:S53) -> -87820038 | Z54: =+R54*0.4 -> -35128015
R55: =+R54/L54 -> 1 | S55: =+S54/L54 -> 1

Sheet Cert. Pto. 02
K1: DÓLAR BNA | L1: DÓLAR MEP
K2: 1066.5 | L2: 1170
K4: 45667
C5: OBRA: EDIFICIO GDR 3760 | N5: Certificado | O5: 13 | S5: 46108
C6: PRESUPUESTO OBRA CIVIL
C7: PRESUPUESTO 02 - ALBANILERIA, INSTALACIONES Y TERMINACIONES | N7: Avance | Q7: Importe | T7: Importe
C8: Descripción | D8: U | E8: Cant | F8: Materiales | G8: Mano de obra | H8: P unit | I8: Materiales | J8: Mano de obra | K8: Subtotal | N8: Anterior | O8: Actual | P8: Acumulado | Q8: Anterior | R8: Actual | S8: Acumulado | T8: Material | U8: Mano de obra | V8: Total
B9: 4 | C9: MAMPOSTERÍA | L9: =+SUM(K10:K23) -> 51045774 | M9: =+L9/$L$195 -> 0.060420265
A10: Albañilería | B10: 4.01 | C10: Muro tipo 1 - Ladrillo hueco 8 x 18 x 33 | D10: m2 | E10: 621 | F10: ='01 (2)'!H47*'01 (2)'!$T$5 -> 8784.0014 | G10: =H10-F10 -> 13355.999 | H10: 22140 | I10: =E10*F10 -> 5454864.9 | J10: =E10*G10 -> 8294075.1 | K10: =+H10*E10 -> 13748940 | N10: 0.85 | O10: 0.02 | P10: =SUM(N10:O10) -> 0.87 | Q10: =K10*N10 -> 11686599 | R10: =K10*O10 -> 274978.8 | S10: =K10*P10 -> 11961578 | T10: =I10*P10 -> 4745732.5 | U10: =J10*P10 -> 7215845.3 | V10: =SUM(T10:U10) -> 11961578
A11: Albañilería | B11: 4.02 | C11: Muro tipo 2 - Ladrillo hueco 12 x 18 x 33 | D11: m2 | E11: 780 | F11: ='01 (2)'!H48*'01 (2)'!$T$5 -> 11080.96 | G11: =H11-F11 -> 13356.04 | H11: 24437 | I11: =E11*F11 -> 8643148.5 | J11: =E11*G11 -> 10417712 | K11: =+H11*E11 -> 19060860 | N11: 0.85 | O11: 0.05 | P11: =SUM(N11:O11) -> 0.9 | Q11: =K11*N11 -> 16201731 | R11: =K11*O11 -> 953043 | S11: =K11*P11 -> 17154774 | T11: =I11*P11 -> 7778833.6 | U11: =J11*P11 -> 9375940.4 | V11: =SUM(T11:U11) -> 17154774
A12: Albañilería | B12: 4.03 | C12: Muro tipo 3 - Ladrillo comun en panderete | D12: m2 | E12: 56 | F12: ='01 (2)'!H49*'01 (2)'!$T$5 -> 8602.3426 | G12: =H12-F12 -> 14645.657 | H12: 23248 | I12: =E12*F12 -> 481731.18 | J12: =E12*G12 -> 820156.82 | K12: =+H12*E12 -> 1301888 | N12: 1 | P12: =SUM(N12:O12) -> 1 | Q12: =K12*N12 -> 1301888 | R12: =K12*O12 -> 0 | S12: =K12*P12 -> 1301888 | T12: =I12*P12 -> 481731.18 | U12: =J12*P12 -> 820156.82 | V12: =SUM(T12:U12) -> 1301888
A13: Albañilería | B13: 4.04 | C13: Muro tipo 4 - Ladrillo hueco portante 12 x 18 x 33 | D13: m2 | E13: 42 | F13: ='01 (2)'!H50*'01 (2)'!$T$5 -> 15390.195 | G13: =H13-F13 -> 13355.805 | H13: 28746 | I13: =E13*F13 -> 646388.18 | J13: =E13*G13 -> 560943.82 | K13: =+H13*E13 -> 1207332 | N13: 0.7 | O13: 0.15 | P13: =SUM(N13:O13) -> 0.85 | Q13: =K13*N13 -> 845132.4 | R13: =K13*O13 -> 181099.8 | S13: =K13*P13 -> 1026232.2 | T13: =I13*P13 -> 549429.95 | U13: =J13*P13 -> 476802.25 | V13: =SUM(T13:U13) -> 1026232.2
A14: Albañilería | B14: 4.05 | C14: Muro tipo 5 - Bloque HCCA e: 7,5 cm | D14: m2 | E14: 70 | F14: ='01 (2)'!H51*'01 (2)'!$T$5 -> 22413.731 | G14: =H14-F14 -> 14519.269 | H14: 36933 | I14: =E14*F14 -> 1568961.2 | J14: =E14*G14 -> 1016348.8 | K14: =+H14*E14 -> 2585310 | N14: 0.1 | P14: =SUM(N14:O14) -> 0.1 | Q14: =K14*N14 -> 258531 | R14: =K14*O14 -> 0 | S14: =K14*P14 -> 258531 | T14: =I14*P14 -> 156896.12 | U14: =J14*P14 -> 101634.88 | V14: =SUM(T14:U14) -> 258531
A15: Albañilería | B15: 4.06 | C15: Muro tipo 6 - Ladrillo hueco 18 x 18 x 33 | D15: m2 | E15: 5 | F15: ='01 (2)'!H52*'01 (2)'!$T$5 -> 15316.29 | G15: =H15-F15 -> 13355.71 | H15: 28672 | I15: =E15*F15 -> 76581.452 | J15: =E15*G15 -> 66778.548 | K15: =+H15*E15 -> 143360 | N15: 0.1 | P15: =SUM(N15:O15) -> 0.1 | Q15: =K15*N15 -> 14336 | R15: =K15*O15 -> 0 | S15: =K15*P15 -> 14336 | T15: =I15*P15 -> 7658.1452 | U15: =J15*P15 -> 6677.8548 | V15: =SUM(T15:U15) -> 14336
A16: Albañilería | B16: 4.07 | C16: Enchape de medianeras existentes - Contemplamos picado zonas sueltas y enchape con ladrillo comun para PB | D16: m2 | E16: 193 | F16: ='01 (2)'!H53*'01 (2)'!$T$5 -> 4301.1713 | G16: =H16-F16 -> 14309.829 | H16: 18611 | I16: =E16*F16 -> 830126.06 | J16: =E16*G16 -> 2761796.9 | K16: =+H16*E16 -> 3591923 | N16: 0 | P16: =SUM(N16:O16) -> 0 | Q16: =K16*N16 -> 0 | R16: =K16*O16 -> 0 | S16: =K16*P16 -> 0 | T16: =I16*P16 -> 0 | U16: =J16*P16 -> 0 | V16: =SUM(T16:U16) -> 0
A17: Albañilería | B17: 4.08 | C17: Cordón de hormigón en umbrales carpinterías | D17: ml | E17: 61 | F17: ='01 (2)'!H54*'01 (2)'!$T$5 -> 12119.805 | G17: =H17-F17 -> 16458.195 | H17: 28578 | I17: =E17*F17 -> 739308.1 | J17: =E17*G17 -> 1003949.9 | K17: =+H17*E17 -> 1743258 | N17: 0.6 | O17: 0.4 | P17: =SUM(N17:O17) -> 1 | Q17: =K17*N17 -> 1045954.8 | R17: =K17*O17 -> 697303.2 | S17: =K17*P17 -> 1743258 | T17: =I17*P17 -> 739308.1 | U17: =J17*P17 -> 1003949.9 | V17: =SUM(T17:U17) -> 1743258
A18: Albañilería | B18: 4.09 | C18: Banquina Sala tanque de bombeo | D18: gl | E18: 1 | F18: ='01 (2)'!H55*'01 (2)'!$T$5 -> 81044.529 | G18: =H18-F18 -> 199778.47 | H18: 280823 | I18: =E18*F18 -> 81044.529 | J18: =E18*G18 -> 199778.47 | K18: =+H18*E18 -> 280823 | N18: 0 | P18: =SUM(N18:O18) -> 0 | Q18: =K18*N18 -> 0 | R18: =K18*O18 -> 0 | S18: =K18*P18 -> 0 | T18: =I18*P18 -> 0 | U18: =J18*P18 -> 0 | V18: =SUM(T18:U18) -> 0
A19: Albañilería | B19: 4.1 | C19: Banquina en parrillas | D19: gl | E19: 1 | F19: ='01 (2)'!H56*'01 (2)'!$T$5 -> 202488.77 | G19: =H19-F19 -> 598725.23 | H19: 801214 | I19: =E19*F19 -> 202488.77 | J19: =E19*G19 -> 598725.23 | K19: =+H19*E19 -> 801214 | N19: 0 | P19: =SUM(N19:O19) -> 0 | Q19: =K19*N19 -> 0 | R19: =K19*O19 -> 0 | S19: =K19*P19 -> 0 | T19: =I19*P19 -> 0 | U19: =J19*P19 -> 0 | V19: =SUM(T19:U19) -> 0
A20: Albañilería | B20: 4.11 | C20: Excavación y amurado con Hº tanque de recuperación de agua de lluvia | D20: gl | E20: 1 | F20: ='01 (2)'!H57*'01 (2)'!$T$5 -> 171579.19 | G20: =H20-F20 -> 353654.81 | H20: 525234 | I20: =E20*F20 -> 171579.19 | J20: =E20*G20 -> 353654.81 | K20: =+H20*E20 -> 525234 | N20: 0 | P20: =SUM(N20:O20) -> 0 | Q20: =K20*N20 -> 0 | R20: =K20*O20 -> 0 | S20: =K20*P20 -> 0 | T20: =I20*P20 -> 0 | U20: =J20*P20 -> 0 | V20: =SUM(T20:U20) -> 0
A21: Albañilería | B21: 4.12 | C21: Provisión y amurado de tapas de inspección para tanque de reserva | D21: u | E21: 3 | F21: ='01 (2)'!H58*'01 (2)'!$T$5 -> 161909.86 | G21: =H21-F21 -> 75874.139 | H21: 237784 | I21: =E21*F21 -> 485729.58 | J21: =E21*G21 -> 227622.42 | K21: =+H21*E21 -> 713352 | N21: 0 | P21: =SUM(N21:O21) -> 0 | Q21: =K21*N21 -> 0 | R21: =K21*O21 -> 0 | S21: =K21*P21 -> 0 | T21: =I21*P21 -> 0 | U21: =J21*P21 -> 0 | V21: =SUM(T21:U21) -> 0
A22: Albañilería | B22: 4.13 | C22: Vigas de encadenado - Cuantía aprox. 60 kg/m3 | D22: ml | E22: 40 | F22: ='01 (2)'!H59*'01 (2)'!$T$5 -> 48976.244 | G22: =H22-F22 -> 49049.756 | H22: 98026 | I22: =E22*F22 -> 1959049.7 | J22: =E22*G22 -> 1961990.3 | K22: =+H22*E22 -> 3921040 | N22: 0 | P22: =SUM(N22:O22) -> 0 | Q22: =K22*N22 -> 0 | R22: =K22*O22 -> 0 | S22: =K22*P22 -> 0 | T22: =I22*P22 -> 0 | U22: =J22*P22 -> 0 | V22: =SUM(T22:U22) -> 0
A23: Albañilería | B23: 4.14 | C23: Amurado de bañera | D23: u | E23: 8 | F23: ='01 (2)'!H60*'01 (2)'!$T$5 -> 31913.84 | G23: =H23-F23 -> 145741.16 | H23: 177655 | I23: =E23*F23 -> 255310.72 | J23: =E23*G23 -> 1165929.3 | K23: =+H23*E23 -> 1421240 | N23: 0 | P23: =SUM(N23:O23) -> 0 | Q23: =K23*N23 -> 0 | R23: =K23*O23 -> 0 | S23: =K23*P23 -> 0 | T23: =I23*P23 -> 0 | U23: =J23*P23 -> 0 | V23: =SUM(T23:U23) -> 0
B24: 5 | C24: AISLACIONES | L24: =+SUM(K25:K31) -> 19239698 | M24: =+L24/$L$195 -> 0.022773044
A25: Albañilería | B25: 5.01 | C25: Cajón hidrofugo | D25: ml | E25: 136 | F25: ='01 (2)'!H62*'01 (2)'!$T$5 -> 1078.9962 | G25: =H25-F25 -> 5417.0038 | H25: 6496 | I25: =E25*F25 -> 146743.48 | J25: =E25*G25 -> 736712.52 | K25: =+H25*E25 -> 883456 | N25: 0 | P25: =SUM(N25:O25) -> 0 | Q25: =K25*N25 -> 0 | R25: =K25*O25 -> 0 | S25: =K25*P25 -> 0 | T25: =I25*P25 -> 0 | U25: =J25*P25 -> 0 | V25: =SUM(T25:U25) -> 0
A26: Albañilería | B26: 5.02 | C26: Aislación hidrófuga horizontal (baños) - Inc. membrana geotextil y 35% en concepto de babetas | D26: m2 | E26: 77 | F26: ='01 (2)'!H63*'01 (2)'!$T$5 -> 17576.486 | G26: =H26-F26 -> 15693.514 | H26: 33270 | I26: =E26*F26 -> 1353389.4 | J26: =E26*G26 -> 1208400.6 | K26: =+H26*E26 -> 2561790 | N26: 0 | P26: =SUM(N26:O26) -> 0 | Q26: =K26*N26 -> 0 | R26: =K26*O26 -> 0 | S26: =K26*P26 -> 0 | T26: =I26*P26 -> 0 | U26: =J26*P26 -> 0 | V26: =SUM(T26:U26) -> 0
A27: Albañilería | B27: 5.03 | C27: Azotado hidrófugo - Contrapiso de PB | D27: m2 | E27: 107 | F27: ='01 (2)'!H64*'01 (2)'!$T$5 -> 1078.9962 | G27: =H27-F27 -> 5417.0038 | H27: 6496 | I27: =E27*F27 -> 115452.59 | J27: =E27*G27 -> 579619.41 | K27: =+H27*E27 -> 695072 | N27: 0 | P27: =SUM(N27:O27) -> 0 | Q27: =K27*N27 -> 0 | R27: =K27*O27 -> 0 | S27: =K27*P27 -> 0 | T27: =I27*P27 -> 0 | U27: =J27*P27 -> 0 | V27: =SUM(T27:U27) -> 0
A28: Albañilería | B28: 5.04 | C28: Aislación térmica en terrazas, eps e:2,00 cm | D28: m2 | E28: 186 | F28: ='01 (2)'!H65*'01 (2)'!$T$5 -> 4831.67 | G28: =H28-F28 -> 0.32998564 | H28: 4832 | I28: =E28*F28 -> 898690.62 | J28: =E28*G28 -> 61.37733 | K28: =+H28*E28 -> 898752 | N28: 0 | P28: =SUM(N28:O28) -> 0 | Q28: =K28*N28 -> 0 | R28: =K28*O28 -> 0 | S28: =K28*P28 -> 0 | T28: =I28*P28 -> 0 | U28: =J28*P28 -> 0 | V28: =SUM(T28:U28) -> 0
A29: Albañilería | B29: 5.05 | C29: Barrera de vapor | D29: m2 | E29: 186 | F29: ='01 (2)'!H66*'01 (2)'!$T$5 -> 1674.722 | G29: =H29-F29 -> 2459.278 | H29: 4134 | I29: =E29*F29 -> 311498.29 | J29: =E29*G29 -> 457425.71 | K29: =+H29*E29 -> 768924 | N29: 1 | P29: =SUM(N29:O29) -> 1 | Q29: =K29*N29 -> 768924 | R29: =K29*O29 -> 0 | S29: =K29*P29 -> 768924 | T29: =I29*P29 -> 311498.29 | U29: =J29*P29 -> 457425.71 | V29: =SUM(T29:U29) -> 768924
A30: Albañilería | B30: 5.06 | C30: Membrana asfáltica geotextil 4mm - Balcones y azotea - Inc. 20% en concepto de babetas | D30: m2 | E30: 390 | F30: ='01 (2)'!H67*'01 (2)'!$T$5 -> 15623.543 | G30: =H30-F30 -> 12563.457 | H30: 28187 | I30: =E30*F30 -> 6093181.8 | J30: =E30*G30 -> 4899748.2 | K30: =+H30*E30 -> 10992930 | N30: 0 | P30: =SUM(N30:O30) -> 0 | Q30: =K30*N30 -> 0 | R30: =K30*O30 -> 0 | S30: =K30*P30 -> 0 | T30: =I30*P30 -> 0 | U30: =J30*P30 -> 0 | V30: =SUM(T30:U30) -> 0
A31: Albañilería | B31: 5.07 | C31: Impermeabilización de tanque de reserva de HºAº | D31: gl | E31: 1 | F31: ='01 (2)'!H68*'01 (2)'!$T$5 -> 0 | G31: =H31-F31 -> 2438774 | H31: 2438774 | I31: =E31*F31 -> 0 | J31: =E31*G31 -> 2438774 | K31: =+H31*E31 -> 2438774 | N31: 0 | P31: =SUM(N31:O31) -> 0 | Q31: =K31*N31 -> 0 | R31: =K31*O31 -> 0 | S31: =K31*P31 -> 0 | T31: =I31*P31 -> 0 | U31: =J31*P31 -> 0 | V31: =SUM(T31:U31) -> 0
B32: 6 | C32: CUBIERTAS | L32: =+SUM(K33) -> 1722875 | M32: =+L32/$L$195 -> 0.0020392788
A33: Albañilería | B33: 6.02 | C33: Babeta de chapa galvanizada en medianeras | D33: ml | E33: 55 | F33: ='01 (2)'!H70*'01 (2)'!$T$5 -> 19854.334 | G33: =H33-F33 -> 11470.666 | H33: 31325 | I33: =E33*F33 -> 1091988.4 | J33: =E33*G33 -> 630886.61 | K33: =+H33*E33 -> 1722875 | N33: 0 | P33: =SUM(N33:O33) -> 0 | Q33: =K33*N33 -> 0 | R33: =K33*O33 -> 0 | S33: =K33*P33 -> 0 | T33: =I33*P33 -> 0 | U33: =J33*P33 -> 0 | V33: =SUM(T33:U33) -> 0
B34: 7 | C34: REVOQUES | L34: =+SUM(K35:K40) -> 92324467 | M34: =+L34/$L$195 -> 0.10927974
A35: Albañilería | B35: 7.01 | C35: Revoque Grueso Impermeable Exterior | D35: m2 | E35: 879 | F35: ='01 (2)'!H72*'01 (2)'!$T$5 -> 5343.2063 | G35: =H35-F35 -> 14599.794 | H35: 19943 | I35: =E35*F35 -> 4696678.3 | J35: =E35*G35 -> 12833219 | K35: =+H35*E35 -> 17529897 | N35: 0 | P35: =SUM(N35:O35) -> 0 | Q35: =K35*N35 -> 0 | R35: =K35*O35 -> 0 | S35: =K35*P35 -> 0 | T35: =I35*P35 -> 0 | U35: =J35*P35 -> 0 | V35: =SUM(T35:U35) -> 0
A36: Albañilería | B36: 7.02 | C36: Revoque Grueso Impermeable Exterior a mas de 3m - Medianero y fachadas | D36: m2 | E36: 716 | F36: ='01 (2)'!H73*'01 (2)'!$T$5 -> 5343.2063 | G36: =H36-F36 -> 21423.794 | H36: 26767 | I36: =E36*F36 -> 3825735.7 | J36: =E36*G36 -> 15339436 | K36: =+H36*E36 -> 19165172 | N36: 0.4 | O36: 0.15 | P36: =SUM(N36:O36) -> 0.55 | Q36: =K36*N36 -> 7666068.8 | R36: =K36*O36 -> 2874775.8 | S36: =K36*P36 -> 10540845 | T36: =I36*P36 -> 2104154.6 | U36: =J36*P36 -> 8436690 | V36: =SUM(T36:U36) -> 10540845
A37: Albañilería | B37: 7.03 | C37: Yeso interior | D37: m2 | E37: 1439 | F37: ='01 (2)'!H74*'01 (2)'!$T$5 -> 7095.6693 | G37: =H37-F37 -> 15867.331 | H37: 22963 | I37: =E37*F37 -> 10210668 | J37: =E37*G37 -> 22833089 | K37: =+H37*E37 -> 33043757 | N37: 0.1 | O37: 0.7 | P37: =SUM(N37:O37) -> 0.8 | Q37: =K37*N37 -> 3304375.7 | R37: =K37*O37 -> 23130630 | S37: =K37*P37 -> 26435006 | T37: =I37*P37 -> 8168534.5 | U37: =J37*P37 -> 18266471 | V37: =SUM(T37:U37) -> 26435006
A38: Albañilería | B38: 7.04 | C38: Arista en yeso | D38: ml | E38: 347 | F38: ='01 (2)'!H75*'01 (2)'!$T$5 -> 0 | G38: =H38-F38 -> 16909 | H38: 16909 | I38: =E38*F38 -> 0 | J38: =E38*G38 -> 5867423 | K38: =+H38*E38 -> 5867423 | N38: 0.1 | O38: 0.7 | P38: =SUM(N38:O38) -> 0.8 | Q38: =K38*N38 -> 586742.3 | R38: =K38*O38 -> 4107196.1 | S38: =K38*P38 -> 4693938.4 | T38: =I38*P38 -> 0 | U38: =J38*P38 -> 4693938.4 | V38: =SUM(T38:U38) -> 4693938.4
A39: Albañilería | B39: 7.05 | C39: Provisión y colocación de guardacanto yesero | D39: un | E39: 132 | F39: ='01 (2)'!H76*'01 (2)'!$T$5 -> 1555.6575 | G39: =H39-F39 -> 17828.343 | H39: 19384 | I39: =E39*F39 -> 205346.79 | J39: =E39*G39 -> 2353341.2 | K39: =+H39*E39 -> 2558688 | N39: 0.1 | O39: 0.7 | P39: =SUM(N39:O39) -> 0.8 | Q39: =K39*N39 -> 255868.8 | R39: =K39*O39 -> 1791081.6 | S39: =K39*P39 -> 2046950.4 | T39: =I39*P39 -> 164277.43 | U39: =J39*P39 -> 1882673 | V39: =SUM(T39:U39) -> 2046950.4
A40: Albañilería | B40: 7.06 | C40: Revoque Grueso Impermeable Interior b/ revestimiento | D40: m2 | E40: 710 | F40: ='01 (2)'!H77*'01 (2)'!$T$5 -> 5343.2063 | G40: =H40-F40 -> 14599.794 | H40: 19943 | I40: =E40*F40 -> 3793676.5 | J40: =E40*G40 -> 10365854 | K40: =+H40*E40 -> 14159530 | N40: 0.05 | O40: 0.2 | P40: =SUM(N40:O40) -> 0.25 | Q40: =K40*N40 -> 707976.5 | R40: =K40*O40 -> 2831906 | S40: =K40*P40 -> 3539882.5 | T40: =I40*P40 -> 948419.11 | U40: =J40*P40 -> 2591463.4 | V40: =SUM(T40:U40) -> 3539882.5
B41: 8 | C41: CONTRAPISOS Y CARPETAS | L41: =+SUM(K42:K49) -> 49520833 | M41: =+L41/$L$195 -> 0.058615271
A42: Albañilería | B42: 8.01 | C42: Contrapiso de Hº armado e: 18 cm, incluye malla Ø 6 mm y film 200 mic. | D42: m2 | E42: 107 | F42: ='01 (2)'!H79*'01 (2)'!$T$5 -> 41234.596 | G42: =H42-F42 -> 17345.404 | H42: 58580 | I42: =E42*F42 -> 4412101.7 | J42: =E42*G42 -> 1855958.3 | K42: =+H42*E42 -> 6268060 | N42: 0 | P42: =SUM(N42:O42) -> 0 | Q42: =K42*N42 -> 0 | R42: =K42*O42 -> 0 | S42: =K42*P42 -> 0 | T42: =I42*P42 -> 0 | U42: =J42*P42 -> 0 | V42: =SUM(T42:U42) -> 0
A43: Albañilería | B43: 8.02 | C43: Contrapiso de H13 subase bajo intertrabado y garden block | D43: m2 | E43: 258 | F43: ='01 (2)'!H80*'01 (2)'!$T$5 -> 29375.015 | G43: =H43-F43 -> 9353.9849 | H43: 38729 | I43: =E43*F43 -> 7578753.9 | J43: =E43*G43 -> 2413328.1 | K43: =+H43*E43 -> 9992082 | N43: 0 | P43: =SUM(N43:O43) -> 0 | Q43: =K43*N43 -> 0 | R43: =K43*O43 -> 0 | S43: =K43*P43 -> 0 | T43: =I43*P43 -> 0 | U43: =J43*P43 -> 0 | V43: =SUM(T43:U43) -> 0
A44: Albañilería | B44: 8.03 | C44: Monolítico e: 6 cm | D44: m2 | E44: 425 | F44: ='01 (2)'!H81*'01 (2)'!$T$5 -> 9286.4855 | G44: =H44-F44 -> 13656.514 | H44: 22943 | I44: =E44*F44 -> 3946756.4 | J44: =E44*G44 -> 5804018.6 | K44: =+H44*E44 -> 9750775 | N44: 0 | P44: =SUM(N44:O44) -> 0 | Q44: =K44*N44 -> 0 | R44: =K44*O44 -> 0 | S44: =K44*P44 -> 0 | T44: =I44*P44 -> 0 | U44: =J44*P44 -> 0 | V44: =SUM(T44:U44) -> 0
A45: Albañilería | B45: 8.04 | C45: Contrapiso alivianado en azoteas (RDC), e: 15 cm | D45: m2 | E45: 200 | F45: ='01 (2)'!H82*'01 (2)'!$T$5 -> 32611.107 | G45: =H45-F45 -> 7743.8929 | H45: 40355 | I45: =E45*F45 -> 6522221.4 | J45: =E45*G45 -> 1548778.6 | K45: =+H45*E45 -> 8071000 | N45: 0 | P45: =SUM(N45:O45) -> 0 | Q45: =K45*N45 -> 0 | R45: =K45*O45 -> 0 | S45: =K45*P45 -> 0 | T45: =I45*P45 -> 0 | U45: =J45*P45 -> 0 | V45: =SUM(T45:U45) -> 0
A46: Albañilería | B46: 8.05 | C46: Contrapiso con piedra binder e: 4/5 cm - En locales húmedos (baños) | D46: m2 | E46: 77 | F46: ='01 (2)'!H83*'01 (2)'!$T$5 -> 10973.624 | G46: =H46-F46 -> 20541.376 | H46: 31515 | I46: =E46*F46 -> 844969.02 | J46: =E46*G46 -> 1581686 | K46: =+H46*E46 -> 2426655 | N46: 0 | P46: =SUM(N46:O46) -> 0 | Q46: =K46*N46 -> 0 | R46: =K46*O46 -> 0 | S46: =K46*P46 -> 0 | T46: =I46*P46 -> 0 | U46: =J46*P46 -> 0 | V46: =SUM(T46:U46) -> 0
A47: Albañilería | B47: 8.06 | C47: Carpeta autonivelante e: 4/10 mm - En locales húmedos (baños) | D47: m2 | E47: 77 | F47: ='01 (2)'!H84*'01 (2)'!$T$5 -> 9849.9099 | G47: =H47-F47 -> 9833.0901 | H47: 19683 | I47: =E47*F47 -> 758443.06 | J47: =E47*G47 -> 757147.94 | K47: =+H47*E47 -> 1515591 | N47: 0 | P47: =SUM(N47:O47) -> 0 | Q47: =K47*N47 -> 0 | R47: =K47*O47 -> 0 | S47: =K47*P47 -> 0 | T47: =I47*P47 -> 0 | U47: =J47*P47 -> 0 | V47: =SUM(T47:U47) -> 0
A48: Albañilería | B48: 8.07 | C48: Carpeta a la cal reforzada | D48: m2 | E48: 442 | F48: ='01 (2)'!H85*'01 (2)'!$T$5 -> 3621.7106 | G48: =H48-F48 -> 10713.289 | H48: 14335 | I48: =E48*F48 -> 1600796.1 | J48: =E48*G48 -> 4735273.9 | K48: =+H48*E48 -> 6336070 | N48: 0 | P48: =SUM(N48:O48) -> 0 | Q48: =K48*N48 -> 0 | R48: =K48*O48 -> 0 | S48: =K48*P48 -> 0 | T48: =I48*P48 -> 0 | U48: =J48*P48 -> 0 | V48: =SUM(T48:U48) -> 0
A49: Albañilería | B49: 8.08 | C49: Carpeta a la cal reforzada s/membrana | D49: m2 | E49: 360 | F49: ='01 (2)'!H86*'01 (2)'!$T$5 -> 3621.7106 | G49: =H49-F49 -> 10713.289 | H49: 14335 | I49: =E49*F49 -> 1303815.8 | J49: =E49*G49 -> 3856784.2 | K49: =+H49*E49 -> 5160600 | N49: 0 | P49: =SUM(N49:O49) -> 0 | Q49: =K49*N49 -> 0 | R49: =K49*O49 -> 0 | S49: =K49*P49 -> 0 | T49: =I49*P49 -> 0 | U49: =J49*P49 -> 0 | V49: =SUM(T49:U49) -> 0
B50: 9 | C50: ESCALERAS | L50: =+SUM(K51:K53) -> 4852846 | M50: =+L50/$L$195 -> 0.005744065
A51: Albañilería | B51: 9.01 | C51: Provisión y ejecución de cemento alisado arrodillado, e: 3,00 cm, en alzada y pedad | D51: gl | E51: 1 | F51: ='01 (2)'!H88*'01 (2)'!$T$5 -> 241430.21 | G51: =H51-F51 -> 1867879.8 | H51: 2109310 | I51: =E51*F51 -> 241430.21 | J51: =E51*G51 -> 1867879.8 | K51: =+H51*E51 -> 2109310 | N51: 0 | P51: =SUM(N51:O51) -> 0 | Q51: =K51*N51 -> 0 | R51: =K51*O51 -> 0 | S51: =K51*P51 -> 0 | T51: =I51*P51 -> 0 | U51: =J51*P51 -> 0 | V51: =SUM(T51:U51) -> 0
A52: Albañilería | B52: 9.02 | C52: Provisión nariz escalera, hierro angulo 5/8 x 1/8" | D52: un | E52: 81 | F52: ='01 (2)'!H89*'01 (2)'!$T$5 -> 3455.732 | G52: =H52-F52 -> 24566.268 | H52: 28022 | I52: =E52*F52 -> 279914.29 | J52: =E52*G52 -> 1989867.7 | K52: =+H52*E52 -> 2269782 | N52: 0 | P52: =SUM(N52:O52) -> 0 | Q52: =K52*N52 -> 0 | R52: =K52*O52 -> 0 | S52: =K52*P52 -> 0 | T52: =I52*P52 -> 0 | U52: =J52*P52 -> 0 | V52: =SUM(T52:U52) -> 0
A53: Albañilería | B53: 9.03 | C53: Ejecución de zócalo rampante de concreto h: 10 cm | D53: ml | E53: 46 | F53: ='01 (2)'!H90*'01 (2)'!$T$5 -> 812.89634 | G53: =H53-F53 -> 9486.1037 | H53: 10299 | I53: =E53*F53 -> 37393.232 | J53: =E53*G53 -> 436360.77 | K53: =+H53*E53 -> 473754 | N53: 0 | P53: =SUM(N53:O53) -> 0 | Q53: =K53*N53 -> 0 | R53: =K53*O53 -> 0 | S53: =K53*P53 -> 0 | T53: =I53*P53 -> 0 | U53: =J53*P53 -> 0 | V53: =SUM(T53:U53) -> 0
B54: 10 | C54: VENTILACIONES - PROVISION A CARGO DEL COMITENTE | L54: =+SUM(K55:K58) -> 4184652 | M54: =+L54/$L$195 -> 0.004953158
A55: Albañilería | B55: 10.01 | C55: Montaje de conductos de ventilación de baños C27 - Provisión a cargo del comitente | D55: gl | E55: 1 | F55: ='01 (2)'!H92*'01 (2)'!$T$5 -> 266545.49 | G55: =H55-F55 -> 1577986.5 | H55: 1844532 | I55: =E55*F55 -> 266545.49 | J55: =E55*G55 -> 1577986.5 | K55: =+H55*E55 -> 1844532 | N55: 0 | O55: 0.75 | P55: =SUM(N55:O55) -> 0.75 | Q55: =K55*N55 -> 0 | R55: =K55*O55 -> 1383399 | S55: =K55*P55 -> 1383399 | T55: =I55*P55 -> 199909.11 | U55: =J55*P55 -> 1183489.9 | V55: =SUM(T55:U55) -> 1383399
A56: Albañilería | B56: 10.02 | C56: Montaje de conductos de ventilación de parrillas C27 - Provisión a cargo del comitente | D56: gl | E56: 1 | F56: ='01 (2)'!H93*'01 (2)'!$T$5 -> 266545.49 | G56: =H56-F56 -> 948391.51 | H56: 1214937 | I56: =E56*F56 -> 266545.49 | J56: =E56*G56 -> 948391.51 | K56: =+H56*E56 -> 1214937 | N56: 0 | P56: =SUM(N56:O56) -> 0 | Q56: =K56*N56 -> 0 | R56: =K56*O56 -> 0 | S56: =K56*P56 -> 0 | T56: =I56*P56 -> 0 | U56: =J56*P56 -> 0 | V56: =SUM(T56:U56) -> 0
A57: Albañilería | B57: 10.03 | C57: Montaje de campanas de parrillas C22 - Provisión a cargo del comitente | D57: gl | E57: 1 | F57: ='01 (2)'!H94*'01 (2)'!$T$5 -> 66636.371 | G57: =H57-F57 -> 473196.63 | H57: 539833 | I57: =E57*F57 -> 66636.371 | J57: =E57*G57 -> 473196.63 | K57: =+H57*E57 -> 539833 | N57: 0 | P57: =SUM(N57:O57) -> 0 | Q57: =K57*N57 -> 0 | R57: =K57*O57 -> 0 | S57: =K57*P57 -> 0 | T57: =I57*P57 -> 0 | U57: =J57*P57 -> 0 | V57: =SUM(T57:U57) -> 0
A58: Albañilería | B58: 10.04 | C58: Montaje de sombreretes en chapa prepintada C25 - Provisión a cargo del comitente | D58: u | E58: 10 | F58: ='01 (2)'!H95*'01 (2)'!$T$5 -> 26654.549 | G58: =H58-F58 -> 31880.451 | H58: 58535 | I58: =E58*F58 -> 266545.49 | J58: =E58*G58 -> 318804.51 | K58: =+H58*E58 -> 585350 | N58: 0 | P58: =SUM(N58:O58) -> 0 | Q58: =K58*N58 -> 0 | R58: =K58*O58 -> 0 | S58: =K58*P58 -> 0 | T58: =I58*P58 -> 0 | U58: =J58*P58 -> 0 | V58: =SUM(T58:U58) -> 0
B59: 11 | C59: PISOS - PROVISION A CARGO DEL COMITENTE | L59: =+SUM(K60:K70) -> 31170783 | M59: =+L59/$L$195 -> 0.036895258
A60: Revestimiento | B60: 11.01 | C60: Provisión y ejecución de alisado de cemento a la llana metálica, e: 6,00 cm | D60: m2 | E60: 0 | F60: ='01 (2)'!H97*'01 (2)'!$T$5 -> 0 | G60: =H60-F60 -> 0 | H60: 0 | I60: =E60*F60 -> 0 | J60: =E60*G60 -> 0 | K60: =+H60*E60 -> 0 | N60: 0 | P60: =SUM(N60:O60) -> 0 | Q60: =K60*N60 -> 0 | R60: =K60*O60 -> 0 | S60: =K60*P60 -> 0 | T60: =I60*P60 -> 0 | U60: =J60*P60 -> 0 | V60: =SUM(T60:U60) -> 0
A61: Revestimiento | B61: 11.02 | C61: Provisión y ejecución de cemento alisado arrodillado, e: 3,00 cm | D61: m2 | E61: 39 | F61: ='01 (2)'!H98*'01 (2)'!$T$5 -> 5419.3089 | G61: =H61-F61 -> 13860.691 | H61: 19280 | I61: =E61*F61 -> 211353.05 | J61: =E61*G61 -> 540566.95 | K61: =+H61*E61 -> 751920 | N61: 0 | P61: =SUM(N61:O61) -> 0 | Q61: =K61*N61 -> 0 | R61: =K61*O61 -> 0 | S61: =K61*P61 -> 0 | T61: =I61*P61 -> 0 | U61: =J61*P61 -> 0 | V61: =SUM(T61:U61) -> 0
A62: Revestimiento | B62: 11.03 | C62: Colocación de porcelanato a definir en sspacios comunes - Provisión a cargo del comitente | D62: m2 | E62: 48 | F62: ='01 (2)'!H99*'01 (2)'!$T$5 -> 9537.3954 | G62: =H62-F62 -> 15824.605 | H62: 25362 | I62: =E62*F62 -> 457794.98 | J62: =E62*G62 -> 759581.02 | K62: =+H62*E62 -> 1217376 | N62: 0 | P62: =SUM(N62:O62) -> 0 | Q62: =K62*N62 -> 0 | R62: =K62*O62 -> 0 | S62: =K62*P62 -> 0 | T62: =I62*P62 -> 0 | U62: =J62*P62 -> 0 | V62: =SUM(T62:U62) -> 0
A63: Revestimiento | B63: 11.04 | C63: Colocación de pavimento intertrabado de H°, incluye provisión y colocación de cama de arena + tomado de junta - Provisión a cargo del comitente | D63: m2 | E63: 174 | F63: ='01 (2)'!H100*'01 (2)'!$T$5 -> 1737.1289 | G63: =H63-F63 -> 17426.871 | H63: 19164 | I63: =E63*F63 -> 302260.43 | J63: =E63*G63 -> 3032275.6 | K63: =+H63*E63 -> 3334536 | N63: 0 | P63: =SUM(N63:O63) -> 0 | Q63: =K63*N63 -> 0 | R63: =K63*O63 -> 0 | S63: =K63*P63 -> 0 | T63: =I63*P63 -> 0 | U63: =J63*P63 -> 0 | V63: =SUM(T63:U63) -> 0
A64: Revestimiento | B64: 11.05 | C64: Colocación de garden block, incluye provisión y colocación de cama de arena + tomado de junta - Provisión a cargo del comitente | D64: m2 | E64: 92 | F64: ='01 (2)'!H101*'01 (2)'!$T$5 -> 1737.1289 | G64: =H64-F64 -> 17426.871 | H64: 19164 | I64: =E64*F64 -> 159815.86 | J64: =E64*G64 -> 1603272.1 | K64: =+H64*E64 -> 1763088 | N64: 0 | P64: =SUM(N64:O64) -> 0 | Q64: =K64*N64 -> 0 | R64: =K64*O64 -> 0 | S64: =K64*P64 -> 0 | T64: =I64*P64 -> 0 | U64: =J64*P64 -> 0 | V64: =SUM(T64:U64) -> 0
A65: Revestimiento | B65: 11.06 | C65: Provisión y colocación de relleno de piedra binder | D65: m2 | E65: 8 | F65: ='01 (2)'!H102*'01 (2)'!$T$5 -> 3695.6638 | G65: =H65-F65 -> 10347.336 | H65: 14043 | I65: =E65*F65 -> 29565.311 | J65: =E65*G65 -> 82778.689 | K65: =+H65*E65 -> 112344 | N65: 0 | P65: =SUM(N65:O65) -> 0 | Q65: =K65*N65 -> 0 | R65: =K65*O65 -> 0 | S65: =K65*P65 -> 0 | T65: =I65*P65 -> 0 | U65: =J65*P65 -> 0 | V65: =SUM(T65:U65) -> 0
A66: Revestimiento | B66: 11.07 | C66: Colocación de baldoson granítico vereda 40 x 40 - Provisión a cargo del comitente | D66: m2 | E66: 46 | F66: ='01 (2)'!H103*'01 (2)'!$T$5 -> 10264.393 | G66: =H66-F66 -> 16365.607 | H66: 26630 | I66: =E66*F66 -> 472162.09 | J66: =E66*G66 -> 752817.91 | K66: =+H66*E66 -> 1224980 | N66: 0 | P66: =SUM(N66:O66) -> 0 | Q66: =K66*N66 -> 0 | R66: =K66*O66 -> 0 | S66: =K66*P66 -> 0 | T66: =I66*P66 -> 0 | U66: =J66*P66 -> 0 | V66: =SUM(T66:U66) -> 0
