Workbook
Name \0: #REF!
Name \c: #REF!
Name \E: #REF!
Name \i: #REF!
Name \j: #REF!
Name \m: #REF!
Name \P: #REF!
Name \P: #REF!
Name \P: #REF!
Name \P: #REF!
Name \r: #N/A
Name \x: #REF!
Name \z: #REF!
Name __________ben1: #REF!
Name __________ben1: #REF!
Name __________ben1: #REF!
Name __________ben1: #REF!
Name __________ben10: #REF!
Name __________ben10: #REF!
Name __________ben10: #REF!
Name __________ben10: #REF!
Name __________ben15: #REF!
Name __________ben15: #REF!
Name __________ben15: #REF!
Name __________ben15: #REF!
Name __________BEN2: #REF!
Name __________ben20: #REF!
Name __________ben20: #REF!
Name __________ben20: #REF!
Name __________ben20: #REF!
Name __________ben25: #REF!
Name __________ben25: #REF!
Name __________ben25: #REF!
Name __________ben25: #REF!
Name __________BEN3: #REF!
Name __________BEN3: #REF!
Name __________BEN3: #REF!
Name __________BEN3: #REF!
Name __________BEN4: #REF!
Name __________BEN4: #REF!
Name __________BEN4: #REF!
Name __________BEN4: #REF!
Name __________ben5: #REF!
Name __________ben5: #REF!
Name __________ben5: #REF!
Name __________ben5: #REF!
Name _________ben1: #REF!
Name _________ben1: #REF!
Name _________ben1: #REF!
Name _________ben1: #REF!
Name _________ben10: #REF!
Name _________ben10: #REF!
Name _________ben10: #REF!
Name _________ben10: #REF!
Name _________ben15: #REF!
Name _________ben15: #REF!
Name _________ben15: #REF!
Name _________ben15: #REF!
Name _________BEN2: #REF!
Name _________ben20: #REF!

Sheet Adic. N°1
G4: 45900 | K4: Certificado | L4: 1 | P4: 45900
C5: OBRA: EDIFICIO GDR 3760
C6: ADICIONALES Y DEDUCTIVOS N° 1 | K6: Avance | N6: Importe
B7: E | C7: Descripción | D7: U | E7: Cant | F7: P unit | G7: Subtotal | K7: Anterior | L7: Actual | M7: Acumulado | N7: Anterior | O7: Actual | P7: Acumulado
C8: ADICIONALES
A9: 5 | C9: ESTRUCTURA RESISTENTE | H9: =SUM(G10:G11) -> 93845459 | I9: =+H9/$H$14 -> 0.97451132
A10: 5.01 | B10: OK | C10: Losa maciza de Hº visto - H35 (100 kg/m3 de hierro) | D10: m3 | E10: =+Computos!R12 -> 83 | F10: 888733 | G10: =+F10*E10 -> 73764839 | K10: 0 | L10: 0.03 | M10: =+K10+L10 -> 0.03 | N10: =G10*K10 -> 0 | O10: =G10*L10 -> 2212945.2 | P10: =G10*M10 -> 2212945.2
A11: 5.02 | B11: OK | C11: Vigas de H° visto - H35 (180 kg/m3 de hierro) | D11: m3 | E11: =+Computos!R14 -> 12 | F11: 1673385 | G11: =+F11*E11 -> 20080620 | K11: 0 | M11: =+K11+L11 -> 0 | N11: =G11*K11 -> 0 | O11: =G11*L11 -> 0 | P11: =G11*M11 -> 0
A12: 6 | C12: CIELORRASOS | H12: =SUM(G13:G13) -> 2454560 | I12: =+H12/$H$14 -> 0.025488676 | O12: =+G12*L12 -> 0
A13: 6.01 | B13: OK | C13: Hormigon visto, maquillaje | D13: m2 | E13: 460 | F13: 5336 | G13: =+F13*E13 -> 2454560 | K13: 0 | L13: 0 | M13: =+K13+L13 -> 0 | N13: =+G13*K13 -> 0 | O13: =+H13*L13 -> 0 | P13: =+I13*M13 -> 0
A14: B | C14: SUB TOTAL ADICIONALES | G14: =SUM(G10:G13) -> 96300019 | H14: =SUM(H9:H13) -> 96300019 | I14: =+SUM(I9:I13) -> 1 | N14: =+SUM(N9:N13) -> 0 | O14: =+SUM(O9:O13) -> 2212945.2 | P14: =+SUM(P9:P13) -> 2212945.2
A16: C | C16: SUBTOTAL (B-A) | H16: =+H14-#REF! -> #REF!
C18: Precios sin IVA. Base indice CAC Diciembre 2024

Sheet Adic. N°2
F4: 45930 | I4: Certificado | J4: 2 | N4: 45930
B5: OBRA: EDIFICIO GDR 3760
B6: ADICIONALES Y DEDUCTIVOS N° 2 | I6: Avance | L6: Importe
B7: Descripción | C7: U | D7: Cant | E7: P unit | F7: Subtotal | I7: Anterior | J7: Actual | K7: Acumulado | L7: Anterior | M7: Actual | N7: Acumulado
B8: ADICIONALES
A9: 5 | B9: ESTRUCTURA RESISTENTE | G9: =SUM(F10:F11) -> 93845459 | H9: =+G9/$G$14 -> 0.97451132
A10: 5.01 | B10: Losa maciza de Hº visto - H35 (100 kg/m3 de hierro) | C10: m3 | D10: =+Computos!R12 -> 83 | E10: 888733 | F10: =+E10*D10 -> 73764839 | I10: 0.03 | J10: 0.3228 | K10: =+I10+J10 -> 0.3528 | L10: =F10*I10 -> 2212945.2 | M10: =F10*J10 -> 23811290 | N10: =F10*K10 -> 26024235
A11: 5.02 | B11: Vigas de H° visto - H35 (180 kg/m3 de hierro) | C11: m3 | D11: =+Computos!R14 -> 12 | E11: 1673385 | F11: =+E11*D11 -> 20080620 | I11: 0 | J11: 0 | K11: =+I11+J11 -> 0 | L11: =F11*I11 -> 0 | M11: =F11*J11 -> 0 | N11: =F11*K11 -> 0
A12: 6 | B12: CIELORRASOS | G12: =SUM(F13:F13) -> 2454560 | H12: =+G12/$G$14 -> 0.025488676
A13: 6.01 | B13: Hormigon visto, maquillaje | C13: m2 | D13: 460 | E13: 5336 | F13: =+E13*D13 -> 2454560 | I13: 0 | J13: 0 | K13: =+I13+J13 -> 0 | L13: =+F13*I13 -> 0 | M13: =+G13*J13 -> 0 | N13: =+H13*K13 -> 0
A14: B | B14: SUB TOTAL ADICIONALES | F14: =SUM(F10:F13) -> 96300019 | G14: =SUM(G9:G13) -> 96300019 | H14: =+SUM(H9:H13) -> 1 | L14: =+SUM(L9:L13) -> 2212945.2 | M14: =+SUM(M9:M13) -> 23811290 | N14: =+SUM(N9:N13) -> 26024235
B17: Precios sin IVA. Base indice CAC Diciembre 2024
B19: RESUMEN CERTIFICADO | K19: CERT. N° | L19: =J4 -> 2 | N19: =N4 -> 45930
B20: Descripción | M20: % | N20: IMPORTE
A21: A | B21: Presupuesto aprobado | N21: =G14 -> 96300019
A22: B | B22: Anticipo | N22: =+M22*N21 -> 0
A23: C | B23: Certificado actual | N23: =M14 -> 23811290
A24: D | B24: Desacopio | M24: =-M22 -> 0 | N24: =+M24*N23 -> 0
A25: E | B25: Subtotal certificacion actual completa (SIN IVA) | N25: =+N23+N24 -> 23811290
B26: Actualizacion por CAC por fuera de OC

Sheet Adic. N°3
F4: 45930 | I4: Certificado | J4: 3 | N4: 45958
B5: OBRA: EDIFICIO GDR 3760
B6: ADICIONALES Y DEDUCTIVOS N° 3 | I6: Avance | L6: Importe
B7: Descripción | C7: U | D7: Cant | E7: P unit | F7: Subtotal | I7: Anterior | J7: Actual | K7: Acumulado | L7: Anterior | M7: Actual | N7: Acumulado
B8: ADICIONALES
A9: 5 | B9: ESTRUCTURA RESISTENTE | G9: =SUM(F10:F11) -> 93845459 | H9: =+G9/$G$14 -> 0.97451132
A10: 5.01 | B10: Losa maciza de Hº visto - H35 (100 kg/m3 de hierro) | C10: m3 | D10: =+Computos!R12 -> 83 | E10: 888733 | F10: =+E10*D10 -> 73764839 | I10: =32.28%+3% -> 0.3528 | J10: 0.3228 | K10: =+I10+J10 -> 0.6756 | L10: =F10*I10 -> 26024235 | M10: =F10*J10 -> 23811290 | N10: =F10*K10 -> 49835525
A11: 5.02 | B11: Vigas de H° visto - H35 (180 kg/m3 de hierro) | C11: m3 | D11: =+Computos!R14 -> 12 | E11: 1673385 | F11: =+E11*D11 -> 20080620 | I11: 0 | J11: 0.566 | K11: =+I11+J11 -> 0.566 | L11: =F11*I11 -> 0 | M11: =F11*J11 -> 11365631 | N11: =F11*K11 -> 11365631
A12: 6 | B12: CIELORRASOS | G12: =SUM(F13:F13) -> 2454560 | H12: =+G12/$G$14 -> 0.025488676
A13: 6.01 | B13: Hormigon visto, maquillaje | C13: m2 | D13: 460 | E13: 5336 | F13: =+E13*D13 -> 2454560 | I13: 0 | J13: 0 | K13: =+I13+J13 -> 0 | L13: =+F13*I13 -> 0 | M13: =+G13*J13 -> 0 | N13: =+H13*K13 -> 0
A14: B | B14: SUB TOTAL ADICIONALES | F14: =SUM(F10:F13) -> 96300019 | G14: =SUM(G9:G13) -> 96300019 | H14: =+SUM(H9:H13) -> 1 | L14: =+SUM(L9:L13) -> 26024235 | M14: =+SUM(M9:M13) -> 35176921 | N14: =+SUM(N9:N13) -> 61201156
B17: Precios sin IVA. Base indice CAC Diciembre 2024
B19: RESUMEN CERTIFICADO | K19: CERT. N° | L19: =J4 -> 3 | N19: =N4 -> 45958
B20: Descripción | M20: % | N20: IMPORTE
A21: A | B21: Presupuesto aprobado | N21: =G14 -> 96300019
A22: B | B22: Anticipo | N22: =+M22*N21 -> 0
A23: C | B23: Certificado actual | N23: =M14 -> 35176921
A24: D | B24: Desacopio | M24: =-M22 -> 0 | N24: =+M24*N23 -> 0
A25: E | B25: Subtotal certificacion actual completa (SIN IVA) | N25: =+N23+N24 -> 35176921
B26: Actualizacion por CAC por fuera de OC

Sheet Computos
B2: COMPUTO AUXILIAR
B3: GDR_Computo Hormigon_Modificado
D4: Tabla resumen de Hº
B5: Elemento | C5: Unidad | D5: Cantidad | E5: Fund | F5: s/PB | G5: s/1º | H5: s/2º | I5: s/3º | J5: s/4º | K5: s/5º | L5: SDM | M5: Total m3 | O5: Proyecto orig | P5: Dif.
B6: Zapata Aislada | C6: m3 | E6: 50.82662 | F6: 0 | G6: 0 | H6: 0 | I6: 0 | J6: 0 | K6: 0 | L6: 0 | M6: 50.8 | O6: 50.8 | P6: =+M6-O6 -> 0 | T6: 50.8
B7: Vigas de Fundacion | C7: m3 | E7: 6.93345 | F7: 0 | G7: 0 | H7: 0 | I7: 0 | J7: 0 | K7: 0 | L7: 0 | M7: 6.9 | O7: 6.9 | P7: =+M7-O7 -> 0 | T7: 6.9
B8: Tabique de submuración | C8: m3 | E8: 20.097 | F8: 0 | G8: 0 | H8: 0 | I8: 0 | J8: 0 | K8: 0 | L8: 0 | M8: 20.1 | O8: 20.1 | P8: =+M8-O8 -> 0 | T8: 20.1
B9: Platea | C9: m3 | E9: 37.58656 | F9: 0 | G9: 0 | H9: 0 | I9: 0 | J9: 0 | K9: 0 | L9: 0 | M9: 37.6 | O9: 37.6 | P9: =+M9-O9 -> 0 | T9: 37.6
B10: Zapata corrida tabique | C10: m3 | E10: 11.136 | F10: 0 | G10: 0 | H10: 0 | I10: 0 | J10: 0 | K10: 0 | L10: 0 | M10: 11.1 | O10: 11.1 | P10: =+M10-O10 -> 0 | T10: 11.1
B11: Losa | C11: m3 | E11: 0 | F11: 11.997384 | G11: 0 | H11: 0 | I11: 0 | J11: 0 | K11: 0 | L11: 2.3274 | M11: 14.3 | O11: 89.3 | P11: =+M11-O11 -> -75 | R11: =-ROUNDUP(P11,0) -> 75 | T11: 89.3
B12: Losa vista | C12: m3 | F12: 7.4544 | G12: 26.797512 | H12: 26.797512 | I12: 26.866728 | J12: 22.882476 | K12: 0 | L12: 2.91525 | M12: 113.7 | O12: 31.6 | P12: =+M12-O12 -> 82.1 | R12: =+ROUNDUP(P12,0) -> 83 | T12: 31.6
B13: Viga | C13: m3 | E13: 0 | F13: 17.221935 | G13: 3.17522 | H13: 3.17522 | I13: 3.27422 | J13: 3.89298 | K13: 1.446 | L13: 0 | M13: 32.2 | O13: 40.5 | P13: =+M13-O13 -> -8.3 | R13: =-ROUNDUP(P13,0) -> 9 | T13: 40.5
B14: Viga vista | C14: m3 | E14: 0 | F14: 15.9256 | G14: 7.30776 | H14: 7.30776 | I14: 7.3667 | J14: 7.04496 | K14: 1.70835 | L14: 0 | M14: 46.7 | O14: 35.5 | P14: =+M14-O14 -> 11.2 | R14: =+ROUNDUP(P14,0) -> 12 | T14: 35.5
B15: Tabiques | C15: m3 | E15: 0 | F15: 6.314925 | G15: 3.11067 | H15: 3.11067 | I15: 3.11067 | J15: 3.11067 | K15: 2.870835 | L15: 0 | M15: 21.6 | O15: 23.2 | P15: =+M15-O15 -> -1.6 | T15: 23.2
B16: Columna | C16: m3 | E16: 0 | F16: 10.41624 | G16: 7.24699 | H16: 7.24699 | I16: 7.06996 | J16: 6.66532 | K16: 0.80478 | L16: 0 | M16: 39.5 | O16: 38.2 | P16: =+M16-O16 -> 1.3 | T16: 38.2
B17: Columna vista | C17: m3 | F17: 0.76728 | G17: 0.58448 | H17: 0.58448 | I17: 0.58448 | J17: 0.58448 | K17: 0.53248 | M17: 3.6 | O17: 3.1 | P17: =+M17-O17 -> 0.5 | T17: 3.1
B18: Troncos de Zapatas | C18: m3 | E18: 15.53471 | F18: 0 | G18: 0 | H18: 0 | I18: 0 | J18: 0 | K18: 0 | L18: 0 | M18: 15.5 | O18: 15.5 | P18: =+M18-O18 -> 0 | T18: 15.5
B19: Escaleras | C19: m3 | E19: 0 | F19: 1.875 | G19: 1.8375 | H19: 1.8375 | I19: 1.8125 | J19: 1.875 | K19: 0 | L19: 0 | M19: 9.2 | O19: 9.2 | P19: =+M19-O19 -> 0 | T19: 9.2
B20: Tanque | E20: 0 | F20: 0 | G20: 0 | H20: 0 | I20: 0 | J20: 0 | K20: 0 | L20: 0 | M20: 0 | O20: 5.1 | P20: =+M20-O20 -> -5.1 | R20: =-ROUNDUP(P20,0) -> 6 | T20: 5.1
E21: =+SUM(E6:E20) -> 142.11434 | F21: =+SUM(F6:F20) -> 71.972764 | G21: =+SUM(G6:G20) -> 50.060132 | H21: =+SUM(H6:H20) -> 50.060132 | I21: =+SUM(I6:I20) -> 50.085258 | J21: =+SUM(J6:J20) -> 46.055886 | K21: =+SUM(K6:K20) -> 7.362445 | L21: =+SUM(L6:L20) -> 5.24265 | M21: =+SUM(M6:M20) -> 422.8 | O21: =+SUM(O6:O20) -> 417.7 | P21: =+SUM(P6:P20) -> 5.1
