Workbook
Name \0: #REF!
Name \c: #REF!
Name \E: #REF!
Name \i: #REF!
Name \j: #REF!
Name \m: #REF!
Name \P: #REF!
Name \P: #REF!
Name \P: #REF!
Name \P: #REF!
Name \P: #REF!
Name \P: #REF!
Name \P: #REF!
Name \P: #REF!
Name \P: #REF!
Name \r: #N/A
Name \x: #REF!
Name \z: #REF!
Name __________ben1: #REF!
Name __________ben1: #REF!
Name __________ben1: #REF!
Name __________ben1: #REF!
Name __________ben1: #REF!
Name __________ben1: #REF!
Name __________ben1: #REF!
Name __________ben1: #REF!
Name __________ben1: #REF!
Name __________ben10: #REF!
Name __________ben10: #REF!
Name __________ben10: #REF!
Name __________ben10: #REF!
Name __________ben10: #REF!
Name __________ben10: #REF!
Name __________ben10: #REF!
Name __________ben10: #REF!
Name __________ben10: #REF!
Name __________ben15: #REF!
Name __________ben15: #REF!
Name __________ben15: #REF!
Name __________ben15: #REF!
Name __________ben15: #REF!
Name __________ben15: #REF!
Name __________ben15: #REF!
Name __________ben15: #REF!
Name __________ben15: #REF!
Name __________BEN2: #REF!
Name __________ben20: #REF!
Name __________ben20: #REF!
Name __________ben20: #REF!
Name __________ben20: #REF!
Name __________ben20: #REF!
Name __________ben20: #REF!
Name __________ben20: #REF!
Name __________ben20: #REF!
Name __________ben20: #REF!
Name __________ben25: #REF!
Name __________ben25: #REF!
Name __________ben25: #REF!
Name __________ben25: #REF!
Name __________ben25: #REF!

Sheet SVD 4140_Pto. 01_Cert. 01
F1: DÓLAR BNA | G1: DÓLAR MEP
F2: 1005 | G2: 1170
F4: 45628
B5: OBRA: EDIFICIO EL SALVADOR 4140 | I5: Certificado | J5: 1 | N5: 45958
B6: PRESUPUESTO OBRA CIVIL
B7: Descripción | C7: U | D7: Cant | E7: P unit | F7: Subtotal | I7: Avance | L7: Importe
B8: PRESUPUESTO 02 - ALBANILERIA + INSTALACIONES + TERMINACIONES | I8: Anterior | J8: Actual | K8: Acumulado | L8: Anterior | M8: Actual | N8: Acumulado
A9: 4 | B9: ALBAÑILERIA | G9: =+SUM(F10:F17) -> 54302890 | H9: =+G9/$G$185 -> 0.073815487
A10: 4.01 | B10: Muro tipo 1 (interiores, divisorio de locales) e: 10 cm - Ladrillo hueco 08 x 18 x 33 | C10: m2 | D10: 819 | E10: 18993 | F10: =+D10*E10 -> 15555267 | K10: =+I10+J10 -> 0 | L10: =+F10*I10 -> 0 | M10: =+F10*J10 -> 0 | N10: =+F10*K10 -> 0
A11: 4.02 | B11: Muro tipo 2 y 3 (medianera, caja de escaleras y ascensor) e: 15 cm - Ladrillo hueco portante 12 x 19 x 33 | C11: m2 | D11: 612 | E11: 25172 | F11: =+D11*E11 -> 15405264 | K11: =+I11+J11 -> 0 | L11: =+F11*I11 -> 0 | M11: =+F11*J11 -> 0 | N11: =+F11*K11 -> 0
A12: 4.03 | B12: Muro tipo 4 (divisorio de unidades y fachas) e: 15 cm - Ladrillo hueco 12 x 18 x 33 | C12: m2 | D12: 636 | E12: 21109 | F12: =+D12*E12 -> 13425324 | K12: =+I12+J12 -> 0 | L12: =+F12*I12 -> 0 | M12: =+F12*J12 -> 0 | N12: =+F12*K12 -> 0
A13: 4.04 | B13: Enchape medianeras existentes - Contemplamos picado zonas sueltas y enchape con ladrillo comun para PB | C13: m2 | D13: 195 | E13: 15092 | F13: =+D13*E13 -> 2942940 | K13: =+I13+J13 -> 0 | L13: =+F13*I13 -> 0 | M13: =+F13*J13 -> 0 | N13: =+F13*K13 -> 0
A14: 4.05 | B14: Mamposteria cribada de ladrillo visto en balcones | C14: m2 | D14: 30.054 | E14: 67420 | F14: =+D14*E14 -> 2026240.7 | K14: =+I14+J14 -> 0 | L14: =+F14*I14 -> 0 | M14: =+F14*J14 -> 0 | N14: =+F14*K14 -> 0
A15: 4.06 | B15: Bloque de H° con masillado de hormigon | C15: m2 | D15: 24 | E15: 54908 | F15: =+D15*E15 -> 1317792 | K15: =+I15+J15 -> 0 | L15: =+F15*I15 -> 0 | M15: =+F15*J15 -> 0 | N15: =+F15*K15 -> 0
A16: 4.07 | B16: Cordón de hormigón en umbrales carpinterías | C16: ml | D16: 81 | E16: 30989 | F16: =+D16*E16 -> 2510109 | K16: =+I16+J16 -> 0 | L16: =+F16*I16 -> 0 | M16: =+F16*J16 -> 0 | N16: =+F16*K16 -> 0
A17: 4.08 | B17: Pozo de bombeo pluvial y cloacal | C17: gl | D17: 1 | E17: 1119953 | F17: =+D17*E17 -> 1119953 | K17: =+I17+J17 -> 0 | L17: =+F17*I17 -> 0 | M17: =+F17*J17 -> 0 | N17: =+F17*K17 -> 0
A18: 5 | B18: AISLACIONES | G18: =+SUM(F19:F25) -> 35966419 | H18: =+G18/$G$185 -> 0.048890193
A19: 5.01 | B19: Aislación hidrófuga horizontal (baños) - Inc. membrana geotextil y 35% en concepto de babetas | C19: m2 | D19: 139.05 | E19: 21800 | F19: =+D19*E19 -> 3031290 | K19: =+I19+J19 -> 0 | L19: =+F19*I19 -> 0 | M19: =+F19*J19 -> 0 | N19: =+F19*K19 -> 0
A20: 5.02 | B20: Azotado hidrofugo - Sobre medianeras existentes | C20: m2 | D20: 300 | E20: 5376 | F20: =+D20*E20 -> 1612800 | K20: =+I20+J20 -> 0 | L20: =+F20*I20 -> 0 | M20: =+F20*J20 -> 0 | N20: =+F20*K20 -> 0
A21: 5.03 | B21: Azotado hidrofugo - Contrapiso de vereda | C21: m2 | D21: 48 | E21: 5376 | F21: =+D21*E21 -> 258048 | K21: =+I21+J21 -> 0 | L21: =+F21*I21 -> 0 | M21: =+F21*J21 -> 0 | N21: =+F21*K21 -> 0
A22: 5.04 | B22: Aislación térmica en terrazas, eps e:2,00 cm | C22: m2 | D22: 262 | E22: 4403 | F22: =+D22*E22 -> 1153586 | K22: =+I22+J22 -> 0 | L22: =+F22*I22 -> 0 | M22: =+F22*J22 -> 0 | N22: =+F22*K22 -> 0
A23: 5.05 | B23: Barrera de vapor | C23: m2 | D23: 510 | E23: 3578 | F23: =+D23*E23 -> 1824780 | K23: =+I23+J23 -> 0 | L23: =+F23*I23 -> 0 | M23: =+F23*J23 -> 0 | N23: =+F23*K23 -> 0
A24: 5.06 | B24: Membrana asfaltica geotextil 4mm - Balcones y azotea - Inc. 20% en concepto de babetas | C24: m2 | D24: 510 | E24: 21800 | F24: =+D24*E24 -> 11118000 | K24: =+I24+J24 -> 0 | L24: =+F24*I24 -> 0 | M24: =+F24*J24 -> 0 | N24: =+F24*K24 -> 0
A25: 5.07 | B25: Impermeabilización de subsuelo | C25: gl | D25: 1 | E25: 16967915 | F25: =+D25*E25 -> 16967915 | J25: 1 | K25: =+I25+J25 -> 1 | L25: =+F25*I25 -> 0 | M25: =+F25*J25 -> 16967915 | N25: =+F25*K25 -> 16967915
A26: 6 | B26: CUBIERTAS | G26: =+SUM(F27) -> 2433900 | H26: =+G26/$G$185 -> 0.0033084706
A27: 6.02 | B27: Babeta de chapa galvanizada en medianeras | C27: ml | D27: 60 | E27: 40565 | F27: =+D27*E27 -> 2433900 | K27: =+I27+J27 -> 0 | L27: =+F27*I27 -> 0 | M27: =+F27*J27 -> 0 | N27: =+F27*K27 -> 0
A28: 7 | B28: REVOQUES | G28: =+SUM(F29:F36) -> 1.3639056e+08 | H28: =+G28/$G$185 -> 0.18539962
A29: 7.01 | B29: Revoque Grueso Impermeable Exterior proyectable | C29: m2 | D29: 678.252 | E29: 16571 | F29: =+D29*E29 -> 11239314 | K29: =+I29+J29 -> 0 | L29: =+F29*I29 -> 0 | M29: =+F29*J29 -> 0 | N29: =+F29*K29 -> 0
A30: 7.02 | B30: Revoque Grueso Impermeable Exterior a mas de 3m proyectable - Medianero y fachadas | C30: m2 | D30: 876.0812 | E30: 22183 | F30: =+D30*E30 -> 19434109 | K30: =+I30+J30 -> 0 | L30: =+F30*I30 -> 0 | M30: =+F30*J30 -> 0 | N30: =+F30*K30 -> 0
A31: 7.03 | B31: Buña en revoque | C31: ml | D31: 182 | E31: 10806 | F31: =+D31*E31 -> 1966692 | K31: =+I31+J31 -> 0 | L31: =+F31*I31 -> 0 | M31: =+F31*J31 -> 0 | N31: =+F31*K31 -> 0
A32: 7.04 | B32: Revoque Grueso Interior + fino | C32: m2 | D32: 995.8511 | E32: 26530 | F32: =+D32*E32 -> 26419930 | K32: =+I32+J32 -> 0 | L32: =+F32*I32 -> 0 | M32: =+F32*J32 -> 0 | N32: =+F32*K32 -> 0
A33: 7.05 | B33: Yeso interior | C33: m2 | D33: 2514.897 | E33: 22566 | F33: =+D33*E33 -> 56751166 | K33: =+I33+J33 -> 0 | L33: =+F33*I33 -> 0 | M33: =+F33*J33 -> 0 | N33: =+F33*K33 -> 0
A34: 7.06 | B34: Arista en yeso | C34: ml | D34: 509.9 | E34: 12771 | F34: =+D34*E34 -> 6511932.9 | K34: =+I34+J34 -> 0 | L34: =+F34*I34 -> 0 | M34: =+F34*J34 -> 0 | N34: =+F34*K34 -> 0
A35: 7.07 | B35: Provisión y colocación de guardacanto yesero | C35: u | D35: 198 | E35: 14947 | F35: =+D35*E35 -> 2959506 | K35: =+I35+J35 -> 0 | L35: =+F35*I35 -> 0 | M35: =+F35*J35 -> 0 | N35: =+F35*K35 -> 0
A36: 7.08 | B36: Revoque Grueso Impermeable Interior b/ revestimiento | C36: m2 | D36: 670.322 | E36: 16571 | F36: =+D36*E36 -> 11107906 | K36: =+I36+J36 -> 0 | L36: =+F36*I36 -> 0 | M36: =+F36*J36 -> 0 | N36: =+F36*K36 -> 0
A37: 8 | B37: CONTRAPISOS Y CARPETAS | G37: =+SUM(F38:F45) -> 44788107 | H37: =+G37/$G$185 -> 0.060881768
A38: 8.01 | B38: Contrapiso de cascotes en SS e: 15 cm | C38: m2 | D38: 104 | E38: 31920 | F38: =+D38*E38 -> 3319680 | J38: 0.5 | K38: =+I38+J38 -> 0.5 | L38: =+F38*I38 -> 0 | M38: =+F38*J38 -> 1659840 | N38: =+F38*K38 -> 1659840
A39: 8.02 | B39: Contrapiso de cascote s/terreno natural e: 20 cm - Incluye film de polietileno | C39: m2 | D39: 48 | E39: 37268 | F39: =+D39*E39 -> 1788864 | K39: =+I39+J39 -> 0 | L39: =+F39*I39 -> 0 | M39: =+F39*J39 -> 0 | N39: =+F39*K39 -> 0
A40: 8.03 | B40: Contrapiso de cascotes en azoteas c/pendiente e: 15 cm | C40: m2 | D40: 235 | E40: 32410 | F40: =+D40*E40 -> 7616350 | K40: =+I40+J40 -> 0 | L40: =+F40*I40 -> 0 | M40: =+F40*J40 -> 0 | N40: =+F40*K40 -> 0
A41: 8.04 | B41: Contrapiso - Carpeta monolitico e: 7 cm | C41: m2 | D41: 878 | E41: 19006 | F41: =+D41*E41 -> 16687268 | K41: =+I41+J41 -> 0 | L41: =+F41*I41 -> 0 | M41: =+F41*J41 -> 0 | N41: =+F41*K41 -> 0
A42: 8.05 | B42: Carpeta en PB y balcones, baños y azoteas e: 3,00 cm | C42: m2 | D42: 564 | E42: 12439 | F42: =+D42*E42 -> 7015596 | K42: =+I42+J42 -> 0 | L42: =+F42*I42 -> 0 | M42: =+F42*J42 -> 0 | N42: =+F42*K42 -> 0
A43: 8.06 | B43: Carpeta sobre membrana | C43: m2 | D43: 438 | E43: 12439 | F43: =+D43*E43 -> 5448282 | K43: =+I43+J43 -> 0 | L43: =+F43*I43 -> 0 | M43: =+F43*J43 -> 0 | N43: =+F43*K43 -> 0
A44: 8.07 | B44: Banquinas para cocinas | C44: gl | D44: 1 | E44: 2426924 | F44: =+D44*E44 -> 2426924 | K44: =+I44+J44 -> 0 | L44: =+F44*I44 -> 0 | M44: =+F44*J44 -> 0 | N44: =+F44*K44 -> 0
A45: 8.08 | B45: Banquinas para bombas y tanques en SB | C45: gl | D45: 1 | E45: 485143 | F45: =+D45*E45 -> 485143 | K45: =+I45+J45 -> 0 | L45: =+F45*I45 -> 0 | M45: =+F45*J45 -> 0 | N45: =+F45*K45 -> 0
A46: 9 | B46: ESCALERAS | G46: =+SUM(F47:F50) -> 5769056.6 | H46: =+G46/$G$185 -> 0.0078420454
A47: 9.01 | B47: Cemento alisado arrodillado en escaleras | C47: gl | D47: 1 | E47: 2024643 | F47: =+D47*E47 -> 2024643 | K47: =+I47+J47 -> 0 | L47: =+F47*I47 -> 0 | M47: =+F47*J47 -> 0 | N47: =+F47*K47 -> 0
A48: 9.02 | B48: Provisión nariz escalera, hierro angulo 5/8 x 1/8" | C48: ml | D48: 122 | E48: 18814 | F48: =+D48*E48 -> 2295308 | K48: =+I48+J48 -> 0 | L48: =+F48*I48 -> 0 | M48: =+F48*J48 -> 0 | N48: =+F48*K48 -> 0
A49: 9.03 | B49: Zócalo de concreto | C49: ml | D49: 155 | E49: 5376 | F49: =+D49*E49 -> 833280 | K49: =+I49+J49 -> 0 | L49: =+F49*I49 -> 0 | M49: =+F49*J49 -> 0 | N49: =+F49*K49 -> 0
A50: 9.04 | B50: Provisión y colocación de Rodapie/ Zócalo rampante en placa cementicia | C50: ml | D50: 31.2 | E50: 19738 | F50: =+D50*E50 -> 615825.6 | K50: =+I50+J50 -> 0 | L50: =+F50*I50 -> 0 | M50: =+F50*J50 -> 0 | N50: =+F50*K50 -> 0
A51: 10 | B51: VENTILACIONES | G51: =+SUM(F52:F55) -> 4669278 | H51: =+G51/$G$185 -> 0.0063470845
A52: 10.01 | B52: Ventilación Conducto Humos. Incluye toma de aire en PB - No aplica s/proyecto | C52: gl | D52: 0 | E52: 0 | F52: =+D52*E52 -> 0 | K52: =+I52+J52 -> 0 | L52: =+F52*I52 -> 0 | M52: =+F52*J52 -> 0 | N52: =+F52*K52 -> 0
A53: 10.02 | B53: Ventilación Baños - En caño Ø 110 | C53: gl | D53: 1 | E53: 2199545 | F53: =+D53*E53 -> 2199545 | K53: =+I53+J53 -> 0 | L53: =+F53*I53 -> 0 | M53: =+F53*J53 -> 0 | N53: =+F53*K53 -> 0
A54: 10.03 | B54: Colocación de rejillas de inyección y extracción - No aplica s/proyecto | C54: un | D54: 0 | E54: 0 | F54: =+D54*E54 -> 0 | K54: =+I54+J54 -> 0 | L54: =+F54*I54 -> 0 | M54: =+F54*J54 -> 0 | N54: =+F54*K54 -> 0
A55: 10.04 | B55: Sombreretes en chapa prepintada C25 | C55: u | D55: 7 | E55: 352819 | F55: =+D55*E55 -> 2469733 | K55: =+I55+J55 -> 0 | L55: =+F55*I55 -> 0 | M55: =+F55*J55 -> 0 | N55: =+F55*K55 -> 0
A56: 11 | B56: PISOS - PROVISION A CARGO DEL COMITENTE | G56: =+SUM(F57:F63) -> 48040802 | H56: =+G56/$G$185 -> 0.06530325
A57: 11.01 | B57: Colocación de travertino en hall PB - Provisión a cargo del comitente | C57: m2 | D57: 30 | E57: 21948 | F57: =+D57*E57 -> 658440 | K57: =+I57+J57 -> 0 | L57: =+F57*I57 -> 0 | M57: =+F57*J57 -> 0 | N57: =+F57*K57 -> 0
A58: 11.02 | B58: Colocación de porcelanato en paliers, terraza y espacios comunes - Provisión a cargo del comitente | C58: m2 | D58: 185 | E58: 21948 | F58: =+D58*E58 -> 4060380 | K58: =+I58+J58 -> 0 | L58: =+F58*I58 -> 0 | M58: =+F58*J58 -> 0 | N58: =+F58*K58 -> 0
A59: 11.03 | B59: Colocación de porcelanato en UF - Provisión a cargo del comitente | C59: m2 | D59: 942 | E59: 21948 | F59: =+D59*E59 -> 20675016 | K59: =+I59+J59 -> 0 | L59: =+F59*I59 -> 0 | M59: =+F59*J59 -> 0 | N59: =+F59*K59 -> 0
A60: 11.04 | B60: Colocación de porcelanato en baños - Provisión a cargo del comitente | C60: m2 | D60: 110 | E60: 25799 | F60: =+D60*E60 -> 2837890 | K60: =+I60+J60 -> 0 | L60: =+F60*I60 -> 0 | M60: =+F60*J60 -> 0 | N60: =+F60*K60 -> 0
A61: 11.05 | B61: Provisión y ejecución de alisado de cemento rodillado | C61: m2 | D61: 128 | E61: 16080 | F61: =+D61*E61 -> 2058240 | K61: =+I61+J61 -> 0 | L61: =+F61*I61 -> 0 | M61: =+F61*J61 -> 0 | N61: =+F61*K61 -> 0
A62: 11.06 | B62: Colocación de baldoson de vereda - Provisión a cargo del comitente | C62: m2 | D62: 48 | E62: 21948 | F62: =+D62*E62 -> 1053504 | K62: =+I62+J62 -> 0 | L62: =+F62*I62 -> 0 | M62: =+F62*J62 -> 0 | N62: =+F62*K62 -> 0
A63: 11.07 | B63: Provisión y ejecución de pavimento e: 18 cm, incluye malla Q188 | C63: m2 | D63: 226 | E63: 73882 | F63: =+D63*E63 -> 16697332 | K63: =+I63+J63 -> 0 | L63: =+F63*I63 -> 0 | M63: =+F63*J63 -> 0 | N63: =+F63*K63 -> 0
A64: 12 | B64: ZOCALOS Y SOLIAS - PROVISION A CARGO DEL COMITENTE | G64: =+SUM(F65:F69) -> 11022518 | H64: =+G64/$G$185 -> 0.014983227
A65: 12.01 | B65: Provisión y colocación de zocalos de Madera (MDF) h: 7 cm | C65: ml | D65: 779 | E65: 7422 | F65: =+D65*E65 -> 5781738 | K65: =+I65+J65 -> 0 | L65: =+F65*I65 -> 0 | M65: =+F65*J65 -> 0 | N65: =+F65*K65 -> 0
A66: 12.02 | B66: Zócalo de concreto | C66: ml | D66: 155 | E66: 5376 | F66: =+D66*E66 -> 833280 | K66: =+I66+J66 -> 0 | L66: =+F66*I66 -> 0 | M66: =+F66*J66 -> 0 | N66: =+F66*K66 -> 0
A67: 12.03 | B67: Colocación de zocalo de porcelanico - Provisión a cargo del comitente | C67: ml | D67: 37 | E67: 7052 | F67: =+D67*E67 -> 260924 | K67: =+I67+J67 -> 0 | L67: =+F67*I67 -> 0 | M67: =+F67*J67 -> 0 | N67: =+F67*K67 -> 0
A68: 12.04 | B68: Colocación de zocalo de porcelanato en palieres - Provisión a cargo del comitente | C68: ml | D68: 433 | E68: 7052 | F68: =+D68*E68 -> 3053516 | K68: =+I68+J68 -> 0 | L68: =+F68*I68 -> 0 | M68: =+F68*J68 -> 0 | N68: =+F68*K68 -> 0
A69: 12.05 | B69: Colocación de zocalo de porcelanato en terraza y espacios comunes - Provisión a cargo del comitente | C69: ml | D69: 155 | E69: 7052 | F69: =+D69*E69 -> 1093060 | K69: =+I69+J69 -> 0 | L69: =+F69*I69 -> 0 | M69: =+F69*J69 -> 0 | N69: =+F69*K69 -> 0
A70: 13 | B70: REVESTIMIENTOS - PROVISION A CARGO DEL COMITENTE | G70: =+SUM(F71:F74) -> 19433086 | H70: =+G70/$G$185 -> 0.026415956
A71: 13.01 | B71: Revestimiento en baños - Provisión a cargo del comitente | C71: m2 | D71: 511 | E71: 25799 | F71: =+D71*E71 -> 13183289 | K71: =+I71+J71 -> 0 | L71: =+F71*I71 -> 0 | M71: =+F71*J71 -> 0 | N71: =+F71*K71 -> 0
A72: 13.02 | B72: Revestimiento en cocinas - Provisión a cargo del comitente | C72: m2 | D72: 40 | E72: 25799 | F72: =+D72*E72 -> 1031960 | K72: =+I72+J72 -> 0 | L72: =+F72*I72 -> 0 | M72: =+F72*J72 -> 0 | N72: =+F72*K72 -> 0
A73: 13.03 | B73: Revestimiento tejuela exterior - Provisión a cargo del comitente | C73: m2 | D73: 147.601 | E73: 29881 | F73: =+D73*E73 -> 4410465.5 | K73: =+I73+J73 -> 0 | L73: =+F73*I73 -> 0 | M73: =+F73*J73 -> 0 | N73: =+F73*K73 -> 0
A74: 13.04 | B74: Provisión y colocación de perfileria de aluminio tipo ATRIM L anod. Natural | C74: u | D74: 41 | E74: 19692 | F74: =+D74*E74 -> 807372 | K74: =+I74+J74 -> 0 | L74: =+F74*I74 -> 0 | M74: =+F74*J74 -> 0 | N74: =+F74*K74 -> 0
A75: 14 | B75: CIELORRASOS | G75: =+SUM(F76:F82) -> 50296169 | H75: =+G75/$G$185 -> 0.068369036
A76: 14.01 | B76: Cielorraso junta tomada placa STD | C76: m2 | D76: 334.9152 | E76: 29270 | F76: =+D76*E76 -> 9802967.9 | K76: =+I76+J76 -> 0 | L76: =+F76*I76 -> 0 | M76: =+F76*J76 -> 0 | N76: =+F76*K76 -> 0
A77: 14.02 | B77: Cielorraso junta tomada placa RH | C77: m2 | D77: 280.3913 | E77: 33967 | F77: =+D77*E77 -> 9524051.3 | K77: =+I77+J77 -> 0 | L77: =+F77*I77 -> 0 | M77: =+F77*J77 -> 0 | N77: =+F77*K77 -> 0
A78: 14.03 | B78: Cajon en junta tomada placa STD | C78: ml | D78: 60.8 | E78: 29270 | F78: =+D78*E78 -> 1779616 | K78: =+I78+J78 -> 0 | L78: =+F78*I78 -> 0 | M78: =+F78*J78 -> 0 | N78: =+F78*K78 -> 0
A79: 14.04 | B79: Buña perimetral / Cantoneras | C79: ml | D79: 1058.38 | E79: 7873 | F79: =+D79*E79 -> 8332625.7 | K79: =+I79+J79 -> 0 | L79: =+F79*I79 -> 0 | M79: =+F79*J79 -> 0 | N79: =+F79*K79 -> 0
A80: 14.05 | B80: Aplicado de yeso interior | C80: m2 | D80: 504.1222 | E80: 23364 | F80: =+D80*E80 -> 11778311 | K80: =+I80+J80 -> 0 | L80: =+F80*I80 -> 0 | M80: =+F80*J80 -> 0 | N80: =+F80*K80 -> 0
A81: 14.06 | B81: Buña en yeso | C81: ml | D81: 555.99 | E81: 12771 | F81: =+D81*E81 -> 7100548.3 | K81: =+I81+J81 -> 0 | L81: =+F81*I81 -> 0 | M81: =+F81*J81 -> 0 | N81: =+F81*K81 -> 0
A82: 14.07 | B82: H° Visto - Maquillaje para recibir pintura | C82: m2 | D82: 429.0778 | E82: 4610 | F82: =+D82*E82 -> 1978048.7 | K82: =+I82+J82 -> 0 | L82: =+F82*I82 -> 0 | M82: =+F82*J82 -> 0 | N82: =+F82*K82 -> 0
A83: 15 | B83: PINTURA | G83: =+SUM(F84:F92) -> 0 | H83: =+G83/$G$185 -> 0
A84: 15.01 | B84: Látex interior para paredes Bco. mate (enduido parcial) | C84: m2 | D84: 2670 | E84: 0 | F84: =+D84*E84 -> 0 | K84: =+I84+J84 -> 0 | L84: =+F84*I84 -> 0 | M84: =+F84*J84 -> 0 | N84: =+F84*K84 -> 0
A85: 15.02 | B85: Látex interior para paredes Bco. mate (s/enduido) | C85: m2 | D85: 961 | E85: 0 | F85: =+D85*E85 -> 0 | K85: =+I85+J85 -> 0 | L85: =+F85*I85 -> 0 | M85: =+F85*J85 -> 0 | N85: =+F85*K85 -> 0
A86: 15.03 | B86: Látex para cielorraso Bco. mate (enduido parcial) | C86: m2 | D86: 518 | E86: 0 | F86: =+D86*E86 -> 0 | K86: =+I86+J86 -> 0 | L86: =+F86*I86 -> 0 | M86: =+F86*J86 -> 0 | N86: =+F86*K86 -> 0
A87: 15.04 | B87: Látex para cielorraso Bco. mate (enduido completo) | C87: m2 | D87: 612 | E87: 0 | F87: =+D87*E87 -> 0 | K87: =+I87+J87 -> 0 | L87: =+F87*I87 -> 0 | M87: =+F87*J87 -> 0 | N87: =+F87*K87 -> 0
A88: 15.05 | B88: Latex interior cielorraso sobre H° | C88: m2 | D88: 422 | E88: 0 | F88: =+D88*E88 -> 0 | K88: =+I88+J88 -> 0 | L88: =+F88*I88 -> 0 | M88: =+F88*J88 -> 0 | N88: =+F88*K88 -> 0
A89: 15.07 | B89: Revestimiento plastico tipo Quimtex en exteriores y PB | C89: m2 | D89: 678.252 | E89: 0 | F89: =+D89*E89 -> 0 | K89: =+I89+J89 -> 0 | L89: =+F89*I89 -> 0 | M89: =+F89*J89 -> 0 | N89: =+F89*K89 -> 0
A90: 15.08 | B90: Revestimiento plastico tipo Quimtex en exteriores a mas de 3m de altura, incluye medianeras | C90: m2 | D90: 728.4802 | E90: 0 | F90: =+D90*E90 -> 0 | K90: =+I90+J90 -> 0 | L90: =+F90*I90 -> 0 | M90: =+F90*J90 -> 0 | N90: =+F90*K90 -> 0
A91: 15.09 | B91: Esmalte sintético en puertas placa, chapa y de ascensor | C91: un | D91: 76 | E91: 0 | F91: =+D91*E91 -> 0 | K91: =+I91+J91 -> 0 | L91: =+F91*I91 -> 0 | M91: =+F91*J91 -> 0 | N91: =+F91*K91 -> 0
A92: 15.1 | B92: Convertidor y esmalte sintentico en barandas - Escalera, balcones, porton, medidores y SDM | C92: gl | D92: 1 | E92: 0 | F92: =+D92*E92 -> 0 | K92: =+I92+J92 -> 0 | L92: =+F92*I92 -> 0 | M92: =+F92*J92 -> 0 | N92: =+F92*K92 -> 0
A93: 16 | B93: MARMOLES Y GRANITOS - PROVISION Y COLOCACION A CARGO DEL COMITENTE | G93: =+SUM(F94) -> 0 | H93: =+G93/$G$185 -> 0
E94: 0 | F94: =+D94*E94 -> 0 | K94: =+I94+J94 -> 0 | L94: =+F94*I94 -> 0 | M94: =+F94*J94 -> 0 | N94: =+F94*K94 -> 0
A95: 17 | B95: CARPINTERIA - PROVISION A CARGO DEL COMITENTE | G95: =+SUM(F96:F99) -> 7258243 | H95: =+G95/$G$185 -> 0.0098663395
A96: 17.01 | B96: Amure de puertas placa Provisión a cargo del comitente | C96: u | D96: 47 | E96: 64232 | F96: =+D96*E96 -> 3018904 | K96: =+I96+J96 -> 0 | L96: =+F96*I96 -> 0 | M96: =+F96*J96 -> 0 | N96: =+F96*K96 -> 0
A97: 17.02 | B97: Amure de puertas de chapa e ingresos depto - Provisión a cargo del comitente | C97: u | D97: 23 | E97: 64232 | F97: =+D97*E97 -> 1477336 | K97: =+I97+J97 -> 0 | L97: =+F97*I97 -> 0 | M97: =+F97*J97 -> 0 | N97: =+F97*K97 -> 0
A98: 17.03 | B98: Amure de premarcos - Provisión a cargo del comitente | C98: u | D98: 51 | E98: 41296 | F98: =+D98*E98 -> 2106096 | K98: =+I98+J98 -> 0 | L98: =+F98*I98 -> 0 | M98: =+F98*J98 -> 0 | N98: =+F98*K98 -> 0
A99: 17.04 | B99: Amure Puertas de Ascensor - Provisión a cargo del comitente | C99: u | D99: 7 | E99: 93701 | F99: =+D99*E99 -> 655907 | K99: =+I99+J99 -> 0 | L99: =+F99*I99 -> 0 | M99: =+F99*J99 -> 0 | N99: =+F99*K99 -> 0
A100: 18 | B100: INSTALACION ELECTRICA | G100: =+SUM(F101:F130) -> 99277732 | H100: =+G100/$G$185 -> 0.13495109
A101: 18.01 | B101: Tendido y cableado boca Iluminación | C101: u | D101: 392 | E101: 59948 | F101: =+D101*E101 -> 23499616 | J101: 0.2 | K101: =+I101+J101 -> 0.2 | L101: =+F101*I101 -> 0 | M101: =+F101*J101 -> 4699923.2 | N101: =+F101*K101 -> 4699923.2
...

Sheet SVD 4140_Pto. 01_Cert. 02
F1: DÓLAR BNA | G1: DÓLAR MEP
F2: 1005 | G2: 1170
F4: 45628
B5: OBRA: EDIFICIO EL SALVADOR 4140 | I5: Certificado | J5: 2 | N5: 45988
B6: PRESUPUESTO OBRA CIVIL
B7: Descripción | C7: U | D7: Cant | E7: P unit | F7: Subtotal | I7: Avance | L7: Importe
B8: PRESUPUESTO 02 - ALBANILERIA + INSTALACIONES + TERMINACIONES | I8: Anterior | J8: Actual | K8: Acumulado | L8: Anterior | M8: Actual | N8: Acumulado
A9: 4 | B9: ALBAÑILERIA | G9: =+SUM(F10:F17) -> 54302890 | H9: =+G9/$G$185 -> 0.073815487
A10: 4.01 | B10: Muro tipo 1 (interiores, divisorio de locales) e: 10 cm - Ladrillo hueco 08 x 18 x 33 | C10: m2 | D10: 819 | E10: 18993 | F10: =+D10*E10 -> 15555267 | I10: =+'SVD 4140_Pto. 01_Cert. 01'!K10 -> 0 | J10: 0.15 | K10: =+I10+J10 -> 0.15 | L10: =+F10*I10 -> 0 | M10: =+F10*J10 -> 2333290 | N10: =+F10*K10 -> 2333290
A11: 4.02 | B11: Muro tipo 2 y 3 (medianera, caja de escaleras y ascensor) e: 15 cm - Ladrillo hueco portante 12 x 19 x 33 | C11: m2 | D11: 612 | E11: 25172 | F11: =+D11*E11 -> 15405264 | I11: =+'SVD 4140_Pto. 01_Cert. 01'!K11 -> 0 | J11: 0.05 | K11: =+I11+J11 -> 0.05 | L11: =+F11*I11 -> 0 | M11: =+F11*J11 -> 770263.2 | N11: =+F11*K11 -> 770263.2
A12: 4.03 | B12: Muro tipo 4 (divisorio de unidades y fachas) e: 15 cm - Ladrillo hueco 12 x 18 x 33 | C12: m2 | D12: 636 | E12: 21109 | F12: =+D12*E12 -> 13425324 | I12: =+'SVD 4140_Pto. 01_Cert. 01'!K12 -> 0 | J12: 0.1 | K12: =+I12+J12 -> 0.1 | L12: =+F12*I12 -> 0 | M12: =+F12*J12 -> 1342532.4 | N12: =+F12*K12 -> 1342532.4
A13: 4.04 | B13: Enchape medianeras existentes - Contemplamos picado zonas sueltas y enchape con ladrillo comun para PB | C13: m2 | D13: 195 | E13: 15092 | F13: =+D13*E13 -> 2942940 | I13: =+'SVD 4140_Pto. 01_Cert. 01'!K13 -> 0 | K13: =+I13+J13 -> 0 | L13: =+F13*I13 -> 0 | M13: =+F13*J13 -> 0 | N13: =+F13*K13 -> 0
A14: 4.05 | B14: Mamposteria cribada de ladrillo visto en balcones | C14: m2 | D14: 30.054 | E14: 67420 | F14: =+D14*E14 -> 2026240.7 | I14: =+'SVD 4140_Pto. 01_Cert. 01'!K14 -> 0 | K14: =+I14+J14 -> 0 | L14: =+F14*I14 -> 0 | M14: =+F14*J14 -> 0 | N14: =+F14*K14 -> 0
A15: 4.06 | B15: Bloque de H° con masillado de hormigon | C15: m2 | D15: 24 | E15: 54908 | F15: =+D15*E15 -> 1317792 | I15: =+'SVD 4140_Pto. 01_Cert. 01'!K15 -> 0 | K15: =+I15+J15 -> 0 | L15: =+F15*I15 -> 0 | M15: =+F15*J15 -> 0 | N15: =+F15*K15 -> 0
A16: 4.07 | B16: Cordón de hormigón en umbrales carpinterías | C16: ml | D16: 81 | E16: 30989 | F16: =+D16*E16 -> 2510109 | I16: =+'SVD 4140_Pto. 01_Cert. 01'!K16 -> 0 | K16: =+I16+J16 -> 0 | L16: =+F16*I16 -> 0 | M16: =+F16*J16 -> 0 | N16: =+F16*K16 -> 0
A17: 4.08 | B17: Pozo de bombeo pluvial y cloacal | C17: gl | D17: 1 | E17: 1119953 | F17: =+D17*E17 -> 1119953 | I17: =+'SVD 4140_Pto. 01_Cert. 01'!K17 -> 0 | J17: 0.5 | K17: =+I17+J17 -> 0.5 | L17: =+F17*I17 -> 0 | M17: =+F17*J17 -> 559976.5 | N17: =+F17*K17 -> 559976.5
A18: 5 | B18: AISLACIONES | G18: =+SUM(F19:F25) -> 35966419 | H18: =+G18/$G$185 -> 0.048890193
A19: 5.01 | B19: Aislación hidrófuga horizontal (baños) - Inc. membrana geotextil y 35% en concepto de babetas | C19: m2 | D19: 139.05 | E19: 21800 | F19: =+D19*E19 -> 3031290 | I19: =+'SVD 4140_Pto. 01_Cert. 01'!K19 -> 0 | K19: =+I19+J19 -> 0 | L19: =+F19*I19 -> 0 | M19: =+F19*J19 -> 0 | N19: =+F19*K19 -> 0
A20: 5.02 | B20: Azotado hidrofugo - Sobre medianeras existentes | C20: m2 | D20: 300 | E20: 5376 | F20: =+D20*E20 -> 1612800 | I20: =+'SVD 4140_Pto. 01_Cert. 01'!K20 -> 0 | K20: =+I20+J20 -> 0 | L20: =+F20*I20 -> 0 | M20: =+F20*J20 -> 0 | N20: =+F20*K20 -> 0
A21: 5.03 | B21: Azotado hidrofugo - Contrapiso de vereda | C21: m2 | D21: 48 | E21: 5376 | F21: =+D21*E21 -> 258048 | I21: =+'SVD 4140_Pto. 01_Cert. 01'!K21 -> 0 | K21: =+I21+J21 -> 0 | L21: =+F21*I21 -> 0 | M21: =+F21*J21 -> 0 | N21: =+F21*K21 -> 0
A22: 5.04 | B22: Aislación térmica en terrazas, eps e:2,00 cm | C22: m2 | D22: 262 | E22: 4403 | F22: =+D22*E22 -> 1153586 | I22: =+'SVD 4140_Pto. 01_Cert. 01'!K22 -> 0 | K22: =+I22+J22 -> 0 | L22: =+F22*I22 -> 0 | M22: =+F22*J22 -> 0 | N22: =+F22*K22 -> 0
A23: 5.05 | B23: Barrera de vapor | C23: m2 | D23: 510 | E23: 3578 | F23: =+D23*E23 -> 1824780 | I23: =+'SVD 4140_Pto. 01_Cert. 01'!K23 -> 0 | K23: =+I23+J23 -> 0 | L23: =+F23*I23 -> 0 | M23: =+F23*J23 -> 0 | N23: =+F23*K23 -> 0
A24: 5.06 | B24: Membrana asfaltica geotextil 4mm - Balcones y azotea - Inc. 20% en concepto de babetas | C24: m2 | D24: 510 | E24: 21800 | F24: =+D24*E24 -> 11118000 | I24: =+'SVD 4140_Pto. 01_Cert. 01'!K24 -> 0 | K24: =+I24+J24 -> 0 | L24: =+F24*I24 -> 0 | M24: =+F24*J24 -> 0 | N24: =+F24*K24 -> 0
A25: 5.07 | B25: Impermeabilización de subsuelo | C25: gl | D25: 1 | E25: 16967915 | F25: =+D25*E25 -> 16967915 | I25: =+'SVD 4140_Pto. 01_Cert. 01'!K25 -> 1 | K25: =+I25+J25 -> 1 | L25: =+F25*I25 -> 16967915 | M25: =+F25*J25 -> 0 | N25: =+F25*K25 -> 16967915
A26: 6 | B26: CUBIERTAS | G26: =+SUM(F27) -> 2433900 | H26: =+G26/$G$185 -> 0.0033084706
A27: 6.02 | B27: Babeta de chapa galvanizada en medianeras | C27: ml | D27: 60 | E27: 40565 | F27: =+D27*E27 -> 2433900 | I27: =+'SVD 4140_Pto. 01_Cert. 01'!K27 -> 0 | K27: =+I27+J27 -> 0 | L27: =+F27*I27 -> 0 | M27: =+F27*J27 -> 0 | N27: =+F27*K27 -> 0
A28: 7 | B28: REVOQUES | G28: =+SUM(F29:F36) -> 1.3639056e+08 | H28: =+G28/$G$185 -> 0.18539962 | I28: =+'SVD 4140_Pto. 01_Cert. 01'!K28 -> 0
A29: 7.01 | B29: Revoque Grueso Impermeable Exterior proyectable | C29: m2 | D29: 678.252 | E29: 16571 | F29: =+D29*E29 -> 11239314 | I29: =+'SVD 4140_Pto. 01_Cert. 01'!K29 -> 0 | K29: =+I29+J29 -> 0 | L29: =+F29*I29 -> 0 | M29: =+F29*J29 -> 0 | N29: =+F29*K29 -> 0
A30: 7.02 | B30: Revoque Grueso Impermeable Exterior a mas de 3m proyectable - Medianero y fachadas | C30: m2 | D30: 876.0812 | E30: 22183 | F30: =+D30*E30 -> 19434109 | I30: =+'SVD 4140_Pto. 01_Cert. 01'!K30 -> 0 | K30: =+I30+J30 -> 0 | L30: =+F30*I30 -> 0 | M30: =+F30*J30 -> 0 | N30: =+F30*K30 -> 0
A31: 7.03 | B31: Buña en revoque | C31: ml | D31: 182 | E31: 10806 | F31: =+D31*E31 -> 1966692 | I31: =+'SVD 4140_Pto. 01_Cert. 01'!K31 -> 0 | K31: =+I31+J31 -> 0 | L31: =+F31*I31 -> 0 | M31: =+F31*J31 -> 0 | N31: =+F31*K31 -> 0
A32: 7.04 | B32: Revoque Grueso Interior + fino | C32: m2 | D32: 995.8511 | E32: 26530 | F32: =+D32*E32 -> 26419930 | I32: =+'SVD 4140_Pto. 01_Cert. 01'!K32 -> 0 | K32: =+I32+J32 -> 0 | L32: =+F32*I32 -> 0 | M32: =+F32*J32 -> 0 | N32: =+F32*K32 -> 0
A33: 7.05 | B33: Yeso interior | C33: m2 | D33: 2514.897 | E33: 22566 | F33: =+D33*E33 -> 56751166 | I33: =+'SVD 4140_Pto. 01_Cert. 01'!K33 -> 0 | K33: =+I33+J33 -> 0 | L33: =+F33*I33 -> 0 | M33: =+F33*J33 -> 0 | N33: =+F33*K33 -> 0
A34: 7.06 | B34: Arista en yeso | C34: ml | D34: 509.9 | E34: 12771 | F34: =+D34*E34 -> 6511932.9 | I34: =+'SVD 4140_Pto. 01_Cert. 01'!K34 -> 0 | K34: =+I34+J34 -> 0 | L34: =+F34*I34 -> 0 | M34: =+F34*J34 -> 0 | N34: =+F34*K34 -> 0
A35: 7.07 | B35: Provisión y colocación de guardacanto yesero | C35: u | D35: 198 | E35: 14947 | F35: =+D35*E35 -> 2959506 | I35: =+'SVD 4140_Pto. 01_Cert. 01'!K35 -> 0 | K35: =+I35+J35 -> 0 | L35: =+F35*I35 -> 0 | M35: =+F35*J35 -> 0 | N35: =+F35*K35 -> 0
A36: 7.08 | B36: Revoque Grueso Impermeable Interior b/ revestimiento | C36: m2 | D36: 670.322 | E36: 16571 | F36: =+D36*E36 -> 11107906 | I36: =+'SVD 4140_Pto. 01_Cert. 01'!K36 -> 0 | K36: =+I36+J36 -> 0 | L36: =+F36*I36 -> 0 | M36: =+F36*J36 -> 0 | N36: =+F36*K36 -> 0
A37: 8 | B37: CONTRAPISOS Y CARPETAS | G37: =+SUM(F38:F45) -> 44788107 | H37: =+G37/$G$185 -> 0.060881768
A38: 8.01 | B38: Contrapiso de cascotes en SS e: 15 cm | C38: m2 | D38: 104 | E38: 31920 | F38: =+D38*E38 -> 3319680 | I38: =+'SVD 4140_Pto. 01_Cert. 01'!K38 -> 0.5 | J38: 0.5 | K38: =+I38+J38 -> 1 | L38: =+F38*I38 -> 1659840 | M38: =+F38*J38 -> 1659840 | N38: =+F38*K38 -> 3319680
A39: 8.02 | B39: Contrapiso de cascote s/terreno natural e: 20 cm - Incluye film de polietileno | C39: m2 | D39: 48 | E39: 37268 | F39: =+D39*E39 -> 1788864 | I39: =+'SVD 4140_Pto. 01_Cert. 01'!K39 -> 0 | K39: =+I39+J39 -> 0 | L39: =+F39*I39 -> 0 | M39: =+F39*J39 -> 0 | N39: =+F39*K39 -> 0
A40: 8.03 | B40: Contrapiso de cascotes en azoteas c/pendiente e: 15 cm | C40: m2 | D40: 235 | E40: 32410 | F40: =+D40*E40 -> 7616350 | I40: =+'SVD 4140_Pto. 01_Cert. 01'!K40 -> 0 | K40: =+I40+J40 -> 0 | L40: =+F40*I40 -> 0 | M40: =+F40*J40 -> 0 | N40: =+F40*K40 -> 0
A41: 8.04 | B41: Contrapiso - Carpeta monolitico e: 7 cm | C41: m2 | D41: 878 | E41: 19006 | F41: =+D41*E41 -> 16687268 | I41: =+'SVD 4140_Pto. 01_Cert. 01'!K41 -> 0 | K41: =+I41+J41 -> 0 | L41: =+F41*I41 -> 0 | M41: =+F41*J41 -> 0 | N41: =+F41*K41 -> 0
A42: 8.05 | B42: Carpeta en PB y balcones, baños y azoteas e: 3,00 cm | C42: m2 | D42: 564 | E42: 12439 | F42: =+D42*E42 -> 7015596 | I42: =+'SVD 4140_Pto. 01_Cert. 01'!K42 -> 0 | K42: =+I42+J42 -> 0 | L42: =+F42*I42 -> 0 | M42: =+F42*J42 -> 0 | N42: =+F42*K42 -> 0
A43: 8.06 | B43: Carpeta sobre membrana | C43: m2 | D43: 438 | E43: 12439 | F43: =+D43*E43 -> 5448282 | I43: =+'SVD 4140_Pto. 01_Cert. 01'!K43 -> 0 | K43: =+I43+J43 -> 0 | L43: =+F43*I43 -> 0 | M43: =+F43*J43 -> 0 | N43: =+F43*K43 -> 0
A44: 8.07 | B44: Banquinas para cocinas | C44: gl | D44: 1 | E44: 2426924 | F44: =+D44*E44 -> 2426924 | I44: =+'SVD 4140_Pto. 01_Cert. 01'!K44 -> 0 | K44: =+I44+J44 -> 0 | L44: =+F44*I44 -> 0 | M44: =+F44*J44 -> 0 | N44: =+F44*K44 -> 0
A45: 8.08 | B45: Banquinas para bombas y tanques en SB | C45: gl | D45: 1 | E45: 485143 | F45: =+D45*E45 -> 485143 | I45: =+'SVD 4140_Pto. 01_Cert. 01'!K45 -> 0 | K45: =+I45+J45 -> 0 | L45: =+F45*I45 -> 0 | M45: =+F45*J45 -> 0 | N45: =+F45*K45 -> 0
A46: 9 | B46: ESCALERAS | G46: =+SUM(F47:F50) -> 5769056.6 | H46: =+G46/$G$185 -> 0.0078420454
A47: 9.01 | B47: Cemento alisado arrodillado en escaleras | C47: gl | D47: 1 | E47: 2024643 | F47: =+D47*E47 -> 2024643 | I47: =+'SVD 4140_Pto. 01_Cert. 01'!K47 -> 0 | K47: =+I47+J47 -> 0 | L47: =+F47*I47 -> 0 | M47: =+F47*J47 -> 0 | N47: =+F47*K47 -> 0
A48: 9.02 | B48: Provisión nariz escalera, hierro angulo 5/8 x 1/8" | C48: ml | D48: 122 | E48: 18814 | F48: =+D48*E48 -> 2295308 | I48: =+'SVD 4140_Pto. 01_Cert. 01'!K48 -> 0 | K48: =+I48+J48 -> 0 | L48: =+F48*I48 -> 0 | M48: =+F48*J48 -> 0 | N48: =+F48*K48 -> 0
A49: 9.03 | B49: Zócalo de concreto | C49: ml | D49: 155 | E49: 5376 | F49: =+D49*E49 -> 833280 | I49: =+'SVD 4140_Pto. 01_Cert. 01'!K49 -> 0 | K49: =+I49+J49 -> 0 | L49: =+F49*I49 -> 0 | M49: =+F49*J49 -> 0 | N49: =+F49*K49 -> 0
A50: 9.04 | B50: Provisión y colocación de Rodapie/ Zócalo rampante en placa cementicia | C50: ml | D50: 31.2 | E50: 19738 | F50: =+D50*E50 -> 615825.6 | I50: =+'SVD 4140_Pto. 01_Cert. 01'!K50 -> 0 | K50: =+I50+J50 -> 0 | L50: =+F50*I50 -> 0 | M50: =+F50*J50 -> 0 | N50: =+F50*K50 -> 0
A51: 10 | B51: VENTILACIONES | G51: =+SUM(F52:F55) -> 4669278 | H51: =+G51/$G$185 -> 0.0063470845
A52: 10.01 | B52: Ventilación Conducto Humos. Incluye toma de aire en PB - No aplica s/proyecto | C52: gl | D52: 0 | E52: 0 | F52: =+D52*E52 -> 0 | I52: =+'SVD 4140_Pto. 01_Cert. 01'!K52 -> 0 | K52: =+I52+J52 -> 0 | L52: =+F52*I52 -> 0 | M52: =+F52*J52 -> 0 | N52: =+F52*K52 -> 0
A53: 10.02 | B53: Ventilación Baños - En caño Ø 110 | C53: gl | D53: 1 | E53: 2199545 | F53: =+D53*E53 -> 2199545 | I53: =+'SVD 4140_Pto. 01_Cert. 01'!K53 -> 0 | K53: =+I53+J53 -> 0 | L53: =+F53*I53 -> 0 | M53: =+F53*J53 -> 0 | N53: =+F53*K53 -> 0
A54: 10.03 | B54: Colocación de rejillas de inyección y extracción - No aplica s/proyecto | C54: un | D54: 0 | E54: 0 | F54: =+D54*E54 -> 0 | I54: =+'SVD 4140_Pto. 01_Cert. 01'!K54 -> 0 | K54: =+I54+J54 -> 0 | L54: =+F54*I54 -> 0 | M54: =+F54*J54 -> 0 | N54: =+F54*K54 -> 0
A55: 10.04 | B55: Sombreretes en chapa prepintada C25 | C55: u | D55: 7 | E55: 352819 | F55: =+D55*E55 -> 2469733 | I55: =+'SVD 4140_Pto. 01_Cert. 01'!K55 -> 0 | K55: =+I55+J55 -> 0 | L55: =+F55*I55 -> 0 | M55: =+F55*J55 -> 0 | N55: =+F55*K55 -> 0
A56: 11 | B56: PISOS - PROVISION A CARGO DEL COMITENTE | G56: =+SUM(F57:F63) -> 48040802 | H56: =+G56/$G$185 -> 0.06530325
A57: 11.01 | B57: Colocación de travertino en hall PB - Provisión a cargo del comitente | C57: m2 | D57: 30 | E57: 21948 | F57: =+D57*E57 -> 658440 | I57: =+'SVD 4140_Pto. 01_Cert. 01'!K57 -> 0 | K57: =+I57+J57 -> 0 | L57: =+F57*I57 -> 0 | M57: =+F57*J57 -> 0 | N57: =+F57*K57 -> 0
A58: 11.02 | B58: Colocación de porcelanato en paliers, terraza y espacios comunes - Provisión a cargo del comitente | C58: m2 | D58: 185 | E58: 21948 | F58: =+D58*E58 -> 4060380 | I58: =+'SVD 4140_Pto. 01_Cert. 01'!K58 -> 0 | K58: =+I58+J58 -> 0 | L58: =+F58*I58 -> 0 | M58: =+F58*J58 -> 0 | N58: =+F58*K58 -> 0
A59: 11.03 | B59: Colocación de porcelanato en UF - Provisión a cargo del comitente | C59: m2 | D59: 942 | E59: 21948 | F59: =+D59*E59 -> 20675016 | I59: =+'SVD 4140_Pto. 01_Cert. 01'!K59 -> 0 | K59: =+I59+J59 -> 0 | L59: =+F59*I59 -> 0 | M59: =+F59*J59 -> 0 | N59: =+F59*K59 -> 0
A60: 11.04 | B60: Colocación de porcelanato en baños - Provisión a cargo del comitente | C60: m2 | D60: 110 | E60: 25799 | F60: =+D60*E60 -> 2837890 | I60: =+'SVD 4140_Pto. 01_Cert. 01'!K60 -> 0 | K60: =+I60+J60 -> 0 | L60: =+F60*I60 -> 0 | M60: =+F60*J60 -> 0 | N60: =+F60*K60 -> 0
A61: 11.05 | B61: Provisión y ejecución de alisado de cemento rodillado | C61: m2 | D61: 128 | E61: 16080 | F61: =+D61*E61 -> 2058240 | I61: =+'SVD 4140_Pto. 01_Cert. 01'!K61 -> 0 | K61: =+I61+J61 -> 0 | L61: =+F61*I61 -> 0 | M61: =+F61*J61 -> 0 | N61: =+F61*K61 -> 0
A62: 11.06 | B62: Colocación de baldoson de vereda - Provisión a cargo del comitente | C62: m2 | D62: 48 | E62: 21948 | F62: =+D62*E62 -> 1053504 | I62: =+'SVD 4140_Pto. 01_Cert. 01'!K62 -> 0 | K62: =+I62+J62 -> 0 | L62: =+F62*I62 -> 0 | M62: =+F62*J62 -> 0 | N62: =+F62*K62 -> 0
A63: 11.07 | B63: Provisión y ejecución de pavimento e: 18 cm, incluye malla Q188 | C63: m2 | D63: 226 | E63: 73882 | F63: =+D63*E63 -> 16697332 | I63: =+'SVD 4140_Pto. 01_Cert. 01'!K63 -> 0 | K63: =+I63+J63 -> 0 | L63: =+F63*I63 -> 0 | M63: =+F63*J63 -> 0 | N63: =+F63*K63 -> 0
A64: 12 | B64: ZOCALOS Y SOLIAS - PROVISION A CARGO DEL COMITENTE | G64: =+SUM(F65:F69) -> 11022518 | H64: =+G64/$G$185 -> 0.014983227
A65: 12.01 | B65: Provisión y colocación de zocalos de Madera (MDF) h: 7 cm | C65: ml | D65: 779 | E65: 7422 | F65: =+D65*E65 -> 5781738 | I65: =+'SVD 4140_Pto. 01_Cert. 01'!K65 -> 0 | K65: =+I65+J65 -> 0 | L65: =+F65*I65 -> 0 | M65: =+F65*J65 -> 0 | N65: =+F65*K65 -> 0
A66: 12.02 | B66: Zócalo de concreto | C66: ml | D66: 155 | E66: 5376 | F66: =+D66*E66 -> 833280 | I66: =+'SVD 4140_Pto. 01_Cert. 01'!K66 -> 0 | K66: =+I66+J66 -> 0 | L66: =+F66*I66 -> 0 | M66: =+F66*J66 -> 0 | N66: =+F66*K66 -> 0
A67: 12.03 | B67: Colocación de zocalo de porcelanico - Provisión a cargo del comitente | C67: ml | D67: 37 | E67: 7052 | F67: =+D67*E67 -> 260924 | I67: =+'SVD 4140_Pto. 01_Cert. 01'!K67 -> 0 | K67: =+I67+J67 -> 0 | L67: =+F67*I67 -> 0 | M67: =+F67*J67 -> 0 | N67: =+F67*K67 -> 0
A68: 12.04 | B68: Colocación de zocalo de porcelanato en palieres - Provisión a cargo del comitente | C68: ml | D68: 433 | E68: 7052 | F68: =+D68*E68 -> 3053516 | I68: =+'SVD 4140_Pto. 01_Cert. 01'!K68 -> 0 | K68: =+I68+J68 -> 0 | L68: =+F68*I68 -> 0 | M68: =+F68*J68 -> 0 | N68: =+F68*K68 -> 0
A69: 12.05 | B69: Colocación de zocalo de porcelanato en terraza y espacios comunes - Provisión a cargo del comitente | C69: ml | D69: 155 | E69: 7052 | F69: =+D69*E69 -> 1093060 | I69: =+'SVD 4140_Pto. 01_Cert. 01'!K69 -> 0 | K69: =+I69+J69 -> 0 | L69: =+F69*I69 -> 0 | M69: =+F69*J69 -> 0 | N69: =+F69*K69 -> 0
A70: 13 | B70: REVESTIMIENTOS - PROVISION A CARGO DEL COMITENTE | G70: =+SUM(F71:F74) -> 19433086 | H70: =+G70/$G$185 -> 0.026415956
A71: 13.01 | B71: Revestimiento en baños - Provisión a cargo del comitente | C71: m2 | D71: 511 | E71: 25799 | F71: =+D71*E71 -> 13183289 | I71: =+'SVD 4140_Pto. 01_Cert. 01'!K71 -> 0 | K71: =+I71+J71 -> 0 | L71: =+F71*I71 -> 0 | M71: =+F71*J71 -> 0 | N71: =+F71*K71 -> 0
A72: 13.02 | B72: Revestimiento en cocinas - Provisión a cargo del comitente | C72: m2 | D72: 40 | E72: 25799 | F72: =+D72*E72 -> 1031960 | I72: =+'SVD 4140_Pto. 01_Cert. 01'!K72 -> 0 | K72: =+I72+J72 -> 0 | L72: =+F72*I72 -> 0 | M72: =+F72*J72 -> 0 | N72: =+F72*K72 -> 0
A73: 13.03 | B73: Revestimiento tejuela exterior - Provisión a cargo del comitente | C73: m2 | D73: 147.601 | E73: 29881 | F73: =+D73*E73 -> 4410465.5 | I73: =+'SVD 4140_Pto. 01_Cert. 01'!K73 -> 0 | K73: =+I73+J73 -> 0 | L73: =+F73*I73 -> 0 | M73: =+F73*J73 -> 0 | N73: =+F73*K73 -> 0
A74: 13.04 | B74: Provisión y colocación de perfileria de aluminio tipo ATRIM L anod. Natural | C74: u | D74: 41 | E74: 19692 | F74: =+D74*E74 -> 807372 | I74: =+'SVD 4140_Pto. 01_Cert. 01'!K74 -> 0 | K74: =+I74+J74 -> 0 | L74: =+F74*I74 -> 0 | M74: =+F74*J74 -> 0 | N74: =+F74*K74 -> 0
A75: 14 | B75: CIELORRASOS | G75: =+SUM(F76:F82) -> 50296169 | H75: =+G75/$G$185 -> 0.068369036
A76: 14.01 | B76: Cielorraso junta tomada placa STD | C76: m2 | D76: 334.9152 | E76: 29270 | F76: =+D76*E76 -> 9802967.9 | I76: =+'SVD 4140_Pto. 01_Cert. 01'!K76 -> 0 | K76: =+I76+J76 -> 0 | L76: =+F76*I76 -> 0 | M76: =+F76*J76 -> 0 | N76: =+F76*K76 -> 0
A77: 14.02 | B77: Cielorraso junta tomada placa RH | C77: m2 | D77: 280.3913 | E77: 33967 | F77: =+D77*E77 -> 9524051.3 | I77: =+'SVD 4140_Pto. 01_Cert. 01'!K77 -> 0 | K77: =+I77+J77 -> 0 | L77: =+F77*I77 -> 0 | M77: =+F77*J77 -> 0 | N77: =+F77*K77 -> 0
A78: 14.03 | B78: Cajon en junta tomada placa STD | C78: ml | D78: 60.8 | E78: 29270 | F78: =+D78*E78 -> 1779616 | I78: =+'SVD 4140_Pto. 01_Cert. 01'!K78 -> 0 | K78: =+I78+J78 -> 0 | L78: =+F78*I78 -> 0 | M78: =+F78*J78 -> 0 | N78: =+F78*K78 -> 0
A79: 14.04 | B79: Buña perimetral / Cantoneras | C79: ml | D79: 1058.38 | E79: 7873 | F79: =+D79*E79 -> 8332625.7 | I79: =+'SVD 4140_Pto. 01_Cert. 01'!K79 -> 0 | K79: =+I79+J79 -> 0 | L79: =+F79*I79 -> 0 | M79: =+F79*J79 -> 0 | N79: =+F79*K79 -> 0
A80: 14.05 | B80: Aplicado de yeso interior | C80: m2 | D80: 504.1222 | E80: 23364 | F80: =+D80*E80 -> 11778311 | I80: =+'SVD 4140_Pto. 01_Cert. 01'!K80 -> 0 | K80: =+I80+J80 -> 0 | L80: =+F80*I80 -> 0 | M80: =+F80*J80 -> 0 | N80: =+F80*K80 -> 0
A81: 14.06 | B81: Buña en yeso | C81: ml | D81: 555.99 | E81: 12771 | F81: =+D81*E81 -> 7100548.3 | I81: =+'SVD 4140_Pto. 01_Cert. 01'!K81 -> 0 | K81: =+I81+J81 -> 0 | L81: =+F81*I81 -> 0 | M81: =+F81*J81 -> 0 | N81: =+F81*K81 -> 0
A82: 14.07 | B82: H° Visto - Maquillaje para recibir pintura | C82: m2 | D82: 429.0778 | E82: 4610 | F82: =+D82*E82 -> 1978048.7 | I82: =+'SVD 4140_Pto. 01_Cert. 01'!K82 -> 0 | K82: =+I82+J82 -> 0 | L82: =+F82*I82 -> 0 | M82: =+F82*J82 -> 0 | N82: =+F82*K82 -> 0
A83: 15 | B83: PINTURA | G83: =+SUM(F84:F92) -> 0 | H83: =+G83/$G$185 -> 0
A84: 15.01 | B84: Látex interior para paredes Bco. mate (enduido parcial) | C84: m2 | D84: 2670 | E84: 0 | F84: =+D84*E84 -> 0 | I84: =+'SVD 4140_Pto. 01_Cert. 01'!K84 -> 0 | K84: =+I84+J84 -> 0 | L84: =+F84*I84 -> 0 | M84: =+F84*J84 -> 0 | N84: =+F84*K84 -> 0
A85: 15.02 | B85: Látex interior para paredes Bco. mate (s/enduido) | C85: m2 | D85: 961 | E85: 0 | F85: =+D85*E85 -> 0 | I85: =+'SVD 4140_Pto. 01_Cert. 01'!K85 -> 0 | K85: =+I85+J85 -> 0 | L85: =+F85*I85 -> 0 | M85: =+F85*J85 -> 0 | N85: =+F85*K85 -> 0
A86: 15.03 | B86: Látex para cielorraso Bco. mate (enduido parcial) | C86: m2 | D86: 518 | E86: 0 | F86: =+D86*E86 -> 0 | I86: =+'SVD 4140_Pto. 01_Cert. 01'!K86 -> 0 | K86: =+I86+J86 -> 0 | L86: =+F86*I86 -> 0 | M86: =+F86*J86 -> 0 | N86: =+F86*K86 -> 0
A87: 15.04 | B87: Látex para cielorraso Bco. mate (enduido completo) | C87: m2 | D87: 612 | E87: 0 | F87: =+D87*E87 -> 0 | I87: =+'SVD 4140_Pto. 01_Cert. 01'!K87 -> 0 | K87: =+I87+J87 -> 0 | L87: =+F87*I87 -> 0 | M87: =+F87*J87 -> 0 | N87: =+F87*K87 -> 0
A88: 15.05 | B88: Latex interior cielorraso sobre H° | C88: m2 | D88: 422 | E88: 0 | F88: =+D88*E88 -> 0 | I88: =+'SVD 4140_Pto. 01_Cert. 01'!K88 -> 0 | K88: =+I88+J88 -> 0 | L88: =+F88*I88 -> 0 | M88: =+F88*J88 -> 0 | N88: =+F88*K88 -> 0
A89: 15.07 | B89: Revestimiento plastico tipo Quimtex en exteriores y PB | C89: m2 | D89: 678.252 | E89: 0 | F89: =+D89*E89 -> 0 | I89: =+'SVD 4140_Pto. 01_Cert. 01'!K89 -> 0 | K89: =+I89+J89 -> 0 | L89: =+F89*I89 -> 0 | M89: =+F89*J89 -> 0 | N89: =+F89*K89 -> 0
A90: 15.08 | B90: Revestimiento plastico tipo Quimtex en exteriores a mas de 3m de altura, incluye medianeras | C90: m2 | D90: 728.4802 | E90: 0 | F90: =+D90*E90 -> 0 | I90: =+'SVD 4140_Pto. 01_Cert. 01'!K90 -> 0 | K90: =+I90+J90 -> 0 | L90: =+F90*I90 -> 0 | M90: =+F90*J90 -> 0 | N90: =+F90*K90 -> 0
A91: 15.09 | B91: Esmalte sintético en puertas placa, chapa y de ascensor | C91: un | D91: 76 | E91: 0 | F91: =+D91*E91 -> 0 | I91: =+'SVD 4140_Pto. 01_Cert. 01'!K91 -> 0 | K91: =+I91+J91 -> 0 | L91: =+F91*I91 -> 0 | M91: =+F91*J91 -> 0 | N91: =+F91*K91 -> 0
A92: 15.1 | B92: Convertidor y esmalte sintentico en barandas - Escalera, balcones, porton, medidores y SDM | C92: gl | D92: 1 | E92: 0 | F92: =+D92*E92 -> 0 | I92: =+'SVD 4140_Pto. 01_Cert. 01'!K92 -> 0 | K92: =+I92+J92 -> 0 | L92: =+F92*I92 -> 0 | M92: =+F92*J92 -> 0 | N92: =+F92*K92 -> 0
A93: 16 | B93: MARMOLES Y GRANITOS - PROVISION Y COLOCACION A CARGO DEL COMITENTE | G93: =+SUM(F94) -> 0 | H93: =+G93/$G$185 -> 0
E94: 0 | F94: =+D94*E94 -> 0 | I94: =+'SVD 4140_Pto. 01_Cert. 01'!K94 -> 0 | K94: =+I94+J94 -> 0 | L94: =+F94*I94 -> 0 | M94: =+F94*J94 -> 0 | N94: =+F94*K94 -> 0
A95: 17 | B95: CARPINTERIA - PROVISION A CARGO DEL COMITENTE | G95: =+SUM(F96:F99) -> 7258243 | H95: =+G95/$G$185 -> 0.0098663395
A96: 17.01 | B96: Amure de puertas placa Provisión a cargo del comitente | C96: u | D96: 47 | E96: 64232 | F96: =+D96*E96 -> 3018904 | I96: =+'SVD 4140_Pto. 01_Cert. 01'!K96 -> 0 | K96: =+I96+J96 -> 0 | L96: =+F96*I96 -> 0 | M96: =+F96*J96 -> 0 | N96: =+F96*K96 -> 0
A97: 17.02 | B97: Amure de puertas de chapa e ingresos depto - Provisión a cargo del comitente | C97: u | D97: 23 | E97: 64232 | F97: =+D97*E97 -> 1477336 | I97: =+'SVD 4140_Pto. 01_Cert. 01'!K97 -> 0 | K97: =+I97+J97 -> 0 | L97: =+F97*I97 -> 0 | M97: =+F97*J97 -> 0 | N97: =+F97*K97 -> 0
A98: 17.03 | B98: Amure de premarcos - Provisión a cargo del comitente | C98: u | D98: 51 | E98: 41296 | F98: =+D98*E98 -> 2106096 | I98: =+'SVD 4140_Pto. 01_Cert. 01'!K98 -> 0 | K98: =+I98+J98 -> 0 | L98: =+F98*I98 -> 0 | M98: =+F98*J98 -> 0 | N98: =+F98*K98 -> 0
A99: 17.04 | B99: Amure Puertas de Ascensor - Provisión a cargo del comitente | C99: u | D99: 7 | E99: 93701 | F99: =+D99*E99 -> 655907 | I99: =+'SVD 4140_Pto. 01_Cert. 01'!K99 -> 0 | K99: =+I99+J99 -> 0 | L99: =+F99*I99 -> 0 | M99: =+F99*J99 -> 0 | N99: =+F99*K99 -> 0
A100: 18 | B100: INSTALACION ELECTRICA | G100: =+SUM(F101:F130) -> 99277732 | H100: =+G100/$G$185 -> 0.13495109
A101: 18.01 | B101: Tendido y cableado boca Iluminación | C101: u | D101: 392 | E101: 59948 | F101: =+D101*E101 -> 23499616 | I101: =+'SVD 4140_Pto. 01_Cert. 01'!K101 -> 0.2 | J101: 0.1 | K101: =+I101+J101 -> 0.3 | L101: =+F101*I101 -> 4699923.2 | M101: =+F101*J101 -> 2349961.6 | N101: =+F101*K101 -> 7049884.8
...

Sheet SVD 4140_Pto. 01_Cert. 03
F1: DÓLAR BNA | G1: DÓLAR MEP
F2: 1005 | G2: 1170
F4: 45628
B5: OBRA: EDIFICIO EL SALVADOR 4140 | I5: Certificado | J5: 3 | N5: 46020
B6: PRESUPUESTO OBRA CIVIL
B7: Descripción | C7: U | D7: Cant | E7: P unit | F7: Subtotal | I7: Avance | L7: Importe
B8: PRESUPUESTO 02 - ALBANILERIA + INSTALACIONES + TERMINACIONES | I8: Anterior | J8: Actual | K8: Acumulado | L8: Anterior | M8: Actual | N8: Acumulado
A9: 4 | B9: ALBAÑILERIA | G9: =+SUM(F10:F17) -> 54302890 | H9: =+G9/$G$185 -> 0.073815487
A10: 4.01 | B10: Muro tipo 1 (interiores, divisorio de locales) e: 10 cm - Ladrillo hueco 08 x 18 x 33 | C10: m2 | D10: 819 | E10: 18993 | F10: =+D10*E10 -> 15555267 | I10: =+'SVD 4140_Pto. 01_Cert. 02'!K10 -> 0.15 | J10: 0.2 | K10: =+I10+J10 -> 0.35 | L10: =+F10*I10 -> 2333290 | M10: =+F10*J10 -> 3111053.4 | N10: =+F10*K10 -> 5444343.4
A11: 4.02 | B11: Muro tipo 2 y 3 (medianera, caja de escaleras y ascensor) e: 15 cm - Ladrillo hueco portante 12 x 19 x 33 | C11: m2 | D11: 612 | E11: 25172 | F11: =+D11*E11 -> 15405264 | I11: =+'SVD 4140_Pto. 01_Cert. 02'!K11 -> 0.05 | J11: 0.2 | K11: =+I11+J11 -> 0.25 | L11: =+F11*I11 -> 770263.2 | M11: =+F11*J11 -> 3081052.8 | N11: =+F11*K11 -> 3851316
A12: 4.03 | B12: Muro tipo 4 (divisorio de unidades y fachas) e: 15 cm - Ladrillo hueco 12 x 18 x 33 | C12: m2 | D12: 636 | E12: 21109 | F12: =+D12*E12 -> 13425324 | I12: =+'SVD 4140_Pto. 01_Cert. 02'!K12 -> 0.1 | J12: 0.25 | K12: =+I12+J12 -> 0.35 | L12: =+F12*I12 -> 1342532.4 | M12: =+F12*J12 -> 3356331 | N12: =+F12*K12 -> 4698863.4
A13: 4.04 | B13: Enchape medianeras existentes - Contemplamos picado zonas sueltas y enchape con ladrillo comun para PB | C13: m2 | D13: 195 | E13: 15092 | F13: =+D13*E13 -> 2942940 | I13: =+'SVD 4140_Pto. 01_Cert. 02'!K13 -> 0 | J13: 0.15 | K13: =+I13+J13 -> 0.15 | L13: =+F13*I13 -> 0 | M13: =+F13*J13 -> 441441 | N13: =+F13*K13 -> 441441
A14: 4.05 | B14: Mamposteria cribada de ladrillo visto en balcones | C14: m2 | D14: 30.054 | E14: 67420 | F14: =+D14*E14 -> 2026240.7 | I14: =+'SVD 4140_Pto. 01_Cert. 02'!K14 -> 0 | K14: =+I14+J14 -> 0 | L14: =+F14*I14 -> 0 | M14: =+F14*J14 -> 0 | N14: =+F14*K14 -> 0
A15: 4.06 | B15: Bloque de H° con masillado de hormigon | C15: m2 | D15: 24 | E15: 54908 | F15: =+D15*E15 -> 1317792 | I15: =+'SVD 4140_Pto. 01_Cert. 02'!K15 -> 0 | K15: =+I15+J15 -> 0 | L15: =+F15*I15 -> 0 | M15: =+F15*J15 -> 0 | N15: =+F15*K15 -> 0
A16: 4.07 | B16: Cordón de hormigón en umbrales carpinterías | C16: ml | D16: 81 | E16: 30989 | F16: =+D16*E16 -> 2510109 | I16: =+'SVD 4140_Pto. 01_Cert. 02'!K16 -> 0 | K16: =+I16+J16 -> 0 | L16: =+F16*I16 -> 0 | M16: =+F16*J16 -> 0 | N16: =+F16*K16 -> 0
A17: 4.08 | B17: Pozo de bombeo pluvial y cloacal | C17: gl | D17: 1 | E17: 1119953 | F17: =+D17*E17 -> 1119953 | I17: =+'SVD 4140_Pto. 01_Cert. 02'!K17 -> 0.5 | K17: =+I17+J17 -> 0.5 | L17: =+F17*I17 -> 559976.5 | M17: =+F17*J17 -> 0 | N17: =+F17*K17 -> 559976.5
A18: 5 | B18: AISLACIONES | G18: =+SUM(F19:F25) -> 35966419 | H18: =+G18/$G$185 -> 0.048890193
A19: 5.01 | B19: Aislación hidrófuga horizontal (baños) - Inc. membrana geotextil y 35% en concepto de babetas | C19: m2 | D19: 139.05 | E19: 21800 | F19: =+D19*E19 -> 3031290 | I19: =+'SVD 4140_Pto. 01_Cert. 02'!K19 -> 0 | K19: =+I19+J19 -> 0 | L19: =+F19*I19 -> 0 | M19: =+F19*J19 -> 0 | N19: =+F19*K19 -> 0
A20: 5.02 | B20: Azotado hidrofugo - Sobre medianeras existentes | C20: m2 | D20: 300 | E20: 5376 | F20: =+D20*E20 -> 1612800 | I20: =+'SVD 4140_Pto. 01_Cert. 02'!K20 -> 0 | K20: =+I20+J20 -> 0 | L20: =+F20*I20 -> 0 | M20: =+F20*J20 -> 0 | N20: =+F20*K20 -> 0
A21: 5.03 | B21: Azotado hidrofugo - Contrapiso de vereda | C21: m2 | D21: 48 | E21: 5376 | F21: =+D21*E21 -> 258048 | I21: =+'SVD 4140_Pto. 01_Cert. 02'!K21 -> 0 | K21: =+I21+J21 -> 0 | L21: =+F21*I21 -> 0 | M21: =+F21*J21 -> 0 | N21: =+F21*K21 -> 0
A22: 5.04 | B22: Aislación térmica en terrazas, eps e:2,00 cm | C22: m2 | D22: 262 | E22: 4403 | F22: =+D22*E22 -> 1153586 | I22: =+'SVD 4140_Pto. 01_Cert. 02'!K22 -> 0 | K22: =+I22+J22 -> 0 | L22: =+F22*I22 -> 0 | M22: =+F22*J22 -> 0 | N22: =+F22*K22 -> 0
A23: 5.05 | B23: Barrera de vapor | C23: m2 | D23: 510 | E23: 3578 | F23: =+D23*E23 -> 1824780 | I23: =+'SVD 4140_Pto. 01_Cert. 02'!K23 -> 0 | K23: =+I23+J23 -> 0 | L23: =+F23*I23 -> 0 | M23: =+F23*J23 -> 0 | N23: =+F23*K23 -> 0
A24: 5.06 | B24: Membrana asfaltica geotextil 4mm - Balcones y azotea - Inc. 20% en concepto de babetas | C24: m2 | D24: 510 | E24: 21800 | F24: =+D24*E24 -> 11118000 | I24: =+'SVD 4140_Pto. 01_Cert. 02'!K24 -> 0 | K24: =+I24+J24 -> 0 | L24: =+F24*I24 -> 0 | M24: =+F24*J24 -> 0 | N24: =+F24*K24 -> 0
A25: 5.07 | B25: Impermeabilización de subsuelo | C25: gl | D25: 1 | E25: 16967915 | F25: =+D25*E25 -> 16967915 | I25: =+'SVD 4140_Pto. 01_Cert. 02'!K25 -> 1 | K25: =+I25+J25 -> 1 | L25: =+F25*I25 -> 16967915 | M25: =+F25*J25 -> 0 | N25: =+F25*K25 -> 16967915
A26: 6 | B26: CUBIERTAS | G26: =+SUM(F27) -> 2433900 | H26: =+G26/$G$185 -> 0.0033084706
A27: 6.02 | B27: Babeta de chapa galvanizada en medianeras | C27: ml | D27: 60 | E27: 40565 | F27: =+D27*E27 -> 2433900 | I27: =+'SVD 4140_Pto. 01_Cert. 02'!K27 -> 0 | K27: =+I27+J27 -> 0 | L27: =+F27*I27 -> 0 | M27: =+F27*J27 -> 0 | N27: =+F27*K27 -> 0
A28: 7 | B28: REVOQUES | G28: =+SUM(F29:F36) -> 1.3639056e+08 | H28: =+G28/$G$185 -> 0.18539962
A29: 7.01 | B29: Revoque Grueso Impermeable Exterior proyectable | C29: m2 | D29: 678.252 | E29: 16571 | F29: =+D29*E29 -> 11239314 | I29: =+'SVD 4140_Pto. 01_Cert. 02'!K29 -> 0 | K29: =+I29+J29 -> 0 | L29: =+F29*I29 -> 0 | M29: =+F29*J29 -> 0 | N29: =+F29*K29 -> 0
A30: 7.02 | B30: Revoque Grueso Impermeable Exterior a mas de 3m proyectable - Medianero y fachadas | C30: m2 | D30: 876.0812 | E30: 22183 | F30: =+D30*E30 -> 19434109 | I30: =+'SVD 4140_Pto. 01_Cert. 02'!K30 -> 0 | K30: =+I30+J30 -> 0 | L30: =+F30*I30 -> 0 | M30: =+F30*J30 -> 0 | N30: =+F30*K30 -> 0
A31: 7.03 | B31: Buña en revoque | C31: ml | D31: 182 | E31: 10806 | F31: =+D31*E31 -> 1966692 | I31: =+'SVD 4140_Pto. 01_Cert. 02'!K31 -> 0 | K31: =+I31+J31 -> 0 | L31: =+F31*I31 -> 0 | M31: =+F31*J31 -> 0 | N31: =+F31*K31 -> 0
A32: 7.04 | B32: Revoque Grueso Interior + fino | C32: m2 | D32: 995.8511 | E32: 26530 | F32: =+D32*E32 -> 26419930 | I32: =+'SVD 4140_Pto. 01_Cert. 02'!K32 -> 0 | K32: =+I32+J32 -> 0 | L32: =+F32*I32 -> 0 | M32: =+F32*J32 -> 0 | N32: =+F32*K32 -> 0
A33: 7.05 | B33: Yeso interior | C33: m2 | D33: 2514.897 | E33: 22566 | F33: =+D33*E33 -> 56751166 | I33: =+'SVD 4140_Pto. 01_Cert. 02'!K33 -> 0 | K33: =+I33+J33 -> 0 | L33: =+F33*I33 -> 0 | M33: =+F33*J33 -> 0 | N33: =+F33*K33 -> 0
A34: 7.06 | B34: Arista en yeso | C34: ml | D34: 509.9 | E34: 12771 | F34: =+D34*E34 -> 6511932.9 | I34: =+'SVD 4140_Pto. 01_Cert. 02'!K34 -> 0 | K34: =+I34+J34 -> 0 | L34: =+F34*I34 -> 0 | M34: =+F34*J34 -> 0 | N34: =+F34*K34 -> 0
A35: 7.07 | B35: Provisión y colocación de guardacanto yesero | C35: u | D35: 198 | E35: 14947 | F35: =+D35*E35 -> 2959506 | I35: =+'SVD 4140_Pto. 01_Cert. 02'!K35 -> 0 | K35: =+I35+J35 -> 0 | L35: =+F35*I35 -> 0 | M35: =+F35*J35 -> 0 | N35: =+F35*K35 -> 0
A36: 7.08 | B36: Revoque Grueso Impermeable Interior b/ revestimiento | C36: m2 | D36: 670.322 | E36: 16571 | F36: =+D36*E36 -> 11107906 | I36: =+'SVD 4140_Pto. 01_Cert. 02'!K36 -> 0 | K36: =+I36+J36 -> 0 | L36: =+F36*I36 -> 0 | M36: =+F36*J36 -> 0 | N36: =+F36*K36 -> 0
A37: 8 | B37: CONTRAPISOS Y CARPETAS | G37: =+SUM(F38:F45) -> 44788107 | H37: =+G37/$G$185 -> 0.060881768
A38: 8.01 | B38: Contrapiso de cascotes en SS e: 15 cm | C38: m2 | D38: 104 | E38: 31920 | F38: =+D38*E38 -> 3319680 | I38: =+'SVD 4140_Pto. 01_Cert. 02'!K38 -> 1 | K38: =+I38+J38 -> 1 | L38: =+F38*I38 -> 3319680 | M38: =+F38*J38 -> 0 | N38: =+F38*K38 -> 3319680
A39: 8.02 | B39: Contrapiso de cascote s/terreno natural e: 20 cm - Incluye film de polietileno | C39: m2 | D39: 48 | E39: 37268 | F39: =+D39*E39 -> 1788864 | I39: =+'SVD 4140_Pto. 01_Cert. 02'!K39 -> 0 | K39: =+I39+J39 -> 0 | L39: =+F39*I39 -> 0 | M39: =+F39*J39 -> 0 | N39: =+F39*K39 -> 0
A40: 8.03 | B40: Contrapiso de cascotes en azoteas c/pendiente e: 15 cm | C40: m2 | D40: 235 | E40: 32410 | F40: =+D40*E40 -> 7616350 | I40: =+'SVD 4140_Pto. 01_Cert. 02'!K40 -> 0 | K40: =+I40+J40 -> 0 | L40: =+F40*I40 -> 0 | M40: =+F40*J40 -> 0 | N40: =+F40*K40 -> 0
A41: 8.04 | B41: Contrapiso - Carpeta monolitico e: 7 cm | C41: m2 | D41: 878 | E41: 19006 | F41: =+D41*E41 -> 16687268 | I41: =+'SVD 4140_Pto. 01_Cert. 02'!K41 -> 0 | K41: =+I41+J41 -> 0 | L41: =+F41*I41 -> 0 | M41: =+F41*J41 -> 0 | N41: =+F41*K41 -> 0
A42: 8.05 | B42: Carpeta en PB y balcones, baños y azoteas e: 3,00 cm | C42: m2 | D42: 564 | E42: 12439 | F42: =+D42*E42 -> 7015596 | I42: =+'SVD 4140_Pto. 01_Cert. 02'!K42 -> 0 | K42: =+I42+J42 -> 0 | L42: =+F42*I42 -> 0 | M42: =+F42*J42 -> 0 | N42: =+F42*K42 -> 0
A43: 8.06 | B43: Carpeta sobre membrana | C43: m2 | D43: 438 | E43: 12439 | F43: =+D43*E43 -> 5448282 | I43: =+'SVD 4140_Pto. 01_Cert. 02'!K43 -> 0 | K43: =+I43+J43 -> 0 | L43: =+F43*I43 -> 0 | M43: =+F43*J43 -> 0 | N43: =+F43*K43 -> 0
A44: 8.07 | B44: Banquinas para cocinas | C44: gl | D44: 1 | E44: 2426924 | F44: =+D44*E44 -> 2426924 | I44: =+'SVD 4140_Pto. 01_Cert. 02'!K44 -> 0 | K44: =+I44+J44 -> 0 | L44: =+F44*I44 -> 0 | M44: =+F44*J44 -> 0 | N44: =+F44*K44 -> 0
A45: 8.08 | B45: Banquinas para bombas y tanques en SB | C45: gl | D45: 1 | E45: 485143 | F45: =+D45*E45 -> 485143 | I45: =+'SVD 4140_Pto. 01_Cert. 02'!K45 -> 0 | K45: =+I45+J45 -> 0 | L45: =+F45*I45 -> 0 | M45: =+F45*J45 -> 0 | N45: =+F45*K45 -> 0
A46: 9 | B46: ESCALERAS | G46: =+SUM(F47:F50) -> 5769056.6 | H46: =+G46/$G$185 -> 0.0078420454
A47: 9.01 | B47: Cemento alisado arrodillado en escaleras | C47: gl | D47: 1 | E47: 2024643 | F47: =+D47*E47 -> 2024643 | I47: =+'SVD 4140_Pto. 01_Cert. 02'!K47 -> 0 | K47: =+I47+J47 -> 0 | L47: =+F47*I47 -> 0 | M47: =+F47*J47 -> 0 | N47: =+F47*K47 -> 0
A48: 9.02 | B48: Provisión nariz escalera, hierro angulo 5/8 x 1/8" | C48: ml | D48: 122 | E48: 18814 | F48: =+D48*E48 -> 2295308 | I48: =+'SVD 4140_Pto. 01_Cert. 02'!K48 -> 0 | K48: =+I48+J48 -> 0 | L48: =+F48*I48 -> 0 | M48: =+F48*J48 -> 0 | N48: =+F48*K48 -> 0
A49: 9.03 | B49: Zócalo de concreto | C49: ml | D49: 155 | E49: 5376 | F49: =+D49*E49 -> 833280 | I49: =+'SVD 4140_Pto. 01_Cert. 02'!K49 -> 0 | K49: =+I49+J49 -> 0 | L49: =+F49*I49 -> 0 | M49: =+F49*J49 -> 0 | N49: =+F49*K49 -> 0
A50: 9.04 | B50: Provisión y colocación de Rodapie/ Zócalo rampante en placa cementicia | C50: ml | D50: 31.2 | E50: 19738 | F50: =+D50*E50 -> 615825.6 | I50: =+'SVD 4140_Pto. 01_Cert. 02'!K50 -> 0 | K50: =+I50+J50 -> 0 | L50: =+F50*I50 -> 0 | M50: =+F50*J50 -> 0 | N50: =+F50*K50 -> 0
A51: 10 | B51: VENTILACIONES | G51: =+SUM(F52:F55) -> 4669278 | H51: =+G51/$G$185 -> 0.0063470845
A52: 10.01 | B52: Ventilación Conducto Humos. Incluye toma de aire en PB - No aplica s/proyecto | C52: gl | D52: 0 | E52: 0 | F52: =+D52*E52 -> 0 | I52: =+'SVD 4140_Pto. 01_Cert. 02'!K52 -> 0 | K52: =+I52+J52 -> 0 | L52: =+F52*I52 -> 0 | M52: =+F52*J52 -> 0 | N52: =+F52*K52 -> 0
A53: 10.02 | B53: Ventilación Baños - En caño Ø 110 | C53: gl | D53: 1 | E53: 2199545 | F53: =+D53*E53 -> 2199545 | I53: =+'SVD 4140_Pto. 01_Cert. 02'!K53 -> 0 | K53: =+I53+J53 -> 0 | L53: =+F53*I53 -> 0 | M53: =+F53*J53 -> 0 | N53: =+F53*K53 -> 0
A54: 10.03 | B54: Colocación de rejillas de inyección y extracción - No aplica s/proyecto | C54: un | D54: 0 | E54: 0 | F54: =+D54*E54 -> 0 | I54: =+'SVD 4140_Pto. 01_Cert. 02'!K54 -> 0 | K54: =+I54+J54 -> 0 | L54: =+F54*I54 -> 0 | M54: =+F54*J54 -> 0 | N54: =+F54*K54 -> 0
A55: 10.04 | B55: Sombreretes en chapa prepintada C25 | C55: u | D55: 7 | E55: 352819 | F55: =+D55*E55 -> 2469733 | I55: =+'SVD 4140_Pto. 01_Cert. 02'!K55 -> 0 | K55: =+I55+J55 -> 0 | L55: =+F55*I55 -> 0 | M55: =+F55*J55 -> 0 | N55: =+F55*K55 -> 0
A56: 11 | B56: PISOS - PROVISION A CARGO DEL COMITENTE | G56: =+SUM(F57:F63) -> 48040802 | H56: =+G56/$G$185 -> 0.06530325
A57: 11.01 | B57: Colocación de travertino en hall PB - Provisión a cargo del comitente | C57: m2 | D57: 30 | E57: 21948 | F57: =+D57*E57 -> 658440 | I57: =+'SVD 4140_Pto. 01_Cert. 02'!K57 -> 0 | K57: =+I57+J57 -> 0 | L57: =+F57*I57 -> 0 | M57: =+F57*J57 -> 0 | N57: =+F57*K57 -> 0
A58: 11.02 | B58: Colocación de porcelanato en paliers, terraza y espacios comunes - Provisión a cargo del comitente | C58: m2 | D58: 185 | E58: 21948 | F58: =+D58*E58 -> 4060380 | I58: =+'SVD 4140_Pto. 01_Cert. 02'!K58 -> 0 | K58: =+I58+J58 -> 0 | L58: =+F58*I58 -> 0 | M58: =+F58*J58 -> 0 | N58: =+F58*K58 -> 0
A59: 11.03 | B59: Colocación de porcelanato en UF - Provisión a cargo del comitente | C59: m2 | D59: 942 | E59: 21948 | F59: =+D59*E59 -> 20675016 | I59: =+'SVD 4140_Pto. 01_Cert. 02'!K59 -> 0 | K59: =+I59+J59 -> 0 | L59: =+F59*I59 -> 0 | M59: =+F59*J59 -> 0 | N59: =+F59*K59 -> 0
A60: 11.04 | B60: Colocación de porcelanato en baños - Provisión a cargo del comitente | C60: m2 | D60: 110 | E60: 25799 | F60: =+D60*E60 -> 2837890 | I60: =+'SVD 4140_Pto. 01_Cert. 02'!K60 -> 0 | K60: =+I60+J60 -> 0 | L60: =+F60*I60 -> 0 | M60: =+F60*J60 -> 0 | N60: =+F60*K60 -> 0
A61: 11.05 | B61: Provisión y ejecución de alisado de cemento rodillado | C61: m2 | D61: 128 | E61: 16080 | F61: =+D61*E61 -> 2058240 | I61: =+'SVD 4140_Pto. 01_Cert. 02'!K61 -> 0 | K61: =+I61+J61 -> 0 | L61: =+F61*I61 -> 0 | M61: =+F61*J61 -> 0 | N61: =+F61*K61 -> 0
A62: 11.06 | B62: Colocación de baldoson de vereda - Provisión a cargo del comitente | C62: m2 | D62: 48 | E62: 21948 | F62: =+D62*E62 -> 1053504 | I62: =+'SVD 4140_Pto. 01_Cert. 02'!K62 -> 0 | K62: =+I62+J62 -> 0 | L62: =+F62*I62 -> 0 | M62: =+F62*J62 -> 0 | N62: =+F62*K62 -> 0
A63: 11.07 | B63: Provisión y ejecución de pavimento e: 18 cm, incluye malla Q188 | C63: m2 | D63: 226 | E63: 73882 | F63: =+D63*E63 -> 16697332 | I63: =+'SVD 4140_Pto. 01_Cert. 02'!K63 -> 0 | K63: =+I63+J63 -> 0 | L63: =+F63*I63 -> 0 | M63: =+F63*J63 -> 0 | N63: =+F63*K63 -> 0
A64: 12 | B64: ZOCALOS Y SOLIAS - PROVISION A CARGO DEL COMITENTE | G64: =+SUM(F65:F69) -> 11022518 | H64: =+G64/$G$185 -> 0.014983227
A65: 12.01 | B65: Provisión y colocación de zocalos de Madera (MDF) h: 7 cm | C65: ml | D65: 779 | E65: 7422 | F65: =+D65*E65 -> 5781738 | I65: =+'SVD 4140_Pto. 01_Cert. 02'!K65 -> 0 | K65: =+I65+J65 -> 0 | L65: =+F65*I65 -> 0 | M65: =+F65*J65 -> 0 | N65: =+F65*K65 -> 0
A66: 12.02 | B66: Zócalo de concreto | C66: ml | D66: 155 | E66: 5376 | F66: =+D66*E66 -> 833280 | I66: =+'SVD 4140_Pto. 01_Cert. 02'!K66 -> 0 | K66: =+I66+J66 -> 0 | L66: =+F66*I66 -> 0 | M66: =+F66*J66 -> 0 | N66: =+F66*K66 -> 0
A67: 12.03 | B67: Colocación de zocalo de porcelanico - Provisión a cargo del comitente | C67: ml | D67: 37 | E67: 7052 | F67: =+D67*E67 -> 260924 | I67: =+'SVD 4140_Pto. 01_Cert. 02'!K67 -> 0 | K67: =+I67+J67 -> 0 | L67: =+F67*I67 -> 0 | M67: =+F67*J67 -> 0 | N67: =+F67*K67 -> 0
A68: 12.04 | B68: Colocación de zocalo de porcelanato en palieres - Provisión a cargo del comitente | C68: ml | D68: 433 | E68: 7052 | F68: =+D68*E68 -> 3053516 | I68: =+'SVD 4140_Pto. 01_Cert. 02'!K68 -> 0 | K68: =+I68+J68 -> 0 | L68: =+F68*I68 -> 0 | M68: =+F68*J68 -> 0 | N68: =+F68*K68 -> 0
A69: 12.05 | B69: Colocación de zocalo de porcelanato en terraza y espacios comunes - Provisión a cargo del comitente | C69: ml | D69: 155 | E69: 7052 | F69: =+D69*E69 -> 1093060 | I69: =+'SVD 4140_Pto. 01_Cert. 02'!K69 -> 0 | K69: =+I69+J69 -> 0 | L69: =+F69*I69 -> 0 | M69: =+F69*J69 -> 0 | N69: =+F69*K69 -> 0
A70: 13 | B70: REVESTIMIENTOS - PROVISION A CARGO DEL COMITENTE | G70: =+SUM(F71:F74) -> 19433086 | H70: =+G70/$G$185 -> 0.026415956
A71: 13.01 | B71: Revestimiento en baños - Provisión a cargo del comitente | C71: m2 | D71: 511 | E71: 25799 | F71: =+D71*E71 -> 13183289 | I71: =+'SVD 4140_Pto. 01_Cert. 02'!K71 -> 0 | K71: =+I71+J71 -> 0 | L71: =+F71*I71 -> 0 | M71: =+F71*J71 -> 0 | N71: =+F71*K71 -> 0
A72: 13.02 | B72: Revestimiento en cocinas - Provisión a cargo del comitente | C72: m2 | D72: 40 | E72: 25799 | F72: =+D72*E72 -> 1031960 | I72: =+'SVD 4140_Pto. 01_Cert. 02'!K72 -> 0 | K72: =+I72+J72 -> 0 | L72: =+F72*I72 -> 0 | M72: =+F72*J72 -> 0 | N72: =+F72*K72 -> 0
A73: 13.03 | B73: Revestimiento tejuela exterior - Provisión a cargo del comitente | C73: m2 | D73: 147.601 | E73: 29881 | F73: =+D73*E73 -> 4410465.5 | I73: =+'SVD 4140_Pto. 01_Cert. 02'!K73 -> 0 | K73: =+I73+J73 -> 0 | L73: =+F73*I73 -> 0 | M73: =+F73*J73 -> 0 | N73: =+F73*K73 -> 0
A74: 13.04 | B74: Provisión y colocación de perfileria de aluminio tipo ATRIM L anod. Natural | C74: u | D74: 41 | E74: 19692 | F74: =+D74*E74 -> 807372 | I74: =+'SVD 4140_Pto. 01_Cert. 02'!K74 -> 0 | K74: =+I74+J74 -> 0 | L74: =+F74*I74 -> 0 | M74: =+F74*J74 -> 0 | N74: =+F74*K74 -> 0
A75: 14 | B75: CIELORRASOS | G75: =+SUM(F76:F82) -> 50296169 | H75: =+G75/$G$185 -> 0.068369036
A76: 14.01 | B76: Cielorraso junta tomada placa STD | C76: m2 | D76: 334.9152 | E76: 29270 | F76: =+D76*E76 -> 9802967.9 | I76: =+'SVD 4140_Pto. 01_Cert. 02'!K76 -> 0 | K76: =+I76+J76 -> 0 | L76: =+F76*I76 -> 0 | M76: =+F76*J76 -> 0 | N76: =+F76*K76 -> 0
A77: 14.02 | B77: Cielorraso junta tomada placa RH | C77: m2 | D77: 280.3913 | E77: 33967 | F77: =+D77*E77 -> 9524051.3 | I77: =+'SVD 4140_Pto. 01_Cert. 02'!K77 -> 0 | K77: =+I77+J77 -> 0 | L77: =+F77*I77 -> 0 | M77: =+F77*J77 -> 0 | N77: =+F77*K77 -> 0
A78: 14.03 | B78: Cajon en junta tomada placa STD | C78: ml | D78: 60.8 | E78: 29270 | F78: =+D78*E78 -> 1779616 | I78: =+'SVD 4140_Pto. 01_Cert. 02'!K78 -> 0 | K78: =+I78+J78 -> 0 | L78: =+F78*I78 -> 0 | M78: =+F78*J78 -> 0 | N78: =+F78*K78 -> 0
A79: 14.04 | B79: Buña perimetral / Cantoneras | C79: ml | D79: 1058.38 | E79: 7873 | F79: =+D79*E79 -> 8332625.7 | I79: =+'SVD 4140_Pto. 01_Cert. 02'!K79 -> 0 | K79: =+I79+J79 -> 0 | L79: =+F79*I79 -> 0 | M79: =+F79*J79 -> 0 | N79: =+F79*K79 -> 0
A80: 14.05 | B80: Aplicado de yeso interior | C80: m2 | D80: 504.1222 | E80: 23364 | F80: =+D80*E80 -> 11778311 | I80: =+'SVD 4140_Pto. 01_Cert. 02'!K80 -> 0 | K80: =+I80+J80 -> 0 | L80: =+F80*I80 -> 0 | M80: =+F80*J80 -> 0 | N80: =+F80*K80 -> 0
A81: 14.06 | B81: Buña en yeso | C81: ml | D81: 555.99 | E81: 12771 | F81: =+D81*E81 -> 7100548.3 | I81: =+'SVD 4140_Pto. 01_Cert. 02'!K81 -> 0 | K81: =+I81+J81 -> 0 | L81: =+F81*I81 -> 0 | M81: =+F81*J81 -> 0 | N81: =+F81*K81 -> 0
A82: 14.07 | B82: H° Visto - Maquillaje para recibir pintura | C82: m2 | D82: 429.0778 | E82: 4610 | F82: =+D82*E82 -> 1978048.7 | I82: =+'SVD 4140_Pto. 01_Cert. 02'!K82 -> 0 | K82: =+I82+J82 -> 0 | L82: =+F82*I82 -> 0 | M82: =+F82*J82 -> 0 | N82: =+F82*K82 -> 0
A83: 15 | B83: PINTURA | G83: =+SUM(F84:F92) -> 0 | H83: =+G83/$G$185 -> 0
A84: 15.01 | B84: Látex interior para paredes Bco. mate (enduido parcial) | C84: m2 | D84: 2670 | E84: 0 | F84: =+D84*E84 -> 0 | I84: =+'SVD 4140_Pto. 01_Cert. 02'!K84 -> 0 | K84: =+I84+J84 -> 0 | L84: =+F84*I84 -> 0 | M84: =+F84*J84 -> 0 | N84: =+F84*K84 -> 0
A85: 15.02 | B85: Látex interior para paredes Bco. mate (s/enduido) | C85: m2 | D85: 961 | E85: 0 | F85: =+D85*E85 -> 0 | I85: =+'SVD 4140_Pto. 01_Cert. 02'!K85 -> 0 | K85: =+I85+J85 -> 0 | L85: =+F85*I85 -> 0 | M85: =+F85*J85 -> 0 | N85: =+F85*K85 -> 0
A86: 15.03 | B86: Látex para cielorraso Bco. mate (enduido parcial) | C86: m2 | D86: 518 | E86: 0 | F86: =+D86*E86 -> 0 | I86: =+'SVD 4140_Pto. 01_Cert. 02'!K86 -> 0 | K86: =+I86+J86 -> 0 | L86: =+F86*I86 -> 0 | M86: =+F86*J86 -> 0 | N86: =+F86*K86 -> 0
A87: 15.04 | B87: Látex para cielorraso Bco. mate (enduido completo) | C87: m2 | D87: 612 | E87: 0 | F87: =+D87*E87 -> 0 | I87: =+'SVD 4140_Pto. 01_Cert. 02'!K87 -> 0 | K87: =+I87+J87 -> 0 | L87: =+F87*I87 -> 0 | M87: =+F87*J87 -> 0 | N87: =+F87*K87 -> 0
A88: 15.05 | B88: Latex interior cielorraso sobre H° | C88: m2 | D88: 422 | E88: 0 | F88: =+D88*E88 -> 0 | I88: =+'SVD 4140_Pto. 01_Cert. 02'!K88 -> 0 | K88: =+I88+J88 -> 0 | L88: =+F88*I88 -> 0 | M88: =+F88*J88 -> 0 | N88: =+F88*K88 -> 0
A89: 15.07 | B89: Revestimiento plastico tipo Quimtex en exteriores y PB | C89: m2 | D89: 678.252 | E89: 0 | F89: =+D89*E89 -> 0 | I89: =+'SVD 4140_Pto. 01_Cert. 02'!K89 -> 0 | K89: =+I89+J89 -> 0 | L89: =+F89*I89 -> 0 | M89: =+F89*J89 -> 0 | N89: =+F89*K89 -> 0
A90: 15.08 | B90: Revestimiento plastico tipo Quimtex en exteriores a mas de 3m de altura, incluye medianeras | C90: m2 | D90: 728.4802 | E90: 0 | F90: =+D90*E90 -> 0 | I90: =+'SVD 4140_Pto. 01_Cert. 02'!K90 -> 0 | K90: =+I90+J90 -> 0 | L90: =+F90*I90 -> 0 | M90: =+F90*J90 -> 0 | N90: =+F90*K90 -> 0
A91: 15.09 | B91: Esmalte sintético en puertas placa, chapa y de ascensor | C91: un | D91: 76 | E91: 0 | F91: =+D91*E91 -> 0 | I91: =+'SVD 4140_Pto. 01_Cert. 02'!K91 -> 0 | K91: =+I91+J91 -> 0 | L91: =+F91*I91 -> 0 | M91: =+F91*J91 -> 0 | N91: =+F91*K91 -> 0
A92: 15.1 | B92: Convertidor y esmalte sintentico en barandas - Escalera, balcones, porton, medidores y SDM | C92: gl | D92: 1 | E92: 0 | F92: =+D92*E92 -> 0 | I92: =+'SVD 4140_Pto. 01_Cert. 02'!K92 -> 0 | K92: =+I92+J92 -> 0 | L92: =+F92*I92 -> 0 | M92: =+F92*J92 -> 0 | N92: =+F92*K92 -> 0
A93: 16 | B93: MARMOLES Y GRANITOS - PROVISION Y COLOCACION A CARGO DEL COMITENTE | G93: =+SUM(F94) -> 0 | H93: =+G93/$G$185 -> 0
E94: 0 | F94: =+D94*E94 -> 0 | I94: =+'SVD 4140_Pto. 01_Cert. 02'!K94 -> 0 | K94: =+I94+J94 -> 0 | L94: =+F94*I94 -> 0 | M94: =+F94*J94 -> 0 | N94: =+F94*K94 -> 0
A95: 17 | B95: CARPINTERIA - PROVISION A CARGO DEL COMITENTE | G95: =+SUM(F96:F99) -> 7258243 | H95: =+G95/$G$185 -> 0.0098663395
A96: 17.01 | B96: Amure de puertas placa Provisión a cargo del comitente | C96: u | D96: 47 | E96: 64232 | F96: =+D96*E96 -> 3018904 | I96: =+'SVD 4140_Pto. 01_Cert. 02'!K96 -> 0 | K96: =+I96+J96 -> 0 | L96: =+F96*I96 -> 0 | M96: =+F96*J96 -> 0 | N96: =+F96*K96 -> 0
A97: 17.02 | B97: Amure de puertas de chapa e ingresos depto - Provisión a cargo del comitente | C97: u | D97: 23 | E97: 64232 | F97: =+D97*E97 -> 1477336 | I97: =+'SVD 4140_Pto. 01_Cert. 02'!K97 -> 0 | J97: 0.08 | K97: =+I97+J97 -> 0.08 | L97: =+F97*I97 -> 0 | M97: =+F97*J97 -> 118186.88 | N97: =+F97*K97 -> 118186.88
A98: 17.03 | B98: Amure de premarcos - Provisión a cargo del comitente | C98: u | D98: 51 | E98: 41296 | F98: =+D98*E98 -> 2106096 | I98: =+'SVD 4140_Pto. 01_Cert. 02'!K98 -> 0 | K98: =+I98+J98 -> 0 | L98: =+F98*I98 -> 0 | M98: =+F98*J98 -> 0 | N98: =+F98*K98 -> 0
A99: 17.04 | B99: Amure Puertas de Ascensor - Provisión a cargo del comitente | C99: u | D99: 7 | E99: 93701 | F99: =+D99*E99 -> 655907 | I99: =+'SVD 4140_Pto. 01_Cert. 02'!K99 -> 0 | K99: =+I99+J99 -> 0 | L99: =+F99*I99 -> 0 | M99: =+F99*J99 -> 0 | N99: =+F99*K99 -> 0
A100: 18 | B100: INSTALACION ELECTRICA | G100: =+SUM(F101:F130) -> 99277732 | H100: =+G100/$G$185 -> 0.13495109
A101: 18.01 | B101: Tendido y cableado boca Iluminación | C101: u | D101: 392 | E101: 59948 | F101: =+D101*E101 -> 23499616 | I101: =+'SVD 4140_Pto. 01_Cert. 02'!K101 -> 0.3 | J101: 0.1 | K101: =+I101+J101 -> 0.4 | L101: =+F101*I101 -> 7049884.8 | M101: =+F101*J101 -> 2349961.6 | N101: =+F101*K101 -> 9399846.4
...

Sheet SVD 4140_Pto. 01_Cert. 04
F1: DÓLAR BNA | G1: DÓLAR MEP
F2: 1005 | G2: 1170
F4: 45628
B5: OBRA: EDIFICIO EL SALVADOR 4140 | I5: Certificado | J5: 4 | N5: 46050
B6: PRESUPUESTO OBRA CIVIL
B7: Descripción | C7: U | D7: Cant | E7: P unit | F7: Subtotal | I7: Avance | L7: Importe
B8: PRESUPUESTO 02 - ALBANILERIA + INSTALACIONES + TERMINACIONES | I8: Anterior | J8: Actual | K8: Acumulado | L8: Anterior | M8: Actual | N8: Acumulado
A9: 4 | B9: ALBAÑILERIA | G9: =+SUM(F10:F17) -> 54302890 | H9: =+G9/$G$185 -> 0.073815487
A10: 4.01 | B10: Muro tipo 1 (interiores, divisorio de locales) e: 10 cm - Ladrillo hueco 08 x 18 x 33 | C10: m2 | D10: 819 | E10: 18993 | F10: =+D10*E10 -> 15555267 | I10: =+'SVD 4140_Pto. 01_Cert. 03'!K10 -> 0.35 | J10: 0.2 | K10: =+I10+J10 -> 0.55 | L10: =+F10*I10 -> 5444343.4 | M10: =+F10*J10 -> 3111053.4 | N10: =+F10*K10 -> 8555396.9
A11: 4.02 | B11: Muro tipo 2 y 3 (medianera, caja de escaleras y ascensor) e: 15 cm - Ladrillo hueco portante 12 x 19 x 33 | C11: m2 | D11: 612 | E11: 25172 | F11: =+D11*E11 -> 15405264 | I11: =+'SVD 4140_Pto. 01_Cert. 03'!K11 -> 0.25 | J11: 0.25 | K11: =+I11+J11 -> 0.5 | L11: =+F11*I11 -> 3851316 | M11: =+F11*J11 -> 3851316 | N11: =+F11*K11 -> 7702632
A12: 4.03 | B12: Muro tipo 4 (divisorio de unidades y fachas) e: 15 cm - Ladrillo hueco 12 x 18 x 33 | C12: m2 | D12: 636 | E12: 21109 | F12: =+D12*E12 -> 13425324 | I12: =+'SVD 4140_Pto. 01_Cert. 03'!K12 -> 0.35 | J12: 0.2 | K12: =+I12+J12 -> 0.55 | L12: =+F12*I12 -> 4698863.4 | M12: =+F12*J12 -> 2685064.8 | N12: =+F12*K12 -> 7383928.2
A13: 4.04 | B13: Enchape medianeras existentes - Contemplamos picado zonas sueltas y enchape con ladrillo comun para PB | C13: m2 | D13: 195 | E13: 15092 | F13: =+D13*E13 -> 2942940 | I13: =+'SVD 4140_Pto. 01_Cert. 03'!K13 -> 0.15 | K13: =+I13+J13 -> 0.15 | L13: =+F13*I13 -> 441441 | M13: =+F13*J13 -> 0 | N13: =+F13*K13 -> 441441
A14: 4.05 | B14: Mamposteria cribada de ladrillo visto en balcones | C14: m2 | D14: 30.054 | E14: 67420 | F14: =+D14*E14 -> 2026240.7 | I14: =+'SVD 4140_Pto. 01_Cert. 03'!K14 -> 0 | K14: =+I14+J14 -> 0 | L14: =+F14*I14 -> 0 | M14: =+F14*J14 -> 0 | N14: =+F14*K14 -> 0
A15: 4.06 | B15: Bloque de H° con masillado de hormigon | C15: m2 | D15: 24 | E15: 54908 | F15: =+D15*E15 -> 1317792 | I15: =+'SVD 4140_Pto. 01_Cert. 03'!K15 -> 0 | K15: =+I15+J15 -> 0 | L15: =+F15*I15 -> 0 | M15: =+F15*J15 -> 0 | N15: =+F15*K15 -> 0
A16: 4.07 | B16: Cordón de hormigón en umbrales carpinterías | C16: ml | D16: 81 | E16: 30989 | F16: =+D16*E16 -> 2510109 | I16: =+'SVD 4140_Pto. 01_Cert. 03'!K16 -> 0 | K16: =+I16+J16 -> 0 | L16: =+F16*I16 -> 0 | M16: =+F16*J16 -> 0 | N16: =+F16*K16 -> 0
A17: 4.08 | B17: Pozo de bombeo pluvial y cloacal | C17: gl | D17: 1 | E17: 1119953 | F17: =+D17*E17 -> 1119953 | I17: =+'SVD 4140_Pto. 01_Cert. 03'!K17 -> 0.5 | K17: =+I17+J17 -> 0.5 | L17: =+F17*I17 -> 559976.5 | M17: =+F17*J17 -> 0 | N17: =+F17*K17 -> 559976.5
A18: 5 | B18: AISLACIONES | G18: =+SUM(F19:F25) -> 35966419 | H18: =+G18/$G$185 -> 0.048890193
A19: 5.01 | B19: Aislación hidrófuga horizontal (baños) - Inc. membrana geotextil y 35% en concepto de babetas | C19: m2 | D19: 139.05 | E19: 21800 | F19: =+D19*E19 -> 3031290 | I19: =+'SVD 4140_Pto. 01_Cert. 03'!K19 -> 0 | K19: =+I19+J19 -> 0 | L19: =+F19*I19 -> 0 | M19: =+F19*J19 -> 0 | N19: =+F19*K19 -> 0
A20: 5.02 | B20: Azotado hidrofugo - Sobre medianeras existentes | C20: m2 | D20: 300 | E20: 5376 | F20: =+D20*E20 -> 1612800 | I20: =+'SVD 4140_Pto. 01_Cert. 03'!K20 -> 0 | K20: =+I20+J20 -> 0 | L20: =+F20*I20 -> 0 | M20: =+F20*J20 -> 0 | N20: =+F20*K20 -> 0
A21: 5.03 | B21: Azotado hidrofugo - Contrapiso de vereda | C21: m2 | D21: 48 | E21: 5376 | F21: =+D21*E21 -> 258048 | I21: =+'SVD 4140_Pto. 01_Cert. 03'!K21 -> 0 | K21: =+I21+J21 -> 0 | L21: =+F21*I21 -> 0 | M21: =+F21*J21 -> 0 | N21: =+F21*K21 -> 0
A22: 5.04 | B22: Aislación térmica en terrazas, eps e:2,00 cm | C22: m2 | D22: 262 | E22: 4403 | F22: =+D22*E22 -> 1153586 | I22: =+'SVD 4140_Pto. 01_Cert. 03'!K22 -> 0 | K22: =+I22+J22 -> 0 | L22: =+F22*I22 -> 0 | M22: =+F22*J22 -> 0 | N22: =+F22*K22 -> 0
A23: 5.05 | B23: Barrera de vapor | C23: m2 | D23: 510 | E23: 3578 | F23: =+D23*E23 -> 1824780 | I23: =+'SVD 4140_Pto. 01_Cert. 03'!K23 -> 0 | K23: =+I23+J23 -> 0 | L23: =+F23*I23 -> 0 | M23: =+F23*J23 -> 0 | N23: =+F23*K23 -> 0
A24: 5.06 | B24: Membrana asfaltica geotextil 4mm - Balcones y azotea - Inc. 20% en concepto de babetas | C24: m2 | D24: 510 | E24: 21800 | F24: =+D24*E24 -> 11118000 | I24: =+'SVD 4140_Pto. 01_Cert. 03'!K24 -> 0 | K24: =+I24+J24 -> 0 | L24: =+F24*I24 -> 0 | M24: =+F24*J24 -> 0 | N24: =+F24*K24 -> 0
A25: 5.07 | B25: Impermeabilización de subsuelo | C25: gl | D25: 1 | E25: 16967915 | F25: =+D25*E25 -> 16967915 | I25: =+'SVD 4140_Pto. 01_Cert. 03'!K25 -> 1 | K25: =+I25+J25 -> 1 | L25: =+F25*I25 -> 16967915 | M25: =+F25*J25 -> 0 | N25: =+F25*K25 -> 16967915
A26: 6 | B26: CUBIERTAS | G26: =+SUM(F27) -> 2433900 | H26: =+G26/$G$185 -> 0.0033084706
A27: 6.02 | B27: Babeta de chapa galvanizada en medianeras | C27: ml | D27: 60 | E27: 40565 | F27: =+D27*E27 -> 2433900 | I27: =+'SVD 4140_Pto. 01_Cert. 03'!K27 -> 0 | K27: =+I27+J27 -> 0 | L27: =+F27*I27 -> 0 | M27: =+F27*J27 -> 0 | N27: =+F27*K27 -> 0
A28: 7 | B28: REVOQUES | G28: =+SUM(F29:F36) -> 1.3639056e+08 | H28: =+G28/$G$185 -> 0.18539962
A29: 7.01 | B29: Revoque Grueso Impermeable Exterior proyectable | C29: m2 | D29: 678.252 | E29: 16571 | F29: =+D29*E29 -> 11239314 | I29: =+'SVD 4140_Pto. 01_Cert. 03'!K29 -> 0 | K29: =+I29+J29 -> 0 | L29: =+F29*I29 -> 0 | M29: =+F29*J29 -> 0 | N29: =+F29*K29 -> 0
A30: 7.02 | B30: Revoque Grueso Impermeable Exterior a mas de 3m proyectable - Medianero y fachadas | C30: m2 | D30: 876.0812 | E30: 22183 | F30: =+D30*E30 -> 19434109 | I30: =+'SVD 4140_Pto. 01_Cert. 03'!K30 -> 0 | K30: =+I30+J30 -> 0 | L30: =+F30*I30 -> 0 | M30: =+F30*J30 -> 0 | N30: =+F30*K30 -> 0
A31: 7.03 | B31: Buña en revoque | C31: ml | D31: 182 | E31: 10806 | F31: =+D31*E31 -> 1966692 | I31: =+'SVD 4140_Pto. 01_Cert. 03'!K31 -> 0 | K31: =+I31+J31 -> 0 | L31: =+F31*I31 -> 0 | M31: =+F31*J31 -> 0 | N31: =+F31*K31 -> 0
A32: 7.04 | B32: Revoque Grueso Interior + fino | C32: m2 | D32: 995.8511 | E32: 26530 | F32: =+D32*E32 -> 26419930 | I32: =+'SVD 4140_Pto. 01_Cert. 03'!K32 -> 0 | J32: 0.45 | K32: =+I32+J32 -> 0.45 | L32: =+F32*I32 -> 0 | M32: =+F32*J32 -> 11888968 | N32: =+F32*K32 -> 11888968
A33: 7.05 | B33: Yeso interior | C33: m2 | D33: 2514.897 | E33: 22566 | F33: =+D33*E33 -> 56751166 | I33: =+'SVD 4140_Pto. 01_Cert. 03'!K33 -> 0 | K33: =+I33+J33 -> 0 | L33: =+F33*I33 -> 0 | M33: =+F33*J33 -> 0 | N33: =+F33*K33 -> 0
A34: 7.06 | B34: Arista en yeso | C34: ml | D34: 509.9 | E34: 12771 | F34: =+D34*E34 -> 6511932.9 | I34: =+'SVD 4140_Pto. 01_Cert. 03'!K34 -> 0 | K34: =+I34+J34 -> 0 | L34: =+F34*I34 -> 0 | M34: =+F34*J34 -> 0 | N34: =+F34*K34 -> 0
A35: 7.07 | B35: Provisión y colocación de guardacanto yesero | C35: u | D35: 198 | E35: 14947 | F35: =+D35*E35 -> 2959506 | I35: =+'SVD 4140_Pto. 01_Cert. 03'!K35 -> 0 | K35: =+I35+J35 -> 0 | L35: =+F35*I35 -> 0 | M35: =+F35*J35 -> 0 | N35: =+F35*K35 -> 0
A36: 7.08 | B36: Revoque Grueso Impermeable Interior b/ revestimiento | C36: m2 | D36: 670.322 | E36: 16571 | F36: =+D36*E36 -> 11107906 | I36: =+'SVD 4140_Pto. 01_Cert. 03'!K36 -> 0 | K36: =+I36+J36 -> 0 | L36: =+F36*I36 -> 0 | M36: =+F36*J36 -> 0 | N36: =+F36*K36 -> 0
A37: 8 | B37: CONTRAPISOS Y CARPETAS | G37: =+SUM(F38:F45) -> 44788107 | H37: =+G37/$G$185 -> 0.060881768
A38: 8.01 | B38: Contrapiso de cascotes en SS e: 15 cm | C38: m2 | D38: 104 | E38: 31920 | F38: =+D38*E38 -> 3319680 | I38: =+'SVD 4140_Pto. 01_Cert. 03'!K38 -> 1 | K38: =+I38+J38 -> 1 | L38: =+F38*I38 -> 3319680 | M38: =+F38*J38 -> 0 | N38: =+F38*K38 -> 3319680
A39: 8.02 | B39: Contrapiso de cascote s/terreno natural e: 20 cm - Incluye film de polietileno | C39: m2 | D39: 48 | E39: 37268 | F39: =+D39*E39 -> 1788864 | I39: =+'SVD 4140_Pto. 01_Cert. 03'!K39 -> 0 | K39: =+I39+J39 -> 0 | L39: =+F39*I39 -> 0 | M39: =+F39*J39 -> 0 | N39: =+F39*K39 -> 0
A40: 8.03 | B40: Contrapiso de cascotes en azoteas c/pendiente e: 15 cm | C40: m2 | D40: 235 | E40: 32410 | F40: =+D40*E40 -> 7616350 | I40: =+'SVD 4140_Pto. 01_Cert. 03'!K40 -> 0 | K40: =+I40+J40 -> 0 | L40: =+F40*I40 -> 0 | M40: =+F40*J40 -> 0 | N40: =+F40*K40 -> 0
A41: 8.04 | B41: Contrapiso - Carpeta monolitico e: 7 cm | C41: m2 | D41: 878 | E41: 19006 | F41: =+D41*E41 -> 16687268 | I41: =+'SVD 4140_Pto. 01_Cert. 03'!K41 -> 0 | K41: =+I41+J41 -> 0 | L41: =+F41*I41 -> 0 | M41: =+F41*J41 -> 0 | N41: =+F41*K41 -> 0
A42: 8.05 | B42: Carpeta en PB y balcones, baños y azoteas e: 3,00 cm | C42: m2 | D42: 564 | E42: 12439 | F42: =+D42*E42 -> 7015596 | I42: =+'SVD 4140_Pto. 01_Cert. 03'!K42 -> 0 | K42: =+I42+J42 -> 0 | L42: =+F42*I42 -> 0 | M42: =+F42*J42 -> 0 | N42: =+F42*K42 -> 0
A43: 8.06 | B43: Carpeta sobre membrana | C43: m2 | D43: 438 | E43: 12439 | F43: =+D43*E43 -> 5448282 | I43: =+'SVD 4140_Pto. 01_Cert. 03'!K43 -> 0 | K43: =+I43+J43 -> 0 | L43: =+F43*I43 -> 0 | M43: =+F43*J43 -> 0 | N43: =+F43*K43 -> 0
A44: 8.07 | B44: Banquinas para cocinas | C44: gl | D44: 1 | E44: 2426924 | F44: =+D44*E44 -> 2426924 | I44: =+'SVD 4140_Pto. 01_Cert. 03'!K44 -> 0 | K44: =+I44+J44 -> 0 | L44: =+F44*I44 -> 0 | M44: =+F44*J44 -> 0 | N44: =+F44*K44 -> 0
A45: 8.08 | B45: Banquinas para bombas y tanques en SB | C45: gl | D45: 1 | E45: 485143 | F45: =+D45*E45 -> 485143 | I45: =+'SVD 4140_Pto. 01_Cert. 03'!K45 -> 0 | K45: =+I45+J45 -> 0 | L45: =+F45*I45 -> 0 | M45: =+F45*J45 -> 0 | N45: =+F45*K45 -> 0
A46: 9 | B46: ESCALERAS | G46: =+SUM(F47:F50) -> 5769056.6 | H46: =+G46/$G$185 -> 0.0078420454
A47: 9.01 | B47: Cemento alisado arrodillado en escaleras | C47: gl | D47: 1 | E47: 2024643 | F47: =+D47*E47 -> 2024643 | I47: =+'SVD 4140_Pto. 01_Cert. 03'!K47 -> 0 | K47: =+I47+J47 -> 0 | L47: =+F47*I47 -> 0 | M47: =+F47*J47 -> 0 | N47: =+F47*K47 -> 0
A48: 9.02 | B48: Provisión nariz escalera, hierro angulo 5/8 x 1/8" | C48: ml | D48: 122 | E48: 18814 | F48: =+D48*E48 -> 2295308 | I48: =+'SVD 4140_Pto. 01_Cert. 03'!K48 -> 0 | K48: =+I48+J48 -> 0 | L48: =+F48*I48 -> 0 | M48: =+F48*J48 -> 0 | N48: =+F48*K48 -> 0
A49: 9.03 | B49: Zócalo de concreto | C49: ml | D49: 155 | E49: 5376 | F49: =+D49*E49 -> 833280 | I49: =+'SVD 4140_Pto. 01_Cert. 03'!K49 -> 0 | K49: =+I49+J49 -> 0 | L49: =+F49*I49 -> 0 | M49: =+F49*J49 -> 0 | N49: =+F49*K49 -> 0
A50: 9.04 | B50: Provisión y colocación de Rodapie/ Zócalo rampante en placa cementicia | C50: ml | D50: 31.2 | E50: 19738 | F50: =+D50*E50 -> 615825.6 | I50: =+'SVD 4140_Pto. 01_Cert. 03'!K50 -> 0 | K50: =+I50+J50 -> 0 | L50: =+F50*I50 -> 0 | M50: =+F50*J50 -> 0 | N50: =+F50*K50 -> 0
A51: 10 | B51: VENTILACIONES | G51: =+SUM(F52:F55) -> 4669278 | H51: =+G51/$G$185 -> 0.0063470845
A52: 10.01 | B52: Ventilación Conducto Humos. Incluye toma de aire en PB - No aplica s/proyecto | C52: gl | D52: 0 | E52: 0 | F52: =+D52*E52 -> 0 | I52: =+'SVD 4140_Pto. 01_Cert. 03'!K52 -> 0 | K52: =+I52+J52 -> 0 | L52: =+F52*I52 -> 0 | M52: =+F52*J52 -> 0 | N52: =+F52*K52 -> 0
A53: 10.02 | B53: Ventilación Baños - En caño Ø 110 | C53: gl | D53: 1 | E53: 2199545 | F53: =+D53*E53 -> 2199545 | I53: =+'SVD 4140_Pto. 01_Cert. 03'!K53 -> 0 | K53: =+I53+J53 -> 0 | L53: =+F53*I53 -> 0 | M53: =+F53*J53 -> 0 | N53: =+F53*K53 -> 0
A54: 10.03 | B54: Colocación de rejillas de inyección y extracción - No aplica s/proyecto | C54: un | D54: 0 | E54: 0 | F54: =+D54*E54 -> 0 | I54: =+'SVD 4140_Pto. 01_Cert. 03'!K54 -> 0 | K54: =+I54+J54 -> 0 | L54: =+F54*I54 -> 0 | M54: =+F54*J54 -> 0 | N54: =+F54*K54 -> 0
A55: 10.04 | B55: Sombreretes en chapa prepintada C25 | C55: u | D55: 7 | E55: 352819 | F55: =+D55*E55 -> 2469733 | I55: =+'SVD 4140_Pto. 01_Cert. 03'!K55 -> 0 | K55: =+I55+J55 -> 0 | L55: =+F55*I55 -> 0 | M55: =+F55*J55 -> 0 | N55: =+F55*K55 -> 0
A56: 11 | B56: PISOS - PROVISION A CARGO DEL COMITENTE | G56: =+SUM(F57:F63) -> 48040802 | H56: =+G56/$G$185 -> 0.06530325
A57: 11.01 | B57: Colocación de travertino en hall PB - Provisión a cargo del comitente | C57: m2 | D57: 30 | E57: 21948 | F57: =+D57*E57 -> 658440 | I57: =+'SVD 4140_Pto. 01_Cert. 03'!K57 -> 0 | K57: =+I57+J57 -> 0 | L57: =+F57*I57 -> 0 | M57: =+F57*J57 -> 0 | N57: =+F57*K57 -> 0
A58: 11.02 | B58: Colocación de porcelanato en paliers, terraza y espacios comunes - Provisión a cargo del comitente | C58: m2 | D58: 185 | E58: 21948 | F58: =+D58*E58 -> 4060380 | I58: =+'SVD 4140_Pto. 01_Cert. 03'!K58 -> 0 | K58: =+I58+J58 -> 0 | L58: =+F58*I58 -> 0 | M58: =+F58*J58 -> 0 | N58: =+F58*K58 -> 0
A59: 11.03 | B59: Colocación de porcelanato en UF - Provisión a cargo del comitente | C59: m2 | D59: 942 | E59: 21948 | F59: =+D59*E59 -> 20675016 | I59: =+'SVD 4140_Pto. 01_Cert. 03'!K59 -> 0 | K59: =+I59+J59 -> 0 | L59: =+F59*I59 -> 0 | M59: =+F59*J59 -> 0 | N59: =+F59*K59 -> 0
A60: 11.04 | B60: Colocación de porcelanato en baños - Provisión a cargo del comitente | C60: m2 | D60: 110 | E60: 25799 | F60: =+D60*E60 -> 2837890 | I60: =+'SVD 4140_Pto. 01_Cert. 03'!K60 -> 0 | K60: =+I60+J60 -> 0 | L60: =+F60*I60 -> 0 | M60: =+F60*J60 -> 0 | N60: =+F60*K60 -> 0
A61: 11.05 | B61: Provisión y ejecución de alisado de cemento rodillado | C61: m2 | D61: 128 | E61: 16080 | F61: =+D61*E61 -> 2058240 | I61: =+'SVD 4140_Pto. 01_Cert. 03'!K61 -> 0 | K61: =+I61+J61 -> 0 | L61: =+F61*I61 -> 0 | M61: =+F61*J61 -> 0 | N61: =+F61*K61 -> 0
A62: 11.06 | B62: Colocación de baldoson de vereda - Provisión a cargo del comitente | C62: m2 | D62: 48 | E62: 21948 | F62: =+D62*E62 -> 1053504 | I62: =+'SVD 4140_Pto. 01_Cert. 03'!K62 -> 0 | K62: =+I62+J62 -> 0 | L62: =+F62*I62 -> 0 | M62: =+F62*J62 -> 0 | N62: =+F62*K62 -> 0
A63: 11.07 | B63: Provisión y ejecución de pavimento e: 18 cm, incluye malla Q188 | C63: m2 | D63: 226 | E63: 73882 | F63: =+D63*E63 -> 16697332 | I63: =+'SVD 4140_Pto. 01_Cert. 03'!K63 -> 0 | K63: =+I63+J63 -> 0 | L63: =+F63*I63 -> 0 | M63: =+F63*J63 -> 0 | N63: =+F63*K63 -> 0
A64: 12 | B64: ZOCALOS Y SOLIAS - PROVISION A CARGO DEL COMITENTE | G64: =+SUM(F65:F69) -> 11022518 | H64: =+G64/$G$185 -> 0.014983227
A65: 12.01 | B65: Provisión y colocación de zocalos de Madera (MDF) h: 7 cm | C65: ml | D65: 779 | E65: 7422 | F65: =+D65*E65 -> 5781738 | I65: =+'SVD 4140_Pto. 01_Cert. 03'!K65 -> 0 | K65: =+I65+J65 -> 0 | L65: =+F65*I65 -> 0 | M65: =+F65*J65 -> 0 | N65: =+F65*K65 -> 0
A66: 12.02 | B66: Zócalo de concreto | C66: ml | D66: 155 | E66: 5376 | F66: =+D66*E66 -> 833280 | I66: =+'SVD 4140_Pto. 01_Cert. 03'!K66 -> 0 | K66: =+I66+J66 -> 0 | L66: =+F66*I66 -> 0 | M66: =+F66*J66 -> 0 | N66: =+F66*K66 -> 0
A67: 12.03 | B67: Colocación de zocalo de porcelanico - Provisión a cargo del comitente | C67: ml | D67: 37 | E67: 7052 | F67: =+D67*E67 -> 260924 | I67: =+'SVD 4140_Pto. 01_Cert. 03'!K67 -> 0 | K67: =+I67+J67 -> 0 | L67: =+F67*I67 -> 0 | M67: =+F67*J67 -> 0 | N67: =+F67*K67 -> 0
A68: 12.04 | B68: Colocación de zocalo de porcelanato en palieres - Provisión a cargo del comitente | C68: ml | D68: 433 | E68: 7052 | F68: =+D68*E68 -> 3053516 | I68: =+'SVD 4140_Pto. 01_Cert. 03'!K68 -> 0 | K68: =+I68+J68 -> 0 | L68: =+F68*I68 -> 0 | M68: =+F68*J68 -> 0 | N68: =+F68*K68 -> 0
A69: 12.05 | B69: Colocación de zocalo de porcelanato en terraza y espacios comunes - Provisión a cargo del comitente | C69: ml | D69: 155 | E69: 7052 | F69: =+D69*E69 -> 1093060 | I69: =+'SVD 4140_Pto. 01_Cert. 03'!K69 -> 0 | K69: =+I69+J69 -> 0 | L69: =+F69*I69 -> 0 | M69: =+F69*J69 -> 0 | N69: =+F69*K69 -> 0
A70: 13 | B70: REVESTIMIENTOS - PROVISION A CARGO DEL COMITENTE | G70: =+SUM(F71:F74) -> 19433086 | H70: =+G70/$G$185 -> 0.026415956
A71: 13.01 | B71: Revestimiento en baños - Provisión a cargo del comitente | C71: m2 | D71: 511 | E71: 25799 | F71: =+D71*E71 -> 13183289 | I71: =+'SVD 4140_Pto. 01_Cert. 03'!K71 -> 0 | K71: =+I71+J71 -> 0 | L71: =+F71*I71 -> 0 | M71: =+F71*J71 -> 0 | N71: =+F71*K71 -> 0
A72: 13.02 | B72: Revestimiento en cocinas - Provisión a cargo del comitente | C72: m2 | D72: 40 | E72: 25799 | F72: =+D72*E72 -> 1031960 | I72: =+'SVD 4140_Pto. 01_Cert. 03'!K72 -> 0 | K72: =+I72+J72 -> 0 | L72: =+F72*I72 -> 0 | M72: =+F72*J72 -> 0 | N72: =+F72*K72 -> 0
A73: 13.03 | B73: Revestimiento tejuela exterior - Provisión a cargo del comitente | C73: m2 | D73: 147.601 | E73: 29881 | F73: =+D73*E73 -> 4410465.5 | I73: =+'SVD 4140_Pto. 01_Cert. 03'!K73 -> 0 | K73: =+I73+J73 -> 0 | L73: =+F73*I73 -> 0 | M73: =+F73*J73 -> 0 | N73: =+F73*K73 -> 0
A74: 13.04 | B74: Provisión y colocación de perfileria de aluminio tipo ATRIM L anod. Natural | C74: u | D74: 41 | E74: 19692 | F74: =+D74*E74 -> 807372 | I74: =+'SVD 4140_Pto. 01_Cert. 03'!K74 -> 0 | K74: =+I74+J74 -> 0 | L74: =+F74*I74 -> 0 | M74: =+F74*J74 -> 0 | N74: =+F74*K74 -> 0
A75: 14 | B75: CIELORRASOS | G75: =+SUM(F76:F82) -> 50296169 | H75: =+G75/$G$185 -> 0.068369036
A76: 14.01 | B76: Cielorraso junta tomada placa STD | C76: m2 | D76: 334.9152 | E76: 29270 | F76: =+D76*E76 -> 9802967.9 | I76: =+'SVD 4140_Pto. 01_Cert. 03'!K76 -> 0 | K76: =+I76+J76 -> 0 | L76: =+F76*I76 -> 0 | M76: =+F76*J76 -> 0 | N76: =+F76*K76 -> 0
A77: 14.02 | B77: Cielorraso junta tomada placa RH | C77: m2 | D77: 280.3913 | E77: 33967 | F77: =+D77*E77 -> 9524051.3 | I77: =+'SVD 4140_Pto. 01_Cert. 03'!K77 -> 0 | K77: =+I77+J77 -> 0 | L77: =+F77*I77 -> 0 | M77: =+F77*J77 -> 0 | N77: =+F77*K77 -> 0
A78: 14.03 | B78: Cajon en junta tomada placa STD | C78: ml | D78: 60.8 | E78: 29270 | F78: =+D78*E78 -> 1779616 | I78: =+'SVD 4140_Pto. 01_Cert. 03'!K78 -> 0 | K78: =+I78+J78 -> 0 | L78: =+F78*I78 -> 0 | M78: =+F78*J78 -> 0 | N78: =+F78*K78 -> 0
A79: 14.04 | B79: Buña perimetral / Cantoneras | C79: ml | D79: 1058.38 | E79: 7873 | F79: =+D79*E79 -> 8332625.7 | I79: =+'SVD 4140_Pto. 01_Cert. 03'!K79 -> 0 | K79: =+I79+J79 -> 0 | L79: =+F79*I79 -> 0 | M79: =+F79*J79 -> 0 | N79: =+F79*K79 -> 0
A80: 14.05 | B80: Aplicado de yeso interior | C80: m2 | D80: 504.1222 | E80: 23364 | F80: =+D80*E80 -> 11778311 | I80: =+'SVD 4140_Pto. 01_Cert. 03'!K80 -> 0 | K80: =+I80+J80 -> 0 | L80: =+F80*I80 -> 0 | M80: =+F80*J80 -> 0 | N80: =+F80*K80 -> 0
A81: 14.06 | B81: Buña en yeso | C81: ml | D81: 555.99 | E81: 12771 | F81: =+D81*E81 -> 7100548.3 | I81: =+'SVD 4140_Pto. 01_Cert. 03'!K81 -> 0 | K81: =+I81+J81 -> 0 | L81: =+F81*I81 -> 0 | M81: =+F81*J81 -> 0 | N81: =+F81*K81 -> 0
A82: 14.07 | B82: H° Visto - Maquillaje para recibir pintura | C82: m2 | D82: 429.0778 | E82: 4610 | F82: =+D82*E82 -> 1978048.7 | I82: =+'SVD 4140_Pto. 01_Cert. 03'!K82 -> 0 | K82: =+I82+J82 -> 0 | L82: =+F82*I82 -> 0 | M82: =+F82*J82 -> 0 | N82: =+F82*K82 -> 0
A83: 15 | B83: PINTURA | G83: =+SUM(F84:F92) -> 0 | H83: =+G83/$G$185 -> 0
A84: 15.01 | B84: Látex interior para paredes Bco. mate (enduido parcial) | C84: m2 | D84: 2670 | E84: 0 | F84: =+D84*E84 -> 0 | I84: =+'SVD 4140_Pto. 01_Cert. 03'!K84 -> 0 | K84: =+I84+J84 -> 0 | L84: =+F84*I84 -> 0 | M84: =+F84*J84 -> 0 | N84: =+F84*K84 -> 0
A85: 15.02 | B85: Látex interior para paredes Bco. mate (s/enduido) | C85: m2 | D85: 961 | E85: 0 | F85: =+D85*E85 -> 0 | I85: =+'SVD 4140_Pto. 01_Cert. 03'!K85 -> 0 | K85: =+I85+J85 -> 0 | L85: =+F85*I85 -> 0 | M85: =+F85*J85 -> 0 | N85: =+F85*K85 -> 0
A86: 15.03 | B86: Látex para cielorraso Bco. mate (enduido parcial) | C86: m2 | D86: 518 | E86: 0 | F86: =+D86*E86 -> 0 | I86: =+'SVD 4140_Pto. 01_Cert. 03'!K86 -> 0 | K86: =+I86+J86 -> 0 | L86: =+F86*I86 -> 0 | M86: =+F86*J86 -> 0 | N86: =+F86*K86 -> 0
A87: 15.04 | B87: Látex para cielorraso Bco. mate (enduido completo) | C87: m2 | D87: 612 | E87: 0 | F87: =+D87*E87 -> 0 | I87: =+'SVD 4140_Pto. 01_Cert. 03'!K87 -> 0 | K87: =+I87+J87 -> 0 | L87: =+F87*I87 -> 0 | M87: =+F87*J87 -> 0 | N87: =+F87*K87 -> 0
A88: 15.05 | B88: Latex interior cielorraso sobre H° | C88: m2 | D88: 422 | E88: 0 | F88: =+D88*E88 -> 0 | I88: =+'SVD 4140_Pto. 01_Cert. 03'!K88 -> 0 | K88: =+I88+J88 -> 0 | L88: =+F88*I88 -> 0 | M88: =+F88*J88 -> 0 | N88: =+F88*K88 -> 0
A89: 15.07 | B89: Revestimiento plastico tipo Quimtex en exteriores y PB | C89: m2 | D89: 678.252 | E89: 0 | F89: =+D89*E89 -> 0 | I89: =+'SVD 4140_Pto. 01_Cert. 03'!K89 -> 0 | K89: =+I89+J89 -> 0 | L89: =+F89*I89 -> 0 | M89: =+F89*J89 -> 0 | N89: =+F89*K89 -> 0
A90: 15.08 | B90: Revestimiento plastico tipo Quimtex en exteriores a mas de 3m de altura, incluye medianeras | C90: m2 | D90: 728.4802 | E90: 0 | F90: =+D90*E90 -> 0 | I90: =+'SVD 4140_Pto. 01_Cert. 03'!K90 -> 0 | K90: =+I90+J90 -> 0 | L90: =+F90*I90 -> 0 | M90: =+F90*J90 -> 0 | N90: =+F90*K90 -> 0
A91: 15.09 | B91: Esmalte sintético en puertas placa, chapa y de ascensor | C91: un | D91: 76 | E91: 0 | F91: =+D91*E91 -> 0 | I91: =+'SVD 4140_Pto. 01_Cert. 03'!K91 -> 0 | K91: =+I91+J91 -> 0 | L91: =+F91*I91 -> 0 | M91: =+F91*J91 -> 0 | N91: =+F91*K91 -> 0
A92: 15.1 | B92: Convertidor y esmalte sintentico en barandas - Escalera, balcones, porton, medidores y SDM | C92: gl | D92: 1 | E92: 0 | F92: =+D92*E92 -> 0 | I92: =+'SVD 4140_Pto. 01_Cert. 03'!K92 -> 0 | K92: =+I92+J92 -> 0 | L92: =+F92*I92 -> 0 | M92: =+F92*J92 -> 0 | N92: =+F92*K92 -> 0
A93: 16 | B93: MARMOLES Y GRANITOS - PROVISION Y COLOCACION A CARGO DEL COMITENTE | G93: =+SUM(F94) -> 0 | H93: =+G93/$G$185 -> 0
E94: 0 | F94: =+D94*E94 -> 0 | I94: =+'SVD 4140_Pto. 01_Cert. 03'!K94 -> 0 | K94: =+I94+J94 -> 0 | L94: =+F94*I94 -> 0 | M94: =+F94*J94 -> 0 | N94: =+F94*K94 -> 0
A95: 17 | B95: CARPINTERIA - PROVISION A CARGO DEL COMITENTE | G95: =+SUM(F96:F99) -> 7258243 | H95: =+G95/$G$185 -> 0.0098663395
A96: 17.01 | B96: Amure de puertas placa Provisión a cargo del comitente | C96: u | D96: 47 | E96: 64232 | F96: =+D96*E96 -> 3018904 | I96: =+'SVD 4140_Pto. 01_Cert. 03'!K96 -> 0 | J96: 0.15 | K96: =+I96+J96 -> 0.15 | L96: =+F96*I96 -> 0 | M96: =+F96*J96 -> 452835.6 | N96: =+F96*K96 -> 452835.6
A97: 17.02 | B97: Amure de puertas de chapa e ingresos depto - Provisión a cargo del comitente | C97: u | D97: 23 | E97: 64232 | F97: =+D97*E97 -> 1477336 | I97: =+'SVD 4140_Pto. 01_Cert. 03'!K97 -> 0.08 | J97: 0.15 | K97: =+I97+J97 -> 0.23 | L97: =+F97*I97 -> 118186.88 | M97: =+F97*J97 -> 221600.4 | N97: =+F97*K97 -> 339787.28
A98: 17.03 | B98: Amure de premarcos - Provisión a cargo del comitente | C98: u | D98: 51 | E98: 41296 | F98: =+D98*E98 -> 2106096 | I98: =+'SVD 4140_Pto. 01_Cert. 03'!K98 -> 0 | J98: 0.1 | K98: =+I98+J98 -> 0.1 | L98: =+F98*I98 -> 0 | M98: =+F98*J98 -> 210609.6 | N98: =+F98*K98 -> 210609.6
A99: 17.04 | B99: Amure Puertas de Ascensor - Provisión a cargo del comitente | C99: u | D99: 7 | E99: 93701 | F99: =+D99*E99 -> 655907 | I99: =+'SVD 4140_Pto. 01_Cert. 03'!K99 -> 0 | K99: =+I99+J99 -> 0 | L99: =+F99*I99 -> 0 | M99: =+F99*J99 -> 0 | N99: =+F99*K99 -> 0
A100: 18 | B100: INSTALACION ELECTRICA | G100: =+SUM(F101:F130) -> 99277732 | H100: =+G100/$G$185 -> 0.13495109
A101: 18.01 | B101: Tendido y cableado boca Iluminación | C101: u | D101: 392 | E101: 59948 | F101: =+D101*E101 -> 23499616 | I101: =+'SVD 4140_Pto. 01_Cert. 03'!K101 -> 0.4 | K101: =+I101+J101 -> 0.4 | L101: =+F101*I101 -> 9399846.4 | M101: =+F101*J101 -> 0 | N101: =+F101*K101 -> 9399846.4
...

Sheet SVD 4140_Pto. 01_Cert. 05
F1: DÓLAR BNA | G1: DÓLAR MEP
F2: 1005 | G2: 1170
F4: 45628
B5: OBRA: EDIFICIO EL SALVADOR 4140 | I5: Certificado | J5: 5 | N5: 46080
B6: PRESUPUESTO OBRA CIVIL
B7: Descripción | C7: U | D7: Cant | E7: P unit | F7: Subtotal | I7: Avance | L7: Importe
B8: PRESUPUESTO 02 - ALBANILERIA + INSTALACIONES + TERMINACIONES | I8: Anterior | J8: Actual | K8: Acumulado | L8: Anterior | M8: Actual | N8: Acumulado
A9: 4 | B9: ALBAÑILERIA | G9: =+SUM(F10:F17) -> 54302890 | H9: =+G9/$G$185 -> 0.073815487
A10: 4.01 | B10: Muro tipo 1 (interiores, divisorio de locales) e: 10 cm - Ladrillo hueco 08 x 18 x 33 | C10: m2 | D10: 819 | E10: 18993 | F10: =+D10*E10 -> 15555267 | I10: =+'SVD 4140_Pto. 01_Cert. 04'!K10 -> 0.55 | J10: 0.15 | K10: =+I10+J10 -> 0.7 | L10: =+F10*I10 -> 8555396.9 | M10: =+F10*J10 -> 2333290 | N10: =+F10*K10 -> 10888687 | P10: 1041
A11: 4.02 | B11: Muro tipo 2 y 3 (medianera, caja de escaleras y ascensor) e: 15 cm - Ladrillo hueco portante 12 x 19 x 33 | C11: m2 | D11: 612 | E11: 25172 | F11: =+D11*E11 -> 15405264 | I11: =+'SVD 4140_Pto. 01_Cert. 04'!K11 -> 0.5 | J11: 0.1 | K11: =+I11+J11 -> 0.6 | L11: =+F11*I11 -> 7702632 | M11: =+F11*J11 -> 1540526.4 | N11: =+F11*K11 -> 9243158.4
A12: 4.03 | B12: Muro tipo 4 (divisorio de unidades y fachas) e: 15 cm - Ladrillo hueco 12 x 18 x 33 | C12: m2 | D12: 636 | E12: 21109 | F12: =+D12*E12 -> 13425324 | I12: =+'SVD 4140_Pto. 01_Cert. 04'!K12 -> 0.55 | J12: 0.15 | K12: =+I12+J12 -> 0.7 | L12: =+F12*I12 -> 7383928.2 | M12: =+F12*J12 -> 2013798.6 | N12: =+F12*K12 -> 9397726.8
A13: 4.04 | B13: Enchape medianeras existentes - Contemplamos picado zonas sueltas y enchape con ladrillo comun para PB | C13: m2 | D13: 195 | E13: 15092 | F13: =+D13*E13 -> 2942940 | I13: =+'SVD 4140_Pto. 01_Cert. 04'!K13 -> 0.15 | J13: 0 | K13: =+I13+J13 -> 0.15 | L13: =+F13*I13 -> 441441 | M13: =+F13*J13 -> 0 | N13: =+F13*K13 -> 441441
A14: 4.05 | B14: Mamposteria cribada de ladrillo visto en balcones | C14: m2 | D14: 30.054 | E14: 67420 | F14: =+D14*E14 -> 2026240.7 | I14: =+'SVD 4140_Pto. 01_Cert. 04'!K14 -> 0 | K14: =+I14+J14 -> 0 | L14: =+F14*I14 -> 0 | M14: =+F14*J14 -> 0 | N14: =+F14*K14 -> 0
A15: 4.06 | B15: Bloque de H° con masillado de hormigon | C15: m2 | D15: 24 | E15: 54908 | F15: =+D15*E15 -> 1317792 | I15: =+'SVD 4140_Pto. 01_Cert. 04'!K15 -> 0 | K15: =+I15+J15 -> 0 | L15: =+F15*I15 -> 0 | M15: =+F15*J15 -> 0 | N15: =+F15*K15 -> 0
A16: 4.07 | B16: Cordón de hormigón en umbrales carpinterías | C16: ml | D16: 81 | E16: 30989 | F16: =+D16*E16 -> 2510109 | I16: =+'SVD 4140_Pto. 01_Cert. 04'!K16 -> 0 | K16: =+I16+J16 -> 0 | L16: =+F16*I16 -> 0 | M16: =+F16*J16 -> 0 | N16: =+F16*K16 -> 0
A17: 4.08 | B17: Pozo de bombeo pluvial y cloacal | C17: gl | D17: 1 | E17: 1119953 | F17: =+D17*E17 -> 1119953 | I17: =+'SVD 4140_Pto. 01_Cert. 04'!K17 -> 0.5 | K17: =+I17+J17 -> 0.5 | L17: =+F17*I17 -> 559976.5 | M17: =+F17*J17 -> 0 | N17: =+F17*K17 -> 559976.5
A18: 5 | B18: AISLACIONES | G18: =+SUM(F19:F25) -> 35966419 | H18: =+G18/$G$185 -> 0.048890193
A19: 5.01 | B19: Aislación hidrófuga horizontal (baños) - Inc. membrana geotextil y 35% en concepto de babetas | C19: m2 | D19: 139.05 | E19: 21800 | F19: =+D19*E19 -> 3031290 | I19: 0 | K19: =+I19+J19 -> 0 | L19: =+F19*I19 -> 0 | M19: =+F19*J19 -> 0 | N19: =+F19*K19 -> 0
A20: 5.02 | B20: Azotado hidrofugo - Sobre medianeras existentes | C20: m2 | D20: 300 | E20: 5376 | F20: =+D20*E20 -> 1612800 | I20: 0 | K20: =+I20+J20 -> 0 | L20: =+F20*I20 -> 0 | M20: =+F20*J20 -> 0 | N20: =+F20*K20 -> 0
A21: 5.03 | B21: Azotado hidrofugo - Contrapiso de vereda | C21: m2 | D21: 48 | E21: 5376 | F21: =+D21*E21 -> 258048 | I21: 0 | K21: =+I21+J21 -> 0 | L21: =+F21*I21 -> 0 | M21: =+F21*J21 -> 0 | N21: =+F21*K21 -> 0
A22: 5.04 | B22: Aislación térmica en terrazas, eps e:2,00 cm | C22: m2 | D22: 262 | E22: 4403 | F22: =+D22*E22 -> 1153586 | I22: 0 | K22: =+I22+J22 -> 0 | L22: =+F22*I22 -> 0 | M22: =+F22*J22 -> 0 | N22: =+F22*K22 -> 0
A23: 5.05 | B23: Barrera de vapor | C23: m2 | D23: 510 | E23: 3578 | F23: =+D23*E23 -> 1824780 | I23: 0 | K23: =+I23+J23 -> 0 | L23: =+F23*I23 -> 0 | M23: =+F23*J23 -> 0 | N23: =+F23*K23 -> 0
A24: 5.06 | B24: Membrana asfaltica geotextil 4mm - Balcones y azotea - Inc. 20% en concepto de babetas | C24: m2 | D24: 510 | E24: 21800 | F24: =+D24*E24 -> 11118000 | I24: 0 | K24: =+I24+J24 -> 0 | L24: =+F24*I24 -> 0 | M24: =+F24*J24 -> 0 | N24: =+F24*K24 -> 0
A25: 5.07 | B25: Impermeabilización de subsuelo | C25: gl | D25: 1 | E25: 16967915 | F25: =+D25*E25 -> 16967915 | I25: 1 | K25: =+I25+J25 -> 1 | L25: =+F25*I25 -> 16967915 | M25: =+F25*J25 -> 0 | N25: =+F25*K25 -> 16967915
A26: 6 | B26: CUBIERTAS | G26: =+SUM(F27) -> 2433900 | H26: =+G26/$G$185 -> 0.0033084706
A27: 6.02 | B27: Babeta de chapa galvanizada en medianeras | C27: ml | D27: 60 | E27: 40565 | F27: =+D27*E27 -> 2433900 | I27: =+'SVD 4140_Pto. 01_Cert. 04'!K27 -> 0 | K27: =+I27+J27 -> 0 | L27: =+F27*I27 -> 0 | M27: =+F27*J27 -> 0 | N27: =+F27*K27 -> 0
A28: 7 | B28: REVOQUES | G28: =+SUM(F29:F36) -> 1.3639056e+08 | H28: =+G28/$G$185 -> 0.18539962
A29: 7.01 | B29: Revoque Grueso Impermeable Exterior proyectable | C29: m2 | D29: 678.252 | E29: 16571 | F29: =+D29*E29 -> 11239314 | I29: =+'SVD 4140_Pto. 01_Cert. 04'!K29 -> 0 | K29: =+I29+J29 -> 0 | L29: =+F29*I29 -> 0 | M29: =+F29*J29 -> 0 | N29: =+F29*K29 -> 0
A30: 7.02 | B30: Revoque Grueso Impermeable Exterior a mas de 3m proyectable - Medianero y fachadas | C30: m2 | D30: 876.0812 | E30: 22183 | F30: =+D30*E30 -> 19434109 | I30: =+'SVD 4140_Pto. 01_Cert. 04'!K30 -> 0 | K30: =+I30+J30 -> 0 | L30: =+F30*I30 -> 0 | M30: =+F30*J30 -> 0 | N30: =+F30*K30 -> 0
A31: 7.03 | B31: Buña en revoque | C31: ml | D31: 182 | E31: 10806 | F31: =+D31*E31 -> 1966692 | I31: =+'SVD 4140_Pto. 01_Cert. 04'!K31 -> 0 | K31: =+I31+J31 -> 0 | L31: =+F31*I31 -> 0 | M31: =+F31*J31 -> 0 | N31: =+F31*K31 -> 0
A32: 7.04 | B32: Revoque Grueso Interior + fino | C32: m2 | D32: 995.8511 | E32: 26530 | F32: =+D32*E32 -> 26419930 | I32: =+'SVD 4140_Pto. 01_Cert. 04'!K32 -> 0.45 | K32: =+I32+J32 -> 0.45 | L32: =+F32*I32 -> 11888968 | M32: =+F32*J32 -> 0 | N32: =+F32*K32 -> 11888968
A33: 7.05 | B33: Yeso interior | C33: m2 | D33: 2514.897 | E33: 22566 | F33: =+D33*E33 -> 56751166 | I33: =+'SVD 4140_Pto. 01_Cert. 04'!K33 -> 0 | J33: 0.05 | K33: =+I33+J33 -> 0.05 | L33: =+F33*I33 -> 0 | M33: =+F33*J33 -> 2837558.3 | N33: =+F33*K33 -> 2837558.3
A34: 7.06 | B34: Arista en yeso | C34: ml | D34: 509.9 | E34: 12771 | F34: =+D34*E34 -> 6511932.9 | I34: =+'SVD 4140_Pto. 01_Cert. 04'!K34 -> 0 | J34: 0.05 | K34: =+I34+J34 -> 0.05 | L34: =+F34*I34 -> 0 | M34: =+F34*J34 -> 325596.65 | N34: =+F34*K34 -> 325596.65
A35: 7.07 | B35: Provisión y colocación de guardacanto yesero | C35: u | D35: 198 | E35: 14947 | F35: =+D35*E35 -> 2959506 | I35: =+'SVD 4140_Pto. 01_Cert. 04'!K35 -> 0 | K35: =+I35+J35 -> 0 | L35: =+F35*I35 -> 0 | M35: =+F35*J35 -> 0 | N35: =+F35*K35 -> 0
A36: 7.08 | B36: Revoque Grueso Impermeable Interior b/ revestimiento | C36: m2 | D36: 670.322 | E36: 16571 | F36: =+D36*E36 -> 11107906 | I36: =+'SVD 4140_Pto. 01_Cert. 04'!K36 -> 0 | K36: =+I36+J36 -> 0 | L36: =+F36*I36 -> 0 | M36: =+F36*J36 -> 0 | N36: =+F36*K36 -> 0
A37: 8 | B37: CONTRAPISOS Y CARPETAS | G37: =+SUM(F38:F45) -> 44788107 | H37: =+G37/$G$185 -> 0.060881768
A38: 8.01 | B38: Contrapiso de cascotes en SS e: 15 cm | C38: m2 | D38: 104 | E38: 31920 | F38: =+D38*E38 -> 3319680 | I38: =+'SVD 4140_Pto. 01_Cert. 04'!K38 -> 1 | K38: =+I38+J38 -> 1 | L38: =+F38*I38 -> 3319680 | M38: =+F38*J38 -> 0 | N38: =+F38*K38 -> 3319680
A39: 8.02 | B39: Contrapiso de cascote s/terreno natural e: 20 cm - Incluye film de polietileno | C39: m2 | D39: 48 | E39: 37268 | F39: =+D39*E39 -> 1788864 | I39: =+'SVD 4140_Pto. 01_Cert. 04'!K39 -> 0 | K39: =+I39+J39 -> 0 | L39: =+F39*I39 -> 0 | M39: =+F39*J39 -> 0 | N39: =+F39*K39 -> 0
A40: 8.03 | B40: Contrapiso de cascotes en azoteas c/pendiente e: 15 cm | C40: m2 | D40: 235 | E40: 32410 | F40: =+D40*E40 -> 7616350 | I40: =+'SVD 4140_Pto. 01_Cert. 04'!K40 -> 0 | K40: =+I40+J40 -> 0 | L40: =+F40*I40 -> 0 | M40: =+F40*J40 -> 0 | N40: =+F40*K40 -> 0
A41: 8.04 | B41: Contrapiso - Carpeta monolitico e: 7 cm | C41: m2 | D41: 878 | E41: 19006 | F41: =+D41*E41 -> 16687268 | I41: =+'SVD 4140_Pto. 01_Cert. 04'!K41 -> 0 | K41: =+I41+J41 -> 0 | L41: =+F41*I41 -> 0 | M41: =+F41*J41 -> 0 | N41: =+F41*K41 -> 0
A42: 8.05 | B42: Carpeta en PB y balcones, baños y azoteas e: 3,00 cm | C42: m2 | D42: 564 | E42: 12439 | F42: =+D42*E42 -> 7015596 | I42: =+'SVD 4140_Pto. 01_Cert. 04'!K42 -> 0 | K42: =+I42+J42 -> 0 | L42: =+F42*I42 -> 0 | M42: =+F42*J42 -> 0 | N42: =+F42*K42 -> 0
A43: 8.06 | B43: Carpeta sobre membrana | C43: m2 | D43: 438 | E43: 12439 | F43: =+D43*E43 -> 5448282 | I43: =+'SVD 4140_Pto. 01_Cert. 04'!K43 -> 0 | K43: =+I43+J43 -> 0 | L43: =+F43*I43 -> 0 | M43: =+F43*J43 -> 0 | N43: =+F43*K43 -> 0
A44: 8.07 | B44: Banquinas para cocinas | C44: gl | D44: 1 | E44: 2426924 | F44: =+D44*E44 -> 2426924 | I44: =+'SVD 4140_Pto. 01_Cert. 04'!K44 -> 0 | K44: =+I44+J44 -> 0 | L44: =+F44*I44 -> 0 | M44: =+F44*J44 -> 0 | N44: =+F44*K44 -> 0
A45: 8.08 | B45: Banquinas para bombas y tanques en SB | C45: gl | D45: 1 | E45: 485143 | F45: =+D45*E45 -> 485143 | I45: =+'SVD 4140_Pto. 01_Cert. 04'!K45 -> 0 | K45: =+I45+J45 -> 0 | L45: =+F45*I45 -> 0 | M45: =+F45*J45 -> 0 | N45: =+F45*K45 -> 0
A46: 9 | B46: ESCALERAS | G46: =+SUM(F47:F50) -> 5769056.6 | H46: =+G46/$G$185 -> 0.0078420454
A47: 9.01 | B47: Cemento alisado arrodillado en escaleras | C47: gl | D47: 1 | E47: 2024643 | F47: =+D47*E47 -> 2024643 | I47: =+'SVD 4140_Pto. 01_Cert. 04'!K47 -> 0 | K47: =+I47+J47 -> 0 | L47: =+F47*I47 -> 0 | M47: =+F47*J47 -> 0 | N47: =+F47*K47 -> 0
A48: 9.02 | B48: Provisión nariz escalera, hierro angulo 5/8 x 1/8" | C48: ml | D48: 122 | E48: 18814 | F48: =+D48*E48 -> 2295308 | I48: =+'SVD 4140_Pto. 01_Cert. 04'!K48 -> 0 | K48: =+I48+J48 -> 0 | L48: =+F48*I48 -> 0 | M48: =+F48*J48 -> 0 | N48: =+F48*K48 -> 0
A49: 9.03 | B49: Zócalo de concreto | C49: ml | D49: 155 | E49: 5376 | F49: =+D49*E49 -> 833280 | I49: =+'SVD 4140_Pto. 01_Cert. 04'!K49 -> 0 | K49: =+I49+J49 -> 0 | L49: =+F49*I49 -> 0 | M49: =+F49*J49 -> 0 | N49: =+F49*K49 -> 0
A50: 9.04 | B50: Provisión y colocación de Rodapie/ Zócalo rampante en placa cementicia | C50: ml | D50: 31.2 | E50: 19738 | F50: =+D50*E50 -> 615825.6 | I50: =+'SVD 4140_Pto. 01_Cert. 04'!K50 -> 0 | K50: =+I50+J50 -> 0 | L50: =+F50*I50 -> 0 | M50: =+F50*J50 -> 0 | N50: =+F50*K50 -> 0
A51: 10 | B51: VENTILACIONES | G51: =+SUM(F52:F55) -> 4669278 | H51: =+G51/$G$185 -> 0.0063470845
A52: 10.01 | B52: Ventilación Conducto Humos. Incluye toma de aire en PB - No aplica s/proyecto | C52: gl | D52: 0 | E52: 0 | F52: =+D52*E52 -> 0 | I52: =+'SVD 4140_Pto. 01_Cert. 04'!K52 -> 0 | K52: =+I52+J52 -> 0 | L52: =+F52*I52 -> 0 | M52: =+F52*J52 -> 0 | N52: =+F52*K52 -> 0
A53: 10.02 | B53: Ventilación Baños - En caño Ø 110 | C53: gl | D53: 1 | E53: 2199545 | F53: =+D53*E53 -> 2199545 | I53: =+'SVD 4140_Pto. 01_Cert. 04'!K53 -> 0 | K53: =+I53+J53 -> 0 | L53: =+F53*I53 -> 0 | M53: =+F53*J53 -> 0 | N53: =+F53*K53 -> 0
A54: 10.03 | B54: Colocación de rejillas de inyección y extracción - No aplica s/proyecto | C54: un | D54: 0 | E54: 0 | F54: =+D54*E54 -> 0 | I54: =+'SVD 4140_Pto. 01_Cert. 04'!K54 -> 0 | K54: =+I54+J54 -> 0 | L54: =+F54*I54 -> 0 | M54: =+F54*J54 -> 0 | N54: =+F54*K54 -> 0
A55: 10.04 | B55: Sombreretes en chapa prepintada C25 | C55: u | D55: 7 | E55: 352819 | F55: =+D55*E55 -> 2469733 | I55: =+'SVD 4140_Pto. 01_Cert. 04'!K55 -> 0 | K55: =+I55+J55 -> 0 | L55: =+F55*I55 -> 0 | M55: =+F55*J55 -> 0 | N55: =+F55*K55 -> 0
A56: 11 | B56: PISOS - PROVISION A CARGO DEL COMITENTE | G56: =+SUM(F57:F63) -> 48040802 | H56: =+G56/$G$185 -> 0.06530325
A57: 11.01 | B57: Colocación de travertino en hall PB - Provisión a cargo del comitente | C57: m2 | D57: 30 | E57: 21948 | F57: =+D57*E57 -> 658440 | I57: =+'SVD 4140_Pto. 01_Cert. 04'!K57 -> 0 | K57: =+I57+J57 -> 0 | L57: =+F57*I57 -> 0 | M57: =+F57*J57 -> 0 | N57: =+F57*K57 -> 0
A58: 11.02 | B58: Colocación de porcelanato en paliers, terraza y espacios comunes - Provisión a cargo del comitente | C58: m2 | D58: 185 | E58: 21948 | F58: =+D58*E58 -> 4060380 | I58: =+'SVD 4140_Pto. 01_Cert. 04'!K58 -> 0 | K58: =+I58+J58 -> 0 | L58: =+F58*I58 -> 0 | M58: =+F58*J58 -> 0 | N58: =+F58*K58 -> 0
A59: 11.03 | B59: Colocación de porcelanato en UF - Provisión a cargo del comitente | C59: m2 | D59: 942 | E59: 21948 | F59: =+D59*E59 -> 20675016 | I59: =+'SVD 4140_Pto. 01_Cert. 04'!K59 -> 0 | K59: =+I59+J59 -> 0 | L59: =+F59*I59 -> 0 | M59: =+F59*J59 -> 0 | N59: =+F59*K59 -> 0
A60: 11.04 | B60: Colocación de porcelanato en baños - Provisión a cargo del comitente | C60: m2 | D60: 110 | E60: 25799 | F60: =+D60*E60 -> 2837890 | I60: =+'SVD 4140_Pto. 01_Cert. 04'!K60 -> 0 | K60: =+I60+J60 -> 0 | L60: =+F60*I60 -> 0 | M60: =+F60*J60 -> 0 | N60: =+F60*K60 -> 0
A61: 11.05 | B61: Provisión y ejecución de alisado de cemento rodillado | C61: m2 | D61: 128 | E61: 16080 | F61: =+D61*E61 -> 2058240 | I61: =+'SVD 4140_Pto. 01_Cert. 04'!K61 -> 0 | K61: =+I61+J61 -> 0 | L61: =+F61*I61 -> 0 | M61: =+F61*J61 -> 0 | N61: =+F61*K61 -> 0
A62: 11.06 | B62: Colocación de baldoson de vereda - Provisión a cargo del comitente | C62: m2 | D62: 48 | E62: 21948 | F62: =+D62*E62 -> 1053504 | I62: =+'SVD 4140_Pto. 01_Cert. 04'!K62 -> 0 | K62: =+I62+J62 -> 0 | L62: =+F62*I62 -> 0 | M62: =+F62*J62 -> 0 | N62: =+F62*K62 -> 0
A63: 11.07 | B63: Provisión y ejecución de pavimento e: 18 cm, incluye malla Q188 | C63: m2 | D63: 226 | E63: 73882 | F63: =+D63*E63 -> 16697332 | I63: =+'SVD 4140_Pto. 01_Cert. 04'!K63 -> 0 | K63: =+I63+J63 -> 0 | L63: =+F63*I63 -> 0 | M63: =+F63*J63 -> 0 | N63: =+F63*K63 -> 0
A64: 12 | B64: ZOCALOS Y SOLIAS - PROVISION A CARGO DEL COMITENTE | G64: =+SUM(F65:F69) -> 11022518 | H64: =+G64/$G$185 -> 0.014983227
A65: 12.01 | B65: Provisión y colocación de zocalos de Madera (MDF) h: 7 cm | C65: ml | D65: 779 | E65: 7422 | F65: =+D65*E65 -> 5781738 | I65: =+'SVD 4140_Pto. 01_Cert. 04'!K65 -> 0 | K65: =+I65+J65 -> 0 | L65: =+F65*I65 -> 0 | M65: =+F65*J65 -> 0 | N65: =+F65*K65 -> 0
A66: 12.02 | B66: Zócalo de concreto | C66: ml | D66: 155 | E66: 5376 | F66: =+D66*E66 -> 833280 | I66: =+'SVD 4140_Pto. 01_Cert. 04'!K66 -> 0 | K66: =+I66+J66 -> 0 | L66: =+F66*I66 -> 0 | M66: =+F66*J66 -> 0 | N66: =+F66*K66 -> 0
A67: 12.03 | B67: Colocación de zocalo de porcelanico - Provisión a cargo del comitente | C67: ml | D67: 37 | E67: 7052 | F67: =+D67*E67 -> 260924 | I67: =+'SVD 4140_Pto. 01_Cert. 04'!K67 -> 0 | K67: =+I67+J67 -> 0 | L67: =+F67*I67 -> 0 | M67: =+F67*J67 -> 0 | N67: =+F67*K67 -> 0
A68: 12.04 | B68: Colocación de zocalo de porcelanato en palieres - Provisión a cargo del comitente | C68: ml | D68: 433 | E68: 7052 | F68: =+D68*E68 -> 3053516 | I68: =+'SVD 4140_Pto. 01_Cert. 04'!K68 -> 0 | K68: =+I68+J68 -> 0 | L68: =+F68*I68 -> 0 | M68: =+F68*J68 -> 0 | N68: =+F68*K68 -> 0
A69: 12.05 | B69: Colocación de zocalo de porcelanato en terraza y espacios comunes - Provisión a cargo del comitente | C69: ml | D69: 155 | E69: 7052 | F69: =+D69*E69 -> 1093060 | I69: =+'SVD 4140_Pto. 01_Cert. 04'!K69 -> 0 | K69: =+I69+J69 -> 0 | L69: =+F69*I69 -> 0 | M69: =+F69*J69 -> 0 | N69: =+F69*K69 -> 0
A70: 13 | B70: REVESTIMIENTOS - PROVISION A CARGO DEL COMITENTE | G70: =+SUM(F71:F74) -> 19433086 | H70: =+G70/$G$185 -> 0.026415956
A71: 13.01 | B71: Revestimiento en baños - Provisión a cargo del comitente | C71: m2 | D71: 511 | E71: 25799 | F71: =+D71*E71 -> 13183289 | I71: =+'SVD 4140_Pto. 01_Cert. 04'!K71 -> 0 | K71: =+I71+J71 -> 0 | L71: =+F71*I71 -> 0 | M71: =+F71*J71 -> 0 | N71: =+F71*K71 -> 0
A72: 13.02 | B72: Revestimiento en cocinas - Provisión a cargo del comitente | C72: m2 | D72: 40 | E72: 25799 | F72: =+D72*E72 -> 1031960 | I72: =+'SVD 4140_Pto. 01_Cert. 04'!K72 -> 0 | K72: =+I72+J72 -> 0 | L72: =+F72*I72 -> 0 | M72: =+F72*J72 -> 0 | N72: =+F72*K72 -> 0
A73: 13.03 | B73: Revestimiento tejuela exterior - Provisión a cargo del comitente | C73: m2 | D73: 147.601 | E73: 29881 | F73: =+D73*E73 -> 4410465.5 | I73: =+'SVD 4140_Pto. 01_Cert. 04'!K73 -> 0 | K73: =+I73+J73 -> 0 | L73: =+F73*I73 -> 0 | M73: =+F73*J73 -> 0 | N73: =+F73*K73 -> 0
A74: 13.04 | B74: Provisión y colocación de perfileria de aluminio tipo ATRIM L anod. Natural | C74: u | D74: 41 | E74: 19692 | F74: =+D74*E74 -> 807372 | I74: =+'SVD 4140_Pto. 01_Cert. 04'!K74 -> 0 | K74: =+I74+J74 -> 0 | L74: =+F74*I74 -> 0 | M74: =+F74*J74 -> 0 | N74: =+F74*K74 -> 0
A75: 14 | B75: CIELORRASOS | G75: =+SUM(F76:F82) -> 50296169 | H75: =+G75/$G$185 -> 0.068369036
A76: 14.01 | B76: Cielorraso junta tomada placa STD | C76: m2 | D76: 334.9152 | E76: 29270 | F76: =+D76*E76 -> 9802967.9 | I76: =+'SVD 4140_Pto. 01_Cert. 04'!K76 -> 0 | K76: =+I76+J76 -> 0 | L76: =+F76*I76 -> 0 | M76: =+F76*J76 -> 0 | N76: =+F76*K76 -> 0
A77: 14.02 | B77: Cielorraso junta tomada placa RH | C77: m2 | D77: 280.3913 | E77: 33967 | F77: =+D77*E77 -> 9524051.3 | I77: =+'SVD 4140_Pto. 01_Cert. 04'!K77 -> 0 | K77: =+I77+J77 -> 0 | L77: =+F77*I77 -> 0 | M77: =+F77*J77 -> 0 | N77: =+F77*K77 -> 0
A78: 14.03 | B78: Cajon en junta tomada placa STD | C78: ml | D78: 60.8 | E78: 29270 | F78: =+D78*E78 -> 1779616 | I78: =+'SVD 4140_Pto. 01_Cert. 04'!K78 -> 0 | K78: =+I78+J78 -> 0 | L78: =+F78*I78 -> 0 | M78: =+F78*J78 -> 0 | N78: =+F78*K78 -> 0
A79: 14.04 | B79: Buña perimetral / Cantoneras | C79: ml | D79: 1058.38 | E79: 7873 | F79: =+D79*E79 -> 8332625.7 | I79: =+'SVD 4140_Pto. 01_Cert. 04'!K79 -> 0 | K79: =+I79+J79 -> 0 | L79: =+F79*I79 -> 0 | M79: =+F79*J79 -> 0 | N79: =+F79*K79 -> 0
A80: 14.05 | B80: Aplicado de yeso interior | C80: m2 | D80: 504.1222 | E80: 23364 | F80: =+D80*E80 -> 11778311 | I80: =+'SVD 4140_Pto. 01_Cert. 04'!K80 -> 0 | K80: =+I80+J80 -> 0 | L80: =+F80*I80 -> 0 | M80: =+F80*J80 -> 0 | N80: =+F80*K80 -> 0
A81: 14.06 | B81: Buña en yeso | C81: ml | D81: 555.99 | E81: 12771 | F81: =+D81*E81 -> 7100548.3 | I81: =+'SVD 4140_Pto. 01_Cert. 04'!K81 -> 0 | K81: =+I81+J81 -> 0 | L81: =+F81*I81 -> 0 | M81: =+F81*J81 -> 0 | N81: =+F81*K81 -> 0
A82: 14.07 | B82: H° Visto - Maquillaje para recibir pintura | C82: m2 | D82: 429.0778 | E82: 4610 | F82: =+D82*E82 -> 1978048.7 | I82: =+'SVD 4140_Pto. 01_Cert. 04'!K82 -> 0 | K82: =+I82+J82 -> 0 | L82: =+F82*I82 -> 0 | M82: =+F82*J82 -> 0 | N82: =+F82*K82 -> 0
A83: 15 | B83: PINTURA | G83: =+SUM(F84:F92) -> 0 | H83: =+G83/$G$185 -> 0
A84: 15.01 | B84: Látex interior para paredes Bco. mate (enduido parcial) | C84: m2 | D84: 2670 | E84: 0 | F84: =+D84*E84 -> 0 | I84: =+'SVD 4140_Pto. 01_Cert. 04'!K84 -> 0 | K84: =+I84+J84 -> 0 | L84: =+F84*I84 -> 0 | M84: =+F84*J84 -> 0 | N84: =+F84*K84 -> 0
A85: 15.02 | B85: Látex interior para paredes Bco. mate (s/enduido) | C85: m2 | D85: 961 | E85: 0 | F85: =+D85*E85 -> 0 | I85: =+'SVD 4140_Pto. 01_Cert. 04'!K85 -> 0 | K85: =+I85+J85 -> 0 | L85: =+F85*I85 -> 0 | M85: =+F85*J85 -> 0 | N85: =+F85*K85 -> 0
A86: 15.03 | B86: Látex para cielorraso Bco. mate (enduido parcial) | C86: m2 | D86: 518 | E86: 0 | F86: =+D86*E86 -> 0 | I86: =+'SVD 4140_Pto. 01_Cert. 04'!K86 -> 0 | K86: =+I86+J86 -> 0 | L86: =+F86*I86 -> 0 | M86: =+F86*J86 -> 0 | N86: =+F86*K86 -> 0
A87: 15.04 | B87: Látex para cielorraso Bco. mate (enduido completo) | C87: m2 | D87: 612 | E87: 0 | F87: =+D87*E87 -> 0 | I87: =+'SVD 4140_Pto. 01_Cert. 04'!K87 -> 0 | K87: =+I87+J87 -> 0 | L87: =+F87*I87 -> 0 | M87: =+F87*J87 -> 0 | N87: =+F87*K87 -> 0
A88: 15.05 | B88: Latex interior cielorraso sobre H° | C88: m2 | D88: 422 | E88: 0 | F88: =+D88*E88 -> 0 | I88: =+'SVD 4140_Pto. 01_Cert. 04'!K88 -> 0 | K88: =+I88+J88 -> 0 | L88: =+F88*I88 -> 0 | M88: =+F88*J88 -> 0 | N88: =+F88*K88 -> 0
A89: 15.07 | B89: Revestimiento plastico tipo Quimtex en exteriores y PB | C89: m2 | D89: 678.252 | E89: 0 | F89: =+D89*E89 -> 0 | I89: =+'SVD 4140_Pto. 01_Cert. 04'!K89 -> 0 | K89: =+I89+J89 -> 0 | L89: =+F89*I89 -> 0 | M89: =+F89*J89 -> 0 | N89: =+F89*K89 -> 0
A90: 15.08 | B90: Revestimiento plastico tipo Quimtex en exteriores a mas de 3m de altura, incluye medianeras | C90: m2 | D90: 728.4802 | E90: 0 | F90: =+D90*E90 -> 0 | I90: =+'SVD 4140_Pto. 01_Cert. 04'!K90 -> 0 | K90: =+I90+J90 -> 0 | L90: =+F90*I90 -> 0 | M90: =+F90*J90 -> 0 | N90: =+F90*K90 -> 0
A91: 15.09 | B91: Esmalte sintético en puertas placa, chapa y de ascensor | C91: un | D91: 76 | E91: 0 | F91: =+D91*E91 -> 0 | I91: =+'SVD 4140_Pto. 01_Cert. 04'!K91 -> 0 | K91: =+I91+J91 -> 0 | L91: =+F91*I91 -> 0 | M91: =+F91*J91 -> 0 | N91: =+F91*K91 -> 0
A92: 15.1 | B92: Convertidor y esmalte sintentico en barandas - Escalera, balcones, porton, medidores y SDM | C92: gl | D92: 1 | E92: 0 | F92: =+D92*E92 -> 0 | I92: =+'SVD 4140_Pto. 01_Cert. 04'!K92 -> 0 | K92: =+I92+J92 -> 0 | L92: =+F92*I92 -> 0 | M92: =+F92*J92 -> 0 | N92: =+F92*K92 -> 0
A93: 16 | B93: MARMOLES Y GRANITOS - PROVISION Y COLOCACION A CARGO DEL COMITENTE | G93: =+SUM(F94) -> 0 | H93: =+G93/$G$185 -> 0
E94: 0 | F94: =+D94*E94 -> 0 | I94: =+'SVD 4140_Pto. 01_Cert. 04'!K94 -> 0 | K94: =+I94+J94 -> 0 | L94: =+F94*I94 -> 0 | M94: =+F94*J94 -> 0 | N94: =+F94*K94 -> 0
A95: 17 | B95: CARPINTERIA - PROVISION A CARGO DEL COMITENTE | G95: =+SUM(F96:F99) -> 7258243 | H95: =+G95/$G$185 -> 0.0098663395
A96: 17.01 | B96: Amure de puertas placa Provisión a cargo del comitente | C96: u | D96: 47 | E96: 64232 | F96: =+D96*E96 -> 3018904 | I96: =+'SVD 4140_Pto. 01_Cert. 04'!K96 -> 0.15 | J96: 0.2 | K96: =+I96+J96 -> 0.35 | L96: =+F96*I96 -> 452835.6 | M96: =+F96*J96 -> 603780.8 | N96: =+F96*K96 -> 1056616.4
A97: 17.02 | B97: Amure de puertas de chapa e ingresos depto - Provisión a cargo del comitente | C97: u | D97: 23 | E97: 64232 | F97: =+D97*E97 -> 1477336 | I97: =+'SVD 4140_Pto. 01_Cert. 04'!K97 -> 0.23 | J97: 0.15 | K97: =+I97+J97 -> 0.38 | L97: =+F97*I97 -> 339787.28 | M97: =+F97*J97 -> 221600.4 | N97: =+F97*K97 -> 561387.68
A98: 17.03 | B98: Amure de premarcos - Provisión a cargo del comitente | C98: u | D98: 51 | E98: 41296 | F98: =+D98*E98 -> 2106096 | I98: =+'SVD 4140_Pto. 01_Cert. 04'!K98 -> 0.1 | J98: 0.3 | K98: =+I98+J98 -> 0.4 | L98: =+F98*I98 -> 210609.6 | M98: =+F98*J98 -> 631828.8 | N98: =+F98*K98 -> 842438.4
A99: 17.04 | B99: Amure Puertas de Ascensor - Provisión a cargo del comitente | C99: u | D99: 7 | E99: 93701 | F99: =+D99*E99 -> 655907 | I99: =+'SVD 4140_Pto. 01_Cert. 04'!K99 -> 0 | K99: =+I99+J99 -> 0 | L99: =+F99*I99 -> 0 | M99: =+F99*J99 -> 0 | N99: =+F99*K99 -> 0
A100: 18 | B100: INSTALACION ELECTRICA | G100: =+SUM(F101:F130) -> 99277732 | H100: =+G100/$G$185 -> 0.13495109
A101: 18.01 | B101: Tendido y cableado boca Iluminación | C101: u | D101: 392 | E101: 59948 | F101: =+D101*E101 -> 23499616 | I101: =+'SVD 4140_Pto. 01_Cert. 04'!K101 -> 0.4 | J101: 0.05 | K101: =+I101+J101 -> 0.45 | L101: =+F101*I101 -> 9399846.4 | M101: =+F101*J101 -> 1174980.8 | N101: =+F101*K101 -> 10574827
...

Sheet SVD 4140_Pto. 01_Cert. 06
F1: DÓLAR BNA | G1: DÓLAR MEP
F2: 1005 | G2: 1170
F4: 45628
B5: OBRA: EDIFICIO EL SALVADOR 4140 | I5: Certificado | J5: 6 | N5: 46108
B6: PRESUPUESTO OBRA CIVIL
B7: Descripción | C7: U | D7: Cant | E7: P unit | F7: Subtotal | I7: Avance | L7: Importe
B8: PRESUPUESTO 02 - ALBANILERIA + INSTALACIONES + TERMINACIONES | I8: Anterior | J8: Actual | K8: Acumulado | L8: Anterior | M8: Actual | N8: Acumulado
A9: 4 | B9: ALBAÑILERIA | G9: =+SUM(F10:F17) -> 54302890 | H9: =+G9/$G$185 -> 0.073815487
A10: 4.01 | B10: Muro tipo 1 (interiores, divisorio de locales) e: 10 cm - Ladrillo hueco 08 x 18 x 33 | C10: m2 | D10: 819 | E10: 18993 | F10: =+D10*E10 -> 15555267 | I10: =+'SVD 4140_Pto. 01_Cert. 04'!K10 -> 0.55 | J10: 0.3 | K10: =+I10+J10 -> 0.85 | L10: =+F10*I10 -> 8555396.9 | M10: =+F10*J10 -> 4666580.1 | N10: =+F10*K10 -> 13221977
A11: 4.02 | B11: Muro tipo 2 y 3 (medianera, caja de escaleras y ascensor) e: 15 cm - Ladrillo hueco portante 12 x 19 x 33 | C11: m2 | D11: 612 | E11: 25172 | F11: =+D11*E11 -> 15405264 | I11: =+'SVD 4140_Pto. 01_Cert. 04'!K11 -> 0.5 | J11: 0.35 | K11: =+I11+J11 -> 0.85 | L11: =+F11*I11 -> 7702632 | M11: =+F11*J11 -> 5391842.4 | N11: =+F11*K11 -> 13094474
A12: 4.03 | B12: Muro tipo 4 (divisorio de unidades y fachas) e: 15 cm - Ladrillo hueco 12 x 18 x 33 | C12: m2 | D12: 636 | E12: 21109 | F12: =+D12*E12 -> 13425324 | I12: =+'SVD 4140_Pto. 01_Cert. 04'!K12 -> 0.55 | J12: 0.3 | K12: =+I12+J12 -> 0.85 | L12: =+F12*I12 -> 7383928.2 | M12: =+F12*J12 -> 4027597.2 | N12: =+F12*K12 -> 11411525
A13: 4.04 | B13: Enchape medianeras existentes - Contemplamos picado zonas sueltas y enchape con ladrillo comun para PB | C13: m2 | D13: 195 | E13: 15092 | F13: =+D13*E13 -> 2942940 | I13: =+'SVD 4140_Pto. 01_Cert. 04'!K13 -> 0.15 | K13: =+I13+J13 -> 0.15 | L13: =+F13*I13 -> 441441 | M13: =+F13*J13 -> 0 | N13: =+F13*K13 -> 441441
A14: 4.05 | B14: Mamposteria cribada de ladrillo visto en balcones | C14: m2 | D14: 30.054 | E14: 67420 | F14: =+D14*E14 -> 2026240.7 | I14: =+'SVD 4140_Pto. 01_Cert. 05'!K14 -> 0 | K14: =+I14+J14 -> 0 | L14: =+F14*I14 -> 0 | M14: =+F14*J14 -> 0 | N14: =+F14*K14 -> 0
A15: 4.06 | B15: Bloque de H° con masillado de hormigon | C15: m2 | D15: 24 | E15: 54908 | F15: =+D15*E15 -> 1317792 | I15: =+'SVD 4140_Pto. 01_Cert. 05'!K15 -> 0 | J15: 1 | K15: =+I15+J15 -> 1 | L15: =+F15*I15 -> 0 | M15: =+F15*J15 -> 1317792 | N15: =+F15*K15 -> 1317792
A16: 4.07 | B16: Cordón de hormigón en umbrales carpinterías | C16: ml | D16: 81 | E16: 30989 | F16: =+D16*E16 -> 2510109 | I16: =+'SVD 4140_Pto. 01_Cert. 05'!K16 -> 0 | J16: 0.75 | K16: =+I16+J16 -> 0.75 | L16: =+F16*I16 -> 0 | M16: =+F16*J16 -> 1882581.8 | N16: =+F16*K16 -> 1882581.8
A17: 4.08 | B17: Pozo de bombeo pluvial y cloacal | C17: gl | D17: 1 | E17: 1119953 | F17: =+D17*E17 -> 1119953 | I17: =+'SVD 4140_Pto. 01_Cert. 05'!K17 -> 0.5 | K17: =+I17+J17 -> 0.5 | L17: =+F17*I17 -> 559976.5 | M17: =+F17*J17 -> 0 | N17: =+F17*K17 -> 559976.5
A18: 5 | B18: AISLACIONES | G18: =+SUM(F19:F25) -> 35966419 | H18: =+G18/$G$185 -> 0.048890193
A19: 5.01 | B19: Aislación hidrófuga horizontal (baños) - Inc. membrana geotextil y 35% en concepto de babetas | C19: m2 | D19: 139.05 | E19: 21800 | F19: =+D19*E19 -> 3031290 | I19: =+'SVD 4140_Pto. 01_Cert. 05'!K19 -> 0 | K19: =+I19+J19 -> 0 | L19: =+F19*I19 -> 0 | M19: =+F19*J19 -> 0 | N19: =+F19*K19 -> 0
A20: 5.02 | B20: Azotado hidrofugo - Sobre medianeras existentes | C20: m2 | D20: 300 | E20: 5376 | F20: =+D20*E20 -> 1612800 | I20: =+'SVD 4140_Pto. 01_Cert. 05'!K20 -> 0 | J20: 0.5 | K20: =+I20+J20 -> 0.5 | L20: =+F20*I20 -> 0 | M20: =+F20*J20 -> 806400 | N20: =+F20*K20 -> 806400
A21: 5.03 | B21: Azotado hidrofugo - Contrapiso de vereda | C21: m2 | D21: 48 | E21: 5376 | F21: =+D21*E21 -> 258048 | I21: =+'SVD 4140_Pto. 01_Cert. 05'!K21 -> 0 | K21: =+I21+J21 -> 0 | L21: =+F21*I21 -> 0 | M21: =+F21*J21 -> 0 | N21: =+F21*K21 -> 0
A22: 5.04 | B22: Aislación térmica en terrazas, eps e:2,00 cm | C22: m2 | D22: 262 | E22: 4403 | F22: =+D22*E22 -> 1153586 | I22: =+'SVD 4140_Pto. 01_Cert. 05'!K22 -> 0 | K22: =+I22+J22 -> 0 | L22: =+F22*I22 -> 0 | M22: =+F22*J22 -> 0 | N22: =+F22*K22 -> 0
A23: 5.05 | B23: Barrera de vapor | C23: m2 | D23: 510 | E23: 3578 | F23: =+D23*E23 -> 1824780 | I23: =+'SVD 4140_Pto. 01_Cert. 05'!K23 -> 0 | K23: =+I23+J23 -> 0 | L23: =+F23*I23 -> 0 | M23: =+F23*J23 -> 0 | N23: =+F23*K23 -> 0
A24: 5.06 | B24: Membrana asfaltica geotextil 4mm - Balcones y azotea - Inc. 20% en concepto de babetas | C24: m2 | D24: 510 | E24: 21800 | F24: =+D24*E24 -> 11118000 | I24: =+'SVD 4140_Pto. 01_Cert. 05'!K24 -> 0 | K24: =+I24+J24 -> 0 | L24: =+F24*I24 -> 0 | M24: =+F24*J24 -> 0 | N24: =+F24*K24 -> 0
A25: 5.07 | B25: Impermeabilización de subsuelo | C25: gl | D25: 1 | E25: 16967915 | F25: =+D25*E25 -> 16967915 | I25: =+'SVD 4140_Pto. 01_Cert. 05'!K25 -> 1 | K25: =+I25+J25 -> 1 | L25: =+F25*I25 -> 16967915 | M25: =+F25*J25 -> 0 | N25: =+F25*K25 -> 16967915
A26: 6 | B26: CUBIERTAS | G26: =+SUM(F27) -> 2433900 | H26: =+G26/$G$185 -> 0.0033084706
A27: 6.02 | B27: Babeta de chapa galvanizada en medianeras | C27: ml | D27: 60 | E27: 40565 | F27: =+D27*E27 -> 2433900 | I27: =+'SVD 4140_Pto. 01_Cert. 05'!K27 -> 0 | K27: =+I27+J27 -> 0 | L27: =+F27*I27 -> 0 | M27: =+F27*J27 -> 0 | N27: =+F27*K27 -> 0
A28: 7 | B28: REVOQUES | G28: =+SUM(F29:F36) -> 1.3639056e+08 | H28: =+G28/$G$185 -> 0.18539962
A29: 7.01 | B29: Revoque Grueso Impermeable Exterior proyectable | C29: m2 | D29: 678.252 | E29: 16571 | F29: =+D29*E29 -> 11239314 | I29: =+'SVD 4140_Pto. 01_Cert. 05'!K29 -> 0 | K29: =+I29+J29 -> 0 | L29: =+F29*I29 -> 0 | M29: =+F29*J29 -> 0 | N29: =+F29*K29 -> 0
A30: 7.02 | B30: Revoque Grueso Impermeable Exterior a mas de 3m proyectable - Medianero y fachadas | C30: m2 | D30: 876.0812 | E30: 22183 | F30: =+D30*E30 -> 19434109 | I30: =+'SVD 4140_Pto. 01_Cert. 05'!K30 -> 0 | K30: =+I30+J30 -> 0 | L30: =+F30*I30 -> 0 | M30: =+F30*J30 -> 0 | N30: =+F30*K30 -> 0
A31: 7.03 | B31: Buña en revoque | C31: ml | D31: 182 | E31: 10806 | F31: =+D31*E31 -> 1966692 | I31: =+'SVD 4140_Pto. 01_Cert. 05'!K31 -> 0 | K31: =+I31+J31 -> 0 | L31: =+F31*I31 -> 0 | M31: =+F31*J31 -> 0 | N31: =+F31*K31 -> 0
A32: 7.04 | B32: Revoque Grueso Interior + fino | C32: m2 | D32: 995.8511 | E32: 26530 | F32: =+D32*E32 -> 26419930 | I32: =+'SVD 4140_Pto. 01_Cert. 05'!K32 -> 0.45 | K32: =+I32+J32 -> 0.45 | L32: =+F32*I32 -> 11888968 | M32: =+F32*J32 -> 0 | N32: =+F32*K32 -> 11888968
A33: 7.05 | B33: Yeso interior | C33: m2 | D33: 2514.897 | E33: 22566 | F33: =+D33*E33 -> 56751166 | I33: =+'SVD 4140_Pto. 01_Cert. 05'!K33 -> 0.05 | K33: =+I33+J33 -> 0.05 | L33: =+F33*I33 -> 2837558.3 | M33: =+F33*J33 -> 0 | N33: =+F33*K33 -> 2837558.3
A34: 7.06 | B34: Arista en yeso | C34: ml | D34: 509.9 | E34: 12771 | F34: =+D34*E34 -> 6511932.9 | I34: =+'SVD 4140_Pto. 01_Cert. 05'!K34 -> 0.05 | K34: =+I34+J34 -> 0.05 | L34: =+F34*I34 -> 325596.65 | M34: =+F34*J34 -> 0 | N34: =+F34*K34 -> 325596.65
A35: 7.07 | B35: Provisión y colocación de guardacanto yesero | C35: u | D35: 198 | E35: 14947 | F35: =+D35*E35 -> 2959506 | I35: =+'SVD 4140_Pto. 01_Cert. 05'!K35 -> 0 | K35: =+I35+J35 -> 0 | L35: =+F35*I35 -> 0 | M35: =+F35*J35 -> 0 | N35: =+F35*K35 -> 0
A36: 7.08 | B36: Revoque Grueso Impermeable Interior b/ revestimiento | C36: m2 | D36: 670.322 | E36: 16571 | F36: =+D36*E36 -> 11107906 | I36: =+'SVD 4140_Pto. 01_Cert. 05'!K36 -> 0 | K36: =+I36+J36 -> 0 | L36: =+F36*I36 -> 0 | M36: =+F36*J36 -> 0 | N36: =+F36*K36 -> 0
A37: 8 | B37: CONTRAPISOS Y CARPETAS | G37: =+SUM(F38:F45) -> 44788107 | H37: =+G37/$G$185 -> 0.060881768
A38: 8.01 | B38: Contrapiso de cascotes en SS e: 15 cm | C38: m2 | D38: 104 | E38: 31920 | F38: =+D38*E38 -> 3319680 | I38: =+'SVD 4140_Pto. 01_Cert. 05'!K38 -> 1 | K38: =+I38+J38 -> 1 | L38: =+F38*I38 -> 3319680 | M38: =+F38*J38 -> 0 | N38: =+F38*K38 -> 3319680
A39: 8.02 | B39: Contrapiso de cascote s/terreno natural e: 20 cm - Incluye film de polietileno | C39: m2 | D39: 48 | E39: 37268 | F39: =+D39*E39 -> 1788864 | I39: =+'SVD 4140_Pto. 01_Cert. 05'!K39 -> 0 | K39: =+I39+J39 -> 0 | L39: =+F39*I39 -> 0 | M39: =+F39*J39 -> 0 | N39: =+F39*K39 -> 0
A40: 8.03 | B40: Contrapiso de cascotes en azoteas c/pendiente e: 15 cm | C40: m2 | D40: 235 | E40: 32410 | F40: =+D40*E40 -> 7616350 | I40: =+'SVD 4140_Pto. 01_Cert. 05'!K40 -> 0 | K40: =+I40+J40 -> 0 | L40: =+F40*I40 -> 0 | M40: =+F40*J40 -> 0 | N40: =+F40*K40 -> 0
A41: 8.04 | B41: Contrapiso - Carpeta monolitico e: 7 cm | C41: m2 | D41: 878 | E41: 19006 | F41: =+D41*E41 -> 16687268 | I41: =+'SVD 4140_Pto. 01_Cert. 05'!K41 -> 0 | K41: =+I41+J41 -> 0 | L41: =+F41*I41 -> 0 | M41: =+F41*J41 -> 0 | N41: =+F41*K41 -> 0
A42: 8.05 | B42: Carpeta en PB y balcones, baños y azoteas e: 3,00 cm | C42: m2 | D42: 564 | E42: 12439 | F42: =+D42*E42 -> 7015596 | I42: =+'SVD 4140_Pto. 01_Cert. 05'!K42 -> 0 | K42: =+I42+J42 -> 0 | L42: =+F42*I42 -> 0 | M42: =+F42*J42 -> 0 | N42: =+F42*K42 -> 0
A43: 8.06 | B43: Carpeta sobre membrana | C43: m2 | D43: 438 | E43: 12439 | F43: =+D43*E43 -> 5448282 | I43: =+'SVD 4140_Pto. 01_Cert. 05'!K43 -> 0 | K43: =+I43+J43 -> 0 | L43: =+F43*I43 -> 0 | M43: =+F43*J43 -> 0 | N43: =+F43*K43 -> 0
A44: 8.07 | B44: Banquinas para cocinas | C44: gl | D44: 1 | E44: 2426924 | F44: =+D44*E44 -> 2426924 | I44: =+'SVD 4140_Pto. 01_Cert. 05'!K44 -> 0 | K44: =+I44+J44 -> 0 | L44: =+F44*I44 -> 0 | M44: =+F44*J44 -> 0 | N44: =+F44*K44 -> 0
A45: 8.08 | B45: Banquinas para bombas y tanques en SB | C45: gl | D45: 1 | E45: 485143 | F45: =+D45*E45 -> 485143 | I45: =+'SVD 4140_Pto. 01_Cert. 05'!K45 -> 0 | K45: =+I45+J45 -> 0 | L45: =+F45*I45 -> 0 | M45: =+F45*J45 -> 0 | N45: =+F45*K45 -> 0
A46: 9 | B46: ESCALERAS | G46: =+SUM(F47:F50) -> 5769056.6 | H46: =+G46/$G$185 -> 0.0078420454
A47: 9.01 | B47: Cemento alisado arrodillado en escaleras | C47: gl | D47: 1 | E47: 2024643 | F47: =+D47*E47 -> 2024643 | I47: =+'SVD 4140_Pto. 01_Cert. 05'!K47 -> 0 | K47: =+I47+J47 -> 0 | L47: =+F47*I47 -> 0 | M47: =+F47*J47 -> 0 | N47: =+F47*K47 -> 0
A48: 9.02 | B48: Provisión nariz escalera, hierro angulo 5/8 x 1/8" | C48: ml | D48: 122 | E48: 18814 | F48: =+D48*E48 -> 2295308 | I48: =+'SVD 4140_Pto. 01_Cert. 05'!K48 -> 0 | K48: =+I48+J48 -> 0 | L48: =+F48*I48 -> 0 | M48: =+F48*J48 -> 0 | N48: =+F48*K48 -> 0
A49: 9.03 | B49: Zócalo de concreto | C49: ml | D49: 155 | E49: 5376 | F49: =+D49*E49 -> 833280 | I49: =+'SVD 4140_Pto. 01_Cert. 05'!K49 -> 0 | K49: =+I49+J49 -> 0 | L49: =+F49*I49 -> 0 | M49: =+F49*J49 -> 0 | N49: =+F49*K49 -> 0
A50: 9.04 | B50: Provisión y colocación de Rodapie/ Zócalo rampante en placa cementicia | C50: ml | D50: 31.2 | E50: 19738 | F50: =+D50*E50 -> 615825.6 | I50: =+'SVD 4140_Pto. 01_Cert. 05'!K50 -> 0 | K50: =+I50+J50 -> 0 | L50: =+F50*I50 -> 0 | M50: =+F50*J50 -> 0 | N50: =+F50*K50 -> 0
A51: 10 | B51: VENTILACIONES | G51: =+SUM(F52:F55) -> 4669278 | H51: =+G51/$G$185 -> 0.0063470845
A52: 10.01 | B52: Ventilación Conducto Humos. Incluye toma de aire en PB - No aplica s/proyecto | C52: gl | D52: 0 | E52: 0 | F52: =+D52*E52 -> 0 | I52: =+'SVD 4140_Pto. 01_Cert. 05'!K52 -> 0 | K52: =+I52+J52 -> 0 | L52: =+F52*I52 -> 0 | M52: =+F52*J52 -> 0 | N52: =+F52*K52 -> 0
A53: 10.02 | B53: Ventilación Baños - En caño Ø 110 | C53: gl | D53: 1 | E53: 2199545 | F53: =+D53*E53 -> 2199545 | I53: =+'SVD 4140_Pto. 01_Cert. 05'!K53 -> 0 | J53: 0.2 | K53: =+I53+J53 -> 0.2 | L53: =+F53*I53 -> 0 | M53: =+F53*J53 -> 439909 | N53: =+F53*K53 -> 439909
A54: 10.03 | B54: Colocación de rejillas de inyección y extracción - No aplica s/proyecto | C54: un | D54: 0 | E54: 0 | F54: =+D54*E54 -> 0 | I54: =+'SVD 4140_Pto. 01_Cert. 05'!K54 -> 0 | K54: =+I54+J54 -> 0 | L54: =+F54*I54 -> 0 | M54: =+F54*J54 -> 0 | N54: =+F54*K54 -> 0
A55: 10.04 | B55: Sombreretes en chapa prepintada C25 | C55: u | D55: 7 | E55: 352819 | F55: =+D55*E55 -> 2469733 | I55: =+'SVD 4140_Pto. 01_Cert. 05'!K55 -> 0 | K55: =+I55+J55 -> 0 | L55: =+F55*I55 -> 0 | M55: =+F55*J55 -> 0 | N55: =+F55*K55 -> 0
A56: 11 | B56: PISOS - PROVISION A CARGO DEL COMITENTE | G56: =+SUM(F57:F63) -> 48040802 | H56: =+G56/$G$185 -> 0.06530325
A57: 11.01 | B57: Colocación de travertino en hall PB - Provisión a cargo del comitente | C57: m2 | D57: 30 | E57: 21948 | F57: =+D57*E57 -> 658440 | I57: =+'SVD 4140_Pto. 01_Cert. 05'!K57 -> 0 | K57: =+I57+J57 -> 0 | L57: =+F57*I57 -> 0 | M57: =+F57*J57 -> 0 | N57: =+F57*K57 -> 0
A58: 11.02 | B58: Colocación de porcelanato en paliers, terraza y espacios comunes - Provisión a cargo del comitente | C58: m2 | D58: 185 | E58: 21948 | F58: =+D58*E58 -> 4060380 | I58: =+'SVD 4140_Pto. 01_Cert. 05'!K58 -> 0 | K58: =+I58+J58 -> 0 | L58: =+F58*I58 -> 0 | M58: =+F58*J58 -> 0 | N58: =+F58*K58 -> 0
A59: 11.03 | B59: Colocación de porcelanato en UF - Provisión a cargo del comitente | C59: m2 | D59: 942 | E59: 21948 | F59: =+D59*E59 -> 20675016 | I59: =+'SVD 4140_Pto. 01_Cert. 05'!K59 -> 0 | K59: =+I59+J59 -> 0 | L59: =+F59*I59 -> 0 | M59: =+F59*J59 -> 0 | N59: =+F59*K59 -> 0
A60: 11.04 | B60: Colocación de porcelanato en baños - Provisión a cargo del comitente | C60: m2 | D60: 110 | E60: 25799 | F60: =+D60*E60 -> 2837890 | I60: =+'SVD 4140_Pto. 01_Cert. 05'!K60 -> 0 | K60: =+I60+J60 -> 0 | L60: =+F60*I60 -> 0 | M60: =+F60*J60 -> 0 | N60: =+F60*K60 -> 0
A61: 11.05 | B61: Provisión y ejecución de alisado de cemento rodillado | C61: m2 | D61: 128 | E61: 16080 | F61: =+D61*E61 -> 2058240 | I61: =+'SVD 4140_Pto. 01_Cert. 05'!K61 -> 0 | K61: =+I61+J61 -> 0 | L61: =+F61*I61 -> 0 | M61: =+F61*J61 -> 0 | N61: =+F61*K61 -> 0
A62: 11.06 | B62: Colocación de baldoson de vereda - Provisión a cargo del comitente | C62: m2 | D62: 48 | E62: 21948 | F62: =+D62*E62 -> 1053504 | I62: =+'SVD 4140_Pto. 01_Cert. 05'!K62 -> 0 | K62: =+I62+J62 -> 0 | L62: =+F62*I62 -> 0 | M62: =+F62*J62 -> 0 | N62: =+F62*K62 -> 0
A63: 11.07 | B63: Provisión y ejecución de pavimento e: 18 cm, incluye malla Q188 | C63: m2 | D63: 226 | E63: 73882 | F63: =+D63*E63 -> 16697332 | I63: =+'SVD 4140_Pto. 01_Cert. 05'!K63 -> 0 | K63: =+I63+J63 -> 0 | L63: =+F63*I63 -> 0 | M63: =+F63*J63 -> 0 | N63: =+F63*K63 -> 0
A64: 12 | B64: ZOCALOS Y SOLIAS - PROVISION A CARGO DEL COMITENTE | G64: =+SUM(F65:F69) -> 11022518 | H64: =+G64/$G$185 -> 0.014983227
A65: 12.01 | B65: Provisión y colocación de zocalos de Madera (MDF) h: 7 cm | C65: ml | D65: 779 | E65: 7422 | F65: =+D65*E65 -> 5781738 | I65: =+'SVD 4140_Pto. 01_Cert. 05'!K65 -> 0 | K65: =+I65+J65 -> 0 | L65: =+F65*I65 -> 0 | M65: =+F65*J65 -> 0 | N65: =+F65*K65 -> 0
A66: 12.02 | B66: Zócalo de concreto | C66: ml | D66: 155 | E66: 5376 | F66: =+D66*E66 -> 833280 | I66: =+'SVD 4140_Pto. 01_Cert. 05'!K66 -> 0 | K66: =+I66+J66 -> 0 | L66: =+F66*I66 -> 0 | M66: =+F66*J66 -> 0 | N66: =+F66*K66 -> 0
A67: 12.03 | B67: Colocación de zocalo de porcelanico - Provisión a cargo del comitente | C67: ml | D67: 37 | E67: 7052 | F67: =+D67*E67 -> 260924 | I67: =+'SVD 4140_Pto. 01_Cert. 05'!K67 -> 0 | K67: =+I67+J67 -> 0 | L67: =+F67*I67 -> 0 | M67: =+F67*J67 -> 0 | N67: =+F67*K67 -> 0
A68: 12.04 | B68: Colocación de zocalo de porcelanato en palieres - Provisión a cargo del comitente | C68: ml | D68: 433 | E68: 7052 | F68: =+D68*E68 -> 3053516 | I68: =+'SVD 4140_Pto. 01_Cert. 05'!K68 -> 0 | K68: =+I68+J68 -> 0 | L68: =+F68*I68 -> 0 | M68: =+F68*J68 -> 0 | N68: =+F68*K68 -> 0
A69: 12.05 | B69: Colocación de zocalo de porcelanato en terraza y espacios comunes - Provisión a cargo del comitente | C69: ml | D69: 155 | E69: 7052 | F69: =+D69*E69 -> 1093060 | I69: =+'SVD 4140_Pto. 01_Cert. 05'!K69 -> 0 | K69: =+I69+J69 -> 0 | L69: =+F69*I69 -> 0 | M69: =+F69*J69 -> 0 | N69: =+F69*K69 -> 0
A70: 13 | B70: REVESTIMIENTOS - PROVISION A CARGO DEL COMITENTE | G70: =+SUM(F71:F74) -> 19433086 | H70: =+G70/$G$185 -> 0.026415956
A71: 13.01 | B71: Revestimiento en baños - Provisión a cargo del comitente | C71: m2 | D71: 511 | E71: 25799 | F71: =+D71*E71 -> 13183289 | I71: =+'SVD 4140_Pto. 01_Cert. 05'!K71 -> 0 | K71: =+I71+J71 -> 0 | L71: =+F71*I71 -> 0 | M71: =+F71*J71 -> 0 | N71: =+F71*K71 -> 0
A72: 13.02 | B72: Revestimiento en cocinas - Provisión a cargo del comitente | C72: m2 | D72: 40 | E72: 25799 | F72: =+D72*E72 -> 1031960 | I72: =+'SVD 4140_Pto. 01_Cert. 05'!K72 -> 0 | K72: =+I72+J72 -> 0 | L72: =+F72*I72 -> 0 | M72: =+F72*J72 -> 0 | N72: =+F72*K72 -> 0
A73: 13.03 | B73: Revestimiento tejuela exterior - Provisión a cargo del comitente | C73: m2 | D73: 147.601 | E73: 29881 | F73: =+D73*E73 -> 4410465.5 | I73: =+'SVD 4140_Pto. 01_Cert. 05'!K73 -> 0 | K73: =+I73+J73 -> 0 | L73: =+F73*I73 -> 0 | M73: =+F73*J73 -> 0 | N73: =+F73*K73 -> 0
A74: 13.04 | B74: Provisión y colocación de perfileria de aluminio tipo ATRIM L anod. Natural | C74: u | D74: 41 | E74: 19692 | F74: =+D74*E74 -> 807372 | I74: =+'SVD 4140_Pto. 01_Cert. 05'!K74 -> 0 | K74: =+I74+J74 -> 0 | L74: =+F74*I74 -> 0 | M74: =+F74*J74 -> 0 | N74: =+F74*K74 -> 0
A75: 14 | B75: CIELORRASOS | G75: =+SUM(F76:F82) -> 50296169 | H75: =+G75/$G$185 -> 0.068369036
A76: 14.01 | B76: Cielorraso junta tomada placa STD | C76: m2 | D76: 334.9152 | E76: 29270 | F76: =+D76*E76 -> 9802967.9 | I76: =+'SVD 4140_Pto. 01_Cert. 05'!K76 -> 0 | J76: 0.05 | K76: =+I76+J76 -> 0.05 | L76: =+F76*I76 -> 0 | M76: =+F76*J76 -> 490148.4 | N76: =+F76*K76 -> 490148.4
A77: 14.02 | B77: Cielorraso junta tomada placa RH | C77: m2 | D77: 280.3913 | E77: 33967 | F77: =+D77*E77 -> 9524051.3 | I77: =+'SVD 4140_Pto. 01_Cert. 05'!K77 -> 0 | J77: 0.05 | K77: =+I77+J77 -> 0.05 | L77: =+F77*I77 -> 0 | M77: =+F77*J77 -> 476202.56 | N77: =+F77*K77 -> 476202.56
A78: 14.03 | B78: Cajon en junta tomada placa STD | C78: ml | D78: 60.8 | E78: 29270 | F78: =+D78*E78 -> 1779616 | I78: =+'SVD 4140_Pto. 01_Cert. 05'!K78 -> 0 | J78: 0.05 | K78: =+I78+J78 -> 0.05 | L78: =+F78*I78 -> 0 | M78: =+F78*J78 -> 88980.8 | N78: =+F78*K78 -> 88980.8
A79: 14.04 | B79: Buña perimetral / Cantoneras | C79: ml | D79: 1058.38 | E79: 7873 | F79: =+D79*E79 -> 8332625.7 | I79: =+'SVD 4140_Pto. 01_Cert. 05'!K79 -> 0 | K79: =+I79+J79 -> 0 | L79: =+F79*I79 -> 0 | M79: =+F79*J79 -> 0 | N79: =+F79*K79 -> 0
A80: 14.05 | B80: Aplicado de yeso interior | C80: m2 | D80: 504.1222 | E80: 23364 | F80: =+D80*E80 -> 11778311 | I80: =+'SVD 4140_Pto. 01_Cert. 05'!K80 -> 0 | K80: =+I80+J80 -> 0 | L80: =+F80*I80 -> 0 | M80: =+F80*J80 -> 0 | N80: =+F80*K80 -> 0
A81: 14.06 | B81: Buña en yeso | C81: ml | D81: 555.99 | E81: 12771 | F81: =+D81*E81 -> 7100548.3 | I81: =+'SVD 4140_Pto. 01_Cert. 05'!K81 -> 0 | K81: =+I81+J81 -> 0 | L81: =+F81*I81 -> 0 | M81: =+F81*J81 -> 0 | N81: =+F81*K81 -> 0
A82: 14.07 | B82: H° Visto - Maquillaje para recibir pintura | C82: m2 | D82: 429.0778 | E82: 4610 | F82: =+D82*E82 -> 1978048.7 | I82: =+'SVD 4140_Pto. 01_Cert. 05'!K82 -> 0 | K82: =+I82+J82 -> 0 | L82: =+F82*I82 -> 0 | M82: =+F82*J82 -> 0 | N82: =+F82*K82 -> 0
A83: 15 | B83: PINTURA | G83: =+SUM(F84:F92) -> 0 | H83: =+G83/$G$185 -> 0
A84: 15.01 | B84: Látex interior para paredes Bco. mate (enduido parcial) | C84: m2 | D84: 2670 | E84: 0 | F84: =+D84*E84 -> 0 | I84: =+'SVD 4140_Pto. 01_Cert. 05'!K84 -> 0 | K84: =+I84+J84 -> 0 | L84: =+F84*I84 -> 0 | M84: =+F84*J84 -> 0 | N84: =+F84*K84 -> 0
A85: 15.02 | B85: Látex interior para paredes Bco. mate (s/enduido) | C85: m2 | D85: 961 | E85: 0 | F85: =+D85*E85 -> 0 | I85: =+'SVD 4140_Pto. 01_Cert. 05'!K85 -> 0 | K85: =+I85+J85 -> 0 | L85: =+F85*I85 -> 0 | M85: =+F85*J85 -> 0 | N85: =+F85*K85 -> 0
A86: 15.03 | B86: Látex para cielorraso Bco. mate (enduido parcial) | C86: m2 | D86: 518 | E86: 0 | F86: =+D86*E86 -> 0 | I86: =+'SVD 4140_Pto. 01_Cert. 05'!K86 -> 0 | K86: =+I86+J86 -> 0 | L86: =+F86*I86 -> 0 | M86: =+F86*J86 -> 0 | N86: =+F86*K86 -> 0
A87: 15.04 | B87: Látex para cielorraso Bco. mate (enduido completo) | C87: m2 | D87: 612 | E87: 0 | F87: =+D87*E87 -> 0 | I87: =+'SVD 4140_Pto. 01_Cert. 05'!K87 -> 0 | K87: =+I87+J87 -> 0 | L87: =+F87*I87 -> 0 | M87: =+F87*J87 -> 0 | N87: =+F87*K87 -> 0
A88: 15.05 | B88: Latex interior cielorraso sobre H° | C88: m2 | D88: 422 | E88: 0 | F88: =+D88*E88 -> 0 | I88: =+'SVD 4140_Pto. 01_Cert. 05'!K88 -> 0 | K88: =+I88+J88 -> 0 | L88: =+F88*I88 -> 0 | M88: =+F88*J88 -> 0 | N88: =+F88*K88 -> 0
A89: 15.07 | B89: Revestimiento plastico tipo Quimtex en exteriores y PB | C89: m2 | D89: 678.252 | E89: 0 | F89: =+D89*E89 -> 0 | I89: =+'SVD 4140_Pto. 01_Cert. 05'!K89 -> 0 | K89: =+I89+J89 -> 0 | L89: =+F89*I89 -> 0 | M89: =+F89*J89 -> 0 | N89: =+F89*K89 -> 0
A90: 15.08 | B90: Revestimiento plastico tipo Quimtex en exteriores a mas de 3m de altura, incluye medianeras | C90: m2 | D90: 728.4802 | E90: 0 | F90: =+D90*E90 -> 0 | I90: =+'SVD 4140_Pto. 01_Cert. 05'!K90 -> 0 | K90: =+I90+J90 -> 0 | L90: =+F90*I90 -> 0 | M90: =+F90*J90 -> 0 | N90: =+F90*K90 -> 0
A91: 15.09 | B91: Esmalte sintético en puertas placa, chapa y de ascensor | C91: un | D91: 76 | E91: 0 | F91: =+D91*E91 -> 0 | I91: =+'SVD 4140_Pto. 01_Cert. 05'!K91 -> 0 | K91: =+I91+J91 -> 0 | L91: =+F91*I91 -> 0 | M91: =+F91*J91 -> 0 | N91: =+F91*K91 -> 0
A92: 15.1 | B92: Convertidor y esmalte sintentico en barandas - Escalera, balcones, porton, medidores y SDM | C92: gl | D92: 1 | E92: 0 | F92: =+D92*E92 -> 0 | I92: =+'SVD 4140_Pto. 01_Cert. 05'!K92 -> 0 | K92: =+I92+J92 -> 0 | L92: =+F92*I92 -> 0 | M92: =+F92*J92 -> 0 | N92: =+F92*K92 -> 0
A93: 16 | B93: MARMOLES Y GRANITOS - PROVISION Y COLOCACION A CARGO DEL COMITENTE | G93: =+SUM(F94) -> 0 | H93: =+G93/$G$185 -> 0
E94: 0 | F94: =+D94*E94 -> 0 | I94: =+'SVD 4140_Pto. 01_Cert. 05'!K94 -> 0 | K94: =+I94+J94 -> 0 | L94: =+F94*I94 -> 0 | M94: =+F94*J94 -> 0 | N94: =+F94*K94 -> 0
A95: 17 | B95: CARPINTERIA - PROVISION A CARGO DEL COMITENTE | G95: =+SUM(F96:F99) -> 7258243 | H95: =+G95/$G$185 -> 0.0098663395
A96: 17.01 | B96: Amure de puertas placa Provisión a cargo del comitente | C96: u | D96: 47 | E96: 64232 | F96: =+D96*E96 -> 3018904 | I96: =+'SVD 4140_Pto. 01_Cert. 05'!K96 -> 0.35 | J96: 0.25 | K96: =+I96+J96 -> 0.6 | L96: =+F96*I96 -> 1056616.4 | M96: =+F96*J96 -> 754726 | N96: =+F96*K96 -> 1811342.4
A97: 17.02 | B97: Amure de puertas de chapa e ingresos depto - Provisión a cargo del comitente | C97: u | D97: 23 | E97: 64232 | F97: =+D97*E97 -> 1477336 | I97: =+'SVD 4140_Pto. 01_Cert. 05'!K97 -> 0.38 | J97: 0.47 | K97: =+I97+J97 -> 0.85 | L97: =+F97*I97 -> 561387.68 | M97: =+F97*J97 -> 694347.92 | N97: =+F97*K97 -> 1255735.6
A98: 17.03 | B98: Amure de premarcos - Provisión a cargo del comitente | C98: u | D98: 51 | E98: 41296 | F98: =+D98*E98 -> 2106096 | I98: =+'SVD 4140_Pto. 01_Cert. 05'!K98 -> 0.4 | J98: 0.3 | K98: =+I98+J98 -> 0.7 | L98: =+F98*I98 -> 842438.4 | M98: =+F98*J98 -> 631828.8 | N98: =+F98*K98 -> 1474267.2
A99: 17.04 | B99: Amure Puertas de Ascensor - Provisión a cargo del comitente | C99: u | D99: 7 | E99: 93701 | F99: =+D99*E99 -> 655907 | I99: =+'SVD 4140_Pto. 01_Cert. 05'!K99 -> 0 | K99: =+I99+J99 -> 0 | L99: =+F99*I99 -> 0 | M99: =+F99*J99 -> 0 | N99: =+F99*K99 -> 0
A100: 18 | B100: INSTALACION ELECTRICA | G100: =+SUM(F101:F130) -> 99277732 | H100: =+G100/$G$185 -> 0.13495109
A101: 18.01 | B101: Tendido y cableado boca Iluminación | C101: u | D101: 392 | E101: 59948 | F101: =+D101*E101 -> 23499616 | I101: =+'SVD 4140_Pto. 01_Cert. 05'!K101 -> 0.45 | K101: =+I101+J101 -> 0.45 | L101: =+F101*I101 -> 10574827 | M101: =+F101*J101 -> 0 | N101: =+F101*K101 -> 10574827
...

Sheet SVD 4140_Pto. 01_Cert. 07
F1: DÓLAR BNA | G1: DÓLAR MEP
F2: 1005 | G2: 1170
F4: 45628
B5: OBRA: EDIFICIO EL SALVADOR 4140 | I5: Certificado | J5: 7 | N5: 46141
B6: PRESUPUESTO OBRA CIVIL
B7: Descripción | C7: U | D7: Cant | E7: P unit | F7: Subtotal | I7: Avance | L7: Importe
B8: PRESUPUESTO 02 - ALBANILERIA + INSTALACIONES + TERMINACIONES | I8: Anterior | J8: Actual | K8: Acumulado | L8: Anterior | M8: Actual | N8: Acumulado
A9: 4 | B9: ALBAÑILERIA | G9: =+SUM(F10:F17) -> 54302890 | H9: =+G9/$G$185 -> 0.073815487
A10: 4.01 | B10: Muro tipo 1 (interiores, divisorio de locales) e: 10 cm - Ladrillo hueco 08 x 18 x 33 | C10: m2 | D10: 819 | E10: 18993 | F10: =+D10*E10 -> 15555267 | I10: =+'SVD 4140_Pto. 01_Cert. 06'!K10 -> 0.85 | K10: =+I10+J10 -> 0.85 | L10: =+F10*I10 -> 13221977 | M10: =+F10*J10 -> 0 | N10: =+F10*K10 -> 13221977
A11: 4.02 | B11: Muro tipo 2 y 3 (medianera, caja de escaleras y ascensor) e: 15 cm - Ladrillo hueco portante 12 x 19 x 33 | C11: m2 | D11: 612 | E11: 25172 | F11: =+D11*E11 -> 15405264 | I11: =+'SVD 4140_Pto. 01_Cert. 06'!K11 -> 0.85 | K11: =+I11+J11 -> 0.85 | L11: =+F11*I11 -> 13094474 | M11: =+F11*J11 -> 0 | N11: =+F11*K11 -> 13094474
A12: 4.03 | B12: Muro tipo 4 (divisorio de unidades y fachas) e: 15 cm - Ladrillo hueco 12 x 18 x 33 | C12: m2 | D12: 636 | E12: 21109 | F12: =+D12*E12 -> 13425324 | I12: =+'SVD 4140_Pto. 01_Cert. 06'!K12 -> 0.85 | K12: =+I12+J12 -> 0.85 | L12: =+F12*I12 -> 11411525 | M12: =+F12*J12 -> 0 | N12: =+F12*K12 -> 11411525
A13: 4.04 | B13: Enchape medianeras existentes - Contemplamos picado zonas sueltas y enchape con ladrillo comun para PB | C13: m2 | D13: 195 | E13: 15092 | F13: =+D13*E13 -> 2942940 | I13: =+'SVD 4140_Pto. 01_Cert. 06'!K13 -> 0.15 | K13: =+I13+J13 -> 0.15 | L13: =+F13*I13 -> 441441 | M13: =+F13*J13 -> 0 | N13: =+F13*K13 -> 441441
A14: 4.05 | B14: Mamposteria cribada de ladrillo visto en balcones | C14: m2 | D14: 30.054 | E14: 67420 | F14: =+D14*E14 -> 2026240.7 | I14: =+'SVD 4140_Pto. 01_Cert. 06'!K14 -> 0 | K14: =+I14+J14 -> 0 | L14: =+F14*I14 -> 0 | M14: =+F14*J14 -> 0 | N14: =+F14*K14 -> 0
A15: 4.06 | B15: Bloque de H° con masillado de hormigon | C15: m2 | D15: 24 | E15: 54908 | F15: =+D15*E15 -> 1317792 | I15: =+'SVD 4140_Pto. 01_Cert. 06'!K15 -> 1 | K15: =+I15+J15 -> 1 | L15: =+F15*I15 -> 1317792 | M15: =+F15*J15 -> 0 | N15: =+F15*K15 -> 1317792
A16: 4.07 | B16: Cordón de hormigón en umbrales carpinterías | C16: ml | D16: 81 | E16: 30989 | F16: =+D16*E16 -> 2510109 | I16: =+'SVD 4140_Pto. 01_Cert. 06'!K16 -> 0.75 | J16: 0.15 | K16: =+I16+J16 -> 0.9 | L16: =+F16*I16 -> 1882581.8 | M16: =+F16*J16 -> 376516.35 | N16: =+F16*K16 -> 2259098.1
A17: 4.08 | B17: Pozo de bombeo pluvial y cloacal | C17: gl | D17: 1 | E17: 1119953 | F17: =+D17*E17 -> 1119953 | I17: =+'SVD 4140_Pto. 01_Cert. 06'!K17 -> 0.5 | K17: =+I17+J17 -> 0.5 | L17: =+F17*I17 -> 559976.5 | M17: =+F17*J17 -> 0 | N17: =+F17*K17 -> 559976.5
A18: 5 | B18: AISLACIONES | G18: =+SUM(F19:F25) -> 35966419 | H18: =+G18/$G$185 -> 0.048890193
A19: 5.01 | B19: Aislación hidrófuga horizontal (baños) - Inc. membrana geotextil y 35% en concepto de babetas | C19: m2 | D19: 139.05 | E19: 21800 | F19: =+D19*E19 -> 3031290 | I19: =+'SVD 4140_Pto. 01_Cert. 06'!K19 -> 0 | K19: =+I19+J19 -> 0 | L19: =+F19*I19 -> 0 | M19: =+F19*J19 -> 0 | N19: =+F19*K19 -> 0
A20: 5.02 | B20: Azotado hidrofugo - Sobre medianeras existentes | C20: m2 | D20: 300 | E20: 5376 | F20: =+D20*E20 -> 1612800 | I20: =+'SVD 4140_Pto. 01_Cert. 06'!K20 -> 0.5 | J20: 0.25 | K20: =+I20+J20 -> 0.75 | L20: =+F20*I20 -> 806400 | M20: =+F20*J20 -> 403200 | N20: =+F20*K20 -> 1209600
A21: 5.03 | B21: Azotado hidrofugo - Contrapiso de vereda | C21: m2 | D21: 48 | E21: 5376 | F21: =+D21*E21 -> 258048 | I21: =+'SVD 4140_Pto. 01_Cert. 06'!K21 -> 0 | K21: =+I21+J21 -> 0 | L21: =+F21*I21 -> 0 | M21: =+F21*J21 -> 0 | N21: =+F21*K21 -> 0
A22: 5.04 | B22: Aislación térmica en terrazas, eps e:2,00 cm | C22: m2 | D22: 262 | E22: 4403 | F22: =+D22*E22 -> 1153586 | I22: =+'SVD 4140_Pto. 01_Cert. 06'!K22 -> 0 | K22: =+I22+J22 -> 0 | L22: =+F22*I22 -> 0 | M22: =+F22*J22 -> 0 | N22: =+F22*K22 -> 0
A23: 5.05 | B23: Barrera de vapor | C23: m2 | D23: 510 | E23: 3578 | F23: =+D23*E23 -> 1824780 | I23: =+'SVD 4140_Pto. 01_Cert. 06'!K23 -> 0 | K23: =+I23+J23 -> 0 | L23: =+F23*I23 -> 0 | M23: =+F23*J23 -> 0 | N23: =+F23*K23 -> 0
A24: 5.06 | B24: Membrana asfaltica geotextil 4mm - Balcones y azotea - Inc. 20% en concepto de babetas | C24: m2 | D24: 510 | E24: 21800 | F24: =+D24*E24 -> 11118000 | I24: =+'SVD 4140_Pto. 01_Cert. 06'!K24 -> 0 | K24: =+I24+J24 -> 0 | L24: =+F24*I24 -> 0 | M24: =+F24*J24 -> 0 | N24: =+F24*K24 -> 0
A25: 5.07 | B25: Impermeabilización de subsuelo | C25: gl | D25: 1 | E25: 16967915 | F25: =+D25*E25 -> 16967915 | I25: =+'SVD 4140_Pto. 01_Cert. 06'!K25 -> 1 | K25: =+I25+J25 -> 1 | L25: =+F25*I25 -> 16967915 | M25: =+F25*J25 -> 0 | N25: =+F25*K25 -> 16967915
A26: 6 | B26: CUBIERTAS | G26: =+SUM(F27) -> 2433900 | H26: =+G26/$G$185 -> 0.0033084706
A27: 6.02 | B27: Babeta de chapa galvanizada en medianeras | C27: ml | D27: 60 | E27: 40565 | F27: =+D27*E27 -> 2433900 | I27: =+'SVD 4140_Pto. 01_Cert. 06'!K27 -> 0 | K27: =+I27+J27 -> 0 | L27: =+F27*I27 -> 0 | M27: =+F27*J27 -> 0 | N27: =+F27*K27 -> 0
A28: 7 | B28: REVOQUES | G28: =+SUM(F29:F36) -> 1.3639056e+08 | H28: =+G28/$G$185 -> 0.18539962
A29: 7.01 | B29: Revoque Grueso Impermeable Exterior proyectable | C29: m2 | D29: 678.252 | E29: 16571 | F29: =+D29*E29 -> 11239314 | I29: =+'SVD 4140_Pto. 01_Cert. 06'!K29 -> 0 | J29: 0.05 | K29: =+I29+J29 -> 0.05 | L29: =+F29*I29 -> 0 | M29: =+F29*J29 -> 561965.69 | N29: =+F29*K29 -> 561965.69
A30: 7.02 | B30: Revoque Grueso Impermeable Exterior a mas de 3m proyectable - Medianero y fachadas | C30: m2 | D30: 876.0812 | E30: 22183 | F30: =+D30*E30 -> 19434109 | I30: =+'SVD 4140_Pto. 01_Cert. 06'!K30 -> 0 | J30: 0.5 | K30: =+I30+J30 -> 0.5 | L30: =+F30*I30 -> 0 | M30: =+F30*J30 -> 9717054.6 | N30: =+F30*K30 -> 9717054.6
A31: 7.03 | B31: Buña en revoque | C31: ml | D31: 182 | E31: 10806 | F31: =+D31*E31 -> 1966692 | I31: =+'SVD 4140_Pto. 01_Cert. 06'!K31 -> 0 | J31: 0.5 | K31: =+I31+J31 -> 0.5 | L31: =+F31*I31 -> 0 | M31: =+F31*J31 -> 983346 | N31: =+F31*K31 -> 983346
A32: 7.04 | B32: Revoque Grueso Interior + fino | C32: m2 | D32: 995.8511 | E32: 26530 | F32: =+D32*E32 -> 26419930 | I32: =+'SVD 4140_Pto. 01_Cert. 06'!K32 -> 0.45 | K32: =+I32+J32 -> 0.45 | L32: =+F32*I32 -> 11888968 | M32: =+F32*J32 -> 0 | N32: =+F32*K32 -> 11888968
A33: 7.05 | B33: Yeso interior | C33: m2 | D33: 2514.897 | E33: 22566 | F33: =+D33*E33 -> 56751166 | I33: =+'SVD 4140_Pto. 01_Cert. 06'!K33 -> 0.05 | J33: 0.15 | K33: =+I33+J33 -> 0.2 | L33: =+F33*I33 -> 2837558.3 | M33: =+F33*J33 -> 8512674.9 | N33: =+F33*K33 -> 11350233
A34: 7.06 | B34: Arista en yeso | C34: ml | D34: 509.9 | E34: 12771 | F34: =+D34*E34 -> 6511932.9 | I34: =+'SVD 4140_Pto. 01_Cert. 06'!K34 -> 0.05 | J34: 0.15 | K34: =+I34+J34 -> 0.2 | L34: =+F34*I34 -> 325596.65 | M34: =+F34*J34 -> 976789.93 | N34: =+F34*K34 -> 1302386.6
A35: 7.07 | B35: Provisión y colocación de guardacanto yesero | C35: u | D35: 198 | E35: 14947 | F35: =+D35*E35 -> 2959506 | I35: =+'SVD 4140_Pto. 01_Cert. 06'!K35 -> 0 | J35: 0.15 | K35: =+I35+J35 -> 0.15 | L35: =+F35*I35 -> 0 | M35: =+F35*J35 -> 443925.9 | N35: =+F35*K35 -> 443925.9
A36: 7.08 | B36: Revoque Grueso Impermeable Interior b/ revestimiento | C36: m2 | D36: 670.322 | E36: 16571 | F36: =+D36*E36 -> 11107906 | I36: =+'SVD 4140_Pto. 01_Cert. 06'!K36 -> 0 | J36: 0.15 | K36: =+I36+J36 -> 0.15 | L36: =+F36*I36 -> 0 | M36: =+F36*J36 -> 1666185.9 | N36: =+F36*K36 -> 1666185.9
A37: 8 | B37: CONTRAPISOS Y CARPETAS | G37: =+SUM(F38:F45) -> 44788107 | H37: =+G37/$G$185 -> 0.060881768
A38: 8.01 | B38: Contrapiso de cascotes en SS e: 15 cm | C38: m2 | D38: 104 | E38: 31920 | F38: =+D38*E38 -> 3319680 | I38: =+'SVD 4140_Pto. 01_Cert. 06'!K38 -> 1 | K38: =+I38+J38 -> 1 | L38: =+F38*I38 -> 3319680 | M38: =+F38*J38 -> 0 | N38: =+F38*K38 -> 3319680
A39: 8.02 | B39: Contrapiso de cascote s/terreno natural e: 20 cm - Incluye film de polietileno | C39: m2 | D39: 48 | E39: 37268 | F39: =+D39*E39 -> 1788864 | I39: =+'SVD 4140_Pto. 01_Cert. 06'!K39 -> 0 | K39: =+I39+J39 -> 0 | L39: =+F39*I39 -> 0 | M39: =+F39*J39 -> 0 | N39: =+F39*K39 -> 0
A40: 8.03 | B40: Contrapiso de cascotes en azoteas c/pendiente e: 15 cm | C40: m2 | D40: 235 | E40: 32410 | F40: =+D40*E40 -> 7616350 | I40: =+'SVD 4140_Pto. 01_Cert. 06'!K40 -> 0 | K40: =+I40+J40 -> 0 | L40: =+F40*I40 -> 0 | M40: =+F40*J40 -> 0 | N40: =+F40*K40 -> 0
A41: 8.04 | B41: Contrapiso - Carpeta monolitico e: 7 cm | C41: m2 | D41: 878 | E41: 19006 | F41: =+D41*E41 -> 16687268 | I41: =+'SVD 4140_Pto. 01_Cert. 06'!K41 -> 0 | K41: =+I41+J41 -> 0 | L41: =+F41*I41 -> 0 | M41: =+F41*J41 -> 0 | N41: =+F41*K41 -> 0
A42: 8.05 | B42: Carpeta en PB y balcones, baños y azoteas e: 3,00 cm | C42: m2 | D42: 564 | E42: 12439 | F42: =+D42*E42 -> 7015596 | I42: =+'SVD 4140_Pto. 01_Cert. 06'!K42 -> 0 | K42: =+I42+J42 -> 0 | L42: =+F42*I42 -> 0 | M42: =+F42*J42 -> 0 | N42: =+F42*K42 -> 0
A43: 8.06 | B43: Carpeta sobre membrana | C43: m2 | D43: 438 | E43: 12439 | F43: =+D43*E43 -> 5448282 | I43: =+'SVD 4140_Pto. 01_Cert. 06'!K43 -> 0 | K43: =+I43+J43 -> 0 | L43: =+F43*I43 -> 0 | M43: =+F43*J43 -> 0 | N43: =+F43*K43 -> 0
A44: 8.07 | B44: Banquinas para cocinas | C44: gl | D44: 1 | E44: 2426924 | F44: =+D44*E44 -> 2426924 | I44: =+'SVD 4140_Pto. 01_Cert. 06'!K44 -> 0 | K44: =+I44+J44 -> 0 | L44: =+F44*I44 -> 0 | M44: =+F44*J44 -> 0 | N44: =+F44*K44 -> 0
A45: 8.08 | B45: Banquinas para bombas y tanques en SB | C45: gl | D45: 1 | E45: 485143 | F45: =+D45*E45 -> 485143 | I45: =+'SVD 4140_Pto. 01_Cert. 06'!K45 -> 0 | K45: =+I45+J45 -> 0 | L45: =+F45*I45 -> 0 | M45: =+F45*J45 -> 0 | N45: =+F45*K45 -> 0
A46: 9 | B46: ESCALERAS | G46: =+SUM(F47:F50) -> 5769056.6 | H46: =+G46/$G$185 -> 0.0078420454
A47: 9.01 | B47: Cemento alisado arrodillado en escaleras | C47: gl | D47: 1 | E47: 2024643 | F47: =+D47*E47 -> 2024643 | I47: =+'SVD 4140_Pto. 01_Cert. 06'!K47 -> 0 | K47: =+I47+J47 -> 0 | L47: =+F47*I47 -> 0 | M47: =+F47*J47 -> 0 | N47: =+F47*K47 -> 0
A48: 9.02 | B48: Provisión nariz escalera, hierro angulo 5/8 x 1/8" | C48: ml | D48: 122 | E48: 18814 | F48: =+D48*E48 -> 2295308 | I48: =+'SVD 4140_Pto. 01_Cert. 06'!K48 -> 0 | K48: =+I48+J48 -> 0 | L48: =+F48*I48 -> 0 | M48: =+F48*J48 -> 0 | N48: =+F48*K48 -> 0
A49: 9.03 | B49: Zócalo de concreto | C49: ml | D49: 155 | E49: 5376 | F49: =+D49*E49 -> 833280 | I49: =+'SVD 4140_Pto. 01_Cert. 06'!K49 -> 0 | K49: =+I49+J49 -> 0 | L49: =+F49*I49 -> 0 | M49: =+F49*J49 -> 0 | N49: =+F49*K49 -> 0
A50: 9.04 | B50: Provisión y colocación de Rodapie/ Zócalo rampante en placa cementicia | C50: ml | D50: 31.2 | E50: 19738 | F50: =+D50*E50 -> 615825.6 | I50: =+'SVD 4140_Pto. 01_Cert. 06'!K50 -> 0 | K50: =+I50+J50 -> 0 | L50: =+F50*I50 -> 0 | M50: =+F50*J50 -> 0 | N50: =+F50*K50 -> 0
A51: 10 | B51: VENTILACIONES | G51: =+SUM(F52:F55) -> 4669278 | H51: =+G51/$G$185 -> 0.0063470845
A52: 10.01 | B52: Ventilación Conducto Humos. Incluye toma de aire en PB - No aplica s/proyecto | C52: gl | D52: 0 | E52: 0 | F52: =+D52*E52 -> 0 | I52: =+'SVD 4140_Pto. 01_Cert. 06'!K52 -> 0 | K52: =+I52+J52 -> 0 | L52: =+F52*I52 -> 0 | M52: =+F52*J52 -> 0 | N52: =+F52*K52 -> 0
A53: 10.02 | B53: Ventilación Baños - En caño Ø 110 | C53: gl | D53: 1 | E53: 2199545 | F53: =+D53*E53 -> 2199545 | I53: =+'SVD 4140_Pto. 01_Cert. 06'!K53 -> 0.2 | J53: 0.3 | K53: =+I53+J53 -> 0.5 | L53: =+F53*I53 -> 439909 | M53: =+F53*J53 -> 659863.5 | N53: =+F53*K53 -> 1099772.5
A54: 10.03 | B54: Colocación de rejillas de inyección y extracción - No aplica s/proyecto | C54: un | D54: 0 | E54: 0 | F54: =+D54*E54 -> 0 | I54: =+'SVD 4140_Pto. 01_Cert. 06'!K54 -> 0 | K54: =+I54+J54 -> 0 | L54: =+F54*I54 -> 0 | M54: =+F54*J54 -> 0 | N54: =+F54*K54 -> 0
A55: 10.04 | B55: Sombreretes en chapa prepintada C25 | C55: u | D55: 7 | E55: 352819 | F55: =+D55*E55 -> 2469733 | I55: =+'SVD 4140_Pto. 01_Cert. 06'!K55 -> 0 | K55: =+I55+J55 -> 0 | L55: =+F55*I55 -> 0 | M55: =+F55*J55 -> 0 | N55: =+F55*K55 -> 0
A56: 11 | B56: PISOS - PROVISION A CARGO DEL COMITENTE | G56: =+SUM(F57:F63) -> 48040802 | H56: =+G56/$G$185 -> 0.06530325
A57: 11.01 | B57: Colocación de travertino en hall PB - Provisión a cargo del comitente | C57: m2 | D57: 30 | E57: 21948 | F57: =+D57*E57 -> 658440 | I57: =+'SVD 4140_Pto. 01_Cert. 06'!K57 -> 0 | K57: =+I57+J57 -> 0 | L57: =+F57*I57 -> 0 | M57: =+F57*J57 -> 0 | N57: =+F57*K57 -> 0
A58: 11.02 | B58: Colocación de porcelanato en paliers, terraza y espacios comunes - Provisión a cargo del comitente | C58: m2 | D58: 185 | E58: 21948 | F58: =+D58*E58 -> 4060380 | I58: =+'SVD 4140_Pto. 01_Cert. 06'!K58 -> 0 | K58: =+I58+J58 -> 0 | L58: =+F58*I58 -> 0 | M58: =+F58*J58 -> 0 | N58: =+F58*K58 -> 0
A59: 11.03 | B59: Colocación de porcelanato en UF - Provisión a cargo del comitente | C59: m2 | D59: 942 | E59: 21948 | F59: =+D59*E59 -> 20675016 | I59: =+'SVD 4140_Pto. 01_Cert. 06'!K59 -> 0 | K59: =+I59+J59 -> 0 | L59: =+F59*I59 -> 0 | M59: =+F59*J59 -> 0 | N59: =+F59*K59 -> 0
A60: 11.04 | B60: Colocación de porcelanato en baños - Provisión a cargo del comitente | C60: m2 | D60: 110 | E60: 25799 | F60: =+D60*E60 -> 2837890 | I60: =+'SVD 4140_Pto. 01_Cert. 06'!K60 -> 0 | K60: =+I60+J60 -> 0 | L60: =+F60*I60 -> 0 | M60: =+F60*J60 -> 0 | N60: =+F60*K60 -> 0
A61: 11.05 | B61: Provisión y ejecución de alisado de cemento rodillado | C61: m2 | D61: 128 | E61: 16080 | F61: =+D61*E61 -> 2058240 | I61: =+'SVD 4140_Pto. 01_Cert. 06'!K61 -> 0 | K61: =+I61+J61 -> 0 | L61: =+F61*I61 -> 0 | M61: =+F61*J61 -> 0 | N61: =+F61*K61 -> 0
A62: 11.06 | B62: Colocación de baldoson de vereda - Provisión a cargo del comitente | C62: m2 | D62: 48 | E62: 21948 | F62: =+D62*E62 -> 1053504 | I62: =+'SVD 4140_Pto. 01_Cert. 06'!K62 -> 0 | K62: =+I62+J62 -> 0 | L62: =+F62*I62 -> 0 | M62: =+F62*J62 -> 0 | N62: =+F62*K62 -> 0
A63: 11.07 | B63: Provisión y ejecución de pavimento e: 18 cm, incluye malla Q188 | C63: m2 | D63: 226 | E63: 73882 | F63: =+D63*E63 -> 16697332 | I63: =+'SVD 4140_Pto. 01_Cert. 06'!K63 -> 0 | J63: 1 | K63: =+I63+J63 -> 1 | L63: =+F63*I63 -> 0 | M63: =+F63*J63 -> 16697332 | N63: =+F63*K63 -> 16697332
A64: 12 | B64: ZOCALOS Y SOLIAS - PROVISION A CARGO DEL COMITENTE | G64: =+SUM(F65:F69) -> 11022518 | H64: =+G64/$G$185 -> 0.014983227
A65: 12.01 | B65: Provisión y colocación de zocalos de Madera (MDF) h: 7 cm | C65: ml | D65: 779 | E65: 7422 | F65: =+D65*E65 -> 5781738 | I65: =+'SVD 4140_Pto. 01_Cert. 06'!K65 -> 0 | K65: =+I65+J65 -> 0 | L65: =+F65*I65 -> 0 | M65: =+F65*J65 -> 0 | N65: =+F65*K65 -> 0
A66: 12.02 | B66: Zócalo de concreto | C66: ml | D66: 155 | E66: 5376 | F66: =+D66*E66 -> 833280 | I66: =+'SVD 4140_Pto. 01_Cert. 06'!K66 -> 0 | K66: =+I66+J66 -> 0 | L66: =+F66*I66 -> 0 | M66: =+F66*J66 -> 0 | N66: =+F66*K66 -> 0
A67: 12.03 | B67: Colocación de zocalo de porcelanico - Provisión a cargo del comitente | C67: ml | D67: 37 | E67: 7052 | F67: =+D67*E67 -> 260924 | I67: =+'SVD 4140_Pto. 01_Cert. 06'!K67 -> 0 | K67: =+I67+J67 -> 0 | L67: =+F67*I67 -> 0 | M67: =+F67*J67 -> 0 | N67: =+F67*K67 -> 0
A68: 12.04 | B68: Colocación de zocalo de porcelanato en palieres - Provisión a cargo del comitente | C68: ml | D68: 433 | E68: 7052 | F68: =+D68*E68 -> 3053516 | I68: =+'SVD 4140_Pto. 01_Cert. 06'!K68 -> 0 | K68: =+I68+J68 -> 0 | L68: =+F68*I68 -> 0 | M68: =+F68*J68 -> 0 | N68: =+F68*K68 -> 0
A69: 12.05 | B69: Colocación de zocalo de porcelanato en terraza y espacios comunes - Provisión a cargo del comitente | C69: ml | D69: 155 | E69: 7052 | F69: =+D69*E69 -> 1093060 | I69: =+'SVD 4140_Pto. 01_Cert. 06'!K69 -> 0 | K69: =+I69+J69 -> 0 | L69: =+F69*I69 -> 0 | M69: =+F69*J69 -> 0 | N69: =+F69*K69 -> 0
A70: 13 | B70: REVESTIMIENTOS - PROVISION A CARGO DEL COMITENTE | G70: =+SUM(F71:F74) -> 19433086 | H70: =+G70/$G$185 -> 0.026415956
A71: 13.01 | B71: Revestimiento en baños - Provisión a cargo del comitente | C71: m2 | D71: 511 | E71: 25799 | F71: =+D71*E71 -> 13183289 | I71: =+'SVD 4140_Pto. 01_Cert. 06'!K71 -> 0 | K71: =+I71+J71 -> 0 | L71: =+F71*I71 -> 0 | M71: =+F71*J71 -> 0 | N71: =+F71*K71 -> 0
A72: 13.02 | B72: Revestimiento en cocinas - Provisión a cargo del comitente | C72: m2 | D72: 40 | E72: 25799 | F72: =+D72*E72 -> 1031960 | I72: =+'SVD 4140_Pto. 01_Cert. 06'!K72 -> 0 | K72: =+I72+J72 -> 0 | L72: =+F72*I72 -> 0 | M72: =+F72*J72 -> 0 | N72: =+F72*K72 -> 0
A73: 13.03 | B73: Revestimiento tejuela exterior - Provisión a cargo del comitente | C73: m2 | D73: 147.601 | E73: 29881 | F73: =+D73*E73 -> 4410465.5 | I73: =+'SVD 4140_Pto. 01_Cert. 06'!K73 -> 0 | K73: =+I73+J73 -> 0 | L73: =+F73*I73 -> 0 | M73: =+F73*J73 -> 0 | N73: =+F73*K73 -> 0
A74: 13.04 | B74: Provisión y colocación de perfileria de aluminio tipo ATRIM L anod. Natural | C74: u | D74: 41 | E74: 19692 | F74: =+D74*E74 -> 807372 | I74: =+'SVD 4140_Pto. 01_Cert. 06'!K74 -> 0 | K74: =+I74+J74 -> 0 | L74: =+F74*I74 -> 0 | M74: =+F74*J74 -> 0 | N74: =+F74*K74 -> 0
A75: 14 | B75: CIELORRASOS | G75: =+SUM(F76:F82) -> 50296169 | H75: =+G75/$G$185 -> 0.068369036
A76: 14.01 | B76: Cielorraso junta tomada placa STD | C76: m2 | D76: 334.9152 | E76: 29270 | F76: =+D76*E76 -> 9802967.9 | I76: =+'SVD 4140_Pto. 01_Cert. 06'!K76 -> 0.05 | J76: 0.15 | K76: =+I76+J76 -> 0.2 | L76: =+F76*I76 -> 490148.4 | M76: =+F76*J76 -> 1470445.2 | N76: =+F76*K76 -> 1960593.6
A77: 14.02 | B77: Cielorraso junta tomada placa RH | C77: m2 | D77: 280.3913 | E77: 33967 | F77: =+D77*E77 -> 9524051.3 | I77: =+'SVD 4140_Pto. 01_Cert. 06'!K77 -> 0.05 | J77: 0.15 | K77: =+I77+J77 -> 0.2 | L77: =+F77*I77 -> 476202.56 | M77: =+F77*J77 -> 1428607.7 | N77: =+F77*K77 -> 1904810.3
A78: 14.03 | B78: Cajon en junta tomada placa STD | C78: ml | D78: 60.8 | E78: 29270 | F78: =+D78*E78 -> 1779616 | I78: =+'SVD 4140_Pto. 01_Cert. 06'!K78 -> 0.05 | J78: 0.2 | K78: =+I78+J78 -> 0.25 | L78: =+F78*I78 -> 88980.8 | M78: =+F78*J78 -> 355923.2 | N78: =+F78*K78 -> 444904
A79: 14.04 | B79: Buña perimetral / Cantoneras | C79: ml | D79: 1058.38 | E79: 7873 | F79: =+D79*E79 -> 8332625.7 | I79: =+'SVD 4140_Pto. 01_Cert. 06'!K79 -> 0 | J79: 0.25 | K79: =+I79+J79 -> 0.25 | L79: =+F79*I79 -> 0 | M79: =+F79*J79 -> 2083156.4 | N79: =+F79*K79 -> 2083156.4
A80: 14.05 | B80: Aplicado de yeso interior | C80: m2 | D80: 504.1222 | E80: 23364 | F80: =+D80*E80 -> 11778311 | I80: =+'SVD 4140_Pto. 01_Cert. 06'!K80 -> 0 | J80: 0.2 | K80: =+I80+J80 -> 0.2 | L80: =+F80*I80 -> 0 | M80: =+F80*J80 -> 2355662.2 | N80: =+F80*K80 -> 2355662.2
A81: 14.06 | B81: Buña en yeso | C81: ml | D81: 555.99 | E81: 12771 | F81: =+D81*E81 -> 7100548.3 | I81: =+'SVD 4140_Pto. 01_Cert. 06'!K81 -> 0 | J81: 0.2 | K81: =+I81+J81 -> 0.2 | L81: =+F81*I81 -> 0 | M81: =+F81*J81 -> 1420109.7 | N81: =+F81*K81 -> 1420109.7
A82: 14.07 | B82: H° Visto - Maquillaje para recibir pintura | C82: m2 | D82: 429.0778 | E82: 4610 | F82: =+D82*E82 -> 1978048.7 | I82: =+'SVD 4140_Pto. 01_Cert. 06'!K82 -> 0 | K82: =+I82+J82 -> 0 | L82: =+F82*I82 -> 0 | M82: =+F82*J82 -> 0 | N82: =+F82*K82 -> 0
A83: 15 | B83: PINTURA | G83: =+SUM(F84:F92) -> 0 | H83: =+G83/$G$185 -> 0
A84: 15.01 | B84: Látex interior para paredes Bco. mate (enduido parcial) | C84: m2 | D84: 2670 | E84: 0 | F84: =+D84*E84 -> 0 | I84: =+'SVD 4140_Pto. 01_Cert. 06'!K84 -> 0 | K84: =+I84+J84 -> 0 | L84: =+F84*I84 -> 0 | M84: =+F84*J84 -> 0 | N84: =+F84*K84 -> 0
A85: 15.02 | B85: Látex interior para paredes Bco. mate (s/enduido) | C85: m2 | D85: 961 | E85: 0 | F85: =+D85*E85 -> 0 | I85: =+'SVD 4140_Pto. 01_Cert. 06'!K85 -> 0 | K85: =+I85+J85 -> 0 | L85: =+F85*I85 -> 0 | M85: =+F85*J85 -> 0 | N85: =+F85*K85 -> 0
A86: 15.03 | B86: Látex para cielorraso Bco. mate (enduido parcial) | C86: m2 | D86: 518 | E86: 0 | F86: =+D86*E86 -> 0 | I86: =+'SVD 4140_Pto. 01_Cert. 06'!K86 -> 0 | K86: =+I86+J86 -> 0 | L86: =+F86*I86 -> 0 | M86: =+F86*J86 -> 0 | N86: =+F86*K86 -> 0
A87: 15.04 | B87: Látex para cielorraso Bco. mate (enduido completo) | C87: m2 | D87: 612 | E87: 0 | F87: =+D87*E87 -> 0 | I87: =+'SVD 4140_Pto. 01_Cert. 06'!K87 -> 0 | K87: =+I87+J87 -> 0 | L87: =+F87*I87 -> 0 | M87: =+F87*J87 -> 0 | N87: =+F87*K87 -> 0
A88: 15.05 | B88: Latex interior cielorraso sobre H° | C88: m2 | D88: 422 | E88: 0 | F88: =+D88*E88 -> 0 | I88: =+'SVD 4140_Pto. 01_Cert. 06'!K88 -> 0 | K88: =+I88+J88 -> 0 | L88: =+F88*I88 -> 0 | M88: =+F88*J88 -> 0 | N88: =+F88*K88 -> 0
A89: 15.07 | B89: Revestimiento plastico tipo Quimtex en exteriores y PB | C89: m2 | D89: 678.252 | E89: 0 | F89: =+D89*E89 -> 0 | I89: =+'SVD 4140_Pto. 01_Cert. 06'!K89 -> 0 | K89: =+I89+J89 -> 0 | L89: =+F89*I89 -> 0 | M89: =+F89*J89 -> 0 | N89: =+F89*K89 -> 0
A90: 15.08 | B90: Revestimiento plastico tipo Quimtex en exteriores a mas de 3m de altura, incluye medianeras | C90: m2 | D90: 728.4802 | E90: 0 | F90: =+D90*E90 -> 0 | I90: =+'SVD 4140_Pto. 01_Cert. 06'!K90 -> 0 | K90: =+I90+J90 -> 0 | L90: =+F90*I90 -> 0 | M90: =+F90*J90 -> 0 | N90: =+F90*K90 -> 0
A91: 15.09 | B91: Esmalte sintético en puertas placa, chapa y de ascensor | C91: un | D91: 76 | E91: 0 | F91: =+D91*E91 -> 0 | I91: =+'SVD 4140_Pto. 01_Cert. 06'!K91 -> 0 | K91: =+I91+J91 -> 0 | L91: =+F91*I91 -> 0 | M91: =+F91*J91 -> 0 | N91: =+F91*K91 -> 0
A92: 15.1 | B92: Convertidor y esmalte sintentico en barandas - Escalera, balcones, porton, medidores y SDM | C92: gl | D92: 1 | E92: 0 | F92: =+D92*E92 -> 0 | I92: =+'SVD 4140_Pto. 01_Cert. 06'!K92 -> 0 | K92: =+I92+J92 -> 0 | L92: =+F92*I92 -> 0 | M92: =+F92*J92 -> 0 | N92: =+F92*K92 -> 0
A93: 16 | B93: MARMOLES Y GRANITOS - PROVISION Y COLOCACION A CARGO DEL COMITENTE | G93: =+SUM(F94) -> 0 | H93: =+G93/$G$185 -> 0
E94: 0 | F94: =+D94*E94 -> 0 | I94: =+'SVD 4140_Pto. 01_Cert. 06'!K94 -> 0 | K94: =+I94+J94 -> 0 | L94: =+F94*I94 -> 0 | M94: =+F94*J94 -> 0 | N94: =+F94*K94 -> 0
A95: 17 | B95: CARPINTERIA - PROVISION A CARGO DEL COMITENTE | G95: =+SUM(F96:F99) -> 7258243 | H95: =+G95/$G$185 -> 0.0098663395
A96: 17.01 | B96: Amure de puertas placa Provisión a cargo del comitente | C96: u | D96: 47 | E96: 64232 | F96: =+D96*E96 -> 3018904 | I96: =+'SVD 4140_Pto. 01_Cert. 06'!K96 -> 0.6 | J96: 0.25 | K96: =+I96+J96 -> 0.85 | L96: =+F96*I96 -> 1811342.4 | M96: =+F96*J96 -> 754726 | N96: =+F96*K96 -> 2566068.4
A97: 17.02 | B97: Amure de puertas de chapa e ingresos depto - Provisión a cargo del comitente | C97: u | D97: 23 | E97: 64232 | F97: =+D97*E97 -> 1477336 | I97: =+'SVD 4140_Pto. 01_Cert. 06'!K97 -> 0.85 | K97: =+I97+J97 -> 0.85 | L97: =+F97*I97 -> 1255735.6 | M97: =+F97*J97 -> 0 | N97: =+F97*K97 -> 1255735.6
A98: 17.03 | B98: Amure de premarcos - Provisión a cargo del comitente | C98: u | D98: 51 | E98: 41296 | F98: =+D98*E98 -> 2106096 | I98: =+'SVD 4140_Pto. 01_Cert. 06'!K98 -> 0.7 | J98: 0.15 | K98: =+I98+J98 -> 0.85 | L98: =+F98*I98 -> 1474267.2 | M98: =+F98*J98 -> 315914.4 | N98: =+F98*K98 -> 1790181.6
A99: 17.04 | B99: Amure Puertas de Ascensor - Provisión a cargo del comitente | C99: u | D99: 7 | E99: 93701 | F99: =+D99*E99 -> 655907 | I99: =+'SVD 4140_Pto. 01_Cert. 06'!K99 -> 0 | K99: =+I99+J99 -> 0 | L99: =+F99*I99 -> 0 | M99: =+F99*J99 -> 0 | N99: =+F99*K99 -> 0
A100: 18 | B100: INSTALACION ELECTRICA | G100: =+SUM(F101:F130) -> 99277732 | H100: =+G100/$G$185 -> 0.13495109
A101: 18.01 | B101: Tendido y cableado boca Iluminación | C101: u | D101: 392 | E101: 59948 | F101: =+D101*E101 -> 23499616 | I101: =+'SVD 4140_Pto. 01_Cert. 06'!K101 -> 0.45 | K101: =+I101+J101 -> 0.45 | L101: =+F101*I101 -> 10574827 | M101: =+F101*J101 -> 0 | N101: =+F101*K101 -> 10574827
...

Sheet SVD 4140_Pto. 01_Cert. 08
F1: DÓLAR BNA | G1: DÓLAR MEP
F2: 1005 | G2: 1170
F4: 45628
B5: OBRA: EDIFICIO EL SALVADOR 4140 | I5: Certificado | J5: 8 | N5: 46174
B6: PRESUPUESTO OBRA CIVIL
B7: Descripción | C7: U | D7: Cant | E7: P unit | F7: Subtotal | I7: Avance | L7: Importe
B8: PRESUPUESTO 02 - ALBANILERIA + INSTALACIONES + TERMINACIONES | I8: Anterior | J8: Actual | K8: Acumulado | L8: Anterior | M8: Actual | N8: Acumulado
A9: 4 | B9: ALBAÑILERIA | G9: =+SUM(F10:F17) -> 54302890 | H9: =+G9/$G$185 -> 0.073815487
A10: 4.01 | B10: Muro tipo 1 (interiores, divisorio de locales) e: 10 cm - Ladrillo hueco 08 x 18 x 33 | C10: m2 | D10: 819 | E10: 18993 | F10: =+D10*E10 -> 15555267 | I10: =+'SVD 4140_Pto. 01_Cert. 07'!K10 -> 0.85 | J10: 0.05 | K10: =+I10+J10 -> 0.9 | L10: =+F10*I10 -> 13221977 | M10: =+F10*J10 -> 777763.35 | N10: =+F10*K10 -> 13999740
A11: 4.02 | B11: Muro tipo 2 y 3 (medianera, caja de escaleras y ascensor) e: 15 cm - Ladrillo hueco portante 12 x 19 x 33 | C11: m2 | D11: 612 | E11: 25172 | F11: =+D11*E11 -> 15405264 | I11: =+'SVD 4140_Pto. 01_Cert. 07'!K11 -> 0.85 | J11: 0.1 | K11: =+I11+J11 -> 0.95 | L11: =+F11*I11 -> 13094474 | M11: =+F11*J11 -> 1540526.4 | N11: =+F11*K11 -> 14635001
A12: 4.03 | B12: Muro tipo 4 (divisorio de unidades y fachas) e: 15 cm - Ladrillo hueco 12 x 18 x 33 | C12: m2 | D12: 636 | E12: 21109 | F12: =+D12*E12 -> 13425324 | I12: =+'SVD 4140_Pto. 01_Cert. 07'!K12 -> 0.85 | J12: 0.05 | K12: =+I12+J12 -> 0.9 | L12: =+F12*I12 -> 11411525 | M12: =+F12*J12 -> 671266.2 | N12: =+F12*K12 -> 12082792
A13: 4.04 | B13: Enchape medianeras existentes - Contemplamos picado zonas sueltas y enchape con ladrillo comun para PB | C13: m2 | D13: 195 | E13: 15092 | F13: =+D13*E13 -> 2942940 | I13: =+'SVD 4140_Pto. 01_Cert. 07'!K13 -> 0.15 | K13: =+I13+J13 -> 0.15 | L13: =+F13*I13 -> 441441 | M13: =+F13*J13 -> 0 | N13: =+F13*K13 -> 441441
A14: 4.05 | B14: Mamposteria cribada de ladrillo visto en balcones | C14: m2 | D14: 30.054 | E14: 67420 | F14: =+D14*E14 -> 2026240.7 | I14: =+'SVD 4140_Pto. 01_Cert. 07'!K14 -> 0 | K14: =+I14+J14 -> 0 | L14: =+F14*I14 -> 0 | M14: =+F14*J14 -> 0 | N14: =+F14*K14 -> 0
A15: 4.06 | B15: Bloque de H° con masillado de hormigon | C15: m2 | D15: 24 | E15: 54908 | F15: =+D15*E15 -> 1317792 | I15: =+'SVD 4140_Pto. 01_Cert. 07'!K15 -> 1 | K15: =+I15+J15 -> 1 | L15: =+F15*I15 -> 1317792 | M15: =+F15*J15 -> 0 | N15: =+F15*K15 -> 1317792
A16: 4.07 | B16: Cordón de hormigón en umbrales carpinterías | C16: ml | D16: 81 | E16: 30989 | F16: =+D16*E16 -> 2510109 | I16: =+'SVD 4140_Pto. 01_Cert. 07'!K16 -> 0.9 | K16: =+I16+J16 -> 0.9 | L16: =+F16*I16 -> 2259098.1 | M16: =+F16*J16 -> 0 | N16: =+F16*K16 -> 2259098.1
A17: 4.08 | B17: Pozo de bombeo pluvial y cloacal | C17: gl | D17: 1 | E17: 1119953 | F17: =+D17*E17 -> 1119953 | I17: =+'SVD 4140_Pto. 01_Cert. 07'!K17 -> 0.5 | K17: =+I17+J17 -> 0.5 | L17: =+F17*I17 -> 559976.5 | M17: =+F17*J17 -> 0 | N17: =+F17*K17 -> 559976.5
A18: 5 | B18: AISLACIONES | G18: =+SUM(F19:F25) -> 35966419 | H18: =+G18/$G$185 -> 0.048890193
A19: 5.01 | B19: Aislación hidrófuga horizontal (baños) - Inc. membrana geotextil y 35% en concepto de babetas | C19: m2 | D19: 139.05 | E19: 21800 | F19: =+D19*E19 -> 3031290 | I19: =+'SVD 4140_Pto. 01_Cert. 07'!K19 -> 0 | J19: 0.3 | K19: =+I19+J19 -> 0.3 | L19: =+F19*I19 -> 0 | M19: =+F19*J19 -> 909387 | N19: =+F19*K19 -> 909387
A20: 5.02 | B20: Azotado hidrofugo - Sobre medianeras existentes | C20: m2 | D20: 300 | E20: 5376 | F20: =+D20*E20 -> 1612800 | I20: =+'SVD 4140_Pto. 01_Cert. 07'!K20 -> 0.75 | J20: 0.25 | K20: =+I20+J20 -> 1 | L20: =+F20*I20 -> 1209600 | M20: =+F20*J20 -> 403200 | N20: =+F20*K20 -> 1612800
A21: 5.03 | B21: Azotado hidrofugo - Contrapiso de vereda | C21: m2 | D21: 48 | E21: 5376 | F21: =+D21*E21 -> 258048 | I21: =+'SVD 4140_Pto. 01_Cert. 07'!K21 -> 0 | K21: =+I21+J21 -> 0 | L21: =+F21*I21 -> 0 | M21: =+F21*J21 -> 0 | N21: =+F21*K21 -> 0
A22: 5.04 | B22: Aislación térmica en terrazas, eps e:2,00 cm | C22: m2 | D22: 262 | E22: 4403 | F22: =+D22*E22 -> 1153586 | I22: =+'SVD 4140_Pto. 01_Cert. 07'!K22 -> 0 | K22: =+I22+J22 -> 0 | L22: =+F22*I22 -> 0 | M22: =+F22*J22 -> 0 | N22: =+F22*K22 -> 0
A23: 5.05 | B23: Barrera de vapor | C23: m2 | D23: 510 | E23: 3578 | F23: =+D23*E23 -> 1824780 | I23: =+'SVD 4140_Pto. 01_Cert. 07'!K23 -> 0 | J23: 0.7 | K23: =+I23+J23 -> 0.7 | L23: =+F23*I23 -> 0 | M23: =+F23*J23 -> 1277346 | N23: =+F23*K23 -> 1277346
A24: 5.06 | B24: Membrana asfaltica geotextil 4mm - Balcones y azotea - Inc. 20% en concepto de babetas | C24: m2 | D24: 510 | E24: 21800 | F24: =+D24*E24 -> 11118000 | I24: =+'SVD 4140_Pto. 01_Cert. 07'!K24 -> 0 | K24: =+I24+J24 -> 0 | L24: =+F24*I24 -> 0 | M24: =+F24*J24 -> 0 | N24: =+F24*K24 -> 0
A25: 5.07 | B25: Impermeabilización de subsuelo | C25: gl | D25: 1 | E25: 16967915 | F25: =+D25*E25 -> 16967915 | I25: =+'SVD 4140_Pto. 01_Cert. 07'!K25 -> 1 | K25: =+I25+J25 -> 1 | L25: =+F25*I25 -> 16967915 | M25: =+F25*J25 -> 0 | N25: =+F25*K25 -> 16967915
A26: 6 | B26: CUBIERTAS | G26: =+SUM(F27) -> 2433900 | H26: =+G26/$G$185 -> 0.0033084706
A27: 6.02 | B27: Babeta de chapa galvanizada en medianeras | C27: ml | D27: 60 | E27: 40565 | F27: =+D27*E27 -> 2433900 | I27: =+'SVD 4140_Pto. 01_Cert. 07'!K27 -> 0 | K27: =+I27+J27 -> 0 | L27: =+F27*I27 -> 0 | M27: =+F27*J27 -> 0 | N27: =+F27*K27 -> 0
A28: 7 | B28: REVOQUES | G28: =+SUM(F29:F36) -> 1.3639056e+08 | H28: =+G28/$G$185 -> 0.18539962 | I28: =+'SVD 4140_Pto. 01_Cert. 07'!K28 -> 0
A29: 7.01 | B29: Revoque Grueso Impermeable Exterior proyectable | C29: m2 | D29: 678.252 | E29: 16571 | F29: =+D29*E29 -> 11239314 | I29: =+'SVD 4140_Pto. 01_Cert. 07'!K29 -> 0.05 | J29: 0.1 | K29: =+I29+J29 -> 0.15 | L29: =+F29*I29 -> 561965.69 | M29: =+F29*J29 -> 1123931.4 | N29: =+F29*K29 -> 1685897.1
A30: 7.02 | B30: Revoque Grueso Impermeable Exterior a mas de 3m proyectable - Medianero y fachadas | C30: m2 | D30: 876.0812 | E30: 22183 | F30: =+D30*E30 -> 19434109 | I30: =+'SVD 4140_Pto. 01_Cert. 07'!K30 -> 0.5 | J30: 0.25 | K30: =+I30+J30 -> 0.75 | L30: =+F30*I30 -> 9717054.6 | M30: =+F30*J30 -> 4858527.3 | N30: =+F30*K30 -> 14575582
A31: 7.03 | B31: Buña en revoque | C31: ml | D31: 182 | E31: 10806 | F31: =+D31*E31 -> 1966692 | I31: =+'SVD 4140_Pto. 01_Cert. 07'!K31 -> 0.5 | J31: 0.15 | K31: =+I31+J31 -> 0.65 | L31: =+F31*I31 -> 983346 | M31: =+F31*J31 -> 295003.8 | N31: =+F31*K31 -> 1278349.8
A32: 7.04 | B32: Revoque Grueso Interior + fino | C32: m2 | D32: 995.8511 | E32: 26530 | F32: =+D32*E32 -> 26419930 | I32: =+'SVD 4140_Pto. 01_Cert. 07'!K32 -> 0.45 | J32: 0.15 | K32: =+I32+J32 -> 0.6 | L32: =+F32*I32 -> 11888968 | M32: =+F32*J32 -> 3962989.5 | N32: =+F32*K32 -> 15851958
A33: 7.05 | B33: Yeso interior | C33: m2 | D33: 2514.897 | E33: 22566 | F33: =+D33*E33 -> 56751166 | I33: =+'SVD 4140_Pto. 01_Cert. 07'!K33 -> 0.2 | J33: 0.3 | K33: =+I33+J33 -> 0.5 | L33: =+F33*I33 -> 11350233 | M33: =+F33*J33 -> 17025350 | N33: =+F33*K33 -> 28375583
A34: 7.06 | B34: Arista en yeso | C34: ml | D34: 509.9 | E34: 12771 | F34: =+D34*E34 -> 6511932.9 | I34: =+'SVD 4140_Pto. 01_Cert. 07'!K34 -> 0.2 | J34: 0.3 | K34: =+I34+J34 -> 0.5 | L34: =+F34*I34 -> 1302386.6 | M34: =+F34*J34 -> 1953579.9 | N34: =+F34*K34 -> 3255966.4
A35: 7.07 | B35: Provisión y colocación de guardacanto yesero | C35: u | D35: 198 | E35: 14947 | F35: =+D35*E35 -> 2959506 | I35: =+'SVD 4140_Pto. 01_Cert. 07'!K35 -> 0.15 | J35: 0.35 | K35: =+I35+J35 -> 0.5 | L35: =+F35*I35 -> 443925.9 | M35: =+F35*J35 -> 1035827.1 | N35: =+F35*K35 -> 1479753
A36: 7.08 | B36: Revoque Grueso Impermeable Interior b/ revestimiento | C36: m2 | D36: 670.322 | E36: 16571 | F36: =+D36*E36 -> 11107906 | I36: =+'SVD 4140_Pto. 01_Cert. 07'!K36 -> 0.15 | J36: 0.4 | K36: =+I36+J36 -> 0.55 | L36: =+F36*I36 -> 1666185.9 | M36: =+F36*J36 -> 4443162.3 | N36: =+F36*K36 -> 6109348.2
A37: 8 | B37: CONTRAPISOS Y CARPETAS | G37: =+SUM(F38:F45) -> 44788107 | H37: =+G37/$G$185 -> 0.060881768
A38: 8.01 | B38: Contrapiso de cascotes en SS e: 15 cm | C38: m2 | D38: 104 | E38: 31920 | F38: =+D38*E38 -> 3319680 | I38: =+'SVD 4140_Pto. 01_Cert. 07'!K38 -> 1 | K38: =+I38+J38 -> 1 | L38: =+F38*I38 -> 3319680 | M38: =+F38*J38 -> 0 | N38: =+F38*K38 -> 3319680
A39: 8.02 | B39: Contrapiso de cascote s/terreno natural e: 20 cm - Incluye film de polietileno | C39: m2 | D39: 48 | E39: 37268 | F39: =+D39*E39 -> 1788864 | I39: =+'SVD 4140_Pto. 01_Cert. 07'!K39 -> 0 | K39: =+I39+J39 -> 0 | L39: =+F39*I39 -> 0 | M39: =+F39*J39 -> 0 | N39: =+F39*K39 -> 0
A40: 8.03 | B40: Contrapiso de cascotes en azoteas c/pendiente e: 15 cm | C40: m2 | D40: 235 | E40: 32410 | F40: =+D40*E40 -> 7616350 | I40: =+'SVD 4140_Pto. 01_Cert. 07'!K40 -> 0 | K40: =+I40+J40 -> 0 | L40: =+F40*I40 -> 0 | M40: =+F40*J40 -> 0 | N40: =+F40*K40 -> 0
A41: 8.04 | B41: Contrapiso - Carpeta monolitico e: 7 cm | C41: m2 | D41: 878 | E41: 19006 | F41: =+D41*E41 -> 16687268 | I41: =+'SVD 4140_Pto. 01_Cert. 07'!K41 -> 0 | J41: 0.05 | K41: =+I41+J41 -> 0.05 | L41: =+F41*I41 -> 0 | M41: =+F41*J41 -> 834363.4 | N41: =+F41*K41 -> 834363.4
A42: 8.05 | B42: Carpeta en PB y balcones, baños y azoteas e: 3,00 cm | C42: m2 | D42: 564 | E42: 12439 | F42: =+D42*E42 -> 7015596 | I42: =+'SVD 4140_Pto. 01_Cert. 07'!K42 -> 0 | K42: =+I42+J42 -> 0 | L42: =+F42*I42 -> 0 | M42: =+F42*J42 -> 0 | N42: =+F42*K42 -> 0
A43: 8.06 | B43: Carpeta sobre membrana | C43: m2 | D43: 438 | E43: 12439 | F43: =+D43*E43 -> 5448282 | I43: =+'SVD 4140_Pto. 01_Cert. 07'!K43 -> 0 | K43: =+I43+J43 -> 0 | L43: =+F43*I43 -> 0 | M43: =+F43*J43 -> 0 | N43: =+F43*K43 -> 0
A44: 8.07 | B44: Banquinas para cocinas | C44: gl | D44: 1 | E44: 2426924 | F44: =+D44*E44 -> 2426924 | I44: =+'SVD 4140_Pto. 01_Cert. 07'!K44 -> 0 | J44: 0.05 | K44: =+I44+J44 -> 0.05 | L44: =+F44*I44 -> 0 | M44: =+F44*J44 -> 121346.2 | N44: =+F44*K44 -> 121346.2
A45: 8.08 | B45: Banquinas para bombas y tanques en SB | C45: gl | D45: 1 | E45: 485143 | F45: =+D45*E45 -> 485143 | I45: =+'SVD 4140_Pto. 01_Cert. 07'!K45 -> 0 | K45: =+I45+J45 -> 0 | L45: =+F45*I45 -> 0 | M45: =+F45*J45 -> 0 | N45: =+F45*K45 -> 0
A46: 9 | B46: ESCALERAS | G46: =+SUM(F47:F50) -> 5769056.6 | H46: =+G46/$G$185 -> 0.0078420454
A47: 9.01 | B47: Cemento alisado arrodillado en escaleras | C47: gl | D47: 1 | E47: 2024643 | F47: =+D47*E47 -> 2024643 | I47: =+'SVD 4140_Pto. 01_Cert. 07'!K47 -> 0 | K47: =+I47+J47 -> 0 | L47: =+F47*I47 -> 0 | M47: =+F47*J47 -> 0 | N47: =+F47*K47 -> 0
A48: 9.02 | B48: Provisión nariz escalera, hierro angulo 5/8 x 1/8" | C48: ml | D48: 122 | E48: 18814 | F48: =+D48*E48 -> 2295308 | I48: =+'SVD 4140_Pto. 01_Cert. 07'!K48 -> 0 | K48: =+I48+J48 -> 0 | L48: =+F48*I48 -> 0 | M48: =+F48*J48 -> 0 | N48: =+F48*K48 -> 0
A49: 9.03 | B49: Zócalo de concreto | C49: ml | D49: 155 | E49: 5376 | F49: =+D49*E49 -> 833280 | I49: =+'SVD 4140_Pto. 01_Cert. 07'!K49 -> 0 | K49: =+I49+J49 -> 0 | L49: =+F49*I49 -> 0 | M49: =+F49*J49 -> 0 | N49: =+F49*K49 -> 0
A50: 9.04 | B50: Provisión y colocación de Rodapie/ Zócalo rampante en placa cementicia | C50: ml | D50: 31.2 | E50: 19738 | F50: =+D50*E50 -> 615825.6 | I50: =+'SVD 4140_Pto. 01_Cert. 07'!K50 -> 0 | K50: =+I50+J50 -> 0 | L50: =+F50*I50 -> 0 | M50: =+F50*J50 -> 0 | N50: =+F50*K50 -> 0
A51: 10 | B51: VENTILACIONES | G51: =+SUM(F52:F55) -> 4669278 | H51: =+G51/$G$185 -> 0.0063470845
A52: 10.01 | B52: Ventilación Conducto Humos. Incluye toma de aire en PB - No aplica s/proyecto | C52: gl | D52: 0 | E52: 0 | F52: =+D52*E52 -> 0 | I52: =+'SVD 4140_Pto. 01_Cert. 07'!K52 -> 0 | K52: =+I52+J52 -> 0 | L52: =+F52*I52 -> 0 | M52: =+F52*J52 -> 0 | N52: =+F52*K52 -> 0
A53: 10.02 | B53: Ventilación Baños - En caño Ø 110 | C53: gl | D53: 1 | E53: 2199545 | F53: =+D53*E53 -> 2199545 | I53: =+'SVD 4140_Pto. 01_Cert. 07'!K53 -> 0.5 | J53: 0.35 | K53: =+I53+J53 -> 0.85 | L53: =+F53*I53 -> 1099772.5 | M53: =+F53*J53 -> 769840.75 | N53: =+F53*K53 -> 1869613.2
A54: 10.03 | B54: Colocación de rejillas de inyección y extracción - No aplica s/proyecto | C54: un | D54: 0 | E54: 0 | F54: =+D54*E54 -> 0 | I54: =+'SVD 4140_Pto. 01_Cert. 07'!K54 -> 0 | K54: =+I54+J54 -> 0 | L54: =+F54*I54 -> 0 | M54: =+F54*J54 -> 0 | N54: =+F54*K54 -> 0
A55: 10.04 | B55: Sombreretes en chapa prepintada C25 | C55: u | D55: 7 | E55: 352819 | F55: =+D55*E55 -> 2469733 | I55: =+'SVD 4140_Pto. 01_Cert. 07'!K55 -> 0 | K55: =+I55+J55 -> 0 | L55: =+F55*I55 -> 0 | M55: =+F55*J55 -> 0 | N55: =+F55*K55 -> 0
A56: 11 | B56: PISOS - PROVISION A CARGO DEL COMITENTE | G56: =+SUM(F57:F63) -> 48040802 | H56: =+G56/$G$185 -> 0.06530325
A57: 11.01 | B57: Colocación de travertino en hall PB - Provisión a cargo del comitente | C57: m2 | D57: 30 | E57: 21948 | F57: =+D57*E57 -> 658440 | I57: =+'SVD 4140_Pto. 01_Cert. 07'!K57 -> 0 | K57: =+I57+J57 -> 0 | L57: =+F57*I57 -> 0 | M57: =+F57*J57 -> 0 | N57: =+F57*K57 -> 0
A58: 11.02 | B58: Colocación de porcelanato en paliers, terraza y espacios comunes - Provisión a cargo del comitente | C58: m2 | D58: 185 | E58: 21948 | F58: =+D58*E58 -> 4060380 | I58: =+'SVD 4140_Pto. 01_Cert. 07'!K58 -> 0 | K58: =+I58+J58 -> 0 | L58: =+F58*I58 -> 0 | M58: =+F58*J58 -> 0 | N58: =+F58*K58 -> 0
A59: 11.03 | B59: Colocación de porcelanato en UF - Provisión a cargo del comitente | C59: m2 | D59: 942 | E59: 21948 | F59: =+D59*E59 -> 20675016 | I59: =+'SVD 4140_Pto. 01_Cert. 07'!K59 -> 0 | K59: =+I59+J59 -> 0 | L59: =+F59*I59 -> 0 | M59: =+F59*J59 -> 0 | N59: =+F59*K59 -> 0
A60: 11.04 | B60: Colocación de porcelanato en baños - Provisión a cargo del comitente | C60: m2 | D60: 110 | E60: 25799 | F60: =+D60*E60 -> 2837890 | I60: =+'SVD 4140_Pto. 01_Cert. 07'!K60 -> 0 | K60: =+I60+J60 -> 0 | L60: =+F60*I60 -> 0 | M60: =+F60*J60 -> 0 | N60: =+F60*K60 -> 0
A61: 11.05 | B61: Provisión y ejecución de alisado de cemento rodillado | C61: m2 | D61: 128 | E61: 16080 | F61: =+D61*E61 -> 2058240 | I61: =+'SVD 4140_Pto. 01_Cert. 07'!K61 -> 0 | K61: =+I61+J61 -> 0 | L61: =+F61*I61 -> 0 | M61: =+F61*J61 -> 0 | N61: =+F61*K61 -> 0
A62: 11.06 | B62: Colocación de baldoson de vereda - Provisión a cargo del comitente | C62: m2 | D62: 48 | E62: 21948 | F62: =+D62*E62 -> 1053504 | I62: =+'SVD 4140_Pto. 01_Cert. 07'!K62 -> 0 | K62: =+I62+J62 -> 0 | L62: =+F62*I62 -> 0 | M62: =+F62*J62 -> 0 | N62: =+F62*K62 -> 0
A63: 11.07 | B63: Provisión y ejecución de pavimento e: 18 cm, incluye malla Q188 | C63: m2 | D63: 226 | E63: 73882 | F63: =+D63*E63 -> 16697332 | I63: =+'SVD 4140_Pto. 01_Cert. 07'!K63 -> 1 | K63: =+I63+J63 -> 1 | L63: =+F63*I63 -> 16697332 | M63: =+F63*J63 -> 0 | N63: =+F63*K63 -> 16697332
A64: 12 | B64: ZOCALOS Y SOLIAS - PROVISION A CARGO DEL COMITENTE | G64: =+SUM(F65:F69) -> 11022518 | H64: =+G64/$G$185 -> 0.014983227
A65: 12.01 | B65: Provisión y colocación de zocalos de Madera (MDF) h: 7 cm | C65: ml | D65: 779 | E65: 7422 | F65: =+D65*E65 -> 5781738 | I65: =+'SVD 4140_Pto. 01_Cert. 07'!K65 -> 0 | K65: =+I65+J65 -> 0 | L65: =+F65*I65 -> 0 | M65: =+F65*J65 -> 0 | N65: =+F65*K65 -> 0
A66: 12.02 | B66: Zócalo de concreto | C66: ml | D66: 155 | E66: 5376 | F66: =+D66*E66 -> 833280 | I66: =+'SVD 4140_Pto. 01_Cert. 07'!K66 -> 0 | K66: =+I66+J66 -> 0 | L66: =+F66*I66 -> 0 | M66: =+F66*J66 -> 0 | N66: =+F66*K66 -> 0
A67: 12.03 | B67: Colocación de zocalo de porcelanico - Provisión a cargo del comitente | C67: ml | D67: 37 | E67: 7052 | F67: =+D67*E67 -> 260924 | I67: =+'SVD 4140_Pto. 01_Cert. 07'!K67 -> 0 | K67: =+I67+J67 -> 0 | L67: =+F67*I67 -> 0 | M67: =+F67*J67 -> 0 | N67: =+F67*K67 -> 0
A68: 12.04 | B68: Colocación de zocalo de porcelanato en palieres - Provisión a cargo del comitente | C68: ml | D68: 433 | E68: 7052 | F68: =+D68*E68 -> 3053516 | I68: =+'SVD 4140_Pto. 01_Cert. 07'!K68 -> 0 | K68: =+I68+J68 -> 0 | L68: =+F68*I68 -> 0 | M68: =+F68*J68 -> 0 | N68: =+F68*K68 -> 0
A69: 12.05 | B69: Colocación de zocalo de porcelanato en terraza y espacios comunes - Provisión a cargo del comitente | C69: ml | D69: 155 | E69: 7052 | F69: =+D69*E69 -> 1093060 | I69: =+'SVD 4140_Pto. 01_Cert. 07'!K69 -> 0 | K69: =+I69+J69 -> 0 | L69: =+F69*I69 -> 0 | M69: =+F69*J69 -> 0 | N69: =+F69*K69 -> 0
A70: 13 | B70: REVESTIMIENTOS - PROVISION A CARGO DEL COMITENTE | G70: =+SUM(F71:F74) -> 19433086 | H70: =+G70/$G$185 -> 0.026415956
A71: 13.01 | B71: Revestimiento en baños - Provisión a cargo del comitente | C71: m2 | D71: 511 | E71: 25799 | F71: =+D71*E71 -> 13183289 | I71: =+'SVD 4140_Pto. 01_Cert. 07'!K71 -> 0 | K71: =+I71+J71 -> 0 | L71: =+F71*I71 -> 0 | M71: =+F71*J71 -> 0 | N71: =+F71*K71 -> 0
A72: 13.02 | B72: Revestimiento en cocinas - Provisión a cargo del comitente | C72: m2 | D72: 40 | E72: 25799 | F72: =+D72*E72 -> 1031960 | I72: =+'SVD 4140_Pto. 01_Cert. 07'!K72 -> 0 | K72: =+I72+J72 -> 0 | L72: =+F72*I72 -> 0 | M72: =+F72*J72 -> 0 | N72: =+F72*K72 -> 0
A73: 13.03 | B73: Revestimiento tejuela exterior - Provisión a cargo del comitente | C73: m2 | D73: 147.601 | E73: 29881 | F73: =+D73*E73 -> 4410465.5 | I73: =+'SVD 4140_Pto. 01_Cert. 07'!K73 -> 0 | K73: =+I73+J73 -> 0 | L73: =+F73*I73 -> 0 | M73: =+F73*J73 -> 0 | N73: =+F73*K73 -> 0
A74: 13.04 | B74: Provisión y colocación de perfileria de aluminio tipo ATRIM L anod. Natural | C74: u | D74: 41 | E74: 19692 | F74: =+D74*E74 -> 807372 | I74: =+'SVD 4140_Pto. 01_Cert. 07'!K74 -> 0 | K74: =+I74+J74 -> 0 | L74: =+F74*I74 -> 0 | M74: =+F74*J74 -> 0 | N74: =+F74*K74 -> 0
A75: 14 | B75: CIELORRASOS | G75: =+SUM(F76:F82) -> 50296169 | H75: =+G75/$G$185 -> 0.068369036
A76: 14.01 | B76: Cielorraso junta tomada placa STD | C76: m2 | D76: 334.9152 | E76: 29270 | F76: =+D76*E76 -> 9802967.9 | I76: =+'SVD 4140_Pto. 01_Cert. 07'!K76 -> 0.2 | J76: 0.4 | K76: =+I76+J76 -> 0.6 | L76: =+F76*I76 -> 1960593.6 | M76: =+F76*J76 -> 3921187.2 | N76: =+F76*K76 -> 5881780.7
A77: 14.02 | B77: Cielorraso junta tomada placa RH | C77: m2 | D77: 280.3913 | E77: 33967 | F77: =+D77*E77 -> 9524051.3 | I77: =+'SVD 4140_Pto. 01_Cert. 07'!K77 -> 0.2 | J77: 0.5 | K77: =+I77+J77 -> 0.7 | L77: =+F77*I77 -> 1904810.3 | M77: =+F77*J77 -> 4762025.6 | N77: =+F77*K77 -> 6666835.9
A78: 14.03 | B78: Cajon en junta tomada placa STD | C78: ml | D78: 60.8 | E78: 29270 | F78: =+D78*E78 -> 1779616 | I78: =+'SVD 4140_Pto. 01_Cert. 07'!K78 -> 0.25 | J78: 0.35 | K78: =+I78+J78 -> 0.6 | L78: =+F78*I78 -> 444904 | M78: =+F78*J78 -> 622865.6 | N78: =+F78*K78 -> 1067769.6
A79: 14.04 | B79: Buña perimetral / Cantoneras | C79: ml | D79: 1058.38 | E79: 7873 | F79: =+D79*E79 -> 8332625.7 | I79: =+'SVD 4140_Pto. 01_Cert. 07'!K79 -> 0.25 | J79: 0.35 | K79: =+I79+J79 -> 0.6 | L79: =+F79*I79 -> 2083156.4 | M79: =+F79*J79 -> 2916419 | N79: =+F79*K79 -> 4999575.4
A80: 14.05 | B80: Aplicado de yeso interior | C80: m2 | D80: 504.1222 | E80: 23364 | F80: =+D80*E80 -> 11778311 | I80: =+'SVD 4140_Pto. 01_Cert. 07'!K80 -> 0.2 | J80: 0.4 | K80: =+I80+J80 -> 0.6 | L80: =+F80*I80 -> 2355662.2 | M80: =+F80*J80 -> 4711324.4 | N80: =+F80*K80 -> 7066986.6
A81: 14.06 | B81: Buña en yeso | C81: ml | D81: 555.99 | E81: 12771 | F81: =+D81*E81 -> 7100548.3 | I81: =+'SVD 4140_Pto. 01_Cert. 07'!K81 -> 0.2 | J81: 0.4 | K81: =+I81+J81 -> 0.6 | L81: =+F81*I81 -> 1420109.7 | M81: =+F81*J81 -> 2840219.3 | N81: =+F81*K81 -> 4260329
A82: 14.07 | B82: H° Visto - Maquillaje para recibir pintura | C82: m2 | D82: 429.0778 | E82: 4610 | F82: =+D82*E82 -> 1978048.7 | I82: =+'SVD 4140_Pto. 01_Cert. 07'!K82 -> 0 | K82: =+I82+J82 -> 0 | L82: =+F82*I82 -> 0 | M82: =+F82*J82 -> 0 | N82: =+F82*K82 -> 0
A83: 15 | B83: PINTURA | G83: =+SUM(F84:F92) -> 0 | H83: =+G83/$G$185 -> 0
A84: 15.01 | B84: Látex interior para paredes Bco. mate (enduido parcial) | C84: m2 | D84: 2670 | E84: 0 | F84: =+D84*E84 -> 0 | I84: =+'SVD 4140_Pto. 01_Cert. 07'!K84 -> 0 | K84: =+I84+J84 -> 0 | L84: =+F84*I84 -> 0 | M84: =+F84*J84 -> 0 | N84: =+F84*K84 -> 0
A85: 15.02 | B85: Látex interior para paredes Bco. mate (s/enduido) | C85: m2 | D85: 961 | E85: 0 | F85: =+D85*E85 -> 0 | I85: =+'SVD 4140_Pto. 01_Cert. 07'!K85 -> 0 | K85: =+I85+J85 -> 0 | L85: =+F85*I85 -> 0 | M85: =+F85*J85 -> 0 | N85: =+F85*K85 -> 0
A86: 15.03 | B86: Látex para cielorraso Bco. mate (enduido parcial) | C86: m2 | D86: 518 | E86: 0 | F86: =+D86*E86 -> 0 | I86: =+'SVD 4140_Pto. 01_Cert. 07'!K86 -> 0 | K86: =+I86+J86 -> 0 | L86: =+F86*I86 -> 0 | M86: =+F86*J86 -> 0 | N86: =+F86*K86 -> 0
A87: 15.04 | B87: Látex para cielorraso Bco. mate (enduido completo) | C87: m2 | D87: 612 | E87: 0 | F87: =+D87*E87 -> 0 | I87: =+'SVD 4140_Pto. 01_Cert. 07'!K87 -> 0 | K87: =+I87+J87 -> 0 | L87: =+F87*I87 -> 0 | M87: =+F87*J87 -> 0 | N87: =+F87*K87 -> 0
A88: 15.05 | B88: Latex interior cielorraso sobre H° | C88: m2 | D88: 422 | E88: 0 | F88: =+D88*E88 -> 0 | I88: =+'SVD 4140_Pto. 01_Cert. 07'!K88 -> 0 | K88: =+I88+J88 -> 0 | L88: =+F88*I88 -> 0 | M88: =+F88*J88 -> 0 | N88: =+F88*K88 -> 0
A89: 15.07 | B89: Revestimiento plastico tipo Quimtex en exteriores y PB | C89: m2 | D89: 678.252 | E89: 0 | F89: =+D89*E89 -> 0 | I89: =+'SVD 4140_Pto. 01_Cert. 07'!K89 -> 0 | K89: =+I89+J89 -> 0 | L89: =+F89*I89 -> 0 | M89: =+F89*J89 -> 0 | N89: =+F89*K89 -> 0
A90: 15.08 | B90: Revestimiento plastico tipo Quimtex en exteriores a mas de 3m de altura, incluye medianeras | C90: m2 | D90: 728.4802 | E90: 0 | F90: =+D90*E90 -> 0 | I90: =+'SVD 4140_Pto. 01_Cert. 07'!K90 -> 0 | K90: =+I90+J90 -> 0 | L90: =+F90*I90 -> 0 | M90: =+F90*J90 -> 0 | N90: =+F90*K90 -> 0
A91: 15.09 | B91: Esmalte sintético en puertas placa, chapa y de ascensor | C91: un | D91: 76 | E91: 0 | F91: =+D91*E91 -> 0 | I91: =+'SVD 4140_Pto. 01_Cert. 07'!K91 -> 0 | K91: =+I91+J91 -> 0 | L91: =+F91*I91 -> 0 | M91: =+F91*J91 -> 0 | N91: =+F91*K91 -> 0
A92: 15.1 | B92: Convertidor y esmalte sintentico en barandas - Escalera, balcones, porton, medidores y SDM | C92: gl | D92: 1 | E92: 0 | F92: =+D92*E92 -> 0 | I92: =+'SVD 4140_Pto. 01_Cert. 07'!K92 -> 0 | K92: =+I92+J92 -> 0 | L92: =+F92*I92 -> 0 | M92: =+F92*J92 -> 0 | N92: =+F92*K92 -> 0
A93: 16 | B93: MARMOLES Y GRANITOS - PROVISION Y COLOCACION A CARGO DEL COMITENTE | G93: =+SUM(F94) -> 0 | H93: =+G93/$G$185 -> 0
E94: 0 | F94: =+D94*E94 -> 0 | I94: =+'SVD 4140_Pto. 01_Cert. 07'!K94 -> 0 | K94: =+I94+J94 -> 0 | L94: =+F94*I94 -> 0 | M94: =+F94*J94 -> 0 | N94: =+F94*K94 -> 0
A95: 17 | B95: CARPINTERIA - PROVISION A CARGO DEL COMITENTE | G95: =+SUM(F96:F99) -> 7258243 | H95: =+G95/$G$185 -> 0.0098663395
A96: 17.01 | B96: Amure de puertas placa Provisión a cargo del comitente | C96: u | D96: 47 | E96: 64232 | F96: =+D96*E96 -> 3018904 | I96: =+'SVD 4140_Pto. 01_Cert. 07'!K96 -> 0.85 | K96: =+I96+J96 -> 0.85 | L96: =+F96*I96 -> 2566068.4 | M96: =+F96*J96 -> 0 | N96: =+F96*K96 -> 2566068.4
A97: 17.02 | B97: Amure de puertas de chapa e ingresos depto - Provisión a cargo del comitente | C97: u | D97: 23 | E97: 64232 | F97: =+D97*E97 -> 1477336 | I97: =+'SVD 4140_Pto. 01_Cert. 07'!K97 -> 0.85 | K97: =+I97+J97 -> 0.85 | L97: =+F97*I97 -> 1255735.6 | M97: =+F97*J97 -> 0 | N97: =+F97*K97 -> 1255735.6
A98: 17.03 | B98: Amure de premarcos - Provisión a cargo del comitente | C98: u | D98: 51 | E98: 41296 | F98: =+D98*E98 -> 2106096 | I98: =+'SVD 4140_Pto. 01_Cert. 07'!K98 -> 0.85 | K98: =+I98+J98 -> 0.85 | L98: =+F98*I98 -> 1790181.6 | M98: =+F98*J98 -> 0 | N98: =+F98*K98 -> 1790181.6
A99: 17.04 | B99: Amure Puertas de Ascensor - Provisión a cargo del comitente | C99: u | D99: 7 | E99: 93701 | F99: =+D99*E99 -> 655907 | I99: =+'SVD 4140_Pto. 01_Cert. 07'!K99 -> 0 | K99: =+I99+J99 -> 0 | L99: =+F99*I99 -> 0 | M99: =+F99*J99 -> 0 | N99: =+F99*K99 -> 0
A100: 18 | B100: INSTALACION ELECTRICA | G100: =+SUM(F101:F130) -> 99277732 | H100: =+G100/$G$185 -> 0.13495109
A101: 18.01 | B101: Tendido y cableado boca Iluminación | C101: u | D101: 392 | E101: 59948 | F101: =+D101*E101 -> 23499616 | I101: =+'SVD 4140_Pto. 01_Cert. 07'!K101 -> 0.45 | J101: 0.05 | K101: =+I101+J101 -> 0.5 | L101: =+F101*I101 -> 10574827 | M101: =+F101*J101 -> 1174980.8 | N101: =+F101*K101 -> 11749808
...
