Workbook
Name \0: #REF!
Name \0: #REF!
Name \0: #REF!
Name \0: #REF!
Name \0: #REF!
Name \0: #REF!
Name \c: #REF!
Name \c: #REF!
Name \c: #REF!
Name \c: #REF!
Name \E: #REF!
Name \E: #REF!
Name \E: #REF!
Name \E: #REF!
Name \i: #REF!
Name \j: #REF!
Name \m: #REF!
Name \P: #REF!
Name \P: #REF!
Name \P: #REF!
Name \P: #REF!
Name \P: #REF!
Name \P: #REF!
Name \P: #REF!
Name \P: #REF!
Name \P: #REF!
Name \P: #REF!
Name \P: #REF!
Name \P: #REF!
Name \P: #REF!
Name \P: #REF!
Name \P: #REF!
Name \P: #REF!
Name \P: #REF!
Name \P: #REF!
Name \P: #REF!
Name \r: #N/A
Name \x: #REF!
Name \z: #REF!
Name \z: #REF!
Name \z: #REF!
Name \z: #REF!
Name \z: #REF!
Name \z: #REF!
Name __________ben1: #REF!
Name __________ben1: #REF!
Name __________ben1: #REF!
Name __________ben1: #REF!
Name __________ben1: #REF!
Name __________ben1: #REF!
Name __________ben1: #REF!
Name __________ben1: #REF!
Name __________ben1: #REF!
Name __________ben1: #REF!
Name __________ben1: #REF!
Name __________ben1: #REF!
Name __________ben1: #REF!
Name __________ben1: #REF!
Name __________ben1: #REF!
Name __________ben1: #REF!

Sheet HOJA DE OBRA
D1: OBRA: Edificio El Salvador 4140
A6: Cliente / Comitente:
A7: Facturacion
A8: Dirección / Jefe de la Obra:
A11: Fecha de Inicio : | D11: Duracion de Obra: | E11: 18 meses
A13: Presupuesto Aprobado : | D13: Fecha de Aprobacion:
A14: Orden de Compra CL : | D14: Nota de Pedido ARQ:
A16: Anticipo : | D16: Condiciones de Pago:
A17: Certifiaciones : | D17: Forma de Pago:
A18: Actualización CAC:
A20: Seguros :
A21: Caucion Anticipo
A22: Caucion Ejecucion
A23: Resp. Civil
A25: Programa S&H :
A26: Aviso de Obra :
A28: Descripcion de Tareas
A33: Contactos del cliente:
A34: Nombre | B34: TEL | C34: Rubro | D34: Mail de contacto
A39: Subcontratistas | B39: Rubro | C39: Inicio | D39: Presupuesto Aprobado | E39: Cerrado / Estimado
A44: Cuadrilla de Obra | B44: Categoría | D44: Observación
A52: Observaciones Particulares

Sheet Resumen General
AE1: Actualizado | AF1: 46174
B3: OBRA: SVD 4140
B4: RESUMEN DE OBRA
D5: 45658 | E5: 45689 | F5: 45717 | G5: 45748 | H5: 45778 | I5: 45809 | J5: 45839 | K5: 45870 | L5: 45901 | M5: 45931 | N5: 45962 | O5: 45992 | P5: 46023 | Q5: 46054 | R5: 46082 | S5: 46113 | T5: 46143 | V5: Acum. Descontado | X5: Presupuesto #1 Act. | Y5: Presupuesto #2 Act. | Z5: Previsto | AA5: % Cert. Acum. | AB5: Saldo Disponible | AC5: Disponible % | AD5: Rubro Completado
B6: Ingresos de Obra
B7: Ingresos por Certificados | D7: =SUM(VLOOKUP($B7,'Resumen Pto #1'!$B$5:$U$10,MATCH('Resumen General'!D$5,'Resumen Pto #1'!$B$5:$U$5,0),0)) -> 0 | E7: =SUM(VLOOKUP($B7,'Resumen Pto #1'!$B$5:$U$10,MATCH('Resumen General'!E$5,'Resumen Pto #1'!$B$5:$U$5,0),0)) -> 11515000 | F7: =SUM(VLOOKUP($B7,'Resumen Pto #1'!$B$5:$U$10,MATCH('Resumen General'!F$5,'Resumen Pto #1'!$B$5:$U$5,0),0)) -> 72746210 | G7: =SUM(VLOOKUP($B7,'Resumen Pto #1'!$B$5:$U$10,MATCH('Resumen General'!G$5,'Resumen Pto #1'!$B$5:$U$5,0),0)) -> 28390040 | H7: =SUM(VLOOKUP($B7,'Resumen Pto #1'!$B$5:$U$10,MATCH('Resumen General'!H$5,'Resumen Pto #1'!$B$5:$U$5,0),0)) -> 28932600 | I7: =SUM(VLOOKUP($B7,'Resumen Pto #1'!$B$5:$U$10,MATCH('Resumen General'!I$5,'Resumen Pto #1'!$B$5:$U$5,0),0)) -> 23665294 | J7: =SUM(VLOOKUP($B7,'Resumen Pto #1'!$B$5:$U$10,MATCH('Resumen General'!J$5,'Resumen Pto #1'!$B$5:$U$5,0),0),VLOOKUP($B7,'Resumen Pto #2'!$B$5:$Q$10,MATCH('Resumen General'!J$5,'Resumen Pto #2'!$B$5:$O$5,0),0)) -> 24611609 | K7: =SUM(VLOOKUP($B7,'Resumen Pto #1'!$B$5:$U$10,MATCH('Resumen General'!K$5,'Resumen Pto #1'!$B$5:$U$5,0),0),VLOOKUP($B7,'Resumen Pto #2'!$B$5:$Q$10,MATCH('Resumen General'!K$5,'Resumen Pto #2'!$B$5:$O$5,0),0)) -> 32566741 | L7: =SUM(VLOOKUP($B7,'Resumen Pto #1'!$B$5:$U$10,MATCH('Resumen General'!L$5,'Resumen Pto #1'!$B$5:$U$5,0),0),VLOOKUP($B7,'Resumen Pto #2'!$B$5:$Q$10,MATCH('Resumen General'!L$5,'Resumen Pto #2'!$B$5:$O$5,0),0)) -> 48704739 | M7: =SUM(VLOOKUP($B7,'Resumen Pto #1'!$B$5:$U$10,MATCH('Resumen General'!M$5,'Resumen Pto #1'!$B$5:$U$5,0),0),VLOOKUP($B7,'Resumen Pto #2'!$B$5:$Q$10,MATCH('Resumen General'!M$5,'Resumen Pto #2'!$B$5:$O$5,0),0)) -> 3.2988773e+08 | N7: =SUM(VLOOKUP($B7,'Resumen Pto #1'!$B$5:$U$10,MATCH('Resumen General'!N$5,'Resumen Pto #1'!$B$5:$U$5,0),0),VLOOKUP($B7,'Resumen Pto #2'!$B$5:$Q$10,MATCH('Resumen General'!N$5,'Resumen Pto #2'!$B$5:$O$5,0),0)) -> 52221423 | O7: =SUM(VLOOKUP($B7,'Resumen Pto #1'!$B$5:$U$10,MATCH('Resumen General'!O$5,'Resumen Pto #1'!$B$5:$U$5,0),0),VLOOKUP($B7,'Resumen Pto #2'!$B$5:$Q$10,MATCH('Resumen General'!O$5,'Resumen Pto #2'!$B$5:$O$5,0),0)) -> 58087412 | P7: =SUM(VLOOKUP($B7,'Resumen Pto #1'!$B$5:$U$10,MATCH('Resumen General'!P$5,'Resumen Pto #1'!$B$5:$U$5,0),0),VLOOKUP($B7,'Resumen Pto #2'!$B$5:$Q$10,MATCH('Resumen General'!P$5,'Resumen Pto #2'!$B$5:$O$5,0),0)) -> 27947358 | Q7: =SUM(VLOOKUP($B7,'Resumen Pto #1'!$B$5:$U$10,MATCH('Resumen General'!Q$5,'Resumen Pto #1'!$B$5:$U$5,0),0),VLOOKUP($B7,'Resumen Pto #2'!$B$5:$Q$10,MATCH('Resumen General'!Q$5,'Resumen Pto #2'!$B$5:$O$5,0),0)) -> 40981161 | ... T7: =SUM(VLOOKUP($B7,'Resumen Pto #1'!$B$5:$U$10,MATCH('Resumen General'!T$5,'Resumen Pto #1'!$B$5:$U$5,0),0),VLOOKUP($B7,'Resumen Pto #2'!$B$5:$Q$10,MATCH('Resumen General'!T$5,'Resumen Pto #2'!$B$5:$O$5,0),0)) -> 41422349 | V7: =SUM(D7:U7) -> 8.71161e+08 | X7: ='Resumen Pto #1'!X7 -> 421306052 | Y7: ='Resumen Pto #2'!R7 -> 7.3685713e+08 | Z7: =SUM(X7:Y7) -> 1.1581632e+09 | AA7: =SUM('Pto. 01 Cert.'!$S$58,'Pto. 02 Cert.'!$S$186)/SUM('Pto. 01 Cert.'!$L$58,'Pto. Vta.'!$L$239) -> 0.64279413 | AB7: =IF(AA7=100%,0,IF(OR(V7<>0,Z7),Z7-V7)) -> 2.8700219e+08 | AC7: =IF(OR(AB7<0,Z7),AB7/Z7,0%) -> 0.24780807 | AD7: =IF(AA7=100%,IF(OR(V7<>0,Z7),Z7-V7),0) -> 0
B8: Total Ingresos de Obra | D8: =SUM(D7) -> 0 | E8: =SUM(E7) -> 11515000 | F8: =SUM(F7) -> 72746210 | G8: =SUM(G7) -> 28390040 | H8: =SUM(H7) -> 28932600 | I8: =SUM(I7) -> 23665294 | J8: =SUM(J7) -> 24611609 | K8: =SUM(K7) -> 32566741 | ... T8: =SUM(T7) -> 41422349 | V8: =SUM(V7) -> 8.71161e+08 | X8: =SUM(X7) -> 421306052 | Y8: =SUM(Y7) -> 7.3685713e+08 | Z8: =SUM(Z7) -> 1.1581632e+09 | AB8: =SUM(AB7) -> 2.8700219e+08 | AC8: =IF(OR(AB8<0,Z8),AB8/Z8,0%) -> 0.24780807 | AD8: =IF(OR(V8<>0,Z8),Z8-V8,) -> 2.8700219e+08
B9: Actualización por CAC | D9: =SUM(VLOOKUP($B9,'Resumen Pto #1'!$B$5:$U$10,MATCH('Resumen General'!D$5,'Resumen Pto #1'!$B$5:$U$5,0),0)) -> 0 | E9: =SUM(VLOOKUP($B9,'Resumen Pto #1'!$B$5:$U$10,MATCH('Resumen General'!E$5,'Resumen Pto #1'!$B$5:$U$5,0),0)) -> 735000 | F9: =SUM(VLOOKUP($B9,'Resumen Pto #1'!$B$5:$U$10,MATCH('Resumen General'!F$5,'Resumen Pto #1'!$B$5:$U$5,0),0)) -> 5068372.2 | G9: =SUM(VLOOKUP($B9,'Resumen Pto #1'!$B$5:$U$10,MATCH('Resumen General'!G$5,'Resumen Pto #1'!$B$5:$U$5,0),0)) -> 2935456.1 | H9: =SUM(VLOOKUP($B9,'Resumen Pto #1'!$B$5:$U$10,MATCH('Resumen General'!H$5,'Resumen Pto #1'!$B$5:$U$5,0),0)) -> 3370711.7 | I9: =SUM(VLOOKUP($B9,'Resumen Pto #1'!$B$5:$U$10,MATCH('Resumen General'!I$5,'Resumen Pto #1'!$B$5:$U$5,0),0)) -> 3338429.3 | J9: =SUM(VLOOKUP($B9,'Resumen Pto #1'!$B$5:$U$10,MATCH('Resumen General'!J$5,'Resumen Pto #1'!$B$5:$U$5,0),0),VLOOKUP($B9,'Resumen Pto #2'!$B$5:$Q$10,MATCH('Resumen General'!J$5,'Resumen Pto #2'!$B$5:$O$5,0),0)) -> 3690653.5 | K9: =SUM(VLOOKUP($B9,'Resumen Pto #1'!$B$5:$U$10,MATCH('Resumen General'!K$5,'Resumen Pto #1'!$B$5:$U$5,0),0),VLOOKUP($B9,'Resumen Pto #2'!$B$5:$Q$10,MATCH('Resumen General'!K$5,'Resumen Pto #2'!$B$5:$O$5,0),0)) -> 5160346.8 | L9: =SUM(VLOOKUP($B9,'Resumen Pto #1'!$B$5:$U$10,MATCH('Resumen General'!L$5,'Resumen Pto #1'!$B$5:$U$5,0),0),VLOOKUP($B9,'Resumen Pto #2'!$B$5:$Q$10,MATCH('Resumen General'!L$5,'Resumen Pto #2'!$B$5:$O$5,0),0)) -> 8721283.8 | M9: =SUM(VLOOKUP($B9,'Resumen Pto #1'!$B$5:$U$10,MATCH('Resumen General'!M$5,'Resumen Pto #1'!$B$5:$U$5,0),0),VLOOKUP($B9,'Resumen Pto #2'!$B$5:$Q$10,MATCH('Resumen General'!M$5,'Resumen Pto #2'!$B$5:$O$5,0),0)) -> 59686343 | N9: =SUM(VLOOKUP($B9,'Resumen Pto #1'!$B$5:$U$10,MATCH('Resumen General'!N$5,'Resumen Pto #1'!$B$5:$U$5,0),0),VLOOKUP($B9,'Resumen Pto #2'!$B$5:$Q$10,MATCH('Resumen General'!N$5,'Resumen Pto #2'!$B$5:$O$5,0),0)) -> 12249470 | O9: =SUM(VLOOKUP($B9,'Resumen Pto #1'!$B$5:$U$10,MATCH('Resumen General'!O$5,'Resumen Pto #1'!$B$5:$U$5,0),0),VLOOKUP($B9,'Resumen Pto #2'!$B$5:$Q$10,MATCH('Resumen General'!O$5,'Resumen Pto #2'!$B$5:$O$5,0),0)) -> 14332314 | P9: =SUM(VLOOKUP($B9,'Resumen Pto #1'!$B$5:$U$10,MATCH('Resumen General'!P$5,'Resumen Pto #1'!$B$5:$U$5,0),0),VLOOKUP($B9,'Resumen Pto #2'!$B$5:$Q$10,MATCH('Resumen General'!P$5,'Resumen Pto #2'!$B$5:$O$5,0),0)) -> 8107844.3 | Q9: =SUM(VLOOKUP($B9,'Resumen Pto #1'!$B$5:$U$10,MATCH('Resumen General'!Q$5,'Resumen Pto #1'!$B$5:$U$5,0),0),VLOOKUP($B9,'Resumen Pto #2'!$B$5:$Q$10,MATCH('Resumen General'!Q$5,'Resumen Pto #2'!$B$5:$O$5,0),0)) -> 12717755 | ... T9: =SUM(VLOOKUP($B9,'Resumen Pto #1'!$B$5:$U$10,MATCH('Resumen General'!T$5,'Resumen Pto #1'!$B$5:$U$5,0),0),VLOOKUP($B9,'Resumen Pto #2'!$B$5:$Q$10,MATCH('Resumen General'!T$5,'Resumen Pto #2'!$B$5:$O$5,0),0)) -> 15732588 | V9: =SUM(D9:U9) -> 1.7298624e+08 | X9: ='Resumen Pto #1'!Y9 -> 0 | Y9: ='Resumen Pto #2'!T9 -> 0 | Z9: 0 | AA9: 0 | AB9: =IF(AA9=100%,0,IF(Z9=0,Z9,Z9-V9)) -> 0 | AC9: =IF(OR(AB9<0,Z9),AB9/Z9,0%) -> 0 | AD9: =IF(AA9=100%,IF(OR(U9<>0,Z9),Z9-U9),0) -> 0
B10: Total Ingresos por CAC | D10: =SUM(D9) -> 0 | E10: =SUM(E9) -> 735000 | F10: =SUM(F9) -> 5068372.2 | G10: =SUM(G9) -> 2935456.1 | H10: =SUM(H9) -> 3370711.7 | I10: =SUM(I9) -> 3338429.3 | J10: =SUM(J9) -> 3690653.5 | K10: =SUM(K9) -> 5160346.8 | ... T10: =SUM(T9) -> 15732588 | V10: =SUM(V9) -> 1.7298624e+08 | X10: =SUM(X9) -> 0 | Y10: =SUM(Y9) -> 0 | Z10: =SUM(Z9) -> 0 | AB10: =SUM(AB9) -> 0 | AC10: =IF(OR(AB10<0,Z10),AB10/Z10,0%) -> 0 | AD10: =SUM(AD9) -> 0
B12: Costos de Obra
B13: Seguridad e Higiene | D13: =IFERROR(SUM(VLOOKUP($B13&$C13,'C. Gestión Pto #1'!$B$4:C$17,MATCH(D$5,'C. Gestión Pto #1'!$B$4:C$4,0),FALSE),0),0) -> 0 | E13: =IFERROR(SUM(VLOOKUP($B13&$C13,'C. Gestión Pto #1'!$B$4:D$17,MATCH(E$5,'C. Gestión Pto #1'!$B$4:D$4,0),FALSE),0),0) -> 0 | F13: =IFERROR(SUM(VLOOKUP($B13&$C13,'C. Gestión Pto #1'!$B$4:E$17,MATCH(F$5,'C. Gestión Pto #1'!$B$4:E$4,0),FALSE),0),0) -> 964000 | G13: =IFERROR(SUM(VLOOKUP($B13&$C13,'C. Gestión Pto #1'!$B$4:F$17,MATCH(G$5,'C. Gestión Pto #1'!$B$4:F$4,0),FALSE),0),0) -> 1763514.1 | H13: =IFERROR(SUM(VLOOKUP($B13&$C13,'C. Gestión Pto #1'!$B$4:G$17,MATCH(H$5,'C. Gestión Pto #1'!$B$4:G$4,0),FALSE),0),0) -> 1757000 | I13: =IFERROR(SUM(VLOOKUP($B13&$C13,'C. Gestión Pto #1'!$B$4:H$17,MATCH(I$5,'C. Gestión Pto #1'!$B$4:H$4,0),FALSE),0),0) -> 1902500 | J13: =SUM(IFERROR(VLOOKUP($B13&$C13,'C. Gestión Pto #1'!$B$4:I$17,MATCH(J$5,'C. Gestión Pto #1'!$B$4:I$4,0),FALSE),0),IFERROR(VLOOKUP($B13&$C13,'C. Gestión Pto #2'!$B$4:C$23,MATCH(J$5,'C. Gestión Pto #2'!$B$4:C$4,0),FALSE),0)) -> 1961406 | K13: =SUM(IFERROR(VLOOKUP($B13&$C13,'C. Gestión Pto #1'!$B$4:J$17,MATCH(K$5,'C. Gestión Pto #1'!$B$4:J$4,0),FALSE),0),IFERROR(VLOOKUP($B13&$C13,'C. Gestión Pto #2'!$B$4:D$23,MATCH(K$5,'C. Gestión Pto #2'!$B$4:D$4,0),FALSE),0)) -> 1951450 | L13: =SUM(IFERROR(VLOOKUP($B13&$C13,'C. Gestión Pto #1'!$B$4:K$17,MATCH(L$5,'C. Gestión Pto #1'!$B$4:K$4,0),FALSE),0),IFERROR(VLOOKUP($B13&$C13,'C. Gestión Pto #2'!$B$4:E$23,MATCH(L$5,'C. Gestión Pto #2'!$B$4:E$4,0),FALSE),0)) -> 853846 | M13: =SUM(IFERROR(VLOOKUP($B13&$C13,'C. Gestión Pto #1'!$B$4:L$17,MATCH(M$5,'C. Gestión Pto #1'!$B$4:L$4,0),FALSE),0),IFERROR(VLOOKUP($B13&$C13,'C. Gestión Pto #2'!$B$4:F$23,MATCH(M$5,'C. Gestión Pto #2'!$B$4:F$4,0),FALSE),0)) -> 622493.01 | N13: =SUM(IFERROR(VLOOKUP($B13&$C13,'C. Gestión Pto #1'!$B$4:M$17,MATCH(N$5,'C. Gestión Pto #1'!$B$4:M$4,0),FALSE),0),IFERROR(VLOOKUP($B13&$C13,'C. Gestión Pto #2'!$B$4:G$23,MATCH(N$5,'C. Gestión Pto #2'!$B$4:G$4,0),FALSE),0)) -> 907500 | O13: =SUM(IFERROR(VLOOKUP($B13&$C13,'C. Gestión Pto #1'!$B$4:N$17,MATCH(O$5,'C. Gestión Pto #1'!$B$4:N$4,0),FALSE),0),IFERROR(VLOOKUP($B13&$C13,'C. Gestión Pto #2'!$B$4:H$23,MATCH(O$5,'C. Gestión Pto #2'!$B$4:H$4,0),FALSE),0)) -> 625825 | P13: =SUM(IFERROR(VLOOKUP($B13&$C13,'C. Gestión Pto #1'!$B$4:O$17,MATCH(P$5,'C. Gestión Pto #1'!$B$4:O$4,0),FALSE),0),IFERROR(VLOOKUP($B13&$C13,'C. Gestión Pto #2'!$B$4:I$23,MATCH(P$5,'C. Gestión Pto #2'!$B$4:I$4,0),FALSE),0)) -> 1020778 | Q13: =SUM(IFERROR(VLOOKUP($B13&$C13,'C. Gestión Pto #1'!$B$4:P$17,MATCH(Q$5,'C. Gestión Pto #1'!$B$4:P$4,0),FALSE),0),IFERROR(VLOOKUP($B13&$C13,'C. Gestión Pto #2'!$B$4:J$23,MATCH(Q$5,'C. Gestión Pto #2'!$B$4:J$4,0),FALSE),0)) -> 659001 | ... T13: =SUM(IFERROR(VLOOKUP($B13&$C13,'C. Gestión Pto #1'!$B$4:S$17,MATCH(T$5,'C. Gestión Pto #1'!$B$4:S$4,0),FALSE),0),IFERROR(VLOOKUP($B13&$C13,'C. Gestión Pto #2'!$B$4:M$23,MATCH(T$5,'C. Gestión Pto #2'!$B$4:M$4,0),FALSE),0)) -> 1407000 | V13: {=SUMPRODUCT($D13:$U13,TRANSPOSE('Indice CAC'!$C$10:$C$27))} -> 15129875 | X13: ='Resumen Pto #1'!X13 -> 7389505.4 | Y13: ='Resumen Pto #2'!R13 -> 900000 | Z13: =SUM(X13:Y13) -> 8289505.4 | AA13: =SUM(IF(C13="MAT",SUMIF('Pto. 01 Cert.'!$A$10:$A$57,$B13,'Pto. 01 Cert.'!$T$10:$T$57),IF(C13="MO",SUMIF('Pto. 01 Cert.'!$A$10:$A$57,$B13,'Pto. 01 Cert.'!$U$10:$U$57),SUMIF('Pto. 01 Cert.'!$A$10:$A$57,$B13,'Pto. 01 Cert.'!$V$10:$V$57))),IF(C13="MAT",SUMIF('Pto. 02 Cert.'!$A$10:$A$185,$B13,'Pto. 02 Cert.'!$T$10:$T$185),IF(C13="MO",SUMIF('Pto. 02 Cert.'!$A$10:$A$185,$B13,'Pto. 02 Cert.'!$U$10:$U$185),SUMIF('Pto. 02 Cert.'!$A$10:$A$185,$B13,'Pto. 02 Cert.'!$V$10:$V$185))))/SUM(IF(C13="MAT",SUMIF('Pto. 01 Cert.'!$A$10:$A$57,$B13,'Pto. 01 Cert.'!$I$10:$I$57),IF(C13="MO",SUMIF('Pto. 01 Cert.'!$A$10:$A$57,$B13,'Pto. 01 Cert.'!$J$10:$J$57),SUMIF('Pto. 01 Cert.'!$A$10:$A$57,$B13,'Pto. 01 Cert.'!$K$10:$K$57))),IF(C13="MAT",SUMIF('Pto. 02 Cert.'!$A$10:$A$185,$B13,'Pto. 02 Cert.'!$I$10:$I$185),IF(C13="MO",SUMIF('Pto. 02 Cert.'!$A$10:$A$185,$B13,'Pto. 02 Cert.'!$J$10:$J$185),SUMIF('Pto. 02 Cert.'!$A$10:$A$185,$B13,'Pto. 02 Cert.'!$K$10:$K$185)))) -> 0.94571437 | AB13: =IF(AA13=100%,0,IF(OR(V13<>0,Z13),Z13-V13)) -> -6840369.8 | AC13: =IF(OR(AB13<0,Z13),AB13/Z13,0%) -> -0.82518431 | AD13: =IF(AA13=100%,IF(OR(V13<>0,Z13),Z13-V13),0) -> 0
B14: Supervisión de Obra | D14: =IFERROR(SUM(VLOOKUP($B14&$C14,'C. Gestión Pto #1'!$B$4:C$17,MATCH(D$5,'C. Gestión Pto #1'!$B$4:C$4,0),FALSE),0),0) -> 2240048.4 | E14: =IFERROR(SUM(VLOOKUP($B14&$C14,'C. Gestión Pto #1'!$B$4:D$17,MATCH(E$5,'C. Gestión Pto #1'!$B$4:D$4,0),FALSE),0),0) -> 1806402.8 | F14: =IFERROR(SUM(VLOOKUP($B14&$C14,'C. Gestión Pto #1'!$B$4:E$17,MATCH(F$5,'C. Gestión Pto #1'!$B$4:E$4,0),FALSE),0),0) -> 2447085 | G14: =IFERROR(SUM(VLOOKUP($B14&$C14,'C. Gestión Pto #1'!$B$4:F$17,MATCH(G$5,'C. Gestión Pto #1'!$B$4:F$4,0),FALSE),0),0) -> 2817108 | H14: =IFERROR(SUM(VLOOKUP($B14&$C14,'C. Gestión Pto #1'!$B$4:G$17,MATCH(H$5,'C. Gestión Pto #1'!$B$4:G$4,0),FALSE),0),0) -> 2817108 | I14: =IFERROR(SUM(VLOOKUP($B14&$C14,'C. Gestión Pto #1'!$B$4:H$17,MATCH(I$5,'C. Gestión Pto #1'!$B$4:H$4,0),FALSE),0),0) -> 2987662.5 | J14: =SUM(IFERROR(VLOOKUP($B14&$C14,'C. Gestión Pto #1'!$B$4:I$17,MATCH(J$5,'C. Gestión Pto #1'!$B$4:I$4,0),FALSE),0),IFERROR(VLOOKUP($B14&$C14,'C. Gestión Pto #2'!$B$4:C$23,MATCH(J$5,'C. Gestión Pto #2'!$B$4:C$4,0),FALSE),0)) -> 3018848 | K14: =SUM(IFERROR(VLOOKUP($B14&$C14,'C. Gestión Pto #1'!$B$4:J$17,MATCH(K$5,'C. Gestión Pto #1'!$B$4:J$4,0),FALSE),0),IFERROR(VLOOKUP($B14&$C14,'C. Gestión Pto #2'!$B$4:D$23,MATCH(K$5,'C. Gestión Pto #2'!$B$4:D$4,0),FALSE),0)) -> 3253763 | L14: =SUM(IFERROR(VLOOKUP($B14&$C14,'C. Gestión Pto #1'!$B$4:K$17,MATCH(L$5,'C. Gestión Pto #1'!$B$4:K$4,0),FALSE),0),IFERROR(VLOOKUP($B14&$C14,'C. Gestión Pto #2'!$B$4:E$23,MATCH(L$5,'C. Gestión Pto #2'!$B$4:E$4,0),FALSE),0)) -> 3252503 | M14: =SUM(IFERROR(VLOOKUP($B14&$C14,'C. Gestión Pto #1'!$B$4:L$17,MATCH(M$5,'C. Gestión Pto #1'!$B$4:L$4,0),FALSE),0),IFERROR(VLOOKUP($B14&$C14,'C. Gestión Pto #2'!$B$4:F$23,MATCH(M$5,'C. Gestión Pto #2'!$B$4:F$4,0),FALSE),0)) -> 3374035.3 | N14: =SUM(IFERROR(VLOOKUP($B14&$C14,'C. Gestión Pto #1'!$B$4:M$17,MATCH(N$5,'C. Gestión Pto #1'!$B$4:M$4,0),FALSE),0),IFERROR(VLOOKUP($B14&$C14,'C. Gestión Pto #2'!$B$4:G$23,MATCH(N$5,'C. Gestión Pto #2'!$B$4:G$4,0),FALSE),0)) -> 3275352.8 | O14: =SUM(IFERROR(VLOOKUP($B14&$C14,'C. Gestión Pto #1'!$B$4:N$17,MATCH(O$5,'C. Gestión Pto #1'!$B$4:N$4,0),FALSE),0),IFERROR(VLOOKUP($B14&$C14,'C. Gestión Pto #2'!$B$4:H$23,MATCH(O$5,'C. Gestión Pto #2'!$B$4:H$4,0),FALSE),0)) -> 4921623.7 | P14: =SUM(IFERROR(VLOOKUP($B14&$C14,'C. Gestión Pto #1'!$B$4:O$17,MATCH(P$5,'C. Gestión Pto #1'!$B$4:O$4,0),FALSE),0),IFERROR(VLOOKUP($B14&$C14,'C. Gestión Pto #2'!$B$4:I$23,MATCH(P$5,'C. Gestión Pto #2'!$B$4:I$4,0),FALSE),0)) -> 3399806.5 | Q14: =SUM(IFERROR(VLOOKUP($B14&$C14,'C. Gestión Pto #1'!$B$4:P$17,MATCH(Q$5,'C. Gestión Pto #1'!$B$4:P$4,0),FALSE),0),IFERROR(VLOOKUP($B14&$C14,'C. Gestión Pto #2'!$B$4:J$23,MATCH(Q$5,'C. Gestión Pto #2'!$B$4:J$4,0),FALSE),0)) -> 3458743.6 | ... T14: =SUM(IFERROR(VLOOKUP($B14&$C14,'C. Gestión Pto #1'!$B$4:S$17,MATCH(T$5,'C. Gestión Pto #1'!$B$4:S$4,0),FALSE),0),IFERROR(VLOOKUP($B14&$C14,'C. Gestión Pto #2'!$B$4:M$23,MATCH(T$5,'C. Gestión Pto #2'!$B$4:M$4,0),FALSE),0)) -> 3838186.8 | V14: {=SUMPRODUCT($D14:$U14,TRANSPOSE('Indice CAC'!$C$10:$C$27))} -> 43333786 | X14: ='Resumen Pto #1'!X14 -> 30386965 | Y14: ='Resumen Pto #2'!R14 -> 22790223 | Z14: =SUM(X14:Y14) -> 53177188 | AA14: =SUM(IF(C14="MAT",SUMIF('Pto. 01 Cert.'!$A$10:$A$57,$B14,'Pto. 01 Cert.'!$T$10:$T$57),IF(C14="MO",SUMIF('Pto. 01 Cert.'!$A$10:$A$57,$B14,'Pto. 01 Cert.'!$U$10:$U$57),SUMIF('Pto. 01 Cert.'!$A$10:$A$57,$B14,'Pto. 01 Cert.'!$V$10:$V$57))),IF(C14="MAT",SUMIF('Pto. 02 Cert.'!$A$10:$A$185,$B14,'Pto. 02 Cert.'!$T$10:$T$185),IF(C14="MO",SUMIF('Pto. 02 Cert.'!$A$10:$A$185,$B14,'Pto. 02 Cert.'!$U$10:$U$185),SUMIF('Pto. 02 Cert.'!$A$10:$A$185,$B14,'Pto. 02 Cert.'!$V$10:$V$185))))/SUM(IF(C14="MAT",SUMIF('Pto. 01 Cert.'!$A$10:$A$57,$B14,'Pto. 01 Cert.'!$I$10:$I$57),IF(C14="MO",SUMIF('Pto. 01 Cert.'!$A$10:$A$57,$B14,'Pto. 01 Cert.'!$J$10:$J$57),SUMIF('Pto. 01 Cert.'!$A$10:$A$57,$B14,'Pto. 01 Cert.'!$K$10:$K$57))),IF(C14="MAT",SUMIF('Pto. 02 Cert.'!$A$10:$A$185,$B14,'Pto. 02 Cert.'!$I$10:$I$185),IF(C14="MO",SUMIF('Pto. 02 Cert.'!$A$10:$A$185,$B14,'Pto. 02 Cert.'!$J$10:$J$185),SUMIF('Pto. 02 Cert.'!$A$10:$A$185,$B14,'Pto. 02 Cert.'!$K$10:$K$185)))) -> 0.78571429 | AB14: =IF(AA14=100%,0,IF(OR(V14<>0,Z14),Z14-V14)) -> 9843402.5 | AC14: =IF(OR(AB14<0,Z14),AB14/Z14,0%) -> 0.18510574 | AD14: =IF(AA14=100%,IF(OR(V14<>0,Z14),Z14-V14),0) -> 0
B15: Movilidad | D15: =IFERROR(SUM(VLOOKUP($B15&$C15,'C. Gestión Pto #1'!$B$4:C$17,MATCH(D$5,'C. Gestión Pto #1'!$B$4:C$4,0),FALSE),0),0) -> 83133.29 | E15: =IFERROR(SUM(VLOOKUP($B15&$C15,'C. Gestión Pto #1'!$B$4:D$17,MATCH(E$5,'C. Gestión Pto #1'!$B$4:D$4,0),FALSE),0),0) -> 108153.67 | F15: =IFERROR(SUM(VLOOKUP($B15&$C15,'C. Gestión Pto #1'!$B$4:E$17,MATCH(F$5,'C. Gestión Pto #1'!$B$4:E$4,0),FALSE),0),0) -> 111838.73 | G15: =IFERROR(SUM(VLOOKUP($B15&$C15,'C. Gestión Pto #1'!$B$4:F$17,MATCH(G$5,'C. Gestión Pto #1'!$B$4:F$4,0),FALSE),0),0) -> 273194.46 | H15: =IFERROR(SUM(VLOOKUP($B15&$C15,'C. Gestión Pto #1'!$B$4:G$17,MATCH(H$5,'C. Gestión Pto #1'!$B$4:G$4,0),FALSE),0),0) -> 382880.04 | I15: =IFERROR(SUM(VLOOKUP($B15&$C15,'C. Gestión Pto #1'!$B$4:H$17,MATCH(I$5,'C. Gestión Pto #1'!$B$4:H$4,0),FALSE),0),0) -> 245052.89 | J15: =SUM(IFERROR(VLOOKUP($B15&$C15,'C. Gestión Pto #1'!$B$4:I$17,MATCH(J$5,'C. Gestión Pto #1'!$B$4:I$4,0),FALSE),0),IFERROR(VLOOKUP($B15&$C15,'C. Gestión Pto #2'!$B$4:C$23,MATCH(J$5,'C. Gestión Pto #2'!$B$4:C$4,0),FALSE),0)) -> 567556.66 | K15: =SUM(IFERROR(VLOOKUP($B15&$C15,'C. Gestión Pto #1'!$B$4:J$17,MATCH(K$5,'C. Gestión Pto #1'!$B$4:J$4,0),FALSE),0),IFERROR(VLOOKUP($B15&$C15,'C. Gestión Pto #2'!$B$4:D$23,MATCH(K$5,'C. Gestión Pto #2'!$B$4:D$4,0),FALSE),0)) -> 322994.82 | L15: =SUM(IFERROR(VLOOKUP($B15&$C15,'C. Gestión Pto #1'!$B$4:K$17,MATCH(L$5,'C. Gestión Pto #1'!$B$4:K$4,0),FALSE),0),IFERROR(VLOOKUP($B15&$C15,'C. Gestión Pto #2'!$B$4:E$23,MATCH(L$5,'C. Gestión Pto #2'!$B$4:E$4,0),FALSE),0)) -> 567394.82 | M15: =SUM(IFERROR(VLOOKUP($B15&$C15,'C. Gestión Pto #1'!$B$4:L$17,MATCH(M$5,'C. Gestión Pto #1'!$B$4:L$4,0),FALSE),0),IFERROR(VLOOKUP($B15&$C15,'C. Gestión Pto #2'!$B$4:F$23,MATCH(M$5,'C. Gestión Pto #2'!$B$4:F$4,0),FALSE),0)) -> 603374.92 | N15: =SUM(IFERROR(VLOOKUP($B15&$C15,'C. Gestión Pto #1'!$B$4:M$17,MATCH(N$5,'C. Gestión Pto #1'!$B$4:M$4,0),FALSE),0),IFERROR(VLOOKUP($B15&$C15,'C. Gestión Pto #2'!$B$4:G$23,MATCH(N$5,'C. Gestión Pto #2'!$B$4:G$4,0),FALSE),0)) -> 447563.68 | O15: =SUM(IFERROR(VLOOKUP($B15&$C15,'C. Gestión Pto #1'!$B$4:N$17,MATCH(O$5,'C. Gestión Pto #1'!$B$4:N$4,0),FALSE),0),IFERROR(VLOOKUP($B15&$C15,'C. Gestión Pto #2'!$B$4:H$23,MATCH(O$5,'C. Gestión Pto #2'!$B$4:H$4,0),FALSE),0)) -> 881403.34 | P15: =SUM(IFERROR(VLOOKUP($B15&$C15,'C. Gestión Pto #1'!$B$4:O$17,MATCH(P$5,'C. Gestión Pto #1'!$B$4:O$4,0),FALSE),0),IFERROR(VLOOKUP($B15&$C15,'C. Gestión Pto #2'!$B$4:I$23,MATCH(P$5,'C. Gestión Pto #2'!$B$4:I$4,0),FALSE),0)) -> 667797.87 | Q15: =SUM(IFERROR(VLOOKUP($B15&$C15,'C. Gestión Pto #1'!$B$4:P$17,MATCH(Q$5,'C. Gestión Pto #1'!$B$4:P$4,0),FALSE),0),IFERROR(VLOOKUP($B15&$C15,'C. Gestión Pto #2'!$B$4:J$23,MATCH(Q$5,'C. Gestión Pto #2'!$B$4:J$4,0),FALSE),0)) -> 1489831.9 | ... T15: =SUM(IFERROR(VLOOKUP($B15&$C15,'C. Gestión Pto #1'!$B$4:S$17,MATCH(T$5,'C. Gestión Pto #1'!$B$4:S$4,0),FALSE),0),IFERROR(VLOOKUP($B15&$C15,'C. Gestión Pto #2'!$B$4:M$23,MATCH(T$5,'C. Gestión Pto #2'!$B$4:M$4,0),FALSE),0)) -> 324436.07 | V15: {=SUMPRODUCT($D15:$U15,TRANSPOSE('Indice CAC'!$C$10:$C$27))} -> 6699010.2 | X15: ='Resumen Pto #1'!X15 -> 6000000 | Y15: ='Resumen Pto #2'!R15 -> 4500000 | Z15: =SUM(X15:Y15) -> 10500000 | AA15: =SUM(IF(C15="MAT",SUMIF('Pto. 01 Cert.'!$A$10:$A$57,$B15,'Pto. 01 Cert.'!$T$10:$T$57),IF(C15="MO",SUMIF('Pto. 01 Cert.'!$A$10:$A$57,$B15,'Pto. 01 Cert.'!$U$10:$U$57),SUMIF('Pto. 01 Cert.'!$A$10:$A$57,$B15,'Pto. 01 Cert.'!$V$10:$V$57))),IF(C15="MAT",SUMIF('Pto. 02 Cert.'!$A$10:$A$185,$B15,'Pto. 02 Cert.'!$T$10:$T$185),IF(C15="MO",SUMIF('Pto. 02 Cert.'!$A$10:$A$185,$B15,'Pto. 02 Cert.'!$U$10:$U$185),SUMIF('Pto. 02 Cert.'!$A$10:$A$185,$B15,'Pto. 02 Cert.'!$V$10:$V$185))))/SUM(IF(C15="MAT",SUMIF('Pto. 01 Cert.'!$A$10:$A$57,$B15,'Pto. 01 Cert.'!$I$10:$I$57),IF(C15="MO",SUMIF('Pto. 01 Cert.'!$A$10:$A$57,$B15,'Pto. 01 Cert.'!$J$10:$J$57),SUMIF('Pto. 01 Cert.'!$A$10:$A$57,$B15,'Pto. 01 Cert.'!$K$10:$K$57))),IF(C15="MAT",SUMIF('Pto. 02 Cert.'!$A$10:$A$185,$B15,'Pto. 02 Cert.'!$I$10:$I$185),IF(C15="MO",SUMIF('Pto. 02 Cert.'!$A$10:$A$185,$B15,'Pto. 02 Cert.'!$J$10:$J$185),SUMIF('Pto. 02 Cert.'!$A$10:$A$185,$B15,'Pto. 02 Cert.'!$K$10:$K$185)))) -> 0.77142857 | AB15: =IF(AA15=100%,0,IF(OR(V15<>0,Z15),Z15-V15)) -> 3800989.8 | AC15: =IF(OR(AB15<0,Z15),AB15/Z15,0%) -> 0.36199903 | AD15: =IF(AA15=100%,IF(OR(V15<>0,Z15),Z15-V15),0) -> 0
B16: Preliminares | D16: =IFERROR(SUM(VLOOKUP($B16&$C16,'C. Gestión Pto #1'!$B$4:C$17,MATCH(D$5,'C. Gestión Pto #1'!$B$4:C$4,0),FALSE),0),0) -> 0 | E16: =IFERROR(SUM(VLOOKUP($B16&$C16,'C. Gestión Pto #1'!$B$4:D$17,MATCH(E$5,'C. Gestión Pto #1'!$B$4:D$4,0),FALSE),0),0) -> 3076445.8 | F16: =IFERROR(SUM(VLOOKUP($B16&$C16,'C. Gestión Pto #1'!$B$4:E$17,MATCH(F$5,'C. Gestión Pto #1'!$B$4:E$4,0),FALSE),0),0) -> 4065955.3 | G16: =IFERROR(SUM(VLOOKUP($B16&$C16,'C. Gestión Pto #1'!$B$4:F$17,MATCH(G$5,'C. Gestión Pto #1'!$B$4:F$4,0),FALSE),0),0) -> 2170465.8 | H16: =IFERROR(SUM(VLOOKUP($B16&$C16,'C. Gestión Pto #1'!$B$4:G$17,MATCH(H$5,'C. Gestión Pto #1'!$B$4:G$4,0),FALSE),0),0) -> 452739.93 | I16: =IFERROR(SUM(VLOOKUP($B16&$C16,'C. Gestión Pto #1'!$B$4:H$17,MATCH(I$5,'C. Gestión Pto #1'!$B$4:H$4,0),FALSE),0),0) -> 333787.7 | J16: =SUM(IFERROR(VLOOKUP($B16&$C16,'C. Gestión Pto #1'!$B$4:I$17,MATCH(J$5,'C. Gestión Pto #1'!$B$4:I$4,0),FALSE),0),IFERROR(VLOOKUP($B16&$C16,'C. Gestión Pto #2'!$B$4:C$23,MATCH(J$5,'C. Gestión Pto #2'!$B$4:C$4,0),FALSE),0)) -> 0 | K16: =SUM(IFERROR(VLOOKUP($B16&$C16,'C. Gestión Pto #1'!$B$4:J$17,MATCH(K$5,'C. Gestión Pto #1'!$B$4:J$4,0),FALSE),0),IFERROR(VLOOKUP($B16&$C16,'C. Gestión Pto #2'!$B$4:D$23,MATCH(K$5,'C. Gestión Pto #2'!$B$4:D$4,0),FALSE),0)) -> 0 | L16: =SUM(IFERROR(VLOOKUP($B16&$C16,'C. Gestión Pto #1'!$B$4:K$17,MATCH(L$5,'C. Gestión Pto #1'!$B$4:K$4,0),FALSE),0),IFERROR(VLOOKUP($B16&$C16,'C. Gestión Pto #2'!$B$4:E$23,MATCH(L$5,'C. Gestión Pto #2'!$B$4:E$4,0),FALSE),0)) -> 0 | M16: =SUM(IFERROR(VLOOKUP($B16&$C16,'C. Gestión Pto #1'!$B$4:L$17,MATCH(M$5,'C. Gestión Pto #1'!$B$4:L$4,0),FALSE),0),IFERROR(VLOOKUP($B16&$C16,'C. Gestión Pto #2'!$B$4:F$23,MATCH(M$5,'C. Gestión Pto #2'!$B$4:F$4,0),FALSE),0)) -> 562822.2 | N16: =SUM(IFERROR(VLOOKUP($B16&$C16,'C. Gestión Pto #1'!$B$4:M$17,MATCH(N$5,'C. Gestión Pto #1'!$B$4:M$4,0),FALSE),0),IFERROR(VLOOKUP($B16&$C16,'C. Gestión Pto #2'!$B$4:G$23,MATCH(N$5,'C. Gestión Pto #2'!$B$4:G$4,0),FALSE),0)) -> 202741.83 | O16: =SUM(IFERROR(VLOOKUP($B16&$C16,'C. Gestión Pto #1'!$B$4:N$17,MATCH(O$5,'C. Gestión Pto #1'!$B$4:N$4,0),FALSE),0),IFERROR(VLOOKUP($B16&$C16,'C. Gestión Pto #2'!$B$4:H$23,MATCH(O$5,'C. Gestión Pto #2'!$B$4:H$4,0),FALSE),0)) -> 0 | P16: =SUM(IFERROR(VLOOKUP($B16&$C16,'C. Gestión Pto #1'!$B$4:O$17,MATCH(P$5,'C. Gestión Pto #1'!$B$4:O$4,0),FALSE),0),IFERROR(VLOOKUP($B16&$C16,'C. Gestión Pto #2'!$B$4:I$23,MATCH(P$5,'C. Gestión Pto #2'!$B$4:I$4,0),FALSE),0)) -> 0 | Q16: =SUM(IFERROR(VLOOKUP($B16&$C16,'C. Gestión Pto #1'!$B$4:P$17,MATCH(Q$5,'C. Gestión Pto #1'!$B$4:P$4,0),FALSE),0),IFERROR(VLOOKUP($B16&$C16,'C. Gestión Pto #2'!$B$4:J$23,MATCH(Q$5,'C. Gestión Pto #2'!$B$4:J$4,0),FALSE),0)) -> 0 | ... T16: =SUM(IFERROR(VLOOKUP($B16&$C16,'C. Gestión Pto #1'!$B$4:S$17,MATCH(T$5,'C. Gestión Pto #1'!$B$4:S$4,0),FALSE),0),IFERROR(VLOOKUP($B16&$C16,'C. Gestión Pto #2'!$B$4:M$23,MATCH(T$5,'C. Gestión Pto #2'!$B$4:M$4,0),FALSE),0)) -> 0 | V16: {=SUMPRODUCT($D16:$U16,TRANSPOSE('Indice CAC'!$C$10:$C$27))} -> 9642624.1 | X16: ='Resumen Pto #1'!X16 -> 9593785.3 | Y16: 0 | Z16: =SUM(X16:Y16) -> 9593785.3 | AA16: =IF(C16="MAT",SUMIF('Pto. 01 Cert.'!$A$10:$A$57,$B16,'Pto. 01 Cert.'!$T$10:$T$57),IF(C16="MO",SUMIF('Pto. 01 Cert.'!$A$10:$A$57,$B16,'Pto. 01 Cert.'!$U$10:$U$57),SUMIF('Pto. 01 Cert.'!$A$10:$A$57,$B16,'Pto. 01 Cert.'!$V$10:$V$57)))/IF(C16="MAT",SUMIF('Pto. 01 Cert.'!$A$10:$A$57,$B16,'Pto. 01 Cert.'!$I$10:$I$57),IF(C16="MO",SUMIF('Pto. 01 Cert.'!$A$10:$A$57,$B16,'Pto. 01 Cert.'!$J$10:$J$57),SUMIF('Pto. 01 Cert.'!$A$10:$A$57,$B16,'Pto. 01 Cert.'!$K$10:$K$57))) -> 1 | AB16: =IF(AA16=100%,0,IF(OR(V16<>0,Z16),Z16-V16)) -> 0 | AC16: =IF(OR(AB16<0,Z16),AB16/Z16,0%) -> 0 | AD16: =IF(AA16=100%,IF(OR(V16<>0,Z16),Z16-V16),0) -> -48838.787
B17: Depresion de napas | D17: =IFERROR(SUM(VLOOKUP($B17&$C17,'C. Gestión Pto #1'!$B$4:C$17,MATCH(D$5,'C. Gestión Pto #1'!$B$4:C$4,0),FALSE),0),0) -> 0 | E17: =IFERROR(SUM(VLOOKUP($B17&$C17,'C. Gestión Pto #1'!$B$4:D$17,MATCH(E$5,'C. Gestión Pto #1'!$B$4:D$4,0),FALSE),0),0) -> 3900000 | F17: =IFERROR(SUM(VLOOKUP($B17&$C17,'C. Gestión Pto #1'!$B$4:E$17,MATCH(F$5,'C. Gestión Pto #1'!$B$4:E$4,0),FALSE),0),0) -> 3900000 | G17: =IFERROR(SUM(VLOOKUP($B17&$C17,'C. Gestión Pto #1'!$B$4:F$17,MATCH(G$5,'C. Gestión Pto #1'!$B$4:F$4,0),FALSE),0),0) -> 0 | H17: =IFERROR(SUM(VLOOKUP($B17&$C17,'C. Gestión Pto #1'!$B$4:G$17,MATCH(H$5,'C. Gestión Pto #1'!$B$4:G$4,0),FALSE),0),0) -> 0 | I17: =IFERROR(SUM(VLOOKUP($B17&$C17,'C. Gestión Pto #1'!$B$4:H$17,MATCH(I$5,'C. Gestión Pto #1'!$B$4:H$4,0),FALSE),0),0) -> 0 | J17: =SUM(IFERROR(VLOOKUP($B17&$C17,'C. Gestión Pto #1'!$B$4:I$17,MATCH(J$5,'C. Gestión Pto #1'!$B$4:I$4,0),FALSE),0),IFERROR(VLOOKUP($B17&$C17,'C. Gestión Pto #2'!$B$4:C$23,MATCH(J$5,'C. Gestión Pto #2'!$B$4:C$4,0),FALSE),0)) -> 0 | K17: =SUM(IFERROR(VLOOKUP($B17&$C17,'C. Gestión Pto #1'!$B$4:J$17,MATCH(K$5,'C. Gestión Pto #1'!$B$4:J$4,0),FALSE),0),IFERROR(VLOOKUP($B17&$C17,'C. Gestión Pto #2'!$B$4:D$23,MATCH(K$5,'C. Gestión Pto #2'!$B$4:D$4,0),FALSE),0)) -> 0 | L17: =SUM(IFERROR(VLOOKUP($B17&$C17,'C. Gestión Pto #1'!$B$4:K$17,MATCH(L$5,'C. Gestión Pto #1'!$B$4:K$4,0),FALSE),0),IFERROR(VLOOKUP($B17&$C17,'C. Gestión Pto #2'!$B$4:E$23,MATCH(L$5,'C. Gestión Pto #2'!$B$4:E$4,0),FALSE),0)) -> 0 | M17: =SUM(IFERROR(VLOOKUP($B17&$C17,'C. Gestión Pto #1'!$B$4:L$17,MATCH(M$5,'C. Gestión Pto #1'!$B$4:L$4,0),FALSE),0),IFERROR(VLOOKUP($B17&$C17,'C. Gestión Pto #2'!$B$4:F$23,MATCH(M$5,'C. Gestión Pto #2'!$B$4:F$4,0),FALSE),0)) -> 0 | N17: =SUM(IFERROR(VLOOKUP($B17&$C17,'C. Gestión Pto #1'!$B$4:M$17,MATCH(N$5,'C. Gestión Pto #1'!$B$4:M$4,0),FALSE),0),IFERROR(VLOOKUP($B17&$C17,'C. Gestión Pto #2'!$B$4:G$23,MATCH(N$5,'C. Gestión Pto #2'!$B$4:G$4,0),FALSE),0)) -> 0 | O17: =SUM(IFERROR(VLOOKUP($B17&$C17,'C. Gestión Pto #1'!$B$4:N$17,MATCH(O$5,'C. Gestión Pto #1'!$B$4:N$4,0),FALSE),0),IFERROR(VLOOKUP($B17&$C17,'C. Gestión Pto #2'!$B$4:H$23,MATCH(O$5,'C. Gestión Pto #2'!$B$4:H$4,0),FALSE),0)) -> 0 | P17: =SUM(IFERROR(VLOOKUP($B17&$C17,'C. Gestión Pto #1'!$B$4:O$17,MATCH(P$5,'C. Gestión Pto #1'!$B$4:O$4,0),FALSE),0),IFERROR(VLOOKUP($B17&$C17,'C. Gestión Pto #2'!$B$4:I$23,MATCH(P$5,'C. Gestión Pto #2'!$B$4:I$4,0),FALSE),0)) -> 0 | Q17: =SUM(IFERROR(VLOOKUP($B17&$C17,'C. Gestión Pto #1'!$B$4:P$17,MATCH(Q$5,'C. Gestión Pto #1'!$B$4:P$4,0),FALSE),0),IFERROR(VLOOKUP($B17&$C17,'C. Gestión Pto #2'!$B$4:J$23,MATCH(Q$5,'C. Gestión Pto #2'!$B$4:J$4,0),FALSE),0)) -> 0 | ... T17: =SUM(IFERROR(VLOOKUP($B17&$C17,'C. Gestión Pto #1'!$B$4:S$17,MATCH(T$5,'C. Gestión Pto #1'!$B$4:S$4,0),FALSE),0),IFERROR(VLOOKUP($B17&$C17,'C. Gestión Pto #2'!$B$4:M$23,MATCH(T$5,'C. Gestión Pto #2'!$B$4:M$4,0),FALSE),0)) -> 0 | V17: {=SUMPRODUCT($D17:$U17,TRANSPOSE('Indice CAC'!$C$10:$C$27))} -> 7037477 | X17: ='Resumen Pto #1'!X17 -> 7800000 | Y17: 0 | Z17: =SUM(X17:Y17) -> 7800000 | AA17: =IF(C17="MAT",SUMIF('Pto. 01 Cert.'!$A$10:$A$57,$B17,'Pto. 01 Cert.'!$T$10:$T$57),IF(C17="MO",SUMIF('Pto. 01 Cert.'!$A$10:$A$57,$B17,'Pto. 01 Cert.'!$U$10:$U$57),SUMIF('Pto. 01 Cert.'!$A$10:$A$57,$B17,'Pto. 01 Cert.'!$V$10:$V$57)))/IF(C17="MAT",SUMIF('Pto. 01 Cert.'!$A$10:$A$57,$B17,'Pto. 01 Cert.'!$I$10:$I$57),IF(C17="MO",SUMIF('Pto. 01 Cert.'!$A$10:$A$57,$B17,'Pto. 01 Cert.'!$J$10:$J$57),SUMIF('Pto. 01 Cert.'!$A$10:$A$57,$B17,'Pto. 01 Cert.'!$K$10:$K$57))) -> 1 | AB17: =IF(AA17=100%,0,IF(OR(V17<>0,Z17),Z17-V17)) -> 0 | AC17: =IF(OR(AB17<0,Z17),AB17/Z17,0%) -> 0 | AD17: =IF(AA17=100%,IF(OR(V17<>0,Z17),Z17-V17),0) -> 762523.04
B18: Agrimensura | D18: =IFERROR(SUM(VLOOKUP($B18&$C18,'C. Gestión Pto #1'!$B$4:C$17,MATCH(D$5,'C. Gestión Pto #1'!$B$4:C$4,0),FALSE),0),0) -> 150000 | E18: =IFERROR(SUM(VLOOKUP($B18&$C18,'C. Gestión Pto #1'!$B$4:D$17,MATCH(E$5,'C. Gestión Pto #1'!$B$4:D$4,0),FALSE),0),0) -> 0 | F18: =IFERROR(SUM(VLOOKUP($B18&$C18,'C. Gestión Pto #1'!$B$4:E$17,MATCH(F$5,'C. Gestión Pto #1'!$B$4:E$4,0),FALSE),0),0) -> 150000 | G18: =IFERROR(SUM(VLOOKUP($B18&$C18,'C. Gestión Pto #1'!$B$4:F$17,MATCH(G$5,'C. Gestión Pto #1'!$B$4:F$4,0),FALSE),0),0) -> 0 | H18: =IFERROR(SUM(VLOOKUP($B18&$C18,'C. Gestión Pto #1'!$B$4:G$17,MATCH(H$5,'C. Gestión Pto #1'!$B$4:G$4,0),FALSE),0),0) -> 0 | I18: =IFERROR(SUM(VLOOKUP($B18&$C18,'C. Gestión Pto #1'!$B$4:H$17,MATCH(I$5,'C. Gestión Pto #1'!$B$4:H$4,0),FALSE),0),0) -> 0 | J18: =SUM(IFERROR(VLOOKUP($B18&$C18,'C. Gestión Pto #1'!$B$4:I$17,MATCH(J$5,'C. Gestión Pto #1'!$B$4:I$4,0),FALSE),0),IFERROR(VLOOKUP($B18&$C18,'C. Gestión Pto #2'!$B$4:C$23,MATCH(J$5,'C. Gestión Pto #2'!$B$4:C$4,0),FALSE),0)) -> 0 | K18: =SUM(IFERROR(VLOOKUP($B18&$C18,'C. Gestión Pto #1'!$B$4:J$17,MATCH(K$5,'C. Gestión Pto #1'!$B$4:J$4,0),FALSE),0),IFERROR(VLOOKUP($B18&$C18,'C. Gestión Pto #2'!$B$4:D$23,MATCH(K$5,'C. Gestión Pto #2'!$B$4:D$4,0),FALSE),0)) -> 0 | L18: =SUM(IFERROR(VLOOKUP($B18&$C18,'C. Gestión Pto #1'!$B$4:K$17,MATCH(L$5,'C. Gestión Pto #1'!$B$4:K$4,0),FALSE),0),IFERROR(VLOOKUP($B18&$C18,'C. Gestión Pto #2'!$B$4:E$23,MATCH(L$5,'C. Gestión Pto #2'!$B$4:E$4,0),FALSE),0)) -> 0 | M18: =SUM(IFERROR(VLOOKUP($B18&$C18,'C. Gestión Pto #1'!$B$4:L$17,MATCH(M$5,'C. Gestión Pto #1'!$B$4:L$4,0),FALSE),0),IFERROR(VLOOKUP($B18&$C18,'C. Gestión Pto #2'!$B$4:F$23,MATCH(M$5,'C. Gestión Pto #2'!$B$4:F$4,0),FALSE),0)) -> 0 | N18: =SUM(IFERROR(VLOOKUP($B18&$C18,'C. Gestión Pto #1'!$B$4:M$17,MATCH(N$5,'C. Gestión Pto #1'!$B$4:M$4,0),FALSE),0),IFERROR(VLOOKUP($B18&$C18,'C. Gestión Pto #2'!$B$4:G$23,MATCH(N$5,'C. Gestión Pto #2'!$B$4:G$4,0),FALSE),0)) -> 0 | O18: =SUM(IFERROR(VLOOKUP($B18&$C18,'C. Gestión Pto #1'!$B$4:N$17,MATCH(O$5,'C. Gestión Pto #1'!$B$4:N$4,0),FALSE),0),IFERROR(VLOOKUP($B18&$C18,'C. Gestión Pto #2'!$B$4:H$23,MATCH(O$5,'C. Gestión Pto #2'!$B$4:H$4,0),FALSE),0)) -> 0 | P18: =SUM(IFERROR(VLOOKUP($B18&$C18,'C. Gestión Pto #1'!$B$4:O$17,MATCH(P$5,'C. Gestión Pto #1'!$B$4:O$4,0),FALSE),0),IFERROR(VLOOKUP($B18&$C18,'C. Gestión Pto #2'!$B$4:I$23,MATCH(P$5,'C. Gestión Pto #2'!$B$4:I$4,0),FALSE),0)) -> 0 | Q18: =SUM(IFERROR(VLOOKUP($B18&$C18,'C. Gestión Pto #1'!$B$4:P$17,MATCH(Q$5,'C. Gestión Pto #1'!$B$4:P$4,0),FALSE),0),IFERROR(VLOOKUP($B18&$C18,'C. Gestión Pto #2'!$B$4:J$23,MATCH(Q$5,'C. Gestión Pto #2'!$B$4:J$4,0),FALSE),0)) -> 0 | ... T18: =SUM(IFERROR(VLOOKUP($B18&$C18,'C. Gestión Pto #1'!$B$4:S$17,MATCH(T$5,'C. Gestión Pto #1'!$B$4:S$4,0),FALSE),0),IFERROR(VLOOKUP($B18&$C18,'C. Gestión Pto #2'!$B$4:M$23,MATCH(T$5,'C. Gestión Pto #2'!$B$4:M$4,0),FALSE),0)) -> 0 | V18: {=SUMPRODUCT($D18:$U18,TRANSPOSE('Indice CAC'!$C$10:$C$27))} -> 272938.14 | X18: ='Resumen Pto #1'!X18 -> 892630.81 | Y18: 0 | Z18: =SUM(X18:Y18) -> 892630.81 | AA18: =IF(C18="MAT",SUMIF('Pto. 01 Cert.'!$A$10:$A$57,$B18,'Pto. 01 Cert.'!$T$10:$T$57),IF(C18="MO",SUMIF('Pto. 01 Cert.'!$A$10:$A$57,$B18,'Pto. 01 Cert.'!$U$10:$U$57),SUMIF('Pto. 01 Cert.'!$A$10:$A$57,$B18,'Pto. 01 Cert.'!$V$10:$V$57)))/IF(C18="MAT",SUMIF('Pto. 01 Cert.'!$A$10:$A$57,$B18,'Pto. 01 Cert.'!$I$10:$I$57),IF(C18="MO",SUMIF('Pto. 01 Cert.'!$A$10:$A$57,$B18,'Pto. 01 Cert.'!$J$10:$J$57),SUMIF('Pto. 01 Cert.'!$A$10:$A$57,$B18,'Pto. 01 Cert.'!$K$10:$K$57))) -> 1 | AB18: =IF(AA18=100%,0,IF(OR(V18<>0,Z18),Z18-V18)) -> 0 | AC18: =IF(OR(AB18<0,Z18),AB18/Z18,0%) -> 0 | AD18: =IF(AA18=100%,IF(OR(V18<>0,Z18),Z18-V18),0) -> 619692.67
B19: Excavación y Mov. de Suelos | D19: =IFERROR(SUM(VLOOKUP($B19&$C19,'C. Gestión Pto #1'!$B$4:C$17,MATCH(D$5,'C. Gestión Pto #1'!$B$4:C$4,0),FALSE),0),0) -> 0 | E19: =IFERROR(SUM(VLOOKUP($B19&$C19,'C. Gestión Pto #1'!$B$4:D$17,MATCH(E$5,'C. Gestión Pto #1'!$B$4:D$4,0),FALSE),0),0) -> 2555627 | F19: =IFERROR(SUM(VLOOKUP($B19&$C19,'C. Gestión Pto #1'!$B$4:E$17,MATCH(F$5,'C. Gestión Pto #1'!$B$4:E$4,0),FALSE),0),0) -> 0 | G19: =IFERROR(SUM(VLOOKUP($B19&$C19,'C. Gestión Pto #1'!$B$4:F$17,MATCH(G$5,'C. Gestión Pto #1'!$B$4:F$4,0),FALSE),0),0) -> 5000000 | H19: =IFERROR(SUM(VLOOKUP($B19&$C19,'C. Gestión Pto #1'!$B$4:G$17,MATCH(H$5,'C. Gestión Pto #1'!$B$4:G$4,0),FALSE),0),0) -> 5000000 | I19: =IFERROR(SUM(VLOOKUP($B19&$C19,'C. Gestión Pto #1'!$B$4:H$17,MATCH(I$5,'C. Gestión Pto #1'!$B$4:H$4,0),FALSE),0),0) -> 5812500 | J19: =SUM(IFERROR(VLOOKUP($B19&$C19,'C. Gestión Pto #1'!$B$4:I$17,MATCH(J$5,'C. Gestión Pto #1'!$B$4:I$4,0),FALSE),0),IFERROR(VLOOKUP($B19&$C19,'C. Gestión Pto #2'!$B$4:C$23,MATCH(J$5,'C. Gestión Pto #2'!$B$4:C$4,0),FALSE),0)) -> 0 | K19: =SUM(IFERROR(VLOOKUP($B19&$C19,'C. Gestión Pto #1'!$B$4:J$17,MATCH(K$5,'C. Gestión Pto #1'!$B$4:J$4,0),FALSE),0),IFERROR(VLOOKUP($B19&$C19,'C. Gestión Pto #2'!$B$4:D$23,MATCH(K$5,'C. Gestión Pto #2'!$B$4:D$4,0),FALSE),0)) -> 6430886.4 | L19: =SUM(IFERROR(VLOOKUP($B19&$C19,'C. Gestión Pto #1'!$B$4:K$17,MATCH(L$5,'C. Gestión Pto #1'!$B$4:K$4,0),FALSE),0),IFERROR(VLOOKUP($B19&$C19,'C. Gestión Pto #2'!$B$4:E$23,MATCH(L$5,'C. Gestión Pto #2'!$B$4:E$4,0),FALSE),0)) -> 0 | M19: =SUM(IFERROR(VLOOKUP($B19&$C19,'C. Gestión Pto #1'!$B$4:L$17,MATCH(M$5,'C. Gestión Pto #1'!$B$4:L$4,0),FALSE),0),IFERROR(VLOOKUP($B19&$C19,'C. Gestión Pto #2'!$B$4:F$23,MATCH(M$5,'C. Gestión Pto #2'!$B$4:F$4,0),FALSE),0)) -> 0 | N19: =SUM(IFERROR(VLOOKUP($B19&$C19,'C. Gestión Pto #1'!$B$4:M$17,MATCH(N$5,'C. Gestión Pto #1'!$B$4:M$4,0),FALSE),0),IFERROR(VLOOKUP($B19&$C19,'C. Gestión Pto #2'!$B$4:G$23,MATCH(N$5,'C. Gestión Pto #2'!$B$4:G$4,0),FALSE),0)) -> 0 | O19: =SUM(IFERROR(VLOOKUP($B19&$C19,'C. Gestión Pto #1'!$B$4:N$17,MATCH(O$5,'C. Gestión Pto #1'!$B$4:N$4,0),FALSE),0),IFERROR(VLOOKUP($B19&$C19,'C. Gestión Pto #2'!$B$4:H$23,MATCH(O$5,'C. Gestión Pto #2'!$B$4:H$4,0),FALSE),0)) -> 0 | P19: =SUM(IFERROR(VLOOKUP($B19&$C19,'C. Gestión Pto #1'!$B$4:O$17,MATCH(P$5,'C. Gestión Pto #1'!$B$4:O$4,0),FALSE),0),IFERROR(VLOOKUP($B19&$C19,'C. Gestión Pto #2'!$B$4:I$23,MATCH(P$5,'C. Gestión Pto #2'!$B$4:I$4,0),FALSE),0)) -> 0 | Q19: =SUM(IFERROR(VLOOKUP($B19&$C19,'C. Gestión Pto #1'!$B$4:P$17,MATCH(Q$5,'C. Gestión Pto #1'!$B$4:P$4,0),FALSE),0),IFERROR(VLOOKUP($B19&$C19,'C. Gestión Pto #2'!$B$4:J$23,MATCH(Q$5,'C. Gestión Pto #2'!$B$4:J$4,0),FALSE),0)) -> 0 | ... T19: =SUM(IFERROR(VLOOKUP($B19&$C19,'C. Gestión Pto #1'!$B$4:S$17,MATCH(T$5,'C. Gestión Pto #1'!$B$4:S$4,0),FALSE),0),IFERROR(VLOOKUP($B19&$C19,'C. Gestión Pto #2'!$B$4:M$23,MATCH(T$5,'C. Gestión Pto #2'!$B$4:M$4,0),FALSE),0)) -> 0 | V19: {=SUMPRODUCT($D19:$U19,TRANSPOSE('Indice CAC'!$C$10:$C$27))} -> 21476728 | X19: ='Resumen Pto #1'!X19 -> 23294400 | Y19: 0 | Z19: =SUM(X19:Y19) -> 23294400 | AA19: =IF(C19="MAT",SUMIF('Pto. 01 Cert.'!$A$10:$A$57,$B19,'Pto. 01 Cert.'!$T$10:$T$57),IF(C19="MO",SUMIF('Pto. 01 Cert.'!$A$10:$A$57,$B19,'Pto. 01 Cert.'!$U$10:$U$57),SUMIF('Pto. 01 Cert.'!$A$10:$A$57,$B19,'Pto. 01 Cert.'!$V$10:$V$57)))/IF(C19="MAT",SUMIF('Pto. 01 Cert.'!$A$10:$A$57,$B19,'Pto. 01 Cert.'!$I$10:$I$57),IF(C19="MO",SUMIF('Pto. 01 Cert.'!$A$10:$A$57,$B19,'Pto. 01 Cert.'!$J$10:$J$57),SUMIF('Pto. 01 Cert.'!$A$10:$A$57,$B19,'Pto. 01 Cert.'!$K$10:$K$57))) -> 1 | AB19: =IF(AA19=100%,0,IF(OR(V19<>0,Z19),Z19-V19)) -> 0 | AC19: =IF(OR(AB19<0,Z19),AB19/Z19,0%) -> 0 | AD19: =IF(AA19=100%,IF(OR(V19<>0,Z19),Z19-V19),0) -> 1817672.1
B20: Hormigón | C20: MAT | D20: =IFERROR(SUM(VLOOKUP($B20&$C20,'C. Gestión Pto #1'!$B$4:C$17,MATCH(D$5,'C. Gestión Pto #1'!$B$4:C$4,0),FALSE),0),0) -> 0 | E20: =IFERROR(SUM(VLOOKUP($B20&$C20,'C. Gestión Pto #1'!$B$4:D$17,MATCH(E$5,'C. Gestión Pto #1'!$B$4:D$4,0),FALSE),0),0) -> 7421307.2 | F20: =IFERROR(SUM(VLOOKUP($B20&$C20,'C. Gestión Pto #1'!$B$4:E$17,MATCH(F$5,'C. Gestión Pto #1'!$B$4:E$4,0),FALSE),0),0) -> 934481.37 | G20: =IFERROR(SUM(VLOOKUP($B20&$C20,'C. Gestión Pto #1'!$B$4:F$17,MATCH(G$5,'C. Gestión Pto #1'!$B$4:F$4,0),FALSE),0),0) -> 6221403.1 | H20: =IFERROR(SUM(VLOOKUP($B20&$C20,'C. Gestión Pto #1'!$B$4:G$17,MATCH(H$5,'C. Gestión Pto #1'!$B$4:G$4,0),FALSE),0),0) -> 3385750.4 | I20: =IFERROR(SUM(VLOOKUP($B20&$C20,'C. Gestión Pto #1'!$B$4:H$17,MATCH(I$5,'C. Gestión Pto #1'!$B$4:H$4,0),FALSE),0),0) -> 3530590.8 | J20: =SUM(IFERROR(VLOOKUP($B20&$C20,'C. Gestión Pto #1'!$B$4:I$17,MATCH(J$5,'C. Gestión Pto #1'!$B$4:I$4,0),FALSE),0),IFERROR(VLOOKUP($B20&$C20,'C. Gestión Pto #2'!$B$4:C$23,MATCH(J$5,'C. Gestión Pto #2'!$B$4:C$4,0),FALSE),0)) -> 0 | K20: =SUM(IFERROR(VLOOKUP($B20&$C20,'C. Gestión Pto #1'!$B$4:J$17,MATCH(K$5,'C. Gestión Pto #1'!$B$4:J$4,0),FALSE),0),IFERROR(VLOOKUP($B20&$C20,'C. Gestión Pto #2'!$B$4:D$23,MATCH(K$5,'C. Gestión Pto #2'!$B$4:D$4,0),FALSE),0)) -> 3744037.3 | L20: =SUM(IFERROR(VLOOKUP($B20&$C20,'C. Gestión Pto #1'!$B$4:K$17,MATCH(L$5,'C. Gestión Pto #1'!$B$4:K$4,0),FALSE),0),IFERROR(VLOOKUP($B20&$C20,'C. Gestión Pto #2'!$B$4:E$23,MATCH(L$5,'C. Gestión Pto #2'!$B$4:E$4,0),FALSE),0)) -> 1646601.2 | M20: =SUM(IFERROR(VLOOKUP($B20&$C20,'C. Gestión Pto #1'!$B$4:L$17,MATCH(M$5,'C. Gestión Pto #1'!$B$4:L$4,0),FALSE),0),IFERROR(VLOOKUP($B20&$C20,'C. Gestión Pto #2'!$B$4:F$23,MATCH(M$5,'C. Gestión Pto #2'!$B$4:F$4,0),FALSE),0)) -> 4258986.7 | N20: =SUM(IFERROR(VLOOKUP($B20&$C20,'C. Gestión Pto #1'!$B$4:M$17,MATCH(N$5,'C. Gestión Pto #1'!$B$4:M$4,0),FALSE),0),IFERROR(VLOOKUP($B20&$C20,'C. Gestión Pto #2'!$B$4:G$23,MATCH(N$5,'C. Gestión Pto #2'!$B$4:G$4,0),FALSE),0)) -> 1572093.6 | O20: =SUM(IFERROR(VLOOKUP($B20&$C20,'C. Gestión Pto #1'!$B$4:N$17,MATCH(O$5,'C. Gestión Pto #1'!$B$4:N$4,0),FALSE),0),IFERROR(VLOOKUP($B20&$C20,'C. Gestión Pto #2'!$B$4:H$23,MATCH(O$5,'C. Gestión Pto #2'!$B$4:H$4,0),FALSE),0)) -> 190000 | P20: =SUM(IFERROR(VLOOKUP($B20&$C20,'C. Gestión Pto #1'!$B$4:O$17,MATCH(P$5,'C. Gestión Pto #1'!$B$4:O$4,0),FALSE),0),IFERROR(VLOOKUP($B20&$C20,'C. Gestión Pto #2'!$B$4:I$23,MATCH(P$5,'C. Gestión Pto #2'!$B$4:I$4,0),FALSE),0)) -> 475000 | Q20: =SUM(IFERROR(VLOOKUP($B20&$C20,'C. Gestión Pto #1'!$B$4:P$17,MATCH(Q$5,'C. Gestión Pto #1'!$B$4:P$4,0),FALSE),0),IFERROR(VLOOKUP($B20&$C20,'C. Gestión Pto #2'!$B$4:J$23,MATCH(Q$5,'C. Gestión Pto #2'!$B$4:J$4,0),FALSE),0)) -> 0 | ... T20: =SUM(IFERROR(VLOOKUP($B20&$C20,'C. Gestión Pto #1'!$B$4:S$17,MATCH(T$5,'C. Gestión Pto #1'!$B$4:S$4,0),FALSE),0),IFERROR(VLOOKUP($B20&$C20,'C. Gestión Pto #2'!$B$4:M$23,MATCH(T$5,'C. Gestión Pto #2'!$B$4:M$4,0),FALSE),0)) -> 0 | V20: {=SUMPRODUCT($D20:$U20,TRANSPOSE('Indice CAC'!$C$10:$C$27))} -> 28825229 | X20: ='Resumen Pto #1'!X20 -> 39767922 | Y20: 0 | Z20: =SUM(X20:Y20) -> 39767922 | AA20: =IF(C20="MAT",SUMIF('Pto. 01 Cert.'!$A$10:$A$57,$B20,'Pto. 01 Cert.'!$T$10:$T$57),IF(C20="MO",SUMIF('Pto. 01 Cert.'!$A$10:$A$57,$B20,'Pto. 01 Cert.'!$U$10:$U$57),SUMIF('Pto. 01 Cert.'!$A$10:$A$57,$B20,'Pto. 01 Cert.'!$V$10:$V$57)))/IF(C20="MAT",SUMIF('Pto. 01 Cert.'!$A$10:$A$57,$B20,'Pto. 01 Cert.'!$I$10:$I$57),IF(C20="MO",SUMIF('Pto. 01 Cert.'!$A$10:$A$57,$B20,'Pto. 01 Cert.'!$J$10:$J$57),SUMIF('Pto. 01 Cert.'!$A$10:$A$57,$B20,'Pto. 01 Cert.'!$K$10:$K$57))) -> 1 | AB20: =IF(AA20=100%,0,IF(OR(V20<>0,Z20),Z20-V20)) -> 0 | AC20: =IF(OR(AB20<0,Z20),AB20/Z20,0%) -> 0 | AD20: =IF(AA20=100%,IF(OR(V20<>0,Z20),Z20-V20),0) -> 10942694
B21: Hormigón | C21: MO | D21: =IFERROR(SUM(VLOOKUP($B21&$C21,'C. Gestión Pto #1'!$B$4:C$17,MATCH(D$5,'C. Gestión Pto #1'!$B$4:C$4,0),FALSE),0),0) -> 0 | E21: =IFERROR(SUM(VLOOKUP($B21&$C21,'C. Gestión Pto #1'!$B$4:D$17,MATCH(E$5,'C. Gestión Pto #1'!$B$4:D$4,0),FALSE),0),0) -> 0 | F21: =IFERROR(SUM(VLOOKUP($B21&$C21,'C. Gestión Pto #1'!$B$4:E$17,MATCH(F$5,'C. Gestión Pto #1'!$B$4:E$4,0),FALSE),0),0) -> 2102991.6 | G21: =IFERROR(SUM(VLOOKUP($B21&$C21,'C. Gestión Pto #1'!$B$4:F$17,MATCH(G$5,'C. Gestión Pto #1'!$B$4:F$4,0),FALSE),0),0) -> 17862837 | H21: =IFERROR(SUM(VLOOKUP($B21&$C21,'C. Gestión Pto #1'!$B$4:G$17,MATCH(H$5,'C. Gestión Pto #1'!$B$4:G$4,0),FALSE),0),0) -> 18399394 | I21: =IFERROR(SUM(VLOOKUP($B21&$C21,'C. Gestión Pto #1'!$B$4:H$17,MATCH(I$5,'C. Gestión Pto #1'!$B$4:H$4,0),FALSE),0),0) -> 21489375 | J21: =SUM(IFERROR(VLOOKUP($B21&$C21,'C. Gestión Pto #1'!$B$4:I$17,MATCH(J$5,'C. Gestión Pto #1'!$B$4:I$4,0),FALSE),0),IFERROR(VLOOKUP($B21&$C21,'C. Gestión Pto #2'!$B$4:C$23,MATCH(J$5,'C. Gestión Pto #2'!$B$4:C$4,0),FALSE),0)) -> 26401198 | K21: =SUM(IFERROR(VLOOKUP($B21&$C21,'C. Gestión Pto #1'!$B$4:J$17,MATCH(K$5,'C. Gestión Pto #1'!$B$4:J$4,0),FALSE),0),IFERROR(VLOOKUP($B21&$C21,'C. Gestión Pto #2'!$B$4:D$23,MATCH(K$5,'C. Gestión Pto #2'!$B$4:D$4,0),FALSE),0)) -> 22702901 | L21: =SUM(IFERROR(VLOOKUP($B21&$C21,'C. Gestión Pto #1'!$B$4:K$17,MATCH(L$5,'C. Gestión Pto #1'!$B$4:K$4,0),FALSE),0),IFERROR(VLOOKUP($B21&$C21,'C. Gestión Pto #2'!$B$4:E$23,MATCH(L$5,'C. Gestión Pto #2'!$B$4:E$4,0),FALSE),0)) -> 26719160 | M21: =SUM(IFERROR(VLOOKUP($B21&$C21,'C. Gestión Pto #1'!$B$4:L$17,MATCH(M$5,'C. Gestión Pto #1'!$B$4:L$4,0),FALSE),0),IFERROR(VLOOKUP($B21&$C21,'C. Gestión Pto #2'!$B$4:F$23,MATCH(M$5,'C. Gestión Pto #2'!$B$4:F$4,0),FALSE),0)) -> 31168841 | N21: =SUM(IFERROR(VLOOKUP($B21&$C21,'C. Gestión Pto #1'!$B$4:M$17,MATCH(N$5,'C. Gestión Pto #1'!$B$4:M$4,0),FALSE),0),IFERROR(VLOOKUP($B21&$C21,'C. Gestión Pto #2'!$B$4:G$23,MATCH(N$5,'C. Gestión Pto #2'!$B$4:G$4,0),FALSE),0)) -> 30645862 | O21: =SUM(IFERROR(VLOOKUP($B21&$C21,'C. Gestión Pto #1'!$B$4:N$17,MATCH(O$5,'C. Gestión Pto #1'!$B$4:N$4,0),FALSE),0),IFERROR(VLOOKUP($B21&$C21,'C. Gestión Pto #2'!$B$4:H$23,MATCH(O$5,'C. Gestión Pto #2'!$B$4:H$4,0),FALSE),0)) -> 29665403 | P21: =SUM(IFERROR(VLOOKUP($B21&$C21,'C. Gestión Pto #1'!$B$4:O$17,MATCH(P$5,'C. Gestión Pto #1'!$B$4:O$4,0),FALSE),0),IFERROR(VLOOKUP($B21&$C21,'C. Gestión Pto #2'!$B$4:I$23,MATCH(P$5,'C. Gestión Pto #2'!$B$4:I$4,0),FALSE),0)) -> 26268531 | Q21: =SUM(IFERROR(VLOOKUP($B21&$C21,'C. Gestión Pto #1'!$B$4:P$17,MATCH(Q$5,'C. Gestión Pto #1'!$B$4:P$4,0),FALSE),0),IFERROR(VLOOKUP($B21&$C21,'C. Gestión Pto #2'!$B$4:J$23,MATCH(Q$5,'C. Gestión Pto #2'!$B$4:J$4,0),FALSE),0)) -> 17271364 | ... T21: =SUM(IFERROR(VLOOKUP($B21&$C21,'C. Gestión Pto #1'!$B$4:S$17,MATCH(T$5,'C. Gestión Pto #1'!$B$4:S$4,0),FALSE),0),IFERROR(VLOOKUP($B21&$C21,'C. Gestión Pto #2'!$B$4:M$23,MATCH(T$5,'C. Gestión Pto #2'!$B$4:M$4,0),FALSE),0)) -> 7793473.3 | V21: {=SUMPRODUCT($D21:$U21,TRANSPOSE('Indice CAC'!$C$10:$C$27))} -> 2.381807e+08 | X21: ='Resumen Pto #1'!X21 -> 1.6001523e+08 | Y21: 0 | Z21: =SUM(X21:Y21) -> 1.6001523e+08 | AA21: =IF(C21="MAT",SUMIF('Pto. 01 Cert.'!$A$10:$A$57,$B21,'Pto. 01 Cert.'!$T$10:$T$57),IF(C21="MO",SUMIF('Pto. 01 Cert.'!$A$10:$A$57,$B21,'Pto. 01 Cert.'!$U$10:$U$57),SUMIF('Pto. 01 Cert.'!$A$10:$A$57,$B21,'Pto. 01 Cert.'!$V$10:$V$57)))/IF(C21="MAT",SUMIF('Pto. 01 Cert.'!$A$10:$A$57,$B21,'Pto. 01 Cert.'!$I$10:$I$57),IF(C21="MO",SUMIF('Pto. 01 Cert.'!$A$10:$A$57,$B21,'Pto. 01 Cert.'!$J$10:$J$57),SUMIF('Pto. 01 Cert.'!$A$10:$A$57,$B21,'Pto. 01 Cert.'!$K$10:$K$57))) -> 1 | AB21: =IF(AA21=100%,0,IF(OR(V21<>0,Z21),Z21-V21)) -> 0 | AC21: =IF(OR(AB21<0,Z21),AB21/Z21,0%) -> 0 | AD21: =IF(AA21=100%,IF(OR(V21<>0,Z21),Z21-V21),0) -> -78165468
B22: Albañilería | C22: MAT | D22: =IFERROR(SUM(VLOOKUP($B22&$C22,'C. Gestión Pto #1'!$B$4:C$17,MATCH(D$5,'C. Gestión Pto #1'!$B$4:C$4,0),FALSE),0),0) -> 22000 | E22: =IFERROR(SUM(VLOOKUP($B22&$C22,'C. Gestión Pto #1'!$B$4:D$17,MATCH(E$5,'C. Gestión Pto #1'!$B$4:D$4,0),FALSE),0),0) -> 0 | F22: =IFERROR(SUM(VLOOKUP($B22&$C22,'C. Gestión Pto #1'!$B$4:E$17,MATCH(F$5,'C. Gestión Pto #1'!$B$4:E$4,0),FALSE),0),0) -> 0 | G22: =IFERROR(SUM(VLOOKUP($B22&$C22,'C. Gestión Pto #1'!$B$4:F$17,MATCH(G$5,'C. Gestión Pto #1'!$B$4:F$4,0),FALSE),0),0) -> 0 | H22: =IFERROR(SUM(VLOOKUP($B22&$C22,'C. Gestión Pto #1'!$B$4:G$17,MATCH(H$5,'C. Gestión Pto #1'!$B$4:G$4,0),FALSE),0),0) -> 0 | I22: =IFERROR(SUM(VLOOKUP($B22&$C22,'C. Gestión Pto #1'!$B$4:H$17,MATCH(I$5,'C. Gestión Pto #1'!$B$4:H$4,0),FALSE),0),0) -> 0 | J22: =SUM(IFERROR(VLOOKUP($B22&$C22,'C. Gestión Pto #1'!$B$4:I$17,MATCH(J$5,'C. Gestión Pto #1'!$B$4:I$4,0),FALSE),0),IFERROR(VLOOKUP($B22&$C22,'C. Gestión Pto #2'!$B$4:C$23,MATCH(J$5,'C. Gestión Pto #2'!$B$4:C$4,0),FALSE),0)) -> 203018.11 | K22: =SUM(IFERROR(VLOOKUP($B22&$C22,'C. Gestión Pto #1'!$B$4:J$17,MATCH(K$5,'C. Gestión Pto #1'!$B$4:J$4,0),FALSE),0),IFERROR(VLOOKUP($B22&$C22,'C. Gestión Pto #2'!$B$4:D$23,MATCH(K$5,'C. Gestión Pto #2'!$B$4:D$4,0),FALSE),0)) -> 955956.22 | L22: =SUM(IFERROR(VLOOKUP($B22&$C22,'C. Gestión Pto #1'!$B$4:K$17,MATCH(L$5,'C. Gestión Pto #1'!$B$4:K$4,0),FALSE),0),IFERROR(VLOOKUP($B22&$C22,'C. Gestión Pto #2'!$B$4:E$23,MATCH(L$5,'C. Gestión Pto #2'!$B$4:E$4,0),FALSE),0)) -> 404650.26 | M22: =SUM(IFERROR(VLOOKUP($B22&$C22,'C. Gestión Pto #1'!$B$4:L$17,MATCH(M$5,'C. Gestión Pto #1'!$B$4:L$4,0),FALSE),0),IFERROR(VLOOKUP($B22&$C22,'C. Gestión Pto #2'!$B$4:F$23,MATCH(M$5,'C. Gestión Pto #2'!$B$4:F$4,0),FALSE),0)) -> 21548948 | N22: =SUM(IFERROR(VLOOKUP($B22&$C22,'C. Gestión Pto #1'!$B$4:M$17,MATCH(N$5,'C. Gestión Pto #1'!$B$4:M$4,0),FALSE),0),IFERROR(VLOOKUP($B22&$C22,'C. Gestión Pto #2'!$B$4:G$23,MATCH(N$5,'C. Gestión Pto #2'!$B$4:G$4,0),FALSE),0)) -> 5653260.9 | O22: =SUM(IFERROR(VLOOKUP($B22&$C22,'C. Gestión Pto #1'!$B$4:N$17,MATCH(O$5,'C. Gestión Pto #1'!$B$4:N$4,0),FALSE),0),IFERROR(VLOOKUP($B22&$C22,'C. Gestión Pto #2'!$B$4:H$23,MATCH(O$5,'C. Gestión Pto #2'!$B$4:H$4,0),FALSE),0)) -> 524503.91 | P22: =SUM(IFERROR(VLOOKUP($B22&$C22,'C. Gestión Pto #1'!$B$4:O$17,MATCH(P$5,'C. Gestión Pto #1'!$B$4:O$4,0),FALSE),0),IFERROR(VLOOKUP($B22&$C22,'C. Gestión Pto #2'!$B$4:I$23,MATCH(P$5,'C. Gestión Pto #2'!$B$4:I$4,0),FALSE),0)) -> 4059472.8 | Q22: =SUM(IFERROR(VLOOKUP($B22&$C22,'C. Gestión Pto #1'!$B$4:P$17,MATCH(Q$5,'C. Gestión Pto #1'!$B$4:P$4,0),FALSE),0),IFERROR(VLOOKUP($B22&$C22,'C. Gestión Pto #2'!$B$4:J$23,MATCH(Q$5,'C. Gestión Pto #2'!$B$4:J$4,0),FALSE),0)) -> 3330609.2 | ... T22: =SUM(IFERROR(VLOOKUP($B22&$C22,'C. Gestión Pto #1'!$B$4:S$17,MATCH(T$5,'C. Gestión Pto #1'!$B$4:S$4,0),FALSE),0),IFERROR(VLOOKUP($B22&$C22,'C. Gestión Pto #2'!$B$4:M$23,MATCH(T$5,'C. Gestión Pto #2'!$B$4:M$4,0),FALSE),0)) -> 23833774 | V22: {=SUMPRODUCT($D22:$U22,TRANSPOSE('Indice CAC'!$C$10:$C$27))} -> 63183132 | X22: ='Resumen Pto #1'!X22 -> 2988097.3 | Y22: ='Resumen Pto #2'!R16 -> 61725811 | Z22: =SUM(X22:Y22) -> 64713908 | AA22: =SUM(IF(C22="MAT",SUMIF('Pto. 01 Cert.'!$A$10:$A$57,$B22,'Pto. 01 Cert.'!$T$10:$T$57),IF(C22="MO",SUMIF('Pto. 01 Cert.'!$A$10:$A$57,$B22,'Pto. 01 Cert.'!$U$10:$U$57),SUMIF('Pto. 01 Cert.'!$A$10:$A$57,$B22,'Pto. 01 Cert.'!$V$10:$V$57))),IF(C22="MAT",SUMIF('Pto. 02 Cert.'!$A$10:$A$185,$B22,'Pto. 02 Cert.'!$T$10:$T$185),IF(C22="MO",SUMIF('Pto. 02 Cert.'!$A$10:$A$185,$B22,'Pto. 02 Cert.'!$U$10:$U$185),SUMIF('Pto. 02 Cert.'!$A$10:$A$185,$B22,'Pto. 02 Cert.'!$V$10:$V$185))))/SUM(IF(C22="MAT",SUMIF('Pto. 01 Cert.'!$A$10:$A$57,$B22,'Pto. 01 Cert.'!$I$10:$I$57),IF(C22="MO",SUMIF('Pto. 01 Cert.'!$A$10:$A$57,$B22,'Pto. 01 Cert.'!$J$10:$J$57),SUMIF('Pto. 01 Cert.'!$A$10:$A$57,$B22,'Pto. 01 Cert.'!$K$10:$K$57))),IF(C22="MAT",SUMIF('Pto. 02 Cert.'!$A$10:$A$185,$B22,'Pto. 02 Cert.'!$I$10:$I$185),IF(C22="MO",SUMIF('Pto. 02 Cert.'!$A$10:$A$185,$B22,'Pto. 02 Cert.'!$J$10:$J$185),SUMIF('Pto. 02 Cert.'!$A$10:$A$185,$B22,'Pto. 02 Cert.'!$K$10:$K$185)))) -> 0.48486163 | AB22: =IF(AA22=100%,0,IF(OR(V22<>0,Z22),Z22-V22)) -> 1530776.1 | AC22: =IF(OR(AB22<0,Z22),AB22/Z22,0%) -> 0.023654515 | AD22: =IF(AA22=100%,IF(OR(V22<>0,Z22),Z22-V22),0) -> 0
B23: Albañilería | C23: MO | D23: =IFERROR(SUM(VLOOKUP($B23&$C23,'C. Gestión Pto #1'!$B$4:C$17,MATCH(D$5,'C. Gestión Pto #1'!$B$4:C$4,0),FALSE),0),0) -> 0 | E23: =IFERROR(SUM(VLOOKUP($B23&$C23,'C. Gestión Pto #1'!$B$4:D$17,MATCH(E$5,'C. Gestión Pto #1'!$B$4:D$4,0),FALSE),0),0) -> 0 | F23: =IFERROR(SUM(VLOOKUP($B23&$C23,'C. Gestión Pto #1'!$B$4:E$17,MATCH(F$5,'C. Gestión Pto #1'!$B$4:E$4,0),FALSE),0),0) -> 67000 | G23: =IFERROR(SUM(VLOOKUP($B23&$C23,'C. Gestión Pto #1'!$B$4:F$17,MATCH(G$5,'C. Gestión Pto #1'!$B$4:F$4,0),FALSE),0),0) -> 240500 | H23: =IFERROR(SUM(VLOOKUP($B23&$C23,'C. Gestión Pto #1'!$B$4:G$17,MATCH(H$5,'C. Gestión Pto #1'!$B$4:G$4,0),FALSE),0),0) -> 497357.68 | I23: =IFERROR(SUM(VLOOKUP($B23&$C23,'C. Gestión Pto #1'!$B$4:H$17,MATCH(I$5,'C. Gestión Pto #1'!$B$4:H$4,0),FALSE),0),0) -> 100000 | J23: =SUM(IFERROR(VLOOKUP($B23&$C23,'C. Gestión Pto #1'!$B$4:I$17,MATCH(J$5,'C. Gestión Pto #1'!$B$4:I$4,0),FALSE),0),IFERROR(VLOOKUP($B23&$C23,'C. Gestión Pto #2'!$B$4:C$23,MATCH(J$5,'C. Gestión Pto #2'!$B$4:C$4,0),FALSE),0)) -> 0 | K23: =SUM(IFERROR(VLOOKUP($B23&$C23,'C. Gestión Pto #1'!$B$4:J$17,MATCH(K$5,'C. Gestión Pto #1'!$B$4:J$4,0),FALSE),0),IFERROR(VLOOKUP($B23&$C23,'C. Gestión Pto #2'!$B$4:D$23,MATCH(K$5,'C. Gestión Pto #2'!$B$4:D$4,0),FALSE),0)) -> 0 | L23: =SUM(IFERROR(VLOOKUP($B23&$C23,'C. Gestión Pto #1'!$B$4:K$17,MATCH(L$5,'C. Gestión Pto #1'!$B$4:K$4,0),FALSE),0),IFERROR(VLOOKUP($B23&$C23,'C. Gestión Pto #2'!$B$4:E$23,MATCH(L$5,'C. Gestión Pto #2'!$B$4:E$4,0),FALSE),0)) -> 2134429.8 | M23: =SUM(IFERROR(VLOOKUP($B23&$C23,'C. Gestión Pto #1'!$B$4:L$17,MATCH(M$5,'C. Gestión Pto #1'!$B$4:L$4,0),FALSE),0),IFERROR(VLOOKUP($B23&$C23,'C. Gestión Pto #2'!$B$4:F$23,MATCH(M$5,'C. Gestión Pto #2'!$B$4:F$4,0),FALSE),0)) -> 10224408 | N23: =SUM(IFERROR(VLOOKUP($B23&$C23,'C. Gestión Pto #1'!$B$4:M$17,MATCH(N$5,'C. Gestión Pto #1'!$B$4:M$4,0),FALSE),0),IFERROR(VLOOKUP($B23&$C23,'C. Gestión Pto #2'!$B$4:G$23,MATCH(N$5,'C. Gestión Pto #2'!$B$4:G$4,0),FALSE),0)) -> 9687819.9 | O23: =SUM(IFERROR(VLOOKUP($B23&$C23,'C. Gestión Pto #1'!$B$4:N$17,MATCH(O$5,'C. Gestión Pto #1'!$B$4:N$4,0),FALSE),0),IFERROR(VLOOKUP($B23&$C23,'C. Gestión Pto #2'!$B$4:H$23,MATCH(O$5,'C. Gestión Pto #2'!$B$4:H$4,0),FALSE),0)) -> 15241735 | P23: =SUM(IFERROR(VLOOKUP($B23&$C23,'C. Gestión Pto #1'!$B$4:O$17,MATCH(P$5,'C. Gestión Pto #1'!$B$4:O$4,0),FALSE),0),IFERROR(VLOOKUP($B23&$C23,'C. Gestión Pto #2'!$B$4:I$23,MATCH(P$5,'C. Gestión Pto #2'!$B$4:I$4,0),FALSE),0)) -> 23120863 | Q23: =SUM(IFERROR(VLOOKUP($B23&$C23,'C. Gestión Pto #1'!$B$4:P$17,MATCH(Q$5,'C. Gestión Pto #1'!$B$4:P$4,0),FALSE),0),IFERROR(VLOOKUP($B23&$C23,'C. Gestión Pto #2'!$B$4:J$23,MATCH(Q$5,'C. Gestión Pto #2'!$B$4:J$4,0),FALSE),0)) -> 23725839 | ... T23: =SUM(IFERROR(VLOOKUP($B23&$C23,'C. Gestión Pto #1'!$B$4:S$17,MATCH(T$5,'C. Gestión Pto #1'!$B$4:S$4,0),FALSE),0),IFERROR(VLOOKUP($B23&$C23,'C. Gestión Pto #2'!$B$4:M$23,MATCH(T$5,'C. Gestión Pto #2'!$B$4:M$4,0),FALSE),0)) -> 34129760 | V23: {=SUMPRODUCT($D23:$U23,TRANSPOSE('Indice CAC'!$C$10:$C$27))} -> 1.30033e+08 | X23: ='Resumen Pto #1'!X23 -> 13017986 | Y23: ='Resumen Pto #2'!R17 -> 1.2838306e+08 | Z23: =SUM(X23:Y23) -> 1.4140104e+08 | AA23: =SUM(IF(C23="MAT",SUMIF('Pto. 01 Cert.'!$A$10:$A$57,$B23,'Pto. 01 Cert.'!$T$10:$T$57),IF(C23="MO",SUMIF('Pto. 01 Cert.'!$A$10:$A$57,$B23,'Pto. 01 Cert.'!$U$10:$U$57),SUMIF('Pto. 01 Cert.'!$A$10:$A$57,$B23,'Pto. 01 Cert.'!$V$10:$V$57))),IF(C23="MAT",SUMIF('Pto. 02 Cert.'!$A$10:$A$185,$B23,'Pto. 02 Cert.'!$T$10:$T$185),IF(C23="MO",SUMIF('Pto. 02 Cert.'!$A$10:$A$185,$B23,'Pto. 02 Cert.'!$U$10:$U$185),SUMIF('Pto. 02 Cert.'!$A$10:$A$185,$B23,'Pto. 02 Cert.'!$V$10:$V$185))))/SUM(IF(C23="MAT",SUMIF('Pto. 01 Cert.'!$A$10:$A$57,$B23,'Pto. 01 Cert.'!$I$10:$I$57),IF(C23="MO",SUMIF('Pto. 01 Cert.'!$A$10:$A$57,$B23,'Pto. 01 Cert.'!$J$10:$J$57),SUMIF('Pto. 01 Cert.'!$A$10:$A$57,$B23,'Pto. 01 Cert.'!$K$10:$K$57))),IF(C23="MAT",SUMIF('Pto. 02 Cert.'!$A$10:$A$185,$B23,'Pto. 02 Cert.'!$I$10:$I$185),IF(C23="MO",SUMIF('Pto. 02 Cert.'!$A$10:$A$185,$B23,'Pto. 02 Cert.'!$J$10:$J$185),SUMIF('Pto. 02 Cert.'!$A$10:$A$185,$B23,'Pto. 02 Cert.'!$K$10:$K$185)))) -> 0.57339098 | AB23: =IF(AA23=100%,0,IF(OR(V23<>0,Z23),Z23-V23)) -> 11368046 | AC23: =IF(OR(AB23<0,Z23),AB23/Z23,0%) -> 0.080395771 | AD23: =IF(AA23=100%,IF(OR(V23<>0,Z23),Z23-V23),0) -> 0
B24: Durlock | C24: MAT | D24: =IFERROR(SUM(VLOOKUP($B24&$C24,'C. Gestión Pto #1'!$B$4:C$17,MATCH(D$5,'C. Gestión Pto #1'!$B$4:C$4,0),FALSE),0),0) -> 0 | E24: =IFERROR(SUM(VLOOKUP($B24&$C24,'C. Gestión Pto #1'!$B$4:D$17,MATCH(E$5,'C. Gestión Pto #1'!$B$4:D$4,0),FALSE),0),0) -> 0 | F24: =IFERROR(SUM(VLOOKUP($B24&$C24,'C. Gestión Pto #1'!$B$4:E$17,MATCH(F$5,'C. Gestión Pto #1'!$B$4:E$4,0),FALSE),0),0) -> 0 | G24: =IFERROR(SUM(VLOOKUP($B24&$C24,'C. Gestión Pto #1'!$B$4:F$17,MATCH(G$5,'C. Gestión Pto #1'!$B$4:F$4,0),FALSE),0),0) -> 0 | H24: =IFERROR(SUM(VLOOKUP($B24&$C24,'C. Gestión Pto #1'!$B$4:G$17,MATCH(H$5,'C. Gestión Pto #1'!$B$4:G$4,0),FALSE),0),0) -> 0 | I24: =IFERROR(SUM(VLOOKUP($B24&$C24,'C. Gestión Pto #1'!$B$4:H$17,MATCH(I$5,'C. Gestión Pto #1'!$B$4:H$4,0),FALSE),0),0) -> 0 | J24: =SUM(IFERROR(VLOOKUP($B24&$C24,'C. Gestión Pto #1'!$B$4:I$17,MATCH(J$5,'C. Gestión Pto #1'!$B$4:I$4,0),FALSE),0),IFERROR(VLOOKUP($B24&$C24,'C. Gestión Pto #2'!$B$4:C$23,MATCH(J$5,'C. Gestión Pto #2'!$B$4:C$4,0),FALSE),0)) -> 0 | K24: =SUM(IFERROR(VLOOKUP($B24&$C24,'C. Gestión Pto #1'!$B$4:J$17,MATCH(K$5,'C. Gestión Pto #1'!$B$4:J$4,0),FALSE),0),IFERROR(VLOOKUP($B24&$C24,'C. Gestión Pto #2'!$B$4:D$23,MATCH(K$5,'C. Gestión Pto #2'!$B$4:D$4,0),FALSE),0)) -> 0 | L24: =SUM(IFERROR(VLOOKUP($B24&$C24,'C. Gestión Pto #1'!$B$4:K$17,MATCH(L$5,'C. Gestión Pto #1'!$B$4:K$4,0),FALSE),0),IFERROR(VLOOKUP($B24&$C24,'C. Gestión Pto #2'!$B$4:E$23,MATCH(L$5,'C. Gestión Pto #2'!$B$4:E$4,0),FALSE),0)) -> 14055.62 | M24: =SUM(IFERROR(VLOOKUP($B24&$C24,'C. Gestión Pto #1'!$B$4:L$17,MATCH(M$5,'C. Gestión Pto #1'!$B$4:L$4,0),FALSE),0),IFERROR(VLOOKUP($B24&$C24,'C. Gestión Pto #2'!$B$4:F$23,MATCH(M$5,'C. Gestión Pto #2'!$B$4:F$4,0),FALSE),0)) -> 0 | N24: =SUM(IFERROR(VLOOKUP($B24&$C24,'C. Gestión Pto #1'!$B$4:M$17,MATCH(N$5,'C. Gestión Pto #1'!$B$4:M$4,0),FALSE),0),IFERROR(VLOOKUP($B24&$C24,'C. Gestión Pto #2'!$B$4:G$23,MATCH(N$5,'C. Gestión Pto #2'!$B$4:G$4,0),FALSE),0)) -> 0 | O24: =SUM(IFERROR(VLOOKUP($B24&$C24,'C. Gestión Pto #1'!$B$4:N$17,MATCH(O$5,'C. Gestión Pto #1'!$B$4:N$4,0),FALSE),0),IFERROR(VLOOKUP($B24&$C24,'C. Gestión Pto #2'!$B$4:H$23,MATCH(O$5,'C. Gestión Pto #2'!$B$4:H$4,0),FALSE),0)) -> 0 | P24: =SUM(IFERROR(VLOOKUP($B24&$C24,'C. Gestión Pto #1'!$B$4:O$17,MATCH(P$5,'C. Gestión Pto #1'!$B$4:O$4,0),FALSE),0),IFERROR(VLOOKUP($B24&$C24,'C. Gestión Pto #2'!$B$4:I$23,MATCH(P$5,'C. Gestión Pto #2'!$B$4:I$4,0),FALSE),0)) -> 0 | Q24: =SUM(IFERROR(VLOOKUP($B24&$C24,'C. Gestión Pto #1'!$B$4:P$17,MATCH(Q$5,'C. Gestión Pto #1'!$B$4:P$4,0),FALSE),0),IFERROR(VLOOKUP($B24&$C24,'C. Gestión Pto #2'!$B$4:J$23,MATCH(Q$5,'C. Gestión Pto #2'!$B$4:J$4,0),FALSE),0)) -> 6856283.7 | ... T24: =SUM(IFERROR(VLOOKUP($B24&$C24,'C. Gestión Pto #1'!$B$4:S$17,MATCH(T$5,'C. Gestión Pto #1'!$B$4:S$4,0),FALSE),0),IFERROR(VLOOKUP($B24&$C24,'C. Gestión Pto #2'!$B$4:M$23,MATCH(T$5,'C. Gestión Pto #2'!$B$4:M$4,0),FALSE),0)) -> 12647943 | V24: {=SUMPRODUCT($D24:$U24,TRANSPOSE('Indice CAC'!$C$10:$C$27))} -> 15079861 | X24: 0 | Y24: ='Resumen Pto #2'!R18 -> 24596469 | Z24: =SUM(X24:Y24) -> 24596469 | AA24: =IF(C24="MAT",SUMIF('Pto. 02 Cert.'!$A$10:$A$185,$B24,'Pto. 02 Cert.'!$T$10:$T$185),IF(C24="MO",SUMIF('Pto. 02 Cert.'!$A$10:$A$185,$B24,'Pto. 02 Cert.'!$U$10:$U$185),SUMIF('Pto. 02 Cert.'!$A$10:$A$185,$B24,'Pto. 02 Cert.'!$V$10:$V$185)))/IF(C24="MAT",SUMIF('Pto. 02 Cert.'!$A$10:$A$185,$B24,'Pto. 02 Cert.'!$I$10:$I$185),IF(C24="MO",SUMIF('Pto. 02 Cert.'!$A$10:$A$185,$B24,'Pto. 02 Cert.'!$J$10:$J$185),SUMIF('Pto. 02 Cert.'!$A$10:$A$185,$B24,'Pto. 02 Cert.'!$K$10:$K$185))) -> 0.56143986 | AB24: =IF(AA24=100%,0,IF(OR(V24<>0,Z24),Z24-V24)) -> 9516608.9 | AC24: =IF(OR(AB24<0,Z24),AB24/Z24,0%) -> 0.38690955 | AD24: =IF(AA24=100%,IF(OR(V24<>0,Z24),Z24-V24),0) -> 0
B25: Durlock | C25: MO | D25: =IFERROR(SUM(VLOOKUP($B25&$C25,'C. Gestión Pto #1'!$B$4:C$17,MATCH(D$5,'C. Gestión Pto #1'!$B$4:C$4,0),FALSE),0),0) -> 0 | E25: =IFERROR(SUM(VLOOKUP($B25&$C25,'C. Gestión Pto #1'!$B$4:D$17,MATCH(E$5,'C. Gestión Pto #1'!$B$4:D$4,0),FALSE),0),0) -> 0 | F25: =IFERROR(SUM(VLOOKUP($B25&$C25,'C. Gestión Pto #1'!$B$4:E$17,MATCH(F$5,'C. Gestión Pto #1'!$B$4:E$4,0),FALSE),0),0) -> 0 | G25: =IFERROR(SUM(VLOOKUP($B25&$C25,'C. Gestión Pto #1'!$B$4:F$17,MATCH(G$5,'C. Gestión Pto #1'!$B$4:F$4,0),FALSE),0),0) -> 0 | H25: =IFERROR(SUM(VLOOKUP($B25&$C25,'C. Gestión Pto #1'!$B$4:G$17,MATCH(H$5,'C. Gestión Pto #1'!$B$4:G$4,0),FALSE),0),0) -> 0 | I25: =IFERROR(SUM(VLOOKUP($B25&$C25,'C. Gestión Pto #1'!$B$4:H$17,MATCH(I$5,'C. Gestión Pto #1'!$B$4:H$4,0),FALSE),0),0) -> 0 | J25: =SUM(IFERROR(VLOOKUP($B25&$C25,'C. Gestión Pto #1'!$B$4:I$17,MATCH(J$5,'C. Gestión Pto #1'!$B$4:I$4,0),FALSE),0),IFERROR(VLOOKUP($B25&$C25,'C. Gestión Pto #2'!$B$4:C$23,MATCH(J$5,'C. Gestión Pto #2'!$B$4:C$4,0),FALSE),0)) -> 0 | K25: =SUM(IFERROR(VLOOKUP($B25&$C25,'C. Gestión Pto #1'!$B$4:J$17,MATCH(K$5,'C. Gestión Pto #1'!$B$4:J$4,0),FALSE),0),IFERROR(VLOOKUP($B25&$C25,'C. Gestión Pto #2'!$B$4:D$23,MATCH(K$5,'C. Gestión Pto #2'!$B$4:D$4,0),FALSE),0)) -> 0 | L25: =SUM(IFERROR(VLOOKUP($B25&$C25,'C. Gestión Pto #1'!$B$4:K$17,MATCH(L$5,'C. Gestión Pto #1'!$B$4:K$4,0),FALSE),0),IFERROR(VLOOKUP($B25&$C25,'C. Gestión Pto #2'!$B$4:E$23,MATCH(L$5,'C. Gestión Pto #2'!$B$4:E$4,0),FALSE),0)) -> 0 | M25: =SUM(IFERROR(VLOOKUP($B25&$C25,'C. Gestión Pto #1'!$B$4:L$17,MATCH(M$5,'C. Gestión Pto #1'!$B$4:L$4,0),FALSE),0),IFERROR(VLOOKUP($B25&$C25,'C. Gestión Pto #2'!$B$4:F$23,MATCH(M$5,'C. Gestión Pto #2'!$B$4:F$4,0),FALSE),0)) -> 0 | N25: =SUM(IFERROR(VLOOKUP($B25&$C25,'C. Gestión Pto #1'!$B$4:M$17,MATCH(N$5,'C. Gestión Pto #1'!$B$4:M$4,0),FALSE),0),IFERROR(VLOOKUP($B25&$C25,'C. Gestión Pto #2'!$B$4:G$23,MATCH(N$5,'C. Gestión Pto #2'!$B$4:G$4,0),FALSE),0)) -> 0 | O25: =SUM(IFERROR(VLOOKUP($B25&$C25,'C. Gestión Pto #1'!$B$4:N$17,MATCH(O$5,'C. Gestión Pto #1'!$B$4:N$4,0),FALSE),0),IFERROR(VLOOKUP($B25&$C25,'C. Gestión Pto #2'!$B$4:H$23,MATCH(O$5,'C. Gestión Pto #2'!$B$4:H$4,0),FALSE),0)) -> 0 | P25: =SUM(IFERROR(VLOOKUP($B25&$C25,'C. Gestión Pto #1'!$B$4:O$17,MATCH(P$5,'C. Gestión Pto #1'!$B$4:O$4,0),FALSE),0),IFERROR(VLOOKUP($B25&$C25,'C. Gestión Pto #2'!$B$4:I$23,MATCH(P$5,'C. Gestión Pto #2'!$B$4:I$4,0),FALSE),0)) -> 1027500 | Q25: =SUM(IFERROR(VLOOKUP($B25&$C25,'C. Gestión Pto #1'!$B$4:P$17,MATCH(Q$5,'C. Gestión Pto #1'!$B$4:P$4,0),FALSE),0),IFERROR(VLOOKUP($B25&$C25,'C. Gestión Pto #2'!$B$4:J$23,MATCH(Q$5,'C. Gestión Pto #2'!$B$4:J$4,0),FALSE),0)) -> 1288504.6 | ... T25: =SUM(IFERROR(VLOOKUP($B25&$C25,'C. Gestión Pto #1'!$B$4:S$17,MATCH(T$5,'C. Gestión Pto #1'!$B$4:S$4,0),FALSE),0),IFERROR(VLOOKUP($B25&$C25,'C. Gestión Pto #2'!$B$4:M$23,MATCH(T$5,'C. Gestión Pto #2'!$B$4:M$4,0),FALSE),0)) -> 0 | V25: {=SUMPRODUCT($D25:$U25,TRANSPOSE('Indice CAC'!$C$10:$C$27))} -> 6558470.8 | X25: 0 | Y25: ='Resumen Pto #2'!R19 -> 66185630 | Z25: =SUM(X25:Y25) -> 66185630 | AA25: =IF(C25="MAT",SUMIF('Pto. 02 Cert.'!$A$10:$A$185,$B25,'Pto. 02 Cert.'!$T$10:$T$185),IF(C25="MO",SUMIF('Pto. 02 Cert.'!$A$10:$A$185,$B25,'Pto. 02 Cert.'!$U$10:$U$185),SUMIF('Pto. 02 Cert.'!$A$10:$A$185,$B25,'Pto. 02 Cert.'!$V$10:$V$185)))/IF(C25="MAT",SUMIF('Pto. 02 Cert.'!$A$10:$A$185,$B25,'Pto. 02 Cert.'!$I$10:$I$185),IF(C25="MO",SUMIF('Pto. 02 Cert.'!$A$10:$A$185,$B25,'Pto. 02 Cert.'!$J$10:$J$185),SUMIF('Pto. 02 Cert.'!$A$10:$A$185,$B25,'Pto. 02 Cert.'!$K$10:$K$185))) -> 0.54645468 | AB25: =IF(AA25=100%,0,IF(OR(V25<>0,Z25),Z25-V25)) -> 59627160 | AC25: =IF(OR(AB25<0,Z25),AB25/Z25,0%) -> 0.90090793 | AD25: =IF(AA25=100%,IF(OR(V25<>0,Z25),Z25-V25),0) -> 0
B26: Eléctrico | C26: MAT | D26: =IFERROR(SUM(VLOOKUP($B26&$C26,'C. Gestión Pto #1'!$B$4:C$17,MATCH(D$5,'C. Gestión Pto #1'!$B$4:C$4,0),FALSE),0),0) -> 0 | E26: =IFERROR(SUM(VLOOKUP($B26&$C26,'C. Gestión Pto #1'!$B$4:D$17,MATCH(E$5,'C. Gestión Pto #1'!$B$4:D$4,0),FALSE),0),0) -> 0 | F26: =IFERROR(SUM(VLOOKUP($B26&$C26,'C. Gestión Pto #1'!$B$4:E$17,MATCH(F$5,'C. Gestión Pto #1'!$B$4:E$4,0),FALSE),0),0) -> 0 | G26: =IFERROR(SUM(VLOOKUP($B26&$C26,'C. Gestión Pto #1'!$B$4:F$17,MATCH(G$5,'C. Gestión Pto #1'!$B$4:F$4,0),FALSE),0),0) -> 0 | H26: =IFERROR(SUM(VLOOKUP($B26&$C26,'C. Gestión Pto #1'!$B$4:G$17,MATCH(H$5,'C. Gestión Pto #1'!$B$4:G$4,0),FALSE),0),0) -> 0 | I26: =IFERROR(SUM(VLOOKUP($B26&$C26,'C. Gestión Pto #1'!$B$4:H$17,MATCH(I$5,'C. Gestión Pto #1'!$B$4:H$4,0),FALSE),0),0) -> 0 | J26: =SUM(IFERROR(VLOOKUP($B26&$C26,'C. Gestión Pto #1'!$B$4:I$17,MATCH(J$5,'C. Gestión Pto #1'!$B$4:I$4,0),FALSE),0),IFERROR(VLOOKUP($B26&$C26,'C. Gestión Pto #2'!$B$4:C$23,MATCH(J$5,'C. Gestión Pto #2'!$B$4:C$4,0),FALSE),0)) -> 0 | K26: =SUM(IFERROR(VLOOKUP($B26&$C26,'C. Gestión Pto #1'!$B$4:J$17,MATCH(K$5,'C. Gestión Pto #1'!$B$4:J$4,0),FALSE),0),IFERROR(VLOOKUP($B26&$C26,'C. Gestión Pto #2'!$B$4:D$23,MATCH(K$5,'C. Gestión Pto #2'!$B$4:D$4,0),FALSE),0)) -> 278030.38 | L26: =SUM(IFERROR(VLOOKUP($B26&$C26,'C. Gestión Pto #1'!$B$4:K$17,MATCH(L$5,'C. Gestión Pto #1'!$B$4:K$4,0),FALSE),0),IFERROR(VLOOKUP($B26&$C26,'C. Gestión Pto #2'!$B$4:E$23,MATCH(L$5,'C. Gestión Pto #2'!$B$4:E$4,0),FALSE),0)) -> 1035273.8 | M26: =SUM(IFERROR(VLOOKUP($B26&$C26,'C. Gestión Pto #1'!$B$4:L$17,MATCH(M$5,'C. Gestión Pto #1'!$B$4:L$4,0),FALSE),0),IFERROR(VLOOKUP($B26&$C26,'C. Gestión Pto #2'!$B$4:F$23,MATCH(M$5,'C. Gestión Pto #2'!$B$4:F$4,0),FALSE),0)) -> 2959054.6 | N26: =SUM(IFERROR(VLOOKUP($B26&$C26,'C. Gestión Pto #1'!$B$4:M$17,MATCH(N$5,'C. Gestión Pto #1'!$B$4:M$4,0),FALSE),0),IFERROR(VLOOKUP($B26&$C26,'C. Gestión Pto #2'!$B$4:G$23,MATCH(N$5,'C. Gestión Pto #2'!$B$4:G$4,0),FALSE),0)) -> 1344156.9 | O26: =SUM(IFERROR(VLOOKUP($B26&$C26,'C. Gestión Pto #1'!$B$4:N$17,MATCH(O$5,'C. Gestión Pto #1'!$B$4:N$4,0),FALSE),0),IFERROR(VLOOKUP($B26&$C26,'C. Gestión Pto #2'!$B$4:H$23,MATCH(O$5,'C. Gestión Pto #2'!$B$4:H$4,0),FALSE),0)) -> 48067.03 | P26: =SUM(IFERROR(VLOOKUP($B26&$C26,'C. Gestión Pto #1'!$B$4:O$17,MATCH(P$5,'C. Gestión Pto #1'!$B$4:O$4,0),FALSE),0),IFERROR(VLOOKUP($B26&$C26,'C. Gestión Pto #2'!$B$4:I$23,MATCH(P$5,'C. Gestión Pto #2'!$B$4:I$4,0),FALSE),0)) -> 529125.51 | Q26: =SUM(IFERROR(VLOOKUP($B26&$C26,'C. Gestión Pto #1'!$B$4:P$17,MATCH(Q$5,'C. Gestión Pto #1'!$B$4:P$4,0),FALSE),0),IFERROR(VLOOKUP($B26&$C26,'C. Gestión Pto #2'!$B$4:J$23,MATCH(Q$5,'C. Gestión Pto #2'!$B$4:J$4,0),FALSE),0)) -> 0 | ... T26: =SUM(IFERROR(VLOOKUP($B26&$C26,'C. Gestión Pto #1'!$B$4:S$17,MATCH(T$5,'C. Gestión Pto #1'!$B$4:S$4,0),FALSE),0),IFERROR(VLOOKUP($B26&$C26,'C. Gestión Pto #2'!$B$4:M$23,MATCH(T$5,'C. Gestión Pto #2'!$B$4:M$4,0),FALSE),0)) -> 6134204.4 | V26: {=SUMPRODUCT($D26:$U26,TRANSPOSE('Indice CAC'!$C$10:$C$27))} -> 9301022.1 | X26: 0 | Y26: ='Resumen Pto #2'!R20 -> 31495173 | Z26: =SUM(X26:Y26) -> 31495173 | AA26: =IF(C26="MAT",SUMIF('Pto. 02 Cert.'!$A$10:$A$185,$B26,'Pto. 02 Cert.'!$T$10:$T$185),IF(C26="MO",SUMIF('Pto. 02 Cert.'!$A$10:$A$185,$B26,'Pto. 02 Cert.'!$U$10:$U$185),SUMIF('Pto. 02 Cert.'!$A$10:$A$185,$B26,'Pto. 02 Cert.'!$V$10:$V$185)))/IF(C26="MAT",SUMIF('Pto. 02 Cert.'!$A$10:$A$185,$B26,'Pto. 02 Cert.'!$I$10:$I$185),IF(C26="MO",SUMIF('Pto. 02 Cert.'!$A$10:$A$185,$B26,'Pto. 02 Cert.'!$J$10:$J$185),SUMIF('Pto. 02 Cert.'!$A$10:$A$185,$B26,'Pto. 02 Cert.'!$K$10:$K$185))) -> 0.1745068 | AB26: =IF(AA26=100%,0,IF(OR(V26<>0,Z26),Z26-V26)) -> 22194151 | AC26: =IF(OR(AB26<0,Z26),AB26/Z26,0%) -> 0.7046842 | AD26: =IF(AA26=100%,IF(OR(V26<>0,Z26),Z26-V26),0) -> 0
B27: Eléctrico | C27: MO | D27: =IFERROR(SUM(VLOOKUP($B27&$C27,'C. Gestión Pto #1'!$B$4:C$17,MATCH(D$5,'C. Gestión Pto #1'!$B$4:C$4,0),FALSE),0),0) -> 0 | E27: =IFERROR(SUM(VLOOKUP($B27&$C27,'C. Gestión Pto #1'!$B$4:D$17,MATCH(E$5,'C. Gestión Pto #1'!$B$4:D$4,0),FALSE),0),0) -> 0 | F27: =IFERROR(SUM(VLOOKUP($B27&$C27,'C. Gestión Pto #1'!$B$4:E$17,MATCH(F$5,'C. Gestión Pto #1'!$B$4:E$4,0),FALSE),0),0) -> 0 | G27: =IFERROR(SUM(VLOOKUP($B27&$C27,'C. Gestión Pto #1'!$B$4:F$17,MATCH(G$5,'C. Gestión Pto #1'!$B$4:F$4,0),FALSE),0),0) -> 0 | H27: =IFERROR(SUM(VLOOKUP($B27&$C27,'C. Gestión Pto #1'!$B$4:G$17,MATCH(H$5,'C. Gestión Pto #1'!$B$4:G$4,0),FALSE),0),0) -> 0 | I27: =IFERROR(SUM(VLOOKUP($B27&$C27,'C. Gestión Pto #1'!$B$4:H$17,MATCH(I$5,'C. Gestión Pto #1'!$B$4:H$4,0),FALSE),0),0) -> 0 | J27: =SUM(IFERROR(VLOOKUP($B27&$C27,'C. Gestión Pto #1'!$B$4:I$17,MATCH(J$5,'C. Gestión Pto #1'!$B$4:I$4,0),FALSE),0),IFERROR(VLOOKUP($B27&$C27,'C. Gestión Pto #2'!$B$4:C$23,MATCH(J$5,'C. Gestión Pto #2'!$B$4:C$4,0),FALSE),0)) -> 550000 | K27: =SUM(IFERROR(VLOOKUP($B27&$C27,'C. Gestión Pto #1'!$B$4:J$17,MATCH(K$5,'C. Gestión Pto #1'!$B$4:J$4,0),FALSE),0),IFERROR(VLOOKUP($B27&$C27,'C. Gestión Pto #2'!$B$4:D$23,MATCH(K$5,'C. Gestión Pto #2'!$B$4:D$4,0),FALSE),0)) -> 0 | L27: =SUM(IFERROR(VLOOKUP($B27&$C27,'C. Gestión Pto #1'!$B$4:K$17,MATCH(L$5,'C. Gestión Pto #1'!$B$4:K$4,0),FALSE),0),IFERROR(VLOOKUP($B27&$C27,'C. Gestión Pto #2'!$B$4:E$23,MATCH(L$5,'C. Gestión Pto #2'!$B$4:E$4,0),FALSE),0)) -> 163802.48 | M27: =SUM(IFERROR(VLOOKUP($B27&$C27,'C. Gestión Pto #1'!$B$4:L$17,MATCH(M$5,'C. Gestión Pto #1'!$B$4:L$4,0),FALSE),0),IFERROR(VLOOKUP($B27&$C27,'C. Gestión Pto #2'!$B$4:F$23,MATCH(M$5,'C. Gestión Pto #2'!$B$4:F$4,0),FALSE),0)) -> 0 | N27: =SUM(IFERROR(VLOOKUP($B27&$C27,'C. Gestión Pto #1'!$B$4:M$17,MATCH(N$5,'C. Gestión Pto #1'!$B$4:M$4,0),FALSE),0),IFERROR(VLOOKUP($B27&$C27,'C. Gestión Pto #2'!$B$4:G$23,MATCH(N$5,'C. Gestión Pto #2'!$B$4:G$4,0),FALSE),0)) -> 0 | O27: =SUM(IFERROR(VLOOKUP($B27&$C27,'C. Gestión Pto #1'!$B$4:N$17,MATCH(O$5,'C. Gestión Pto #1'!$B$4:N$4,0),FALSE),0),IFERROR(VLOOKUP($B27&$C27,'C. Gestión Pto #2'!$B$4:H$23,MATCH(O$5,'C. Gestión Pto #2'!$B$4:H$4,0),FALSE),0)) -> 605000 | P27: =SUM(IFERROR(VLOOKUP($B27&$C27,'C. Gestión Pto #1'!$B$4:O$17,MATCH(P$5,'C. Gestión Pto #1'!$B$4:O$4,0),FALSE),0),IFERROR(VLOOKUP($B27&$C27,'C. Gestión Pto #2'!$B$4:I$23,MATCH(P$5,'C. Gestión Pto #2'!$B$4:I$4,0),FALSE),0)) -> 2580200 | Q27: =SUM(IFERROR(VLOOKUP($B27&$C27,'C. Gestión Pto #1'!$B$4:P$17,MATCH(Q$5,'C. Gestión Pto #1'!$B$4:P$4,0),FALSE),0),IFERROR(VLOOKUP($B27&$C27,'C. Gestión Pto #2'!$B$4:J$23,MATCH(Q$5,'C. Gestión Pto #2'!$B$4:J$4,0),FALSE),0)) -> 0 | ... T27: =SUM(IFERROR(VLOOKUP($B27&$C27,'C. Gestión Pto #1'!$B$4:S$17,MATCH(T$5,'C. Gestión Pto #1'!$B$4:S$4,0),FALSE),0),IFERROR(VLOOKUP($B27&$C27,'C. Gestión Pto #2'!$B$4:M$23,MATCH(T$5,'C. Gestión Pto #2'!$B$4:M$4,0),FALSE),0)) -> 6915189.5 | V27: {=SUMPRODUCT($D27:$U27,TRANSPOSE('Indice CAC'!$C$10:$C$27))} -> 9654242.5 | X27: 0 | Y27: ='Resumen Pto #2'!R21 -> 47599191 | Z27: =SUM(X27:Y27) -> 47599191 | AA27: =IF(C27="MAT",SUMIF('Pto. 02 Cert.'!$A$10:$A$185,$B27,'Pto. 02 Cert.'!$T$10:$T$185),IF(C27="MO",SUMIF('Pto. 02 Cert.'!$A$10:$A$185,$B27,'Pto. 02 Cert.'!$U$10:$U$185),SUMIF('Pto. 02 Cert.'!$A$10:$A$185,$B27,'Pto. 02 Cert.'!$V$10:$V$185)))/IF(C27="MAT",SUMIF('Pto. 02 Cert.'!$A$10:$A$185,$B27,'Pto. 02 Cert.'!$I$10:$I$185),IF(C27="MO",SUMIF('Pto. 02 Cert.'!$A$10:$A$185,$B27,'Pto. 02 Cert.'!$J$10:$J$185),SUMIF('Pto. 02 Cert.'!$A$10:$A$185,$B27,'Pto. 02 Cert.'!$K$10:$K$185))) -> 0.29819713 | AB27: =IF(AA27=100%,0,IF(OR(V27<>0,Z27),Z27-V27)) -> 37944948 | AC27: =IF(OR(AB27<0,Z27),AB27/Z27,0%) -> 0.79717633 | AD27: =IF(AA27=100%,IF(OR(V27<>0,Z27),Z27-V27),0) -> 0
B28: Sanitaria | C28: MAT | D28: =IFERROR(SUM(VLOOKUP($B28&$C28,'C. Gestión Pto #1'!$B$4:C$17,MATCH(D$5,'C. Gestión Pto #1'!$B$4:C$4,0),FALSE),0),0) -> 0 | E28: =IFERROR(SUM(VLOOKUP($B28&$C28,'C. Gestión Pto #1'!$B$4:D$17,MATCH(E$5,'C. Gestión Pto #1'!$B$4:D$4,0),FALSE),0),0) -> 0 | F28: =IFERROR(SUM(VLOOKUP($B28&$C28,'C. Gestión Pto #1'!$B$4:E$17,MATCH(F$5,'C. Gestión Pto #1'!$B$4:E$4,0),FALSE),0),0) -> 0 | G28: =IFERROR(SUM(VLOOKUP($B28&$C28,'C. Gestión Pto #1'!$B$4:F$17,MATCH(G$5,'C. Gestión Pto #1'!$B$4:F$4,0),FALSE),0),0) -> 0 | H28: =IFERROR(SUM(VLOOKUP($B28&$C28,'C. Gestión Pto #1'!$B$4:G$17,MATCH(H$5,'C. Gestión Pto #1'!$B$4:G$4,0),FALSE),0),0) -> 0 | I28: =IFERROR(SUM(VLOOKUP($B28&$C28,'C. Gestión Pto #1'!$B$4:H$17,MATCH(I$5,'C. Gestión Pto #1'!$B$4:H$4,0),FALSE),0),0) -> 0 | J28: =SUM(IFERROR(VLOOKUP($B28&$C28,'C. Gestión Pto #1'!$B$4:I$17,MATCH(J$5,'C. Gestión Pto #1'!$B$4:I$4,0),FALSE),0),IFERROR(VLOOKUP($B28&$C28,'C. Gestión Pto #2'!$B$4:C$23,MATCH(J$5,'C. Gestión Pto #2'!$B$4:C$4,0),FALSE),0)) -> 0 | K28: =SUM(IFERROR(VLOOKUP($B28&$C28,'C. Gestión Pto #1'!$B$4:J$17,MATCH(K$5,'C. Gestión Pto #1'!$B$4:J$4,0),FALSE),0),IFERROR(VLOOKUP($B28&$C28,'C. Gestión Pto #2'!$B$4:D$23,MATCH(K$5,'C. Gestión Pto #2'!$B$4:D$4,0),FALSE),0)) -> 1350839.1 | L28: =SUM(IFERROR(VLOOKUP($B28&$C28,'C. Gestión Pto #1'!$B$4:K$17,MATCH(L$5,'C. Gestión Pto #1'!$B$4:K$4,0),FALSE),0),IFERROR(VLOOKUP($B28&$C28,'C. Gestión Pto #2'!$B$4:E$23,MATCH(L$5,'C. Gestión Pto #2'!$B$4:E$4,0),FALSE),0)) -> 261266.49 | M28: =SUM(IFERROR(VLOOKUP($B28&$C28,'C. Gestión Pto #1'!$B$4:L$17,MATCH(M$5,'C. Gestión Pto #1'!$B$4:L$4,0),FALSE),0),IFERROR(VLOOKUP($B28&$C28,'C. Gestión Pto #2'!$B$4:F$23,MATCH(M$5,'C. Gestión Pto #2'!$B$4:F$4,0),FALSE),0)) -> 950806.06 | N28: =SUM(IFERROR(VLOOKUP($B28&$C28,'C. Gestión Pto #1'!$B$4:M$17,MATCH(N$5,'C. Gestión Pto #1'!$B$4:M$4,0),FALSE),0),IFERROR(VLOOKUP($B28&$C28,'C. Gestión Pto #2'!$B$4:G$23,MATCH(N$5,'C. Gestión Pto #2'!$B$4:G$4,0),FALSE),0)) -> 230784.75 | O28: =SUM(IFERROR(VLOOKUP($B28&$C28,'C. Gestión Pto #1'!$B$4:N$17,MATCH(O$5,'C. Gestión Pto #1'!$B$4:N$4,0),FALSE),0),IFERROR(VLOOKUP($B28&$C28,'C. Gestión Pto #2'!$B$4:H$23,MATCH(O$5,'C. Gestión Pto #2'!$B$4:H$4,0),FALSE),0)) -> 6006212.1 | P28: =SUM(IFERROR(VLOOKUP($B28&$C28,'C. Gestión Pto #1'!$B$4:O$17,MATCH(P$5,'C. Gestión Pto #1'!$B$4:O$4,0),FALSE),0),IFERROR(VLOOKUP($B28&$C28,'C. Gestión Pto #2'!$B$4:I$23,MATCH(P$5,'C. Gestión Pto #2'!$B$4:I$4,0),FALSE),0)) -> 13136483 | Q28: =SUM(IFERROR(VLOOKUP($B28&$C28,'C. Gestión Pto #1'!$B$4:P$17,MATCH(Q$5,'C. Gestión Pto #1'!$B$4:P$4,0),FALSE),0),IFERROR(VLOOKUP($B28&$C28,'C. Gestión Pto #2'!$B$4:J$23,MATCH(Q$5,'C. Gestión Pto #2'!$B$4:J$4,0),FALSE),0)) -> 3423387.7 | ... T28: =SUM(IFERROR(VLOOKUP($B28&$C28,'C. Gestión Pto #1'!$B$4:S$17,MATCH(T$5,'C. Gestión Pto #1'!$B$4:S$4,0),FALSE),0),IFERROR(VLOOKUP($B28&$C28,'C. Gestión Pto #2'!$B$4:M$23,MATCH(T$5,'C. Gestión Pto #2'!$B$4:M$4,0),FALSE),0)) -> 934654.52 | V28: {=SUMPRODUCT($D28:$U28,TRANSPOSE('Indice CAC'!$C$10:$C$27))} -> 34151989 | X28: 0 | Y28: ='Resumen Pto #2'!R22 -> 31719694 | Z28: =SUM(X28:Y28) -> 31719694 | AA28: =IF(C28="MAT",SUMIF('Pto. 02 Cert.'!$A$10:$A$185,$B28,'Pto. 02 Cert.'!$T$10:$T$185),IF(C28="MO",SUMIF('Pto. 02 Cert.'!$A$10:$A$185,$B28,'Pto. 02 Cert.'!$U$10:$U$185),SUMIF('Pto. 02 Cert.'!$A$10:$A$185,$B28,'Pto. 02 Cert.'!$V$10:$V$185)))/IF(C28="MAT",SUMIF('Pto. 02 Cert.'!$A$10:$A$185,$B28,'Pto. 02 Cert.'!$I$10:$I$185),IF(C28="MO",SUMIF('Pto. 02 Cert.'!$A$10:$A$185,$B28,'Pto. 02 Cert.'!$J$10:$J$185),SUMIF('Pto. 02 Cert.'!$A$10:$A$185,$B28,'Pto. 02 Cert.'!$K$10:$K$185))) -> 0.44230624 | AB28: =IF(AA28=100%,0,IF(OR(V28<>0,Z28),Z28-V28)) -> -2432294.8 | AC28: =IF(OR(AB28<0,Z28),AB28/Z28,0%) -> -0.076680903 | AD28: =IF(AA28=100%,IF(OR(V28<>0,Z28),Z28-V28),0) -> 0
B29: Sanitaria | C29: MO | D29: =IFERROR(SUM(VLOOKUP($B29&$C29,'C. Gestión Pto #1'!$B$4:C$17,MATCH(D$5,'C. Gestión Pto #1'!$B$4:C$4,0),FALSE),0),0) -> 0 | E29: =IFERROR(SUM(VLOOKUP($B29&$C29,'C. Gestión Pto #1'!$B$4:D$17,MATCH(E$5,'C. Gestión Pto #1'!$B$4:D$4,0),FALSE),0),0) -> 0 | F29: =IFERROR(SUM(VLOOKUP($B29&$C29,'C. Gestión Pto #1'!$B$4:E$17,MATCH(F$5,'C. Gestión Pto #1'!$B$4:E$4,0),FALSE),0),0) -> 0 | G29: =IFERROR(SUM(VLOOKUP($B29&$C29,'C. Gestión Pto #1'!$B$4:F$17,MATCH(G$5,'C. Gestión Pto #1'!$B$4:F$4,0),FALSE),0),0) -> 0 | H29: =IFERROR(SUM(VLOOKUP($B29&$C29,'C. Gestión Pto #1'!$B$4:G$17,MATCH(H$5,'C. Gestión Pto #1'!$B$4:G$4,0),FALSE),0),0) -> 0 | I29: =IFERROR(SUM(VLOOKUP($B29&$C29,'C. Gestión Pto #1'!$B$4:H$17,MATCH(I$5,'C. Gestión Pto #1'!$B$4:H$4,0),FALSE),0),0) -> 0 | J29: =SUM(IFERROR(VLOOKUP($B29&$C29,'C. Gestión Pto #1'!$B$4:I$17,MATCH(J$5,'C. Gestión Pto #1'!$B$4:I$4,0),FALSE),0),IFERROR(VLOOKUP($B29&$C29,'C. Gestión Pto #2'!$B$4:C$23,MATCH(J$5,'C. Gestión Pto #2'!$B$4:C$4,0),FALSE),0)) -> 0 | K29: =SUM(IFERROR(VLOOKUP($B29&$C29,'C. Gestión Pto #1'!$B$4:J$17,MATCH(K$5,'C. Gestión Pto #1'!$B$4:J$4,0),FALSE),0),IFERROR(VLOOKUP($B29&$C29,'C. Gestión Pto #2'!$B$4:D$23,MATCH(K$5,'C. Gestión Pto #2'!$B$4:D$4,0),FALSE),0)) -> 0 | L29: =SUM(IFERROR(VLOOKUP($B29&$C29,'C. Gestión Pto #1'!$B$4:K$17,MATCH(L$5,'C. Gestión Pto #1'!$B$4:K$4,0),FALSE),0),IFERROR(VLOOKUP($B29&$C29,'C. Gestión Pto #2'!$B$4:E$23,MATCH(L$5,'C. Gestión Pto #2'!$B$4:E$4,0),FALSE),0)) -> 709198.46 | M29: =SUM(IFERROR(VLOOKUP($B29&$C29,'C. Gestión Pto #1'!$B$4:L$17,MATCH(M$5,'C. Gestión Pto #1'!$B$4:L$4,0),FALSE),0),IFERROR(VLOOKUP($B29&$C29,'C. Gestión Pto #2'!$B$4:F$23,MATCH(M$5,'C. Gestión Pto #2'!$B$4:F$4,0),FALSE),0)) -> 177942.15 | N29: =SUM(IFERROR(VLOOKUP($B29&$C29,'C. Gestión Pto #1'!$B$4:M$17,MATCH(N$5,'C. Gestión Pto #1'!$B$4:M$4,0),FALSE),0),IFERROR(VLOOKUP($B29&$C29,'C. Gestión Pto #2'!$B$4:G$23,MATCH(N$5,'C. Gestión Pto #2'!$B$4:G$4,0),FALSE),0)) -> 390000 | O29: =SUM(IFERROR(VLOOKUP($B29&$C29,'C. Gestión Pto #1'!$B$4:N$17,MATCH(O$5,'C. Gestión Pto #1'!$B$4:N$4,0),FALSE),0),IFERROR(VLOOKUP($B29&$C29,'C. Gestión Pto #2'!$B$4:H$23,MATCH(O$5,'C. Gestión Pto #2'!$B$4:H$4,0),FALSE),0)) -> 523583.1 | P29: =SUM(IFERROR(VLOOKUP($B29&$C29,'C. Gestión Pto #1'!$B$4:O$17,MATCH(P$5,'C. Gestión Pto #1'!$B$4:O$4,0),FALSE),0),IFERROR(VLOOKUP($B29&$C29,'C. Gestión Pto #2'!$B$4:I$23,MATCH(P$5,'C. Gestión Pto #2'!$B$4:I$4,0),FALSE),0)) -> 6425606.5 | Q29: =SUM(IFERROR(VLOOKUP($B29&$C29,'C. Gestión Pto #1'!$B$4:P$17,MATCH(Q$5,'C. Gestión Pto #1'!$B$4:P$4,0),FALSE),0),IFERROR(VLOOKUP($B29&$C29,'C. Gestión Pto #2'!$B$4:J$23,MATCH(Q$5,'C. Gestión Pto #2'!$B$4:J$4,0),FALSE),0)) -> 7858885.1 | ... T29: =SUM(IFERROR(VLOOKUP($B29&$C29,'C. Gestión Pto #1'!$B$4:S$17,MATCH(T$5,'C. Gestión Pto #1'!$B$4:S$4,0),FALSE),0),IFERROR(VLOOKUP($B29&$C29,'C. Gestión Pto #2'!$B$4:M$23,MATCH(T$5,'C. Gestión Pto #2'!$B$4:M$4,0),FALSE),0)) -> 10832622 | V29: {=SUMPRODUCT($D29:$U29,TRANSPOSE('Indice CAC'!$C$10:$C$27))} -> 36890057 | X29: 0 | Y29: ='Resumen Pto #2'!R23 -> 61809617 | Z29: =SUM(X29:Y29) -> 61809617 | AA29: =IF(C29="MAT",SUMIF('Pto. 02 Cert.'!$A$10:$A$185,$B29,'Pto. 02 Cert.'!$T$10:$T$185),IF(C29="MO",SUMIF('Pto. 02 Cert.'!$A$10:$A$185,$B29,'Pto. 02 Cert.'!$U$10:$U$185),SUMIF('Pto. 02 Cert.'!$A$10:$A$185,$B29,'Pto. 02 Cert.'!$V$10:$V$185)))/IF(C29="MAT",SUMIF('Pto. 02 Cert.'!$A$10:$A$185,$B29,'Pto. 02 Cert.'!$I$10:$I$185),IF(C29="MO",SUMIF('Pto. 02 Cert.'!$A$10:$A$185,$B29,'Pto. 02 Cert.'!$J$10:$J$185),SUMIF('Pto. 02 Cert.'!$A$10:$A$185,$B29,'Pto. 02 Cert.'!$K$10:$K$185))) -> 0.43165448 | AB29: =IF(AA29=100%,0,IF(OR(V29<>0,Z29),Z29-V29)) -> 24919560 | AC29: =IF(OR(AB29<0,Z29),AB29/Z29,0%) -> 0.40316638 | AD29: =IF(AA29=100%,IF(OR(V29<>0,Z29),Z29-V29),0) -> 0
B30: Revestimiento | C30: MO | D30: =IFERROR(SUM(VLOOKUP($B30&$C30,'C. Gestión Pto #1'!$B$4:C$17,MATCH(D$5,'C. Gestión Pto #1'!$B$4:C$4,0),FALSE),0),0) -> 0 | E30: =IFERROR(SUM(VLOOKUP($B30&$C30,'C. Gestión Pto #1'!$B$4:D$17,MATCH(E$5,'C. Gestión Pto #1'!$B$4:D$4,0),FALSE),0),0) -> 0 | F30: =IFERROR(SUM(VLOOKUP($B30&$C30,'C. Gestión Pto #1'!$B$4:E$17,MATCH(F$5,'C. Gestión Pto #1'!$B$4:E$4,0),FALSE),0),0) -> 0 | G30: =IFERROR(SUM(VLOOKUP($B30&$C30,'C. Gestión Pto #1'!$B$4:F$17,MATCH(G$5,'C. Gestión Pto #1'!$B$4:F$4,0),FALSE),0),0) -> 0 | H30: =IFERROR(SUM(VLOOKUP($B30&$C30,'C. Gestión Pto #1'!$B$4:G$17,MATCH(H$5,'C. Gestión Pto #1'!$B$4:G$4,0),FALSE),0),0) -> 0 | I30: =IFERROR(SUM(VLOOKUP($B30&$C30,'C. Gestión Pto #1'!$B$4:H$17,MATCH(I$5,'C. Gestión Pto #1'!$B$4:H$4,0),FALSE),0),0) -> 0 | J30: =SUM(IFERROR(VLOOKUP($B30&$C30,'C. Gestión Pto #1'!$B$4:I$17,MATCH(J$5,'C. Gestión Pto #1'!$B$4:I$4,0),FALSE),0),IFERROR(VLOOKUP($B30&$C30,'C. Gestión Pto #2'!$B$4:C$23,MATCH(J$5,'C. Gestión Pto #2'!$B$4:C$4,0),FALSE),0)) -> 0 | K30: =SUM(IFERROR(VLOOKUP($B30&$C30,'C. Gestión Pto #1'!$B$4:J$17,MATCH(K$5,'C. Gestión Pto #1'!$B$4:J$4,0),FALSE),0),IFERROR(VLOOKUP($B30&$C30,'C. Gestión Pto #2'!$B$4:D$23,MATCH(K$5,'C. Gestión Pto #2'!$B$4:D$4,0),FALSE),0)) -> 0 | L30: =SUM(IFERROR(VLOOKUP($B30&$C30,'C. Gestión Pto #1'!$B$4:K$17,MATCH(L$5,'C. Gestión Pto #1'!$B$4:K$4,0),FALSE),0),IFERROR(VLOOKUP($B30&$C30,'C. Gestión Pto #2'!$B$4:E$23,MATCH(L$5,'C. Gestión Pto #2'!$B$4:E$4,0),FALSE),0)) -> 0 | M30: =SUM(IFERROR(VLOOKUP($B30&$C30,'C. Gestión Pto #1'!$B$4:L$17,MATCH(M$5,'C. Gestión Pto #1'!$B$4:L$4,0),FALSE),0),IFERROR(VLOOKUP($B30&$C30,'C. Gestión Pto #2'!$B$4:F$23,MATCH(M$5,'C. Gestión Pto #2'!$B$4:F$4,0),FALSE),0)) -> 0 | N30: =SUM(IFERROR(VLOOKUP($B30&$C30,'C. Gestión Pto #1'!$B$4:M$17,MATCH(N$5,'C. Gestión Pto #1'!$B$4:M$4,0),FALSE),0),IFERROR(VLOOKUP($B30&$C30,'C. Gestión Pto #2'!$B$4:G$23,MATCH(N$5,'C. Gestión Pto #2'!$B$4:G$4,0),FALSE),0)) -> 0 | O30: =SUM(IFERROR(VLOOKUP($B30&$C30,'C. Gestión Pto #1'!$B$4:N$17,MATCH(O$5,'C. Gestión Pto #1'!$B$4:N$4,0),FALSE),0),IFERROR(VLOOKUP($B30&$C30,'C. Gestión Pto #2'!$B$4:H$23,MATCH(O$5,'C. Gestión Pto #2'!$B$4:H$4,0),FALSE),0)) -> 0 | P30: =SUM(IFERROR(VLOOKUP($B30&$C30,'C. Gestión Pto #1'!$B$4:O$17,MATCH(P$5,'C. Gestión Pto #1'!$B$4:O$4,0),FALSE),0),IFERROR(VLOOKUP($B30&$C30,'C. Gestión Pto #2'!$B$4:I$23,MATCH(P$5,'C. Gestión Pto #2'!$B$4:I$4,0),FALSE),0)) -> 0 | Q30: =SUM(IFERROR(VLOOKUP($B30&$C30,'C. Gestión Pto #1'!$B$4:P$17,MATCH(Q$5,'C. Gestión Pto #1'!$B$4:P$4,0),FALSE),0),IFERROR(VLOOKUP($B30&$C30,'C. Gestión Pto #2'!$B$4:J$23,MATCH(Q$5,'C. Gestión Pto #2'!$B$4:J$4,0),FALSE),0)) -> 0 | ... T30: =SUM(IFERROR(VLOOKUP($B30&$C30,'C. Gestión Pto #1'!$B$4:S$17,MATCH(T$5,'C. Gestión Pto #1'!$B$4:S$4,0),FALSE),0),IFERROR(VLOOKUP($B30&$C30,'C. Gestión Pto #2'!$B$4:M$23,MATCH(T$5,'C. Gestión Pto #2'!$B$4:M$4,0),FALSE),0)) -> 350000 | V30: {=SUMPRODUCT($D30:$U30,TRANSPOSE('Indice CAC'!$C$10:$C$27))} -> 3107555.7 | X30: 0 | Y30: ='Resumen Pto #2'!R24 -> 29057105 | Z30: =SUM(X30:Y30) -> 29057105 | AA30: =IF(C30="MAT",SUMIF('Pto. 02 Cert.'!$A$10:$A$185,$B30,'Pto. 02 Cert.'!$T$10:$T$185),IF(C30="MO",SUMIF('Pto. 02 Cert.'!$A$10:$A$185,$B30,'Pto. 02 Cert.'!$U$10:$U$185),SUMIF('Pto. 02 Cert.'!$A$10:$A$185,$B30,'Pto. 02 Cert.'!$V$10:$V$185)))/IF(C30="MAT",SUMIF('Pto. 02 Cert.'!$A$10:$A$185,$B30,'Pto. 02 Cert.'!$I$10:$I$185),IF(C30="MO",SUMIF('Pto. 02 Cert.'!$A$10:$A$185,$B30,'Pto. 02 Cert.'!$J$10:$J$185),SUMIF('Pto. 02 Cert.'!$A$10:$A$185,$B30,'Pto. 02 Cert.'!$K$10:$K$185))) -> 0.097485725 | AB30: =IF(AA30=100%,0,IF(OR(V30<>0,Z30),Z30-V30)) -> 25949549 | AC30: =IF(OR(AB30<0,Z30),AB30/Z30,0%) -> 0.8930535 | AD30: =IF(AA30=100%,IF(OR(V30<>0,Z30),Z30-V30),0) -> 0
B31: Revestimiento | C31: MAT | D31: =IFERROR(SUM(VLOOKUP($B31&$C31,'C. Gestión Pto #1'!$B$4:C$17,MATCH(D$5,'C. Gestión Pto #1'!$B$4:C$4,0),FALSE),0),0) -> 0 | E31: =IFERROR(SUM(VLOOKUP($B31&$C31,'C. Gestión Pto #1'!$B$4:D$17,MATCH(E$5,'C. Gestión Pto #1'!$B$4:D$4,0),FALSE),0),0) -> 0 | F31: =IFERROR(SUM(VLOOKUP($B31&$C31,'C. Gestión Pto #1'!$B$4:E$17,MATCH(F$5,'C. Gestión Pto #1'!$B$4:E$4,0),FALSE),0),0) -> 0 | G31: =IFERROR(SUM(VLOOKUP($B31&$C31,'C. Gestión Pto #1'!$B$4:F$17,MATCH(G$5,'C. Gestión Pto #1'!$B$4:F$4,0),FALSE),0),0) -> 0 | H31: =IFERROR(SUM(VLOOKUP($B31&$C31,'C. Gestión Pto #1'!$B$4:G$17,MATCH(H$5,'C. Gestión Pto #1'!$B$4:G$4,0),FALSE),0),0) -> 0 | I31: =IFERROR(SUM(VLOOKUP($B31&$C31,'C. Gestión Pto #1'!$B$4:H$17,MATCH(I$5,'C. Gestión Pto #1'!$B$4:H$4,0),FALSE),0),0) -> 0 | J31: =SUM(IFERROR(VLOOKUP($B31&$C31,'C. Gestión Pto #1'!$B$4:I$17,MATCH(J$5,'C. Gestión Pto #1'!$B$4:I$4,0),FALSE),0),IFERROR(VLOOKUP($B31&$C31,'C. Gestión Pto #2'!$B$4:C$23,MATCH(J$5,'C. Gestión Pto #2'!$B$4:C$4,0),FALSE),0)) -> 0 | K31: =SUM(IFERROR(VLOOKUP($B31&$C31,'C. Gestión Pto #1'!$B$4:J$17,MATCH(K$5,'C. Gestión Pto #1'!$B$4:J$4,0),FALSE),0),IFERROR(VLOOKUP($B31&$C31,'C. Gestión Pto #2'!$B$4:D$23,MATCH(K$5,'C. Gestión Pto #2'!$B$4:D$4,0),FALSE),0)) -> 0 | L31: =SUM(IFERROR(VLOOKUP($B31&$C31,'C. Gestión Pto #1'!$B$4:K$17,MATCH(L$5,'C. Gestión Pto #1'!$B$4:K$4,0),FALSE),0),IFERROR(VLOOKUP($B31&$C31,'C. Gestión Pto #2'!$B$4:E$23,MATCH(L$5,'C. Gestión Pto #2'!$B$4:E$4,0),FALSE),0)) -> 0 | M31: =SUM(IFERROR(VLOOKUP($B31&$C31,'C. Gestión Pto #1'!$B$4:L$17,MATCH(M$5,'C. Gestión Pto #1'!$B$4:L$4,0),FALSE),0),IFERROR(VLOOKUP($B31&$C31,'C. Gestión Pto #2'!$B$4:F$23,MATCH(M$5,'C. Gestión Pto #2'!$B$4:F$4,0),FALSE),0)) -> 0 | N31: =SUM(IFERROR(VLOOKUP($B31&$C31,'C. Gestión Pto #1'!$B$4:M$17,MATCH(N$5,'C. Gestión Pto #1'!$B$4:M$4,0),FALSE),0),IFERROR(VLOOKUP($B31&$C31,'C. Gestión Pto #2'!$B$4:G$23,MATCH(N$5,'C. Gestión Pto #2'!$B$4:G$4,0),FALSE),0)) -> 0 | O31: =SUM(IFERROR(VLOOKUP($B31&$C31,'C. Gestión Pto #1'!$B$4:N$17,MATCH(O$5,'C. Gestión Pto #1'!$B$4:N$4,0),FALSE),0),IFERROR(VLOOKUP($B31&$C31,'C. Gestión Pto #2'!$B$4:H$23,MATCH(O$5,'C. Gestión Pto #2'!$B$4:H$4,0),FALSE),0)) -> 4076500 | P31: =SUM(IFERROR(VLOOKUP($B31&$C31,'C. Gestión Pto #1'!$B$4:O$17,MATCH(P$5,'C. Gestión Pto #1'!$B$4:O$4,0),FALSE),0),IFERROR(VLOOKUP($B31&$C31,'C. Gestión Pto #2'!$B$4:I$23,MATCH(P$5,'C. Gestión Pto #2'!$B$4:I$4,0),FALSE),0)) -> 0 | Q31: =SUM(IFERROR(VLOOKUP($B31&$C31,'C. Gestión Pto #1'!$B$4:P$17,MATCH(Q$5,'C. Gestión Pto #1'!$B$4:P$4,0),FALSE),0),IFERROR(VLOOKUP($B31&$C31,'C. Gestión Pto #2'!$B$4:J$23,MATCH(Q$5,'C. Gestión Pto #2'!$B$4:J$4,0),FALSE),0)) -> 0 | ... T31: =SUM(IFERROR(VLOOKUP($B31&$C31,'C. Gestión Pto #1'!$B$4:S$17,MATCH(T$5,'C. Gestión Pto #1'!$B$4:S$4,0),FALSE),0),IFERROR(VLOOKUP($B31&$C31,'C. Gestión Pto #2'!$B$4:M$23,MATCH(T$5,'C. Gestión Pto #2'!$B$4:M$4,0),FALSE),0)) -> 0 | V31: {=SUMPRODUCT($D31:$U31,TRANSPOSE('Indice CAC'!$C$10:$C$27))} -> 9212674 | X31: 0 | Y31: ='Resumen Pto #2'!R25 -> 32520619 | Z31: =SUM(X31:Y31) -> 32520619 | AA31: =IF(C31="MAT",SUMIF('Pto. 02 Cert.'!$A$10:$A$185,$B31,'Pto. 02 Cert.'!$T$10:$T$185),IF(C31="MO",SUMIF('Pto. 02 Cert.'!$A$10:$A$185,$B31,'Pto. 02 Cert.'!$U$10:$U$185),SUMIF('Pto. 02 Cert.'!$A$10:$A$185,$B31,'Pto. 02 Cert.'!$V$10:$V$185)))/IF(C31="MAT",SUMIF('Pto. 02 Cert.'!$A$10:$A$185,$B31,'Pto. 02 Cert.'!$I$10:$I$185),IF(C31="MO",SUMIF('Pto. 02 Cert.'!$A$10:$A$185,$B31,'Pto. 02 Cert.'!$J$10:$J$185),SUMIF('Pto. 02 Cert.'!$A$10:$A$185,$B31,'Pto. 02 Cert.'!$K$10:$K$185))) -> 0.3451504 | AB31: =IF(AA31=100%,0,IF(OR(V31<>0,Z31),Z31-V31)) -> 23307945 | AC31: =IF(OR(AB31<0,Z31),AB31/Z31,0%) -> 0.71671284 | AD31: =IF(AA31=100%,IF(OR(V31<>0,Z31),Z31-V31),0) -> 0
B32: Termomecánica | C32: MAT | D32: =IFERROR(SUM(VLOOKUP($B32&$C32,'C. Gestión Pto #1'!$B$4:C$17,MATCH(D$5,'C. Gestión Pto #1'!$B$4:C$4,0),FALSE),0),0) -> 0 | E32: =IFERROR(SUM(VLOOKUP($B32&$C32,'C. Gestión Pto #1'!$B$4:D$17,MATCH(E$5,'C. Gestión Pto #1'!$B$4:D$4,0),FALSE),0),0) -> 0 | F32: =IFERROR(SUM(VLOOKUP($B32&$C32,'C. Gestión Pto #1'!$B$4:E$17,MATCH(F$5,'C. Gestión Pto #1'!$B$4:E$4,0),FALSE),0),0) -> 0 | G32: =IFERROR(SUM(VLOOKUP($B32&$C32,'C. Gestión Pto #1'!$B$4:F$17,MATCH(G$5,'C. Gestión Pto #1'!$B$4:F$4,0),FALSE),0),0) -> 0 | H32: =IFERROR(SUM(VLOOKUP($B32&$C32,'C. Gestión Pto #1'!$B$4:G$17,MATCH(H$5,'C. Gestión Pto #1'!$B$4:G$4,0),FALSE),0),0) -> 0 | I32: =IFERROR(SUM(VLOOKUP($B32&$C32,'C. Gestión Pto #1'!$B$4:H$17,MATCH(I$5,'C. Gestión Pto #1'!$B$4:H$4,0),FALSE),0),0) -> 0 | J32: =SUM(IFERROR(VLOOKUP($B32&$C32,'C. Gestión Pto #1'!$B$4:I$17,MATCH(J$5,'C. Gestión Pto #1'!$B$4:I$4,0),FALSE),0),IFERROR(VLOOKUP($B32&$C32,'C. Gestión Pto #2'!$B$4:C$23,MATCH(J$5,'C. Gestión Pto #2'!$B$4:C$4,0),FALSE),0)) -> 0 | K32: =SUM(IFERROR(VLOOKUP($B32&$C32,'C. Gestión Pto #1'!$B$4:J$17,MATCH(K$5,'C. Gestión Pto #1'!$B$4:J$4,0),FALSE),0),IFERROR(VLOOKUP($B32&$C32,'C. Gestión Pto #2'!$B$4:D$23,MATCH(K$5,'C. Gestión Pto #2'!$B$4:D$4,0),FALSE),0)) -> 0 | L32: =SUM(IFERROR(VLOOKUP($B32&$C32,'C. Gestión Pto #1'!$B$4:K$17,MATCH(L$5,'C. Gestión Pto #1'!$B$4:K$4,0),FALSE),0),IFERROR(VLOOKUP($B32&$C32,'C. Gestión Pto #2'!$B$4:E$23,MATCH(L$5,'C. Gestión Pto #2'!$B$4:E$4,0),FALSE),0)) -> 0 | M32: =SUM(IFERROR(VLOOKUP($B32&$C32,'C. Gestión Pto #1'!$B$4:L$17,MATCH(M$5,'C. Gestión Pto #1'!$B$4:L$4,0),FALSE),0),IFERROR(VLOOKUP($B32&$C32,'C. Gestión Pto #2'!$B$4:F$23,MATCH(M$5,'C. Gestión Pto #2'!$B$4:F$4,0),FALSE),0)) -> 0 | N32: =SUM(IFERROR(VLOOKUP($B32&$C32,'C. Gestión Pto #1'!$B$4:M$17,MATCH(N$5,'C. Gestión Pto #1'!$B$4:M$4,0),FALSE),0),IFERROR(VLOOKUP($B32&$C32,'C. Gestión Pto #2'!$B$4:G$23,MATCH(N$5,'C. Gestión Pto #2'!$B$4:G$4,0),FALSE),0)) -> 0 | O32: =SUM(IFERROR(VLOOKUP($B32&$C32,'C. Gestión Pto #1'!$B$4:N$17,MATCH(O$5,'C. Gestión Pto #1'!$B$4:N$4,0),FALSE),0),IFERROR(VLOOKUP($B32&$C32,'C. Gestión Pto #2'!$B$4:H$23,MATCH(O$5,'C. Gestión Pto #2'!$B$4:H$4,0),FALSE),0)) -> 0 | P32: =SUM(IFERROR(VLOOKUP($B32&$C32,'C. Gestión Pto #1'!$B$4:O$17,MATCH(P$5,'C. Gestión Pto #1'!$B$4:O$4,0),FALSE),0),IFERROR(VLOOKUP($B32&$C32,'C. Gestión Pto #2'!$B$4:I$23,MATCH(P$5,'C. Gestión Pto #2'!$B$4:I$4,0),FALSE),0)) -> 0 | Q32: =SUM(IFERROR(VLOOKUP($B32&$C32,'C. Gestión Pto #1'!$B$4:P$17,MATCH(Q$5,'C. Gestión Pto #1'!$B$4:P$4,0),FALSE),0),IFERROR(VLOOKUP($B32&$C32,'C. Gestión Pto #2'!$B$4:J$23,MATCH(Q$5,'C. Gestión Pto #2'!$B$4:J$4,0),FALSE),0)) -> 0 | ... T32: =SUM(IFERROR(VLOOKUP($B32&$C32,'C. Gestión Pto #1'!$B$4:S$17,MATCH(T$5,'C. Gestión Pto #1'!$B$4:S$4,0),FALSE),0),IFERROR(VLOOKUP($B32&$C32,'C. Gestión Pto #2'!$B$4:M$23,MATCH(T$5,'C. Gestión Pto #2'!$B$4:M$4,0),FALSE),0)) -> 0 | V32: {=SUMPRODUCT($D32:$U32,TRANSPOSE('Indice CAC'!$C$10:$C$27))} -> 0 | X32: 0 | Y32: ='Resumen Pto #2'!R26 -> 13500000 | Z32: =SUM(X32:Y32) -> 13500000 | AA32: =IF(C32="MAT",SUMIF('Pto. 02 Cert.'!$A$10:$A$185,$B32,'Pto. 02 Cert.'!$T$10:$T$185),IF(C32="MO",SUMIF('Pto. 02 Cert.'!$A$10:$A$185,$B32,'Pto. 02 Cert.'!$U$10:$U$185),SUMIF('Pto. 02 Cert.'!$A$10:$A$185,$B32,'Pto. 02 Cert.'!$V$10:$V$185)))/IF(C32="MAT",SUMIF('Pto. 02 Cert.'!$A$10:$A$185,$B32,'Pto. 02 Cert.'!$I$10:$I$185),IF(C32="MO",SUMIF('Pto. 02 Cert.'!$A$10:$A$185,$B32,'Pto. 02 Cert.'!$J$10:$J$185),SUMIF('Pto. 02 Cert.'!$A$10:$A$185,$B32,'Pto. 02 Cert.'!$K$10:$K$185))) -> 0.8 | AB32: =IF(AA32=100%,0,IF(OR(V32<>0,Z32),Z32-V32)) -> 13500000 | AC32: =IF(OR(AB32<0,Z32),AB32/Z32,0%) -> 1 | AD32: =IF(AA32=100%,IF(OR(V32<>0,Z32),Z32-V32),0) -> 0
B33: Termomecánica | C33: MO | D33: =IFERROR(SUM(VLOOKUP($B33&$C33,'C. Gestión Pto #1'!$B$4:C$17,MATCH(D$5,'C. Gestión Pto #1'!$B$4:C$4,0),FALSE),0),0) -> 0 | E33: =IFERROR(SUM(VLOOKUP($B33&$C33,'C. Gestión Pto #1'!$B$4:D$17,MATCH(E$5,'C. Gestión Pto #1'!$B$4:D$4,0),FALSE),0),0) -> 0 | F33: =IFERROR(SUM(VLOOKUP($B33&$C33,'C. Gestión Pto #1'!$B$4:E$17,MATCH(F$5,'C. Gestión Pto #1'!$B$4:E$4,0),FALSE),0),0) -> 0 | G33: =IFERROR(SUM(VLOOKUP($B33&$C33,'C. Gestión Pto #1'!$B$4:F$17,MATCH(G$5,'C. Gestión Pto #1'!$B$4:F$4,0),FALSE),0),0) -> 0 | H33: =IFERROR(SUM(VLOOKUP($B33&$C33,'C. Gestión Pto #1'!$B$4:G$17,MATCH(H$5,'C. Gestión Pto #1'!$B$4:G$4,0),FALSE),0),0) -> 0 | I33: =IFERROR(SUM(VLOOKUP($B33&$C33,'C. Gestión Pto #1'!$B$4:H$17,MATCH(I$5,'C. Gestión Pto #1'!$B$4:H$4,0),FALSE),0),0) -> 0 | J33: =SUM(IFERROR(VLOOKUP($B33&$C33,'C. Gestión Pto #1'!$B$4:I$17,MATCH(J$5,'C. Gestión Pto #1'!$B$4:I$4,0),FALSE),0),IFERROR(VLOOKUP($B33&$C33,'C. Gestión Pto #2'!$B$4:C$23,MATCH(J$5,'C. Gestión Pto #2'!$B$4:C$4,0),FALSE),0)) -> 0 | K33: =SUM(IFERROR(VLOOKUP($B33&$C33,'C. Gestión Pto #1'!$B$4:J$17,MATCH(K$5,'C. Gestión Pto #1'!$B$4:J$4,0),FALSE),0),IFERROR(VLOOKUP($B33&$C33,'C. Gestión Pto #2'!$B$4:D$23,MATCH(K$5,'C. Gestión Pto #2'!$B$4:D$4,0),FALSE),0)) -> 0 | L33: =SUM(IFERROR(VLOOKUP($B33&$C33,'C. Gestión Pto #1'!$B$4:K$17,MATCH(L$5,'C. Gestión Pto #1'!$B$4:K$4,0),FALSE),0),IFERROR(VLOOKUP($B33&$C33,'C. Gestión Pto #2'!$B$4:E$23,MATCH(L$5,'C. Gestión Pto #2'!$B$4:E$4,0),FALSE),0)) -> 0 | M33: =SUM(IFERROR(VLOOKUP($B33&$C33,'C. Gestión Pto #1'!$B$4:L$17,MATCH(M$5,'C. Gestión Pto #1'!$B$4:L$4,0),FALSE),0),IFERROR(VLOOKUP($B33&$C33,'C. Gestión Pto #2'!$B$4:F$23,MATCH(M$5,'C. Gestión Pto #2'!$B$4:F$4,0),FALSE),0)) -> 0 | N33: =SUM(IFERROR(VLOOKUP($B33&$C33,'C. Gestión Pto #1'!$B$4:M$17,MATCH(N$5,'C. Gestión Pto #1'!$B$4:M$4,0),FALSE),0),IFERROR(VLOOKUP($B33&$C33,'C. Gestión Pto #2'!$B$4:G$23,MATCH(N$5,'C. Gestión Pto #2'!$B$4:G$4,0),FALSE),0)) -> 0 | O33: =SUM(IFERROR(VLOOKUP($B33&$C33,'C. Gestión Pto #1'!$B$4:N$17,MATCH(O$5,'C. Gestión Pto #1'!$B$4:N$4,0),FALSE),0),IFERROR(VLOOKUP($B33&$C33,'C. Gestión Pto #2'!$B$4:H$23,MATCH(O$5,'C. Gestión Pto #2'!$B$4:H$4,0),FALSE),0)) -> 0 | P33: =SUM(IFERROR(VLOOKUP($B33&$C33,'C. Gestión Pto #1'!$B$4:O$17,MATCH(P$5,'C. Gestión Pto #1'!$B$4:O$4,0),FALSE),0),IFERROR(VLOOKUP($B33&$C33,'C. Gestión Pto #2'!$B$4:I$23,MATCH(P$5,'C. Gestión Pto #2'!$B$4:I$4,0),FALSE),0)) -> 4235000 | Q33: =SUM(IFERROR(VLOOKUP($B33&$C33,'C. Gestión Pto #1'!$B$4:P$17,MATCH(Q$5,'C. Gestión Pto #1'!$B$4:P$4,0),FALSE),0),IFERROR(VLOOKUP($B33&$C33,'C. Gestión Pto #2'!$B$4:J$23,MATCH(Q$5,'C. Gestión Pto #2'!$B$4:J$4,0),FALSE),0)) -> 0 | ... T33: =SUM(IFERROR(VLOOKUP($B33&$C33,'C. Gestión Pto #1'!$B$4:S$17,MATCH(T$5,'C. Gestión Pto #1'!$B$4:S$4,0),FALSE),0),IFERROR(VLOOKUP($B33&$C33,'C. Gestión Pto #2'!$B$4:M$23,MATCH(T$5,'C. Gestión Pto #2'!$B$4:M$4,0),FALSE),0)) -> 0 | V33: {=SUMPRODUCT($D33:$U33,TRANSPOSE('Indice CAC'!$C$10:$C$27))} -> 8173029.4 | X33: 0 | Y33: ='Resumen Pto #2'!R27 -> 14504000 | Z33: =SUM(X33:Y33) -> 14504000 | AA33: =IF(C33="MAT",SUMIF('Pto. 02 Cert.'!$A$10:$A$185,$B33,'Pto. 02 Cert.'!$T$10:$T$185),IF(C33="MO",SUMIF('Pto. 02 Cert.'!$A$10:$A$185,$B33,'Pto. 02 Cert.'!$U$10:$U$185),SUMIF('Pto. 02 Cert.'!$A$10:$A$185,$B33,'Pto. 02 Cert.'!$V$10:$V$185)))/IF(C33="MAT",SUMIF('Pto. 02 Cert.'!$A$10:$A$185,$B33,'Pto. 02 Cert.'!$I$10:$I$185),IF(C33="MO",SUMIF('Pto. 02 Cert.'!$A$10:$A$185,$B33,'Pto. 02 Cert.'!$J$10:$J$185),SUMIF('Pto. 02 Cert.'!$A$10:$A$185,$B33,'Pto. 02 Cert.'!$K$10:$K$185))) -> 0.42471087 | AB33: =IF(AA33=100%,0,IF(OR(V33<>0,Z33),Z33-V33)) -> 6330970.6 | AC33: =IF(OR(AB33<0,Z33),AB33/Z33,0%) -> 0.43649825 | AD33: =IF(AA33=100%,IF(OR(V33<>0,Z33),Z33-V33),0) -> 0
B34: Equipos | D34: =IFERROR(SUM(VLOOKUP($B34&$C34,'C. Gestión Pto #1'!$B$4:C$17,MATCH(D$5,'C. Gestión Pto #1'!$B$4:C$4,0),FALSE),0),0) -> 296509.21 | E34: =IFERROR(SUM(VLOOKUP($B34&$C34,'C. Gestión Pto #1'!$B$4:D$17,MATCH(E$5,'C. Gestión Pto #1'!$B$4:D$4,0),FALSE),0),0) -> 257327.67 | F34: =IFERROR(SUM(VLOOKUP($B34&$C34,'C. Gestión Pto #1'!$B$4:E$17,MATCH(F$5,'C. Gestión Pto #1'!$B$4:E$4,0),FALSE),0),0) -> 257327.67 | G34: =IFERROR(SUM(VLOOKUP($B34&$C34,'C. Gestión Pto #1'!$B$4:F$17,MATCH(G$5,'C. Gestión Pto #1'!$B$4:F$4,0),FALSE),0),0) -> 290739.63 | H34: =IFERROR(SUM(VLOOKUP($B34&$C34,'C. Gestión Pto #1'!$B$4:G$17,MATCH(H$5,'C. Gestión Pto #1'!$B$4:G$4,0),FALSE),0),0) -> 296307.18 | I34: =IFERROR(SUM(VLOOKUP($B34&$C34,'C. Gestión Pto #1'!$B$4:H$17,MATCH(I$5,'C. Gestión Pto #1'!$B$4:H$4,0),FALSE),0),0) -> 301650.01 | J34: =SUM(IFERROR(VLOOKUP($B34&$C34,'C. Gestión Pto #1'!$B$4:I$17,MATCH(J$5,'C. Gestión Pto #1'!$B$4:I$4,0),FALSE),0),IFERROR(VLOOKUP($B34&$C34,'C. Gestión Pto #2'!$B$4:C$23,MATCH(J$5,'C. Gestión Pto #2'!$B$4:C$4,0),FALSE),0)) -> 315509.7 | K34: =SUM(IFERROR(VLOOKUP($B34&$C34,'C. Gestión Pto #1'!$B$4:J$17,MATCH(K$5,'C. Gestión Pto #1'!$B$4:J$4,0),FALSE),0),IFERROR(VLOOKUP($B34&$C34,'C. Gestión Pto #2'!$B$4:D$23,MATCH(K$5,'C. Gestión Pto #2'!$B$4:D$4,0),FALSE),0)) -> 525701.05 | L34: =SUM(IFERROR(VLOOKUP($B34&$C34,'C. Gestión Pto #1'!$B$4:K$17,MATCH(L$5,'C. Gestión Pto #1'!$B$4:K$4,0),FALSE),0),IFERROR(VLOOKUP($B34&$C34,'C. Gestión Pto #2'!$B$4:E$23,MATCH(L$5,'C. Gestión Pto #2'!$B$4:E$4,0),FALSE),0)) -> 562300.63 | M34: =SUM(IFERROR(VLOOKUP($B34&$C34,'C. Gestión Pto #1'!$B$4:L$17,MATCH(M$5,'C. Gestión Pto #1'!$B$4:L$4,0),FALSE),0),IFERROR(VLOOKUP($B34&$C34,'C. Gestión Pto #2'!$B$4:F$23,MATCH(M$5,'C. Gestión Pto #2'!$B$4:F$4,0),FALSE),0)) -> 589101.04 | N34: =SUM(IFERROR(VLOOKUP($B34&$C34,'C. Gestión Pto #1'!$B$4:M$17,MATCH(N$5,'C. Gestión Pto #1'!$B$4:M$4,0),FALSE),0),IFERROR(VLOOKUP($B34&$C34,'C. Gestión Pto #2'!$B$4:G$23,MATCH(N$5,'C. Gestión Pto #2'!$B$4:G$4,0),FALSE),0)) -> 574796.94 | O34: =SUM(IFERROR(VLOOKUP($B34&$C34,'C. Gestión Pto #1'!$B$4:N$17,MATCH(O$5,'C. Gestión Pto #1'!$B$4:N$4,0),FALSE),0),IFERROR(VLOOKUP($B34&$C34,'C. Gestión Pto #2'!$B$4:H$23,MATCH(O$5,'C. Gestión Pto #2'!$B$4:H$4,0),FALSE),0)) -> 594839.99 | P34: =SUM(IFERROR(VLOOKUP($B34&$C34,'C. Gestión Pto #1'!$B$4:O$17,MATCH(P$5,'C. Gestión Pto #1'!$B$4:O$4,0),FALSE),0),IFERROR(VLOOKUP($B34&$C34,'C. Gestión Pto #2'!$B$4:I$23,MATCH(P$5,'C. Gestión Pto #2'!$B$4:I$4,0),FALSE),0)) -> 617445.23 | Q34: =SUM(IFERROR(VLOOKUP($B34&$C34,'C. Gestión Pto #1'!$B$4:P$17,MATCH(Q$5,'C. Gestión Pto #1'!$B$4:P$4,0),FALSE),0),IFERROR(VLOOKUP($B34&$C34,'C. Gestión Pto #2'!$B$4:J$23,MATCH(Q$5,'C. Gestión Pto #2'!$B$4:J$4,0),FALSE),0)) -> 637742.13 | ... T34: =SUM(IFERROR(VLOOKUP($B34&$C34,'C. Gestión Pto #1'!$B$4:S$17,MATCH(T$5,'C. Gestión Pto #1'!$B$4:S$4,0),FALSE),0),IFERROR(VLOOKUP($B34&$C34,'C. Gestión Pto #2'!$B$4:M$23,MATCH(T$5,'C. Gestión Pto #2'!$B$4:M$4,0),FALSE),0)) -> 702737.42 | V34: {=SUMPRODUCT($D34:$U34,TRANSPOSE('Indice CAC'!$C$10:$C$27))} -> 6427885.8 | X34: ='Resumen Pto #1'!X24 -> 12019074 | Y34: ='Resumen Pto #2'!R28 -> 8515663.9 | Z34: =SUM(X34:Y34) -> 20534738 | AA34: =SUM('Pto. 01 Cert.'!$S$58,'Pto. 02 Cert.'!$S$186)/SUM('Pto. 01 Cert.'!$L$58,'Pto. Vta.'!$L$239) -> 0.64279413 | AB34: =IF(AA34=100%,0,IF(OR(V34<>0,Z34),Z34-V34)) -> 14106852 | AC34: =IF(OR(AB34<0,Z34),AB34/Z34,0%) -> 0.68697503 | AD34: =IF(AA34=100%,IF(OR(V34<>0,Z34),Z34-V34),0) -> 0
B35: Gastos Generales Obra | D35: =IFERROR(SUM(VLOOKUP($B35&$C35,'C. Gestión Pto #1'!$B$4:C$17,MATCH(D$5,'C. Gestión Pto #1'!$B$4:C$4,0),FALSE),0),0) -> 0 | E35: =IFERROR(SUM(VLOOKUP($B35&$C35,'C. Gestión Pto #1'!$B$4:D$17,MATCH(E$5,'C. Gestión Pto #1'!$B$4:D$4,0),FALSE),0),0) -> 165000 | F35: =IFERROR(SUM(VLOOKUP($B35&$C35,'C. Gestión Pto #1'!$B$4:E$17,MATCH(F$5,'C. Gestión Pto #1'!$B$4:E$4,0),FALSE),0),0) -> 80000 | G35: =IFERROR(SUM(VLOOKUP($B35&$C35,'C. Gestión Pto #1'!$B$4:F$17,MATCH(G$5,'C. Gestión Pto #1'!$B$4:F$4,0),FALSE),0),0) -> 237000 | H35: =IFERROR(SUM(VLOOKUP($B35&$C35,'C. Gestión Pto #1'!$B$4:G$17,MATCH(H$5,'C. Gestión Pto #1'!$B$4:G$4,0),FALSE),0),0) -> 337000 | I35: =IFERROR(SUM(VLOOKUP($B35&$C35,'C. Gestión Pto #1'!$B$4:H$17,MATCH(I$5,'C. Gestión Pto #1'!$B$4:H$4,0),FALSE),0),0) -> 543000 | J35: =SUM(IFERROR(VLOOKUP($B35&$C35,'C. Gestión Pto #1'!$B$4:I$17,MATCH(J$5,'C. Gestión Pto #1'!$B$4:I$4,0),FALSE),0),IFERROR(VLOOKUP($B35&$C35,'C. Gestión Pto #2'!$B$4:C$23,MATCH(J$5,'C. Gestión Pto #2'!$B$4:C$4,0),FALSE),0)) -> 256958.68 | K35: =SUM(IFERROR(VLOOKUP($B35&$C35,'C. Gestión Pto #1'!$B$4:J$17,MATCH(K$5,'C. Gestión Pto #1'!$B$4:J$4,0),FALSE),0),IFERROR(VLOOKUP($B35&$C35,'C. Gestión Pto #2'!$B$4:D$23,MATCH(K$5,'C. Gestión Pto #2'!$B$4:D$4,0),FALSE),0)) -> 425200 | L35: =SUM(IFERROR(VLOOKUP($B35&$C35,'C. Gestión Pto #1'!$B$4:K$17,MATCH(L$5,'C. Gestión Pto #1'!$B$4:K$4,0),FALSE),0),IFERROR(VLOOKUP($B35&$C35,'C. Gestión Pto #2'!$B$4:E$23,MATCH(L$5,'C. Gestión Pto #2'!$B$4:E$4,0),FALSE),0)) -> 246000 | M35: =SUM(IFERROR(VLOOKUP($B35&$C35,'C. Gestión Pto #1'!$B$4:L$17,MATCH(M$5,'C. Gestión Pto #1'!$B$4:L$4,0),FALSE),0),IFERROR(VLOOKUP($B35&$C35,'C. Gestión Pto #2'!$B$4:F$23,MATCH(M$5,'C. Gestión Pto #2'!$B$4:F$4,0),FALSE),0)) -> 479500 | N35: =SUM(IFERROR(VLOOKUP($B35&$C35,'C. Gestión Pto #1'!$B$4:M$17,MATCH(N$5,'C. Gestión Pto #1'!$B$4:M$4,0),FALSE),0),IFERROR(VLOOKUP($B35&$C35,'C. Gestión Pto #2'!$B$4:G$23,MATCH(N$5,'C. Gestión Pto #2'!$B$4:G$4,0),FALSE),0)) -> 0 | O35: =SUM(IFERROR(VLOOKUP($B35&$C35,'C. Gestión Pto #1'!$B$4:N$17,MATCH(O$5,'C. Gestión Pto #1'!$B$4:N$4,0),FALSE),0),IFERROR(VLOOKUP($B35&$C35,'C. Gestión Pto #2'!$B$4:H$23,MATCH(O$5,'C. Gestión Pto #2'!$B$4:H$4,0),FALSE),0)) -> 0 | P35: =SUM(IFERROR(VLOOKUP($B35&$C35,'C. Gestión Pto #1'!$B$4:O$17,MATCH(P$5,'C. Gestión Pto #1'!$B$4:O$4,0),FALSE),0),IFERROR(VLOOKUP($B35&$C35,'C. Gestión Pto #2'!$B$4:I$23,MATCH(P$5,'C. Gestión Pto #2'!$B$4:I$4,0),FALSE),0)) -> 1142857.1 | Q35: =SUM(IFERROR(VLOOKUP($B35&$C35,'C. Gestión Pto #1'!$B$4:P$17,MATCH(Q$5,'C. Gestión Pto #1'!$B$4:P$4,0),FALSE),0),IFERROR(VLOOKUP($B35&$C35,'C. Gestión Pto #2'!$B$4:J$23,MATCH(Q$5,'C. Gestión Pto #2'!$B$4:J$4,0),FALSE),0)) -> 26363.64 | ... T35: =SUM(IFERROR(VLOOKUP($B35&$C35,'C. Gestión Pto #1'!$B$4:S$17,MATCH(T$5,'C. Gestión Pto #1'!$B$4:S$4,0),FALSE),0),IFERROR(VLOOKUP($B35&$C35,'C. Gestión Pto #2'!$B$4:M$23,MATCH(T$5,'C. Gestión Pto #2'!$B$4:M$4,0),FALSE),0)) -> 120000 | V35: {=SUMPRODUCT($D35:$U35,TRANSPOSE('Indice CAC'!$C$10:$C$27))} -> 4401625.8 | X35: ='Resumen Pto #1'!X25 -> 2875034.6 | Y35: ='Resumen Pto #2'!R29 -> 1200000 | Z35: =SUM(X35:Y35) -> 4075034.6 | AA35: =SUM(IF(C35="MAT",SUMIF('Pto. 01 Cert.'!$A$10:$A$57,$B35,'Pto. 01 Cert.'!$T$10:$T$57),IF(C35="MO",SUMIF('Pto. 01 Cert.'!$A$10:$A$57,$B35,'Pto. 01 Cert.'!$U$10:$U$57),SUMIF('Pto. 01 Cert.'!$A$10:$A$57,$B35,'Pto. 01 Cert.'!$V$10:$V$57))),IF(C35="MAT",SUMIF('Pto. 02 Cert.'!$A$10:$A$185,$B35,'Pto. 02 Cert.'!$T$10:$T$185),IF(C35="MO",SUMIF('Pto. 02 Cert.'!$A$10:$A$185,$B35,'Pto. 02 Cert.'!$U$10:$U$185),SUMIF('Pto. 02 Cert.'!$A$10:$A$185,$B35,'Pto. 02 Cert.'!$V$10:$V$185))))/SUM(IF(C35="MAT",SUMIF('Pto. 01 Cert.'!$A$10:$A$57,$B35,'Pto. 01 Cert.'!$I$10:$I$57),IF(C35="MO",SUMIF('Pto. 01 Cert.'!$A$10:$A$57,$B35,'Pto. 01 Cert.'!$J$10:$J$57),SUMIF('Pto. 01 Cert.'!$A$10:$A$57,$B35,'Pto. 01 Cert.'!$K$10:$K$57))),IF(C35="MAT",SUMIF('Pto. 02 Cert.'!$A$10:$A$185,$B35,'Pto. 02 Cert.'!$I$10:$I$185),IF(C35="MO",SUMIF('Pto. 02 Cert.'!$A$10:$A$185,$B35,'Pto. 02 Cert.'!$J$10:$J$185),SUMIF('Pto. 02 Cert.'!$A$10:$A$185,$B35,'Pto. 02 Cert.'!$K$10:$K$185)))) -> 0.79282792 | AB35: =IF(AA35=100%,0,IF(OR(V35<>0,Z35),Z35-V35)) -> -326591.18 | AC35: =IF(OR(AB35<0,Z35),AB35/Z35,0%) -> -0.080144394 | AD35: =IF(AA35=100%,IF(OR(V35<>0,Z35),Z35-V35),0) -> 0
B36: Total Egresos de Obra | D36: =SUM(D13:D35) -> 2791690.9 | E36: =SUM(E13:E35) -> 19290264 | F36: =SUM(F13:F35) -> 15080680 | G36: =SUM(G13:G35) -> 36876762 | H36: =SUM(H13:H35) -> 33325537 | I36: =SUM(I13:I35) -> 37246119 | J36: =SUM(J13:J35) -> 33274495 | K36: =SUM(K13:K35) -> 41941759 | ... T36: =SUM(T13:T35) -> 1.0996398e+08 | V36: =SUM(V13:V35) -> 7.0677291e+08 | X36: =SUM(X13:X35) -> 3.1604063e+08 | Y36: =SUM(Y13:Y35) -> 5.8100225e+08 | Z36: =SUM(Z13:Z35) -> 8.9704289e+08 | AB36: =SUM(AB13:AB35) -> 2.543417e+08 | AC36: =IF(OR(AB36<0,Z36),AB36/Z36,0%) -> 0.28353349 | AD36: =SUM(AD13:AD35) -> -64071725
B38: Gastos Generales
B39: Gastos Directos | D39: =SUM(VLOOKUP($B39,'C. Gestión Pto #1'!$B$34:L$34,MATCH('Resumen Pto #1'!D$5,'C. Gestión Pto #1'!$B$20:L$20,0),0),0) -> 966547.14 | E39: =SUM(VLOOKUP($B39,'C. Gestión Pto #1'!$B$34:M$34,MATCH('Resumen Pto #1'!E$5,'C. Gestión Pto #1'!$B$20:M$20,0),0),0) -> 724628.24 | F39: =SUM(VLOOKUP($B39,'C. Gestión Pto #1'!$B$34:N$34,MATCH('Resumen Pto #1'!F$5,'C. Gestión Pto #1'!$B$20:N$20,0),0),0) -> 2047489.7 | G39: =SUM(VLOOKUP($B39,'C. Gestión Pto #1'!$B$34:O$34,MATCH('Resumen Pto #1'!G$5,'C. Gestión Pto #1'!$B$20:O$20,0),0),0) -> 1556001.8 | H39: =SUM(VLOOKUP($B39,'C. Gestión Pto #1'!$B$34:P$34,MATCH('Resumen Pto #1'!H$5,'C. Gestión Pto #1'!$B$20:P$20,0),0),0) -> 1451425.4 | I39: =SUM(VLOOKUP($B39,'C. Gestión Pto #1'!$B$34:Q$34,MATCH('Resumen Pto #1'!I$5,'C. Gestión Pto #1'!$B$20:Q$20,0),0),0) -> 1216663.4 | J39: =SUM(VLOOKUP($B39,'C. Gestión Pto #1'!$B$34:R$34,MATCH('Resumen Pto #1'!J$5,'C. Gestión Pto #1'!$B$20:R$20,0),0),VLOOKUP($B39,'C. Gestión Pto #2'!$B$41:J$41,MATCH('Resumen Pto #2'!D$5,'C. Gestión Pto #2'!$B$27:J$27,0),0)) -> 2128961.3 | K39: =SUM(VLOOKUP($B39,'C. Gestión Pto #1'!$B$34:S$34,MATCH('Resumen Pto #1'!K$5,'C. Gestión Pto #1'!$B$20:S$20,0),0),VLOOKUP($B39,'C. Gestión Pto #2'!$B$41:K$41,MATCH('Resumen Pto #2'!E$5,'C. Gestión Pto #2'!$B$27:K$27,0),0)) -> 3072710.3 | L39: =SUM(VLOOKUP($B39,'C. Gestión Pto #1'!$B$34:T$34,MATCH('Resumen Pto #1'!L$5,'C. Gestión Pto #1'!$B$20:T$20,0),0),VLOOKUP($B39,'C. Gestión Pto #2'!$B$41:L$41,MATCH('Resumen Pto #2'!F$5,'C. Gestión Pto #2'!$B$27:L$27,0),0)) -> 2114569.7 | M39: =SUM(VLOOKUP($B39,'C. Gestión Pto #1'!$B$34:U$34,MATCH('Resumen Pto #1'!M$5,'C. Gestión Pto #1'!$B$20:U$20,0),0),VLOOKUP($B39,'C. Gestión Pto #2'!$B$41:M$41,MATCH('Resumen Pto #2'!G$5,'C. Gestión Pto #2'!$B$27:M$27,0),0)) -> 2962726.9 | N39: =SUM(VLOOKUP($B39,'C. Gestión Pto #1'!$B$34:V$34,MATCH('Resumen Pto #1'!N$5,'C. Gestión Pto #1'!$B$20:V$20,0),0),VLOOKUP($B39,'C. Gestión Pto #2'!$B$41:N$41,MATCH('Resumen Pto #2'!H$5,'C. Gestión Pto #2'!$B$27:N$27,0),0)) -> 2897224.5 | O39: =SUM(VLOOKUP($B39,'C. Gestión Pto #1'!$B$34:W$34,MATCH('Resumen Pto #1'!O$5,'C. Gestión Pto #1'!$B$20:W$20,0),0),VLOOKUP($B39,'C. Gestión Pto #2'!$B$41:O$41,MATCH('Resumen Pto #2'!I$5,'C. Gestión Pto #2'!$B$27:O$27,0),0)) -> 4034621.5 | P39: =SUM(VLOOKUP($B39,'C. Gestión Pto #1'!$B$34:X$34,MATCH('Resumen Pto #1'!P$5,'C. Gestión Pto #1'!$B$20:X$20,0),0),VLOOKUP($B39,'C. Gestión Pto #2'!$B$41:P$41,MATCH('Resumen Pto #2'!J$5,'C. Gestión Pto #2'!$B$27:P$27,0),0)) -> 2054329.6 | Q39: =SUM(VLOOKUP($B39,'C. Gestión Pto #1'!$B$34:Y$34,MATCH('Resumen Pto #1'!Q$5,'C. Gestión Pto #1'!$B$20:Y$20,0),0),VLOOKUP($B39,'C. Gestión Pto #2'!$B$41:Q$41,MATCH('Resumen Pto #2'!K$5,'C. Gestión Pto #2'!$B$27:Q$27,0),0)) -> 2194576 | ... T39: =SUM(VLOOKUP($B39,'C. Gestión Pto #1'!$B$34:AB$34,MATCH('Resumen Pto #1'!T$5,'C. Gestión Pto #1'!$B$20:AB$20,0),0),VLOOKUP($B39,'C. Gestión Pto #2'!$B$41:T$41,MATCH('Resumen Pto #2'!N$5,'C. Gestión Pto #2'!$B$27:T$27,0),0)) -> 3047610.9 | V39: {=SUMPRODUCT($D39:$U39,TRANSPOSE('Indice CAC'!$C$10:$C$27))} -> 29444130 | X39: ='Resumen Pto #1'!X29 -> 20045880 | Y39: ='Resumen Pto #2'!T33 -> 23362296 | Z39: =SUM(X39:Y39)*sept24 -> 43408176 | AA39: =SUM('Pto. 01 Cert.'!$S$58,'Pto. 02 Cert.'!$S$186)/SUM('Pto. 01 Cert.'!$L$58,'Pto. Vta.'!$L$239) -> 0.64279413 | AB39: =IF(AA39=100%,0,IF(OR(V39<>0,Z39),Z39-V39)) -> 13964046 | AC39: =IF(OR(AB39<0,Z39),AB39/Z39,0%) -> 0.3216916 | AD39: =IF(OR(V39<>0,Z39),Z39-V39,) -> 13964046
B40: Gastos Indirectos | D40: =SUM(VLOOKUP($B40,'C. Gestión Pto #1'!$B$39:L$39,MATCH('Resumen Pto #1'!D$5,'C. Gestión Pto #1'!$B$36:L$36,0),0),0) -> 1825790.3 | E40: =SUM(VLOOKUP($B40,'C. Gestión Pto #1'!$B$39:M$39,MATCH('Resumen Pto #1'!E$5,'C. Gestión Pto #1'!$B$36:M$36,0),0),0) -> 1368018.8 | F40: =SUM(VLOOKUP($B40,'C. Gestión Pto #1'!$B$39:N$39,MATCH('Resumen Pto #1'!F$5,'C. Gestión Pto #1'!$B$36:N$36,0),0),0) -> 2137192 | G40: =SUM(VLOOKUP($B40,'C. Gestión Pto #1'!$B$39:O$39,MATCH('Resumen Pto #1'!G$5,'C. Gestión Pto #1'!$B$36:O$36,0),0),0) -> 2169029.3 | H40: =SUM(VLOOKUP($B40,'C. Gestión Pto #1'!$B$39:P$39,MATCH('Resumen Pto #1'!H$5,'C. Gestión Pto #1'!$B$36:P$36,0),0),0) -> 1800256.2 | I40: =SUM(VLOOKUP($B40,'C. Gestión Pto #1'!$B$39:Q$39,MATCH('Resumen Pto #1'!I$5,'C. Gestión Pto #1'!$B$36:Q$36,0),0),0) -> 2949259.1 | J40: =VLOOKUP($B40,'C. Gestión Pto #1'!$B$39:R$39,MATCH('Resumen Pto #1'!J$5,'C. Gestión Pto #1'!$B$36:R$36,0),0) -> 1800256.2 | K40: =VLOOKUP($B40,'C. Gestión Pto #1'!$B$39:S$39,MATCH('Resumen Pto #1'!K$5,'C. Gestión Pto #1'!$B$36:S$36,0),0) -> 2235375.3 | L40: =VLOOKUP($B40,'C. Gestión Pto #1'!$B$39:T$39,MATCH('Resumen Pto #1'!L$5,'C. Gestión Pto #1'!$B$36:T$36,0),0) -> 3075477.6 | M40: =VLOOKUP($B40,'C. Gestión Pto #1'!$B$39:U$39,MATCH('Resumen Pto #1'!M$5,'C. Gestión Pto #1'!$B$36:U$36,0),0) -> 2221900.7 | N40: =VLOOKUP($B40,'C. Gestión Pto #1'!$B$39:V$39,MATCH('Resumen Pto #1'!N$5,'C. Gestión Pto #1'!$B$36:V$36,0),0) -> 2220557.8 | O40: =SUM(VLOOKUP($B40,'C. Gestión Pto #1'!$B$39:W$39,MATCH('Resumen Pto #1'!O$5,'C. Gestión Pto #1'!$B$36:W$36,0),0),VLOOKUP($B40,'C. Gestión Pto #2'!$B$46:$W$46,MATCH('Resumen General'!O$5,'C. Gestión Pto #2'!$B$43:$W$43,0))) -> 3192269.4 | P40: =SUM(VLOOKUP($B40,'C. Gestión Pto #1'!$B$39:X$39,MATCH('Resumen Pto #1'!P$5,'C. Gestión Pto #1'!$B$36:X$36,0),0),VLOOKUP($B40,'C. Gestión Pto #2'!$B$46:$W$46,MATCH('Resumen General'!P$5,'C. Gestión Pto #2'!$B$43:$W$43,0))) -> 2546573.8 | Q40: =SUM(VLOOKUP($B40,'C. Gestión Pto #1'!$B$39:Y$39,MATCH('Resumen Pto #1'!Q$5,'C. Gestión Pto #1'!$B$36:Y$36,0),0),VLOOKUP($B40,'C. Gestión Pto #2'!$B$46:$W$46,MATCH('Resumen General'!Q$5,'C. Gestión Pto #2'!$B$43:$W$43,0))) -> 2601372.3 | R40: =SUM(VLOOKUP($B40,'C. Gestión Pto #1'!$B$39:Z$39,MATCH('Resumen Pto #1'!R$5,'C. Gestión Pto #1'!$B$36:Z$36,0),0),VLOOKUP($B40,'C. Gestión Pto #2'!$B$46:$W$46,MATCH('Resumen General'!R$5,'C. Gestión Pto #2'!$B$43:$W$43,0))) -> 2601372.3 | S40: =SUM(VLOOKUP($B40,'C. Gestión Pto #1'!$B$39:AA$39,MATCH('Resumen Pto #1'!S$5,'C. Gestión Pto #1'!$B$36:AA$36,0),0),VLOOKUP($B40,'C. Gestión Pto #2'!$B$46:$W$46,MATCH('Resumen General'!S$5,'C. Gestión Pto #2'!$B$43:$W$43,0))) -> 2830419.6 | T40: =SUM(VLOOKUP($B40,'C. Gestión Pto #1'!$B$39:AB$39,MATCH('Resumen Pto #1'!T$5,'C. Gestión Pto #1'!$B$36:AB$36,0),0),VLOOKUP($B40,'C. Gestión Pto #2'!$B$46:$W$46,MATCH('Resumen General'!T$5,'C. Gestión Pto #2'!$B$43:$W$43,0))) -> 2750603.9 | V40: {=SUMPRODUCT($D40:$U40,TRANSPOSE('Indice CAC'!$C$10:$C$27))} -> 32336031 | X40: ='Resumen Pto #1'!X30 -> 21358198 | Y40: ='Resumen Pto #2'!T34 -> 25250157 | Z40: =SUM(X40:Y40)*sept24 -> 46608355 | AA40: =SUM('Pto. 01 Cert.'!$S$58,'Pto. 02 Cert.'!$S$186)/SUM('Pto. 01 Cert.'!$L$58,'Pto. Vta.'!$L$239) -> 0.64279413 | AB40: =IF(AA40=100%,0,IF(OR(V40<>0,Z40),Z40-V40)) -> 14272324 | AC40: =IF(OR(AB40<0,Z40),AB40/Z40,0%) -> 0.30621814 | AD40: =IF(OR(V40<>0,Z40),Z40-V40,) -> 14272324
B41: Total Gastos Generales | D41: =SUM(D39:D40) -> 2792337.4 | E41: =SUM(E39:E40) -> 2092647 | F41: =SUM(F39:F40) -> 4184681.7 | G41: =SUM(G39:G40) -> 3725031.1 | H41: =SUM(H39:H40) -> 3251681.6 | I41: =SUM(I39:I40) -> 4165922.5 | J41: =SUM(J39:J40) -> 3929217.5 | K41: =SUM(K39:K40) -> 5308085.6 | ... T41: =SUM(T39:T40) -> 5798214.7 | V41: =SUM(V39:V40) -> 61780162 | X41: =SUM(X39:X40) -> 41404078 | Y41: =SUM(Y39:Y40) -> 48612453 | Z41: =SUM(Z39:Z40) -> 90016531 | AB41: =SUM(AB39:AB40) -> 28236370 | AC41: =IF(OR(AB41<0,Z41),AB41/Z41,0%) -> 0.31367982 | AD41: =SUM(AD39:AD40) -> 28236370
B43: Total Egresos | D43: =D36+D41 -> 5584028.3 | E43: =E36+E41 -> 21382911 | F43: =F36+F41 -> 19265361 | G43: =G36+G41 -> 40601793 | H43: =H36+H41 -> 36577219 | I43: =I36+I41 -> 41412041 | J43: =J36+J41 -> 37203713 | K43: =K36+K41 -> 47249845 | ... T43: =T36+T41 -> 1.1576219e+08 | V43: =V36+V41 -> 7.6855307e+08 | X43: =X36+X41 -> 3.5744471e+08 | Y43: =Y36+Y41 -> 6.2961471e+08 | Z43: =Z36+Z41 -> 9.8705942e+08
B45: Resultado Operativo | D45: =SUM(D8,D10,-D43) -> -5584028.3 | E45: =SUM(E8,E10,-E43) -> -9132911.2 | F45: =SUM(F8,F10,-F43) -> 58549221 | G45: =SUM(G8,G10,-G43) -> -9276297.1 | H45: =SUM(H8,H10,-H43) -> -4273907.6 | I45: =SUM(I8,I10,-I43) -> -14408318 | J45: =SUM(J8,J10,-J43) -> -8901450.5 | K45: =SUM(K8,K10,-K43) -> -9522756.9 | ... T45: =SUM(T8,T10,-T43) -> -58607258 | V45: =V8-V43 -> 1.0260792e+08
B46: Resultado Acumulado | D46: =D45 -> -5584028.3 | E46: =E45+D46 -> -14716940 | F46: =F45+E46 -> 43832282 | G46: =G45+F46 -> 34555985 | H46: =H45+G46 -> 30282077 | I46: =I45+H46 -> 15873759 | J46: =J45+I46 -> 6972308.9 | K46: =K45+J46 -> -2550448 | L46: =L45+K46 -> 11115044 | ... T46: =T45+S46 -> 52708785
B48: Resultado Operativo USD | D48: =D45/VLOOKUP(EOMONTH(DATE(2025,COLUMN(A1),1),0),'TC USD MEP'!$B$6:$C$1808,2,0) -> -4794.0215 | E48: =E45/VLOOKUP(EOMONTH(DATE(2025,COLUMN(B1),1),0),'TC USD MEP'!$B$6:$C$1808,2,0) -> -7434.3182 | F48: =F45/VLOOKUP(EOMONTH(DATE(2025,COLUMN(C1),1),0),'TC USD MEP'!$B$6:$C$1808,2,0) -> 44559.024 | G48: =G45/VLOOKUP(EOMONTH(DATE(2025,COLUMN(D1),1),0),'TC USD MEP'!$B$6:$C$1808,2,0) -> -7838.8814 | H48: =H45/VLOOKUP(EOMONTH(DATE(2025,COLUMN(E1),1),0),'TC USD MEP'!$B$6:$C$1808,2,0) -> -3586.3354 | I48: =I45/VLOOKUP(EOMONTH(DATE(2025,COLUMN(F1),1),0),'TC USD MEP'!$B$6:$C$1808,2,0) -> -11896.885 | J48: =J45/VLOOKUP(EOMONTH(DATE(2025,COLUMN(G1),1),0),'TC USD MEP'!$B$6:$C$1808,2,0) -> -6546.3395 | K48: =K45/VLOOKUP(EOMONTH(DATE(2025,COLUMN(H1),1),0),'TC USD MEP'!$B$6:$C$1808,2,0) -> -7015.7491 | ... O48: =O45/VLOOKUP(EOMONTH(DATE(2025,COLUMN(L1),1),0),'TC USD MEP'!$B$6:$C$1808,2,0) -> 869.92902 | P48: =P45/VLOOKUP(EOMONTH(DATE(2026,COLUMN(A1),1),0),'TC USD MEP'!$B$6:$C$1808,2,0) -> -39205.221 | Q48: =Q45/VLOOKUP(EOMONTH(DATE(2026,COLUMN(B1),1),0),'TC USD MEP'!$B$6:$C$1808,2,0) -> -14880.587 | R48: =R45/VLOOKUP(EOMONTH(DATE(2026,COLUMN(C1),1),0),'TC USD MEP'!$B$6:$C$1808,2,0) -> -41771.585 | S48: =S45/VLOOKUP(EOMONTH(DATE(2026,COLUMN(D1),1),0),'TC USD MEP'!$B$6:$C$1808,2,0) -> -51695.69 | T48: =T45/VLOOKUP(EOMONTH(DATE(2026,COLUMN(E1),1),0),'TC USD MEP'!$B$6:$C$1808,2,0) -> #N/A
B49: Resultado Acumulado USD | D49: =D48 -> -4794.0215 | E49: =E48+D49 -> -12228.34 | F49: =F48+E49 -> 32330.685 | G49: =G48+F49 -> 24491.803 | H49: =H48+G49 -> 20905.468 | I49: =I48+H49 -> 9008.5827 | J49: =J48+I49 -> 2462.2433 | K49: =K48+J49 -> -4553.5058 | L49: =L48+K49 -> 4593.2877 | ... T49: =T48+S49 -> #N/A

Sheet Resumen Pto #1
AC1: Actualizado | AD1: ='C. Gestión Pto #1'!V1 -> 46174
B3: OBRA: SVD 4140
B4: RESUMEN DE OBRA
D5: 45658 | E5: 45689 | F5: 45717 | G5: 45748 | H5: 45778 | I5: 45809 | J5: 45839 | K5: 45870 | L5: 45901 | M5: 45931 | N5: 45962 | O5: 45992 | P5: 46023 | Q5: 46054 | R5: 46082 | S5: 46113 | T5: 46143 | V5: Acum. Descontado | X5: Previsto Etapa Hormigón | Y5: % Cert. Acum. | Z5: Saldo Disponible | AA5: Disponible % | AB5: Rubro Completado
B6: Ingresos de Obra
B7: Ingresos por certificados | D7: =SUM(SUMIFS(Facturacion!$E$11:$E$64,Facturacion!$A$11:$A$64,">="&DATE(2024,12,1),Facturacion!$A$11:$A$64,"<="&DATE(2024,12,31),Facturacion!$C$11:$C$64,Facturacion!$C$4),SUMIFS(Facturacion!$E$11:$E$64,Facturacion!$A$11:$A$64,">="&DATE(2024,12,1),Facturacion!$A$11:$A$64,"<="&DATE(2024,12,31),Facturacion!$C$11:$C$64,Facturacion!#REF!),SUMIFS(Facturacion!$E$11:$E$64,Facturacion!$A$11:$A$64,">="&DATE(2024,12,1),Facturacion!$A$11:$A$64,"<="&DATE(2024,12,31),Facturacion!$C$11:$C$64,Facturacion!$C$5)) -> 0 | E7: =SUM(SUMIFS(Facturacion!$E$11:$E$64,Facturacion!$A$11:$A$64,">="&DATE(2025,2,1),Facturacion!$A$11:$A$64,"<="&DATE(2025,2,28),Facturacion!$C$11:$C$64,Facturacion!$C$4),SUMIFS(Facturacion!$E$11:$E$64,Facturacion!$A$11:$A$64,">="&DATE(2025,2,1),Facturacion!$A$11:$A$64,"<="&DATE(2025,2,28),Facturacion!$C$11:$C$64,Facturacion!#REF!),SUMIFS(Facturacion!$E$11:$E$64,Facturacion!$A$11:$A$64,">="&DATE(2025,2,1),Facturacion!$A$11:$A$64,"<="&DATE(2025,2,28),Facturacion!$C$11:$C$64,Facturacion!$C$5)) -> 11515000 | F7: =SUM(SUMIFS(Facturacion!$E$11:$E$64,Facturacion!$A$11:$A$64,">="&DATE(2025,3,1),Facturacion!$A$11:$A$64,"<="&DATE(2025,3,31),Facturacion!$C$11:$C$64,Facturacion!$C$4)) -> 72746210 | G7: =SUM(SUMIFS(Facturacion!$E$11:$E$64,Facturacion!$A$11:$A$64,">="&DATE(2025,4,1),Facturacion!$A$11:$A$64,"<="&DATE(2025,4,30),Facturacion!$C$11:$C$64,Facturacion!$C$4)) -> 28390040 | H7: =SUM(SUMIFS(Facturacion!$E$11:$E$64,Facturacion!$A$11:$A$64,">="&DATE(2025,5,1),Facturacion!$A$11:$A$64,"<="&DATE(2025,5,31),Facturacion!$C$11:$C$64,Facturacion!$C$4)) -> 28932600 | I7: =SUM(SUMIFS(Facturacion!$E$11:$E$64,Facturacion!$A$11:$A$64,">="&DATE(2025,6,1),Facturacion!$A$11:$A$64,"<="&DATE(2025,6,30),Facturacion!$C$11:$C$64,Facturacion!$C$4)) -> 23665294 | J7: =SUM(SUMIFS(Facturacion!$E$11:$E$64,Facturacion!$A$11:$A$64,">="&DATE(2025,7,1),Facturacion!$A$11:$A$64,"<="&DATE(2025,7,31),Facturacion!$C$11:$C$64,Facturacion!$C$4)) -> 24611609 | K7: =SUM(SUMIFS(Facturacion!$E$11:$E$64,Facturacion!$A$11:$A$64,">="&DATE(2025,8,1),Facturacion!$A$11:$A$64,"<="&DATE(2025,8,31),Facturacion!$C$11:$C$64,Facturacion!$C$4)) -> 32566741 | L7: =SUM(SUMIFS(Facturacion!$E$11:$E$64,Facturacion!$A$11:$A$64,">="&DATE(2025,9,1),Facturacion!$A$11:$A$64,"<="&DATE(2025,9,30),Facturacion!$C$11:$C$64,Facturacion!$C$4)) -> 48704739 | M7: =SUM(SUMIFS(Facturacion!$E$11:$E$64,Facturacion!$A$11:$A$64,">="&DATE(2025,10,1),Facturacion!$A$11:$A$64,"<="&DATE(2025,10,30),Facturacion!$C$11:$C$64,Facturacion!$C$4)) -> 16380000 | N7: =SUM(SUMIFS(Facturacion!$E$11:$E$64,Facturacion!$A$11:$A$64,">="&DATE(2025,11,1),Facturacion!$A$11:$A$64,"<="&DATE(2025,11,30),Facturacion!$C$11:$C$64,Facturacion!$C$4)) -> 35338659 | O7: =SUM(SUMIFS(Facturacion!$E$11:$E$64,Facturacion!$A$11:$A$64,">="&DATE(2025,12,1),Facturacion!$A$11:$A$64,"<="&DATE(2025,12,31),Facturacion!$C$11:$C$64,Facturacion!$C$4)) -> 48233236 | P7: =SUM(SUMIFS(Facturacion!$E$11:$E$64,Facturacion!$A$11:$A$64,">="&DATE(2026,1,1),Facturacion!$A$11:$A$64,"<="&DATE(2026,1,31),Facturacion!$C$11:$C$64,Facturacion!$C$4)) -> 19659972 | Q7: =SUM(SUMIFS(Facturacion!$E$11:$E$64,Facturacion!$A$11:$A$64,">="&DATE(2026,2,1),Facturacion!$A$11:$A$64,"<="&DATE(2026,2,28),Facturacion!$C$11:$C$64,Facturacion!$C$4)) -> 24825507 | R7: =SUM(SUMIFS(Facturacion!$E$11:$E$64,Facturacion!$A$11:$A$64,">="&DATE(2026,3,1),Facturacion!$A$11:$A$64,"<="&DATE(2026,3,31),Facturacion!$C$11:$C$64,Facturacion!$C$4)) -> 6545705 | S7: =SUM(SUMIFS(Facturacion!$E$11:$E$64,Facturacion!$A$11:$A$64,">="&DATE(2026,4,1),Facturacion!$A$11:$A$64,"<="&DATE(2026,4,30),Facturacion!$C$11:$C$64,Facturacion!$C$4)) -> 0 | T7: =SUM(SUMIFS(Facturacion!$E$11:$E$64,Facturacion!$A$11:$A$64,">="&DATE(2026,5,1),Facturacion!$A$11:$A$64,"<="&DATE(2026,5,31),Facturacion!$C$11:$C$64,Facturacion!$C$4)) -> 0 | V7: =SUM(D7:U7) -> 4.2211531e+08 | X7: =Facturacion!E4 -> 421306052 | Y7: ='Pto. 01 Cert.'!$S$58/'Pto. 01 Cert.'!$L$58 -> 1.0029914 | Z7: =IF(Y7=100%,0,IF(OR(V7<>0,X7),X7-V7)) -> -809260.27 | AA7: =IF(OR(Z7<0,X7),Z7/X7,0%) -> -0.001920837 | AB7: =IF(Y7=100%,IF(OR(V7<>0,X7),X7-V7),0) -> 0
B8: Total Ingresos de Obra | D8: =SUM(D7) -> 0 | E8: =SUM(E7) -> 11515000 | F8: =SUM(F7) -> 72746210 | G8: =SUM(G7) -> 28390040 | H8: =SUM(H7) -> 28932600 | I8: =SUM(I7) -> 23665294 | J8: =SUM(J7) -> 24611609 | K8: =SUM(K7) -> 32566741 | ... T8: =SUM(T7) -> 0 | V8: =SUM(V7) -> 4.2211531e+08 | X8: =SUM(X7) -> 421306052 | Z8: =SUM(Z7) -> -809260.27 | AA8: =IF(OR(Z8<0,X8),Z8/X8,0%) -> -0.001920837 | AB8: =SUM(AB7) -> 0
B9: Actualización por CAC | D9: =SUM(SUMIFS(Facturacion!$F$11:$F$64,Facturacion!$A$11:$A$64,">="&DATE(2024,12,1),Facturacion!$A$11:$A$64,"<="&DATE(2024,12,31),Facturacion!$J$11:$J$64,Facturacion!$J$4),SUMIFS(Facturacion!$F$11:$F$64,Facturacion!$A$11:$A$64,">="&DATE(2024,12,1),Facturacion!$A$11:$A$64,"<="&DATE(2024,12,31),Facturacion!$J$11:$J$64,Facturacion!$J$5)) -> 0 | E9: =SUM(SUMIFS(Facturacion!$F$11:$F$64,Facturacion!$A$11:$A$64,">="&DATE(2025,2,1),Facturacion!$A$11:$A$64,"<="&DATE(2025,2,28),Facturacion!$J$11:$J$64,Facturacion!$J$4),SUMIFS(Facturacion!$F$11:$F$64,Facturacion!$A$11:$A$64,">="&DATE(2025,2,1),Facturacion!$A$11:$A$64,"<="&DATE(2025,2,28),Facturacion!$J$11:$J$64,Facturacion!$J$5)) -> 735000 | F9: =SUM(SUMIFS(Facturacion!$F$11:$F$64,Facturacion!$A$11:$A$64,">="&DATE(2025,3,1),Facturacion!$A$11:$A$64,"<="&DATE(2025,3,31),Facturacion!$J$11:$J$64,Facturacion!$J$4)) -> 5068372.2 | G9: =SUM(SUMIFS(Facturacion!$F$11:$F$64,Facturacion!$A$11:$A$64,">="&DATE(2025,4,1),Facturacion!$A$11:$A$64,"<="&DATE(2025,4,30),Facturacion!$J$11:$J$64,Facturacion!$J$4)) -> 2935456.1 | H9: =SUM(SUMIFS(Facturacion!$F$11:$F$64,Facturacion!$A$11:$A$64,">="&DATE(2025,5,1),Facturacion!$A$11:$A$64,"<="&DATE(2025,5,31),Facturacion!$J$11:$J$64,Facturacion!$J$4)) -> 3370711.7 | I9: =SUM(SUMIFS(Facturacion!$F$11:$F$64,Facturacion!$A$11:$A$64,">="&DATE(2025,6,1),Facturacion!$A$11:$A$64,"<="&DATE(2025,6,30),Facturacion!$J$11:$J$64,Facturacion!$J$4)) -> 3338429.3 | J9: =SUM(SUMIFS(Facturacion!$F$11:$F$64,Facturacion!$A$11:$A$64,">="&DATE(2025,7,1),Facturacion!$A$11:$A$64,"<="&DATE(2025,7,31),Facturacion!$J$11:$J$64,Facturacion!$J$4)) -> 3690653.5 | K9: =SUM(SUMIFS(Facturacion!$F$11:$F$64,Facturacion!$A$11:$A$64,">="&DATE(2025,8,1),Facturacion!$A$11:$A$64,"<="&DATE(2025,8,31),Facturacion!$J$11:$J$64,Facturacion!$J$4)) -> 5160346.8 | L9: =SUM(SUMIFS(Facturacion!$F$11:$F$64,Facturacion!$A$11:$A$64,">="&DATE(2025,9,1),Facturacion!$A$11:$A$64,"<="&DATE(2025,9,30),Facturacion!$J$11:$J$64,Facturacion!$J$4)) -> 8721283.8 | M9: =SUM(SUMIFS(Facturacion!$F$11:$F$64,Facturacion!$A$11:$A$64,">="&DATE(2025,10,1),Facturacion!$A$11:$A$64,"<="&DATE(2025,10,30),Facturacion!$J$11:$J$64,Facturacion!$J$4)) -> 6994348.2 | N9: =SUM(SUMIFS(Facturacion!$F$11:$F$64,Facturacion!$A$11:$A$64,">="&DATE(2025,11,1),Facturacion!$A$11:$A$64,"<="&DATE(2025,11,30),Facturacion!$J$11:$J$64,Facturacion!$J$4)) -> 8289315.1 | O9: =SUM(SUMIFS(Facturacion!$F$11:$F$64,Facturacion!$A$11:$A$64,">="&DATE(2025,12,1),Facturacion!$A$11:$A$64,"<="&DATE(2025,12,31),Facturacion!$J$11:$J$64,Facturacion!$J$4)) -> 11945758 | P9: =SUM(SUMIFS(Facturacion!$F$11:$F$64,Facturacion!$A$11:$A$64,">="&DATE(2026,1,1),Facturacion!$A$11:$A$64,"<="&DATE(2026,1,31),Facturacion!$J$11:$J$64,Facturacion!$J$4)) -> 5703580 | Q9: =SUM(SUMIFS(Facturacion!$F$11:$F$64,Facturacion!$A$11:$A$64,">="&DATE(2026,2,1),Facturacion!$A$11:$A$64,"<="&DATE(2026,2,28),Facturacion!$J$11:$J$64,Facturacion!$J$4)) -> 7619636.5 | R9: =SUM(SUMIFS(Facturacion!$F$11:$F$64,Facturacion!$A$11:$A$64,">="&DATE(2026,3,1),Facturacion!$A$11:$A$64,"<="&DATE(2026,3,31),Facturacion!$J$11:$J$64,Facturacion!$J$4)) -> 2206292 | S9: =SUM(SUMIFS(Facturacion!$F$11:$F$64,Facturacion!$A$11:$A$64,">="&DATE(2026,4,1),Facturacion!$A$11:$A$64,"<="&DATE(2026,4,30),Facturacion!$J$11:$J$64,Facturacion!$J$4)) -> 0 | T9: =SUM(SUMIFS(Facturacion!$F$11:$F$64,Facturacion!$A$11:$A$64,">="&DATE(2026,5,1),Facturacion!$A$11:$A$64,"<="&DATE(2026,5,31),Facturacion!$J$11:$J$64,Facturacion!$J$4)) -> 0 | V9: =SUM(D9:U9) -> 75779183 | X9: 0 | Y9: 0 | Z9: =IF(Y9=100%,0,IF(X9=0,X9,X9-V9)) -> 0 | AA9: =IF(OR(Z9<0,X9),Z9/X9,0%) -> 0 | AB9: =IF(Y9=100%,IF(OR(V9<>0,X9),X9-V9),0) -> 0
B10: Total Ingresos por CAC | D10: =SUM(D9) -> 0 | E10: =SUM(E9) -> 735000 | F10: =SUM(F9) -> 5068372.2 | G10: =SUM(G9) -> 2935456.1 | H10: =SUM(H9) -> 3370711.7 | I10: =SUM(I9) -> 3338429.3 | J10: =SUM(J9) -> 3690653.5 | K10: =SUM(K9) -> 5160346.8 | ... T10: =SUM(T9) -> 0 | V10: =SUM(V9) -> 75779183 | X10: =SUM(X9) -> 0 | Z10: =SUM(Z9) -> 0 | AA10: =IF(OR(Z10<0,X10),Z10/X10,0%) -> 0 | AB10: =SUM(AB9) -> 0
B12: Costos de Obra
B13: Seguridad e Higiene | D13: =IFERROR(VLOOKUP($B13&$C13,'C. Gestión Pto #1'!$B$4:C$17,MATCH(D$5,'C. Gestión Pto #1'!$B$4:C$4,0),FALSE),0) -> 0 | E13: =IFERROR(VLOOKUP($B13&$C13,'C. Gestión Pto #1'!$B$4:D$17,MATCH(E$5,'C. Gestión Pto #1'!$B$4:D$4,0),FALSE),0) -> 0 | F13: =IFERROR(VLOOKUP($B13&$C13,'C. Gestión Pto #1'!$B$4:E$17,MATCH(F$5,'C. Gestión Pto #1'!$B$4:E$4,0),FALSE),0) -> 964000 | G13: =IFERROR(VLOOKUP($B13&$C13,'C. Gestión Pto #1'!$B$4:F$17,MATCH(G$5,'C. Gestión Pto #1'!$B$4:F$4,0),FALSE),0) -> 1763514.1 | H13: =IFERROR(VLOOKUP($B13&$C13,'C. Gestión Pto #1'!$B$4:G$17,MATCH(H$5,'C. Gestión Pto #1'!$B$4:G$4,0),FALSE),0) -> 1757000 | I13: =IFERROR(VLOOKUP($B13&$C13,'C. Gestión Pto #1'!$B$4:H$17,MATCH(I$5,'C. Gestión Pto #1'!$B$4:H$4,0),FALSE),0) -> 1902500 | J13: =IFERROR(VLOOKUP($B13&$C13,'C. Gestión Pto #1'!$B$4:I$17,MATCH(J$5,'C. Gestión Pto #1'!$B$4:I$4,0),FALSE),0) -> 1961406 | K13: =IFERROR(VLOOKUP($B13&$C13,'C. Gestión Pto #1'!$B$4:J$17,MATCH(K$5,'C. Gestión Pto #1'!$B$4:J$4,0),FALSE),0) -> 1951450 | ... T13: =IFERROR(VLOOKUP($B13&$C13,'C. Gestión Pto #1'!$B$4:S$17,MATCH(T$5,'C. Gestión Pto #1'!$B$4:S$4,0),FALSE),0) -> 0 | V13: {=SUMPRODUCT($D13:$U13,TRANSPOSE('Indice CAC'!$C$10:$C$27))} -> 14142435 | X13: =IF($C13="MAT",SUMIF('Pto. Costos'!$A$9:$A$57,'Resumen Pto #1'!$B13,'Pto. Costos'!$G$9:$G$57),IF($C13="MO",SUMIF('Pto. Costos'!$A$9:$A$57,'Resumen Pto #1'!$B13,'Pto. Costos'!$I$9:$I$57),SUMIF('Pto. Costos'!$A$9:$A$57,'Resumen Pto #1'!$B13,'Pto. Costos'!$L$9:$L$57))) -> 7389505.4 | Y13: =IF(C13="MAT",SUMIF('Pto. 01 Cert.'!$A$10:$A$57,$B13,'Pto. 01 Cert.'!$T$10:$T$57),IF(C13="MO",SUMIF('Pto. 01 Cert.'!$A$10:$A$57,$B13,'Pto. 01 Cert.'!$U$10:$U$57),SUMIF('Pto. 01 Cert.'!$A$10:$A$57,$B13,'Pto. 01 Cert.'!$V$10:$V$57)))/IF(C13="MAT",SUMIF('Pto. 01 Cert.'!$A$10:$A$57,$B13,'Pto. 01 Cert.'!$I$10:$I$57),IF(C13="MO",SUMIF('Pto. 01 Cert.'!$A$10:$A$57,$B13,'Pto. 01 Cert.'!$J$10:$J$57),SUMIF('Pto. 01 Cert.'!$A$10:$A$57,$B13,'Pto. 01 Cert.'!$K$10:$K$57))) -> 1 | Z13: =IF(Y13=100%,0,IF(OR(V13<>0,X13),X13-V13)) -> 0 | AA13: =IF(OR(Z13<0,X13),Z13/X13,0%) -> 0 | AB13: =IF(Y13=100%,IF(OR(V13<>0,X13),X13-V13),0) -> -6752929.7
B14: Supervisión de Obra | D14: =IFERROR(VLOOKUP($B14&$C14,'C. Gestión Pto #1'!$B$4:C$17,MATCH(D$5,'C. Gestión Pto #1'!$B$4:C$4,0),FALSE),0) -> 2240048.4 | E14: =IFERROR(VLOOKUP($B14&$C14,'C. Gestión Pto #1'!$B$4:D$17,MATCH(E$5,'C. Gestión Pto #1'!$B$4:D$4,0),FALSE),0) -> 1806402.8 | F14: =IFERROR(VLOOKUP($B14&$C14,'C. Gestión Pto #1'!$B$4:E$17,MATCH(F$5,'C. Gestión Pto #1'!$B$4:E$4,0),FALSE),0) -> 2447085 | G14: =IFERROR(VLOOKUP($B14&$C14,'C. Gestión Pto #1'!$B$4:F$17,MATCH(G$5,'C. Gestión Pto #1'!$B$4:F$4,0),FALSE),0) -> 2817108 | H14: =IFERROR(VLOOKUP($B14&$C14,'C. Gestión Pto #1'!$B$4:G$17,MATCH(H$5,'C. Gestión Pto #1'!$B$4:G$4,0),FALSE),0) -> 2817108 | I14: =IFERROR(VLOOKUP($B14&$C14,'C. Gestión Pto #1'!$B$4:H$17,MATCH(I$5,'C. Gestión Pto #1'!$B$4:H$4,0),FALSE),0) -> 2987662.5 | J14: =IFERROR(VLOOKUP($B14&$C14,'C. Gestión Pto #1'!$B$4:I$17,MATCH(J$5,'C. Gestión Pto #1'!$B$4:I$4,0),FALSE),0) -> 3018848 | K14: =IFERROR(VLOOKUP($B14&$C14,'C. Gestión Pto #1'!$B$4:J$17,MATCH(K$5,'C. Gestión Pto #1'!$B$4:J$4,0),FALSE),0) -> 3253763 | ... T14: =IFERROR(VLOOKUP($B14&$C14,'C. Gestión Pto #1'!$B$4:S$17,MATCH(T$5,'C. Gestión Pto #1'!$B$4:S$4,0),FALSE),0) -> 0 | V14: {=SUMPRODUCT($D14:$U14,TRANSPOSE('Indice CAC'!$C$10:$C$27))} -> 26535076 | X14: =IF($C14="MAT",SUMIF('Pto. Costos'!$A$9:$A$57,'Resumen Pto #1'!$B14,'Pto. Costos'!$G$9:$G$57),IF($C14="MO",SUMIF('Pto. Costos'!$A$9:$A$57,'Resumen Pto #1'!$B14,'Pto. Costos'!$I$9:$I$57),SUMIF('Pto. Costos'!$A$9:$A$57,'Resumen Pto #1'!$B14,'Pto. Costos'!$L$9:$L$57))) -> 30386965 | Y14: =IF(C14="MAT",SUMIF('Pto. 01 Cert.'!$A$10:$A$57,$B14,'Pto. 01 Cert.'!$T$10:$T$57),IF(C14="MO",SUMIF('Pto. 01 Cert.'!$A$10:$A$57,$B14,'Pto. 01 Cert.'!$U$10:$U$57),SUMIF('Pto. 01 Cert.'!$A$10:$A$57,$B14,'Pto. 01 Cert.'!$V$10:$V$57)))/IF(C14="MAT",SUMIF('Pto. 01 Cert.'!$A$10:$A$57,$B14,'Pto. 01 Cert.'!$I$10:$I$57),IF(C14="MO",SUMIF('Pto. 01 Cert.'!$A$10:$A$57,$B14,'Pto. 01 Cert.'!$J$10:$J$57),SUMIF('Pto. 01 Cert.'!$A$10:$A$57,$B14,'Pto. 01 Cert.'!$K$10:$K$57))) -> 1 | Z14: =IF(Y14=100%,0,IF(OR(V14<>0,X14),X14-V14)) -> 0 | AA14: =IF(OR(Z14<0,X14),Z14/X14,0%) -> 0 | AB14: =IF(Y14=100%,IF(OR(V14<>0,X14),X14-V14),0) -> 3851888.8
B15: Movilidad | D15: =IFERROR(VLOOKUP($B15&$C15,'C. Gestión Pto #1'!$B$4:C$17,MATCH(D$5,'C. Gestión Pto #1'!$B$4:C$4,0),FALSE),0) -> 83133.29 | E15: =IFERROR(VLOOKUP($B15&$C15,'C. Gestión Pto #1'!$B$4:D$17,MATCH(E$5,'C. Gestión Pto #1'!$B$4:D$4,0),FALSE),0) -> 108153.67 | F15: =IFERROR(VLOOKUP($B15&$C15,'C. Gestión Pto #1'!$B$4:E$17,MATCH(F$5,'C. Gestión Pto #1'!$B$4:E$4,0),FALSE),0) -> 111838.73 | G15: =IFERROR(VLOOKUP($B15&$C15,'C. Gestión Pto #1'!$B$4:F$17,MATCH(G$5,'C. Gestión Pto #1'!$B$4:F$4,0),FALSE),0) -> 273194.46 | H15: =IFERROR(VLOOKUP($B15&$C15,'C. Gestión Pto #1'!$B$4:G$17,MATCH(H$5,'C. Gestión Pto #1'!$B$4:G$4,0),FALSE),0) -> 382880.04 | I15: =IFERROR(VLOOKUP($B15&$C15,'C. Gestión Pto #1'!$B$4:H$17,MATCH(I$5,'C. Gestión Pto #1'!$B$4:H$4,0),FALSE),0) -> 245052.89 | J15: =IFERROR(VLOOKUP($B15&$C15,'C. Gestión Pto #1'!$B$4:I$17,MATCH(J$5,'C. Gestión Pto #1'!$B$4:I$4,0),FALSE),0) -> 567556.66 | K15: =IFERROR(VLOOKUP($B15&$C15,'C. Gestión Pto #1'!$B$4:J$17,MATCH(K$5,'C. Gestión Pto #1'!$B$4:J$4,0),FALSE),0) -> 322994.82 | ... T15: =IFERROR(VLOOKUP($B15&$C15,'C. Gestión Pto #1'!$B$4:S$17,MATCH(T$5,'C. Gestión Pto #1'!$B$4:S$4,0),FALSE),0) -> 0 | V15: {=SUMPRODUCT($D15:$U15,TRANSPOSE('Indice CAC'!$C$10:$C$27))} -> 6471319.2 | X15: =IF($C15="MAT",SUMIF('Pto. Costos'!$A$9:$A$57,'Resumen Pto #1'!$B15,'Pto. Costos'!$G$9:$G$57),IF($C15="MO",SUMIF('Pto. Costos'!$A$9:$A$57,'Resumen Pto #1'!$B15,'Pto. Costos'!$I$9:$I$57),SUMIF('Pto. Costos'!$A$9:$A$57,'Resumen Pto #1'!$B15,'Pto. Costos'!$L$9:$L$57))) -> 6000000 | Y15: =IF(C15="MAT",SUMIF('Pto. 01 Cert.'!$A$10:$A$57,$B15,'Pto. 01 Cert.'!$T$10:$T$57),IF(C15="MO",SUMIF('Pto. 01 Cert.'!$A$10:$A$57,$B15,'Pto. 01 Cert.'!$U$10:$U$57),SUMIF('Pto. 01 Cert.'!$A$10:$A$57,$B15,'Pto. 01 Cert.'!$V$10:$V$57)))/IF(C15="MAT",SUMIF('Pto. 01 Cert.'!$A$10:$A$57,$B15,'Pto. 01 Cert.'!$I$10:$I$57),IF(C15="MO",SUMIF('Pto. 01 Cert.'!$A$10:$A$57,$B15,'Pto. 01 Cert.'!$J$10:$J$57),SUMIF('Pto. 01 Cert.'!$A$10:$A$57,$B15,'Pto. 01 Cert.'!$K$10:$K$57))) -> 1 | Z15: =IF(Y15=100%,0,IF(OR(V15<>0,X15),X15-V15)) -> 0 | AA15: =IF(OR(Z15<0,X15),Z15/X15,0%) -> 0 | AB15: =IF(Y15=100%,IF(OR(V15<>0,X15),X15-V15),0) -> -471319.24
B16: Preliminares | D16: =IFERROR(VLOOKUP($B16&$C16,'C. Gestión Pto #1'!$B$4:C$17,MATCH(D$5,'C. Gestión Pto #1'!$B$4:C$4,0),FALSE),0) -> 0 | E16: =IFERROR(VLOOKUP($B16&$C16,'C. Gestión Pto #1'!$B$4:D$17,MATCH(E$5,'C. Gestión Pto #1'!$B$4:D$4,0),FALSE),0) -> 3076445.8 | F16: =IFERROR(VLOOKUP($B16&$C16,'C. Gestión Pto #1'!$B$4:E$17,MATCH(F$5,'C. Gestión Pto #1'!$B$4:E$4,0),FALSE),0) -> 4065955.3 | G16: =IFERROR(VLOOKUP($B16&$C16,'C. Gestión Pto #1'!$B$4:F$17,MATCH(G$5,'C. Gestión Pto #1'!$B$4:F$4,0),FALSE),0) -> 2170465.8 | H16: =IFERROR(VLOOKUP($B16&$C16,'C. Gestión Pto #1'!$B$4:G$17,MATCH(H$5,'C. Gestión Pto #1'!$B$4:G$4,0),FALSE),0) -> 452739.93 | I16: =IFERROR(VLOOKUP($B16&$C16,'C. Gestión Pto #1'!$B$4:H$17,MATCH(I$5,'C. Gestión Pto #1'!$B$4:H$4,0),FALSE),0) -> 333787.7 | J16: =IFERROR(VLOOKUP($B16&$C16,'C. Gestión Pto #1'!$B$4:I$17,MATCH(J$5,'C. Gestión Pto #1'!$B$4:I$4,0),FALSE),0) -> 0 | K16: =IFERROR(VLOOKUP($B16&$C16,'C. Gestión Pto #1'!$B$4:J$17,MATCH(K$5,'C. Gestión Pto #1'!$B$4:J$4,0),FALSE),0) -> 0 | ... T16: =IFERROR(VLOOKUP($B16&$C16,'C. Gestión Pto #1'!$B$4:S$17,MATCH(T$5,'C. Gestión Pto #1'!$B$4:S$4,0),FALSE),0) -> 0 | V16: {=SUMPRODUCT($D16:$U16,TRANSPOSE('Indice CAC'!$C$10:$C$27))} -> 9642624.1 | X16: =IF($C16="MAT",SUMIF('Pto. Costos'!$A$9:$A$57,'Resumen Pto #1'!$B16,'Pto. Costos'!$G$9:$G$57),IF($C16="MO",SUMIF('Pto. Costos'!$A$9:$A$57,'Resumen Pto #1'!$B16,'Pto. Costos'!$I$9:$I$57),SUMIF('Pto. Costos'!$A$9:$A$57,'Resumen Pto #1'!$B16,'Pto. Costos'!$L$9:$L$57))) -> 9593785.3 | Y16: =IF(C16="MAT",SUMIF('Pto. 01 Cert.'!$A$10:$A$57,$B16,'Pto. 01 Cert.'!$T$10:$T$57),IF(C16="MO",SUMIF('Pto. 01 Cert.'!$A$10:$A$57,$B16,'Pto. 01 Cert.'!$U$10:$U$57),SUMIF('Pto. 01 Cert.'!$A$10:$A$57,$B16,'Pto. 01 Cert.'!$V$10:$V$57)))/IF(C16="MAT",SUMIF('Pto. 01 Cert.'!$A$10:$A$57,$B16,'Pto. 01 Cert.'!$I$10:$I$57),IF(C16="MO",SUMIF('Pto. 01 Cert.'!$A$10:$A$57,$B16,'Pto. 01 Cert.'!$J$10:$J$57),SUMIF('Pto. 01 Cert.'!$A$10:$A$57,$B16,'Pto. 01 Cert.'!$K$10:$K$57))) -> 1 | Z16: =IF(Y16=100%,0,IF(OR(V16<>0,X16),X16-V16)) -> 0 | AA16: =IF(OR(Z16<0,X16),Z16/X16,0%) -> 0 | AB16: =IF(Y16=100%,IF(OR(V16<>0,X16),X16-V16),0) -> -48838.787
B17: Depresion de napas | D17: =IFERROR(VLOOKUP($B17&$C17,'C. Gestión Pto #1'!$B$4:C$17,MATCH(D$5,'C. Gestión Pto #1'!$B$4:C$4,0),FALSE),0) -> 0 | E17: =IFERROR(VLOOKUP($B17&$C17,'C. Gestión Pto #1'!$B$4:D$17,MATCH(E$5,'C. Gestión Pto #1'!$B$4:D$4,0),FALSE),0) -> 3900000 | F17: =IFERROR(VLOOKUP($B17&$C17,'C. Gestión Pto #1'!$B$4:E$17,MATCH(F$5,'C. Gestión Pto #1'!$B$4:E$4,0),FALSE),0) -> 3900000 | G17: =IFERROR(VLOOKUP($B17&$C17,'C. Gestión Pto #1'!$B$4:F$17,MATCH(G$5,'C. Gestión Pto #1'!$B$4:F$4,0),FALSE),0) -> 0 | H17: =IFERROR(VLOOKUP($B17&$C17,'C. Gestión Pto #1'!$B$4:G$17,MATCH(H$5,'C. Gestión Pto #1'!$B$4:G$4,0),FALSE),0) -> 0 | I17: =IFERROR(VLOOKUP($B17&$C17,'C. Gestión Pto #1'!$B$4:H$17,MATCH(I$5,'C. Gestión Pto #1'!$B$4:H$4,0),FALSE),0) -> 0 | J17: =IFERROR(VLOOKUP($B17&$C17,'C. Gestión Pto #1'!$B$4:I$17,MATCH(J$5,'C. Gestión Pto #1'!$B$4:I$4,0),FALSE),0) -> 0 | K17: =IFERROR(VLOOKUP($B17&$C17,'C. Gestión Pto #1'!$B$4:J$17,MATCH(K$5,'C. Gestión Pto #1'!$B$4:J$4,0),FALSE),0) -> 0 | ... T17: =IFERROR(VLOOKUP($B17&$C17,'C. Gestión Pto #1'!$B$4:S$17,MATCH(T$5,'C. Gestión Pto #1'!$B$4:S$4,0),FALSE),0) -> 0 | V17: {=SUMPRODUCT($D17:$U17,TRANSPOSE('Indice CAC'!$C$10:$C$27))} -> 7037477 | X17: =IF($C17="MAT",SUMIF('Pto. Costos'!$A$9:$A$57,'Resumen Pto #1'!$B17,'Pto. Costos'!$G$9:$G$57),IF($C17="MO",SUMIF('Pto. Costos'!$A$9:$A$57,'Resumen Pto #1'!$B17,'Pto. Costos'!$I$9:$I$57),SUMIF('Pto. Costos'!$A$9:$A$57,'Resumen Pto #1'!$B17,'Pto. Costos'!$L$9:$L$57))) -> 7800000 | Y17: =IF(C17="MAT",SUMIF('Pto. 01 Cert.'!$A$10:$A$57,$B17,'Pto. 01 Cert.'!$T$10:$T$57),IF(C17="MO",SUMIF('Pto. 01 Cert.'!$A$10:$A$57,$B17,'Pto. 01 Cert.'!$U$10:$U$57),SUMIF('Pto. 01 Cert.'!$A$10:$A$57,$B17,'Pto. 01 Cert.'!$V$10:$V$57)))/IF(C17="MAT",SUMIF('Pto. 01 Cert.'!$A$10:$A$57,$B17,'Pto. 01 Cert.'!$I$10:$I$57),IF(C17="MO",SUMIF('Pto. 01 Cert.'!$A$10:$A$57,$B17,'Pto. 01 Cert.'!$J$10:$J$57),SUMIF('Pto. 01 Cert.'!$A$10:$A$57,$B17,'Pto. 01 Cert.'!$K$10:$K$57))) -> 1 | Z17: =IF(Y17=100%,0,IF(OR(V17<>0,X17),X17-V17)) -> 0 | AA17: =IF(OR(Z17<0,X17),Z17/X17,0%) -> 0 | AB17: =IF(Y17=100%,IF(OR(V17<>0,X17),X17-V17),0) -> 762523.04
B18: Agrimensura | D18: =IFERROR(VLOOKUP($B18&$C18,'C. Gestión Pto #1'!$B$4:C$17,MATCH(D$5,'C. Gestión Pto #1'!$B$4:C$4,0),FALSE),0) -> 150000 | E18: =IFERROR(VLOOKUP($B18&$C18,'C. Gestión Pto #1'!$B$4:D$17,MATCH(E$5,'C. Gestión Pto #1'!$B$4:D$4,0),FALSE),0) -> 0 | F18: =IFERROR(VLOOKUP($B18&$C18,'C. Gestión Pto #1'!$B$4:E$17,MATCH(F$5,'C. Gestión Pto #1'!$B$4:E$4,0),FALSE),0) -> 150000 | G18: =IFERROR(VLOOKUP($B18&$C18,'C. Gestión Pto #1'!$B$4:F$17,MATCH(G$5,'C. Gestión Pto #1'!$B$4:F$4,0),FALSE),0) -> 0 | H18: =IFERROR(VLOOKUP($B18&$C18,'C. Gestión Pto #1'!$B$4:G$17,MATCH(H$5,'C. Gestión Pto #1'!$B$4:G$4,0),FALSE),0) -> 0 | I18: =IFERROR(VLOOKUP($B18&$C18,'C. Gestión Pto #1'!$B$4:H$17,MATCH(I$5,'C. Gestión Pto #1'!$B$4:H$4,0),FALSE),0) -> 0 | J18: =IFERROR(VLOOKUP($B18&$C18,'C. Gestión Pto #1'!$B$4:I$17,MATCH(J$5,'C. Gestión Pto #1'!$B$4:I$4,0),FALSE),0) -> 0 | K18: =IFERROR(VLOOKUP($B18&$C18,'C. Gestión Pto #1'!$B$4:J$17,MATCH(K$5,'C. Gestión Pto #1'!$B$4:J$4,0),FALSE),0) -> 0 | ... T18: =IFERROR(VLOOKUP($B18&$C18,'C. Gestión Pto #1'!$B$4:S$17,MATCH(T$5,'C. Gestión Pto #1'!$B$4:S$4,0),FALSE),0) -> 0 | V18: {=SUMPRODUCT($D18:$U18,TRANSPOSE('Indice CAC'!$C$10:$C$27))} -> 272938.14 | X18: =IF($C18="MAT",SUMIF('Pto. Costos'!$A$9:$A$57,'Resumen Pto #1'!$B18,'Pto. Costos'!$G$9:$G$57),IF($C18="MO",SUMIF('Pto. Costos'!$A$9:$A$57,'Resumen Pto #1'!$B18,'Pto. Costos'!$I$9:$I$57),SUMIF('Pto. Costos'!$A$9:$A$57,'Resumen Pto #1'!$B18,'Pto. Costos'!$L$9:$L$57))) -> 892630.81 | Y18: =IF(C18="MAT",SUMIF('Pto. 01 Cert.'!$A$10:$A$57,$B18,'Pto. 01 Cert.'!$T$10:$T$57),IF(C18="MO",SUMIF('Pto. 01 Cert.'!$A$10:$A$57,$B18,'Pto. 01 Cert.'!$U$10:$U$57),SUMIF('Pto. 01 Cert.'!$A$10:$A$57,$B18,'Pto. 01 Cert.'!$V$10:$V$57)))/IF(C18="MAT",SUMIF('Pto. 01 Cert.'!$A$10:$A$57,$B18,'Pto. 01 Cert.'!$I$10:$I$57),IF(C18="MO",SUMIF('Pto. 01 Cert.'!$A$10:$A$57,$B18,'Pto. 01 Cert.'!$J$10:$J$57),SUMIF('Pto. 01 Cert.'!$A$10:$A$57,$B18,'Pto. 01 Cert.'!$K$10:$K$57))) -> 1 | Z18: =IF(Y18=100%,0,IF(OR(V18<>0,X18),X18-V18)) -> 0 | AA18: =IF(OR(Z18<0,X18),Z18/X18,0%) -> 0 | AB18: =IF(Y18=100%,IF(OR(V18<>0,X18),X18-V18),0) -> 619692.67
B19: Excavación y Mov. de Suelos | D19: =IFERROR(VLOOKUP($B19&$C19,'C. Gestión Pto #1'!$B$4:C$17,MATCH(D$5,'C. Gestión Pto #1'!$B$4:C$4,0),FALSE),0) -> 0 | E19: =IFERROR(VLOOKUP($B19&$C19,'C. Gestión Pto #1'!$B$4:D$17,MATCH(E$5,'C. Gestión Pto #1'!$B$4:D$4,0),FALSE),0) -> 2555627 | F19: =IFERROR(VLOOKUP($B19&$C19,'C. Gestión Pto #1'!$B$4:E$17,MATCH(F$5,'C. Gestión Pto #1'!$B$4:E$4,0),FALSE),0) -> 0 | G19: =IFERROR(VLOOKUP($B19&$C19,'C. Gestión Pto #1'!$B$4:F$17,MATCH(G$5,'C. Gestión Pto #1'!$B$4:F$4,0),FALSE),0) -> 5000000 | H19: =IFERROR(VLOOKUP($B19&$C19,'C. Gestión Pto #1'!$B$4:G$17,MATCH(H$5,'C. Gestión Pto #1'!$B$4:G$4,0),FALSE),0) -> 5000000 | I19: =IFERROR(VLOOKUP($B19&$C19,'C. Gestión Pto #1'!$B$4:H$17,MATCH(I$5,'C. Gestión Pto #1'!$B$4:H$4,0),FALSE),0) -> 5812500 | J19: =IFERROR(VLOOKUP($B19&$C19,'C. Gestión Pto #1'!$B$4:I$17,MATCH(J$5,'C. Gestión Pto #1'!$B$4:I$4,0),FALSE),0) -> 0 | K19: =IFERROR(VLOOKUP($B19&$C19,'C. Gestión Pto #1'!$B$4:J$17,MATCH(K$5,'C. Gestión Pto #1'!$B$4:J$4,0),FALSE),0) -> 6430886.4 | ... T19: =IFERROR(VLOOKUP($B19&$C19,'C. Gestión Pto #1'!$B$4:S$17,MATCH(T$5,'C. Gestión Pto #1'!$B$4:S$4,0),FALSE),0) -> 0 | V19: {=SUMPRODUCT($D19:$U19,TRANSPOSE('Indice CAC'!$C$10:$C$27))} -> 21476728 | X19: =IF($C19="MAT",SUMIF('Pto. Costos'!$A$9:$A$57,'Resumen Pto #1'!$B19,'Pto. Costos'!$G$9:$G$57),IF($C19="MO",SUMIF('Pto. Costos'!$A$9:$A$57,'Resumen Pto #1'!$B19,'Pto. Costos'!$I$9:$I$57),SUMIF('Pto. Costos'!$A$9:$A$57,'Resumen Pto #1'!$B19,'Pto. Costos'!$L$9:$L$57))) -> 23294400 | Y19: =IF(C19="MAT",SUMIF('Pto. 01 Cert.'!$A$10:$A$57,$B19,'Pto. 01 Cert.'!$T$10:$T$57),IF(C19="MO",SUMIF('Pto. 01 Cert.'!$A$10:$A$57,$B19,'Pto. 01 Cert.'!$U$10:$U$57),SUMIF('Pto. 01 Cert.'!$A$10:$A$57,$B19,'Pto. 01 Cert.'!$V$10:$V$57)))/IF(C19="MAT",SUMIF('Pto. 01 Cert.'!$A$10:$A$57,$B19,'Pto. 01 Cert.'!$I$10:$I$57),IF(C19="MO",SUMIF('Pto. 01 Cert.'!$A$10:$A$57,$B19,'Pto. 01 Cert.'!$J$10:$J$57),SUMIF('Pto. 01 Cert.'!$A$10:$A$57,$B19,'Pto. 01 Cert.'!$K$10:$K$57))) -> 1 | Z19: =IF(Y19=100%,0,IF(OR(V19<>0,X19),X19-V19)) -> 0 | AA19: =IF(OR(Z19<0,X19),Z19/X19,0%) -> 0 | AB19: =IF(Y19=100%,IF(OR(V19<>0,X19),X19-V19),0) -> 1817672.1
B20: Hormigón | C20: MAT | D20: =IFERROR(VLOOKUP($B20&$C20,'C. Gestión Pto #1'!$B$4:C$17,MATCH(D$5,'C. Gestión Pto #1'!$B$4:C$4,0),FALSE),0) -> 0 | E20: =IFERROR(VLOOKUP($B20&$C20,'C. Gestión Pto #1'!$B$4:D$17,MATCH(E$5,'C. Gestión Pto #1'!$B$4:D$4,0),FALSE),0) -> 7421307.2 | F20: =IFERROR(VLOOKUP($B20&$C20,'C. Gestión Pto #1'!$B$4:E$17,MATCH(F$5,'C. Gestión Pto #1'!$B$4:E$4,0),FALSE),0) -> 934481.37 | G20: =IFERROR(VLOOKUP($B20&$C20,'C. Gestión Pto #1'!$B$4:F$17,MATCH(G$5,'C. Gestión Pto #1'!$B$4:F$4,0),FALSE),0) -> 6221403.1 | H20: =IFERROR(VLOOKUP($B20&$C20,'C. Gestión Pto #1'!$B$4:G$17,MATCH(H$5,'C. Gestión Pto #1'!$B$4:G$4,0),FALSE),0) -> 3385750.4 | I20: =IFERROR(VLOOKUP($B20&$C20,'C. Gestión Pto #1'!$B$4:H$17,MATCH(I$5,'C. Gestión Pto #1'!$B$4:H$4,0),FALSE),0) -> 3530590.8 | J20: =IFERROR(VLOOKUP($B20&$C20,'C. Gestión Pto #1'!$B$4:I$17,MATCH(J$5,'C. Gestión Pto #1'!$B$4:I$4,0),FALSE),0) -> 0 | K20: =IFERROR(VLOOKUP($B20&$C20,'C. Gestión Pto #1'!$B$4:J$17,MATCH(K$5,'C. Gestión Pto #1'!$B$4:J$4,0),FALSE),0) -> 3744037.3 | ... T20: =IFERROR(VLOOKUP($B20&$C20,'C. Gestión Pto #1'!$B$4:S$17,MATCH(T$5,'C. Gestión Pto #1'!$B$4:S$4,0),FALSE),0) -> 0 | V20: {=SUMPRODUCT($D20:$U20,TRANSPOSE('Indice CAC'!$C$10:$C$27))} -> 28825229 | X20: =IF($C20="MAT",SUMIF('Pto. Costos'!$A$9:$A$57,'Resumen Pto #1'!$B20,'Pto. Costos'!$G$9:$G$57),IF($C20="MO",SUMIF('Pto. Costos'!$A$9:$A$57,'Resumen Pto #1'!$B20,'Pto. Costos'!$I$9:$I$57),SUMIF('Pto. Costos'!$A$9:$A$57,'Resumen Pto #1'!$B20,'Pto. Costos'!$L$9:$L$57))) -> 39767922 | Y20: =IF(C20="MAT",SUMIF('Pto. 01 Cert.'!$A$10:$A$57,$B20,'Pto. 01 Cert.'!$T$10:$T$57),IF(C20="MO",SUMIF('Pto. 01 Cert.'!$A$10:$A$57,$B20,'Pto. 01 Cert.'!$U$10:$U$57),SUMIF('Pto. 01 Cert.'!$A$10:$A$57,$B20,'Pto. 01 Cert.'!$V$10:$V$57)))/IF(C20="MAT",SUMIF('Pto. 01 Cert.'!$A$10:$A$57,$B20,'Pto. 01 Cert.'!$I$10:$I$57),IF(C20="MO",SUMIF('Pto. 01 Cert.'!$A$10:$A$57,$B20,'Pto. 01 Cert.'!$J$10:$J$57),SUMIF('Pto. 01 Cert.'!$A$10:$A$57,$B20,'Pto. 01 Cert.'!$K$10:$K$57))) -> 1 | Z20: =IF(Y20=100%,0,IF(OR(V20<>0,X20),X20-V20)) -> 0 | AA20: =IF(OR(Z20<0,X20),Z20/X20,0%) -> 0 | AB20: =IF(Y20=100%,IF(OR(V20<>0,X20),X20-V20),0) -> 10942694
B21: Hormigón | C21: MO | D21: =IFERROR(VLOOKUP($B21&$C21,'C. Gestión Pto #1'!$B$4:C$17,MATCH(D$5,'C. Gestión Pto #1'!$B$4:C$4,0),FALSE),0) -> 0 | E21: =IFERROR(VLOOKUP($B21&$C21,'C. Gestión Pto #1'!$B$4:D$17,MATCH(E$5,'C. Gestión Pto #1'!$B$4:D$4,0),FALSE),0) -> 0 | F21: =IFERROR(VLOOKUP($B21&$C21,'C. Gestión Pto #1'!$B$4:E$17,MATCH(F$5,'C. Gestión Pto #1'!$B$4:E$4,0),FALSE),0) -> 2102991.6 | G21: =IFERROR(VLOOKUP($B21&$C21,'C. Gestión Pto #1'!$B$4:F$17,MATCH(G$5,'C. Gestión Pto #1'!$B$4:F$4,0),FALSE),0) -> 17862837 | H21: =IFERROR(VLOOKUP($B21&$C21,'C. Gestión Pto #1'!$B$4:G$17,MATCH(H$5,'C. Gestión Pto #1'!$B$4:G$4,0),FALSE),0) -> 18399394 | I21: =IFERROR(VLOOKUP($B21&$C21,'C. Gestión Pto #1'!$B$4:H$17,MATCH(I$5,'C. Gestión Pto #1'!$B$4:H$4,0),FALSE),0) -> 21489375 | J21: =IFERROR(VLOOKUP($B21&$C21,'C. Gestión Pto #1'!$B$4:I$17,MATCH(J$5,'C. Gestión Pto #1'!$B$4:I$4,0),FALSE),0) -> 26401198 | K21: =IFERROR(VLOOKUP($B21&$C21,'C. Gestión Pto #1'!$B$4:J$17,MATCH(K$5,'C. Gestión Pto #1'!$B$4:J$4,0),FALSE),0) -> 22702901 | ... T21: =IFERROR(VLOOKUP($B21&$C21,'C. Gestión Pto #1'!$B$4:S$17,MATCH(T$5,'C. Gestión Pto #1'!$B$4:S$4,0),FALSE),0) -> 7793473.3 | V21: {=SUMPRODUCT($D21:$U21,TRANSPOSE('Indice CAC'!$C$10:$C$27))} -> 2.381807e+08 | X21: =IF($C21="MAT",SUMIF('Pto. Costos'!$A$9:$A$57,'Resumen Pto #1'!$B21,'Pto. Costos'!$G$9:$G$57),IF($C21="MO",SUMIF('Pto. Costos'!$A$9:$A$57,'Resumen Pto #1'!$B21,'Pto. Costos'!$I$9:$I$57),SUMIF('Pto. Costos'!$A$9:$A$57,'Resumen Pto #1'!$B21,'Pto. Costos'!$L$9:$L$57))) -> 1.6001523e+08 | Y21: =IF(C21="MAT",SUMIF('Pto. 01 Cert.'!$A$10:$A$57,$B21,'Pto. 01 Cert.'!$T$10:$T$57),IF(C21="MO",SUMIF('Pto. 01 Cert.'!$A$10:$A$57,$B21,'Pto. 01 Cert.'!$U$10:$U$57),SUMIF('Pto. 01 Cert.'!$A$10:$A$57,$B21,'Pto. 01 Cert.'!$V$10:$V$57)))/IF(C21="MAT",SUMIF('Pto. 01 Cert.'!$A$10:$A$57,$B21,'Pto. 01 Cert.'!$I$10:$I$57),IF(C21="MO",SUMIF('Pto. 01 Cert.'!$A$10:$A$57,$B21,'Pto. 01 Cert.'!$J$10:$J$57),SUMIF('Pto. 01 Cert.'!$A$10:$A$57,$B21,'Pto. 01 Cert.'!$K$10:$K$57))) -> 1 | Z21: =IF(Y21=100%,0,IF(OR(V21<>0,X21),X21-V21)) -> 0 | AA21: =IF(OR(Z21<0,X21),Z21/X21,0%) -> 0 | AB21: =IF(Y21=100%,IF(OR(V21<>0,X21),X21-V21),0) -> -78165468
B22: Albañilería | C22: MAT | D22: =IFERROR(VLOOKUP($B22&$C22,'C. Gestión Pto #1'!$B$4:C$17,MATCH(D$5,'C. Gestión Pto #1'!$B$4:C$4,0),FALSE),0) -> 22000 | E22: =IFERROR(VLOOKUP($B22&$C22,'C. Gestión Pto #1'!$B$4:D$17,MATCH(E$5,'C. Gestión Pto #1'!$B$4:D$4,0),FALSE),0) -> 0 | F22: =IFERROR(VLOOKUP($B22&$C22,'C. Gestión Pto #1'!$B$4:E$17,MATCH(F$5,'C. Gestión Pto #1'!$B$4:E$4,0),FALSE),0) -> 0 | G22: =IFERROR(VLOOKUP($B22&$C22,'C. Gestión Pto #1'!$B$4:F$17,MATCH(G$5,'C. Gestión Pto #1'!$B$4:F$4,0),FALSE),0) -> 0 | H22: =IFERROR(VLOOKUP($B22&$C22,'C. Gestión Pto #1'!$B$4:G$17,MATCH(H$5,'C. Gestión Pto #1'!$B$4:G$4,0),FALSE),0) -> 0 | I22: =IFERROR(VLOOKUP($B22&$C22,'C. Gestión Pto #1'!$B$4:H$17,MATCH(I$5,'C. Gestión Pto #1'!$B$4:H$4,0),FALSE),0) -> 0 | J22: =IFERROR(VLOOKUP($B22&$C22,'C. Gestión Pto #1'!$B$4:I$17,MATCH(J$5,'C. Gestión Pto #1'!$B$4:I$4,0),FALSE),0) -> 203018.11 | K22: =IFERROR(VLOOKUP($B22&$C22,'C. Gestión Pto #1'!$B$4:J$17,MATCH(K$5,'C. Gestión Pto #1'!$B$4:J$4,0),FALSE),0) -> 955956.22 | ... T22: =IFERROR(VLOOKUP($B22&$C22,'C. Gestión Pto #1'!$B$4:S$17,MATCH(T$5,'C. Gestión Pto #1'!$B$4:S$4,0),FALSE),0) -> 0 | V22: {=SUMPRODUCT($D22:$U22,TRANSPOSE('Indice CAC'!$C$10:$C$27))} -> 1448122.7 | X22: =IF($C22="MAT",SUMIF('Pto. Costos'!$A$9:$A$57,'Resumen Pto #1'!$B22,'Pto. Costos'!$G$9:$G$57),IF($C22="MO",SUMIF('Pto. Costos'!$A$9:$A$57,'Resumen Pto #1'!$B22,'Pto. Costos'!$I$9:$I$57),SUMIF('Pto. Costos'!$A$9:$A$57,'Resumen Pto #1'!$B22,'Pto. Costos'!$L$9:$L$57))) -> 2988097.3 | Y22: =IF(C22="MAT",SUMIF('Pto. 01 Cert.'!$A$10:$A$57,$B22,'Pto. 01 Cert.'!$T$10:$T$57),IF(C22="MO",SUMIF('Pto. 01 Cert.'!$A$10:$A$57,$B22,'Pto. 01 Cert.'!$U$10:$U$57),SUMIF('Pto. 01 Cert.'!$A$10:$A$57,$B22,'Pto. 01 Cert.'!$V$10:$V$57)))/IF(C22="MAT",SUMIF('Pto. 01 Cert.'!$A$10:$A$57,$B22,'Pto. 01 Cert.'!$I$10:$I$57),IF(C22="MO",SUMIF('Pto. 01 Cert.'!$A$10:$A$57,$B22,'Pto. 01 Cert.'!$J$10:$J$57),SUMIF('Pto. 01 Cert.'!$A$10:$A$57,$B22,'Pto. 01 Cert.'!$K$10:$K$57))) -> 1 | Z22: =IF(Y22=100%,0,IF(OR(V22<>0,X22),X22-V22)) -> 0 | AA22: =IF(OR(Z22<0,X22),Z22/X22,0%) -> 0 | AB22: =IF(Y22=100%,IF(OR(V22<>0,X22),X22-V22),0) -> 1539974.5
B23: Albañilería | C23: MO | D23: =IFERROR(VLOOKUP($B23&$C23,'C. Gestión Pto #1'!$B$4:C$17,MATCH(D$5,'C. Gestión Pto #1'!$B$4:C$4,0),FALSE),0) -> 0 | E23: =IFERROR(VLOOKUP($B23&$C23,'C. Gestión Pto #1'!$B$4:D$17,MATCH(E$5,'C. Gestión Pto #1'!$B$4:D$4,0),FALSE),0) -> 0 | F23: =IFERROR(VLOOKUP($B23&$C23,'C. Gestión Pto #1'!$B$4:E$17,MATCH(F$5,'C. Gestión Pto #1'!$B$4:E$4,0),FALSE),0) -> 67000 | G23: =IFERROR(VLOOKUP($B23&$C23,'C. Gestión Pto #1'!$B$4:F$17,MATCH(G$5,'C. Gestión Pto #1'!$B$4:F$4,0),FALSE),0) -> 240500 | H23: =IFERROR(VLOOKUP($B23&$C23,'C. Gestión Pto #1'!$B$4:G$17,MATCH(H$5,'C. Gestión Pto #1'!$B$4:G$4,0),FALSE),0) -> 497357.68 | I23: =IFERROR(VLOOKUP($B23&$C23,'C. Gestión Pto #1'!$B$4:H$17,MATCH(I$5,'C. Gestión Pto #1'!$B$4:H$4,0),FALSE),0) -> 100000 | J23: =IFERROR(VLOOKUP($B23&$C23,'C. Gestión Pto #1'!$B$4:I$17,MATCH(J$5,'C. Gestión Pto #1'!$B$4:I$4,0),FALSE),0) -> 0 | K23: =IFERROR(VLOOKUP($B23&$C23,'C. Gestión Pto #1'!$B$4:J$17,MATCH(K$5,'C. Gestión Pto #1'!$B$4:J$4,0),FALSE),0) -> 0 | ... T23: =IFERROR(VLOOKUP($B23&$C23,'C. Gestión Pto #1'!$B$4:S$17,MATCH(T$5,'C. Gestión Pto #1'!$B$4:S$4,0),FALSE),0) -> 0 | V23: {=SUMPRODUCT($D23:$U23,TRANSPOSE('Indice CAC'!$C$10:$C$27))} -> 2518003.7 | X23: =IF($C23="MAT",SUMIF('Pto. Costos'!$A$9:$A$57,'Resumen Pto #1'!$B23,'Pto. Costos'!$G$9:$G$57),IF($C23="MO",SUMIF('Pto. Costos'!$A$9:$A$57,'Resumen Pto #1'!$B23,'Pto. Costos'!$I$9:$I$57),SUMIF('Pto. Costos'!$A$9:$A$57,'Resumen Pto #1'!$B23,'Pto. Costos'!$L$9:$L$57))) -> 13017986 | Y23: =IF(C23="MAT",SUMIF('Pto. 01 Cert.'!$A$10:$A$57,$B23,'Pto. 01 Cert.'!$T$10:$T$57),IF(C23="MO",SUMIF('Pto. 01 Cert.'!$A$10:$A$57,$B23,'Pto. 01 Cert.'!$U$10:$U$57),SUMIF('Pto. 01 Cert.'!$A$10:$A$57,$B23,'Pto. 01 Cert.'!$V$10:$V$57)))/IF(C23="MAT",SUMIF('Pto. 01 Cert.'!$A$10:$A$57,$B23,'Pto. 01 Cert.'!$I$10:$I$57),IF(C23="MO",SUMIF('Pto. 01 Cert.'!$A$10:$A$57,$B23,'Pto. 01 Cert.'!$J$10:$J$57),SUMIF('Pto. 01 Cert.'!$A$10:$A$57,$B23,'Pto. 01 Cert.'!$K$10:$K$57))) -> 1 | Z23: =IF(Y23=100%,0,IF(OR(V23<>0,X23),X23-V23)) -> 0 | AA23: =IF(OR(Z23<0,X23),Z23/X23,0%) -> 0 | AB23: =IF(Y23=100%,IF(OR(V23<>0,X23),X23-V23),0) -> 10499982
B24: Equipos | D24: =IFERROR(VLOOKUP($B24&$C24,'C. Gestión Pto #1'!$B$4:C$17,MATCH(D$5,'C. Gestión Pto #1'!$B$4:C$4,0),FALSE),0) -> 296509.21 | E24: =IFERROR(VLOOKUP($B24&$C24,'C. Gestión Pto #1'!$B$4:D$17,MATCH(E$5,'C. Gestión Pto #1'!$B$4:D$4,0),FALSE),0) -> 257327.67 | F24: =IFERROR(VLOOKUP($B24&$C24,'C. Gestión Pto #1'!$B$4:E$17,MATCH(F$5,'C. Gestión Pto #1'!$B$4:E$4,0),FALSE),0) -> 257327.67 | G24: =IFERROR(VLOOKUP($B24&$C24,'C. Gestión Pto #1'!$B$4:F$17,MATCH(G$5,'C. Gestión Pto #1'!$B$4:F$4,0),FALSE),0) -> 290739.63 | H24: =IFERROR(VLOOKUP($B24&$C24,'C. Gestión Pto #1'!$B$4:G$17,MATCH(H$5,'C. Gestión Pto #1'!$B$4:G$4,0),FALSE),0) -> 296307.18 | I24: =IFERROR(VLOOKUP($B24&$C24,'C. Gestión Pto #1'!$B$4:H$17,MATCH(I$5,'C. Gestión Pto #1'!$B$4:H$4,0),FALSE),0) -> 301650.01 | J24: =IFERROR(VLOOKUP($B24&$C24,'C. Gestión Pto #1'!$B$4:I$17,MATCH(J$5,'C. Gestión Pto #1'!$B$4:I$4,0),FALSE),0) -> 315509.7 | K24: =IFERROR(VLOOKUP($B24&$C24,'C. Gestión Pto #1'!$B$4:J$17,MATCH(K$5,'C. Gestión Pto #1'!$B$4:J$4,0),FALSE),0) -> 525701.05 | ... T24: =IFERROR(VLOOKUP($B24&$C24,'C. Gestión Pto #1'!$B$4:S$17,MATCH(T$5,'C. Gestión Pto #1'!$B$4:S$4,0),FALSE),0) -> 0 | V24: {=SUMPRODUCT($D24:$U24,TRANSPOSE('Indice CAC'!$C$10:$C$27))} -> 3585696.7 | X24: =IF($C24="MAT",SUMIF('Pto. Costos'!$A$9:$A$57,'Resumen Pto #1'!$B24,'Pto. Costos'!$G$9:$G$57),IF($C24="MO",SUMIF('Pto. Costos'!$A$9:$A$57,'Resumen Pto #1'!$B24,'Pto. Costos'!$I$9:$I$57),SUMIF('Pto. Costos'!$A$9:$A$57,"",'Pto. Costos'!$K$9:$K$57))) -> 12019074 | Y24: ='Pto. 01 Cert.'!$S$58/'Pto. 01 Cert.'!$L$58 -> 1.0029914 | Z24: =IF(Y24=100%,0,IF(OR(V24<>0,X24),X24-V24)) -> 8433377.3 | AA24: =IF(OR(Z24<0,X24),Z24/X24,0%) -> 0.70166614 | AB24: =IF(Y24=100%,IF(OR(V24<>0,X24),X24-V24),0) -> 0
B25: Gastos Generales Obra | D25: =IFERROR(VLOOKUP($B25&$C25,'C. Gestión Pto #1'!$B$4:C$17,MATCH(D$5,'C. Gestión Pto #1'!$B$4:C$4,0),FALSE),0) -> 0 | E25: =IFERROR(VLOOKUP($B25&$C25,'C. Gestión Pto #1'!$B$4:D$17,MATCH(E$5,'C. Gestión Pto #1'!$B$4:D$4,0),FALSE),0) -> 165000 | F25: =IFERROR(VLOOKUP($B25&$C25,'C. Gestión Pto #1'!$B$4:E$17,MATCH(F$5,'C. Gestión Pto #1'!$B$4:E$4,0),FALSE),0) -> 80000 | G25: =IFERROR(VLOOKUP($B25&$C25,'C. Gestión Pto #1'!$B$4:F$17,MATCH(G$5,'C. Gestión Pto #1'!$B$4:F$4,0),FALSE),0) -> 237000 | H25: =IFERROR(VLOOKUP($B25&$C25,'C. Gestión Pto #1'!$B$4:G$17,MATCH(H$5,'C. Gestión Pto #1'!$B$4:G$4,0),FALSE),0) -> 337000 | I25: =IFERROR(VLOOKUP($B25&$C25,'C. Gestión Pto #1'!$B$4:H$17,MATCH(I$5,'C. Gestión Pto #1'!$B$4:H$4,0),FALSE),0) -> 543000 | J25: =IFERROR(VLOOKUP($B25&$C25,'C. Gestión Pto #1'!$B$4:I$17,MATCH(J$5,'C. Gestión Pto #1'!$B$4:I$4,0),FALSE),0) -> 256958.68 | K25: =IFERROR(VLOOKUP($B25&$C25,'C. Gestión Pto #1'!$B$4:J$17,MATCH(K$5,'C. Gestión Pto #1'!$B$4:J$4,0),FALSE),0) -> 425200 | ... T25: =IFERROR(VLOOKUP($B25&$C25,'C. Gestión Pto #1'!$B$4:S$17,MATCH(T$5,'C. Gestión Pto #1'!$B$4:S$4,0),FALSE),0) -> 0 | V25: {=SUMPRODUCT($D25:$U25,TRANSPOSE('Indice CAC'!$C$10:$C$27))} -> 3889372.6 | X25: =IF($C25="MAT",SUMIF('Pto. Costos'!$A$9:$A$57,'Resumen Pto #1'!$B25,'Pto. Costos'!$G$9:$G$57),IF($C25="MO",SUMIF('Pto. Costos'!$A$9:$A$57,'Resumen Pto #1'!$B25,'Pto. Costos'!$I$9:$I$57),SUMIF('Pto. Costos'!$A$9:$A$57,'Resumen Pto #1'!$B25,'Pto. Costos'!$L$9:$L$57))) -> 2875034.6 | Y25: =IF(C25="MAT",SUMIF('Pto. 01 Cert.'!$A$10:$A$57,$B25,'Pto. 01 Cert.'!$T$10:$T$57),IF(C25="MO",SUMIF('Pto. 01 Cert.'!$A$10:$A$57,$B25,'Pto. 01 Cert.'!$U$10:$U$57),SUMIF('Pto. 01 Cert.'!$A$10:$A$57,$B25,'Pto. 01 Cert.'!$V$10:$V$57)))/IF(C25="MAT",SUMIF('Pto. 01 Cert.'!$A$10:$A$57,$B25,'Pto. 01 Cert.'!$I$10:$I$57),IF(C25="MO",SUMIF('Pto. 01 Cert.'!$A$10:$A$57,$B25,'Pto. 01 Cert.'!$J$10:$J$57),SUMIF('Pto. 01 Cert.'!$A$10:$A$57,$B25,'Pto. 01 Cert.'!$K$10:$K$57))) -> 1 | Z25: =IF(Y25=100%,0,IF(OR(V25<>0,X25),X25-V25)) -> 0 | AA25: =IF(OR(Z25<0,X25),Z25/X25,0%) -> 0 | AB25: =IF(Y25=100%,IF(OR(V25<>0,X25),X25-V25),0) -> -1014338
B26: Total Egresos de Obra | D26: =SUM(D13:D25) -> 2791690.9 | E26: =SUM(E13:E25) -> 19290264 | F26: =SUM(F13:F25) -> 15080680 | G26: =SUM(G13:G25) -> 36876762 | H26: =SUM(H13:H25) -> 33325537 | I26: =SUM(I13:I25) -> 37246119 | J26: =SUM(J13:J25) -> 32724495 | K26: =SUM(K13:K25) -> 40312889 | ... T26: =SUM(T13:T25) -> 7793473.3 | V26: =SUM(V13:V25) -> 3.6402572e+08 | X26: =SUM(X13:X25) -> 3.1604063e+08 | Z26: =IF(Y26=100%,0,IF(OR(V26<>0,X26),X26-V26)) -> -47985090 | AA26: =IF(OR(Z26<0,X26),Z26/X26,0%) -> -0.15183203 | AB26: =SUM(AB13:AB25) -> -56418467
X27: =X26-'Pto. Costos'!M244 -> 0
B28: Gastos Generales
B29: Gastos Directos | D29: =VLOOKUP($B29,'C. Gestión Pto #1'!$B$34:L$34,MATCH('Resumen Pto #1'!D$5,'C. Gestión Pto #1'!$B$20:L$20,0),0) -> 966547.14 | E29: =VLOOKUP($B29,'C. Gestión Pto #1'!$B$34:M$34,MATCH('Resumen Pto #1'!E$5,'C. Gestión Pto #1'!$B$20:M$20,0),0) -> 724628.24 | F29: =VLOOKUP($B29,'C. Gestión Pto #1'!$B$34:N$34,MATCH('Resumen Pto #1'!F$5,'C. Gestión Pto #1'!$B$20:N$20,0),0) -> 2047489.7 | G29: =VLOOKUP($B29,'C. Gestión Pto #1'!$B$34:O$34,MATCH('Resumen Pto #1'!G$5,'C. Gestión Pto #1'!$B$20:O$20,0),0) -> 1556001.8 | H29: =VLOOKUP($B29,'C. Gestión Pto #1'!$B$34:P$34,MATCH('Resumen Pto #1'!H$5,'C. Gestión Pto #1'!$B$20:P$20,0),0) -> 1451425.4 | I29: =VLOOKUP($B29,'C. Gestión Pto #1'!$B$34:Q$34,MATCH('Resumen Pto #1'!I$5,'C. Gestión Pto #1'!$B$20:Q$20,0),0) -> 1216663.4 | J29: =VLOOKUP($B29,'C. Gestión Pto #1'!$B$34:R$34,MATCH('Resumen Pto #1'!J$5,'C. Gestión Pto #1'!$B$20:R$20,0),0) -> 2128961.3 | K29: =VLOOKUP($B29,'C. Gestión Pto #1'!$B$34:S$34,MATCH('Resumen Pto #1'!K$5,'C. Gestión Pto #1'!$B$20:S$20,0),0) -> 3072710.3 | ... T29: =VLOOKUP($B29,'C. Gestión Pto #1'!$B$34:AB$34,MATCH('Resumen Pto #1'!T$5,'C. Gestión Pto #1'!$B$20:AB$20,0),0) -> 0 | V29: {=SUMPRODUCT($D29:$U29,TRANSPOSE('Indice CAC'!$C$10:$C$27))} -> 17746523 | X29: =SUM(GGBB!H7:H40)*'Pto. Vta.'!N242 -> 20045880 | Y29: ='Pto. 01 Cert.'!$S$58/'Pto. 01 Cert.'!$L$58 -> 1.0029914 | Z29: =IF(Y29=100%,0,IF(OR(V29<>0,X29),X29-V29)) -> 2299356.3 | AA29: =IF(OR(Z29<0,X29),Z29/X29,0%) -> 0.11470468 | AB29: =IF(Y29=100%,IF(OR(V29<>0,X29),X29-V29),0) -> 0
B30: Gastos Indirectos | D30: =VLOOKUP($B30,'C. Gestión Pto #1'!$B$39:L$39,MATCH('Resumen Pto #1'!D$5,'C. Gestión Pto #1'!$B$36:L$36,0),0) -> 1825790.3 | E30: =VLOOKUP($B30,'C. Gestión Pto #1'!$B$39:M$39,MATCH('Resumen Pto #1'!E$5,'C. Gestión Pto #1'!$B$36:M$36,0),0) -> 1368018.8 | F30: =VLOOKUP($B30,'C. Gestión Pto #1'!$B$39:N$39,MATCH('Resumen Pto #1'!F$5,'C. Gestión Pto #1'!$B$36:N$36,0),0) -> 2137192 | G30: =VLOOKUP($B30,'C. Gestión Pto #1'!$B$39:O$39,MATCH('Resumen Pto #1'!G$5,'C. Gestión Pto #1'!$B$36:O$36,0),0) -> 2169029.3 | H30: =VLOOKUP($B30,'C. Gestión Pto #1'!$B$39:P$39,MATCH('Resumen Pto #1'!H$5,'C. Gestión Pto #1'!$B$36:P$36,0),0) -> 1800256.2 | I30: =VLOOKUP($B30,'C. Gestión Pto #1'!$B$39:Q$39,MATCH('Resumen Pto #1'!I$5,'C. Gestión Pto #1'!$B$36:Q$36,0),0) -> 2949259.1 | J30: =VLOOKUP($B30,'C. Gestión Pto #1'!$B$39:R$39,MATCH('Resumen Pto #1'!J$5,'C. Gestión Pto #1'!$B$36:R$36,0),0) -> 1800256.2 | K30: =VLOOKUP($B30,'C. Gestión Pto #1'!$B$39:S$39,MATCH('Resumen Pto #1'!K$5,'C. Gestión Pto #1'!$B$36:S$36,0),0) -> 2235375.3 | ... T30: =VLOOKUP($B30,'C. Gestión Pto #1'!$B$39:AB$39,MATCH('Resumen Pto #1'!T$5,'C. Gestión Pto #1'!$B$36:AB$36,0),0) -> 0 | V30: {=SUMPRODUCT($D30:$U30,TRANSPOSE('Indice CAC'!$C$10:$C$27))} -> 20231063 | X30: =SUM(GGBB!H41:H47)*'Pto. Vta.'!N242 -> 21358198 | Y30: ='Pto. 01 Cert.'!$S$58/'Pto. 01 Cert.'!$L$58 -> 1.0029914 | Z30: =IF(Y30=100%,0,IF(OR(V30<>0,X30),X30-V30)) -> 1127135.4 | AA30: =IF(OR(Z30<0,X30),Z30/X30,0%) -> 0.052772961 | AB30: =IF(Y30=100%,IF(OR(V30<>0,X30),X30-V30),0) -> 0
B31: Total Gastos Generales | D31: =SUM(D29:D30) -> 2792337.4 | E31: =SUM(E29:E30) -> 2092647 | F31: =SUM(F29:F30) -> 4184681.7 | G31: =SUM(G29:G30) -> 3725031.1 | H31: =SUM(H29:H30) -> 3251681.6 | I31: =SUM(I29:I30) -> 4165922.5 | J31: =SUM(J29:J30) -> 3929217.5 | K31: =SUM(K29:K30) -> 5308085.6 | ... T31: =SUM(T29:T30) -> 0 | V31: =SUM(V29:V30) -> 37977586 | X31: =SUM(X29:X30) -> 41404078 | Z31: =IF(Y31=100%,0,IF(OR(V31<>0,X31),X31-V31)) -> 3426491.6 | AA31: =IF(OR(Z31<0,X31),Z31/X31,0%) -> 0.082757347 | AB31: =SUM(AB29:AB30) -> 0
B33: Resultado Operativo | D33: =SUM(D8,D10,-D26,-D31) -> -5584028.3 | E33: =SUM(E8,E10,-E26,-E31) -> -9132911.2 | F33: =SUM(F8,F10,-F26,-F31) -> 58549221 | G33: =SUM(G8,G10,-G26,-G31) -> -9276297.1 | H33: =SUM(H8,H10,-H26,-H31) -> -4273907.6 | I33: =SUM(I8,I10,-I26,-I31) -> -14408318 | J33: =SUM(J8,J10,-J26,-J31) -> -8351450.5 | K33: =SUM(K8,K10,-K26,-K31) -> -7893887.4 | ... T33: =SUM(T8,T10,-T26,-T31) -> -7793473.3 | V33: =SUM(V8,-V26,-V31) -> 20112003 | X33: =SUM(X8,-X26,-X31) -> 63861341
B34: Resultado Acumulado | D34: =D33 -> -5584028.3 | E34: =E33+D34 -> -14716940 | F34: =F33+E34 -> 43832282 | G34: =G33+F34 -> 34555985 | H34: =H33+G34 -> 30282077 | I34: =I33+H34 -> 15873759 | J34: =J33+I34 -> 7522308.9 | K34: =K33+J34 -> -371578.47 | L34: =L33+K34 -> 15477511 | ... T34: =T33+S34 -> 6798010

Sheet Resumen Pto #2
W1: Actualizado | X1: ='C. Gestión Pto #1'!V1 -> 46174
B3: OBRA: SVD 4140
B4: RESUMEN DE OBRA
D5: 45839 | E5: 45870 | F5: 45901 | G5: 45931 | H5: 45962 | I5: 45992 | J5: 46023 | K5: 46054 | L5: 46082 | M5: 46113 | N5: 46143 | P5: Acum. Descontado | R5: Previsto Etapa Albañilería | S5: % Cert. Acum. | T5: Saldo Disponible | U5: Disponible % | V5: Rubro Completado
B6: Ingresos de Obra
B7: Ingresos por certificados | D7: =SUM(SUMIFS(Facturacion!$E$11:$E$64,Facturacion!$A$11:$A$64,">="&DATE(2025,7,1),Facturacion!$A$11:$A$64,"<="&DATE(2025,7,31),Facturacion!$C$11:$C$64,Facturacion!$C$5)) -> 0 | E7: =SUM(SUMIFS(Facturacion!$E$11:$E$64,Facturacion!$A$11:$A$64,">="&DATE(2025,8,1),Facturacion!$A$11:$A$64,"<="&DATE(2025,8,31),Facturacion!$C$11:$C$64,Facturacion!$C$5)) -> 0 | F7: =SUM(SUMIFS(Facturacion!$E$11:$E$64,Facturacion!$A$11:$A$64,">="&DATE(2025,9,1),Facturacion!$A$11:$A$64,"<="&DATE(2025,9,30),Facturacion!$C$11:$C$64,Facturacion!$C$5)) -> 0 | G7: =SUM(SUMIFS(Facturacion!$E$11:$E$64,Facturacion!$A$11:$A$64,">="&DATE(2025,10,1),Facturacion!$A$11:$A$64,"<="&DATE(2025,10,30),Facturacion!$C$11:$C$64,Facturacion!$C$5)) -> 3.1350773e+08 | H7: =SUM(SUMIFS(Facturacion!$E$11:$E$64,Facturacion!$A$11:$A$64,">="&DATE(2025,11,1),Facturacion!$A$11:$A$64,"<="&DATE(2025,11,30),Facturacion!$C$11:$C$64,Facturacion!$C$5)) -> 16882763 | I7: =SUM(SUMIFS(Facturacion!$E$11:$E$64,Facturacion!$A$11:$A$64,">="&DATE(2025,12,1),Facturacion!$A$11:$A$64,"<="&DATE(2025,12,31),Facturacion!$C$11:$C$64,Facturacion!$C$5)) -> 9854176 | J7: =SUM(SUMIFS(Facturacion!$E$11:$E$64,Facturacion!$A$11:$A$64,">="&DATE(2026,1,1),Facturacion!$A$11:$A$64,"<="&DATE(2026,1,31),Facturacion!$C$11:$C$64,Facturacion!$C$5)) -> 8287386 | K7: =SUM(SUMIFS(Facturacion!$E$11:$E$64,Facturacion!$A$11:$A$64,">="&DATE(2026,2,1),Facturacion!$A$11:$A$64,"<="&DATE(2026,2,28),Facturacion!$C$11:$C$64,Facturacion!$C$5)) -> 16155654 | L7: =SUM(SUMIFS(Facturacion!$E$11:$E$64,Facturacion!$A$11:$A$64,">="&DATE(2026,3,1),Facturacion!$A$11:$A$64,"<="&DATE(2026,3,31),Facturacion!$C$11:$C$64,Facturacion!$C$5)) -> 15716390 | M7: =SUM(SUMIFS(Facturacion!$E$11:$E$64,Facturacion!$A$11:$A$64,">="&DATE(2026,4,1),Facturacion!$A$11:$A$64,"<="&DATE(2026,4,30),Facturacion!$C$11:$C$64,Facturacion!$C$5)) -> 27219231 | N7: =SUM(SUMIFS(Facturacion!$E$11:$E$64,Facturacion!$A$11:$A$64,">="&DATE(2026,5,1),Facturacion!$A$11:$A$64,"<="&DATE(2026,5,31),Facturacion!$C$11:$C$64,Facturacion!$C$5)) -> 41422349 | P7: =SUM($D7:$O7) -> 4.4904568e+08 | R7: =Facturacion!E5 -> 7.3685713e+08 | S7: ='Pto. 02 Cert.'!S186/'Pto. 02 Cert.'!L186 -> 0.4390752 | T7: =IF(S7=100%,0,IF(OR(P7<>0,R7),R7-P7)) -> 2.8781145e+08 | U7: =IF(OR(T7<0,R7),T7/R7,0%) -> 0.39059329 | V7: =IF(S7=100%,IF(OR(P7<>0,R7),R7-P7),0) -> 0
B8: Total Ingresos de Obra | D8: =SUM(D7) -> 0 | E8: =SUM(E7) -> 0 | F8: =SUM(F7) -> 0 | G8: =SUM(G7) -> 3.1350773e+08 | H8: =SUM(H7) -> 16882763 | I8: =SUM(I7) -> 9854176 | J8: =SUM(J7) -> 8287386 | K8: =SUM(K7) -> 16155654 | ... N8: =SUM(N7) -> 41422349 | P8: =SUM(P7) -> 4.4904568e+08 | R8: =SUM(R7) -> 7.3685713e+08 | T8: =IF(S8=100%,0,IF(OR(P8<>0,R8),R8-P8)) -> 2.8781145e+08 | U8: =IF(OR(T8<0,R8),T8/R8,0%) -> 0.39059329 | V8: =SUM(V7) -> 0
B9: Actualización por CAC | D9: =SUM(SUMIFS(Facturacion!$F$11:$F$64,Facturacion!$A$11:$A$64,">="&DATE(2025,7,1),Facturacion!$A$11:$A$64,"<="&DATE(2025,7,31),Facturacion!$J$11:$J$64,Facturacion!$J$5)) -> 0 | E9: =SUM(SUMIFS(Facturacion!$F$11:$F$64,Facturacion!$A$11:$A$64,">="&DATE(2025,8,1),Facturacion!$A$11:$A$64,"<="&DATE(2025,8,31),Facturacion!$J$11:$J$64,Facturacion!$J$5)) -> 0 | F9: =SUM(SUMIFS(Facturacion!$F$11:$F$64,Facturacion!$A$11:$A$64,">="&DATE(2025,9,1),Facturacion!$A$11:$A$64,"<="&DATE(2025,9,30),Facturacion!$J$11:$J$64,Facturacion!$J$5)) -> 0 | G9: =SUM(SUMIFS(Facturacion!$F$11:$F$64,Facturacion!$A$11:$A$64,">="&DATE(2025,10,1),Facturacion!$A$11:$A$64,"<="&DATE(2025,10,30),Facturacion!$J$11:$J$64,Facturacion!$J$5)) -> 52691995 | H9: =SUM(SUMIFS(Facturacion!$F$11:$F$64,Facturacion!$A$11:$A$64,">="&DATE(2025,11,1),Facturacion!$A$11:$A$64,"<="&DATE(2025,11,30),Facturacion!$J$11:$J$64,Facturacion!$J$5)) -> 3960154.4 | I9: =SUM(SUMIFS(Facturacion!$F$11:$F$64,Facturacion!$A$11:$A$64,">="&DATE(2025,12,1),Facturacion!$A$11:$A$64,"<="&DATE(2025,12,31),Facturacion!$J$11:$J$64,Facturacion!$J$5)) -> 2386555.9 | J9: =SUM(SUMIFS(Facturacion!$F$11:$F$64,Facturacion!$A$11:$A$64,">="&DATE(2026,1,1),Facturacion!$A$11:$A$64,"<="&DATE(2026,1,31),Facturacion!$J$11:$J$64,Facturacion!$J$5)) -> 2404264.3 | K9: =SUM(SUMIFS(Facturacion!$F$11:$F$64,Facturacion!$A$11:$A$64,">="&DATE(2026,2,1),Facturacion!$A$11:$A$64,"<="&DATE(2026,2,28),Facturacion!$J$11:$J$64,Facturacion!$J$5)) -> 5098118.2 | L9: =SUM(SUMIFS(Facturacion!$F$11:$F$64,Facturacion!$A$11:$A$64,">="&DATE(2026,3,1),Facturacion!$A$11:$A$64,"<="&DATE(2026,3,31),Facturacion!$J$11:$J$64,Facturacion!$J$5)) -> 5297358.4 | M9: =SUM(SUMIFS(Facturacion!$F$11:$F$64,Facturacion!$A$11:$A$64,">="&DATE(2026,4,1),Facturacion!$A$11:$A$64,"<="&DATE(2026,4,30),Facturacion!$J$11:$J$64,Facturacion!$J$5)) -> 9636019.7 | N9: =SUM(SUMIFS(Facturacion!$F$11:$F$64,Facturacion!$A$11:$A$64,">="&DATE(2026,5,1),Facturacion!$A$11:$A$64,"<="&DATE(2026,5,31),Facturacion!$J$11:$J$64,Facturacion!$J$5)) -> 15732588 | P9: =SUM($D9:$O9) -> 97207054 | R9: 0 | S9: 0 | T9: =IF(S9=100%,0,IF(R9=0,R9,R9-P9)) -> 0 | U9: =IF(OR(T9<0,R9),T9/R9,0%) -> 0 | V9: =IF(S9=100%,IF(OR(P9<>0,R9),R9-P9),0) -> 0
B10: Total Ingresos por CAC | D10: =SUM(D9) -> 0 | E10: =SUM(E9) -> 0 | F10: =SUM(F9) -> 0 | G10: =SUM(G9) -> 52691995 | H10: =SUM(H9) -> 3960154.4 | I10: =SUM(I9) -> 2386555.9 | J10: =SUM(J9) -> 2404264.3 | K10: =SUM(K9) -> 5098118.2 | ... N10: =SUM(N9) -> 15732588 | P10: =SUM(P9) -> 97207054 | R10: =SUM(R9) -> 0 | T10: =SUM(T9) -> 0 | U10: =IF(OR(T10<0,R10),T10/R10,0%) -> 0 | V10: =SUM(V9) -> 0
B12: Costos de Obra
B13: Seguridad e Higiene | D13: =IFERROR(VLOOKUP($B13&$C13,'C. Gestión Pto #2'!$B$4:C$23,MATCH(D$5,'C. Gestión Pto #2'!$B$4:C$4,0),FALSE),0) -> 0 | E13: =IFERROR(VLOOKUP($B13&$C13,'C. Gestión Pto #2'!$B$4:D$23,MATCH(E$5,'C. Gestión Pto #2'!$B$4:D$4,0),FALSE),0) -> 0 | F13: =IFERROR(VLOOKUP($B13&$C13,'C. Gestión Pto #2'!$B$4:E$23,MATCH(F$5,'C. Gestión Pto #2'!$B$4:E$4,0),FALSE),0) -> 0 | G13: =IFERROR(VLOOKUP($B13&$C13,'C. Gestión Pto #2'!$B$4:F$23,MATCH(G$5,'C. Gestión Pto #2'!$B$4:F$4,0),FALSE),0) -> 0 | H13: =IFERROR(VLOOKUP($B13&$C13,'C. Gestión Pto #2'!$B$4:G$23,MATCH(H$5,'C. Gestión Pto #2'!$B$4:G$4,0),FALSE),0) -> 0 | I13: =IFERROR(VLOOKUP($B13&$C13,'C. Gestión Pto #2'!$B$4:H$23,MATCH(I$5,'C. Gestión Pto #2'!$B$4:H$4,0),FALSE),0) -> 0 | J13: =IFERROR(VLOOKUP($B13&$C13,'C. Gestión Pto #2'!$B$4:I$23,MATCH(J$5,'C. Gestión Pto #2'!$B$4:I$4,0),FALSE),0) -> 0 | K13: =IFERROR(VLOOKUP($B13&$C13,'C. Gestión Pto #2'!$B$4:J$23,MATCH(K$5,'C. Gestión Pto #2'!$B$4:J$4,0),FALSE),0) -> 0 | ... N13: =IFERROR(VLOOKUP($B13&$C13,'C. Gestión Pto #2'!$B$4:M$23,MATCH(N$5,'C. Gestión Pto #2'!$B$4:M$4,0),FALSE),0) -> 1407000 | P13: {=SUMPRODUCT($D13:$O13,TRANSPOSE('Indice CAC'!$C$16:$C$27))} -> 987440.11 | R13: =IF($C13="MAT",SUMIF('Pto. Costos'!$A$64:$A$240,'Resumen Pto #2'!$B13,'Pto. Costos'!$G$64:$G$240),IF($C13="MO",SUMIF('Pto. Costos'!$A$64:$A$240,'Resumen Pto #2'!$B13,'Pto. Costos'!$I$64:$I$240),SUMIF('Pto. Costos'!$A$64:$A$240,'Resumen Pto #2'!$B13,'Pto. Costos'!$L$64:$L$240))) -> 900000 | S13: =IF(C13="MAT",SUMIF('Pto. 02 Cert.'!$A$10:$A$185,$B13,'Pto. 02 Cert.'!$T$10:$T$185),IF(C13="MO",SUMIF('Pto. 02 Cert.'!$A$10:$A$185,$B13,'Pto. 02 Cert.'!$U$10:$U$185),SUMIF('Pto. 02 Cert.'!$A$10:$A$185,$B13,'Pto. 02 Cert.'!$V$10:$V$185)))/IF(C13="MAT",SUMIF('Pto. 02 Cert.'!$A$10:$A$185,$B13,'Pto. 02 Cert.'!$I$10:$I$185),IF(C13="MO",SUMIF('Pto. 02 Cert.'!$A$10:$A$185,$B13,'Pto. 02 Cert.'!$J$10:$J$185),SUMIF('Pto. 02 Cert.'!$A$10:$A$185,$B13,'Pto. 02 Cert.'!$K$10:$K$185))) -> 0.5 | T13: =IF(S13=100%,0,IF(OR(P13<>0,R13),R13-P13)) -> -87440.107 | U13: =IF(OR(T13<0,R13),T13/R13,0%) -> -0.097155674 | V13: =IF(S13=100%,IF(OR(P13<>0,R13),R13-P13),0) -> 0
B14: Supervisión de Obra | D14: =IFERROR(VLOOKUP($B14&$C14,'C. Gestión Pto #2'!$B$4:C$23,MATCH(D$5,'C. Gestión Pto #2'!$B$4:C$4,0),FALSE),0) -> 0 | E14: =IFERROR(VLOOKUP($B14&$C14,'C. Gestión Pto #2'!$B$4:D$23,MATCH(E$5,'C. Gestión Pto #2'!$B$4:D$4,0),FALSE),0) -> 0 | F14: =IFERROR(VLOOKUP($B14&$C14,'C. Gestión Pto #2'!$B$4:E$23,MATCH(F$5,'C. Gestión Pto #2'!$B$4:E$4,0),FALSE),0) -> 0 | G14: =IFERROR(VLOOKUP($B14&$C14,'C. Gestión Pto #2'!$B$4:F$23,MATCH(G$5,'C. Gestión Pto #2'!$B$4:F$4,0),FALSE),0) -> 0 | H14: =IFERROR(VLOOKUP($B14&$C14,'C. Gestión Pto #2'!$B$4:G$23,MATCH(H$5,'C. Gestión Pto #2'!$B$4:G$4,0),FALSE),0) -> 0 | I14: =IFERROR(VLOOKUP($B14&$C14,'C. Gestión Pto #2'!$B$4:H$23,MATCH(I$5,'C. Gestión Pto #2'!$B$4:H$4,0),FALSE),0) -> 4921623.7 | J14: =IFERROR(VLOOKUP($B14&$C14,'C. Gestión Pto #2'!$B$4:I$23,MATCH(J$5,'C. Gestión Pto #2'!$B$4:I$4,0),FALSE),0) -> 3399806.5 | K14: =IFERROR(VLOOKUP($B14&$C14,'C. Gestión Pto #2'!$B$4:J$23,MATCH(K$5,'C. Gestión Pto #2'!$B$4:J$4,0),FALSE),0) -> 3458743.6 | ... N14: =IFERROR(VLOOKUP($B14&$C14,'C. Gestión Pto #2'!$B$4:M$23,MATCH(N$5,'C. Gestión Pto #2'!$B$4:M$4,0),FALSE),0) -> 3838186.8 | P14: {=SUMPRODUCT($D14:$O14,TRANSPOSE('Indice CAC'!$C$16:$C$27))} -> 16798710 | R14: =IF($C14="MAT",SUMIF('Pto. Costos'!$A$64:$A$240,'Resumen Pto #2'!$B14,'Pto. Costos'!$G$64:$G$240),IF($C14="MO",SUMIF('Pto. Costos'!$A$64:$A$240,'Resumen Pto #2'!$B14,'Pto. Costos'!$I$64:$I$240),SUMIF('Pto. Costos'!$A$64:$A$240,'Resumen Pto #2'!$B14,'Pto. Costos'!$L$64:$L$240))) -> 22790223 | S14: =IF(C14="MAT",SUMIF('Pto. 02 Cert.'!$A$10:$A$185,$B14,'Pto. 02 Cert.'!$T$10:$T$185),IF(C14="MO",SUMIF('Pto. 02 Cert.'!$A$10:$A$185,$B14,'Pto. 02 Cert.'!$U$10:$U$185),SUMIF('Pto. 02 Cert.'!$A$10:$A$185,$B14,'Pto. 02 Cert.'!$V$10:$V$185)))/IF(C14="MAT",SUMIF('Pto. 02 Cert.'!$A$10:$A$185,$B14,'Pto. 02 Cert.'!$I$10:$I$185),IF(C14="MO",SUMIF('Pto. 02 Cert.'!$A$10:$A$185,$B14,'Pto. 02 Cert.'!$J$10:$J$185),SUMIF('Pto. 02 Cert.'!$A$10:$A$185,$B14,'Pto. 02 Cert.'!$K$10:$K$185))) -> 0.5 | T14: =IF(S14=100%,0,IF(OR(P14<>0,R14),R14-P14)) -> 5991513.8 | U14: =IF(OR(T14<0,R14),T14/R14,0%) -> 0.26289842 | V14: =IF(S14=100%,IF(OR(P14<>0,R14),R14-P14),0) -> 0
B15: Movilidad | D15: =IFERROR(VLOOKUP($B15&$C15,'C. Gestión Pto #2'!$B$4:C$23,MATCH(D$5,'C. Gestión Pto #2'!$B$4:C$4,0),FALSE),0) -> 0 | E15: =IFERROR(VLOOKUP($B15&$C15,'C. Gestión Pto #2'!$B$4:D$23,MATCH(E$5,'C. Gestión Pto #2'!$B$4:D$4,0),FALSE),0) -> 0 | F15: =IFERROR(VLOOKUP($B15&$C15,'C. Gestión Pto #2'!$B$4:E$23,MATCH(F$5,'C. Gestión Pto #2'!$B$4:E$4,0),FALSE),0) -> 0 | G15: =IFERROR(VLOOKUP($B15&$C15,'C. Gestión Pto #2'!$B$4:F$23,MATCH(G$5,'C. Gestión Pto #2'!$B$4:F$4,0),FALSE),0) -> 0 | H15: =IFERROR(VLOOKUP($B15&$C15,'C. Gestión Pto #2'!$B$4:G$23,MATCH(H$5,'C. Gestión Pto #2'!$B$4:G$4,0),FALSE),0) -> 0 | I15: =IFERROR(VLOOKUP($B15&$C15,'C. Gestión Pto #2'!$B$4:H$23,MATCH(I$5,'C. Gestión Pto #2'!$B$4:H$4,0),FALSE),0) -> 0 | J15: =IFERROR(VLOOKUP($B15&$C15,'C. Gestión Pto #2'!$B$4:I$23,MATCH(J$5,'C. Gestión Pto #2'!$B$4:I$4,0),FALSE),0) -> 0 | K15: =IFERROR(VLOOKUP($B15&$C15,'C. Gestión Pto #2'!$B$4:J$23,MATCH(K$5,'C. Gestión Pto #2'!$B$4:J$4,0),FALSE),0) -> 0 | ... N15: =IFERROR(VLOOKUP($B15&$C15,'C. Gestión Pto #2'!$B$4:M$23,MATCH(N$5,'C. Gestión Pto #2'!$B$4:M$4,0),FALSE),0) -> 324436.07 | P15: {=SUMPRODUCT($D15:$O15,TRANSPOSE('Indice CAC'!$C$16:$C$27))} -> 227690.96 | R15: =IF($C15="MAT",SUMIF('Pto. Costos'!$A$64:$A$240,'Resumen Pto #2'!$B15,'Pto. Costos'!$G$64:$G$240),IF($C15="MO",SUMIF('Pto. Costos'!$A$64:$A$240,'Resumen Pto #2'!$B15,'Pto. Costos'!$I$64:$I$240),SUMIF('Pto. Costos'!$A$64:$A$240,'Resumen Pto #2'!$B15,'Pto. Costos'!$L$64:$L$240))) -> 4500000 | S15: =IF(C15="MAT",SUMIF('Pto. 02 Cert.'!$A$10:$A$185,$B15,'Pto. 02 Cert.'!$T$10:$T$185),IF(C15="MO",SUMIF('Pto. 02 Cert.'!$A$10:$A$185,$B15,'Pto. 02 Cert.'!$U$10:$U$185),SUMIF('Pto. 02 Cert.'!$A$10:$A$185,$B15,'Pto. 02 Cert.'!$V$10:$V$185)))/IF(C15="MAT",SUMIF('Pto. 02 Cert.'!$A$10:$A$185,$B15,'Pto. 02 Cert.'!$I$10:$I$185),IF(C15="MO",SUMIF('Pto. 02 Cert.'!$A$10:$A$185,$B15,'Pto. 02 Cert.'!$J$10:$J$185),SUMIF('Pto. 02 Cert.'!$A$10:$A$185,$B15,'Pto. 02 Cert.'!$K$10:$K$185))) -> 0.46666667 | T15: =IF(S15=100%,0,IF(OR(P15<>0,R15),R15-P15)) -> 4272309 | U15: =IF(OR(T15<0,R15),T15/R15,0%) -> 0.94940201 | V15: =IF(S15=100%,IF(OR(P15<>0,R15),R15-P15),0) -> 0
B16: Albañilería | C16: MAT | D16: =IFERROR(VLOOKUP($B16&$C16,'C. Gestión Pto #2'!$B$4:C$23,MATCH(D$5,'C. Gestión Pto #2'!$B$4:C$4,0),FALSE),0) -> 0 | E16: =IFERROR(VLOOKUP($B16&$C16,'C. Gestión Pto #2'!$B$4:D$23,MATCH(E$5,'C. Gestión Pto #2'!$B$4:D$4,0),FALSE),0) -> 0 | F16: =IFERROR(VLOOKUP($B16&$C16,'C. Gestión Pto #2'!$B$4:E$23,MATCH(F$5,'C. Gestión Pto #2'!$B$4:E$4,0),FALSE),0) -> 0 | G16: =IFERROR(VLOOKUP($B16&$C16,'C. Gestión Pto #2'!$B$4:F$23,MATCH(G$5,'C. Gestión Pto #2'!$B$4:F$4,0),FALSE),0) -> 21385401 | H16: =IFERROR(VLOOKUP($B16&$C16,'C. Gestión Pto #2'!$B$4:G$23,MATCH(H$5,'C. Gestión Pto #2'!$B$4:G$4,0),FALSE),0) -> 5653260.9 | I16: =IFERROR(VLOOKUP($B16&$C16,'C. Gestión Pto #2'!$B$4:H$23,MATCH(I$5,'C. Gestión Pto #2'!$B$4:H$4,0),FALSE),0) -> 524503.91 | J16: =IFERROR(VLOOKUP($B16&$C16,'C. Gestión Pto #2'!$B$4:I$23,MATCH(J$5,'C. Gestión Pto #2'!$B$4:I$4,0),FALSE),0) -> 4059472.8 | K16: =IFERROR(VLOOKUP($B16&$C16,'C. Gestión Pto #2'!$B$4:J$23,MATCH(K$5,'C. Gestión Pto #2'!$B$4:J$4,0),FALSE),0) -> 3330609.2 | ... N16: =IFERROR(VLOOKUP($B16&$C16,'C. Gestión Pto #2'!$B$4:M$23,MATCH(N$5,'C. Gestión Pto #2'!$B$4:M$4,0),FALSE),0) -> 23833774 | P16: {=SUMPRODUCT($D16:$O16,TRANSPOSE('Indice CAC'!$C$16:$C$27))} -> 61735009 | R16: =IF($C16="MAT",SUMIF('Pto. Costos'!$A$64:$A$240,'Resumen Pto #2'!$B16,'Pto. Costos'!$G$64:$G$240),IF($C16="MO",SUMIF('Pto. Costos'!$A$64:$A$240,'Resumen Pto #2'!$B16,'Pto. Costos'!$I$64:$I$240),SUMIF('Pto. Costos'!$A$64:$A$240,'Resumen Pto #2'!$B16,'Pto. Costos'!$L$64:$L$240))) -> 61725811 | S16: =IF(C16="MAT",SUMIF('Pto. 02 Cert.'!$A$10:$A$185,$B16,'Pto. 02 Cert.'!$T$10:$T$185),IF(C16="MO",SUMIF('Pto. 02 Cert.'!$A$10:$A$185,$B16,'Pto. 02 Cert.'!$U$10:$U$185),SUMIF('Pto. 02 Cert.'!$A$10:$A$185,$B16,'Pto. 02 Cert.'!$V$10:$V$185)))/IF(C16="MAT",SUMIF('Pto. 02 Cert.'!$A$10:$A$185,$B16,'Pto. 02 Cert.'!$I$10:$I$185),IF(C16="MO",SUMIF('Pto. 02 Cert.'!$A$10:$A$185,$B16,'Pto. 02 Cert.'!$J$10:$J$185),SUMIF('Pto. 02 Cert.'!$A$10:$A$185,$B16,'Pto. 02 Cert.'!$K$10:$K$185))) -> 0.4538506 | T16: =IF(S16=100%,0,IF(OR(P16<>0,R16),R16-P16)) -> -9198.4568 | U16: =IF(OR(T16<0,R16),T16/R16,0%) -> -0.00014902124 | V16: =IF(S16=100%,IF(OR(P16<>0,R16),R16-P16),0) -> 0
B17: Albañilería | C17: MO | D17: =IFERROR(VLOOKUP($B17&$C17,'C. Gestión Pto #2'!$B$4:C$23,MATCH(D$5,'C. Gestión Pto #2'!$B$4:C$4,0),FALSE),0) -> 0 | E17: =IFERROR(VLOOKUP($B17&$C17,'C. Gestión Pto #2'!$B$4:D$23,MATCH(E$5,'C. Gestión Pto #2'!$B$4:D$4,0),FALSE),0) -> 0 | F17: =IFERROR(VLOOKUP($B17&$C17,'C. Gestión Pto #2'!$B$4:E$23,MATCH(F$5,'C. Gestión Pto #2'!$B$4:E$4,0),FALSE),0) -> 0 | G17: =IFERROR(VLOOKUP($B17&$C17,'C. Gestión Pto #2'!$B$4:F$23,MATCH(G$5,'C. Gestión Pto #2'!$B$4:F$4,0),FALSE),0) -> 10224408 | H17: =IFERROR(VLOOKUP($B17&$C17,'C. Gestión Pto #2'!$B$4:G$23,MATCH(H$5,'C. Gestión Pto #2'!$B$4:G$4,0),FALSE),0) -> 9687819.9 | I17: =IFERROR(VLOOKUP($B17&$C17,'C. Gestión Pto #2'!$B$4:H$23,MATCH(I$5,'C. Gestión Pto #2'!$B$4:H$4,0),FALSE),0) -> 15241735 | J17: =IFERROR(VLOOKUP($B17&$C17,'C. Gestión Pto #2'!$B$4:I$23,MATCH(J$5,'C. Gestión Pto #2'!$B$4:I$4,0),FALSE),0) -> 23120863 | K17: =IFERROR(VLOOKUP($B17&$C17,'C. Gestión Pto #2'!$B$4:J$23,MATCH(K$5,'C. Gestión Pto #2'!$B$4:J$4,0),FALSE),0) -> 23725839 | ... N17: =IFERROR(VLOOKUP($B17&$C17,'C. Gestión Pto #2'!$B$4:M$23,MATCH(N$5,'C. Gestión Pto #2'!$B$4:M$4,0),FALSE),0) -> 34129760 | P17: {=SUMPRODUCT($D17:$O17,TRANSPOSE('Indice CAC'!$C$16:$C$27))} -> 1.2751499e+08 | R17: =IF($C17="MAT",SUMIF('Pto. Costos'!$A$64:$A$240,'Resumen Pto #2'!$B17,'Pto. Costos'!$G$64:$G$240),IF($C17="MO",SUMIF('Pto. Costos'!$A$64:$A$240,'Resumen Pto #2'!$B17,'Pto. Costos'!$I$64:$I$240),SUMIF('Pto. Costos'!$A$64:$A$240,'Resumen Pto #2'!$B17,'Pto. Costos'!$L$64:$L$240))) -> 1.2838306e+08 | S17: =IF(C17="MAT",SUMIF('Pto. 02 Cert.'!$A$10:$A$185,$B17,'Pto. 02 Cert.'!$T$10:$T$185),IF(C17="MO",SUMIF('Pto. 02 Cert.'!$A$10:$A$185,$B17,'Pto. 02 Cert.'!$U$10:$U$185),SUMIF('Pto. 02 Cert.'!$A$10:$A$185,$B17,'Pto. 02 Cert.'!$V$10:$V$185)))/IF(C17="MAT",SUMIF('Pto. 02 Cert.'!$A$10:$A$185,$B17,'Pto. 02 Cert.'!$I$10:$I$185),IF(C17="MO",SUMIF('Pto. 02 Cert.'!$A$10:$A$185,$B17,'Pto. 02 Cert.'!$J$10:$J$185),SUMIF('Pto. 02 Cert.'!$A$10:$A$185,$B17,'Pto. 02 Cert.'!$K$10:$K$185))) -> 0.5311314 | T17: =IF(S17=100%,0,IF(OR(P17<>0,R17),R17-P17)) -> 868063.68 | U17: =IF(OR(T17<0,R17),T17/R17,0%) -> 0.0067615128 | V17: =IF(S17=100%,IF(OR(P17<>0,R17),R17-P17),0) -> 0
B18: Durlock | C18: MAT | D18: =IFERROR(VLOOKUP($B18&$C18,'C. Gestión Pto #2'!$B$4:C$23,MATCH(D$5,'C. Gestión Pto #2'!$B$4:C$4,0),FALSE),0) -> 0 | E18: =IFERROR(VLOOKUP($B18&$C18,'C. Gestión Pto #2'!$B$4:D$23,MATCH(E$5,'C. Gestión Pto #2'!$B$4:D$4,0),FALSE),0) -> 0 | F18: =IFERROR(VLOOKUP($B18&$C18,'C. Gestión Pto #2'!$B$4:E$23,MATCH(F$5,'C. Gestión Pto #2'!$B$4:E$4,0),FALSE),0) -> 14055.62 | G18: =IFERROR(VLOOKUP($B18&$C18,'C. Gestión Pto #2'!$B$4:F$23,MATCH(G$5,'C. Gestión Pto #2'!$B$4:F$4,0),FALSE),0) -> 0 | H18: =IFERROR(VLOOKUP($B18&$C18,'C. Gestión Pto #2'!$B$4:G$23,MATCH(H$5,'C. Gestión Pto #2'!$B$4:G$4,0),FALSE),0) -> 0 | I18: =IFERROR(VLOOKUP($B18&$C18,'C. Gestión Pto #2'!$B$4:H$23,MATCH(I$5,'C. Gestión Pto #2'!$B$4:H$4,0),FALSE),0) -> 0 | J18: =IFERROR(VLOOKUP($B18&$C18,'C. Gestión Pto #2'!$B$4:I$23,MATCH(J$5,'C. Gestión Pto #2'!$B$4:I$4,0),FALSE),0) -> 0 | K18: =IFERROR(VLOOKUP($B18&$C18,'C. Gestión Pto #2'!$B$4:J$23,MATCH(K$5,'C. Gestión Pto #2'!$B$4:J$4,0),FALSE),0) -> 6856283.7 | ... N18: =IFERROR(VLOOKUP($B18&$C18,'C. Gestión Pto #2'!$B$4:M$23,MATCH(N$5,'C. Gestión Pto #2'!$B$4:M$4,0),FALSE),0) -> 12647943 | P18: {=SUMPRODUCT($D18:$O18,TRANSPOSE('Indice CAC'!$C$16:$C$27))} -> 15079861 | R18: =IF($C18="MAT",SUMIF('Pto. Costos'!$A$64:$A$240,'Resumen Pto #2'!$B18,'Pto. Costos'!$G$64:$G$240),IF($C18="MO",SUMIF('Pto. Costos'!$A$64:$A$240,'Resumen Pto #2'!$B18,'Pto. Costos'!$I$64:$I$240),SUMIF('Pto. Costos'!$A$64:$A$240,'Resumen Pto #2'!$B18,'Pto. Costos'!$L$64:$L$240))) -> 24596469 | S18: =IF(C18="MAT",SUMIF('Pto. 02 Cert.'!$A$10:$A$185,$B18,'Pto. 02 Cert.'!$T$10:$T$185),IF(C18="MO",SUMIF('Pto. 02 Cert.'!$A$10:$A$185,$B18,'Pto. 02 Cert.'!$U$10:$U$185),SUMIF('Pto. 02 Cert.'!$A$10:$A$185,$B18,'Pto. 02 Cert.'!$V$10:$V$185)))/IF(C18="MAT",SUMIF('Pto. 02 Cert.'!$A$10:$A$185,$B18,'Pto. 02 Cert.'!$I$10:$I$185),IF(C18="MO",SUMIF('Pto. 02 Cert.'!$A$10:$A$185,$B18,'Pto. 02 Cert.'!$J$10:$J$185),SUMIF('Pto. 02 Cert.'!$A$10:$A$185,$B18,'Pto. 02 Cert.'!$K$10:$K$185))) -> 0.56143986 | T18: =IF(S18=100%,0,IF(OR(P18<>0,R18),R18-P18)) -> 9516608.9 | U18: =IF(OR(T18<0,R18),T18/R18,0%) -> 0.38690955 | V18: =IF(S18=100%,IF(OR(P18<>0,R18),R18-P18),0) -> 0
B19: Durlock | C19: MO | D19: =IFERROR(VLOOKUP($B19&$C19,'C. Gestión Pto #2'!$B$4:C$23,MATCH(D$5,'C. Gestión Pto #2'!$B$4:C$4,0),FALSE),0) -> 0 | E19: =IFERROR(VLOOKUP($B19&$C19,'C. Gestión Pto #2'!$B$4:D$23,MATCH(E$5,'C. Gestión Pto #2'!$B$4:D$4,0),FALSE),0) -> 0 | F19: =IFERROR(VLOOKUP($B19&$C19,'C. Gestión Pto #2'!$B$4:E$23,MATCH(F$5,'C. Gestión Pto #2'!$B$4:E$4,0),FALSE),0) -> 0 | G19: =IFERROR(VLOOKUP($B19&$C19,'C. Gestión Pto #2'!$B$4:F$23,MATCH(G$5,'C. Gestión Pto #2'!$B$4:F$4,0),FALSE),0) -> 0 | H19: =IFERROR(VLOOKUP($B19&$C19,'C. Gestión Pto #2'!$B$4:G$23,MATCH(H$5,'C. Gestión Pto #2'!$B$4:G$4,0),FALSE),0) -> 0 | I19: =IFERROR(VLOOKUP($B19&$C19,'C. Gestión Pto #2'!$B$4:H$23,MATCH(I$5,'C. Gestión Pto #2'!$B$4:H$4,0),FALSE),0) -> 0 | J19: =IFERROR(VLOOKUP($B19&$C19,'C. Gestión Pto #2'!$B$4:I$23,MATCH(J$5,'C. Gestión Pto #2'!$B$4:I$4,0),FALSE),0) -> 1027500 | K19: =IFERROR(VLOOKUP($B19&$C19,'C. Gestión Pto #2'!$B$4:J$23,MATCH(K$5,'C. Gestión Pto #2'!$B$4:J$4,0),FALSE),0) -> 1288504.6 | ... N19: =IFERROR(VLOOKUP($B19&$C19,'C. Gestión Pto #2'!$B$4:M$23,MATCH(N$5,'C. Gestión Pto #2'!$B$4:M$4,0),FALSE),0) -> 0 | P19: {=SUMPRODUCT($D19:$O19,TRANSPOSE('Indice CAC'!$C$16:$C$27))} -> 6558470.8 | R19: =IF($C19="MAT",SUMIF('Pto. Costos'!$A$64:$A$240,'Resumen Pto #2'!$B19,'Pto. Costos'!$G$64:$G$240),IF($C19="MO",SUMIF('Pto. Costos'!$A$64:$A$240,'Resumen Pto #2'!$B19,'Pto. Costos'!$I$64:$I$240),SUMIF('Pto. Costos'!$A$64:$A$240,'Resumen Pto #2'!$B19,'Pto. Costos'!$L$64:$L$240))) -> 66185630 | S19: =IF(C19="MAT",SUMIF('Pto. 02 Cert.'!$A$10:$A$185,$B19,'Pto. 02 Cert.'!$T$10:$T$185),IF(C19="MO",SUMIF('Pto. 02 Cert.'!$A$10:$A$185,$B19,'Pto. 02 Cert.'!$U$10:$U$185),SUMIF('Pto. 02 Cert.'!$A$10:$A$185,$B19,'Pto. 02 Cert.'!$V$10:$V$185)))/IF(C19="MAT",SUMIF('Pto. 02 Cert.'!$A$10:$A$185,$B19,'Pto. 02 Cert.'!$I$10:$I$185),IF(C19="MO",SUMIF('Pto. 02 Cert.'!$A$10:$A$185,$B19,'Pto. 02 Cert.'!$J$10:$J$185),SUMIF('Pto. 02 Cert.'!$A$10:$A$185,$B19,'Pto. 02 Cert.'!$K$10:$K$185))) -> 0.54645468 | T19: =IF(S19=100%,0,IF(OR(P19<>0,R19),R19-P19)) -> 59627160 | U19: =IF(OR(T19<0,R19),T19/R19,0%) -> 0.90090793 | V19: =IF(S19=100%,IF(OR(P19<>0,R19),R19-P19),0) -> 0
B20: Eléctrico | C20: MAT | D20: =IFERROR(VLOOKUP($B20&$C20,'C. Gestión Pto #2'!$B$4:C$23,MATCH(D$5,'C. Gestión Pto #2'!$B$4:C$4,0),FALSE),0) -> 0 | E20: =IFERROR(VLOOKUP($B20&$C20,'C. Gestión Pto #2'!$B$4:D$23,MATCH(E$5,'C. Gestión Pto #2'!$B$4:D$4,0),FALSE),0) -> 278030.38 | F20: =IFERROR(VLOOKUP($B20&$C20,'C. Gestión Pto #2'!$B$4:E$23,MATCH(F$5,'C. Gestión Pto #2'!$B$4:E$4,0),FALSE),0) -> 1035273.8 | G20: =IFERROR(VLOOKUP($B20&$C20,'C. Gestión Pto #2'!$B$4:F$23,MATCH(G$5,'C. Gestión Pto #2'!$B$4:F$4,0),FALSE),0) -> 2959054.6 | H20: =IFERROR(VLOOKUP($B20&$C20,'C. Gestión Pto #2'!$B$4:G$23,MATCH(H$5,'C. Gestión Pto #2'!$B$4:G$4,0),FALSE),0) -> 1344156.9 | I20: =IFERROR(VLOOKUP($B20&$C20,'C. Gestión Pto #2'!$B$4:H$23,MATCH(I$5,'C. Gestión Pto #2'!$B$4:H$4,0),FALSE),0) -> 48067.03 | J20: =IFERROR(VLOOKUP($B20&$C20,'C. Gestión Pto #2'!$B$4:I$23,MATCH(J$5,'C. Gestión Pto #2'!$B$4:I$4,0),FALSE),0) -> 529125.51 | K20: =IFERROR(VLOOKUP($B20&$C20,'C. Gestión Pto #2'!$B$4:J$23,MATCH(K$5,'C. Gestión Pto #2'!$B$4:J$4,0),FALSE),0) -> 0 | ... N20: =IFERROR(VLOOKUP($B20&$C20,'C. Gestión Pto #2'!$B$4:M$23,MATCH(N$5,'C. Gestión Pto #2'!$B$4:M$4,0),FALSE),0) -> 6134204.4 | P20: {=SUMPRODUCT($D20:$O20,TRANSPOSE('Indice CAC'!$C$16:$C$27))} -> 9301022.1 | R20: =IF($C20="MAT",SUMIF('Pto. Costos'!$A$64:$A$240,'Resumen Pto #2'!$B20,'Pto. Costos'!$G$64:$G$240),IF($C20="MO",SUMIF('Pto. Costos'!$A$64:$A$240,'Resumen Pto #2'!$B20,'Pto. Costos'!$I$64:$I$240),SUMIF('Pto. Costos'!$A$64:$A$240,'Resumen Pto #2'!$B20,'Pto. Costos'!$L$64:$L$240))) -> 31495173 | S20: =IF(C20="MAT",SUMIF('Pto. 02 Cert.'!$A$10:$A$185,$B20,'Pto. 02 Cert.'!$T$10:$T$185),IF(C20="MO",SUMIF('Pto. 02 Cert.'!$A$10:$A$185,$B20,'Pto. 02 Cert.'!$U$10:$U$185),SUMIF('Pto. 02 Cert.'!$A$10:$A$185,$B20,'Pto. 02 Cert.'!$V$10:$V$185)))/IF(C20="MAT",SUMIF('Pto. 02 Cert.'!$A$10:$A$185,$B20,'Pto. 02 Cert.'!$I$10:$I$185),IF(C20="MO",SUMIF('Pto. 02 Cert.'!$A$10:$A$185,$B20,'Pto. 02 Cert.'!$J$10:$J$185),SUMIF('Pto. 02 Cert.'!$A$10:$A$185,$B20,'Pto. 02 Cert.'!$K$10:$K$185))) -> 0.1745068 | T20: =IF(S20=100%,0,IF(OR(P20<>0,R20),R20-P20)) -> 22194151 | U20: =IF(OR(T20<0,R20),T20/R20,0%) -> 0.7046842 | V20: =IF(S20=100%,IF(OR(P20<>0,R20),R20-P20),0) -> 0
B21: Eléctrico | C21: MO | D21: =IFERROR(VLOOKUP($B21&$C21,'C. Gestión Pto #2'!$B$4:C$23,MATCH(D$5,'C. Gestión Pto #2'!$B$4:C$4,0),FALSE),0) -> 550000 | E21: =IFERROR(VLOOKUP($B21&$C21,'C. Gestión Pto #2'!$B$4:D$23,MATCH(E$5,'C. Gestión Pto #2'!$B$4:D$4,0),FALSE),0) -> 0 | F21: =IFERROR(VLOOKUP($B21&$C21,'C. Gestión Pto #2'!$B$4:E$23,MATCH(F$5,'C. Gestión Pto #2'!$B$4:E$4,0),FALSE),0) -> 163802.48 | G21: =IFERROR(VLOOKUP($B21&$C21,'C. Gestión Pto #2'!$B$4:F$23,MATCH(G$5,'C. Gestión Pto #2'!$B$4:F$4,0),FALSE),0) -> 0 | H21: =IFERROR(VLOOKUP($B21&$C21,'C. Gestión Pto #2'!$B$4:G$23,MATCH(H$5,'C. Gestión Pto #2'!$B$4:G$4,0),FALSE),0) -> 0 | I21: =IFERROR(VLOOKUP($B21&$C21,'C. Gestión Pto #2'!$B$4:H$23,MATCH(I$5,'C. Gestión Pto #2'!$B$4:H$4,0),FALSE),0) -> 605000 | J21: =IFERROR(VLOOKUP($B21&$C21,'C. Gestión Pto #2'!$B$4:I$23,MATCH(J$5,'C. Gestión Pto #2'!$B$4:I$4,0),FALSE),0) -> 2580200 | K21: =IFERROR(VLOOKUP($B21&$C21,'C. Gestión Pto #2'!$B$4:J$23,MATCH(K$5,'C. Gestión Pto #2'!$B$4:J$4,0),FALSE),0) -> 0 | ... N21: =IFERROR(VLOOKUP($B21&$C21,'C. Gestión Pto #2'!$B$4:M$23,MATCH(N$5,'C. Gestión Pto #2'!$B$4:M$4,0),FALSE),0) -> 6915189.5 | P21: {=SUMPRODUCT($D21:$O21,TRANSPOSE('Indice CAC'!$C$16:$C$27))} -> 9654242.5 | R21: =IF($C21="MAT",SUMIF('Pto. Costos'!$A$64:$A$240,'Resumen Pto #2'!$B21,'Pto. Costos'!$G$64:$G$240),IF($C21="MO",SUMIF('Pto. Costos'!$A$64:$A$240,'Resumen Pto #2'!$B21,'Pto. Costos'!$I$64:$I$240),SUMIF('Pto. Costos'!$A$64:$A$240,'Resumen Pto #2'!$B21,'Pto. Costos'!$L$64:$L$240))) -> 47599191 | S21: =IF(C21="MAT",SUMIF('Pto. 02 Cert.'!$A$10:$A$185,$B21,'Pto. 02 Cert.'!$T$10:$T$185),IF(C21="MO",SUMIF('Pto. 02 Cert.'!$A$10:$A$185,$B21,'Pto. 02 Cert.'!$U$10:$U$185),SUMIF('Pto. 02 Cert.'!$A$10:$A$185,$B21,'Pto. 02 Cert.'!$V$10:$V$185)))/IF(C21="MAT",SUMIF('Pto. 02 Cert.'!$A$10:$A$185,$B21,'Pto. 02 Cert.'!$I$10:$I$185),IF(C21="MO",SUMIF('Pto. 02 Cert.'!$A$10:$A$185,$B21,'Pto. 02 Cert.'!$J$10:$J$185),SUMIF('Pto. 02 Cert.'!$A$10:$A$185,$B21,'Pto. 02 Cert.'!$K$10:$K$185))) -> 0.29819713 | T21: =IF(S21=100%,0,IF(OR(P21<>0,R21),R21-P21)) -> 37944948 | U21: =IF(OR(T21<0,R21),T21/R21,0%) -> 0.79717633 | V21: =IF(S21=100%,IF(OR(P21<>0,R21),R21-P21),0) -> 0
B22: Sanitaria | C22: MAT | D22: =IFERROR(VLOOKUP($B22&$C22,'C. Gestión Pto #2'!$B$4:C$23,MATCH(D$5,'C. Gestión Pto #2'!$B$4:C$4,0),FALSE),0) -> 0 | E22: =IFERROR(VLOOKUP($B22&$C22,'C. Gestión Pto #2'!$B$4:D$23,MATCH(E$5,'C. Gestión Pto #2'!$B$4:D$4,0),FALSE),0) -> 1350839.1 | F22: =IFERROR(VLOOKUP($B22&$C22,'C. Gestión Pto #2'!$B$4:E$23,MATCH(F$5,'C. Gestión Pto #2'!$B$4:E$4,0),FALSE),0) -> 261266.49 | G22: =IFERROR(VLOOKUP($B22&$C22,'C. Gestión Pto #2'!$B$4:F$23,MATCH(G$5,'C. Gestión Pto #2'!$B$4:F$4,0),FALSE),0) -> 950806.06 | H22: =IFERROR(VLOOKUP($B22&$C22,'C. Gestión Pto #2'!$B$4:G$23,MATCH(H$5,'C. Gestión Pto #2'!$B$4:G$4,0),FALSE),0) -> 230784.75 | I22: =IFERROR(VLOOKUP($B22&$C22,'C. Gestión Pto #2'!$B$4:H$23,MATCH(I$5,'C. Gestión Pto #2'!$B$4:H$4,0),FALSE),0) -> 6006212.1 | J22: =IFERROR(VLOOKUP($B22&$C22,'C. Gestión Pto #2'!$B$4:I$23,MATCH(J$5,'C. Gestión Pto #2'!$B$4:I$4,0),FALSE),0) -> 13136483 | K22: =IFERROR(VLOOKUP($B22&$C22,'C. Gestión Pto #2'!$B$4:J$23,MATCH(K$5,'C. Gestión Pto #2'!$B$4:J$4,0),FALSE),0) -> 3423387.7 | ... N22: =IFERROR(VLOOKUP($B22&$C22,'C. Gestión Pto #2'!$B$4:M$23,MATCH(N$5,'C. Gestión Pto #2'!$B$4:M$4,0),FALSE),0) -> 934654.52 | P22: {=SUMPRODUCT($D22:$O22,TRANSPOSE('Indice CAC'!$C$16:$C$27))} -> 34151989 | R22: =IF($C22="MAT",SUMIF('Pto. Costos'!$A$64:$A$240,'Resumen Pto #2'!$B22,'Pto. Costos'!$G$64:$G$240),IF($C22="MO",SUMIF('Pto. Costos'!$A$64:$A$240,'Resumen Pto #2'!$B22,'Pto. Costos'!$I$64:$I$240),SUMIF('Pto. Costos'!$A$64:$A$240,'Resumen Pto #2'!$B22,'Pto. Costos'!$L$64:$L$240))) -> 31719694 | S22: =IF(C22="MAT",SUMIF('Pto. 02 Cert.'!$A$10:$A$185,$B22,'Pto. 02 Cert.'!$T$10:$T$185),IF(C22="MO",SUMIF('Pto. 02 Cert.'!$A$10:$A$185,$B22,'Pto. 02 Cert.'!$U$10:$U$185),SUMIF('Pto. 02 Cert.'!$A$10:$A$185,$B22,'Pto. 02 Cert.'!$V$10:$V$185)))/IF(C22="MAT",SUMIF('Pto. 02 Cert.'!$A$10:$A$185,$B22,'Pto. 02 Cert.'!$I$10:$I$185),IF(C22="MO",SUMIF('Pto. 02 Cert.'!$A$10:$A$185,$B22,'Pto. 02 Cert.'!$J$10:$J$185),SUMIF('Pto. 02 Cert.'!$A$10:$A$185,$B22,'Pto. 02 Cert.'!$K$10:$K$185))) -> 0.44230624 | T22: =IF(S22=100%,0,IF(OR(P22<>0,R22),R22-P22)) -> -2432294.8 | U22: =IF(OR(T22<0,R22),T22/R22,0%) -> -0.076680903 | V22: =IF(S22=100%,IF(OR(P22<>0,R22),R22-P22),0) -> 0
B23: Sanitaria | C23: MO | D23: =IFERROR(VLOOKUP($B23&$C23,'C. Gestión Pto #2'!$B$4:C$23,MATCH(D$5,'C. Gestión Pto #2'!$B$4:C$4,0),FALSE),0) -> 0 | E23: =IFERROR(VLOOKUP($B23&$C23,'C. Gestión Pto #2'!$B$4:D$23,MATCH(E$5,'C. Gestión Pto #2'!$B$4:D$4,0),FALSE),0) -> 0 | F23: =IFERROR(VLOOKUP($B23&$C23,'C. Gestión Pto #2'!$B$4:E$23,MATCH(F$5,'C. Gestión Pto #2'!$B$4:E$4,0),FALSE),0) -> 709198.46 | G23: =IFERROR(VLOOKUP($B23&$C23,'C. Gestión Pto #2'!$B$4:F$23,MATCH(G$5,'C. Gestión Pto #2'!$B$4:F$4,0),FALSE),0) -> 177942.15 | H23: =IFERROR(VLOOKUP($B23&$C23,'C. Gestión Pto #2'!$B$4:G$23,MATCH(H$5,'C. Gestión Pto #2'!$B$4:G$4,0),FALSE),0) -> 390000 | I23: =IFERROR(VLOOKUP($B23&$C23,'C. Gestión Pto #2'!$B$4:H$23,MATCH(I$5,'C. Gestión Pto #2'!$B$4:H$4,0),FALSE),0) -> 523583.1 | J23: =IFERROR(VLOOKUP($B23&$C23,'C. Gestión Pto #2'!$B$4:I$23,MATCH(J$5,'C. Gestión Pto #2'!$B$4:I$4,0),FALSE),0) -> 6425606.5 | K23: =IFERROR(VLOOKUP($B23&$C23,'C. Gestión Pto #2'!$B$4:J$23,MATCH(K$5,'C. Gestión Pto #2'!$B$4:J$4,0),FALSE),0) -> 7858885.1 | ... N23: =IFERROR(VLOOKUP($B23&$C23,'C. Gestión Pto #2'!$B$4:M$23,MATCH(N$5,'C. Gestión Pto #2'!$B$4:M$4,0),FALSE),0) -> 10832622 | P23: {=SUMPRODUCT($D23:$O23,TRANSPOSE('Indice CAC'!$C$16:$C$27))} -> 36890057 | R23: =IF($C23="MAT",SUMIF('Pto. Costos'!$A$64:$A$240,'Resumen Pto #2'!$B23,'Pto. Costos'!$G$64:$G$240),IF($C23="MO",SUMIF('Pto. Costos'!$A$64:$A$240,'Resumen Pto #2'!$B23,'Pto. Costos'!$I$64:$I$240),SUMIF('Pto. Costos'!$A$64:$A$240,'Resumen Pto #2'!$B23,'Pto. Costos'!$L$64:$L$240))) -> 61809617 | S23: =IF(C23="MAT",SUMIF('Pto. 02 Cert.'!$A$10:$A$185,$B23,'Pto. 02 Cert.'!$T$10:$T$185),IF(C23="MO",SUMIF('Pto. 02 Cert.'!$A$10:$A$185,$B23,'Pto. 02 Cert.'!$U$10:$U$185),SUMIF('Pto. 02 Cert.'!$A$10:$A$185,$B23,'Pto. 02 Cert.'!$V$10:$V$185)))/IF(C23="MAT",SUMIF('Pto. 02 Cert.'!$A$10:$A$185,$B23,'Pto. 02 Cert.'!$I$10:$I$185),IF(C23="MO",SUMIF('Pto. 02 Cert.'!$A$10:$A$185,$B23,'Pto. 02 Cert.'!$J$10:$J$185),SUMIF('Pto. 02 Cert.'!$A$10:$A$185,$B23,'Pto. 02 Cert.'!$K$10:$K$185))) -> 0.43165448 | T23: =IF(S23=100%,0,IF(OR(P23<>0,R23),R23-P23)) -> 24919560 | U23: =IF(OR(T23<0,R23),T23/R23,0%) -> 0.40316638 | V23: =IF(S23=100%,IF(OR(P23<>0,R23),R23-P23),0) -> 0
B24: Revestimiento | C24: MAT | D24: =IFERROR(VLOOKUP($B24&$C24,'C. Gestión Pto #2'!$B$4:C$23,MATCH(D$5,'C. Gestión Pto #2'!$B$4:C$4,0),FALSE),0) -> 0 | E24: =IFERROR(VLOOKUP($B24&$C24,'C. Gestión Pto #2'!$B$4:D$23,MATCH(E$5,'C. Gestión Pto #2'!$B$4:D$4,0),FALSE),0) -> 0 | F24: =IFERROR(VLOOKUP($B24&$C24,'C. Gestión Pto #2'!$B$4:E$23,MATCH(F$5,'C. Gestión Pto #2'!$B$4:E$4,0),FALSE),0) -> 0 | G24: =IFERROR(VLOOKUP($B24&$C24,'C. Gestión Pto #2'!$B$4:F$23,MATCH(G$5,'C. Gestión Pto #2'!$B$4:F$4,0),FALSE),0) -> 0 | H24: =IFERROR(VLOOKUP($B24&$C24,'C. Gestión Pto #2'!$B$4:G$23,MATCH(H$5,'C. Gestión Pto #2'!$B$4:G$4,0),FALSE),0) -> 0 | I24: =IFERROR(VLOOKUP($B24&$C24,'C. Gestión Pto #2'!$B$4:H$23,MATCH(I$5,'C. Gestión Pto #2'!$B$4:H$4,0),FALSE),0) -> 4076500 | J24: =IFERROR(VLOOKUP($B24&$C24,'C. Gestión Pto #2'!$B$4:I$23,MATCH(J$5,'C. Gestión Pto #2'!$B$4:I$4,0),FALSE),0) -> 0 | K24: =IFERROR(VLOOKUP($B24&$C24,'C. Gestión Pto #2'!$B$4:J$23,MATCH(K$5,'C. Gestión Pto #2'!$B$4:J$4,0),FALSE),0) -> 0 | ... N24: =IFERROR(VLOOKUP($B24&$C24,'C. Gestión Pto #2'!$B$4:M$23,MATCH(N$5,'C. Gestión Pto #2'!$B$4:M$4,0),FALSE),0) -> 0 | P24: {=SUMPRODUCT($D24:$O24,TRANSPOSE('Indice CAC'!$C$16:$C$27))} -> 9212674 | R24: =IF($C24="MAT",SUMIF('Pto. Costos'!$A$64:$A$240,'Resumen Pto #2'!$B24,'Pto. Costos'!$G$64:$G$240),IF($C24="MO",SUMIF('Pto. Costos'!$A$64:$A$240,'Resumen Pto #2'!$B24,'Pto. Costos'!$I$64:$I$240),SUMIF('Pto. Costos'!$A$64:$A$240,'Resumen Pto #2'!$B24,'Pto. Costos'!$L$64:$L$240))) -> 29057105 | S24: =IF(C24="MAT",SUMIF('Pto. 02 Cert.'!$A$10:$A$185,$B24,'Pto. 02 Cert.'!$T$10:$T$185),IF(C24="MO",SUMIF('Pto. 02 Cert.'!$A$10:$A$185,$B24,'Pto. 02 Cert.'!$U$10:$U$185),SUMIF('Pto. 02 Cert.'!$A$10:$A$185,$B24,'Pto. 02 Cert.'!$V$10:$V$185)))/IF(C24="MAT",SUMIF('Pto. 02 Cert.'!$A$10:$A$185,$B24,'Pto. 02 Cert.'!$I$10:$I$185),IF(C24="MO",SUMIF('Pto. 02 Cert.'!$A$10:$A$185,$B24,'Pto. 02 Cert.'!$J$10:$J$185),SUMIF('Pto. 02 Cert.'!$A$10:$A$185,$B24,'Pto. 02 Cert.'!$K$10:$K$185))) -> 0.3451504 | T24: =IF(S24=100%,0,IF(OR(P24<>0,R24),R24-P24)) -> 19844431 | U24: =IF(OR(T24<0,R24),T24/R24,0%) -> 0.6829459 | V24: =IF(S24=100%,IF(OR(P24<>0,R24),R24-P24),0) -> 0
B25: Revestimiento | C25: MO | D25: =IFERROR(VLOOKUP($B25&$C25,'C. Gestión Pto #2'!$B$4:C$23,MATCH(D$5,'C. Gestión Pto #2'!$B$4:C$4,0),FALSE),0) -> 0 | E25: =IFERROR(VLOOKUP($B25&$C25,'C. Gestión Pto #2'!$B$4:D$23,MATCH(E$5,'C. Gestión Pto #2'!$B$4:D$4,0),FALSE),0) -> 0 | F25: =IFERROR(VLOOKUP($B25&$C25,'C. Gestión Pto #2'!$B$4:E$23,MATCH(F$5,'C. Gestión Pto #2'!$B$4:E$4,0),FALSE),0) -> 0 | G25: =IFERROR(VLOOKUP($B25&$C25,'C. Gestión Pto #2'!$B$4:F$23,MATCH(G$5,'C. Gestión Pto #2'!$B$4:F$4,0),FALSE),0) -> 0 | H25: =IFERROR(VLOOKUP($B25&$C25,'C. Gestión Pto #2'!$B$4:G$23,MATCH(H$5,'C. Gestión Pto #2'!$B$4:G$4,0),FALSE),0) -> 0 | I25: =IFERROR(VLOOKUP($B25&$C25,'C. Gestión Pto #2'!$B$4:H$23,MATCH(I$5,'C. Gestión Pto #2'!$B$4:H$4,0),FALSE),0) -> 0 | J25: =IFERROR(VLOOKUP($B25&$C25,'C. Gestión Pto #2'!$B$4:I$23,MATCH(J$5,'C. Gestión Pto #2'!$B$4:I$4,0),FALSE),0) -> 0 | K25: =IFERROR(VLOOKUP($B25&$C25,'C. Gestión Pto #2'!$B$4:J$23,MATCH(K$5,'C. Gestión Pto #2'!$B$4:J$4,0),FALSE),0) -> 0 | ... N25: =IFERROR(VLOOKUP($B25&$C25,'C. Gestión Pto #2'!$B$4:M$23,MATCH(N$5,'C. Gestión Pto #2'!$B$4:M$4,0),FALSE),0) -> 350000 | P25: {=SUMPRODUCT($D25:$O25,TRANSPOSE('Indice CAC'!$C$16:$C$27))} -> 3107555.7 | R25: =IF($C25="MAT",SUMIF('Pto. Costos'!$A$64:$A$240,'Resumen Pto #2'!$B25,'Pto. Costos'!$G$64:$G$240),IF($C25="MO",SUMIF('Pto. Costos'!$A$64:$A$240,'Resumen Pto #2'!$B25,'Pto. Costos'!$I$64:$I$240),SUMIF('Pto. Costos'!$A$64:$A$240,'Resumen Pto #2'!$B25,'Pto. Costos'!$L$64:$L$240))) -> 32520619 | S25: =IF(C25="MAT",SUMIF('Pto. 02 Cert.'!$A$10:$A$185,$B25,'Pto. 02 Cert.'!$T$10:$T$185),IF(C25="MO",SUMIF('Pto. 02 Cert.'!$A$10:$A$185,$B25,'Pto. 02 Cert.'!$U$10:$U$185),SUMIF('Pto. 02 Cert.'!$A$10:$A$185,$B25,'Pto. 02 Cert.'!$V$10:$V$185)))/IF(C25="MAT",SUMIF('Pto. 02 Cert.'!$A$10:$A$185,$B25,'Pto. 02 Cert.'!$I$10:$I$185),IF(C25="MO",SUMIF('Pto. 02 Cert.'!$A$10:$A$185,$B25,'Pto. 02 Cert.'!$J$10:$J$185),SUMIF('Pto. 02 Cert.'!$A$10:$A$185,$B25,'Pto. 02 Cert.'!$K$10:$K$185))) -> 0.097485725 | T25: =IF(S25=100%,0,IF(OR(P25<>0,R25),R25-P25)) -> 29413064 | U25: =IF(OR(T25<0,R25),T25/R25,0%) -> 0.90444353 | V25: =IF(S25=100%,IF(OR(P25<>0,R25),R25-P25),0) -> 0
B26: Termomecánica | C26: MAT | D26: =IFERROR(VLOOKUP($B26&$C26,'C. Gestión Pto #2'!$B$4:C$23,MATCH(D$5,'C. Gestión Pto #2'!$B$4:C$4,0),FALSE),0) -> 0 | E26: =IFERROR(VLOOKUP($B26&$C26,'C. Gestión Pto #2'!$B$4:D$23,MATCH(E$5,'C. Gestión Pto #2'!$B$4:D$4,0),FALSE),0) -> 0 | F26: =IFERROR(VLOOKUP($B26&$C26,'C. Gestión Pto #2'!$B$4:E$23,MATCH(F$5,'C. Gestión Pto #2'!$B$4:E$4,0),FALSE),0) -> 0 | G26: =IFERROR(VLOOKUP($B26&$C26,'C. Gestión Pto #2'!$B$4:F$23,MATCH(G$5,'C. Gestión Pto #2'!$B$4:F$4,0),FALSE),0) -> 0 | H26: =IFERROR(VLOOKUP($B26&$C26,'C. Gestión Pto #2'!$B$4:G$23,MATCH(H$5,'C. Gestión Pto #2'!$B$4:G$4,0),FALSE),0) -> 0 | I26: =IFERROR(VLOOKUP($B26&$C26,'C. Gestión Pto #2'!$B$4:H$23,MATCH(I$5,'C. Gestión Pto #2'!$B$4:H$4,0),FALSE),0) -> 0 | J26: =IFERROR(VLOOKUP($B26&$C26,'C. Gestión Pto #2'!$B$4:I$23,MATCH(J$5,'C. Gestión Pto #2'!$B$4:I$4,0),FALSE),0) -> 0 | K26: =IFERROR(VLOOKUP($B26&$C26,'C. Gestión Pto #2'!$B$4:J$23,MATCH(K$5,'C. Gestión Pto #2'!$B$4:J$4,0),FALSE),0) -> 0 | ... N26: =IFERROR(VLOOKUP($B26&$C26,'C. Gestión Pto #2'!$B$4:M$23,MATCH(N$5,'C. Gestión Pto #2'!$B$4:M$4,0),FALSE),0) -> 0 | P26: {=SUMPRODUCT($D26:$O26,TRANSPOSE('Indice CAC'!$C$16:$C$27))} -> 0 | R26: =IF($C26="MAT",SUMIF('Pto. Costos'!$A$64:$A$240,'Resumen Pto #2'!$B26,'Pto. Costos'!$G$64:$G$240),IF($C26="MO",SUMIF('Pto. Costos'!$A$64:$A$240,'Resumen Pto #2'!$B26,'Pto. Costos'!$I$64:$I$240),SUMIF('Pto. Costos'!$A$64:$A$240,'Resumen Pto #2'!$B26,'Pto. Costos'!$L$64:$L$240))) -> 13500000 | S26: =IF(C26="MAT",SUMIF('Pto. 02 Cert.'!$A$10:$A$185,$B26,'Pto. 02 Cert.'!$T$10:$T$185),IF(C26="MO",SUMIF('Pto. 02 Cert.'!$A$10:$A$185,$B26,'Pto. 02 Cert.'!$U$10:$U$185),SUMIF('Pto. 02 Cert.'!$A$10:$A$185,$B26,'Pto. 02 Cert.'!$V$10:$V$185)))/IF(C26="MAT",SUMIF('Pto. 02 Cert.'!$A$10:$A$185,$B26,'Pto. 02 Cert.'!$I$10:$I$185),IF(C26="MO",SUMIF('Pto. 02 Cert.'!$A$10:$A$185,$B26,'Pto. 02 Cert.'!$J$10:$J$185),SUMIF('Pto. 02 Cert.'!$A$10:$A$185,$B26,'Pto. 02 Cert.'!$K$10:$K$185))) -> 0.8 | T26: =IF(S26=100%,0,IF(OR(P26<>0,R26),R26-P26)) -> 13500000 | U26: =IF(OR(T26<0,R26),T26/R26,0%) -> 1 | V26: =IF(S26=100%,IF(OR(P26<>0,R26),R26-P26),0) -> 0
B27: Termomecánica | C27: MO | D27: =IFERROR(VLOOKUP($B27&$C27,'C. Gestión Pto #2'!$B$4:C$23,MATCH(D$5,'C. Gestión Pto #2'!$B$4:C$4,0),FALSE),0) -> 0 | E27: =IFERROR(VLOOKUP($B27&$C27,'C. Gestión Pto #2'!$B$4:D$23,MATCH(E$5,'C. Gestión Pto #2'!$B$4:D$4,0),FALSE),0) -> 0 | F27: =IFERROR(VLOOKUP($B27&$C27,'C. Gestión Pto #2'!$B$4:E$23,MATCH(F$5,'C. Gestión Pto #2'!$B$4:E$4,0),FALSE),0) -> 0 | G27: =IFERROR(VLOOKUP($B27&$C27,'C. Gestión Pto #2'!$B$4:F$23,MATCH(G$5,'C. Gestión Pto #2'!$B$4:F$4,0),FALSE),0) -> 0 | H27: =IFERROR(VLOOKUP($B27&$C27,'C. Gestión Pto #2'!$B$4:G$23,MATCH(H$5,'C. Gestión Pto #2'!$B$4:G$4,0),FALSE),0) -> 0 | I27: =IFERROR(VLOOKUP($B27&$C27,'C. Gestión Pto #2'!$B$4:H$23,MATCH(I$5,'C. Gestión Pto #2'!$B$4:H$4,0),FALSE),0) -> 0 | J27: =IFERROR(VLOOKUP($B27&$C27,'C. Gestión Pto #2'!$B$4:I$23,MATCH(J$5,'C. Gestión Pto #2'!$B$4:I$4,0),FALSE),0) -> 4235000 | K27: =IFERROR(VLOOKUP($B27&$C27,'C. Gestión Pto #2'!$B$4:J$23,MATCH(K$5,'C. Gestión Pto #2'!$B$4:J$4,0),FALSE),0) -> 0 | ... N27: =IFERROR(VLOOKUP($B27&$C27,'C. Gestión Pto #2'!$B$4:M$23,MATCH(N$5,'C. Gestión Pto #2'!$B$4:M$4,0),FALSE),0) -> 0 | P27: {=SUMPRODUCT($D27:$O27,TRANSPOSE('Indice CAC'!$C$16:$C$27))} -> 8173029.4 | R27: =IF($C27="MAT",SUMIF('Pto. Costos'!$A$64:$A$240,'Resumen Pto #2'!$B27,'Pto. Costos'!$G$64:$G$240),IF($C27="MO",SUMIF('Pto. Costos'!$A$64:$A$240,'Resumen Pto #2'!$B27,'Pto. Costos'!$I$64:$I$240),SUMIF('Pto. Costos'!$A$64:$A$240,'Resumen Pto #2'!$B27,'Pto. Costos'!$L$64:$L$240))) -> 14504000 | S27: =IF(C27="MAT",SUMIF('Pto. 02 Cert.'!$A$10:$A$185,$B27,'Pto. 02 Cert.'!$T$10:$T$185),IF(C27="MO",SUMIF('Pto. 02 Cert.'!$A$10:$A$185,$B27,'Pto. 02 Cert.'!$U$10:$U$185),SUMIF('Pto. 02 Cert.'!$A$10:$A$185,$B27,'Pto. 02 Cert.'!$V$10:$V$185)))/IF(C27="MAT",SUMIF('Pto. 02 Cert.'!$A$10:$A$185,$B27,'Pto. 02 Cert.'!$I$10:$I$185),IF(C27="MO",SUMIF('Pto. 02 Cert.'!$A$10:$A$185,$B27,'Pto. 02 Cert.'!$J$10:$J$185),SUMIF('Pto. 02 Cert.'!$A$10:$A$185,$B27,'Pto. 02 Cert.'!$K$10:$K$185))) -> 0.42471087 | T27: =IF(S27=100%,0,IF(OR(P27<>0,R27),R27-P27)) -> 6330970.6 | U27: =IF(OR(T27<0,R27),T27/R27,0%) -> 0.43649825 | V27: =IF(S27=100%,IF(OR(P27<>0,R27),R27-P27),0) -> 0
B28: Equipos | D28: =IFERROR(VLOOKUP($B28&$C28,'C. Gestión Pto #2'!$B$4:C$23,MATCH(D$5,'C. Gestión Pto #2'!$B$4:C$4,0),FALSE),0) -> 0 | E28: =IFERROR(VLOOKUP($B28&$C28,'C. Gestión Pto #2'!$B$4:D$23,MATCH(E$5,'C. Gestión Pto #2'!$B$4:D$4,0),FALSE),0) -> 0 | F28: =IFERROR(VLOOKUP($B28&$C28,'C. Gestión Pto #2'!$B$4:E$23,MATCH(F$5,'C. Gestión Pto #2'!$B$4:E$4,0),FALSE),0) -> 0 | G28: =IFERROR(VLOOKUP($B28&$C28,'C. Gestión Pto #2'!$B$4:F$23,MATCH(G$5,'C. Gestión Pto #2'!$B$4:F$4,0),FALSE),0) -> 0 | H28: =IFERROR(VLOOKUP($B28&$C28,'C. Gestión Pto #2'!$B$4:G$23,MATCH(H$5,'C. Gestión Pto #2'!$B$4:G$4,0),FALSE),0) -> 0 | I28: =IFERROR(VLOOKUP($B28&$C28,'C. Gestión Pto #2'!$B$4:H$23,MATCH(I$5,'C. Gestión Pto #2'!$B$4:H$4,0),FALSE),0) -> 594839.99 | J28: =IFERROR(VLOOKUP($B28&$C28,'C. Gestión Pto #2'!$B$4:I$23,MATCH(J$5,'C. Gestión Pto #2'!$B$4:I$4,0),FALSE),0) -> 617445.23 | K28: =IFERROR(VLOOKUP($B28&$C28,'C. Gestión Pto #2'!$B$4:J$23,MATCH(K$5,'C. Gestión Pto #2'!$B$4:J$4,0),FALSE),0) -> 637742.13 | ... N28: =IFERROR(VLOOKUP($B28&$C28,'C. Gestión Pto #2'!$B$4:M$23,MATCH(N$5,'C. Gestión Pto #2'!$B$4:M$4,0),FALSE),0) -> 702737.42 | P28: {=SUMPRODUCT($D28:$O28,TRANSPOSE('Indice CAC'!$C$16:$C$27))} -> 2842189.1 | R28: =IF($C28="MAT",SUMIF('Pto. Costos'!$A$64:$A$240,'Resumen Pto #2'!$B28,'Pto. Costos'!$G$64:$G$240),IF($C28="MO",SUMIF('Pto. Costos'!$A$64:$A$240,'Resumen Pto #2'!$B28,'Pto. Costos'!$I$64:$I$240),SUMIF('Pto. Costos'!$A$64:$A$240,"",'Pto. Costos'!$K$64:$K$240))) -> 8515663.9 | S28: ='Pto. 02 Cert.'!S187 -> 0.4390752 | T28: =IF(S28=100%,0,IF(OR(P28<>0,R28),R28-P28)) -> 5673474.8 | U28: =IF(OR(T28<0,R28),T28/R28,0%) -> 0.66623987 | V28: =IF(S28=100%,IF(OR(P28<>0,R28),R28-P28),0) -> 0
B29: Gastos Generales Obra | D29: =IFERROR(VLOOKUP($B29&$C29,'C. Gestión Pto #2'!$B$4:C$23,MATCH(D$5,'C. Gestión Pto #2'!$B$4:C$4,0),FALSE),0) -> 0 | E29: =IFERROR(VLOOKUP($B29&$C29,'C. Gestión Pto #2'!$B$4:D$23,MATCH(E$5,'C. Gestión Pto #2'!$B$4:D$4,0),FALSE),0) -> 0 | F29: =IFERROR(VLOOKUP($B29&$C29,'C. Gestión Pto #2'!$B$4:E$23,MATCH(F$5,'C. Gestión Pto #2'!$B$4:E$4,0),FALSE),0) -> 0 | G29: =IFERROR(VLOOKUP($B29&$C29,'C. Gestión Pto #2'!$B$4:F$23,MATCH(G$5,'C. Gestión Pto #2'!$B$4:F$4,0),FALSE),0) -> 0 | H29: =IFERROR(VLOOKUP($B29&$C29,'C. Gestión Pto #2'!$B$4:G$23,MATCH(H$5,'C. Gestión Pto #2'!$B$4:G$4,0),FALSE),0) -> 0 | I29: =IFERROR(VLOOKUP($B29&$C29,'C. Gestión Pto #2'!$B$4:H$23,MATCH(I$5,'C. Gestión Pto #2'!$B$4:H$4,0),FALSE),0) -> 0 | J29: =IFERROR(VLOOKUP($B29&$C29,'C. Gestión Pto #2'!$B$4:I$23,MATCH(J$5,'C. Gestión Pto #2'!$B$4:I$4,0),FALSE),0) -> 0 | K29: =IFERROR(VLOOKUP($B29&$C29,'C. Gestión Pto #2'!$B$4:J$23,MATCH(K$5,'C. Gestión Pto #2'!$B$4:J$4,0),FALSE),0) -> 0 | ... N29: =IFERROR(VLOOKUP($B29&$C29,'C. Gestión Pto #2'!$B$4:M$23,MATCH(N$5,'C. Gestión Pto #2'!$B$4:M$4,0),FALSE),0) -> 120000 | P29: {=SUMPRODUCT($D29:$O29,TRANSPOSE('Indice CAC'!$C$16:$C$27))} -> 512253.21 | R29: =IF($C29="MAT",SUMIF('Pto. Costos'!$A$64:$A$240,'Resumen Pto #2'!$B29,'Pto. Costos'!$G$64:$G$240),IF($C29="MO",SUMIF('Pto. Costos'!$A$64:$A$240,'Resumen Pto #2'!$B29,'Pto. Costos'!$I$64:$I$240),SUMIF('Pto. Costos'!$A$64:$A$240,'Resumen Pto #2'!$B29,'Pto. Costos'!$L$64:$L$240))) -> 1200000 | S29: =IF(C29="MAT",SUMIF('Pto. 02 Cert.'!$A$10:$A$185,$B29,'Pto. 02 Cert.'!$T$10:$T$185),IF(C29="MO",SUMIF('Pto. 02 Cert.'!$A$10:$A$185,$B29,'Pto. 02 Cert.'!$U$10:$U$185),SUMIF('Pto. 02 Cert.'!$A$10:$A$185,$B29,'Pto. 02 Cert.'!$V$10:$V$185)))/IF(C29="MAT",SUMIF('Pto. 02 Cert.'!$A$10:$A$185,$B29,'Pto. 02 Cert.'!$I$10:$I$185),IF(C29="MO",SUMIF('Pto. 02 Cert.'!$A$10:$A$185,$B29,'Pto. 02 Cert.'!$J$10:$J$185),SUMIF('Pto. 02 Cert.'!$A$10:$A$185,$B29,'Pto. 02 Cert.'!$K$10:$K$185))) -> 0.4 | T29: =IF(S29=100%,0,IF(OR(P29<>0,R29),R29-P29)) -> 687746.79 | U29: =IF(OR(T29<0,R29),T29/R29,0%) -> 0.57312233 | V29: =IF(S29=100%,IF(OR(P29<>0,R29),R29-P29),0) -> 0
B30: Total Egresos de Obra | D30: =SUM(D13:D29) -> 550000 | E30: =SUM(E13:E29) -> 1628869.5 | F30: =SUM(F13:F29) -> 2183596.9 | G30: =SUM(G13:G29) -> 35697612 | H30: =SUM(H13:H29) -> 17306022 | I30: =SUM(I13:I29) -> 32542065 | J30: =SUM(J13:J29) -> 59131502 | K30: =SUM(K13:K29) -> 50579995 | ... N30: =SUM(N13:N29) -> 1.0217051e+08 | P30: =SUM(P13:P29) -> 3.4274719e+08 | R30: =SUM(R13:R29) -> 5.8100225e+08 | T30: =IF(S30=100%,0,IF(OR(P30<>0,R30),R30-P30)) -> 2.3825507e+08 | U30: =IF(OR(T30<0,R30),T30/R30,0%) -> 0.41007598 | V30: =IF(S30=100%,IF(OR(P30<>0,R30),R30-P30),0) -> 0
B32: Gastos Generales
B33: Gastos Directos | D33: =VLOOKUP($B33,'C. Gestión Pto #2'!$B$41:J$41,MATCH('Resumen Pto #2'!D$5,'C. Gestión Pto #2'!$B$27:J$27,0),0) -> 0 | E33: =VLOOKUP($B33,'C. Gestión Pto #2'!$B$41:K$41,MATCH('Resumen Pto #2'!E$5,'C. Gestión Pto #2'!$B$27:K$27,0),0) -> 0 | F33: =VLOOKUP($B33,'C. Gestión Pto #2'!$B$41:L$41,MATCH('Resumen Pto #2'!F$5,'C. Gestión Pto #2'!$B$27:L$27,0),0) -> 0 | G33: =VLOOKUP($B33,'C. Gestión Pto #2'!$B$41:M$41,MATCH('Resumen Pto #2'!G$5,'C. Gestión Pto #2'!$B$27:M$27,0),0) -> 0 | H33: =VLOOKUP($B33,'C. Gestión Pto #2'!$B$41:N$41,MATCH('Resumen Pto #2'!H$5,'C. Gestión Pto #2'!$B$27:N$27,0),0) -> 0 | I33: =VLOOKUP($B33,'C. Gestión Pto #2'!$B$41:O$41,MATCH('Resumen Pto #2'!I$5,'C. Gestión Pto #2'!$B$27:O$27,0),0) -> 4034621.5 | J33: =VLOOKUP($B33,'C. Gestión Pto #2'!$B$41:P$41,MATCH('Resumen Pto #2'!J$5,'C. Gestión Pto #2'!$B$27:P$27,0),0) -> 2054329.6 | K33: =VLOOKUP($B33,'C. Gestión Pto #2'!$B$41:Q$41,MATCH('Resumen Pto #2'!K$5,'C. Gestión Pto #2'!$B$27:Q$27,0),0) -> 2194576 | ... N33: =VLOOKUP($B33,'C. Gestión Pto #2'!$B$41:T$41,MATCH('Resumen Pto #2'!N$5,'C. Gestión Pto #2'!$B$27:T$27,0),0) -> 3047610.9 | P33: {=SUMPRODUCT($D33:$O33,TRANSPOSE('Indice CAC'!$C$16:$C$27))} -> 11697607 | R33: =SUM(GGBB!H7:H40)*'Pto. Vta.'!N243 -> 35059903 | S33: 0 | T33: =IF(S33=100%,0,IF(OR(P33<>0,R33),R33-P33)) -> 23362296 | U33: =IF(OR(T33<0,R33),T33/R33,0%) -> 0.6663537 | V33: =IF(S33=100%,IF(OR(P33<>0,R33),R33-P33),0) -> 0
B34: Gastos Indirectos | D34: =VLOOKUP($B34,'C. Gestión Pto #2'!$B$46:J$46,MATCH('Resumen Pto #2'!D$5,'C. Gestión Pto #2'!$B$43:J$43,0),0) -> 0 | E34: =VLOOKUP($B34,'C. Gestión Pto #2'!$B$46:K$46,MATCH('Resumen Pto #2'!E$5,'C. Gestión Pto #2'!$B$43:K$43,0),0) -> 0 | F34: =VLOOKUP($B34,'C. Gestión Pto #2'!$B$46:L$46,MATCH('Resumen Pto #2'!F$5,'C. Gestión Pto #2'!$B$43:L$43,0),0) -> 0 | G34: =VLOOKUP($B34,'C. Gestión Pto #2'!$B$46:M$46,MATCH('Resumen Pto #2'!G$5,'C. Gestión Pto #2'!$B$43:M$43,0),0) -> 0 | H34: =VLOOKUP($B34,'C. Gestión Pto #2'!$B$46:N$46,MATCH('Resumen Pto #2'!H$5,'C. Gestión Pto #2'!$B$43:N$43,0),0) -> 0 | I34: =VLOOKUP($B34,'C. Gestión Pto #2'!$B$46:O$46,MATCH('Resumen Pto #2'!I$5,'C. Gestión Pto #2'!$B$43:O$43,0),0) -> 3192269.4 | J34: =VLOOKUP($B34,'C. Gestión Pto #2'!$B$46:P$46,MATCH('Resumen Pto #2'!J$5,'C. Gestión Pto #2'!$B$43:P$43,0),0) -> 2546573.8 | K34: =VLOOKUP($B34,'C. Gestión Pto #2'!$B$46:Q$46,MATCH('Resumen Pto #2'!K$5,'C. Gestión Pto #2'!$B$43:Q$43,0),0) -> 2601372.3 | ... N34: =VLOOKUP($B34,'C. Gestión Pto #2'!$B$46:T$46,MATCH('Resumen Pto #2'!N$5,'C. Gestión Pto #2'!$B$43:T$43,0),0) -> 2750603.9 | P34: {=SUMPRODUCT($D34:$O34,TRANSPOSE('Indice CAC'!$C$16:$C$27))} -> 12104969 | R34: =SUM(GGBB!H41:H47)*'Pto. Vta.'!N243 -> 37355126 | S34: 0 | T34: =IF(S34=100%,0,IF(OR(P34<>0,R34),R34-P34)) -> 25250157 | U34: =IF(OR(T34<0,R34),T34/R34,0%) -> 0.67594893 | V34: =IF(S34=100%,IF(OR(P34<>0,R34),R34-P34),0) -> 0
B35: Total Gastos Generales | D35: =SUM(D33:D34) -> 0 | E35: =SUM(E33:E34) -> 0 | F35: =SUM(F33:F34) -> 0 | G35: =SUM(G33:G34) -> 0 | H35: =SUM(H33:H34) -> 0 | I35: =SUM(I33:I34) -> 7226891 | J35: =SUM(J33:J34) -> 4600903.4 | K35: =SUM(K33:K34) -> 4795948.3 | ... N35: =SUM(N33:N34) -> 5798214.7 | P35: =SUM(P33:P34) -> 23802576 | R35: =SUM(R33:R34) -> 72415029 | T35: =IF(S35=100%,0,IF(OR(P35<>0,R35),R35-P35)) -> 48612453 | U35: =IF(OR(T35<0,R35),T35/R35,0%) -> 0.67130338 | V35: =SUM(V33:V34) -> 0
B37: Resultado Operativo | D37: =SUM(D8,D10,-D30,-D35) -> -550000 | E37: =SUM(E8,E10,-E30,-E35) -> -1628869.5 | F37: =SUM(F8,F10,-F30,-F35) -> -2183596.9 | G37: =SUM(G8,G10,-G30,-G35) -> 3.3050212e+08 | H37: =SUM(H8,H10,-H30,-H35) -> 3536895.4 | I37: =SUM(I8,I10,-I30,-I35) -> -27528224 | J37: =SUM(J8,J10,-J30,-J35) -> -53040756 | K37: =SUM(K8,K10,-K30,-K35) -> -34122171 | ... N37: =SUM(N8,N10,-N30,-N35) -> -50813784 | P37: =SUM(P8,-P30,-P35) -> 82495921 | R37: =SUM(R8,-R30,-R35) -> 83439849
B38: Resultado Acumulado | D38: =D37 -> -550000 | E38: =D38+E37 -> -2178869.5 | F38: =E38+F37 -> -4362466.4 | G38: =F38+G37 -> 3.2613965e+08 | H38: =G38+H37 -> 3.2967655e+08 | I38: =H38+I37 -> 3.0214832e+08 | J38: =I38+J37 -> 2.4910757e+08 | K38: =J38+K37 -> 2.149854e+08 | L38: =K38+L37 -> 1.6056089e+08 | ... N38: =M38+N37 -> 45910775

Sheet Facturacion
A1: Obra: SVD 4140
R2: Anticipo
C3: O.C. | D3: Descripcion | E3: Importe | F3: IVA | G3: Total | I3: Anticipo | S3: Bruto | T3: IVA | U3: Total
