Workbook

Sheet README
A1: PRESUPUESTO UNIFICADO GDR 3760 — APU + Presupuesto
A3: OBJETIVO
A4: Modelo unificado donde cada partida del presupuesto está vinculada a una fila en PARTIDAS,
A5: y cada partida está alimentada por filas en COMPOSICIÓN (materiales, mano de obra, equipos).
A6: Estructura formula-pure, sin macros, vinculada por VLOOKUP/SUMIFS a tablas maestras de insumos.
A8: OBJETIVO PRIMARIO: Reconstruir correctamente la composición técnica real de cada partida,
A9: manteniendo trazabilidad de materiales, mano de obra, equipos, subcontratos, consumibles,
A10: desperdicios y relaciones entre partidas/APUs. Igualar el costo del GDR original es secundario.
A12: REGLAS ESTRUCTURALES DEL MODELO
A14: REGLA 1 — PRIORIDAD DE TRAZABILIDAD DE COMPOSICIÓN
A15: Siempre revisar de dónde viene el costo unitario de cada partida del presupuesto original.
A16: Orden de prioridad:
... A158: Los hallazgos detectados se documentan en la hoja OBSERVACIONES.

Sheet CONFIG
A1: CONFIGURACIÓN DEL APU
A3: Parámetro | B3: Valor | C3: Notas
A4: Mes de referencia | B4: Diciembre | C4: Mes de precios del APU
A5: Año de referencia | B5: 2024
A6: Versión | B6: v7.0 — Migración a APU 12-24 + Presupuesto GDR 3760 unificado
A7: GG% | B7: 0 | C7: 0 = se aplica en presupuesto de obra
A8: BB% | B8: 0 | C8: 0 = se aplica en presupuesto de obra
A9: Tipo Cambio USD (MEP) | B9: 1500 | C9: Pesos por dólar
A10: Revisado por | B10: MC | C10: Según archivo original
A11: Mes base CAC | B11: Diciembre 2024 | C11: Mes base para normalización de precios
A12: CAC base (valor) | B12: 13278 | C12: Índice CAC Diciembre 2024 (referencial — verificar)
A14: TABLA DE CARGAS MO
A15: Componente | B15: Tipo | C15: Valor | D15: Fuente
A16: Cargas patronales | B16: % | C16: 0.42 | D16: Convenio UOCRA (estimado)
A17: ART | B17: % | C17: 0.085 | D17: Aseguradora (estimado)
A18: Ropa de trabajo | B18: $/mes | C18: 85000 | D18: Compras (estimado)
A19: Viáticos | B19: $/día | C19: 3200 | D19: Convenio UOCRA (estimado)
A20: Vacaciones + SAC | B20: % | C20: 0.15 | D20: Cálculo legal (estimado)
A22: COEFICIENTE FINAL | B22: multiplicador | C22: =1+C16+C17+C20+(C18/78291/22)+(C19/78291) -> 1.7452228
A24: CONTROLES DE INTEGRIDAD
A25: Duplicados MATERIALES | B25: =SUMPRODUCT((COUNTIF(MATERIALES!$A$2:$A$200,MATERIALES!$A$2:$A$200)>1)*(MATERIALES!$A$2:$A$200<>"")) -> 0 | C25: =IF(B25>0,"¡DUPLICADOS DETECTADOS!","OK") -> OK
A26: Duplicados MANO_DE_OBRA | B26: =SUMPRODUCT((COUNTIF(MANO_DE_OBRA!$A$2:$A$11,MANO_DE_OBRA!$A$2:$A$11)>1)*(MANO_DE_OBRA!$A$2:$A$11<>"")) -> 0 | C26: =IF(B26>0,"¡DUPLICADOS DETECTADOS!","OK") -> OK
A27: Duplicados EQUIPOS | B27: =SUMPRODUCT((COUNTIF(EQUIPOS!$A$2:$A$50,EQUIPOS!$A$2:$A$50)>1)*(EQUIPOS!$A$2:$A$50<>"")) -> 0 | C27: =IF(B27>0,"¡DUPLICADOS DETECTADOS!","OK") -> OK
A28: Duplicados PARTIDAS | B28: =SUMPRODUCT((COUNTIF(PARTIDAS!$A$2:$A$198,PARTIDAS!$A$2:$A$198)>1)*(PARTIDAS!$A$2:$A$198<>"")) -> 0 | C28: =IF(B28>0,"¡DUPLICADOS DETECTADOS!","OK") -> OK
A30: INTEGRIDAD REFERENCIAL
A31: MAT sin match en MATERIALES | B31: {=SUMPRODUCT((COMPOSICIÓN!B$2:B$1838="MAT")*(COMPOSICIÓN!C$2:C$1838<>"")*(ISNA(MATCH(COMPOSICIÓN!C$2:C$1838,MATERIALES!$A$2:$A$200,0))))} -> 1032 | C31: =IF(B31>0,"¡REFS ROTAS!","OK") -> ¡REFS ROTAS!
A32: MO sin match en MANO_DE_OBRA | B32: {=SUMPRODUCT((COMPOSICIÓN!B$2:B$1838="MO")*(COMPOSICIÓN!C$2:C$1838<>"")*(ISNA(MATCH(COMPOSICIÓN!C$2:C$1838,MANO_DE_OBRA!$A$2:$A$11,0))))} -> 432 | C32: =IF(B32>0,"¡REFS ROTAS!","OK") -> ¡REFS ROTAS!
A33: EQ sin match en EQUIPOS | B33: {=SUMPRODUCT((COMPOSICIÓN!B$2:B$1838="EQ")*(COMPOSICIÓN!C$2:C$1838<>"")*(ISNA(MATCH(COMPOSICIÓN!C$2:C$1838,EQUIPOS!$A$2:$A$50,0))))} -> 0 | C33: =IF(B33>0,"¡REFS ROTAS!","OK") -> OK

Sheet MATERIALES
A1: Código | B1: Descripción | C1: Unidad | D1: Precio $ | E1: Proveedor | F1: Fecha Cotiz. | G1: Categoría | H1: Cód. Original | I1: Nota | J1: Alerta
A2: AGR-001 | B2: ARENA LAVADA | C2: m3 | D2: 32399.77 | E2: Cutuli Hnos | F2: 2024-11-29 | G2: Corralón | H2: *AGREG02 | I2: BOLSÓN | J2: =IF(F2="","SIN FECHA","")
A3: AGR-002 | B3: Piedra Partida | C3: m3 | D3: 56202.3 | E3: Cutuli Hnos | F3: 2024-11-29 | G3: Corralón | I3: BOLSÓN | J3: =IF(F3="","SIN FECHA","")
A4: AGR-003 | B4: Cascote | C4: m3 | D4: 34246.8 | E4: Cutuli Hnos | F4: 2024-11-29 | G4: Corralón | I4: BOLSÓN | J4: =IF(F4="","SIN FECHA","")
A5: AGR-004 | B5: Cemento Portland x 50kg | C5: Bol | D5: 7809.48 | E5: Cutuli Hnos | F5: 2024-11-29 | G5: Corralón | H5: *AGREG01 | I5: CEMENTO AVELLANEDA | J5: =IF(F5="","SIN FECHA","")
A6: AGR-005 | B6: Cal Comun x 25kg | C6: bol | D6: 3837.96 | E6: Cutuli Hnos | F6: 2024-11-29 | G6: Corralón | H6: AGREG11 | J6: =IF(F6="","SIN FECHA","")
A7: AGR-006 | B7: cal milagro | C7: bol | D7: 10936.8 | E7: Cutuli Hnos | F7: 2024-11-29 | G7: Corralón | H7: CALMILAG | J7: =IF(F7="","SIN FECHA","")
A8: ACE-001 | B8: Barra de Acero Aleteado - 6mm x 12m | C8: u | D8: 3424.53 | E8: Cutuli Hnos | F8: 2024-11-29 | G8: Corralón | H8: FE06 | J8: =IF(F8="","SIN FECHA","")
A9: ACE-002 | B9: Barra de Acero Aleteado - 8mm x 12m | C9: u | D9: 6017.04 | E9: Cutuli Hnos | F9: 2024-11-29 | G9: Corralón | J9: =IF(F9="","SIN FECHA","")
A10: ACE-003 | B10: Barra de Acero Aleteado - 10mm x 12m | C10: u | D10: 9272.75 | E10: Cutuli Hnos | F10: 2024-11-29 | G10: Corralón | J10: =IF(F10="","SIN FECHA","")
A11: ACE-004 | B11: Barra de Acero Aleteado - 12mm x 12m | C11: u | D11: 13312.25 | E11: Cutuli Hnos | F11: 2024-11-29 | G11: Corralón | J11: =IF(F11="","SIN FECHA","")
A12: ACE-005 | B12: Barra de Acero Aleteado - 16mm x 12m | C12: u | D12: 23236.16 | E12: Cutuli Hnos | F12: 2024-11-29 | G12: Corralón | J12: =IF(F12="","SIN FECHA","")
A13: ACE-006 | B13: Barra de Acero Aleteado - 20mm x 12m | C13: u | D13: 36391.64 | E13: Cutuli Hnos | F13: 2024-11-29 | G13: Corralón | J13: =IF(F13="","SIN FECHA","")
A14: ACE-007 | B14: Barra de Acero Aleteado - 25mm x 12m | C14: u | D14: 56794.12 | E14: Cutuli Hnos | F14: 2024-11-29 | G14: Corralón | J14: =IF(F14="","SIN FECHA","")
A15: CER-001 | B15: ladrillo a la vista 1 cara | C15: u | D15: 233.44 | E15: Cutuli Hnos | F15: 2024-11-29 | G15: Corralón | H15: LADVISTA | I15: 1/2 VISTA MDQ | J15: =IF(F15="","SIN FECHA","")
A16: CER-002 | B16: LADRILLO CERAMICO 8 x 18 x 33 cm | C16: u | D16: 292.32 | E16: Cutuli Hnos | F16: 2024-11-29 | G16: Corralón | H16: *LADRI03 | J16: =IF(F16="","SIN FECHA","")
A17: CER-003 | B17: LADRILLO CERAMICO 12 x 18 x 33 cm | C17: u | D17: 365.4 | E17: Cutuli Hnos | F17: 2024-11-29 | G17: Corralón | H17: LADRI12 | I17: 9 AGUJEROS | J17: =IF(F17="","SIN FECHA","")
A18: CER-004 | B18: LADRILLO CERAMICO 18 x 18 x 33 cm | C18: u | D18: 519.12 | E18: Cutuli Hnos | F18: 2024-11-29 | G18: Corralón | H18: LADRI181 | J18: =IF(F18="","SIN FECHA","")
A19: CER-005 | B19: Ladrillo Comun 12.5 x 5.5 x 25 | C19: u | D19: 132.3 | E19: Cutuli Hnos | F19: 2024-11-29 | G19: Corralón | H19: LADRIC | J19: =IF(F19="","SIN FECHA","")
A20: CER-006 | B20: Ladrillo hueco ceramico 12x19x33 - Portante | C20: u | D20: 563.22 | E20: Cutuli Hnos | F20: 2024-11-29 | G20: Corralón | H20: LADRI182 | J20: =IF(F20="","SIN FECHA","")
A21: CER-007 | B21: Ladrillo hueco ceramico 18x19x33 - Portante | C21: u | D21: 694.26 | E21: Cutuli Hnos | F21: 2024-11-29 | G21: Corralón | J21: =IF(F21="","SIN FECHA","")
A22: BLO-001 | B22: Bloque de Hormigon 19 x 19 x 39 | C22: u | D22: 1016.6 | E22: Cutuli Hnos | F22: 2024-11-29 | G22: Corralón | J22: =IF(F22="","SIN FECHA","")
A23: BLO-002 | B23: Bloque de Hormigon 10 x 19 x 39 | C23: u | D23: 682.52 | E23: Cutuli Hnos | F23: 2024-11-29 | G23: Corralón | J23: =IF(F23="","SIN FECHA","")
A24: ADH-001 | B24: Adhesivo Klaukol Porcellanato Fluido x 30Kg | C24: bol | D24: 18802.512 | E24: Cutuli Hnos | F24: 2024-11-29 | G24: Adhesivos y pastinas | H24: *AGREG11 | I24: WEBER FORTE PORCELLANATO X 25 KG | J24: =IF(F24="","SIN FECHA","")
A25: ADH-002 | B25: Adhesivo Klaukol Impermeable Petenciado x 30Kg | C25: bol | D25: 29811.732 | E25: Cutuli Hnos | F25: 2024-11-29 | G25: Adhesivos y pastinas | I25: WEBER SUPLER FLEX 25 KG | J25: =IF(F25="","SIN FECHA","")
A26: AIS-001 | B26: Aditivo Hidrofugo en pasta - Ceresita x 1kg | C26: kg | D26: 1256.128 | E26: Cutuli Hnos | F26: 2024-11-29 | G26: Impermeabilizantes | H26: AGREG07 | I26: CERESITA X 20 LTS | J26: =IF(F26="","SIN FECHA","")
A27: REV-001 | B27: Yeso Tuyango x 30kg | C27: b | D27: 9639 | E27: Cutuli Hnos | F27: 2024-11-29 | G27: Revestimientos y yesos | H27: PINT015 | J27: =IF(F27="","SIN FECHA","")
A28: ADH-003 | B28: Pastina Klaukol x 1kg - Alta performance | C28: u | D28: 3214.35 | E28: Cutuli Hnos | F28: 2024-11-29 | G28: Adhesivos y pastinas | I28: Prestige nieve | J28: =IF(F28="","SIN FECHA","")
A29: REV-002 | B29: Promex E x 30 kg (3 en 1 proyectable exterior) | C29: bol | D29: 6683.37 | E29: Cutuli Hnos | F29: 2024-12-05 | G29: Revestimientos y yesos | I29: PROMEX E X 30 [Deflactado v6/1.27] | J29: =IF(F29="","SIN FECHA","")
A30: REV-003 | B30: Promex I x 30 kg (2 en 1 proyectable interior) | C30: bol | D30: 5260 | E30: Cutuli Hnos | F30: 2024-12-05 | G30: Revestimientos y yesos | I30: [Deflactado v6/1.27] | J30: =IF(F30="","SIN FECHA","")
A31: ACE-008 | B31: Malla SIMA Q335 (8mm) | C31: u | D31: 126755.8 | E31: Cutuli Hnos | F31: 2024-11-29 | G31: Corralón | J31: =IF(F31="","SIN FECHA","")
A32: ACE-009 | B32: Malla SIMA Q188 (6mm) | C32: u | D32: 69985.79 | E32: Cutuli Hnos | F32: 2024-11-29 | G32: Corralón | J32: =IF(F32="","SIN FECHA","")
A33: ACE-010 | B33: Alambre de Fardo | C33: kg | D33: 2302.02 | E33: Cutuli Hnos | F33: 2024-11-29 | G33: Corralón | I33: Alambre N°16 | J33: =IF(F33="","SIN FECHA","")
A34: ADT-001 | B34: Sika Poro Plus x 10 kg | C34: b | D34: 252066.12 | E34: ML | F34: 2024-12-05 | G34: Impermeabilizantes | I34: https://articulo.mercadolibre.com.ar/MLA-1239468887-sika-poro-plus-espumigeno-para-hormigon-10-kg-_JM#polycard_client=search-nordic&position=11&search_layout=grid&type=item&tracking_id=c5802d9e-4804-403a-958c-824dd473f5b4 | J34: =IF(F34="","SIN FECHA","")
A35: BLO-003 | B35: Bloque HCCA Brimax 5 x 20 x 60 | C35: u | D35: 1140.68 | E35: Cutuli Hnos | F35: 2024-12-05 | G35: Corralón | I35: BRIMAX (Pallet 260 u) [Deflactado v6/1.27] | J35: =IF(F35="","SIN FECHA","")
A36: BLO-004 | B36: Bloque HCCA Brimax 7,5 x 20 x 60 | C36: u | D36: 1516.11 | E36: Cutuli Hnos | F36: 2024-12-05 | G36: Corralón | I36: BRIMAX (Pallet 200 u) [Deflactado v6/1.27] | J36: =IF(F36="","SIN FECHA","")
A37: BLO-005 | B37: Bloque HCCA Brimax 10 x 20 x 60 | C37: u | D37: 2003.62 | E37: Cutuli Hnos | F37: 2024-12-05 | G37: Corralón | I37: BRIMAX (Pallet 150 u) [Deflactado v6/1.27] | J37: =IF(F37="","SIN FECHA","")
A38: BLO-006 | B38: Bloque HCCA Brimax 12,5 x 20 x 60 | C38: u | D38: 2504.53 | E38: Cutuli Hnos | F38: 2024-12-05 | G38: Corralón | I38: BRIMAX (Pallet 120 u) [Deflactado v6/1.27] | J38: =IF(F38="","SIN FECHA","")
A39: BLO-007 | B39: Bloque HCCA Brimax 15 x 20 x 60 | C39: u | D39: 3094.7 | E39: Cutuli Hnos | F39: 2024-12-05 | G39: Corralón | I39: BRIMAX (Pallet 100 u) [Deflactado v6/1.27] | J39: =IF(F39="","SIN FECHA","")
A40: BLO-008 | B40: Bloque HCCA Brimax 17,5 x 20 x 60 | C40: u | D40: 3625.36 | E40: Cutuli Hnos | F40: 2024-12-05 | G40: Corralón | I40: BRIMAX (Pallet 80 u) [Deflactado v6/1.27] | J40: =IF(F40="","SIN FECHA","")
A41: BLO-009 | B41: Bloque HCCA Brimax 20 x 20 x 60 | C41: u | D41: 4146.11 | E41: Cutuli Hnos | F41: 2024-12-05 | G41: Corralón | I41: BRIMAX (Pallet 70 u) [Deflactado v6/1.27] | J41: =IF(F41="","SIN FECHA","")
A42: ACE-011 | B42: Kg hierro liso 4 mm | C42: kg | D42: 1977.26 | E42: Cutuli Hnos | F42: 2024-12-05 | G42: Corralón | I42: [Deflactado v6/1.27] | J42: =IF(F42="","SIN FECHA","")
A43: ACE-012 | B43: Kg hierro liso 6 mm | C43: kg | D43: 1395.71 | E43: Cutuli Hnos | F43: 2024-12-05 | G43: Corralón | I43: [Deflactado v6/1.27] | J43: =IF(F43="","SIN FECHA","")
A44: OTR-001 | B44: Weberblock x 30 kg | C44: bol | D44: 6218.17 | E44: Cutuli Hnos | F44: 2024-12-05 | G44: Corralón | I44: [Deflactado v6/1.27] | J44: =IF(F44="","SIN FECHA","")
... A52: REV-005 | B52: Guardacanto yesero 2,60 m | C52: u | D52: 1409.89 | E52: Cutuli Hnos | F52: 2024-12-05 | G52: Revestimientos y yesos | I52: [Deflactado v6/1.27] | J52: =IF(F52="","SIN FECHA","")
A53: DUR-001 | B53: Solera 70mm x 2.60m | C53: u | D53: 2932.93 | E53: Cutuli Hnos | F53: 2024-11-29 | G53: Construcción en seco | J53: =IF(F53="","SIN FECHA","")
A54: DUR-002 | B54: Montante 69mm x 2.60m | C54: u | D54: 3295.47 | E54: Cutuli Hnos | F54: 2024-11-29 | G54: Construcción en seco | J54: =IF(F54="","SIN FECHA","")
A55: DUR-003 | B55: Solera 35mm x 2.60m | C55: u | D55: 2147.85 | E55: Cutuli Hnos | F55: 2024-11-29 | G55: Construcción en seco | J55: =IF(F55="","SIN FECHA","")
A56: DUR-004 | B56: Montante 34mm x 2.60m | C56: u | D56: 2468.66 | E56: Cutuli Hnos | F56: 2024-11-29 | G56: Construcción en seco | J56: =IF(F56="","SIN FECHA","")
A57: OTR-007 | B57: Tornillo T1 - Aguja | C57: u | D57: 32.707174 | E57: CMP online | F57: 2024-12-05 | G57: Construcción en seco | J57: =IF(F57="","SIN FECHA","")
A58: OTR-008 | B58: Tornillo T2 - Aguja | C58: u | D58: 17.196318 | E58: CMP online | F58: 2024-12-05 | G58: Construcción en seco | J58: =IF(F58="","SIN FECHA","")
A59: OTR-009 | B59: Tornillo T3 - Aguja | C59: u | D59: 41.375227 | E59: CMP online | F59: 2024-12-05 | G59: Construcción en seco | J59: =IF(F59="","SIN FECHA","")
A60: OTR-010 | B60: Fijacion completa del 8 | C60: u | D60: 65.919008 | E60: CMP online | F60: 2024-12-05 | G60: Construcción en seco | J60: =IF(F60="","SIN FECHA","")
A61: OTR-011 | B61: Cinta Entramada - 90m | C61: u | D61: 4042.71 | E61: Cutuli Hnos | F61: 2024-11-29 | G61: Construcción en seco | J61: =IF(F61="","SIN FECHA","")
A62: OTR-012 | B62: Cinta de Papel - 75m | C62: u | D62: 5920.61 | E62: Cutuli Hnos | F62: 2024-11-29 | G62: Construcción en seco | I62: Pegue la de 150 m entramada | J62: =IF(F62="","SIN FECHA","")
A63: DUR-005 | B63: Masilla x 32kg | C63: u | D63: 26872.02 | E63: Cutuli Hnos | F63: 2024-11-29 | G63: Construcción en seco | J63: =IF(F63="","SIN FECHA","")
A64: REV-006 | B64: Placa Roca de Yeso 1220 x 2440 - 12.5mm - STD | C64: u | D64: 10022.96 | E64: Cutuli Hnos | F64: 2024-11-29 | G64: Revestimientos y yesos | J64: =IF(F64="","SIN FECHA","")
A65: REV-007 | B65: Placa Roca de Yeso 1220 x 2440 - 12.5mm - RH | C65: u | D65: 16160.1 | E65: Cutuli Hnos | F65: 2024-11-29 | G65: Revestimientos y yesos | J65: =IF(F65="","SIN FECHA","")
A66: REV-008 | B66: Placa Roca de Yeso 1220 x 2440 - 12.5mm - RF | C66: u | D66: 14217.87 | E66: Cutuli Hnos | F66: 2024-11-29 | G66: Revestimientos y yesos | J66: =IF(F66="","SIN FECHA","")
A67: OTR-013 | B67: Cantonera x 2.60 | C67: u | D67: 1421.47 | E67: Cutuli Hnos | F67: 2024-11-29 | G67: Construcción en seco | J67: =IF(F67="","SIN FECHA","")
A68: OTR-014 | B68: Buña Z x 2.60m | C68: u | D68: 2351.29 | E68: Cutuli Hnos | F68: 2024-11-29 | G68: Construcción en seco | J68: =IF(F68="","SIN FECHA","")
A69: DUR-006 | B69: Lana De Vidrio 40mm X 21,6m2 Alta Densidad | C69: u | D69: 97970.9 | E69: Cutuli Hnos | F69: 2024-11-29 | G69: Construcción en seco | I69: Rolac plata cubierta 1,20 x 18 x 50 mm | J69: =IF(F69="","SIN FECHA","")
A70: DUR-007 | B70: Perfil Perimetral x 3.05 | C70: u | D70: 2470.562 | E70: CMP online | F70: 2024-12-05 | G70: Construcción en seco | J70: =IF(F70="","SIN FECHA","")
A71: OTR-015 | B71: Larguero x 3.66 | C71: u | D71: 3894.6612 | E71: CMP online | F71: 2024-12-05 | G71: Construcción en seco | J71: =IF(F71="","SIN FECHA","")
A72: OTR-016 | B72: Travesaño x 1.22 | C72: u | D72: 1262.1736 | E72: CMP online | F72: 2024-12-05 | G72: Construcción en seco | J72: =IF(F72="","SIN FECHA","")
A73: OTR-017 | B73: Travesaño x 0.60 | C73: u | D73: 647.24793 | E73: CMP online | F73: 2024-12-05 | G73: Construcción en seco | J73: =IF(F73="","SIN FECHA","")
A74: OTR-018 | B74: Placa Decovinyl Liso 60x60 | C74: u | D74: 6538.6116 | E74: ML | F74: 2024-12-05 | G74: Construcción en seco | I74: https://www.mercadolibre.com.ar/placas-desmontables-deco-vinyl-cielorraso-060-x-060-x-m2/up/MLAU364356693?highlight=false&headerTopBrand=true#polycard_client=search-nordic&searchVariation=MLAU364356693&wid=MLA1755838658&position=3&search_layout=stack&type=product&tracking_id=a6d04372-95d1-4609-a7c0-bc66c65b36db&sid=search | J74: =IF(F74="","SIN FECHA","")
A75: ACE-014 | B75: Alambre galvanizado N°14 x kg | C75: u | D75: 2474.3471 | E75: CMP online | F75: 2024-12-05 | G75: Corralón | J75: =IF(F75="","SIN FECHA","")
A76: OTR-019 | B76: Placa Decovinyl Liso 120x60 | C76: u | D76: 4751.7079 | E76: ML | F76: 2024-02-28 | G76: Construcción en seco | I76: no tengo coti | J76: =IF(F76="","SIN FECHA","")
A77: PIN-001 | B77: Latex Loxon Interior Sherwin Williams Mate Bco x 20lts | C77: B | D77: 120622.23 | E77: Prestigio | F77: 2024-12-16 | G77: Pinturas | H77: PINT001 | J77: =IF(F77="","SIN FECHA","")
A78: PIN-002 | B78: Latex Loxon Interior Sherwin Williams Satinado Bco x 20lts | C78: u | D78: 237603.31 | E78: Prestigio Web | F78: 2024-12-28 | G78: Pinturas | J78: =IF(F78="","SIN FECHA","")
A79: PIN-003 | B79: Latex Loxon Exterior Sherwin Williams Mate Bco x 20lts | C79: u | D79: 105657.74 | E79: Prestigio | F79: 2024-12-16 | G79: Pinturas | J79: =IF(F79="","SIN FECHA","")
A80: PIN-004 | B80: Esmalte sintetico brillante Albalux Blanco x 4lts | C80: b | D80: 28011.57 | E80: Prestigio | F80: 2024-12-16 | G80: Pinturas | H80: ESMALTES | J80: =IF(F80="","SIN FECHA","")
A81: PIN-005 | B81: Esmalte sintetico semi mate Albalux Blanco x 4lts | C81: b | D81: 28011.57 | E81: Prestigio | F81: 2024-12-16 | G81: Pinturas | H81: ESMALTES | J81: =IF(F81="","SIN FECHA","")
A82: PIN-006 | B82: Esmalte sintetico satinado Satinol Blanco x 4lts | C82: b | D82: 28011.57 | E82: Prestigio | F82: 2024-12-16 | G82: Pinturas | H82: ESMALTES | J82: =IF(F82="","SIN FECHA","")
A83: PIN-007 | B83: Enduido Interior x 20lts | C83: B | D83: 18735.77 | E83: Prestigio | F83: 2024-12-16 | G83: Pinturas | H83: PINT010 | I83: COVER | J83: =IF(F83="","SIN FECHA","")
A84: ELE-001 | B84: Recuplast Tradicional Blanco x 20 lts | C84: u | D84: 124188.43 | E84: Prestigio Web | F84: 2024-12-28 | G84: Eléctricos | J84: =IF(F84="","SIN FECHA","")
A85: PIN-008 | B85: Pintura Asfaltica Asfasol x18ts | C85: b | D85: 32845.78 | E85: Cutuli Hnos | F85: 2024-11-29 | G85: Pinturas | I85: MEGAFLEX | J85: =IF(F85="","SIN FECHA","")
A86: REV-009 | B86: Quimtex Romano Fino x 27 kg | C86: u | D86: 57033.884 | E86: Quimtex | F86: 2024-08-05 | G86: Revestimientos y yesos | J86: =IF(F86="","SIN FECHA","")
A87: REV-010 | B87: Quimtex base cuarzo 18 lts | C87: u | D87: 93388.43 | E87: Quimtex | F87: 2024-08-05 | G87: Revestimientos y yesos | J87: =IF(F87="","SIN FECHA","")
A88: AIS-002 | B88: Membrana Geotextil Ormiflex 4mm - (35kg) x10m | C88: u | D88: 70192.21 | E88: Cutuli Hnos | F88: 2024-11-29 | G88: Impermeabilizantes | I88: Membrana EMAPI W450 | J88: =IF(F88="","SIN FECHA","")
A89: ADT-002 | B89: Venda SikaTEX 75 - Rollo | C89: u | D89: 66115.702 | E89: Prestifio Web | F89: 2024-12-28 | G89: Impermeabilizantes | J89: =IF(F89="","SIN FECHA","")
A90: OTR-020 | B90: Fijador al Aguarras x 4lts | C90: B | D90: 43017.107 | E90: Prestigio WEB | F90: 2024-08-19 | G90: Pinturas | H90: PINT014 | J90: =IF(F90="","SIN FECHA","")
A91: OTR-021 | B91: Fijador al agua x 20 lts | C91: b | D91: 30467.49 | E91: Prestigio | F91: 2024-12-16 | G91: Pinturas | I91: PRINZ | J91: =IF(F91="","SIN FECHA","")
A92: OTR-022 | B92: Aguarras Hydrarras Hydra x 18lts | C92: b | D92: 26907.33 | E92: Prestigio | F92: 2024-12-16 | G92: Pinturas | H92: PINT016 | J92: =IF(F92="","SIN FECHA","")
A93: OTR-023 | B93: Lija 180 al agua x 10u | C93: u | D93: 5661.4 | E93: Prestigio | F93: 2024-12-16 | G93: Pinturas | H93: PINT011 | J93: =IF(F93="","SIN FECHA","")
A94: OTR-024 | B94: Cinta de Papel 36 mm x 40m | C94: u | D94: 3293.01 | E94: Prestigio | F94: 2024-12-16 | G94: Pinturas | H94: PINT012 | I94: 48 mm | J94: =IF(F94="","SIN FECHA","")
A95: OTR-025 | B95: Trapo | C95: u | D95: 735.06 | E95: Prestigio | F95: 2024-12-16 | G95: Pinturas | H95: PINT013 | J95: =IF(F95="","SIN FECHA","")
A96: CER-008 | B96: Impregnante p/ Ladrillos Brikol 20 L - Semi Satinado | C96: u | D96: 199110.12 | E96: Prestigio WEB | F96: 2024-12-28 | G96: Revestimientos y yesos | I96: SikaGuard | J96: =IF(F96="","SIN FECHA","")
A97: OTR-026 | B97: Rodillo de lana pelo corto antigota N°22 - El Galgo | C97: u | D97: 6678.36 | E97: Prestigio | F97: 2024-12-16 | G97: Pinturas | J97: =IF(F97="","SIN FECHA","")
A98: OTR-027 | B98: Rodillo de lana pelo largo N°22 - El Galgo | C98: u | D98: 6678.36 | E98: Prestigio | F98: 2024-12-16 | G98: Pinturas | J98: =IF(F98="","SIN FECHA","")
A99: OTR-028 | B99: Pincel N° 20 - El Galgo | C99: u | D99: 5282.24 | E99: Prestigio | F99: 2024-12-16 | G99: Pinturas | I99: N25 | J99: =IF(F99="","SIN FECHA","")
A100: OTR-029 | B100: Rollo de cartón corrugado 0,90 x 25 mts | C100: u | D100: 7427.6 | E100: Prestigio | F100: 2024-12-16 | G100: Construcción en seco | J100: =IF(F100="","SIN FECHA","")
A101: OTR-030 | B101: Llana Plástica 12 x 25 cm | C101: u | D101: 12575.207 | E101: Prestigio WEB | F101: 2024-12-28 | G101: Construcción en seco | J101: =IF(F101="","SIN FECHA","")
A102: ACE-015 | B102: CLAVOS DE 21/2" X 12 | C102: KG | D102: 2130.1681 | E102: Cutuli Hnos | F102: 2024-11-29 | G102: Corralón | H102: CLAVO25 | J102: =IF(F102="","SIN FECHA","")
A103: OTR-031 | B103: FENOLICO 18MM. COMUN 1.22 x 2.40 | C103: UD | D103: 26322.68 | E103: Newton | F103: 2024-10-18 | G103: Corralón | H103: FENOLICO | J103: =IF(F103="","SIN FECHA","")
A104: OTR-032 | B104: FENOLICO 18MM. LAMINADO MELAMINICO | C104: M2 | D104: 51752.74 | E104: Newton | F104: 2024-11-06 | G104: Corralón | H104: FENOLMEL | J104: =IF(F104="","SIN FECHA","")
A105: OTR-033 | B105: tirante 3x3 para puntal 3.66 | C105: ml | D105: 1213.73 | E105: Newton | F105: 2024-10-18 | G105: Corralón | H105: PUNTA3X3 | J105: =IF(F105="","SIN FECHA","")
A106: OTR-034 | B106: tirante 3x6 3.66 | C106: un | D106: 4442.2518 | E106: Newton | F106: 2024-10-18 | G106: Corralón | H106: TIRAN3X6 | J106: =IF(F106="","SIN FECHA","")
A107: ACE-016 | B107: ACERO ESTRUCTURAL POR KILO | C107: KGF | D107: 1269.26 | E107: Cutuli Hnos | F107: 2024-11-29 | G107: Corralón | H107: ACEROEST | J107: =IF(F107="","SIN FECHA","")
...

Sheet MANO_DE_OBRA
A1: Código | B1: Descripción | C1: Salario/día $ | D1: Coef. Cargas | E1: Costo Jornal $ | F1: Tipo | G1: Cód. Original
A2: MO-TOP | B2: TOPOGRAFO | C2: 171854.19 | D2: =CONFIG!C22 -> 1.7452228 | E2: =C2*D2 -> 299923.87 | F2: Operativo | G2: *TOPOGRA
A3: MO-EESPE | B3: ESPECIALIZADO | C3: 85927.097 | D3: =CONFIG!C22 -> 1.7452228 | E3: =C3*D3 -> 149961.93 | F3: Estructura | G3: EST-ESPE
A4: MO-EOFIC | B4: OFICIAL | C4: 76955.08 | D4: =CONFIG!C22 -> 1.7452228 | E4: =C4*D4 -> 134303.76 | F4: Estructura | G4: EST-OFIC
A5: MO-EMEDI | B5: MEDIO OFICIAL | C5: 65493.072 | D5: =CONFIG!C22 -> 1.7452228 | E5: =C5*D5 -> 114300 | F5: Estructura | G5: EST-MEDI
A6: MO-EAYUD | B6: AYUDANTE | C6: 60860.581 | D6: =CONFIG!C22 -> 1.7452228 | E6: =C6*D6 -> 106215.28 | F6: Estructura | G6: EST-AYUD
A7: ── ESTRUCTURA GERENCIAL — NO USAR EN APU ──
A8: MO-ESOBR | B8: SOBRESTANTE | C8: 3009340.6 | D8: =CONFIG!C22 -> 1.7452228 | E8: =C8*D8 -> 5251969.9 | F8: Estructura | G8: EST-SOBR
A9: MO-EJEFE | B9: JEFE DE OBRA | C9: 4372210.6 | D9: =CONFIG!C22 -> 1.7452228 | E9: =C9*D9 -> 7630481.8 | F9: Estructura | G9: EST-JEFE
A10: MO-ECOOR | B10: COORD OBRAS | C10: 5273644.1 | D10: =CONFIG!C22 -> 1.7452228 | E10: =C10*D10 -> 9203684.1 | F10: Estructura | G10: EST-COOR
F11: Estructura | G11: EST-CAPA

Sheet EQUIPOS
A1: Código | B1: Descripción | C1: Costo Total Set $ | D1: Vida (años) | E1: Vida (días) | F1: $/día | G1: Categoría | H1: Cód. Original
A2: EQ-ANDAM0 | B2: ANDAMIO TUBULAR DE UNO A TRES CUERPOS | C2: 1028123.1 | D2: 5 | E2: =D2*360 -> 1800 | F2: =IF(E2=0,0,C2/E2) -> 571.17949 | G2: Equipo propio | H2: *ANDAM05
A3: EQ-EQALBA | B3: EQUIPO DE ALBAÑILERIA, carpetas, ladrillo | C3: 2470106.6 | D3: 3 | E3: =D3*360 -> 1080 | F3: =IF(E3=0,0,C3/E3) -> 2287.1357 | G3: Equipo propio | H3: EQALBA
A4: EQ-EQCERA | B4: EQUIPO PARA COLOCACION DE CERAMICA | C4: 1424056.6 | D4: 1.5 | E4: =D4*360 -> 540 | F4: =IF(E4=0,0,C4/E4) -> 2637.1418 | G4: Equipo propio | H4: EQCERAMI
A5: EQ-EQUIP0 | B5: EQUIPO PARA INSTALACION ELECTRICA | C5: 2734071.2 | D5: 1.5 | E5: =D5*360 -> 540 | F5: =IF(E5=0,0,C5/E5) -> 5063.0948 | G5: Equipo propio | H5: *EQUIP09
A6: EQ-EQUIPI | B6: EQUIPO PARA PINTAR | C6: 1241010.7 | D6: 2 | E6: =D6*360 -> 720 | F6: =IF(E6=0,0,C6/E6) -> 1723.626 | G6: Equipo propio | H6: *EQUIPIN
A7: EQ-EQPLOM | B7: EQUIPO PARA PLOMERIA | C7: 2058254 | D7: 2 | E7: =D7*360 -> 720 | F7: =IF(E7=0,0,C7/E7) -> 2858.6861 | G7: Equipo propio | H7: EQPLOME
A8: EQ-HORMI | B8: EQUIPO PARA HORMIGON | C8: 3739856.7 | D8: 1.5 | E8: =D8*360 -> 540 | F8: =IF(E8=0,0,C8/E8) -> 6925.6605 | G8: Equipo propio | H8: *EQUIP02
A9: EQ-TROMPO | B9: Hormigonera De 150 Litros 1hp Con Rueda Maciza | C9: 689222.3 | D9: 2 | E9: =D9*360 -> 720 | F9: =IF(E9=0,0,C9/E9) -> 957.2532 | G9: Equipo propio | H9: TROMPO
A10: EQ-SOLD00 | B10: Soldador Soplete A Gas Techista Membrana 10 Kg Boca 50mm | C10: 579244.09 | D10: 2 | E10: =D10*360 -> 720 | F10: =IF(E10=0,0,C10/E10) -> 804.50569 | G10: Equipo propio | H10: SOLD003
A11: EQ-CORTA | B11: CORTADORA CERAMICA PROFESIONAL 1200MM (PORCELANATO HASTA 16MM) | C11: 537162.92 | D11: 5 | E11: =D11*360 -> 1800 | F11: =IF(E11=0,0,C11/E11) -> 298.42384 | G11: Equipo propio | H11: EQCERAMI02
A12: EQ-ESCALE | B12: ESCALERA GLOSS ALUMINIO ARTICULADA 4 X 4 ESCALONES HASTA 150KG | C12: 201885.25 | D12: 4 | E12: =D12*360 -> 1440 | F12: =IF(E12=0,0,C12/E12) -> 140.19809 | G12: Equipo propio | H12: *ESCALE1
A13: EQ-SILLET | B13: Kit Complementario Silleta Descensor Conector Soga X 50 Mts | C13: 683705.75 | D13: 1 | E13: =D13*360 -> 360 | F13: =IF(E13=0,0,C13/E13) -> 1899.1826 | G13: Equipo propio | H13: SILLETA
... A18: EQ-KITPIN | B18: Kit de pintura completo | C18: 1468137.4 | D18: 3 | E18: =D18*360 -> 1080 | F18: =IF(E18=0,0,C18/E18) -> 1359.3865 | G18: Equipo propio | H18: *KITPINT
A19: EQ-REVOC | B19: Máquina revocadora proyectable - Alquiler mensual | C19: 976113.01 | E19: 30 | F19: =IF(E19=0,0,C19/E19) -> 32537.1 | G19: Equipo propio | H19: SIN_COD
A20: EQ-FRAT36 | B20: FRATACHADORA MASTERPAC PMT36H - Alq. X dia | C20: 61876.7 | E20: 1 | F20: =IF(E20=0,0,C20/E20) -> 61876.7 | G20: Alquiler diario | H20: ALQ_DIARIO
A21: EQ-FRAT24 | B21: FRATACHADORA MASALTA MT24-2 - Alq. X dia | C21: 72723.2 | E21: 1 | F21: =IF(E21=0,0,C21/E21) -> 72723.2 | G21: Alquiler diario | H21: ALQ_DIARIO
A22: EQ-REVOC2 | B22: Maquina revocadora Revoque/Yeso - Alq. X mes | C22: 1230000 | E22: 30 | F22: =IF(E22=0,0,C22/E22) -> 41000 | G22: Equipo propio | H22: ALQ_DIARIO
A23: EQ-COMBB | B23: Combustible bobcat (36 lts) | C23: 40428 | E23: 1 | F23: =IF(E23=0,0,C23/E23) -> 40428 | G23: Alquiler diario | H23: ALQ_DIARIO
A24: EQ-COMBPR | B24: Combustible Pala y Retro (60 lts) | C24: 67380 | E24: 1 | F24: =IF(E24=0,0,C24/E24) -> 67380 | G24: Alquiler diario | H24: ALQ_DIARIO
A25: EQ-CARG2M | B25: Pala cargadora frontal (2 m) 936 - (c/ operario y combustible) - Alq. X dia | C25: 506170 | E25: 1 | F25: =IF(E25=0,0,C25/E25) -> 506170 | G25: Alquiler diario | H25: ALQ_DIARIO
A26: EQ-CARG3M | B26: Pala cargadora frontal (3 m) 950 - (c/ operario y combustible) - Alq. X dia | C26: 588810 | E26: 1 | F26: =IF(E26=0,0,C26/E26) -> 588810 | G26: Alquiler diario | H26: ALQ_DIARIO
A27: EQ-COMPCT | B27: Compactador pata de cabra 612H - (c/operario y combustible) - Alq. X dia | C27: 568150 | E27: 1 | F27: =IF(E27=0,0,C27/E27) -> 568150 | G27: Alquiler diario | H27: ALQ_DIARIO
A28: EQ-EXCAV | B28: Excavador sobre orugas PC-200 - (c/operario y combustible) - Alq. X dia | C28: 878050 | E28: 1 | F28: =IF(E28=0,0,C28/E28) -> 878050 | G28: Alquiler diario | H28: ALQ_DIARIO
A29: EQ-MOTON | B29: Motoniveladora 120H - (c/operario y combustible) - Alq. X dia | C29: 929700 | E29: 1 | F29: =IF(E29=0,0,C29/E29) -> 929700 | G29: Alquiler diario | H29: ALQ_DIARIO
A30: EQ-VOLC | B30: Camion chasis volcador 170E22 - (c/ operario y combustible) - Alq. X dia | C30: 258250 | E30: 1 | F30: =IF(E30=0,0,C30/E30) -> 258250 | G30: Alquiler diario | H30: ALQ_DIARIO
... A34: EQ-PALA310 | B34: Pala y retro 310J (c/ operario y combustible) | C34: 464850 | E34: 1 | F34: =IF(E34=0,0,C34/E34) -> 464850 | G34: Alquiler diario | H34: ALQ_DIARIO
A35: EQ-PTO001 | B35: Baño portatil / Ducha | C35: 1 | E35: 1 | F35: 79748.53 | G35: Herramientas — Preliminares | H35: Cotizaciones D47
A36: EQ-PTO002 | B36: Traslado flete entrega/ retiro | C36: 1 | E36: 1 | F36: 13291.422 | G36: Herramientas — Preliminares | H36: Cotizaciones D48
A37: EQ-PTO003 | B37: Alquiler vibropisson | C37: 1 | E37: 1 | F37: 65000 | G37: Herramientas — Hormigón | H37: Tareas/2.02 alquiler
A38: EQ-PTO004 | B38: Herramientas y consumibles Excavación manual para vigas de fundación | C38: 1 | E38: 1 | F38: 1302.9087 | G38: Herramientas — Hormigón | H38: PTO 2.03 (% s/MAT+MO)
A39: EQ-PTO005 | B39: Herramientas y consumibles Tabique submuración - H35 (95 kg/m3 de hierro) | C39: 1 | E39: 1 | F39: 11395.702 | G39: Herramientas — Hormigón | H39: PTO 3.03 (% s/MAT+MO)
A40: EQ-PTO006 | B40: Herramientas y consumibles Zapata corrida tabique - H35 (120 kg/m3 de hierro) | C40: 1 | E40: 1 | F40: 10647.458 | G40: Herramientas — Hormigón | H40: PTO 3.04 (% s/MAT+MO)
A41: EQ-PTO007 | B41: Herramientas y consumibles Platea - H35 (95 kg/m3 de hierro) | C41: 1 | E41: 1 | F41: 7920.4191 | G41: Herramientas — Hormigón | H41: PTO 3.05 (% s/MAT+MO)
A42: EQ-PTO008 | B42: Herramientas y consumibles Bases aisladas - (60 kg/m3 de hierro) | C42: 1 | E42: 1 | F42: 7040.5472 | G42: Herramientas — Hormigón | H42: PTO 3.06 (% s/MAT+MO)
A43: EQ-PTO009 | B43: Herramientas y consumibles Troncos de columnas - H35 (240 kg/m3 de hierro) | C43: 1 | E43: 1 | F43: 14296.601 | G43: Herramientas — Hormigón | H43: PTO 3.07 (% s/MAT+MO)
A44: EQ-PTO010 | B44: Herramientas y consumibles Viga de encadenado - H35 (180 kg/m3 de hierro) | C44: 1 | E44: 1 | F44: 12155.81 | G44: Herramientas — Hormigón | H44: PTO 3.08 (% s/MAT+MO)
A45: EQ-PTO011 | B45: Herramientas y consumibles Losa maciza - H35 (100 kg/m3 de hierro) | C45: 1 | E45: 1 | F45: 8915.6269 | G45: Herramientas — Hormigón | H45: PTO 3.09 (% s/MAT+MO)
A46: EQ-PTO012 | B46: Herramientas y consumibles Losa maciza de Hº visto - H35 (100 kg/m3 de hierro | C46: 1 | E46: 1 | F46: 9854.9599 | G46: Herramientas — Hormigón | H46: PTO 3.1 (% s/MAT+MO)
... A157: EQ-PTO123 | B157: Herramientas y consumibles - PTO-1832 Puesta tierra | C157: 1 | E157: 1 | F157: 10618.104 | G157: Herramientas — Instalaciones | H157: PTO-1832 EQ 1.5% s/MAT+MO

Sheet SUBCONTRATOS
A1: Rubro | B1: Tarea | C1: Contratista | D1: Ud. | E1: PU Actualizado $ | F1: Fecha Act. | G1: PU Original | H1: Fecha Orig.
A2: Colocacion | B2: Ceramico en pisos y pared | C2: Zotelo | D2: m2 | E2: 19490.499 | F2: 2025-09-19 | G2: 2000 | H2: 2022-10-01
A3: Colocacion | B3: Porcelanato en piso | C3: Zotelo | D3: m2 | E3: 17541.449 | F3: 2025-09-19 | G3: 1800 | H3: 2022-10-01
A4: Pintura | B4: Latex Mate | C4: Lionel | D4: m2 | E4: 6620.5651 | F4: 2025-09-19 | G4: 800 | H4: 2022-12-01
A5: Pintura | B5: Latex Mate s/ Pared + Enduido | C5: Lionel | D5: m2 | E5: 8275.7063 | F5: 2025-09-19 | G5: 1000 | H5: 2022-12-01
A6: Pintura | B6: Latex Mate s/ Cielorraso + Enduido | C6: Lionel | D6: m2 | E6: 8275.7063 | F6: 2025-09-19 | G6: 1000 | H6: 2022-12-01
A7: Pintura | B7: Latex Satinado s/ Pared + Enduido | C7: Lionel | D7: m2 | E7: 16551.413 | F7: 2025-09-19 | G7: 2000 | H7: 2022-12-01
A8: Pintura | B8: Latex Satinado s/ Cielorraso + Enduido | C8: Lionel | D8: m2 | E8: 16551.413 | F8: 2025-09-19 | G8: 2000 | H8: 2022-12-01
A9: Pintura | B9: Esmalte Sintetico | C9: Lionel | D9: m2 | E9: 10758.418 | F9: 2025-09-19 | G9: 1300 | H9: 2022-12-01
A10: Pintura | B10: Esmalte sintetico en Herrerias | C10: Lionel | D10: m2 | E10: 10758.418 | F10: 2025-09-19 | G10: 1300 | H10: 2022-12-01
A11: Pintura | B11: Tarquini | C11: Lionel | D11: m2 | E11: 12413.56 | F11: 2025-09-19 | G11: 1500 | H11: 2023-04-01
A12: Durlock | B12: Tabique simple | C12: Mario Silva | D12: m2 | E12: 28402.767 | F12: 2025-09-19 | G12: 2500 | H12: 2022-08-01
A13: Durlock | B13: Medio Forro | C13: Mario Silva | D13: m2 | E13: 20449.992 | F13: 2025-09-19 | G13: 1800 | H13: 2022-08-01
... A20: Yeso | B20: Aristas | C20: Miguel Galleguillo | D20: ml | E20: 6620.5651 | F20: 2025-09-19 | G20: 750 | H20: 2022-11-25
A21: Yeso | B21: Enlucidos en paredes | C21: Miguel Galleguillo | D21: m2 | E21: 13241.13 | F21: 2025-09-19
A22: Yeso | B22: Buñas | C22: Jorge Yesero (CDR) | D22: ml | E22: 6620.5651 | F22: 2025-09-19 | G22: 750 | H22: 2022-11-25
A23: Electrico | B23: Cableado x boca | C23: Demian | D23: u | E23: 14617.874 | F23: 2025-09-19 | G23: 1500 | H23: 2022-10-01
A24: Electrico | B24: Cableado x bandeja (cable 4x10mm x ml) | C24: Demian | D24: ml | E24: 14617.874 | F24: 2025-09-19 | G24: 1500 | H24: 2022-10-01
A25: Electrico | B25: Cañeria PVC (x boca) | C25: Demian | D25: u | E25: 29235.748 | F25: 2025-09-19 | G25: 3000 | H25: 2022-10-01
A26: Electrico | B26: Cañeria Metalica (x boca) | C26: Demian | D26: u | E26: 29235.748 | F26: 2025-09-19 | G26: 3000 | H26: 2022-10-01
A27: Electrico | B27: Cañeria EXT | C27: Demian | D27: ml | E27: 29235.748 | F27: 2025-09-19 | G27: 3000 | H27: 2022-10-01
A28: Electrico | B28: Bandeja 450/600 (xml) | C28: Demian | D28: ml | E28: 13156.087 | F28: 2025-09-19 | G28: 1350 | H28: 2022-10-01
A29: Electrico | B29: Colocacion Interruptores / Tomas | C29: Demian | D29: u | E29: 4872.6247 | F29: 2025-09-19 | G29: 500 | H29: 2022-10-01
A30: Electrico | B30: Colocacion de fichas / tomas de Telefono o TV | C30: Demian | D30: u | E30: 4872.6247 | F30: 2025-09-19 | G30: 500 | H30: 2022-10-01
A31: Electrico | B31: Colocacion de Artefactos tipo (aplique, extractores, campanillas, etc) | C31: Demian | D31: u | E31: 14617.874 | F31: 2025-09-19 | G31: 1500 | H31: 2022-10-01
A32: Electrico | B32: Armado de Tablero de Bombas | C32: Demian | D32: u | E32: 194904.99 | F32: 2025-09-19 | G32: 20000 | H32: 2022-10-01
A33: Electrico | B33: Portero Electrico hasta 2m | C33: Demian | D33: u | E33: 43853.622 | F33: 2025-09-19 | G33: 4500 | H33: 2022-10-01
... A42: Electrico | B42: Cable subterraneo (1 boca cada 5 metros) | C42: Demian | D42: b | E42: 34108.373 | F42: 2025-09-19 | G42: 3500 | H42: 2022-10-01

Sheet SUBCONTRATOS_PRY
A1: Código | B1: Descripción | C1: Ud | D1: Precio Unitario Dic-24 ($) | E1: Categoría | F1: Notas
A2: SUB-PRYELEC | B2: Proyecto instalacion electrica | C2: gl | D2: 1204015.5 | E2: Electricidad — Gestión | F2: GESTOR ELECTRICO
A3: SUB-BAJASUM | B3: Baja de suministros | C3: gl | D3: 49052.483 | E3: Electricidad — Gestión | F3: GESTOR ELECTRICO
A4: SUB-CORDEM | B4: Corte por demolicion | C4: gl | D4: 109996.48 | E4: Electricidad — Gestión | F4: GESTOR ELECTRICO
A5: SUB-INSDES | B5: Instalacion electrica desenergizada | C5: gl | D5: 135265.94 | E5: Electricidad — Gestión | F5: GESTOR ELECTRICO
A6: SUB-TRASLA | B6: Traslado de alumbrado publico | C6: gl | D6: 114455.79 | E6: Electricidad — Gestión | F6: GESTOR ELECTRICO
A7: SUB-FACTIB | B7: Factibilidad y renovacion | C7: gl | D7: 245262.41 | E7: Electricidad — Gestión | F7: GESTOR ELECTRICO
A8: SUB-CERTLUZ | B8: Gestion suministros luz de obra | C8: gl | D8: 148643.89 | E8: Electricidad — Gestión | F8: GESTOR ELECTRICO
A9: SUB-SALAMED | B9: Sala de medidores / Camara transformadora | C9: gl | D9: 520253.61 | E9: Electricidad — Gestión | F9: GESTOR ELECTRICO
A10: SUB-CERTLUZ2 | B10: Luz de Obra | C10: u | D10: 107023.6 | E10: Electricidad — Gestión | F10: Certificados
A11: SUB-CERTSGT1 | B11: Servicios grales T1 | C11: u | D11: 107023.6 | E11: Electricidad — Gestión | F11: Certificados
A12: SUB-CERTSGT2 | B12: Servicios grales T2 | C12: u | D12: 157562.52 | E12: Electricidad — Gestión | F12: Certificados
A13: SUB-CERTRES | B13: Residencial | C13: u | D13: 74321.944 | E13: Electricidad — Gestión | F13: Certificados
... A146: SUB-VIBRO3 | B146: Alquiler vibropison | C146: sem | D146: 250000 | E146: Varios | F146: MO/OTR PTO-1104/1105

Sheet PARTIDAS
A1: Código | B1: P# | C1: Rubro | D1: Descripción | E1: Ud. | F1: Rend. | G1: Cant Cons. | H1: % Cons. Desp. | I1: Grado Dif. | J1: MAT (sum/ud) | K1: MO (sum/día) | L1: EQ (sum/día) | M1: MAT/ud | N1: MO/ud | O1: EQ/ud | P1: CD/ud | Q1: # Comp. | R1: Fuente
A2: PRE-032 | B2: 32 | C2: MOVIMIENTO DE TIERRA | D2: Movimiento de suelos para bases c/ aporte de tosca (e: 40 cm en 2 capas de 20 cm) | E2: m3 | F2: 25 | G2: 0 | H2: 0 | I2: 1 | J2: =SUMIFS(COMPOSICIÓN!J$2:J$1879,COMPOSICIÓN!A$2:A$1879,A2,COMPOSICIÓN!B$2:B$1879,"MAT") -> 12754.673 | K2: =SUMIFS(COMPOSICIÓN!J$2:J$1879,COMPOSICIÓN!A$2:A$1879,A2,COMPOSICIÓN!B$2:B$1879,"MO")*I2 -> 151420.17 | L2: =SUMIFS(COMPOSICIÓN!J$2:J$1879,COMPOSICIÓN!A$2:A$1879,A2,COMPOSICIÓN!B$2:B$1879,"EQ") -> 865137.5 | M2: =J2 -> 12754.673 | N2: =IF(F2=0,0,K2/F2) -> 6056.8068 | O2: =IF(F2=0,0,L2/F2) -> 34605.5 | P2: =M2+N2+O2 -> 53416.98 | Q2: =COUNTIF(COMPOSICIÓN!$A:$A,A2) -> 6 | R2: APU
A3: ALB-033 | B3: 33 | C3: MAMPOSTERÍA | D3: Ladrillo común 12,5 x 5,5 x 25 (e:15 cm) | E3: m2 | F3: 7 | G3: 0 | H3: 0 | I3: 1 | J3: =SUMIFS(COMPOSICIÓN!J$2:J$1879,COMPOSICIÓN!A$2:A$1879,A3,COMPOSICIÓN!B$2:B$1879,"MAT") -> 12779.085 | K3: =SUMIFS(COMPOSICIÓN!J$2:J$1879,COMPOSICIÓN!A$2:A$1879,A3,COMPOSICIÓN!B$2:B$1879,"MO")*I3 -> 146787.68 | L3: =SUMIFS(COMPOSICIÓN!J$2:J$1879,COMPOSICIÓN!A$2:A$1879,A3,COMPOSICIÓN!B$2:B$1879,"EQ") -> 3529.9787 | M3: =J3 -> 12779.085 | N3: =IF(F3=0,0,K3/F3) -> 20969.668 | O3: =IF(F3=0,0,L3/F3) -> 504.28267 | P3: =M3+N3+O3 -> 34253.036 | Q3: =COUNTIF(COMPOSICIÓN!$A:$A,A3) -> 11 | R3: APU
A4: ALB-034 | B4: 34 | C4: MAMPOSTERÍA | D4: Ladrillo cerámico 8 x 18 x 33 cm | E4: m2 | F4: 15 | G4: 0 | H4: 0 | I4: 1 | J4: =SUMIFS(COMPOSICIÓN!J$2:J$1879,COMPOSICIÓN!A$2:A$1879,A4,COMPOSICIÓN!B$2:B$1879,"MAT") -> 6590.9962 | K4: =SUMIFS(COMPOSICIÓN!J$2:J$1879,COMPOSICIÓN!A$2:A$1879,A4,COMPOSICIÓN!B$2:B$1879,"MO")*I4 -> 146787.68 | L4: =SUMIFS(COMPOSICIÓN!J$2:J$1879,COMPOSICIÓN!A$2:A$1879,A4,COMPOSICIÓN!B$2:B$1879,"EQ") -> 3529.9787 | M4: =J4 -> 6590.9962 | N4: =IF(F4=0,0,K4/F4) -> 9785.8452 | O4: =IF(F4=0,0,L4/F4) -> 235.33191 | P4: =M4+N4+O4 -> 16612.173 | Q4: =COUNTIF(COMPOSICIÓN!$A:$A,A4) -> 11 | R4: APU
A5: ALB-035 | B5: 35 | C5: MAMPOSTERÍA | D5: Ladrillo cerámico 12 x 18 x 33 cm | E5: m2 | F5: 15 | G5: 0 | H5: 0 | I5: 1 | J5: =SUMIFS(COMPOSICIÓN!J$2:J$1879,COMPOSICIÓN!A$2:A$1879,A5,COMPOSICIÓN!B$2:B$1879,"MAT") -> 8400.1374 | K5: =SUMIFS(COMPOSICIÓN!J$2:J$1879,COMPOSICIÓN!A$2:A$1879,A5,COMPOSICIÓN!B$2:B$1879,"MO")*I5 -> 146787.68 | L5: =SUMIFS(COMPOSICIÓN!J$2:J$1879,COMPOSICIÓN!A$2:A$1879,A5,COMPOSICIÓN!B$2:B$1879,"EQ") -> 3529.9787 | M5: =J5 -> 8400.1374 | N5: =IF(F5=0,0,K5/F5) -> 9785.8452 | O5: =IF(F5=0,0,L5/F5) -> 235.33191 | P5: =M5+N5+O5 -> 18421.314 | Q5: =COUNTIF(COMPOSICIÓN!$A:$A,A5) -> 11 | R5: APU
A6: ALB-036 | B6: 36 | C6: MAMPOSTERÍA | D6: Ladrillo cerámico 18 x 18 x 33 cm | E6: m2 | F6: 15 | G6: 0 | H6: 0 | I6: 1 | J6: =SUMIFS(COMPOSICIÓN!J$2:J$1879,COMPOSICIÓN!A$2:A$1879,A6,COMPOSICIÓN!B$2:B$1879,"MAT") -> 11492.44 | K6: =SUMIFS(COMPOSICIÓN!J$2:J$1879,COMPOSICIÓN!A$2:A$1879,A6,COMPOSICIÓN!B$2:B$1879,"MO")*I6 -> 146787.68 | L6: =SUMIFS(COMPOSICIÓN!J$2:J$1879,COMPOSICIÓN!A$2:A$1879,A6,COMPOSICIÓN!B$2:B$1879,"EQ") -> 3529.9787 | M6: =J6 -> 11492.44 | N6: =IF(F6=0,0,K6/F6) -> 9785.8452 | O6: =IF(F6=0,0,L6/F6) -> 235.33191 | P6: =M6+N6+O6 -> 21513.617 | Q6: =COUNTIF(COMPOSICIÓN!$A:$A,A6) -> 11 | R6: APU
A7: ALB-037 | B7: 37 | C7: MAMPOSTERÍA | D7: Pared DOBLE Comun / 5 / LHC 08 - (ladrillo a la vista) | E7: m2 | F7: 4 | G7: 0 | H7: 0 | I7: 1 | J7: =SUMIFS(COMPOSICIÓN!J$2:J$1879,COMPOSICIÓN!A$2:A$1879,A7,COMPOSICIÓN!B$2:B$1879,"MAT") -> 27983.303 | K7: =SUMIFS(COMPOSICIÓN!J$2:J$1879,COMPOSICIÓN!A$2:A$1879,A7,COMPOSICIÓN!B$2:B$1879,"MO")*I7 -> 141310.23 | L7: =SUMIFS(COMPOSICIÓN!J$2:J$1879,COMPOSICIÓN!A$2:A$1879,A7,COMPOSICIÓN!B$2:B$1879,"EQ") -> 3529.9787 | M7: =J7 -> 27983.303 | N7: =IF(F7=0,0,K7/F7) -> 35327.556 | O7: =IF(F7=0,0,L7/F7) -> 882.49467 | P7: =M7+N7+O7 -> 64193.354 | Q7: =COUNTIF(COMPOSICIÓN!$A:$A,A7) -> 16 | R7: APU
A8: ALB-038 | B8: 38 | C8: MAMPOSTERÍA | D8: Ladrillo hueco portante 12 x 19 x 33 | E8: m2 | F8: 15 | G8: 0 | H8: 0 | I8: 1 | J8: =SUMIFS(COMPOSICIÓN!J$2:J$1879,COMPOSICIÓN!A$2:A$1879,A8,COMPOSICIÓN!B$2:B$1879,"MAT") -> 11547.894 | K8: =SUMIFS(COMPOSICIÓN!J$2:J$1879,COMPOSICIÓN!A$2:A$1879,A8,COMPOSICIÓN!B$2:B$1879,"MO")*I8 -> 146787.68 | L8: =SUMIFS(COMPOSICIÓN!J$2:J$1879,COMPOSICIÓN!A$2:A$1879,A8,COMPOSICIÓN!B$2:B$1879,"EQ") -> 3529.9787 | M8: =J8 -> 11547.894 | N8: =IF(F8=0,0,K8/F8) -> 9785.8452 | O8: =IF(F8=0,0,L8/F8) -> 235.33191 | P8: =M8+N8+O8 -> 21569.071 | Q8: =COUNTIF(COMPOSICIÓN!$A:$A,A8) -> 11 | R8: APU
A9: ALB-039 | B9: 39 | C9: MAMPOSTERÍA | D9: Amure puertas tipo (0,90 x 2,00 m) | E9: u | F9: 2 | G9: 0 | H9: 0 | I9: 1 | J9: =SUMIFS(COMPOSICIÓN!J$2:J$1879,COMPOSICIÓN!A$2:A$1879,A9,COMPOSICIÓN!B$2:B$1879,"MAT") -> 4066.3296 | K9: =SUMIFS(COMPOSICIÓN!J$2:J$1879,COMPOSICIÓN!A$2:A$1879,A9,COMPOSICIÓN!B$2:B$1879,"MO")*I9 -> 110090.76 | L9: =SUMIFS(COMPOSICIÓN!J$2:J$1879,COMPOSICIÓN!A$2:A$1879,A9,COMPOSICIÓN!B$2:B$1879,"EQ") -> 811.09724 | M9: =J9 -> 4066.3296 | N9: =IF(F9=0,0,K9/F9) -> 55045.379 | O9: =IF(F9=0,0,L9/F9) -> 405.54862 | P9: =M9+N9+O9 -> 59517.257 | Q9: =COUNTIF(COMPOSICIÓN!$A:$A,A9) -> 6 | R9: APU
A10: ALB-040 | B10: 40 | C10: MAMPOSTERÍA | D10: Amure Premarcos | E10: u | F10: 4 | G10: 0 | H10: 0 | I10: 1 | J10: =SUMIFS(COMPOSICIÓN!J$2:J$1879,COMPOSICIÓN!A$2:A$1879,A10,COMPOSICIÓN!B$2:B$1879,"MAT") -> 1487.907 | K10: =SUMIFS(COMPOSICIÓN!J$2:J$1879,COMPOSICIÓN!A$2:A$1879,A10,COMPOSICIÓN!B$2:B$1879,"MO")*I10 -> 146787.68 | L10: =SUMIFS(COMPOSICIÓN!J$2:J$1879,COMPOSICIÓN!A$2:A$1879,A10,COMPOSICIÓN!B$2:B$1879,"EQ") -> 811.09724 | M10: =J10 -> 1487.907 | N10: =IF(F10=0,0,K10/F10) -> 36696.919 | O10: =IF(F10=0,0,L10/F10) -> 202.77431 | P10: =M10+N10+O10 -> 38387.601 | Q10: =COUNTIF(COMPOSICIÓN!$A:$A,A10) -> 6 | R10: APU
A11: ALB-041 | B11: 41 | C11: MAMPOSTERÍA | D11: Amure barandas (insertos c/1,00 m) | E11: ml | F11: 5 | G11: 0 | H11: 0 | I11: 1 | J11: =SUMIFS(COMPOSICIÓN!J$2:J$1879,COMPOSICIÓN!A$2:A$1879,A11,COMPOSICIÓN!B$2:B$1879,"MAT") -> 204.36356 | K11: =SUMIFS(COMPOSICIÓN!J$2:J$1879,COMPOSICIÓN!A$2:A$1879,A11,COMPOSICIÓN!B$2:B$1879,"MO")*I11 -> 146787.68 | L11: =SUMIFS(COMPOSICIÓN!J$2:J$1879,COMPOSICIÓN!A$2:A$1879,A11,COMPOSICIÓN!B$2:B$1879,"EQ") -> 1382.8812 | M11: =J11 -> 204.36356 | N11: =IF(F11=0,0,K11/F11) -> 29357.536 | O11: =IF(F11=0,0,L11/F11) -> 276.57623 | P11: =M11+N11+O11 -> 29838.475 | Q11: =COUNTIF(COMPOSICIÓN!$A:$A,A11) -> 7 | R11: APU
A12: ALB-042 | B12: 42 | C12: MAMPOSTERÍA | D12: Azotado hidrófugo | E12: m2 | F12: 28 | G12: 0 | H12: 0 | I12: 1 | J12: =SUMIFS(COMPOSICIÓN!J$2:J$1879,COMPOSICIÓN!A$2:A$1879,A12,COMPOSICIÓN!B$2:B$1879,"MAT") -> 809.61503 | K12: =SUMIFS(COMPOSICIÓN!J$2:J$1879,COMPOSICIÓN!A$2:A$1879,A12,COMPOSICIÓN!B$2:B$1879,"MO")*I12 -> 110271.33 | L12: =SUMIFS(COMPOSICIÓN!J$2:J$1879,COMPOSICIÓN!A$2:A$1879,A12,COMPOSICIÓN!B$2:B$1879,"EQ") -> 3529.9787 | M12: =J12 -> 809.61503 | N12: =IF(F12=0,0,K12/F12) -> 3938.2618 | O12: =IF(F12=0,0,L12/F12) -> 126.07067 | P12: =M12+N12+O12 -> 4873.9475 | Q12: =COUNTIF(COMPOSICIÓN!$A:$A,A12) -> 8 | R12: APU
A13: ALB-043 | B13: 43 | C13: MAMPOSTERÍA | D13: Interior jaharro a la cal + Enlucido a la cal | E13: m2 | F13: 6 | G13: 0 | H13: 0 | I13: 1 | J13: =SUMIFS(COMPOSICIÓN!J$2:J$1879,COMPOSICIÓN!A$2:A$1879,A13,COMPOSICIÓN!B$2:B$1879,"MAT") -> 2735.3164 | K13: =SUMIFS(COMPOSICIÓN!J$2:J$1879,COMPOSICIÓN!A$2:A$1879,A13,COMPOSICIÓN!B$2:B$1879,"MO")*I13 -> 125486.47 | L13: =SUMIFS(COMPOSICIÓN!J$2:J$1879,COMPOSICIÓN!A$2:A$1879,A13,COMPOSICIÓN!B$2:B$1879,"EQ") -> 3529.9787 | M13: =J13 -> 2735.3164 | N13: =IF(F13=0,0,K13/F13) -> 20914.412 | O13: =IF(F13=0,0,L13/F13) -> 588.32978 | P13: =M13+N13+O13 -> 24238.059 | Q13: =COUNTIF(COMPOSICIÓN!$A:$A,A13) -> 9 | R13: APU
... A78: PIN-146 | B78: 146 | C78: PINTURA | D78: Látex interior para paredes (s/enduido) | E78: m2 | F78: 25 | G78: 0 | H78: 0 | I78: 1 | J78: =SUMIFS(COMPOSICIÓN!J$2:J$1879,COMPOSICIÓN!A$2:A$1879,A78,COMPOSICIÓN!B$2:B$1879,"MAT") -> 2141.693 | K78: =SUMIFS(COMPOSICIÓN!J$2:J$1879,COMPOSICIÓN!A$2:A$1879,A78,COMPOSICIÓN!B$2:B$1879,"MO")*I78 -> 85927.097 | L78: =SUMIFS(COMPOSICIÓN!J$2:J$1879,COMPOSICIÓN!A$2:A$1879,A78,COMPOSICIÓN!B$2:B$1879,"EQ") -> 1923.879 | M78: =J78 -> 2141.693 | N78: =IF(F78=0,0,K78/F78) -> 3437.0839 | O78: =IF(F78=0,0,L78/F78) -> 76.955162 | P78: =M78+N78+O78 -> 5655.732 | Q78: =COUNTIF(COMPOSICIÓN!$A:$A,A78) -> 11 | R78: APU
A79: PTO-0101 | C79: PRELIMINARES | D79: Limpieza y preparación del terreno - No cotiza | E79: gl | F79: 1 | G79: 0 | H79: 0 | I79: 1 | J79: =SUMIFS(COMPOSICIÓN!J$2:J$1879,COMPOSICIÓN!A$2:A$1879,A79,COMPOSICIÓN!B$2:B$1879,"MAT") -> 0 | K79: =SUMIFS(COMPOSICIÓN!J$2:J$1879,COMPOSICIÓN!A$2:A$1879,A79,COMPOSICIÓN!B$2:B$1879,"MO")*I79 -> 0 | L79: =SUMIFS(COMPOSICIÓN!J$2:J$1879,COMPOSICIÓN!A$2:A$1879,A79,COMPOSICIÓN!B$2:B$1879,"EQ") -> 0 | M79: =J79 -> 0 | N79: =IF(F79=0,0,K79/F79) -> 0 | O79: =IF(F79=0,0,L79/F79) -> 0 | P79: =M79+N79+O79 -> 0 | Q79: =COUNTIF(COMPOSICIÓN!$A:$A,A79) -> 0 | R79: PTO/sin cotizar
A80: PTO-0102 | C80: PRELIMINARES | D80: Topógrafo - Visita de obra replanteo | E80: gl | F80: 1 | G80: 0 | H80: 0 | I80: 1 | J80: =SUMIFS(COMPOSICIÓN!J$2:J$1879,COMPOSICIÓN!A$2:A$1879,A80,COMPOSICIÓN!B$2:B$1879,"MAT") -> 25000 | K80: =SUMIFS(COMPOSICIÓN!J$2:J$1879,COMPOSICIÓN!A$2:A$1879,A80,COMPOSICIÓN!B$2:B$1879,"MO")*I80 -> 259597.43 | L80: =SUMIFS(COMPOSICIÓN!J$2:J$1879,COMPOSICIÓN!A$2:A$1879,A80,COMPOSICIÓN!B$2:B$1879,"EQ") -> 4268.9614 | M80: =J80 -> 25000 | N80: =IF(F80=0,0,K80/F80) -> 259597.43 | O80: =IF(F80=0,0,L80/F80) -> 4268.9614 | P80: =M80+N80+O80 -> 288866.39 | Q80: =COUNTIF(COMPOSICIÓN!$A:$A,A80) -> 4 | R80: PTO/Tareas
A81: PTO-0103 | C81: PRELIMINARES | D81: Cartel de Obra - No cotiza | E81: gl | F81: 1 | G81: 0 | H81: 0 | I81: 1 | J81: =SUMIFS(COMPOSICIÓN!J$2:J$1879,COMPOSICIÓN!A$2:A$1879,A81,COMPOSICIÓN!B$2:B$1879,"MAT") -> 0 | K81: =SUMIFS(COMPOSICIÓN!J$2:J$1879,COMPOSICIÓN!A$2:A$1879,A81,COMPOSICIÓN!B$2:B$1879,"MO")*I81 -> 0 | L81: =SUMIFS(COMPOSICIÓN!J$2:J$1879,COMPOSICIÓN!A$2:A$1879,A81,COMPOSICIÓN!B$2:B$1879,"EQ") -> 0 | M81: =J81 -> 0 | N81: =IF(F81=0,0,K81/F81) -> 0 | O81: =IF(F81=0,0,L81/F81) -> 0 | P81: =M81+N81+O81 -> 0 | Q81: =COUNTIF(COMPOSICIÓN!$A:$A,A81) -> 0 | R81: PTO/sin cotizar
A82: PTO-0104 | C82: PRELIMINARES | D82: Cerco de obra perimetral - En chapa C25 + Concertina + Porton corredizo | E82: ml | F82: 1 | G82: 0 | H82: 0 | I82: 1 | J82: =SUMIFS(COMPOSICIÓN!J$2:J$1879,COMPOSICIÓN!A$2:A$1879,A82,COMPOSICIÓN!B$2:B$1879,"MAT") -> 88330.703 | K82: =SUMIFS(COMPOSICIÓN!J$2:J$1879,COMPOSICIÓN!A$2:A$1879,A82,COMPOSICIÓN!B$2:B$1879,"MO")*I82 -> 101654.37 | L82: =SUMIFS(COMPOSICIÓN!J$2:J$1879,COMPOSICIÓN!A$2:A$1879,A82,COMPOSICIÓN!B$2:B$1879,"EQ") -> 2849.776 | M82: =J82 -> 88330.703 | N82: =IF(F82=0,0,K82/F82) -> 101654.37 | O82: =IF(F82=0,0,L82/F82) -> 2849.776 | P82: =M82+N82+O82 -> 192834.84 | Q82: =COUNTIF(COMPOSICIÓN!$A:$A,A82) -> 12 | R82: PTO/Tareas
A83: PTO-0105 | C83: PRELIMINARES | D83: Obrador, pañol y ducha. | E83: gl | F83: 1 | G83: 0 | H83: 0 | I83: 1 | J83: =SUMIFS(COMPOSICIÓN!J$2:J$1879,COMPOSICIÓN!A$2:A$1879,A83,COMPOSICIÓN!B$2:B$1879,"MAT") -> 2078824.7 | K83: =SUMIFS(COMPOSICIÓN!J$2:J$1879,COMPOSICIÓN!A$2:A$1879,A83,COMPOSICIÓN!B$2:B$1879,"MO")*I83 -> 5174962.9 | L83: =SUMIFS(COMPOSICIÓN!J$2:J$1879,COMPOSICIÓN!A$2:A$1879,A83,COMPOSICIÓN!B$2:B$1879,"EQ") -> 108806.81 | M83: =J83 -> 2078824.7 | N83: =IF(F83=0,0,K83/F83) -> 5174962.9 | O83: =IF(F83=0,0,L83/F83) -> 108806.81 | P83: =M83+N83+O83 -> 7362594.4 | Q83: =COUNTIF(COMPOSICIÓN!$A:$A,A83) -> 23 | R83: PTO/Tareas
A84: PTO-0106 | C84: PRELIMINARES | D84: Alquiler de baños quimicos y duchas portatiles | E84: mes | F84: 1 | G84: 0 | H84: 0 | I84: 1 | J84: =SUMIFS(COMPOSICIÓN!J$2:J$1879,COMPOSICIÓN!A$2:A$1879,A84,COMPOSICIÓN!B$2:B$1879,"MAT") -> 0 | K84: =SUMIFS(COMPOSICIÓN!J$2:J$1879,COMPOSICIÓN!A$2:A$1879,A84,COMPOSICIÓN!B$2:B$1879,"MO")*I84 -> 332285.54 | L84: =SUMIFS(COMPOSICIÓN!J$2:J$1879,COMPOSICIÓN!A$2:A$1879,A84,COMPOSICIÓN!B$2:B$1879,"EQ") -> 0 | M84: =J84 -> 0 | N84: =IF(F84=0,0,K84/F84) -> 332285.54 | O84: =IF(F84=0,0,L84/F84) -> 0 | P84: =M84+N84+O84 -> 332285.54 | Q84: =COUNTIF(COMPOSICIÓN!$A:$A,A84) -> 2 | R84: PTO/Cotizaciones
A85: PTO-0107 | C85: PRELIMINARES | D85: Conexión pilar y luz de obra + Tablero de obra | E85: gl | F85: 1 | G85: 0 | H85: 0 | I85: 1 | J85: =SUMIFS(COMPOSICIÓN!J$2:J$1879,COMPOSICIÓN!A$2:A$1879,A85,COMPOSICIÓN!B$2:B$1879,"MAT") -> 1090000 | K85: =SUMIFS(COMPOSICIÓN!J$2:J$1879,COMPOSICIÓN!A$2:A$1879,A85,COMPOSICIÓN!B$2:B$1879,"MO")*I85 -> 601395.67 | L85: =SUMIFS(COMPOSICIÓN!J$2:J$1879,COMPOSICIÓN!A$2:A$1879,A85,COMPOSICIÓN!B$2:B$1879,"EQ") -> 25370.935 | M85: =J85 -> 1090000 | N85: =IF(F85=0,0,K85/F85) -> 601395.67 | O85: =IF(F85=0,0,L85/F85) -> 25370.935 | P85: =M85+N85+O85 -> 1716766.6 | Q85: =COUNTIF(COMPOSICIÓN!$A:$A,A85) -> 9 | R85: PTO/Tareas
A86: PTO-0108 | C86: PRELIMINARES | D86: Conexión agua de obra, tanque + bomba | E86: gl | F86: 1 | G86: 0 | H86: 0 | I86: 1 | J86: =SUMIFS(COMPOSICIÓN!J$2:J$1879,COMPOSICIÓN!A$2:A$1879,A86,COMPOSICIÓN!B$2:B$1879,"MAT") -> 685200 | K86: =SUMIFS(COMPOSICIÓN!J$2:J$1879,COMPOSICIÓN!A$2:A$1879,A86,COMPOSICIÓN!B$2:B$1879,"MO")*I86 -> 651528.71 | L86: =SUMIFS(COMPOSICIÓN!J$2:J$1879,COMPOSICIÓN!A$2:A$1879,A86,COMPOSICIÓN!B$2:B$1879,"EQ") -> 20050.931 | M86: =J86 -> 685200 | N86: =IF(F86=0,0,K86/F86) -> 651528.71 | O86: =IF(F86=0,0,L86/F86) -> 20050.931 | P86: =M86+N86+O86 -> 1356779.6 | Q86: =COUNTIF(COMPOSICIÓN!$A:$A,A86) -> 11 | R86: PTO/Tareas
A87: PTO-0109 | C87: PRELIMINARES | D87: Tramite luz de obra, certificado luz de obra (2) y medición PAT | E87: gl | F87: 1 | G87: 0 | H87: 0 | I87: 1 | J87: =SUMIFS(COMPOSICIÓN!J$2:J$1879,COMPOSICIÓN!A$2:A$1879,A87,COMPOSICIÓN!B$2:B$1879,"MAT") -> 0 | K87: =SUMIFS(COMPOSICIÓN!J$2:J$1879,COMPOSICIÓN!A$2:A$1879,A87,COMPOSICIÓN!B$2:B$1879,"MO")*I87 -> 456336.73 | L87: =SUMIFS(COMPOSICIÓN!J$2:J$1879,COMPOSICIÓN!A$2:A$1879,A87,COMPOSICIÓN!B$2:B$1879,"EQ") -> 0 | M87: =J87 -> 0 | N87: =IF(F87=0,0,K87/F87) -> 456336.73 | O87: =IF(F87=0,0,L87/F87) -> 0 | P87: =M87+N87+O87 -> 456336.73 | Q87: =COUNTIF(COMPOSICIÓN!$A:$A,A87) -> 3 | R87: PTO/Tareas
A88: PTO-0201 | C88: MOVIMIENTO DE TIERRA | D88: Excavación a maquina para submuración, subsuelo y fundaciones | E88: m3 | F88: 1 | G88: 0 | H88: 0 | I88: 1 | J88: =SUMIFS(COMPOSICIÓN!J$2:J$1879,COMPOSICIÓN!A$2:A$1879,A88,COMPOSICIÓN!B$2:B$1879,"MAT") -> 0 | K88: =SUMIFS(COMPOSICIÓN!J$2:J$1879,COMPOSICIÓN!A$2:A$1879,A88,COMPOSICIÓN!B$2:B$1879,"MO")*I88 -> 39520.777 | L88: =SUMIFS(COMPOSICIÓN!J$2:J$1879,COMPOSICIÓN!A$2:A$1879,A88,COMPOSICIÓN!B$2:B$1879,"EQ") -> 97.811648 | M88: =J88 -> 0 | N88: =IF(F88=0,0,K88/F88) -> 39520.777 | O88: =IF(F88=0,0,L88/F88) -> 97.811648 | P88: =M88+N88+O88 -> 39618.588 | Q88: =COUNTIF(COMPOSICIÓN!$A:$A,A88) -> 3 | R88: PTO/Tareas
A89: PTO-0202 | C89: MOVIMIENTO DE TIERRA | D89: Perfilado manual de bases. Relleno y compactación de pozos | E89: gl | F89: 1 | G89: 0 | H89: 0 | I89: 1 | J89: =SUMIFS(COMPOSICIÓN!J$2:J$1879,COMPOSICIÓN!A$2:A$1879,A89,COMPOSICIÓN!B$2:B$1879,"MAT") -> 105000 | K89: =SUMIFS(COMPOSICIÓN!J$2:J$1879,COMPOSICIÓN!A$2:A$1879,A89,COMPOSICIÓN!B$2:B$1879,"MO")*I89 -> 8488596.7 | L89: =SUMIFS(COMPOSICIÓN!J$2:J$1879,COMPOSICIÓN!A$2:A$1879,A89,COMPOSICIÓN!B$2:B$1879,"EQ") -> 128903.95 | M89: =J89 -> 105000 | N89: =IF(F89=0,0,K89/F89) -> 8488596.7 | O89: =IF(F89=0,0,L89/F89) -> 128903.95 | P89: =M89+N89+O89 -> 8722500.6 | Q89: =COUNTIF(COMPOSICIÓN!$A:$A,A89) -> 4 | R89: PTO/Tareas
A90: PTO-0203 | C90: MOVIMIENTO DE TIERRA | D90: Excavación manual para vigas de fundación | E90: m3 | F90: 1 | G90: 0 | H90: 0 | I90: 1 | J90: =SUMIFS(COMPOSICIÓN!J$2:J$1879,COMPOSICIÓN!A$2:A$1879,A90,COMPOSICIÓN!B$2:B$1879,"MAT") -> 26000 | K90: =SUMIFS(COMPOSICIÓN!J$2:J$1879,COMPOSICIÓN!A$2:A$1879,A90,COMPOSICIÓN!B$2:B$1879,"MO")*I90 -> 60860.581 | L90: =SUMIFS(COMPOSICIÓN!J$2:J$1879,COMPOSICIÓN!A$2:A$1879,A90,COMPOSICIÓN!B$2:B$1879,"EQ") -> 1302.9087 | M90: =J90 -> 26000 | N90: =IF(F90=0,0,K90/F90) -> 60860.581 | O90: =IF(F90=0,0,L90/F90) -> 1302.9087 | P90: =M90+N90+O90 -> 88163.489 | Q90: =COUNTIF(COMPOSICIÓN!$A:$A,A90) -> 3 | R90: PTO/lump
... A113: PTO-0322 | C113: ESTRUCTURA DE HORMIGÓN ARMADO | D113: Picado de medianeras para columnas y vigas - Cotizado para PB y 1P | E113: m2 | F113: 1 | G113: 0 | H113: 0 | I113: 1 | J113: =SUMIFS(COMPOSICIÓN!J$2:J$1879,COMPOSICIÓN!A$2:A$1879,A113,COMPOSICIÓN!B$2:B$1879,"MAT") -> 7051.2821 | K113: =SUMIFS(COMPOSICIÓN!J$2:J$1879,COMPOSICIÓN!A$2:A$1879,A113,COMPOSICIÓN!B$2:B$1879,"MO")*I113 -> 17829.919 | L113: =SUMIFS(COMPOSICIÓN!J$2:J$1879,COMPOSICIÓN!A$2:A$1879,A113,COMPOSICIÓN!B$2:B$1879,"EQ") -> 373.21802 | M113: =J113 -> 7051.2821 | N113: =IF(F113=0,0,K113/F113) -> 17829.919 | O113: =IF(F113=0,0,L113/F113) -> 373.21802 | P113: =M113+N113+O113 -> 25254.419 | Q113: =COUNTIF(COMPOSICIÓN!$A:$A,A113) -> 5 | R113: PTO/Tareas
A114: PTO-0401 | B114: 34 | C114: MAMPOSTERÍA | D114: Muro tipo 1 - Ladrillo hueco 8 x 18 x 33 | E114: m2 | F114: 15 | G114: 0 | H114: 0 | I114: 1 | J114: =SUMIFS(COMPOSICIÓN!J$2:J$1879,COMPOSICIÓN!A$2:A$1879,A114,COMPOSICIÓN!B$2:B$1879,"MAT") -> 6523.8011 | K114: =SUMIFS(COMPOSICIÓN!J$2:J$1879,COMPOSICIÓN!A$2:A$1879,A114,COMPOSICIÓN!B$2:B$1879,"MO")*I114 -> 146787.68 | L114: =SUMIFS(COMPOSICIÓN!J$2:J$1879,COMPOSICIÓN!A$2:A$1879,A114,COMPOSICIÓN!B$2:B$1879,"EQ") -> 3529.9787 | M114: =J114 -> 6523.8011 | N114: =IF(F114=0,0,K114/F114) -> 9785.8452 | O114: =IF(F114=0,0,L114/F114) -> 235.33191 | P114: =M114+N114+O114 -> 16544.978 | Q114: =COUNTIF(COMPOSICIÓN!$A:$A,A114) -> 10 | R114: PTO/APU P-34
A115: PTO-0402 | B115: 35 | C115: MAMPOSTERÍA | D115: Muro tipo 2 - Ladrillo hueco 12 x 18 x 33 | E115: m2 | F115: 15 | G115: 0 | H115: 0 | I115: 1 | J115: =SUMIFS(COMPOSICIÓN!J$2:J$1879,COMPOSICIÓN!A$2:A$1879,A115,COMPOSICIÓN!B$2:B$1879,"MAT") -> 8314.4981 | K115: =SUMIFS(COMPOSICIÓN!J$2:J$1879,COMPOSICIÓN!A$2:A$1879,A115,COMPOSICIÓN!B$2:B$1879,"MO")*I115 -> 146787.68 | L115: =SUMIFS(COMPOSICIÓN!J$2:J$1879,COMPOSICIÓN!A$2:A$1879,A115,COMPOSICIÓN!B$2:B$1879,"EQ") -> 3529.9787 | M115: =J115 -> 8314.4981 | N115: =IF(F115=0,0,K115/F115) -> 9785.8452 | O115: =IF(F115=0,0,L115/F115) -> 235.33191 | P115: =M115+N115+O115 -> 18335.675 | Q115: =COUNTIF(COMPOSICIÓN!$A:$A,A115) -> 10 | R115: PTO/APU P-35
A116: PTO-0403 | B116: 33 | C116: MAMPOSTERÍA | D116: Muro tipo 3 - Ladrillo comun en panderete | E116: m2 | F116: 7 | G116: 0 | H116: 0 | I116: 1 | J116: =SUMIFS(COMPOSICIÓN!J$2:J$1879,COMPOSICIÓN!A$2:A$1879,A116,COMPOSICIÓN!B$2:B$1879,"MAT") -> 6454.6901 | K116: =SUMIFS(COMPOSICIÓN!J$2:J$1879,COMPOSICIÓN!A$2:A$1879,A116,COMPOSICIÓN!B$2:B$1879,"MO")*I116 -> 73393.839 | L116: =SUMIFS(COMPOSICIÓN!J$2:J$1879,COMPOSICIÓN!A$2:A$1879,A116,COMPOSICIÓN!B$2:B$1879,"EQ") -> 3529.9787 | M116: =J116 -> 6454.6901 | N116: =IF(F116=0,0,K116/F116) -> 10484.834 | O116: =IF(F116=0,0,L116/F116) -> 504.28267 | P116: =M116+N116+O116 -> 17443.807 | Q116: =COUNTIF(COMPOSICIÓN!$A:$A,A116) -> 11 | R116: PTO/APU P-33 MAT÷2 MO÷2 EQ÷1
A117: PTO-0404 | B117: 38 | C117: MAMPOSTERÍA | D117: Muro tipo 4 - Ladrillo hueco portante 12 x 18 x 33 | E117: m2 | F117: 15 | G117: 0 | H117: 0 | I117: 1 | J117: =SUMIFS(COMPOSICIÓN!J$2:J$1879,COMPOSICIÓN!A$2:A$1879,A117,COMPOSICIÓN!B$2:B$1879,"MAT") -> 11430.163 | K117: =SUMIFS(COMPOSICIÓN!J$2:J$1879,COMPOSICIÓN!A$2:A$1879,A117,COMPOSICIÓN!B$2:B$1879,"MO")*I117 -> 146787.68 | L117: =SUMIFS(COMPOSICIÓN!J$2:J$1879,COMPOSICIÓN!A$2:A$1879,A117,COMPOSICIÓN!B$2:B$1879,"EQ") -> 3529.9787 | M117: =J117 -> 11430.163 | N117: =IF(F117=0,0,K117/F117) -> 9785.8452 | O117: =IF(F117=0,0,L117/F117) -> 235.33191 | P117: =M117+N117+O117 -> 21451.34 | Q117: =COUNTIF(COMPOSICIÓN!$A:$A,A117) -> 10 | R117: PTO/APU P-38
A118: PTO-0405 | C118: MAMPOSTERÍA | D118: Muro tipo 5 - Bloque HCCA e: 7,5 cm | E118: m2 | F118: 1 | G118: 0 | H118: 0 | I118: 1 | J118: =SUMIFS(COMPOSICIÓN!J$2:J$1879,COMPOSICIÓN!A$2:A$1879,A118,COMPOSICIÓN!B$2:B$1879,"MAT") -> 16817.941 | K118: =SUMIFS(COMPOSICIÓN!J$2:J$1879,COMPOSICIÓN!A$2:A$1879,A118,COMPOSICIÓN!B$2:B$1879,"MO")*I118 -> 10484.834 | L118: =SUMIFS(COMPOSICIÓN!J$2:J$1879,COMPOSICIÓN!A$2:A$1879,A118,COMPOSICIÓN!B$2:B$1879,"EQ") -> 409.54162 | M118: =J118 -> 16817.941 | N118: =IF(F118=0,0,K118/F118) -> 10484.834 | O118: =IF(F118=0,0,L118/F118) -> 409.54162 | P118: =M118+N118+O118 -> 27712.316 | Q118: =COUNTIF(COMPOSICIÓN!$A:$A,A118) -> 7 | R118: PTO/Tareas
A119: PTO-0406 | B119: 36 | C119: MAMPOSTERÍA | D119: Muro tipo 6 - Ladrillo hueco 18 x 18 x 33 | E119: m2 | F119: 15 | G119: 0 | H119: 0 | I119: 1 | J119: =SUMIFS(COMPOSICIÓN!J$2:J$1879,COMPOSICIÓN!A$2:A$1879,A119,COMPOSICIÓN!B$2:B$1879,"MAT") -> 11375.275 | K119: =SUMIFS(COMPOSICIÓN!J$2:J$1879,COMPOSICIÓN!A$2:A$1879,A119,COMPOSICIÓN!B$2:B$1879,"MO")*I119 -> 146787.68 | L119: =SUMIFS(COMPOSICIÓN!J$2:J$1879,COMPOSICIÓN!A$2:A$1879,A119,COMPOSICIÓN!B$2:B$1879,"EQ") -> 3529.9787 | M119: =J119 -> 11375.275 | N119: =IF(F119=0,0,K119/F119) -> 9785.8452 | O119: =IF(F119=0,0,L119/F119) -> 235.33191 | P119: =M119+N119+O119 -> 21396.452 | Q119: =COUNTIF(COMPOSICIÓN!$A:$A,A119) -> 10 | R119: PTO/APU P-36
A120: PTO-0407 | B120: 33 | C120: MAMPOSTERÍA | D120: Enchape de medianeras existentes - Contemplamos picado zonas sueltas y enchape con ladrillo comun para PB | E120: m2 | F120: 7 | G120: 0 | H120: 0 | I120: 1 | J120: =SUMIFS(COMPOSICIÓN!J$2:J$1879,COMPOSICIÓN!A$2:A$1879,A120,COMPOSICIÓN!B$2:B$1879,"MAT") -> 3227.3451 | K120: =SUMIFS(COMPOSICIÓN!J$2:J$1879,COMPOSICIÓN!A$2:A$1879,A120,COMPOSICIÓN!B$2:B$1879,"MO")*I120 -> 73393.839 | L120: =SUMIFS(COMPOSICIÓN!J$2:J$1879,COMPOSICIÓN!A$2:A$1879,A120,COMPOSICIÓN!B$2:B$1879,"EQ") -> 1764.9893 | M120: =J120 -> 3227.3451 | N120: =IF(F120=0,0,K120/F120) -> 10484.834 | O120: =IF(F120=0,0,L120/F120) -> 252.14133 | P120: =M120+N120+O120 -> 13964.321 | Q120: =COUNTIF(COMPOSICIÓN!$A:$A,A120) -> 11 | R120: PTO/APU P-33 MAT÷4 MO÷2 EQ÷2
A121: PTO-0408 | C121: MAMPOSTERÍA | D121: Cordón de hormigón en umbrales carpinterías | E121: ml | F121: 1 | G121: 0 | H121: 0 | I121: 1 | J121: =SUMIFS(COMPOSICIÓN!J$2:J$1879,COMPOSICIÓN!A$2:A$1879,A121,COMPOSICIÓN!B$2:B$1879,"MAT") -> 9093.9863 | K121: =SUMIFS(COMPOSICIÓN!J$2:J$1879,COMPOSICIÓN!A$2:A$1879,A121,COMPOSICIÓN!B$2:B$1879,"MO")*I121 -> 12031.777 | L121: =SUMIFS(COMPOSICIÓN!J$2:J$1879,COMPOSICIÓN!A$2:A$1879,A121,COMPOSICIÓN!B$2:B$1879,"EQ") -> 316.88645 | M121: =J121 -> 9093.9863 | N121: =IF(F121=0,0,K121/F121) -> 12031.777 | O121: =IF(F121=0,0,L121/F121) -> 316.88645 | P121: =M121+N121+O121 -> 21442.65 | Q121: =COUNTIF(COMPOSICIÓN!$A:$A,A121) -> 7 | R121: PTO/Tareas
A122: PTO-0409 | C122: MAMPOSTERÍA | D122: Banquina Sala tanque de bombeo | E122: gl | F122: 1 | G122: 0 | H122: 0 | I122: 1 | J122: =SUMIFS(COMPOSICIÓN!J$2:J$1879,COMPOSICIÓN!A$2:A$1879,A122,COMPOSICIÓN!B$2:B$1879,"MAT") -> 60811.031 | K122: =SUMIFS(COMPOSICIÓN!J$2:J$1879,COMPOSICIÓN!A$2:A$1879,A122,COMPOSICIÓN!B$2:B$1879,"MO")*I122 -> 146787.68 | L122: =SUMIFS(COMPOSICIÓN!J$2:J$1879,COMPOSICIÓN!A$2:A$1879,A122,COMPOSICIÓN!B$2:B$1879,"EQ") -> 3113.9806 | M122: =J122 -> 60811.031 | N122: =IF(F122=0,0,K122/F122) -> 146787.68 | O122: =IF(F122=0,0,L122/F122) -> 3113.9806 | P122: =M122+N122+O122 -> 210712.69 | Q122: =COUNTIF(COMPOSICIÓN!$A:$A,A122) -> 6 | R122: PTO/Tareas
A123: PTO-0410 | C123: MAMPOSTERÍA | D123: Banquina en parrillas | E123: gl | F123: 1 | G123: 0 | H123: 0 | I123: 1 | J123: =SUMIFS(COMPOSICIÓN!J$2:J$1879,COMPOSICIÓN!A$2:A$1879,A123,COMPOSICIÓN!B$2:B$1879,"MAT") -> 151935.62 | K123: =SUMIFS(COMPOSICIÓN!J$2:J$1879,COMPOSICIÓN!A$2:A$1879,A123,COMPOSICIÓN!B$2:B$1879,"MO")*I123 -> 440363.03 | L123: =SUMIFS(COMPOSICIÓN!J$2:J$1879,COMPOSICIÓN!A$2:A$1879,A123,COMPOSICIÓN!B$2:B$1879,"EQ") -> 8884.4798 | M123: =J123 -> 151935.62 | N123: =IF(F123=0,0,K123/F123) -> 440363.03 | O123: =IF(F123=0,0,L123/F123) -> 8884.4798 | P123: =M123+N123+O123 -> 601183.14 | Q123: =COUNTIF(COMPOSICIÓN!$A:$A,A123) -> 6 | R123: PTO/Tareas
A124: PTO-0411 | C124: MAMPOSTERÍA | D124: Excavación y amurado con Hº tanque de recuperación de agua de lluvia | E124: gl | F124: 1 | G124: 0 | H124: 0 | I124: 1 | J124: =SUMIFS(COMPOSICIÓN!J$2:J$1879,COMPOSICIÓN!A$2:A$1879,A124,COMPOSICIÓN!B$2:B$1879,"MAT") -> 128742.89 | K124: =SUMIFS(COMPOSICIÓN!J$2:J$1879,COMPOSICIÓN!A$2:A$1879,A124,COMPOSICIÓN!B$2:B$1879,"MO")*I124 -> 259536.82 | L124: =SUMIFS(COMPOSICIÓN!J$2:J$1879,COMPOSICIÓN!A$2:A$1879,A124,COMPOSICIÓN!B$2:B$1879,"EQ") -> 5824.1958 | M124: =J124 -> 128742.89 | N124: =IF(F124=0,0,K124/F124) -> 259536.82 | O124: =IF(F124=0,0,L124/F124) -> 5824.1958 | P124: =M124+N124+O124 -> 394103.91 | Q124: =COUNTIF(COMPOSICIÓN!$A:$A,A124) -> 5 | R124: PTO/Tareas
A125: PTO-0412 | C125: MAMPOSTERÍA | D125: Provisión y amurado de tapas de inspección para tanque de reserva | E125: u | F125: 1 | G125: 0 | H125: 0 | I125: 1 | J125: =SUMIFS(COMPOSICIÓN!J$2:J$1879,COMPOSICIÓN!A$2:A$1879,A125,COMPOSICIÓN!B$2:B$1879,"MAT") -> 121487.6 | K125: =SUMIFS(COMPOSICIÓN!J$2:J$1879,COMPOSICIÓN!A$2:A$1879,A125,COMPOSICIÓN!B$2:B$1879,"MO")*I125 -> 54294.059 | L125: =SUMIFS(COMPOSICIÓN!J$2:J$1879,COMPOSICIÓN!A$2:A$1879,A125,COMPOSICIÓN!B$2:B$1879,"EQ") -> 2636.7249 | M125: =J125 -> 121487.6 | N125: =IF(F125=0,0,K125/F125) -> 54294.059 | O125: =IF(F125=0,0,L125/F125) -> 2636.7249 | P125: =M125+N125+O125 -> 178418.39 | Q125: =COUNTIF(COMPOSICIÓN!$A:$A,A125) -> 4 | R125: PTO/Tareas
A126: PTO-0413 | C126: MAMPOSTERÍA | D126: Vigas de encadenado - Cuantía aprox. 60 kg/m3 | E126: ml | F126: 1 | G126: 0 | H126: 0 | I126: 1 | J126: =SUMIFS(COMPOSICIÓN!J$2:J$1879,COMPOSICIÓN!A$2:A$1879,A126,COMPOSICIÓN!B$2:B$1879,"MAT") -> 36748.882 | K126: =SUMIFS(COMPOSICIÓN!J$2:J$1879,COMPOSICIÓN!A$2:A$1879,A126,COMPOSICIÓN!B$2:B$1879,"MO")*I126 -> 35716.756 | L126: =SUMIFS(COMPOSICIÓN!J$2:J$1879,COMPOSICIÓN!A$2:A$1879,A126,COMPOSICIÓN!B$2:B$1879,"EQ") -> 1086.9846 | M126: =J126 -> 36748.882 | N126: =IF(F126=0,0,K126/F126) -> 35716.756 | O126: =IF(F126=0,0,L126/F126) -> 1086.9846 | P126: =M126+N126+O126 -> 73552.623 | Q126: =COUNTIF(COMPOSICIÓN!$A:$A,A126) -> 8 | R126: PTO/Tareas
A127: PTO-0414 | C127: MAMPOSTERÍA | D127: Amurado de bañera | E127: u | F127: 1 | G127: 0 | H127: 0 | I127: 1 | J127: =SUMIFS(COMPOSICIÓN!J$2:J$1879,COMPOSICIÓN!A$2:A$1879,A127,COMPOSICIÓN!B$2:B$1879,"MAT") -> 23946.262 | K127: =SUMIFS(COMPOSICIÓN!J$2:J$1879,COMPOSICIÓN!A$2:A$1879,A127,COMPOSICIÓN!B$2:B$1879,"MO")*I127 -> 107385.37 | L127: =SUMIFS(COMPOSICIÓN!J$2:J$1879,COMPOSICIÓN!A$2:A$1879,A127,COMPOSICIÓN!B$2:B$1879,"EQ") -> 1969.9745 | M127: =J127 -> 23946.262 | N127: =IF(F127=0,0,K127/F127) -> 107385.37 | O127: =IF(F127=0,0,L127/F127) -> 1969.9745 | P127: =M127+N127+O127 -> 133301.61 | Q127: =COUNTIF(COMPOSICIÓN!$A:$A,A127) -> 7 | R127: PTO/Tareas
A128: PTO-0501 | B128: 42 | C128: IMPERMEABILIZACIONES Y AISLACIONES | D128: Cajón hidrofugo | E128: ml | F128: 28 | G128: 0 | H128: 0 | I128: 1 | J128: =SUMIFS(COMPOSICIÓN!J$2:J$1879,COMPOSICIÓN!A$2:A$1879,A128,COMPOSICIÓN!B$2:B$1879,"MAT") -> 809.61503 | K128: =SUMIFS(COMPOSICIÓN!J$2:J$1879,COMPOSICIÓN!A$2:A$1879,A128,COMPOSICIÓN!B$2:B$1879,"MO")*I128 -> 110271.33 | L128: =SUMIFS(COMPOSICIÓN!J$2:J$1879,COMPOSICIÓN!A$2:A$1879,A128,COMPOSICIÓN!B$2:B$1879,"EQ") -> 3529.9787 | M128: =J128 -> 809.61503 | N128: =IF(F128=0,0,K128/F128) -> 3938.2618 | O128: =IF(F128=0,0,L128/F128) -> 126.07067 | P128: =M128+N128+O128 -> 4873.9475 | Q128: =COUNTIF(COMPOSICIÓN!$A:$A,A128) -> 8 | R128: PTO/APU P-42
A129: PTO-0502 | B129: 70 | C129: IMPERMEABILIZACIONES Y AISLACIONES | D129: Aislación hidrófuga horizontal (baños) - Inc. membrana geotextil y 35% en concepto de babetas | E129: m2 | F129: 25 | G129: 0 | H129: 0 | I129: 1 | J129: =SUMIFS(COMPOSICIÓN!J$2:J$1879,COMPOSICIÓN!A$2:A$1879,A129,COMPOSICIÓN!B$2:B$1879,"MAT") -> 13188.358 | K129: =SUMIFS(COMPOSICIÓN!J$2:J$1879,COMPOSICIÓN!A$2:A$1879,A129,COMPOSICIÓN!B$2:B$1879,"MO")*I129 -> 293575.36 | L129: =SUMIFS(COMPOSICIÓN!J$2:J$1879,COMPOSICIÓN!A$2:A$1879,A129,COMPOSICIÓN!B$2:B$1879,"EQ") -> 804.50569 | M129: =J129 -> 13188.358 | N129: =IF(F129=0,0,K129/F129) -> 11743.014 | O129: =IF(F129=0,0,L129/F129) -> 32.180227 | P129: =M129+N129+O129 -> 24963.552 | Q129: =COUNTIF(COMPOSICIÓN!$A:$A,A129) -> 13 | R129: PTO/APU P-70 + lump MAT(35%) MO(100%)
A130: PTO-0503 | B130: 42 | C130: IMPERMEABILIZACIONES Y AISLACIONES | D130: Azotado hidrófugo - Contrapiso de PB | E130: m2 | F130: 28 | G130: 0 | H130: 0 | I130: 1 | J130: =SUMIFS(COMPOSICIÓN!J$2:J$1879,COMPOSICIÓN!A$2:A$1879,A130,COMPOSICIÓN!B$2:B$1879,"MAT") -> 809.61503 | K130: =SUMIFS(COMPOSICIÓN!J$2:J$1879,COMPOSICIÓN!A$2:A$1879,A130,COMPOSICIÓN!B$2:B$1879,"MO")*I130 -> 110271.33 | L130: =SUMIFS(COMPOSICIÓN!J$2:J$1879,COMPOSICIÓN!A$2:A$1879,A130,COMPOSICIÓN!B$2:B$1879,"EQ") -> 3529.9787 | M130: =J130 -> 809.61503 | N130: =IF(F130=0,0,K130/F130) -> 3938.2618 | O130: =IF(F130=0,0,L130/F130) -> 126.07067 | P130: =M130+N130+O130 -> 4873.9475 | Q130: =COUNTIF(COMPOSICIÓN!$A:$A,A130) -> 8 | R130: PTO/APU P-42
A131: PTO-0504 | C131: IMPERMEABILIZACIONES Y AISLACIONES | D131: Aislación térmica en terrazas, eps e:2,00 cm | E131: m2 | F131: 1 | G131: 0 | H131: 0 | I131: 1 | J131: =SUMIFS(COMPOSICIÓN!J$2:J$1879,COMPOSICIÓN!A$2:A$1879,A131,COMPOSICIÓN!B$2:B$1879,"MAT") -> 3625.4 | K131: =SUMIFS(COMPOSICIÓN!J$2:J$1879,COMPOSICIÓN!A$2:A$1879,A131,COMPOSICIÓN!B$2:B$1879,"MO")*I131 -> 0 | L131: =SUMIFS(COMPOSICIÓN!J$2:J$1879,COMPOSICIÓN!A$2:A$1879,A131,COMPOSICIÓN!B$2:B$1879,"EQ") -> 0 | M131: =J131 -> 3625.4 | N131: =IF(F131=0,0,K131/F131) -> 0 | O131: =IF(F131=0,0,L131/F131) -> 0 | P131: =M131+N131+O131 -> 3625.4 | Q131: =COUNTIF(COMPOSICIÓN!$A:$A,A131) -> 1 | R131: PTO/Cotizaciones
A132: PTO-0505 | B132: 113 | C132: IMPERMEABILIZACIONES Y AISLACIONES | D132: Barrera de vapor | E132: m2 | F132: 80 | G132: 0 | H132: 0 | I132: 1 | J132: =SUMIFS(COMPOSICIÓN!J$2:J$1879,COMPOSICIÓN!A$2:A$1879,A132,COMPOSICIÓN!B$2:B$1879,"MAT") -> 1256.6125 | K132: =SUMIFS(COMPOSICIÓN!J$2:J$1879,COMPOSICIÓN!A$2:A$1879,A132,COMPOSICIÓN!B$2:B$1879,"MO")*I132 -> 137815.66 | L132: =SUMIFS(COMPOSICIÓN!J$2:J$1879,COMPOSICIÓN!A$2:A$1879,A132,COMPOSICIÓN!B$2:B$1879,"EQ") -> 804.50569 | M132: =J132 -> 1256.6125 | N132: =IF(F132=0,0,K132/F132) -> 1722.6958 | O132: =IF(F132=0,0,L132/F132) -> 10.056321 | P132: =M132+N132+O132 -> 2989.3646 | Q132: =COUNTIF(COMPOSICIÓN!$A:$A,A132) -> 8 | R132: PTO/APU P-113
A133: PTO-0506 | B133: 70 | C133: IMPERMEABILIZACIONES Y AISLACIONES | D133: Membrana asfáltica geotextil 4mm - Balcones y azotea - Inc. 20% en concepto de babetas | E133: m2 | F133: 25 | G133: 0 | H133: 0 | I133: 1 | J133: =SUMIFS(COMPOSICIÓN!J$2:J$1879,COMPOSICIÓN!A$2:A$1879,A133,COMPOSICIÓN!B$2:B$1879,"MAT") -> 11722.985 | K133: =SUMIFS(COMPOSICIÓN!J$2:J$1879,COMPOSICIÓN!A$2:A$1879,A133,COMPOSICIÓN!B$2:B$1879,"MO")*I133 -> 234860.28 | L133: =SUMIFS(COMPOSICIÓN!J$2:J$1879,COMPOSICIÓN!A$2:A$1879,A133,COMPOSICIÓN!B$2:B$1879,"EQ") -> 804.50569 | M133: =J133 -> 11722.985 | N133: =IF(F133=0,0,K133/F133) -> 9394.4114 | O133: =IF(F133=0,0,L133/F133) -> 32.180227 | P133: =M133+N133+O133 -> 21149.576 | Q133: =COUNTIF(COMPOSICIÓN!$A:$A,A133) -> 13 | R133: PTO/APU P-70 + lump MAT(20%) MO(60%)
A134: PTO-0507 | C134: IMPERMEABILIZACIONES Y AISLACIONES | D134: Impermeabilización de tanque de reserva de HºAº | E134: gl | F134: 1 | G134: 0 | H134: 0 | I134: 1 | J134: =SUMIFS(COMPOSICIÓN!J$2:J$1879,COMPOSICIÓN!A$2:A$1879,A134,COMPOSICIÓN!B$2:B$1879,"MAT") -> 0 | K134: =SUMIFS(COMPOSICIÓN!J$2:J$1879,COMPOSICIÓN!A$2:A$1879,A134,COMPOSICIÓN!B$2:B$1879,"MO")*I134 -> 1829911.6 | L134: =SUMIFS(COMPOSICIÓN!J$2:J$1879,COMPOSICIÓN!A$2:A$1879,A134,COMPOSICIÓN!B$2:B$1879,"EQ") -> 0 | M134: =J134 -> 0 | N134: =IF(F134=0,0,K134/F134) -> 1829911.6 | O134: =IF(F134=0,0,L134/F134) -> 0 | P134: =M134+N134+O134 -> 1829911.6 | Q134: =COUNTIF(COMPOSICIÓN!$A:$A,A134) -> 1 | R134: PTO/aux
A135: PTO-0602 | C135: CUBIERTAS | D135: Babeta de chapa galvanizada en medianeras | E135: ml | F135: 1 | G135: 0 | H135: 0 | I135: 1 | J135: =SUMIFS(COMPOSICIÓN!J$2:J$1879,COMPOSICIÓN!A$2:A$1879,A135,COMPOSICIÓN!B$2:B$1879,"MAT") -> 14897.521 | K135: =SUMIFS(COMPOSICIÓN!J$2:J$1879,COMPOSICIÓN!A$2:A$1879,A135,COMPOSICIÓN!B$2:B$1879,"MO")*I135 -> 8259.2819 | L135: =SUMIFS(COMPOSICIÓN!J$2:J$1879,COMPOSICIÓN!A$2:A$1879,A135,COMPOSICIÓN!B$2:B$1879,"EQ") -> 347.35204 | M135: =J135 -> 14897.521 | N135: =IF(F135=0,0,K135/F135) -> 8259.2819 | O135: =IF(F135=0,0,L135/F135) -> 347.35204 | P135: =M135+N135+O135 -> 23504.155 | Q135: =COUNTIF(COMPOSICIÓN!$A:$A,A135) -> 6 | R135: PTO/Tareas
A136: PTO-0701 | B136: 44 | C136: REVOQUES | D136: Revoque Grueso Impermeable Exterior | E136: m2 | F136: 11.5 | G136: 0 | H136: 0 | I136: 1 | J136: =SUMIFS(COMPOSICIÓN!J$2:J$1879,COMPOSICIÓN!A$2:A$1879,A136,COMPOSICIÓN!B$2:B$1879,"MAT") -> 4009.2266 | K136: =SUMIFS(COMPOSICIÓN!J$2:J$1879,COMPOSICIÓN!A$2:A$1879,A136,COMPOSICIÓN!B$2:B$1879,"MO")*I136 -> 122443.45 | L136: =SUMIFS(COMPOSICIÓN!J$2:J$1879,COMPOSICIÓN!A$2:A$1879,A136,COMPOSICIÓN!B$2:B$1879,"EQ") -> 3529.9787 | M136: =J136 -> 4009.2266 | N136: =IF(F136=0,0,K136/F136) -> 10647.256 | O136: =IF(F136=0,0,L136/F136) -> 306.95467 | P136: =M136+N136+O136 -> 14963.437 | Q136: =COUNTIF(COMPOSICIÓN!$A:$A,A136) -> 9 | R136: PTO/APU P-44
A137: PTO-0702 | B137: 45 | C137: REVOQUES | D137: Revoque Grueso Impermeable Exterior a mas de 3m - Medianero y fachadas | E137: m2 | F137: 8 | G137: 0 | H137: 0 | I137: 1 | J137: =SUMIFS(COMPOSICIÓN!J$2:J$1879,COMPOSICIÓN!A$2:A$1879,A137,COMPOSICIÓN!B$2:B$1879,"MAT") -> 4009.2266 | K137: =SUMIFS(COMPOSICIÓN!J$2:J$1879,COMPOSICIÓN!A$2:A$1879,A137,COMPOSICIÓN!B$2:B$1879,"MO")*I137 -> 122443.45 | L137: =SUMIFS(COMPOSICIÓN!J$2:J$1879,COMPOSICIÓN!A$2:A$1879,A137,COMPOSICIÓN!B$2:B$1879,"EQ") -> 6154.5221 | M137: =J137 -> 4009.2266 | N137: =IF(F137=0,0,K137/F137) -> 15305.431 | O137: =IF(F137=0,0,L137/F137) -> 769.31526 | P137: =M137+N137+O137 -> 20083.973 | Q137: =COUNTIF(COMPOSICIÓN!$A:$A,A137) -> 9 | R137: PTO/APU P-45
A138: PTO-0703 | C138: REVOQUES | D138: Yeso interior | E138: m2 | F138: 1 | G138: 0 | H138: 0 | I138: 1 | J138: =SUMIFS(COMPOSICIÓN!J$2:J$1879,COMPOSICIÓN!A$2:A$1879,A138,COMPOSICIÓN!B$2:B$1879,"MAT") -> 5324.1715 | K138: =SUMIFS(COMPOSICIÓN!J$2:J$1879,COMPOSICIÓN!A$2:A$1879,A138,COMPOSICIÓN!B$2:B$1879,"MO")*I138 -> 11651.218 | L138: =SUMIFS(COMPOSICIÓN!J$2:J$1879,COMPOSICIÓN!A$2:A$1879,A138,COMPOSICIÓN!B$2:B$1879,"EQ") -> 254.63085 | M138: =J138 -> 5324.1715 | N138: =IF(F138=0,0,K138/F138) -> 11651.218 | O138: =IF(F138=0,0,L138/F138) -> 254.63085 | P138: =M138+N138+O138 -> 17230.021 | Q138: =COUNTIF(COMPOSICIÓN!$A:$A,A138) -> 5 | R138: PTO/Tareas
A139: PTO-0704 | C139: REVOQUES | D139: Arista en yeso | E139: ml | F139: 1 | G139: 0 | H139: 0 | I139: 1 | J139: =SUMIFS(COMPOSICIÓN!J$2:J$1879,COMPOSICIÓN!A$2:A$1879,A139,COMPOSICIÓN!B$2:B$1879,"MAT") -> 0 | K139: =SUMIFS(COMPOSICIÓN!J$2:J$1879,COMPOSICIÓN!A$2:A$1879,A139,COMPOSICIÓN!B$2:B$1879,"MO")*I139 -> 12499.473 | L139: =SUMIFS(COMPOSICIÓN!J$2:J$1879,COMPOSICIÓN!A$2:A$1879,A139,COMPOSICIÓN!B$2:B$1879,"EQ") -> 187.4921 | M139: =J139 -> 0 | N139: =IF(F139=0,0,K139/F139) -> 12499.473 | O139: =IF(F139=0,0,L139/F139) -> 187.4921 | P139: =M139+N139+O139 -> 12686.965 | Q139: =COUNTIF(COMPOSICIÓN!$A:$A,A139) -> 2 | R139: PTO/Tareas
A140: PTO-0705 | C140: REVOQUES | D140: Provisión y colocación de guardacanto yesero | E140: un | F140: 1 | G140: 0 | H140: 0 | I140: 1 | J140: =SUMIFS(COMPOSICIÓN!J$2:J$1879,COMPOSICIÓN!A$2:A$1879,A140,COMPOSICIÓN!B$2:B$1879,"MAT") -> 1167.2736 | K140: =SUMIFS(COMPOSICIÓN!J$2:J$1879,COMPOSICIÓN!A$2:A$1879,A140,COMPOSICIÓN!B$2:B$1879,"MO")*I140 -> 13162.324 | L140: =SUMIFS(COMPOSICIÓN!J$2:J$1879,COMPOSICIÓN!A$2:A$1879,A140,COMPOSICIÓN!B$2:B$1879,"EQ") -> 214.94396 | M140: =J140 -> 1167.2736 | N140: =IF(F140=0,0,K140/F140) -> 13162.324 | O140: =IF(F140=0,0,L140/F140) -> 214.94396 | P140: =M140+N140+O140 -> 14544.542 | Q140: =COUNTIF(COMPOSICIÓN!$A:$A,A140) -> 3 | R140: PTO/Tareas
A141: PTO-0706 | B141: 44 | C141: REVOQUES | D141: Revoque Grueso Impermeable Interior b/ revestimiento | E141: m2 | F141: 11.5 | G141: 0 | H141: 0 | I141: 1 | J141: =SUMIFS(COMPOSICIÓN!J$2:J$1879,COMPOSICIÓN!A$2:A$1879,A141,COMPOSICIÓN!B$2:B$1879,"MAT") -> 4009.2266 | K141: =SUMIFS(COMPOSICIÓN!J$2:J$1879,COMPOSICIÓN!A$2:A$1879,A141,COMPOSICIÓN!B$2:B$1879,"MO")*I141 -> 122443.45 | L141: =SUMIFS(COMPOSICIÓN!J$2:J$1879,COMPOSICIÓN!A$2:A$1879,A141,COMPOSICIÓN!B$2:B$1879,"EQ") -> 3529.9787 | M141: =J141 -> 4009.2266 | N141: =IF(F141=0,0,K141/F141) -> 10647.256 | O141: =IF(F141=0,0,L141/F141) -> 306.95467 | P141: =M141+N141+O141 -> 14963.437 | Q141: =COUNTIF(COMPOSICIÓN!$A:$A,A141) -> 9 | R141: PTO/APU P-44
A142: PTO-0801 | C142: CONTRAPISOS Y CARPETAS | D142: Contrapiso de Hº armado e: 18 cm, incluye malla Ø 6 mm y film 200 mic. | E142: m2 | F142: 1 | G142: 0 | H142: 0 | I142: 1 | J142: =SUMIFS(COMPOSICIÓN!J$2:J$1879,COMPOSICIÓN!A$2:A$1879,A142,COMPOSICIÓN!B$2:B$1879,"MAT") -> 30940.007 | K142: =SUMIFS(COMPOSICIÓN!J$2:J$1879,COMPOSICIÓN!A$2:A$1879,A142,COMPOSICIÓN!B$2:B$1879,"MO")*I142 -> 12364.893 | L142: =SUMIFS(COMPOSICIÓN!J$2:J$1879,COMPOSICIÓN!A$2:A$1879,A142,COMPOSICIÓN!B$2:B$1879,"EQ") -> 649.5735 | M142: =J142 -> 30940.007 | N142: =IF(F142=0,0,K142/F142) -> 12364.893 | O142: =IF(F142=0,0,L142/F142) -> 649.5735 | P142: =M142+N142+O142 -> 43954.474 | Q142: =COUNTIF(COMPOSICIÓN!$A:$A,A142) -> 8 | R142: PTO/Tareas
A143: PTO-0802 | C143: CONTRAPISOS Y CARPETAS | D143: Contrapiso de H13 subase bajo intertrabado y garden block | E143: m2 | F143: 1 | G143: 0 | H143: 0 | I143: 1 | J143: =SUMIFS(COMPOSICIÓN!J$2:J$1879,COMPOSICIÓN!A$2:A$1879,A143,COMPOSICIÓN!B$2:B$1879,"MAT") -> 22041.278 | K143: =SUMIFS(COMPOSICIÓN!J$2:J$1879,COMPOSICIÓN!A$2:A$1879,A143,COMPOSICIÓN!B$2:B$1879,"MO")*I143 -> 6588.4933 | L143: =SUMIFS(COMPOSICIÓN!J$2:J$1879,COMPOSICIÓN!A$2:A$1879,A143,COMPOSICIÓN!B$2:B$1879,"EQ") -> 429.44656 | M143: =J143 -> 22041.278 | N143: =IF(F143=0,0,K143/F143) -> 6588.4933 | O143: =IF(F143=0,0,L143/F143) -> 429.44656 | P143: =M143+N143+O143 -> 29059.217 | Q143: =COUNTIF(COMPOSICIÓN!$A:$A,A143) -> 12 | R143: PTO/Tareas
A144: PTO-0803 | B144: 48 | C144: CONTRAPISOS Y CARPETAS | D144: Monolítico e: 6 cm | E144: m2 | F144: 35 | G144: 0 | H144: 0 | I144: 1 | J144: =SUMIFS(COMPOSICIÓN!J$2:J$1879,COMPOSICIÓN!A$2:A$1879,A144,COMPOSICIÓN!B$2:B$1879,"MAT") -> 6968.0306 | K144: =SUMIFS(COMPOSICIÓN!J$2:J$1879,COMPOSICIÓN!A$2:A$1879,A144,COMPOSICIÓN!B$2:B$1879,"MO")*I144 -> 354435.94 | L144: =SUMIFS(COMPOSICIÓN!J$2:J$1879,COMPOSICIÓN!A$2:A$1879,A144,COMPOSICIÓN!B$2:B$1879,"EQ") -> 4201.6421 | M144: =J144 -> 6968.0306 | N144: =IF(F144=0,0,K144/F144) -> 10126.741 | O144: =IF(F144=0,0,L144/F144) -> 120.04692 | P144: =M144+N144+O144 -> 17214.819 | Q144: =COUNTIF(COMPOSICIÓN!$A:$A,A144) -> 8 | R144: PTO/APU P-48
A145: PTO-0804 | C145: CONTRAPISOS Y CARPETAS | D145: Contrapiso alivianado en azoteas (RDC), e: 15 cm | E145: m2 | F145: 1 | G145: 0 | H145: 0 | I145: 1 | J145: =SUMIFS(COMPOSICIÓN!J$2:J$1879,COMPOSICIÓN!A$2:A$1879,A145,COMPOSICIÓN!B$2:B$1879,"MAT") -> 24469.45 | K145: =SUMIFS(COMPOSICIÓN!J$2:J$1879,COMPOSICIÓN!A$2:A$1879,A145,COMPOSICIÓN!B$2:B$1879,"MO")*I145 -> 5362.3939 | L145: =SUMIFS(COMPOSICIÓN!J$2:J$1879,COMPOSICIÓN!A$2:A$1879,A145,COMPOSICIÓN!B$2:B$1879,"EQ") -> 447.47766 | M145: =J145 -> 24469.45 | N145: =IF(F145=0,0,K145/F145) -> 5362.3939 | O145: =IF(F145=0,0,L145/F145) -> 447.47766 | P145: =M145+N145+O145 -> 30279.322 | Q145: =COUNTIF(COMPOSICIÓN!$A:$A,A145) -> 9 | R145: PTO/Tareas
A146: PTO-0805 | C146: CONTRAPISOS Y CARPETAS | D146: Contrapiso con piedra binder e: 4/5 cm - En locales húmedos (baños) | E146: m2 | F146: 1 | G146: 0 | H146: 0 | I146: 1 | J146: =SUMIFS(COMPOSICIÓN!J$2:J$1879,COMPOSICIÓN!A$2:A$1879,A146,COMPOSICIÓN!B$2:B$1879,"MAT") -> 8233.9595 | K146: =SUMIFS(COMPOSICIÓN!J$2:J$1879,COMPOSICIÓN!A$2:A$1879,A146,COMPOSICIÓN!B$2:B$1879,"MO")*I146 -> 15063.227 | L146: =SUMIFS(COMPOSICIÓN!J$2:J$1879,COMPOSICIÓN!A$2:A$1879,A146,COMPOSICIÓN!B$2:B$1879,"EQ") -> 349.45779 | M146: =J146 -> 8233.9595 | N146: =IF(F146=0,0,K146/F146) -> 15063.227 | O146: =IF(F146=0,0,L146/F146) -> 349.45779 | P146: =M146+N146+O146 -> 23646.644 | Q146: =COUNTIF(COMPOSICIÓN!$A:$A,A146) -> 6 | R146: PTO/Tareas
A147: PTO-0806 | C147: CONTRAPISOS Y CARPETAS | D147: Carpeta autonivelante e: 4/10 mm - En locales húmedos (baños) | E147: m2 | F147: 1 | G147: 0 | H147: 0 | I147: 1 | J147: =SUMIFS(COMPOSICIÓN!J$2:J$1879,COMPOSICIÓN!A$2:A$1879,A147,COMPOSICIÓN!B$2:B$1879,"MAT") -> 7390.791 | K147: =SUMIFS(COMPOSICIÓN!J$2:J$1879,COMPOSICIÓN!A$2:A$1879,A147,COMPOSICIÓN!B$2:B$1879,"MO")*I147 -> 7159.2551 | L147: =SUMIFS(COMPOSICIÓN!J$2:J$1879,COMPOSICIÓN!A$2:A$1879,A147,COMPOSICIÓN!B$2:B$1879,"EQ") -> 218.25069 | M147: =J147 -> 7390.791 | N147: =IF(F147=0,0,K147/F147) -> 7159.2551 | O147: =IF(F147=0,0,L147/F147) -> 218.25069 | P147: =M147+N147+O147 -> 14768.297 | Q147: =COUNTIF(COMPOSICIÓN!$A:$A,A147) -> 6 | R147: PTO/Tareas
A148: PTO-0807 | B148: 136 | C148: CONTRAPISOS Y CARPETAS | D148: Carpeta a la cal reforzada | E148: m2 | F148: 14.5 | G148: 0 | H148: 0 | I148: 1 | J148: =SUMIFS(COMPOSICIÓN!J$2:J$1879,COMPOSICIÓN!A$2:A$1879,A148,COMPOSICIÓN!B$2:B$1879,"MAT") -> 2717.5179 | K148: =SUMIFS(COMPOSICIÓN!J$2:J$1879,COMPOSICIÓN!A$2:A$1879,A148,COMPOSICIÓN!B$2:B$1879,"MO")*I148 -> 113314.36 | L148: =SUMIFS(COMPOSICIÓN!J$2:J$1879,COMPOSICIÓN!A$2:A$1879,A148,COMPOSICIÓN!B$2:B$1879,"EQ") -> 3244.3889 | M148: =J148 -> 2717.5179 | N148: =IF(F148=0,0,K148/F148) -> 7814.7833 | O148: =IF(F148=0,0,L148/F148) -> 223.75096 | P148: =M148+N148+O148 -> 10756.052 | Q148: =COUNTIF(COMPOSICIÓN!$A:$A,A148) -> 7 | R148: PTO/APU P-136
A149: PTO-0808 | B149: 136 | C149: CONTRAPISOS Y CARPETAS | D149: Carpeta a la cal reforzada s/membrana | E149: m2 | F149: 14.5 | G149: 0 | H149: 0 | I149: 1 | J149: =SUMIFS(COMPOSICIÓN!J$2:J$1879,COMPOSICIÓN!A$2:A$1879,A149,COMPOSICIÓN!B$2:B$1879,"MAT") -> 2717.5179 | K149: =SUMIFS(COMPOSICIÓN!J$2:J$1879,COMPOSICIÓN!A$2:A$1879,A149,COMPOSICIÓN!B$2:B$1879,"MO")*I149 -> 113314.36 | L149: =SUMIFS(COMPOSICIÓN!J$2:J$1879,COMPOSICIÓN!A$2:A$1879,A149,COMPOSICIÓN!B$2:B$1879,"EQ") -> 3244.3889 | M149: =J149 -> 2717.5179 | N149: =IF(F149=0,0,K149/F149) -> 7814.7833 | O149: =IF(F149=0,0,L149/F149) -> 223.75096 | P149: =M149+N149+O149 -> 10756.052 | Q149: =COUNTIF(COMPOSICIÓN!$A:$A,A149) -> 7 | R149: PTO/APU P-136
A150: PTO-0901 | C150: ESCALERAS | D150: Provisión y ejecución de cemento alisado arrodillado, e: 3,00 cm, en alzada y pedad | E150: gl | F150: 1 | G150: 0 | H150: 0 | I150: 1 | J150: =SUMIFS(COMPOSICIÓN!J$2:J$1879,COMPOSICIÓN!A$2:A$1879,A150,COMPOSICIÓN!B$2:B$1879,"MAT") -> 181154.98 | K150: =SUMIFS(COMPOSICIÓN!J$2:J$1879,COMPOSICIÓN!A$2:A$1879,A150,COMPOSICIÓN!B$2:B$1879,"MO")*I150 -> 1378156.6 | L150: =SUMIFS(COMPOSICIÓN!J$2:J$1879,COMPOSICIÓN!A$2:A$1879,A150,COMPOSICIÓN!B$2:B$1879,"EQ") -> 23389.674 | M150: =J150 -> 181154.98 | N150: =IF(F150=0,0,K150/F150) -> 1378156.6 | O150: =IF(F150=0,0,L150/F150) -> 23389.674 | P150: =M150+N150+O150 -> 1582701.3 | Q150: =COUNTIF(COMPOSICIÓN!$A:$A,A150) -> 4 | R150: PTO/Tareas
A151: PTO-0902 | C151: ESCALERAS | D151: Provisión nariz escalera, hierro angulo 5/8 x 1/8" | E151: un | F151: 1 | G151: 0 | H151: 0 | I151: 1 | J151: =SUMIFS(COMPOSICIÓN!J$2:J$1879,COMPOSICIÓN!A$2:A$1879,A151,COMPOSICIÓN!B$2:B$1879,"MAT") -> 2592.9773 | K151: =SUMIFS(COMPOSICIÓN!J$2:J$1879,COMPOSICIÓN!A$2:A$1879,A151,COMPOSICIÓN!B$2:B$1879,"MO")*I151 -> 18121.936 | L151: =SUMIFS(COMPOSICIÓN!J$2:J$1879,COMPOSICIÓN!A$2:A$1879,A151,COMPOSICIÓN!B$2:B$1879,"EQ") -> 310.72369 | M151: =J151 -> 2592.9773 | N151: =IF(F151=0,0,K151/F151) -> 18121.936 | O151: =IF(F151=0,0,L151/F151) -> 310.72369 | P151: =M151+N151+O151 -> 21025.637 | Q151: =COUNTIF(COMPOSICIÓN!$A:$A,A151) -> 6 | R151: PTO/Tareas
A152: PTO-0903 | C152: ESCALERAS | D152: Ejecución de zócalo rampante de concreto h: 10 cm | E152: ml | F152: 1 | G152: 0 | H152: 0 | I152: 1 | J152: =SUMIFS(COMPOSICIÓN!J$2:J$1879,COMPOSICIÓN!A$2:A$1879,A152,COMPOSICIÓN!B$2:B$1879,"MAT") -> 609.94943 | K152: =SUMIFS(COMPOSICIÓN!J$2:J$1879,COMPOSICIÓN!A$2:A$1879,A152,COMPOSICIÓN!B$2:B$1879,"MO")*I152 -> 7003.3937 | L152: =SUMIFS(COMPOSICIÓN!J$2:J$1879,COMPOSICIÓN!A$2:A$1879,A152,COMPOSICIÓN!B$2:B$1879,"EQ") -> 114.20015 | M152: =J152 -> 609.94943 | N152: =IF(F152=0,0,K152/F152) -> 7003.3937 | O152: =IF(F152=0,0,L152/F152) -> 114.20015 | P152: =M152+N152+O152 -> 7727.5433 | Q152: =COUNTIF(COMPOSICIÓN!$A:$A,A152) -> 4 | R152: PTO/Tareas
A153: PTO-1001 | C153: VENTILACIONES | D153: Montaje de conductos de ventilación de baños C27 - Provisión a cargo del comitente | E153: gl | F153: 1 | G153: 0 | H153: 0 | I153: 1 | J153: =SUMIFS(COMPOSICIÓN!J$2:J$1879,COMPOSICIÓN!A$2:A$1879,A153,COMPOSICIÓN!B$2:B$1879,"MAT") -> 200000 | K153: =SUMIFS(COMPOSICIÓN!J$2:J$1879,COMPOSICIÓN!A$2:A$1879,A153,COMPOSICIÓN!B$2:B$1879,"MO")*I153 -> 1163573.9 | L153: =SUMIFS(COMPOSICIÓN!J$2:J$1879,COMPOSICIÓN!A$2:A$1879,A153,COMPOSICIÓN!B$2:B$1879,"EQ") -> 20453.608 | M153: =J153 -> 200000 | N153: =IF(F153=0,0,K153/F153) -> 1163573.9 | O153: =IF(F153=0,0,L153/F153) -> 20453.608 | P153: =M153+N153+O153 -> 1384027.5 | Q153: =COUNTIF(COMPOSICIÓN!$A:$A,A153) -> 4 | R153: PTO/Tareas
A154: PTO-1002 | C154: VENTILACIONES | D154: Montaje de conductos de ventilación de parrillas C27 - Provisión a cargo del comitente | E154: gl | F154: 1 | G154: 0 | H154: 0 | I154: 1 | J154: =SUMIFS(COMPOSICIÓN!J$2:J$1879,COMPOSICIÓN!A$2:A$1879,A154,COMPOSICIÓN!B$2:B$1879,"MAT") -> 200000 | K154: =SUMIFS(COMPOSICIÓN!J$2:J$1879,COMPOSICIÓN!A$2:A$1879,A154,COMPOSICIÓN!B$2:B$1879,"MO")*I154 -> 698144.33 | L154: =SUMIFS(COMPOSICIÓN!J$2:J$1879,COMPOSICIÓN!A$2:A$1879,A154,COMPOSICIÓN!B$2:B$1879,"EQ") -> 13472.165 | M154: =J154 -> 200000 | N154: =IF(F154=0,0,K154/F154) -> 698144.33 | O154: =IF(F154=0,0,L154/F154) -> 13472.165 | P154: =M154+N154+O154 -> 911616.49 | Q154: =COUNTIF(COMPOSICIÓN!$A:$A,A154) -> 4 | R154: PTO/Tareas
A155: PTO-1003 | C155: VENTILACIONES | D155: Montaje de campanas de parrillas C22 - Provisión a cargo del comitente | E155: gl | F155: 1 | G155: 0 | H155: 0 | I155: 1 | J155: =SUMIFS(COMPOSICIÓN!J$2:J$1879,COMPOSICIÓN!A$2:A$1879,A155,COMPOSICIÓN!B$2:B$1879,"MAT") -> 50000 | K155: =SUMIFS(COMPOSICIÓN!J$2:J$1879,COMPOSICIÓN!A$2:A$1879,A155,COMPOSICIÓN!B$2:B$1879,"MO")*I155 -> 349072.16 | L155: =SUMIFS(COMPOSICIÓN!J$2:J$1879,COMPOSICIÓN!A$2:A$1879,A155,COMPOSICIÓN!B$2:B$1879,"EQ") -> 5986.0824 | M155: =J155 -> 50000 | N155: =IF(F155=0,0,K155/F155) -> 349072.16 | O155: =IF(F155=0,0,L155/F155) -> 5986.0824 | P155: =M155+N155+O155 -> 405058.25 | Q155: =COUNTIF(COMPOSICIÓN!$A:$A,A155) -> 4 | R155: PTO/Tareas
A156: PTO-1004 | C156: VENTILACIONES | D156: Montaje de sombreretes en chapa prepintada C25 - Provisión a cargo del comitente | E156: u | F156: 1 | G156: 0 | H156: 0 | I156: 1 | J156: =SUMIFS(COMPOSICIÓN!J$2:J$1879,COMPOSICIÓN!A$2:A$1879,A156,COMPOSICIÓN!B$2:B$1879,"MAT") -> 20000 | K156: =SUMIFS(COMPOSICIÓN!J$2:J$1879,COMPOSICIÓN!A$2:A$1879,A156,COMPOSICIÓN!B$2:B$1879,"MO")*I156 -> 23271.478 | L156: =SUMIFS(COMPOSICIÓN!J$2:J$1879,COMPOSICIÓN!A$2:A$1879,A156,COMPOSICIÓN!B$2:B$1879,"EQ") -> 649.07216 | M156: =J156 -> 20000 | N156: =IF(F156=0,0,K156/F156) -> 23271.478 | O156: =IF(F156=0,0,L156/F156) -> 649.07216 | P156: =M156+N156+O156 -> 43920.55 | Q156: =COUNTIF(COMPOSICIÓN!$A:$A,A156) -> 4 | R156: PTO/Tareas
A157: PTO-1101 | C157: PISOS | D157: Provisión y ejecución de alisado de cemento a la llana metálica, e: 6,00 cm | E157: m2 | F157: 1 | G157: 0 | H157: 0 | I157: 1 | J157: =SUMIFS(COMPOSICIÓN!J$2:J$1879,COMPOSICIÓN!A$2:A$1879,A157,COMPOSICIÓN!B$2:B$1879,"MAT") -> 0 | K157: =SUMIFS(COMPOSICIÓN!J$2:J$1879,COMPOSICIÓN!A$2:A$1879,A157,COMPOSICIÓN!B$2:B$1879,"MO")*I157 -> 0 | L157: =SUMIFS(COMPOSICIÓN!J$2:J$1879,COMPOSICIÓN!A$2:A$1879,A157,COMPOSICIÓN!B$2:B$1879,"EQ") -> 0 | M157: =J157 -> 0 | N157: =IF(F157=0,0,K157/F157) -> 0 | O157: =IF(F157=0,0,L157/F157) -> 0 | P157: =M157+N157+O157 -> 0 | Q157: =COUNTIF(COMPOSICIÓN!$A:$A,A157) -> 0 | R157: PTO/sin cotizar
A158: PTO-1102 | B158: 50 | C158: PISOS | D158: Provisión y ejecución de cemento alisado arrodillado, e: 3,00 cm | E158: m2 | F158: 11.5 | G158: 0 | H158: 0 | I158: 1 | J158: =SUMIFS(COMPOSICIÓN!J$2:J$1879,COMPOSICIÓN!A$2:A$1879,A158,COMPOSICIÓN!B$2:B$1879,"MAT") -> 4066.3296 | K158: =SUMIFS(COMPOSICIÓN!J$2:J$1879,COMPOSICIÓN!A$2:A$1879,A158,COMPOSICIÓN!B$2:B$1879,"MO")*I158 -> 116357.39 | L158: =SUMIFS(COMPOSICIÓN!J$2:J$1879,COMPOSICIÓN!A$2:A$1879,A158,COMPOSICIÓN!B$2:B$1879,"EQ") -> 3244.3889 | M158: =J158 -> 4066.3296 | N158: =IF(F158=0,0,K158/F158) -> 10118.034 | O158: =IF(F158=0,0,L158/F158) -> 282.12078 | P158: =M158+N158+O158 -> 14466.484 | Q158: =COUNTIF(COMPOSICIÓN!$A:$A,A158) -> 6 | R158: PTO/APU P-50
A159: PTO-1103 | B159: 56 | C159: PISOS | D159: Colocación de porcelanato a definir en sspacios comunes - Provisión a cargo del comitente | E159: m2 | F159: 13 | G159: 0 | H159: 0 | I159: 1 | J159: =SUMIFS(COMPOSICIÓN!J$2:J$1879,COMPOSICIÓN!A$2:A$1879,A159,COMPOSICIÓN!B$2:B$1879,"MAT") -> 3810.903 | K159: =SUMIFS(COMPOSICIÓN!J$2:J$1879,COMPOSICIÓN!A$2:A$1879,A159,COMPOSICIÓN!B$2:B$1879,"MO")*I159 -> 162882.18 | L159: =SUMIFS(COMPOSICIÓN!J$2:J$1879,COMPOSICIÓN!A$2:A$1879,A159,COMPOSICIÓN!B$2:B$1879,"EQ") -> 2935.5657 | M159: =J159 -> 3810.903 | N159: =IF(F159=0,0,K159/F159) -> 12529.398 | O159: =IF(F159=0,0,L159/F159) -> 225.81275 | P159: =M159+N159+O159 -> 16566.114 | Q159: =COUNTIF(COMPOSICIÓN!$A:$A,A159) -> 8 | R159: PTO/APU P-56
A160: PTO-1104 | C160: PISOS | D160: Colocación de pavimento intertrabado de H°, incluye provisión y colocación de cama de arena + tomado de junta - Provisión a cargo del comitente | E160: m2 | F160: 1 | G160: 0 | H160: 0 | I160: 1 | J160: =SUMIFS(COMPOSICIÓN!J$2:J$1879,COMPOSICIÓN!A$2:A$1879,A160,COMPOSICIÓN!B$2:B$1879,"MAT") -> 1303.439 | K160: =SUMIFS(COMPOSICIÓN!J$2:J$1879,COMPOSICIÓN!A$2:A$1879,A160,COMPOSICIÓN!B$2:B$1879,"MO")*I160 -> 12863.34 | L160: =SUMIFS(COMPOSICIÓN!J$2:J$1879,COMPOSICIÓN!A$2:A$1879,A160,COMPOSICIÓN!B$2:B$1879,"EQ") -> 212.50168 | M160: =J160 -> 1303.439 | N160: =IF(F160=0,0,K160/F160) -> 12863.34 | O160: =IF(F160=0,0,L160/F160) -> 212.50168 | P160: =M160+N160+O160 -> 14379.281 | Q160: =COUNTIF(COMPOSICIÓN!$A:$A,A160) -> 7 | R160: PTO/Tareas
A161: PTO-1105 | C161: PISOS | D161: Colocación de garden block, incluye provisión y colocación de cama de arena + tomado de junta - Provisión a cargo del comitente | E161: m2 | F161: 1 | G161: 0 | H161: 0 | I161: 1 | J161: =SUMIFS(COMPOSICIÓN!J$2:J$1879,COMPOSICIÓN!A$2:A$1879,A161,COMPOSICIÓN!B$2:B$1879,"MAT") -> 1303.439 | K161: =SUMIFS(COMPOSICIÓN!J$2:J$1879,COMPOSICIÓN!A$2:A$1879,A161,COMPOSICIÓN!B$2:B$1879,"MO")*I161 -> 12863.34 | L161: =SUMIFS(COMPOSICIÓN!J$2:J$1879,COMPOSICIÓN!A$2:A$1879,A161,COMPOSICIÓN!B$2:B$1879,"EQ") -> 212.50168 | M161: =J161 -> 1303.439 | N161: =IF(F161=0,0,K161/F161) -> 12863.34 | O161: =IF(F161=0,0,L161/F161) -> 212.50168 | P161: =M161+N161+O161 -> 14379.281 | Q161: =COUNTIF(COMPOSICIÓN!$A:$A,A161) -> 7 | R161: PTO/lump
A162: PTO-1106 | C162: PISOS | D162: Provisión y colocación de relleno de piedra binder | E162: m2 | F162: 1 | G162: 0 | H162: 0 | I162: 1 | J162: =SUMIFS(COMPOSICIÓN!J$2:J$1879,COMPOSICIÓN!A$2:A$1879,A162,COMPOSICIÓN!B$2:B$1879,"MAT") -> 2773.008 | K162: =SUMIFS(COMPOSICIÓN!J$2:J$1879,COMPOSICIÓN!A$2:A$1879,A162,COMPOSICIÓN!B$2:B$1879,"MO")*I162 -> 7607.5726 | L162: =SUMIFS(COMPOSICIÓN!J$2:J$1879,COMPOSICIÓN!A$2:A$1879,A162,COMPOSICIÓN!B$2:B$1879,"EQ") -> 155.70871 | M162: =J162 -> 2773.008 | N162: =IF(F162=0,0,K162/F162) -> 7607.5726 | O162: =IF(F162=0,0,L162/F162) -> 155.70871 | P162: =M162+N162+O162 -> 10536.289 | Q162: =COUNTIF(COMPOSICIÓN!$A:$A,A162) -> 3 | R162: PTO/Tareas
A163: PTO-1107 | C163: PISOS | D163: Colocación de baldoson granítico vereda 40 x 40 - Provisión a cargo del comitente | E163: m2 | F163: 1 | G163: 0 | H163: 0 | I163: 1 | J163: =SUMIFS(COMPOSICIÓN!J$2:J$1879,COMPOSICIÓN!A$2:A$1879,A163,COMPOSICIÓN!B$2:B$1879,"MAT") -> 7701.7949 | K163: =SUMIFS(COMPOSICIÓN!J$2:J$1879,COMPOSICIÓN!A$2:A$1879,A163,COMPOSICIÓN!B$2:B$1879,"MO")*I163 -> 11983.97 | L163: =SUMIFS(COMPOSICIÓN!J$2:J$1879,COMPOSICIÓN!A$2:A$1879,A163,COMPOSICIÓN!B$2:B$1879,"EQ") -> 295.28648 | M163: =J163 -> 7701.7949 | N163: =IF(F163=0,0,K163/F163) -> 11983.97 | O163: =IF(F163=0,0,L163/F163) -> 295.28648 | P163: =M163+N163+O163 -> 19981.052 | Q163: =COUNTIF(COMPOSICIÓN!$A:$A,A163) -> 8 | R163: PTO/Tareas
A164: PTO-1108 | B164: 56 | C164: PISOS | D164: Colocación de porcelanato a definir Interior UF - Provisión a cargo del comitente | E164: m2 | F164: 13 | G164: 0 | H164: 0 | I164: 1 | J164: =SUMIFS(COMPOSICIÓN!J$2:J$1879,COMPOSICIÓN!A$2:A$1879,A164,COMPOSICIÓN!B$2:B$1879,"MAT") -> 3810.903 | K164: =SUMIFS(COMPOSICIÓN!J$2:J$1879,COMPOSICIÓN!A$2:A$1879,A164,COMPOSICIÓN!B$2:B$1879,"MO")*I164 -> 162882.18 | L164: =SUMIFS(COMPOSICIÓN!J$2:J$1879,COMPOSICIÓN!A$2:A$1879,A164,COMPOSICIÓN!B$2:B$1879,"EQ") -> 2935.5657 | M164: =J164 -> 3810.903 | N164: =IF(F164=0,0,K164/F164) -> 12529.398 | O164: =IF(F164=0,0,L164/F164) -> 225.81275 | P164: =M164+N164+O164 -> 16566.114 | Q164: =COUNTIF(COMPOSICIÓN!$A:$A,A164) -> 8 | R164: PTO/APU P-56
A165: PTO-1109 | B165: 57 | C165: PISOS | D165: Colocación de porcelanato a definir Baños - Provisión a cargo del comitente | E165: m2 | F165: 10 | G165: 0 | H165: 0 | I165: 1 | J165: =SUMIFS(COMPOSICIÓN!J$2:J$1879,COMPOSICIÓN!A$2:A$1879,A165,COMPOSICIÓN!B$2:B$1879,"MAT") -> 3810.903 | K165: =SUMIFS(COMPOSICIÓN!J$2:J$1879,COMPOSICIÓN!A$2:A$1879,A165,COMPOSICIÓN!B$2:B$1879,"MO")*I165 -> 162882.18 | L165: =SUMIFS(COMPOSICIÓN!J$2:J$1879,COMPOSICIÓN!A$2:A$1879,A165,COMPOSICIÓN!B$2:B$1879,"EQ") -> 2935.5657 | M165: =J165 -> 3810.903 | N165: =IF(F165=0,0,K165/F165) -> 16288.218 | O165: =IF(F165=0,0,L165/F165) -> 293.55657 | P165: =M165+N165+O165 -> 20392.677 | Q165: =COUNTIF(COMPOSICIÓN!$A:$A,A165) -> 8 | R165: PTO/APU P-57
A166: PTO-1110 | B166: 56 | C166: PISOS | D166: Colocación de porcelanato a definir Balcones - Provisión a cargo del comitente | E166: m2 | F166: 13 | G166: 0 | H166: 0 | I166: 1 | J166: =SUMIFS(COMPOSICIÓN!J$2:J$1879,COMPOSICIÓN!A$2:A$1879,A166,COMPOSICIÓN!B$2:B$1879,"MAT") -> 3810.903 | K166: =SUMIFS(COMPOSICIÓN!J$2:J$1879,COMPOSICIÓN!A$2:A$1879,A166,COMPOSICIÓN!B$2:B$1879,"MO")*I166 -> 162882.18 | L166: =SUMIFS(COMPOSICIÓN!J$2:J$1879,COMPOSICIÓN!A$2:A$1879,A166,COMPOSICIÓN!B$2:B$1879,"EQ") -> 2935.5657 | M166: =J166 -> 3810.903 | N166: =IF(F166=0,0,K166/F166) -> 12529.398 | O166: =IF(F166=0,0,L166/F166) -> 225.81275 | P166: =M166+N166+O166 -> 16566.114 | Q166: =COUNTIF(COMPOSICIÓN!$A:$A,A166) -> 8 | R166: PTO/APU P-56
A167: PTO-1111 | B167: 56 | C167: PISOS | D167: Colocación de porcelanato a definir Palier - Provisión a cargo del comitente | E167: m2 | F167: 13 | G167: 0 | H167: 0 | I167: 1 | J167: =SUMIFS(COMPOSICIÓN!J$2:J$1879,COMPOSICIÓN!A$2:A$1879,A167,COMPOSICIÓN!B$2:B$1879,"MAT") -> 3810.903 | K167: =SUMIFS(COMPOSICIÓN!J$2:J$1879,COMPOSICIÓN!A$2:A$1879,A167,COMPOSICIÓN!B$2:B$1879,"MO")*I167 -> 162882.18 | L167: =SUMIFS(COMPOSICIÓN!J$2:J$1879,COMPOSICIÓN!A$2:A$1879,A167,COMPOSICIÓN!B$2:B$1879,"EQ") -> 2935.5657 | M167: =J167 -> 3810.903 | N167: =IF(F167=0,0,K167/F167) -> 12529.398 | O167: =IF(F167=0,0,L167/F167) -> 225.81275 | P167: =M167+N167+O167 -> 16566.114 | Q167: =COUNTIF(COMPOSICIÓN!$A:$A,A167) -> 8 | R167: PTO/APU P-56
A168: PTO-1201 | B168: 42 | C168: ZÓCALOS | D168: Ejecución de zócalo de concreto h: 10 cm | E168: ml | F168: 28 | G168: 0 | H168: 0 | I168: 1 | J168: =SUMIFS(COMPOSICIÓN!J$2:J$1879,COMPOSICIÓN!A$2:A$1879,A168,COMPOSICIÓN!B$2:B$1879,"MAT") -> 809.61503 | K168: =SUMIFS(COMPOSICIÓN!J$2:J$1879,COMPOSICIÓN!A$2:A$1879,A168,COMPOSICIÓN!B$2:B$1879,"MO")*I168 -> 110271.33 | L168: =SUMIFS(COMPOSICIÓN!J$2:J$1879,COMPOSICIÓN!A$2:A$1879,A168,COMPOSICIÓN!B$2:B$1879,"EQ") -> 3529.9787 | M168: =J168 -> 809.61503 | N168: =IF(F168=0,0,K168/F168) -> 3938.2618 | O168: =IF(F168=0,0,L168/F168) -> 126.07067 | P168: =M168+N168+O168 -> 4873.9475 | Q168: =COUNTIF(COMPOSICIÓN!$A:$A,A168) -> 8 | R168: PTO/APU P-42
A169: PTO-1202 | C169: ZÓCALOS | D169: Provisión y colocación de zócalo de MDF prepintado color bco. h: 7cm | E169: ml | F169: 1 | G169: 0 | H169: 0 | I169: 1 | J169: =SUMIFS(COMPOSICIÓN!J$2:J$1879,COMPOSICIÓN!A$2:A$1879,A169,COMPOSICIÓN!B$2:B$1879,"MAT") -> 7090.9091 | K169: =SUMIFS(COMPOSICIÓN!J$2:J$1879,COMPOSICIÓN!A$2:A$1879,A169,COMPOSICIÓN!B$2:B$1879,"MO")*I169 -> 3196.2174 | L169: =SUMIFS(COMPOSICIÓN!J$2:J$1879,COMPOSICIÓN!A$2:A$1879,A169,COMPOSICIÓN!B$2:B$1879,"EQ") -> 100.44326 | M169: =J169 -> 7090.9091 | N169: =IF(F169=0,0,K169/F169) -> 3196.2174 | O169: =IF(F169=0,0,L169/F169) -> 100.44326 | P169: =M169+N169+O169 -> 10387.57 | Q169: =COUNTIF(COMPOSICIÓN!$A:$A,A169) -> 4 | R169: PTO/Tareas
A170: PTO-1203 | B170: 58 | C170: ZÓCALOS | D170: Colocación de zócalo de porcelanato - Provisión a cargo del comitente | E170: ml | F170: 30 | G170: 0 | H170: 0 | I170: 1 | J170: =SUMIFS(COMPOSICIÓN!J$2:J$1879,COMPOSICIÓN!A$2:A$1879,A170,COMPOSICIÓN!B$2:B$1879,"MAT") -> 397.26413 | K170: =SUMIFS(COMPOSICIÓN!J$2:J$1879,COMPOSICIÓN!A$2:A$1879,A170,COMPOSICIÓN!B$2:B$1879,"MO")*I170 -> 162882.18 | L170: =SUMIFS(COMPOSICIÓN!J$2:J$1879,COMPOSICIÓN!A$2:A$1879,A170,COMPOSICIÓN!B$2:B$1879,"EQ") -> 2935.5657 | M170: =J170 -> 397.26413 | N170: =IF(F170=0,0,K170/F170) -> 5429.4059 | O170: =IF(F170=0,0,L170/F170) -> 97.85219 | P170: =M170+N170+O170 -> 5924.5222 | Q170: =COUNTIF(COMPOSICIÓN!$A:$A,A170) -> 7 | R170: PTO/APU P-58
A171: PTO-1301 | B171: 57 | C171: REVESTIMIENTOS | D171: Colocación de porcelanato en baños - Provisión a cargo del comitente | E171: m2 | F171: 10 | G171: 0 | H171: 0 | I171: 1 | J171: =SUMIFS(COMPOSICIÓN!J$2:J$1879,COMPOSICIÓN!A$2:A$1879,A171,COMPOSICIÓN!B$2:B$1879,"MAT") -> 3810.903 | K171: =SUMIFS(COMPOSICIÓN!J$2:J$1879,COMPOSICIÓN!A$2:A$1879,A171,COMPOSICIÓN!B$2:B$1879,"MO")*I171 -> 162882.18 | L171: =SUMIFS(COMPOSICIÓN!J$2:J$1879,COMPOSICIÓN!A$2:A$1879,A171,COMPOSICIÓN!B$2:B$1879,"EQ") -> 2935.5657 | M171: =J171 -> 3810.903 | N171: =IF(F171=0,0,K171/F171) -> 16288.218 | O171: =IF(F171=0,0,L171/F171) -> 293.55657 | P171: =M171+N171+O171 -> 20392.677 | Q171: =COUNTIF(COMPOSICIÓN!$A:$A,A171) -> 8 | R171: PTO/APU P-57
A172: PTO-1302 | B172: 57 | C172: REVESTIMIENTOS | D172: Colocación de revestimiento en cocinas - Provisión a cargo del comitente | E172: m2 | F172: 10 | G172: 0 | H172: 0 | I172: 1 | J172: =SUMIFS(COMPOSICIÓN!J$2:J$1879,COMPOSICIÓN!A$2:A$1879,A172,COMPOSICIÓN!B$2:B$1879,"MAT") -> 3810.903 | K172: =SUMIFS(COMPOSICIÓN!J$2:J$1879,COMPOSICIÓN!A$2:A$1879,A172,COMPOSICIÓN!B$2:B$1879,"MO")*I172 -> 162882.18 | L172: =SUMIFS(COMPOSICIÓN!J$2:J$1879,COMPOSICIÓN!A$2:A$1879,A172,COMPOSICIÓN!B$2:B$1879,"EQ") -> 2935.5657 | M172: =J172 -> 3810.903 | N172: =IF(F172=0,0,K172/F172) -> 16288.218 | O172: =IF(F172=0,0,L172/F172) -> 293.55657 | P172: =M172+N172+O172 -> 20392.677 | Q172: =COUNTIF(COMPOSICIÓN!$A:$A,A172) -> 8 | R172: PTO/APU P-57
A173: PTO-1303 | C173: REVESTIMIENTOS | D173: Colocación de listones refractarios en parrillas - Provisión a cargo del comitente | E173: m2 | F173: 1 | G173: 0 | H173: 0 | I173: 1 | J173: =SUMIFS(COMPOSICIÓN!J$2:J$1879,COMPOSICIÓN!A$2:A$1879,A173,COMPOSICIÓN!B$2:B$1879,"MAT") -> 36508.296 | K173: =SUMIFS(COMPOSICIÓN!J$2:J$1879,COMPOSICIÓN!A$2:A$1879,A173,COMPOSICIÓN!B$2:B$1879,"MO")*I173 -> 32215.611 | L173: =SUMIFS(COMPOSICIÓN!J$2:J$1879,COMPOSICIÓN!A$2:A$1879,A173,COMPOSICIÓN!B$2:B$1879,"EQ") -> 1030.8586 | M173: =J173 -> 36508.296 | N173: =IF(F173=0,0,K173/F173) -> 32215.611 | O173: =IF(F173=0,0,L173/F173) -> 1030.8586 | P173: =M173+N173+O173 -> 69754.766 | Q173: =COUNTIF(COMPOSICIÓN!$A:$A,A173) -> 5 | R173: PTO/Tareas
A174: PTO-1304 | C174: REVESTIMIENTOS | D174: Revestimiento Simil madera - Cotizado en provisiones | E174: m2 | F174: 1 | G174: 0 | H174: 0 | I174: 1 | J174: =SUMIFS(COMPOSICIÓN!J$2:J$1879,COMPOSICIÓN!A$2:A$1879,A174,COMPOSICIÓN!B$2:B$1879,"MAT") -> 0 | K174: =SUMIFS(COMPOSICIÓN!J$2:J$1879,COMPOSICIÓN!A$2:A$1879,A174,COMPOSICIÓN!B$2:B$1879,"MO")*I174 -> 0 | L174: =SUMIFS(COMPOSICIÓN!J$2:J$1879,COMPOSICIÓN!A$2:A$1879,A174,COMPOSICIÓN!B$2:B$1879,"EQ") -> 0 | M174: =J174 -> 0 | N174: =IF(F174=0,0,K174/F174) -> 0 | O174: =IF(F174=0,0,L174/F174) -> 0 | P174: =M174+N174+O174 -> 0 | Q174: =COUNTIF(COMPOSICIÓN!$A:$A,A174) -> 0 | R174: PTO/sin cotizar
A175: PTO-1401 | C175: REVOQUES FINOS Y CIELORRASOS | D175: Aplicado de yeso | E175: m2 | F175: 1 | G175: 0 | H175: 0 | I175: 1 | J175: =SUMIFS(COMPOSICIÓN!J$2:J$1879,COMPOSICIÓN!A$2:A$1879,A175,COMPOSICIÓN!B$2:B$1879,"MAT") -> 5812.2329 | K175: =SUMIFS(COMPOSICIÓN!J$2:J$1879,COMPOSICIÓN!A$2:A$1879,A175,COMPOSICIÓN!B$2:B$1879,"MO")*I175 -> 11651.218 | L175: =SUMIFS(COMPOSICIÓN!J$2:J$1879,COMPOSICIÓN!A$2:A$1879,A175,COMPOSICIÓN!B$2:B$1879,"EQ") -> 261.95177 | M175: =J175 -> 5812.2329 | N175: =IF(F175=0,0,K175/F175) -> 11651.218 | O175: =IF(F175=0,0,L175/F175) -> 261.95177 | P175: =M175+N175+O175 -> 17725.403 | Q175: =COUNTIF(COMPOSICIÓN!$A:$A,A175) -> 4 | R175: PTO/Tareas
A176: PTO-1402 | C176: REVOQUES FINOS Y CIELORRASOS | D176: Buña en yeso aplicado | E176: ml | F176: 1 | G176: 0 | H176: 0 | I176: 1 | J176: =SUMIFS(COMPOSICIÓN!J$2:J$1879,COMPOSICIÓN!A$2:A$1879,A176,COMPOSICIÓN!B$2:B$1879,"MAT") -> 0 | K176: =SUMIFS(COMPOSICIÓN!J$2:J$1879,COMPOSICIÓN!A$2:A$1879,A176,COMPOSICIÓN!B$2:B$1879,"MO")*I176 -> 12499.473 | L176: =SUMIFS(COMPOSICIÓN!J$2:J$1879,COMPOSICIÓN!A$2:A$1879,A176,COMPOSICIÓN!B$2:B$1879,"EQ") -> 0 | M176: =J176 -> 0 | N176: =IF(F176=0,0,K176/F176) -> 12499.473 | O176: =IF(F176=0,0,L176/F176) -> 0 | P176: =M176+N176+O176 -> 12499.473 | Q176: =COUNTIF(COMPOSICIÓN!$A:$A,A176) -> 1 | R176: PTO/aux
A177: PTO-1403 | B177: 60 | C177: REVOQUES FINOS Y CIELORRASOS | D177: Cielorraso suspendido en placa STD | E177: m2 | F177: 9.5 | G177: 0 | H177: 0 | I177: 1 | J177: =SUMIFS(COMPOSICIÓN!J$2:J$1879,COMPOSICIÓN!A$2:A$1879,A177,COMPOSICIÓN!B$2:B$1879,"MAT") -> 10671.937 | K177: =SUMIFS(COMPOSICIÓN!J$2:J$1879,COMPOSICIÓN!A$2:A$1879,A177,COMPOSICIÓN!B$2:B$1879,"MO")*I177 -> 151420.17 | L177: =SUMIFS(COMPOSICIÓN!J$2:J$1879,COMPOSICIÓN!A$2:A$1879,A177,COMPOSICIÓN!B$2:B$1879,"EQ") -> 2505.4362 | M177: =J177 -> 10671.937 | N177: =IF(F177=0,0,K177/F177) -> 15938.965 | O177: =IF(F177=0,0,L177/F177) -> 263.73013 | P177: =M177+N177+O177 -> 26874.632 | Q177: =COUNTIF(COMPOSICIÓN!$A:$A,A177) -> 12 | R177: PTO/APU P-60
A178: PTO-1404 | B178: 61 | C178: REVOQUES FINOS Y CIELORRASOS | D178: Cielorraso suspendido en placa RH | E178: m2 | F178: 9.5 | G178: 0 | H178: 0 | I178: 1 | J178: =SUMIFS(COMPOSICIÓN!J$2:J$1879,COMPOSICIÓN!A$2:A$1879,A178,COMPOSICIÓN!B$2:B$1879,"MAT") -> 14660.055 | K178: =SUMIFS(COMPOSICIÓN!J$2:J$1879,COMPOSICIÓN!A$2:A$1879,A178,COMPOSICIÓN!B$2:B$1879,"MO")*I178 -> 151420.17 | L178: =SUMIFS(COMPOSICIÓN!J$2:J$1879,COMPOSICIÓN!A$2:A$1879,A178,COMPOSICIÓN!B$2:B$1879,"EQ") -> 2505.4362 | M178: =J178 -> 14660.055 | N178: =IF(F178=0,0,K178/F178) -> 15938.965 | O178: =IF(F178=0,0,L178/F178) -> 263.73013 | P178: =M178+N178+O178 -> 30862.75 | Q178: =COUNTIF(COMPOSICIÓN!$A:$A,A178) -> 12 | R178: PTO/APU P-61
A179: PTO-1405 | B179: 117 | C179: REVOQUES FINOS Y CIELORRASOS | D179: Buña Z en cielorraso suspendido | E179: ml | F179: 15 | G179: 0 | H179: 0 | I179: 1 | J179: =SUMIFS(COMPOSICIÓN!J$2:J$1879,COMPOSICIÓN!A$2:A$1879,A179,COMPOSICIÓN!B$2:B$1879,"MAT") -> 1062.8718 | K179: =SUMIFS(COMPOSICIÓN!J$2:J$1879,COMPOSICIÓN!A$2:A$1879,A179,COMPOSICIÓN!B$2:B$1879,"MO")*I179 -> 85927.097 | L179: =SUMIFS(COMPOSICIÓN!J$2:J$1879,COMPOSICIÓN!A$2:A$1879,A179,COMPOSICIÓN!B$2:B$1879,"EQ") -> 2505.4362 | M179: =J179 -> 1062.8718 | N179: =IF(F179=0,0,K179/F179) -> 5728.4731 | O179: =IF(F179=0,0,L179/F179) -> 167.02908 | P179: =M179+N179+O179 -> 6958.374 | Q179: =COUNTIF(COMPOSICIÓN!$A:$A,A179) -> 5 | R179: PTO/APU P-117
A180: PTO-1406 | B180: 117 | C180: REVOQUES FINOS Y CIELORRASOS | D180: Cantonera / Cajón | E180: ml | F180: 15 | G180: 0 | H180: 0 | I180: 1 | J180: =SUMIFS(COMPOSICIÓN!J$2:J$1879,COMPOSICIÓN!A$2:A$1879,A180,COMPOSICIÓN!B$2:B$1879,"MAT") -> 0 | K180: =SUMIFS(COMPOSICIÓN!J$2:J$1879,COMPOSICIÓN!A$2:A$1879,A180,COMPOSICIÓN!B$2:B$1879,"MO")*I180 -> 0 | L180: =SUMIFS(COMPOSICIÓN!J$2:J$1879,COMPOSICIÓN!A$2:A$1879,A180,COMPOSICIÓN!B$2:B$1879,"EQ") -> 167.02908 | M180: =J180 -> 0 | N180: =IF(F180=0,0,K180/F180) -> 0 | O180: =IF(F180=0,0,L180/F180) -> 11.135272 | P180: =M180+N180+O180 -> 11.135272 | Q180: =COUNTIF(COMPOSICIÓN!$A:$A,A180) -> 1 | R180: PTO/APU P-117
A181: PTO-1407 | C181: REVOQUES FINOS Y CIELORRASOS | D181: Hormigon visto, maquillaje | E181: m2 | F181: 1 | G181: 0 | H181: 0 | I181: 1 | J181: =SUMIFS(COMPOSICIÓN!J$2:J$1879,COMPOSICIÓN!A$2:A$1879,A181,COMPOSICIÓN!B$2:B$1879,"MAT") -> 1066.0981 | K181: =SUMIFS(COMPOSICIÓN!J$2:J$1879,COMPOSICIÓN!A$2:A$1879,A181,COMPOSICIÓN!B$2:B$1879,"MO")*I181 -> 2877.8543 | L181: =SUMIFS(COMPOSICIÓN!J$2:J$1879,COMPOSICIÓN!A$2:A$1879,A181,COMPOSICIÓN!B$2:B$1879,"EQ") -> 59.159286 | M181: =J181 -> 1066.0981 | N181: =IF(F181=0,0,K181/F181) -> 2877.8543 | O181: =IF(F181=0,0,L181/F181) -> 59.159286 | P181: =M181+N181+O181 -> 4003.1117 | Q181: =COUNTIF(COMPOSICIÓN!$A:$A,A181) -> 5 | R181: PTO/Tareas
A182: PTO-1501 | C182: PINTURA | D182: Latex exterior mate en paredes, color bco., sin enduido, a mas de 3 m de altura - Medianeras | E182: m2 | F182: 1 | G182: 0 | H182: 0 | I182: 1 | J182: =SUMIFS(COMPOSICIÓN!J$2:J$1879,COMPOSICIÓN!A$2:A$1879,A182,COMPOSICIÓN!B$2:B$1879,"MAT") -> 1824.9263 | K182: =SUMIFS(COMPOSICIÓN!J$2:J$1879,COMPOSICIÓN!A$2:A$1879,A182,COMPOSICIÓN!B$2:B$1879,"MO")*I182 -> 14504.13 | L182: =SUMIFS(COMPOSICIÓN!J$2:J$1879,COMPOSICIÓN!A$2:A$1879,A182,COMPOSICIÓN!B$2:B$1879,"EQ") -> 234.44231 | M182: =J182 -> 1824.9263 | N182: =IF(F182=0,0,K182/F182) -> 14504.13 | O182: =IF(F182=0,0,L182/F182) -> 234.44231 | P182: =M182+N182+O182 -> 16563.498 | Q182: =COUNTIF(COMPOSICIÓN!$A:$A,A182) -> 3 | R182: PTO/lump-no-apu
A183: PTO-1502 | B183: 137 | C183: PINTURA | D183: Latex interior mate en paredes, color bco., con enduido parcial | E183: m2 | F183: 20 | G183: 0 | H183: 0 | I183: 1 | J183: =SUMIFS(COMPOSICIÓN!J$2:J$1879,COMPOSICIÓN!A$2:A$1879,A183,COMPOSICIÓN!B$2:B$1879,"MAT") -> 2272.0787 | K183: =SUMIFS(COMPOSICIÓN!J$2:J$1879,COMPOSICIÓN!A$2:A$1879,A183,COMPOSICIÓN!B$2:B$1879,"MO")*I183 -> 85927.097 | L183: =SUMIFS(COMPOSICIÓN!J$2:J$1879,COMPOSICIÓN!A$2:A$1879,A183,COMPOSICIÓN!B$2:B$1879,"EQ") -> 1923.879 | M183: =J183 -> 2272.0787 | N183: =IF(F183=0,0,K183/F183) -> 4296.3549 | O183: =IF(F183=0,0,L183/F183) -> 96.193952 | P183: =M183+N183+O183 -> 6664.6275 | Q183: =COUNTIF(COMPOSICIÓN!$A:$A,A183) -> 13 | R183: PTO/APU P-137
A184: PTO-1503 | B184: 51 | C184: PINTURA | D184: Latex interior mate en paredes, color bco., con enduido completo | E184: m2 | F184: 22 | G184: 0 | H184: 0 | I184: 1 | J184: =SUMIFS(COMPOSICIÓN!J$2:J$1879,COMPOSICIÓN!A$2:A$1879,A184,COMPOSICIÓN!B$2:B$1879,"MAT") -> 2923.7665 | K184: =SUMIFS(COMPOSICIÓN!J$2:J$1879,COMPOSICIÓN!A$2:A$1879,A184,COMPOSICIÓN!B$2:B$1879,"MO")*I184 -> 167793.44 | L184: =SUMIFS(COMPOSICIÓN!J$2:J$1879,COMPOSICIÓN!A$2:A$1879,A184,COMPOSICIÓN!B$2:B$1879,"EQ") -> 3847.7581 | M184: =J184 -> 2923.7665 | N184: =IF(F184=0,0,K184/F184) -> 7626.9744 | O184: =IF(F184=0,0,L184/F184) -> 174.89809 | P184: =M184+N184+O184 -> 10725.639 | Q184: =COUNTIF(COMPOSICIÓN!$A:$A,A184) -> 14 | R184: PTO/APU P-51
A185: PTO-1504 | B185: 146 | C185: PINTURA | D185: Latex exterior acrílico en cielorraso, color a definir, sin enduido - Sector cocheras | E185: m2 | F185: 25 | G185: 0 | H185: 0 | I185: 1 | J185: =SUMIFS(COMPOSICIÓN!J$2:J$1879,COMPOSICIÓN!A$2:A$1879,A185,COMPOSICIÓN!B$2:B$1879,"MAT") -> 2141.693 | K185: =SUMIFS(COMPOSICIÓN!J$2:J$1879,COMPOSICIÓN!A$2:A$1879,A185,COMPOSICIÓN!B$2:B$1879,"MO")*I185 -> 85927.097 | L185: =SUMIFS(COMPOSICIÓN!J$2:J$1879,COMPOSICIÓN!A$2:A$1879,A185,COMPOSICIÓN!B$2:B$1879,"EQ") -> 1923.879 | M185: =J185 -> 2141.693 | N185: =IF(F185=0,0,K185/F185) -> 3437.0839 | O185: =IF(F185=0,0,L185/F185) -> 76.955162 | P185: =M185+N185+O185 -> 5655.732 | Q185: =COUNTIF(COMPOSICIÓN!$A:$A,A185) -> 11 | R185: PTO/APU P-146
A186: PTO-1505 | B186: 137 | C186: PINTURA | D186: Latex interior mate en cielorraso, color bco., con enduido parcial | E186: m2 | F186: 20 | G186: 0 | H186: 0 | I186: 1 | J186: =SUMIFS(COMPOSICIÓN!J$2:J$1879,COMPOSICIÓN!A$2:A$1879,A186,COMPOSICIÓN!B$2:B$1879,"MAT") -> 2272.0787 | K186: =SUMIFS(COMPOSICIÓN!J$2:J$1879,COMPOSICIÓN!A$2:A$1879,A186,COMPOSICIÓN!B$2:B$1879,"MO")*I186 -> 85927.097 | L186: =SUMIFS(COMPOSICIÓN!J$2:J$1879,COMPOSICIÓN!A$2:A$1879,A186,COMPOSICIÓN!B$2:B$1879,"EQ") -> 1923.879 | M186: =J186 -> 2272.0787 | N186: =IF(F186=0,0,K186/F186) -> 4296.3549 | O186: =IF(F186=0,0,L186/F186) -> 96.193952 | P186: =M186+N186+O186 -> 6664.6275 | Q186: =COUNTIF(COMPOSICIÓN!$A:$A,A186) -> 13 | R186: PTO/APU P-137
...

Sheet COMPOSICIÓN
A1: Partida | B1: Tipo | C1: Subtipo | D1: Cod_Insumo | E1: Descripción | F1: Unidad de medida | G1: Cant | H1: %Desp | I1: Precio | J1: Costo | K1: Clave | L1: Count | M1: Clave2 | N1: Rend. Part. | O1: Cant MO/ALB Unit | P1: Cant. Ej. Part. | Q1: Cant MO/ALB Total | R1: en PPTO?
A2: AIS-114 | B2: EQ | D2: EQ-SOLD00 | E2: =IFERROR(VLOOKUP(D2,EQUIPOS!A:B,2,FALSE()),"?") -> Soldador Soplete A Gas Techista Membrana 10 Kg Boca 50mm | G2: 1 | H2: 0 | I2: =IFERROR(VLOOKUP(D2,EQUIPOS!A:F,6,FALSE()),0) -> 804.50569 | J2: =G2*I2 -> 804.50569 | K2: =A2&"|"&B2 -> AIS-114|EQ | L2: =COUNTIFS($K$2:K2,K2) -> 1 | M2: =K2&"|"&L2 -> AIS-114|EQ|1 | N2: =IFERROR(VLOOKUP(A2,PARTIDAS!A:F,6,FALSE()),0) -> 60 | O2: =+IF(C2="ALB",G2/N2,G2) -> 1 | P2: =+_xlfn.XLOOKUP(A2,PPTO_GENERADOR!Q:Q,PPTO_GENERADOR!E:E,"-",0) -> - | Q2: =IFERROR(P2*O2,0) -> 0 | R2: =+_xlfn.XLOOKUP(A2,PPTO_GENERADOR!$Q:$Q,PPTO_GENERADOR!A:A,"-",0) -> -
A3: AIS-114 | B3: MAT | C3: OTR | D3: OTR-022 | E3: =IFERROR(VLOOKUP(D3,MATERIALES!A:B,2,FALSE()),"?") -> Aguarras Hydrarras Hydra x 18lts | F3: =IFERROR(VLOOKUP(D3,MATERIALES!A:C,3,FALSE()),"?") -> b | G3: 0.005 | H3: 0.05 | I3: =IFERROR(VLOOKUP(D3,MATERIALES!A:D,4,FALSE()),0) -> 26907.33 | J3: =G3*I3*(1+H3) -> 141.26348 | K3: =A3&"|"&B3 -> AIS-114|MAT | L3: =COUNTIFS($K$2:K3,K3) -> 1 | M3: =K3&"|"&L3 -> AIS-114|MAT|1 | N3: =IFERROR(VLOOKUP(A3,PARTIDAS!A:F,6,FALSE()),0) -> 60 | O3: =+IF(C3="ALB",G3/N3,G3) -> 0.005 | P3: =+_xlfn.XLOOKUP(A3,PPTO_GENERADOR!Q:Q,PPTO_GENERADOR!E:E,"-",0) -> - | Q3: =IFERROR(P3*O3,0) -> 0 | R3: =+_xlfn.XLOOKUP(A3,PPTO_GENERADOR!$Q:$Q,PPTO_GENERADOR!A:A,"-",0) -> -
A4: AIS-114 | B4: MAT | C4: OTR | D4: OTR-025 | E4: =IFERROR(VLOOKUP(D4,MATERIALES!A:B,2,FALSE()),"?") -> Trapo | F4: =IFERROR(VLOOKUP(D4,MATERIALES!A:C,3,FALSE()),"?") -> u | G4: 0.01 | H4: 0.05 | I4: =IFERROR(VLOOKUP(D4,MATERIALES!A:D,4,FALSE()),0) -> 735.06 | J4: =G4*I4*(1+H4) -> 7.71813 | K4: =A4&"|"&B4 -> AIS-114|MAT | L4: =COUNTIFS($K$2:K4,K4) -> 2 | M4: =K4&"|"&L4 -> AIS-114|MAT|2 | N4: =IFERROR(VLOOKUP(A4,PARTIDAS!A:F,6,FALSE()),0) -> 60 | O4: =+IF(C4="ALB",G4/N4,G4) -> 0.01 | P4: =+_xlfn.XLOOKUP(A4,PPTO_GENERADOR!Q:Q,PPTO_GENERADOR!E:E,"-",0) -> - | Q4: =IFERROR(P4*O4,0) -> 0 | R4: =+_xlfn.XLOOKUP(A4,PPTO_GENERADOR!$Q:$Q,PPTO_GENERADOR!A:A,"-",0) -> -
A5: AIS-114 | B5: MAT | C5: OTR | D5: OTR-027 | E5: =IFERROR(VLOOKUP(D5,MATERIALES!A:B,2,FALSE()),"?") -> Rodillo de lana pelo largo N°22 - El Galgo | F5: =IFERROR(VLOOKUP(D5,MATERIALES!A:C,3,FALSE()),"?") -> u | G5: 0.005 | H5: 0.05 | I5: =IFERROR(VLOOKUP(D5,MATERIALES!A:D,4,FALSE()),0) -> 6678.36 | J5: =G5*I5*(1+H5) -> 35.06139 | K5: =A5&"|"&B5 -> AIS-114|MAT | L5: =COUNTIFS($K$2:K5,K5) -> 3 | M5: =K5&"|"&L5 -> AIS-114|MAT|3 | N5: =IFERROR(VLOOKUP(A5,PARTIDAS!A:F,6,FALSE()),0) -> 60 | O5: =+IF(C5="ALB",G5/N5,G5) -> 0.005 | P5: =+_xlfn.XLOOKUP(A5,PPTO_GENERADOR!Q:Q,PPTO_GENERADOR!E:E,"-",0) -> - | Q5: =IFERROR(P5*O5,0) -> 0 | R5: =+_xlfn.XLOOKUP(A5,PPTO_GENERADOR!$Q:$Q,PPTO_GENERADOR!A:A,"-",0) -> -
A6: AIS-114 | B6: MAT | C6: OTR | D6: OTR-028 | E6: =IFERROR(VLOOKUP(D6,MATERIALES!A:B,2,FALSE()),"?") -> Pincel N° 20 - El Galgo | F6: =IFERROR(VLOOKUP(D6,MATERIALES!A:C,3,FALSE()),"?") -> u | G6: 0.01 | H6: 0.05 | I6: =IFERROR(VLOOKUP(D6,MATERIALES!A:D,4,FALSE()),0) -> 5282.24 | J6: =G6*I6*(1+H6) -> 55.46352 | K6: =A6&"|"&B6 -> AIS-114|MAT | L6: =COUNTIFS($K$2:K6,K6) -> 4 | M6: =K6&"|"&L6 -> AIS-114|MAT|4 | N6: =IFERROR(VLOOKUP(A6,PARTIDAS!A:F,6,FALSE()),0) -> 60 | O6: =+IF(C6="ALB",G6/N6,G6) -> 0.01 | P6: =+_xlfn.XLOOKUP(A6,PPTO_GENERADOR!Q:Q,PPTO_GENERADOR!E:E,"-",0) -> - | Q6: =IFERROR(P6*O6,0) -> 0 | R6: =+_xlfn.XLOOKUP(A6,PPTO_GENERADOR!$Q:$Q,PPTO_GENERADOR!A:A,"-",0) -> -
A7: AIS-114 | B7: MAT | C7: OTR | D7: OTR-047 | E7: =IFERROR(VLOOKUP(D7,MATERIALES!A:B,2,FALSE()),"?") -> Guante Vaqueta Medio Paseo | F7: =IFERROR(VLOOKUP(D7,MATERIALES!A:C,3,FALSE()),"?") -> par | G7: 0.03 | H7: 0.05 | I7: =IFERROR(VLOOKUP(D7,MATERIALES!A:D,4,FALSE()),0) -> 4842 | J7: =G7*I7*(1+H7) -> 152.523 | K7: =A7&"|"&B7 -> AIS-114|MAT | L7: =COUNTIFS($K$2:K7,K7) -> 5 | M7: =K7&"|"&L7 -> AIS-114|MAT|5 | N7: =IFERROR(VLOOKUP(A7,PARTIDAS!A:F,6,FALSE()),0) -> 60 | O7: =+IF(C7="ALB",G7/N7,G7) -> 0.03 | P7: =+_xlfn.XLOOKUP(A7,PPTO_GENERADOR!Q:Q,PPTO_GENERADOR!E:E,"-",0) -> - | Q7: =IFERROR(P7*O7,0) -> 0 | R7: =+_xlfn.XLOOKUP(A7,PPTO_GENERADOR!$Q:$Q,PPTO_GENERADOR!A:A,"-",0) -> -
A8: AIS-114 | B8: MAT | C8: OTR | D8: OTR-048 | E8: =IFERROR(VLOOKUP(D8,MATERIALES!A:B,2,FALSE()),"?") -> Recarga de garrafa | F8: =IFERROR(VLOOKUP(D8,MATERIALES!A:C,3,FALSE()),"?") -> u | G8: 0.01 | H8: 0.05 | I8: =IFERROR(VLOOKUP(D8,MATERIALES!A:D,4,FALSE()),0) -> 12396.694 | J8: =G8*I8*(1+H8) -> 130.16529 | K8: =A8&"|"&B8 -> AIS-114|MAT | L8: =COUNTIFS($K$2:K8,K8) -> 6 | M8: =K8&"|"&L8 -> AIS-114|MAT|6 | N8: =IFERROR(VLOOKUP(A8,PARTIDAS!A:F,6,FALSE()),0) -> 60 | O8: =+IF(C8="ALB",G8/N8,G8) -> 0.01 | P8: =+_xlfn.XLOOKUP(A8,PPTO_GENERADOR!Q:Q,PPTO_GENERADOR!E:E,"-",0) -> - | Q8: =IFERROR(P8*O8,0) -> 0 | R8: =+_xlfn.XLOOKUP(A8,PPTO_GENERADOR!$Q:$Q,PPTO_GENERADOR!A:A,"-",0) -> -
A9: AIS-114 | B9: MAT | C9: OTR | D9: PIN-008 | E9: =IFERROR(VLOOKUP(D9,MATERIALES!A:B,2,FALSE()),"?") -> Pintura Asfaltica Asfasol x18ts | F9: =IFERROR(VLOOKUP(D9,MATERIALES!A:C,3,FALSE()),"?") -> b | G9: 0.015 | H9: 0.1 | I9: =IFERROR(VLOOKUP(D9,MATERIALES!A:D,4,FALSE()),0) -> 32845.78 | J9: =G9*I9*(1+H9) -> 541.95537 | K9: =A9&"|"&B9 -> AIS-114|MAT | L9: =COUNTIFS($K$2:K9,K9) -> 7 | M9: =K9&"|"&L9 -> AIS-114|MAT|7 | N9: =IFERROR(VLOOKUP(A9,PARTIDAS!A:F,6,FALSE()),0) -> 60 | O9: =+IF(C9="ALB",G9/N9,G9) -> 0.015 | P9: =+_xlfn.XLOOKUP(A9,PPTO_GENERADOR!Q:Q,PPTO_GENERADOR!E:E,"-",0) -> - | Q9: =IFERROR(P9*O9,0) -> 0 | R9: =+_xlfn.XLOOKUP(A9,PPTO_GENERADOR!$Q:$Q,PPTO_GENERADOR!A:A,"-",0) -> -
A10: AIS-114 | B10: MAT | C10: OTR | D10: AIS-002 | E10: =IFERROR(VLOOKUP(D10,MATERIALES!A:B,2,FALSE()),"?") -> Membrana Geotextil Ormiflex 4mm - (35kg) x10m | F10: =IFERROR(VLOOKUP(D10,MATERIALES!A:C,3,FALSE()),"?") -> u | G10: 0.05 | H10: 0.1 | I10: =IFERROR(VLOOKUP(D10,MATERIALES!A:D,4,FALSE()),0) -> 70192.21 | J10: =G10*I10*(1+H10) -> 3860.5716 | K10: =A10&"|"&B10 -> AIS-114|MAT | L10: =COUNTIFS($K$2:K10,K10) -> 8 | M10: =K10&"|"&L10 -> AIS-114|MAT|8 | N10: =IFERROR(VLOOKUP(A10,PARTIDAS!A:F,6,FALSE()),0) -> 60 | O10: =+IF(C10="ALB",G10/N10,G10) -> 0.05 | P10: =+_xlfn.XLOOKUP(A10,PPTO_GENERADOR!Q:Q,PPTO_GENERADOR!E:E,"-",0) -> - | Q10: =IFERROR(P10*O10,0) -> 0 | R10: =+_xlfn.XLOOKUP(A10,PPTO_GENERADOR!$Q:$Q,PPTO_GENERADOR!A:A,"-",0) -> -
A11: AIS-114 | B11: MO | C11: ALB | D11: MO-EAYUD | E11: =IFERROR(VLOOKUP(D11,MANO_DE_OBRA!A:B,2,FALSE()),"?") -> AYUDANTE | F11: j | G11: 1 | H11: 0 | I11: =IFERROR(VLOOKUP(D11,MANO_DE_OBRA!A:C,3,FALSE()),0) -> 60860.581 | J11: =G11*I11 -> 60860.581 | K11: =A11&"|"&B11 -> AIS-114|MO | L11: =COUNTIFS($K$2:K11,K11) -> 1 | M11: =K11&"|"&L11 -> AIS-114|MO|1 | N11: =IFERROR(VLOOKUP(A11,PARTIDAS!A:F,6,FALSE()),0) -> 60 | O11: =+IF(C11="ALB",G11/N11,G11) -> 0.016666667 | P11: =+_xlfn.XLOOKUP(A11,PPTO_GENERADOR!Q:Q,PPTO_GENERADOR!E:E,"-",0) -> - | Q11: =IFERROR(P11*O11,0) -> 0 | R11: =+_xlfn.XLOOKUP(A11,PPTO_GENERADOR!$Q:$Q,PPTO_GENERADOR!A:A,"-",0) -> -
A12: AIS-114 | B12: MO | C12: ALB | D12: MO-EESPE | E12: =IFERROR(VLOOKUP(D12,MANO_DE_OBRA!A:B,2,FALSE()),"?") -> ESPECIALIZADO | F12: j | G12: 1 | H12: 0 | I12: =IFERROR(VLOOKUP(D12,MANO_DE_OBRA!A:C,3,FALSE()),0) -> 85927.097 | J12: =G12*I12 -> 85927.097 | K12: =A12&"|"&B12 -> AIS-114|MO | L12: =COUNTIFS($K$2:K12,K12) -> 2 | M12: =K12&"|"&L12 -> AIS-114|MO|2 | N12: =IFERROR(VLOOKUP(A12,PARTIDAS!A:F,6,FALSE()),0) -> 60 | O12: =+IF(C12="ALB",G12/N12,G12) -> 0.016666667 | P12: =+_xlfn.XLOOKUP(A12,PPTO_GENERADOR!Q:Q,PPTO_GENERADOR!E:E,"-",0) -> - | Q12: =IFERROR(P12*O12,0) -> 0 | R12: =+_xlfn.XLOOKUP(A12,PPTO_GENERADOR!$Q:$Q,PPTO_GENERADOR!A:A,"-",0) -> -
A13: ALB-033 | B13: EQ | D13: EQ-ANDAM0 | E13: =IFERROR(VLOOKUP(D13,EQUIPOS!A:B,2,FALSE()),"?") -> ANDAMIO TUBULAR DE UNO A TRES CUERPOS | G13: 0.5 | H13: 0 | I13: =IFERROR(VLOOKUP(D13,EQUIPOS!A:F,6,FALSE()),0) -> 571.17949 | J13: =G13*I13 -> 285.58975 | K13: =A13&"|"&B13 -> ALB-033|EQ | L13: =COUNTIFS($K$2:K13,K13) -> 1 | M13: =K13&"|"&L13 -> ALB-033|EQ|1 | N13: =IFERROR(VLOOKUP(A13,PARTIDAS!A:F,6,FALSE()),0) -> 7 | O13: =+IF(C13="ALB",G13/N13,G13) -> 0.5 | P13: =+_xlfn.XLOOKUP(A13,PPTO_GENERADOR!Q:Q,PPTO_GENERADOR!E:E,"-",0) -> - | Q13: =IFERROR(P13*O13,0) -> 0 | R13: =+_xlfn.XLOOKUP(A13,PPTO_GENERADOR!$Q:$Q,PPTO_GENERADOR!A:A,"-",0) -> -
A14: ALB-033 | B14: EQ | D14: EQ-EQALBA | E14: =IFERROR(VLOOKUP(D14,EQUIPOS!A:B,2,FALSE()),"?") -> EQUIPO DE ALBAÑILERIA, carpetas, ladrillo | G14: 1 | H14: 0 | I14: =IFERROR(VLOOKUP(D14,EQUIPOS!A:F,6,FALSE()),0) -> 2287.1357 | J14: =G14*I14 -> 2287.1357 | K14: =A14&"|"&B14 -> ALB-033|EQ | L14: =COUNTIFS($K$2:K14,K14) -> 2 | M14: =K14&"|"&L14 -> ALB-033|EQ|2 | N14: =IFERROR(VLOOKUP(A14,PARTIDAS!A:F,6,FALSE()),0) -> 7 | O14: =+IF(C14="ALB",G14/N14,G14) -> 1 | P14: =+_xlfn.XLOOKUP(A14,PPTO_GENERADOR!Q:Q,PPTO_GENERADOR!E:E,"-",0) -> - | Q14: =IFERROR(P14*O14,0) -> 0 | R14: =+_xlfn.XLOOKUP(A14,PPTO_GENERADOR!$Q:$Q,PPTO_GENERADOR!A:A,"-",0) -> -
A15: ALB-033 | B15: EQ | D15: EQ-TROMPO | E15: =IFERROR(VLOOKUP(D15,EQUIPOS!A:B,2,FALSE()),"?") -> Hormigonera De 150 Litros 1hp Con Rueda Maciza | G15: 1 | H15: 0 | I15: =IFERROR(VLOOKUP(D15,EQUIPOS!A:F,6,FALSE()),0) -> 957.2532 | J15: =G15*I15 -> 957.2532 | K15: =A15&"|"&B15 -> ALB-033|EQ | L15: =COUNTIFS($K$2:K15,K15) -> 3 | M15: =K15&"|"&L15 -> ALB-033|EQ|3 | N15: =IFERROR(VLOOKUP(A15,PARTIDAS!A:F,6,FALSE()),0) -> 7 | O15: =+IF(C15="ALB",G15/N15,G15) -> 1 | P15: =+_xlfn.XLOOKUP(A15,PPTO_GENERADOR!Q:Q,PPTO_GENERADOR!E:E,"-",0) -> - | Q15: =IFERROR(P15*O15,0) -> 0 | R15: =+_xlfn.XLOOKUP(A15,PPTO_GENERADOR!$Q:$Q,PPTO_GENERADOR!A:A,"-",0) -> -
A16: ALB-033 | B16: MAT | C16: OTR | D16: ACE-001 | E16: =IFERROR(VLOOKUP(D16,MATERIALES!A:B,2,FALSE()),"?") -> Barra de Acero Aleteado - 6mm x 12m | F16: =IFERROR(VLOOKUP(D16,MATERIALES!A:C,3,FALSE()),"?") -> u | G16: 0.17 | H16: 0.1 | I16: =IFERROR(VLOOKUP(D16,MATERIALES!A:D,4,FALSE()),0) -> 3424.53 | J16: =G16*I16*(1+H16) -> 640.38711 | K16: =A16&"|"&B16 -> ALB-033|MAT | L16: =COUNTIFS($K$2:K16,K16) -> 1 | M16: =K16&"|"&L16 -> ALB-033|MAT|1 | N16: =IFERROR(VLOOKUP(A16,PARTIDAS!A:F,6,FALSE()),0) -> 7 | O16: =+IF(C16="ALB",G16/N16,G16) -> 0.17 | P16: =+_xlfn.XLOOKUP(A16,PPTO_GENERADOR!Q:Q,PPTO_GENERADOR!E:E,"-",0) -> - | Q16: =IFERROR(P16*O16,0) -> 0 | R16: =+_xlfn.XLOOKUP(A16,PPTO_GENERADOR!$Q:$Q,PPTO_GENERADOR!A:A,"-",0) -> -
A17: ALB-033 | B17: MAT | C17: OTR | D17: AGR-001 | E17: =IFERROR(VLOOKUP(D17,MATERIALES!A:B,2,FALSE()),"?") -> ARENA LAVADA | F17: =IFERROR(VLOOKUP(D17,MATERIALES!A:C,3,FALSE()),"?") -> m3 | G17: 0.035 | H17: 0.1 | I17: =IFERROR(VLOOKUP(D17,MATERIALES!A:D,4,FALSE()),0) -> 32399.77 | J17: =G17*I17*(1+H17) -> 1247.3911 | K17: =A17&"|"&B17 -> ALB-033|MAT | L17: =COUNTIFS($K$2:K17,K17) -> 2 | M17: =K17&"|"&L17 -> ALB-033|MAT|2 | N17: =IFERROR(VLOOKUP(A17,PARTIDAS!A:F,6,FALSE()),0) -> 7 | O17: =+IF(C17="ALB",G17/N17,G17) -> 0.035 | P17: =+_xlfn.XLOOKUP(A17,PPTO_GENERADOR!Q:Q,PPTO_GENERADOR!E:E,"-",0) -> - | Q17: =IFERROR(P17*O17,0) -> 0 | R17: =+_xlfn.XLOOKUP(A17,PPTO_GENERADOR!$Q:$Q,PPTO_GENERADOR!A:A,"-",0) -> -
A18: ALB-033 | B18: MAT | C18: OTR | D18: AGR-004 | E18: =IFERROR(VLOOKUP(D18,MATERIALES!A:B,2,FALSE()),"?") -> Cemento Portland x 50kg | F18: =IFERROR(VLOOKUP(D18,MATERIALES!A:C,3,FALSE()),"?") -> Bol | G18: 0.15 | H18: 0.1 | I18: =IFERROR(VLOOKUP(D18,MATERIALES!A:D,4,FALSE()),0) -> 7809.48 | J18: =G18*I18*(1+H18) -> 1288.5642 | K18: =A18&"|"&B18 -> ALB-033|MAT | L18: =COUNTIFS($K$2:K18,K18) -> 3 | M18: =K18&"|"&L18 -> ALB-033|MAT|3 | N18: =IFERROR(VLOOKUP(A18,PARTIDAS!A:F,6,FALSE()),0) -> 7 | O18: =+IF(C18="ALB",G18/N18,G18) -> 0.15 | P18: =+_xlfn.XLOOKUP(A18,PPTO_GENERADOR!Q:Q,PPTO_GENERADOR!E:E,"-",0) -> - | Q18: =IFERROR(P18*O18,0) -> 0 | R18: =+_xlfn.XLOOKUP(A18,PPTO_GENERADOR!$Q:$Q,PPTO_GENERADOR!A:A,"-",0) -> -
A19: ALB-033 | B19: MAT | C19: OTR | D19: AGR-005 | E19: =IFERROR(VLOOKUP(D19,MATERIALES!A:B,2,FALSE()),"?") -> Cal Comun x 25kg | F19: =IFERROR(VLOOKUP(D19,MATERIALES!A:C,3,FALSE()),"?") -> bol | G19: 0.3 | H19: 0.1 | I19: =IFERROR(VLOOKUP(D19,MATERIALES!A:D,4,FALSE()),0) -> 3837.96 | J19: =G19*I19*(1+H19) -> 1266.5268 | K19: =A19&"|"&B19 -> ALB-033|MAT | L19: =COUNTIFS($K$2:K19,K19) -> 4 | M19: =K19&"|"&L19 -> ALB-033|MAT|4 | N19: =IFERROR(VLOOKUP(A19,PARTIDAS!A:F,6,FALSE()),0) -> 7 | O19: =+IF(C19="ALB",G19/N19,G19) -> 0.3 | P19: =+_xlfn.XLOOKUP(A19,PPTO_GENERADOR!Q:Q,PPTO_GENERADOR!E:E,"-",0) -> - | Q19: =IFERROR(P19*O19,0) -> 0 | R19: =+_xlfn.XLOOKUP(A19,PPTO_GENERADOR!$Q:$Q,PPTO_GENERADOR!A:A,"-",0) -> -
A20: ALB-033 | B20: MAT | C20: OTR | D20: CER-005 | E20: =IFERROR(VLOOKUP(D20,MATERIALES!A:B,2,FALSE()),"?") -> Ladrillo Comun 12.5 x 5.5 x 25 | F20: =IFERROR(VLOOKUP(D20,MATERIALES!A:C,3,FALSE()),"?") -> u | G20: 60 | H20: 0.05 | I20: =IFERROR(VLOOKUP(D20,MATERIALES!A:D,4,FALSE()),0) -> 132.3 | J20: =G20*I20*(1+H20) -> 8334.9 | K20: =A20&"|"&B20 -> ALB-033|MAT | L20: =COUNTIFS($K$2:K20,K20) -> 5 | M20: =K20&"|"&L20 -> ALB-033|MAT|5 | N20: =IFERROR(VLOOKUP(A20,PARTIDAS!A:F,6,FALSE()),0) -> 7 | O20: =+IF(C20="ALB",G20/N20,G20) -> 60 | P20: =+_xlfn.XLOOKUP(A20,PPTO_GENERADOR!Q:Q,PPTO_GENERADOR!E:E,"-",0) -> - | Q20: =IFERROR(P20*O20,0) -> 0 | R20: =+_xlfn.XLOOKUP(A20,PPTO_GENERADOR!$Q:$Q,PPTO_GENERADOR!A:A,"-",0) -> -
A21: ALB-033 | B21: MAT | C21: OTR | D21: MAT-CONS | E21: =IFERROR(VLOOKUP(D21,MATERIALES!A:B,2,FALSE()),"?") -> Consumibles | F21: =IFERROR(VLOOKUP(D21,MATERIALES!A:C,3,FALSE()),"?") -> gl | G21: 1.3161102 | H21: 0 | I21: =IFERROR(VLOOKUP(D21,MATERIALES!A:D,4,FALSE()),0) -> 1 | J21: =G21*I21*(1+H21) -> 1.3161102 | K21: =A21&"|"&B21 -> ALB-033|MAT | L21: =COUNTIFS($K$2:K21,K21) -> 6 | M21: =K21&"|"&L21 -> ALB-033|MAT|6 | N21: =IFERROR(VLOOKUP(A21,PARTIDAS!A:F,6,FALSE()),0) -> 7 | O21: =+IF(C21="ALB",G21/N21,G21) -> 1.3161102 | P21: =+_xlfn.XLOOKUP(A21,PPTO_GENERADOR!Q:Q,PPTO_GENERADOR!E:E,"-",0) -> - | Q21: =IFERROR(P21*O21,0) -> 0 | R21: =+_xlfn.XLOOKUP(A21,PPTO_GENERADOR!$Q:$Q,PPTO_GENERADOR!A:A,"-",0) -> -
A22: ALB-033 | B22: MO | C22: ALB | D22: MO-EAYUD | E22: =IFERROR(VLOOKUP(D22,MANO_DE_OBRA!A:B,2,FALSE()),"?") -> AYUDANTE | F22: j | G22: 1 | H22: 0 | I22: =IFERROR(VLOOKUP(D22,MANO_DE_OBRA!A:C,3,FALSE()),0) -> 60860.581 | J22: =G22*I22 -> 60860.581 | K22: =A22&"|"&B22 -> ALB-033|MO | L22: =COUNTIFS($K$2:K22,K22) -> 1 | M22: =K22&"|"&L22 -> ALB-033|MO|1 | N22: =IFERROR(VLOOKUP(A22,PARTIDAS!A:F,6,FALSE()),0) -> 7 | O22: =+IF(C22="ALB",G22/N22,G22) -> 0.14285714 | P22: =+_xlfn.XLOOKUP(A22,PPTO_GENERADOR!Q:Q,PPTO_GENERADOR!E:E,"-",0) -> - | Q22: =IFERROR(P22*O22,0) -> 0 | R22: =+_xlfn.XLOOKUP(A22,PPTO_GENERADOR!$Q:$Q,PPTO_GENERADOR!A:A,"-",0) -> -
A23: ALB-033 | B23: MO | C23: ALB | D23: MO-EESPE | E23: =IFERROR(VLOOKUP(D23,MANO_DE_OBRA!A:B,2,FALSE()),"?") -> ESPECIALIZADO | F23: j | G23: 1 | H23: 0 | I23: =IFERROR(VLOOKUP(D23,MANO_DE_OBRA!A:C,3,FALSE()),0) -> 85927.097 | J23: =G23*I23 -> 85927.097 | K23: =A23&"|"&B23 -> ALB-033|MO | L23: =COUNTIFS($K$2:K23,K23) -> 2 | M23: =K23&"|"&L23 -> ALB-033|MO|2 | N23: =IFERROR(VLOOKUP(A23,PARTIDAS!A:F,6,FALSE()),0) -> 7 | O23: =+IF(C23="ALB",G23/N23,G23) -> 0.14285714 | P23: =+_xlfn.XLOOKUP(A23,PPTO_GENERADOR!Q:Q,PPTO_GENERADOR!E:E,"-",0) -> - | Q23: =IFERROR(P23*O23,0) -> 0 | R23: =+_xlfn.XLOOKUP(A23,PPTO_GENERADOR!$Q:$Q,PPTO_GENERADOR!A:A,"-",0) -> -
A24: ALB-034 | B24: EQ | D24: EQ-ANDAM0 | E24: =IFERROR(VLOOKUP(D24,EQUIPOS!A:B,2,FALSE()),"?") -> ANDAMIO TUBULAR DE UNO A TRES CUERPOS | G24: 0.5 | H24: 0 | I24: =IFERROR(VLOOKUP(D24,EQUIPOS!A:F,6,FALSE()),0) -> 571.17949 | J24: =G24*I24 -> 285.58975 | K24: =A24&"|"&B24 -> ALB-034|EQ | L24: =COUNTIFS($K$2:K24,K24) -> 1 | M24: =K24&"|"&L24 -> ALB-034|EQ|1 | N24: =IFERROR(VLOOKUP(A24,PARTIDAS!A:F,6,FALSE()),0) -> 15 | O24: =+IF(C24="ALB",G24/N24,G24) -> 0.5 | P24: =+_xlfn.XLOOKUP(A24,PPTO_GENERADOR!Q:Q,PPTO_GENERADOR!E:E,"-",0) -> 621 | Q24: =IFERROR(P24*O24,0) -> 310.5 | R24: =+_xlfn.XLOOKUP(A24,PPTO_GENERADOR!$Q:$Q,PPTO_GENERADOR!A:A,"-",0) -> 4.01
A25: ALB-034 | B25: EQ | D25: EQ-EQALBA | E25: =IFERROR(VLOOKUP(D25,EQUIPOS!A:B,2,FALSE()),"?") -> EQUIPO DE ALBAÑILERIA, carpetas, ladrillo | G25: 1 | H25: 0 | I25: =IFERROR(VLOOKUP(D25,EQUIPOS!A:F,6,FALSE()),0) -> 2287.1357 | J25: =G25*I25 -> 2287.1357 | K25: =A25&"|"&B25 -> ALB-034|EQ | L25: =COUNTIFS($K$2:K25,K25) -> 2 | M25: =K25&"|"&L25 -> ALB-034|EQ|2 | N25: =IFERROR(VLOOKUP(A25,PARTIDAS!A:F,6,FALSE()),0) -> 15 | O25: =+IF(C25="ALB",G25/N25,G25) -> 1 | P25: =+_xlfn.XLOOKUP(A25,PPTO_GENERADOR!Q:Q,PPTO_GENERADOR!E:E,"-",0) -> 621 | Q25: =IFERROR(P25*O25,0) -> 621 | R25: =+_xlfn.XLOOKUP(A25,PPTO_GENERADOR!$Q:$Q,PPTO_GENERADOR!A:A,"-",0) -> 4.01
A26: ALB-034 | B26: EQ | D26: EQ-TROMPO | E26: =IFERROR(VLOOKUP(D26,EQUIPOS!A:B,2,FALSE()),"?") -> Hormigonera De 150 Litros 1hp Con Rueda Maciza | G26: 1 | H26: 0 | I26: =IFERROR(VLOOKUP(D26,EQUIPOS!A:F,6,FALSE()),0) -> 957.2532 | J26: =G26*I26 -> 957.2532 | K26: =A26&"|"&B26 -> ALB-034|EQ | L26: =COUNTIFS($K$2:K26,K26) -> 3 | M26: =K26&"|"&L26 -> ALB-034|EQ|3 | N26: =IFERROR(VLOOKUP(A26,PARTIDAS!A:F,6,FALSE()),0) -> 15 | O26: =+IF(C26="ALB",G26/N26,G26) -> 1 | P26: =+_xlfn.XLOOKUP(A26,PPTO_GENERADOR!Q:Q,PPTO_GENERADOR!E:E,"-",0) -> 621 | Q26: =IFERROR(P26*O26,0) -> 621 | R26: =+_xlfn.XLOOKUP(A26,PPTO_GENERADOR!$Q:$Q,PPTO_GENERADOR!A:A,"-",0) -> 4.01
A27: ALB-034 | B27: MAT | C27: OTR | D27: ACE-001 | E27: =IFERROR(VLOOKUP(D27,MATERIALES!A:B,2,FALSE()),"?") -> Barra de Acero Aleteado - 6mm x 12m | F27: =IFERROR(VLOOKUP(D27,MATERIALES!A:C,3,FALSE()),"?") -> u | G27: 0.17 | H27: 0.1 | I27: =IFERROR(VLOOKUP(D27,MATERIALES!A:D,4,FALSE()),0) -> 3424.53 | J27: =G27*I27*(1+H27) -> 640.38711 | K27: =A27&"|"&B27 -> ALB-034|MAT | L27: =COUNTIFS($K$2:K27,K27) -> 1 | M27: =K27&"|"&L27 -> ALB-034|MAT|1 | N27: =IFERROR(VLOOKUP(A27,PARTIDAS!A:F,6,FALSE()),0) -> 15 | O27: =+IF(C27="ALB",G27/N27,G27) -> 0.17 | P27: =+_xlfn.XLOOKUP(A27,PPTO_GENERADOR!Q:Q,PPTO_GENERADOR!E:E,"-",0) -> 621 | Q27: =IFERROR(P27*O27,0) -> 105.57 | R27: =+_xlfn.XLOOKUP(A27,PPTO_GENERADOR!$Q:$Q,PPTO_GENERADOR!A:A,"-",0) -> 4.01
A28: ALB-034 | B28: MAT | C28: OTR | D28: AGR-001 | E28: =IFERROR(VLOOKUP(D28,MATERIALES!A:B,2,FALSE()),"?") -> ARENA LAVADA | F28: =IFERROR(VLOOKUP(D28,MATERIALES!A:C,3,FALSE()),"?") -> m3 | G28: 0.012 | H28: 0.1 | I28: =IFERROR(VLOOKUP(D28,MATERIALES!A:D,4,FALSE()),0) -> 32399.77 | J28: =G28*I28*(1+H28) -> 427.67696 | K28: =A28&"|"&B28 -> ALB-034|MAT | L28: =COUNTIFS($K$2:K28,K28) -> 2 | M28: =K28&"|"&L28 -> ALB-034|MAT|2 | N28: =IFERROR(VLOOKUP(A28,PARTIDAS!A:F,6,FALSE()),0) -> 15 | O28: =+IF(C28="ALB",G28/N28,G28) -> 0.012 | P28: =+_xlfn.XLOOKUP(A28,PPTO_GENERADOR!Q:Q,PPTO_GENERADOR!E:E,"-",0) -> 621 | Q28: =IFERROR(P28*O28,0) -> 7.452 | R28: =+_xlfn.XLOOKUP(A28,PPTO_GENERADOR!$Q:$Q,PPTO_GENERADOR!A:A,"-",0) -> 4.01
A29: ALB-034 | B29: MAT | C29: OTR | D29: AGR-004 | E29: =IFERROR(VLOOKUP(D29,MATERIALES!A:B,2,FALSE()),"?") -> Cemento Portland x 50kg | F29: =IFERROR(VLOOKUP(D29,MATERIALES!A:C,3,FALSE()),"?") -> Bol | G29: 0.05 | H29: 0.1 | I29: =IFERROR(VLOOKUP(D29,MATERIALES!A:D,4,FALSE()),0) -> 7809.48 | J29: =G29*I29*(1+H29) -> 429.5214 | K29: =A29&"|"&B29 -> ALB-034|MAT | L29: =COUNTIFS($K$2:K29,K29) -> 3 | M29: =K29&"|"&L29 -> ALB-034|MAT|3 | N29: =IFERROR(VLOOKUP(A29,PARTIDAS!A:F,6,FALSE()),0) -> 15 | O29: =+IF(C29="ALB",G29/N29,G29) -> 0.05 | P29: =+_xlfn.XLOOKUP(A29,PPTO_GENERADOR!Q:Q,PPTO_GENERADOR!E:E,"-",0) -> 621 | Q29: =IFERROR(P29*O29,0) -> 31.05 | R29: =+_xlfn.XLOOKUP(A29,PPTO_GENERADOR!$Q:$Q,PPTO_GENERADOR!A:A,"-",0) -> 4.01
A30: ALB-034 | B30: MAT | C30: OTR | D30: AGR-005 | E30: =IFERROR(VLOOKUP(D30,MATERIALES!A:B,2,FALSE()),"?") -> Cal Comun x 25kg | F30: =IFERROR(VLOOKUP(D30,MATERIALES!A:C,3,FALSE()),"?") -> bol | G30: 0.1 | H30: 0.1 | I30: =IFERROR(VLOOKUP(D30,MATERIALES!A:D,4,FALSE()),0) -> 3837.96 | J30: =G30*I30*(1+H30) -> 422.1756 | K30: =A30&"|"&B30 -> ALB-034|MAT | L30: =COUNTIFS($K$2:K30,K30) -> 4 | M30: =K30&"|"&L30 -> ALB-034|MAT|4 | N30: =IFERROR(VLOOKUP(A30,PARTIDAS!A:F,6,FALSE()),0) -> 15 | O30: =+IF(C30="ALB",G30/N30,G30) -> 0.1 | P30: =+_xlfn.XLOOKUP(A30,PPTO_GENERADOR!Q:Q,PPTO_GENERADOR!E:E,"-",0) -> 621 | Q30: =IFERROR(P30*O30,0) -> 62.1 | R30: =+_xlfn.XLOOKUP(A30,PPTO_GENERADOR!$Q:$Q,PPTO_GENERADOR!A:A,"-",0) -> 4.01
A31: ALB-034 | B31: MAT | C31: OTR | D31: CER-002 | E31: =IFERROR(VLOOKUP(D31,MATERIALES!A:B,2,FALSE()),"?") -> LADRILLO CERAMICO 8 x 18 x 33 cm | F31: =IFERROR(VLOOKUP(D31,MATERIALES!A:C,3,FALSE()),"?") -> u | G31: 15 | H31: 0.05 | I31: =IFERROR(VLOOKUP(D31,MATERIALES!A:D,4,FALSE()),0) -> 292.32 | J31: =G31*I31*(1+H31) -> 4604.04 | K31: =A31&"|"&B31 -> ALB-034|MAT | L31: =COUNTIFS($K$2:K31,K31) -> 5 | M31: =K31&"|"&L31 -> ALB-034|MAT|5 | N31: =IFERROR(VLOOKUP(A31,PARTIDAS!A:F,6,FALSE()),0) -> 15 | O31: =+IF(C31="ALB",G31/N31,G31) -> 15 | P31: =+_xlfn.XLOOKUP(A31,PPTO_GENERADOR!Q:Q,PPTO_GENERADOR!E:E,"-",0) -> 621 | Q31: =IFERROR(P31*O31,0) -> 9315 | R31: =+_xlfn.XLOOKUP(A31,PPTO_GENERADOR!$Q:$Q,PPTO_GENERADOR!A:A,"-",0) -> 4.01
A32: ALB-034 | B32: MAT | C32: OTR | D32: MAT-CONS | E32: =IFERROR(VLOOKUP(D32,MATERIALES!A:B,2,FALSE()),"?") -> Consumibles | F32: =IFERROR(VLOOKUP(D32,MATERIALES!A:C,3,FALSE()),"?") -> gl | G32: 67.195151 | H32: 0 | I32: =IFERROR(VLOOKUP(D32,MATERIALES!A:D,4,FALSE()),0) -> 1 | J32: =G32*I32*(1+H32) -> 67.195151 | K32: =A32&"|"&B32 -> ALB-034|MAT | L32: =COUNTIFS($K$2:K32,K32) -> 6 | M32: =K32&"|"&L32 -> ALB-034|MAT|6 | N32: =IFERROR(VLOOKUP(A32,PARTIDAS!A:F,6,FALSE()),0) -> 15 | O32: =+IF(C32="ALB",G32/N32,G32) -> 67.195151 | P32: =+_xlfn.XLOOKUP(A32,PPTO_GENERADOR!Q:Q,PPTO_GENERADOR!E:E,"-",0) -> 621 | Q32: =IFERROR(P32*O32,0) -> 41728.189 | R32: =+_xlfn.XLOOKUP(A32,PPTO_GENERADOR!$Q:$Q,PPTO_GENERADOR!A:A,"-",0) -> 4.01
A33: ALB-034 | B33: MO | C33: ALB | D33: MO-EAYUD | E33: =IFERROR(VLOOKUP(D33,MANO_DE_OBRA!A:B,2,FALSE()),"?") -> AYUDANTE | F33: j | G33: 1 | H33: 0 | I33: =IFERROR(VLOOKUP(D33,MANO_DE_OBRA!A:C,3,FALSE()),0) -> 60860.581 | J33: =G33*I33 -> 60860.581 | K33: =A33&"|"&B33 -> ALB-034|MO | L33: =COUNTIFS($K$2:K33,K33) -> 1 | M33: =K33&"|"&L33 -> ALB-034|MO|1 | N33: =IFERROR(VLOOKUP(A33,PARTIDAS!A:F,6,FALSE()),0) -> 15 | O33: =+IF(C33="ALB",G33/N33,G33) -> 0.066666667 | P33: =+_xlfn.XLOOKUP(A33,PPTO_GENERADOR!Q:Q,PPTO_GENERADOR!E:E,"-",0) -> 621 | Q33: =IFERROR(P33*O33,0) -> 41.4 | R33: =+_xlfn.XLOOKUP(A33,PPTO_GENERADOR!$Q:$Q,PPTO_GENERADOR!A:A,"-",0) -> 4.01
A34: ALB-034 | B34: MO | C34: ALB | D34: MO-EESPE | E34: =IFERROR(VLOOKUP(D34,MANO_DE_OBRA!A:B,2,FALSE()),"?") -> ESPECIALIZADO | F34: j | G34: 1 | H34: 0 | I34: =IFERROR(VLOOKUP(D34,MANO_DE_OBRA!A:C,3,FALSE()),0) -> 85927.097 | J34: =G34*I34 -> 85927.097 | K34: =A34&"|"&B34 -> ALB-034|MO | L34: =COUNTIFS($K$2:K34,K34) -> 2 | M34: =K34&"|"&L34 -> ALB-034|MO|2 | N34: =IFERROR(VLOOKUP(A34,PARTIDAS!A:F,6,FALSE()),0) -> 15 | O34: =+IF(C34="ALB",G34/N34,G34) -> 0.066666667 | P34: =+_xlfn.XLOOKUP(A34,PPTO_GENERADOR!Q:Q,PPTO_GENERADOR!E:E,"-",0) -> 621 | Q34: =IFERROR(P34*O34,0) -> 41.4 | R34: =+_xlfn.XLOOKUP(A34,PPTO_GENERADOR!$Q:$Q,PPTO_GENERADOR!A:A,"-",0) -> 4.01
A35: ALB-035 | B35: EQ | D35: EQ-ANDAM0 | E35: =IFERROR(VLOOKUP(D35,EQUIPOS!A:B,2,FALSE()),"?") -> ANDAMIO TUBULAR DE UNO A TRES CUERPOS | G35: 0.5 | H35: 0 | I35: =IFERROR(VLOOKUP(D35,EQUIPOS!A:F,6,FALSE()),0) -> 571.17949 | J35: =G35*I35 -> 285.58975 | K35: =A35&"|"&B35 -> ALB-035|EQ | L35: =COUNTIFS($K$2:K35,K35) -> 1 | M35: =K35&"|"&L35 -> ALB-035|EQ|1 | N35: =IFERROR(VLOOKUP(A35,PARTIDAS!A:F,6,FALSE()),0) -> 15 | O35: =+IF(C35="ALB",G35/N35,G35) -> 0.5 | P35: =+_xlfn.XLOOKUP(A35,PPTO_GENERADOR!Q:Q,PPTO_GENERADOR!E:E,"-",0) -> 780 | Q35: =IFERROR(P35*O35,0) -> 390 | R35: =+_xlfn.XLOOKUP(A35,PPTO_GENERADOR!$Q:$Q,PPTO_GENERADOR!A:A,"-",0) -> 4.02
A36: ALB-035 | B36: EQ | D36: EQ-EQALBA | E36: =IFERROR(VLOOKUP(D36,EQUIPOS!A:B,2,FALSE()),"?") -> EQUIPO DE ALBAÑILERIA, carpetas, ladrillo | G36: 1 | H36: 0 | I36: =IFERROR(VLOOKUP(D36,EQUIPOS!A:F,6,FALSE()),0) -> 2287.1357 | J36: =G36*I36 -> 2287.1357 | K36: =A36&"|"&B36 -> ALB-035|EQ | L36: =COUNTIFS($K$2:K36,K36) -> 2 | M36: =K36&"|"&L36 -> ALB-035|EQ|2 | N36: =IFERROR(VLOOKUP(A36,PARTIDAS!A:F,6,FALSE()),0) -> 15 | O36: =+IF(C36="ALB",G36/N36,G36) -> 1 | P36: =+_xlfn.XLOOKUP(A36,PPTO_GENERADOR!Q:Q,PPTO_GENERADOR!E:E,"-",0) -> 780 | Q36: =IFERROR(P36*O36,0) -> 780 | R36: =+_xlfn.XLOOKUP(A36,PPTO_GENERADOR!$Q:$Q,PPTO_GENERADOR!A:A,"-",0) -> 4.02
A37: ALB-035 | B37: EQ | D37: EQ-TROMPO | E37: =IFERROR(VLOOKUP(D37,EQUIPOS!A:B,2,FALSE()),"?") -> Hormigonera De 150 Litros 1hp Con Rueda Maciza | G37: 1 | H37: 0 | I37: =IFERROR(VLOOKUP(D37,EQUIPOS!A:F,6,FALSE()),0) -> 957.2532 | J37: =G37*I37 -> 957.2532 | K37: =A37&"|"&B37 -> ALB-035|EQ | L37: =COUNTIFS($K$2:K37,K37) -> 3 | M37: =K37&"|"&L37 -> ALB-035|EQ|3 | N37: =IFERROR(VLOOKUP(A37,PARTIDAS!A:F,6,FALSE()),0) -> 15 | O37: =+IF(C37="ALB",G37/N37,G37) -> 1 | P37: =+_xlfn.XLOOKUP(A37,PPTO_GENERADOR!Q:Q,PPTO_GENERADOR!E:E,"-",0) -> 780 | Q37: =IFERROR(P37*O37,0) -> 780 | R37: =+_xlfn.XLOOKUP(A37,PPTO_GENERADOR!$Q:$Q,PPTO_GENERADOR!A:A,"-",0) -> 4.02
A38: ALB-035 | B38: MAT | C38: OTR | D38: ACE-001 | E38: =IFERROR(VLOOKUP(D38,MATERIALES!A:B,2,FALSE()),"?") -> Barra de Acero Aleteado - 6mm x 12m | F38: =IFERROR(VLOOKUP(D38,MATERIALES!A:C,3,FALSE()),"?") -> u | G38: 0.17 | H38: 0.1 | I38: =IFERROR(VLOOKUP(D38,MATERIALES!A:D,4,FALSE()),0) -> 3424.53 | J38: =G38*I38*(1+H38) -> 640.38711 | K38: =A38&"|"&B38 -> ALB-035|MAT | L38: =COUNTIFS($K$2:K38,K38) -> 1 | M38: =K38&"|"&L38 -> ALB-035|MAT|1 | N38: =IFERROR(VLOOKUP(A38,PARTIDAS!A:F,6,FALSE()),0) -> 15 | O38: =+IF(C38="ALB",G38/N38,G38) -> 0.17 | P38: =+_xlfn.XLOOKUP(A38,PPTO_GENERADOR!Q:Q,PPTO_GENERADOR!E:E,"-",0) -> 780 | Q38: =IFERROR(P38*O38,0) -> 132.6 | R38: =+_xlfn.XLOOKUP(A38,PPTO_GENERADOR!$Q:$Q,PPTO_GENERADOR!A:A,"-",0) -> 4.02
A39: ALB-035 | B39: MAT | C39: OTR | D39: AGR-001 | E39: =IFERROR(VLOOKUP(D39,MATERIALES!A:B,2,FALSE()),"?") -> ARENA LAVADA | F39: =IFERROR(VLOOKUP(D39,MATERIALES!A:C,3,FALSE()),"?") -> m3 | G39: 0.018 | H39: 0.1 | I39: =IFERROR(VLOOKUP(D39,MATERIALES!A:D,4,FALSE()),0) -> 32399.77 | J39: =G39*I39*(1+H39) -> 641.51545 | K39: =A39&"|"&B39 -> ALB-035|MAT | L39: =COUNTIFS($K$2:K39,K39) -> 2 | M39: =K39&"|"&L39 -> ALB-035|MAT|2 | N39: =IFERROR(VLOOKUP(A39,PARTIDAS!A:F,6,FALSE()),0) -> 15 | O39: =+IF(C39="ALB",G39/N39,G39) -> 0.018 | P39: =+_xlfn.XLOOKUP(A39,PPTO_GENERADOR!Q:Q,PPTO_GENERADOR!E:E,"-",0) -> 780 | Q39: =IFERROR(P39*O39,0) -> 14.04 | R39: =+_xlfn.XLOOKUP(A39,PPTO_GENERADOR!$Q:$Q,PPTO_GENERADOR!A:A,"-",0) -> 4.02
A40: ALB-035 | B40: MAT | C40: OTR | D40: AGR-004 | E40: =IFERROR(VLOOKUP(D40,MATERIALES!A:B,2,FALSE()),"?") -> Cemento Portland x 50kg | F40: =IFERROR(VLOOKUP(D40,MATERIALES!A:C,3,FALSE()),"?") -> Bol | G40: 0.075 | H40: 0.1 | I40: =IFERROR(VLOOKUP(D40,MATERIALES!A:D,4,FALSE()),0) -> 7809.48 | J40: =G40*I40*(1+H40) -> 644.2821 | K40: =A40&"|"&B40 -> ALB-035|MAT | L40: =COUNTIFS($K$2:K40,K40) -> 3 | M40: =K40&"|"&L40 -> ALB-035|MAT|3 | N40: =IFERROR(VLOOKUP(A40,PARTIDAS!A:F,6,FALSE()),0) -> 15 | O40: =+IF(C40="ALB",G40/N40,G40) -> 0.075 | P40: =+_xlfn.XLOOKUP(A40,PPTO_GENERADOR!Q:Q,PPTO_GENERADOR!E:E,"-",0) -> 780 | Q40: =IFERROR(P40*O40,0) -> 58.5 | R40: =+_xlfn.XLOOKUP(A40,PPTO_GENERADOR!$Q:$Q,PPTO_GENERADOR!A:A,"-",0) -> 4.02
A41: ALB-035 | B41: MAT | C41: OTR | D41: AGR-005 | E41: =IFERROR(VLOOKUP(D41,MATERIALES!A:B,2,FALSE()),"?") -> Cal Comun x 25kg | F41: =IFERROR(VLOOKUP(D41,MATERIALES!A:C,3,FALSE()),"?") -> bol | G41: 0.15 | H41: 0.1 | I41: =IFERROR(VLOOKUP(D41,MATERIALES!A:D,4,FALSE()),0) -> 3837.96 | J41: =G41*I41*(1+H41) -> 633.2634 | K41: =A41&"|"&B41 -> ALB-035|MAT | L41: =COUNTIFS($K$2:K41,K41) -> 4 | M41: =K41&"|"&L41 -> ALB-035|MAT|4 | N41: =IFERROR(VLOOKUP(A41,PARTIDAS!A:F,6,FALSE()),0) -> 15 | O41: =+IF(C41="ALB",G41/N41,G41) -> 0.15 | P41: =+_xlfn.XLOOKUP(A41,PPTO_GENERADOR!Q:Q,PPTO_GENERADOR!E:E,"-",0) -> 780 | Q41: =IFERROR(P41*O41,0) -> 117 | R41: =+_xlfn.XLOOKUP(A41,PPTO_GENERADOR!$Q:$Q,PPTO_GENERADOR!A:A,"-",0) -> 4.02
A42: ALB-035 | B42: MAT | C42: OTR | D42: CER-003 | E42: =IFERROR(VLOOKUP(D42,MATERIALES!A:B,2,FALSE()),"?") -> LADRILLO CERAMICO 12 x 18 x 33 cm | F42: =IFERROR(VLOOKUP(D42,MATERIALES!A:C,3,FALSE()),"?") -> u | G42: 15 | H42: 0.05 | I42: =IFERROR(VLOOKUP(D42,MATERIALES!A:D,4,FALSE()),0) -> 365.4 | J42: =G42*I42*(1+H42) -> 5755.05 | K42: =A42&"|"&B42 -> ALB-035|MAT | L42: =COUNTIFS($K$2:K42,K42) -> 5 | M42: =K42&"|"&L42 -> ALB-035|MAT|5 | N42: =IFERROR(VLOOKUP(A42,PARTIDAS!A:F,6,FALSE()),0) -> 15 | O42: =+IF(C42="ALB",G42/N42,G42) -> 15 | P42: =+_xlfn.XLOOKUP(A42,PPTO_GENERADOR!Q:Q,PPTO_GENERADOR!E:E,"-",0) -> 780 | Q42: =IFERROR(P42*O42,0) -> 11700 | R42: =+_xlfn.XLOOKUP(A42,PPTO_GENERADOR!$Q:$Q,PPTO_GENERADOR!A:A,"-",0) -> 4.02
A43: ALB-035 | B43: MAT | C43: OTR | D43: MAT-CONS | E43: =IFERROR(VLOOKUP(D43,MATERIALES!A:B,2,FALSE()),"?") -> Consumibles | F43: =IFERROR(VLOOKUP(D43,MATERIALES!A:C,3,FALSE()),"?") -> gl | G43: 85.63933 | H43: 0 | I43: =IFERROR(VLOOKUP(D43,MATERIALES!A:D,4,FALSE()),0) -> 1 | J43: =G43*I43*(1+H43) -> 85.63933 | K43: =A43&"|"&B43 -> ALB-035|MAT | L43: =COUNTIFS($K$2:K43,K43) -> 6 | M43: =K43&"|"&L43 -> ALB-035|MAT|6 | N43: =IFERROR(VLOOKUP(A43,PARTIDAS!A:F,6,FALSE()),0) -> 15 | O43: =+IF(C43="ALB",G43/N43,G43) -> 85.63933 | P43: =+_xlfn.XLOOKUP(A43,PPTO_GENERADOR!Q:Q,PPTO_GENERADOR!E:E,"-",0) -> 780 | Q43: =IFERROR(P43*O43,0) -> 66798.677 | R43: =+_xlfn.XLOOKUP(A43,PPTO_GENERADOR!$Q:$Q,PPTO_GENERADOR!A:A,"-",0) -> 4.02
A44: ALB-035 | B44: MO | C44: ALB | D44: MO-EAYUD | E44: =IFERROR(VLOOKUP(D44,MANO_DE_OBRA!A:B,2,FALSE()),"?") -> AYUDANTE | F44: j | G44: 1 | H44: 0 | I44: =IFERROR(VLOOKUP(D44,MANO_DE_OBRA!A:C,3,FALSE()),0) -> 60860.581 | J44: =G44*I44 -> 60860.581 | K44: =A44&"|"&B44 -> ALB-035|MO | L44: =COUNTIFS($K$2:K44,K44) -> 1 | M44: =K44&"|"&L44 -> ALB-035|MO|1 | N44: =IFERROR(VLOOKUP(A44,PARTIDAS!A:F,6,FALSE()),0) -> 15 | O44: =+IF(C44="ALB",G44/N44,G44) -> 0.066666667 | P44: =+_xlfn.XLOOKUP(A44,PPTO_GENERADOR!Q:Q,PPTO_GENERADOR!E:E,"-",0) -> 780 | Q44: =IFERROR(P44*O44,0) -> 52 | R44: =+_xlfn.XLOOKUP(A44,PPTO_GENERADOR!$Q:$Q,PPTO_GENERADOR!A:A,"-",0) -> 4.02
A45: ALB-035 | B45: MO | C45: ALB | D45: MO-EESPE | E45: =IFERROR(VLOOKUP(D45,MANO_DE_OBRA!A:B,2,FALSE()),"?") -> ESPECIALIZADO | F45: j | G45: 1 | H45: 0 | I45: =IFERROR(VLOOKUP(D45,MANO_DE_OBRA!A:C,3,FALSE()),0) -> 85927.097 | J45: =G45*I45 -> 85927.097 | K45: =A45&"|"&B45 -> ALB-035|MO | L45: =COUNTIFS($K$2:K45,K45) -> 2 | M45: =K45&"|"&L45 -> ALB-035|MO|2 | N45: =IFERROR(VLOOKUP(A45,PARTIDAS!A:F,6,FALSE()),0) -> 15 | O45: =+IF(C45="ALB",G45/N45,G45) -> 0.066666667 | P45: =+_xlfn.XLOOKUP(A45,PPTO_GENERADOR!Q:Q,PPTO_GENERADOR!E:E,"-",0) -> 780 | Q45: =IFERROR(P45*O45,0) -> 52 | R45: =+_xlfn.XLOOKUP(A45,PPTO_GENERADOR!$Q:$Q,PPTO_GENERADOR!A:A,"-",0) -> 4.02
A46: ALB-036 | B46: EQ | D46: EQ-ANDAM0 | E46: =IFERROR(VLOOKUP(D46,EQUIPOS!A:B,2,FALSE()),"?") -> ANDAMIO TUBULAR DE UNO A TRES CUERPOS | G46: 0.5 | H46: 0 | I46: =IFERROR(VLOOKUP(D46,EQUIPOS!A:F,6,FALSE()),0) -> 571.17949 | J46: =G46*I46 -> 285.58975 | K46: =A46&"|"&B46 -> ALB-036|EQ | L46: =COUNTIFS($K$2:K46,K46) -> 1 | M46: =K46&"|"&L46 -> ALB-036|EQ|1 | N46: =IFERROR(VLOOKUP(A46,PARTIDAS!A:F,6,FALSE()),0) -> 15 | O46: =+IF(C46="ALB",G46/N46,G46) -> 0.5 | P46: =+_xlfn.XLOOKUP(A46,PPTO_GENERADOR!Q:Q,PPTO_GENERADOR!E:E,"-",0) -> 5 | Q46: =IFERROR(P46*O46,0) -> 2.5 | R46: =+_xlfn.XLOOKUP(A46,PPTO_GENERADOR!$Q:$Q,PPTO_GENERADOR!A:A,"-",0) -> 4.06
A47: ALB-036 | B47: EQ | D47: EQ-EQALBA | E47: =IFERROR(VLOOKUP(D47,EQUIPOS!A:B,2,FALSE()),"?") -> EQUIPO DE ALBAÑILERIA, carpetas, ladrillo | G47: 1 | H47: 0 | I47: =IFERROR(VLOOKUP(D47,EQUIPOS!A:F,6,FALSE()),0) -> 2287.1357 | J47: =G47*I47 -> 2287.1357 | K47: =A47&"|"&B47 -> ALB-036|EQ | L47: =COUNTIFS($K$2:K47,K47) -> 2 | M47: =K47&"|"&L47 -> ALB-036|EQ|2 | N47: =IFERROR(VLOOKUP(A47,PARTIDAS!A:F,6,FALSE()),0) -> 15 | O47: =+IF(C47="ALB",G47/N47,G47) -> 1 | P47: =+_xlfn.XLOOKUP(A47,PPTO_GENERADOR!Q:Q,PPTO_GENERADOR!E:E,"-",0) -> 5 | Q47: =IFERROR(P47*O47,0) -> 5 | R47: =+_xlfn.XLOOKUP(A47,PPTO_GENERADOR!$Q:$Q,PPTO_GENERADOR!A:A,"-",0) -> 4.06
A48: ALB-036 | B48: EQ | D48: EQ-TROMPO | E48: =IFERROR(VLOOKUP(D48,EQUIPOS!A:B,2,FALSE()),"?") -> Hormigonera De 150 Litros 1hp Con Rueda Maciza | G48: 1 | H48: 0 | I48: =IFERROR(VLOOKUP(D48,EQUIPOS!A:F,6,FALSE()),0) -> 957.2532 | J48: =G48*I48 -> 957.2532 | K48: =A48&"|"&B48 -> ALB-036|EQ | L48: =COUNTIFS($K$2:K48,K48) -> 3 | M48: =K48&"|"&L48 -> ALB-036|EQ|3 | N48: =IFERROR(VLOOKUP(A48,PARTIDAS!A:F,6,FALSE()),0) -> 15 | O48: =+IF(C48="ALB",G48/N48,G48) -> 1 | P48: =+_xlfn.XLOOKUP(A48,PPTO_GENERADOR!Q:Q,PPTO_GENERADOR!E:E,"-",0) -> 5 | Q48: =IFERROR(P48*O48,0) -> 5 | R48: =+_xlfn.XLOOKUP(A48,PPTO_GENERADOR!$Q:$Q,PPTO_GENERADOR!A:A,"-",0) -> 4.06
A49: ALB-036 | B49: MAT | C49: OTR | D49: ACE-001 | E49: =IFERROR(VLOOKUP(D49,MATERIALES!A:B,2,FALSE()),"?") -> Barra de Acero Aleteado - 6mm x 12m | F49: =IFERROR(VLOOKUP(D49,MATERIALES!A:C,3,FALSE()),"?") -> u | G49: 0.17 | H49: 0.1 | I49: =IFERROR(VLOOKUP(D49,MATERIALES!A:D,4,FALSE()),0) -> 3424.53 | J49: =G49*I49*(1+H49) -> 640.38711 | K49: =A49&"|"&B49 -> ALB-036|MAT | L49: =COUNTIFS($K$2:K49,K49) -> 1 | M49: =K49&"|"&L49 -> ALB-036|MAT|1 | N49: =IFERROR(VLOOKUP(A49,PARTIDAS!A:F,6,FALSE()),0) -> 15 | O49: =+IF(C49="ALB",G49/N49,G49) -> 0.17 | P49: =+_xlfn.XLOOKUP(A49,PPTO_GENERADOR!Q:Q,PPTO_GENERADOR!E:E,"-",0) -> 5 | Q49: =IFERROR(P49*O49,0) -> 0.85 | R49: =+_xlfn.XLOOKUP(A49,PPTO_GENERADOR!$Q:$Q,PPTO_GENERADOR!A:A,"-",0) -> 4.06
A50: ALB-036 | B50: MAT | C50: OTR | D50: AGR-001 | E50: =IFERROR(VLOOKUP(D50,MATERIALES!A:B,2,FALSE()),"?") -> ARENA LAVADA | F50: =IFERROR(VLOOKUP(D50,MATERIALES!A:C,3,FALSE()),"?") -> m3 | G50: 0.024 | H50: 0.1 | I50: =IFERROR(VLOOKUP(D50,MATERIALES!A:D,4,FALSE()),0) -> 32399.77 | J50: =G50*I50*(1+H50) -> 855.35393 | K50: =A50&"|"&B50 -> ALB-036|MAT | L50: =COUNTIFS($K$2:K50,K50) -> 2 | M50: =K50&"|"&L50 -> ALB-036|MAT|2 | N50: =IFERROR(VLOOKUP(A50,PARTIDAS!A:F,6,FALSE()),0) -> 15 | O50: =+IF(C50="ALB",G50/N50,G50) -> 0.024 | P50: =+_xlfn.XLOOKUP(A50,PPTO_GENERADOR!Q:Q,PPTO_GENERADOR!E:E,"-",0) -> 5 | Q50: =IFERROR(P50*O50,0) -> 0.12 | R50: =+_xlfn.XLOOKUP(A50,PPTO_GENERADOR!$Q:$Q,PPTO_GENERADOR!A:A,"-",0) -> 4.06
A51: ALB-036 | B51: MAT | C51: OTR | D51: AGR-004 | E51: =IFERROR(VLOOKUP(D51,MATERIALES!A:B,2,FALSE()),"?") -> Cemento Portland x 50kg | F51: =IFERROR(VLOOKUP(D51,MATERIALES!A:C,3,FALSE()),"?") -> Bol | G51: 0.1 | H51: 0.1 | I51: =IFERROR(VLOOKUP(D51,MATERIALES!A:D,4,FALSE()),0) -> 7809.48 | J51: =G51*I51*(1+H51) -> 859.0428 | K51: =A51&"|"&B51 -> ALB-036|MAT | L51: =COUNTIFS($K$2:K51,K51) -> 3 | M51: =K51&"|"&L51 -> ALB-036|MAT|3 | N51: =IFERROR(VLOOKUP(A51,PARTIDAS!A:F,6,FALSE()),0) -> 15 | O51: =+IF(C51="ALB",G51/N51,G51) -> 0.1 | P51: =+_xlfn.XLOOKUP(A51,PPTO_GENERADOR!Q:Q,PPTO_GENERADOR!E:E,"-",0) -> 5 | Q51: =IFERROR(P51*O51,0) -> 0.5 | R51: =+_xlfn.XLOOKUP(A51,PPTO_GENERADOR!$Q:$Q,PPTO_GENERADOR!A:A,"-",0) -> 4.06
A52: ALB-036 | B52: MAT | C52: OTR | D52: AGR-005 | E52: =IFERROR(VLOOKUP(D52,MATERIALES!A:B,2,FALSE()),"?") -> Cal Comun x 25kg | F52: =IFERROR(VLOOKUP(D52,MATERIALES!A:C,3,FALSE()),"?") -> bol | G52: 0.2 | H52: 0.1 | I52: =IFERROR(VLOOKUP(D52,MATERIALES!A:D,4,FALSE()),0) -> 3837.96 | J52: =G52*I52*(1+H52) -> 844.3512 | K52: =A52&"|"&B52 -> ALB-036|MAT | L52: =COUNTIFS($K$2:K52,K52) -> 4 | M52: =K52&"|"&L52 -> ALB-036|MAT|4 | N52: =IFERROR(VLOOKUP(A52,PARTIDAS!A:F,6,FALSE()),0) -> 15 | O52: =+IF(C52="ALB",G52/N52,G52) -> 0.2 | P52: =+_xlfn.XLOOKUP(A52,PPTO_GENERADOR!Q:Q,PPTO_GENERADOR!E:E,"-",0) -> 5 | Q52: =IFERROR(P52*O52,0) -> 1 | R52: =+_xlfn.XLOOKUP(A52,PPTO_GENERADOR!$Q:$Q,PPTO_GENERADOR!A:A,"-",0) -> 4.06
A53: ALB-036 | B53: MAT | C53: OTR | D53: CER-004 | E53: =IFERROR(VLOOKUP(D53,MATERIALES!A:B,2,FALSE()),"?") -> LADRILLO CERAMICO 18 x 18 x 33 cm | F53: =IFERROR(VLOOKUP(D53,MATERIALES!A:C,3,FALSE()),"?") -> u | G53: 15 | H53: 0.05 | I53: =IFERROR(VLOOKUP(D53,MATERIALES!A:D,4,FALSE()),0) -> 519.12 | J53: =G53*I53*(1+H53) -> 8176.14 | K53: =A53&"|"&B53 -> ALB-036|MAT | L53: =COUNTIFS($K$2:K53,K53) -> 5 | M53: =K53&"|"&L53 -> ALB-036|MAT|5 | N53: =IFERROR(VLOOKUP(A53,PARTIDAS!A:F,6,FALSE()),0) -> 15 | O53: =+IF(C53="ALB",G53/N53,G53) -> 15 | P53: =+_xlfn.XLOOKUP(A53,PPTO_GENERADOR!Q:Q,PPTO_GENERADOR!E:E,"-",0) -> 5 | Q53: =IFERROR(P53*O53,0) -> 75 | R53: =+_xlfn.XLOOKUP(A53,PPTO_GENERADOR!$Q:$Q,PPTO_GENERADOR!A:A,"-",0) -> 4.06
A54: ALB-036 | B54: MAT | C54: OTR | D54: MAT-CONS | E54: =IFERROR(VLOOKUP(D54,MATERIALES!A:B,2,FALSE()),"?") -> Consumibles | F54: =IFERROR(VLOOKUP(D54,MATERIALES!A:C,3,FALSE()),"?") -> gl | G54: 117.16533 | H54: 0 | I54: =IFERROR(VLOOKUP(D54,MATERIALES!A:D,4,FALSE()),0) -> 1 | J54: =G54*I54*(1+H54) -> 117.16533 | K54: =A54&"|"&B54 -> ALB-036|MAT | L54: =COUNTIFS($K$2:K54,K54) -> 6 | M54: =K54&"|"&L54 -> ALB-036|MAT|6 | N54: =IFERROR(VLOOKUP(A54,PARTIDAS!A:F,6,FALSE()),0) -> 15 | O54: =+IF(C54="ALB",G54/N54,G54) -> 117.16533 | P54: =+_xlfn.XLOOKUP(A54,PPTO_GENERADOR!Q:Q,PPTO_GENERADOR!E:E,"-",0) -> 5 | Q54: =IFERROR(P54*O54,0) -> 585.82666 | R54: =+_xlfn.XLOOKUP(A54,PPTO_GENERADOR!$Q:$Q,PPTO_GENERADOR!A:A,"-",0) -> 4.06
A55: ALB-036 | B55: MO | C55: ALB | D55: MO-EAYUD | E55: =IFERROR(VLOOKUP(D55,MANO_DE_OBRA!A:B,2,FALSE()),"?") -> AYUDANTE | F55: j | G55: 1 | H55: 0 | I55: =IFERROR(VLOOKUP(D55,MANO_DE_OBRA!A:C,3,FALSE()),0) -> 60860.581 | J55: =G55*I55 -> 60860.581 | K55: =A55&"|"&B55 -> ALB-036|MO | L55: =COUNTIFS($K$2:K55,K55) -> 1 | M55: =K55&"|"&L55 -> ALB-036|MO|1 | N55: =IFERROR(VLOOKUP(A55,PARTIDAS!A:F,6,FALSE()),0) -> 15 | O55: =+IF(C55="ALB",G55/N55,G55) -> 0.066666667 | P55: =+_xlfn.XLOOKUP(A55,PPTO_GENERADOR!Q:Q,PPTO_GENERADOR!E:E,"-",0) -> 5 | Q55: =IFERROR(P55*O55,0) -> 0.33333333 | R55: =+_xlfn.XLOOKUP(A55,PPTO_GENERADOR!$Q:$Q,PPTO_GENERADOR!A:A,"-",0) -> 4.06
A56: ALB-036 | B56: MO | C56: ALB | D56: MO-EESPE | E56: =IFERROR(VLOOKUP(D56,MANO_DE_OBRA!A:B,2,FALSE()),"?") -> ESPECIALIZADO | F56: j | G56: 1 | H56: 0 | I56: =IFERROR(VLOOKUP(D56,MANO_DE_OBRA!A:C,3,FALSE()),0) -> 85927.097 | J56: =G56*I56 -> 85927.097 | K56: =A56&"|"&B56 -> ALB-036|MO | L56: =COUNTIFS($K$2:K56,K56) -> 2 | M56: =K56&"|"&L56 -> ALB-036|MO|2 | N56: =IFERROR(VLOOKUP(A56,PARTIDAS!A:F,6,FALSE()),0) -> 15 | O56: =+IF(C56="ALB",G56/N56,G56) -> 0.066666667 | P56: =+_xlfn.XLOOKUP(A56,PPTO_GENERADOR!Q:Q,PPTO_GENERADOR!E:E,"-",0) -> 5 | Q56: =IFERROR(P56*O56,0) -> 0.33333333 | R56: =+_xlfn.XLOOKUP(A56,PPTO_GENERADOR!$Q:$Q,PPTO_GENERADOR!A:A,"-",0) -> 4.06
A57: ALB-037 | B57: EQ | D57: EQ-ANDAM0 | E57: =IFERROR(VLOOKUP(D57,EQUIPOS!A:B,2,FALSE()),"?") -> ANDAMIO TUBULAR DE UNO A TRES CUERPOS | G57: 0.5 | H57: 0 | I57: =IFERROR(VLOOKUP(D57,EQUIPOS!A:F,6,FALSE()),0) -> 571.17949 | J57: =G57*I57 -> 285.58975 | K57: =A57&"|"&B57 -> ALB-037|EQ | L57: =COUNTIFS($K$2:K57,K57) -> 1 | M57: =K57&"|"&L57 -> ALB-037|EQ|1 | N57: =IFERROR(VLOOKUP(A57,PARTIDAS!A:F,6,FALSE()),0) -> 4 | O57: =+IF(C57="ALB",G57/N57,G57) -> 0.5 | P57: =+_xlfn.XLOOKUP(A57,PPTO_GENERADOR!Q:Q,PPTO_GENERADOR!E:E,"-",0) -> - | Q57: =IFERROR(P57*O57,0) -> 0 | R57: =+_xlfn.XLOOKUP(A57,PPTO_GENERADOR!$Q:$Q,PPTO_GENERADOR!A:A,"-",0) -> -
A58: ALB-037 | B58: EQ | D58: EQ-EQALBA | E58: =IFERROR(VLOOKUP(D58,EQUIPOS!A:B,2,FALSE()),"?") -> EQUIPO DE ALBAÑILERIA, carpetas, ladrillo | G58: 1 | H58: 0 | I58: =IFERROR(VLOOKUP(D58,EQUIPOS!A:F,6,FALSE()),0) -> 2287.1357 | J58: =G58*I58 -> 2287.1357 | K58: =A58&"|"&B58 -> ALB-037|EQ | L58: =COUNTIFS($K$2:K58,K58) -> 2 | M58: =K58&"|"&L58 -> ALB-037|EQ|2 | N58: =IFERROR(VLOOKUP(A58,PARTIDAS!A:F,6,FALSE()),0) -> 4 | O58: =+IF(C58="ALB",G58/N58,G58) -> 1 | P58: =+_xlfn.XLOOKUP(A58,PPTO_GENERADOR!Q:Q,PPTO_GENERADOR!E:E,"-",0) -> - | Q58: =IFERROR(P58*O58,0) -> 0 | R58: =+_xlfn.XLOOKUP(A58,PPTO_GENERADOR!$Q:$Q,PPTO_GENERADOR!A:A,"-",0) -> -
A59: ALB-037 | B59: EQ | D59: EQ-TROMPO | E59: =IFERROR(VLOOKUP(D59,EQUIPOS!A:B,2,FALSE()),"?") -> Hormigonera De 150 Litros 1hp Con Rueda Maciza | G59: 1 | H59: 0 | I59: =IFERROR(VLOOKUP(D59,EQUIPOS!A:F,6,FALSE()),0) -> 957.2532 | J59: =G59*I59 -> 957.2532 | K59: =A59&"|"&B59 -> ALB-037|EQ | L59: =COUNTIFS($K$2:K59,K59) -> 3 | M59: =K59&"|"&L59 -> ALB-037|EQ|3 | N59: =IFERROR(VLOOKUP(A59,PARTIDAS!A:F,6,FALSE()),0) -> 4 | O59: =+IF(C59="ALB",G59/N59,G59) -> 1 | P59: =+_xlfn.XLOOKUP(A59,PPTO_GENERADOR!Q:Q,PPTO_GENERADOR!E:E,"-",0) -> - | Q59: =IFERROR(P59*O59,0) -> 0 | R59: =+_xlfn.XLOOKUP(A59,PPTO_GENERADOR!$Q:$Q,PPTO_GENERADOR!A:A,"-",0) -> -
A60: ALB-037 | B60: MAT | C60: OTR | D60: ACE-001 | E60: =IFERROR(VLOOKUP(D60,MATERIALES!A:B,2,FALSE()),"?") -> Barra de Acero Aleteado - 6mm x 12m | F60: =IFERROR(VLOOKUP(D60,MATERIALES!A:C,3,FALSE()),"?") -> u | G60: 0.34 | H60: 0.1 | I60: =IFERROR(VLOOKUP(D60,MATERIALES!A:D,4,FALSE()),0) -> 3424.53 | J60: =G60*I60*(1+H60) -> 1280.7742 | K60: =A60&"|"&B60 -> ALB-037|MAT | L60: =COUNTIFS($K$2:K60,K60) -> 1 | M60: =K60&"|"&L60 -> ALB-037|MAT|1 | N60: =IFERROR(VLOOKUP(A60,PARTIDAS!A:F,6,FALSE()),0) -> 4 | O60: =+IF(C60="ALB",G60/N60,G60) -> 0.34 | P60: =+_xlfn.XLOOKUP(A60,PPTO_GENERADOR!Q:Q,PPTO_GENERADOR!E:E,"-",0) -> - | Q60: =IFERROR(P60*O60,0) -> 0 | R60: =+_xlfn.XLOOKUP(A60,PPTO_GENERADOR!$Q:$Q,PPTO_GENERADOR!A:A,"-",0) -> -
A61: ALB-037 | B61: MAT | C61: OTR | D61: AGR-001 | E61: =IFERROR(VLOOKUP(D61,MATERIALES!A:B,2,FALSE()),"?") -> ARENA LAVADA | F61: =IFERROR(VLOOKUP(D61,MATERIALES!A:C,3,FALSE()),"?") -> m3 | G61: 0.053 | H61: 0.1 | I61: =IFERROR(VLOOKUP(D61,MATERIALES!A:D,4,FALSE()),0) -> 32399.77 | J61: =G61*I61*(1+H61) -> 1888.9066 | K61: =A61&"|"&B61 -> ALB-037|MAT | L61: =COUNTIFS($K$2:K61,K61) -> 2 | M61: =K61&"|"&L61 -> ALB-037|MAT|2 | N61: =IFERROR(VLOOKUP(A61,PARTIDAS!A:F,6,FALSE()),0) -> 4 | O61: =+IF(C61="ALB",G61/N61,G61) -> 0.053 | P61: =+_xlfn.XLOOKUP(A61,PPTO_GENERADOR!Q:Q,PPTO_GENERADOR!E:E,"-",0) -> - | Q61: =IFERROR(P61*O61,0) -> 0 | R61: =+_xlfn.XLOOKUP(A61,PPTO_GENERADOR!$Q:$Q,PPTO_GENERADOR!A:A,"-",0) -> -
A62: ALB-037 | B62: MAT | C62: OTR | D62: AGR-004 | E62: =IFERROR(VLOOKUP(D62,MATERIALES!A:B,2,FALSE()),"?") -> Cemento Portland x 50kg | F62: =IFERROR(VLOOKUP(D62,MATERIALES!A:C,3,FALSE()),"?") -> Bol | G62: 0.254 | H62: 0.1 | I62: =IFERROR(VLOOKUP(D62,MATERIALES!A:D,4,FALSE()),0) -> 7809.48 | J62: =G62*I62*(1+H62) -> 2181.9687 | K62: =A62&"|"&B62 -> ALB-037|MAT | L62: =COUNTIFS($K$2:K62,K62) -> 3 | M62: =K62&"|"&L62 -> ALB-037|MAT|3 | N62: =IFERROR(VLOOKUP(A62,PARTIDAS!A:F,6,FALSE()),0) -> 4 | O62: =+IF(C62="ALB",G62/N62,G62) -> 0.254 | P62: =+_xlfn.XLOOKUP(A62,PPTO_GENERADOR!Q:Q,PPTO_GENERADOR!E:E,"-",0) -> - | Q62: =IFERROR(P62*O62,0) -> 0 | R62: =+_xlfn.XLOOKUP(A62,PPTO_GENERADOR!$Q:$Q,PPTO_GENERADOR!A:A,"-",0) -> -
A63: ALB-037 | B63: MAT | C63: OTR | D63: AGR-005 | E63: =IFERROR(VLOOKUP(D63,MATERIALES!A:B,2,FALSE()),"?") -> Cal Comun x 25kg | F63: =IFERROR(VLOOKUP(D63,MATERIALES!A:C,3,FALSE()),"?") -> bol | G63: 0.4 | H63: 0.1 | I63: =IFERROR(VLOOKUP(D63,MATERIALES!A:D,4,FALSE()),0) -> 3837.96 | J63: =G63*I63*(1+H63) -> 1688.7024 | K63: =A63&"|"&B63 -> ALB-037|MAT | L63: =COUNTIFS($K$2:K63,K63) -> 4 | M63: =K63&"|"&L63 -> ALB-037|MAT|4 | N63: =IFERROR(VLOOKUP(A63,PARTIDAS!A:F,6,FALSE()),0) -> 4 | O63: =+IF(C63="ALB",G63/N63,G63) -> 0.4 | P63: =+_xlfn.XLOOKUP(A63,PPTO_GENERADOR!Q:Q,PPTO_GENERADOR!E:E,"-",0) -> - | Q63: =IFERROR(P63*O63,0) -> 0 | R63: =+_xlfn.XLOOKUP(A63,PPTO_GENERADOR!$Q:$Q,PPTO_GENERADOR!A:A,"-",0) -> -
A64: ALB-037 | B64: MAT | C64: OTR | D64: AIS-001 | E64: =IFERROR(VLOOKUP(D64,MATERIALES!A:B,2,FALSE()),"?") -> Aditivo Hidrofugo en pasta - Ceresita x 1kg | F64: =IFERROR(VLOOKUP(D64,MATERIALES!A:C,3,FALSE()),"?") -> kg | G64: 0.1 | H64: 0.05 | I64: =IFERROR(VLOOKUP(D64,MATERIALES!A:D,4,FALSE()),0) -> 1256.128 | J64: =G64*I64*(1+H64) -> 131.89344 | K64: =A64&"|"&B64 -> ALB-037|MAT | L64: =COUNTIFS($K$2:K64,K64) -> 5 | M64: =K64&"|"&L64 -> ALB-037|MAT|5 | N64: =IFERROR(VLOOKUP(A64,PARTIDAS!A:F,6,FALSE()),0) -> 4 | O64: =+IF(C64="ALB",G64/N64,G64) -> 0.1 | P64: =+_xlfn.XLOOKUP(A64,PPTO_GENERADOR!Q:Q,PPTO_GENERADOR!E:E,"-",0) -> - | Q64: =IFERROR(P64*O64,0) -> 0 | R64: =+_xlfn.XLOOKUP(A64,PPTO_GENERADOR!$Q:$Q,PPTO_GENERADOR!A:A,"-",0) -> -
A65: ALB-037 | B65: MAT | C65: OTR | D65: CER-002 | E65: =IFERROR(VLOOKUP(D65,MATERIALES!A:B,2,FALSE()),"?") -> LADRILLO CERAMICO 8 x 18 x 33 cm | F65: =IFERROR(VLOOKUP(D65,MATERIALES!A:C,3,FALSE()),"?") -> u | G65: 15 | H65: 0.05 | I65: =IFERROR(VLOOKUP(D65,MATERIALES!A:D,4,FALSE()),0) -> 292.32 | J65: =G65*I65*(1+H65) -> 4604.04 | K65: =A65&"|"&B65 -> ALB-037|MAT | L65: =COUNTIFS($K$2:K65,K65) -> 6 | M65: =K65&"|"&L65 -> ALB-037|MAT|6 | N65: =IFERROR(VLOOKUP(A65,PARTIDAS!A:F,6,FALSE()),0) -> 4 | O65: =+IF(C65="ALB",G65/N65,G65) -> 15 | P65: =+_xlfn.XLOOKUP(A65,PPTO_GENERADOR!Q:Q,PPTO_GENERADOR!E:E,"-",0) -> - | Q65: =IFERROR(P65*O65,0) -> 0 | R65: =+_xlfn.XLOOKUP(A65,PPTO_GENERADOR!$Q:$Q,PPTO_GENERADOR!A:A,"-",0) -> -
A66: ALB-037 | B66: MAT | C66: OTR | D66: CER-001 | E66: =IFERROR(VLOOKUP(D66,MATERIALES!A:B,2,FALSE()),"?") -> ladrillo a la vista 1 cara | F66: =IFERROR(VLOOKUP(D66,MATERIALES!A:C,3,FALSE()),"?") -> u | G66: 60 | H66: 0.05 | I66: =IFERROR(VLOOKUP(D66,MATERIALES!A:D,4,FALSE()),0) -> 233.44 | J66: =G66*I66*(1+H66) -> 14706.72 | K66: =A66&"|"&B66 -> ALB-037|MAT | L66: =COUNTIFS($K$2:K66,K66) -> 7 | M66: =K66&"|"&L66 -> ALB-037|MAT|7 | N66: =IFERROR(VLOOKUP(A66,PARTIDAS!A:F,6,FALSE()),0) -> 4 | O66: =+IF(C66="ALB",G66/N66,G66) -> 60 | P66: =+_xlfn.XLOOKUP(A66,PPTO_GENERADOR!Q:Q,PPTO_GENERADOR!E:E,"-",0) -> - | Q66: =IFERROR(P66*O66,0) -> 0 | R66: =+_xlfn.XLOOKUP(A66,PPTO_GENERADOR!$Q:$Q,PPTO_GENERADOR!A:A,"-",0) -> -
A67: ALB-037 | B67: MAT | C67: OTR | D67: MAT-CONS | E67: =IFERROR(VLOOKUP(D67,MATERIALES!A:B,2,FALSE()),"?") -> Consumibles | F67: =IFERROR(VLOOKUP(D67,MATERIALES!A:C,3,FALSE()),"?") -> gl | G67: 285.29 | H67: 0 | I67: =IFERROR(VLOOKUP(D67,MATERIALES!A:D,4,FALSE()),0) -> 1 | J67: =G67*I67*(1+H67) -> 285.29 | K67: =A67&"|"&B67 -> ALB-037|MAT | L67: =COUNTIFS($K$2:K67,K67) -> 8 | M67: =K67&"|"&L67 -> ALB-037|MAT|8 | N67: =IFERROR(VLOOKUP(A67,PARTIDAS!A:F,6,FALSE()),0) -> 4 | O67: =+IF(C67="ALB",G67/N67,G67) -> 285.29 | P67: =+_xlfn.XLOOKUP(A67,PPTO_GENERADOR!Q:Q,PPTO_GENERADOR!E:E,"-",0) -> - | Q67: =IFERROR(P67*O67,0) -> 0 | R67: =+_xlfn.XLOOKUP(A67,PPTO_GENERADOR!$Q:$Q,PPTO_GENERADOR!A:A,"-",0) -> -
A68: ALB-037 | B68: MAT | C68: OTR | D68: OTR-022 | E68: =IFERROR(VLOOKUP(D68,MATERIALES!A:B,2,FALSE()),"?") -> Aguarras Hydrarras Hydra x 18lts | F68: =IFERROR(VLOOKUP(D68,MATERIALES!A:C,3,FALSE()),"?") -> b | G68: 0.005 | H68: 0.05 | I68: =IFERROR(VLOOKUP(D68,MATERIALES!A:D,4,FALSE()),0) -> 26907.33 | J68: =G68*I68*(1+H68) -> 141.26348 | K68: =A68&"|"&B68 -> ALB-037|MAT | L68: =COUNTIFS($K$2:K68,K68) -> 9 | M68: =K68&"|"&L68 -> ALB-037|MAT|9 | N68: =IFERROR(VLOOKUP(A68,PARTIDAS!A:F,6,FALSE()),0) -> 4 | O68: =+IF(C68="ALB",G68/N68,G68) -> 0.005 | P68: =+_xlfn.XLOOKUP(A68,PPTO_GENERADOR!Q:Q,PPTO_GENERADOR!E:E,"-",0) -> - | Q68: =IFERROR(P68*O68,0) -> 0 | R68: =+_xlfn.XLOOKUP(A68,PPTO_GENERADOR!$Q:$Q,PPTO_GENERADOR!A:A,"-",0) -> -
A69: ALB-037 | B69: MAT | C69: OTR | D69: OTR-027 | E69: =IFERROR(VLOOKUP(D69,MATERIALES!A:B,2,FALSE()),"?") -> Rodillo de lana pelo largo N°22 - El Galgo | F69: =IFERROR(VLOOKUP(D69,MATERIALES!A:C,3,FALSE()),"?") -> u | G69: 0.01 | H69: 0.05 | I69: =IFERROR(VLOOKUP(D69,MATERIALES!A:D,4,FALSE()),0) -> 6678.36 | J69: =G69*I69*(1+H69) -> 70.12278 | K69: =A69&"|"&B69 -> ALB-037|MAT | L69: =COUNTIFS($K$2:K69,K69) -> 10 | M69: =K69&"|"&L69 -> ALB-037|MAT|10 | N69: =IFERROR(VLOOKUP(A69,PARTIDAS!A:F,6,FALSE()),0) -> 4 | O69: =+IF(C69="ALB",G69/N69,G69) -> 0.01 | P69: =+_xlfn.XLOOKUP(A69,PPTO_GENERADOR!Q:Q,PPTO_GENERADOR!E:E,"-",0) -> - | Q69: =IFERROR(P69*O69,0) -> 0 | R69: =+_xlfn.XLOOKUP(A69,PPTO_GENERADOR!$Q:$Q,PPTO_GENERADOR!A:A,"-",0) -> -
A70: ALB-037 | B70: MAT | C70: OTR | D70: PIN-008 | E70: =IFERROR(VLOOKUP(D70,MATERIALES!A:B,2,FALSE()),"?") -> Pintura Asfaltica Asfasol x18ts | F70: =IFERROR(VLOOKUP(D70,MATERIALES!A:C,3,FALSE()),"?") -> b | G70: 0.027777778 | H70: 0.1 | I70: =IFERROR(VLOOKUP(D70,MATERIALES!A:D,4,FALSE()),0) -> 32845.78 | J70: =G70*I70*(1+H70) -> 1003.6211 | K70: =A70&"|"&B70 -> ALB-037|MAT | L70: =COUNTIFS($K$2:K70,K70) -> 11 | M70: =K70&"|"&L70 -> ALB-037|MAT|11 | N70: =IFERROR(VLOOKUP(A70,PARTIDAS!A:F,6,FALSE()),0) -> 4 | O70: =+IF(C70="ALB",G70/N70,G70) -> 0.027777778 | P70: =+_xlfn.XLOOKUP(A70,PPTO_GENERADOR!Q:Q,PPTO_GENERADOR!E:E,"-",0) -> - | Q70: =IFERROR(P70*O70,0) -> 0 | R70: =+_xlfn.XLOOKUP(A70,PPTO_GENERADOR!$Q:$Q,PPTO_GENERADOR!A:A,"-",0) -> -
A71: ALB-037 | B71: MO | C71: ALB | D71: MO-EAYUD | E71: =IFERROR(VLOOKUP(D71,MANO_DE_OBRA!A:B,2,FALSE()),"?") -> AYUDANTE | F71: j | G71: 0.91 | H71: 0 | I71: =IFERROR(VLOOKUP(D71,MANO_DE_OBRA!A:C,3,FALSE()),0) -> 60860.581 | J71: =G71*I71 -> 55383.129 | K71: =A71&"|"&B71 -> ALB-037|MO | L71: =COUNTIFS($K$2:K71,K71) -> 1 | M71: =K71&"|"&L71 -> ALB-037|MO|1 | N71: =IFERROR(VLOOKUP(A71,PARTIDAS!A:F,6,FALSE()),0) -> 4 | O71: =+IF(C71="ALB",G71/N71,G71) -> 0.2275 | P71: =+_xlfn.XLOOKUP(A71,PPTO_GENERADOR!Q:Q,PPTO_GENERADOR!E:E,"-",0) -> - | Q71: =IFERROR(P71*O71,0) -> 0 | R71: =+_xlfn.XLOOKUP(A71,PPTO_GENERADOR!$Q:$Q,PPTO_GENERADOR!A:A,"-",0) -> -
A72: ALB-037 | B72: MO | C72: ALB | D72: MO-EESPE | E72: =IFERROR(VLOOKUP(D72,MANO_DE_OBRA!A:B,2,FALSE()),"?") -> ESPECIALIZADO | F72: j | G72: 1 | H72: 0 | I72: =IFERROR(VLOOKUP(D72,MANO_DE_OBRA!A:C,3,FALSE()),0) -> 85927.097 | J72: =G72*I72 -> 85927.097 | K72: =A72&"|"&B72 -> ALB-037|MO | L72: =COUNTIFS($K$2:K72,K72) -> 2 | M72: =K72&"|"&L72 -> ALB-037|MO|2 | N72: =IFERROR(VLOOKUP(A72,PARTIDAS!A:F,6,FALSE()),0) -> 4 | O72: =+IF(C72="ALB",G72/N72,G72) -> 0.25 | P72: =+_xlfn.XLOOKUP(A72,PPTO_GENERADOR!Q:Q,PPTO_GENERADOR!E:E,"-",0) -> - | Q72: =IFERROR(P72*O72,0) -> 0 | R72: =+_xlfn.XLOOKUP(A72,PPTO_GENERADOR!$Q:$Q,PPTO_GENERADOR!A:A,"-",0) -> -
A73: ALB-038 | B73: EQ | D73: EQ-ANDAM0 | E73: =IFERROR(VLOOKUP(D73,EQUIPOS!A:B,2,FALSE()),"?") -> ANDAMIO TUBULAR DE UNO A TRES CUERPOS | G73: 0.5 | H73: 0 | I73: =IFERROR(VLOOKUP(D73,EQUIPOS!A:F,6,FALSE()),0) -> 571.17949 | J73: =G73*I73 -> 285.58975 | K73: =A73&"|"&B73 -> ALB-038|EQ | L73: =COUNTIFS($K$2:K73,K73) -> 1 | M73: =K73&"|"&L73 -> ALB-038|EQ|1 | N73: =IFERROR(VLOOKUP(A73,PARTIDAS!A:F,6,FALSE()),0) -> 15 | O73: =+IF(C73="ALB",G73/N73,G73) -> 0.5 | P73: =+_xlfn.XLOOKUP(A73,PPTO_GENERADOR!Q:Q,PPTO_GENERADOR!E:E,"-",0) -> 42 | Q73: =IFERROR(P73*O73,0) -> 21 | R73: =+_xlfn.XLOOKUP(A73,PPTO_GENERADOR!$Q:$Q,PPTO_GENERADOR!A:A,"-",0) -> 4.04
A74: ALB-038 | B74: EQ | D74: EQ-EQALBA | E74: =IFERROR(VLOOKUP(D74,EQUIPOS!A:B,2,FALSE()),"?") -> EQUIPO DE ALBAÑILERIA, carpetas, ladrillo | G74: 1 | H74: 0 | I74: =IFERROR(VLOOKUP(D74,EQUIPOS!A:F,6,FALSE()),0) -> 2287.1357 | J74: =G74*I74 -> 2287.1357 | K74: =A74&"|"&B74 -> ALB-038|EQ | L74: =COUNTIFS($K$2:K74,K74) -> 2 | M74: =K74&"|"&L74 -> ALB-038|EQ|2 | N74: =IFERROR(VLOOKUP(A74,PARTIDAS!A:F,6,FALSE()),0) -> 15 | O74: =+IF(C74="ALB",G74/N74,G74) -> 1 | P74: =+_xlfn.XLOOKUP(A74,PPTO_GENERADOR!Q:Q,PPTO_GENERADOR!E:E,"-",0) -> 42 | Q74: =IFERROR(P74*O74,0) -> 42 | R74: =+_xlfn.XLOOKUP(A74,PPTO_GENERADOR!$Q:$Q,PPTO_GENERADOR!A:A,"-",0) -> 4.04
A75: ALB-038 | B75: EQ | D75: EQ-TROMPO | E75: =IFERROR(VLOOKUP(D75,EQUIPOS!A:B,2,FALSE()),"?") -> Hormigonera De 150 Litros 1hp Con Rueda Maciza | G75: 1 | H75: 0 | I75: =IFERROR(VLOOKUP(D75,EQUIPOS!A:F,6,FALSE()),0) -> 957.2532 | J75: =G75*I75 -> 957.2532 | K75: =A75&"|"&B75 -> ALB-038|EQ | L75: =COUNTIFS($K$2:K75,K75) -> 3 | M75: =K75&"|"&L75 -> ALB-038|EQ|3 | N75: =IFERROR(VLOOKUP(A75,PARTIDAS!A:F,6,FALSE()),0) -> 15 | O75: =+IF(C75="ALB",G75/N75,G75) -> 1 | P75: =+_xlfn.XLOOKUP(A75,PPTO_GENERADOR!Q:Q,PPTO_GENERADOR!E:E,"-",0) -> 42 | Q75: =IFERROR(P75*O75,0) -> 42 | R75: =+_xlfn.XLOOKUP(A75,PPTO_GENERADOR!$Q:$Q,PPTO_GENERADOR!A:A,"-",0) -> 4.04
A76: ALB-038 | B76: MAT | C76: OTR | D76: ACE-001 | E76: =IFERROR(VLOOKUP(D76,MATERIALES!A:B,2,FALSE()),"?") -> Barra de Acero Aleteado - 6mm x 12m | F76: =IFERROR(VLOOKUP(D76,MATERIALES!A:C,3,FALSE()),"?") -> u | G76: 0.17 | H76: 0.1 | I76: =IFERROR(VLOOKUP(D76,MATERIALES!A:D,4,FALSE()),0) -> 3424.53 | J76: =G76*I76*(1+H76) -> 640.38711 | K76: =A76&"|"&B76 -> ALB-038|MAT | L76: =COUNTIFS($K$2:K76,K76) -> 1 | M76: =K76&"|"&L76 -> ALB-038|MAT|1 | N76: =IFERROR(VLOOKUP(A76,PARTIDAS!A:F,6,FALSE()),0) -> 15 | O76: =+IF(C76="ALB",G76/N76,G76) -> 0.17 | P76: =+_xlfn.XLOOKUP(A76,PPTO_GENERADOR!Q:Q,PPTO_GENERADOR!E:E,"-",0) -> 42 | Q76: =IFERROR(P76*O76,0) -> 7.14 | R76: =+_xlfn.XLOOKUP(A76,PPTO_GENERADOR!$Q:$Q,PPTO_GENERADOR!A:A,"-",0) -> 4.04
A77: ALB-038 | B77: MAT | C77: OTR | D77: AGR-001 | E77: =IFERROR(VLOOKUP(D77,MATERIALES!A:B,2,FALSE()),"?") -> ARENA LAVADA | F77: =IFERROR(VLOOKUP(D77,MATERIALES!A:C,3,FALSE()),"?") -> m3 | G77: 0.018 | H77: 0.1 | I77: =IFERROR(VLOOKUP(D77,MATERIALES!A:D,4,FALSE()),0) -> 32399.77 | J77: =G77*I77*(1+H77) -> 641.51545 | K77: =A77&"|"&B77 -> ALB-038|MAT | L77: =COUNTIFS($K$2:K77,K77) -> 2 | M77: =K77&"|"&L77 -> ALB-038|MAT|2 | N77: =IFERROR(VLOOKUP(A77,PARTIDAS!A:F,6,FALSE()),0) -> 15 | O77: =+IF(C77="ALB",G77/N77,G77) -> 0.018 | P77: =+_xlfn.XLOOKUP(A77,PPTO_GENERADOR!Q:Q,PPTO_GENERADOR!E:E,"-",0) -> 42 | Q77: =IFERROR(P77*O77,0) -> 0.756 | R77: =+_xlfn.XLOOKUP(A77,PPTO_GENERADOR!$Q:$Q,PPTO_GENERADOR!A:A,"-",0) -> 4.04
A78: ALB-038 | B78: MAT | C78: OTR | D78: AGR-004 | E78: =IFERROR(VLOOKUP(D78,MATERIALES!A:B,2,FALSE()),"?") -> Cemento Portland x 50kg | F78: =IFERROR(VLOOKUP(D78,MATERIALES!A:C,3,FALSE()),"?") -> Bol | G78: 0.075 | H78: 0.1 | I78: =IFERROR(VLOOKUP(D78,MATERIALES!A:D,4,FALSE()),0) -> 7809.48 | J78: =G78*I78*(1+H78) -> 644.2821 | K78: =A78&"|"&B78 -> ALB-038|MAT | L78: =COUNTIFS($K$2:K78,K78) -> 3 | M78: =K78&"|"&L78 -> ALB-038|MAT|3 | N78: =IFERROR(VLOOKUP(A78,PARTIDAS!A:F,6,FALSE()),0) -> 15 | O78: =+IF(C78="ALB",G78/N78,G78) -> 0.075 | P78: =+_xlfn.XLOOKUP(A78,PPTO_GENERADOR!Q:Q,PPTO_GENERADOR!E:E,"-",0) -> 42 | Q78: =IFERROR(P78*O78,0) -> 3.15 | R78: =+_xlfn.XLOOKUP(A78,PPTO_GENERADOR!$Q:$Q,PPTO_GENERADOR!A:A,"-",0) -> 4.04
A79: ALB-038 | B79: MAT | C79: OTR | D79: AGR-005 | E79: =IFERROR(VLOOKUP(D79,MATERIALES!A:B,2,FALSE()),"?") -> Cal Comun x 25kg | F79: =IFERROR(VLOOKUP(D79,MATERIALES!A:C,3,FALSE()),"?") -> bol | G79: 0.15 | H79: 0.1 | I79: =IFERROR(VLOOKUP(D79,MATERIALES!A:D,4,FALSE()),0) -> 3837.96 | J79: =G79*I79*(1+H79) -> 633.2634 | K79: =A79&"|"&B79 -> ALB-038|MAT | L79: =COUNTIFS($K$2:K79,K79) -> 4 | M79: =K79&"|"&L79 -> ALB-038|MAT|4 | N79: =IFERROR(VLOOKUP(A79,PARTIDAS!A:F,6,FALSE()),0) -> 15 | O79: =+IF(C79="ALB",G79/N79,G79) -> 0.15 | P79: =+_xlfn.XLOOKUP(A79,PPTO_GENERADOR!Q:Q,PPTO_GENERADOR!E:E,"-",0) -> 42 | Q79: =IFERROR(P79*O79,0) -> 6.3 | R79: =+_xlfn.XLOOKUP(A79,PPTO_GENERADOR!$Q:$Q,PPTO_GENERADOR!A:A,"-",0) -> 4.04
A80: ALB-038 | B80: MAT | C80: OTR | D80: CER-006 | E80: =IFERROR(VLOOKUP(D80,MATERIALES!A:B,2,FALSE()),"?") -> Ladrillo hueco ceramico 12x19x33 - Portante | F80: =IFERROR(VLOOKUP(D80,MATERIALES!A:C,3,FALSE()),"?") -> u | G80: 15 | H80: 0.05 | I80: =IFERROR(VLOOKUP(D80,MATERIALES!A:D,4,FALSE()),0) -> 563.22 | J80: =G80*I80*(1+H80) -> 8870.715 | K80: =A80&"|"&B80 -> ALB-038|MAT | L80: =COUNTIFS($K$2:K80,K80) -> 5 | M80: =K80&"|"&L80 -> ALB-038|MAT|5 | N80: =IFERROR(VLOOKUP(A80,PARTIDAS!A:F,6,FALSE()),0) -> 15 | O80: =+IF(C80="ALB",G80/N80,G80) -> 15 | P80: =+_xlfn.XLOOKUP(A80,PPTO_GENERADOR!Q:Q,PPTO_GENERADOR!E:E,"-",0) -> 42 | Q80: =IFERROR(P80*O80,0) -> 630 | R80: =+_xlfn.XLOOKUP(A80,PPTO_GENERADOR!$Q:$Q,PPTO_GENERADOR!A:A,"-",0) -> 4.04
A81: ALB-038 | B81: MAT | C81: OTR | D81: MAT-CONS | E81: =IFERROR(VLOOKUP(D81,MATERIALES!A:B,2,FALSE()),"?") -> Consumibles | F81: =IFERROR(VLOOKUP(D81,MATERIALES!A:C,3,FALSE()),"?") -> gl | G81: 117.73068 | H81: 0 | I81: =IFERROR(VLOOKUP(D81,MATERIALES!A:D,4,FALSE()),0) -> 1 | J81: =G81*I81*(1+H81) -> 117.73068 | K81: =A81&"|"&B81 -> ALB-038|MAT | L81: =COUNTIFS($K$2:K81,K81) -> 6 | M81: =K81&"|"&L81 -> ALB-038|MAT|6 | N81: =IFERROR(VLOOKUP(A81,PARTIDAS!A:F,6,FALSE()),0) -> 15 | O81: =+IF(C81="ALB",G81/N81,G81) -> 117.73068 | P81: =+_xlfn.XLOOKUP(A81,PPTO_GENERADOR!Q:Q,PPTO_GENERADOR!E:E,"-",0) -> 42 | Q81: =IFERROR(P81*O81,0) -> 4944.6885 | R81: =+_xlfn.XLOOKUP(A81,PPTO_GENERADOR!$Q:$Q,PPTO_GENERADOR!A:A,"-",0) -> 4.04
A82: ALB-038 | B82: MO | C82: ALB | D82: MO-EAYUD | E82: =IFERROR(VLOOKUP(D82,MANO_DE_OBRA!A:B,2,FALSE()),"?") -> AYUDANTE | F82: j | G82: 1 | H82: 0 | I82: =IFERROR(VLOOKUP(D82,MANO_DE_OBRA!A:C,3,FALSE()),0) -> 60860.581 | J82: =G82*I82 -> 60860.581 | K82: =A82&"|"&B82 -> ALB-038|MO | L82: =COUNTIFS($K$2:K82,K82) -> 1 | M82: =K82&"|"&L82 -> ALB-038|MO|1 | N82: =IFERROR(VLOOKUP(A82,PARTIDAS!A:F,6,FALSE()),0) -> 15 | O82: =+IF(C82="ALB",G82/N82,G82) -> 0.066666667 | P82: =+_xlfn.XLOOKUP(A82,PPTO_GENERADOR!Q:Q,PPTO_GENERADOR!E:E,"-",0) -> 42 | Q82: =IFERROR(P82*O82,0) -> 2.8 | R82: =+_xlfn.XLOOKUP(A82,PPTO_GENERADOR!$Q:$Q,PPTO_GENERADOR!A:A,"-",0) -> 4.04
A83: ALB-038 | B83: MO | C83: ALB | D83: MO-EESPE | E83: =IFERROR(VLOOKUP(D83,MANO_DE_OBRA!A:B,2,FALSE()),"?") -> ESPECIALIZADO | F83: j | G83: 1 | H83: 0 | I83: =IFERROR(VLOOKUP(D83,MANO_DE_OBRA!A:C,3,FALSE()),0) -> 85927.097 | J83: =G83*I83 -> 85927.097 | K83: =A83&"|"&B83 -> ALB-038|MO | L83: =COUNTIFS($K$2:K83,K83) -> 2 | M83: =K83&"|"&L83 -> ALB-038|MO|2 | N83: =IFERROR(VLOOKUP(A83,PARTIDAS!A:F,6,FALSE()),0) -> 15 | O83: =+IF(C83="ALB",G83/N83,G83) -> 0.066666667 | P83: =+_xlfn.XLOOKUP(A83,PPTO_GENERADOR!Q:Q,PPTO_GENERADOR!E:E,"-",0) -> 42 | Q83: =IFERROR(P83*O83,0) -> 2.8 | R83: =+_xlfn.XLOOKUP(A83,PPTO_GENERADOR!$Q:$Q,PPTO_GENERADOR!A:A,"-",0) -> 4.04
A84: ALB-039 | B84: EQ | D84: EQ-EQALBA | E84: =IFERROR(VLOOKUP(D84,EQUIPOS!A:B,2,FALSE()),"?") -> EQUIPO DE ALBAÑILERIA, carpetas, ladrillo | G84: 0.25 | H84: 0 | I84: =IFERROR(VLOOKUP(D84,EQUIPOS!A:F,6,FALSE()),0) -> 2287.1357 | J84: =G84*I84 -> 571.78394 | K84: =A84&"|"&B84 -> ALB-039|EQ | L84: =COUNTIFS($K$2:K84,K84) -> 1 | M84: =K84&"|"&L84 -> ALB-039|EQ|1 | N84: =IFERROR(VLOOKUP(A84,PARTIDAS!A:F,6,FALSE()),0) -> 2 | O84: =+IF(C84="ALB",G84/N84,G84) -> 0.25 | P84: =+_xlfn.XLOOKUP(A84,PPTO_GENERADOR!Q:Q,PPTO_GENERADOR!E:E,"-",0) -> - | Q84: =IFERROR(P84*O84,0) -> 0 | R84: =+_xlfn.XLOOKUP(A84,PPTO_GENERADOR!$Q:$Q,PPTO_GENERADOR!A:A,"-",0) -> -
A85: ALB-039 | B85: EQ | D85: EQ-TROMPO | E85: =IFERROR(VLOOKUP(D85,EQUIPOS!A:B,2,FALSE()),"?") -> Hormigonera De 150 Litros 1hp Con Rueda Maciza | G85: 0.25 | H85: 0 | I85: =IFERROR(VLOOKUP(D85,EQUIPOS!A:F,6,FALSE()),0) -> 957.2532 | J85: =G85*I85 -> 239.3133 | K85: =A85&"|"&B85 -> ALB-039|EQ | L85: =COUNTIFS($K$2:K85,K85) -> 2 | M85: =K85&"|"&L85 -> ALB-039|EQ|2 | N85: =IFERROR(VLOOKUP(A85,PARTIDAS!A:F,6,FALSE()),0) -> 2 | O85: =+IF(C85="ALB",G85/N85,G85) -> 0.25 | P85: =+_xlfn.XLOOKUP(A85,PPTO_GENERADOR!Q:Q,PPTO_GENERADOR!E:E,"-",0) -> - | Q85: =IFERROR(P85*O85,0) -> 0 | R85: =+_xlfn.XLOOKUP(A85,PPTO_GENERADOR!$Q:$Q,PPTO_GENERADOR!A:A,"-",0) -> -
A86: ALB-039 | B86: MAT | C86: OTR | D86: AGR-001 | E86: =IFERROR(VLOOKUP(D86,MATERIALES!A:B,2,FALSE()),"?") -> ARENA LAVADA | F86: =IFERROR(VLOOKUP(D86,MATERIALES!A:C,3,FALSE()),"?") -> m3 | G86: 0.036 | H86: 0.1 | I86: =IFERROR(VLOOKUP(D86,MATERIALES!A:D,4,FALSE()),0) -> 32399.77 | J86: =G86*I86*(1+H86) -> 1283.0309 | K86: =A86&"|"&B86 -> ALB-039|MAT | L86: =COUNTIFS($K$2:K86,K86) -> 1 | M86: =K86&"|"&L86 -> ALB-039|MAT|1 | N86: =IFERROR(VLOOKUP(A86,PARTIDAS!A:F,6,FALSE()),0) -> 2 | O86: =+IF(C86="ALB",G86/N86,G86) -> 0.036 | P86: =+_xlfn.XLOOKUP(A86,PPTO_GENERADOR!Q:Q,PPTO_GENERADOR!E:E,"-",0) -> - | Q86: =IFERROR(P86*O86,0) -> 0 | R86: =+_xlfn.XLOOKUP(A86,PPTO_GENERADOR!$Q:$Q,PPTO_GENERADOR!A:A,"-",0) -> -
A87: ALB-039 | B87: MAT | C87: OTR | D87: AGR-004 | E87: =IFERROR(VLOOKUP(D87,MATERIALES!A:B,2,FALSE()),"?") -> Cemento Portland x 50kg | F87: =IFERROR(VLOOKUP(D87,MATERIALES!A:C,3,FALSE()),"?") -> Bol | G87: 0.324 | H87: 0.1 | I87: =IFERROR(VLOOKUP(D87,MATERIALES!A:D,4,FALSE()),0) -> 7809.48 | J87: =G87*I87*(1+H87) -> 2783.2987 | K87: =A87&"|"&B87 -> ALB-039|MAT | L87: =COUNTIFS($K$2:K87,K87) -> 2 | M87: =K87&"|"&L87 -> ALB-039|MAT|2 | N87: =IFERROR(VLOOKUP(A87,PARTIDAS!A:F,6,FALSE()),0) -> 2 | O87: =+IF(C87="ALB",G87/N87,G87) -> 0.324 | P87: =+_xlfn.XLOOKUP(A87,PPTO_GENERADOR!Q:Q,PPTO_GENERADOR!E:E,"-",0) -> - | Q87: =IFERROR(P87*O87,0) -> 0 | R87: =+_xlfn.XLOOKUP(A87,PPTO_GENERADOR!$Q:$Q,PPTO_GENERADOR!A:A,"-",0) -> -
A88: ALB-039 | B88: MO | C88: ALB | D88: MO-EAYUD | E88: =IFERROR(VLOOKUP(D88,MANO_DE_OBRA!A:B,2,FALSE()),"?") -> AYUDANTE | F88: j | G88: 0.75 | H88: 0 | I88: =IFERROR(VLOOKUP(D88,MANO_DE_OBRA!A:C,3,FALSE()),0) -> 60860.581 | J88: =G88*I88 -> 45645.436 | K88: =A88&"|"&B88 -> ALB-039|MO | L88: =COUNTIFS($K$2:K88,K88) -> 1 | M88: =K88&"|"&L88 -> ALB-039|MO|1 | N88: =IFERROR(VLOOKUP(A88,PARTIDAS!A:F,6,FALSE()),0) -> 2 | O88: =+IF(C88="ALB",G88/N88,G88) -> 0.375 | P88: =+_xlfn.XLOOKUP(A88,PPTO_GENERADOR!Q:Q,PPTO_GENERADOR!E:E,"-",0) -> - | Q88: =IFERROR(P88*O88,0) -> 0 | R88: =+_xlfn.XLOOKUP(A88,PPTO_GENERADOR!$Q:$Q,PPTO_GENERADOR!A:A,"-",0) -> -
A89: ALB-039 | B89: MO | C89: ALB | D89: MO-EESPE | E89: =IFERROR(VLOOKUP(D89,MANO_DE_OBRA!A:B,2,FALSE()),"?") -> ESPECIALIZADO | F89: j | G89: 0.75 | H89: 0 | I89: =IFERROR(VLOOKUP(D89,MANO_DE_OBRA!A:C,3,FALSE()),0) -> 85927.097 | J89: =G89*I89 -> 64445.323 | K89: =A89&"|"&B89 -> ALB-039|MO | L89: =COUNTIFS($K$2:K89,K89) -> 2 | M89: =K89&"|"&L89 -> ALB-039|MO|2 | N89: =IFERROR(VLOOKUP(A89,PARTIDAS!A:F,6,FALSE()),0) -> 2 | O89: =+IF(C89="ALB",G89/N89,G89) -> 0.375 | P89: =+_xlfn.XLOOKUP(A89,PPTO_GENERADOR!Q:Q,PPTO_GENERADOR!E:E,"-",0) -> - | Q89: =IFERROR(P89*O89,0) -> 0 | R89: =+_xlfn.XLOOKUP(A89,PPTO_GENERADOR!$Q:$Q,PPTO_GENERADOR!A:A,"-",0) -> -
A90: ALB-040 | B90: EQ | D90: EQ-EQALBA | E90: =IFERROR(VLOOKUP(D90,EQUIPOS!A:B,2,FALSE()),"?") -> EQUIPO DE ALBAÑILERIA, carpetas, ladrillo | G90: 0.25 | H90: 0 | I90: =IFERROR(VLOOKUP(D90,EQUIPOS!A:F,6,FALSE()),0) -> 2287.1357 | J90: =G90*I90 -> 571.78394 | K90: =A90&"|"&B90 -> ALB-040|EQ | L90: =COUNTIFS($K$2:K90,K90) -> 1 | M90: =K90&"|"&L90 -> ALB-040|EQ|1 | N90: =IFERROR(VLOOKUP(A90,PARTIDAS!A:F,6,FALSE()),0) -> 4 | O90: =+IF(C90="ALB",G90/N90,G90) -> 0.25 | P90: =+_xlfn.XLOOKUP(A90,PPTO_GENERADOR!Q:Q,PPTO_GENERADOR!E:E,"-",0) -> - | Q90: =IFERROR(P90*O90,0) -> 0 | R90: =+_xlfn.XLOOKUP(A90,PPTO_GENERADOR!$Q:$Q,PPTO_GENERADOR!A:A,"-",0) -> -
A91: ALB-040 | B91: EQ | D91: EQ-TROMPO | E91: =IFERROR(VLOOKUP(D91,EQUIPOS!A:B,2,FALSE()),"?") -> Hormigonera De 150 Litros 1hp Con Rueda Maciza | G91: 0.25 | H91: 0 | I91: =IFERROR(VLOOKUP(D91,EQUIPOS!A:F,6,FALSE()),0) -> 957.2532 | J91: =G91*I91 -> 239.3133 | K91: =A91&"|"&B91 -> ALB-040|EQ | L91: =COUNTIFS($K$2:K91,K91) -> 2 | M91: =K91&"|"&L91 -> ALB-040|EQ|2 | N91: =IFERROR(VLOOKUP(A91,PARTIDAS!A:F,6,FALSE()),0) -> 4 | O91: =+IF(C91="ALB",G91/N91,G91) -> 0.25 | P91: =+_xlfn.XLOOKUP(A91,PPTO_GENERADOR!Q:Q,PPTO_GENERADOR!E:E,"-",0) -> - | Q91: =IFERROR(P91*O91,0) -> 0 | R91: =+_xlfn.XLOOKUP(A91,PPTO_GENERADOR!$Q:$Q,PPTO_GENERADOR!A:A,"-",0) -> -
A92: ALB-040 | B92: MAT | C92: OTR | D92: AGR-001 | E92: =IFERROR(VLOOKUP(D92,MATERIALES!A:B,2,FALSE()),"?") -> ARENA LAVADA | F92: =IFERROR(VLOOKUP(D92,MATERIALES!A:C,3,FALSE()),"?") -> m3 | G92: 0.0138 | H92: 0.05 | I92: =IFERROR(VLOOKUP(D92,MATERIALES!A:D,4,FALSE()),0) -> 32399.77 | J92: =G92*I92*(1+H92) -> 469.47267 | K92: =A92&"|"&B92 -> ALB-040|MAT | L92: =COUNTIFS($K$2:K92,K92) -> 1 | M92: =K92&"|"&L92 -> ALB-040|MAT|1 | N92: =IFERROR(VLOOKUP(A92,PARTIDAS!A:F,6,FALSE()),0) -> 4 | O92: =+IF(C92="ALB",G92/N92,G92) -> 0.0138 | P92: =+_xlfn.XLOOKUP(A92,PPTO_GENERADOR!Q:Q,PPTO_GENERADOR!E:E,"-",0) -> - | Q92: =IFERROR(P92*O92,0) -> 0 | R92: =+_xlfn.XLOOKUP(A92,PPTO_GENERADOR!$Q:$Q,PPTO_GENERADOR!A:A,"-",0) -> -
A93: ALB-040 | B93: MAT | C93: OTR | D93: AGR-004 | E93: =IFERROR(VLOOKUP(D93,MATERIALES!A:B,2,FALSE()),"?") -> Cemento Portland x 50kg | F93: =IFERROR(VLOOKUP(D93,MATERIALES!A:C,3,FALSE()),"?") -> Bol | G93: 0.1242 | H93: 0.05 | I93: =IFERROR(VLOOKUP(D93,MATERIALES!A:D,4,FALSE()),0) -> 7809.48 | J93: =G93*I93*(1+H93) -> 1018.4343 | K93: =A93&"|"&B93 -> ALB-040|MAT | L93: =COUNTIFS($K$2:K93,K93) -> 2 | M93: =K93&"|"&L93 -> ALB-040|MAT|2 | N93: =IFERROR(VLOOKUP(A93,PARTIDAS!A:F,6,FALSE()),0) -> 4 | O93: =+IF(C93="ALB",G93/N93,G93) -> 0.1242 | P93: =+_xlfn.XLOOKUP(A93,PPTO_GENERADOR!Q:Q,PPTO_GENERADOR!E:E,"-",0) -> - | Q93: =IFERROR(P93*O93,0) -> 0 | R93: =+_xlfn.XLOOKUP(A93,PPTO_GENERADOR!$Q:$Q,PPTO_GENERADOR!A:A,"-",0) -> -
A94: ALB-040 | B94: MO | C94: ALB | D94: MO-EAYUD | E94: =IFERROR(VLOOKUP(D94,MANO_DE_OBRA!A:B,2,FALSE()),"?") -> AYUDANTE | F94: j | G94: 1 | H94: 0 | I94: =IFERROR(VLOOKUP(D94,MANO_DE_OBRA!A:C,3,FALSE()),0) -> 60860.581 | J94: =G94*I94 -> 60860.581 | K94: =A94&"|"&B94 -> ALB-040|MO | L94: =COUNTIFS($K$2:K94,K94) -> 1 | M94: =K94&"|"&L94 -> ALB-040|MO|1 | N94: =IFERROR(VLOOKUP(A94,PARTIDAS!A:F,6,FALSE()),0) -> 4 | O94: =+IF(C94="ALB",G94/N94,G94) -> 0.25 | P94: =+_xlfn.XLOOKUP(A94,PPTO_GENERADOR!Q:Q,PPTO_GENERADOR!E:E,"-",0) -> - | Q94: =IFERROR(P94*O94,0) -> 0 | R94: =+_xlfn.XLOOKUP(A94,PPTO_GENERADOR!$Q:$Q,PPTO_GENERADOR!A:A,"-",0) -> -
A95: ALB-040 | B95: MO | C95: ALB | D95: MO-EESPE | E95: =IFERROR(VLOOKUP(D95,MANO_DE_OBRA!A:B,2,FALSE()),"?") -> ESPECIALIZADO | F95: j | G95: 1 | H95: 0 | I95: =IFERROR(VLOOKUP(D95,MANO_DE_OBRA!A:C,3,FALSE()),0) -> 85927.097 | J95: =G95*I95 -> 85927.097 | K95: =A95&"|"&B95 -> ALB-040|MO | L95: =COUNTIFS($K$2:K95,K95) -> 2 | M95: =K95&"|"&L95 -> ALB-040|MO|2 | N95: =IFERROR(VLOOKUP(A95,PARTIDAS!A:F,6,FALSE()),0) -> 4 | O95: =+IF(C95="ALB",G95/N95,G95) -> 0.25 | P95: =+_xlfn.XLOOKUP(A95,PPTO_GENERADOR!Q:Q,PPTO_GENERADOR!E:E,"-",0) -> - | Q95: =IFERROR(P95*O95,0) -> 0 | R95: =+_xlfn.XLOOKUP(A95,PPTO_GENERADOR!$Q:$Q,PPTO_GENERADOR!A:A,"-",0) -> -
A96: ALB-041 | B96: EQ | D96: EQ-EQALBA | E96: =IFERROR(VLOOKUP(D96,EQUIPOS!A:B,2,FALSE()),"?") -> EQUIPO DE ALBAÑILERIA, carpetas, ladrillo | G96: 0.5 | H96: 0 | I96: =IFERROR(VLOOKUP(D96,EQUIPOS!A:F,6,FALSE()),0) -> 2287.1357 | J96: =G96*I96 -> 1143.5679 | K96: =A96&"|"&B96 -> ALB-041|EQ | L96: =COUNTIFS($K$2:K96,K96) -> 1 | M96: =K96&"|"&L96 -> ALB-041|EQ|1 | N96: =IFERROR(VLOOKUP(A96,PARTIDAS!A:F,6,FALSE()),0) -> 5 | O96: =+IF(C96="ALB",G96/N96,G96) -> 0.5 | P96: =+_xlfn.XLOOKUP(A96,PPTO_GENERADOR!Q:Q,PPTO_GENERADOR!E:E,"-",0) -> - | Q96: =IFERROR(P96*O96,0) -> 0 | R96: =+_xlfn.XLOOKUP(A96,PPTO_GENERADOR!$Q:$Q,PPTO_GENERADOR!A:A,"-",0) -> -
A97: ALB-041 | B97: EQ | D97: EQ-TROMPO | E97: =IFERROR(VLOOKUP(D97,EQUIPOS!A:B,2,FALSE()),"?") -> Hormigonera De 150 Litros 1hp Con Rueda Maciza | G97: 0.25 | H97: 0 | I97: =IFERROR(VLOOKUP(D97,EQUIPOS!A:F,6,FALSE()),0) -> 957.2532 | J97: =G97*I97 -> 239.3133 | K97: =A97&"|"&B97 -> ALB-041|EQ | L97: =COUNTIFS($K$2:K97,K97) -> 2 | M97: =K97&"|"&L97 -> ALB-041|EQ|2 | N97: =IFERROR(VLOOKUP(A97,PARTIDAS!A:F,6,FALSE()),0) -> 5 | O97: =+IF(C97="ALB",G97/N97,G97) -> 0.25 | P97: =+_xlfn.XLOOKUP(A97,PPTO_GENERADOR!Q:Q,PPTO_GENERADOR!E:E,"-",0) -> - | Q97: =IFERROR(P97*O97,0) -> 0 | R97: =+_xlfn.XLOOKUP(A97,PPTO_GENERADOR!$Q:$Q,PPTO_GENERADOR!A:A,"-",0) -> -
A98: ALB-041 | B98: MAT | C98: OTR | D98: AGR-001 | E98: =IFERROR(VLOOKUP(D98,MATERIALES!A:B,2,FALSE()),"?") -> ARENA LAVADA | F98: =IFERROR(VLOOKUP(D98,MATERIALES!A:C,3,FALSE()),"?") -> m3 | G98: 0.0018 | H98: 0.1 | I98: =IFERROR(VLOOKUP(D98,MATERIALES!A:D,4,FALSE()),0) -> 32399.77 | J98: =G98*I98*(1+H98) -> 64.151545 | K98: =A98&"|"&B98 -> ALB-041|MAT | L98: =COUNTIFS($K$2:K98,K98) -> 1 | M98: =K98&"|"&L98 -> ALB-041|MAT|1 | N98: =IFERROR(VLOOKUP(A98,PARTIDAS!A:F,6,FALSE()),0) -> 5 | O98: =+IF(C98="ALB",G98/N98,G98) -> 0.0018 | P98: =+_xlfn.XLOOKUP(A98,PPTO_GENERADOR!Q:Q,PPTO_GENERADOR!E:E,"-",0) -> - | Q98: =IFERROR(P98*O98,0) -> 0 | R98: =+_xlfn.XLOOKUP(A98,PPTO_GENERADOR!$Q:$Q,PPTO_GENERADOR!A:A,"-",0) -> -
A99: ALB-041 | B99: MAT | C99: OTR | D99: AGR-004 | E99: =IFERROR(VLOOKUP(D99,MATERIALES!A:B,2,FALSE()),"?") -> Cemento Portland x 50kg | F99: =IFERROR(VLOOKUP(D99,MATERIALES!A:C,3,FALSE()),"?") -> Bol | G99: 0.0162 | H99: 0.1 | I99: =IFERROR(VLOOKUP(D99,MATERIALES!A:D,4,FALSE()),0) -> 7809.48 | J99: =G99*I99*(1+H99) -> 139.16493 | K99: =A99&"|"&B99 -> ALB-041|MAT | L99: =COUNTIFS($K$2:K99,K99) -> 2 | M99: =K99&"|"&L99 -> ALB-041|MAT|2 | N99: =IFERROR(VLOOKUP(A99,PARTIDAS!A:F,6,FALSE()),0) -> 5 | O99: =+IF(C99="ALB",G99/N99,G99) -> 0.0162 | P99: =+_xlfn.XLOOKUP(A99,PPTO_GENERADOR!Q:Q,PPTO_GENERADOR!E:E,"-",0) -> - | Q99: =IFERROR(P99*O99,0) -> 0 | R99: =+_xlfn.XLOOKUP(A99,PPTO_GENERADOR!$Q:$Q,PPTO_GENERADOR!A:A,"-",0) -> -
A100: ALB-041 | B100: MAT | C100: OTR | D100: MAT-CONS | E100: =IFERROR(VLOOKUP(D100,MATERIALES!A:B,2,FALSE()),"?") -> Consumibles | F100: =IFERROR(VLOOKUP(D100,MATERIALES!A:C,3,FALSE()),"?") -> gl | G100: 1.0470799 | H100: 0 | I100: =IFERROR(VLOOKUP(D100,MATERIALES!A:D,4,FALSE()),0) -> 1 | J100: =G100*I100*(1+H100) -> 1.0470799 | K100: =A100&"|"&B100 -> ALB-041|MAT | L100: =COUNTIFS($K$2:K100,K100) -> 3 | M100: =K100&"|"&L100 -> ALB-041|MAT|3 | N100: =IFERROR(VLOOKUP(A100,PARTIDAS!A:F,6,FALSE()),0) -> 5 | O100: =+IF(C100="ALB",G100/N100,G100) -> 1.0470799 | P100: =+_xlfn.XLOOKUP(A100,PPTO_GENERADOR!Q:Q,PPTO_GENERADOR!E:E,"-",0) -> - | Q100: =IFERROR(P100*O100,0) -> 0 | R100: =+_xlfn.XLOOKUP(A100,PPTO_GENERADOR!$Q:$Q,PPTO_GENERADOR!A:A,"-",0) -> -
...

Sheet PPTO_GENERADOR
A1: PRESUPUESTO GDR 3760 — GENERADOR
A2: Versión APU: | G2: Mes base CAC: | H2: =CONFIG!B11 -> Diciembre 2024 | M2: Coeficinte GGBB | N2: 1.3327
A3: # | B3: Rubro | C3: Descripción | D3: Ud. | E3: Cant. | F3: MAT/ud | G3: MO/ud | H3: EQ/ud | I3: CD/ud | J3: MAT total | K3: MO total | L3: EQ total | M3: Costo Total | N3: Precio Venta (xK) | Q3: APU Link | R3: Pto# | S3: Fuente | T3: Rubro MO/ALB | X3: Observaciones | Y3: PPTO original | Z3: Observaciones
A4: 1 | C4: PRELIMINARES | O4: =+SUM(M5:M11) -> 15016567 | P4: =+SUM(N5:N11) -> 20012579
A5: 1.02 | B5: PRELIMINARES | C5: Topógrafo - Visita de obra replanteo | D5: gl | E5: 3 | F5: =IF(Q5<>"",IFERROR(VLOOKUP(Q5,PARTIDAS!A:P,13,FALSE()),0),0) -> 25000 | G5: =IF(Q5<>"",IFERROR(VLOOKUP(Q5,PARTIDAS!A:P,14,FALSE()),0),0) -> 259597.43 | H5: =IF(Q5<>"",IFERROR(VLOOKUP(Q5,PARTIDAS!A:P,15,FALSE()),0),0) -> 4268.9614 | I5: =F5+G5+H5 -> 288866.39 | J5: =F5*E5 -> 75000 | K5: =G5*E5 -> 778792.28 | L5: =H5*E5 -> 12806.884 | M5: =I5*E5 -> 866599.16 | N5: =M5*$N$2 -> 1154916.7 | Q5: PTO-0102 | R5: 1 | S5: PRESUPUESTO | T5: =+_xlfn.XLOOKUP(A5,Sheet1!C:C,Sheet1!A:A,"-",0) -> Preliminares | Y5: 866599.16 | Z5: =+M5-Y5 -> 1.1641532e-09
A6: 1.04 | B6: PRELIMINARES | C6: Cerco de obra perimetral - En chapa C25 + Concertina + Porton corredizo | D6: ml | E6: 10 | F6: =IFERROR(VLOOKUP(Q6,PARTIDAS!A:M,13,FALSE()),0) -> 88330.703 | G6: =IFERROR(VLOOKUP(Q6,PARTIDAS!A:N,14,FALSE()),0) -> 101654.37 | H6: =IFERROR(VLOOKUP(Q6,PARTIDAS!A:O,15,FALSE()),0) -> 2849.776 | I6: =F6+G6+H6 -> 192834.84 | J6: =F6*E6 -> 883307.03 | K6: =G6*E6 -> 1016543.7 | L6: =H6*E6 -> 28497.76 | M6: =I6*E6 -> 1928348.4 | N6: =M6*$N$2 -> 2569910 | Q6: PTO-0104 | S6: PRESUPUESTO | T6: =+_xlfn.XLOOKUP(A6,Sheet1!C:C,Sheet1!A:A,"-",0) -> Preliminares | Y6: 1928348.4 | Z6: =+M6-Y6 -> -2.7474016e-08
A7: 1.05 | B7: PRELIMINARES | C7: Obrador, pañol y ducha. | D7: gl | E7: 1 | F7: =IFERROR(VLOOKUP(Q7,PARTIDAS!A:M,13,FALSE()),0) -> 2078824.7 | G7: =IFERROR(VLOOKUP(Q7,PARTIDAS!A:N,14,FALSE()),0) -> 5174962.9 | H7: =IFERROR(VLOOKUP(Q7,PARTIDAS!A:O,15,FALSE()),0) -> 108806.81 | I7: =F7+G7+H7 -> 7362594.4 | J7: =F7*E7 -> 2078824.7 | K7: =G7*E7 -> 5174962.9 | L7: =H7*E7 -> 108806.81 | M7: =I7*E7 -> 7362594.4 | N7: =M7*$N$2 -> 9812129.5 | Q7: PTO-0105 | S7: PRESUPUESTO | T7: =+_xlfn.XLOOKUP(A7,Sheet1!C:C,Sheet1!A:A,"-",0) -> Preliminares | Y7: 7362594.4 | Z7: =+M7-Y7 -> 0
A8: 1.06 | B8: PRELIMINARES | C8: Alquiler de baños quimicos y duchas portatiles | D8: mes | E8: 4 | F8: =IF(Q8<>"",IFERROR(VLOOKUP(Q8,PARTIDAS!A:P,13,FALSE()),0),0) -> 0 | G8: =IF(Q8<>"",IFERROR(VLOOKUP(Q8,PARTIDAS!A:P,14,FALSE()),0),0) -> 332285.54 | H8: =IF(Q8<>"",IFERROR(VLOOKUP(Q8,PARTIDAS!A:P,15,FALSE()),0),0) -> 0 | I8: =F8+G8+H8 -> 332285.54 | J8: =F8*E8 -> 0 | K8: =G8*E8 -> 1329142.2 | L8: =H8*E8 -> 0 | M8: =I8*E8 -> 1329142.2 | N8: =M8*$N$2 -> 1771347.8 | Q8: PTO-0106 | R8: 1 | S8: PRESUPUESTO | T8: =+_xlfn.XLOOKUP(A8,Sheet1!C:C,Sheet1!A:A,"-",0) -> Preliminares | Y8: 1329142.2 | Z8: =+M8-Y8 -> 0
A9: 1.07 | B9: PRELIMINARES | C9: Conexión pilar y luz de obra + Tablero de obra | D9: gl | E9: 1 | F9: =IF(Q9<>"",IFERROR(VLOOKUP(Q9,PARTIDAS!A:P,13,FALSE()),0),0) -> 1090000 | G9: =IF(Q9<>"",IFERROR(VLOOKUP(Q9,PARTIDAS!A:P,14,FALSE()),0),0) -> 601395.67 | H9: =IF(Q9<>"",IFERROR(VLOOKUP(Q9,PARTIDAS!A:P,15,FALSE()),0),0) -> 25370.935 | I9: =F9+G9+H9 -> 1716766.6 | J9: =F9*E9 -> 1090000 | K9: =G9*E9 -> 601395.67 | L9: =H9*E9 -> 25370.935 | M9: =I9*E9 -> 1716766.6 | N9: =M9*$N$2 -> 2287934.9 | Q9: PTO-0107 | R9: 1 | S9: PRESUPUESTO | T9: =+_xlfn.XLOOKUP(A9,Sheet1!C:C,Sheet1!A:A,"-",0) -> Preliminares | Y9: 1716766.6 | Z9: =+M9-Y9 -> 0
A10: 1.08 | B10: PRELIMINARES | C10: Conexión agua de obra, tanque + bomba | D10: gl | E10: 1 | F10: =IF(Q10<>"",IFERROR(VLOOKUP(Q10,PARTIDAS!A:P,13,FALSE()),0),0) -> 685200 | G10: =IF(Q10<>"",IFERROR(VLOOKUP(Q10,PARTIDAS!A:P,14,FALSE()),0),0) -> 651528.71 | H10: =IF(Q10<>"",IFERROR(VLOOKUP(Q10,PARTIDAS!A:P,15,FALSE()),0),0) -> 20050.931 | I10: =F10+G10+H10 -> 1356779.6 | J10: =F10*E10 -> 685200 | K10: =G10*E10 -> 651528.71 | L10: =H10*E10 -> 20050.931 | M10: =I10*E10 -> 1356779.6 | N10: =M10*$N$2 -> 1808180.2 | Q10: PTO-0108 | R10: 1 | S10: PRESUPUESTO | T10: =+_xlfn.XLOOKUP(A10,Sheet1!C:C,Sheet1!A:A,"-",0) -> Preliminares | Y10: 1356779.6 | Z10: =+M10-Y10 -> 0
A11: 1.09 | B11: PRELIMINARES | C11: Tramite luz de obra, certificado luz de obra (2) y medición PAT | D11: gl | E11: 1 | F11: =IF(Q11<>"",IFERROR(VLOOKUP(Q11,PARTIDAS!A:P,13,FALSE()),0),0) -> 0 | G11: =IF(Q11<>"",IFERROR(VLOOKUP(Q11,PARTIDAS!A:P,14,FALSE()),0),0) -> 456336.73 | H11: =IF(Q11<>"",IFERROR(VLOOKUP(Q11,PARTIDAS!A:P,15,FALSE()),0),0) -> 0 | I11: =F11+G11+H11 -> 456336.73 | J11: =F11*E11 -> 0 | K11: =G11*E11 -> 456336.73 | L11: =H11*E11 -> 0 | M11: =I11*E11 -> 456336.73 | N11: =M11*$N$2 -> 608159.97 | Q11: PTO-0109 | R11: 1 | S11: PRESUPUESTO | T11: =+_xlfn.XLOOKUP(A11,Sheet1!C:C,Sheet1!A:A,"-",0) -> - | X11: error fórmula en PPTO Original | Y11: 362691.09 | Z11: =+M11-Y11 -> 93645.649
A12: 2 | C12: MOVIMIENTO DE TIERRA | O12: =+SUM(M13:M15) -> 22247478 | P12: =+SUM(N13:N15) -> 29649214 | Y12: 0 | Z12: =+M12-Y12 -> 0
A13: 2.01 | B13: MOVIMIENTO DE TIERRA | C13: Excavación a maquina para submuración, subsuelo y fundaciones | D13: m3 | E13: 308 | F13: =IF(Q13<>"",IFERROR(VLOOKUP(Q13,PARTIDAS!A:P,13,FALSE()),0),0) -> 0 | G13: =IF(Q13<>"",IFERROR(VLOOKUP(Q13,PARTIDAS!A:P,14,FALSE()),0),0) -> 39520.777 | H13: =IF(Q13<>"",IFERROR(VLOOKUP(Q13,PARTIDAS!A:P,15,FALSE()),0),0) -> 97.811648 | I13: =F13+G13+H13 -> 39618.588 | J13: =F13*E13 -> 0 | K13: =G13*E13 -> 12172399 | L13: =H13*E13 -> 30125.987 | M13: =I13*E13 -> 12202525 | N13: =M13*$N$2 -> 16262305 | Q13: PTO-0201 | R13: 1 | S13: PRESUPUESTO | T13: =+_xlfn.XLOOKUP(A13,Sheet1!C:C,Sheet1!A:A,"-",0) -> Hormigón | Y13: 12202525 | Z13: =+M13-Y13 -> 0
A14: 2.02 | B14: MOVIMIENTO DE TIERRA | C14: Perfilado manual de bases. Relleno y compactación de pozos | D14: gl | E14: 1 | F14: =IF(Q14<>"",IFERROR(VLOOKUP(Q14,PARTIDAS!A:P,13,FALSE()),0),0) -> 105000 | G14: =IF(Q14<>"",IFERROR(VLOOKUP(Q14,PARTIDAS!A:P,14,FALSE()),0),0) -> 8488596.7 | H14: =IF(Q14<>"",IFERROR(VLOOKUP(Q14,PARTIDAS!A:P,15,FALSE()),0),0) -> 128903.95 | I14: =F14+G14+H14 -> 8722500.6 | J14: =F14*E14 -> 105000 | K14: =G14*E14 -> 8488596.7 | L14: =H14*E14 -> 128903.95 | M14: =I14*E14 -> 8722500.6 | N14: =M14*$N$2 -> 11624477 | Q14: PTO-0202 | R14: 1 | S14: PRESUPUESTO | T14: =+_xlfn.XLOOKUP(A14,Sheet1!C:C,Sheet1!A:A,"-",0) -> Preliminares | Y14: 8722500.6 | Z14: =+M14-Y14 -> 0
A15: 2.03 | B15: MOVIMIENTO DE TIERRA | C15: Excavación manual para vigas de fundación | D15: m3 | E15: 15 | F15: =IF(Q15<>"",IFERROR(VLOOKUP(Q15,PARTIDAS!A:P,13,FALSE()),0),0) -> 26000 | G15: =IF(Q15<>"",IFERROR(VLOOKUP(Q15,PARTIDAS!A:P,14,FALSE()),0),0) -> 60860.581 | H15: =IF(Q15<>"",IFERROR(VLOOKUP(Q15,PARTIDAS!A:P,15,FALSE()),0),0) -> 1302.9087 | I15: =F15+G15+H15 -> 88163.489 | J15: =F15*E15 -> 390000 | K15: =G15*E15 -> 912908.71 | L15: =H15*E15 -> 19543.631 | M15: =I15*E15 -> 1322452.3 | N15: =M15*$N$2 -> 1762432.2 | Q15: PTO-0203 | R15: 1 | S15: PRESUPUESTO | T15: =+_xlfn.XLOOKUP(A15,Sheet1!C:C,Sheet1!A:A,"-",0) -> Preliminares | Y15: 1322452.3 | Z15: =+M15-Y15 -> 0
A16: 3 | C16: ESTRUCTURA DE HORMIGÓN ARMADO | O16: =+SUM(M17:M37) -> 3.3868088e+08 | P16: =+SUM(N17:N37) -> 4.5136e+08 | Y16: 0 | Z16: =+M16-Y16 -> 0
A17: 3.01 | B17: ESTRUCTURA DE HORMIGÓN ARMADO | C17: Hormigón de limpieza - e: 10 cm | D17: m3 | E17: 13 | F17: =IF(Q17<>"",IFERROR(VLOOKUP(Q17,PARTIDAS!A:P,13,FALSE()),0),0) -> 115100 | G17: =IF(Q17<>"",IFERROR(VLOOKUP(Q17,PARTIDAS!A:P,14,FALSE()),0),0) -> 101603.58 | H17: =IF(Q17<>"",IFERROR(VLOOKUP(Q17,PARTIDAS!A:P,15,FALSE()),0),0) -> 3250.5537 | I17: =F17+G17+H17 -> 219954.14 | J17: =F17*E17 -> 1496300 | K17: =G17*E17 -> 1320846.6 | L17: =H17*E17 -> 42257.198 | M17: =I17*E17 -> 2859403.8 | N17: =M17*$N$2 -> 3810727.4 | Q17: PTO-0301 | R17: 1 | S17: PRESUPUESTO | T17: =+_xlfn.XLOOKUP(A17,Sheet1!C:C,Sheet1!A:A,"-",0) -> Hormigón | Y17: 2859403.8 | Z17: =+M17-Y17 -> 0
A18: 3.02 | B18: ESTRUCTURA DE HORMIGÓN ARMADO | C18: Pilotes de tracción Ø 20 cm - (120 kg/m3 de hierro) | D18: u | E18: 18 | F18: =IF(Q18<>"",IFERROR(VLOOKUP(Q18,PARTIDAS!A:P,13,FALSE()),0),0) -> 90570.796 | G18: =IF(Q18<>"",IFERROR(VLOOKUP(Q18,PARTIDAS!A:P,14,FALSE()),0),0) -> 250000 | H18: =IF(Q18<>"",IFERROR(VLOOKUP(Q18,PARTIDAS!A:P,15,FALSE()),0),0) -> 5108.5619 | I18: =F18+G18+H18 -> 345679.36 | J18: =F18*E18 -> 1630274.3 | K18: =G18*E18 -> 4500000 | L18: =H18*E18 -> 91954.115 | M18: =I18*E18 -> 6222228.4 | N18: =M18*$N$2 -> 8292363.9 | Q18: PTO-0302 | R18: 1 | S18: PRESUPUESTO | T18: =+_xlfn.XLOOKUP(A18,Sheet1!C:C,Sheet1!A:A,"-",0) -> - | Y18: 6222228.4 | Z18: =+M18-Y18 -> 0
A19: 3.03 | B19: ESTRUCTURA DE HORMIGÓN ARMADO | C19: Tabique submuración - H35 (95 kg/m3 de hierro) | D19: m3 | E19: 12 | F19: =IF(Q19<>"",IFERROR(VLOOKUP(Q19,PARTIDAS!A:P,13,FALSE()),0),0) -> 402072.54 | G19: =IF(Q19<>"",IFERROR(VLOOKUP(Q19,PARTIDAS!A:P,14,FALSE()),0),0) -> 357640.9 | H19: =IF(Q19<>"",IFERROR(VLOOKUP(Q19,PARTIDAS!A:P,15,FALSE()),0),0) -> 11395.702 | I19: =F19+G19+H19 -> 771109.14 | J19: =F19*E19 -> 4824870.5 | K19: =G19*E19 -> 4291690.8 | L19: =H19*E19 -> 136748.42 | M19: =I19*E19 -> 9253309.7 | N19: =M19*$N$2 -> 12331886 | Q19: PTO-0303 | R19: 1 | S19: PRESUPUESTO | T19: =+_xlfn.XLOOKUP(A19,Sheet1!C:C,Sheet1!A:A,"-",0) -> - | Y19: 9253309.7 | Z19: =+M19-Y19 -> 0
A20: 3.04 | B20: ESTRUCTURA DE HORMIGÓN ARMADO | C20: Zapata corrida tabique - H35 (120 kg/m3 de hierro) | D20: m3 | E20: 7 | F20: =IF(Q20<>"",IFERROR(VLOOKUP(Q20,PARTIDAS!A:P,13,FALSE()),0),0) -> 428196.58 | G20: =IF(Q20<>"",IFERROR(VLOOKUP(Q20,PARTIDAS!A:P,14,FALSE()),0),0) -> 281633.96 | H20: =IF(Q20<>"",IFERROR(VLOOKUP(Q20,PARTIDAS!A:P,15,FALSE()),0),0) -> 10647.458 | I20: =F20+G20+H20 -> 720478 | J20: =F20*E20 -> 2997376.1 | K20: =G20*E20 -> 1971437.7 | L20: =H20*E20 -> 74532.207 | M20: =I20*E20 -> 5043346 | N20: =M20*$N$2 -> 6721267.2 | Q20: PTO-0304 | R20: 1 | S20: PRESUPUESTO | T20: =+_xlfn.XLOOKUP(A20,Sheet1!C:C,Sheet1!A:A,"-",0) -> - | Y20: 5043346 | Z20: =+M20-Y20 -> 0
A21: 3.05 | B21: ESTRUCTURA DE HORMIGÓN ARMADO | C21: Platea - H35 (95 kg/m3 de hierro) | D21: m3 | E21: 38 | F21: =IF(Q21<>"",IFERROR(VLOOKUP(Q21,PARTIDAS!A:P,13,FALSE()),0),0) -> 333700.51 | G21: =IF(Q21<>"",IFERROR(VLOOKUP(Q21,PARTIDAS!A:P,14,FALSE()),0),0) -> 194327.43 | H21: =IF(Q21<>"",IFERROR(VLOOKUP(Q21,PARTIDAS!A:P,15,FALSE()),0),0) -> 7920.4191 | I21: =F21+G21+H21 -> 535948.36 | J21: =F21*E21 -> 12680619 | K21: =G21*E21 -> 7384442.5 | L21: =H21*E21 -> 300975.93 | M21: =I21*E21 -> 20366038 | N21: =M21*$N$2 -> 27141818 | Q21: PTO-0305 | R21: 1 | S21: PRESUPUESTO | T21: =+_xlfn.XLOOKUP(A21,Sheet1!C:C,Sheet1!A:A,"-",0) -> - | Y21: 20366038 | Z21: =+M21-Y21 -> 0
A22: 3.06 | B22: ESTRUCTURA DE HORMIGÓN ARMADO | C22: Bases aisladas - (60 kg/m3 de hierro) | D22: m3 | E22: 51 | F22: =IF(Q22<>"",IFERROR(VLOOKUP(Q22,PARTIDAS!A:P,13,FALSE()),0),0) -> 275042.38 | G22: =IF(Q22<>"",IFERROR(VLOOKUP(Q22,PARTIDAS!A:P,14,FALSE()),0),0) -> 194327.43 | H22: =IF(Q22<>"",IFERROR(VLOOKUP(Q22,PARTIDAS!A:P,15,FALSE()),0),0) -> 7040.5472 | I22: =F22+G22+H22 -> 476410.36 | J22: =F22*E22 -> 14027161 | K22: =G22*E22 -> 9910699.1 | L22: =H22*E22 -> 359067.91 | M22: =I22*E22 -> 24296928 | N22: =M22*$N$2 -> 32380516 | Q22: PTO-0306 | R22: 1 | S22: PRESUPUESTO | T22: =+_xlfn.XLOOKUP(A22,Sheet1!C:C,Sheet1!A:A,"-",0) -> - | Y22: 24296928 | Z22: =+M22-Y22 -> 0
A23: 3.07 | B23: ESTRUCTURA DE HORMIGÓN ARMADO | C23: Troncos de columnas - H35 (240 kg/m3 de hierro) | D23: m3 | E23: 16 | F23: =IF(Q23<>"",IFERROR(VLOOKUP(Q23,PARTIDAS!A:P,13,FALSE()),0),0) -> 635192.72 | G23: =IF(Q23<>"",IFERROR(VLOOKUP(Q23,PARTIDAS!A:P,14,FALSE()),0),0) -> 317914.05 | H23: =IF(Q23<>"",IFERROR(VLOOKUP(Q23,PARTIDAS!A:P,15,FALSE()),0),0) -> 14296.601 | I23: =F23+G23+H23 -> 967403.37 | J23: =F23*E23 -> 10163083 | K23: =G23*E23 -> 5086624.8 | L23: =H23*E23 -> 228745.62 | M23: =I23*E23 -> 15478454 | N23: =M23*$N$2 -> 20628135 | Q23: PTO-0307 | R23: 1 | S23: PRESUPUESTO | T23: =+_xlfn.XLOOKUP(A23,Sheet1!C:C,Sheet1!A:A,"-",0) -> - | Y23: 15478454 | Z23: =+M23-Y23 -> 0
A24: 3.08 | B24: ESTRUCTURA DE HORMIGÓN ARMADO | C24: Viga de encadenado - H35 (180 kg/m3 de hierro) | D24: m3 | E24: 7 | F24: =IF(Q24<>"",IFERROR(VLOOKUP(Q24,PARTIDAS!A:P,13,FALSE()),0),0) -> 528753.37 | G24: =IF(Q24<>"",IFERROR(VLOOKUP(Q24,PARTIDAS!A:P,14,FALSE()),0),0) -> 281633.96 | H24: =IF(Q24<>"",IFERROR(VLOOKUP(Q24,PARTIDAS!A:P,15,FALSE()),0),0) -> 12155.81 | I24: =F24+G24+H24 -> 822543.14 | J24: =F24*E24 -> 3701273.6 | K24: =G24*E24 -> 1971437.7 | L24: =H24*E24 -> 85090.67 | M24: =I24*E24 -> 5757802 | N24: =M24*$N$2 -> 7673422.7 | Q24: PTO-0308 | R24: 1 | S24: PRESUPUESTO | T24: =+_xlfn.XLOOKUP(A24,Sheet1!C:C,Sheet1!A:A,"-",0) -> - | Y24: 5757802 | Z24: =+M24-Y24 -> 0
A25: 3.09 | B25: ESTRUCTURA DE HORMIGÓN ARMADO | C25: Losa maciza - H35 (100 kg/m3 de hierro) | D25: m3 | E25: 90 | F25: =IF(Q25<>"",IFERROR(VLOOKUP(Q25,PARTIDAS!A:P,13,FALSE()),0),0) -> 372584.33 | G25: =IF(Q25<>"",IFERROR(VLOOKUP(Q25,PARTIDAS!A:P,14,FALSE()),0),0) -> 221790.79 | H25: =IF(Q25<>"",IFERROR(VLOOKUP(Q25,PARTIDAS!A:P,15,FALSE()),0),0) -> 8915.6269 | I25: =F25+G25+H25 -> 603290.75 | J25: =F25*E25 -> 33532590 | K25: =G25*E25 -> 19961172 | L25: =H25*E25 -> 802406.42 | M25: =I25*E25 -> 54296168 | N25: =M25*$N$2 -> 72360503 | Q25: PTO-0309 | R25: 1 | S25: PRESUPUESTO | T25: =+_xlfn.XLOOKUP(A25,Sheet1!C:C,Sheet1!A:A,"-",0) -> - | Y25: 54296168 | Z25: =+M25-Y25 -> 0
A26: 3.1 | B26: ESTRUCTURA DE HORMIGÓN ARMADO | C26: Losa maciza de Hº visto - H35 (100 kg/m3 de hierro) | D26: m3 | E26: 32 | F26: =IF(Q26<>"",IFERROR(VLOOKUP(Q26,PARTIDAS!A:P,13,FALSE()),0),0) -> 379758.83 | G26: =IF(Q26<>"",IFERROR(VLOOKUP(Q26,PARTIDAS!A:P,14,FALSE()),0),0) -> 277238.49 | H26: =IF(Q26<>"",IFERROR(VLOOKUP(Q26,PARTIDAS!A:P,15,FALSE()),0),0) -> 9854.9599 | I26: =F26+G26+H26 -> 666852.29 | J26: =F26*E26 -> 12152283 | K26: =G26*E26 -> 8871631.8 | L26: =H26*E26 -> 315358.72 | M26: =I26*E26 -> 21339273 | N26: =M26*$N$2 -> 28438849 | Q26: PTO-0310 | R26: 1 | S26: PRESUPUESTO | T26: =+_xlfn.XLOOKUP(A26,Sheet1!C:C,Sheet1!A:A,"-",0) -> Hormigón | Y26: 21339273 | Z26: =+M26-Y26 -> 0
A27: 3.11 | B27: ESTRUCTURA DE HORMIGÓN ARMADO | C27: Vigas - H35 (180 kg/m3 de hierro) | D27: m3 | E27: 46 | F27: =IF(Q27<>"",IFERROR(VLOOKUP(Q27,PARTIDAS!A:P,13,FALSE()),0),0) -> 567913.51 | G27: =IF(Q27<>"",IFERROR(VLOOKUP(Q27,PARTIDAS!A:P,14,FALSE()),0),0) -> 537036.81 | H27: =IF(Q27<>"",IFERROR(VLOOKUP(Q27,PARTIDAS!A:P,15,FALSE()),0),0) -> 16574.255 | I27: =F27+G27+H27 -> 1121524.6 | J27: =F27*E27 -> 26124021 | K27: =G27*E27 -> 24703693 | L27: =H27*E27 -> 762415.72 | M27: =I27*E27 -> 51590130 | N27: =M27*$N$2 -> 68754166 | Q27: PTO-0311 | R27: 1 | S27: PRESUPUESTO | T27: =+_xlfn.XLOOKUP(A27,Sheet1!C:C,Sheet1!A:A,"-",0) -> - | Y27: 51590130 | Z27: =+M27-Y27 -> 0
A28: 3.12 | B28: ESTRUCTURA DE HORMIGÓN ARMADO | C28: Vigas de H° visto - H35 (180 kg/m3 de hierro) | D28: m3 | E28: 31 | F28: =IF(Q28<>"",IFERROR(VLOOKUP(Q28,PARTIDAS!A:P,13,FALSE()),0),0) -> 565756.87 | G28: =IF(Q28<>"",IFERROR(VLOOKUP(Q28,PARTIDAS!A:P,14,FALSE()),0),0) -> 671296.01 | H28: =IF(Q28<>"",IFERROR(VLOOKUP(Q28,PARTIDAS!A:P,15,FALSE()),0),0) -> 18555.793 | I28: =F28+G28+H28 -> 1255608.7 | J28: =F28*E28 -> 17538463 | K28: =G28*E28 -> 20810176 | L28: =H28*E28 -> 575229.59 | M28: =I28*E28 -> 38923869 | N28: =M28*$N$2 -> 51873840 | Q28: PTO-0312 | R28: 1 | S28: PRESUPUESTO | T28: =+_xlfn.XLOOKUP(A28,Sheet1!C:C,Sheet1!A:A,"-",0) -> Hormigón | Y28: 38923869 | Z28: =+M28-Y28 -> 0
... A32: 3.17 | B32: ESTRUCTURA DE HORMIGÓN ARMADO | C32: Escaleras de Hº visto - H35 (105 kg/m3 de hierro) | D32: m3 | E32: 10 | F32: =IF(Q32<>"",IFERROR(VLOOKUP(Q32,PARTIDAS!A:P,13,FALSE()),0),0) -> 416173.6 | G32: =IF(Q32<>"",IFERROR(VLOOKUP(Q32,PARTIDAS!A:P,14,FALSE()),0),0) -> 405530.54 | H32: =IF(Q32<>"",IFERROR(VLOOKUP(Q32,PARTIDAS!A:P,15,FALSE()),0),0) -> 12325.562 | I32: =F32+G32+H32 -> 834029.71 | J32: =F32*E32 -> 4161736 | K32: =G32*E32 -> 4055305.4 | L32: =H32*E32 -> 123255.62 | M32: =I32*E32 -> 8340297.1 | N32: =M32*$N$2 -> 11115114 | Q32: PTO-0317 | R32: 1 | S32: PRESUPUESTO | T32: =+_xlfn.XLOOKUP(A32,Sheet1!C:C,Sheet1!A:A,"-",0) -> Hormigón | Y32: 8340297.1 | Z32: =+M32-Y32 -> 0
A33: 3.18 | B33: ESTRUCTURA DE HORMIGÓN ARMADO | C33: Tanques de HºAº - H35 (100 kg/m3 de hierro) - Tanque de reserva | D33: m3 | E33: 6 | F33: =IF(Q33<>"",IFERROR(VLOOKUP(Q33,PARTIDAS!A:P,13,FALSE()),0),0) -> 410452.27 | G33: =IF(Q33<>"",IFERROR(VLOOKUP(Q33,PARTIDAS!A:P,14,FALSE()),0),0) -> 357640.9 | H33: =IF(Q33<>"",IFERROR(VLOOKUP(Q33,PARTIDAS!A:P,15,FALSE()),0),0) -> 11521.398 | I33: =F33+G33+H33 -> 779614.57 | J33: =F33*E33 -> 2462713.6 | K33: =G33*E33 -> 2145845.4 | L33: =H33*E33 -> 69128.386 | M33: =I33*E33 -> 4677687.4 | N33: =M33*$N$2 -> 6233954 | Q33: PTO-0318 | S33: PRESUPUESTO | T33: =+_xlfn.XLOOKUP(A33,Sheet1!C:C,Sheet1!A:A,"-",0) -> - | Y33: 4677687.4 | Z33: =+M33-Y33 -> 0
A34: 3.19 | B34: ESTRUCTURA DE HORMIGÓN ARMADO | C34: Sistema de apuntalamiento y reapuntalamiento | D34: gl | E34: 1 | F34: =IF(Q34<>"",IFERROR(VLOOKUP(Q34,PARTIDAS!A:P,13,FALSE()),0),0) -> 0 | G34: =IF(Q34<>"",IFERROR(VLOOKUP(Q34,PARTIDAS!A:P,14,FALSE()),0),0) -> 0 | H34: =IF(Q34<>"",IFERROR(VLOOKUP(Q34,PARTIDAS!A:P,15,FALSE()),0),0) -> 8458556.6 | I34: =F34+G34+H34 -> 8458556.6 | J34: =F34*E34 -> 0 | K34: =G34*E34 -> 0 | L34: =H34*E34 -> 8458556.6 | M34: =I34*E34 -> 8458556.6 | N34: =M34*$N$2 -> 11272718 | Q34: PTO-0319 | R34: 1 | S34: PRESUPUESTO | T34: =+_xlfn.XLOOKUP(A34,Sheet1!C:C,Sheet1!A:A,"-",0) -> - | Y34: 8458556.6 | Z34: =+M34-Y34 -> 0
A35: 3.2 | B35: ESTRUCTURA DE HORMIGÓN ARMADO | C35: Ensayos de hormigon por etapas de hormigonado | D35: u | E35: 15 | F35: =IF(Q35<>"",IFERROR(VLOOKUP(Q35,PARTIDAS!A:P,13,FALSE()),0),0) -> 0 | G35: =IF(Q35<>"",IFERROR(VLOOKUP(Q35,PARTIDAS!A:P,14,FALSE()),0),0) -> 228712 | H35: =IF(Q35<>"",IFERROR(VLOOKUP(Q35,PARTIDAS!A:P,15,FALSE()),0),0) -> 0 | I35: =F35+G35+H35 -> 228712 | J35: =F35*E35 -> 0 | K35: =G35*E35 -> 3430680 | L35: =H35*E35 -> 0 | M35: =I35*E35 -> 3430680 | N35: =M35*$N$2 -> 4572067.2 | Q35: PTO-0320 | R35: 1 | S35: PRESUPUESTO | T35: =+_xlfn.XLOOKUP(A35,Sheet1!C:C,Sheet1!A:A,"-",0) -> - | Y35: 3430680 | Z35: =+M35-Y35 -> 0
A36: 3.21 | B36: ESTRUCTURA DE HORMIGÓN ARMADO | C36: Permiso de estacionamiento de bomba de hormigón a contramano | D36: gl | E36: 3 | F36: =IF(Q36<>"",IFERROR(VLOOKUP(Q36,PARTIDAS!A:P,13,FALSE()),0),0) -> 51239.669 | G36: =IF(Q36<>"",IFERROR(VLOOKUP(Q36,PARTIDAS!A:P,14,FALSE()),0),0) -> 0 | H36: =IF(Q36<>"",IFERROR(VLOOKUP(Q36,PARTIDAS!A:P,15,FALSE()),0),0) -> 0 | I36: =F36+G36+H36 -> 51239.669 | J36: =F36*E36 -> 153719.01 | K36: =G36*E36 -> 0 | L36: =H36*E36 -> 0 | M36: =I36*E36 -> 153719.01 | N36: =M36*$N$2 -> 204861.32 | Q36: PTO-0321 | R36: 1 | S36: PRESUPUESTO | T36: =+_xlfn.XLOOKUP(A36,Sheet1!C:C,Sheet1!A:A,"-",0) -> - | Y36: 153719.01 | Z36: =+M36-Y36 -> 0
A37: 3.22 | B37: ESTRUCTURA DE HORMIGÓN ARMADO | C37: Picado de medianeras para columnas y vigas - Cotizado para PB y 1P | D37: m2 | E37: 78 | F37: =IFERROR(VLOOKUP(Q37,PARTIDAS!A:M,13,FALSE()),0) -> 7051.2821 | G37: =IFERROR(VLOOKUP(Q37,PARTIDAS!A:N,14,FALSE()),0) -> 17829.919 | H37: =IFERROR(VLOOKUP(Q37,PARTIDAS!A:O,15,FALSE()),0) -> 373.21802 | I37: =F37+G37+H37 -> 25254.419 | J37: =F37*E37 -> 550000 | K37: =G37*E37 -> 1390733.7 | L37: =H37*E37 -> 29111.005 | M37: =I37*E37 -> 1969844.7 | N37: =M37*$N$2 -> 2625212 | Q37: PTO-0322 | S37: PRESUPUESTO | T37: =+_xlfn.XLOOKUP(A37,Sheet1!C:C,Sheet1!A:A,"-",0) -> Hormigón | Y37: 1969844.7 | Z37: =+M37-Y37 -> 2.4354085e-07
A38: 4 | C38: MAMPOSTERÍA | O38: =+SUM(M39:M52) -> 38367858 | P38: =+SUM(N39:N52) -> 51132844 | Y38: 0 | Z38: =+M38-Y38 -> 0
A39: 4.01 | B39: MAMPOSTERÍA | C39: Muro tipo 1 - Ladrillo hueco 8 x 18 x 33 | D39: m2 | E39: 621 | F39: =IF(Q39<>"",IFERROR(VLOOKUP(Q39,PARTIDAS!A:P,13,FALSE()),0),0) -> 6590.9962 | G39: =IF(Q39<>"",IFERROR(VLOOKUP(Q39,PARTIDAS!A:P,14,FALSE()),0),0) -> 9785.8452 | H39: =IF(Q39<>"",IFERROR(VLOOKUP(Q39,PARTIDAS!A:P,15,FALSE()),0),0) -> 235.33191 | I39: =F39+G39+H39 -> 16612.173 | J39: =F39*E39 -> 4093008.7 | K39: =G39*E39 -> 6077009.9 | L39: =H39*E39 -> 146141.12 | M39: =I39*E39 -> 10316160 | N39: =M39*$N$2 -> 13748346 | Q39: ALB-034 | R39: 2 | S39: APU | T39: =+_xlfn.XLOOKUP(A39,Sheet1!C:C,Sheet1!A:A,"-",0) -> Albañilería | Y39: 10316160 | Z39: =+M39-Y39 -> 0
A40: 4.02 | B40: MAMPOSTERÍA | C40: Muro tipo 2 - Ladrillo hueco 12 x 18 x 33 | D40: m2 | E40: 780 | F40: =IF(Q40<>"",IFERROR(VLOOKUP(Q40,PARTIDAS!A:P,13,FALSE()),0),0) -> 8400.1374 | G40: =IF(Q40<>"",IFERROR(VLOOKUP(Q40,PARTIDAS!A:P,14,FALSE()),0),0) -> 9785.8452 | H40: =IF(Q40<>"",IFERROR(VLOOKUP(Q40,PARTIDAS!A:P,15,FALSE()),0),0) -> 235.33191 | I40: =F40+G40+H40 -> 18421.314 | J40: =F40*E40 -> 6552107.2 | K40: =G40*E40 -> 7632959.3 | L40: =H40*E40 -> 183558.89 | M40: =I40*E40 -> 14368625 | N40: =M40*$N$2 -> 19149067 | Q40: ALB-035 | R40: 2 | S40: APU | T40: =+_xlfn.XLOOKUP(A40,Sheet1!C:C,Sheet1!A:A,"-",0) -> Albañilería | Y40: 14368625 | Z40: =+M40-Y40 -> 0
A41: 4.03 | B41: MAMPOSTERÍA | C41: Muro tipo 3 - Ladrillo comun en panderete | D41: m2 | E41: 56 | F41: =IF(Q41<>"",IFERROR(VLOOKUP(Q41,PARTIDAS!A:P,13,FALSE()),0),0) -> 6454.6901 | G41: =IF(Q41<>"",IFERROR(VLOOKUP(Q41,PARTIDAS!A:P,14,FALSE()),0),0) -> 10484.834 | H41: =IF(Q41<>"",IFERROR(VLOOKUP(Q41,PARTIDAS!A:P,15,FALSE()),0),0) -> 504.28267 | I41: =F41+G41+H41 -> 17443.807 | J41: =F41*E41 -> 361462.65 | K41: =G41*E41 -> 587150.71 | L41: =H41*E41 -> 28239.829 | M41: =I41*E41 -> 976853.19 | N41: =M41*$N$2 -> 1301852.2 | Q41: PTO-0403 | R41: 2 | S41: PRESUPUESTO | T41: =+_xlfn.XLOOKUP(A41,Sheet1!C:C,Sheet1!A:A,"-",0) -> Albañilería | Y41: 976853.19 | Z41: =+M41-Y41 -> 0
A42: 4.04 | B42: MAMPOSTERÍA | C42: Muro tipo 4 - Ladrillo hueco portante 12 x 18 x 33 | D42: m2 | E42: 42 | F42: =IF(Q42<>"",IFERROR(VLOOKUP(Q42,PARTIDAS!A:P,13,FALSE()),0),0) -> 11547.894 | G42: =IF(Q42<>"",IFERROR(VLOOKUP(Q42,PARTIDAS!A:P,14,FALSE()),0),0) -> 9785.8452 | H42: =IF(Q42<>"",IFERROR(VLOOKUP(Q42,PARTIDAS!A:P,15,FALSE()),0),0) -> 235.33191 | I42: =F42+G42+H42 -> 21569.071 | J42: =F42*E42 -> 485011.54 | K42: =G42*E42 -> 411005.5 | L42: =H42*E42 -> 9883.9403 | M42: =I42*E42 -> 905900.98 | N42: =M42*$N$2 -> 1207294.2 | Q42: ALB-038 | R42: 2 | S42: APU | T42: =+_xlfn.XLOOKUP(A42,Sheet1!C:C,Sheet1!A:A,"-",0) -> Albañilería | Y42: 905900.98 | Z42: =+M42-Y42 -> 0
A43: 4.05 | B43: MAMPOSTERÍA | C43: Muro tipo 5 - Bloque HCCA e: 7,5 cm | D43: m2 | E43: 70 | F43: =IF(Q43<>"",IFERROR(VLOOKUP(Q43,PARTIDAS!A:P,13,FALSE()),0),0) -> 16817.941 | G43: =IF(Q43<>"",IFERROR(VLOOKUP(Q43,PARTIDAS!A:P,14,FALSE()),0),0) -> 10484.834 | H43: =IF(Q43<>"",IFERROR(VLOOKUP(Q43,PARTIDAS!A:P,15,FALSE()),0),0) -> 409.54162 | I43: =F43+G43+H43 -> 27712.316 | J43: =F43*E43 -> 1177255.8 | K43: =G43*E43 -> 733938.39 | L43: =H43*E43 -> 28667.914 | M43: =I43*E43 -> 1939862.2 | N43: =M43*$N$2 -> 2585254.3 | Q43: PTO-0405 | R43: 2 | S43: PRESUPUESTO | T43: =+_xlfn.XLOOKUP(A43,Sheet1!C:C,Sheet1!A:A,"-",0) -> Albañilería | Y43: 1939862.2 | Z43: =+M43-Y43 -> 3.001187e-07
A44: 4.06 | B44: MAMPOSTERÍA | C44: Muro tipo 6 - Ladrillo hueco 18 x 18 x 33 | D44: m2 | E44: 5 | F44: =IF(Q44<>"",IFERROR(VLOOKUP(Q44,PARTIDAS!A:P,13,FALSE()),0),0) -> 11492.44 | G44: =IF(Q44<>"",IFERROR(VLOOKUP(Q44,PARTIDAS!A:P,14,FALSE()),0),0) -> 9785.8452 | H44: =IF(Q44<>"",IFERROR(VLOOKUP(Q44,PARTIDAS!A:P,15,FALSE()),0),0) -> 235.33191 | I44: =F44+G44+H44 -> 21513.617 | J44: =F44*E44 -> 57462.202 | K44: =G44*E44 -> 48929.226 | L44: =H44*E44 -> 1176.6596 | M44: =I44*E44 -> 107568.09 | N44: =M44*$N$2 -> 143355.99 | Q44: ALB-036 | R44: 2 | S44: APU | T44: =+_xlfn.XLOOKUP(A44,Sheet1!C:C,Sheet1!A:A,"-",0) -> Albañilería | Y44: 107568.09 | Z44: =+M44-Y44 -> 0
A45: 4.07 | B45: MAMPOSTERÍA | C45: Enchape de medianeras existentes - Contemplamos picado zonas sueltas y enchape con ladrillo comun para PB | D45: m2 | E45: 193 | F45: =IF(Q45<>"",IFERROR(VLOOKUP(Q45,PARTIDAS!A:P,13,FALSE()),0),0) -> 3227.3451 | G45: =IF(Q45<>"",IFERROR(VLOOKUP(Q45,PARTIDAS!A:P,14,FALSE()),0),0) -> 10484.834 | H45: =IF(Q45<>"",IFERROR(VLOOKUP(Q45,PARTIDAS!A:P,15,FALSE()),0),0) -> 252.14133 | I45: =F45+G45+H45 -> 13964.321 | J45: =F45*E45 -> 622877.6 | K45: =G45*E45 -> 2023573 | L45: =H45*E45 -> 48663.278 | M45: =I45*E45 -> 2695113.9 | N45: =M45*$N$2 -> 3591778.2 | Q45: PTO-0407 | S45: PRESUPUESTO | T45: =+_xlfn.XLOOKUP(A45,Sheet1!C:C,Sheet1!A:A,"-",0) -> Albañilería | Y45: 2695113.9 | Z45: =+M45-Y45 -> 0
A46: 4.08 | B46: MAMPOSTERÍA | C46: Cordón de hormigón en umbrales carpinterías | D46: ml | E46: 61 | F46: =IF(Q46<>"",IFERROR(VLOOKUP(Q46,PARTIDAS!A:P,13,FALSE()),0),0) -> 9093.9863 | G46: =IF(Q46<>"",IFERROR(VLOOKUP(Q46,PARTIDAS!A:P,14,FALSE()),0),0) -> 12031.777 | H46: =IF(Q46<>"",IFERROR(VLOOKUP(Q46,PARTIDAS!A:P,15,FALSE()),0),0) -> 316.88645 | I46: =F46+G46+H46 -> 21442.65 | J46: =F46*E46 -> 554733.16 | K46: =G46*E46 -> 733938.39 | L46: =H46*E46 -> 19330.073 | M46: =I46*E46 -> 1308001.6 | N46: =M46*$N$2 -> 1743173.8 | Q46: PTO-0408 | R46: 2 | S46: PRESUPUESTO | T46: =+_xlfn.XLOOKUP(A46,Sheet1!C:C,Sheet1!A:A,"-",0) -> Albañilería | Y46: 1308001.6 | Z46: =+M46-Y46 -> 0
