Workbook

Sheet CONFIG
A1: CONFIGURACIÓN DEL APU
A3: Parámetro | B3: Valor | C3: Notas
A4: Mes de referencia | B4: Junio | C4: Mes de precios del APU
A5: Año de referencia | B5: 2025
A6: Versión | B6: v3.0 — APU Chivilcoy 06-25
A7: GG% | B7: 0 | C7: 0 = se aplica en presupuesto de obra
A8: BB% | B8: 0
A9: Tipo Cambio USD (MEP) | B9: 1200 | C9: Pesos por dólar
A10: Revisado por | B10: MC
A11: Mes base CAC | B11: Junio 2025
A12: CAC base (valor) | B12: 16000 | C12: Referencial
A14: TABLA DE CARGAS MO
A15: Componente | B15: Tipo | C15: Valor | D15: Fuente
A16: Cargas patronales | B16: % | C16: 0.42 | D16: Convenio UOCRA (est.)
A17: ART | B17: % | C17: 0.085 | D17: Aseguradora (est.)
A18: Ropa de trabajo | B18: $/mes | C18: 85000 | D18: Compras (est.)
A19: Viáticos | B19: $/día | C19: 3200 | D19: Convenio UOCRA (est.)
A20: Vacaciones + SAC | B20: % | C20: 0.15 | D20: Cálculo legal (est.)
A22: COEFICIENTE FINAL | B22: multiplicador | C22: =1+C16+C17+C20+(C18/78291/22)+(C19/78291) -> 1.7452228
A24: Última corrección | B24: 2026-05-14
A25: Hallazgos aplicados | B25: H-002, H-003, H-004, H-005, H-006, H-007 (v3.1)
A26: Hallazgos pendientes | B26: H-001, H-008, H-009, H-010, H-011

Sheet MATERIALES
A1: Código | B1: Descripción | C1: Unidad | D1: Precio $ | E1: Proveedor | F1: Fecha Cotiz. | G1: Categoría | H1: Cód. Original | I1: Nota
A2: ACE-001 | B2: Barra de Acero Aleteado - 6mm x 12m | D2: 3620.13 | G2: Corralón
A3: ACE-016 | B3: ACERO ESTRUCTURAL POR KILO | D3: 1338.79 | G3: Corralón
A4: AGR-001 | B4: ARENA LAVADA | D4: 32620.38 | G4: Corralón
A5: AGR-004 | B5: Cemento Portland x 50kg | D5: 7891.74 | G5: Corralón
A6: AGR-005 | B6: Cal Comun x 25kg | D6: 3927.28 | G6: Corralón
A7: AIS-001 | B7: Aditivo Hidrofugo en pasta - Ceresita x 1kg | D7: 1363.95 | G7: Impermeabilizantes
A8: CER-005 | B8: Ladrillo Comun 12.5 x 5.5 x 25 | D8: 148.05 | G8: Corralón
A9: ACE-015 | B9: CLAVOS DE 21/2" X 12 | D9: 2647.2225 | G9: Corralón
A10: ACE-010 | B10: Alambre de fardo | D10: 2660.68 | G10: Corralón
A11: OTR-031 | B11: FENOLICO 18MM. COMUN 1.22 x 2.40 | D11: 20401.25 | G11: Corralón
A12: OTR-033 | B12: tirante 3x3 para puntal 3.66 | D12: 1270.4832 | G12: Corralón
A13: OTR-034 | B13: tirante 3x6 3.66 | D13: 4649.9685 | G13: Corralón
A14: MAT-CONS | B14: CONSUMIBLES (varios) | C14: gl | D14: 1 | G14: Consumibles
A15: OTR-032 | B15: FENOLICO 18MM. LAMINADO MELAMINICO | D15: 49748.25 | G15: Corralón
A16: CER-002 | B16: LADRILLO CERAMICO 8 x 18 x 33 cm | D16: 506.52 | G16: Corralón
A17: CER-003 | B17: LADRILLO CERAMICO 12 x 18 x 33 cm | D17: 624.96 | G17: Corralón
A18: CER-004 | B18: LADRILLO CERAMICO 18 x 18 x 33 cm | D18: 894.6 | G18: Corralón
A19: CER-006 | B19: Ladrillo hueco ceramico 12x19x33 - Portante | D19: 977.76 | G19: Corralón
A20: PIN-008 | B20: Pintura Asfaltica Asfasol x18ts | D20: 35525.95 | G20: Pinturas
A21: ELE-001 | B21: Recuplast Tradicional Blanco x 20 lts | D21: 106809.92 | G21: Eléctricos
A22: PIN-001 | B22: Latex Loxon Interior Sherwin Williams Mate Bco x 20lts | D22: 143389.26 | G22: Pinturas
A23: PIN-007 | B23: Enduido Interior x 20lts | D23: 41314.05 | G23: Pinturas
A24: OTR-023 | B24: Lija 180 al agua x 10u | D24: 7917.3554 | G24: Pinturas
A25: OTR-024 | B25: Cinta de Papel 36 mm x 40m | D25: 5885.9504 | G25: Pinturas
A26: OTR-025 | B26: Trapo | D26: 1182.6446 | G26: Pinturas
... A29: OTR-022 | B29: Aguarras Hydrarras Hydra x 18lts | D29: 58016.529 | G29: Pinturas
A30: OTR-PTO002 | B30: Chapa acanalada C25 | C30: u | D30: 10861.769 | G30: Carpintería metálica
A31: OTR-PTO003 | B31: Perfiles UPN 100 | C31: u | D31: 271144.89 | G31: Carpintería metálica
A32: OTR-PTO004 | B32: Bastidor para porton corredizo - Perfil 40 x 40 x 2 | C32: u | D32: 23523.752 | G32: Carpintería metálica
A33: OTR-PTO005 | B33: Riel Roma 174 e: 2,1 mm. 53 x 60 x 6000 | C33: u | D33: 85391.38 | G33: Carpintería metálica
A34: OTR-PTO006 | B34: Carro acero 174 4 ruedas puertas portones Ø45mm | C34: u | D34: 11534.744 | G34: Carpintería metálica
A35: OTR-PTO007 | B35: Autoperforantes punta mecha 14 x 2 | C35: u | D35: 120 | G35: Ferretería
A36: OTR-PTO008 | B36: Rollo Concertina | C36: u | D36: 41322.314 | G36: Carpintería metálica
A37: OTR-PTO9000 | B37: Puntales 3 x 3 x 3,7 | C37: u | D37: 4992.1647 | G37: Encofrados
A38: OTR-PTO009 | B38: Chapa acanalada C25 - Reutilizado (estimado 3 usos) | C38: u | D38: 5430.8843 | G38: Encofrados
A39: OTR-PTO010 | B39: Fenolico 1,22 x 2,44 - Reutilizado (estimado 3 usos) | C39: u | D39: 13196.9 | G39: Encofrados
A40: OTR-PTO011 | B40: Puntales 1 x 4 x 3,7 - Reutilizado (estimado 3 usos) | C40: u | D40: 1109.369 | G40: Encofrados
A41: OTR-PTO012 | B41: Puntales 3 x 3 x 3,7 - Reutilizado (estimado 3 usos) | C41: u | D41: 2496.0823 | G41: Encofrados
... A187: OTR-PTO159 | B187: ELECT — Módulo completo TV/RED marca Cambre línea SXX | C187: u | D187: 2203.1709 | G187: Eléctricos
A188: ELE-011 | B188: Cable unipolar 1 x 4,00 | D188: 895.33242 | G188: Eléctricos
A189: ADT-002 | B189: Venda SikaTEX 75 - Rollo | D189: 100000 | G189: Impermeabilizantes
A190: PIN-006 | B190: Esmalte sintetico satinado Satinol Blanco x 4lts | D190: 50027.273 | G190: Pinturas
A191: CER-001 | B191: Ladrillo a la vista 1 cara | C191: u | D191: 233.44 | G191: Corralón
A192: DRY-KLIMABLOCK | B192: Ladrillo Ceramico Kilablock 27 x 18 x 33 | C192: u | D192: 0 | G192: Corralón
A193: OTR-027 | B193: Rodillo de lana pelo largo N°22 - El Galgo | C193: u | D193: 6442.15 | G193: Pinturas
A194: DUR-001 | B194: Solera 70mm x 2.60m | C194: u | D194: 3084.79 | G194: Construcción en seco
A195: DUR-002 | B195: Montante 69mm x 2.60m | C195: u | D195: 3385.62 | G195: Construcción en seco
A196: DUR-003 | B196: Solera 35mm x 2.60m | C196: u | D196: 2244.87 | G196: Construcción en seco
A197: DUR-004 | B197: Montante 34mm x 2.60m | C197: u | D197: 2574.72 | G197: Construcción en seco
A198: OTR-007 | B198: Tornillo T1 - Aguja | C198: u | D198: 26.153884 | G198: Construcción en seco
A199: OTR-008 | B199: Tornillo T2 - Aguja | C199: u | D199: 9.114692 | G199: Construcción en seco
A200: OTR-009 | B200: Tornillo T3 - Aguja | C200: u | D200: 18.832004 | G200: Construcción en seco
A201: OTR-010 | B201: Fijacion completa del 8 | C201: u | D201: 63.381983 | G201: Construcción en seco
A202: OTR-011 | B202: Cinta Entramada - 90m | C202: u | D202: 4734.07 | G202: Construcción en seco
... A368: HAO-ENC-ESCAL | B368: ENCOFRADO — Escalera | C368: m3 | D368: 59263.233 | G368: Encofrados

Sheet EQUIPOS
A1: Código | B1: Descripción | C1: Costo Total $ | D1: Vida (años) | E1: Vida (días) | F1: $/día | G1: Categoría
A2: EQ-ESCALE | B2: ESCALERA GLOSS ALUMINIO ARTICULADA 4 X 4 ESCALONES HASTA 150KG | C2: 219427.59 | D2: 4 | E2: =D2*360 -> 1440 | F2: =IF(E2=0,0,C2/E2) -> 152.38027 | G2: Equipo propio
A3: EQ-ANDAM0 | B3: ANDAMIO TUBULAR DE UNO A TRES CUERPOS | C3: 1117459.4 | D3: 5 | E3: =D3*360 -> 1800 | F3: =IF(E3=0,0,C3/E3) -> 620.81078 | G3: Equipo propio
A4: EQ-BALANC | B4: Balancin | C4: 12170160 | D4: 10 | E4: =D4*360 -> 3600 | F4: =IF(E4=0,0,C4/E4) -> 3380.6 | G4: Equipo propio
A5: EQ-CORTA | B5: CORTADORA CERAMICA PROFESIONAL 1200MM (PORCELANATO HASTA 16MM) | C5: 583838.42 | D5: 5 | E5: =D5*360 -> 1800 | F5: =IF(E5=0,0,C5/E5) -> 324.35468 | G5: Equipo propio
A6: EQ-EQALBA | B6: EQUIPO DE ALBAÑILERIA, carpetas, ladrillo | C6: 2684740.7 | D6: 3 | E6: =D6*360 -> 1080 | F6: =IF(E6=0,0,C6/E6) -> 2485.871 | G6: Equipo propio
A7: EQ-EQCERA | B7: EQUIPO PARA COLOCACION DE CERAMICA | C7: 1547796.6 | D7: 1.5 | E7: =D7*360 -> 540 | F7: =IF(E7=0,0,C7/E7) -> 2866.29 | G7: Equipo propio
A8: EQ-EQPLOM | B8: EQUIPO PARA PLOMERIA | C8: 2237101.1 | D8: 2 | E8: =D8*360 -> 720 | F8: =IF(E8=0,0,C8/E8) -> 3107.0849 | G8: Equipo propio
A9: EQ-EQUIP0 | B9: EQUIPO PARA INSTALACION ELECTRICA | C9: 2971641.8 | D9: 1.5 | E9: =D9*360 -> 540 | F9: =IF(E9=0,0,C9/E9) -> 5503.0404 | G9: Equipo propio
A10: EQ-EQUIPI | B10: EQUIPO PARA PINTAR | C10: 1348845.4 | D10: 2 | E10: =D10*360 -> 720 | F10: =IF(E10=0,0,C10/E10) -> 1873.3964 | G10: Equipo propio
A11: EQ-HORMI | B11: EQUIPO PARA HORMIGON | C11: 4064822.7 | D11: 1.5 | E11: =D11*360 -> 540 | F11: =IF(E11=0,0,C11/E11) -> 7527.4494 | G11: Equipo propio
A12: EQ-PTO001 | B12: Herramientas — Topógrafo - Visita de obra replanteo | C12: 4599.5184 | D12: 1 | E12: 1 | F12: =IF(E12=0,0,C12/E12) -> 4599.5184 | G12: Herramientas — Preliminares
A13: EQ-PTO002 | B13: Herramientas — Cerco de obra perimetral - En chapa C25 | C13: 3162.1221 | D13: 1 | E13: 1 | F13: =IF(E13=0,0,C13/E13) -> 3162.1221 | G13: Herramientas — Preliminares
A14: EQ-PTO003 | B14: Herramientas — Obrador, pañol y ducha | C14: 128918.42 | D14: 1 | E14: 1 | F14: =IF(E14=0,0,C14/E14) -> 128918.42 | G14: Herramientas — Preliminares
A15: EQ-PTO004 | B15: Herramientas — Conexión pilar y luz de obra + Tablero d | C15: 30769.28 | D15: 1 | E15: 1 | F15: =IF(E15=0,0,C15/E15) -> 30769.28 | G15: Herramientas — Preliminares
A16: EQ-PTO005 | B16: Herramientas — Conexión agua de obra, tanque + bomba | C16: 22085.534 | D16: 1 | E16: 1 | F16: =IF(E16=0,0,C16/E16) -> 22085.534 | G16: Herramientas — Preliminares
A17: EQ-PTO006 | B17: Herramientas — Excavación para cámara transformadora | C17: 467.46075 | D17: 1 | E17: 1 | F17: =IF(E17=0,0,C17/E17) -> 467.46075 | G17: Herramientas — Preliminares
A18: EQ-PTO007 | B18: Herramientas — Hormigón de limpieza - e: 10 cm | C18: 4132.0683 | D18: 1 | E18: 1 | F18: =IF(E18=0,0,C18/E18) -> 4132.0683 | G18: Herramientas — Hormigón
A19: EQ-PTO008 | B19: Herramientas — Micropilotes Ø 20 cm | C19: 718505.14 | D19: 1 | E19: 1 | F19: =IF(E19=0,0,C19/E19) -> 718505.14 | G19: Herramientas — Hormigón
A20: EQ-PTO009 | B20: Herramientas — Platea - H30 (110 kg/m3 de hierro) | C20: 8701.1119 | D20: 1 | E20: 1 | F20: =IF(E20=0,0,C20/E20) -> 8701.1119 | G20: Herramientas — Hormigón
A21: EQ-PTO010 | B21: Herramientas — Zapata corrida tabique - H30 (180 kg/m3 | C21: 12913.459 | D21: 1 | E21: 1 | F21: =IF(E21=0,0,C21/E21) -> 12913.459 | G21: Herramientas — Hormigón
A22: EQ-PTO011 | B22: Herramientas — Bases aisladas - H30 (110 kg/m3 de hierr | C22: 8701.1119 | D22: 1 | E22: 1 | F22: =IF(E22=0,0,C22/E22) -> 8701.1119 | G22: Herramientas — Hormigón
A23: EQ-PTO012 | B23: Herramientas — Cabezales - H30 (130 kg/m3 de hierro) | C23: 9232.7119 | D23: 1 | E23: 1 | F23: =IF(E23=0,0,C23/E23) -> 9232.7119 | G23: Herramientas — Hormigón
... A97: EQ-PTO086 | B97: Herramientas — Volquetes | C97: 4008.6075 | D97: 1 | E97: 1 | F97: =IF(E97=0,0,C97/E97) -> 4008.6075 | G97: Herramientas — Instalaciones
A98: EQ-SILLET | B98: Kit Complementario Silleta Descensor Conector Soga X 50 Mts | C98: 743114.75 | D98: 1 | E98: =D98*360 -> 360 | F98: =IF(E98=0,0,C98/E98) -> 2064.2076 | G98: Equipo propio
A99: EQ-SOLD00 | B99: Soldador Soplete A Gas Techista Membrana 10 Kg Boca 50mm | C99: 629576.14 | D99: 2 | E99: =D99*360 -> 720 | F99: =IF(E99=0,0,C99/E99) -> 874.41131 | G99: Equipo propio
A100: EQ-TROMPO | B100: Hormigonera De 150 Litros 1hp Con Rueda Maciza | C100: 749110.64 | D100: 2 | E100: =D100*360 -> 720 | F100: =IF(E100=0,0,C100/E100) -> 1040.4314 | G100: Equipo propio
A101: EQ-PTO026 | B101: Escalera madera pintor 8 escalones | C101: 78355.295 | D101: 1 | E101: =D101*360 -> 360 | F101: =IF(E101=0,0,C101/E101) -> 217.6536 | G101: Equipo propio
A102: EQ-PTO087 | B102: Equipos viales — Pala/retro 310J + Camión volcador 170E22 + Compactador pata cabra 612H | C102: 1005000 | D102: 0.0027777778 | E102: =D102*360 -> 1 | F102: =IF(E102=0,0,C102/E102) -> 1005000 | G102: Alquiler diario
A103: EQ-PTO024 | B103: EQUIPO DE CONSTRUCCION EN SECO | C103: 1850947.1 | D103: 2 | E103: =D103*360 -> 720 | F103: =IF(E103=0,0,C103/E103) -> 2570.7599 | G103: Equipo propio
A104: EQ-REVOC | B104: Máquina revocadora Yeso/Revoque 3-en-1 | C104: 1230000 | D104: 0.083333333 | E104: =D104*360 -> 30 | F104: =IF(E104=0,0,C104/E104) -> 41000 | G104: Equipo propio

Sheet SUBCONTRATOS_PRY
A1: Código | B1: Descripción | C1: Ud | D1: Precio Unitario ($) | E1: Categoría | F1: Notas
A2: SUB-PTO001 | B2: M.Obra topografo | C2: d | D2: 214394.06 | E2: Varios
A3: SUB-PTO002 | B3: Flete madera | C3: u | D3: 250000 | E3: Varios
A4: SUB-PTO003 | B4: Alquiler de baños quimico | C4: mes | D4: 80000 | E4: Varios
A5: SUB-PTO004 | B5: Limpieza adicional | C5: mes | D5: 80000 | E5: Varios
A6: SUB-PTO005 | B6: Alquiler de modulo de ducha | C6: mes | D6: 80000 | E6: Varios
A7: SUB-PTO006 | B7: Fletes de entrega y retiro | C7: u | D7: 20000 | E7: Varios
A8: SUB-PTO007 | B8: Gestion suministro luz de obra | C8: u | D8: 157327.46 | E8: Electricidad — Gestión
A9: SUB-PTO008 | B9: Luz de Obra | C9: u | D9: 113275.77 | E9: Electricidad — Gestión
A10: SUB-PTO009 | B10: Medicion PAT luz de obra | C10: u | D10: 99116.3 | E10: Electricidad — Gestión
A11: SUB-PTO010 | B11: Desmonte y aporte de tosca | C11: m2 | D11: 23552.222 | E11: Movimiento de suelos
A12: SUB-PTO011 | B12: Maquina 6 tn | C12: d | D12: 528000 | E12: Movimiento de suelos
A13: SUB-PTO012 | B13: Viajes camión | C13: u | D13: 140000 | E13: Movimiento de suelos
... A93: SUB-PTO093 | B93: Gestor Gas — Final | C93: gl | D93: 400000 | E93: Gas
A94: SUB-PTO094 | B94: MO — Zócalo de concreto en escalera | C94: ml | D94: =4324.04776527307*28 -> 121073.34 | E94: Revestimientos y yesos
A95: SUB-PTO095 | B95: MO — Revestimiento plástico a llana tipo Quimtex en altura - Aire luz y balcones | C95: m2 | D95: 4940.3619 | E95: Revestimientos y yesos

Sheet MANO_DE_OBRA
A1: Código | B1: Descripción | C1: Salario/día $ | D1: Coef. Cargas | E1: Costo Jornal $ | F1: Tipo | G1: Cód. Original
A2: MO-EAYUD | B2: AYUDANTE | C2: 67240.499 | D2: =CONFIG!C22 -> 1.7452228 | E2: =C2*D2 -> 117349.65 | F2: Operativo
A3: MO-EMEDI | B3: MEDIO OFICIAL | C3: 72132.138 | D3: =CONFIG!C22 -> 1.7452228 | E3: =C3*D3 -> 125886.66 | F3: Operativo
A4: MO-EOFIC | B4: OFICIAL | C4: 84612.513 | D4: =CONFIG!C22 -> 1.7452228 | E4: =C4*D4 -> 147667.69 | F4: Operativo
A5: MO-EESPE | B5: ESPECIALIZADO | C5: 94177.138 | D5: =CONFIG!C22 -> 1.7452228 | E5: =C5*D5 -> 164360.09 | F5: Operativo
A6: MO-ESOBR | B6: SOBRESTANTE | C6: 147568.59 | D6: =CONFIG!C22 -> 1.7452228 | E6: =C6*D6 -> 257540.07 | F6: Gerencial
A7: MO-ECAPA | B7: CAPATAZ | C7: 161430.42 | D7: =CONFIG!C22 -> 1.7452228 | E7: =C7*D7 -> 281732.06 | F7: Gerencial
A8: MO-TOP | B8: TOPOGRAFO | C8: 188354.28 | D8: =CONFIG!C22 -> 1.7452228 | E8: =C8*D8 -> 328720.18 | F8: Operativo
A9: MO-EJEFE | B9: JEFE DE OBRA | C9: 214394.06 | D9: =CONFIG!C22 -> 1.7452228 | E9: =C9*D9 -> 374165.41 | F9: Gerencial
A10: MO-ECOOR | B10: COORD OBRAS | C10: 258581.93 | D10: =CONFIG!C22 -> 1.7452228 | E10: =C10*D10 -> 451283.09 | F10: Gerencial
A11: MO-ALBVHV | B11: MO Albañilería complementaria — Viga H°V (25% MO H°A°) | C11: 157396.09 | D11: =CONFIG!C22 -> 1.7452228 | E11: =C11*D11 -> 274691.25 | F11: Operativo
A12: MO-ALBLHV | B12: MO Albañilería complementaria — Losa H°V (25% MO H°A°) | C12: 63408.113 | D12: =CONFIG!C22 -> 1.7452228 | E12: =C12*D12 -> 110661.29 | F12: Operativo

Sheet COMPOSICIÓN
A1: Partida | B1: Tipo | C1: Subtipo | D1: Cod_Insumo | E1: Descripción | F1: Unidad de medida | G1: Cant | H1: %Desp | I1: Precio | J1: Costo | K1: Clave | L1: Count | M1: Clave2 | N1: Rend. Part. | O1: Cant MO/ALB Unit | P1: Cant. Ej. Part. | Q1: Cant MO/ALB Total | R1: en PPTO?
A2: APU-101 | B2: MO | C2: ALB | D2: MO-EESPE | E2: =IFERROR(VLOOKUP(D2,MANO_DE_OBRA!A:B,2,FALSE()),"?") -> ESPECIALIZADO | F2: j | G2: 1 | H2: 0 | I2: =IFERROR(VLOOKUP(D2,MANO_DE_OBRA!A:C,3,FALSE()),0) -> 94177.138 | J2: =G2*I2 -> 94177.138 | K2: =A2&"|"&B2 -> APU-101|MO | L2: =COUNTIFS($K$2:K2,K2) -> 1 | M2: =K2&"|"&L2 -> APU-101|MO|1 | N2: =IFERROR(VLOOKUP(A2,PARTIDAS!A:F,6,FALSE()),0) -> 1 | O2: =+IF(C2="ALB",G2/N2,0) -> 1 | P2: =+_xlfn.XLOOKUP(A2,PPTO_GENERADOR!Q:Q,PPTO_GENERADOR!E:E,"-",0) -> - | Q2: =IFERROR(P2*O2,0) -> 0 | R2: =+_xlfn.XLOOKUP(A2,PPTO_GENERADOR!$Q:$Q,PPTO_GENERADOR!A:A,"-",0) -> -
A3: APU-101 | B3: MO | C3: ALB | D3: MO-EAYUD | E3: =IFERROR(VLOOKUP(D3,MANO_DE_OBRA!A:B,2,FALSE()),"?") -> AYUDANTE | F3: j | G3: 1 | H3: 0 | I3: =IFERROR(VLOOKUP(D3,MANO_DE_OBRA!A:C,3,FALSE()),0) -> 67240.499 | J3: =G3*I3 -> 67240.499 | K3: =A3&"|"&B3 -> APU-101|MO | L3: =COUNTIFS($K$2:K3,K3) -> 2 | M3: =K3&"|"&L3 -> APU-101|MO|2 | N3: =IFERROR(VLOOKUP(A3,PARTIDAS!A:F,6,FALSE()),0) -> 1 | O3: =+IF(C3="ALB",G3/N3,0) -> 1 | P3: =+_xlfn.XLOOKUP(A3,PPTO_GENERADOR!Q:Q,PPTO_GENERADOR!E:E,"-",0) -> - | Q3: =IFERROR(P3*O3,0) -> 0 | R3: =+_xlfn.XLOOKUP(A3,PPTO_GENERADOR!$Q:$Q,PPTO_GENERADOR!A:A,"-",0) -> -
A4: BAN-106 | B4: MO | C4: ALB | D4: MO-EESPE | E4: =IFERROR(VLOOKUP(D4,MANO_DE_OBRA!A:B,2,FALSE()),"?") -> ESPECIALIZADO | F4: j | G4: 1 | H4: 0 | I4: =IFERROR(VLOOKUP(D4,MANO_DE_OBRA!A:C,3,FALSE()),0) -> 94177.138 | J4: =G4*I4 -> 94177.138 | K4: =A4&"|"&B4 -> BAN-106|MO | L4: =COUNTIFS($K$2:K4,K4) -> 1 | M4: =K4&"|"&L4 -> BAN-106|MO|1 | N4: =IFERROR(VLOOKUP(A4,PARTIDAS!A:F,6,FALSE()),0) -> 3.8 | O4: =+IF(C4="ALB",G4/N4,0) -> 0.26315789 | P4: =+_xlfn.XLOOKUP(A4,PPTO_GENERADOR!Q:Q,PPTO_GENERADOR!E:E,"-",0) -> - | Q4: =IFERROR(P4*O4,0) -> 0 | R4: =+_xlfn.XLOOKUP(A4,PPTO_GENERADOR!$Q:$Q,PPTO_GENERADOR!A:A,"-",0) -> -
A5: BAN-106 | B5: MO | C5: ALB | D5: MO-EAYUD | E5: =IFERROR(VLOOKUP(D5,MANO_DE_OBRA!A:B,2,FALSE()),"?") -> AYUDANTE | F5: j | G5: 1 | H5: 0 | I5: =IFERROR(VLOOKUP(D5,MANO_DE_OBRA!A:C,3,FALSE()),0) -> 67240.499 | J5: =G5*I5 -> 67240.499 | K5: =A5&"|"&B5 -> BAN-106|MO | L5: =COUNTIFS($K$2:K5,K5) -> 2 | M5: =K5&"|"&L5 -> BAN-106|MO|2 | N5: =IFERROR(VLOOKUP(A5,PARTIDAS!A:F,6,FALSE()),0) -> 3.8 | O5: =+IF(C5="ALB",G5/N5,0) -> 0.26315789 | P5: =+_xlfn.XLOOKUP(A5,PPTO_GENERADOR!Q:Q,PPTO_GENERADOR!E:E,"-",0) -> - | Q5: =IFERROR(P5*O5,0) -> 0 | R5: =+_xlfn.XLOOKUP(A5,PPTO_GENERADOR!$Q:$Q,PPTO_GENERADOR!A:A,"-",0) -> -
A6: ALB-110 | B6: MO | C6: ALB | D6: MO-EESPE | E6: =IFERROR(VLOOKUP(D6,MANO_DE_OBRA!A:B,2,FALSE()),"?") -> ESPECIALIZADO | F6: j | G6: 1 | H6: 0 | I6: =IFERROR(VLOOKUP(D6,MANO_DE_OBRA!A:C,3,FALSE()),0) -> 94177.138 | J6: =G6*I6 -> 94177.138 | K6: =A6&"|"&B6 -> ALB-110|MO | L6: =COUNTIFS($K$2:K6,K6) -> 1 | M6: =K6&"|"&L6 -> ALB-110|MO|1 | N6: =IFERROR(VLOOKUP(A6,PARTIDAS!A:F,6,FALSE()),0) -> 36 | O6: =+IF(C6="ALB",G6/N6,0) -> 0.027777778 | P6: =+_xlfn.XLOOKUP(A6,PPTO_GENERADOR!Q:Q,PPTO_GENERADOR!E:E,"-",0) -> - | Q6: =IFERROR(P6*O6,0) -> 0 | R6: =+_xlfn.XLOOKUP(A6,PPTO_GENERADOR!$Q:$Q,PPTO_GENERADOR!A:A,"-",0) -> -
A7: ALB-110 | B7: MO | C7: ALB | D7: MO-EAYUD | E7: =IFERROR(VLOOKUP(D7,MANO_DE_OBRA!A:B,2,FALSE()),"?") -> AYUDANTE | F7: j | G7: 2 | H7: 0 | I7: =IFERROR(VLOOKUP(D7,MANO_DE_OBRA!A:C,3,FALSE()),0) -> 67240.499 | J7: =G7*I7 -> 134481 | K7: =A7&"|"&B7 -> ALB-110|MO | L7: =COUNTIFS($K$2:K7,K7) -> 2 | M7: =K7&"|"&L7 -> ALB-110|MO|2 | N7: =IFERROR(VLOOKUP(A7,PARTIDAS!A:F,6,FALSE()),0) -> 36 | O7: =+IF(C7="ALB",G7/N7,0) -> 0.055555556 | P7: =+_xlfn.XLOOKUP(A7,PPTO_GENERADOR!Q:Q,PPTO_GENERADOR!E:E,"-",0) -> - | Q7: =IFERROR(P7*O7,0) -> 0 | R7: =+_xlfn.XLOOKUP(A7,PPTO_GENERADOR!$Q:$Q,PPTO_GENERADOR!A:A,"-",0) -> -
A8: ALB-110 | B8: MO | C8: ALB | D8: MO-EMEDI | E8: =IFERROR(VLOOKUP(D8,MANO_DE_OBRA!A:B,2,FALSE()),"?") -> MEDIO OFICIAL | F8: j | G8: 5 | H8: 0 | I8: =IFERROR(VLOOKUP(D8,MANO_DE_OBRA!A:C,3,FALSE()),0) -> 72132.138 | J8: =G8*I8 -> 360660.69 | K8: =A8&"|"&B8 -> ALB-110|MO | L8: =COUNTIFS($K$2:K8,K8) -> 3 | M8: =K8&"|"&L8 -> ALB-110|MO|3 | N8: =IFERROR(VLOOKUP(A8,PARTIDAS!A:F,6,FALSE()),0) -> 36 | O8: =+IF(C8="ALB",G8/N8,0) -> 0.13888889 | P8: =+_xlfn.XLOOKUP(A8,PPTO_GENERADOR!Q:Q,PPTO_GENERADOR!E:E,"-",0) -> - | Q8: =IFERROR(P8*O8,0) -> 0 | R8: =+_xlfn.XLOOKUP(A8,PPTO_GENERADOR!$Q:$Q,PPTO_GENERADOR!A:A,"-",0) -> -
A9: AIS-113 | B9: MAT | C9: OTR | D9: PIN-008 | E9: =IFERROR(VLOOKUP(D9,MATERIALES!A:B,2,FALSE()),"?") -> Pintura Asfaltica Asfasol x18ts | F9: =IFERROR(VLOOKUP(D9,MATERIALES!A:C,3,FALSE()),"?") -> 0 | G9: 0.0278 | H9: 0.1 | I9: =IFERROR(VLOOKUP(D9,MATERIALES!A:D,4,FALSE()),0) -> 35525.95 | J9: =G9*I9*(1+H9) -> 1086.3836 | K9: =A9&"|"&B9 -> AIS-113|MAT | L9: =COUNTIFS($K$2:K9,K9) -> 1 | M9: =K9&"|"&L9 -> AIS-113|MAT|1 | N9: =IFERROR(VLOOKUP(A9,PARTIDAS!A:F,6,FALSE()),0) -> 80 | O9: =+IF(C9="ALB",G9/N9,0) -> 0 | P9: =+_xlfn.XLOOKUP(A9,PPTO_GENERADOR!Q:Q,PPTO_GENERADOR!E:E,"-",0) -> - | Q9: =IFERROR(P9*O9,0) -> 0 | R9: =+_xlfn.XLOOKUP(A9,PPTO_GENERADOR!$Q:$Q,PPTO_GENERADOR!A:A,"-",0) -> -
A10: AIS-113 | B10: MAT | C10: OTR | D10: OTR-027 | E10: =IFERROR(VLOOKUP(D10,MATERIALES!A:B,2,FALSE()),"?") -> Rodillo de lana pelo largo N°22 - El Galgo | F10: =IFERROR(VLOOKUP(D10,MATERIALES!A:C,3,FALSE()),"?") -> u | G10: 0.01 | H10: 0.05 | I10: =IFERROR(VLOOKUP(D10,MATERIALES!A:D,4,FALSE()),0) -> 6442.15 | J10: =G10*I10*(1+H10) -> 67.642575 | K10: =A10&"|"&B10 -> AIS-113|MAT | L10: =COUNTIFS($K$2:K10,K10) -> 2 | M10: =K10&"|"&L10 -> AIS-113|MAT|2 | N10: =IFERROR(VLOOKUP(A10,PARTIDAS!A:F,6,FALSE()),0) -> 80 | O10: =+IF(C10="ALB",G10/N10,0) -> 0 | P10: =+_xlfn.XLOOKUP(A10,PPTO_GENERADOR!Q:Q,PPTO_GENERADOR!E:E,"-",0) -> - | Q10: =IFERROR(P10*O10,0) -> 0 | R10: =+_xlfn.XLOOKUP(A10,PPTO_GENERADOR!$Q:$Q,PPTO_GENERADOR!A:A,"-",0) -> -
A11: AIS-113 | B11: MAT | C11: OTR | D11: OTR-028 | E11: =IFERROR(VLOOKUP(D11,MATERIALES!A:B,2,FALSE()),"?") -> Pincel N° 20 - El Galgo | F11: =IFERROR(VLOOKUP(D11,MATERIALES!A:C,3,FALSE()),"?") -> u | G11: 0.02 | H11: 0.05 | I11: =IFERROR(VLOOKUP(D11,MATERIALES!A:D,4,FALSE()),0) -> 4418.1818 | J11: =G11*I11*(1+H11) -> 92.781818 | K11: =A11&"|"&B11 -> AIS-113|MAT | L11: =COUNTIFS($K$2:K11,K11) -> 3 | M11: =K11&"|"&L11 -> AIS-113|MAT|3 | N11: =IFERROR(VLOOKUP(A11,PARTIDAS!A:F,6,FALSE()),0) -> 80 | O11: =+IF(C11="ALB",G11/N11,0) -> 0 | P11: =+_xlfn.XLOOKUP(A11,PPTO_GENERADOR!Q:Q,PPTO_GENERADOR!E:E,"-",0) -> - | Q11: =IFERROR(P11*O11,0) -> 0 | R11: =+_xlfn.XLOOKUP(A11,PPTO_GENERADOR!$Q:$Q,PPTO_GENERADOR!A:A,"-",0) -> -
A12: AIS-113 | B12: MAT | C12: OTR | D12: OTR-022 | E12: =IFERROR(VLOOKUP(D12,MATERIALES!A:B,2,FALSE()),"?") -> Aguarras Hydrarras Hydra x 18lts | F12: =IFERROR(VLOOKUP(D12,MATERIALES!A:C,3,FALSE()),"?") -> 0 | G12: 0.002 | H12: 0.05 | I12: =IFERROR(VLOOKUP(D12,MATERIALES!A:D,4,FALSE()),0) -> 58016.529 | J12: =G12*I12*(1+H12) -> 121.83471 | K12: =A12&"|"&B12 -> AIS-113|MAT | L12: =COUNTIFS($K$2:K12,K12) -> 4 | M12: =K12&"|"&L12 -> AIS-113|MAT|4 | N12: =IFERROR(VLOOKUP(A12,PARTIDAS!A:F,6,FALSE()),0) -> 80 | O12: =+IF(C12="ALB",G12/N12,0) -> 0 | P12: =+_xlfn.XLOOKUP(A12,PPTO_GENERADOR!Q:Q,PPTO_GENERADOR!E:E,"-",0) -> - | Q12: =IFERROR(P12*O12,0) -> 0 | R12: =+_xlfn.XLOOKUP(A12,PPTO_GENERADOR!$Q:$Q,PPTO_GENERADOR!A:A,"-",0) -> -
A13: AIS-113 | B13: MAT | C13: OTR | D13: OTR-025 | E13: =IFERROR(VLOOKUP(D13,MATERIALES!A:B,2,FALSE()),"?") -> Trapo | F13: =IFERROR(VLOOKUP(D13,MATERIALES!A:C,3,FALSE()),"?") -> 0 | G13: 0.02 | H13: 0.05 | I13: =IFERROR(VLOOKUP(D13,MATERIALES!A:D,4,FALSE()),0) -> 1182.6446 | J13: =G13*I13*(1+H13) -> 24.835537 | K13: =A13&"|"&B13 -> AIS-113|MAT | L13: =COUNTIFS($K$2:K13,K13) -> 5 | M13: =K13&"|"&L13 -> AIS-113|MAT|5 | N13: =IFERROR(VLOOKUP(A13,PARTIDAS!A:F,6,FALSE()),0) -> 80 | O13: =+IF(C13="ALB",G13/N13,0) -> 0 | P13: =+_xlfn.XLOOKUP(A13,PPTO_GENERADOR!Q:Q,PPTO_GENERADOR!E:E,"-",0) -> - | Q13: =IFERROR(P13*O13,0) -> 0 | R13: =+_xlfn.XLOOKUP(A13,PPTO_GENERADOR!$Q:$Q,PPTO_GENERADOR!A:A,"-",0) -> -
A14: AIS-113 | B14: EQ | D14: EQ-SOLD00 | E14: =IFERROR(VLOOKUP(D14,EQUIPOS!A:B,2,FALSE()),"?") -> Soldador Soplete A Gas Techista Membrana 10 Kg Boca 50mm | G14: 1 | H14: 0 | I14: =IFERROR(VLOOKUP(D14,EQUIPOS!A:F,6,FALSE()),0) -> 874.41131 | J14: =G14*I14 -> 874.41131 | K14: =A14&"|"&B14 -> AIS-113|EQ | L14: =COUNTIFS($K$2:K14,K14) -> 1 | M14: =K14&"|"&L14 -> AIS-113|EQ|1 | N14: =IFERROR(VLOOKUP(A14,PARTIDAS!A:F,6,FALSE()),0) -> 80 | O14: =+IF(C14="ALB",G14/N14,0) -> 0 | P14: =+_xlfn.XLOOKUP(A14,PPTO_GENERADOR!Q:Q,PPTO_GENERADOR!E:E,"-",0) -> - | Q14: =IFERROR(P14*O14,0) -> 0 | R14: =+_xlfn.XLOOKUP(A14,PPTO_GENERADOR!$Q:$Q,PPTO_GENERADOR!A:A,"-",0) -> -
A15: AIS-113 | B15: MO | C15: ALB | D15: MO-EAYUD | E15: =IFERROR(VLOOKUP(D15,MANO_DE_OBRA!A:B,2,FALSE()),"?") -> AYUDANTE | F15: j | G15: 1 | H15: 0 | I15: =IFERROR(VLOOKUP(D15,MANO_DE_OBRA!A:C,3,FALSE()),0) -> 67240.499 | J15: =G15*I15 -> 67240.499 | K15: =A15&"|"&B15 -> AIS-113|MO | L15: =COUNTIFS($K$2:K15,K15) -> 1 | M15: =K15&"|"&L15 -> AIS-113|MO|1 | N15: =IFERROR(VLOOKUP(A15,PARTIDAS!A:F,6,FALSE()),0) -> 80 | O15: =+IF(C15="ALB",G15/N15,0) -> 0.0125 | P15: =+_xlfn.XLOOKUP(A15,PPTO_GENERADOR!Q:Q,PPTO_GENERADOR!E:E,"-",0) -> - | Q15: =IFERROR(P15*O15,0) -> 0 | R15: =+_xlfn.XLOOKUP(A15,PPTO_GENERADOR!$Q:$Q,PPTO_GENERADOR!A:A,"-",0) -> -
A16: AIS-113 | B16: MO | C16: ALB | D16: MO-EESPE | E16: =IFERROR(VLOOKUP(D16,MANO_DE_OBRA!A:B,2,FALSE()),"?") -> ESPECIALIZADO | F16: j | G16: 1 | H16: 0 | I16: =IFERROR(VLOOKUP(D16,MANO_DE_OBRA!A:C,3,FALSE()),0) -> 94177.138 | J16: =G16*I16 -> 94177.138 | K16: =A16&"|"&B16 -> AIS-113|MO | L16: =COUNTIFS($K$2:K16,K16) -> 2 | M16: =K16&"|"&L16 -> AIS-113|MO|2 | N16: =IFERROR(VLOOKUP(A16,PARTIDAS!A:F,6,FALSE()),0) -> 80 | O16: =+IF(C16="ALB",G16/N16,0) -> 0.0125 | P16: =+_xlfn.XLOOKUP(A16,PPTO_GENERADOR!Q:Q,PPTO_GENERADOR!E:E,"-",0) -> - | Q16: =IFERROR(P16*O16,0) -> 0 | R16: =+_xlfn.XLOOKUP(A16,PPTO_GENERADOR!$Q:$Q,PPTO_GENERADOR!A:A,"-",0) -> -
A17: AIS-114 | B17: MAT | C17: OTR | D17: PIN-008 | E17: =IFERROR(VLOOKUP(D17,MATERIALES!A:B,2,FALSE()),"?") -> Pintura Asfaltica Asfasol x18ts | F17: =IFERROR(VLOOKUP(D17,MATERIALES!A:C,3,FALSE()),"?") -> 0 | G17: 0.015 | H17: 0.1 | I17: =IFERROR(VLOOKUP(D17,MATERIALES!A:D,4,FALSE()),0) -> 35525.95 | J17: =G17*I17*(1+H17) -> 586.17818 | K17: =A17&"|"&B17 -> AIS-114|MAT | L17: =COUNTIFS($K$2:K17,K17) -> 1 | M17: =K17&"|"&L17 -> AIS-114|MAT|1 | N17: =IFERROR(VLOOKUP(A17,PARTIDAS!A:F,6,FALSE()),0) -> 60 | O17: =+IF(C17="ALB",G17/N17,0) -> 0 | P17: =+_xlfn.XLOOKUP(A17,PPTO_GENERADOR!Q:Q,PPTO_GENERADOR!E:E,"-",0) -> - | Q17: =IFERROR(P17*O17,0) -> 0 | R17: =+_xlfn.XLOOKUP(A17,PPTO_GENERADOR!$Q:$Q,PPTO_GENERADOR!A:A,"-",0) -> -
A18: AIS-114 | B18: MAT | C18: OTR | D18: AIS-002 | E18: =IFERROR(VLOOKUP(D18,MATERIALES!A:B,2,FALSE()),"?") -> Membrana Geotextil Ormiflex 4mm - (35kg) x10m | F18: =IFERROR(VLOOKUP(D18,MATERIALES!A:C,3,FALSE()),"?") -> u | G18: 0.05 | H18: 0.1 | I18: =IFERROR(VLOOKUP(D18,MATERIALES!A:D,4,FALSE()),0) -> 57227.91 | J18: =G18*I18*(1+H18) -> 3147.5351 | K18: =A18&"|"&B18 -> AIS-114|MAT | L18: =COUNTIFS($K$2:K18,K18) -> 2 | M18: =K18&"|"&L18 -> AIS-114|MAT|2 | N18: =IFERROR(VLOOKUP(A18,PARTIDAS!A:F,6,FALSE()),0) -> 60 | O18: =+IF(C18="ALB",G18/N18,0) -> 0 | P18: =+_xlfn.XLOOKUP(A18,PPTO_GENERADOR!Q:Q,PPTO_GENERADOR!E:E,"-",0) -> - | Q18: =IFERROR(P18*O18,0) -> 0 | R18: =+_xlfn.XLOOKUP(A18,PPTO_GENERADOR!$Q:$Q,PPTO_GENERADOR!A:A,"-",0) -> -
A19: AIS-114 | B19: EQ | D19: EQ-SOLD00 | E19: =IFERROR(VLOOKUP(D19,EQUIPOS!A:B,2,FALSE()),"?") -> Soldador Soplete A Gas Techista Membrana 10 Kg Boca 50mm | G19: 1 | H19: 0 | I19: =IFERROR(VLOOKUP(D19,EQUIPOS!A:F,6,FALSE()),0) -> 874.41131 | J19: =G19*I19 -> 874.41131 | K19: =A19&"|"&B19 -> AIS-114|EQ | L19: =COUNTIFS($K$2:K19,K19) -> 1 | M19: =K19&"|"&L19 -> AIS-114|EQ|1 | N19: =IFERROR(VLOOKUP(A19,PARTIDAS!A:F,6,FALSE()),0) -> 60 | O19: =+IF(C19="ALB",G19/N19,0) -> 0 | P19: =+_xlfn.XLOOKUP(A19,PPTO_GENERADOR!Q:Q,PPTO_GENERADOR!E:E,"-",0) -> - | Q19: =IFERROR(P19*O19,0) -> 0 | R19: =+_xlfn.XLOOKUP(A19,PPTO_GENERADOR!$Q:$Q,PPTO_GENERADOR!A:A,"-",0) -> -
A20: AIS-114 | B20: MO | C20: ALB | D20: MO-EAYUD | E20: =IFERROR(VLOOKUP(D20,MANO_DE_OBRA!A:B,2,FALSE()),"?") -> AYUDANTE | F20: j | G20: 1 | H20: 0 | I20: =IFERROR(VLOOKUP(D20,MANO_DE_OBRA!A:C,3,FALSE()),0) -> 67240.499 | J20: =G20*I20 -> 67240.499 | K20: =A20&"|"&B20 -> AIS-114|MO | L20: =COUNTIFS($K$2:K20,K20) -> 1 | M20: =K20&"|"&L20 -> AIS-114|MO|1 | N20: =IFERROR(VLOOKUP(A20,PARTIDAS!A:F,6,FALSE()),0) -> 60 | O20: =+IF(C20="ALB",G20/N20,0) -> 0.016666667 | P20: =+_xlfn.XLOOKUP(A20,PPTO_GENERADOR!Q:Q,PPTO_GENERADOR!E:E,"-",0) -> - | Q20: =IFERROR(P20*O20,0) -> 0 | R20: =+_xlfn.XLOOKUP(A20,PPTO_GENERADOR!$Q:$Q,PPTO_GENERADOR!A:A,"-",0) -> -
A21: AIS-114 | B21: MO | C21: ALB | D21: MO-EESPE | E21: =IFERROR(VLOOKUP(D21,MANO_DE_OBRA!A:B,2,FALSE()),"?") -> ESPECIALIZADO | F21: j | G21: 1 | H21: 0 | I21: =IFERROR(VLOOKUP(D21,MANO_DE_OBRA!A:C,3,FALSE()),0) -> 94177.138 | J21: =G21*I21 -> 94177.138 | K21: =A21&"|"&B21 -> AIS-114|MO | L21: =COUNTIFS($K$2:K21,K21) -> 2 | M21: =K21&"|"&L21 -> AIS-114|MO|2 | N21: =IFERROR(VLOOKUP(A21,PARTIDAS!A:F,6,FALSE()),0) -> 60 | O21: =+IF(C21="ALB",G21/N21,0) -> 0.016666667 | P21: =+_xlfn.XLOOKUP(A21,PPTO_GENERADOR!Q:Q,PPTO_GENERADOR!E:E,"-",0) -> - | Q21: =IFERROR(P21*O21,0) -> 0 | R21: =+_xlfn.XLOOKUP(A21,PPTO_GENERADOR!$Q:$Q,PPTO_GENERADOR!A:A,"-",0) -> -
A22: REV-115 | B22: MAT | C22: OTR | D22: AGR-001 | E22: =IFERROR(VLOOKUP(D22,MATERIALES!A:B,2,FALSE()),"?") -> ARENA LAVADA | F22: =IFERROR(VLOOKUP(D22,MATERIALES!A:C,3,FALSE()),"?") -> 0 | G22: 0.02 | H22: 0.03 | I22: =IFERROR(VLOOKUP(D22,MATERIALES!A:D,4,FALSE()),0) -> 32620.38 | J22: =G22*I22*(1+H22) -> 671.97983 | K22: =A22&"|"&B22 -> REV-115|MAT | L22: =COUNTIFS($K$2:K22,K22) -> 1 | M22: =K22&"|"&L22 -> REV-115|MAT|1 | N22: =IFERROR(VLOOKUP(A22,PARTIDAS!A:F,6,FALSE()),0) -> 15 | O22: =+IF(C22="ALB",G22/N22,0) -> 0 | P22: =+_xlfn.XLOOKUP(A22,PPTO_GENERADOR!Q:Q,PPTO_GENERADOR!E:E,"-",0) -> - | Q22: =IFERROR(P22*O22,0) -> 0 | R22: =+_xlfn.XLOOKUP(A22,PPTO_GENERADOR!$Q:$Q,PPTO_GENERADOR!A:A,"-",0) -> -
A23: REV-115 | B23: MAT | C23: OTR | D23: AGR-005 | E23: =IFERROR(VLOOKUP(D23,MATERIALES!A:B,2,FALSE()),"?") -> Cal Comun x 25kg | F23: =IFERROR(VLOOKUP(D23,MATERIALES!A:C,3,FALSE()),"?") -> 0 | G23: 0.06 | H23: 0.05 | I23: =IFERROR(VLOOKUP(D23,MATERIALES!A:D,4,FALSE()),0) -> 3927.28 | J23: =G23*I23*(1+H23) -> 247.41864 | K23: =A23&"|"&B23 -> REV-115|MAT | L23: =COUNTIFS($K$2:K23,K23) -> 2 | M23: =K23&"|"&L23 -> REV-115|MAT|2 | N23: =IFERROR(VLOOKUP(A23,PARTIDAS!A:F,6,FALSE()),0) -> 15 | O23: =+IF(C23="ALB",G23/N23,0) -> 0 | P23: =+_xlfn.XLOOKUP(A23,PPTO_GENERADOR!Q:Q,PPTO_GENERADOR!E:E,"-",0) -> - | Q23: =IFERROR(P23*O23,0) -> 0 | R23: =+_xlfn.XLOOKUP(A23,PPTO_GENERADOR!$Q:$Q,PPTO_GENERADOR!A:A,"-",0) -> -
A24: REV-115 | B24: MAT | C24: OTR | D24: AGR-004 | E24: =IFERROR(VLOOKUP(D24,MATERIALES!A:B,2,FALSE()),"?") -> Cemento Portland x 50kg | F24: =IFERROR(VLOOKUP(D24,MATERIALES!A:C,3,FALSE()),"?") -> 0 | G24: 0.26 | H24: 0.03 | I24: =IFERROR(VLOOKUP(D24,MATERIALES!A:D,4,FALSE()),0) -> 7891.74 | J24: =G24*I24*(1+H24) -> 2113.408 | K24: =A24&"|"&B24 -> REV-115|MAT | L24: =COUNTIFS($K$2:K24,K24) -> 3 | M24: =K24&"|"&L24 -> REV-115|MAT|3 | N24: =IFERROR(VLOOKUP(A24,PARTIDAS!A:F,6,FALSE()),0) -> 15 | O24: =+IF(C24="ALB",G24/N24,0) -> 0 | P24: =+_xlfn.XLOOKUP(A24,PPTO_GENERADOR!Q:Q,PPTO_GENERADOR!E:E,"-",0) -> - | Q24: =IFERROR(P24*O24,0) -> 0 | R24: =+_xlfn.XLOOKUP(A24,PPTO_GENERADOR!$Q:$Q,PPTO_GENERADOR!A:A,"-",0) -> -
A25: REV-115 | B25: MO | C25: ALB | D25: MO-EESPE | E25: =IFERROR(VLOOKUP(D25,MANO_DE_OBRA!A:B,2,FALSE()),"?") -> ESPECIALIZADO | F25: j | G25: 1 | H25: 0 | I25: =IFERROR(VLOOKUP(D25,MANO_DE_OBRA!A:C,3,FALSE()),0) -> 94177.138 | J25: =G25*I25 -> 94177.138 | K25: =A25&"|"&B25 -> REV-115|MO | L25: =COUNTIFS($K$2:K25,K25) -> 1 | M25: =K25&"|"&L25 -> REV-115|MO|1 | N25: =IFERROR(VLOOKUP(A25,PARTIDAS!A:F,6,FALSE()),0) -> 15 | O25: =+IF(C25="ALB",G25/N25,0) -> 0.066666667 | P25: =+_xlfn.XLOOKUP(A25,PPTO_GENERADOR!Q:Q,PPTO_GENERADOR!E:E,"-",0) -> - | Q25: =IFERROR(P25*O25,0) -> 0 | R25: =+_xlfn.XLOOKUP(A25,PPTO_GENERADOR!$Q:$Q,PPTO_GENERADOR!A:A,"-",0) -> -
A26: REV-115 | B26: MO | C26: ALB | D26: MO-EAYUD | E26: =IFERROR(VLOOKUP(D26,MANO_DE_OBRA!A:B,2,FALSE()),"?") -> AYUDANTE | F26: j | G26: 1 | H26: 0 | I26: =IFERROR(VLOOKUP(D26,MANO_DE_OBRA!A:C,3,FALSE()),0) -> 67240.499 | J26: =G26*I26 -> 67240.499 | K26: =A26&"|"&B26 -> REV-115|MO | L26: =COUNTIFS($K$2:K26,K26) -> 2 | M26: =K26&"|"&L26 -> REV-115|MO|2 | N26: =IFERROR(VLOOKUP(A26,PARTIDAS!A:F,6,FALSE()),0) -> 15 | O26: =+IF(C26="ALB",G26/N26,0) -> 0.066666667 | P26: =+_xlfn.XLOOKUP(A26,PPTO_GENERADOR!Q:Q,PPTO_GENERADOR!E:E,"-",0) -> - | Q26: =IFERROR(P26*O26,0) -> 0 | R26: =+_xlfn.XLOOKUP(A26,PPTO_GENERADOR!$Q:$Q,PPTO_GENERADOR!A:A,"-",0) -> -
A27: REV-115 | B27: MO | C27: ALB | D27: MO-EMEDI | E27: =IFERROR(VLOOKUP(D27,MANO_DE_OBRA!A:B,2,FALSE()),"?") -> MEDIO OFICIAL | F27: j | G27: 0 | H27: 0 | I27: =IFERROR(VLOOKUP(D27,MANO_DE_OBRA!A:C,3,FALSE()),0) -> 72132.138 | J27: =G27*I27 -> 0 | K27: =A27&"|"&B27 -> REV-115|MO | L27: =COUNTIFS($K$2:K27,K27) -> 3 | M27: =K27&"|"&L27 -> REV-115|MO|3 | N27: =IFERROR(VLOOKUP(A27,PARTIDAS!A:F,6,FALSE()),0) -> 15 | O27: =+IF(C27="ALB",G27/N27,0) -> 0 | P27: =+_xlfn.XLOOKUP(A27,PPTO_GENERADOR!Q:Q,PPTO_GENERADOR!E:E,"-",0) -> - | Q27: =IFERROR(P27*O27,0) -> 0 | R27: =+_xlfn.XLOOKUP(A27,PPTO_GENERADOR!$Q:$Q,PPTO_GENERADOR!A:A,"-",0) -> -
A28: REV-116 | B28: MAT | C28: OTR | D28: DUR-007 | E28: =IFERROR(VLOOKUP(D28,MATERIALES!A:B,2,FALSE()),"?") -> Perfil Perimetral x 3.05 | F28: =IFERROR(VLOOKUP(D28,MATERIALES!A:C,3,FALSE()),"?") -> u | G28: 0.495 | H28: 0.1 | I28: =IFERROR(VLOOKUP(D28,MATERIALES!A:D,4,FALSE()),0) -> 3028.9421 | J28: =G28*I28*(1+H28) -> 1649.259 | K28: =A28&"|"&B28 -> REV-116|MAT | L28: =COUNTIFS($K$2:K28,K28) -> 1 | M28: =K28&"|"&L28 -> REV-116|MAT|1 | N28: =IFERROR(VLOOKUP(A28,PARTIDAS!A:F,6,FALSE()),0) -> 12 | O28: =+IF(C28="ALB",G28/N28,0) -> 0 | P28: =+_xlfn.XLOOKUP(A28,PPTO_GENERADOR!Q:Q,PPTO_GENERADOR!E:E,"-",0) -> - | Q28: =IFERROR(P28*O28,0) -> 0 | R28: =+_xlfn.XLOOKUP(A28,PPTO_GENERADOR!$Q:$Q,PPTO_GENERADOR!A:A,"-",0) -> -
A29: REV-116 | B29: MAT | C29: OTR | D29: OTR-015 | E29: =IFERROR(VLOOKUP(D29,MATERIALES!A:B,2,FALSE()),"?") -> Larguero x 3.66 | F29: =IFERROR(VLOOKUP(D29,MATERIALES!A:C,3,FALSE()),"?") -> u | G29: 0.45 | H29: 0.1 | I29: =IFERROR(VLOOKUP(D29,MATERIALES!A:D,4,FALSE()),0) -> 4774.9091 | J29: =G29*I29*(1+H29) -> 2363.58 | K29: =A29&"|"&B29 -> REV-116|MAT | L29: =COUNTIFS($K$2:K29,K29) -> 2 | M29: =K29&"|"&L29 -> REV-116|MAT|2 | N29: =IFERROR(VLOOKUP(A29,PARTIDAS!A:F,6,FALSE()),0) -> 12 | O29: =+IF(C29="ALB",G29/N29,0) -> 0 | P29: =+_xlfn.XLOOKUP(A29,PPTO_GENERADOR!Q:Q,PPTO_GENERADOR!E:E,"-",0) -> - | Q29: =IFERROR(P29*O29,0) -> 0 | R29: =+_xlfn.XLOOKUP(A29,PPTO_GENERADOR!$Q:$Q,PPTO_GENERADOR!A:A,"-",0) -> -
A30: REV-116 | B30: MAT | C30: OTR | D30: OTR-016 | E30: =IFERROR(VLOOKUP(D30,MATERIALES!A:B,2,FALSE()),"?") -> Travesaño x 1.22 | F30: =IFERROR(VLOOKUP(D30,MATERIALES!A:C,3,FALSE()),"?") -> u | G30: 2.62 | H30: 0.1 | I30: =IFERROR(VLOOKUP(D30,MATERIALES!A:D,4,FALSE()),0) -> 1547.438 | J30: =G30*I30*(1+H30) -> 4459.7164 | K30: =A30&"|"&B30 -> REV-116|MAT | L30: =COUNTIFS($K$2:K30,K30) -> 3 | M30: =K30&"|"&L30 -> REV-116|MAT|3 | N30: =IFERROR(VLOOKUP(A30,PARTIDAS!A:F,6,FALSE()),0) -> 12 | O30: =+IF(C30="ALB",G30/N30,0) -> 0 | P30: =+_xlfn.XLOOKUP(A30,PPTO_GENERADOR!Q:Q,PPTO_GENERADOR!E:E,"-",0) -> - | Q30: =IFERROR(P30*O30,0) -> 0 | R30: =+_xlfn.XLOOKUP(A30,PPTO_GENERADOR!$Q:$Q,PPTO_GENERADOR!A:A,"-",0) -> -
A31: REV-116 | B31: MAT | C31: OTR | D31: OTR-017 | E31: =IFERROR(VLOOKUP(D31,MATERIALES!A:B,2,FALSE()),"?") -> Travesaño x 0.60 | F31: =IFERROR(VLOOKUP(D31,MATERIALES!A:C,3,FALSE()),"?") -> u | G31: 0 | H31: 0.1 | I31: =IFERROR(VLOOKUP(D31,MATERIALES!A:D,4,FALSE()),0) -> 793.53719 | J31: =G31*I31*(1+H31) -> 0 | K31: =A31&"|"&B31 -> REV-116|MAT | L31: =COUNTIFS($K$2:K31,K31) -> 4 | M31: =K31&"|"&L31 -> REV-116|MAT|4 | N31: =IFERROR(VLOOKUP(A31,PARTIDAS!A:F,6,FALSE()),0) -> 12 | O31: =+IF(C31="ALB",G31/N31,0) -> 0 | P31: =+_xlfn.XLOOKUP(A31,PPTO_GENERADOR!Q:Q,PPTO_GENERADOR!E:E,"-",0) -> - | Q31: =IFERROR(P31*O31,0) -> 0 | R31: =+_xlfn.XLOOKUP(A31,PPTO_GENERADOR!$Q:$Q,PPTO_GENERADOR!A:A,"-",0) -> -
A32: REV-116 | B32: MAT | C32: OTR | D32: OTR-010 | E32: =IFERROR(VLOOKUP(D32,MATERIALES!A:B,2,FALSE()),"?") -> Fijacion completa del 8 | F32: =IFERROR(VLOOKUP(D32,MATERIALES!A:C,3,FALSE()),"?") -> u | G32: 6 | H32: 0.1 | I32: =IFERROR(VLOOKUP(D32,MATERIALES!A:D,4,FALSE()),0) -> 63.381983 | J32: =G32*I32*(1+H32) -> 418.32109 | K32: =A32&"|"&B32 -> REV-116|MAT | L32: =COUNTIFS($K$2:K32,K32) -> 5 | M32: =K32&"|"&L32 -> REV-116|MAT|5 | N32: =IFERROR(VLOOKUP(A32,PARTIDAS!A:F,6,FALSE()),0) -> 12 | O32: =+IF(C32="ALB",G32/N32,0) -> 0 | P32: =+_xlfn.XLOOKUP(A32,PPTO_GENERADOR!Q:Q,PPTO_GENERADOR!E:E,"-",0) -> - | Q32: =IFERROR(P32*O32,0) -> 0 | R32: =+_xlfn.XLOOKUP(A32,PPTO_GENERADOR!$Q:$Q,PPTO_GENERADOR!A:A,"-",0) -> -
A33: REV-116 | B33: MAT | C33: OTR | D33: ACE-014 | E33: =IFERROR(VLOOKUP(D33,MATERIALES!A:B,2,FALSE()),"?") -> Alambre galvanizado N°14 x kg | F33: =IFERROR(VLOOKUP(D33,MATERIALES!A:C,3,FALSE()),"?") -> kg | G33: 0.06 | H33: 0.1 | I33: =IFERROR(VLOOKUP(D33,MATERIALES!A:D,4,FALSE()),0) -> 2755.6116 | J33: =G33*I33*(1+H33) -> 181.87036 | K33: =A33&"|"&B33 -> REV-116|MAT | L33: =COUNTIFS($K$2:K33,K33) -> 6 | M33: =K33&"|"&L33 -> REV-116|MAT|6 | N33: =IFERROR(VLOOKUP(A33,PARTIDAS!A:F,6,FALSE()),0) -> 12 | O33: =+IF(C33="ALB",G33/N33,0) -> 0 | P33: =+_xlfn.XLOOKUP(A33,PPTO_GENERADOR!Q:Q,PPTO_GENERADOR!E:E,"-",0) -> - | Q33: =IFERROR(P33*O33,0) -> 0 | R33: =+_xlfn.XLOOKUP(A33,PPTO_GENERADOR!$Q:$Q,PPTO_GENERADOR!A:A,"-",0) -> -
A34: REV-116 | B34: MAT | C34: OTR | D34: OTR-019 | E34: =IFERROR(VLOOKUP(D34,MATERIALES!A:B,2,FALSE()),"?") -> Placa Decovinyl Liso 120x60 | F34: =IFERROR(VLOOKUP(D34,MATERIALES!A:C,3,FALSE()),"?") -> u | G34: 1.3889 | H34: 0.1 | I34: =IFERROR(VLOOKUP(D34,MATERIALES!A:D,4,FALSE()),0) -> 4751.7079 | J34: =G34*I34*(1+H34) -> 7259.6118 | K34: =A34&"|"&B34 -> REV-116|MAT | L34: =COUNTIFS($K$2:K34,K34) -> 7 | M34: =K34&"|"&L34 -> REV-116|MAT|7 | N34: =IFERROR(VLOOKUP(A34,PARTIDAS!A:F,6,FALSE()),0) -> 12 | O34: =+IF(C34="ALB",G34/N34,0) -> 0 | P34: =+_xlfn.XLOOKUP(A34,PPTO_GENERADOR!Q:Q,PPTO_GENERADOR!E:E,"-",0) -> - | Q34: =IFERROR(P34*O34,0) -> 0 | R34: =+_xlfn.XLOOKUP(A34,PPTO_GENERADOR!$Q:$Q,PPTO_GENERADOR!A:A,"-",0) -> -
A35: REV-116 | B35: EQ | D35: EQ-ESCALE | E35: =IFERROR(VLOOKUP(D35,EQUIPOS!A:B,2,FALSE()),"?") -> ESCALERA GLOSS ALUMINIO ARTICULADA 4 X 4 ESCALONES HASTA 150KG | G35: 1 | H35: 0 | I35: =IFERROR(VLOOKUP(D35,EQUIPOS!A:F,6,FALSE()),0) -> 152.38027 | J35: =G35*I35 -> 152.38027 | K35: =A35&"|"&B35 -> REV-116|EQ | L35: =COUNTIFS($K$2:K35,K35) -> 1 | M35: =K35&"|"&L35 -> REV-116|EQ|1 | N35: =IFERROR(VLOOKUP(A35,PARTIDAS!A:F,6,FALSE()),0) -> 12 | O35: =+IF(C35="ALB",G35/N35,0) -> 0 | P35: =+_xlfn.XLOOKUP(A35,PPTO_GENERADOR!Q:Q,PPTO_GENERADOR!E:E,"-",0) -> - | Q35: =IFERROR(P35*O35,0) -> 0 | R35: =+_xlfn.XLOOKUP(A35,PPTO_GENERADOR!$Q:$Q,PPTO_GENERADOR!A:A,"-",0) -> -
A36: REV-116 | B36: EQ | D36: EQ-PTO024 | E36: =IFERROR(VLOOKUP(D36,EQUIPOS!A:B,2,FALSE()),"?") -> EQUIPO DE CONSTRUCCION EN SECO | G36: 1 | H36: 0 | I36: =IFERROR(VLOOKUP(D36,EQUIPOS!A:F,6,FALSE()),0) -> 2570.7599 | J36: =G36*I36 -> 2570.7599 | K36: =A36&"|"&B36 -> REV-116|EQ | L36: =COUNTIFS($K$2:K36,K36) -> 2 | M36: =K36&"|"&L36 -> REV-116|EQ|2 | N36: =IFERROR(VLOOKUP(A36,PARTIDAS!A:F,6,FALSE()),0) -> 12 | O36: =+IF(C36="ALB",G36/N36,0) -> 0 | P36: =+_xlfn.XLOOKUP(A36,PPTO_GENERADOR!Q:Q,PPTO_GENERADOR!E:E,"-",0) -> - | Q36: =IFERROR(P36*O36,0) -> 0 | R36: =+_xlfn.XLOOKUP(A36,PPTO_GENERADOR!$Q:$Q,PPTO_GENERADOR!A:A,"-",0) -> -
A37: REV-116 | B37: MO | C37: ALB | D37: MO-EESPE | E37: =IFERROR(VLOOKUP(D37,MANO_DE_OBRA!A:B,2,FALSE()),"?") -> ESPECIALIZADO | F37: j | G37: 1 | H37: 0 | I37: =IFERROR(VLOOKUP(D37,MANO_DE_OBRA!A:C,3,FALSE()),0) -> 94177.138 | J37: =G37*I37 -> 94177.138 | K37: =A37&"|"&B37 -> REV-116|MO | L37: =COUNTIFS($K$2:K37,K37) -> 1 | M37: =K37&"|"&L37 -> REV-116|MO|1 | N37: =IFERROR(VLOOKUP(A37,PARTIDAS!A:F,6,FALSE()),0) -> 12 | O37: =+IF(C37="ALB",G37/N37,0) -> 0.083333333 | P37: =+_xlfn.XLOOKUP(A37,PPTO_GENERADOR!Q:Q,PPTO_GENERADOR!E:E,"-",0) -> - | Q37: =IFERROR(P37*O37,0) -> 0 | R37: =+_xlfn.XLOOKUP(A37,PPTO_GENERADOR!$Q:$Q,PPTO_GENERADOR!A:A,"-",0) -> -
A38: REV-116 | B38: MO | C38: ALB | D38: MO-EMEDI | E38: =IFERROR(VLOOKUP(D38,MANO_DE_OBRA!A:B,2,FALSE()),"?") -> MEDIO OFICIAL | F38: j | G38: 1 | H38: 0 | I38: =IFERROR(VLOOKUP(D38,MANO_DE_OBRA!A:C,3,FALSE()),0) -> 72132.138 | J38: =G38*I38 -> 72132.138 | K38: =A38&"|"&B38 -> REV-116|MO | L38: =COUNTIFS($K$2:K38,K38) -> 2 | M38: =K38&"|"&L38 -> REV-116|MO|2 | N38: =IFERROR(VLOOKUP(A38,PARTIDAS!A:F,6,FALSE()),0) -> 12 | O38: =+IF(C38="ALB",G38/N38,0) -> 0.083333333 | P38: =+_xlfn.XLOOKUP(A38,PPTO_GENERADOR!Q:Q,PPTO_GENERADOR!E:E,"-",0) -> - | Q38: =IFERROR(P38*O38,0) -> 0 | R38: =+_xlfn.XLOOKUP(A38,PPTO_GENERADOR!$Q:$Q,PPTO_GENERADOR!A:A,"-",0) -> -
A39: YES-117 | B39: MAT | C39: OTR | D39: OTR-014 | E39: =IFERROR(VLOOKUP(D39,MATERIALES!A:B,2,FALSE()),"?") -> Buña Z x 2.60m | F39: =IFERROR(VLOOKUP(D39,MATERIALES!A:C,3,FALSE()),"?") -> u | G39: 0.39 | H39: 0.1 | I39: =IFERROR(VLOOKUP(D39,MATERIALES!A:D,4,FALSE()),0) -> 2234.18 | J39: =G39*I39*(1+H39) -> 958.46322 | K39: =A39&"|"&B39 -> YES-117|MAT | L39: =COUNTIFS($K$2:K39,K39) -> 1 | M39: =K39&"|"&L39 -> YES-117|MAT|1 | N39: =IFERROR(VLOOKUP(A39,PARTIDAS!A:F,6,FALSE()),0) -> 15 | O39: =+IF(C39="ALB",G39/N39,0) -> 0 | P39: =+_xlfn.XLOOKUP(A39,PPTO_GENERADOR!Q:Q,PPTO_GENERADOR!E:E,"-",0) -> - | Q39: =IFERROR(P39*O39,0) -> 0 | R39: =+_xlfn.XLOOKUP(A39,PPTO_GENERADOR!$Q:$Q,PPTO_GENERADOR!A:A,"-",0) -> -
A40: YES-117 | B40: MAT | C40: OTR | D40: OTR-008 | E40: =IFERROR(VLOOKUP(D40,MATERIALES!A:B,2,FALSE()),"?") -> Tornillo T2 - Aguja | F40: =IFERROR(VLOOKUP(D40,MATERIALES!A:C,3,FALSE()),"?") -> u | G40: 3 | H40: 0.05 | I40: =IFERROR(VLOOKUP(D40,MATERIALES!A:D,4,FALSE()),0) -> 9.114692 | J40: =G40*I40*(1+H40) -> 28.71128 | K40: =A40&"|"&B40 -> YES-117|MAT | L40: =COUNTIFS($K$2:K40,K40) -> 2 | M40: =K40&"|"&L40 -> YES-117|MAT|2 | N40: =IFERROR(VLOOKUP(A40,PARTIDAS!A:F,6,FALSE()),0) -> 15 | O40: =+IF(C40="ALB",G40/N40,0) -> 0 | P40: =+_xlfn.XLOOKUP(A40,PPTO_GENERADOR!Q:Q,PPTO_GENERADOR!E:E,"-",0) -> - | Q40: =IFERROR(P40*O40,0) -> 0 | R40: =+_xlfn.XLOOKUP(A40,PPTO_GENERADOR!$Q:$Q,PPTO_GENERADOR!A:A,"-",0) -> -
A41: CER-060 | B41: EQ | D41: EQ-ESCALE | E41: =IFERROR(VLOOKUP(D41,EQUIPOS!A:B,2,FALSE()),"?") -> ESCALERA GLOSS ALUMINIO ARTICULADA 4 X 4 ESCALONES HASTA 150KG | G41: 1 | H41: 0 | I41: =IFERROR(VLOOKUP(D41,EQUIPOS!A:F,6,FALSE()),0) -> 152.38027 | J41: =G41*I41 -> 152.38027 | K41: =A41&"|"&B41 -> CER-060|EQ | L41: =COUNTIFS($K$2:K41,K41) -> 1 | M41: =K41&"|"&L41 -> CER-060|EQ|1 | N41: =IFERROR(VLOOKUP(A41,PARTIDAS!A:F,6,FALSE()),0) -> 9.5 | O41: =+IF(C41="ALB",G41/N41,0) -> 0 | P41: =+_xlfn.XLOOKUP(A41,PPTO_GENERADOR!Q:Q,PPTO_GENERADOR!E:E,"-",0) -> - | Q41: =IFERROR(P41*O41,0) -> 0 | R41: =+_xlfn.XLOOKUP(A41,PPTO_GENERADOR!$Q:$Q,PPTO_GENERADOR!A:A,"-",0) -> -
A42: CER-060 | B42: EQ | D42: EQ-PTO024 | E42: =IFERROR(VLOOKUP(D42,EQUIPOS!A:B,2,FALSE()),"?") -> EQUIPO DE CONSTRUCCION EN SECO | G42: 1 | H42: 0 | I42: =IFERROR(VLOOKUP(D42,EQUIPOS!A:F,6,FALSE()),0) -> 2570.7599 | J42: =G42*I42 -> 2570.7599 | K42: =A42&"|"&B42 -> CER-060|EQ | L42: =COUNTIFS($K$2:K42,K42) -> 2 | M42: =K42&"|"&L42 -> CER-060|EQ|2 | N42: =IFERROR(VLOOKUP(A42,PARTIDAS!A:F,6,FALSE()),0) -> 9.5 | O42: =+IF(C42="ALB",G42/N42,0) -> 0 | P42: =+_xlfn.XLOOKUP(A42,PPTO_GENERADOR!Q:Q,PPTO_GENERADOR!E:E,"-",0) -> - | Q42: =IFERROR(P42*O42,0) -> 0 | R42: =+_xlfn.XLOOKUP(A42,PPTO_GENERADOR!$Q:$Q,PPTO_GENERADOR!A:A,"-",0) -> -
A43: YES-117 | B43: MO | C43: ALB | D43: MO-EESPE | E43: =IFERROR(VLOOKUP(D43,MANO_DE_OBRA!A:B,2,FALSE()),"?") -> ESPECIALIZADO | F43: j | G43: 1 | H43: 0 | I43: =IFERROR(VLOOKUP(D43,MANO_DE_OBRA!A:C,3,FALSE()),0) -> 94177.138 | J43: =G43*I43 -> 94177.138 | K43: =A43&"|"&B43 -> YES-117|MO | L43: =COUNTIFS($K$2:K43,K43) -> 1 | M43: =K43&"|"&L43 -> YES-117|MO|1 | N43: =IFERROR(VLOOKUP(A43,PARTIDAS!A:F,6,FALSE()),0) -> 15 | O43: =+IF(C43="ALB",G43/N43,0) -> 0.066666667 | P43: =+_xlfn.XLOOKUP(A43,PPTO_GENERADOR!Q:Q,PPTO_GENERADOR!E:E,"-",0) -> - | Q43: =IFERROR(P43*O43,0) -> 0 | R43: =+_xlfn.XLOOKUP(A43,PPTO_GENERADOR!$Q:$Q,PPTO_GENERADOR!A:A,"-",0) -> -
A44: YES-118 | B44: MAT | C44: OTR | D44: MAT-CONS | E44: =IFERROR(VLOOKUP(D44,MATERIALES!A:B,2,FALSE()),"?") -> CONSUMIBLES (varios) | F44: =IFERROR(VLOOKUP(D44,MATERIALES!A:C,3,FALSE()),"?") -> gl | G44: 129.82087 | H44: 0 | I44: =IFERROR(VLOOKUP(D44,MATERIALES!A:D,4,FALSE()),0) -> 1 | J44: =G44*I44*(1+H44) -> 129.82087 | K44: =A44&"|"&B44 -> YES-118|MAT | L44: =COUNTIFS($K$2:K44,K44) -> 1 | M44: =K44&"|"&L44 -> YES-118|MAT|1 | N44: =IFERROR(VLOOKUP(A44,PARTIDAS!A:F,6,FALSE()),0) -> 11.5 | O44: =+IF(C44="ALB",G44/N44,0) -> 0 | P44: =+_xlfn.XLOOKUP(A44,PPTO_GENERADOR!Q:Q,PPTO_GENERADOR!E:E,"-",0) -> - | Q44: =IFERROR(P44*O44,0) -> 0 | R44: =+_xlfn.XLOOKUP(A44,PPTO_GENERADOR!$Q:$Q,PPTO_GENERADOR!A:A,"-",0) -> -
A45: YES-118 | B45: MAT | C45: OTR | D45: ACE-001 | E45: =IFERROR(VLOOKUP(D45,MATERIALES!A:B,2,FALSE()),"?") -> Barra de Acero Aleteado - 6mm x 12m | F45: =IFERROR(VLOOKUP(D45,MATERIALES!A:C,3,FALSE()),"?") -> 0 | G45: 0.17 | H45: 0.1 | I45: =IFERROR(VLOOKUP(D45,MATERIALES!A:D,4,FALSE()),0) -> 3620.13 | J45: =G45*I45*(1+H45) -> 676.96431 | K45: =A45&"|"&B45 -> YES-118|MAT | L45: =COUNTIFS($K$2:K45,K45) -> 2 | M45: =K45&"|"&L45 -> YES-118|MAT|2 | N45: =IFERROR(VLOOKUP(A45,PARTIDAS!A:F,6,FALSE()),0) -> 11.5 | O45: =+IF(C45="ALB",G45/N45,0) -> 0 | P45: =+_xlfn.XLOOKUP(A45,PPTO_GENERADOR!Q:Q,PPTO_GENERADOR!E:E,"-",0) -> - | Q45: =IFERROR(P45*O45,0) -> 0 | R45: =+_xlfn.XLOOKUP(A45,PPTO_GENERADOR!$Q:$Q,PPTO_GENERADOR!A:A,"-",0) -> -
A46: YES-118 | B46: MAT | C46: OTR | D46: AGR-001 | E46: =IFERROR(VLOOKUP(D46,MATERIALES!A:B,2,FALSE()),"?") -> ARENA LAVADA | F46: =IFERROR(VLOOKUP(D46,MATERIALES!A:C,3,FALSE()),"?") -> 0 | G46: 0.012 | H46: 0.1 | I46: =IFERROR(VLOOKUP(D46,MATERIALES!A:D,4,FALSE()),0) -> 32620.38 | J46: =G46*I46*(1+H46) -> 430.58902 | K46: =A46&"|"&B46 -> YES-118|MAT | L46: =COUNTIFS($K$2:K46,K46) -> 3 | M46: =K46&"|"&L46 -> YES-118|MAT|3 | N46: =IFERROR(VLOOKUP(A46,PARTIDAS!A:F,6,FALSE()),0) -> 11.5 | O46: =+IF(C46="ALB",G46/N46,0) -> 0 | P46: =+_xlfn.XLOOKUP(A46,PPTO_GENERADOR!Q:Q,PPTO_GENERADOR!E:E,"-",0) -> - | Q46: =IFERROR(P46*O46,0) -> 0 | R46: =+_xlfn.XLOOKUP(A46,PPTO_GENERADOR!$Q:$Q,PPTO_GENERADOR!A:A,"-",0) -> -
A47: YES-118 | B47: MAT | C47: OTR | D47: YES-BLOQUE10 | E47: =IFERROR(VLOOKUP(D47,MATERIALES!A:B,2,FALSE()),"?") -> Bloque hormigón 10×19×39 | F47: =IFERROR(VLOOKUP(D47,MATERIALES!A:C,3,FALSE()),"?") -> u | G47: 12.5 | H47: 0.05 | I47: =IFERROR(VLOOKUP(D47,MATERIALES!A:D,4,FALSE()),0) -> 808.61 | J47: =G47*I47*(1+H47) -> 10613.006 | K47: =A47&"|"&B47 -> YES-118|MAT | L47: =COUNTIFS($K$2:K47,K47) -> 4 | M47: =K47&"|"&L47 -> YES-118|MAT|4 | N47: =IFERROR(VLOOKUP(A47,PARTIDAS!A:F,6,FALSE()),0) -> 11.5 | O47: =+IF(C47="ALB",G47/N47,0) -> 0 | P47: =+_xlfn.XLOOKUP(A47,PPTO_GENERADOR!Q:Q,PPTO_GENERADOR!E:E,"-",0) -> - | Q47: =IFERROR(P47*O47,0) -> 0 | R47: =+_xlfn.XLOOKUP(A47,PPTO_GENERADOR!$Q:$Q,PPTO_GENERADOR!A:A,"-",0) -> -
A48: YES-118 | B48: MAT | C48: OTR | D48: AGR-004 | E48: =IFERROR(VLOOKUP(D48,MATERIALES!A:B,2,FALSE()),"?") -> Cemento Portland x 50kg | F48: =IFERROR(VLOOKUP(D48,MATERIALES!A:C,3,FALSE()),"?") -> 0 | G48: 0.052 | H48: 0.1 | I48: =IFERROR(VLOOKUP(D48,MATERIALES!A:D,4,FALSE()),0) -> 7891.74 | J48: =G48*I48*(1+H48) -> 451.40753 | K48: =A48&"|"&B48 -> YES-118|MAT | L48: =COUNTIFS($K$2:K48,K48) -> 5 | M48: =K48&"|"&L48 -> YES-118|MAT|5 | N48: =IFERROR(VLOOKUP(A48,PARTIDAS!A:F,6,FALSE()),0) -> 11.5 | O48: =+IF(C48="ALB",G48/N48,0) -> 0 | P48: =+_xlfn.XLOOKUP(A48,PPTO_GENERADOR!Q:Q,PPTO_GENERADOR!E:E,"-",0) -> - | Q48: =IFERROR(P48*O48,0) -> 0 | R48: =+_xlfn.XLOOKUP(A48,PPTO_GENERADOR!$Q:$Q,PPTO_GENERADOR!A:A,"-",0) -> -
A49: YES-118 | B49: EQ | D49: EQ-EQALBA | E49: =IFERROR(VLOOKUP(D49,EQUIPOS!A:B,2,FALSE()),"?") -> EQUIPO DE ALBAÑILERIA, carpetas, ladrillo | G49: 1 | H49: 0 | I49: =IFERROR(VLOOKUP(D49,EQUIPOS!A:F,6,FALSE()),0) -> 2485.871 | J49: =G49*I49 -> 2485.871 | K49: =A49&"|"&B49 -> YES-118|EQ | L49: =COUNTIFS($K$2:K49,K49) -> 1 | M49: =K49&"|"&L49 -> YES-118|EQ|1 | N49: =IFERROR(VLOOKUP(A49,PARTIDAS!A:F,6,FALSE()),0) -> 11.5 | O49: =+IF(C49="ALB",G49/N49,0) -> 0 | P49: =+_xlfn.XLOOKUP(A49,PPTO_GENERADOR!Q:Q,PPTO_GENERADOR!E:E,"-",0) -> - | Q49: =IFERROR(P49*O49,0) -> 0 | R49: =+_xlfn.XLOOKUP(A49,PPTO_GENERADOR!$Q:$Q,PPTO_GENERADOR!A:A,"-",0) -> -
A50: YES-118 | B50: EQ | D50: EQ-ANDAM0 | E50: =IFERROR(VLOOKUP(D50,EQUIPOS!A:B,2,FALSE()),"?") -> ANDAMIO TUBULAR DE UNO A TRES CUERPOS | G50: 0.5 | H50: 0 | I50: =IFERROR(VLOOKUP(D50,EQUIPOS!A:F,6,FALSE()),0) -> 620.81078 | J50: =G50*I50 -> 310.40539 | K50: =A50&"|"&B50 -> YES-118|EQ | L50: =COUNTIFS($K$2:K50,K50) -> 2 | M50: =K50&"|"&L50 -> YES-118|EQ|2 | N50: =IFERROR(VLOOKUP(A50,PARTIDAS!A:F,6,FALSE()),0) -> 11.5 | O50: =+IF(C50="ALB",G50/N50,0) -> 0 | P50: =+_xlfn.XLOOKUP(A50,PPTO_GENERADOR!Q:Q,PPTO_GENERADOR!E:E,"-",0) -> - | Q50: =IFERROR(P50*O50,0) -> 0 | R50: =+_xlfn.XLOOKUP(A50,PPTO_GENERADOR!$Q:$Q,PPTO_GENERADOR!A:A,"-",0) -> -
A51: YES-118 | B51: EQ | D51: EQ-TROMPO | E51: =IFERROR(VLOOKUP(D51,EQUIPOS!A:B,2,FALSE()),"?") -> Hormigonera De 150 Litros 1hp Con Rueda Maciza | G51: 1 | H51: 0 | I51: =IFERROR(VLOOKUP(D51,EQUIPOS!A:F,6,FALSE()),0) -> 1040.4314 | J51: =G51*I51 -> 1040.4314 | K51: =A51&"|"&B51 -> YES-118|EQ | L51: =COUNTIFS($K$2:K51,K51) -> 3 | M51: =K51&"|"&L51 -> YES-118|EQ|3 | N51: =IFERROR(VLOOKUP(A51,PARTIDAS!A:F,6,FALSE()),0) -> 11.5 | O51: =+IF(C51="ALB",G51/N51,0) -> 0 | P51: =+_xlfn.XLOOKUP(A51,PPTO_GENERADOR!Q:Q,PPTO_GENERADOR!E:E,"-",0) -> - | Q51: =IFERROR(P51*O51,0) -> 0 | R51: =+_xlfn.XLOOKUP(A51,PPTO_GENERADOR!$Q:$Q,PPTO_GENERADOR!A:A,"-",0) -> -
A52: YES-118 | B52: MO | C52: ALB | D52: MO-EESPE | E52: =IFERROR(VLOOKUP(D52,MANO_DE_OBRA!A:B,2,FALSE()),"?") -> ESPECIALIZADO | F52: j | G52: 1 | H52: 0 | I52: =IFERROR(VLOOKUP(D52,MANO_DE_OBRA!A:C,3,FALSE()),0) -> 94177.138 | J52: =G52*I52 -> 94177.138 | K52: =A52&"|"&B52 -> YES-118|MO | L52: =COUNTIFS($K$2:K52,K52) -> 1 | M52: =K52&"|"&L52 -> YES-118|MO|1 | N52: =IFERROR(VLOOKUP(A52,PARTIDAS!A:F,6,FALSE()),0) -> 11.5 | O52: =+IF(C52="ALB",G52/N52,0) -> 0.086956522 | P52: =+_xlfn.XLOOKUP(A52,PPTO_GENERADOR!Q:Q,PPTO_GENERADOR!E:E,"-",0) -> - | Q52: =IFERROR(P52*O52,0) -> 0 | R52: =+_xlfn.XLOOKUP(A52,PPTO_GENERADOR!$Q:$Q,PPTO_GENERADOR!A:A,"-",0) -> -
A53: YES-118 | B53: MO | C53: ALB | D53: MO-EMEDI | E53: =IFERROR(VLOOKUP(D53,MANO_DE_OBRA!A:B,2,FALSE()),"?") -> MEDIO OFICIAL | F53: j | G53: 0.75 | H53: 0 | I53: =IFERROR(VLOOKUP(D53,MANO_DE_OBRA!A:C,3,FALSE()),0) -> 72132.138 | J53: =G53*I53 -> 54099.104 | K53: =A53&"|"&B53 -> YES-118|MO | L53: =COUNTIFS($K$2:K53,K53) -> 2 | M53: =K53&"|"&L53 -> YES-118|MO|2 | N53: =IFERROR(VLOOKUP(A53,PARTIDAS!A:F,6,FALSE()),0) -> 11.5 | O53: =+IF(C53="ALB",G53/N53,0) -> 0.065217391 | P53: =+_xlfn.XLOOKUP(A53,PPTO_GENERADOR!Q:Q,PPTO_GENERADOR!E:E,"-",0) -> - | Q53: =IFERROR(P53*O53,0) -> 0 | R53: =+_xlfn.XLOOKUP(A53,PPTO_GENERADOR!$Q:$Q,PPTO_GENERADOR!A:A,"-",0) -> -
A54: PIN-119 | B54: MAT | C54: OTR | D54: MAT-CONS | E54: =IFERROR(VLOOKUP(D54,MATERIALES!A:B,2,FALSE()),"?") -> CONSUMIBLES (varios) | F54: =IFERROR(VLOOKUP(D54,MATERIALES!A:C,3,FALSE()),"?") -> gl | G54: 186.03762 | H54: 0 | I54: =IFERROR(VLOOKUP(D54,MATERIALES!A:D,4,FALSE()),0) -> 1 | J54: =G54*I54*(1+H54) -> 186.03762 | K54: =A54&"|"&B54 -> PIN-119|MAT | L54: =COUNTIFS($K$2:K54,K54) -> 1 | M54: =K54&"|"&L54 -> PIN-119|MAT|1 | N54: =IFERROR(VLOOKUP(A54,PARTIDAS!A:F,6,FALSE()),0) -> 11.5 | O54: =+IF(C54="ALB",G54/N54,0) -> 0 | P54: =+_xlfn.XLOOKUP(A54,PPTO_GENERADOR!Q:Q,PPTO_GENERADOR!E:E,"-",0) -> - | Q54: =IFERROR(P54*O54,0) -> 0 | R54: =+_xlfn.XLOOKUP(A54,PPTO_GENERADOR!$Q:$Q,PPTO_GENERADOR!A:A,"-",0) -> -
A55: PIN-119 | B55: MAT | C55: OTR | D55: ACE-001 | E55: =IFERROR(VLOOKUP(D55,MATERIALES!A:B,2,FALSE()),"?") -> Barra de Acero Aleteado - 6mm x 12m | F55: =IFERROR(VLOOKUP(D55,MATERIALES!A:C,3,FALSE()),"?") -> 0 | G55: 0.17 | H55: 0.1 | I55: =IFERROR(VLOOKUP(D55,MATERIALES!A:D,4,FALSE()),0) -> 3620.13 | J55: =G55*I55*(1+H55) -> 676.96431 | K55: =A55&"|"&B55 -> PIN-119|MAT | L55: =COUNTIFS($K$2:K55,K55) -> 2 | M55: =K55&"|"&L55 -> PIN-119|MAT|2 | N55: =IFERROR(VLOOKUP(A55,PARTIDAS!A:F,6,FALSE()),0) -> 11.5 | O55: =+IF(C55="ALB",G55/N55,0) -> 0 | P55: =+_xlfn.XLOOKUP(A55,PPTO_GENERADOR!Q:Q,PPTO_GENERADOR!E:E,"-",0) -> - | Q55: =IFERROR(P55*O55,0) -> 0 | R55: =+_xlfn.XLOOKUP(A55,PPTO_GENERADOR!$Q:$Q,PPTO_GENERADOR!A:A,"-",0) -> -
A56: PIN-119 | B56: MAT | C56: OTR | D56: AGR-001 | E56: =IFERROR(VLOOKUP(D56,MATERIALES!A:B,2,FALSE()),"?") -> ARENA LAVADA | F56: =IFERROR(VLOOKUP(D56,MATERIALES!A:C,3,FALSE()),"?") -> 0 | G56: 0.0144 | H56: 0.1 | I56: =IFERROR(VLOOKUP(D56,MATERIALES!A:D,4,FALSE()),0) -> 32620.38 | J56: =G56*I56*(1+H56) -> 516.70682 | K56: =A56&"|"&B56 -> PIN-119|MAT | L56: =COUNTIFS($K$2:K56,K56) -> 3 | M56: =K56&"|"&L56 -> PIN-119|MAT|3 | N56: =IFERROR(VLOOKUP(A56,PARTIDAS!A:F,6,FALSE()),0) -> 11.5 | O56: =+IF(C56="ALB",G56/N56,0) -> 0 | P56: =+_xlfn.XLOOKUP(A56,PPTO_GENERADOR!Q:Q,PPTO_GENERADOR!E:E,"-",0) -> - | Q56: =IFERROR(P56*O56,0) -> 0 | R56: =+_xlfn.XLOOKUP(A56,PPTO_GENERADOR!$Q:$Q,PPTO_GENERADOR!A:A,"-",0) -> -
A57: PIN-119 | B57: MAT | C57: OTR | D57: YES-BLOQUE19 | E57: =IFERROR(VLOOKUP(D57,MATERIALES!A:B,2,FALSE()),"?") -> Bloque hormigón 19×19×39 | F57: =IFERROR(VLOOKUP(D57,MATERIALES!A:C,3,FALSE()),"?") -> u | G57: 12.5 | H57: 0.05 | I57: =IFERROR(VLOOKUP(D57,MATERIALES!A:D,4,FALSE()),0) -> 1204.43 | J57: =G57*I57*(1+H57) -> 15808.144 | K57: =A57&"|"&B57 -> PIN-119|MAT | L57: =COUNTIFS($K$2:K57,K57) -> 4 | M57: =K57&"|"&L57 -> PIN-119|MAT|4 | N57: =IFERROR(VLOOKUP(A57,PARTIDAS!A:F,6,FALSE()),0) -> 11.5 | O57: =+IF(C57="ALB",G57/N57,0) -> 0 | P57: =+_xlfn.XLOOKUP(A57,PPTO_GENERADOR!Q:Q,PPTO_GENERADOR!E:E,"-",0) -> - | Q57: =IFERROR(P57*O57,0) -> 0 | R57: =+_xlfn.XLOOKUP(A57,PPTO_GENERADOR!$Q:$Q,PPTO_GENERADOR!A:A,"-",0) -> -
A58: PIN-119 | B58: MAT | C58: OTR | D58: AGR-004 | E58: =IFERROR(VLOOKUP(D58,MATERIALES!A:B,2,FALSE()),"?") -> Cemento Portland x 50kg | F58: =IFERROR(VLOOKUP(D58,MATERIALES!A:C,3,FALSE()),"?") -> 0 | G58: 0.0624 | H58: 0.1 | I58: =IFERROR(VLOOKUP(D58,MATERIALES!A:D,4,FALSE()),0) -> 7891.74 | J58: =G58*I58*(1+H58) -> 541.68903 | K58: =A58&"|"&B58 -> PIN-119|MAT | L58: =COUNTIFS($K$2:K58,K58) -> 5 | M58: =K58&"|"&L58 -> PIN-119|MAT|5 | N58: =IFERROR(VLOOKUP(A58,PARTIDAS!A:F,6,FALSE()),0) -> 11.5 | O58: =+IF(C58="ALB",G58/N58,0) -> 0 | P58: =+_xlfn.XLOOKUP(A58,PPTO_GENERADOR!Q:Q,PPTO_GENERADOR!E:E,"-",0) -> - | Q58: =IFERROR(P58*O58,0) -> 0 | R58: =+_xlfn.XLOOKUP(A58,PPTO_GENERADOR!$Q:$Q,PPTO_GENERADOR!A:A,"-",0) -> -
A59: PIN-119 | B59: EQ | D59: EQ-EQALBA | E59: =IFERROR(VLOOKUP(D59,EQUIPOS!A:B,2,FALSE()),"?") -> EQUIPO DE ALBAÑILERIA, carpetas, ladrillo | G59: 1 | H59: 0 | I59: =IFERROR(VLOOKUP(D59,EQUIPOS!A:F,6,FALSE()),0) -> 2485.871 | J59: =G59*I59 -> 2485.871 | K59: =A59&"|"&B59 -> PIN-119|EQ | L59: =COUNTIFS($K$2:K59,K59) -> 1 | M59: =K59&"|"&L59 -> PIN-119|EQ|1 | N59: =IFERROR(VLOOKUP(A59,PARTIDAS!A:F,6,FALSE()),0) -> 11.5 | O59: =+IF(C59="ALB",G59/N59,0) -> 0 | P59: =+_xlfn.XLOOKUP(A59,PPTO_GENERADOR!Q:Q,PPTO_GENERADOR!E:E,"-",0) -> - | Q59: =IFERROR(P59*O59,0) -> 0 | R59: =+_xlfn.XLOOKUP(A59,PPTO_GENERADOR!$Q:$Q,PPTO_GENERADOR!A:A,"-",0) -> -
A60: PIN-119 | B60: EQ | D60: EQ-ANDAM0 | E60: =IFERROR(VLOOKUP(D60,EQUIPOS!A:B,2,FALSE()),"?") -> ANDAMIO TUBULAR DE UNO A TRES CUERPOS | G60: 0.5 | H60: 0 | I60: =IFERROR(VLOOKUP(D60,EQUIPOS!A:F,6,FALSE()),0) -> 620.81078 | J60: =G60*I60 -> 310.40539 | K60: =A60&"|"&B60 -> PIN-119|EQ | L60: =COUNTIFS($K$2:K60,K60) -> 2 | M60: =K60&"|"&L60 -> PIN-119|EQ|2 | N60: =IFERROR(VLOOKUP(A60,PARTIDAS!A:F,6,FALSE()),0) -> 11.5 | O60: =+IF(C60="ALB",G60/N60,0) -> 0 | P60: =+_xlfn.XLOOKUP(A60,PPTO_GENERADOR!Q:Q,PPTO_GENERADOR!E:E,"-",0) -> - | Q60: =IFERROR(P60*O60,0) -> 0 | R60: =+_xlfn.XLOOKUP(A60,PPTO_GENERADOR!$Q:$Q,PPTO_GENERADOR!A:A,"-",0) -> -
A61: PIN-119 | B61: EQ | D61: EQ-TROMPO | E61: =IFERROR(VLOOKUP(D61,EQUIPOS!A:B,2,FALSE()),"?") -> Hormigonera De 150 Litros 1hp Con Rueda Maciza | G61: 1 | H61: 0 | I61: =IFERROR(VLOOKUP(D61,EQUIPOS!A:F,6,FALSE()),0) -> 1040.4314 | J61: =G61*I61 -> 1040.4314 | K61: =A61&"|"&B61 -> PIN-119|EQ | L61: =COUNTIFS($K$2:K61,K61) -> 3 | M61: =K61&"|"&L61 -> PIN-119|EQ|3 | N61: =IFERROR(VLOOKUP(A61,PARTIDAS!A:F,6,FALSE()),0) -> 11.5 | O61: =+IF(C61="ALB",G61/N61,0) -> 0 | P61: =+_xlfn.XLOOKUP(A61,PPTO_GENERADOR!Q:Q,PPTO_GENERADOR!E:E,"-",0) -> - | Q61: =IFERROR(P61*O61,0) -> 0 | R61: =+_xlfn.XLOOKUP(A61,PPTO_GENERADOR!$Q:$Q,PPTO_GENERADOR!A:A,"-",0) -> -
A62: PIN-119 | B62: MO | C62: ALB | D62: MO-EESPE | E62: =IFERROR(VLOOKUP(D62,MANO_DE_OBRA!A:B,2,FALSE()),"?") -> ESPECIALIZADO | F62: j | G62: 1 | H62: 0 | I62: =IFERROR(VLOOKUP(D62,MANO_DE_OBRA!A:C,3,FALSE()),0) -> 94177.138 | J62: =G62*I62 -> 94177.138 | K62: =A62&"|"&B62 -> PIN-119|MO | L62: =COUNTIFS($K$2:K62,K62) -> 1 | M62: =K62&"|"&L62 -> PIN-119|MO|1 | N62: =IFERROR(VLOOKUP(A62,PARTIDAS!A:F,6,FALSE()),0) -> 11.5 | O62: =+IF(C62="ALB",G62/N62,0) -> 0.086956522 | P62: =+_xlfn.XLOOKUP(A62,PPTO_GENERADOR!Q:Q,PPTO_GENERADOR!E:E,"-",0) -> - | Q62: =IFERROR(P62*O62,0) -> 0 | R62: =+_xlfn.XLOOKUP(A62,PPTO_GENERADOR!$Q:$Q,PPTO_GENERADOR!A:A,"-",0) -> -
A63: PIN-119 | B63: MO | C63: ALB | D63: MO-EMEDI | E63: =IFERROR(VLOOKUP(D63,MANO_DE_OBRA!A:B,2,FALSE()),"?") -> MEDIO OFICIAL | F63: j | G63: 0.75 | H63: 0 | I63: =IFERROR(VLOOKUP(D63,MANO_DE_OBRA!A:C,3,FALSE()),0) -> 72132.138 | J63: =G63*I63 -> 54099.104 | K63: =A63&"|"&B63 -> PIN-119|MO | L63: =COUNTIFS($K$2:K63,K63) -> 2 | M63: =K63&"|"&L63 -> PIN-119|MO|2 | N63: =IFERROR(VLOOKUP(A63,PARTIDAS!A:F,6,FALSE()),0) -> 11.5 | O63: =+IF(C63="ALB",G63/N63,0) -> 0.065217391 | P63: =+_xlfn.XLOOKUP(A63,PPTO_GENERADOR!Q:Q,PPTO_GENERADOR!E:E,"-",0) -> - | Q63: =IFERROR(P63*O63,0) -> 0 | R63: =+_xlfn.XLOOKUP(A63,PPTO_GENERADOR!$Q:$Q,PPTO_GENERADOR!A:A,"-",0) -> -
A64: ELE-120 | B64: MAT | C64: OTR | D64: MAT-CONS | E64: =IFERROR(VLOOKUP(D64,MATERIALES!A:B,2,FALSE()),"?") -> CONSUMIBLES (varios) | F64: =IFERROR(VLOOKUP(D64,MATERIALES!A:C,3,FALSE()),"?") -> gl | G64: 3056.3166 | H64: 0 | I64: =IFERROR(VLOOKUP(D64,MATERIALES!A:D,4,FALSE()),0) -> 1 | J64: =G64*I64*(1+H64) -> 3056.3166 | K64: =A64&"|"&B64 -> ELE-120|MAT | L64: =COUNTIFS($K$2:K64,K64) -> 1 | M64: =K64&"|"&L64 -> ELE-120|MAT|1 | N64: =IFERROR(VLOOKUP(A64,PARTIDAS!A:F,6,FALSE()),0) -> 3.25 | O64: =+IF(C64="ALB",G64/N64,0) -> 0 | P64: =+_xlfn.XLOOKUP(A64,PPTO_GENERADOR!Q:Q,PPTO_GENERADOR!E:E,"-",0) -> - | Q64: =IFERROR(P64*O64,0) -> 0 | R64: =+_xlfn.XLOOKUP(A64,PPTO_GENERADOR!$Q:$Q,PPTO_GENERADOR!A:A,"-",0) -> -
A65: ELE-120 | B65: EQ | D65: EQ-EQUIP0 | E65: =IFERROR(VLOOKUP(D65,EQUIPOS!A:B,2,FALSE()),"?") -> EQUIPO PARA INSTALACION ELECTRICA | G65: 1 | H65: 0 | I65: =IFERROR(VLOOKUP(D65,EQUIPOS!A:F,6,FALSE()),0) -> 5503.0404 | J65: =G65*I65 -> 5503.0404 | K65: =A65&"|"&B65 -> ELE-120|EQ | L65: =COUNTIFS($K$2:K65,K65) -> 1 | M65: =K65&"|"&L65 -> ELE-120|EQ|1 | N65: =IFERROR(VLOOKUP(A65,PARTIDAS!A:F,6,FALSE()),0) -> 3.25 | O65: =+IF(C65="ALB",G65/N65,0) -> 0 | P65: =+_xlfn.XLOOKUP(A65,PPTO_GENERADOR!Q:Q,PPTO_GENERADOR!E:E,"-",0) -> - | Q65: =IFERROR(P65*O65,0) -> 0 | R65: =+_xlfn.XLOOKUP(A65,PPTO_GENERADOR!$Q:$Q,PPTO_GENERADOR!A:A,"-",0) -> -
A66: ELE-120 | B66: EQ | D66: EQ-ANDAM0 | E66: =IFERROR(VLOOKUP(D66,EQUIPOS!A:B,2,FALSE()),"?") -> ANDAMIO TUBULAR DE UNO A TRES CUERPOS | G66: 0.5 | H66: 0 | I66: =IFERROR(VLOOKUP(D66,EQUIPOS!A:F,6,FALSE()),0) -> 620.81078 | J66: =G66*I66 -> 310.40539 | K66: =A66&"|"&B66 -> ELE-120|EQ | L66: =COUNTIFS($K$2:K66,K66) -> 2 | M66: =K66&"|"&L66 -> ELE-120|EQ|2 | N66: =IFERROR(VLOOKUP(A66,PARTIDAS!A:F,6,FALSE()),0) -> 3.25 | O66: =+IF(C66="ALB",G66/N66,0) -> 0 | P66: =+_xlfn.XLOOKUP(A66,PPTO_GENERADOR!Q:Q,PPTO_GENERADOR!E:E,"-",0) -> - | Q66: =IFERROR(P66*O66,0) -> 0 | R66: =+_xlfn.XLOOKUP(A66,PPTO_GENERADOR!$Q:$Q,PPTO_GENERADOR!A:A,"-",0) -> -
A67: ELE-120 | B67: EQ | D67: EQ-ESCALE | E67: =IFERROR(VLOOKUP(D67,EQUIPOS!A:B,2,FALSE()),"?") -> ESCALERA GLOSS ALUMINIO ARTICULADA 4 X 4 ESCALONES HASTA 150KG | G67: 0.5 | H67: 0 | I67: =IFERROR(VLOOKUP(D67,EQUIPOS!A:F,6,FALSE()),0) -> 152.38027 | J67: =G67*I67 -> 76.190137 | K67: =A67&"|"&B67 -> ELE-120|EQ | L67: =COUNTIFS($K$2:K67,K67) -> 3 | M67: =K67&"|"&L67 -> ELE-120|EQ|3 | N67: =IFERROR(VLOOKUP(A67,PARTIDAS!A:F,6,FALSE()),0) -> 3.25 | O67: =+IF(C67="ALB",G67/N67,0) -> 0 | P67: =+_xlfn.XLOOKUP(A67,PPTO_GENERADOR!Q:Q,PPTO_GENERADOR!E:E,"-",0) -> - | Q67: =IFERROR(P67*O67,0) -> 0 | R67: =+_xlfn.XLOOKUP(A67,PPTO_GENERADOR!$Q:$Q,PPTO_GENERADOR!A:A,"-",0) -> -
A68: ELE-120 | B68: MO | C68: ALB | D68: MO-EESPE | E68: =IFERROR(VLOOKUP(D68,MANO_DE_OBRA!A:B,2,FALSE()),"?") -> ESPECIALIZADO | F68: j | G68: 1 | H68: 0 | I68: =IFERROR(VLOOKUP(D68,MANO_DE_OBRA!A:C,3,FALSE()),0) -> 94177.138 | J68: =G68*I68 -> 94177.138 | K68: =A68&"|"&B68 -> ELE-120|MO | L68: =COUNTIFS($K$2:K68,K68) -> 1 | M68: =K68&"|"&L68 -> ELE-120|MO|1 | N68: =IFERROR(VLOOKUP(A68,PARTIDAS!A:F,6,FALSE()),0) -> 3.25 | O68: =+IF(C68="ALB",G68/N68,0) -> 0.30769231 | P68: =+_xlfn.XLOOKUP(A68,PPTO_GENERADOR!Q:Q,PPTO_GENERADOR!E:E,"-",0) -> - | Q68: =IFERROR(P68*O68,0) -> 0 | R68: =+_xlfn.XLOOKUP(A68,PPTO_GENERADOR!$Q:$Q,PPTO_GENERADOR!A:A,"-",0) -> -
A69: ELE-120 | B69: MO | C69: ALB | D69: MO-EAYUD | E69: =IFERROR(VLOOKUP(D69,MANO_DE_OBRA!A:B,2,FALSE()),"?") -> AYUDANTE | F69: j | G69: 1 | H69: 0 | I69: =IFERROR(VLOOKUP(D69,MANO_DE_OBRA!A:C,3,FALSE()),0) -> 67240.499 | J69: =G69*I69 -> 67240.499 | K69: =A69&"|"&B69 -> ELE-120|MO | L69: =COUNTIFS($K$2:K69,K69) -> 2 | M69: =K69&"|"&L69 -> ELE-120|MO|2 | N69: =IFERROR(VLOOKUP(A69,PARTIDAS!A:F,6,FALSE()),0) -> 3.25 | O69: =+IF(C69="ALB",G69/N69,0) -> 0.30769231 | P69: =+_xlfn.XLOOKUP(A69,PPTO_GENERADOR!Q:Q,PPTO_GENERADOR!E:E,"-",0) -> - | Q69: =IFERROR(P69*O69,0) -> 0 | R69: =+_xlfn.XLOOKUP(A69,PPTO_GENERADOR!$Q:$Q,PPTO_GENERADOR!A:A,"-",0) -> -
A70: ELE-121 | B70: MAT | C70: OTR | D70: ELE-004 | E70: =IFERROR(VLOOKUP(D70,MATERIALES!A:B,2,FALSE()),"?") -> Caño rigido 3/4" | F70: =IFERROR(VLOOKUP(D70,MATERIALES!A:C,3,FALSE()),"?") -> u | G70: 5 | H70: 0.05 | I70: =IFERROR(VLOOKUP(D70,MATERIALES!A:D,4,FALSE()),0) -> 504.29657 | J70: =G70*I70*(1+H70) -> 2647.557 | K70: =A70&"|"&B70 -> ELE-121|MAT | L70: =COUNTIFS($K$2:K70,K70) -> 1 | M70: =K70&"|"&L70 -> ELE-121|MAT|1 | N70: =IFERROR(VLOOKUP(A70,PARTIDAS!A:F,6,FALSE()),0) -> 3.25 | O70: =+IF(C70="ALB",G70/N70,0) -> 0 | P70: =+_xlfn.XLOOKUP(A70,PPTO_GENERADOR!Q:Q,PPTO_GENERADOR!E:E,"-",0) -> - | Q70: =IFERROR(P70*O70,0) -> 0 | R70: =+_xlfn.XLOOKUP(A70,PPTO_GENERADOR!$Q:$Q,PPTO_GENERADOR!A:A,"-",0) -> -
A71: ELE-121 | B71: MAT | C71: OTR | D71: ACE-017 | E71: =IFERROR(VLOOKUP(D71,MATERIALES!A:B,2,FALSE()),"?") -> Conector hierro 3/4" | F71: =IFERROR(VLOOKUP(D71,MATERIALES!A:C,3,FALSE()),"?") -> u | G71: 4 | H71: 0.1 | I71: =IFERROR(VLOOKUP(D71,MATERIALES!A:D,4,FALSE()),0) -> 250.319 | J71: =G71*I71*(1+H71) -> 1101.4036 | K71: =A71&"|"&B71 -> ELE-121|MAT | L71: =COUNTIFS($K$2:K71,K71) -> 2 | M71: =K71&"|"&L71 -> ELE-121|MAT|2 | N71: =IFERROR(VLOOKUP(A71,PARTIDAS!A:F,6,FALSE()),0) -> 3.25 | O71: =+IF(C71="ALB",G71/N71,0) -> 0 | P71: =+_xlfn.XLOOKUP(A71,PPTO_GENERADOR!Q:Q,PPTO_GENERADOR!E:E,"-",0) -> - | Q71: =IFERROR(P71*O71,0) -> 0 | R71: =+_xlfn.XLOOKUP(A71,PPTO_GENERADOR!$Q:$Q,PPTO_GENERADOR!A:A,"-",0) -> -
A72: ELE-121 | B72: MAT | C72: OTR | D72: ELE-005 | E72: =IFERROR(VLOOKUP(D72,MATERIALES!A:B,2,FALSE()),"?") -> Cupla PVC 3/4" | F72: =IFERROR(VLOOKUP(D72,MATERIALES!A:C,3,FALSE()),"?") -> u | G72: 1.2 | H72: 0.1 | I72: =IFERROR(VLOOKUP(D72,MATERIALES!A:D,4,FALSE()),0) -> 110.121 | J72: =G72*I72*(1+H72) -> 145.35972 | K72: =A72&"|"&B72 -> ELE-121|MAT | L72: =COUNTIFS($K$2:K72,K72) -> 3 | M72: =K72&"|"&L72 -> ELE-121|MAT|3 | N72: =IFERROR(VLOOKUP(A72,PARTIDAS!A:F,6,FALSE()),0) -> 3.25 | O72: =+IF(C72="ALB",G72/N72,0) -> 0 | P72: =+_xlfn.XLOOKUP(A72,PPTO_GENERADOR!Q:Q,PPTO_GENERADOR!E:E,"-",0) -> - | Q72: =IFERROR(P72*O72,0) -> 0 | R72: =+_xlfn.XLOOKUP(A72,PPTO_GENERADOR!$Q:$Q,PPTO_GENERADOR!A:A,"-",0) -> -
A73: ELE-121 | B73: MAT | C73: OTR | D73: ELE-009 | E73: =IFERROR(VLOOKUP(D73,MATERIALES!A:B,2,FALSE()),"?") -> Cable unipolar 1 x 2,50 VA | F73: =IFERROR(VLOOKUP(D73,MATERIALES!A:C,3,FALSE()),"?") -> m | G73: 5 | H73: 0.1 | I73: =IFERROR(VLOOKUP(D73,MATERIALES!A:D,4,FALSE()),0) -> 546.37688 | J73: =G73*I73*(1+H73) -> 3005.0728 | K73: =A73&"|"&B73 -> ELE-121|MAT | L73: =COUNTIFS($K$2:K73,K73) -> 4 | M73: =K73&"|"&L73 -> ELE-121|MAT|4 | N73: =IFERROR(VLOOKUP(A73,PARTIDAS!A:F,6,FALSE()),0) -> 3.25 | O73: =+IF(C73="ALB",G73/N73,0) -> 0 | P73: =+_xlfn.XLOOKUP(A73,PPTO_GENERADOR!Q:Q,PPTO_GENERADOR!E:E,"-",0) -> - | Q73: =IFERROR(P73*O73,0) -> 0 | R73: =+_xlfn.XLOOKUP(A73,PPTO_GENERADOR!$Q:$Q,PPTO_GENERADOR!A:A,"-",0) -> -
A74: ELE-121 | B74: MAT | C74: OTR | D74: ELE-009 | E74: =IFERROR(VLOOKUP(D74,MATERIALES!A:B,2,FALSE()),"?") -> Cable unipolar 1 x 2,50 VA | F74: =IFERROR(VLOOKUP(D74,MATERIALES!A:C,3,FALSE()),"?") -> m | G74: 10 | H74: 0.1 | I74: =IFERROR(VLOOKUP(D74,MATERIALES!A:D,4,FALSE()),0) -> 546.37688 | J74: =G74*I74*(1+H74) -> 6010.1456 | K74: =A74&"|"&B74 -> ELE-121|MAT | L74: =COUNTIFS($K$2:K74,K74) -> 5 | M74: =K74&"|"&L74 -> ELE-121|MAT|5 | N74: =IFERROR(VLOOKUP(A74,PARTIDAS!A:F,6,FALSE()),0) -> 3.25 | O74: =+IF(C74="ALB",G74/N74,0) -> 0 | P74: =+_xlfn.XLOOKUP(A74,PPTO_GENERADOR!Q:Q,PPTO_GENERADOR!E:E,"-",0) -> - | Q74: =IFERROR(P74*O74,0) -> 0 | R74: =+_xlfn.XLOOKUP(A74,PPTO_GENERADOR!$Q:$Q,PPTO_GENERADOR!A:A,"-",0) -> -
A75: ELE-121 | B75: MAT | C75: OTR | D75: ELE-014 | E75: =IFERROR(VLOOKUP(D75,MATERIALES!A:B,2,FALSE()),"?") -> Caja rectangular chica | F75: =IFERROR(VLOOKUP(D75,MATERIALES!A:C,3,FALSE()),"?") -> u | G75: 1 | H75: 0.05 | I75: =IFERROR(VLOOKUP(D75,MATERIALES!A:D,4,FALSE()),0) -> 217.14976 | J75: =G75*I75*(1+H75) -> 228.00725 | K75: =A75&"|"&B75 -> ELE-121|MAT | L75: =COUNTIFS($K$2:K75,K75) -> 6 | M75: =K75&"|"&L75 -> ELE-121|MAT|6 | N75: =IFERROR(VLOOKUP(A75,PARTIDAS!A:F,6,FALSE()),0) -> 3.25 | O75: =+IF(C75="ALB",G75/N75,0) -> 0 | P75: =+_xlfn.XLOOKUP(A75,PPTO_GENERADOR!Q:Q,PPTO_GENERADOR!E:E,"-",0) -> - | Q75: =IFERROR(P75*O75,0) -> 0 | R75: =+_xlfn.XLOOKUP(A75,PPTO_GENERADOR!$Q:$Q,PPTO_GENERADOR!A:A,"-",0) -> -
A76: ELE-121 | B76: MAT | C76: OTR | D76: MAT-CONS | E76: =IFERROR(VLOOKUP(D76,MATERIALES!A:B,2,FALSE()),"?") -> CONSUMIBLES (varios) | F76: =IFERROR(VLOOKUP(D76,MATERIALES!A:C,3,FALSE()),"?") -> gl | G76: 2758.8847 | H76: 0 | I76: =IFERROR(VLOOKUP(D76,MATERIALES!A:D,4,FALSE()),0) -> 1 | J76: =G76*I76*(1+H76) -> 2758.8847 | K76: =A76&"|"&B76 -> ELE-121|MAT | L76: =COUNTIFS($K$2:K76,K76) -> 7 | M76: =K76&"|"&L76 -> ELE-121|MAT|7 | N76: =IFERROR(VLOOKUP(A76,PARTIDAS!A:F,6,FALSE()),0) -> 3.25 | O76: =+IF(C76="ALB",G76/N76,0) -> 0 | P76: =+_xlfn.XLOOKUP(A76,PPTO_GENERADOR!Q:Q,PPTO_GENERADOR!E:E,"-",0) -> - | Q76: =IFERROR(P76*O76,0) -> 0 | R76: =+_xlfn.XLOOKUP(A76,PPTO_GENERADOR!$Q:$Q,PPTO_GENERADOR!A:A,"-",0) -> -
A77: ELE-121 | B77: EQ | D77: EQ-EQUIP0 | E77: =IFERROR(VLOOKUP(D77,EQUIPOS!A:B,2,FALSE()),"?") -> EQUIPO PARA INSTALACION ELECTRICA | G77: 1 | H77: 0 | I77: =IFERROR(VLOOKUP(D77,EQUIPOS!A:F,6,FALSE()),0) -> 5503.0404 | J77: =G77*I77 -> 5503.0404 | K77: =A77&"|"&B77 -> ELE-121|EQ | L77: =COUNTIFS($K$2:K77,K77) -> 1 | M77: =K77&"|"&L77 -> ELE-121|EQ|1 | N77: =IFERROR(VLOOKUP(A77,PARTIDAS!A:F,6,FALSE()),0) -> 3.25 | O77: =+IF(C77="ALB",G77/N77,0) -> 0 | P77: =+_xlfn.XLOOKUP(A77,PPTO_GENERADOR!Q:Q,PPTO_GENERADOR!E:E,"-",0) -> - | Q77: =IFERROR(P77*O77,0) -> 0 | R77: =+_xlfn.XLOOKUP(A77,PPTO_GENERADOR!$Q:$Q,PPTO_GENERADOR!A:A,"-",0) -> -
A78: ELE-121 | B78: EQ | D78: EQ-ANDAM0 | E78: =IFERROR(VLOOKUP(D78,EQUIPOS!A:B,2,FALSE()),"?") -> ANDAMIO TUBULAR DE UNO A TRES CUERPOS | G78: 0.5 | H78: 0 | I78: =IFERROR(VLOOKUP(D78,EQUIPOS!A:F,6,FALSE()),0) -> 620.81078 | J78: =G78*I78 -> 310.40539 | K78: =A78&"|"&B78 -> ELE-121|EQ | L78: =COUNTIFS($K$2:K78,K78) -> 2 | M78: =K78&"|"&L78 -> ELE-121|EQ|2 | N78: =IFERROR(VLOOKUP(A78,PARTIDAS!A:F,6,FALSE()),0) -> 3.25 | O78: =+IF(C78="ALB",G78/N78,0) -> 0 | P78: =+_xlfn.XLOOKUP(A78,PPTO_GENERADOR!Q:Q,PPTO_GENERADOR!E:E,"-",0) -> - | Q78: =IFERROR(P78*O78,0) -> 0 | R78: =+_xlfn.XLOOKUP(A78,PPTO_GENERADOR!$Q:$Q,PPTO_GENERADOR!A:A,"-",0) -> -
A79: ELE-121 | B79: EQ | D79: EQ-ESCALE | E79: =IFERROR(VLOOKUP(D79,EQUIPOS!A:B,2,FALSE()),"?") -> ESCALERA GLOSS ALUMINIO ARTICULADA 4 X 4 ESCALONES HASTA 150KG | G79: 0.5 | H79: 0 | I79: =IFERROR(VLOOKUP(D79,EQUIPOS!A:F,6,FALSE()),0) -> 152.38027 | J79: =G79*I79 -> 76.190137 | K79: =A79&"|"&B79 -> ELE-121|EQ | L79: =COUNTIFS($K$2:K79,K79) -> 3 | M79: =K79&"|"&L79 -> ELE-121|EQ|3 | N79: =IFERROR(VLOOKUP(A79,PARTIDAS!A:F,6,FALSE()),0) -> 3.25 | O79: =+IF(C79="ALB",G79/N79,0) -> 0 | P79: =+_xlfn.XLOOKUP(A79,PPTO_GENERADOR!Q:Q,PPTO_GENERADOR!E:E,"-",0) -> - | Q79: =IFERROR(P79*O79,0) -> 0 | R79: =+_xlfn.XLOOKUP(A79,PPTO_GENERADOR!$Q:$Q,PPTO_GENERADOR!A:A,"-",0) -> -
A80: ELE-121 | B80: MO | C80: ALB | D80: MO-EESPE | E80: =IFERROR(VLOOKUP(D80,MANO_DE_OBRA!A:B,2,FALSE()),"?") -> ESPECIALIZADO | F80: j | G80: 1 | H80: 0 | I80: =IFERROR(VLOOKUP(D80,MANO_DE_OBRA!A:C,3,FALSE()),0) -> 94177.138 | J80: =G80*I80 -> 94177.138 | K80: =A80&"|"&B80 -> ELE-121|MO | L80: =COUNTIFS($K$2:K80,K80) -> 1 | M80: =K80&"|"&L80 -> ELE-121|MO|1 | N80: =IFERROR(VLOOKUP(A80,PARTIDAS!A:F,6,FALSE()),0) -> 3.25 | O80: =+IF(C80="ALB",G80/N80,0) -> 0.30769231 | P80: =+_xlfn.XLOOKUP(A80,PPTO_GENERADOR!Q:Q,PPTO_GENERADOR!E:E,"-",0) -> - | Q80: =IFERROR(P80*O80,0) -> 0 | R80: =+_xlfn.XLOOKUP(A80,PPTO_GENERADOR!$Q:$Q,PPTO_GENERADOR!A:A,"-",0) -> -
A81: ELE-121 | B81: MO | C81: ALB | D81: MO-EAYUD | E81: =IFERROR(VLOOKUP(D81,MANO_DE_OBRA!A:B,2,FALSE()),"?") -> AYUDANTE | F81: j | G81: 1 | H81: 0 | I81: =IFERROR(VLOOKUP(D81,MANO_DE_OBRA!A:C,3,FALSE()),0) -> 67240.499 | J81: =G81*I81 -> 67240.499 | K81: =A81&"|"&B81 -> ELE-121|MO | L81: =COUNTIFS($K$2:K81,K81) -> 2 | M81: =K81&"|"&L81 -> ELE-121|MO|2 | N81: =IFERROR(VLOOKUP(A81,PARTIDAS!A:F,6,FALSE()),0) -> 3.25 | O81: =+IF(C81="ALB",G81/N81,0) -> 0.30769231 | P81: =+_xlfn.XLOOKUP(A81,PPTO_GENERADOR!Q:Q,PPTO_GENERADOR!E:E,"-",0) -> - | Q81: =IFERROR(P81*O81,0) -> 0 | R81: =+_xlfn.XLOOKUP(A81,PPTO_GENERADOR!$Q:$Q,PPTO_GENERADOR!A:A,"-",0) -> -
A82: BAN-122 | B82: MAT | C82: OTR | D82: OTR-038 | E82: =IFERROR(VLOOKUP(D82,MATERIALES!A:B,2,FALSE()),"?") -> SMARTTRAY TRX3M BJA PERF 200-22 | F82: =IFERROR(VLOOKUP(D82,MATERIALES!A:C,3,FALSE()),"?") -> u | G82: 0.35 | H82: 0.05 | I82: =IFERROR(VLOOKUP(D82,MATERIALES!A:D,4,FALSE()),0) -> 25108.056 | J82: =G82*I82*(1+H82) -> 9227.2106 | K82: =A82&"|"&B82 -> BAN-122|MAT | L82: =COUNTIFS($K$2:K82,K82) -> 1 | M82: =K82&"|"&L82 -> BAN-122|MAT|1 | N82: =IFERROR(VLOOKUP(A82,PARTIDAS!A:F,6,FALSE()),0) -> 12 | O82: =+IF(C82="ALB",G82/N82,0) -> 0 | P82: =+_xlfn.XLOOKUP(A82,PPTO_GENERADOR!Q:Q,PPTO_GENERADOR!E:E,"-",0) -> - | Q82: =IFERROR(P82*O82,0) -> 0 | R82: =+_xlfn.XLOOKUP(A82,PPTO_GENERADOR!$Q:$Q,PPTO_GENERADOR!A:A,"-",0) -> -
A83: BAN-122 | B83: MAT | C83: OTR | D83: OTR-039 | E83: =IFERROR(VLOOKUP(D83,MATERIALES!A:B,2,FALSE()),"?") -> SMARTTRAY TAPA CIEGA P/BJA 200-22 | F83: =IFERROR(VLOOKUP(D83,MATERIALES!A:C,3,FALSE()),"?") -> u | G83: 0.35 | H83: 0.1 | I83: =IFERROR(VLOOKUP(D83,MATERIALES!A:D,4,FALSE()),0) -> 16853.812 | J83: =G83*I83*(1+H83) -> 6488.7176 | K83: =A83&"|"&B83 -> BAN-122|MAT | L83: =COUNTIFS($K$2:K83,K83) -> 2 | M83: =K83&"|"&L83 -> BAN-122|MAT|2 | N83: =IFERROR(VLOOKUP(A83,PARTIDAS!A:F,6,FALSE()),0) -> 12 | O83: =+IF(C83="ALB",G83/N83,0) -> 0 | P83: =+_xlfn.XLOOKUP(A83,PPTO_GENERADOR!Q:Q,PPTO_GENERADOR!E:E,"-",0) -> - | Q83: =IFERROR(P83*O83,0) -> 0 | R83: =+_xlfn.XLOOKUP(A83,PPTO_GENERADOR!$Q:$Q,PPTO_GENERADOR!A:A,"-",0) -> -
A84: BAN-122 | B84: MAT | C84: OTR | D84: BAN-MAT003 | E84: =IFERROR(VLOOKUP(D84,MATERIALES!A:B,2,FALSE()),"?") -> SMARTTRAY CUPLA UNION JBCC-M6-100 | F84: =IFERROR(VLOOKUP(D84,MATERIALES!A:C,3,FALSE()),"?") -> u | G84: 0.015 | H84: 0.1 | I84: =IFERROR(VLOOKUP(D84,MATERIALES!A:D,4,FALSE()),0) -> 14030.018 | J84: =G84*I84*(1+H84) -> 231.49529 | K84: =A84&"|"&B84 -> BAN-122|MAT | L84: =COUNTIFS($K$2:K84,K84) -> 3 | M84: =K84&"|"&L84 -> BAN-122|MAT|3 | N84: =IFERROR(VLOOKUP(A84,PARTIDAS!A:F,6,FALSE()),0) -> 12 | O84: =+IF(C84="ALB",G84/N84,0) -> 0 | P84: =+_xlfn.XLOOKUP(A84,PPTO_GENERADOR!Q:Q,PPTO_GENERADOR!E:E,"-",0) -> - | Q84: =IFERROR(P84*O84,0) -> 0 | R84: =+_xlfn.XLOOKUP(A84,PPTO_GENERADOR!$Q:$Q,PPTO_GENERADOR!A:A,"-",0) -> -
A85: BAN-122 | B85: MAT | C85: OTR | D85: BAN-MAT004 | E85: =IFERROR(VLOOKUP(D85,MATERIALES!A:B,2,FALSE()),"?") -> GRAMPA FIJACION CABLE | F85: =IFERROR(VLOOKUP(D85,MATERIALES!A:C,3,FALSE()),"?") -> u | G85: 0.35 | H85: 0.1 | I85: =IFERROR(VLOOKUP(D85,MATERIALES!A:D,4,FALSE()),0) -> 2124.5318 | J85: =G85*I85*(1+H85) -> 817.94474 | K85: =A85&"|"&B85 -> BAN-122|MAT | L85: =COUNTIFS($K$2:K85,K85) -> 4 | M85: =K85&"|"&L85 -> BAN-122|MAT|4 | N85: =IFERROR(VLOOKUP(A85,PARTIDAS!A:F,6,FALSE()),0) -> 12 | O85: =+IF(C85="ALB",G85/N85,0) -> 0 | P85: =+_xlfn.XLOOKUP(A85,PPTO_GENERADOR!Q:Q,PPTO_GENERADOR!E:E,"-",0) -> - | Q85: =IFERROR(P85*O85,0) -> 0 | R85: =+_xlfn.XLOOKUP(A85,PPTO_GENERADOR!$Q:$Q,PPTO_GENERADOR!A:A,"-",0) -> -
A86: BAN-122 | B86: MAT | C86: OTR | D86: OTR-040 | E86: =IFERROR(VLOOKUP(D86,MATERIALES!A:B,2,FALSE()),"?") -> ACOMETIDA PARA TABLERO | F86: =IFERROR(VLOOKUP(D86,MATERIALES!A:C,3,FALSE()),"?") -> u | G86: 0.03 | H86: 0.1 | I86: =IFERROR(VLOOKUP(D86,MATERIALES!A:D,4,FALSE()),0) -> 6773.5985 | J86: =G86*I86*(1+H86) -> 223.52875 | K86: =A86&"|"&B86 -> BAN-122|MAT | L86: =COUNTIFS($K$2:K86,K86) -> 5 | M86: =K86&"|"&L86 -> BAN-122|MAT|5 | N86: =IFERROR(VLOOKUP(A86,PARTIDAS!A:F,6,FALSE()),0) -> 12 | O86: =+IF(C86="ALB",G86/N86,0) -> 0 | P86: =+_xlfn.XLOOKUP(A86,PPTO_GENERADOR!Q:Q,PPTO_GENERADOR!E:E,"-",0) -> - | Q86: =IFERROR(P86*O86,0) -> 0 | R86: =+_xlfn.XLOOKUP(A86,PPTO_GENERADOR!$Q:$Q,PPTO_GENERADOR!A:A,"-",0) -> -
A87: BAN-122 | B87: MAT | C87: OTR | D87: OTR-041 | E87: =IFERROR(VLOOKUP(D87,MATERIALES!A:B,2,FALSE()),"?") -> EMBUDO | F87: =IFERROR(VLOOKUP(D87,MATERIALES!A:C,3,FALSE()),"?") -> u | G87: 0.03 | H87: 0.1 | I87: =IFERROR(VLOOKUP(D87,MATERIALES!A:D,4,FALSE()),0) -> 6773.5985 | J87: =G87*I87*(1+H87) -> 223.52875 | K87: =A87&"|"&B87 -> BAN-122|MAT | L87: =COUNTIFS($K$2:K87,K87) -> 6 | M87: =K87&"|"&L87 -> BAN-122|MAT|6 | N87: =IFERROR(VLOOKUP(A87,PARTIDAS!A:F,6,FALSE()),0) -> 12 | O87: =+IF(C87="ALB",G87/N87,0) -> 0 | P87: =+_xlfn.XLOOKUP(A87,PPTO_GENERADOR!Q:Q,PPTO_GENERADOR!E:E,"-",0) -> - | Q87: =IFERROR(P87*O87,0) -> 0 | R87: =+_xlfn.XLOOKUP(A87,PPTO_GENERADOR!$Q:$Q,PPTO_GENERADOR!A:A,"-",0) -> -
A88: BAN-122 | B88: MAT | C88: OTR | D88: BAN-MAT007 | E88: =IFERROR(VLOOKUP(D88,MATERIALES!A:B,2,FALSE()),"?") -> GRAMPA FIJACION 200-22 | F88: =IFERROR(VLOOKUP(D88,MATERIALES!A:C,3,FALSE()),"?") -> u | G88: 0.57 | H88: 0.1 | I88: =IFERROR(VLOOKUP(D88,MATERIALES!A:D,4,FALSE()),0) -> 1979.0429 | J88: =G88*I88*(1+H88) -> 1240.8599 | K88: =A88&"|"&B88 -> BAN-122|MAT | L88: =COUNTIFS($K$2:K88,K88) -> 7 | M88: =K88&"|"&L88 -> BAN-122|MAT|7 | N88: =IFERROR(VLOOKUP(A88,PARTIDAS!A:F,6,FALSE()),0) -> 12 | O88: =+IF(C88="ALB",G88/N88,0) -> 0 | P88: =+_xlfn.XLOOKUP(A88,PPTO_GENERADOR!Q:Q,PPTO_GENERADOR!E:E,"-",0) -> - | Q88: =IFERROR(P88*O88,0) -> 0 | R88: =+_xlfn.XLOOKUP(A88,PPTO_GENERADOR!$Q:$Q,PPTO_GENERADOR!A:A,"-",0) -> -
A89: BAN-122 | B89: MAT | C89: OTR | D89: OTR-044 | E89: =IFERROR(VLOOKUP(D89,MATERIALES!A:B,2,FALSE()),"?") -> VARILLA ROSCADA 1/4 | F89: =IFERROR(VLOOKUP(D89,MATERIALES!A:C,3,FALSE()),"?") -> u | G89: 0.3 | H89: 0.1 | I89: =IFERROR(VLOOKUP(D89,MATERIALES!A:D,4,FALSE()),0) -> 1069.6694 | J89: =G89*I89*(1+H89) -> 352.99091 | K89: =A89&"|"&B89 -> BAN-122|MAT | L89: =COUNTIFS($K$2:K89,K89) -> 8 | M89: =K89&"|"&L89 -> BAN-122|MAT|8 | N89: =IFERROR(VLOOKUP(A89,PARTIDAS!A:F,6,FALSE()),0) -> 12 | O89: =+IF(C89="ALB",G89/N89,0) -> 0 | P89: =+_xlfn.XLOOKUP(A89,PPTO_GENERADOR!Q:Q,PPTO_GENERADOR!E:E,"-",0) -> - | Q89: =IFERROR(P89*O89,0) -> 0 | R89: =+_xlfn.XLOOKUP(A89,PPTO_GENERADOR!$Q:$Q,PPTO_GENERADOR!A:A,"-",0) -> -
A90: BAN-122 | B90: MAT | C90: OTR | D90: OTR-045 | E90: =IFERROR(VLOOKUP(D90,MATERIALES!A:B,2,FALSE()),"?") -> TUERCA Y ARANDELA 1/4 | F90: =IFERROR(VLOOKUP(D90,MATERIALES!A:C,3,FALSE()),"?") -> u | G90: 1.2 | H90: 0.05 | I90: =IFERROR(VLOOKUP(D90,MATERIALES!A:D,4,FALSE()),0) -> 33.3 | J90: =G90*I90*(1+H90) -> 41.958 | K90: =A90&"|"&B90 -> BAN-122|MAT | L90: =COUNTIFS($K$2:K90,K90) -> 9 | M90: =K90&"|"&L90 -> BAN-122|MAT|9 | N90: =IFERROR(VLOOKUP(A90,PARTIDAS!A:F,6,FALSE()),0) -> 12 | O90: =+IF(C90="ALB",G90/N90,0) -> 0 | P90: =+_xlfn.XLOOKUP(A90,PPTO_GENERADOR!Q:Q,PPTO_GENERADOR!E:E,"-",0) -> - | Q90: =IFERROR(P90*O90,0) -> 0 | R90: =+_xlfn.XLOOKUP(A90,PPTO_GENERADOR!$Q:$Q,PPTO_GENERADOR!A:A,"-",0) -> -
A91: BAN-122 | B91: MO | C91: ALB | D91: MO-EESPE | E91: =IFERROR(VLOOKUP(D91,MANO_DE_OBRA!A:B,2,FALSE()),"?") -> ESPECIALIZADO | F91: j | G91: 1 | H91: 0 | I91: =IFERROR(VLOOKUP(D91,MANO_DE_OBRA!A:C,3,FALSE()),0) -> 94177.138 | J91: =G91*I91 -> 94177.138 | K91: =A91&"|"&B91 -> BAN-122|MO | L91: =COUNTIFS($K$2:K91,K91) -> 1 | M91: =K91&"|"&L91 -> BAN-122|MO|1 | N91: =IFERROR(VLOOKUP(A91,PARTIDAS!A:F,6,FALSE()),0) -> 12 | O91: =+IF(C91="ALB",G91/N91,0) -> 0.083333333 | P91: =+_xlfn.XLOOKUP(A91,PPTO_GENERADOR!Q:Q,PPTO_GENERADOR!E:E,"-",0) -> - | Q91: =IFERROR(P91*O91,0) -> 0 | R91: =+_xlfn.XLOOKUP(A91,PPTO_GENERADOR!$Q:$Q,PPTO_GENERADOR!A:A,"-",0) -> -
A92: BAN-122 | B92: MO | C92: ALB | D92: MO-EAYUD | E92: =IFERROR(VLOOKUP(D92,MANO_DE_OBRA!A:B,2,FALSE()),"?") -> AYUDANTE | F92: j | G92: 0.59245025 | H92: 0 | I92: =IFERROR(VLOOKUP(D92,MANO_DE_OBRA!A:C,3,FALSE()),0) -> 67240.499 | J92: =G92*I92 -> 39836.65 | K92: =A92&"|"&B92 -> BAN-122|MO | L92: =COUNTIFS($K$2:K92,K92) -> 2 | M92: =K92&"|"&L92 -> BAN-122|MO|2 | N92: =IFERROR(VLOOKUP(A92,PARTIDAS!A:F,6,FALSE()),0) -> 12 | O92: =+IF(C92="ALB",G92/N92,0) -> 0.049370854 | P92: =+_xlfn.XLOOKUP(A92,PPTO_GENERADOR!Q:Q,PPTO_GENERADOR!E:E,"-",0) -> - | Q92: =IFERROR(P92*O92,0) -> 0 | R92: =+_xlfn.XLOOKUP(A92,PPTO_GENERADOR!$Q:$Q,PPTO_GENERADOR!A:A,"-",0) -> -
A93: HHA-123 | B93: MAT | C93: OTR | D93: MAT-CONS | E93: =IFERROR(VLOOKUP(D93,MATERIALES!A:B,2,FALSE()),"?") -> CONSUMIBLES (varios) | F93: =IFERROR(VLOOKUP(D93,MATERIALES!A:C,3,FALSE()),"?") -> gl | G93: 1 | H93: 0.1 | I93: =IFERROR(VLOOKUP(D93,MATERIALES!A:D,4,FALSE()),0) -> 1 | J93: =G93*I93*(1+H93) -> 1.1 | K93: =A93&"|"&B93 -> HHA-123|MAT | L93: =COUNTIFS($K$2:K93,K93) -> 1 | M93: =K93&"|"&L93 -> HHA-123|MAT|1 | N93: =IFERROR(VLOOKUP(A93,PARTIDAS!A:F,6,FALSE()),0) -> 12 | O93: =+IF(C93="ALB",G93/N93,0) -> 0 | P93: =+_xlfn.XLOOKUP(A93,PPTO_GENERADOR!Q:Q,PPTO_GENERADOR!E:E,"-",0) -> - | Q93: =IFERROR(P93*O93,0) -> 0 | R93: =+_xlfn.XLOOKUP(A93,PPTO_GENERADOR!$Q:$Q,PPTO_GENERADOR!A:A,"-",0) -> -
A94: HHA-123 | B94: MO | C94: ALB | D94: MO-EESPE | E94: =IFERROR(VLOOKUP(D94,MANO_DE_OBRA!A:B,2,FALSE()),"?") -> ESPECIALIZADO | F94: j | G94: 1 | H94: 0 | I94: =IFERROR(VLOOKUP(D94,MANO_DE_OBRA!A:C,3,FALSE()),0) -> 94177.138 | J94: =G94*I94 -> 94177.138 | K94: =A94&"|"&B94 -> HHA-123|MO | L94: =COUNTIFS($K$2:K94,K94) -> 1 | M94: =K94&"|"&L94 -> HHA-123|MO|1 | N94: =IFERROR(VLOOKUP(A94,PARTIDAS!A:F,6,FALSE()),0) -> 12 | O94: =+IF(C94="ALB",G94/N94,0) -> 0.083333333 | P94: =+_xlfn.XLOOKUP(A94,PPTO_GENERADOR!Q:Q,PPTO_GENERADOR!E:E,"-",0) -> - | Q94: =IFERROR(P94*O94,0) -> 0 | R94: =+_xlfn.XLOOKUP(A94,PPTO_GENERADOR!$Q:$Q,PPTO_GENERADOR!A:A,"-",0) -> -
A95: HHA-123 | B95: MO | C95: ALB | D95: MO-EMEDI | E95: =IFERROR(VLOOKUP(D95,MANO_DE_OBRA!A:B,2,FALSE()),"?") -> MEDIO OFICIAL | F95: j | G95: 0.75 | H95: 0 | I95: =IFERROR(VLOOKUP(D95,MANO_DE_OBRA!A:C,3,FALSE()),0) -> 72132.138 | J95: =G95*I95 -> 54099.104 | K95: =A95&"|"&B95 -> HHA-123|MO | L95: =COUNTIFS($K$2:K95,K95) -> 2 | M95: =K95&"|"&L95 -> HHA-123|MO|2 | N95: =IFERROR(VLOOKUP(A95,PARTIDAS!A:F,6,FALSE()),0) -> 12 | O95: =+IF(C95="ALB",G95/N95,0) -> 0.0625 | P95: =+_xlfn.XLOOKUP(A95,PPTO_GENERADOR!Q:Q,PPTO_GENERADOR!E:E,"-",0) -> - | Q95: =IFERROR(P95*O95,0) -> 0 | R95: =+_xlfn.XLOOKUP(A95,PPTO_GENERADOR!$Q:$Q,PPTO_GENERADOR!A:A,"-",0) -> -
A96: HHA-124 | B96: MAT | C96: OTR | D96: MAT-CONS | E96: =IFERROR(VLOOKUP(D96,MATERIALES!A:B,2,FALSE()),"?") -> CONSUMIBLES (varios) | F96: =IFERROR(VLOOKUP(D96,MATERIALES!A:C,3,FALSE()),"?") -> gl | G96: 1 | H96: 0.05 | I96: =IFERROR(VLOOKUP(D96,MATERIALES!A:D,4,FALSE()),0) -> 1 | J96: =G96*I96*(1+H96) -> 1.05 | K96: =A96&"|"&B96 -> HHA-124|MAT | L96: =COUNTIFS($K$2:K96,K96) -> 1 | M96: =K96&"|"&L96 -> HHA-124|MAT|1 | N96: =IFERROR(VLOOKUP(A96,PARTIDAS!A:F,6,FALSE()),0) -> 12 | O96: =+IF(C96="ALB",G96/N96,0) -> 0 | P96: =+_xlfn.XLOOKUP(A96,PPTO_GENERADOR!Q:Q,PPTO_GENERADOR!E:E,"-",0) -> - | Q96: =IFERROR(P96*O96,0) -> 0 | R96: =+_xlfn.XLOOKUP(A96,PPTO_GENERADOR!$Q:$Q,PPTO_GENERADOR!A:A,"-",0) -> -
A97: HHA-124 | B97: MAT | C97: OTR | D97: MAT-CONS | E97: =IFERROR(VLOOKUP(D97,MATERIALES!A:B,2,FALSE()),"?") -> CONSUMIBLES (varios) | F97: =IFERROR(VLOOKUP(D97,MATERIALES!A:C,3,FALSE()),"?") -> gl | G97: 1 | H97: 0.05 | I97: =IFERROR(VLOOKUP(D97,MATERIALES!A:D,4,FALSE()),0) -> 1 | J97: =G97*I97*(1+H97) -> 1.05 | K97: =A97&"|"&B97 -> HHA-124|MAT | L97: =COUNTIFS($K$2:K97,K97) -> 2 | M97: =K97&"|"&L97 -> HHA-124|MAT|2 | N97: =IFERROR(VLOOKUP(A97,PARTIDAS!A:F,6,FALSE()),0) -> 12 | O97: =+IF(C97="ALB",G97/N97,0) -> 0 | P97: =+_xlfn.XLOOKUP(A97,PPTO_GENERADOR!Q:Q,PPTO_GENERADOR!E:E,"-",0) -> - | Q97: =IFERROR(P97*O97,0) -> 0 | R97: =+_xlfn.XLOOKUP(A97,PPTO_GENERADOR!$Q:$Q,PPTO_GENERADOR!A:A,"-",0) -> -
A98: HHA-124 | B98: MO | C98: ALB | D98: MO-EESPE | E98: =IFERROR(VLOOKUP(D98,MANO_DE_OBRA!A:B,2,FALSE()),"?") -> ESPECIALIZADO | F98: j | G98: 1 | H98: 0 | I98: =IFERROR(VLOOKUP(D98,MANO_DE_OBRA!A:C,3,FALSE()),0) -> 94177.138 | J98: =G98*I98 -> 94177.138 | K98: =A98&"|"&B98 -> HHA-124|MO | L98: =COUNTIFS($K$2:K98,K98) -> 1 | M98: =K98&"|"&L98 -> HHA-124|MO|1 | N98: =IFERROR(VLOOKUP(A98,PARTIDAS!A:F,6,FALSE()),0) -> 12 | O98: =+IF(C98="ALB",G98/N98,0) -> 0.083333333 | P98: =+_xlfn.XLOOKUP(A98,PPTO_GENERADOR!Q:Q,PPTO_GENERADOR!E:E,"-",0) -> - | Q98: =IFERROR(P98*O98,0) -> 0 | R98: =+_xlfn.XLOOKUP(A98,PPTO_GENERADOR!$Q:$Q,PPTO_GENERADOR!A:A,"-",0) -> -
A99: HHA-124 | B99: MO | C99: ALB | D99: MO-EMEDI | E99: =IFERROR(VLOOKUP(D99,MANO_DE_OBRA!A:B,2,FALSE()),"?") -> MEDIO OFICIAL | F99: j | G99: 0.75 | H99: 0 | I99: =IFERROR(VLOOKUP(D99,MANO_DE_OBRA!A:C,3,FALSE()),0) -> 72132.138 | J99: =G99*I99 -> 54099.104 | K99: =A99&"|"&B99 -> HHA-124|MO | L99: =COUNTIFS($K$2:K99,K99) -> 2 | M99: =K99&"|"&L99 -> HHA-124|MO|2 | N99: =IFERROR(VLOOKUP(A99,PARTIDAS!A:F,6,FALSE()),0) -> 12 | O99: =+IF(C99="ALB",G99/N99,0) -> 0.0625 | P99: =+_xlfn.XLOOKUP(A99,PPTO_GENERADOR!Q:Q,PPTO_GENERADOR!E:E,"-",0) -> - | Q99: =IFERROR(P99*O99,0) -> 0 | R99: =+_xlfn.XLOOKUP(A99,PPTO_GENERADOR!$Q:$Q,PPTO_GENERADOR!A:A,"-",0) -> -
A100: CER-134 | B100: MAT | C100: OTR | D100: AGR-001 | E100: =IFERROR(VLOOKUP(D100,MATERIALES!A:B,2,FALSE()),"?") -> ARENA LAVADA | F100: =IFERROR(VLOOKUP(D100,MATERIALES!A:C,3,FALSE()),"?") -> 0 | G100: 0.017 | H100: 0.1 | I100: =IFERROR(VLOOKUP(D100,MATERIALES!A:D,4,FALSE()),0) -> 32620.38 | J100: =G100*I100*(1+H100) -> 610.00111 | K100: =A100&"|"&B100 -> CER-134|MAT | L100: =COUNTIFS($K$2:K100,K100) -> 1 | M100: =K100&"|"&L100 -> CER-134|MAT|1 | N100: =IFERROR(VLOOKUP(A100,PARTIDAS!A:F,6,FALSE()),0) -> 18 | O100: =+IF(C100="ALB",G100/N100,0) -> 0 | P100: =+_xlfn.XLOOKUP(A100,PPTO_GENERADOR!Q:Q,PPTO_GENERADOR!E:E,"-",0) -> - | Q100: =IFERROR(P100*O100,0) -> 0 | R100: =+_xlfn.XLOOKUP(A100,PPTO_GENERADOR!$Q:$Q,PPTO_GENERADOR!A:A,"-",0) -> -
...

Sheet PARTIDAS
A1: Código | B1: P# | C1: Rubro | D1: Descripción | E1: Ud. | F1: Rend. | G1: Cant Cons. | H1: % Cons. Desp. | I1: Grado Dif. | J1: MAT (sum/ud) | K1: MO (sum/día) | L1: EQ (sum/día) | M1: MAT/ud | N1: MO/ud | O1: EQ/ud | P1: CD/ud | Q1: # Comp. | S1: Fuente | T1: GDR MAT | U1: GDR MO | V1: GDR EQ
A2: APU-101 | B2: 101 | C2: General | D2: Viga de Hormigon Armado - Encofrado Fenolico | E2: m3 | F2: 1 | G2: 0 | H2: 0 | I2: 1 | J2: =SUMIFS(COMPOSICIÓN!J$2:J$1892,COMPOSICIÓN!A$2:A$1892,A2,COMPOSICIÓN!B$2:B$1892,"MAT") -> 0 | K2: =SUMIFS(COMPOSICIÓN!J$2:J$1892,COMPOSICIÓN!A$2:A$1892,A2,COMPOSICIÓN!B$2:B$1892,"MO")*I2 -> 161417.64 | L2: =SUMIFS(COMPOSICIÓN!J$2:J$1892,COMPOSICIÓN!A$2:A$1892,A2,COMPOSICIÓN!B$2:B$1892,"EQ") -> 0 | M2: =J2 -> 0 | N2: =IF(F2=0,0,K2/F2) -> 161417.64 | O2: =IF(F2=0,0,L2/F2) -> 0 | P2: =M2+N2+O2 -> 161417.64 | Q2: =COUNTIF(COMPOSICIÓN!$A:$A,A2) -> 2 | S2: APU
A3: BAN-106 | B3: 106 | C3: Bandeja | D3: Viga de Hormigon Armado - FE Doblado y Armado | E3: m3 | F3: 3.8 | G3: 0 | H3: 0 | I3: 1 | J3: =SUMIFS(COMPOSICIÓN!J$2:J$1892,COMPOSICIÓN!A$2:A$1892,A3,COMPOSICIÓN!B$2:B$1892,"MAT") -> 0 | K3: =SUMIFS(COMPOSICIÓN!J$2:J$1892,COMPOSICIÓN!A$2:A$1892,A3,COMPOSICIÓN!B$2:B$1892,"MO")*I3 -> 161417.64 | L3: =SUMIFS(COMPOSICIÓN!J$2:J$1892,COMPOSICIÓN!A$2:A$1892,A3,COMPOSICIÓN!B$2:B$1892,"EQ") -> 0 | M3: =J3 -> 0 | N3: =IF(F3=0,0,K3/F3) -> 42478.325 | O3: =IF(F3=0,0,L3/F3) -> 0 | P3: =M3+N3+O3 -> 42478.325 | Q3: =COUNTIF(COMPOSICIÓN!$A:$A,A3) -> 2 | R3: REVISAR — P-XX sin Unitario Materiales legible. Sin corrección pendiente. Chat 5. | S3: APU
A4: ALB-110 | B4: 110 | C4: MAMPOSTERÍA | D4: Viga de Hormigon Armado - Llenado | E4: m3 | F4: 36 | G4: 0 | H4: 0 | I4: 1 | J4: =SUMIFS(COMPOSICIÓN!J$2:J$1892,COMPOSICIÓN!A$2:A$1892,A4,COMPOSICIÓN!B$2:B$1892,"MAT") -> 0 | K4: =SUMIFS(COMPOSICIÓN!J$2:J$1892,COMPOSICIÓN!A$2:A$1892,A4,COMPOSICIÓN!B$2:B$1892,"MO")*I4 -> 589318.83 | L4: =SUMIFS(COMPOSICIÓN!J$2:J$1892,COMPOSICIÓN!A$2:A$1892,A4,COMPOSICIÓN!B$2:B$1892,"EQ") -> 0 | M4: =J4 -> 0 | N4: =IF(F4=0,0,K4/F4) -> 16369.967 | O4: =IF(F4=0,0,L4/F4) -> 0 | P4: =M4+N4+O4 -> 16369.967 | Q4: =COUNTIF(COMPOSICIÓN!$A:$A,A4) -> 3 | R4: REVISAR — P-XX sin Unitario Materiales legible. Sin corrección pendiente. Chat 5. | S4: APU
A5: AIS-113 | B5: 113 | C5: AISLACIONES | D5: Impermeabilizacion de azotea con pintura asfaltica / Barrera de vapor | E5: m2 | F5: 80 | G5: 0 | H5: 0 | I5: 1 | J5: =SUMIFS(COMPOSICIÓN!J$2:J$1892,COMPOSICIÓN!A$2:A$1892,A5,COMPOSICIÓN!B$2:B$1892,"MAT") -> 1393.4782 | K5: =SUMIFS(COMPOSICIÓN!J$2:J$1892,COMPOSICIÓN!A$2:A$1892,A5,COMPOSICIÓN!B$2:B$1892,"MO")*I5 -> 161417.64 | L5: =SUMIFS(COMPOSICIÓN!J$2:J$1892,COMPOSICIÓN!A$2:A$1892,A5,COMPOSICIÓN!B$2:B$1892,"EQ") -> 874.41131 | M5: =J5 -> 1393.4782 | N5: =IF(F5=0,0,K5/F5) -> 2017.7205 | O5: =IF(F5=0,0,L5/F5) -> 10.930141 | P5: =M5+N5+O5 -> 3422.1288 | Q5: =COUNTIF(COMPOSICIÓN!$A:$A,A5) -> 8 | S5: APU | T5: 1392.6098 | U5: 2017.7205 | V5: 10.930141
A6: AIS-114 | B6: 114 | C6: AISLACIONES | D6: Babeta en Azotea con membrana Geotextil Ormiflex de 4mm, a soplete. | E6: m | F6: 60 | G6: 0 | H6: 0 | I6: 1 | J6: =SUMIFS(COMPOSICIÓN!J$2:J$1892,COMPOSICIÓN!A$2:A$1892,A6,COMPOSICIÓN!B$2:B$1892,"MAT") -> 4401.83 | K6: =SUMIFS(COMPOSICIÓN!J$2:J$1892,COMPOSICIÓN!A$2:A$1892,A6,COMPOSICIÓN!B$2:B$1892,"MO")*I6 -> 161417.64 | L6: =SUMIFS(COMPOSICIÓN!J$2:J$1892,COMPOSICIÓN!A$2:A$1892,A6,COMPOSICIÓN!B$2:B$1892,"EQ") -> 874.41131 | M6: =J6 -> 4401.83 | N6: =IF(F6=0,0,K6/F6) -> 2690.2939 | O6: =IF(F6=0,0,L6/F6) -> 14.573522 | P6: =M6+N6+O6 -> 7106.6974 | Q6: =COUNTIF(COMPOSICIÓN!$A:$A,A6) -> 11 | S6: APU | T6: 3733.7132 | U6: 2690.2939 | V6: 14.573522
A7: REV-115 | B7: 115 | C7: REVOQUES | D7: Revoque Grueso Exterior S/hidrofugo hasta 3.00 m | E7: m2 | F7: 15 | G7: 0 | H7: 0 | I7: 1 | J7: =SUMIFS(COMPOSICIÓN!J$2:J$1892,COMPOSICIÓN!A$2:A$1892,A7,COMPOSICIÓN!B$2:B$1892,"MAT") -> 3032.8064 | K7: =SUMIFS(COMPOSICIÓN!J$2:J$1892,COMPOSICIÓN!A$2:A$1892,A7,COMPOSICIÓN!B$2:B$1892,"MO")*I7 -> 161417.64 | L7: =SUMIFS(COMPOSICIÓN!J$2:J$1892,COMPOSICIÓN!A$2:A$1892,A7,COMPOSICIÓN!B$2:B$1892,"EQ") -> 0 | M7: =J7 -> 3032.8064 | N7: =IF(F7=0,0,K7/F7) -> 10761.176 | O7: =IF(F7=0,0,L7/F7) -> 0 | P7: =M7+N7+O7 -> 13793.982 | Q7: =COUNTIF(COMPOSICIÓN!$A:$A,A7) -> 6 | R7: Desvío MAT +2.8%. Probable redondeo de %desp vs APU original. Sin acción correctiva. | S7: APU | T7: 2950.8968 | U7: 10761.176 | V7: 0
A8: REV-116 | B8: 116 | C8: REVOQUES | D8: Cielorraso Desmontable 120x60 - incluye placa | E8: m2 | F8: 12 | G8: 0 | H8: 0 | I8: 1 | J8: =SUMIFS(COMPOSICIÓN!J$2:J$1892,COMPOSICIÓN!A$2:A$1892,A8,COMPOSICIÓN!B$2:B$1892,"MAT") -> 16332.359 | K8: =SUMIFS(COMPOSICIÓN!J$2:J$1892,COMPOSICIÓN!A$2:A$1892,A8,COMPOSICIÓN!B$2:B$1892,"MO")*I8 -> 166309.28 | L8: =SUMIFS(COMPOSICIÓN!J$2:J$1892,COMPOSICIÓN!A$2:A$1892,A8,COMPOSICIÓN!B$2:B$1892,"EQ") -> 2723.1402 | M8: =J8 -> 16332.359 | N8: =IF(F8=0,0,K8/F8) -> 13859.106 | O8: =IF(F8=0,0,L8/F8) -> 226.92835 | P8: =M8+N8+O8 -> 30418.393 | Q8: =COUNTIF(COMPOSICIÓN!$A:$A,A8) -> 11 | S8: APU | T8: 16332.301 | U8: 13859.106 | V8: 226.92835
A9: YES-117 | B9: 117 | C9: REVOQUES FINOS Y CIELORRASOS | D9: Perfil buña Z / Cantonera | E9: ml | F9: 15 | G9: 0 | H9: 0 | I9: 1 | J9: =SUMIFS(COMPOSICIÓN!J$2:J$1892,COMPOSICIÓN!A$2:A$1892,A9,COMPOSICIÓN!B$2:B$1892,"MAT") -> 987.1745 | K9: =SUMIFS(COMPOSICIÓN!J$2:J$1892,COMPOSICIÓN!A$2:A$1892,A9,COMPOSICIÓN!B$2:B$1892,"MO")*I9 -> 94177.138 | L9: =SUMIFS(COMPOSICIÓN!J$2:J$1892,COMPOSICIÓN!A$2:A$1892,A9,COMPOSICIÓN!B$2:B$1892,"EQ") -> 2723.1402 | M9: =J9 -> 987.1745 | N9: =IF(F9=0,0,K9/F9) -> 6278.4759 | O9: =IF(F9=0,0,L9/F9) -> 181.54268 | P9: =M9+N9+O9 -> 7447.193 | Q9: =COUNTIF(COMPOSICIÓN!$A:$A,A9) -> 5 | S9: APU | T9: 987.1745 | U9: 6278.4759 | V9: 181.54268
A10: YES-118 | B10: 118 | C10: REVOQUES FINOS Y CIELORRASOS | D10: Bloque de Hormigon 10 x 19 x 39 | E10: m2 | F10: 11.5 | G10: 0 | H10: 0 | I10: 1 | J10: =SUMIFS(COMPOSICIÓN!J$2:J$1892,COMPOSICIÓN!A$2:A$1892,A10,COMPOSICIÓN!B$2:B$1892,"MAT") -> 12733.789 | K10: =SUMIFS(COMPOSICIÓN!J$2:J$1892,COMPOSICIÓN!A$2:A$1892,A10,COMPOSICIÓN!B$2:B$1892,"MO")*I10 -> 148276.24 | L10: =SUMIFS(COMPOSICIÓN!J$2:J$1892,COMPOSICIÓN!A$2:A$1892,A10,COMPOSICIÓN!B$2:B$1892,"EQ") -> 3836.7078 | M10: =J10 -> 12733.789 | N10: =IF(F10=0,0,K10/F10) -> 12893.586 | O10: =IF(F10=0,0,L10/F10) -> 333.62677 | P10: =M10+N10+O10 -> 25961.002 | Q10: =COUNTIF(COMPOSICIÓN!$A:$A,A10) -> 11 | R10: Desvío MO +2.5%. Desvío menor. Sin acción correctiva. | S10: APU | T10: 12733.789 | U10: 12574.566 | V10: 333.62677
A11: PIN-119 | B11: 119 | C11: PINTURA | D11: Bloque de Hormigon 19 x 19 x 39 | E11: m2 | F11: 11.5 | G11: 0 | H11: 0 | I11: 1 | J11: =SUMIFS(COMPOSICIÓN!J$2:J$1892,COMPOSICIÓN!A$2:A$1892,A11,COMPOSICIÓN!B$2:B$1892,"MAT") -> 18247.942 | K11: =SUMIFS(COMPOSICIÓN!J$2:J$1892,COMPOSICIÓN!A$2:A$1892,A11,COMPOSICIÓN!B$2:B$1892,"MO")*I11 -> 148276.24 | L11: =SUMIFS(COMPOSICIÓN!J$2:J$1892,COMPOSICIÓN!A$2:A$1892,A11,COMPOSICIÓN!B$2:B$1892,"EQ") -> 3836.7078 | M11: =J11 -> 18247.942 | N11: =IF(F11=0,0,K11/F11) -> 12893.586 | O11: =IF(F11=0,0,L11/F11) -> 333.62677 | P11: =M11+N11+O11 -> 31475.155 | Q11: =COUNTIF(COMPOSICIÓN!$A:$A,A11) -> 11 | R11: Desvío MO +2.5%. Desvío menor. Sin acción correctiva. | S11: APU | T11: 18247.942 | U11: 12574.566 | V11: 333.62677
A12: ELE-120 | B12: 120 | C12: INSTALACIÓN ELÉCTRICA | D12: BOCA ILUMINACIÓN | E12: m2 | F12: 3.25 | G12: 0 | H12: 0 | I12: 1 | J12: =SUMIFS(COMPOSICIÓN!J$2:J$1892,COMPOSICIÓN!A$2:A$1892,A12,COMPOSICIÓN!B$2:B$1892,"MAT") -> 17610.205 | K12: =SUMIFS(COMPOSICIÓN!J$2:J$1892,COMPOSICIÓN!A$2:A$1892,A12,COMPOSICIÓN!B$2:B$1892,"MO")*I12 -> 161417.64 | L12: =SUMIFS(COMPOSICIÓN!J$2:J$1892,COMPOSICIÓN!A$2:A$1892,A12,COMPOSICIÓN!B$2:B$1892,"EQ") -> 5889.636 | M12: =J12 -> 17610.205 | N12: =IF(F12=0,0,K12/F12) -> 49666.965 | O12: =IF(F12=0,0,L12/F12) -> 1812.1957 | P12: =M12+N12+O12 -> 69089.366 | Q12: =COUNTIF(COMPOSICIÓN!$A:$A,A12) -> 14 | S12: APU | T12: 17610.205 | U12: 49666.965 | V12: 1812.1957
A13: ELE-121 | B13: 121 | C13: INSTALACIÓN ELÉCTRICA | D13: BOCA TOMACORRIENTE | E13: m2 | F13: 3.25 | G13: 0 | H13: 0 | I13: 1 | J13: =SUMIFS(COMPOSICIÓN!J$2:J$1892,COMPOSICIÓN!A$2:A$1892,A13,COMPOSICIÓN!B$2:B$1892,"MAT") -> 15896.431 | K13: =SUMIFS(COMPOSICIÓN!J$2:J$1892,COMPOSICIÓN!A$2:A$1892,A13,COMPOSICIÓN!B$2:B$1892,"MO")*I13 -> 161417.64 | L13: =SUMIFS(COMPOSICIÓN!J$2:J$1892,COMPOSICIÓN!A$2:A$1892,A13,COMPOSICIÓN!B$2:B$1892,"EQ") -> 5889.636 | M13: =J13 -> 15896.431 | N13: =IF(F13=0,0,K13/F13) -> 49666.965 | O13: =IF(F13=0,0,L13/F13) -> 1812.1957 | P13: =M13+N13+O13 -> 67375.592 | Q13: =COUNTIF(COMPOSICIÓN!$A:$A,A13) -> 12 | S13: APU | T13: 15896.431 | U13: 49666.965 | V13: 1812.1957
A14: BAN-122 | B14: 122 | C14: Bandeja | D14: BANDEJA PORTACABLES 200 | E14: m2 | F14: 12 | G14: 0 | H14: 0 | I14: 1 | J14: =SUMIFS(COMPOSICIÓN!J$2:J$1892,COMPOSICIÓN!A$2:A$1892,A14,COMPOSICIÓN!B$2:B$1892,"MAT") -> 18848.235 | K14: =SUMIFS(COMPOSICIÓN!J$2:J$1892,COMPOSICIÓN!A$2:A$1892,A14,COMPOSICIÓN!B$2:B$1892,"MO")*I14 -> 134013.79 | L14: =SUMIFS(COMPOSICIÓN!J$2:J$1892,COMPOSICIÓN!A$2:A$1892,A14,COMPOSICIÓN!B$2:B$1892,"EQ") -> 0 | M14: =J14 -> 18848.235 | N14: =IF(F14=0,0,K14/F14) -> 11167.816 | O14: =IF(F14=0,0,L14/F14) -> 0 | P14: =M14+N14+O14 -> 30016.05 | Q14: =COUNTIF(COMPOSICIÓN!$A:$A,A14) -> 11 | R14: MO: MO-MOFA→MO-AYU02 (APU P-122 usa Ayudante Albañil $67,240, no Medio Oficial $72,132). cant=0.5925 para paridad con RESUMEN APU 06.25 ($11,167.82/ud). Hoja P-122 calcula $12,050.63 (cant=0.75×AYU02) — divergencia documentada. | S14: APU | T14: 18848.235 | U14: 11167.816 | V14: 0
A15: HHA-123 | B15: 123 | C15: ESTRUCTURA DE HORMIGÓN ARMADO | D15: COLUMNA HORMIGÓN RÚSTICO 85 kg/m3 | E15: m3 | F15: 12 | G15: 0 | H15: 0 | I15: 1 | J15: =SUMIFS(COMPOSICIÓN!J$2:J$1892,COMPOSICIÓN!A$2:A$1892,A15,COMPOSICIÓN!B$2:B$1892,"MAT") -> 1.1 | K15: =SUMIFS(COMPOSICIÓN!J$2:J$1892,COMPOSICIÓN!A$2:A$1892,A15,COMPOSICIÓN!B$2:B$1892,"MO")*I15 -> 148276.24 | L15: =SUMIFS(COMPOSICIÓN!J$2:J$1892,COMPOSICIÓN!A$2:A$1892,A15,COMPOSICIÓN!B$2:B$1892,"EQ") -> 0 | M15: =J15 -> 1.1 | N15: =IF(F15=0,0,K15/F15) -> 12356.353 | O15: =IF(F15=0,0,L15/F15) -> 0 | P15: =M15+N15+O15 -> 12357.453 | Q15: =COUNTIF(COMPOSICIÓN!$A:$A,A15) -> 3 | R15: REVISAR — P-XX sin Unitario Materiales legible. Sin corrección pendiente. Chat 5. | S15: APU
A16: HHA-124 | B16: 124 | C16: ESTRUCTURA DE HORMIGÓN ARMADO | D16: COLUMNA HORMIGÓN VISTO | E16: m3 | F16: 12 | G16: 0 | H16: 0 | I16: 1 | J16: =SUMIFS(COMPOSICIÓN!J$2:J$1892,COMPOSICIÓN!A$2:A$1892,A16,COMPOSICIÓN!B$2:B$1892,"MAT") -> 2.1 | K16: =SUMIFS(COMPOSICIÓN!J$2:J$1892,COMPOSICIÓN!A$2:A$1892,A16,COMPOSICIÓN!B$2:B$1892,"MO")*I16 -> 148276.24 | L16: =SUMIFS(COMPOSICIÓN!J$2:J$1892,COMPOSICIÓN!A$2:A$1892,A16,COMPOSICIÓN!B$2:B$1892,"EQ") -> 0 | M16: =J16 -> 2.1 | N16: =IF(F16=0,0,K16/F16) -> 12356.353 | O16: =IF(F16=0,0,L16/F16) -> 0 | P16: =M16+N16+O16 -> 12358.453 | Q16: =COUNTIF(COMPOSICIÓN!$A:$A,A16) -> 4 | R16: REVISAR — P-XX sin Unitario Materiales legible. Sin corrección pendiente. Chat 5. | S16: APU
A17: CER-134 | B17: 134 | C17: CERÁMICOS | D17: Revoque grueso para interiores | E17: m2 | F17: 18 | G17: 0 | H17: 0 | I17: 1 | J17: =SUMIFS(COMPOSICIÓN!J$2:J$1892,COMPOSICIÓN!A$2:A$1892,A17,COMPOSICIÓN!B$2:B$1892,"MAT") -> 1553.2761 | K17: =SUMIFS(COMPOSICIÓN!J$2:J$1892,COMPOSICIÓN!A$2:A$1892,A17,COMPOSICIÓN!B$2:B$1892,"MO")*I17 -> 144607.51 | L17: =SUMIFS(COMPOSICIÓN!J$2:J$1892,COMPOSICIÓN!A$2:A$1892,A17,COMPOSICIÓN!B$2:B$1892,"EQ") -> 3106.6818 | M17: =J17 -> 1553.2761 | N17: =IF(F17=0,0,K17/F17) -> 8033.7507 | O17: =IF(F17=0,0,L17/F17) -> 172.59343 | P17: =M17+N17+O17 -> 9759.6202 | Q17: =COUNTIF(COMPOSICIÓN!$A:$A,A17) -> 8 | R17: EQ: EQ-TROMPO cant=0. APU P-134 lo incluye pero RESUMEN APU lo omitió; GDR tomó valor del RESUMEN ($172.59). Bug del RESUMEN APU — paridad preservada. | S17: APU | T17: 1553.2761 | U17: 8033.7507 | V17: 172.59343
A18: CER-135 | B18: 135 | C18: CERÁMICOS | D18: Revoque fino a la cal | E18: m2 | F18: 9 | G18: 0 | H18: 0 | I18: 1 | J18: =SUMIFS(COMPOSICIÓN!J$2:J$1892,COMPOSICIÓN!A$2:A$1892,A18,COMPOSICIÓN!B$2:B$1892,"MAT") -> 1337.9415 | K18: =SUMIFS(COMPOSICIÓN!J$2:J$1892,COMPOSICIÓN!A$2:A$1892,A18,COMPOSICIÓN!B$2:B$1892,"MO")*I18 -> 134521.44 | L18: =SUMIFS(COMPOSICIÓN!J$2:J$1892,COMPOSICIÓN!A$2:A$1892,A18,COMPOSICIÓN!B$2:B$1892,"EQ") -> 4147.1132 | M18: =J18 -> 1337.9415 | N18: =IF(F18=0,0,K18/F18) -> 14946.826 | O18: =IF(F18=0,0,L18/F18) -> 460.79036 | P18: =M18+N18+O18 -> 16745.558 | Q18: =COUNTIF(COMPOSICIÓN!$A:$A,A18) -> 8 | S18: APU | T18: 1337.9415 | U18: 14946.826 | V18: 460.79036
A19: CER-136 | B19: 136 | C19: CERÁMICOS | D19: Carpeta cal reforzada (e: 1,5 cm) | E19: m2 | F19: 14.5 | G19: 0 | H19: 0 | I19: 1 | J19: =SUMIFS(COMPOSICIÓN!J$2:J$1892,COMPOSICIÓN!A$2:A$1892,A19,COMPOSICIÓN!B$2:B$1892,"MAT") -> 2755.4985 | K19: =SUMIFS(COMPOSICIÓN!J$2:J$1892,COMPOSICIÓN!A$2:A$1892,A19,COMPOSICIÓN!B$2:B$1892,"MO")*I19 -> 124435.36 | L19: =SUMIFS(COMPOSICIÓN!J$2:J$1892,COMPOSICIÓN!A$2:A$1892,A19,COMPOSICIÓN!B$2:B$1892,"EQ") -> 3526.3024 | M19: =J19 -> 2755.4985 | N19: =IF(F19=0,0,K19/F19) -> 8581.7491 | O19: =IF(F19=0,0,L19/F19) -> 243.19327 | P19: =M19+N19+O19 -> 11580.441 | Q19: =COUNTIF(COMPOSICIÓN!$A:$A,A19) -> 7 | S19: APU | T19: 2755.4985 | U19: 8581.7491 | V19: 243.19327
A20: CER-137 | B20: 137 | C20: CERÁMICOS | D20: Látex interior para paredes (enduido parcial) | E20: m2 | F20: 20 | G20: 0 | H20: 0 | I20: 1 | J20: =SUMIFS(COMPOSICIÓN!J$2:J$1892,COMPOSICIÓN!A$2:A$1892,A20,COMPOSICIÓN!B$2:B$1892,"MAT") -> 2880.1573 | K20: =SUMIFS(COMPOSICIÓN!J$2:J$1892,COMPOSICIÓN!A$2:A$1892,A20,COMPOSICIÓN!B$2:B$1892,"MO")*I20 -> 94177.138 | L20: =SUMIFS(COMPOSICIÓN!J$2:J$1892,COMPOSICIÓN!A$2:A$1892,A20,COMPOSICIÓN!B$2:B$1892,"EQ") -> 2091.05 | M20: =J20 -> 2880.1573 | N20: =IF(F20=0,0,K20/F20) -> 4708.8569 | O20: =IF(F20=0,0,L20/F20) -> 104.5525 | P20: =M20+N20+O20 -> 7693.5667 | Q20: =COUNTIF(COMPOSICIÓN!$A:$A,A20) -> 14 | R20: EQ: EQ-EQUIPI ok. EQ-ESCPINT cant=1 agregado (fila nueva). MAT +0.24% residual: redondeo float APU $4251.394 vs GDR $4251.40. | S20: APU | T20: 2880.1573 | U20: 4708.8569 | V20: 104.5525
A21: PIN-146 | B21: 146 | C21: PINTURA | D21: Látex interior para paredes (s/enduido) | E21: m2 | F21: 25 | G21: 0 | H21: 0 | I21: 1 | J21: =SUMIFS(COMPOSICIÓN!J$2:J$1892,COMPOSICIÓN!A$2:A$1892,A21,COMPOSICIÓN!B$2:B$1892,"MAT") -> 2664.568 | K21: =SUMIFS(COMPOSICIÓN!J$2:J$1892,COMPOSICIÓN!A$2:A$1892,A21,COMPOSICIÓN!B$2:B$1892,"MO")*I21 -> 94177.138 | L21: =SUMIFS(COMPOSICIÓN!J$2:J$1892,COMPOSICIÓN!A$2:A$1892,A21,COMPOSICIÓN!B$2:B$1892,"EQ") -> 2091.05 | M21: =J21 -> 2664.568 | N21: =IF(F21=0,0,K21/F21) -> 3767.0855 | O21: =IF(F21=0,0,L21/F21) -> 83.641998 | P21: =M21+N21+O21 -> 6515.2955 | Q21: =COUNTIF(COMPOSICIÓN!$A:$A,A21) -> 11 | R21: EQ: EQ-EQUIPI ok. EQ-ESCPINT cant=1 agregado (fila nueva). | S21: APU | T21: 2664.568 | U21: 3767.0855 | V21: 83.641998
A22: PRE-032 | B22: 32 | C22: MOVIMIENTO DE TIERRA | D22: Movimiento de suelos para bases c/ aporte de tosca (e: 40 cm en 2 capas de 20 cm) | E22: m3 | F22: 25 | G22: 0 | H22: 0 | I22: 1 | J22: =SUMIFS(COMPOSICIÓN!J$2:J$1892,COMPOSICIÓN!A$2:A$1892,A22,COMPOSICIÓN!B$2:B$1892,"MAT") -> 12754.673 | K22: =SUMIFS(COMPOSICIÓN!J$2:J$1892,COMPOSICIÓN!A$2:A$1892,A22,COMPOSICIÓN!B$2:B$1892,"MO")*I22 -> 166309.28 | L22: =SUMIFS(COMPOSICIÓN!J$2:J$1892,COMPOSICIÓN!A$2:A$1892,A22,COMPOSICIÓN!B$2:B$1892,"EQ") -> 1005000 | M22: =J22 -> 12754.673 | N22: =IF(F22=0,0,K22/F22) -> 6652.371 | O22: =IF(F22=0,0,L22/F22) -> 40200 | P22: =M22+N22+O22 -> 59607.044 | Q22: =COUNTIF(COMPOSICIÓN!$A:$A,A22) -> 4 | R22: EQ: EQ-PTO087 vida corregida 1año(360d)→1día; APU P-32 usa alquiler diario dep=1 → $1,005,000/día. EQ/ud=$40,200. | S22: APU | T22: 12754.673 | U22: 6652.371 | V22: 40200
A23: ALB-033 | B23: 33 | C23: MAMPOSTERÍA | D23: Ladrillo común 12,5 x 5,5 x 25 (e:15 cm) | E23: m2 | F23: 7 | G23: 0 | H23: 0 | I23: 1 | J23: =SUMIFS(COMPOSICIÓN!J$2:J$1892,COMPOSICIÓN!A$2:A$1892,A23,COMPOSICIÓN!B$2:B$1892,"MAT") -> 14000.877 | K23: =SUMIFS(COMPOSICIÓN!J$2:J$1892,COMPOSICIÓN!A$2:A$1892,A23,COMPOSICIÓN!B$2:B$1892,"MO")*I23 -> 161417.64 | L23: =SUMIFS(COMPOSICIÓN!J$2:J$1892,COMPOSICIÓN!A$2:A$1892,A23,COMPOSICIÓN!B$2:B$1892,"EQ") -> 3836.7078 | M23: =J23 -> 14000.877 | N23: =IF(F23=0,0,K23/F23) -> 23059.662 | O23: =IF(F23=0,0,L23/F23) -> 548.10112 | P23: =M23+N23+O23 -> 37608.641 | Q23: =COUNTIF(COMPOSICIÓN!$A:$A,A23) -> 11 | S23: APU | T23: 14000.877 | U23: 23059.662 | V23: 548.10112
A24: ALB-034 | B24: 34 | C24: MAMPOSTERÍA | D24: Ladrillo cerámico 8 x 18 x 33 cm | E24: m2 | F24: 15 | G24: 0 | H24: 0 | I24: 1 | J24: =SUMIFS(COMPOSICIÓN!J$2:J$1892,COMPOSICIÓN!A$2:A$1892,A24,COMPOSICIÓN!B$2:B$1892,"MAT") -> 10053.788 | K24: =SUMIFS(COMPOSICIÓN!J$2:J$1892,COMPOSICIÓN!A$2:A$1892,A24,COMPOSICIÓN!B$2:B$1892,"MO")*I24 -> 161417.64 | L24: =SUMIFS(COMPOSICIÓN!J$2:J$1892,COMPOSICIÓN!A$2:A$1892,A24,COMPOSICIÓN!B$2:B$1892,"EQ") -> 3836.7078 | M24: =J24 -> 10053.788 | N24: =IF(F24=0,0,K24/F24) -> 10761.176 | O24: =IF(F24=0,0,L24/F24) -> 255.78052 | P24: =M24+N24+O24 -> 21070.744 | Q24: =COUNTIF(COMPOSICIÓN!$A:$A,A24) -> 11 | S24: APU | T24: 10053.788 | U24: 10761.176 | V24: 255.78052
A25: ALB-035 | B25: 35 | C25: MAMPOSTERÍA | D25: Ladrillo cerámico 12 x 18 x 33 cm | E25: m2 | F25: 15 | G25: 0 | H25: 0 | I25: 1 | J25: =SUMIFS(COMPOSICIÓN!J$2:J$1892,COMPOSICIÓN!A$2:A$1892,A25,COMPOSICIÓN!B$2:B$1892,"MAT") -> 12465.038 | K25: =SUMIFS(COMPOSICIÓN!J$2:J$1892,COMPOSICIÓN!A$2:A$1892,A25,COMPOSICIÓN!B$2:B$1892,"MO")*I25 -> 161417.64 | L25: =SUMIFS(COMPOSICIÓN!J$2:J$1892,COMPOSICIÓN!A$2:A$1892,A25,COMPOSICIÓN!B$2:B$1892,"EQ") -> 3836.7078 | M25: =J25 -> 12465.038 | N25: =IF(F25=0,0,K25/F25) -> 10761.176 | O25: =IF(F25=0,0,L25/F25) -> 255.78052 | P25: =M25+N25+O25 -> 23481.994 | Q25: =COUNTIF(COMPOSICIÓN!$A:$A,A25) -> 10 | S25: APU | T25: 12465.038 | U25: 10761.176 | V25: 255.78052
A26: ALB-036 | B26: 36 | C26: MAMPOSTERÍA | D26: Ladrillo cerámico 18 x 18 x 33 cm | E26: m2 | F26: 15 | G26: 0 | H26: 0 | I26: 1 | J26: =SUMIFS(COMPOSICIÓN!J$2:J$1892,COMPOSICIÓN!A$2:A$1892,A26,COMPOSICIÓN!B$2:B$1892,"MAT") -> 17538.995 | K26: =SUMIFS(COMPOSICIÓN!J$2:J$1892,COMPOSICIÓN!A$2:A$1892,A26,COMPOSICIÓN!B$2:B$1892,"MO")*I26 -> 161417.64 | L26: =SUMIFS(COMPOSICIÓN!J$2:J$1892,COMPOSICIÓN!A$2:A$1892,A26,COMPOSICIÓN!B$2:B$1892,"EQ") -> 3836.7078 | M26: =J26 -> 17538.995 | N26: =IF(F26=0,0,K26/F26) -> 10761.176 | O26: =IF(F26=0,0,L26/F26) -> 255.78052 | P26: =M26+N26+O26 -> 28555.952 | Q26: =COUNTIF(COMPOSICIÓN!$A:$A,A26) -> 11 | S26: APU | T26: 17538.995 | U26: 10761.176 | V26: 255.78052
A27: ALB-037 | B27: 37 | C27: MAMPOSTERÍA | D27: Pared DOBLE Comun / 5 / LHC 08 - (ladrillo a la vista) | E27: m2 | F27: 4 | G27: 0 | H27: 0 | I27: 1 | J27: =SUMIFS(COMPOSICIÓN!J$2:J$1892,COMPOSICIÓN!A$2:A$1892,A27,COMPOSICIÓN!B$2:B$1892,"MAT") -> 31798.204 | K27: =SUMIFS(COMPOSICIÓN!J$2:J$1892,COMPOSICIÓN!A$2:A$1892,A27,COMPOSICIÓN!B$2:B$1892,"MO")*I27 -> 155365.99 | L27: =SUMIFS(COMPOSICIÓN!J$2:J$1892,COMPOSICIÓN!A$2:A$1892,A27,COMPOSICIÓN!B$2:B$1892,"EQ") -> 3836.7078 | M27: =J27 -> 31798.204 | N27: =IF(F27=0,0,K27/F27) -> 38841.498 | O27: =IF(F27=0,0,L27/F27) -> 959.17696 | P27: =M27+N27+O27 -> 71598.879 | Q27: =COUNTIF(COMPOSICIÓN!$A:$A,A27) -> 16 | S27: APU | T27: 31798.204 | U27: 38841.498 | V27: 959.17696
A28: ALB-038 | B28: 38 | C28: MAMPOSTERÍA | D28: Ladrillo hueco portante 12 x 19 x 33 | E28: m2 | F28: 15 | G28: 0 | H28: 0 | I28: 1 | J28: =SUMIFS(COMPOSICIÓN!J$2:J$1892,COMPOSICIÓN!A$2:A$1892,A28,COMPOSICIÓN!B$2:B$1892,"MAT") -> 18207.26 | K28: =SUMIFS(COMPOSICIÓN!J$2:J$1892,COMPOSICIÓN!A$2:A$1892,A28,COMPOSICIÓN!B$2:B$1892,"MO")*I28 -> 161417.64 | L28: =SUMIFS(COMPOSICIÓN!J$2:J$1892,COMPOSICIÓN!A$2:A$1892,A28,COMPOSICIÓN!B$2:B$1892,"EQ") -> 3836.7078 | M28: =J28 -> 18207.26 | N28: =IF(F28=0,0,K28/F28) -> 10761.176 | O28: =IF(F28=0,0,L28/F28) -> 255.78052 | P28: =M28+N28+O28 -> 29224.217 | Q28: =COUNTIF(COMPOSICIÓN!$A:$A,A28) -> 11 | S28: APU | T28: 18207.26 | U28: 10761.176 | V28: 255.78052
A29: ALB-039 | B29: 39 | C29: MAMPOSTERÍA | D29: Amure puertas tipo (0,90 x 2,00 m) | E29: u | F29: 2 | G29: 0 | H29: 0 | I29: 1 | J29: =SUMIFS(COMPOSICIÓN!J$2:J$1892,COMPOSICIÓN!A$2:A$1892,A29,COMPOSICIÓN!B$2:B$1892,"MAT") -> 4104.3832 | K29: =SUMIFS(COMPOSICIÓN!J$2:J$1892,COMPOSICIÓN!A$2:A$1892,A29,COMPOSICIÓN!B$2:B$1892,"MO")*I29 -> 121063.23 | L29: =SUMIFS(COMPOSICIÓN!J$2:J$1892,COMPOSICIÓN!A$2:A$1892,A29,COMPOSICIÓN!B$2:B$1892,"EQ") -> 881.57561 | M29: =J29 -> 4104.3832 | N29: =IF(F29=0,0,K29/F29) -> 60531.614 | O29: =IF(F29=0,0,L29/F29) -> 440.78781 | P29: =M29+N29+O29 -> 65076.785 | Q29: =COUNTIF(COMPOSICIÓN!$A:$A,A29) -> 6 | S29: APU | T29: 4104.3832 | U29: 60531.614 | V29: 440.78781
A30: ALB-040 | B30: 40 | C30: MAMPOSTERÍA | D30: Amure Premarcos | E30: u | F30: 4 | G30: 0 | H30: 0 | I30: 1 | J30: =SUMIFS(COMPOSICIÓN!J$2:J$1892,COMPOSICIÓN!A$2:A$1892,A30,COMPOSICIÓN!B$2:B$1892,"MAT") -> 1501.8311 | K30: =SUMIFS(COMPOSICIÓN!J$2:J$1892,COMPOSICIÓN!A$2:A$1892,A30,COMPOSICIÓN!B$2:B$1892,"MO")*I30 -> 161417.64 | L30: =SUMIFS(COMPOSICIÓN!J$2:J$1892,COMPOSICIÓN!A$2:A$1892,A30,COMPOSICIÓN!B$2:B$1892,"EQ") -> 881.57561 | M30: =J30 -> 1501.8311 | N30: =IF(F30=0,0,K30/F30) -> 40354.409 | O30: =IF(F30=0,0,L30/F30) -> 220.3939 | P30: =M30+N30+O30 -> 42076.634 | Q30: =COUNTIF(COMPOSICIÓN!$A:$A,A30) -> 6 | S30: APU | T30: 1501.8311 | U30: 40354.409 | V30: 220.3939
A31: ALB-041 | B31: 41 | C31: MAMPOSTERÍA | D31: Amure barandas (insertos c/1,00 m) | E31: ml | F31: 5 | G31: 0 | H31: 0 | I31: 1 | J31: =SUMIFS(COMPOSICIÓN!J$2:J$1892,COMPOSICIÓN!A$2:A$1892,A31,COMPOSICIÓN!B$2:B$1892,"MAT") -> 310.90706 | K31: =SUMIFS(COMPOSICIÓN!J$2:J$1892,COMPOSICIÓN!A$2:A$1892,A31,COMPOSICIÓN!B$2:B$1892,"MO")*I31 -> 161417.64 | L31: =SUMIFS(COMPOSICIÓN!J$2:J$1892,COMPOSICIÓN!A$2:A$1892,A31,COMPOSICIÓN!B$2:B$1892,"EQ") -> 1503.0434 | M31: =J31 -> 310.90706 | N31: =IF(F31=0,0,K31/F31) -> 32283.527 | O31: =IF(F31=0,0,L31/F31) -> 300.60867 | P31: =M31+N31+O31 -> 32895.043 | Q31: =COUNTIF(COMPOSICIÓN!$A:$A,A31) -> 7 | R31: EQ: EQ-EQUIP04 reemplazado por EQ-EQALBA (misma tarifa, vida útil 3 años vs 1 año en catálogo). EQ-EQUIP04 eliminado del catálogo EQUIPOS. | S31: APU | T31: 310.90703 | U31: 32283.527 | V31: 300.60867
A32: IMP-042 | B32: 42 | C32: IMPERMEABILIZACIONES Y AISLACIONES | D32: Azotado hidrófugo | E32: m2 | F32: 28 | G32: 0 | H32: 0 | I32: 1 | J32: =SUMIFS(COMPOSICIÓN!J$2:J$1892,COMPOSICIÓN!A$2:A$1892,A32,COMPOSICIÓN!B$2:B$1892,"MAT") -> 827.27861 | K32: =SUMIFS(COMPOSICIÓN!J$2:J$1892,COMPOSICIÓN!A$2:A$1892,A32,COMPOSICIÓN!B$2:B$1892,"MO")*I32 -> 121073.34 | L32: =SUMIFS(COMPOSICIÓN!J$2:J$1892,COMPOSICIÓN!A$2:A$1892,A32,COMPOSICIÓN!B$2:B$1892,"EQ") -> 3836.7078 | M32: =J32 -> 827.27861 | N32: =IF(F32=0,0,K32/F32) -> 4324.0478 | O32: =IF(F32=0,0,L32/F32) -> 137.02528 | P32: =M32+N32+O32 -> 5288.3517 | Q32: =COUNTIF(COMPOSICIÓN!$A:$A,A32) -> 8 | S32: APU | T32: 827.27861 | U32: 4324.0478 | V32: 137.02528
A33: REV-043 | B33: 43 | C33: REVOQUES | D33: Interior jaharro a la cal + Enlucido a la cal | E33: m2 | F33: 6 | G33: 0 | H33: 0 | I33: 1 | J33: =SUMIFS(COMPOSICIÓN!J$2:J$1892,COMPOSICIÓN!A$2:A$1892,A33,COMPOSICIÓN!B$2:B$1892,"MAT") -> 2891.2175 | K33: =SUMIFS(COMPOSICIÓN!J$2:J$1892,COMPOSICIÓN!A$2:A$1892,A33,COMPOSICIÓN!B$2:B$1892,"MO")*I33 -> 137883.46 | L33: =SUMIFS(COMPOSICIÓN!J$2:J$1892,COMPOSICIÓN!A$2:A$1892,A33,COMPOSICIÓN!B$2:B$1892,"EQ") -> 3836.7078 | M33: =J33 -> 2891.2175 | N33: =IF(F33=0,0,K33/F33) -> 22980.577 | O33: =IF(F33=0,0,L33/F33) -> 639.45131 | P33: =M33+N33+O33 -> 26511.246 | Q33: =COUNTIF(COMPOSICIÓN!$A:$A,A33) -> 9 | S33: APU | T33: 2891.2175 | U33: 22980.577 | V33: 639.45131
A34: REV-044 | B34: 44 | C34: REVOQUES | D34: Revoque Grueso impermeable Exterior hasta 3.00 m - Incl. Azotado hidrófugo | E34: m2 | F34: 11.5 | G34: 0 | H34: 0 | I34: 1 | J34: =SUMIFS(COMPOSICIÓN!J$2:J$1892,COMPOSICIÓN!A$2:A$1892,A34,COMPOSICIÓN!B$2:B$1892,"MAT") -> 4061.1651 | K34: =SUMIFS(COMPOSICIÓN!J$2:J$1892,COMPOSICIÓN!A$2:A$1892,A34,COMPOSICIÓN!B$2:B$1892,"MO")*I34 -> 134521.44 | L34: =SUMIFS(COMPOSICIÓN!J$2:J$1892,COMPOSICIÓN!A$2:A$1892,A34,COMPOSICIÓN!B$2:B$1892,"EQ") -> 3836.7078 | M34: =J34 -> 4061.1651 | N34: =IF(F34=0,0,K34/F34) -> 11697.516 | O34: =IF(F34=0,0,L34/F34) -> 333.62677 | P34: =M34+N34+O34 -> 16092.308 | Q34: =COUNTIF(COMPOSICIÓN!$A:$A,A34) -> 9 | S34: APU | T34: 4061.1651 | U34: 11697.516 | V34: 333.62677
A35: REV-045 | B35: 45 | C35: REVOQUES | D35: Revoque Grueso impermeable Exterior a mas de 3.00 m - Incl. Azotado hidrófugo | E35: m2 | F35: 8 | G35: 0 | H35: 0 | I35: 1 | J35: =SUMIFS(COMPOSICIÓN!J$2:J$1892,COMPOSICIÓN!A$2:A$1892,A35,COMPOSICIÓN!B$2:B$1892,"MAT") -> 4061.1651 | K35: =SUMIFS(COMPOSICIÓN!J$2:J$1892,COMPOSICIÓN!A$2:A$1892,A35,COMPOSICIÓN!B$2:B$1892,"MO")*I35 -> 134521.44 | L35: =SUMIFS(COMPOSICIÓN!J$2:J$1892,COMPOSICIÓN!A$2:A$1892,A35,COMPOSICIÓN!B$2:B$1892,"EQ") -> 6906.9024 | M35: =J35 -> 4061.1651 | N35: =IF(F35=0,0,K35/F35) -> 16815.18 | O35: =IF(F35=0,0,L35/F35) -> 863.36281 | P35: =M35+N35+O35 -> 21739.708 | Q35: =COUNTIF(COMPOSICIÓN!$A:$A,A35) -> 10 | S35: APU | T35: 4061.1651 | U35: 16815.18 | V35: 863.36281
A36: REV-046 | B36: 46 | C36: REVOQUES | D36: Contrapiso HHRP | E36: m3 | F36: 1.4 | G36: 0 | H36: 0 | I36: 1 | J36: =SUMIFS(COMPOSICIÓN!J$2:J$1892,COMPOSICIÓN!A$2:A$1892,A36,COMPOSICIÓN!B$2:B$1892,"MAT") -> 67976.634 | K36: =SUMIFS(COMPOSICIÓN!J$2:J$1892,COMPOSICIÓN!A$2:A$1892,A36,COMPOSICIÓN!B$2:B$1892,"MO")*I36 -> 137873.35 | L36: =SUMIFS(COMPOSICIÓN!J$2:J$1892,COMPOSICIÓN!A$2:A$1892,A36,COMPOSICIÓN!B$2:B$1892,"EQ") -> 3526.3024 | M36: =J36 -> 67976.634 | N36: =IF(F36=0,0,K36/F36) -> 98480.966 | O36: =IF(F36=0,0,L36/F36) -> 2518.7875 | P36: =M36+N36+O36 -> 168976.39 | Q36: =COUNTIF(COMPOSICIÓN!$A:$A,A36) -> 8 | S36: APU | T36: 67976.634 | U36: 98480.966 | V36: 2518.7875
A37: REV-047 | B37: 47 | C37: REVOQUES | D37: Carpeta MC 1:3 (e: 2cm) | E37: m2 | F37: 15 | G37: 0 | H37: 0 | I37: 1 | J37: =SUMIFS(COMPOSICIÓN!J$2:J$1892,COMPOSICIÓN!A$2:A$1892,A37,COMPOSICIÓN!B$2:B$1892,"MAT") -> 3420.3193 | K37: =SUMIFS(COMPOSICIÓN!J$2:J$1892,COMPOSICIÓN!A$2:A$1892,A37,COMPOSICIÓN!B$2:B$1892,"MO")*I37 -> 124435.36 | L37: =SUMIFS(COMPOSICIÓN!J$2:J$1892,COMPOSICIÓN!A$2:A$1892,A37,COMPOSICIÓN!B$2:B$1892,"EQ") -> 3526.3024 | M37: =J37 -> 3420.3193 | N37: =IF(F37=0,0,K37/F37) -> 8295.6908 | O37: =IF(F37=0,0,L37/F37) -> 235.08683 | P37: =M37+N37+O37 -> 11951.097 | Q37: =COUNTIF(COMPOSICIÓN!$A:$A,A37) -> 6 | S37: APU | T37: 3420.3193 | U37: 8295.6908 | V37: 235.08683
A38: REV-048 | B38: 48 | C38: REVOQUES | D38: Carpeta monolítico h = 7 cm | E38: m2 | F38: 35 | G38: 0 | H38: 0 | I38: 1 | J38: =SUMIFS(COMPOSICIÓN!J$2:J$1892,COMPOSICIÓN!A$2:A$1892,A38,COMPOSICIÓN!B$2:B$1892,"MAT") -> 6717.8752 | K38: =SUMIFS(COMPOSICIÓN!J$2:J$1892,COMPOSICIÓN!A$2:A$1892,A38,COMPOSICIÓN!B$2:B$1892,"MO")*I38 -> 390075.77 | L38: =SUMIFS(COMPOSICIÓN!J$2:J$1892,COMPOSICIÓN!A$2:A$1892,A38,COMPOSICIÓN!B$2:B$1892,"EQ") -> 4566.7339 | M38: =J38 -> 6717.8752 | N38: =IF(F38=0,0,K38/F38) -> 11145.022 | O38: =IF(F38=0,0,L38/F38) -> 130.47811 | P38: =M38+N38+O38 -> 17993.375 | Q38: =COUNTIF(COMPOSICIÓN!$A:$A,A38) -> 8 | S38: APU | T38: 6717.8752 | U38: 11145.022 | V38: 130.47811
A39: REV-049 | B39: 49 | C39: REVOQUES | D39: Carpeta hidrófuga (e: 2 cm) | E39: m2 | F39: 15 | G39: 0 | H39: 0 | I39: 1 | J39: =SUMIFS(COMPOSICIÓN!J$2:J$1892,COMPOSICIÓN!A$2:A$1892,A39,COMPOSICIÓN!B$2:B$1892,"MAT") -> 4136.3931 | K39: =SUMIFS(COMPOSICIÓN!J$2:J$1892,COMPOSICIÓN!A$2:A$1892,A39,COMPOSICIÓN!B$2:B$1892,"MO")*I39 -> 124435.36 | L39: =SUMIFS(COMPOSICIÓN!J$2:J$1892,COMPOSICIÓN!A$2:A$1892,A39,COMPOSICIÓN!B$2:B$1892,"EQ") -> 3526.3024 | M39: =J39 -> 4136.3931 | N39: =IF(F39=0,0,K39/F39) -> 8295.6908 | O39: =IF(F39=0,0,L39/F39) -> 235.08683 | P39: =M39+N39+O39 -> 12667.171 | Q39: =COUNTIF(COMPOSICIÓN!$A:$A,A39) -> 7 | S39: APU | T39: 4136.3931 | U39: 8295.6908 | V39: 235.08683
A40: CON-050 | B40: 50 | C40: CONTRAPISOS | D40: Cemento alisado o cilindrado (e: 3 cm) | E40: m2 | F40: 11.5 | G40: 0 | H40: 0 | I40: 1 | J40: =SUMIFS(COMPOSICIÓN!J$2:J$1892,COMPOSICIÓN!A$2:A$1892,A40,COMPOSICIÓN!B$2:B$1892,"MAT") -> 4104.3832 | K40: =SUMIFS(COMPOSICIÓN!J$2:J$1892,COMPOSICIÓN!A$2:A$1892,A40,COMPOSICIÓN!B$2:B$1892,"MO")*I40 -> 127797.39 | L40: =SUMIFS(COMPOSICIÓN!J$2:J$1892,COMPOSICIÓN!A$2:A$1892,A40,COMPOSICIÓN!B$2:B$1892,"EQ") -> 3526.3024 | M40: =J40 -> 4104.3832 | N40: =IF(F40=0,0,K40/F40) -> 11112.816 | O40: =IF(F40=0,0,L40/F40) -> 306.635 | P40: =M40+N40+O40 -> 15523.834 | Q40: =COUNTIF(COMPOSICIÓN!$A:$A,A40) -> 6 | S40: APU | T40: 4104.3832 | U40: 11112.816 | V40: 306.635
A41: CON-051 | B41: 51 | C41: CONTRAPISOS | D41: Látex interior para paredes (incl. enduido) | E41: m2 | F41: 22 | G41: 0 | H41: 0 | I41: 1 | J41: =SUMIFS(COMPOSICIÓN!J$2:J$1892,COMPOSICIÓN!A$2:A$1892,A41,COMPOSICIÓN!B$2:B$1892,"MAT") -> 4251.3982 | K41: =SUMIFS(COMPOSICIÓN!J$2:J$1892,COMPOSICIÓN!A$2:A$1892,A41,COMPOSICIÓN!B$2:B$1892,"MO")*I41 -> 184342.31 | L41: =SUMIFS(COMPOSICIÓN!J$2:J$1892,COMPOSICIÓN!A$2:A$1892,A41,COMPOSICIÓN!B$2:B$1892,"EQ") -> 4182.0999 | M41: =J41 -> 4251.3982 | N41: =IF(F41=0,0,K41/F41) -> 8379.1959 | O41: =IF(F41=0,0,L41/F41) -> 190.09545 | P41: =M41+N41+O41 -> 12820.69 | Q41: =COUNTIF(COMPOSICIÓN!$A:$A,A41) -> 14 | R41: EQ: EQ-EQUIPI cant=2 ok. EQ-ESCPINT cant=2 agregado. MAT: OTR-PINT014 cant corregida 0.005→0.004; MAT-CONS consolidada cant=142.84 (rodillo+pincel+cartón). | S41: APU | T41: 4251.3982 | U41: 8379.1959 | V41: 190.09545
A42: CON-052 | B42: 52 | C42: CONTRAPISOS | D42: látex para cielorrasos (incl. enduido) | E42: m2 | F42: 17.5 | G42: 0 | H42: 0 | I42: 1 | J42: =SUMIFS(COMPOSICIÓN!J$2:J$1892,COMPOSICIÓN!A$2:A$1892,A42,COMPOSICIÓN!B$2:B$1892,"MAT") -> 4251.3982 | K42: =SUMIFS(COMPOSICIÓN!J$2:J$1892,COMPOSICIÓN!A$2:A$1892,A42,COMPOSICIÓN!B$2:B$1892,"MO")*I42 -> 166309.28 | L42: =SUMIFS(COMPOSICIÓN!J$2:J$1892,COMPOSICIÓN!A$2:A$1892,A42,COMPOSICIÓN!B$2:B$1892,"EQ") -> 4585.2571 | M42: =J42 -> 4251.3982 | N42: =IF(F42=0,0,K42/F42) -> 9503.3872 | O42: =IF(F42=0,0,L42/F42) -> 262.01469 | P42: =M42+N42+O42 -> 14016.8 | Q42: =COUNTIF(COMPOSICIÓN!$A:$A,A42) -> 15 | R42: EQ: EQ-ESCPINT cant=1 agregado. MAT: MAT-CONS consolidada cant=142.84 (rodillo+pincel+cartón). | S42: APU | T42: 4251.3982 | U42: 9503.3872 | V42: 262.01469
A43: CON-053 | B43: 53 | C43: CONTRAPISOS | D43: látex exterior para paredes hasta 3.00 m de altura | E43: m2 | F43: 15.5 | G43: 0 | H43: 0 | I43: 1 | J43: =SUMIFS(COMPOSICIÓN!J$2:J$1892,COMPOSICIÓN!A$2:A$1892,A43,COMPOSICIÓN!B$2:B$1892,"MAT") -> 2901.8567 | K43: =SUMIFS(COMPOSICIÓN!J$2:J$1892,COMPOSICIÓN!A$2:A$1892,A43,COMPOSICIÓN!B$2:B$1892,"MO")*I43 -> 94177.138 | L43: =SUMIFS(COMPOSICIÓN!J$2:J$1892,COMPOSICIÓN!A$2:A$1892,A43,COMPOSICIÓN!B$2:B$1892,"EQ") -> 2091.05 | M43: =J43 -> 2901.8567 | N43: =IF(F43=0,0,K43/F43) -> 6075.9444 | O43: =IF(F43=0,0,L43/F43) -> 134.90645 | P43: =M43+N43+O43 -> 9112.7075 | Q43: =COUNTIF(COMPOSICIÓN!$A:$A,A43) -> 11 | S43: APU | T43: 2901.8567 | U43: 6075.9444 | V43: 134.90645
A44: CON-053B | B44: 53 | C44: CONTRAPISOS | D44: látex exterior para paredes a más 3.00 m de altura | E44: m2 | F44: 15.5 | G44: 0 | H44: 0 | I44: 1 | J44: =SUMIFS(COMPOSICIÓN!J$2:J$1892,COMPOSICIÓN!A$2:A$1892,A44,COMPOSICIÓN!B$2:B$1892,"MAT") -> 2901.8567 | K44: =SUMIFS(COMPOSICIÓN!J$2:J$1892,COMPOSICIÓN!A$2:A$1892,A44,COMPOSICIÓN!B$2:B$1892,"MO")*I44 -> 94177.138 | L44: =SUMIFS(COMPOSICIÓN!J$2:J$1892,COMPOSICIÓN!A$2:A$1892,A44,COMPOSICIÓN!B$2:B$1892,"EQ") -> 3884.3377 | M44: =J44 -> 2901.8567 | N44: =IF(F44=0,0,K44/F44) -> 6075.9444 | O44: =IF(F44=0,0,L44/F44) -> 250.60244 | P44: =M44+N44+O44 -> 9228.4035 | Q44: =COUNTIF(COMPOSICIÓN!$A:$A,A44) -> 13 | R44: GDR_EQ congelado divergente vs APU P-53bis ($134.91 vs $254.81). EQ correcto según P-53bis. No corregir GDR. | S44: APU | T44: 2901.8567 | U44: 6075.9444 | V44: 134.90645
A45: CON-054 | B45: 54 | C45: CONTRAPISOS | D45: Esmalte sintético sobre carpintería metálica , herrería (cuando es vacio x lleno contemplar MAT al 6 | E45: m2 | F45: 8 | G45: 0 | H45: 0 | I45: 1 | J45: =SUMIFS(COMPOSICIÓN!J$2:J$1892,COMPOSICIÓN!A$2:A$1892,A45,COMPOSICIÓN!B$2:B$1892,"MAT") -> 4461.163 | K45: =SUMIFS(COMPOSICIÓN!J$2:J$1892,COMPOSICIÓN!A$2:A$1892,A45,COMPOSICIÓN!B$2:B$1892,"MO")*I45 -> 94177.138 | L45: =SUMIFS(COMPOSICIÓN!J$2:J$1892,COMPOSICIÓN!A$2:A$1892,A45,COMPOSICIÓN!B$2:B$1892,"EQ") -> 2091.05 | M45: =J45 -> 4461.163 | N45: =IF(F45=0,0,K45/F45) -> 11772.142 | O45: =IF(F45=0,0,L45/F45) -> 261.38124 | P45: =M45+N45+O45 -> 16494.687 | Q45: =COUNTIF(COMPOSICIÓN!$A:$A,A45) -> 11 | R45: EQ: EQ-ESCPINT→EQ-ESCPINT ok. MAT: MAT-CONS consolidada cant=199.85 (rodillo+pincel+cartón APU P-54). | S45: APU | T45: 4460.7312 | U45: 11772.142 | V45: 261.38124
A46: PIR-055 | B46: 55 | C46: PISOS | D46: Revestimiento plastico texturado tipo Quimtex fino | E46: m2 | F46: 20 | G46: 0 | H46: 0 | I46: 1 | J46: =SUMIFS(COMPOSICIÓN!J$2:J$1892,COMPOSICIÓN!A$2:A$1892,A46,COMPOSICIÓN!B$2:B$1892,"MAT") -> 6910.6245 | K46: =SUMIFS(COMPOSICIÓN!J$2:J$1892,COMPOSICIÓN!A$2:A$1892,A46,COMPOSICIÓN!B$2:B$1892,"MO")*I46 -> 249463.91 | L46: =SUMIFS(COMPOSICIÓN!J$2:J$1892,COMPOSICIÓN!A$2:A$1892,A46,COMPOSICIÓN!B$2:B$1892,"EQ") -> 3949.6111 | M46: =J46 -> 6910.6245 | N46: =IF(F46=0,0,K46/F46) -> 12473.196 | O46: =IF(F46=0,0,L46/F46) -> 197.48055 | P46: =M46+N46+O46 -> 19581.301 | Q46: =COUNTIF(COMPOSICIÓN!$A:$A,A46) -> 13 | R46: EQ: EQ-*ESCALE1→EQ-ESCPINT (escalera madera pintor $217.65, APU P-55). | S46: APU | T46: 6929.178 | U46: 12350.905 | V46: 197.48055
A47: PIR-056 | B47: 56 | C47: PISOS | D47: Colocación porcelanato en pisos (no incluye baños) | E47: m2 | F47: 13 | G47: 0 | H47: 0 | I47: 1 | J47: =SUMIFS(COMPOSICIÓN!J$2:J$1892,COMPOSICIÓN!A$2:A$1892,A47,COMPOSICIÓN!B$2:B$1892,"MAT") -> 6932.2708 | K47: =SUMIFS(COMPOSICIÓN!J$2:J$1892,COMPOSICIÓN!A$2:A$1892,A47,COMPOSICIÓN!B$2:B$1892,"MO")*I47 -> 166309.28 | L47: =SUMIFS(COMPOSICIÓN!J$2:J$1892,COMPOSICIÓN!A$2:A$1892,A47,COMPOSICIÓN!B$2:B$1892,"EQ") -> 3190.6447 | M47: =J47 -> 6932.2708 | N47: =IF(F47=0,0,K47/F47) -> 12793.021 | O47: =IF(F47=0,0,L47/F47) -> 245.43421 | P47: =M47+N47+O47 -> 19970.726 | Q47: =COUNTIF(COMPOSICIÓN!$A:$A,A47) -> 9 | R47: EQ: EQ-EQCERA ok. EQ-CORTA cant=1 agregado (fila nueva). | S47: APU | T47: 6932.2708 | U47: 12793.021 | V47: 245.43421
A48: PIR-057 | B48: 57 | C48: PISOS | D48: Revestimiento porcelanato en paredes y piso baños | E48: m2 | F48: 10 | G48: 0 | H48: 0 | I48: 1 | J48: =SUMIFS(COMPOSICIÓN!J$2:J$1892,COMPOSICIÓN!A$2:A$1892,A48,COMPOSICIÓN!B$2:B$1892,"MAT") -> 6932.2708 | K48: =SUMIFS(COMPOSICIÓN!J$2:J$1892,COMPOSICIÓN!A$2:A$1892,A48,COMPOSICIÓN!B$2:B$1892,"MO")*I48 -> 166309.28 | L48: =SUMIFS(COMPOSICIÓN!J$2:J$1892,COMPOSICIÓN!A$2:A$1892,A48,COMPOSICIÓN!B$2:B$1892,"EQ") -> 3190.6447 | M48: =J48 -> 6932.2708 | N48: =IF(F48=0,0,K48/F48) -> 16630.928 | O48: =IF(F48=0,0,L48/F48) -> 319.06447 | P48: =M48+N48+O48 -> 23882.263 | Q48: =COUNTIF(COMPOSICIÓN!$A:$A,A48) -> 9 | S48: APU | T48: 6932.2708 | U48: 16630.928 | V48: 319.06447
A49: CER-058 | B49: 58 | C49: CERÁMICOS | D49: Colocacion de zocalo porcelanato | E49: ml | F49: 30 | G49: 0 | H49: 0 | I49: 1 | J49: =SUMIFS(COMPOSICIÓN!J$2:J$1892,COMPOSICIÓN!A$2:A$1892,A49,COMPOSICIÓN!B$2:B$1892,"MAT") -> 1001.4972 | K49: =SUMIFS(COMPOSICIÓN!J$2:J$1892,COMPOSICIÓN!A$2:A$1892,A49,COMPOSICIÓN!B$2:B$1892,"MO")*I49 -> 166309.28 | L49: =SUMIFS(COMPOSICIÓN!J$2:J$1892,COMPOSICIÓN!A$2:A$1892,A49,COMPOSICIÓN!B$2:B$1892,"EQ") -> 3190.6447 | M49: =J49 -> 1001.4972 | N49: =IF(F49=0,0,K49/F49) -> 5543.6425 | O49: =IF(F49=0,0,L49/F49) -> 106.35482 | P49: =M49+N49+O49 -> 6651.4946 | Q49: =COUNTIF(COMPOSICIÓN!$A:$A,A49) -> 8 | R49: EQ: EQ-EQCERA ok. EQ-CORTA cant=1 agregado (fila nueva). | S49: APU | T49: 1001.4972 | U49: 5543.6425 | V49: 106.35482
A50: CER-059 | B50: 59 | C50: CERÁMICOS | D50: Látex interior satinado para paredes | E50: m2 | F50: 11 | G50: 0 | H50: 0 | I50: 1 | J50: =SUMIFS(COMPOSICIÓN!J$2:J$1892,COMPOSICIÓN!A$2:A$1892,A50,COMPOSICIÓN!B$2:B$1892,"MAT") -> 6691.9788 | K50: =SUMIFS(COMPOSICIÓN!J$2:J$1892,COMPOSICIÓN!A$2:A$1892,A50,COMPOSICIÓN!B$2:B$1892,"MO")*I50 -> 166309.28 | L50: =SUMIFS(COMPOSICIÓN!J$2:J$1892,COMPOSICIÓN!A$2:A$1892,A50,COMPOSICIÓN!B$2:B$1892,"EQ") -> 3964.4463 | M50: =J50 -> 6691.9788 | N50: =IF(F50=0,0,K50/F50) -> 15119.025 | O50: =IF(F50=0,0,L50/F50) -> 360.40421 | P50: =M50+N50+O50 -> 22171.408 | Q50: =COUNTIF(COMPOSICIÓN!$A:$A,A50) -> 14 | R50: EQ: EQ-*ESCALE1→EQ-ESCPINT (escalera madera pintor $217.65, APU P-59). | S50: APU | T50: 6691.9788 | U50: 15119.025 | V50: 360.40421
A51: CER-060 | B51: 60 | C51: CERÁMICOS | D51: Cielorraso Durlock - Junta Tomada STD | E51: m2 | F51: 9.5 | G51: 0 | H51: 0 | I51: 1 | J51: =SUMIFS(COMPOSICIÓN!J$2:J$1892,COMPOSICIÓN!A$2:A$1892,A51,COMPOSICIÓN!B$2:B$1892,"MAT") -> 10666.377 | K51: =SUMIFS(COMPOSICIÓN!J$2:J$1892,COMPOSICIÓN!A$2:A$1892,A51,COMPOSICIÓN!B$2:B$1892,"MO")*I51 -> 166309.28 | L51: =SUMIFS(COMPOSICIÓN!J$2:J$1892,COMPOSICIÓN!A$2:A$1892,A51,COMPOSICIÓN!B$2:B$1892,"EQ") -> 2723.1402 | M51: =J51 -> 10666.377 | N51: =IF(F51=0,0,K51/F51) -> 17506.24 | O51: =IF(F51=0,0,L51/F51) -> 286.64634 | P51: =M51+N51+O51 -> 28459.263 | Q51: =COUNTIF(COMPOSICIÓN!$A:$A,A51) -> 12 | S51: APU | T51: 10667.045 | U51: 17506.24 | V51: 286.64634
A52: CER-061 | B52: 61 | C52: CERÁMICOS | D52: Cielorraso Durlock - Junta Tomada RH | E52: m2 | F52: 9.5 | G52: 0 | H52: 0 | I52: 1 | J52: =SUMIFS(COMPOSICIÓN!J$2:J$1892,COMPOSICIÓN!A$2:A$1892,A52,COMPOSICIÓN!B$2:B$1892,"MAT") -> 14748.067 | K52: =SUMIFS(COMPOSICIÓN!J$2:J$1892,COMPOSICIÓN!A$2:A$1892,A52,COMPOSICIÓN!B$2:B$1892,"MO")*I52 -> 166309.28 | L52: =SUMIFS(COMPOSICIÓN!J$2:J$1892,COMPOSICIÓN!A$2:A$1892,A52,COMPOSICIÓN!B$2:B$1892,"EQ") -> 2723.1402 | M52: =J52 -> 14748.067 | N52: =IF(F52=0,0,K52/F52) -> 17506.24 | O52: =IF(F52=0,0,L52/F52) -> 286.64634 | P52: =M52+N52+O52 -> 32540.953 | Q52: =COUNTIF(COMPOSICIÓN!$A:$A,A52) -> 12 | S52: APU | T52: 14748.7 | U52: 17506.24 | V52: 286.64634
A53: CER-062 | B53: 62 | C53: CERÁMICOS | D53: Cielorraso Durlock - Junta Tomada RF | E53: m2 | F53: 9.5 | G53: 0 | H53: 0 | I53: 1 | J53: =SUMIFS(COMPOSICIÓN!J$2:J$1892,COMPOSICIÓN!A$2:A$1892,A53,COMPOSICIÓN!B$2:B$1892,"MAT") -> 13947.236 | K53: =SUMIFS(COMPOSICIÓN!J$2:J$1892,COMPOSICIÓN!A$2:A$1892,A53,COMPOSICIÓN!B$2:B$1892,"MO")*I53 -> 166309.28 | L53: =SUMIFS(COMPOSICIÓN!J$2:J$1892,COMPOSICIÓN!A$2:A$1892,A53,COMPOSICIÓN!B$2:B$1892,"EQ") -> 2723.1402 | M53: =J53 -> 13947.236 | N53: =IF(F53=0,0,K53/F53) -> 17506.24 | O53: =IF(F53=0,0,L53/F53) -> 286.64634 | P53: =M53+N53+O53 -> 31740.122 | Q53: =COUNTIF(COMPOSICIÓN!$A:$A,A53) -> 12 | S53: APU | T53: 13947.896 | U53: 17506.24 | V53: 286.64634
A54: CER-063 | B54: 63 | C54: CERÁMICOS | D54: Cielorraso Desmontable 60x60 - sin provision | E54: m2 | F54: 10 | G54: 0 | H54: 0 | I54: 1 | J54: =SUMIFS(COMPOSICIÓN!J$2:J$1892,COMPOSICIÓN!A$2:A$1892,A54,COMPOSICIÓN!B$2:B$1892,"MAT") -> 6636.1994 | K54: =SUMIFS(COMPOSICIÓN!J$2:J$1892,COMPOSICIÓN!A$2:A$1892,A54,COMPOSICIÓN!B$2:B$1892,"MO")*I54 -> 166309.28 | L54: =SUMIFS(COMPOSICIÓN!J$2:J$1892,COMPOSICIÓN!A$2:A$1892,A54,COMPOSICIÓN!B$2:B$1892,"EQ") -> 2723.1402 | M54: =J54 -> 6636.1994 | N54: =IF(F54=0,0,K54/F54) -> 16630.928 | O54: =IF(F54=0,0,L54/F54) -> 272.31402 | P54: =M54+N54+O54 -> 23539.441 | Q54: =COUNTIF(COMPOSICIÓN!$A:$A,A54) -> 9 | S54: APU | T54: 6636.1994 | U54: 16630.928 | V54: 272.31402
A55: CER-063B | B55: 63 | C55: CERÁMICOS | D55: Cielorraso Desmontable 60x60 - incluye placa Deco Vinyl | E55: m2 | F55: 10 | G55: 0 | H55: 0 | I55: 1 | J55: =SUMIFS(COMPOSICIÓN!J$2:J$1892,COMPOSICIÓN!A$2:A$1892,A55,COMPOSICIÓN!B$2:B$1892,"MAT") -> 6636.1994 | K55: =SUMIFS(COMPOSICIÓN!J$2:J$1892,COMPOSICIÓN!A$2:A$1892,A55,COMPOSICIÓN!B$2:B$1892,"MO")*I55 -> 166309.28 | L55: =SUMIFS(COMPOSICIÓN!J$2:J$1892,COMPOSICIÓN!A$2:A$1892,A55,COMPOSICIÓN!B$2:B$1892,"EQ") -> 2723.1402 | M55: =J55 -> 6636.1994 | N55: =IF(F55=0,0,K55/F55) -> 16630.928 | O55: =IF(F55=0,0,L55/F55) -> 272.31402 | P55: =M55+N55+O55 -> 23539.441 | Q55: =COUNTIF(COMPOSICIÓN!$A:$A,A55) -> 9 | R55: MAT: REV-TRAV122→REV-TRAV060 (Travesaño 0.60m $793, APU P-63). REV-DECOVINYL60 eliminado (no en APU). desp corregido 10%→5% en LARG366, TRAV060, FIJ8, ALAMB14. | S55: APU | T55: 6636.1994 | U55: 16630.928 | V55: 272.31402
A56: CER-064 | B56: 64 | C56: CERÁMICOS | D56: Pared Durlock - Simple | E56: m2 | F56: 7 | G56: 0 | H56: 0 | I56: 1 | J56: =SUMIFS(COMPOSICIÓN!J$2:J$1892,COMPOSICIÓN!A$2:A$1892,A56,COMPOSICIÓN!B$2:B$1892,"MAT") -> 16393.634 | K56: =SUMIFS(COMPOSICIÓN!J$2:J$1892,COMPOSICIÓN!A$2:A$1892,A56,COMPOSICIÓN!B$2:B$1892,"MO")*I56 -> 166309.28 | L56: =SUMIFS(COMPOSICIÓN!J$2:J$1892,COMPOSICIÓN!A$2:A$1892,A56,COMPOSICIÓN!B$2:B$1892,"EQ") -> 2646.9501 | M56: =J56 -> 16393.634 | N56: =IF(F56=0,0,K56/F56) -> 23758.468 | O56: =IF(F56=0,0,L56/F56) -> 378.13572 | P56: =M56+N56+O56 -> 40530.238 | Q56: =COUNTIF(COMPOSICIÓN!$A:$A,A56) -> 13 | S56: APU | T56: 16393.937 | U56: 23758.468 | V56: 378.13572
A57: DRY-065 | B57: 65 | C57: DURLOCK | D57: Pared Durlock - Doble placa STD ambas caras y asilación lana de vidrio | E57: m2 | F57: 6 | G57: 0 | H57: 0 | I57: 1 | J57: =SUMIFS(COMPOSICIÓN!J$2:J$1892,COMPOSICIÓN!A$2:A$1892,A57,COMPOSICIÓN!B$2:B$1892,"MAT") -> 28944.117 | K57: =SUMIFS(COMPOSICIÓN!J$2:J$1892,COMPOSICIÓN!A$2:A$1892,A57,COMPOSICIÓN!B$2:B$1892,"MO")*I57 -> 166309.28 | L57: =SUMIFS(COMPOSICIÓN!J$2:J$1892,COMPOSICIÓN!A$2:A$1892,A57,COMPOSICIÓN!B$2:B$1892,"EQ") -> 2646.9501 | M57: =J57 -> 28944.117 | N57: =IF(F57=0,0,K57/F57) -> 27718.213 | O57: =IF(F57=0,0,L57/F57) -> 441.15834 | P57: =M57+N57+O57 -> 57103.488 | Q57: =COUNTIF(COMPOSICIÓN!$A:$A,A57) -> 14 | S57: APU | T57: 28944.105 | U57: 27718.213 | V57: 441.15834
A58: DRY-066 | B58: 66 | C58: DURLOCK | D58: Medio tabique espesor total 8,5 cm | E58: m2 | F58: 11 | G58: 0 | H58: 0 | I58: 1 | J58: =SUMIFS(COMPOSICIÓN!J$2:J$1892,COMPOSICIÓN!A$2:A$1892,A58,COMPOSICIÓN!B$2:B$1892,"MAT") -> 11506.657 | K58: =SUMIFS(COMPOSICIÓN!J$2:J$1892,COMPOSICIÓN!A$2:A$1892,A58,COMPOSICIÓN!B$2:B$1892,"MO")*I58 -> 166309.28 | L58: =SUMIFS(COMPOSICIÓN!J$2:J$1892,COMPOSICIÓN!A$2:A$1892,A58,COMPOSICIÓN!B$2:B$1892,"EQ") -> 2646.9501 | M58: =J58 -> 11506.657 | N58: =IF(F58=0,0,K58/F58) -> 15119.025 | O58: =IF(F58=0,0,L58/F58) -> 240.63182 | P58: =M58+N58+O58 -> 26866.314 | Q58: =COUNTIF(COMPOSICIÓN!$A:$A,A58) -> 12 | R58: GDR_EQ divergente vs APU P-66 ($441.16 vs $240.63). Composición correcta según APU. Chat 7+. | S58: APU | T58: 11507.597 | U58: 15119.025 | V58: 441.15834
A59: DRY-067 | B59: 67 | C59: DURLOCK | D59: Esmalte sintetico para paredes | E59: m2 | F59: 20 | G59: 0 | H59: 0 | I59: 1 | J59: =SUMIFS(COMPOSICIÓN!J$2:J$1892,COMPOSICIÓN!A$2:A$1892,A59,COMPOSICIÓN!B$2:B$1892,"MAT") -> 4981.3709 | K59: =SUMIFS(COMPOSICIÓN!J$2:J$1892,COMPOSICIÓN!A$2:A$1892,A59,COMPOSICIÓN!B$2:B$1892,"MO")*I59 -> 166309.28 | L59: =SUMIFS(COMPOSICIÓN!J$2:J$1892,COMPOSICIÓN!A$2:A$1892,A59,COMPOSICIÓN!B$2:B$1892,"EQ") -> 2091.05 | M59: =J59 -> 4981.3709 | N59: =IF(F59=0,0,K59/F59) -> 8315.4638 | O59: =IF(F59=0,0,L59/F59) -> 104.5525 | P59: =M59+N59+O59 -> 13401.387 | Q59: =COUNTIF(COMPOSICIÓN!$A:$A,A59) -> 13 | R59: EQ: EQ-*ESCALE1→EQ-ESCPINT. | S59: APU | T59: 4981.3709 | U59: 8315.4638 | V59: 104.5525
A60: DRY-068 | B60: 68 | C60: DURLOCK | D60: Ladrillo Klimablock 27 x 19 x 30 cm | E60: m2 | F60: 15 | G60: 0 | H60: 0 | I60: 1 | J60: =SUMIFS(COMPOSICIÓN!J$2:J$1892,COMPOSICIÓN!A$2:A$1892,A60,COMPOSICIÓN!B$2:B$1892,"MAT") -> 3751.4788 | K60: =SUMIFS(COMPOSICIÓN!J$2:J$1892,COMPOSICIÓN!A$2:A$1892,A60,COMPOSICIÓN!B$2:B$1892,"MO")*I60 -> 161417.64 | L60: =SUMIFS(COMPOSICIÓN!J$2:J$1892,COMPOSICIÓN!A$2:A$1892,A60,COMPOSICIÓN!B$2:B$1892,"EQ") -> 3836.7078 | M60: =J60 -> 3751.4788 | N60: =IF(F60=0,0,K60/F60) -> 10761.176 | O60: =IF(F60=0,0,L60/F60) -> 255.78052 | P60: =M60+N60+O60 -> 14768.435 | Q60: =COUNTIF(COMPOSICIÓN!$A:$A,A60) -> 10 | S60: APU | T60: 3751.4788 | U60: 10761.176 | V60: 255.78052
A61: IMP-070 | B61: 70 | C61: IMPERMEABILIZACIONES Y AISLACIONES | D61: Impermeabilización de cubierta transitable sobre carpeta horizontal con membrana Geotextil de 4mm, a | E61: m2 | F61: 25 | G61: 0 | H61: 0 | I61: 1 | J61: =SUMIFS(COMPOSICIÓN!J$2:J$1892,COMPOSICIÓN!A$2:A$1892,A61,COMPOSICIÓN!B$2:B$1892,"MAT") -> 8716.8274 | K61: =SUMIFS(COMPOSICIÓN!J$2:J$1892,COMPOSICIÓN!A$2:A$1892,A61,COMPOSICIÓN!B$2:B$1892,"MO")*I61 -> 161417.64 | L61: =SUMIFS(COMPOSICIÓN!J$2:J$1892,COMPOSICIÓN!A$2:A$1892,A61,COMPOSICIÓN!B$2:B$1892,"EQ") -> 874.41131 | M61: =J61 -> 8716.8274 | N61: =IF(F61=0,0,K61/F61) -> 6456.7055 | O61: =IF(F61=0,0,L61/F61) -> 34.976452 | P61: =M61+N61+O61 -> 15208.509 | Q61: =COUNTIF(COMPOSICIÓN!$A:$A,A61) -> 11 | S61: APU | T61: 8716.8187 | U61: 6456.7055 | V61: 34.976452
A62: CUB-071 | B62: 71 | C62: CUBIERTAS | D62: Impermeabilización de cubierta con Malla no tejida de poliester y pintura poliuretánica | E62: m2 | F62: 50 | G62: 0 | H62: 0 | I62: 1 | J62: =SUMIFS(COMPOSICIÓN!J$2:J$1892,COMPOSICIÓN!A$2:A$1892,A62,COMPOSICIÓN!B$2:B$1892,"MAT") -> 8765.0843 | K62: =SUMIFS(COMPOSICIÓN!J$2:J$1892,COMPOSICIÓN!A$2:A$1892,A62,COMPOSICIÓN!B$2:B$1892,"MO")*I62 -> 161417.64 | L62: =SUMIFS(COMPOSICIÓN!J$2:J$1892,COMPOSICIÓN!A$2:A$1892,A62,COMPOSICIÓN!B$2:B$1892,"EQ") -> 2025.7766 | M62: =J62 -> 8765.0843 | N62: =IF(F62=0,0,K62/F62) -> 3228.3527 | O62: =IF(F62=0,0,L62/F62) -> 40.515533 | P62: =M62+N62+O62 -> 12033.953 | Q62: =COUNTIF(COMPOSICIÓN!$A:$A,A62) -> 10 | R62: EQ: EQ-KITPIN→EQ-EQUIPI (APU P-71 usa *KITPINT=vida 2a/720d=$1873.40, no vida 1a). MAT: rodillo+pincel+trapo (filas sin código APU) consolidados en MAT-CONS cant=126.45. | S62: APU | T62: 8638.6331 | U62: 3228.3527 | V62: 40.515533
A63: AIS-072 | B63: 72 | C63: AISLACIONES | D63: Revoque Exterior 3 en 1 hasta 3,00 m | E63: m2 | F63: 35 | G63: 0 | H63: 0 | I63: 1 | J63: =SUMIFS(COMPOSICIÓN!J$2:J$1892,COMPOSICIÓN!A$2:A$1892,A63,COMPOSICIÓN!B$2:B$1892,"MAT") -> 13018.852 | K63: =SUMIFS(COMPOSICIÓN!J$2:J$1892,COMPOSICIÓN!A$2:A$1892,A63,COMPOSICIÓN!B$2:B$1892,"MO")*I63 -> 267170.02 | L63: =SUMIFS(COMPOSICIÓN!J$2:J$1892,COMPOSICIÓN!A$2:A$1892,A63,COMPOSICIÓN!B$2:B$1892,"EQ") -> 44106.682 | M63: =J63 -> 13018.852 | N63: =IF(F63=0,0,K63/F63) -> 7633.4293 | O63: =IF(F63=0,0,L63/F63) -> 1260.1909 | P63: =M63+N63+O63 -> 21912.472 | Q63: =COUNTIF(COMPOSICIÓN!$A:$A,A63) -> 8 | R63: EQ: EQ-REVOC vida corregida 1año(360d)→30días; APU P-72 usa alquiler mensual $1,230,000/mes dep=1/30 → $41,000/día. | S63: APU | T63: 13018.852 | U63: 7633.4293 | V63: 1260.1909
A64: AIS-073 | B64: 73 | C64: AISLACIONES | D64: Pintura sobre pared existente | E64: m2 | F64: 20 | G64: 0 | H64: 0 | I64: 1 | J64: =SUMIFS(COMPOSICIÓN!J$2:J$1892,COMPOSICIÓN!A$2:A$1892,A64,COMPOSICIÓN!B$2:B$1892,"MAT") -> 2616.1485 | K64: =SUMIFS(COMPOSICIÓN!J$2:J$1892,COMPOSICIÓN!A$2:A$1892,A64,COMPOSICIÓN!B$2:B$1892,"MO")*I64 -> 94177.138 | L64: =SUMIFS(COMPOSICIÓN!J$2:J$1892,COMPOSICIÓN!A$2:A$1892,A64,COMPOSICIÓN!B$2:B$1892,"EQ") -> 2091.05 | M64: =J64 -> 2616.1485 | N64: =IF(F64=0,0,K64/F64) -> 4708.8569 | O64: =IF(F64=0,0,L64/F64) -> 104.5525 | P64: =M64+N64+O64 -> 7429.5579 | Q64: =COUNTIF(COMPOSICIÓN!$A:$A,A64) -> 10 | R64: EQ: EQ-*ESCALE1→EQ-ESCPINT. | S64: APU | T64: 2616.1485 | U64: 4708.8569 | V64: 104.5525
A65: AIS-075 | B65: 75 | C65: AISLACIONES | D65: Ladrillo hueco portante 18 x 19 x 33 | E65: m2 | F65: 15 | G65: 0 | H65: 0 | I65: 1 | J65: =SUMIFS(COMPOSICIÓN!J$2:J$1892,COMPOSICIÓN!A$2:A$1892,A65,COMPOSICIÓN!B$2:B$1892,"MAT") -> 22250.605 | K65: =SUMIFS(COMPOSICIÓN!J$2:J$1892,COMPOSICIÓN!A$2:A$1892,A65,COMPOSICIÓN!B$2:B$1892,"MO")*I65 -> 166309.28 | L65: =SUMIFS(COMPOSICIÓN!J$2:J$1892,COMPOSICIÓN!A$2:A$1892,A65,COMPOSICIÓN!B$2:B$1892,"EQ") -> 3836.7078 | M65: =J65 -> 22250.605 | N65: =IF(F65=0,0,K65/F65) -> 11087.285 | O65: =IF(F65=0,0,L65/F65) -> 255.78052 | P65: =M65+N65+O65 -> 33593.671 | Q65: =COUNTIF(COMPOSICIÓN!$A:$A,A65) -> 11 | S65: APU | T65: 22250.605 | U65: 11087.285 | V65: 255.78052
A66: PIN-080 | B66: 80 | C66: PINTURA | D66: Provision, preparacion y colocacion de acero de refuerzo en Vigas de Fundacion | E66: kgf | F66: 450 | G66: 0 | H66: 0 | I66: 1 | J66: =SUMIFS(COMPOSICIÓN!J$2:J$1892,COMPOSICIÓN!A$2:A$1892,A66,COMPOSICIÓN!B$2:B$1892,"MAT") -> 1639.3994 | K66: =SUMIFS(COMPOSICIÓN!J$2:J$1892,COMPOSICIÓN!A$2:A$1892,A66,COMPOSICIÓN!B$2:B$1892,"MO")*I66 -> 399859.05 | L66: =SUMIFS(COMPOSICIÓN!J$2:J$1892,COMPOSICIÓN!A$2:A$1892,A66,COMPOSICIÓN!B$2:B$1892,"EQ") -> 0 | M66: =J66 -> 1639.3994 | N66: =IF(F66=0,0,K66/F66) -> 888.57567 | O66: =IF(F66=0,0,L66/F66) -> 0 | P66: =M66+N66+O66 -> 2527.975 | Q66: =COUNTIF(COMPOSICIÓN!$A:$A,A66) -> 5 | S66: APU
A67: PIN-081 | B67: 81 | C67: PINTURA | D67: Provision, preparacion y colocacion de acero de refuerzo en Columnas | E67: kgf | F67: 380 | G67: 0 | H67: 0 | I67: 1 | J67: =SUMIFS(COMPOSICIÓN!J$2:J$1892,COMPOSICIÓN!A$2:A$1892,A67,COMPOSICIÓN!B$2:B$1892,"MAT") -> 1634.6031 | K67: =SUMIFS(COMPOSICIÓN!J$2:J$1892,COMPOSICIÓN!A$2:A$1892,A67,COMPOSICIÓN!B$2:B$1892,"MO")*I67 -> 399859.05 | L67: =SUMIFS(COMPOSICIÓN!J$2:J$1892,COMPOSICIÓN!A$2:A$1892,A67,COMPOSICIÓN!B$2:B$1892,"EQ") -> 0 | M67: =J67 -> 1634.6031 | N67: =IF(F67=0,0,K67/F67) -> 1052.2607 | O67: =IF(F67=0,0,L67/F67) -> 0 | P67: =M67+N67+O67 -> 2686.8637 | Q67: =COUNTIF(COMPOSICIÓN!$A:$A,A67) -> 5 | S67: APU
A68: PIN-082 | B68: 82 | C68: PINTURA | D68: Provision, preparacion y colocacion de acero de refuerzo en Vigas | E68: kgf | F68: 420 | G68: 0 | H68: 0 | I68: 1 | J68: =SUMIFS(COMPOSICIÓN!J$2:J$1892,COMPOSICIÓN!A$2:A$1892,A68,COMPOSICIÓN!B$2:B$1892,"MAT") -> 1641.5728 | K68: =SUMIFS(COMPOSICIÓN!J$2:J$1892,COMPOSICIÓN!A$2:A$1892,A68,COMPOSICIÓN!B$2:B$1892,"MO")*I68 -> 399859.05 | L68: =SUMIFS(COMPOSICIÓN!J$2:J$1892,COMPOSICIÓN!A$2:A$1892,A68,COMPOSICIÓN!B$2:B$1892,"EQ") -> 0 | M68: =J68 -> 1641.5728 | N68: =IF(F68=0,0,K68/F68) -> 952.04536 | O68: =IF(F68=0,0,L68/F68) -> 0 | P68: =M68+N68+O68 -> 2593.6181 | Q68: =COUNTIF(COMPOSICIÓN!$A:$A,A68) -> 5 | S68: APU
A69: PIN-083 | B69: 83 | C69: PINTURA | D69: Provision, preparacion y colocacion de acero de refuerzo en Losa (arm inf) | E69: kgf | F69: 400 | G69: 0 | H69: 0 | I69: 1 | J69: =SUMIFS(COMPOSICIÓN!J$2:J$1892,COMPOSICIÓN!A$2:A$1892,A69,COMPOSICIÓN!B$2:B$1892,"MAT") -> 1637.6056 | K69: =SUMIFS(COMPOSICIÓN!J$2:J$1892,COMPOSICIÓN!A$2:A$1892,A69,COMPOSICIÓN!B$2:B$1892,"MO")*I69 -> 399859.05 | L69: =SUMIFS(COMPOSICIÓN!J$2:J$1892,COMPOSICIÓN!A$2:A$1892,A69,COMPOSICIÓN!B$2:B$1892,"EQ") -> 0 | M69: =J69 -> 1637.6056 | N69: =IF(F69=0,0,K69/F69) -> 999.64763 | O69: =IF(F69=0,0,L69/F69) -> 0 | P69: =M69+N69+O69 -> 2637.2532 | Q69: =COUNTIF(COMPOSICIÓN!$A:$A,A69) -> 5 | S69: APU
A70: PIN-084 | B70: 84 | C70: PINTURA | D70: Provision y colocacion de malla de acero de refuerzo Q335 en Losas (arm sup) | E70: m2 | F70: 150 | G70: 0 | H70: 0 | I70: 1 | J70: =SUMIFS(COMPOSICIÓN!J$2:J$1892,COMPOSICIÓN!A$2:A$1892,A70,COMPOSICIÓN!B$2:B$1892,"MAT") -> 319.00329 | K70: =SUMIFS(COMPOSICIÓN!J$2:J$1892,COMPOSICIÓN!A$2:A$1892,A70,COMPOSICIÓN!B$2:B$1892,"MO")*I70 -> 426795.69 | L70: =SUMIFS(COMPOSICIÓN!J$2:J$1892,COMPOSICIÓN!A$2:A$1892,A70,COMPOSICIÓN!B$2:B$1892,"EQ") -> 0 | M70: =J70 -> 319.00329 | N70: =IF(F70=0,0,K70/F70) -> 2845.3046 | O70: =IF(F70=0,0,L70/F70) -> 0 | P70: =M70+N70+O70 -> 3164.3079 | Q70: =COUNTIF(COMPOSICIÓN!$A:$A,A70) -> 4 | S70: APU
A71: APU-005 | B71: 5 | C71: General | D71: Provision, preparacion y colocacion de acero de refuerzo en Escaleras | E71: kgf | F71: 400 | G71: 0 | H71: 0 | I71: 1 | J71: =SUMIFS(COMPOSICIÓN!J$2:J$1892,COMPOSICIÓN!A$2:A$1892,A71,COMPOSICIÓN!B$2:B$1892,"MAT") -> 1.6894704 | K71: =SUMIFS(COMPOSICIÓN!J$2:J$1892,COMPOSICIÓN!A$2:A$1892,A71,COMPOSICIÓN!B$2:B$1892,"MO")*I71 -> 399859.05 | L71: =SUMIFS(COMPOSICIÓN!J$2:J$1892,COMPOSICIÓN!A$2:A$1892,A71,COMPOSICIÓN!B$2:B$1892,"EQ") -> 0 | M71: =J71 -> 1.6894704 | N71: =IF(F71=0,0,K71/F71) -> 999.64763 | O71: =IF(F71=0,0,L71/F71) -> 0 | P71: =M71+N71+O71 -> 1001.3371 | Q71: =COUNTIF(COMPOSICIÓN!$A:$A,A71) -> 5 | S71: APU
A72: PIN-086 | B72: 86 | C72: PINTURA | D72: Provision, preparacion y colocacion de acero de refuerzo en Tabiques | E72: kgf | F72: 400 | G72: 0 | H72: 0 | I72: 1 | J72: =SUMIFS(COMPOSICIÓN!J$2:J$1892,COMPOSICIÓN!A$2:A$1892,A72,COMPOSICIÓN!B$2:B$1892,"MAT") -> 1637.0087 | K72: =SUMIFS(COMPOSICIÓN!J$2:J$1892,COMPOSICIÓN!A$2:A$1892,A72,COMPOSICIÓN!B$2:B$1892,"MO")*I72 -> 399859.05 | L72: =SUMIFS(COMPOSICIÓN!J$2:J$1892,COMPOSICIÓN!A$2:A$1892,A72,COMPOSICIÓN!B$2:B$1892,"EQ") -> 0 | M72: =J72 -> 1637.0087 | N72: =IF(F72=0,0,K72/F72) -> 999.64763 | O72: =IF(F72=0,0,L72/F72) -> 0 | P72: =M72+N72+O72 -> 2636.6563 | Q72: =COUNTIF(COMPOSICIÓN!$A:$A,A72) -> 5 | S72: APU
A73: ENC-087 | B73: 87 | C73: ENCOFRADO | D73: Encofrado de Madera - Acabado Normal en Vigas de Fundacion | E73: m2 | F73: 24 | G73: 0 | H73: 0 | I73: 1 | J73: =SUMIFS(COMPOSICIÓN!J$2:J$1892,COMPOSICIÓN!A$2:A$1892,A73,COMPOSICIÓN!B$2:B$1892,"MAT") -> 385.61186 | K73: =SUMIFS(COMPOSICIÓN!J$2:J$1892,COMPOSICIÓN!A$2:A$1892,A73,COMPOSICIÓN!B$2:B$1892,"MO")*I73 -> 166309.28 | L73: =SUMIFS(COMPOSICIÓN!J$2:J$1892,COMPOSICIÓN!A$2:A$1892,A73,COMPOSICIÓN!B$2:B$1892,"EQ") -> 0 | M73: =J73 -> 385.61186 | N73: =IF(F73=0,0,K73/F73) -> 6929.5532 | O73: =IF(F73=0,0,L73/F73) -> 0 | P73: =M73+N73+O73 -> 7315.165 | Q73: =COUNTIF(COMPOSICIÓN!$A:$A,A73) -> 4 | R73: REVISAR — P-XX sin Unitario Materiales legible. Sin corrección pendiente. Chat 5. | S73: APU
A74: ENC-088 | B74: 88 | C74: ENCOFRADO | D74: Encofrado de Madera - Acabado Normal en Losa | E74: m2 | F74: 28 | G74: 0 | H74: 0 | I74: 1 | J74: =SUMIFS(COMPOSICIÓN!J$2:J$1892,COMPOSICIÓN!A$2:A$1892,A74,COMPOSICIÓN!B$2:B$1892,"MAT") -> 7524.0024 | K74: =SUMIFS(COMPOSICIÓN!J$2:J$1892,COMPOSICIÓN!A$2:A$1892,A74,COMPOSICIÓN!B$2:B$1892,"MO")*I74 -> 233549.78 | L74: =SUMIFS(COMPOSICIÓN!J$2:J$1892,COMPOSICIÓN!A$2:A$1892,A74,COMPOSICIÓN!B$2:B$1892,"EQ") -> 0 | M74: =J74 -> 7524.0024 | N74: =IF(F74=0,0,K74/F74) -> 8341.0634 | O74: =IF(F74=0,0,L74/F74) -> 0 | P74: =M74+N74+O74 -> 15865.066 | Q74: =COUNTIF(COMPOSICIÓN!$A:$A,A74) -> 8 | R74: REVISAR — P-XX sin Unitario Materiales legible. Sin corrección pendiente. Chat 5. | S74: APU
A75: ENC-089 | B75: 89 | C75: ENCOFRADO | D75: Encofrado de Madera - Acabado Normal en Escalera | E75: m2 | F75: 25 | G75: 0 | H75: 0 | I75: 1 | J75: =SUMIFS(COMPOSICIÓN!J$2:J$1892,COMPOSICIÓN!A$2:A$1892,A75,COMPOSICIÓN!B$2:B$1892,"MAT") -> 7524.4778 | K75: =SUMIFS(COMPOSICIÓN!J$2:J$1892,COMPOSICIÓN!A$2:A$1892,A75,COMPOSICIÓN!B$2:B$1892,"MO")*I75 -> 233549.78 | L75: =SUMIFS(COMPOSICIÓN!J$2:J$1892,COMPOSICIÓN!A$2:A$1892,A75,COMPOSICIÓN!B$2:B$1892,"EQ") -> 0 | M75: =J75 -> 7524.4778 | N75: =IF(F75=0,0,K75/F75) -> 9341.991 | O75: =IF(F75=0,0,L75/F75) -> 0 | P75: =M75+N75+O75 -> 16866.469 | Q75: =COUNTIF(COMPOSICIÓN!$A:$A,A75) -> 8 | R75: REVISAR — P-XX sin Unitario Materiales legible. Sin corrección pendiente. Chat 5. | S75: APU
A76: ENC-090 | B76: 90 | C76: ENCOFRADO | D76: Encofrado de Madera - Acabado VISTO en Losas | E76: m2 | F76: 28 | G76: 0 | H76: 0 | I76: 1 | J76: =SUMIFS(COMPOSICIÓN!J$2:J$1892,COMPOSICIÓN!A$2:A$1892,A76,COMPOSICIÓN!B$2:B$1892,"MAT") -> 25808.122 | K76: =SUMIFS(COMPOSICIÓN!J$2:J$1892,COMPOSICIÓN!A$2:A$1892,A76,COMPOSICIÓN!B$2:B$1892,"MO")*I76 -> 233549.78 | L76: =SUMIFS(COMPOSICIÓN!J$2:J$1892,COMPOSICIÓN!A$2:A$1892,A76,COMPOSICIÓN!B$2:B$1892,"EQ") -> 0 | M76: =J76 -> 25808.122 | N76: =IF(F76=0,0,K76/F76) -> 8341.0634 | O76: =IF(F76=0,0,L76/F76) -> 0 | P76: =M76+N76+O76 -> 34149.185 | Q76: =COUNTIF(COMPOSICIÓN!$A:$A,A76) -> 8 | R76: REVISAR — P-XX sin Unitario Materiales legible. Sin corrección pendiente. Chat 5. | S76: APU
A77: ENC-091 | B77: 91 | C77: ENCOFRADO | D77: Encofrado de Madera - Acabado VISTO en Tabiques | E77: m2 | F77: 26 | G77: 0 | H77: 0 | I77: 1 | J77: =SUMIFS(COMPOSICIÓN!J$2:J$1892,COMPOSICIÓN!A$2:A$1892,A77,COMPOSICIÓN!B$2:B$1892,"MAT") -> 11226.809 | K77: =SUMIFS(COMPOSICIÓN!J$2:J$1892,COMPOSICIÓN!A$2:A$1892,A77,COMPOSICIÓN!B$2:B$1892,"MO")*I77 -> 233549.78 | L77: =SUMIFS(COMPOSICIÓN!J$2:J$1892,COMPOSICIÓN!A$2:A$1892,A77,COMPOSICIÓN!B$2:B$1892,"EQ") -> 0 | M77: =J77 -> 11226.809 | N77: =IF(F77=0,0,K77/F77) -> 8982.6837 | O77: =IF(F77=0,0,L77/F77) -> 0 | P77: =M77+N77+O77 -> 20209.493 | Q77: =COUNTIF(COMPOSICIÓN!$A:$A,A77) -> 8 | R77: REVISAR — P-XX sin Unitario Materiales legible. Sin corrección pendiente. Chat 5. | S77: APU
A78: PTO-0101 | C78: PRELIMINARES | D78: Limpieza y preparación del terreno - No cotiza | E78: gl | F78: 1 | G78: 0 | H78: 0 | I78: 1 | J78: =SUMIFS(COMPOSICIÓN!J$2:J$1892,COMPOSICIÓN!A$2:A$1892,A78,COMPOSICIÓN!B$2:B$1892,"MAT") -> 0 | K78: =SUMIFS(COMPOSICIÓN!J$2:J$1892,COMPOSICIÓN!A$2:A$1892,A78,COMPOSICIÓN!B$2:B$1892,"MO")*I78 -> 0 | L78: =SUMIFS(COMPOSICIÓN!J$2:J$1892,COMPOSICIÓN!A$2:A$1892,A78,COMPOSICIÓN!B$2:B$1892,"EQ") -> 0 | M78: =J78 -> 0 | N78: =IF(F78=0,0,K78/F78) -> 0 | O78: =IF(F78=0,0,L78/F78) -> 0 | P78: =M78+N78+O78 -> 0 | Q78: =COUNTIF(COMPOSICIÓN!$A:$A,A78) -> 0 | S78: lump_directo | T78: 0 | U78: 0 | V78: 0
A79: PTO-0102 | C79: PRELIMINARES | D79: Topógrafo - Visita de obra replanteo | E79: un | F79: 1 | G79: 0 | H79: 0 | I79: 1 | J79: =SUMIFS(COMPOSICIÓN!J$2:J$1892,COMPOSICIÓN!A$2:A$1892,A79,COMPOSICIÓN!B$2:B$1892,"MAT") -> 25000 | K79: =SUMIFS(COMPOSICIÓN!J$2:J$1892,COMPOSICIÓN!A$2:A$1892,A79,COMPOSICIÓN!B$2:B$1892,"MO")*I79 -> 281634.56 | L79: =SUMIFS(COMPOSICIÓN!J$2:J$1892,COMPOSICIÓN!A$2:A$1892,A79,COMPOSICIÓN!B$2:B$1892,"EQ") -> 4599.5184 | M79: =J79 -> 25000 | N79: =IF(F79=0,0,K79/F79) -> 281634.56 | O79: =IF(F79=0,0,L79/F79) -> 4599.5184 | P79: =M79+N79+O79 -> 311234.08 | Q79: =COUNTIF(COMPOSICIÓN!$A:$A,A79) -> 4 | S79: Tareas | T79: 25000 | U79: 281634.56 | V79: 4599.5184
A80: PTO-0103 | C80: PRELIMINARES | D80: Cartel de Obra - No cotiza | E80: gl | F80: 1 | G80: 0 | H80: 0 | I80: 1 | J80: =SUMIFS(COMPOSICIÓN!J$2:J$1892,COMPOSICIÓN!A$2:A$1892,A80,COMPOSICIÓN!B$2:B$1892,"MAT") -> 0 | K80: =SUMIFS(COMPOSICIÓN!J$2:J$1892,COMPOSICIÓN!A$2:A$1892,A80,COMPOSICIÓN!B$2:B$1892,"MO")*I80 -> 0 | L80: =SUMIFS(COMPOSICIÓN!J$2:J$1892,COMPOSICIÓN!A$2:A$1892,A80,COMPOSICIÓN!B$2:B$1892,"EQ") -> 0 | M80: =J80 -> 0 | N80: =IF(F80=0,0,K80/F80) -> 0 | O80: =IF(F80=0,0,L80/F80) -> 0 | P80: =M80+N80+O80 -> 0 | Q80: =COUNTIF(COMPOSICIÓN!$A:$A,A80) -> 0 | S80: lump_directo | T80: 0 | U80: 0 | V80: 0
A81: PTO-0104 | C81: PRELIMINARES | D81: Cerco de obra perimetral - En chapa C25 + Concertina + Porton corredizo | E81: ml | F81: 1 | G81: 0 | H81: 0 | I81: 1 | J81: =SUMIFS(COMPOSICIÓN!J$2:J$1892,COMPOSICIÓN!A$2:A$1892,A81,COMPOSICIÓN!B$2:B$1892,"MAT") -> 98815.568 | K81: =SUMIFS(COMPOSICIÓN!J$2:J$1892,COMPOSICIÓN!A$2:A$1892,A81,COMPOSICIÓN!B$2:B$1892,"MO")*I81 -> 111992.57 | L81: =SUMIFS(COMPOSICIÓN!J$2:J$1892,COMPOSICIÓN!A$2:A$1892,A81,COMPOSICIÓN!B$2:B$1892,"EQ") -> 3162.1221 | M81: =J81 -> 98815.568 | N81: =IF(F81=0,0,K81/F81) -> 111992.57 | O81: =IF(F81=0,0,L81/F81) -> 3162.1221 | P81: =M81+N81+O81 -> 213970.27 | Q81: =COUNTIF(COMPOSICIÓN!$A:$A,A81) -> 13 | S81: Tareas | T81: 98815.568 | U81: 111992.57 | V81: 3162.1221
A82: PTO-0105 | C82: PRELIMINARES | D82: Obrador, pañol y ducha | E82: gl | F82: 1 | G82: 0 | H82: 0 | I82: 1 | J82: =SUMIFS(COMPOSICIÓN!J$2:J$1892,COMPOSICIÓN!A$2:A$1892,A82,COMPOSICIÓN!B$2:B$1892,"MAT") -> 2570625.2 | K82: =SUMIFS(COMPOSICIÓN!J$2:J$1892,COMPOSICIÓN!A$2:A$1892,A82,COMPOSICIÓN!B$2:B$1892,"MO")*I82 -> 6023936.4 | L82: =SUMIFS(COMPOSICIÓN!J$2:J$1892,COMPOSICIÓN!A$2:A$1892,A82,COMPOSICIÓN!B$2:B$1892,"EQ") -> 128918.42 | M82: =J82 -> 2570625.2 | N82: =IF(F82=0,0,K82/F82) -> 6023936.4 | O82: =IF(F82=0,0,L82/F82) -> 128918.42 | P82: =M82+N82+O82 -> 8723480 | Q82: =COUNTIF(COMPOSICIÓN!$A:$A,A82) -> 22 | S82: Tareas | T82: 2570625.2 | U82: 6023936.4 | V82: 128918.42
A83: PTO-0106 | C83: PRELIMINARES | D83: Alquiler de baños quimicos y duchas portatiles | E83: mes | F83: 1 | G83: 0 | H83: 0 | I83: 1 | J83: =SUMIFS(COMPOSICIÓN!J$2:J$1892,COMPOSICIÓN!A$2:A$1892,A83,COMPOSICIÓN!B$2:B$1892,"MAT") -> 0 | K83: =SUMIFS(COMPOSICIÓN!J$2:J$1892,COMPOSICIÓN!A$2:A$1892,A83,COMPOSICIÓN!B$2:B$1892,"MO")*I83 -> 260000 | L83: =SUMIFS(COMPOSICIÓN!J$2:J$1892,COMPOSICIÓN!A$2:A$1892,A83,COMPOSICIÓN!B$2:B$1892,"EQ") -> 0 | M83: =J83 -> 0 | N83: =IF(F83=0,0,K83/F83) -> 260000 | O83: =IF(F83=0,0,L83/F83) -> 0 | P83: =M83+N83+O83 -> 260000 | Q83: =COUNTIF(COMPOSICIÓN!$A:$A,A83) -> 4 | S83: Tareas | T83: 0 | U83: 260000 | V83: 0
A84: PTO-0107 | C84: PRELIMINARES | D84: Conexión pilar y luz de obra + Tablero de obra | E84: gl | F84: 1 | G84: 0 | H84: 0 | I84: 1 | J84: =SUMIFS(COMPOSICIÓN!J$2:J$1892,COMPOSICIÓN!A$2:A$1892,A84,COMPOSICIÓN!B$2:B$1892,"MAT") -> 1390000 | K84: =SUMIFS(COMPOSICIÓN!J$2:J$1892,COMPOSICIÓN!A$2:A$1892,A84,COMPOSICIÓN!B$2:B$1892,"MO")*I84 -> 661285.32 | L84: =SUMIFS(COMPOSICIÓN!J$2:J$1892,COMPOSICIÓN!A$2:A$1892,A84,COMPOSICIÓN!B$2:B$1892,"EQ") -> 30769.28 | M84: =J84 -> 1390000 | N84: =IF(F84=0,0,K84/F84) -> 661285.32 | O84: =IF(F84=0,0,L84/F84) -> 30769.28 | P84: =M84+N84+O84 -> 2082054.6 | Q84: =COUNTIF(COMPOSICIÓN!$A:$A,A84) -> 9 | S84: Tareas | T84: 1390000 | U84: 661285.32 | V84: 30769.28
A85: PTO-0108 | C85: PRELIMINARES | D85: Conexión agua de obra, tanque + bomba | E85: gl | F85: 1 | G85: 0 | H85: 0 | I85: 1 | J85: =SUMIFS(COMPOSICIÓN!J$2:J$1892,COMPOSICIÓN!A$2:A$1892,A85,COMPOSICIÓN!B$2:B$1892,"MAT") -> 936000 | K85: =SUMIFS(COMPOSICIÓN!J$2:J$1892,COMPOSICIÓN!A$2:A$1892,A85,COMPOSICIÓN!B$2:B$1892,"MO")*I85 -> 536368.95 | L85: =SUMIFS(COMPOSICIÓN!J$2:J$1892,COMPOSICIÓN!A$2:A$1892,A85,COMPOSICIÓN!B$2:B$1892,"EQ") -> 22085.534 | M85: =J85 -> 936000 | N85: =IF(F85=0,0,K85/F85) -> 536368.95 | O85: =IF(F85=0,0,L85/F85) -> 22085.534 | P85: =M85+N85+O85 -> 1494454.5 | Q85: =COUNTIF(COMPOSICIÓN!$A:$A,A85) -> 11 | S85: Tareas | T85: 936000 | U85: 536368.95 | V85: 22085.534
A86: PTO-0109 | C86: PRELIMINARES | D86: Tramite luz de obra, certificado luz de obra (2) y medición PAT | E86: gl | F86: 1 | G86: 0 | H86: 0 | I86: 1 | J86: =SUMIFS(COMPOSICIÓN!J$2:J$1892,COMPOSICIÓN!A$2:A$1892,A86,COMPOSICIÓN!B$2:B$1892,"MAT") -> 0 | K86: =SUMIFS(COMPOSICIÓN!J$2:J$1892,COMPOSICIÓN!A$2:A$1892,A86,COMPOSICIÓN!B$2:B$1892,"MO")*I86 -> 482995.31 | L86: =SUMIFS(COMPOSICIÓN!J$2:J$1892,COMPOSICIÓN!A$2:A$1892,A86,COMPOSICIÓN!B$2:B$1892,"EQ") -> 0 | M86: =J86 -> 0 | N86: =IF(F86=0,0,K86/F86) -> 482995.31 | O86: =IF(F86=0,0,L86/F86) -> 0 | P86: =M86+N86+O86 -> 482995.31 | Q86: =COUNTIF(COMPOSICIÓN!$A:$A,A86) -> 3 | S86: Tareas | T86: 0 | U86: 482995.31 | V86: 0
A87: PTO-0201 | C87: MOVIMIENTO DE TIERRA | D87: Retiro de suelo vegetal e: 50 cm, aporte y compactación de tosca e: 40 cm (dos c | E87: m2 | F87: 1 | G87: 0 | H87: 0 | I87: 1 | J87: =SUMIFS(COMPOSICIÓN!J$2:J$1892,COMPOSICIÓN!A$2:A$1892,A87,COMPOSICIÓN!B$2:B$1892,"MAT") -> 0 | K87: =SUMIFS(COMPOSICIÓN!J$2:J$1892,COMPOSICIÓN!A$2:A$1892,A87,COMPOSICIÓN!B$2:B$1892,"MO")*I87 -> 28977.78 | L87: =SUMIFS(COMPOSICIÓN!J$2:J$1892,COMPOSICIÓN!A$2:A$1892,A87,COMPOSICIÓN!B$2:B$1892,"EQ") -> 0 | M87: =J87 -> 0 | N87: =IF(F87=0,0,K87/F87) -> 28977.78 | O87: =IF(F87=0,0,L87/F87) -> 0 | P87: =M87+N87+O87 -> 28977.78 | Q87: =COUNTIF(COMPOSICIÓN!$A:$A,A87) -> 2 | S87: Tareas | T87: 0 | U87: 28977.787 | V87: 0
A88: PTO-0202 | C88: MOVIMIENTO DE TIERRA | D88: Excavación para cámara transformadora | E88: m3 | F88: 1 | G88: 0 | H88: 0 | I88: 1 | J88: =SUMIFS(COMPOSICIÓN!J$2:J$1892,COMPOSICIÓN!A$2:A$1892,A88,COMPOSICIÓN!B$2:B$1892,"MAT") -> 0 | K88: =SUMIFS(COMPOSICIÓN!J$2:J$1892,COMPOSICIÓN!A$2:A$1892,A88,COMPOSICIÓN!B$2:B$1892,"MO")*I88 -> 31164.05 | L88: =SUMIFS(COMPOSICIÓN!J$2:J$1892,COMPOSICIÓN!A$2:A$1892,A88,COMPOSICIÓN!B$2:B$1892,"EQ") -> 467.46075 | M88: =J88 -> 0 | N88: =IF(F88=0,0,K88/F88) -> 31164.05 | O88: =IF(F88=0,0,L88/F88) -> 467.46075 | P88: =M88+N88+O88 -> 31631.511 | Q88: =COUNTIF(COMPOSICIÓN!$A:$A,A88) -> 5 | S88: Tareas | T88: 0 | U88: 31164.05 | V88: 467.46075
A89: PTO-0203 | C89: MOVIMIENTO DE TIERRA | D89: Excavación manual para tensores y vigas de fundación | E89: m3 | F89: 1 | G89: 0 | H89: 0 | I89: 1 | J89: =SUMIFS(COMPOSICIÓN!J$2:J$1892,COMPOSICIÓN!A$2:A$1892,A89,COMPOSICIÓN!B$2:B$1892,"MAT") -> 0 | K89: =SUMIFS(COMPOSICIÓN!J$2:J$1892,COMPOSICIÓN!A$2:A$1892,A89,COMPOSICIÓN!B$2:B$1892,"MO")*I89 -> 67240.499 | L89: =SUMIFS(COMPOSICIÓN!J$2:J$1892,COMPOSICIÓN!A$2:A$1892,A89,COMPOSICIÓN!B$2:B$1892,"EQ") -> 0 | M89: =J89 -> 0 | N89: =IF(F89=0,0,K89/F89) -> 67240.499 | O89: =IF(F89=0,0,L89/F89) -> 0 | P89: =M89+N89+O89 -> 67240.499 | Q89: =COUNTIF(COMPOSICIÓN!$A:$A,A89) -> 1 | S89: lump_directo | T89: 0 | U89: 67240.499 | V89: 0
... A91: PTO-0301 | C91: ESTRUCTURA DE HORMIGÓN ARMADO | D91: Hormigón de limpieza - e: 10 cm | E91: m3 | F91: 1 | G91: 0 | H91: 0 | I91: 1 | J91: =SUMIFS(COMPOSICIÓN!J$2:J$1892,COMPOSICIÓN!A$2:A$1892,A91,COMPOSICIÓN!B$2:B$1892,"MAT") -> 120430 | K91: =SUMIFS(COMPOSICIÓN!J$2:J$1892,COMPOSICIÓN!A$2:A$1892,A91,COMPOSICIÓN!B$2:B$1892,"MO")*I91 -> 155041.22 | L91: =SUMIFS(COMPOSICIÓN!J$2:J$1892,COMPOSICIÓN!A$2:A$1892,A91,COMPOSICIÓN!B$2:B$1892,"EQ") -> 4132.0683 | M91: =J91 -> 120430 | N91: =IF(F91=0,0,K91/F91) -> 155041.22 | O91: =IF(F91=0,0,L91/F91) -> 4132.0683 | P91: =M91+N91+O91 -> 279603.29 | Q91: =COUNTIF(COMPOSICIÓN!$A:$A,A91) -> 7 | S91: Tareas | T91: 120430 | U91: 155041.22 | V91: 4132.0683
A92: PTO-0302 | C92: ESTRUCTURA DE HORMIGÓN ARMADO | D92: Micropilotes Ø 20 cm | E92: gl | F92: 1 | G92: 0 | H92: 0 | I92: 1 | J92: =SUMIFS(COMPOSICIÓN!J$2:J$1892,COMPOSICIÓN!A$2:A$1892,A92,COMPOSICIÓN!B$2:B$1892,"MAT") -> 11090041 | K92: =SUMIFS(COMPOSICIÓN!J$2:J$1892,COMPOSICIÓN!A$2:A$1892,A92,COMPOSICIÓN!B$2:B$1892,"MO")*I92 -> 37760301 | L92: =SUMIFS(COMPOSICIÓN!J$2:J$1892,COMPOSICIÓN!A$2:A$1892,A92,COMPOSICIÓN!B$2:B$1892,"EQ") -> 718505.14 | M92: =J92 -> 11090041 | N92: =IF(F92=0,0,K92/F92) -> 37760301 | O92: =IF(F92=0,0,L92/F92) -> 718505.14 | P92: =M92+N92+O92 -> 49568848 | Q92: =COUNTIF(COMPOSICIÓN!$A:$A,A92) -> 10 | R92: Desvío MO +2.6%. Desvío menor. Sin acción correctiva. | S92: Tareas | T92: 11090041 | U92: 36810301 | V92: 718505.14
A93: PTO-0303 | C93: ESTRUCTURA DE HORMIGÓN ARMADO | D93: Platea - H30 (110 kg/m3 de hierro) | E93: m3 | F93: 1 | G93: 0 | H93: 0 | I93: 1 | J93: =SUMIFS(COMPOSICIÓN!J$2:J$1892,COMPOSICIÓN!A$2:A$1892,A93,COMPOSICIÓN!B$2:B$1892,"MAT") -> 357146.17 | K93: =SUMIFS(COMPOSICIÓN!J$2:J$1892,COMPOSICIÓN!A$2:A$1892,A93,COMPOSICIÓN!B$2:B$1892,"MO")*I93 -> 222927.96 | L93: =SUMIFS(COMPOSICIÓN!J$2:J$1892,COMPOSICIÓN!A$2:A$1892,A93,COMPOSICIÓN!B$2:B$1892,"EQ") -> 8701.1119 | M93: =J93 -> 357146.17 | N93: =IF(F93=0,0,K93/F93) -> 222927.96 | O93: =IF(F93=0,0,L93/F93) -> 8701.1119 | P93: =M93+N93+O93 -> 588775.24 | Q93: =COUNTIF(COMPOSICIÓN!$A:$A,A93) -> 5 | S93: lump_directo | T93: 357146.17 | U93: 222927.96 | V93: 8701.1119
A94: PTO-0304 | C94: ESTRUCTURA DE HORMIGÓN ARMADO | D94: Zapata corrida tabique - H30 (180 kg/m3 de hierro) | E94: m3 | F94: 1 | G94: 0 | H94: 0 | I94: 1 | J94: =SUMIFS(COMPOSICIÓN!J$2:J$1892,COMPOSICIÓN!A$2:A$1892,A94,COMPOSICIÓN!B$2:B$1892,"MAT") -> 537813.29 | K94: =SUMIFS(COMPOSICIÓN!J$2:J$1892,COMPOSICIÓN!A$2:A$1892,A94,COMPOSICIÓN!B$2:B$1892,"MO")*I94 -> 323084 | L94: =SUMIFS(COMPOSICIÓN!J$2:J$1892,COMPOSICIÓN!A$2:A$1892,A94,COMPOSICIÓN!B$2:B$1892,"EQ") -> 12913.459 | M94: =J94 -> 537813.29 | N94: =IF(F94=0,0,K94/F94) -> 323084 | O94: =IF(F94=0,0,L94/F94) -> 12913.459 | P94: =M94+N94+O94 -> 873810.75 | Q94: =COUNTIF(COMPOSICIÓN!$A:$A,A94) -> 5 | S94: lump_directo | T94: 537813.29 | U94: 323084 | V94: 12913.459
A95: PTO-0305 | C95: ESTRUCTURA DE HORMIGÓN ARMADO | D95: Bases aisladas - H30 (110 kg/m3 de hierro) | E95: m3 | F95: 1 | G95: 0 | H95: 0 | I95: 1 | J95: =SUMIFS(COMPOSICIÓN!J$2:J$1892,COMPOSICIÓN!A$2:A$1892,A95,COMPOSICIÓN!B$2:B$1892,"MAT") -> 357146.17 | K95: =SUMIFS(COMPOSICIÓN!J$2:J$1892,COMPOSICIÓN!A$2:A$1892,A95,COMPOSICIÓN!B$2:B$1892,"MO")*I95 -> 222927.96 | L95: =SUMIFS(COMPOSICIÓN!J$2:J$1892,COMPOSICIÓN!A$2:A$1892,A95,COMPOSICIÓN!B$2:B$1892,"EQ") -> 8701.1119 | M95: =J95 -> 357146.17 | N95: =IF(F95=0,0,K95/F95) -> 222927.96 | O95: =IF(F95=0,0,L95/F95) -> 8701.1119 | P95: =M95+N95+O95 -> 588775.24 | Q95: =COUNTIF(COMPOSICIÓN!$A:$A,A95) -> 3 | S95: lump_directo | T95: 357146.17 | U95: 222927.96 | V95: 8701.1119
A96: PTO-0306 | C96: ESTRUCTURA DE HORMIGÓN ARMADO | D96: Cabezales - H30 (130 kg/m3 de hierro) | E96: m3 | F96: 1 | G96: 0 | H96: 0 | I96: 1 | J96: =SUMIFS(COMPOSICIÓN!J$2:J$1892,COMPOSICIÓN!A$2:A$1892,A96,COMPOSICIÓN!B$2:B$1892,"MAT") -> 392586.17 | K96: =SUMIFS(COMPOSICIÓN!J$2:J$1892,COMPOSICIÓN!A$2:A$1892,A96,COMPOSICIÓN!B$2:B$1892,"MO")*I96 -> 222927.96 | L96: =SUMIFS(COMPOSICIÓN!J$2:J$1892,COMPOSICIÓN!A$2:A$1892,A96,COMPOSICIÓN!B$2:B$1892,"EQ") -> 9232.7119 | M96: =J96 -> 392586.17 | N96: =IF(F96=0,0,K96/F96) -> 222927.96 | O96: =IF(F96=0,0,L96/F96) -> 9232.7119 | P96: =M96+N96+O96 -> 624746.84 | Q96: =COUNTIF(COMPOSICIÓN!$A:$A,A96) -> 5 | S96: lump_directo | T96: 392586.17 | U96: 222927.96 | V96: 9232.7119
A97: PTO-0307 | C97: ESTRUCTURA DE HORMIGÓN ARMADO | D97: Viga de fundación - H30 (180 kg/m3 de hierro) | E97: m3 | F97: 1 | G97: 0 | H97: 0 | I97: 1 | J97: =SUMIFS(COMPOSICIÓN!J$2:J$1892,COMPOSICIÓN!A$2:A$1892,A97,COMPOSICIÓN!B$2:B$1892,"MAT") -> 537813.29 | K97: =SUMIFS(COMPOSICIÓN!J$2:J$1892,COMPOSICIÓN!A$2:A$1892,A97,COMPOSICIÓN!B$2:B$1892,"MO")*I97 -> 323084 | L97: =SUMIFS(COMPOSICIÓN!J$2:J$1892,COMPOSICIÓN!A$2:A$1892,A97,COMPOSICIÓN!B$2:B$1892,"EQ") -> 12913.459 | M97: =J97 -> 537813.29 | N97: =IF(F97=0,0,K97/F97) -> 323084 | O97: =IF(F97=0,0,L97/F97) -> 12913.459 | P97: =M97+N97+O97 -> 873810.75 | Q97: =COUNTIF(COMPOSICIÓN!$A:$A,A97) -> 5 | S97: lump_directo | T97: 537813.29 | U97: 323084 | V97: 12913.459
A98: PTO-0308 | C98: ESTRUCTURA DE HORMIGÓN ARMADO | D98: Tabique submuración - H30 (90 kg/m3 de hierro) | E98: m3 | F98: 1 | G98: 0 | H98: 0 | I98: 1 | J98: =SUMIFS(COMPOSICIÓN!J$2:J$1892,COMPOSICIÓN!A$2:A$1892,A98,COMPOSICIÓN!B$2:B$1892,"MAT") -> 394401.89 | K98: =SUMIFS(COMPOSICIÓN!J$2:J$1892,COMPOSICIÓN!A$2:A$1892,A98,COMPOSICIÓN!B$2:B$1892,"MO")*I98 -> 392678.73 | L98: =SUMIFS(COMPOSICIÓN!J$2:J$1892,COMPOSICIÓN!A$2:A$1892,A98,COMPOSICIÓN!B$2:B$1892,"EQ") -> 11806.209 | M98: =J98 -> 394401.89 | N98: =IF(F98=0,0,K98/F98) -> 392678.73 | O98: =IF(F98=0,0,L98/F98) -> 11806.209 | P98: =M98+N98+O98 -> 798886.83 | Q98: =COUNTIF(COMPOSICIÓN!$A:$A,A98) -> 5 | S98: lump_directo | T98: 394401.89 | U98: 392678.73 | V98: 11806.209
A99: PTO-0309 | C99: ESTRUCTURA DE HORMIGÓN ARMADO | D99: Puntales de compresión/codales - H30 (120 kg/m3) | E99: m3 | F99: 1 | G99: 0 | H99: 0 | I99: 1 | J99: =SUMIFS(COMPOSICIÓN!J$2:J$1892,COMPOSICIÓN!A$2:A$1892,A99,COMPOSICIÓN!B$2:B$1892,"MAT") -> 542036.05 | K99: =SUMIFS(COMPOSICIÓN!J$2:J$1892,COMPOSICIÓN!A$2:A$1892,A99,COMPOSICIÓN!B$2:B$1892,"MO")*I99 -> 362209.61 | L99: =SUMIFS(COMPOSICIÓN!J$2:J$1892,COMPOSICIÓN!A$2:A$1892,A99,COMPOSICIÓN!B$2:B$1892,"EQ") -> 13563.685 | M99: =J99 -> 542036.05 | N99: =IF(F99=0,0,K99/F99) -> 362209.61 | O99: =IF(F99=0,0,L99/F99) -> 13563.685 | P99: =M99+N99+O99 -> 917809.34 | Q99: =COUNTIF(COMPOSICIÓN!$A:$A,A99) -> 3 | S99: lump_directo | T99: 542036.05 | U99: 362209.61 | V99: 13563.685
A100: PTO-0031 | C100: ESTRUCTURA DE HORMIGÓN ARMADO | D100: Columna - H30 (240 kg/m3 de hierro) | E100: m3 | F100: 1 | G100: 0 | H100: 0 | I100: 1 | J100: =SUMIFS(COMPOSICIÓN!J$2:J$1892,COMPOSICIÓN!A$2:A$1892,A100,COMPOSICIÓN!B$2:B$1892,"MAT") -> 648356.05 | K100: =SUMIFS(COMPOSICIÓN!J$2:J$1892,COMPOSICIÓN!A$2:A$1892,A100,COMPOSICIÓN!B$2:B$1892,"MO")*I100 -> 362209.61 | L100: =SUMIFS(COMPOSICIÓN!J$2:J$1892,COMPOSICIÓN!A$2:A$1892,A100,COMPOSICIÓN!B$2:B$1892,"EQ") -> 15158.485 | M100: =J100 -> 648356.05 | N100: =IF(F100=0,0,K100/F100) -> 362209.61 | O100: =IF(F100=0,0,L100/F100) -> 15158.485 | P100: =M100+N100+O100 -> 1025724.1 | Q100: =COUNTIF(COMPOSICIÓN!$A:$A,A100) -> 5 | S100: lump_directo | T100: 648356.05 | U100: 362209.61 | V100: 15158.485
A101: PTO-0311 | C101: ESTRUCTURA DE HORMIGÓN ARMADO | D101: Tabiques - H30 (120 kg/m3 de hierro) | E101: m3 | F101: 1 | G101: 0 | H101: 0 | I101: 1 | J101: =SUMIFS(COMPOSICIÓN!J$2:J$1892,COMPOSICIÓN!A$2:A$1892,A101,COMPOSICIÓN!B$2:B$1892,"MAT") -> 447561.89 | K101: =SUMIFS(COMPOSICIÓN!J$2:J$1892,COMPOSICIÓN!A$2:A$1892,A101,COMPOSICIÓN!B$2:B$1892,"MO")*I101 -> 392678.73 | L101: =SUMIFS(COMPOSICIÓN!J$2:J$1892,COMPOSICIÓN!A$2:A$1892,A101,COMPOSICIÓN!B$2:B$1892,"EQ") -> 12603.609 | M101: =J101 -> 447561.89 | N101: =IF(F101=0,0,K101/F101) -> 392678.73 | O101: =IF(F101=0,0,L101/F101) -> 12603.609 | P101: =M101+N101+O101 -> 852844.23 | Q101: =COUNTIF(COMPOSICIÓN!$A:$A,A101) -> 5 | S101: lump_directo | T101: 447561.89 | U101: 392678.73 | V101: 12603.609
...

Sheet PPTO_GENERADOR
A1: PRESUPUESTO CH 2171 — GENERADOR
A2: Versión APU: | B2: =CONFIG!B6 -> v3.0 — APU Chivilcoy 06-25 | G2: Mes base CAC: | H2: =CONFIG!B11 -> Junio 2025 | M2: Coeficiente GGBB | N2: 1
A3: # | B3: Rubro | C3: Descripción | D3: Ud. | E3: Cant. | F3: MAT/ud | G3: MO/ud | H3: EQ/ud | I3: CD/ud | J3: MAT total | K3: MO total | L3: EQ total | M3: Costo Total | N3: Precio Venta (xK) | Q3: APU Link | R3: Pto# | S3: Fuente | T3: Rubro MO/ALB | U3: Observaciones | V3: PPTO original | W3: Diferencia | X3: Var (%)
A4: 1 | C4: PRELIMINARES | O4: =SUM(M5:M13) -> 17207623 | P4: =SUM(N5:N13) -> 17207623
A5: 1.01 | B5: PRELIMINARES | C5: Limpieza y preparación del terreno - No cotiza | D5: gl | E5: 0 | F5: =IF(Q5<>"",IFERROR(VLOOKUP(Q5,PARTIDAS!A:P,13,FALSE()),0),0) -> 0 | G5: =IF(Q5<>"",IFERROR(VLOOKUP(Q5,PARTIDAS!A:P,14,FALSE()),0),0) -> 0 | H5: =IF(Q5<>"",IFERROR(VLOOKUP(Q5,PARTIDAS!A:P,15,FALSE()),0),0) -> 0 | I5: =F5+G5+H5 -> 0 | J5: =F5*E5 -> 0 | K5: =G5*E5 -> 0 | L5: =H5*E5 -> 0 | M5: =I5*E5 -> 0 | N5: =M5*$N$2 -> 0 | Q5: PTO-0101 | R5: 1 | S5: lump_directo | T5: =+_xlfn.XLOOKUP(A5,[1]Sheet1!C:C,[1]Sheet1!A:A,"-",0) -> - | V5: 0 | W5: =M5-V5 -> 0 | X5: =IFERROR(W5/V5-1,0) -> 0
A6: 1.02 | B6: PRELIMINARES | C6: Topógrafo - Visita de obra replanteo | D6: un | E6: 4 | F6: =IF(Q6<>"",IFERROR(VLOOKUP(Q6,PARTIDAS!A:P,13,FALSE()),0),0) -> 25000 | G6: =IF(Q6<>"",IFERROR(VLOOKUP(Q6,PARTIDAS!A:P,14,FALSE()),0),0) -> 281634.56 | H6: =IF(Q6<>"",IFERROR(VLOOKUP(Q6,PARTIDAS!A:P,15,FALSE()),0),0) -> 4599.5184 | I6: =F6+G6+H6 -> 311234.08 | J6: =F6*E6 -> 100000 | K6: =G6*E6 -> 1126538.2 | L6: =H6*E6 -> 18398.074 | M6: =I6*E6 -> 1244936.3 | N6: =M6*$N$2 -> 1244936.3 | Q6: PTO-0102 | R6: 1 | S6: Tareas | V6: 1244936.3 | W6: =M6-V6 -> -5.5879354e-09 | X6: =IFERROR(W6/V6,0) -> -4.4885312e-15
A7: 1.03 | B7: PRELIMINARES | C7: Cartel de Obra - No cotiza | D7: gl | E7: 1 | F7: =IF(Q7<>"",IFERROR(VLOOKUP(Q7,PARTIDAS!A:P,13,FALSE()),0),0) -> 0 | G7: =IF(Q7<>"",IFERROR(VLOOKUP(Q7,PARTIDAS!A:P,14,FALSE()),0),0) -> 0 | H7: =IF(Q7<>"",IFERROR(VLOOKUP(Q7,PARTIDAS!A:P,15,FALSE()),0),0) -> 0 | I7: =F7+G7+H7 -> 0 | J7: =F7*E7 -> 0 | K7: =G7*E7 -> 0 | L7: =H7*E7 -> 0 | M7: =I7*E7 -> 0 | N7: =M7*$N$2 -> 0 | Q7: PTO-0103 | R7: 1 | S7: lump_directo | V7: 0 | W7: =M7-V7 -> 0 | X7: =IFERROR(W7/V7,0) -> 0
A8: 1.04 | B8: PRELIMINARES | C8: Cerco de obra perimetral - En chapa C25 + Concertina + Porton corredizo | D8: ml | E8: 10 | F8: =IF(Q8<>"",IFERROR(VLOOKUP(Q8,PARTIDAS!A:P,13,FALSE()),0),0) -> 98815.568 | G8: =IF(Q8<>"",IFERROR(VLOOKUP(Q8,PARTIDAS!A:P,14,FALSE()),0),0) -> 111992.57 | H8: =IF(Q8<>"",IFERROR(VLOOKUP(Q8,PARTIDAS!A:P,15,FALSE()),0),0) -> 3162.1221 | I8: =F8+G8+H8 -> 213970.27 | J8: =F8*E8 -> 988155.68 | K8: =G8*E8 -> 1119925.7 | L8: =H8*E8 -> 31621.221 | M8: =I8*E8 -> 2139702.7 | N8: =M8*$N$2 -> 2139702.7 | Q8: PTO-0104 | R8: 1 | S8: Tareas | V8: 2139702.7 | W8: =M8-V8 -> 0 | X8: =IFERROR(W8/V8,0) -> 0
A9: 1.05 | B9: PRELIMINARES | C9: Obrador, pañol y ducha | D9: gl | E9: 1 | F9: =IF(Q9<>"",IFERROR(VLOOKUP(Q9,PARTIDAS!A:P,13,FALSE()),0),0) -> 2570625.2 | G9: =IF(Q9<>"",IFERROR(VLOOKUP(Q9,PARTIDAS!A:P,14,FALSE()),0),0) -> 6023936.4 | H9: =IF(Q9<>"",IFERROR(VLOOKUP(Q9,PARTIDAS!A:P,15,FALSE()),0),0) -> 128918.42 | I9: =F9+G9+H9 -> 8723480 | J9: =F9*E9 -> 2570625.2 | K9: =G9*E9 -> 6023936.4 | L9: =H9*E9 -> 128918.42 | M9: =I9*E9 -> 8723480 | N9: =M9*$N$2 -> 8723480 | Q9: PTO-0105 | R9: 1 | S9: Tareas | V9: 8723480 | W9: =M9-V9 -> 0 | X9: =IFERROR(W9/V9,0) -> 0
A10: 1.06 | B10: PRELIMINARES | C10: Alquiler de baños quimicos y duchas portatiles | D10: mes | E10: 4 | F10: =IF(Q10<>"",IFERROR(VLOOKUP(Q10,PARTIDAS!A:P,13,FALSE()),0),0) -> 0 | G10: =IF(Q10<>"",IFERROR(VLOOKUP(Q10,PARTIDAS!A:P,14,FALSE()),0),0) -> 260000 | H10: =IF(Q10<>"",IFERROR(VLOOKUP(Q10,PARTIDAS!A:P,15,FALSE()),0),0) -> 0 | I10: =F10+G10+H10 -> 260000 | J10: =F10*E10 -> 0 | K10: =G10*E10 -> 1040000 | L10: =H10*E10 -> 0 | M10: =I10*E10 -> 1040000 | N10: =M10*$N$2 -> 1040000 | Q10: PTO-0106 | R10: 1 | S10: Tareas | V10: 1040000 | W10: =M10-V10 -> 0 | X10: =IFERROR(W10/V10,0) -> 0
A11: 1.07 | B11: PRELIMINARES | C11: Conexión pilar y luz de obra + Tablero de obra | D11: gl | E11: 1 | F11: =IF(Q11<>"",IFERROR(VLOOKUP(Q11,PARTIDAS!A:P,13,FALSE()),0),0) -> 1390000 | G11: =IF(Q11<>"",IFERROR(VLOOKUP(Q11,PARTIDAS!A:P,14,FALSE()),0),0) -> 661285.32 | H11: =IF(Q11<>"",IFERROR(VLOOKUP(Q11,PARTIDAS!A:P,15,FALSE()),0),0) -> 30769.28 | I11: =F11+G11+H11 -> 2082054.6 | J11: =F11*E11 -> 1390000 | K11: =G11*E11 -> 661285.32 | L11: =H11*E11 -> 30769.28 | M11: =I11*E11 -> 2082054.6 | N11: =M11*$N$2 -> 2082054.6 | Q11: PTO-0107 | R11: 1 | S11: Tareas | V11: 2082054.6 | W11: =M11-V11 -> -3.259629e-09 | X11: =IFERROR(W11/V11,0) -> -1.5655829e-15
A12: 1.08 | B12: PRELIMINARES | C12: Conexión agua de obra, tanque + bomba | D12: gl | E12: 1 | F12: =IF(Q12<>"",IFERROR(VLOOKUP(Q12,PARTIDAS!A:P,13,FALSE()),0),0) -> 936000 | G12: =IF(Q12<>"",IFERROR(VLOOKUP(Q12,PARTIDAS!A:P,14,FALSE()),0),0) -> 536368.95 | H12: =IF(Q12<>"",IFERROR(VLOOKUP(Q12,PARTIDAS!A:P,15,FALSE()),0),0) -> 22085.534 | I12: =F12+G12+H12 -> 1494454.5 | J12: =F12*E12 -> 936000 | K12: =G12*E12 -> 536368.95 | L12: =H12*E12 -> 22085.534 | M12: =I12*E12 -> 1494454.5 | N12: =M12*$N$2 -> 1494454.5 | Q12: PTO-0108 | R12: 1 | S12: Tareas | V12: 1494454.5 | W12: =M12-V12 -> -4.4237822e-09 | X12: =IFERROR(W12/V12,0) -> -2.9601318e-15
A13: 1.09 | B13: PRELIMINARES | C13: Tramite luz de obra, certificado luz de obra (2) y medición PAT | D13: gl | E13: 1 | F13: =IF(Q13<>"",IFERROR(VLOOKUP(Q13,PARTIDAS!A:P,13,FALSE()),0),0) -> 0 | G13: =IF(Q13<>"",IFERROR(VLOOKUP(Q13,PARTIDAS!A:P,14,FALSE()),0),0) -> 482995.31 | H13: =IF(Q13<>"",IFERROR(VLOOKUP(Q13,PARTIDAS!A:P,15,FALSE()),0),0) -> 0 | I13: =F13+G13+H13 -> 482995.31 | J13: =F13*E13 -> 0 | K13: =G13*E13 -> 482995.31 | L13: =H13*E13 -> 0 | M13: =I13*E13 -> 482995.31 | N13: =M13*$N$2 -> 482995.31 | Q13: PTO-0109 | R13: 1 | S13: Tareas | V13: 482995.31 | W13: =M13-V13 -> 1.5133992e-09 | X13: =IFERROR(W13/V13,0) -> 3.1333621e-15
A14: 2 | C14: MOVIMIENTO DE TIERRA | O14: =SUM(M15:M18) -> 12400626 | P14: =SUM(N15:N18) -> 12400626 | X14: =IFERROR(W14/V14,0) -> 0
A15: 2.01 | B15: MOVIMIENTO DE TIERRA | C15: Retiro de suelo vegetal e: 50 cm, aporte y compactación de tosca e: 40 cm (dos c | D15: m2 | E15: 219 | F15: =IF(Q15<>"",IFERROR(VLOOKUP(Q15,PARTIDAS!A:P,13,FALSE()),0),0) -> 0 | G15: =IF(Q15<>"",IFERROR(VLOOKUP(Q15,PARTIDAS!A:P,14,FALSE()),0),0) -> 28977.78 | H15: =IF(Q15<>"",IFERROR(VLOOKUP(Q15,PARTIDAS!A:P,15,FALSE()),0),0) -> 0 | I15: =F15+G15+H15 -> 28977.78 | J15: =F15*E15 -> 0 | K15: =G15*E15 -> 6346133.8 | L15: =H15*E15 -> 0 | M15: =I15*E15 -> 6346133.8 | N15: =M15*$N$2 -> 6346133.8 | Q15: PTO-0201 | R15: 1 | S15: Tareas | V15: 6346135.3 | W15: =M15-V15 -> -1.479291 | X15: =IFERROR(W15/V15,0) -> -2.3310108e-07
A16: 2.02 | B16: MOVIMIENTO DE TIERRA | C16: Excavación para cámara transformadora | D16: m3 | E16: 100 | F16: =IF(Q16<>"",IFERROR(VLOOKUP(Q16,PARTIDAS!A:P,13,FALSE()),0),0) -> 0 | G16: =IF(Q16<>"",IFERROR(VLOOKUP(Q16,PARTIDAS!A:P,14,FALSE()),0),0) -> 31164.05 | H16: =IF(Q16<>"",IFERROR(VLOOKUP(Q16,PARTIDAS!A:P,15,FALSE()),0),0) -> 467.46075 | I16: =F16+G16+H16 -> 31631.511 | J16: =F16*E16 -> 0 | K16: =G16*E16 -> 3116405 | L16: =H16*E16 -> 46746.075 | M16: =I16*E16 -> 3163151.1 | N16: =M16*$N$2 -> 3163151.1 | Q16: PTO-0202 | R16: 1 | S16: Tareas | V16: 3163151.1 | W16: =M16-V16 -> -3.7252903e-09 | X16: =IFERROR(W16/V16,0) -> -1.177715e-15
A17: 2.03 | B17: MOVIMIENTO DE TIERRA | C17: Excavación manual para tensores y vigas de fundación | D17: m3 | E17: 43 | F17: =IF(Q17<>"",IFERROR(VLOOKUP(Q17,PARTIDAS!A:P,13,FALSE()),0),0) -> 0 | G17: =IF(Q17<>"",IFERROR(VLOOKUP(Q17,PARTIDAS!A:P,14,FALSE()),0),0) -> 67240.499 | H17: =IF(Q17<>"",IFERROR(VLOOKUP(Q17,PARTIDAS!A:P,15,FALSE()),0),0) -> 0 | I17: =F17+G17+H17 -> 67240.499 | J17: =F17*E17 -> 0 | K17: =G17*E17 -> 2891341.5 | L17: =H17*E17 -> 0 | M17: =I17*E17 -> 2891341.5 | N17: =M17*$N$2 -> 2891341.5 | Q17: PTO-0203 | R17: 1 | S17: lump_directo | V17: 2891341.5 | W17: =M17-V17 -> 0 | X17: =IFERROR(W17/V17,0) -> 0
A18: 2.04 | B18: MOVIMIENTO DE TIERRA | C18: Demolición y retiro de fundaciones existentes - No cotiza | D18: gl | E18: 0 | F18: =IF(Q18<>"",IFERROR(VLOOKUP(Q18,PARTIDAS!A:P,13,FALSE()),0),0) -> 0 | G18: =IF(Q18<>"",IFERROR(VLOOKUP(Q18,PARTIDAS!A:P,14,FALSE()),0),0) -> 0 | H18: =IF(Q18<>"",IFERROR(VLOOKUP(Q18,PARTIDAS!A:P,15,FALSE()),0),0) -> 0 | I18: =F18+G18+H18 -> 0 | J18: =F18*E18 -> 0 | K18: =G18*E18 -> 0 | L18: =H18*E18 -> 0 | M18: =I18*E18 -> 0 | N18: =M18*$N$2 -> 0 | Q18: PTO-0204 | R18: 1 | S18: lump_directo | V18: 0 | W18: =M18-V18 -> 0 | X18: =IFERROR(W18/V18,0) -> 0
A19: 3 | C19: ESTRUCTURA DE HORMIGÓN ARMADO | O19: =SUM(M20:M41) -> 3.3463577e+08 | P19: =SUM(N20:N41) -> 3.3463577e+08 | X19: =IFERROR(W19/V19,0) -> 0
A20: 3.01 | B20: ESTRUCTURA DE HORMIGÓN ARMADO | C20: Hormigón de limpieza - e: 10 cm | D20: m3 | E20: 3 | F20: =IF(Q20<>"",IFERROR(VLOOKUP(Q20,PARTIDAS!A:P,13,FALSE()),0),0) -> 120430 | G20: =IF(Q20<>"",IFERROR(VLOOKUP(Q20,PARTIDAS!A:P,14,FALSE()),0),0) -> 155041.22 | H20: =IF(Q20<>"",IFERROR(VLOOKUP(Q20,PARTIDAS!A:P,15,FALSE()),0),0) -> 4132.0683 | I20: =F20+G20+H20 -> 279603.29 | J20: =F20*E20 -> 361290 | K20: =G20*E20 -> 465123.65 | L20: =H20*E20 -> 12396.205 | M20: =I20*E20 -> 838809.86 | N20: =M20*$N$2 -> 838809.86 | Q20: PTO-0301 | R20: 1 | S20: Tareas | V20: 838809.86 | W20: =M20-V20 -> -0.0095646254 | X20: =IFERROR(W20/V20,0) -> -1.1402614e-08
A21: 3.02 | B21: ESTRUCTURA DE HORMIGÓN ARMADO | C21: Micropilotes Ø 20 cm | D21: gl | E21: 1 | F21: =IF(Q21<>"",IFERROR(VLOOKUP(Q21,PARTIDAS!A:P,13,FALSE()),0),0) -> 11090041 | G21: =IF(Q21<>"",IFERROR(VLOOKUP(Q21,PARTIDAS!A:P,14,FALSE()),0),0) -> 37760301 | H21: =IF(Q21<>"",IFERROR(VLOOKUP(Q21,PARTIDAS!A:P,15,FALSE()),0),0) -> 718505.14 | I21: =F21+G21+H21 -> 49568848 | J21: =F21*E21 -> 11090041 | K21: =G21*E21 -> 37760301 | L21: =H21*E21 -> 718505.14 | M21: =I21*E21 -> 49568848 | N21: =M21*$N$2 -> 49568848 | Q21: PTO-0302 | R21: 1 | S21: Tareas | V21: 48618848 | W21: =M21-V21 -> 950000 | X21: =IFERROR(W21/V21,0) -> 0.019539747
A22: 3.03 | B22: ESTRUCTURA DE HORMIGÓN ARMADO | C22: Platea - H30 (110 kg/m3 de hierro) | D22: m3 | E22: 7 | F22: =IF(Q22<>"",IFERROR(VLOOKUP(Q22,PARTIDAS!A:P,13,FALSE()),0),0) -> 357146.17 | G22: =IF(Q22<>"",IFERROR(VLOOKUP(Q22,PARTIDAS!A:P,14,FALSE()),0),0) -> 222927.96 | H22: =IF(Q22<>"",IFERROR(VLOOKUP(Q22,PARTIDAS!A:P,15,FALSE()),0),0) -> 8701.1119 | I22: =F22+G22+H22 -> 588775.24 | J22: =F22*E22 -> 2500023.2 | K22: =G22*E22 -> 1560495.7 | L22: =H22*E22 -> 60907.784 | M22: =I22*E22 -> 4121426.7 | N22: =M22*$N$2 -> 4121426.7 | Q22: PTO-0303 | R22: 1 | S22: lump_directo | V22: 4121426.7 | W22: =M22-V22 -> 0 | X22: =IFERROR(W22/V22,0) -> 0
A23: 3.04 | B23: ESTRUCTURA DE HORMIGÓN ARMADO | C23: Zapata corrida tabique - H30 (180 kg/m3 de hierro) | D23: m3 | E23: 4 | F23: =IF(Q23<>"",IFERROR(VLOOKUP(Q23,PARTIDAS!A:P,13,FALSE()),0),0) -> 537813.29 | G23: =IF(Q23<>"",IFERROR(VLOOKUP(Q23,PARTIDAS!A:P,14,FALSE()),0),0) -> 323084 | H23: =IF(Q23<>"",IFERROR(VLOOKUP(Q23,PARTIDAS!A:P,15,FALSE()),0),0) -> 12913.459 | I23: =F23+G23+H23 -> 873810.75 | J23: =F23*E23 -> 2151253.2 | K23: =G23*E23 -> 1292336 | L23: =H23*E23 -> 51653.837 | M23: =I23*E23 -> 3495243 | N23: =M23*$N$2 -> 3495243 | Q23: PTO-0304 | R23: 1 | S23: lump_directo | V23: 3495243 | W23: =M23-V23 -> 0 | X23: =IFERROR(W23/V23,0) -> 0
A24: 3.05 | B24: ESTRUCTURA DE HORMIGÓN ARMADO | C24: Bases aisladas - H30 (110 kg/m3 de hierro) | D24: m3 | E24: 2 | F24: =IF(Q24<>"",IFERROR(VLOOKUP(Q24,PARTIDAS!A:P,13,FALSE()),0),0) -> 357146.17 | G24: =IF(Q24<>"",IFERROR(VLOOKUP(Q24,PARTIDAS!A:P,14,FALSE()),0),0) -> 222927.96 | H24: =IF(Q24<>"",IFERROR(VLOOKUP(Q24,PARTIDAS!A:P,15,FALSE()),0),0) -> 8701.1119 | I24: =F24+G24+H24 -> 588775.24 | J24: =F24*E24 -> 714292.34 | K24: =G24*E24 -> 445855.92 | L24: =H24*E24 -> 17402.224 | M24: =I24*E24 -> 1177550.5 | N24: =M24*$N$2 -> 1177550.5 | Q24: PTO-0305 | R24: 1 | S24: lump_directo | V24: 1177550.5 | W24: =M24-V24 -> -3.9581209e-09 | X24: =IFERROR(W24/V24,0) -> -3.3613174e-15
A25: 3.06 | B25: ESTRUCTURA DE HORMIGÓN ARMADO | C25: Cabezales - H30 (130 kg/m3 de hierro) | D25: m3 | E25: 11 | F25: =IF(Q25<>"",IFERROR(VLOOKUP(Q25,PARTIDAS!A:P,13,FALSE()),0),0) -> 392586.17 | G25: =IF(Q25<>"",IFERROR(VLOOKUP(Q25,PARTIDAS!A:P,14,FALSE()),0),0) -> 222927.96 | H25: =IF(Q25<>"",IFERROR(VLOOKUP(Q25,PARTIDAS!A:P,15,FALSE()),0),0) -> 9232.7119 | I25: =F25+G25+H25 -> 624746.84 | J25: =F25*E25 -> 4318447.9 | K25: =G25*E25 -> 2452207.6 | L25: =H25*E25 -> 101559.83 | M25: =I25*E25 -> 6872215.3 | N25: =M25*$N$2 -> 6872215.3 | Q25: PTO-0306 | R25: 1 | S25: lump_directo | V25: 6872215.3 | W25: =M25-V25 -> -8.3819032e-09 | X25: =IFERROR(W25/V25,0) -> -1.21968e-15
A26: 3.07 | B26: ESTRUCTURA DE HORMIGÓN ARMADO | C26: Viga defundación - H30 (180 kg/m3 de hierro) | D26: m3 | E26: 9 | F26: =IF(Q26<>"",IFERROR(VLOOKUP(Q26,PARTIDAS!A:P,13,FALSE()),0),0) -> 537813.29 | G26: =IF(Q26<>"",IFERROR(VLOOKUP(Q26,PARTIDAS!A:P,14,FALSE()),0),0) -> 323084 | H26: =IF(Q26<>"",IFERROR(VLOOKUP(Q26,PARTIDAS!A:P,15,FALSE()),0),0) -> 12913.459 | I26: =F26+G26+H26 -> 873810.75 | J26: =F26*E26 -> 4840319.6 | K26: =G26*E26 -> 2907756 | L26: =H26*E26 -> 116221.13 | M26: =I26*E26 -> 7864296.7 | N26: =M26*$N$2 -> 7864296.7 | Q26: PTO-0307 | R26: 1 | S26: lump_directo | V26: 7864296.7 | W26: =M26-V26 -> 0 | X26: =IFERROR(W26/V26,0) -> 0
A27: 3.08 | B27: ESTRUCTURA DE HORMIGÓN ARMADO | C27: Tabique submuración - H30 (90 kg/m3 de hierro) | D27: m3 | E27: 9 | F27: =IF(Q27<>"",IFERROR(VLOOKUP(Q27,PARTIDAS!A:P,13,FALSE()),0),0) -> 394401.89 | G27: =IF(Q27<>"",IFERROR(VLOOKUP(Q27,PARTIDAS!A:P,14,FALSE()),0),0) -> 392678.73 | H27: =IF(Q27<>"",IFERROR(VLOOKUP(Q27,PARTIDAS!A:P,15,FALSE()),0),0) -> 11806.209 | I27: =F27+G27+H27 -> 798886.83 | J27: =F27*E27 -> 3549617 | K27: =G27*E27 -> 3534108.6 | L27: =H27*E27 -> 106255.88 | M27: =I27*E27 -> 7189981.5 | N27: =M27*$N$2 -> 7189981.5 | Q27: PTO-0308 | R27: 1 | S27: lump_directo | V27: 7189981.5 | W27: =M27-V27 -> 0 | X27: =IFERROR(W27/V27,0) -> 0
A28: 3.09 | B28: ESTRUCTURA DE HORMIGÓN ARMADO | C28: Puntales de compresión/codales - H30 (120 kg/m3) | D28: m3 | E28: 1 | F28: =IF(Q28<>"",IFERROR(VLOOKUP(Q28,PARTIDAS!A:P,13,FALSE()),0),0) -> 542036.05 | G28: =IF(Q28<>"",IFERROR(VLOOKUP(Q28,PARTIDAS!A:P,14,FALSE()),0),0) -> 362209.61 | H28: =IF(Q28<>"",IFERROR(VLOOKUP(Q28,PARTIDAS!A:P,15,FALSE()),0),0) -> 13563.685 | I28: =F28+G28+H28 -> 917809.34 | J28: =F28*E28 -> 542036.05 | K28: =G28*E28 -> 362209.61 | L28: =H28*E28 -> 13563.685 | M28: =I28*E28 -> 917809.34 | N28: =M28*$N$2 -> 917809.34 | Q28: PTO-0309 | R28: 1 | S28: lump_directo | V28: 917809.34 | W28: =M28-V28 -> 0 | X28: =IFERROR(W28/V28,0) -> 0
A29: 3.1 | B29: ESTRUCTURA DE HORMIGÓN ARMADO | C29: Columna - H30 (240 kg/m3 de hierro) | D29: m3 | E29: 32 | F29: =IF(Q29<>"",IFERROR(VLOOKUP(Q29,PARTIDAS!A:P,13,FALSE()),0),0) -> 648356.05 | G29: =IF(Q29<>"",IFERROR(VLOOKUP(Q29,PARTIDAS!A:P,14,FALSE()),0),0) -> 362209.61 | H29: =IF(Q29<>"",IFERROR(VLOOKUP(Q29,PARTIDAS!A:P,15,FALSE()),0),0) -> 15158.485 | I29: =F29+G29+H29 -> 1025724.1 | J29: =F29*E29 -> 20747394 | K29: =G29*E29 -> 11590707 | L29: =H29*E29 -> 485071.52 | M29: =I29*E29 -> 32823173 | N29: =M29*$N$2 -> 32823173 | Q29: PTO-0031 | R29: 1 | S29: lump_directo | V29: 32823173 | W29: =M29-V29 -> 0 | X29: =IFERROR(W29/V29,0) -> 0
A30: 3.11 | B30: ESTRUCTURA DE HORMIGÓN ARMADO | C30: Tabiques - H30 (120 kg/m3 de hierro) | D30: m3 | E30: 30 | F30: =IF(Q30<>"",IFERROR(VLOOKUP(Q30,PARTIDAS!A:P,13,FALSE()),0),0) -> 447561.89 | G30: =IF(Q30<>"",IFERROR(VLOOKUP(Q30,PARTIDAS!A:P,14,FALSE()),0),0) -> 392678.73 | H30: =IF(Q30<>"",IFERROR(VLOOKUP(Q30,PARTIDAS!A:P,15,FALSE()),0),0) -> 12603.609 | I30: =F30+G30+H30 -> 852844.23 | J30: =F30*E30 -> 13426857 | K30: =G30*E30 -> 11780362 | L30: =H30*E30 -> 378108.28 | M30: =I30*E30 -> 25585327 | N30: =M30*$N$2 -> 25585327 | Q30: PTO-0311 | R30: 1 | S30: lump_directo | V30: 25585327 | W30: =M30-V30 -> 0 | X30: =IFERROR(W30/V30,0) -> 0
A31: 3.12 | B31: ESTRUCTURA DE HORMIGÓN ARMADO | C31: Viga H° Visto - H30 (120 kg/m3 de hierro) | D31: m3 | E31: 7 | F31: =IF(Q31<>"",IFERROR(VLOOKUP(Q31,PARTIDAS!A:P,13,FALSE()),0),0) -> 466389.3 | G31: =IF(Q31<>"",IFERROR(VLOOKUP(Q31,PARTIDAS!A:P,14,FALSE()),0),0) -> 786980.44 | H31: =IF(Q31<>"",IFERROR(VLOOKUP(Q31,PARTIDAS!A:P,15,FALSE()),0),0) -> 18800.546 | I31: =F31+G31+H31 -> 1272170.3 | J31: =F31*E31 -> 3264725.1 | K31: =G31*E31 -> 5508863.1 | L31: =H31*E31 -> 131603.82 | M31: =I31*E31 -> 8905192 | N31: =M31*$N$2 -> 8905192 | Q31: PTO-0312 | R31: 1 | S31: lump_directo | V31: 8905192 | W31: =M31-V31 -> 0.0017500017 | X31: =IFERROR(W31/V31,0) -> 1.9651476e-10
... A41: 3.22 | B41: ESTRUCTURA DE HORMIGÓN ARMADO | C41: Picado de medianeras para columnas y vigas - Cotizado solo para PB, 1P, NO conte | D41: m2 | E41: 65 | F41: =IF(Q41<>"",IFERROR(VLOOKUP(Q41,PARTIDAS!A:P,13,FALSE()),0),0) -> 9230.7846 | G41: =IF(Q41<>"",IFERROR(VLOOKUP(Q41,PARTIDAS!A:P,14,FALSE()),0),0) -> 20224.017 | H41: =IF(Q41<>"",IFERROR(VLOOKUP(Q41,PARTIDAS!A:P,15,FALSE()),0),0) -> 441.82178 | I41: =F41+G41+H41 -> 29896.623 | J41: =F41*E41 -> 600001 | K41: =G41*E41 -> 1314561.1 | L41: =H41*E41 -> 28718.416 | M41: =I41*E41 -> 1943280.5 | N41: =M41*$N$2 -> 1943280.5 | Q41: PTO-0322 | R41: 1 | S41: Tareas | V41: 1943279.5 | W41: =M41-V41 -> 1.0112128 | X41: =IFERROR(W41/V41,0) -> 5.2036405e-07
A42: 4 | C42: MAMPOSTERÍA | O42: =SUM(M43:M48) -> 59733620 | P42: =SUM(N43:N48) -> 59733620 | X42: =IFERROR(W42/V42,0) -> 0
A43: 4.01 | B43: MAMPOSTERÍA | C43: Muro tipo 1 (interiores, divisorio de locales) e: 10 cm - Ladrillo hueco 08 x 18 | D43: m2 | E43: 437 | F43: =IF(Q43<>"",IFERROR(VLOOKUP(Q43,PARTIDAS!A:P,13,FALSE()),0),0) -> 10053.788 | G43: =IF(Q43<>"",IFERROR(VLOOKUP(Q43,PARTIDAS!A:P,14,FALSE()),0),0) -> 10761.176 | H43: =IF(Q43<>"",IFERROR(VLOOKUP(Q43,PARTIDAS!A:P,15,FALSE()),0),0) -> 255.78052 | I43: =F43+G43+H43 -> 21070.744 | J43: =F43*E43 -> 4393505.4 | K43: =G43*E43 -> 4702633.8 | L43: =H43*E43 -> 111776.09 | M43: =I43*E43 -> 9207915.3 | N43: =M43*$N$2 -> 9207915.3 | Q43: PTO-0401 | R43: 1 | S43: APU P-34 | V43: 9207915.3 | W43: =M43-V43 -> 0.0064641945 | X43: =IFERROR(W43/V43,0) -> 7.0202584e-10
A44: 4.02 | B44: MAMPOSTERÍA | C44: Muro tipo 2 y 3 (medianera, caja de escaleras y ascensor) e: 15 cm - Ladrillo hu | D44: m2 | E44: 723 | F44: =IF(Q44<>"",IFERROR(VLOOKUP(Q44,PARTIDAS!A:P,13,FALSE()),0),0) -> 18207.26 | G44: =IF(Q44<>"",IFERROR(VLOOKUP(Q44,PARTIDAS!A:P,14,FALSE()),0),0) -> 10761.176 | H44: =IF(Q44<>"",IFERROR(VLOOKUP(Q44,PARTIDAS!A:P,15,FALSE()),0),0) -> 255.78052 | I44: =F44+G44+H44 -> 29224.217 | J44: =F44*E44 -> 13163849 | K44: =G44*E44 -> 7780330.1 | L44: =H44*E44 -> 184929.32 | M44: =I44*E44 -> 21129109 | N44: =M44*$N$2 -> 21129109 | Q44: PTO-0402 | R44: 1 | S44: APU P-38 | V44: 21129109 | W44: =M44-V44 -> 0.023775686 | X44: =IFERROR(W44/V44,0) -> 1.1252574e-09
A45: 4.03 | B45: MAMPOSTERÍA | C45: Muro tipo 4 (divisorio de unidades y fachadas) e: 15 cm -Ladrillo hueco 12 x 1 | D45: m2 | E45: 1008 | F45: =IF(Q45<>"",IFERROR(VLOOKUP(Q45,PARTIDAS!A:P,13,FALSE()),0),0) -> 12465.048 | G45: =IF(Q45<>"",IFERROR(VLOOKUP(Q45,PARTIDAS!A:P,14,FALSE()),0),0) -> 10761.176 | H45: =IF(Q45<>"",IFERROR(VLOOKUP(Q45,PARTIDAS!A:P,15,FALSE()),0),0) -> 255.78052 | I45: =F45+G45+H45 -> 23482.004 | J45: =F45*E45 -> 12564768 | K45: =G45*E45 -> 10847265 | L45: =H45*E45 -> 257826.77 | M45: =I45*E45 -> 23669860 | N45: =M45*$N$2 -> 23669860 | Q45: PTO-0403 | R45: 1 | S45: APU P-35 | V45: 23669850 | W45: =M45-V45 -> 10.08 | X45: =IFERROR(W45/V45,0) -> 4.2585821e-07
A46: 4.04 | B46: MAMPOSTERÍA | C46: Enchape medianeras existentes - Contemplamos picado zonas sueltas y enchape con | D46: m2 | E46: 199 | F46: =IF(Q46<>"",IFERROR(VLOOKUP(Q46,PARTIDAS!A:P,13,FALSE()),0),0) -> 6069.2196 | G46: =IF(Q46<>"",IFERROR(VLOOKUP(Q46,PARTIDAS!A:P,14,FALSE()),0),0) -> 5380.5879 | H46: =IF(Q46<>"",IFERROR(VLOOKUP(Q46,PARTIDAS!A:P,15,FALSE()),0),0) -> 255.78052 | I46: =F46+G46+H46 -> 11705.588 | J46: =F46*E46 -> 1207774.7 | K46: =G46*E46 -> 1070737 | L46: =H46*E46 -> 50900.324 | M46: =I46*E46 -> 2329412 | N46: =M46*$N$2 -> 2329412 | Q46: PTO-0404 | R46: 1 | S46: APU P-34 | V46: 2329385.6 | W46: =M46-V46 -> 26.417063 | X46: =IFERROR(W46/V46,0) -> 1.1340786e-05
A47: 4.05 | B47: MAMPOSTERÍA | C47: Muro de tabique seco ignifugo | D47: m2 | E47: 34 | F47: =IF(Q47<>"",IFERROR(VLOOKUP(Q47,PARTIDAS!A:P,13,FALSE()),0),0) -> 28944.117 | G47: =IF(Q47<>"",IFERROR(VLOOKUP(Q47,PARTIDAS!A:P,14,FALSE()),0),0) -> 27718.213 | H47: =IF(Q47<>"",IFERROR(VLOOKUP(Q47,PARTIDAS!A:P,15,FALSE()),0),0) -> 441.15834 | I47: =F47+G47+H47 -> 57103.488 | J47: =F47*E47 -> 984099.99 | K47: =G47*E47 -> 942419.23 | L47: =H47*E47 -> 14999.384 | M47: =I47*E47 -> 1941518.6 | N47: =M47*$N$2 -> 1941518.6 | Q47: PTO-0405 | R47: 1 | S47: APU P-65 | V47: 1941518.2 | W47: =M47-V47 -> 0.41526593 | X47: =IFERROR(W47/V47,0) -> 2.1388722e-07
A48: 4.06 | B48: MAMPOSTERÍA | C48: Vigas de encadenado - En muros de PB, incl. excavación y armado | D48: ml | E48: 24 | F48: =IF(Q48<>"",IFERROR(VLOOKUP(Q48,PARTIDAS!A:P,13,FALSE()),0),0) -> 23405.003 | G48: =IF(Q48<>"",IFERROR(VLOOKUP(Q48,PARTIDAS!A:P,14,FALSE()),0),0) -> 36357.144 | H48: =IF(Q48<>"",IFERROR(VLOOKUP(Q48,PARTIDAS!A:P,15,FALSE()),0),0) -> 896.43233 | I48: =F48+G48+H48 -> 60658.579 | J48: =F48*E48 -> 561720.08 | K48: =G48*E48 -> 872571.45 | L48: =H48*E48 -> 21514.376 | M48: =I48*E48 -> 1455805.9 | N48: =M48*$N$2 -> 1455805.9 | Q48: PTO-0406 | R48: 1 | S48: Tareas | V48: 1455806.1 | W48: =M48-V48 -> -0.2 | X48: =IFERROR(W48/V48,0) -> -1.3738093e-07
A49: 5 | C49: IMPERMEABILIZACIONES Y AISLACIONES | O49: =SUM(M50:M55) -> 12211939 | P49: =SUM(N50:N55) -> 12211939 | X49: =IFERROR(W49/V49,0) -> 0
A50: 5.01 | B50: IMPERMEABILIZACIONES Y AISLACIONES | C50: Aislación hidrófuga horizontal (baños) - Inc. membrana geotextil y 35% en concep | D50: m2 | E50: 79 | F50: =IF(Q50<>"",IFERROR(VLOOKUP(Q50,PARTIDAS!A:P,13,FALSE()),0),0) -> 11767.714 | G50: =IF(Q50<>"",IFERROR(VLOOKUP(Q50,PARTIDAS!A:P,14,FALSE()),0),0) -> 17247.086 | H50: =IF(Q50<>"",IFERROR(VLOOKUP(Q50,PARTIDAS!A:P,15,FALSE()),0),0) -> 34.976452 | I50: =F50+G50+H50 -> 29049.776 | J50: =F50*E50 -> 929649.4 | K50: =G50*E50 -> 1362519.8 | L50: =H50*E50 -> 2763.1397 | M50: =I50*E50 -> 2294932.3 | N50: =M50*$N$2 -> 2294932.3 | Q50: PTO-0501 | R50: 1 | S50: APU P-70 | V50: 2294931.7 | W50: =M50-V50 -> 0.68707387 | X50: =IFERROR(W50/V50,0) -> 2.9938751e-07
A51: 5.02 | B51: IMPERMEABILIZACIONES Y AISLACIONES | C51: Cajón hidrófugo - Muros de PB | D51: ml | E51: 113 | F51: =IF(Q51<>"",IFERROR(VLOOKUP(Q51,PARTIDAS!A:P,13,FALSE()),0),0) -> 827.27861 | G51: =IF(Q51<>"",IFERROR(VLOOKUP(Q51,PARTIDAS!A:P,14,FALSE()),0),0) -> 4324.0478 | H51: =IF(Q51<>"",IFERROR(VLOOKUP(Q51,PARTIDAS!A:P,15,FALSE()),0),0) -> 137.02528 | I51: =F51+G51+H51 -> 5288.3517 | J51: =F51*E51 -> 93482.483 | K51: =G51*E51 -> 488617.4 | L51: =H51*E51 -> 15483.857 | M51: =I51*E51 -> 597583.74 | N51: =M51*$N$2 -> 597583.74 | Q51: PTO-0502 | R51: 1 | S51: APU P-42 | V51: 597583.74 | W51: =M51-V51 -> 0 | X51: =IFERROR(W51/V51,0) -> 0
A52: 5.03 | B52: IMPERMEABILIZACIONES Y AISLACIONES | C52: Azotado hidrófugo - Sobre contrapiso en vereda y PB | D52: m2 | E52: 207 | F52: =IF(Q52<>"",IFERROR(VLOOKUP(Q52,PARTIDAS!A:P,13,FALSE()),0),0) -> 827.27861 | G52: =IF(Q52<>"",IFERROR(VLOOKUP(Q52,PARTIDAS!A:P,14,FALSE()),0),0) -> 4324.0478 | H52: =IF(Q52<>"",IFERROR(VLOOKUP(Q52,PARTIDAS!A:P,15,FALSE()),0),0) -> 137.02528 | I52: =F52+G52+H52 -> 5288.3517 | J52: =F52*E52 -> 171246.67 | K52: =G52*E52 -> 895077.89 | L52: =H52*E52 -> 28364.233 | M52: =I52*E52 -> 1094688.8 | N52: =M52*$N$2 -> 1094688.8 | Q52: PTO-0503 | R52: 1 | S52: APU P-42 | V52: 1094688.8 | W52: =M52-V52 -> 0 | X52: =IFERROR(W52/V52,0) -> 0
A53: 5.04 | B53: IMPERMEABILIZACIONES Y AISLACIONES | C53: Aislación térmica en terrazas, eps e:2,00 cm | D53: m2 | E53: 165 | F53: =IF(Q53<>"",IFERROR(VLOOKUP(Q53,PARTIDAS!A:P,13,FALSE()),0),0) -> 3538.08 | G53: =IF(Q53<>"",IFERROR(VLOOKUP(Q53,PARTIDAS!A:P,14,FALSE()),0),0) -> 0 | H53: =IF(Q53<>"",IFERROR(VLOOKUP(Q53,PARTIDAS!A:P,15,FALSE()),0),0) -> 0 | I53: =F53+G53+H53 -> 3538.08 | J53: =F53*E53 -> 583783.2 | K53: =G53*E53 -> 0 | L53: =H53*E53 -> 0 | M53: =I53*E53 -> 583783.2 | N53: =M53*$N$2 -> 583783.2 | Q53: PTO-0504 | R53: 1 | S53: lump_directo | V53: 583783.2 | W53: =M53-V53 -> 0 | X53: =IFERROR(W53/V53,0) -> 0
A54: 5.05 | B54: IMPERMEABILIZACIONES Y AISLACIONES | C54: Barrera de vapor | D54: m2 | E54: 165 | F54: =IF(Q54<>"",IFERROR(VLOOKUP(Q54,PARTIDAS!A:P,13,FALSE()),0),0) -> 1393.4782 | G54: =IF(Q54<>"",IFERROR(VLOOKUP(Q54,PARTIDAS!A:P,14,FALSE()),0),0) -> 2017.7205 | H54: =IF(Q54<>"",IFERROR(VLOOKUP(Q54,PARTIDAS!A:P,15,FALSE()),0),0) -> 10.930141 | I54: =F54+G54+H54 -> 3422.1288 | J54: =F54*E54 -> 229923.9 | K54: =G54*E54 -> 332923.88 | L54: =H54*E54 -> 1803.4733 | M54: =I54*E54 -> 564651.25 | N54: =M54*$N$2 -> 564651.25 | Q54: PTO-0505 | R54: 1 | S54: APU P-113 | V54: 564507.96 | W54: =M54-V54 -> 143.29015 | X54: =IFERROR(W54/V54,0) -> 0.00025383193
A55: 5.06 | B55: IMPERMEABILIZACIONES Y AISLACIONES | C55: Membrana asfaltica geotextil 4mm - Balcones y azotea - Inc. 20% en concepto de b | D55: m2 | E55: 274 | F55: =IF(Q55<>"",IFERROR(VLOOKUP(Q55,PARTIDAS!A:P,13,FALSE()),0),0) -> 10460.191 | G55: =IF(Q55<>"",IFERROR(VLOOKUP(Q55,PARTIDAS!A:P,14,FALSE()),0),0) -> 15330.743 | H55: =IF(Q55<>"",IFERROR(VLOOKUP(Q55,PARTIDAS!A:P,15,FALSE()),0),0) -> 34.976452 | I55: =F55+G55+H55 -> 25825.911 | J55: =F55*E55 -> 2866092.4 | K55: =G55*E55 -> 4200623.6 | L55: =H55*E55 -> 9583.5479 | M55: =I55*E55 -> 7076299.6 | N55: =M55*$N$2 -> 7076299.6 | Q55: PTO-0506 | R55: 1 | S55: APU P-70 | V55: 7076297.2 | W55: =M55-V55 -> 2.3830157 | X55: =IFERROR(W55/V55,0) -> 3.3676026e-07
A56: 6 | C56: CONTRAPISOS | O56: =SUM(M57:M57) -> 1090680.2 | P56: =SUM(N57:N57) -> 1090680.2 | X56: =IFERROR(W56/V56,0) -> 0
A57: 6.01 | B57: CONTRAPISOS | C57: Babeta de chapa galvanizada en medianeras | D57: ml | E57: 44 | F57: =IF(Q57<>"",IFERROR(VLOOKUP(Q57,PARTIDAS!A:P,13,FALSE()),0),0) -> 16294.977 | G57: =IF(Q57<>"",IFERROR(VLOOKUP(Q57,PARTIDAS!A:P,14,FALSE()),0),0) -> 8126.8836 | H57: =IF(Q57<>"",IFERROR(VLOOKUP(Q57,PARTIDAS!A:P,15,FALSE()),0),0) -> 366.327 | I57: =F57+G57+H57 -> 24788.187 | J57: =F57*E57 -> 716978.97 | K57: =G57*E57 -> 357582.88 | L57: =H57*E57 -> 16118.388 | M57: =I57*E57 -> 1090680.2 | N57: =M57*$N$2 -> 1090680.2 | Q57: PTO-0601 | R57: 1 | S57: Tareas | V57: 1090677.6 | W57: =M57-V57 -> 2.6525472 | X57: =IFERROR(W57/V57,0) -> 2.4320177e-06
A58: 7 | C58: REVOQUES | O58: =SUM(M59:M66) -> 1.1177094e+08 | P58: =SUM(N59:N66) -> 1.1177094e+08 | X58: =IFERROR(W58/V58,0) -> 0
A59: 7.01 | B59: REVOQUES | C59: Revoque Grueso Impermeable Exterior | D59: m2 | E59: 663 | F59: =IF(Q59<>"",IFERROR(VLOOKUP(Q59,PARTIDAS!A:P,13,FALSE()),0),0) -> 4061.1651 | G59: =IF(Q59<>"",IFERROR(VLOOKUP(Q59,PARTIDAS!A:P,14,FALSE()),0),0) -> 11697.516 | H59: =IF(Q59<>"",IFERROR(VLOOKUP(Q59,PARTIDAS!A:P,15,FALSE()),0),0) -> 333.62677 | I59: =F59+G59+H59 -> 16092.308 | J59: =F59*E59 -> 2692552.5 | K59: =G59*E59 -> 7755453.3 | L59: =H59*E59 -> 221194.55 | M59: =I59*E59 -> 10669200 | N59: =M59*$N$2 -> 10669200 | Q59: PTO-0701 | R59: 1 | S59: APU P-44 | V59: 10669200 | W59: =M59-V59 -> -2.7939677e-08 | X59: =IFERROR(W59/V59,0) -> -2.6187227e-15
A60: 7.02 | B60: REVOQUES | C60: Revoque Grueso Impermeable Exterior a mas de 3m - Medianero y fachadas | D60: m2 | E60: 1164 | F60: =IF(Q60<>"",IFERROR(VLOOKUP(Q60,PARTIDAS!A:P,13,FALSE()),0),0) -> 4061.1651 | G60: =IF(Q60<>"",IFERROR(VLOOKUP(Q60,PARTIDAS!A:P,14,FALSE()),0),0) -> 16815.18 | H60: =IF(Q60<>"",IFERROR(VLOOKUP(Q60,PARTIDAS!A:P,15,FALSE()),0),0) -> 863.36281 | I60: =F60+G60+H60 -> 21739.708 | J60: =F60*E60 -> 4727196.2 | K60: =G60*E60 -> 19572869 | L60: =H60*E60 -> 1004954.3 | M60: =I60*E60 -> 25305020 | N60: =M60*$N$2 -> 25305020 | Q60: PTO-0702 | R60: 1 | S60: APU P-45 | V60: 25305020 | W60: =M60-V60 -> 0 | X60: =IFERROR(W60/V60,0) -> 0
A61: 7.03 | B61: REVOQUES | C61: Buña en revoque - Estimados ml en medianeras | D61: ml | E61: 500 | F61: =IF(Q61<>"",IFERROR(VLOOKUP(Q61,PARTIDAS!A:P,13,FALSE()),0),0) -> 0 | G61: =IF(Q61<>"",IFERROR(VLOOKUP(Q61,PARTIDAS!A:P,14,FALSE()),0),0) -> 11122.339 | H61: =IF(Q61<>"",IFERROR(VLOOKUP(Q61,PARTIDAS!A:P,15,FALSE()),0),0) -> 0 | I61: =F61+G61+H61 -> 11122.339 | J61: =F61*E61 -> 0 | K61: =G61*E61 -> 5561169.6 | L61: =H61*E61 -> 0 | M61: =I61*E61 -> 5561169.6 | N61: =M61*$N$2 -> 5561169.6 | Q61: PTO-0703 | R61: 1 | S61: lump_directo | V61: 5561169.6 | W61: =M61-V61 -> 0 | X61: =IFERROR(W61/V61,0) -> 0
A62: 7.04 | B62: REVOQUES | C62: Revoque Grueso Interior + fino | D62: m2 | E62: 521 | F62: =IF(Q62<>"",IFERROR(VLOOKUP(Q62,PARTIDAS!A:P,13,FALSE()),0),0) -> 2891.2175 | G62: =IF(Q62<>"",IFERROR(VLOOKUP(Q62,PARTIDAS!A:P,14,FALSE()),0),0) -> 22980.577 | H62: =IF(Q62<>"",IFERROR(VLOOKUP(Q62,PARTIDAS!A:P,15,FALSE()),0),0) -> 639.45131 | I62: =F62+G62+H62 -> 26511.246 | J62: =F62*E62 -> 1506324.3 | K62: =G62*E62 -> 11972881 | L62: =H62*E62 -> 333154.13 | M62: =I62*E62 -> 13812359 | N62: =M62*$N$2 -> 13812359 | Q62: PTO-0704 | R62: 1 | S62: APU P-43 | V62: 13812359 | W62: =M62-V62 -> 2.2351742e-08 | X62: =IFERROR(W62/V62,0) -> 1.6182422e-15
A63: 7.05 | B63: REVOQUES | C63: Yeso interior | D63: m2 | E63: 2180 | F63: =IF(Q63<>"",IFERROR(VLOOKUP(Q63,PARTIDAS!A:P,13,FALSE()),0),0) -> 5780.8364 | G63: =IF(Q63<>"",IFERROR(VLOOKUP(Q63,PARTIDAS!A:P,14,FALSE()),0),0) -> 12252.549 | H63: =IF(Q63<>"",IFERROR(VLOOKUP(Q63,PARTIDAS!A:P,15,FALSE()),0),0) -> 270.50123 | I63: =F63+G63+H63 -> 18303.886 | J63: =F63*E63 -> 12602223 | K63: =G63*E63 -> 26710556 | L63: =H63*E63 -> 589692.69 | M63: =I63*E63 -> 39902472 | N63: =M63*$N$2 -> 39902472 | Q63: PTO-0705 | R63: 1 | S63: Tareas | V63: 39902538 | W63: =M63-V63 -> -66.410915 | X63: =IFERROR(W63/V63,0) -> -1.6643281e-06
A64: 7.06 | B64: REVOQUES | C64: Arista en yeso | D64: ml | E64: 255 | F64: =IF(Q64<>"",IFERROR(VLOOKUP(Q64,PARTIDAS!A:P,13,FALSE()),0),0) -> 0 | G64: =IF(Q64<>"",IFERROR(VLOOKUP(Q64,PARTIDAS!A:P,14,FALSE()),0),0) -> 13144.583 | H64: =IF(Q64<>"",IFERROR(VLOOKUP(Q64,PARTIDAS!A:P,15,FALSE()),0),0) -> 197.16874 | I64: =F64+G64+H64 -> 13341.751 | J64: =F64*E64 -> 0 | K64: =G64*E64 -> 3351868.6 | L64: =H64*E64 -> 50278.029 | M64: =I64*E64 -> 3402146.6 | N64: =M64*$N$2 -> 3402146.6 | Q64: PTO-0706 | R64: 1 | S64: Tareas | V64: 3402146.6 | W64: =M64-V64 -> 8.3819032e-09 | X64: =IFERROR(W64/V64,0) -> 2.4637102e-15
A65: 7.07 | B65: REVOQUES | C65: Provisión y colocación de guardacanto yesero | D65: u | E65: 102 | F65: =IF(Q65<>"",IFERROR(VLOOKUP(Q65,PARTIDAS!A:P,13,FALSE()),0),0) -> 1658.1184 | G65: =IF(Q65<>"",IFERROR(VLOOKUP(Q65,PARTIDAS!A:P,14,FALSE()),0),0) -> 13917.8 | H65: =IF(Q65<>"",IFERROR(VLOOKUP(Q65,PARTIDAS!A:P,15,FALSE()),0),0) -> 233.63867 | I65: =F65+G65+H65 -> 15809.557 | J65: =F65*E65 -> 169128.08 | K65: =G65*E65 -> 1419615.6 | L65: =H65*E65 -> 23831.144 | M65: =I65*E65 -> 1612574.8 | N65: =M65*$N$2 -> 1612574.8 | Q65: PTO-0707 | R65: 1 | S65: Tareas | V65: 1612574.1 | W65: =M65-V65 -> 0.70610797 | X65: =IFERROR(W65/V65,0) -> 4.378763e-07
A66: 7.08 | B66: REVOQUES | C66: Revoque Grueso Impermeable Interior b/ revestimiento | D66: m2 | E66: 715 | F66: =IF(Q66<>"",IFERROR(VLOOKUP(Q66,PARTIDAS!A:P,13,FALSE()),0),0) -> 4061.1651 | G66: =IF(Q66<>"",IFERROR(VLOOKUP(Q66,PARTIDAS!A:P,14,FALSE()),0),0) -> 11697.516 | H66: =IF(Q66<>"",IFERROR(VLOOKUP(Q66,PARTIDAS!A:P,15,FALSE()),0),0) -> 333.62677 | I66: =F66+G66+H66 -> 16092.308 | J66: =F66*E66 -> 2903733 | K66: =G66*E66 -> 8363724.1 | L66: =H66*E66 -> 238543.14 | M66: =I66*E66 -> 11506000 | N66: =M66*$N$2 -> 11506000 | Q66: PTO-0708 | R66: 1 | S66: APU P-44 | V66: 11506000 | W66: =M66-V66 -> 0 | X66: =IFERROR(W66/V66,0) -> 0
A67: 8 | C67: AISLACIONES | O67: =SUM(M68:M75) -> 36751191 | P67: =SUM(N68:N75) -> 36751191 | X67: =IFERROR(W67/V67,0) -> 0
A68: 8.01 | B68: AISLACIONES | C68: Contrapiso de cascotes s/ss e: 15 cm | D68: m2 | E68: 21 | F68: =IF(Q68<>"",IFERROR(VLOOKUP(Q68,PARTIDAS!A:P,13,FALSE()),0),0) -> 13595.327 | G68: =IF(Q68<>"",IFERROR(VLOOKUP(Q68,PARTIDAS!A:P,14,FALSE()),0),0) -> 19696.193 | H68: =IF(Q68<>"",IFERROR(VLOOKUP(Q68,PARTIDAS!A:P,15,FALSE()),0),0) -> 503.75749 | I68: =F68+G68+H68 -> 33795.278 | J68: =F68*E68 -> 285501.86 | K68: =G68*E68 -> 413620.06 | L68: =H68*E68 -> 10578.907 | M68: =I68*E68 -> 709700.83 | N68: =M68*$N$2 -> 709700.83 | Q68: PTO-0801 | R68: 1 | S68: APU P-46 | V68: 709700.83 | W68: =M68-V68 -> 0 | X68: =IFERROR(W68/V68,0) -> 0
A69: 8.02 | B69: AISLACIONES | C69: Contrapiso armado de H° pobre s/terreno natural e: 20 cm - Incluye film de polie | D69: m2 | E69: 201 | F69: =IF(Q69<>"",IFERROR(VLOOKUP(Q69,PARTIDAS!A:P,13,FALSE()),0),0) -> 30954.653 | G69: =IF(Q69<>"",IFERROR(VLOOKUP(Q69,PARTIDAS!A:P,14,FALSE()),0),0) -> 8768.7577 | H69: =IF(Q69<>"",IFERROR(VLOOKUP(Q69,PARTIDAS!A:P,15,FALSE()),0),0) -> 595.85225 | I69: =F69+G69+H69 -> 40319.263 | J69: =F69*E69 -> 6221885.3 | K69: =G69*E69 -> 1762520.3 | L69: =H69*E69 -> 119766.3 | M69: =I69*E69 -> 8104171.9 | N69: =M69*$N$2 -> 8104171.9 | Q69: PTO-0802 | R69: 1 | S69: Tareas | V69: 8104186.4 | W69: =M69-V69 -> -14.482533 | X69: =IFERROR(W69/V69,0) -> -1.7870435e-06
A70: 8.03 | B70: AISLACIONES | C70: Contrapiso de cascotes en azoteas c/pendiente e: 15 cm | D70: m2 | E70: 107 | F70: =IF(Q70<>"",IFERROR(VLOOKUP(Q70,PARTIDAS!A:P,13,FALSE()),0),0) -> 13595.327 | G70: =IF(Q70<>"",IFERROR(VLOOKUP(Q70,PARTIDAS!A:P,14,FALSE()),0),0) -> 19696.193 | H70: =IF(Q70<>"",IFERROR(VLOOKUP(Q70,PARTIDAS!A:P,15,FALSE()),0),0) -> 503.75749 | I70: =F70+G70+H70 -> 33795.278 | J70: =F70*E70 -> 1454700 | K70: =G70*E70 -> 2107492.7 | L70: =H70*E70 -> 53902.052 | M70: =I70*E70 -> 3616094.7 | N70: =M70*$N$2 -> 3616094.7 | Q70: PTO-0803 | R70: 1 | S70: APU P-46 | V70: 3616094.7 | W70: =M70-V70 -> 0 | X70: =IFERROR(W70/V70,0) -> 0
A71: 8.04 | B71: AISLACIONES | C71: Contrapiso - Carpeta monolitico e: 6 cm | D71: m2 | E71: 850 | F71: =IF(Q71<>"",IFERROR(VLOOKUP(Q71,PARTIDAS!A:P,13,FALSE()),0),0) -> 6717.8752 | G71: =IF(Q71<>"",IFERROR(VLOOKUP(Q71,PARTIDAS!A:P,14,FALSE()),0),0) -> 11145.022 | H71: =IF(Q71<>"",IFERROR(VLOOKUP(Q71,PARTIDAS!A:P,15,FALSE()),0),0) -> 130.47811 | I71: =F71+G71+H71 -> 17993.375 | J71: =F71*E71 -> 5710194 | K71: =G71*E71 -> 9473268.8 | L71: =H71*E71 -> 110906.39 | M71: =I71*E71 -> 15294369 | N71: =M71*$N$2 -> 15294369 | Q71: PTO-0804 | R71: 1 | S71: APU P-48 | V71: 15294369 | W71: =M71-V71 -> 3.5390258e-08 | X71: =IFERROR(W71/V71,0) -> 2.3139404e-15
A72: 8.05 | B72: AISLACIONES | C72: Carpeta en PB, balcones, baños y azoteas e: 3,00 cm | D72: m2 | E72: 365 | F72: =IF(Q72<>"",IFERROR(VLOOKUP(Q72,PARTIDAS!A:P,13,FALSE()),0),0) -> 3420.3193 | G72: =IF(Q72<>"",IFERROR(VLOOKUP(Q72,PARTIDAS!A:P,14,FALSE()),0),0) -> 8295.6908 | H72: =IF(Q72<>"",IFERROR(VLOOKUP(Q72,PARTIDAS!A:P,15,FALSE()),0),0) -> 235.08683 | I72: =F72+G72+H72 -> 11951.097 | J72: =F72*E72 -> 1248416.6 | K72: =G72*E72 -> 3027927.2 | L72: =H72*E72 -> 85806.693 | M72: =I72*E72 -> 4362150.4 | N72: =M72*$N$2 -> 4362150.4 | Q72: PTO-0805 | R72: 1 | S72: APU P-47 | V72: 4362150.4 | W72: =M72-V72 -> 0 | X72: =IFERROR(W72/V72,0) -> 0
A73: 8.06 | B73: AISLACIONES | C73: Carpeta sobre membrana, e: 3,00 cm | D73: m2 | E73: 357 | F73: =IF(Q73<>"",IFERROR(VLOOKUP(Q73,PARTIDAS!A:P,13,FALSE()),0),0) -> 3420.3193 | G73: =IF(Q73<>"",IFERROR(VLOOKUP(Q73,PARTIDAS!A:P,14,FALSE()),0),0) -> 8295.6908 | H73: =IF(Q73<>"",IFERROR(VLOOKUP(Q73,PARTIDAS!A:P,15,FALSE()),0),0) -> 235.08683 | I73: =F73+G73+H73 -> 11951.097 | J73: =F73*E73 -> 1221054 | K73: =G73*E73 -> 2961561.6 | L73: =H73*E73 -> 83925.998 | M73: =I73*E73 -> 4266541.6 | N73: =M73*$N$2 -> 4266541.6 | Q73: PTO-0806 | R73: 1 | S73: APU P-47 | V73: 4266541.6 | W73: =M73-V73 -> 0 | X73: =IFERROR(W73/V73,0) -> 0
A74: 8.07 | B74: AISLACIONES | C74: Banquinas para cocinas - N/A | D74: gl | E74: 0 | F74: =IF(Q74<>"",IFERROR(VLOOKUP(Q74,PARTIDAS!A:P,13,FALSE()),0),0) -> 0 | G74: =IF(Q74<>"",IFERROR(VLOOKUP(Q74,PARTIDAS!A:P,14,FALSE()),0),0) -> 0 | H74: =IF(Q74<>"",IFERROR(VLOOKUP(Q74,PARTIDAS!A:P,15,FALSE()),0),0) -> 0 | I74: =F74+G74+H74 -> 0 | J74: =F74*E74 -> 0 | K74: =G74*E74 -> 0 | L74: =H74*E74 -> 0 | M74: =I74*E74 -> 0 | N74: =M74*$N$2 -> 0 | Q74: PTO-0807 | R74: 1 | S74: lump_directo | V74: 0 | W74: =M74-V74 -> 0 | X74: =IFERROR(W74/V74,0) -> 0
A75: 8.08 | B75: AISLACIONES | C75: Banquinas para bombas, TT, etc. h: 15 cm | D75: gl | E75: 1 | F75: =IF(Q75<>"",IFERROR(VLOOKUP(Q75,PARTIDAS!A:P,13,FALSE()),0),0) -> 88498.55 | G75: =IF(Q75<>"",IFERROR(VLOOKUP(Q75,PARTIDAS!A:P,14,FALSE()),0),0) -> 303706.02 | H75: =IF(Q75<>"",IFERROR(VLOOKUP(Q75,PARTIDAS!A:P,15,FALSE()),0),0) -> 5957.8657 | I75: =F75+G75+H75 -> 398162.44 | J75: =F75*E75 -> 88498.55 | K75: =G75*E75 -> 303706.02 | L75: =H75*E75 -> 5957.8657 | M75: =I75*E75 -> 398162.44 | N75: =M75*$N$2 -> 398162.44 | Q75: PTO-0808 | R75: 1 | S75: Tareas | V75: 398087.64 | W75: =M75-V75 -> 74.797098 | X75: =IFERROR(W75/V75,0) -> 0.00018789103 | Y75: mal presupuestado. OTR-PTO081 en vez de OTR-PTO081B
A76: 9 | C76: PISOS | O76: =SUM(M77:M79) -> 5878466.6 | P76: =SUM(N77:N79) -> 5878466.6 | X76: =IFERROR(W76/V76,0) -> 0
A77: 9.01 | B77: PISOS | C77: Provisión y ejecución de alisado de cemento en pedadas y alzadas | D77: gl | E77: 1 | F77: =IF(Q77<>"",IFERROR(VLOOKUP(Q77,PARTIDAS!A:P,13,FALSE()),0),0) -> 427516.45 | G77: =IF(Q77<>"",IFERROR(VLOOKUP(Q77,PARTIDAS!A:P,14,FALSE()),0),0) -> 2044758.2 | H77: =IF(Q77<>"",IFERROR(VLOOKUP(Q77,PARTIDAS!A:P,15,FALSE()),0),0) -> 37083.997 | I77: =F77+G77+H77 -> 2509358.6 | J77: =F77*E77 -> 427516.45 | K77: =G77*E77 -> 2044758.2 | L77: =H77*E77 -> 37083.997 | M77: =I77*E77 -> 2509358.6 | N77: =M77*$N$2 -> 2509358.6 | Q77: PTO-0901 | R77: 1 | S77: Tareas | V77: 2509350.4 | W77: =M77-V77 -> 8.2087664 | X77: =IFERROR(W77/V77,0) -> 3.2712714e-06
A78: 9.02 | B78: PISOS | C78: Provisión y colocación de nariz metálica en escalones | D78: gl | E78: 1 | F78: =IF(Q78<>"",IFERROR(VLOOKUP(Q78,PARTIDAS!A:P,13,FALSE()),0),0) -> 463902.77 | G78: =IF(Q78<>"",IFERROR(VLOOKUP(Q78,PARTIDAS!A:P,14,FALSE()),0),0) -> 1775796.2 | H78: =IF(Q78<>"",IFERROR(VLOOKUP(Q78,PARTIDAS!A:P,15,FALSE()),0),0) -> 33595.485 | I78: =F78+G78+H78 -> 2273294.5 | J78: =F78*E78 -> 463902.77 | K78: =G78*E78 -> 1775796.2 | L78: =H78*E78 -> 33595.485 | M78: =I78*E78 -> 2273294.5 | N78: =M78*$N$2 -> 2273294.5 | Q78: PTO-0902 | R78: 1 | S78: Tareas | V78: 2273294.5 | W78: =M78-V78 -> -6.519258e-09 | X78: =IFERROR(W78/V78,0) -> -2.8677579e-15
A79: 9.03 | B79: PISOS | C79: Zócalo de concreto en escalera - No incluye el ojo | D79: ml | E79: 114 | F79: =IF(Q79<>"",IFERROR(VLOOKUP(Q79,PARTIDAS!A:P,13,FALSE()),0),0) -> 827.27861 | G79: =IF(Q79<>"",IFERROR(VLOOKUP(Q79,PARTIDAS!A:P,14,FALSE()),0),0) -> 8648.0955 | H79: =IF(Q79<>"",IFERROR(VLOOKUP(Q79,PARTIDAS!A:P,15,FALSE()),0),0) -> 137.02528 | I79: =F79+G79+H79 -> 9612.3994 | J79: =F79*E79 -> 94309.762 | K79: =G79*E79 -> 985882.89 | L79: =H79*E79 -> 15620.882 | M79: =I79*E79 -> 1095813.5 | N79: =M79*$N$2 -> 1095813.5 | Q79: PTO-0903 | R79: 1 | S79: APU P-42 | V79: 1095813.5 | W79: =M79-V79 -> -3.259629e-09 | X79: =IFERROR(W79/V79,0) -> -2.9746201e-15
A80: 10 | C80: CERÁMICOS | O80: =SUM(M81:M83) -> 4784536 | P80: =SUM(N81:N83) -> 4784536 | X80: =IFERROR(W80/V80,0) -> 0
A81: 10.01 | B81: CERÁMICOS | C81: Colocación de ventilación de conducto de humos. Inc. toma de aire en PB | D81: gl | E81: 1 | F81: =IF(Q81<>"",IFERROR(VLOOKUP(Q81,PARTIDAS!A:P,13,FALSE()),0),0) -> 250000 | G81: =IF(Q81<>"",IFERROR(VLOOKUP(Q81,PARTIDAS!A:P,14,FALSE()),0),0) -> 1663092.8 | H81: =IF(Q81<>"",IFERROR(VLOOKUP(Q81,PARTIDAS!A:P,15,FALSE()),0),0) -> 28696.391 | I81: =F81+G81+H81 -> 1941789.2 | J81: =F81*E81 -> 250000 | K81: =G81*E81 -> 1663092.8 | L81: =H81*E81 -> 28696.391 | M81: =I81*E81 -> 1941789.2 | N81: =M81*$N$2 -> 1941789.2 | Q81: PTO-1001 | R81: 1 | S81: Tareas | V81: 1941789.2 | W81: =M81-V81 -> 0 | X81: =IFERROR(W81/V81,0) -> 0
A82: 10.02 | B82: CERÁMICOS | C82: Colocación y montaje de conducto de ventilación en baños | D82: gl | E82: 1 | F82: =IF(Q82<>"",IFERROR(VLOOKUP(Q82,PARTIDAS!A:P,13,FALSE()),0),0) -> 250000 | G82: =IF(Q82<>"",IFERROR(VLOOKUP(Q82,PARTIDAS!A:P,14,FALSE()),0),0) -> 1663092.8 | H82: =IF(Q82<>"",IFERROR(VLOOKUP(Q82,PARTIDAS!A:P,15,FALSE()),0),0) -> 28696.391 | I82: =F82+G82+H82 -> 1941789.2 | J82: =F82*E82 -> 250000 | K82: =G82*E82 -> 1663092.8 | L82: =H82*E82 -> 28696.391 | M82: =I82*E82 -> 1941789.2 | N82: =M82*$N$2 -> 1941789.2 | Q82: PTO-1002 | R82: 1 | S82: Tareas | V82: 1941789.2 | W82: =M82-V82 -> 0 | X82: =IFERROR(W82/V82,0) -> 0
A83: 10.03 | B83: CERÁMICOS | C83: Colocación sombreretes en chapa prepintada C25 - Provisión en item 26 | D83: u | E83: 7 | F83: =IF(Q83<>"",IFERROR(VLOOKUP(Q83,PARTIDAS!A:P,13,FALSE()),0),0) -> 31772.202 | G83: =IF(Q83<>"",IFERROR(VLOOKUP(Q83,PARTIDAS!A:P,14,FALSE()),0),0) -> 95033.943 | H83: =IF(Q83<>"",IFERROR(VLOOKUP(Q83,PARTIDAS!A:P,15,FALSE()),0),0) -> 1902.0923 | I83: =F83+G83+H83 -> 128708.24 | J83: =F83*E83 -> 222405.41 | K83: =G83*E83 -> 665237.6 | L83: =H83*E83 -> 13314.646 | M83: =I83*E83 -> 900957.66 | N83: =M83*$N$2 -> 900957.66 | Q83: PTO-1003 | R83: 1 | S83: Tareas | V83: 900957.72 | W83: =M83-V83 -> -0.057087089 | X83: =IFERROR(W83/V83,0) -> -6.3362672e-08
A84: 11 | C84: CARPINTERÍA | O84: =SUM(M85:M91) -> 27324425 | P84: =SUM(N85:N91) -> 27324425 | X84: =IFERROR(W84/V84,0) -> 0
A85: 11.01 | B85: CARPINTERÍA | C85: Colocación de baldosas en palieres- Provisión a cargo del comitente | D85: m2 | E85: 101 | F85: =IF(Q85<>"",IFERROR(VLOOKUP(Q85,PARTIDAS!A:P,13,FALSE()),0),0) -> 6932.2708 | G85: =IF(Q85<>"",IFERROR(VLOOKUP(Q85,PARTIDAS!A:P,14,FALSE()),0),0) -> 12793.021 | H85: =IF(Q85<>"",IFERROR(VLOOKUP(Q85,PARTIDAS!A:P,15,FALSE()),0),0) -> 245.43421 | I85: =F85+G85+H85 -> 19970.726 | J85: =F85*E85 -> 700159.35 | K85: =G85*E85 -> 1292095.1 | L85: =H85*E85 -> 24788.855 | M85: =I85*E85 -> 2017043.4 | N85: =M85*$N$2 -> 2017043.4 | Q85: PTO-1101 | R85: 1 | S85: APU P-56 | V85: 2017043.4 | W85: =M85-V85 -> -4.8894435e-09 | X85: =IFERROR(W85/V85,0) -> -2.4240647e-15
A86: 11.02 | B86: CARPINTERÍA | C86: Colocación de porcelanato en UF - Provisión a cargo del comitente | D86: m2 | E86: 898 | F86: =IF(Q86<>"",IFERROR(VLOOKUP(Q86,PARTIDAS!A:P,13,FALSE()),0),0) -> 6932.2708 | G86: =IF(Q86<>"",IFERROR(VLOOKUP(Q86,PARTIDAS!A:P,14,FALSE()),0),0) -> 12793.021 | H86: =IF(Q86<>"",IFERROR(VLOOKUP(Q86,PARTIDAS!A:P,15,FALSE()),0),0) -> 245.43421 | I86: =F86+G86+H86 -> 19970.726 | J86: =F86*E86 -> 6225179.2 | K86: =G86*E86 -> 11488133 | L86: =H86*E86 -> 220399.92 | M86: =I86*E86 -> 17933712 | N86: =M86*$N$2 -> 17933712 | Q86: PTO-1102 | R86: 1 | S86: APU P-56 | V86: 17933712 | W86: =M86-V86 -> -4.8428774e-08 | X86: =IFERROR(W86/V86,0) -> -2.7004322e-15
A87: 11.03 | B87: CARPINTERÍA | C87: Colocación de porcelanato en baños - Provisión a cargo del comitente | D87: m2 | E87: 88 | F87: =IF(Q87<>"",IFERROR(VLOOKUP(Q87,PARTIDAS!A:P,13,FALSE()),0),0) -> 6932.2708 | G87: =IF(Q87<>"",IFERROR(VLOOKUP(Q87,PARTIDAS!A:P,14,FALSE()),0),0) -> 16630.928 | H87: =IF(Q87<>"",IFERROR(VLOOKUP(Q87,PARTIDAS!A:P,15,FALSE()),0),0) -> 319.06447 | I87: =F87+G87+H87 -> 23882.263 | J87: =F87*E87 -> 610039.83 | K87: =G87*E87 -> 1463521.6 | L87: =H87*E87 -> 28077.674 | M87: =I87*E87 -> 2101639.1 | N87: =M87*$N$2 -> 2101639.1 | Q87: PTO-1103 | R87: 1 | S87: APU P-57 | V87: 2101639.1 | W87: =M87-V87 -> 0 | X87: =IFERROR(W87/V87,0) -> 0
