Workbook

Sheet 0_CONFIG
A1: CONFIGURACIÓN DE OBRA
A3: Obra | B3: Edificio GDR 3760 — García del Río 3760
A4: Estado | B4: En ejecución
A5: Fecha de inicio de obra | B5: 45689 | C5: (presupuesto cerrado dic-2024)
A6: Duración estimada (meses) | B6: 18 | C6: feb-2025 a ago-2026
A7: — ÍNDICE CAC —
A8: Mes base CAC | B8: ='0_Indice_CAC'!A4 -> 45627 | C8: fecha base del presupuesto
A9: Valor CAC base | B9: ='0_Indice_CAC'!B4 -> 15356.4 | C9: valor del índice en mes base
A10: Mes CAC más reciente cargado | B10: =INDEX('0_Indice_CAC'!A:A,MATCH(1E+300,'0_Indice_CAC'!B:B)) -> 46174 | C10: último mes con valor en B
A11: Ratio CAC mes corriente | B11: =MIN('0_Indice_CAC'!D:D) -> 0.79437459 | C11: ratio del mes más reciente
A13: — COEFICIENTE K —
A14: K (coeficiente GG+B) | B14: ='1_GGBB'!F67 -> 1.4355353 | C14: incluye GG + Equipos + Imprevistos + Beneficio
A15: % GG+B sobre costo | B15: ='1_GGBB'!F65 -> 0.43553532 | C15: sumatoria sin el 1
A17: — PRESUPUESTO —
A18: Costo total presupuestado | B18: =SUMPRODUCT(('1_Presupuesto'!$K$5:$K$227+'1_Presupuesto'!$L$5:$L$227+'1_Presupuesto'!$M$5:$M$227)*'1_Presupuesto'!$J$5:$J$227) -> 9.9459803e+08 | C18: costo controlable por rubro (excl. EQ $21.5M)
A19: Precio de venta total | B19: =SUMPRODUCT('1_Presupuesto'!$O$5:$O$227*'1_Presupuesto'!$J$5:$J$227)*B14 -> 1.4587531e+09 | C19: costo × K
A20: Sanity Check (P. Costo) | B20: =SUMPRODUCT('1_Presupuesto'!$P$5:$P$227*'1_Presupuesto'!$J$5:$J$227)-B19 -> 0
A21: — NOTAS DE VERSIÓN —
A22: Versión | B22: Resumen GDR 3760 — v7 (Cash Flow Monto Base + 6 mejoras Cat. A)
A23: Hojas eliminadas en Tanda 1 | B23: "HOJA DE OBRA", "Certificaciones de avance" (vieja)
A24: Bugs corregidos | B24: CAC D17-D20 contra $B$2; K vinculado a GGBB!F67; cols fantasma Gastos
A25: Columna nueva en Gastos | B25: U: "Contrato" — llenar SC-XXX en pagos a subcontratos
A27: — TANDA 2 (rediseño certificación/facturación) —
A28: Hojas eliminadas en T2 | B28: "Cert. Pto. 01", "Cert. Pto. 02", "Certificados", "Facturacion", "Preventivo Vta", "Contratistas"
A29: Hoja nueva en T2 | B29: 2_Certificaciones — registro unificado con estado Certificado → Facturado → Cobrado
A30: Renombre con prefijos | B30: 0_ (config/refs) / 1_ (presupuesto) / 2_ (operativo) / 3_ (control) / _ (legacy)
A31: Pagos actualizada | B31: usa Tabla18[Contrato] — se llena sola con pagos que tengan código SC- cargado
A32: Pendiente para T3 | B32: Reconstruir Cash Flow y armar Dashboard
A34: — TANDA 3 (Cash Flow + Gastos Directos/Indirectos) —
A35: Hoja nueva: 2_Gastos_DirInd | B35: Carga mensual de 13 directos + 3 indirectos. Total Real y Total Descontado por CAC calculados.
A36: Hoja rediseñada: 3_Cash_Flow | B36: 22 meses (nov-24 → ago-26). 8 filas: Ingresos, Ingresos CAC, Egresos, Directos, Indirectos, Total Eg., Resultado mes, Acumulado.
A37: Col nueva en 2_Gastos: X "En Ppto" | B37: TRUE/FALSE según si el Rubro está en Control PPTO. Filtra egresos del Cash Flow.
A38: Control PPTO ampliado | B38: Filas 40-52 (Directos) completadas con ppto desde GGBB. Filas 55-57 (Indirectos) con ppto VACÍO (cargar manual).
A39: Pendiente — Ingresos por CAC | B39: Stand by: usar col V "Monto CAC" para identificar componente CAC en cobros, cuando se defina con Arquinering.
A40: — AUDITORÍA FINAL (Dashboard + Limpieza) —
A41: Hoja nueva: 3_Dashboard | B41: Vista ejecutiva una página con 5 secciones (Avance Fin., Avance Pres., Rentab., Top desvíos, Subcontratos)
A42: Hoja eliminada | B42: _01_snapshot (250 filas, 0 referencias — historial obsoleto)
A43: Validaciones de datos | B43: 2_Gastos col A (Rubro) y B (MT/MO) ahora usan listas desde _Listas
A44: Formato condicional | B44: Semáforos en %desvío (Control PPTO) + resultado del mes (Cash Flow) + KPIs (Dashboard)
A45: Protección de hojas 3_ | B45: Las 4 vistas calculadas están bloqueadas para edición accidental — desproteger desde Revisar > Desproteger Hoja
A46: Sanity Check movido | B46: Desde 3_Control_Ppto!E35 a 0_CONFIG!B20
A49: — RECONCILIACIÓN MENSUAL CON TEZAMAT —
A50: Total mes corriente cargado en 2_Gastos | B50: =SUMIFS(Tabla18[Monto Real],Tabla18[Mes],DATE(YEAR(TODAY()),MONTH(TODAY()),1)) -> 0 | C50: (calculado)
A51: Total mes corriente según Tezamat | C51: (pegar manualmente cada mes)
A52: Diferencia (debe dar 0) | B52: =B50-IF(B51="",B50,B51) -> 0 | C52: > 0 = faltan pagos en Gastos / < 0 = sobran pagos
A54: — ITERACIÓN v7 (Cash Flow + Cat. A) —
A55: Cash Flow fila 6 | B55: Ahora usa Monto Base (col W) — no incluye CAC. Comparación válida vs Ppto Venta.
A56: Rangos extendidos | B56: Buffers ampliados: rubros B3:B60, subcontratos A4:A50, certificaciones K5:K500. Soporta crecimiento sin romper.
A57: % Tiempo transcurrido | B57: Dashboard F17 — (HOY - Inicio) / Duración. Compara avance financiero vs cronograma.
A58: % Avance físico certificado | B58: Dashboard F18 — desde 2_Certif_avance. Detecta over/under-certification vs cobros.
A59: Mes corriente en resultado | B59: Dashboard C22 ahora apunta a la columna del mes calendario actual.
A60: Reconciliación Tezamat | B60: Bloque en 0_CONFIG (filas 49-52) compara total Gastos del mes vs Tezamat.
A61: Estado cierre mensual | B61: 2_Gastos_DirInd fila 6: marcar ✓ cuando se cierra carga del mes. Dashboard avisa si quedan meses sin cerrar.
A62: — PENDIENTE 1 (2_Pagos_Quincena_SC) — Junio 2026 —
A63: Hoja nueva: 2_Pagos_Quincena_SC | B63: Carga manual de quincenas pagadas a obreros de subcontratos con nómina propia. Insertada entre 2_Pagos_Subc y 2_Gastos_DirInd.
A64: 2_Subcontratos!I (Total Pagado) | B64: Fórmula actualizada: ahora suma SUMIFS(Tabla18[Monto Base],...) + SUMIFS(2_Pagos_Quincena_SC!I:I,...). El saldo del contrato descuenta lo pagado por quincenas.
A67: — PENDIENTE 2 (Unificación 1_Presupuesto + 2_Certif_avance) — Junio 2026 —
A68: 1_Presupuesto nueva | B68: Fusión de 1_Presupuesto (costo) + 2_Certif_avance (avance). Hoja única con cols de costo congeladas a valores y cols AC/AD editables.
A69: 2_Certif_avance eliminada | B69: Hoja obsoleta eliminada. Referencias en 3_Dashboard C18 y 3_Control_Ppto R actualizadas a 1_Presupuesto.
A70: ROUNDUP eliminado | B70: Col P (Precio de Venta) usa =O*K exacto sin redondeo. Diferencias de centavos vs versión anterior posibles.

Sheet 0_Indice_CAC
A1: INDICE CAC
A3: Escala de tiempo | B3: Valores | C3: Previsión | D3: Indice
A4: 45627 | B4: 15356.4 | D4: =$B$4/B4 -> 1
A5: 45658 | B5: 15592.5 | D5: =$B$4/B5 -> 0.9848581
A6: 45689 | B6: 15852.4 | D6: =$B$4/B6 -> 0.96871136
A7: 45717 | B7: 15995.4 | D7: =$B$4/B7 -> 0.96005101
A8: 45748 | B8: 16253.5 | D8: =$B$4/B8 -> 0.94480573
A9: 45778 | B9: 16521.3 | D9: =$B$4/B9 -> 0.92949102
A10: 45809 | B10: 16643.4 | D10: =$B$4/B10 -> 0.92267205
A11: 45839 | B11: 16939.5 | D11: =$B$4/B11 -> 0.90654388
A12: 45870 | B12: 17187.6 | D12: =$B$4/B12 -> 0.89345807
A13: 45901 | B13: 17762.3 | D13: =$B$4/B13 -> 0.8645502
A14: 45931 | B14: 18172.8 | D14: =$B$4/B14 -> 0.84502113
A15: 45962 | B15: 18534.9 | D15: =$B$4/B15 -> 0.8285127
A16: 45992 | B16: 18993.891 | C16: 18993.891 | D16: =$B$4/B16 -> 0.80849152
A17: 46023 | B17: 19331.434 | C17: 19331.434 | D17: =$B$4/B17 -> 0.79437459
A18: 46054 | B18: 19331.434 | D18: =$B$4/B18 -> 0.79437459
A19: 46082 | B19: 19331.434 | D19: =$B$4/B19 -> 0.79437459
A20: 46113 | B20: 19331.434 | D20: =$B$4/B20 -> 0.79437459
A21: 46143 | B21: 19331.434 | D21: =$B$4/B21 -> 0.79437459
A22: 46174 | B22: 19331.434 | D22: =$B$4/B22 -> 0.79437459

Sheet 0_Jornales_MO
A1: SECCIÓN A — TABLA DE TARIFAS POR CATEGORÍA (Costo por Día/Quincena)
A3: PERÍODO | B3: ESPEC. ($/día) | C3: OFICIAL ($/día) | D3: 1/2 OFICIAL ($/día) | E3: AYUDANTE ($/día) | G3: ESPEC. ($/hr) | H3: OFICIAL ($/día) | I3: 1/2 OFICIAL ($/día) | J3: AYUDANTE ($/día)
A4: 45627 | B4: 85927.1 | C4: 76955.08 | D4: 65493.07 | E4: 60860.58 | G4: =+B4/8 -> 10740.888 | H4: =+C4/8 -> 9619.385 | I4: =+D4/8 -> 8186.6337 | J4: =+E4/8 -> 7607.5725
A5: 45658 | B5: 87384 | C5: 78375 | D5: 66853 | E5: 61892 | G5: =+B5/8 -> 10923 | H5: =+C5/8 -> 9796.875 | I5: =+D5/8 -> 8356.625 | J5: =+E5/8 -> 7736.5
A6: 45689 | B6: 89383 | C6: 80395 | D6: 68472 | E6: 63382 | G6: =+B6/8 -> 11172.875 | H6: =+C6/8 -> 10049.375 | I6: =+D6/8 -> 8559 | J6: =+E6/8 -> 7922.75
A7: 45717 | B7: 91464 | C7: 82269 | D7: 70296 | E7: 65595 | G7: =+B7/8 -> 11433 | H7: =+C7/8 -> 10283.625 | I7: =+D7/8 -> 8787 | J7: =+E7/8 -> 8199.375
A8: 45778 | B8: 93235.367 | C8: 83766.388 | D8: 71410.817 | E8: 66568.094 | G8: =+B8/8 -> 11654.421 | H8: =+C8/8 -> 10470.798 | I8: =+D8/8 -> 8926.3521 | J8: =+E8/8 -> 8321.0117
A9: 45809 | B9: 94177.138 | C9: 84612.513 | D9: 72132.138 | E9: 67240.499 | G9: =+B9/8 -> 11772.142 | H9: =+C9/8 -> 10576.564 | I9: =+D9/8 -> 9016.5173 | J9: =+E9/8 -> 8405.0624
A10: 45839 | B10: 95080 | C10: 85425 | D10: 72871 | E10: 67908 | G10: =+B10/8 -> 11885 | H10: =+C10/8 -> 10678.125 | I10: =+D10/8 -> 9108.875 | J10: =+E10/8 -> 8488.5
A11: 45870 | B11: 95889.2 | C11: 86356.18 | D11: 73781.11 | E11: 68935.35 | G11: =+B11/8 -> 11986.15 | H11: =+C11/8 -> 10794.522 | I11: =+D11/8 -> 9222.6388 | J11: =+E11/8 -> 8616.9188
A12: 45901 | B12: 106516.02 | C12: 88649.808 | D12: 75758.192 | E12: 71041.119 | G12: =+B12/8 -> 13314.502 | H12: =+C12/8 -> 11081.226 | I12: =+D12/8 -> 9469.774 | J12: =+E12/8 -> 8880.1398
A13: 45931 | B13: 106864.21 | C13: 88971.073 | D13: 76032.176 | E13: 71292.271 | G13: =+B13/8 -> 13358.026 | H13: =+C13/8 -> 11121.384 | I13: =+D13/8 -> 9504.0221 | J13: =+E13/8 -> 8911.5339
A14: 45962 | B14: 109621.11 | C14: 91252.851 | D14: 77612.118 | E14: 72486.683 | G14: =+B14/8 -> 13702.638 | H14: =+C14/8 -> 11406.606 | I14: =+D14/8 -> 9701.5148 | J14: =+E14/8 -> 9060.8353
A15: 45992 | B15: 113865.18 | C15: 95196.927 | D15: 81356.194 | E15: 76230.759 | G15: =+B15/8 -> 14233.148 | H15: =+C15/8 -> 11899.616 | I15: =+D15/8 -> 10169.524 | J15: =+E15/8 -> 9528.8449
... A21: 46174 | B21: 122445.79 | C21: 102029.07 | D21: 87100.47 | E21: 81453.719 | G21: =+B21/8 -> 15305.724 | H21: =+C21/8 -> 12753.633 | I21: =+D21/8 -> 10887.559 | J21: =+E21/8 -> 10181.715

Sheet 1_Presupuesto
A1: PRESUPUESTO OBRA CIVIL y CERTIFICACIONES DE AVANCE
P2: ='1_GGBB'!F67 -> 1.4355353
A3: Rubro MT | B3: Rubro MT / Prov | C3: Rubro MO / OTR | D3: Rubro MO / ALB | G3: E | H3: Descripción | I3: U | J3: Cant | K3: MT | L3: MO / OTR | M3: MO / ALB | N3: EQ | O3: Costo Unit. | P3: P Unit. | R3: MT | S3: MO / OTR | T3: MO / ALB | U3: EQ | V3: P.Unit | X3: MT | Y3: MO | Z3: Subtotal | AB3: ETAPA | AC3: % Acum. Ant. | AD3: % Cert. Actual | AE3: % Acum. Total | AG3: Imp. Acum. Ant. | AH3: Imp. Cert. Actual | AI3: Imp. Acum. Total | AK3: Acum. MT | AL3: Acum. MO/OTR | AM3: Acum. MO/ALB | AN3: Acum. EQ | AO3: Acum. Subtotal | AQ3: Costo_ud | AR3: Costo_total
F4: 1 | H4: TAREAS PRELIMINARES | AA4: =+SUM(Z5:Z13) -> 21422381 | AB4: TAREAS PRELIMINARES
A5: - | B5: - | C5: - | D5: - | F5: 1.01 | G5: OK | H5: Limpieza y preparación del terreno - No cotiza | I5: gl | J5: 1 | K5: 0 | L5: 0 | M5: 0 | N5: 0 | O5: =+SUM(K5:N5) -> 0 | P5: =+O5*$P$2 -> 0 | R5: =+K5*$P$2 -> 0 | S5: =+L5*$P$2 -> 0 | T5: =+M5*$P$2 -> 0 | U5: =+N5*$P$2 -> 0 | V5: =+SUM(R5:U5) -> 0 | X5: =+R5*J5 -> 0 | Y5: =+Z5-X5 -> 0 | Z5: =+V5*J5 -> 0 | AB5: TAREAS PRELIMINARES | AC5: 0 | AD5: 0 | AE5: =AC5+AD5 -> 0 | AF5: =IF($AE5=1,"🔴","⚪") -> ⚪ | AG5: =AC5*Z5 -> 0 | AH5: =AD5*Z5 -> 0 | AI5: =AE5*Z5 -> 0 | AK5: =AE5*X5 -> 0 | AL5: =AE5*S5*J5 -> 0 | AM5: =AE5*T5*J5 -> 0 | AN5: =AE5*U5*J5 -> 0 | AO5: =AK5+AL5+AM5+AN5 -> 0 | AQ5: =+O5 -> 0 | AR5: =+O5*J5 -> 0
A6: Agrimensura | B6: - | C6: Agrimensura | D6: Preliminar | F6: 1.02 | G6: OK | H6: Topógrafo - Visita de obra replanteo | I6: gl | J6: 3 | K6: 25000 | L6: 198736.84 | M6: 60860.581 | N6: 4268.9614 | O6: =+SUM(K6:N6) -> 288866.39 | P6: =+O6*$P$2 -> 414677.9 | R6: =+K6*$P$2 -> 35888.383 | S6: =+L6*$P$2 -> 285293.76 | T6: =+M6*$P$2 -> 87367.513 | U6: =+N6*$P$2 -> 6128.2448 | V6: =+SUM(R6:U6) -> 414677.9 | X6: =+R6*J6 -> 107665.15 | Y6: =+Z6-X6 -> 1136368.6 | Z6: =+V6*J6 -> 1244033.7 | AB6: TAREAS PRELIMINARES | AC6: 1 | AD6: 0 | AE6: =AC6+AD6 -> 1 | AF6: =IF($AE6=1,"🔴","⚪") -> 🔴 | AG6: =AC6*Z6 -> 1244033.7 | AH6: =AD6*Z6 -> 0 | AI6: =AE6*Z6 -> 1244033.7 | AK6: =AE6*X6 -> 107665.15 | AL6: =AE6*S6*J6 -> 855881.28 | AM6: =AE6*T6*J6 -> 262102.54 | AN6: =AE6*U6*J6 -> 18384.735 | AO6: =AK6+AL6+AM6+AN6 -> 1244033.7 | AQ6: =+O6 -> 288866.39 | AR6: =+O6*J6 -> 866599.16
A7: - | B7: - | C7: - | D7: - | F7: 1.03 | G7: OK | H7: Cartel de Obra - No cotiza | I7: gl | J7: 1 | K7: 0 | L7: 0 | M7: 0 | N7: 0 | O7: =+SUM(K7:N7) -> 0 | P7: =+O7*$P$2 -> 0 | R7: =+K7*$P$2 -> 0 | S7: =+L7*$P$2 -> 0 | T7: =+M7*$P$2 -> 0 | U7: =+N7*$P$2 -> 0 | V7: =+SUM(R7:U7) -> 0 | X7: =+R7*J7 -> 0 | Y7: =+Z7-X7 -> 0 | Z7: =+V7*J7 -> 0 | AB7: TAREAS PRELIMINARES | AC7: 0 | AD7: 0 | AE7: =AC7+AD7 -> 0 | AF7: =IF($AE7=1,"🔴","⚪") -> ⚪ | AG7: =AC7*Z7 -> 0 | AH7: =AD7*Z7 -> 0 | AI7: =AE7*Z7 -> 0 | AK7: =AE7*X7 -> 0 | AL7: =AE7*S7*J7 -> 0 | AM7: =AE7*T7*J7 -> 0 | AN7: =AE7*U7*J7 -> 0 | AO7: =AK7+AL7+AM7+AN7 -> 0 | AQ7: =+O7 -> 0 | AR7: =+O7*J7 -> 0
A8: Preliminar | B8: - | C8: - | D8: Preliminar | F8: 1.04 | G8: OK | H8: Cerco de obra perimetral - En chapa C25 + Concertina + Porton corredizo | I8: ml | J8: 10 | K8: 88330.703 | L8: 0 | M8: 101654.37 | N8: 2849.776 | O8: =+SUM(K8:N8) -> 192834.84 | P8: =+O8*$P$2 -> 276821.23 | R8: =+K8*$P$2 -> 126801.84 | S8: =+L8*$P$2 -> 0 | T8: =+M8*$P$2 -> 145928.43 | U8: =+N8*$P$2 -> 4090.9541 | V8: =+SUM(R8:U8) -> 276821.23 | X8: =+R8*J8 -> 1268018.4 | Y8: =+Z8-X8 -> 1500193.9 | Z8: =+V8*J8 -> 2768212.3 | AB8: TAREAS PRELIMINARES | AC8: 1 | AD8: 0 | AE8: =AC8+AD8 -> 1 | AF8: =IF($AE8=1,"🔴","⚪") -> 🔴 | AG8: =AC8*Z8 -> 2768212.3 | AH8: =AD8*Z8 -> 0 | AI8: =AE8*Z8 -> 2768212.3 | AK8: =AE8*X8 -> 1268018.4 | AL8: =AE8*S8*J8 -> 0 | AM8: =AE8*T8*J8 -> 1459284.3 | AN8: =AE8*U8*J8 -> 40909.541 | AO8: =AK8+AL8+AM8+AN8 -> 2768212.3 | AQ8: =+O8 -> 192834.84 | AR8: =+O8*J8 -> 1928348.4
A9: Preliminar | B9: - | C9: Preliminar | D9: Preliminar | F9: 1.05 | G9: OK | H9: Obrador, pañol y ducha. | I9: gl | J9: 1 | K9: 2078824.7 | L9: 750000 | M9: 4424962.9 | N9: 108806.81 | O9: =+SUM(K9:N9) -> 7362594.4 | P9: =+O9*$P$2 -> 10569264 | R9: =+K9*$P$2 -> 2984226.3 | S9: =+L9*$P$2 -> 1076651.5 | T9: =+M9*$P$2 -> 6352190.5 | U9: =+N9*$P$2 -> 156196.02 | V9: =+SUM(R9:U9) -> 10569264 | X9: =+R9*J9 -> 2984226.3 | Y9: =+Z9-X9 -> 7585038 | Z9: =+V9*J9 -> 10569264 | AB9: TAREAS PRELIMINARES | AC9: 1 | AD9: 0 | AE9: =AC9+AD9 -> 1 | AF9: =IF($AE9=1,"🔴","⚪") -> 🔴 | AG9: =AC9*Z9 -> 10569264 | AH9: =AD9*Z9 -> 0 | AI9: =AE9*Z9 -> 10569264 | AK9: =AE9*X9 -> 2984226.3 | AL9: =AE9*S9*J9 -> 1076651.5 | AM9: =AE9*T9*J9 -> 6352190.5 | AN9: =AE9*U9*J9 -> 156196.02 | AO9: =AK9+AL9+AM9+AN9 -> 10569264 | AQ9: =+O9 -> 7362594.4 | AR9: =+O9*J9 -> 7362594.4
A10: Gastos Generales Obra | B10: - | C10: Gastos Generales Obra | D10: Preliminar | F10: 1.06 | G10: OK | H10: Alquiler de baños quimicos y duchas portatiles | I10: mes | J10: 4 | K10: 0 | L10: 318994.12 | M10: 13291.422 | N10: 0 | O10: =+SUM(K10:N10) -> 332285.54 | P10: =+O10*$P$2 -> 477007.63 | R10: =+K10*$P$2 -> 0 | S10: =+L10*$P$2 -> 457927.33 | T10: =+M10*$P$2 -> 19080.305 | U10: =+N10*$P$2 -> 0 | V10: =+SUM(R10:U10) -> 477007.63 | X10: =+R10*J10 -> 0 | Y10: =+Z10-X10 -> 1908030.5 | Z10: =+V10*J10 -> 1908030.5 | AB10: TAREAS PRELIMINARES | AC10: 1 | AD10: 0 | AE10: =AC10+AD10 -> 1 | AF10: =IF($AE10=1,"🔴","⚪") -> 🔴 | AG10: =AC10*Z10 -> 1908030.5 | AH10: =AD10*Z10 -> 0 | AI10: =AE10*Z10 -> 1908030.5 | AK10: =AE10*X10 -> 0 | AL10: =AE10*S10*J10 -> 1831709.3 | AM10: =AE10*T10*J10 -> 76321.221 | AN10: =AE10*U10*J10 -> 0 | AO10: =AK10+AL10+AM10+AN10 -> 1908030.5 | AQ10: =+O10 -> 332285.54 | AR10: =+O10*J10 -> 1329142.2
A11: Preliminar | B11: - | C11: - | D11: Preliminar | F11: 1.07 | G11: OK | H11: Conexión pilar y luz de obra + Tablero de obra | I11: gl | J11: 1 | K11: 1090000 | L11: 0 | M11: 601395.67 | N11: 25370.935 | O11: =+SUM(K11:N11) -> 1716766.6 | P11: =+O11*$P$2 -> 2464479.1 | R11: =+K11*$P$2 -> 1564733.5 | S11: =+L11*$P$2 -> 0 | T11: =+M11*$P$2 -> 863324.73 | U11: =+N11*$P$2 -> 36420.873 | V11: =+SUM(R11:U11) -> 2464479.1 | X11: =+R11*J11 -> 1564733.5 | Y11: =+Z11-X11 -> 899745.6 | Z11: =+V11*J11 -> 2464479.1 | AB11: TAREAS PRELIMINARES | AC11: 1 | AD11: 0 | AE11: =AC11+AD11 -> 1 | AF11: =IF($AE11=1,"🔴","⚪") -> 🔴 | AG11: =AC11*Z11 -> 2464479.1 | AH11: =AD11*Z11 -> 0 | AI11: =AE11*Z11 -> 2464479.1 | AK11: =AE11*X11 -> 1564733.5 | AL11: =AE11*S11*J11 -> 0 | AM11: =AE11*T11*J11 -> 863324.73 | AN11: =AE11*U11*J11 -> 36420.873 | AO11: =AK11+AL11+AM11+AN11 -> 2464479.1 | AQ11: =+O11 -> 1716766.6 | AR11: =+O11*J11 -> 1716766.6
A12: Preliminar | B12: - | C12: - | D12: Preliminar | F12: 1.08 | G12: OK | H12: Conexión agua de obra, tanque + bomba | I12: gl | J12: 1 | K12: 685200 | L12: 0 | M12: 651528.71 | N12: 20050.931 | O12: =+SUM(K12:N12) -> 1356779.6 | P12: =+O12*$P$2 -> 1947705.1 | R12: =+K12*$P$2 -> 983628.8 | S12: =+L12*$P$2 -> 0 | T12: =+M12*$P$2 -> 935292.47 | U12: =+N12*$P$2 -> 28783.819 | V12: =+SUM(R12:U12) -> 1947705.1 | X12: =+R12*J12 -> 983628.8 | Y12: =+Z12-X12 -> 964076.29 | Z12: =+V12*J12 -> 1947705.1 | AB12: TAREAS PRELIMINARES | AC12: 1 | AD12: 0 | AE12: =AC12+AD12 -> 1 | AF12: =IF($AE12=1,"🔴","⚪") -> 🔴 | AG12: =AC12*Z12 -> 1947705.1 | AH12: =AD12*Z12 -> 0 | AI12: =AE12*Z12 -> 1947705.1 | AK12: =AE12*X12 -> 983628.8 | AL12: =AE12*S12*J12 -> 0 | AM12: =AE12*T12*J12 -> 935292.47 | AN12: =AE12*U12*J12 -> 28783.819 | AO12: =AK12+AL12+AM12+AN12 -> 1947705.1 | AQ12: =+O12 -> 1356779.6 | AR12: =+O12*J12 -> 1356779.6
A13: Preliminar | B13: - | C13: Preliminar | D13: - | F13: 1.09 | G13: OK | H13: Tramite luz de obra, certificado luz de obra (2) y medición PAT | I13: gl | J13: 1 | K13: 0 | L13: 362691.09 | M13: 0 | N13: 0 | O13: =+SUM(K13:N13) -> 362691.09 | P13: =+O13*$P$2 -> 520655.86 | R13: =+K13*$P$2 -> 0 | S13: =+L13*$P$2 -> 520655.86 | T13: =+M13*$P$2 -> 0 | U13: =+N13*$P$2 -> 0 | V13: =+SUM(R13:U13) -> 520655.86 | X13: =+R13*J13 -> 0 | Y13: =+Z13-X13 -> 520655.86 | Z13: =+V13*J13 -> 520655.86 | AB13: TAREAS PRELIMINARES | AC13: 1 | AD13: 0 | AE13: =AC13+AD13 -> 1 | AF13: =IF($AE13=1,"🔴","⚪") -> 🔴 | AG13: =AC13*Z13 -> 520655.86 | AH13: =AD13*Z13 -> 0 | AI13: =AE13*Z13 -> 520655.86 | AK13: =AE13*X13 -> 0 | AL13: =AE13*S13*J13 -> 520655.86 | AM13: =AE13*T13*J13 -> 0 | AN13: =AE13*U13*J13 -> 0 | AO13: =AK13+AL13+AM13+AN13 -> 520655.86 | AQ13: =+O13 -> 362691.09 | AR13: =+O13*J13 -> 362691.09
A14: - | B14: - | C14: - | D14: - | F14: 2 | H14: MOVIMIENTO DE TIERRA, COMPACTACION Y RELLENO | AA14: =+SUM(Z15:Z19) -> 31937041 | AB14: MOVIMIENTO DE TIERRA, COMPACTACION Y RELLENO
A15: Excavación y Mov. de Suelos | B15: - | C15: Excavación y Mov. de Suelos | D15: Hormigón | F15: 2.01 | G15: OK | H15: Excavación a maquina para submuración, subsuelo y fundaciones | I15: m3 | J15: 308 | K15: 0 | L15: 33000 | M15: 6520.7765 | N15: 97.811648 | O15: =+SUM(K15:N15) -> 39618.588 | P15: =+O15*$P$2 -> 56873.883 | R15: =+K15*$P$2 -> 0 | S15: =+L15*$P$2 -> 47372.665 | T15: =+M15*$P$2 -> 9360.805 | U15: =+N15*$P$2 -> 140.41207 | V15: =+SUM(R15:U15) -> 56873.883 | X15: =+R15*J15 -> 0 | Y15: =+Z15-X15 -> 17517156 | Z15: =+V15*J15 -> 17517156 | AB15: MOVIMIENTO DE TIERRA, COMPACTACION Y RELLENO | AC15: 1 | AD15: 0 | AE15: =AC15+AD15 -> 1 | AF15: =IF($AE15=1,"🔴","⚪") -> 🔴 | AG15: =AC15*Z15 -> 17517156 | AH15: =AD15*Z15 -> 0 | AI15: =AE15*Z15 -> 17517156 | AK15: =AE15*X15 -> 0 | AL15: =AE15*S15*J15 -> 14590781 | AM15: =AE15*T15*J15 -> 2883127.9 | AN15: =AE15*U15*J15 -> 43246.919 | AO15: =AK15+AL15+AM15+AN15 -> 17517156 | AQ15: =+O15 -> 39618.588 | AR15: =+O15*J15 -> 12202525
A16: Excavación y Mov. de Suelos | B16: - | C16: Excavación y Mov. de Suelos | D16: Preliminar | F16: 2.02 | G16: OK | H16: Perfilado manual de bases. Relleno y compactación de pozos | I16: gl | J16: 1 | K16: 105000 | L16: 455000 | M16: 8033596.7 | N16: 128903.95 | O16: =+SUM(K16:N16) -> 8722500.6 | P16: =+O16*$P$2 -> 12521458 | R16: =+K16*$P$2 -> 150731.21 | S16: =+L16*$P$2 -> 653168.57 | T16: =+M16*$P$2 -> 11532512 | U16: =+N16*$P$2 -> 185046.17 | V16: =+SUM(R16:U16) -> 12521458 | X16: =+R16*J16 -> 150731.21 | Y16: =+Z16-X16 -> 12370726 | Z16: =+V16*J16 -> 12521458 | AB16: MOVIMIENTO DE TIERRA, COMPACTACION Y RELLENO | AC16: 1 | AD16: 0 | AE16: =AC16+AD16 -> 1 | AF16: =IF($AE16=1,"🔴","⚪") -> 🔴 | AG16: =AC16*Z16 -> 12521458 | AH16: =AD16*Z16 -> 0 | AI16: =AE16*Z16 -> 12521458 | AK16: =AE16*X16 -> 150731.21 | AL16: =AE16*S16*J16 -> 653168.57 | AM16: =AE16*T16*J16 -> 11532512 | AN16: =AE16*U16*J16 -> 185046.17 | AO16: =AK16+AL16+AM16+AN16 -> 12521458 | AQ16: =+O16 -> 8722500.6 | AR16: =+O16*J16 -> 8722500.6
A17: Excavación y Mov. de Suelos | B17: - | C17: - | D17: Preliminar | F17: 2.03 | G17: OK | H17: Excavación manual para vigas de fundación | I17: m3 | J17: 15 | K17: 26000 | L17: 0 | M17: 60860.581 | N17: 1302.9087 | O17: =+SUM(K17:N17) -> 88163.489 | P17: =+O17*$P$2 -> 126561.8 | R17: =+K17*$P$2 -> 37323.918 | S17: =+L17*$P$2 -> 0 | T17: =+M17*$P$2 -> 87367.513 | U17: =+N17*$P$2 -> 1870.3715 | V17: =+SUM(R17:U17) -> 126561.8 | X17: =+R17*J17 -> 559858.77 | Y17: =+Z17-X17 -> 1338568.3 | Z17: =+V17*J17 -> 1898427 | AB17: MOVIMIENTO DE TIERRA, COMPACTACION Y RELLENO | AC17: 1 | AD17: 0 | AE17: =AC17+AD17 -> 1 | AF17: =IF($AE17=1,"🔴","⚪") -> 🔴 | AG17: =AC17*Z17 -> 1898427 | AH17: =AD17*Z17 -> 0 | AI17: =AE17*Z17 -> 1898427 | AK17: =AE17*X17 -> 559858.77 | AL17: =AE17*S17*J17 -> 0 | AM17: =AE17*T17*J17 -> 1310512.7 | AN17: =AE17*U17*J17 -> 28055.572 | AO17: =AK17+AL17+AM17+AN17 -> 1898427 | AQ17: =+O17 -> 88163.489 | AR17: =+O17*J17 -> 1322452.3
A18: - | B18: - | C18: - | D18: - | F18: 2.04 | G18: IN | H18: Aporte y compactación de suelo seleccionado, e: 40 cm (2 capas de 20 cm) - Cotizado Hº Pobre en item 8,02 | I18: m2 | J18: 0 | K18: 0 | L18: 0 | M18: 0 | N18: 0 | O18: =+SUM(K18:N18) -> 0 | P18: =+O18*$P$2 -> 0 | R18: =+K18*$P$2 -> 0 | S18: =+L18*$P$2 -> 0 | T18: =+M18*$P$2 -> 0 | U18: =+N18*$P$2 -> 0 | V18: =+SUM(R18:U18) -> 0 | X18: =+R18*J18 -> 0 | Y18: =+Z18-X18 -> 0 | Z18: =+V18*J18 -> 0 | AB18: MOVIMIENTO DE TIERRA, COMPACTACION Y RELLENO | AC18: 0 | AD18: 0 | AE18: =AC18+AD18 -> 0 | AF18: =IF($AE18=1,"🔴","⚪") -> ⚪ | AG18: =AC18*Z18 -> 0 | AH18: =AD18*Z18 -> 0 | AI18: =AE18*Z18 -> 0 | AK18: =AE18*X18 -> 0 | AL18: =AE18*S18*J18 -> 0 | AM18: =AE18*T18*J18 -> 0 | AN18: =AE18*U18*J18 -> 0 | AO18: =AK18+AL18+AM18+AN18 -> 0 | AQ18: =+O18 -> 0 | AR18: =+O18*J18 -> 0
A19: - | B19: - | C19: - | D19: - | F19: 2.05 | G19: OK | H19: Demolición de bases existentes - No cotiza | I19: gl | J19: 0 | K19: 0 | L19: 0 | M19: 0 | N19: 0 | O19: =+SUM(K19:N19) -> 0 | P19: =+O19*$P$2 -> 0 | R19: =+K19*$P$2 -> 0 | S19: =+L19*$P$2 -> 0 | T19: =+M19*$P$2 -> 0 | U19: =+N19*$P$2 -> 0 | V19: =+SUM(R19:U19) -> 0 | X19: =+R19*J19 -> 0 | Y19: =+Z19-X19 -> 0 | Z19: =+V19*J19 -> 0 | AB19: MOVIMIENTO DE TIERRA, COMPACTACION Y RELLENO | AC19: 0 | AD19: 0 | AE19: =AC19+AD19 -> 0 | AF19: =IF($AE19=1,"🔴","⚪") -> ⚪ | AG19: =AC19*Z19 -> 0 | AH19: =AD19*Z19 -> 0 | AI19: =AE19*Z19 -> 0 | AK19: =AE19*X19 -> 0 | AL19: =AE19*S19*J19 -> 0 | AM19: =AE19*T19*J19 -> 0 | AN19: =AE19*U19*J19 -> 0 | AO19: =AK19+AL19+AM19+AN19 -> 0 | AQ19: =+O19 -> 0 | AR19: =+O19*J19 -> 0
A20: - | B20: - | C20: - | D20: - | F20: 3 | H20: ESTRUCTURA RESISTENTE | AA20: =+SUM(Z21:Z41) -> 4.8618836e+08 | AB20: ESTRUCTURA RESISTENTE
A21: Hormigón | B21: - | C21: - | D21: Hormigón | F21: 3.01 | G21: OK | H21: Hormigón de limpieza - e: 10 cm | I21: m3 | J21: 13 | K21: 115100 | L21: 0 | M21: 101603.58 | N21: 3250.5537 | O21: =+SUM(K21:N21) -> 219954.14 | P21: =+O21*$P$2 -> 315751.93 | R21: =+K21*$P$2 -> 165230.12 | S21: =+L21*$P$2 -> 0 | T21: =+M21*$P$2 -> 145855.53 | U21: =+N21*$P$2 -> 4666.2847 | V21: =+SUM(R21:U21) -> 315751.93 | X21: =+R21*J21 -> 2147991.5 | Y21: =+Z21-X21 -> 1956783.6 | Z21: =+V21*J21 -> 4104775.1 | AB21: ESTRUCTURA RESISTENTE | AC21: 1 | AD21: 0 | AE21: =AC21+AD21 -> 1 | AF21: =IF($AE21=1,"🔴","⚪") -> 🔴 | AG21: =AC21*Z21 -> 4104775.1 | AH21: =AD21*Z21 -> 0 | AI21: =AE21*Z21 -> 4104775.1 | AK21: =AE21*X21 -> 2147991.5 | AL21: =AE21*S21*J21 -> 0 | AM21: =AE21*T21*J21 -> 1896121.9 | AN21: =AE21*U21*J21 -> 60661.701 | AO21: =AK21+AL21+AM21+AN21 -> 4104775.1 | AQ21: =+O21 -> 219954.14 | AR21: =+O21*J21 -> 2859403.8
A22: Hormigón | B22: - | C22: Hormigón | D22: - | F22: 3.02 | G22: OK | H22: Pilotes de tracción Ø 20 cm - (120 kg/m3 de hierro) | I22: u | J22: 18 | K22: 90570.796 | L22: 250000 | M22: 0 | N22: 5108.5619 | O22: =+SUM(K22:N22) -> 345679.36 | P22: =+O22*$P$2 -> 496234.93 | R22: =+K22*$P$2 -> 130017.58 | S22: =+L22*$P$2 -> 358883.83 | T22: =+M22*$P$2 -> 0 | U22: =+N22*$P$2 -> 7333.5211 | V22: =+SUM(R22:U22) -> 496234.93 | X22: =+R22*J22 -> 2340316.4 | Y22: =+Z22-X22 -> 6591912.3 | Z22: =+V22*J22 -> 8932228.7 | AB22: ESTRUCTURA RESISTENTE | AC22: 1 | AD22: 0 | AE22: =AC22+AD22 -> 1 | AF22: =IF($AE22=1,"🔴","⚪") -> 🔴 | AG22: =AC22*Z22 -> 8932228.7 | AH22: =AD22*Z22 -> 0 | AI22: =AE22*Z22 -> 8932228.7 | AK22: =AE22*X22 -> 2340316.4 | AL22: =AE22*S22*J22 -> 6459908.9 | AM22: =AE22*T22*J22 -> 0 | AN22: =AE22*U22*J22 -> 132003.38 | AO22: =AK22+AL22+AM22+AN22 -> 8932228.7 | AQ22: =+O22 -> 345679.36 | AR22: =+O22*J22 -> 6222228.4
A23: Hormigón | B23: - | C23: Hormigón | D23: - | F23: 3.03 | G23: OK | H23: Tabique submuración - H35 (95 kg/m3 de hierro) | I23: m3 | J23: 12 | K23: 402072.54 | L23: 357640.9 | M23: 0 | N23: 11395.702 | O23: =+SUM(K23:N23) -> 771109.14 | P23: =+O23*$P$2 -> 1106954.4 | R23: =+K23*$P$2 -> 577189.33 | S23: =+L23*$P$2 -> 513406.14 | T23: =+M23*$P$2 -> 0 | U23: =+N23*$P$2 -> 16358.932 | V23: =+SUM(R23:U23) -> 1106954.4 | X23: =+R23*J23 -> 6926272 | Y23: =+Z23-X23 -> 6357180.9 | Z23: =+V23*J23 -> 13283453 | AB23: ESTRUCTURA RESISTENTE | AC23: 1 | AD23: 0 | AE23: =AC23+AD23 -> 1 | AF23: =IF($AE23=1,"🔴","⚪") -> 🔴 | AG23: =AC23*Z23 -> 13283453 | AH23: =AD23*Z23 -> 0 | AI23: =AE23*Z23 -> 13283453 | AK23: =AE23*X23 -> 6926272 | AL23: =AE23*S23*J23 -> 6160873.7 | AM23: =AE23*T23*J23 -> 0 | AN23: =AE23*U23*J23 -> 196307.19 | AO23: =AK23+AL23+AM23+AN23 -> 13283453 | AQ23: =+O23 -> 771109.14 | AR23: =+O23*J23 -> 9253309.7
A24: Hormigón | B24: - | C24: Hormigón | D24: - | F24: 3.04 | G24: OK | H24: Zapata corrida tabique - H35 (120 kg/m3 de hierro) | I24: m3 | J24: 7 | K24: 428196.58 | L24: 281633.96 | M24: 0 | N24: 10647.458 | O24: =+SUM(K24:N24) -> 720478 | P24: =+O24*$P$2 -> 1034271.6 | R24: =+K24*$P$2 -> 614691.31 | S24: =+L24*$P$2 -> 404295.5 | T24: =+M24*$P$2 -> 0 | U24: =+N24*$P$2 -> 15284.802 | V24: =+SUM(R24:U24) -> 1034271.6 | X24: =+R24*J24 -> 4302839.2 | Y24: =+Z24-X24 -> 2937062.1 | Z24: =+V24*J24 -> 7239901.3 | AB24: ESTRUCTURA RESISTENTE | AC24: 1 | AD24: 0 | AE24: =AC24+AD24 -> 1 | AF24: =IF($AE24=1,"🔴","⚪") -> 🔴 | AG24: =AC24*Z24 -> 7239901.3 | AH24: =AD24*Z24 -> 0 | AI24: =AE24*Z24 -> 7239901.3 | AK24: =AE24*X24 -> 4302839.2 | AL24: =AE24*S24*J24 -> 2830068.5 | AM24: =AE24*T24*J24 -> 0 | AN24: =AE24*U24*J24 -> 106993.62 | AO24: =AK24+AL24+AM24+AN24 -> 7239901.3 | AQ24: =+O24 -> 720478 | AR24: =+O24*J24 -> 5043346
A25: Hormigón | B25: - | C25: Hormigón | D25: - | F25: 3.05 | G25: OK | H25: Platea - H35 (95 kg/m3 de hierro) | I25: m3 | J25: 38 | K25: 333700.51 | L25: 194327.43 | M25: 0 | N25: 7920.4191 | O25: =+SUM(K25:N25) -> 535948.36 | P25: =+O25*$P$2 -> 769372.8 | R25: =+K25*$P$2 -> 479038.86 | S25: =+L25*$P$2 -> 278963.89 | T25: =+M25*$P$2 -> 0 | U25: =+N25*$P$2 -> 11370.041 | V25: =+SUM(R25:U25) -> 769372.8 | X25: =+R25*J25 -> 18203477 | Y25: =+Z25-X25 -> 11032690 | Z25: =+V25*J25 -> 29236166 | AB25: ESTRUCTURA RESISTENTE | AC25: 1 | AD25: 0 | AE25: =AC25+AD25 -> 1 | AF25: =IF($AE25=1,"🔴","⚪") -> 🔴 | AG25: =AC25*Z25 -> 29236166 | AH25: =AD25*Z25 -> 0 | AI25: =AE25*Z25 -> 29236166 | AK25: =AE25*X25 -> 18203477 | AL25: =AE25*S25*J25 -> 10600628 | AM25: =AE25*T25*J25 -> 0 | AN25: =AE25*U25*J25 -> 432061.57 | AO25: =AK25+AL25+AM25+AN25 -> 29236166 | AQ25: =+O25 -> 535948.36 | AR25: =+O25*J25 -> 20366038
A26: Hormigón | B26: - | C26: Hormigón | D26: - | F26: 3.06 | G26: OK | H26: Bases aisladas - (60 kg/m3 de hierro) | I26: m3 | J26: 51 | K26: 275042.38 | L26: 194327.43 | M26: 0 | N26: 7040.5472 | O26: =+SUM(K26:N26) -> 476410.36 | P26: =+O26*$P$2 -> 683903.9 | R26: =+K26*$P$2 -> 394833.05 | S26: =+L26*$P$2 -> 278963.89 | T26: =+M26*$P$2 -> 0 | U26: =+N26*$P$2 -> 10106.954 | V26: =+SUM(R26:U26) -> 683903.9 | X26: =+R26*J26 -> 20136485 | Y26: =+Z26-X26 -> 14742613 | Z26: =+V26*J26 -> 34879099 | AB26: ESTRUCTURA RESISTENTE | AC26: 1 | AD26: 0 | AE26: =AC26+AD26 -> 1 | AF26: =IF($AE26=1,"🔴","⚪") -> 🔴 | AG26: =AC26*Z26 -> 34879099 | AH26: =AD26*Z26 -> 0 | AI26: =AE26*Z26 -> 34879099 | AK26: =AE26*X26 -> 20136485 | AL26: =AE26*S26*J26 -> 14227159 | AM26: =AE26*T26*J26 -> 0 | AN26: =AE26*U26*J26 -> 515454.66 | AO26: =AK26+AL26+AM26+AN26 -> 34879099 | AQ26: =+O26 -> 476410.36 | AR26: =+O26*J26 -> 24296928
A27: Hormigón | B27: - | C27: Hormigón | D27: - | F27: 3.07 | G27: OK | H27: Troncos de columnas - H35 (240 kg/m3 de hierro) | I27: m3 | J27: 16 | K27: 635192.72 | L27: 317914.05 | M27: 0 | N27: 14296.601 | O27: =+SUM(K27:N27) -> 967403.37 | P27: =+O27*$P$2 -> 1388741.7 | R27: =+K27*$P$2 -> 911841.58 | S27: =+L27*$P$2 -> 456376.84 | T27: =+M27*$P$2 -> 0 | U27: =+N27*$P$2 -> 20523.276 | V27: =+SUM(R27:U27) -> 1388741.7 | X27: =+R27*J27 -> 14589465 | Y27: =+Z27-X27 -> 7630401.9 | Z27: =+V27*J27 -> 22219867 | AB27: ESTRUCTURA RESISTENTE | AC27: 1 | AD27: 0 | AE27: =AC27+AD27 -> 1 | AF27: =IF($AE27=1,"🔴","⚪") -> 🔴 | AG27: =AC27*Z27 -> 22219867 | AH27: =AD27*Z27 -> 0 | AI27: =AE27*Z27 -> 22219867 | AK27: =AE27*X27 -> 14589465 | AL27: =AE27*S27*J27 -> 7302029.5 | AM27: =AE27*T27*J27 -> 0 | AN27: =AE27*U27*J27 -> 328372.42 | AO27: =AK27+AL27+AM27+AN27 -> 22219867 | AQ27: =+O27 -> 967403.37 | AR27: =+O27*J27 -> 15478454
A28: Hormigón | B28: - | C28: Hormigón | D28: - | F28: 3.08 | G28: OK | H28: Viga de encadenado - H35 (180 kg/m3 de hierro) | I28: m3 | J28: 7 | K28: 528753.37 | L28: 281633.96 | M28: 0 | N28: 12155.81 | O28: =+SUM(K28:N28) -> 822543.14 | P28: =+O28*$P$2 -> 1180789.7 | R28: =+K28*$P$2 -> 759044.14 | S28: =+L28*$P$2 -> 404295.5 | T28: =+M28*$P$2 -> 0 | U28: =+N28*$P$2 -> 17450.095 | V28: =+SUM(R28:U28) -> 1180789.7 | X28: =+R28*J28 -> 5313309 | Y28: =+Z28-X28 -> 2952219.2 | Z28: =+V28*J28 -> 8265528.1 | AB28: ESTRUCTURA RESISTENTE | AC28: 1 | AD28: 0 | AE28: =AC28+AD28 -> 1 | AF28: =IF($AE28=1,"🔴","⚪") -> 🔴 | AG28: =AC28*Z28 -> 8265528.1 | AH28: =AD28*Z28 -> 0 | AI28: =AE28*Z28 -> 8265528.1 | AK28: =AE28*X28 -> 5313309 | AL28: =AE28*S28*J28 -> 2830068.5 | AM28: =AE28*T28*J28 -> 0 | AN28: =AE28*U28*J28 -> 122150.66 | AO28: =AK28+AL28+AM28+AN28 -> 8265528.1 | AQ28: =+O28 -> 822543.14 | AR28: =+O28*J28 -> 5757802
A29: Hormigón | B29: - | C29: Hormigón | D29: - | F29: 3.09 | G29: OK | H29: Losa maciza - H35 (100 kg/m3 de hierro) | I29: m3 | J29: 90 | K29: 372584.33 | L29: 221790.79 | M29: 0 | N29: 8915.6269 | O29: =+SUM(K29:N29) -> 603290.75 | P29: =+O29*$P$2 -> 866045.18 | R29: =+K29*$P$2 -> 534857.96 | S29: =+L29*$P$2 -> 318388.52 | T29: =+M29*$P$2 -> 0 | U29: =+N29*$P$2 -> 12798.697 | V29: =+SUM(R29:U29) -> 866045.18 | X29: =+R29*J29 -> 48137217 | Y29: =+Z29-X29 -> 29806849 | Z29: =+V29*J29 -> 77944066 | AB29: ESTRUCTURA RESISTENTE | AC29: 0.1591 | AD29: 0 | AE29: =AC29+AD29 -> 0.1591 | AF29: =IF($AE29=1,"🔴","⚪") -> ⚪ | AG29: =AC29*Z29 -> 12400901 | AH29: =AD29*Z29 -> 0 | AI29: =AE29*Z29 -> 12400901 | AK29: =AE29*X29 -> 7658631.2 | AL29: =AE29*S29*J29 -> 4559005.2 | AM29: =AE29*T29*J29 -> 0 | AN29: =AE29*U29*J29 -> 183264.55 | AO29: =AK29+AL29+AM29+AN29 -> 12400901 | AQ29: =+O29 -> 603290.75 | AR29: =+O29*J29 -> 54296168
A30: Hormigón | B30: - | C30: Hormigón | D30: Hormigón | F30: 3.1 | G30: OK | H30: Losa maciza de Hº visto - H35 (100 kg/m3 de hierro) | I30: m3 | J30: 32 | K30: 379758.83 | L30: 221790.79 | M30: 55447.699 | N30: 9854.9599 | O30: =+SUM(K30:N30) -> 666852.29 | P30: =+O30*$P$2 -> 957290.01 | R30: =+K30*$P$2 -> 545157.22 | S30: =+L30*$P$2 -> 318388.52 | T30: =+M30*$P$2 -> 79597.13 | U30: =+N30*$P$2 -> 14147.143 | V30: =+SUM(R30:U30) -> 957290.01 | X30: =+R30*J30 -> 17445031 | Y30: =+Z30-X30 -> 13188249 | Z30: =+V30*J30 -> 30633280 | AB30: ESTRUCTURA RESISTENTE | AC30: 1 | AD30: 0 | AE30: =AC30+AD30 -> 1 | AF30: =IF($AE30=1,"🔴","⚪") -> 🔴 | AG30: =AC30*Z30 -> 30633280 | AH30: =AD30*Z30 -> 0 | AI30: =AE30*Z30 -> 30633280 | AK30: =AE30*X30 -> 17445031 | AL30: =AE30*S30*J30 -> 10188433 | AM30: =AE30*T30*J30 -> 2547108.2 | AN30: =AE30*U30*J30 -> 452708.58 | AO30: =AK30+AL30+AM30+AN30 -> 30633280 | AQ30: =+O30 -> 666852.29 | AR30: =+O30*J30 -> 21339273
A31: Hormigón | B31: - | C31: Hormigón | D31: - | F31: 3.11 | G31: OK | H31: Vigas - H35 (180 kg/m3 de hierro) | I31: m3 | J31: 46 | K31: 567913.51 | L31: 537036.81 | M31: 0 | N31: 16574.255 | O31: =+SUM(K31:N31) -> 1121524.6 | P31: =+O31*$P$2 -> 1609988.1 | R31: =+K31*$P$2 -> 815259.9 | S31: =+L31*$P$2 -> 770935.3 | T31: =+M31*$P$2 -> 0 | U31: =+N31*$P$2 -> 23792.928 | V31: =+SUM(R31:U31) -> 1609988.1 | X31: =+R31*J31 -> 37501955 | Y31: =+Z31-X31 -> 36557499 | Z31: =+V31*J31 -> 74059454 | AB31: ESTRUCTURA RESISTENTE | AC31: 0.6984 | AD31: 0 | AE31: =AC31+AD31 -> 0.6984 | AF31: =IF($AE31=1,"🔴","⚪") -> ⚪ | AG31: =AC31*Z31 -> 51723123 | AH31: =AD31*Z31 -> 0 | AI31: =AE31*Z31 -> 51723123 | AK31: =AE31*X31 -> 26191366 | AL31: =AE31*S31*J31 -> 24767376 | AM31: =AE31*T31*J31 -> 0 | AN31: =AE31*U31*J31 -> 764381.12 | AO31: =AK31+AL31+AM31+AN31 -> 51723123 | AQ31: =+O31 -> 1121524.6 | AR31: =+O31*J31 -> 51590130
A32: Hormigón | B32: - | C32: Hormigón | D32: Hormigón | F32: 3.12 | G32: OK | H32: Vigas de H° visto - H35 (180 kg/m3 de hierro) | I32: m3 | J32: 31 | K32: 565756.87 | L32: 537036.81 | M32: 134259.2 | N32: 18555.793 | O32: =+SUM(K32:N32) -> 1255608.7 | P32: =+O32*$P$2 -> 1802470.6 | R32: =+K32*$P$2 -> 812163.96 | S32: =+L32*$P$2 -> 770935.3 | T32: =+M32*$P$2 -> 192733.83 | U32: =+N32*$P$2 -> 26637.496 | V32: =+SUM(R32:U32) -> 1802470.6 | X32: =+R32*J32 -> 25177083 | Y32: =+Z32-X32 -> 30699505 | Z32: =+V32*J32 -> 55876588 | AB32: ESTRUCTURA RESISTENTE | AC32: 1 | AD32: 0 | AE32: =AC32+AD32 -> 1 | AF32: =IF($AE32=1,"🔴","⚪") -> 🔴 | AG32: =AC32*Z32 -> 55876588 | AH32: =AD32*Z32 -> 0 | AI32: =AE32*Z32 -> 55876588 | AK32: =AE32*X32 -> 25177083 | AL32: =AE32*S32*J32 -> 23898994 | AM32: =AE32*T32*J32 -> 5974748.6 | AN32: =AE32*U32*J32 -> 825762.39 | AO32: =AK32+AL32+AM32+AN32 -> 55876588 | AQ32: =+O32 -> 1255608.7 | AR32: =+O32*J32 -> 38923869
... A41: Hormigón | B41: - | C41: - | D41: Hormigón | F41: 3.22 | G41: OK | H41: Picado de medianeras para columnas y vigas - Cotizado para PB y 1P | I41: m2 | J41: 78 | K41: 7051.2821 | L41: 0 | M41: 17829.919 | N41: 373.21802 | O41: =+SUM(K41:N41) -> 25254.419 | P41: =+O41*$P$2 -> 36253.611 | R41: =+K41*$P$2 -> 10122.364 | S41: =+L41*$P$2 -> 0 | T41: =+M41*$P$2 -> 25595.479 | U41: =+N41*$P$2 -> 535.76764 | V41: =+SUM(R41:U41) -> 36253.611 | X41: =+R41*J41 -> 789544.42 | Y41: =+Z41-X41 -> 2038237.2 | Z41: =+V41*J41 -> 2827781.6 | AB41: ESTRUCTURA RESISTENTE | AC41: 1 | AD41: 0 | AE41: =AC41+AD41 -> 1 | AF41: =IF($AE41=1,"🔴","⚪") -> 🔴 | AG41: =AC41*Z41 -> 2827781.6 | AH41: =AD41*Z41 -> 0 | AI41: =AE41*Z41 -> 2827781.6 | AK41: =AE41*X41 -> 789544.42 | AL41: =AE41*S41*J41 -> 0 | AM41: =AE41*T41*J41 -> 1996447.3 | AN41: =AE41*U41*J41 -> 41789.876 | AO41: =AK41+AL41+AM41+AN41 -> 2827781.6 | AQ41: =+O41 -> 25254.419 | AR41: =+O41*J41 -> 1969844.7
A42: - | B42: - | C42: - | D42: - | F42: 4 | H42: MAMPOSTERÍA | AA42: =+SUM(Z43:Z56) -> 64182207 | AB42: MAMPOSTERÍA
A43: Albañilería | B43: - | C43: - | D43: Albañilería | F43: 4.01 | G43: OK | H43: Muro tipo 1 - Ladrillo hueco 8 x 18 x 33 | I43: m2 | J43: 621 | K43: 10253.952 | L43: 0 | M43: 16311.975 | N43: 365.95526 | O43: =+SUM(K43:N43) -> 26931.882 | P43: =+O43*$P$2 -> 38661.668 | R43: =+K43*$P$2 -> 14719.91 | S43: =+L43*$P$2 -> 0 | T43: =+M43*$P$2 -> 23416.416 | U43: =+N43*$P$2 -> 525.34171 | V43: =+SUM(R43:U43) -> 38661.668 | X43: =+R43*J43 -> 9141064.1 | Y43: =+Z43-X43 -> 14867832 | Z43: =+V43*J43 -> 24008896 | AB43: MAMPOSTERÍA | AC43: 0.85 | AD43: 0 | AE43: =AC43+AD43 -> 0.85 | AF43: =IF($AE43=1,"🔴","⚪") -> ⚪ | AG43: =AC43*Z43 -> 20407561 | AH43: =AD43*Z43 -> 0 | AI43: =AE43*Z43 -> 20407561 | AK43: =AE43*X43 -> 7769904.5 | AL43: =AE43*S43*J43 -> 0 | AM43: =AE43*T43*J43 -> 12360355 | AN43: =AE43*U43*J43 -> 277301.62 | AO43: =AK43+AL43+AM43+AN43 -> 20407561 | AQ43: =+O43 -> 26931.882 | AR43: =+O43*J43 -> 16724699
A44: Albañilería | B44: - | C44: - | D44: Albañilería | F44: 4.02 | G44: OK | H44: Muro tipo 2 - Ladrillo hueco 12 x 18 x 33 | I44: m2 | J44: 780 | K44: 8314.4981 | L44: 0 | M44: 9785.8452 | N44: 235.33191 | O44: =+SUM(K44:N44) -> 18335.675 | P44: =+O44*$P$2 -> 26321.509 | R44: =+K44*$P$2 -> 11935.756 | S44: =+L44*$P$2 -> 0 | T44: =+M44*$P$2 -> 14047.926 | U44: =+N44*$P$2 -> 337.82727 | V44: =+SUM(R44:U44) -> 26321.509 | X44: =+R44*J44 -> 9309889.4 | Y44: =+Z44-X44 -> 11220888 | Z44: =+V44*J44 -> 20530777 | AB44: MAMPOSTERÍA | AC44: 0.85 | AD44: 0 | AE44: =AC44+AD44 -> 0.85 | AF44: =IF($AE44=1,"🔴","⚪") -> ⚪ | AG44: =AC44*Z44 -> 17451161 | AH44: =AD44*Z44 -> 0 | AI44: =AE44*Z44 -> 17451161 | AK44: =AE44*X44 -> 7913406 | AL44: =AE44*S44*J44 -> 0 | AM44: =AE44*T44*J44 -> 9313775.2 | AN44: =AE44*U44*J44 -> 223979.48 | AO44: =AK44+AL44+AM44+AN44 -> 17451161 | AQ44: =+O44 -> 18335.675 | AR44: =+O44*J44 -> 14301827
A45: Albañilería | B45: - | C45: - | D45: Albañilería | F45: 4.03 | G45: OK | H45: Muro tipo 3 - Ladrillo comun en panderete | I45: m2 | J45: 56 | K45: 6454.6901 | L45: 0 | M45: 10484.834 | N45: 504.28267 | O45: =+SUM(K45:N45) -> 17443.807 | P45: =+O45*$P$2 -> 25041.201 | R45: =+K45*$P$2 -> 9265.9357 | S45: =+L45*$P$2 -> 0 | T45: =+M45*$P$2 -> 15051.35 | U45: =+N45*$P$2 -> 723.91558 | V45: =+SUM(R45:U45) -> 25041.201 | X45: =+R45*J45 -> 518892.4 | Y45: =+Z45-X45 -> 883414.86 | Z45: =+V45*J45 -> 1402307.3 | AB45: MAMPOSTERÍA | AC45: 1 | AD45: 0 | AE45: =AC45+AD45 -> 1 | AF45: =IF($AE45=1,"🔴","⚪") -> 🔴 | AG45: =AC45*Z45 -> 1402307.3 | AH45: =AD45*Z45 -> 0 | AI45: =AE45*Z45 -> 1402307.3 | AK45: =AE45*X45 -> 518892.4 | AL45: =AE45*S45*J45 -> 0 | AM45: =AE45*T45*J45 -> 842875.58 | AN45: =AE45*U45*J45 -> 40539.273 | AO45: =AK45+AL45+AM45+AN45 -> 1402307.3 | AQ45: =+O45 -> 17443.807 | AR45: =+O45*J45 -> 976853.19
A46: Albañilería | B46: - | C46: - | D46: Albañilería | F46: 4.04 | G46: OK | H46: Muro tipo 4 - Ladrillo hueco portante 12 x 18 x 33 | I46: m2 | J46: 42 | K46: 11547.894 | L46: 0 | M46: 9785.8452 | N46: 235.33191 | O46: =+SUM(K46:N46) -> 21569.071 | P46: =+O46*$P$2 -> 30963.163 | R46: =+K46*$P$2 -> 16577.409 | S46: =+L46*$P$2 -> 0 | T46: =+M46*$P$2 -> 14047.926 | U46: =+N46*$P$2 -> 337.82727 | V46: =+SUM(R46:U46) -> 30963.163 | X46: =+R46*J46 -> 696251.19 | Y46: =+Z46-X46 -> 604201.65 | Z46: =+V46*J46 -> 1300452.8 | AB46: MAMPOSTERÍA | AC46: 0.7 | AD46: 0 | AE46: =AC46+AD46 -> 0.7 | AF46: =IF($AE46=1,"🔴","⚪") -> ⚪ | AG46: =AC46*Z46 -> 910316.99 | AH46: =AD46*Z46 -> 0 | AI46: =AE46*Z46 -> 910316.99 | AK46: =AE46*X46 -> 487375.83 | AL46: =AE46*S46*J46 -> 0 | AM46: =AE46*T46*J46 -> 413009.04 | AN46: =AE46*U46*J46 -> 9932.1218 | AO46: =AK46+AL46+AM46+AN46 -> 910316.99 | AQ46: =+O46 -> 21569.071 | AR46: =+O46*J46 -> 905900.98
A47: Albañilería | B47: - | C47: - | D47: Albañilería | F47: 4.05 | G47: IN | H47: Muro tipo 5 - Bloque HCCA e: 7,5 cm | I47: m2 | J47: 70 | K47: 16817.941 | L47: 0 | M47: 10484.834 | N47: 409.54162 | O47: =+SUM(K47:N47) -> 27712.316 | P47: =+O47*$P$2 -> 39782.009 | R47: =+K47*$P$2 -> 24142.748 | S47: =+L47*$P$2 -> 0 | T47: =+M47*$P$2 -> 15051.35 | U47: =+N47*$P$2 -> 587.91146 | V47: =+SUM(R47:U47) -> 39782.009 | X47: =+R47*J47 -> 1689992.3 | Y47: =+Z47-X47 -> 1094748.3 | Z47: =+V47*J47 -> 2784740.6 | AB47: MAMPOSTERÍA | AC47: 0.1 | AD47: 0 | AE47: =AC47+AD47 -> 0.1 | AF47: =IF($AE47=1,"🔴","⚪") -> ⚪ | AG47: =AC47*Z47 -> 278474.06 | AH47: =AD47*Z47 -> 0 | AI47: =AE47*Z47 -> 278474.06 | AK47: =AE47*X47 -> 168999.23 | AL47: =AE47*S47*J47 -> 0 | AM47: =AE47*T47*J47 -> 105359.45 | AN47: =AE47*U47*J47 -> 4115.3802 | AO47: =AK47+AL47+AM47+AN47 -> 278474.06 | AQ47: =+O47 -> 27712.316 | AR47: =+O47*J47 -> 1939862.2
A48: Albañilería | B48: - | C48: - | D48: Albañilería | F48: 4.06 | G48: OK | H48: Muro tipo 6 - Ladrillo hueco 18 x 18 x 33 | I48: m2 | J48: 5 | K48: 11492.44 | L48: 0 | M48: 9785.8452 | N48: 235.33191 | O48: =+SUM(K48:N48) -> 21513.617 | P48: =+O48*$P$2 -> 30883.558 | R48: =+K48*$P$2 -> 16497.804 | S48: =+L48*$P$2 -> 0 | T48: =+M48*$P$2 -> 14047.926 | U48: =+N48*$P$2 -> 337.82727 | V48: =+SUM(R48:U48) -> 30883.558 | X48: =+R48*J48 -> 82489.02 | Y48: =+Z48-X48 -> 71928.768 | Z48: =+V48*J48 -> 154417.79 | AB48: MAMPOSTERÍA | AC48: 0.1 | AD48: 0 | AE48: =AC48+AD48 -> 0.1 | AF48: =IF($AE48=1,"🔴","⚪") -> ⚪ | AG48: =AC48*Z48 -> 15441.779 | AH48: =AD48*Z48 -> 0 | AI48: =AE48*Z48 -> 15441.779 | AK48: =AE48*X48 -> 8248.902 | AL48: =AE48*S48*J48 -> 0 | AM48: =AE48*T48*J48 -> 7023.9632 | AN48: =AE48*U48*J48 -> 168.91364 | AO48: =AK48+AL48+AM48+AN48 -> 15441.779 | AQ48: =+O48 -> 21513.617 | AR48: =+O48*J48 -> 107568.09
A49: Albañilería | B49: - | C49: - | D49: Albañilería | F49: 4.07 | G49: OK | H49: Enchape de medianeras existentes - Contemplamos picado zonas sueltas y enchape con ladrillo comun para PB | I49: m2 | J49: 193 | K49: 3227.3451 | L49: 0 | M49: 10484.834 | N49: 252.14133 | O49: =+SUM(K49:N49) -> 13964.321 | P49: =+O49*$P$2 -> 20046.275 | R49: =+K49*$P$2 -> 4632.9678 | S49: =+L49*$P$2 -> 0 | T49: =+M49*$P$2 -> 15051.35 | U49: =+N49*$P$2 -> 361.95779 | V49: =+SUM(R49:U49) -> 20046.275 | X49: =+R49*J49 -> 894162.79 | Y49: =+Z49-X49 -> 2974768.3 | Z49: =+V49*J49 -> 3868931.1 | AB49: MAMPOSTERÍA | AC49: 0 | AD49: 0 | AE49: =AC49+AD49 -> 0 | AF49: =IF($AE49=1,"🔴","⚪") -> ⚪ | AG49: =AC49*Z49 -> 0 | AH49: =AD49*Z49 -> 0 | AI49: =AE49*Z49 -> 0 | AK49: =AE49*X49 -> 0 | AL49: =AE49*S49*J49 -> 0 | AM49: =AE49*T49*J49 -> 0 | AN49: =AE49*U49*J49 -> 0 | AO49: =AK49+AL49+AM49+AN49 -> 0 | AQ49: =+O49 -> 13964.321 | AR49: =+O49*J49 -> 2695113.9
A50: Albañilería | B50: - | C50: - | D50: Albañilería | F50: 4.08 | G50: IN | H50: Cordón de hormigón en umbrales carpinterías | I50: ml | J50: 61 | K50: 9093.9863 | L50: 0 | M50: 12031.777 | N50: 316.88645 | O50: =+SUM(K50:N50) -> 21442.65 | P50: =+O50*$P$2 -> 30781.681 | R50: =+K50*$P$2 -> 13054.738 | S50: =+L50*$P$2 -> 0 | T50: =+M50*$P$2 -> 17272.041 | U50: =+N50*$P$2 -> 454.90169 | V50: =+SUM(R50:U50) -> 30781.681 | X50: =+R50*J50 -> 796339.05 | Y50: =+Z50-X50 -> 1081343.5 | Z50: =+V50*J50 -> 1877682.5 | AB50: MAMPOSTERÍA | AC50: 0.6 | AD50: 0 | AE50: =AC50+AD50 -> 0.6 | AF50: =IF($AE50=1,"🔴","⚪") -> ⚪ | AG50: =AC50*Z50 -> 1126609.5 | AH50: =AD50*Z50 -> 0 | AI50: =AE50*Z50 -> 1126609.5 | AK50: =AE50*X50 -> 477803.43 | AL50: =AE50*S50*J50 -> 0 | AM50: =AE50*T50*J50 -> 632156.69 | AN50: =AE50*U50*J50 -> 16649.402 | AO50: =AK50+AL50+AM50+AN50 -> 1126609.5 | AQ50: =+O50 -> 21442.65 | AR50: =+O50*J50 -> 1308001.6
A51: Albañilería | B51: - | C51: - | D51: Albañilería | F51: 4.09 | G51: IN | H51: Banquina Sala tanque de bombeo | I51: gl | J51: 1 | K51: 60811.031 | L51: 0 | M51: 146787.68 | N51: 3113.9806 | O51: =+SUM(K51:N51) -> 210712.69 | P51: =+O51*$P$2 -> 302485.51 | R51: =+K51*$P$2 -> 87296.383 | S51: =+L51*$P$2 -> 0 | T51: =+M51*$P$2 -> 210718.9 | U51: =+N51*$P$2 -> 4470.2292 | V51: =+SUM(R51:U51) -> 302485.51 | X51: =+R51*J51 -> 87296.383 | Y51: =+Z51-X51 -> 215189.13 | Z51: =+V51*J51 -> 302485.51 | AB51: MAMPOSTERÍA | AC51: 0 | AD51: 0 | AE51: =AC51+AD51 -> 0 | AF51: =IF($AE51=1,"🔴","⚪") -> ⚪ | AG51: =AC51*Z51 -> 0 | AH51: =AD51*Z51 -> 0 | AI51: =AE51*Z51 -> 0 | AK51: =AE51*X51 -> 0 | AL51: =AE51*S51*J51 -> 0 | AM51: =AE51*T51*J51 -> 0 | AN51: =AE51*U51*J51 -> 0 | AO51: =AK51+AL51+AM51+AN51 -> 0 | AQ51: =+O51 -> 210712.69 | AR51: =+O51*J51 -> 210712.69
A52: Albañilería | B52: - | C52: - | D52: Albañilería | F52: 4.1 | G52: IN | H52: Banquina en parrillas | I52: gl | J52: 1 | K52: 151935.62 | L52: 0 | M52: 440363.03 | N52: 8884.4798 | O52: =+SUM(K52:N52) -> 601183.14 | P52: =+O52*$P$2 -> 863019.62 | R52: =+K52*$P$2 -> 218108.95 | S52: =+L52*$P$2 -> 0 | T52: =+M52*$P$2 -> 632156.69 | U52: =+N52*$P$2 -> 12753.985 | V52: =+SUM(R52:U52) -> 863019.62 | X52: =+R52*J52 -> 218108.95 | Y52: =+Z52-X52 -> 644910.67 | Z52: =+V52*J52 -> 863019.62 | AB52: MAMPOSTERÍA | AC52: 0 | AD52: 0 | AE52: =AC52+AD52 -> 0 | AF52: =IF($AE52=1,"🔴","⚪") -> ⚪ | AG52: =AC52*Z52 -> 0 | AH52: =AD52*Z52 -> 0 | AI52: =AE52*Z52 -> 0 | AK52: =AE52*X52 -> 0 | AL52: =AE52*S52*J52 -> 0 | AM52: =AE52*T52*J52 -> 0 | AN52: =AE52*U52*J52 -> 0 | AO52: =AK52+AL52+AM52+AN52 -> 0 | AQ52: =+O52 -> 601183.14 | AR52: =+O52*J52 -> 601183.14
A53: Albañilería | B53: - | C53: - | D53: Albañilería | F53: 4.11 | G53: OK | H53: Excavación y amurado con Hº tanque de recuperación de agua de lluvia | I53: gl | J53: 1 | K53: 128742.9 | L53: 0 | M53: 259536.82 | N53: 5824.1958 | O53: =+SUM(K53:N53) -> 394103.91 | P53: =+O53*$P$2 -> 565750.09 | R53: =+K53*$P$2 -> 184814.97 | S53: =+L53*$P$2 -> 0 | T53: =+M53*$P$2 -> 372574.27 | U53: =+N53*$P$2 -> 8360.8387 | V53: =+SUM(R53:U53) -> 565750.09 | X53: =+R53*J53 -> 184814.97 | Y53: =+Z53-X53 -> 380935.11 | Z53: =+V53*J53 -> 565750.09 | AB53: MAMPOSTERÍA | AC53: 0 | AD53: 0 | AE53: =AC53+AD53 -> 0 | AF53: =IF($AE53=1,"🔴","⚪") -> ⚪ | AG53: =AC53*Z53 -> 0 | AH53: =AD53*Z53 -> 0 | AI53: =AE53*Z53 -> 0 | AK53: =AE53*X53 -> 0 | AL53: =AE53*S53*J53 -> 0 | AM53: =AE53*T53*J53 -> 0 | AN53: =AE53*U53*J53 -> 0 | AO53: =AK53+AL53+AM53+AN53 -> 0 | AQ53: =+O53 -> 394103.91 | AR53: =+O53*J53 -> 394103.91
A54: Albañilería | B54: - | C54: - | D54: Albañilería | F54: 4.12 | G54: OK | H54: Provisión y amurado de tapas de inspección para tanque de reserva | I54: u | J54: 3 | K54: 121487.6 | L54: 0 | M54: 54294.059 | N54: 2636.7249 | O54: =+SUM(K54:N54) -> 178418.39 | P54: =+O54*$P$2 -> 256125.9 | R54: =+K54*$P$2 -> 174399.75 | S54: =+L54*$P$2 -> 0 | T54: =+M54*$P$2 -> 77941.039 | U54: =+N54*$P$2 -> 3785.1118 | V54: =+SUM(R54:U54) -> 256125.9 | X54: =+R54*J54 -> 523199.24 | Y54: =+Z54-X54 -> 245178.45 | Z54: =+V54*J54 -> 768377.69 | AB54: MAMPOSTERÍA | AC54: 0 | AD54: 0 | AE54: =AC54+AD54 -> 0 | AF54: =IF($AE54=1,"🔴","⚪") -> ⚪ | AG54: =AC54*Z54 -> 0 | AH54: =AD54*Z54 -> 0 | AI54: =AE54*Z54 -> 0 | AK54: =AE54*X54 -> 0 | AL54: =AE54*S54*J54 -> 0 | AM54: =AE54*T54*J54 -> 0 | AN54: =AE54*U54*J54 -> 0 | AO54: =AK54+AL54+AM54+AN54 -> 0 | AQ54: =+O54 -> 178418.39 | AR54: =+O54*J54 -> 535255.16
... A56: Albañilería | B56: - | C56: - | D56: Albañilería | F56: 4.14 | G56: IN | H56: Amurado de bañera | I56: u | J56: 8 | K56: 23946.262 | L56: 0 | M56: 107385.37 | N56: 1969.9745 | O56: =+SUM(K56:N56) -> 133301.61 | P56: =+O56*$P$2 -> 191359.16 | R56: =+K56*$P$2 -> 34375.705 | S56: =+L56*$P$2 -> 0 | T56: =+M56*$P$2 -> 154155.49 | U56: =+N56*$P$2 -> 2827.9679 | V56: =+SUM(R56:U56) -> 191359.16 | X56: =+R56*J56 -> 275005.64 | Y56: =+Z56-X56 -> 1255867.7 | Z56: =+V56*J56 -> 1530873.3 | AB56: MAMPOSTERÍA | AC56: 0 | AD56: 0 | AE56: =AC56+AD56 -> 0 | AF56: =IF($AE56=1,"🔴","⚪") -> ⚪ | AG56: =AC56*Z56 -> 0 | AH56: =AD56*Z56 -> 0 | AI56: =AE56*Z56 -> 0 | AK56: =AE56*X56 -> 0 | AL56: =AE56*S56*J56 -> 0 | AM56: =AE56*T56*J56 -> 0 | AN56: =AE56*U56*J56 -> 0 | AO56: =AK56+AL56+AM56+AN56 -> 0 | AQ56: =+O56 -> 133301.61 | AR56: =+O56*J56 -> 1066412.9
A57: - | B57: - | C57: - | D57: - | F57: 5 | H57: AISLACIONES | AA57: =+SUM(Z58:Z64) -> 20723410 | AB57: AISLACIONES
A58: Albañilería | B58: - | C58: - | D58: Albañilería | F58: 5.01 | G58: OK | H58: Cajón hidrofugo | I58: ml | J58: 136 | K58: 809.61503 | L58: 0 | M58: 3938.2618 | N58: 126.07067 | O58: =+SUM(K58:N58) -> 4873.9475 | P58: =+O58*$P$2 -> 6996.7237 | R58: =+K58*$P$2 -> 1162.231 | S58: =+L58*$P$2 -> 0 | T58: =+M58*$P$2 -> 5653.5139 | U58: =+N58*$P$2 -> 180.9789 | V58: =+SUM(R58:U58) -> 6996.7237 | X58: =+R58*J58 -> 158063.41 | Y58: =+Z58-X58 -> 793491.01 | Z58: =+V58*J58 -> 951554.43 | AB58: AISLACIONES | AC58: 0 | AD58: 0 | AE58: =AC58+AD58 -> 0 | AF58: =IF($AE58=1,"🔴","⚪") -> ⚪ | AG58: =AC58*Z58 -> 0 | AH58: =AD58*Z58 -> 0 | AI58: =AE58*Z58 -> 0 | AK58: =AE58*X58 -> 0 | AL58: =AE58*S58*J58 -> 0 | AM58: =AE58*T58*J58 -> 0 | AN58: =AE58*U58*J58 -> 0 | AO58: =AK58+AL58+AM58+AN58 -> 0 | AQ58: =+O58 -> 4873.9475 | AR58: =+O58*J58 -> 662856.86
A59: Albañilería | B59: - | C59: Albañilería | D59: Albañilería | F59: 5.02 | G59: OK | H59: Aislación hidrófuga horizontal (baños) - Inc. membrana geotextil y 35% en concepto de babetas | I59: m2 | J59: 77 | K59: 13188.358 | L59: 5871.5071 | M59: 5871.5071 | N59: 32.180227 | O59: =+SUM(K59:N59) -> 24963.552 | P59: =+O59*$P$2 -> 35836.061 | R59: =+K59*$P$2 -> 18932.353 | S59: =+L59*$P$2 -> 8428.7558 | T59: =+M59*$P$2 -> 8428.7558 | U59: =+N59*$P$2 -> 46.195853 | V59: =+SUM(R59:U59) -> 35836.061 | X59: =+R59*J59 -> 1457791.2 | Y59: =+Z59-X59 -> 1301585.5 | Z59: =+V59*J59 -> 2759376.7 | AB59: AISLACIONES | AC59: 0 | AD59: 0 | AE59: =AC59+AD59 -> 0 | AF59: =IF($AE59=1,"🔴","⚪") -> ⚪ | AG59: =AC59*Z59 -> 0 | AH59: =AD59*Z59 -> 0 | AI59: =AE59*Z59 -> 0 | AK59: =AE59*X59 -> 0 | AL59: =AE59*S59*J59 -> 0 | AM59: =AE59*T59*J59 -> 0 | AN59: =AE59*U59*J59 -> 0 | AO59: =AK59+AL59+AM59+AN59 -> 0 | AQ59: =+O59 -> 24963.552 | AR59: =+O59*J59 -> 1922193.5
A60: Albañilería | B60: - | C60: - | D60: Albañilería | F60: 5.03 | G60: OK | H60: Azotado hidrófugo - Contrapiso de PB | I60: m2 | J60: 107 | K60: 809.61503 | L60: 0 | M60: 3938.2618 | N60: 126.07067 | O60: =+SUM(K60:N60) -> 4873.9475 | P60: =+O60*$P$2 -> 6996.7237 | R60: =+K60*$P$2 -> 1162.231 | S60: =+L60*$P$2 -> 0 | T60: =+M60*$P$2 -> 5653.5139 | U60: =+N60*$P$2 -> 180.9789 | V60: =+SUM(R60:U60) -> 6996.7237 | X60: =+R60*J60 -> 124358.71 | Y60: =+Z60-X60 -> 624290.72 | Z60: =+V60*J60 -> 748649.44 | AB60: AISLACIONES | AC60: 0 | AD60: 0 | AE60: =AC60+AD60 -> 0 | AF60: =IF($AE60=1,"🔴","⚪") -> ⚪ | AG60: =AC60*Z60 -> 0 | AH60: =AD60*Z60 -> 0 | AI60: =AE60*Z60 -> 0 | AK60: =AE60*X60 -> 0 | AL60: =AE60*S60*J60 -> 0 | AM60: =AE60*T60*J60 -> 0 | AN60: =AE60*U60*J60 -> 0 | AO60: =AK60+AL60+AM60+AN60 -> 0 | AQ60: =+O60 -> 4873.9475 | AR60: =+O60*J60 -> 521512.38
A61: Albañilería | B61: - | C61: - | D61: - | F61: 5.04 | G61: OK | H61: Aislación térmica en terrazas, eps e:2,00 cm | I61: m2 | J61: 186 | K61: 3625.4 | L61: 0 | M61: 0 | N61: 0 | O61: =+SUM(K61:N61) -> 3625.4 | P61: =+O61*$P$2 -> 5204.3897 | R61: =+K61*$P$2 -> 5204.3897 | S61: =+L61*$P$2 -> 0 | T61: =+M61*$P$2 -> 0 | U61: =+N61*$P$2 -> 0 | V61: =+SUM(R61:U61) -> 5204.3897 | X61: =+R61*J61 -> 968016.49 | Y61: =+Z61-X61 -> 0 | Z61: =+V61*J61 -> 968016.49 | AB61: AISLACIONES | AC61: 0 | AD61: 0 | AE61: =AC61+AD61 -> 0 | AF61: =IF($AE61=1,"🔴","⚪") -> ⚪ | AG61: =AC61*Z61 -> 0 | AH61: =AD61*Z61 -> 0 | AI61: =AE61*Z61 -> 0 | AK61: =AE61*X61 -> 0 | AL61: =AE61*S61*J61 -> 0 | AM61: =AE61*T61*J61 -> 0 | AN61: =AE61*U61*J61 -> 0 | AO61: =AK61+AL61+AM61+AN61 -> 0 | AQ61: =+O61 -> 3625.4 | AR61: =+O61*J61 -> 674324.4
A62: Albañilería | B62: - | C62: - | D62: Albañilería | F62: 5.05 | G62: OK | H62: Barrera de vapor | I62: m2 | J62: 186 | K62: 1256.6125 | L62: 0 | M62: 1834.846 | N62: 10.056321 | O62: =+SUM(K62:N62) -> 3101.5148 | P62: =+O62*$P$2 -> 4452.3341 | R62: =+K62*$P$2 -> 1803.9117 | S62: =+L62*$P$2 -> 0 | T62: =+M62*$P$2 -> 2633.9862 | U62: =+N62*$P$2 -> 14.436204 | V62: =+SUM(R62:U62) -> 4452.3341 | X62: =+R62*J62 -> 335527.57 | Y62: =+Z62-X62 -> 492606.57 | Z62: =+V62*J62 -> 828134.14 | AB62: AISLACIONES | AC62: 1 | AD62: 0 | AE62: =AC62+AD62 -> 1 | AF62: =IF($AE62=1,"🔴","⚪") -> 🔴 | AG62: =AC62*Z62 -> 828134.14 | AH62: =AD62*Z62 -> 0 | AI62: =AE62*Z62 -> 828134.14 | AK62: =AE62*X62 -> 335527.57 | AL62: =AE62*S62*J62 -> 0 | AM62: =AE62*T62*J62 -> 489921.43 | AN62: =AE62*U62*J62 -> 2685.134 | AO62: =AK62+AL62+AM62+AN62 -> 828134.14 | AQ62: =+O62 -> 3101.5148 | AR62: =+O62*J62 -> 576881.76
A63: Albañilería | B63: - | C63: Albañilería | D63: Albañilería | F63: 5.06 | G63: OK | H63: Membrana asfáltica geotextil 4mm - Balcones y azotea - Inc. 20% en concepto de babetas | I63: m2 | J63: 390 | K63: 11722.985 | L63: 3522.9043 | M63: 5871.5071 | N63: 32.180227 | O63: =+SUM(K63:N63) -> 21149.576 | P63: =+O63*$P$2 -> 30360.964 | R63: =+K63*$P$2 -> 16828.758 | S63: =+L63*$P$2 -> 5057.2535 | T63: =+M63*$P$2 -> 8428.7558 | U63: =+N63*$P$2 -> 46.195853 | V63: =+SUM(R63:U63) -> 30360.964 | X63: =+R63*J63 -> 6563215.7 | Y63: =+Z63-X63 -> 5277560 | Z63: =+V63*J63 -> 11840776 | AB63: AISLACIONES | AC63: 0 | AD63: 0 | AE63: =AC63+AD63 -> 0 | AF63: =IF($AE63=1,"🔴","⚪") -> ⚪ | AG63: =AC63*Z63 -> 0 | AH63: =AD63*Z63 -> 0 | AI63: =AE63*Z63 -> 0 | AK63: =AE63*X63 -> 0 | AL63: =AE63*S63*J63 -> 0 | AM63: =AE63*T63*J63 -> 0 | AN63: =AE63*U63*J63 -> 0 | AO63: =AK63+AL63+AM63+AN63 -> 0 | AQ63: =+O63 -> 21149.576 | AR63: =+O63*J63 -> 8248334.7
A64: Albañilería | B64: - | C64: Albañilería | D64: - | F64: 5.07 | G64: OK | H64: Impermeabilización de tanque de reserva de HºAº | I64: gl | J64: 1 | K64: 0 | L64: 1829911.6 | M64: 0 | N64: 0 | O64: =+SUM(K64:N64) -> 1829911.6 | P64: =+O64*$P$2 -> 2626902.7 | R64: =+K64*$P$2 -> 0 | S64: =+L64*$P$2 -> 2626902.7 | T64: =+M64*$P$2 -> 0 | U64: =+N64*$P$2 -> 0 | V64: =+SUM(R64:U64) -> 2626902.7 | X64: =+R64*J64 -> 0 | Y64: =+Z64-X64 -> 2626902.7 | Z64: =+V64*J64 -> 2626902.7 | AB64: AISLACIONES | AC64: 0 | AD64: 0 | AE64: =AC64+AD64 -> 0 | AF64: =IF($AE64=1,"🔴","⚪") -> ⚪ | AG64: =AC64*Z64 -> 0 | AH64: =AD64*Z64 -> 0 | AI64: =AE64*Z64 -> 0 | AK64: =AE64*X64 -> 0 | AL64: =AE64*S64*J64 -> 0 | AM64: =AE64*T64*J64 -> 0 | AN64: =AE64*U64*J64 -> 0 | AO64: =AK64+AL64+AM64+AN64 -> 0 | AQ64: =+O64 -> 1829911.6 | AR64: =+O64*J64 -> 1829911.6
A65: - | B65: - | C65: - | D65: - | F65: 6 | H65: CUBIERTAS | AA65: =+Z66 -> 1855757.4 | AB65: CUBIERTAS
A66: Albañilería | B66: - | C66: - | D66: Albañilería | F66: 6.02 | G66: OK | H66: Babeta de chapa galvanizada en medianeras | I66: ml | J66: 55 | K66: 14897.521 | L66: 0 | M66: 8259.2819 | N66: 347.35204 | O66: =+SUM(K66:N66) -> 23504.155 | P66: =+O66*$P$2 -> 33741.044 | R66: =+K66*$P$2 -> 21385.917 | S66: =+L66*$P$2 -> 0 | T66: =+M66*$P$2 -> 11856.491 | U66: =+N66*$P$2 -> 498.63612 | V66: =+SUM(R66:U66) -> 33741.044 | X66: =+R66*J66 -> 1176225.4 | Y66: =+Z66-X66 -> 679531.99 | Z66: =+V66*J66 -> 1855757.4 | AB66: CUBIERTAS | AC66: 0 | AD66: 0 | AE66: =AC66+AD66 -> 0 | AF66: =IF($AE66=1,"🔴","⚪") -> ⚪ | AG66: =AC66*Z66 -> 0 | AH66: =AD66*Z66 -> 0 | AI66: =AE66*Z66 -> 0 | AK66: =AE66*X66 -> 0 | AL66: =AE66*S66*J66 -> 0 | AM66: =AE66*T66*J66 -> 0 | AN66: =AE66*U66*J66 -> 0 | AO66: =AK66+AL66+AM66+AN66 -> 0 | AQ66: =+O66 -> 23504.155 | AR66: =+O66*J66 -> 1292728.5
A67: - | B67: - | C67: - | D67: - | F67: 7 | H67: REVOQUES | AA67: =+SUM(Z68:Z73) -> 99444244 | AB67: REVOQUES
A68: Albañilería | B68: - | C68: - | D68: Albañilería | F68: 7.01 | G68: OK | H68: Revoque Grueso Impermeable Exterior | I68: m2 | J68: 879 | K68: 4009.2266 | L68: 0 | M68: 10647.256 | N68: 306.95467 | O68: =+SUM(K68:N68) -> 14963.437 | P68: =+O68*$P$2 -> 21480.543 | R68: =+K68*$P$2 -> 5755.3864 | S68: =+L68*$P$2 -> 0 | T68: =+M68*$P$2 -> 15284.512 | U68: =+N68*$P$2 -> 440.64427 | V68: =+SUM(R68:U68) -> 21480.543 | X68: =+R68*J68 -> 5058984.6 | Y68: =+Z68-X68 -> 13822413 | Z68: =+V68*J68 -> 18881397 | AB68: REVOQUES | AC68: 0 | AD68: 0 | AE68: =AC68+AD68 -> 0 | AF68: =IF($AE68=1,"🔴","⚪") -> ⚪ | AG68: =AC68*Z68 -> 0 | AH68: =AD68*Z68 -> 0 | AI68: =AE68*Z68 -> 0 | AK68: =AE68*X68 -> 0 | AL68: =AE68*S68*J68 -> 0 | AM68: =AE68*T68*J68 -> 0 | AN68: =AE68*U68*J68 -> 0 | AO68: =AK68+AL68+AM68+AN68 -> 0 | AQ68: =+O68 -> 14963.437 | AR68: =+O68*J68 -> 13152861
A69: Albañilería | B69: - | C69: - | D69: Albañilería | F69: 7.02 | G69: OK | H69: Revoque Grueso Impermeable Exterior a mas de 3m - Medianero y fachadas | I69: m2 | J69: 716 | K69: 4009.2266 | L69: 0 | M69: 15305.431 | N69: 769.31526 | O69: =+SUM(K69:N69) -> 20083.973 | P69: =+O69*$P$2 -> 28831.252 | R69: =+K69*$P$2 -> 5755.3864 | S69: =+L69*$P$2 -> 0 | T69: =+M69*$P$2 -> 21971.486 | U69: =+N69*$P$2 -> 1104.3792 | V69: =+SUM(R69:U69) -> 28831.252 | X69: =+R69*J69 -> 4120856.7 | Y69: =+Z69-X69 -> 16522320 | Z69: =+V69*J69 -> 20643176 | AB69: REVOQUES | AC69: 0.4 | AD69: 0 | AE69: =AC69+AD69 -> 0.4 | AF69: =IF($AE69=1,"🔴","⚪") -> ⚪ | AG69: =AC69*Z69 -> 8257270.6 | AH69: =AD69*Z69 -> 0 | AI69: =AE69*Z69 -> 8257270.6 | AK69: =AE69*X69 -> 1648342.7 | AL69: =AE69*S69*J69 -> 0 | AM69: =AE69*T69*J69 -> 6292633.7 | AN69: =AE69*U69*J69 -> 316294.21 | AO69: =AK69+AL69+AM69+AN69 -> 8257270.6 | AQ69: =+O69 -> 20083.973 | AR69: =+O69*J69 -> 14380124
A70: Durlock/Yeso | B70: - | C70: Durlock/Yeso | D70: - | F70: 7.03 | G70: OK | H70: Yeso interior | I70: m2 | J70: 1439 | K70: 5324.1715 | L70: 11651.218 | M70: 0 | N70: 254.63085 | O70: =+SUM(K70:N70) -> 17230.021 | P70: =+O70*$P$2 -> 24734.303 | R70: =+K70*$P$2 -> 7643.0362 | S70: =+L70*$P$2 -> 16725.735 | T70: =+M70*$P$2 -> 0 | U70: =+N70*$P$2 -> 365.53157 | V70: =+SUM(R70:U70) -> 24734.303 | X70: =+R70*J70 -> 10998329 | Y70: =+Z70-X70 -> 24594333 | Z70: =+V70*J70 -> 35592662 | AB70: REVOQUES | AC70: 0.1 | AD70: 0 | AE70: =AC70+AD70 -> 0.1 | AF70: =IF($AE70=1,"🔴","⚪") -> ⚪ | AG70: =AC70*Z70 -> 3559266.2 | AH70: =AD70*Z70 -> 0 | AI70: =AE70*Z70 -> 3559266.2 | AK70: =AE70*X70 -> 1099832.9 | AL70: =AE70*S70*J70 -> 2406833.3 | AM70: =AE70*T70*J70 -> 0 | AN70: =AE70*U70*J70 -> 52599.993 | AO70: =AK70+AL70+AM70+AN70 -> 3559266.2 | AQ70: =+O70 -> 17230.021 | AR70: =+O70*J70 -> 24794000
A71: Durlock/Yeso | B71: - | C71: Durlock/Yeso | D71: - | F71: 7.04 | G71: OK | H71: Arista en yeso | I71: ml | J71: 347 | K71: 0 | L71: 12499.473 | M71: 0 | N71: 187.4921 | O71: =+SUM(K71:N71) -> 12686.965 | P71: =+O71*$P$2 -> 18212.587 | R71: =+K71*$P$2 -> 0 | S71: =+L71*$P$2 -> 17943.435 | T71: =+M71*$P$2 -> 0 | U71: =+N71*$P$2 -> 269.15153 | V71: =+SUM(R71:U71) -> 18212.587 | X71: =+R71*J71 -> 0 | Y71: =+Z71-X71 -> 6319767.6 | Z71: =+V71*J71 -> 6319767.6 | AB71: REVOQUES | AC71: 0.1 | AD71: 0 | AE71: =AC71+AD71 -> 0.1 | AF71: =IF($AE71=1,"🔴","⚪") -> ⚪ | AG71: =AC71*Z71 -> 631976.76 | AH71: =AD71*Z71 -> 0 | AI71: =AE71*Z71 -> 631976.76 | AK71: =AE71*X71 -> 0 | AL71: =AE71*S71*J71 -> 622637.2 | AM71: =AE71*T71*J71 -> 0 | AN71: =AE71*U71*J71 -> 9339.558 | AO71: =AK71+AL71+AM71+AN71 -> 631976.76 | AQ71: =+O71 -> 12686.965 | AR71: =+O71*J71 -> 4402376.9
A72: Albañilería | B72: - | C72: Albañilería | D72: - | F72: 7.05 | G72: OK | H72: Provisión y colocación de guardacanto yesero | I72: un | J72: 132 | K72: 1167.2736 | L72: 13162.324 | M72: 0 | N72: 214.94396 | O72: =+SUM(K72:N72) -> 14544.542 | P72: =+O72*$P$2 -> 20879.203 | R72: =+K72*$P$2 -> 1675.6624 | S72: =+L72*$P$2 -> 18894.981 | T72: =+M72*$P$2 -> 0 | U72: =+N72*$P$2 -> 308.55965 | V72: =+SUM(R72:U72) -> 20879.203 | X72: =+R72*J72 -> 221187.44 | Y72: =+Z72-X72 -> 2534867.4 | Z72: =+V72*J72 -> 2756054.8 | AB72: REVOQUES | AC72: 0.1 | AD72: 0 | AE72: =AC72+AD72 -> 0.1 | AF72: =IF($AE72=1,"🔴","⚪") -> ⚪ | AG72: =AC72*Z72 -> 275605.48 | AH72: =AD72*Z72 -> 0 | AI72: =AE72*Z72 -> 275605.48 | AK72: =AE72*X72 -> 22118.744 | AL72: =AE72*S72*J72 -> 249413.75 | AM72: =AE72*T72*J72 -> 0 | AN72: =AE72*U72*J72 -> 4072.9874 | AO72: =AK72+AL72+AM72+AN72 -> 275605.48 | AQ72: =+O72 -> 14544.542 | AR72: =+O72*J72 -> 1919879.5
A73: Albañilería | B73: - | C73: - | D73: Albañilería | F73: 7.06 | G73: OK | H73: Revoque Grueso Impermeable Interior b/ revestimiento | I73: m2 | J73: 710 | K73: 4009.2266 | L73: 0 | M73: 10647.256 | N73: 306.95467 | O73: =+SUM(K73:N73) -> 14963.437 | P73: =+O73*$P$2 -> 21480.543 | R73: =+K73*$P$2 -> 5755.3864 | S73: =+L73*$P$2 -> 0 | T73: =+M73*$P$2 -> 15284.512 | U73: =+N73*$P$2 -> 440.64427 | V73: =+SUM(R73:U73) -> 21480.543 | X73: =+R73*J73 -> 4086324.3 | Y73: =+Z73-X73 -> 11164861 | Z73: =+V73*J73 -> 15251185 | AB73: REVOQUES | AC73: 0.05 | AD73: 0 | AE73: =AC73+AD73 -> 0.05 | AF73: =IF($AE73=1,"🔴","⚪") -> ⚪ | AG73: =AC73*Z73 -> 762559.27 | AH73: =AD73*Z73 -> 0 | AI73: =AE73*Z73 -> 762559.27 | AK73: =AE73*X73 -> 204316.22 | AL73: =AE73*S73*J73 -> 0 | AM73: =AE73*T73*J73 -> 542600.18 | AN73: =AE73*U73*J73 -> 15642.871 | AO73: =AK73+AL73+AM73+AN73 -> 762559.27 | AQ73: =+O73 -> 14963.437 | AR73: =+O73*J73 -> 10624041
A74: - | B74: - | C74: - | D74: - | F74: 8 | H74: CONTRAPISOS Y CARPETAS | AA74: =+SUM(Z75:Z82) -> 53340004 | AB74: CONTRAPISOS Y CARPETAS
A75: Albañilería | B75: - | C75: - | D75: Albañilería | F75: 8.01 | G75: IN | H75: Contrapiso de Hº armado e: 18 cm, incluye malla Ø 6 mm y film 200 mic. | I75: m2 | J75: 107 | K75: 30940.007 | L75: 0 | M75: 12364.893 | N75: 649.5735 | O75: =+SUM(K75:N75) -> 43954.474 | P75: =+O75*$P$2 -> 63098.199 | R75: =+K75*$P$2 -> 44415.473 | S75: =+L75*$P$2 -> 0 | T75: =+M75*$P$2 -> 17750.241 | U75: =+N75*$P$2 -> 932.48571 | V75: =+SUM(R75:U75) -> 63098.199 | X75: =+R75*J75 -> 4752455.6 | Y75: =+Z75-X75 -> 1999051.8 | Z75: =+V75*J75 -> 6751507.3 | AB75: CONTRAPISOS Y CARPETAS | AC75: 0 | AD75: 0 | AE75: =AC75+AD75 -> 0 | AF75: =IF($AE75=1,"🔴","⚪") -> ⚪ | AG75: =AC75*Z75 -> 0 | AH75: =AD75*Z75 -> 0 | AI75: =AE75*Z75 -> 0 | AK75: =AE75*X75 -> 0 | AL75: =AE75*S75*J75 -> 0 | AM75: =AE75*T75*J75 -> 0 | AN75: =AE75*U75*J75 -> 0 | AO75: =AK75+AL75+AM75+AN75 -> 0 | AQ75: =+O75 -> 43954.474 | AR75: =+O75*J75 -> 4703128.7
A76: Albañilería | B76: - | C76: Albañilería | D76: Albañilería | F76: 8.02 | G76: IN | H76: Contrapiso de H13 subase bajo intertrabado y garden block | I76: m2 | J76: 258 | K76: 22041.278 | L76: 891.47287 | M76: 5697.0204 | N76: 429.44656 | O76: =+SUM(K76:N76) -> 29059.217 | P76: =+O76*$P$2 -> 41715.533 | R76: =+K76*$P$2 -> 31641.032 | S76: =+L76*$P$2 -> 1279.7408 | T76: =+M76*$P$2 -> 8178.274 | U76: =+N76*$P$2 -> 616.48571 | V76: =+SUM(R76:U76) -> 41715.533 | X76: =+R76*J76 -> 8163386.3 | Y76: =+Z76-X76 -> 2599221.1 | Z76: =+V76*J76 -> 10762607 | AB76: CONTRAPISOS Y CARPETAS | AC76: 0 | AD76: 0 | AE76: =AC76+AD76 -> 0 | AF76: =IF($AE76=1,"🔴","⚪") -> ⚪ | AG76: =AC76*Z76 -> 0 | AH76: =AD76*Z76 -> 0 | AI76: =AE76*Z76 -> 0 | AK76: =AE76*X76 -> 0 | AL76: =AE76*S76*J76 -> 0 | AM76: =AE76*T76*J76 -> 0 | AN76: =AE76*U76*J76 -> 0 | AO76: =AK76+AL76+AM76+AN76 -> 0 | AQ76: =+O76 -> 29059.217 | AR76: =+O76*J76 -> 7497278.1
A77: Albañilería | B77: - | C77: - | D77: Albañilería | F77: 8.03 | G77: OK | H77: Monolítico e: 6 cm | I77: m2 | J77: 425 | K77: 6968.0306 | L77: 0 | M77: 10126.741 | N77: 120.04692 | O77: =+SUM(K77:N77) -> 17214.819 | P77: =+O77*$P$2 -> 24712.48 | R77: =+K77*$P$2 -> 10002.854 | S77: =+L77*$P$2 -> 0 | T77: =+M77*$P$2 -> 14537.294 | U77: =+N77*$P$2 -> 172.33159 | V77: =+SUM(R77:U77) -> 24712.48 | X77: =+R77*J77 -> 4251213 | Y77: =+Z77-X77 -> 6251591.1 | Z77: =+V77*J77 -> 10502804 | AB77: CONTRAPISOS Y CARPETAS | AC77: 0 | AD77: 0 | AE77: =AC77+AD77 -> 0 | AF77: =IF($AE77=1,"🔴","⚪") -> ⚪ | AG77: =AC77*Z77 -> 0 | AH77: =AD77*Z77 -> 0 | AI77: =AE77*Z77 -> 0 | AK77: =AE77*X77 -> 0 | AL77: =AE77*S77*J77 -> 0 | AM77: =AE77*T77*J77 -> 0 | AN77: =AE77*U77*J77 -> 0 | AO77: =AK77+AL77+AM77+AN77 -> 0 | AQ77: =+O77 -> 17214.819 | AR77: =+O77*J77 -> 7316297.9
A78: Albañilería | B78: - | C78: - | D78: Albañilería | F78: 8.04 | G78: IN | H78: Contrapiso alivianado en azoteas (RDC), e: 15 cm | I78: m2 | J78: 200 | K78: 24469.45 | L78: 0 | M78: 5362.3939 | N78: 447.47766 | O78: =+SUM(K78:N78) -> 30279.322 | P78: =+O78*$P$2 -> 43467.036 | R78: =+K78*$P$2 -> 35126.76 | S78: =+L78*$P$2 -> 0 | T78: =+M78*$P$2 -> 7697.9059 | U78: =+N78*$P$2 -> 642.36998 | V78: =+SUM(R78:U78) -> 43467.036 | X78: =+R78*J78 -> 7025351.9 | Y78: =+Z78-X78 -> 1668055.2 | Z78: =+V78*J78 -> 8693407.1 | AB78: CONTRAPISOS Y CARPETAS | AC78: 0 | AD78: 0 | AE78: =AC78+AD78 -> 0 | AF78: =IF($AE78=1,"🔴","⚪") -> ⚪ | AG78: =AC78*Z78 -> 0 | AH78: =AD78*Z78 -> 0 | AI78: =AE78*Z78 -> 0 | AK78: =AE78*X78 -> 0 | AL78: =AE78*S78*J78 -> 0 | AM78: =AE78*T78*J78 -> 0 | AN78: =AE78*U78*J78 -> 0 | AO78: =AK78+AL78+AM78+AN78 -> 0 | AQ78: =+O78 -> 30279.322 | AR78: =+O78*J78 -> 6055864.3
A79: Albañilería | B79: - | C79: - | D79: Albañilería | F79: 8.05 | G79: IN | H79: Contrapiso con piedra binder e: 4/5 cm - En locales húmedos (baños) | I79: m2 | J79: 77 | K79: 8233.9595 | L79: 0 | M79: 15063.227 | N79: 349.45779 | O79: =+SUM(K79:N79) -> 23646.644 | P79: =+O79*$P$2 -> 33945.592 | R79: =+K79*$P$2 -> 11820.14 | S79: =+L79*$P$2 -> 0 | T79: =+M79*$P$2 -> 21623.794 | U79: =+N79*$P$2 -> 501.659 | V79: =+SUM(R79:U79) -> 33945.592 | X79: =+R79*J79 -> 910150.75 | Y79: =+Z79-X79 -> 1703659.9 | Z79: =+V79*J79 -> 2613810.6 | AB79: CONTRAPISOS Y CARPETAS | AC79: 0 | AD79: 0 | AE79: =AC79+AD79 -> 0 | AF79: =IF($AE79=1,"🔴","⚪") -> ⚪ | AG79: =AC79*Z79 -> 0 | AH79: =AD79*Z79 -> 0 | AI79: =AE79*Z79 -> 0 | AK79: =AE79*X79 -> 0 | AL79: =AE79*S79*J79 -> 0 | AM79: =AE79*T79*J79 -> 0 | AN79: =AE79*U79*J79 -> 0 | AO79: =AK79+AL79+AM79+AN79 -> 0 | AQ79: =+O79 -> 23646.644 | AR79: =+O79*J79 -> 1820791.6
A80: Albañilería | B80: - | C80: - | D80: Albañilería | F80: 8.06 | G80: IN | H80: Carpeta autonivelante e: 4/10 mm - En locales húmedos (baños) | I80: m2 | J80: 77 | K80: 7390.791 | L80: 0 | M80: 7159.2551 | N80: 218.25069 | O80: =+SUM(K80:N80) -> 14768.297 | P80: =+O80*$P$2 -> 21200.412 | R80: =+K80*$P$2 -> 10609.742 | S80: =+L80*$P$2 -> 0 | T80: =+M80*$P$2 -> 10277.364 | U80: =+N80*$P$2 -> 313.30658 | V80: =+SUM(R80:U80) -> 21200.412 | X80: =+R80*J80 -> 816950.1 | Y80: =+Z80-X80 -> 815481.6 | Z80: =+V80*J80 -> 1632431.7 | AB80: CONTRAPISOS Y CARPETAS | AC80: 0 | AD80: 0 | AE80: =AC80+AD80 -> 0 | AF80: =IF($AE80=1,"🔴","⚪") -> ⚪ | AG80: =AC80*Z80 -> 0 | AH80: =AD80*Z80 -> 0 | AI80: =AE80*Z80 -> 0 | AK80: =AE80*X80 -> 0 | AL80: =AE80*S80*J80 -> 0 | AM80: =AE80*T80*J80 -> 0 | AN80: =AE80*U80*J80 -> 0 | AO80: =AK80+AL80+AM80+AN80 -> 0 | AQ80: =+O80 -> 14768.297 | AR80: =+O80*J80 -> 1137158.9
A81: Albañilería | B81: - | C81: - | D81: Albañilería | F81: 8.07 | G81: OK | H81: Carpeta a la cal reforzada | I81: m2 | J81: 442 | K81: 2717.5179 | L81: 0 | M81: 7814.7833 | N81: 223.75096 | O81: =+SUM(K81:N81) -> 10756.052 | P81: =+O81*$P$2 -> 15440.693 | R81: =+K81*$P$2 -> 3901.0929 | S81: =+L81*$P$2 -> 0 | T81: =+M81*$P$2 -> 11218.397 | U81: =+N81*$P$2 -> 321.20241 | V81: =+SUM(R81:U81) -> 15440.693 | X81: =+R81*J81 -> 1724283 | Y81: =+Z81-X81 -> 5100503.2 | Z81: =+V81*J81 -> 6824786.2 | AB81: CONTRAPISOS Y CARPETAS | AC81: 0 | AD81: 0 | AE81: =AC81+AD81 -> 0 | AF81: =IF($AE81=1,"🔴","⚪") -> ⚪ | AG81: =AC81*Z81 -> 0 | AH81: =AD81*Z81 -> 0 | AI81: =AE81*Z81 -> 0 | AK81: =AE81*X81 -> 0 | AL81: =AE81*S81*J81 -> 0 | AM81: =AE81*T81*J81 -> 0 | AN81: =AE81*U81*J81 -> 0 | AO81: =AK81+AL81+AM81+AN81 -> 0 | AQ81: =+O81 -> 10756.052 | AR81: =+O81*J81 -> 4754175.1
A82: Albañilería | B82: - | C82: - | D82: Albañilería | F82: 8.08 | G82: OK | H82: Carpeta a la cal reforzada s/membrana | I82: m2 | J82: 360 | K82: 2717.5179 | L82: 0 | M82: 7814.7833 | N82: 223.75096 | O82: =+SUM(K82:N82) -> 10756.052 | P82: =+O82*$P$2 -> 15440.693 | R82: =+K82*$P$2 -> 3901.0929 | S82: =+L82*$P$2 -> 0 | T82: =+M82*$P$2 -> 11218.397 | U82: =+N82*$P$2 -> 321.20241 | V82: =+SUM(R82:U82) -> 15440.693 | X82: =+R82*J82 -> 1404393.4 | Y82: =+Z82-X82 -> 4154256 | Z82: =+V82*J82 -> 5558649.4 | AB82: CONTRAPISOS Y CARPETAS | AC82: 0 | AD82: 0 | AE82: =AC82+AD82 -> 0 | AF82: =IF($AE82=1,"🔴","⚪") -> ⚪ | AG82: =AC82*Z82 -> 0 | AH82: =AD82*Z82 -> 0 | AI82: =AE82*Z82 -> 0 | AK82: =AE82*X82 -> 0 | AL82: =AE82*S82*J82 -> 0 | AM82: =AE82*T82*J82 -> 0 | AN82: =AE82*U82*J82 -> 0 | AO82: =AK82+AL82+AM82+AN82 -> 0 | AQ82: =+O82 -> 10756.052 | AR82: =+O82*J82 -> 3872178.8
A83: - | B83: - | C83: - | D83: - | F83: 9 | H83: ESCALERAS | AA83: =+SUM(Z84:Z86) -> 5227135.5 | AB83: ESCALERAS
A84: Albañilería | B84: - | C84: - | D84: Albañilería | F84: 9.01 | G84: OK | H84: Provisión y ejecución de cemento alisado arrodillado, e: 3,00 cm, en alzada y pedad | I84: gl | J84: 1 | K84: 181154.98 | L84: 0 | M84: 1378156.6 | N84: 23389.674 | O84: =+SUM(K84:N84) -> 1582701.3 | P84: =+O84*$P$2 -> 2272023.6 | R84: =+K84*$P$2 -> 260054.37 | S84: =+L84*$P$2 -> 0 | T84: =+M84*$P$2 -> 1978392.5 | U84: =+N84*$P$2 -> 33576.703 | V84: =+SUM(R84:U84) -> 2272023.6 | X84: =+R84*J84 -> 260054.37 | Y84: =+Z84-X84 -> 2011969.2 | Z84: =+V84*J84 -> 2272023.6 | AB84: ESCALERAS | AC84: 0 | AD84: 0 | AE84: =AC84+AD84 -> 0 | AF84: =IF($AE84=1,"🔴","⚪") -> ⚪ | AG84: =AC84*Z84 -> 0 | AH84: =AD84*Z84 -> 0 | AI84: =AE84*Z84 -> 0 | AK84: =AE84*X84 -> 0 | AL84: =AE84*S84*J84 -> 0 | AM84: =AE84*T84*J84 -> 0 | AN84: =AE84*U84*J84 -> 0 | AO84: =AK84+AL84+AM84+AN84 -> 0 | AQ84: =+O84 -> 1582701.3 | AR84: =+O84*J84 -> 1582701.3
A85: Albañilería | B85: - | C85: - | D85: Albañilería | F85: 9.02 | G85: OK | H85: Provisión nariz escalera, hierro angulo 5/8 x 1/8" | I85: un | J85: 81 | K85: 2592.9773 | L85: 0 | M85: 18121.936 | N85: 310.72369 | O85: =+SUM(K85:N85) -> 21025.637 | P85: =+O85*$P$2 -> 30183.044 | R85: =+K85*$P$2 -> 3722.3106 | S85: =+L85*$P$2 -> 0 | T85: =+M85*$P$2 -> 26014.679 | U85: =+N85*$P$2 -> 446.05484 | V85: =+SUM(R85:U85) -> 30183.044 | X85: =+R85*J85 -> 301507.16 | Y85: =+Z85-X85 -> 2143319.4 | Z85: =+V85*J85 -> 2444826.6 | AB85: ESCALERAS | AC85: 0 | AD85: 0 | AE85: =AC85+AD85 -> 0 | AF85: =IF($AE85=1,"🔴","⚪") -> ⚪ | AG85: =AC85*Z85 -> 0 | AH85: =AD85*Z85 -> 0 | AI85: =AE85*Z85 -> 0 | AK85: =AE85*X85 -> 0 | AL85: =AE85*S85*J85 -> 0 | AM85: =AE85*T85*J85 -> 0 | AN85: =AE85*U85*J85 -> 0 | AO85: =AK85+AL85+AM85+AN85 -> 0 | AQ85: =+O85 -> 21025.637 | AR85: =+O85*J85 -> 1703076.6
A86: Albañilería | B86: - | C86: - | D86: Albañilería | F86: 9.03 | G86: OK | H86: Ejecución de zócalo rampante de concreto h: 10 cm | I86: ml | J86: 46 | K86: 609.94943 | L86: 0 | M86: 7003.3937 | N86: 114.20015 | O86: =+SUM(K86:N86) -> 7727.5433 | P86: =+O86*$P$2 -> 11093.161 | R86: =+K86*$P$2 -> 875.60396 | S86: =+L86*$P$2 -> 0 | T86: =+M86*$P$2 -> 10053.619 | U86: =+N86*$P$2 -> 163.93834 | V86: =+SUM(R86:U86) -> 11093.161 | X86: =+R86*J86 -> 40277.782 | Y86: =+Z86-X86 -> 470007.64 | Z86: =+V86*J86 -> 510285.42 | AB86: ESCALERAS | AC86: 0 | AD86: 0 | AE86: =AC86+AD86 -> 0 | AF86: =IF($AE86=1,"🔴","⚪") -> ⚪ | AG86: =AC86*Z86 -> 0 | AH86: =AD86*Z86 -> 0 | AI86: =AE86*Z86 -> 0 | AK86: =AE86*X86 -> 0 | AL86: =AE86*S86*J86 -> 0 | AM86: =AE86*T86*J86 -> 0 | AN86: =AE86*U86*J86 -> 0 | AO86: =AK86+AL86+AM86+AN86 -> 0 | AQ86: =+O86 -> 7727.5433 | AR86: =+O86*J86 -> 355466.99
A87: - | B87: - | C87: - | D87: - | F87: 10 | H87: VENTILACIONES - PROVISION A CARGO DEL COMITENTE | AA87: =+SUM(Z88:Z91) -> 4507448.4 | AB87: VENTILACIONES - PROVISION A CARGO DEL COMITENTE
A88: Albañilería | B88: - | C88: - | D88: Albañilería | F88: 10.01 | G88: IN | H88: Montaje de conductos de ventilación de baños C27 - Provisión a cargo del comitente | I88: gl | J88: 1 | K88: 200000 | L88: 0 | M88: 1163573.9 | N88: 20453.608 | O88: =+SUM(K88:N88) -> 1384027.5 | P88: =+O88*$P$2 -> 1986820.3 | R88: =+K88*$P$2 -> 287107.06 | S88: =+L88*$P$2 -> 0 | T88: =+M88*$P$2 -> 1670351.4 | U88: =+N88*$P$2 -> 29361.877 | V88: =+SUM(R88:U88) -> 1986820.3 | X88: =+R88*J88 -> 287107.06 | Y88: =+Z88-X88 -> 1699713.3 | Z88: =+V88*J88 -> 1986820.3 | AB88: VENTILACIONES - PROVISION A CARGO DEL COMITENTE | AC88: 0 | AD88: 0 | AE88: =AC88+AD88 -> 0 | AF88: =IF($AE88=1,"🔴","⚪") -> ⚪ | AG88: =AC88*Z88 -> 0 | AH88: =AD88*Z88 -> 0 | AI88: =AE88*Z88 -> 0 | AK88: =AE88*X88 -> 0 | AL88: =AE88*S88*J88 -> 0 | AM88: =AE88*T88*J88 -> 0 | AN88: =AE88*U88*J88 -> 0 | AO88: =AK88+AL88+AM88+AN88 -> 0 | AQ88: =+O88 -> 1384027.5 | AR88: =+O88*J88 -> 1384027.5
A89: Albañilería | B89: - | C89: - | D89: Albañilería | F89: 10.02 | G89: IN | H89: Montaje de conductos de ventilación de parrillas C27 - Provisión a cargo del comitente | I89: gl | J89: 1 | K89: 200000 | L89: 0 | M89: 698144.33 | N89: 13472.165 | O89: =+SUM(K89:N89) -> 911616.49 | P89: =+O89*$P$2 -> 1308657.7 | R89: =+K89*$P$2 -> 287107.06 | S89: =+L89*$P$2 -> 0 | T89: =+M89*$P$2 -> 1002210.8 | U89: =+N89*$P$2 -> 19339.768 | V89: =+SUM(R89:U89) -> 1308657.7 | X89: =+R89*J89 -> 287107.06 | Y89: =+Z89-X89 -> 1021550.6 | Z89: =+V89*J89 -> 1308657.7 | AB89: VENTILACIONES - PROVISION A CARGO DEL COMITENTE | AC89: 0 | AD89: 0 | AE89: =AC89+AD89 -> 0 | AF89: =IF($AE89=1,"🔴","⚪") -> ⚪ | AG89: =AC89*Z89 -> 0 | AH89: =AD89*Z89 -> 0 | AI89: =AE89*Z89 -> 0 | AK89: =AE89*X89 -> 0 | AL89: =AE89*S89*J89 -> 0 | AM89: =AE89*T89*J89 -> 0 | AN89: =AE89*U89*J89 -> 0 | AO89: =AK89+AL89+AM89+AN89 -> 0 | AQ89: =+O89 -> 911616.49 | AR89: =+O89*J89 -> 911616.49
A90: Albañilería | B90: - | C90: - | D90: Albañilería | F90: 10.03 | G90: IN | H90: Montaje de campanas de parrillas C22 - Provisión a cargo del comitente | I90: gl | J90: 1 | K90: 50000 | L90: 0 | M90: 349072.16 | N90: 5986.0824 | O90: =+SUM(K90:N90) -> 405058.25 | P90: =+O90*$P$2 -> 581475.42 | R90: =+K90*$P$2 -> 71776.766 | S90: =+L90*$P$2 -> 0 | T90: =+M90*$P$2 -> 501105.42 | U90: =+N90*$P$2 -> 8593.2328 | V90: =+SUM(R90:U90) -> 581475.42 | X90: =+R90*J90 -> 71776.766 | Y90: =+Z90-X90 -> 509698.65 | Z90: =+V90*J90 -> 581475.42 | AB90: VENTILACIONES - PROVISION A CARGO DEL COMITENTE | AC90: 0 | AD90: 0 | AE90: =AC90+AD90 -> 0 | AF90: =IF($AE90=1,"🔴","⚪") -> ⚪ | AG90: =AC90*Z90 -> 0 | AH90: =AD90*Z90 -> 0 | AI90: =AE90*Z90 -> 0 | AK90: =AE90*X90 -> 0 | AL90: =AE90*S90*J90 -> 0 | AM90: =AE90*T90*J90 -> 0 | AN90: =AE90*U90*J90 -> 0 | AO90: =AK90+AL90+AM90+AN90 -> 0 | AQ90: =+O90 -> 405058.25 | AR90: =+O90*J90 -> 405058.25
A91: Albañilería | B91: - | C91: - | D91: Albañilería | F91: 10.04 | G91: IN | H91: Montaje de sombreretes en chapa prepintada C25 - Provisión a cargo del comitente | I91: u | J91: 10 | K91: 20000 | L91: 0 | M91: 23271.478 | N91: 649.07216 | O91: =+SUM(K91:N91) -> 43920.55 | P91: =+O91*$P$2 -> 63049.5 | R91: =+K91*$P$2 -> 28710.706 | S91: =+L91*$P$2 -> 0 | T91: =+M91*$P$2 -> 33407.028 | U91: =+N91*$P$2 -> 931.76601 | V91: =+SUM(R91:U91) -> 63049.5 | X91: =+R91*J91 -> 287107.06 | Y91: =+Z91-X91 -> 343387.94 | Z91: =+V91*J91 -> 630495 | AB91: VENTILACIONES - PROVISION A CARGO DEL COMITENTE | AC91: 0 | AD91: 0 | AE91: =AC91+AD91 -> 0 | AF91: =IF($AE91=1,"🔴","⚪") -> ⚪ | AG91: =AC91*Z91 -> 0 | AH91: =AD91*Z91 -> 0 | AI91: =AE91*Z91 -> 0 | AK91: =AE91*X91 -> 0 | AL91: =AE91*S91*J91 -> 0 | AM91: =AE91*T91*J91 -> 0 | AN91: =AE91*U91*J91 -> 0 | AO91: =AK91+AL91+AM91+AN91 -> 0 | AQ91: =+O91 -> 43920.55 | AR91: =+O91*J91 -> 439205.5
A92: - | B92: - | C92: - | D92: - | F92: 11 | H92: PISOS - PROVISION A CARGO DEL COMITENTE | AA92: =+SUM(Z93:Z103) -> 33574758 | AB92: PISOS - PROVISION A CARGO DEL COMITENTE
A93: - | B93: - | C93: - | D93: - | F93: 11.01 | G93: OK | H93: Provisión y ejecución de alisado de cemento a la llana metálica, e: 6,00 cm | I93: m2 | J93: 0 | K93: 0 | L93: 0 | M93: 0 | N93: 0 | O93: =+SUM(K93:N93) -> 0 | P93: =+O93*$P$2 -> 0 | R93: =+K93*$P$2 -> 0 | S93: =+L93*$P$2 -> 0 | T93: =+M93*$P$2 -> 0 | U93: =+N93*$P$2 -> 0 | V93: =+SUM(R93:U93) -> 0 | X93: =+R93*J93 -> 0 | Y93: =+Z93-X93 -> 0 | Z93: =+V93*J93 -> 0 | AB93: PISOS - PROVISION A CARGO DEL COMITENTE | AC93: 0 | AD93: 0 | AE93: =AC93+AD93 -> 0 | AF93: =IF($AE93=1,"🔴","⚪") -> ⚪ | AG93: =AC93*Z93 -> 0 | AH93: =AD93*Z93 -> 0 | AI93: =AE93*Z93 -> 0 | AK93: =AE93*X93 -> 0 | AL93: =AE93*S93*J93 -> 0 | AM93: =AE93*T93*J93 -> 0 | AN93: =AE93*U93*J93 -> 0 | AO93: =AK93+AL93+AM93+AN93 -> 0 | AQ93: =+O93 -> 0 | AR93: =+O93*J93 -> 0
A94: Revestimiento | B94: - | C94: - | D94: Revestimiento | F94: 11.02 | G94: OK | H94: Provisión y ejecución de cemento alisado arrodillado, e: 3,00 cm | I94: m2 | J94: 39 | K94: 4066.3296 | L94: 0 | M94: 10118.034 | N94: 282.12078 | O94: =+SUM(K94:N94) -> 14466.484 | P94: =+O94*$P$2 -> 20767.149 | R94: =+K94*$P$2 -> 5837.3597 | S94: =+L94*$P$2 -> 0 | T94: =+M94*$P$2 -> 14524.795 | U94: =+N94*$P$2 -> 404.99434 | V94: =+SUM(R94:U94) -> 20767.149 | X94: =+R94*J94 -> 227657.03 | Y94: =+Z94-X94 -> 582261.77 | Z94: =+V94*J94 -> 809918.8 | AB94: PISOS - PROVISION A CARGO DEL COMITENTE | AC94: 0 | AD94: 0 | AE94: =AC94+AD94 -> 0 | AF94: =IF($AE94=1,"🔴","⚪") -> ⚪ | AG94: =AC94*Z94 -> 0 | AH94: =AD94*Z94 -> 0 | AI94: =AE94*Z94 -> 0 | AK94: =AE94*X94 -> 0 | AL94: =AE94*S94*J94 -> 0 | AM94: =AE94*T94*J94 -> 0 | AN94: =AE94*U94*J94 -> 0 | AO94: =AK94+AL94+AM94+AN94 -> 0 | AQ94: =+O94 -> 14466.484 | AR94: =+O94*J94 -> 564192.88
A95: Revestimiento | B95: - | C95: - | D95: Revestimiento | F95: 11.03 | G95: OK | H95: Colocación de porcelanato a definir en sspacios comunes - Provisión a cargo del comitente | I95: m2 | J95: 48 | K95: 7156.2986 | L95: 0 | M95: 11647.705 | N95: 225.81275 | O95: =+SUM(K95:N95) -> 19029.817 | P95: =+O95*$P$2 -> 27317.974 | R95: =+K95*$P$2 -> 10273.119 | S95: =+L95*$P$2 -> 0 | T95: =+M95*$P$2 -> 16720.692 | U95: =+N95*$P$2 -> 324.16217 | V95: =+SUM(R95:U95) -> 27317.974 | X95: =+R95*J95 -> 493109.73 | Y95: =+Z95-X95 -> 818153.02 | Z95: =+V95*J95 -> 1311262.7 | AB95: PISOS - PROVISION A CARGO DEL COMITENTE | AC95: 0 | AD95: 0 | AE95: =AC95+AD95 -> 0 | AF95: =IF($AE95=1,"🔴","⚪") -> ⚪ | AG95: =AC95*Z95 -> 0 | AH95: =AD95*Z95 -> 0 | AI95: =AE95*Z95 -> 0 | AK95: =AE95*X95 -> 0 | AL95: =AE95*S95*J95 -> 0 | AM95: =AE95*T95*J95 -> 0 | AN95: =AE95*U95*J95 -> 0 | AO95: =AK95+AL95+AM95+AN95 -> 0 | AQ95: =+O95 -> 19029.817 | AR95: =+O95*J95 -> 913431.2
A96: Revestimiento | B96: - | C96: Revestimiento | D96: Revestimiento | F96: 11.04 | G96: OK | H96: Colocación de pavimento intertrabado de H°, incluye provisión y colocación de cama de arena + tomado de junta - Provisión a cargo del comitente | I96: m2 | J96: 174 | K96: 1303.439 | L96: 1609.1954 | M96: 11254.144 | N96: 212.50168 | O96: =+SUM(K96:N96) -> 14379.281 | P96: =+O96*$P$2 -> 20641.965 | R96: =+K96*$P$2 -> 1871.1328 | S96: =+L96*$P$2 -> 2310.0568 | T96: =+M96*$P$2 -> 16155.722 | U96: =+N96*$P$2 -> 305.05367 | V96: =+SUM(R96:U96) -> 20641.965 | X96: =+R96*J96 -> 325577.1 | Y96: =+Z96-X96 -> 3266124.8 | Z96: =+V96*J96 -> 3591701.9 | AB96: PISOS - PROVISION A CARGO DEL COMITENTE | AC96: 0 | AD96: 0 | AE96: =AC96+AD96 -> 0 | AF96: =IF($AE96=1,"🔴","⚪") -> ⚪ | AG96: =AC96*Z96 -> 0 | AH96: =AD96*Z96 -> 0 | AI96: =AE96*Z96 -> 0 | AK96: =AE96*X96 -> 0 | AL96: =AE96*S96*J96 -> 0 | AM96: =AE96*T96*J96 -> 0 | AN96: =AE96*U96*J96 -> 0 | AO96: =AK96+AL96+AM96+AN96 -> 0 | AQ96: =+O96 -> 14379.281 | AR96: =+O96*J96 -> 2501994.8
A97: Revestimiento | B97: - | C97: Revestimiento | D97: Revestimiento | F97: 11.05 | G97: OK | H97: Colocación de garden block, incluye provisión y colocación de cama de arena + tomado de junta - Provisión a cargo del comitente | I97: m2 | J97: 92 | K97: 1303.439 | L97: 1609.1954 | M97: 11254.144 | N97: 212.50168 | O97: =+SUM(K97:N97) -> 14379.281 | P97: =+O97*$P$2 -> 20641.965 | R97: =+K97*$P$2 -> 1871.1328 | S97: =+L97*$P$2 -> 2310.0568 | T97: =+M97*$P$2 -> 16155.722 | U97: =+N97*$P$2 -> 305.05367 | V97: =+SUM(R97:U97) -> 20641.965 | X97: =+R97*J97 -> 172144.21 | Y97: =+Z97-X97 -> 1726916.6 | Z97: =+V97*J97 -> 1899060.8 | AB97: PISOS - PROVISION A CARGO DEL COMITENTE | AC97: 0 | AD97: 0 | AE97: =AC97+AD97 -> 0 | AF97: =IF($AE97=1,"🔴","⚪") -> ⚪ | AG97: =AC97*Z97 -> 0 | AH97: =AD97*Z97 -> 0 | AI97: =AE97*Z97 -> 0 | AK97: =AE97*X97 -> 0 | AL97: =AE97*S97*J97 -> 0 | AM97: =AE97*T97*J97 -> 0 | AN97: =AE97*U97*J97 -> 0 | AO97: =AK97+AL97+AM97+AN97 -> 0 | AQ97: =+O97 -> 14379.281 | AR97: =+O97*J97 -> 1322893.8
A98: Revestimiento | B98: - | C98: - | D98: Revestimiento | F98: 11.06 | G98: OK | H98: Provisión y colocación de relleno de piedra binder | I98: m2 | J98: 8 | K98: 2773.008 | L98: 0 | M98: 7607.5726 | N98: 155.70871 | O98: =+SUM(K98:N98) -> 10536.289 | P98: =+O98*$P$2 -> 15125.215 | R98: =+K98*$P$2 -> 3980.7509 | S98: =+L98*$P$2 -> 0 | T98: =+M98*$P$2 -> 10920.939 | U98: =+N98*$P$2 -> 223.52535 | V98: =+SUM(R98:U98) -> 15125.215 | X98: =+R98*J98 -> 31846.007 | Y98: =+Z98-X98 -> 89155.716 | Z98: =+V98*J98 -> 121001.72 | AB98: PISOS - PROVISION A CARGO DEL COMITENTE | AC98: 0 | AD98: 0 | AE98: =AC98+AD98 -> 0 | AF98: =IF($AE98=1,"🔴","⚪") -> ⚪ | AG98: =AC98*Z98 -> 0 | AH98: =AD98*Z98 -> 0 | AI98: =AE98*Z98 -> 0 | AK98: =AE98*X98 -> 0 | AL98: =AE98*S98*J98 -> 0 | AM98: =AE98*T98*J98 -> 0 | AN98: =AE98*U98*J98 -> 0 | AO98: =AK98+AL98+AM98+AN98 -> 0 | AQ98: =+O98 -> 10536.289 | AR98: =+O98*J98 -> 84290.314
A99: Revestimiento | B99: - | C99: - | D99: Revestimiento | F99: 11.07 | G99: OK | H99: Colocación de baldoson granítico vereda 40 x 40 - Provisión a cargo del comitente | I99: m2 | J99: 46 | K99: 7701.7949 | L99: 0 | M99: 11983.97 | N99: 295.28648 | O99: =+SUM(K99:N99) -> 19981.052 | P99: =+O99*$P$2 -> 28683.506 | R99: =+K99*$P$2 -> 11056.199 | S99: =+L99*$P$2 -> 0 | T99: =+M99*$P$2 -> 17203.413 | U99: =+N99*$P$2 -> 423.89417 | V99: =+SUM(R99:U99) -> 28683.506 | X99: =+R99*J99 -> 508585.13 | Y99: =+Z99-X99 -> 810856.12 | Z99: =+V99*J99 -> 1319441.3 | AB99: PISOS - PROVISION A CARGO DEL COMITENTE | AC99: 0 | AD99: 0 | AE99: =AC99+AD99 -> 0 | AF99: =IF($AE99=1,"🔴","⚪") -> ⚪ | AG99: =AC99*Z99 -> 0 | AH99: =AD99*Z99 -> 0 | AI99: =AE99*Z99 -> 0 | AK99: =AE99*X99 -> 0 | AL99: =AE99*S99*J99 -> 0 | AM99: =AE99*T99*J99 -> 0 | AN99: =AE99*U99*J99 -> 0 | AO99: =AK99+AL99+AM99+AN99 -> 0 | AQ99: =+O99 -> 19981.052 | AR99: =+O99*J99 -> 919128.39
A100: Revestimiento | B100: - | C100: - | D100: Revestimiento | F100: 11.08 | G100: OK | H100: Colocación de porcelanato a definir Interior UF - Provisión a cargo del comitente | I100: m2 | J100: 562 | K100: 7156.2986 | L100: 0 | M100: 11647.705 | N100: 225.81275 | O100: =+SUM(K100:N100) -> 19029.817 | P100: =+O100*$P$2 -> 27317.974 | R100: =+K100*$P$2 -> 10273.119 | S100: =+L100*$P$2 -> 0 | T100: =+M100*$P$2 -> 16720.692 | U100: =+N100*$P$2 -> 324.16217 | V100: =+SUM(R100:U100) -> 27317.974 | X100: =+R100*J100 -> 5773493.1 | Y100: =+Z100-X100 -> 9579208.2 | Z100: =+V100*J100 -> 15352701 | AB100: PISOS - PROVISION A CARGO DEL COMITENTE | AC100: 0 | AD100: 0 | AE100: =AC100+AD100 -> 0 | AF100: =IF($AE100=1,"🔴","⚪") -> ⚪ | AG100: =AC100*Z100 -> 0 | AH100: =AD100*Z100 -> 0 | AI100: =AE100*Z100 -> 0 | AK100: =AE100*X100 -> 0 | AL100: =AE100*S100*J100 -> 0 | AM100: =AE100*T100*J100 -> 0 | AN100: =AE100*U100*J100 -> 0 | AO100: =AK100+AL100+AM100+AN100 -> 0 | AQ100: =+O100 -> 19029.817 | AR100: =+O100*J100 -> 10694757
A101: Revestimiento | B101: - | C101: - | D101: Revestimiento | F101: 11.09 | G101: OK | H101: Colocación de porcelanato a definir Baños - Provisión a cargo del comitente | I101: m2 | J101: 73 | K101: 7156.2986 | L101: 0 | M101: 15142.017 | N101: 293.55657 | O101: =+SUM(K101:N101) -> 22591.872 | P101: =+O101*$P$2 -> 32431.43 | R101: =+K101*$P$2 -> 10273.119 | S101: =+L101*$P$2 -> 0 | T101: =+M101*$P$2 -> 21736.9 | U101: =+N101*$P$2 -> 421.41082 | V101: =+SUM(R101:U101) -> 32431.43 | X101: =+R101*J101 -> 749937.72 | Y101: =+Z101-X101 -> 1617556.7 | Z101: =+V101*J101 -> 2367494.4 | AB101: PISOS - PROVISION A CARGO DEL COMITENTE | AC101: 0 | AD101: 0 | AE101: =AC101+AD101 -> 0 | AF101: =IF($AE101=1,"🔴","⚪") -> ⚪ | AG101: =AC101*Z101 -> 0 | AH101: =AD101*Z101 -> 0 | AI101: =AE101*Z101 -> 0 | AK101: =AE101*X101 -> 0 | AL101: =AE101*S101*J101 -> 0 | AM101: =AE101*T101*J101 -> 0 | AN101: =AE101*U101*J101 -> 0 | AO101: =AK101+AL101+AM101+AN101 -> 0 | AQ101: =+O101 -> 22591.872 | AR101: =+O101*J101 -> 1649206.7
A102: Revestimiento | B102: - | C102: - | D102: Revestimiento | F102: 11.1 | G102: OK | H102: Colocación de porcelanato a definir Balcones - Provisión a cargo del comitente | I102: m2 | J102: 143 | K102: 7156.2986 | L102: 0 | M102: 11647.705 | N102: 225.81275 | O102: =+SUM(K102:N102) -> 19029.817 | P102: =+O102*$P$2 -> 27317.974 | R102: =+K102*$P$2 -> 10273.119 | S102: =+L102*$P$2 -> 0 | T102: =+M102*$P$2 -> 16720.692 | U102: =+N102*$P$2 -> 324.16217 | V102: =+SUM(R102:U102) -> 27317.974 | X102: =+R102*J102 -> 1469056.1 | Y102: =+Z102-X102 -> 2437414.2 | Z102: =+V102*J102 -> 3906470.3 | AB102: PISOS - PROVISION A CARGO DEL COMITENTE | AC102: 0 | AD102: 0 | AE102: =AC102+AD102 -> 0 | AF102: =IF($AE102=1,"🔴","⚪") -> ⚪ | AG102: =AC102*Z102 -> 0 | AH102: =AD102*Z102 -> 0 | AI102: =AE102*Z102 -> 0 | AK102: =AE102*X102 -> 0 | AL102: =AE102*S102*J102 -> 0 | AM102: =AE102*T102*J102 -> 0 | AN102: =AE102*U102*J102 -> 0 | AO102: =AK102+AL102+AM102+AN102 -> 0 | AQ102: =+O102 -> 19029.817 | AR102: =+O102*J102 -> 2721263.8
A103: Revestimiento | B103: - | C103: - | D103: Revestimiento | F103: 11.11 | G103: OK | H103: Colocación de porcelanato a definir Palier - Provisión a cargo del comitente | I103: m2 | J103: 106 | K103: 7156.2986 | L103: 0 | M103: 11647.705 | N103: 225.81275 | O103: =+SUM(K103:N103) -> 19029.817 | P103: =+O103*$P$2 -> 27317.974 | R103: =+K103*$P$2 -> 10273.119 | S103: =+L103*$P$2 -> 0 | T103: =+M103*$P$2 -> 16720.692 | U103: =+N103*$P$2 -> 324.16217 | V103: =+SUM(R103:U103) -> 27317.974 | X103: =+R103*J103 -> 1088950.7 | Y103: =+Z103-X103 -> 1806754.6 | Z103: =+V103*J103 -> 2895705.2 | AB103: PISOS - PROVISION A CARGO DEL COMITENTE | AC103: 0 | AD103: 0 | AE103: =AC103+AD103 -> 0 | AF103: =IF($AE103=1,"🔴","⚪") -> ⚪ | AG103: =AC103*Z103 -> 0 | AH103: =AD103*Z103 -> 0 | AI103: =AE103*Z103 -> 0 | AK103: =AE103*X103 -> 0 | AL103: =AE103*S103*J103 -> 0 | AM103: =AE103*T103*J103 -> 0 | AN103: =AE103*U103*J103 -> 0 | AO103: =AK103+AL103+AM103+AN103 -> 0 | AQ103: =+O103 -> 19029.817 | AR103: =+O103*J103 -> 2017160.6
A104: - | B104: - | C104: - | D104: - | F104: 12 | H104: ZOCALOS Y SOLIAS - PROVISION A CARGO DEL COMITENTE | AA104: =+SUM(Z105:Z107) -> 9682638.1 | AB104: ZOCALOS Y SOLIAS - PROVISION A CARGO DEL COMITENTE
A105: Revestimiento | B105: - | C105: - | D105: Revestimiento | F105: =+F104+0.01 -> 12.01 | G105: OK | H105: Ejecución de zócalo de concreto h: 10 cm | I105: ml | J105: 19 | K105: 809.61503 | L105: 0 | M105: 3938.2618 | N105: 126.07067 | O105: =+SUM(K105:N105) -> 4873.9475 | P105: =+O105*$P$2 -> 6996.7237 | R105: =+K105*$P$2 -> 1162.231 | S105: =+L105*$P$2 -> 0 | T105: =+M105*$P$2 -> 5653.5139 | U105: =+N105*$P$2 -> 180.9789 | V105: =+SUM(R105:U105) -> 6996.7237 | X105: =+R105*J105 -> 22082.389 | Y105: =+Z105-X105 -> 110855.36 | Z105: =+V105*J105 -> 132937.75 | AB105: ZOCALOS Y SOLIAS - PROVISION A CARGO DEL COMITENTE | AC105: 0 | AD105: 0 | AE105: =AC105+AD105 -> 0 | AF105: =IF($AE105=1,"🔴","⚪") -> ⚪ | AG105: =AC105*Z105 -> 0 | AH105: =AD105*Z105 -> 0 | AI105: =AE105*Z105 -> 0 | AK105: =AE105*X105 -> 0 | AL105: =AE105*S105*J105 -> 0 | AM105: =AE105*T105*J105 -> 0 | AN105: =AE105*U105*J105 -> 0 | AO105: =AK105+AL105+AM105+AN105 -> 0 | AQ105: =+O105 -> 4873.9475 | AR105: =+O105*J105 -> 92605.002
A106: Revestimiento | B106: - | C106: - | D106: Revestimiento | F106: 12.02 | G106: OK | H106: Provisión y colocación de zócalo de MDF prepintado color bco. h: 7cm | I106: ml | J106: 626 | K106: 3500 | L106: 0 | M106: 3196.2174 | N106: 100.44326 | O106: =+SUM(K106:N106) -> 6796.6606 | P106: =+O106*$P$2 -> 9756.8464 | R106: =+K106*$P$2 -> 5024.3736 | S106: =+L106*$P$2 -> 0 | T106: =+M106*$P$2 -> 4588.2829 | U106: =+N106*$P$2 -> 144.18985 | V106: =+SUM(R106:U106) -> 9756.8464 | X106: =+R106*J106 -> 3145257.9 | Y106: =+Z106-X106 -> 2962527.9 | Z106: =+V106*J106 -> 6107785.8 | AB106: ZOCALOS Y SOLIAS - PROVISION A CARGO DEL COMITENTE | AC106: 0 | AD106: 0 | AE106: =AC106+AD106 -> 0 | AF106: =IF($AE106=1,"🔴","⚪") -> ⚪ | AG106: =AC106*Z106 -> 0 | AH106: =AD106*Z106 -> 0 | AI106: =AE106*Z106 -> 0 | AK106: =AE106*X106 -> 0 | AL106: =AE106*S106*J106 -> 0 | AM106: =AE106*T106*J106 -> 0 | AN106: =AE106*U106*J106 -> 0 | AO106: =AK106+AL106+AM106+AN106 -> 0 | AQ106: =+O106 -> 6796.6606 | AR106: =+O106*J106 -> 4254709.6
A107: Revestimiento | B107: - | C107: - | D107: Revestimiento | F107: 12.03 | G107: OK | H107: Colocación de zócalo de porcelanato - Provisión a cargo del comitente | I107: ml | J107: 386 | K107: 1066.3432 | L107: 0 | M107: 5047.339 | N107: 97.85219 | O107: =+SUM(K107:N107) -> 6211.5344 | P107: =+O107*$P$2 -> 8916.877 | R107: =+K107*$P$2 -> 1530.7734 | S107: =+L107*$P$2 -> 0 | T107: =+M107*$P$2 -> 7245.6333 | U107: =+N107*$P$2 -> 140.47027 | V107: =+SUM(R107:U107) -> 8916.877 | X107: =+R107*J107 -> 590878.53 | Y107: =+Z107-X107 -> 2851036 | Z107: =+V107*J107 -> 3441914.5 | AB107: ZOCALOS Y SOLIAS - PROVISION A CARGO DEL COMITENTE | AC107: 0 | AD107: 0 | AE107: =AC107+AD107 -> 0 | AF107: =IF($AE107=1,"🔴","⚪") -> ⚪ | AG107: =AC107*Z107 -> 0 | AH107: =AD107*Z107 -> 0 | AI107: =AE107*Z107 -> 0 | AK107: =AE107*X107 -> 0 | AL107: =AE107*S107*J107 -> 0 | AM107: =AE107*T107*J107 -> 0 | AN107: =AE107*U107*J107 -> 0 | AO107: =AK107+AL107+AM107+AN107 -> 0 | AQ107: =+O107 -> 6211.5344 | AR107: =+O107*J107 -> 2397652.3
A108: - | B108: - | C108: - | D108: - | F108: 13 | H108: REVESTIMIENTOS - PROVISION A CARGO DEL COMITENTE | AA108: =+SUM(Z109:Z112) -> 15980655 | AB108: REVESTIMIENTOS - PROVISION A CARGO DEL COMITENTE
A109: Revestimiento | B109: - | C109: - | D109: Revestimiento | F109: 13.01 | G109: OK | H109: Colocación de porcelanato en baños - Provisión a cargo del comitente | I109: m2 | J109: 413 | K109: 7156.2986 | L109: 0 | M109: 15142.017 | N109: 293.55657 | O109: =+SUM(K109:N109) -> 22591.872 | P109: =+O109*$P$2 -> 32431.43 | R109: =+K109*$P$2 -> 10273.119 | S109: =+L109*$P$2 -> 0 | T109: =+M109*$P$2 -> 21736.9 | U109: =+N109*$P$2 -> 421.41082 | V109: =+SUM(R109:U109) -> 32431.43 | X109: =+R109*J109 -> 4242798.3 | Y109: =+Z109-X109 -> 9151382.4 | Z109: =+V109*J109 -> 13394181 | AB109: REVESTIMIENTOS - PROVISION A CARGO DEL COMITENTE | AC109: 0 | AD109: 0 | AE109: =AC109+AD109 -> 0 | AF109: =IF($AE109=1,"🔴","⚪") -> ⚪ | AG109: =AC109*Z109 -> 0 | AH109: =AD109*Z109 -> 0 | AI109: =AE109*Z109 -> 0 | AK109: =AE109*X109 -> 0 | AL109: =AE109*S109*J109 -> 0 | AM109: =AE109*T109*J109 -> 0 | AN109: =AE109*U109*J109 -> 0 | AO109: =AK109+AL109+AM109+AN109 -> 0 | AQ109: =+O109 -> 22591.872 | AR109: =+O109*J109 -> 9330443.2
...

Sheet 1_GGBB
H2: 45679 | O2: 26
F3: MESES | G3: DÓLAR BNA | H3: DÓLAR MEP | M3: Descrip | N3: Mes | O3: Total Dias
B4: GASTOS GENERALES y BENEFICIO | F4: =+ROUNDUP(N17,0) -> 17 | G4: 1066.5 | H4: 1170 | M4: Prelim | N4: 1 | O4: =+N4*$O$2 -> 26 | Q4: Syh permanente
M5: Mov de suelos y excav. | N5: 2.5 | O5: =+N5*$O$2 -> 65 | Q5: =+ROUNDUP(SUM(N4:N5),0) -> 4
B6: Gastos Grales de obra en items | C6: U | D6: Cant | F6: Precio Unit | G6: Subtotal | H6: =SUM(G7:G10) -> 0 | M6: Losa sobre PB | N6: 1 | O6: =+N6*$O$2 -> 26
B7: Oficina en obra (6x3 c/AA) | C7: mes | D7: =+$F$4 -> 17 | E7: 0 | F7: =E7*I7+J7 -> 0 | G7: =+F7*D7*E7 -> 0 | M7: Losa sobre 1 | N7: 0.75 | O7: =+N7*$O$2 -> 19.5
B8: Obrador 6x3 s/AA | C8: mes | D8: =+$F$4 -> 17 | E8: 0 | F8: =E8*I8+J8 -> 0 | G8: =+F8*D8*E8 -> 0 | M8: Losa sobre 2 | N8: 0.75 | O8: =+N8*$O$2 -> 19.5
B9: Pañol (6x3) | C9: mes | D9: =+$F$4 -> 17 | E9: 1 | F9: =E9*I9+J9 -> 0 | G9: =+F9*D9*E9 -> 0 | M9: Losa sobre 3 | N9: 0.75 | O9: =+N9*$O$2 -> 19.5 | P9: Inicio mamposteria
B10: Baños | C10: mes | D10: =+$F$4 -> 17 | E10: 2 | F10: =E10*I10+J10 -> 0 | G10: =+F10*D10*E10 -> 0 | M10: Losa sobre 4 | N10: 0.75 | O10: =+N10*$O$2 -> 19.5
B11: Gastos Grales de obra en items | H11: =SUM(G12:G19) -> 40948076 | M11: Losa sobre SM | N11: 0.5 | O11: =+N11*$O$2 -> 13 | Q11: Meses H° | R11: Estacionamiento en contramano
B12: HyS permanente | C12: mes | D12: =+Q5 -> 4 | E12: 1 | G12: =+K12 -> 6018681.2 | J12: 1504670.3 | K12: =+J12*D12*E12 -> 6018681.2 | M12: Mampostería | N12: 2 | O12: =+N12*$O$2 -> 52 | Q12: =+SUM(N5:N11) -> 7 | R12: =+ROUNDUP(Q12/3,0) -> 3
B13: HyS | C13: mes | D13: =+$F$4 -> 17 | E13: 1 | G13: =+K13 -> 2550000 | J13: 150000 | K13: =+J13*D13*E13 -> 2550000 | M13: Revoques, contrap y carp | N13: 2 | O13: =+N13*$O$2 -> 52
B14: Energía de obra | C14: mes | D14: =+$F$4 -> 17 | E14: 0.5 | F14: 200000 | G14: =+F14*D14*E14 -> 1700000 | M14: Colocación | N14: 2 | O14: =+N14*$O$2 -> 52
B15: Agua de obra | C15: mes | D15: =+$F$4 -> 17 | E15: 1 | F15: 250000 | G15: =+F15*D15*E15 -> 4250000 | M15: Pintura | N15: 2 | O15: =+N15*$O$2 -> 52
B16: Internet | C16: mes | D16: =+$F$4 -> 17 | E16: 1 | F16: 50000 | G16: =+F16*D16*E16 -> 850000 | M16: Terminaciones | N16: 1 | O16: =+N16*$O$2 -> 26
B17: Alquiler cerco de obra chapa | C17: mes | D17: =+$F$4 -> 17 | E17: 0 | F17: 10000 | G17: =+F17*D17*E17 -> 0 | N17: =SUM(N4:N16) -> 17 | O17: =SUM(O4:O16) -> 442
B18: Proyecto Ejecutivo | C18: mes | D18: =+$F$4 -> 17 | E18: 0 | F18: 3009340.6 | G18: =+F18*D18*E18 -> 0
B19: Proyecto (50%) | C19: mes | D19: =+$F$4 -> 17 | E19: 0.5 | F19: 3009340.6 | G19: =+F19*D19*E19 -> 25579395
B20: Gastos Directos | H20: =SUM(G21:G31) -> 1.5582366e+08
B21: Coordinacion de obra | C21: mes | D21: =+$F$4 -> 17 | E21: 0.15 | F21: 5273644.1 | G21: =+F21*D21*E21 -> 13447792
B22: Jefe de obra | C22: mes | D22: =+$F$4 -> 17 | E22: 1 | G22: =+K22 -> 74327580 | J22: 4372210.6 | K22: =+J22*D22*E22 -> 74327580
B23: Sobrestante | C23: mes | D23: =+$F$4 -> 17 | E23: 0 | F23: 3009340.6 | G23: =+F23*D23*E23 -> 0
B24: Administrativo en obra | C24: mes | D24: =+$F$4 -> 17 | E24: 0 | F24: =+F23 -> 3009340.6 | G24: =+F24*D24*E24 -> 0
B25: Capataz | C25: mes | D25: =+$F$4 -> 17 | E25: 0.5 | F25: 3545026.5 | G25: =+F25*D25*E25 -> 30132725
B26: Logistica | C26: mes | D26: =+$F$4 -> 17 | E26: 1 | F26: 500000 | G26: =+F26*D26*E26 -> 8500000
B27: Vehiculo obra | C27: mes | D27: =+$F$4 -> 17 | E27: 1 | F27: =F26 -> 500000 | G27: =+F27*D27*E27 -> 8500000
B28: Mov y viaticos | C28: mes | D28: =+$F$4 -> 17 | E28: 1 | G28: =+K28 -> 8500000 | J28: =F26 -> 500000 | K28: =+J28*D28*E28 -> 8500000
B29: UOCRA | C29: mes | D29: =+$F$4 -> 17 | E29: 1 | G29: =+F29*D29*E29 -> 0
B30: Pañolero/Sereno | C30: mes | D30: =+$F$4 -> 17 | E30: 1 | G30: =+K30 -> 12415558 | J30: 730326.97 | K30: =+J30*D30*E30 -> 12415558
B32: Equipos | H32: =SUM(G33:G41) -> 0
B33: Bobcat | C33: mes | F33: 130000 | G33: =+F33*D33 -> 0
B34: Camion limpieza | C34: mes | F34: 100000 | G34: =+F34*D34 -> 0
B35: Tijera electrica 12 | C35: mes | F35: 33600 | G35: =+F35*D35 -> 0
B36: JLG | C36: mes | F36: 89000 | G36: =+F36*D36 -> 0
B37: Grua 20ton | C37: mes | F37: 70000 | G37: =+F37*D37 -> 0
B42: Gastos Indirectos | H42: =SUM(G43:G48) -> 82753395
B43: Admin (50%Compras - 50%RRHH) | C43: mes | D43: =+$F$4 -> 17 | E43: 0.5 | F43: 3009340.6 | G43: =+F43*D43*E43 -> 25579395
B44: Seguros | C44: gl | D44: =+D43 -> 17 | E44: 1 | F44: 250000 | G44: =+F44*D44 -> 4250000
B45: IIBB (monto venta obra gris) | C45: gl | D45: 0.04 | E45: 0.7 | F45: 1400000000 | G45: =+F45*D45*E45 -> 39200000
B46: Imp cheque | C46: gl | D46: =1.2/100 -> 0.012 | E46: =+E45 -> 0.7 | F46: =+F45*1.15 -> 1.61e+09 | G46: =+F46*D46*E46 -> 13524000
B47: Contrato | C47: gl | D47: 1 | E47: 1 | F47: 200000 | G47: =+F47*D47*E47 -> 200000
G49: =SUM(G7:G48) -> 2.7952513e+08 | H49: =SUM(H6:H48) -> 2.7952513e+08 | K49: =SUM(K6:K48) -> 1.0381182e+08 | L49: =+H49+K49 -> 3.8333695e+08
B50: Monto puesto en Ayuda de gremio que no se eroga | K50: Imputados en pres | L50: Total GGBB
B51: Total de Gastos Generales | H51: =+H50+H49 -> 2.7952513e+08
B53: Otro | G53: 2.9493528e+08 | H53: =+G53/$H$4 -> 252081.44 | J53: =+H53/$H$59 -> 0.29208306 | K53: =+H53/$H$69 -> 0.2034663
B54: Corralon | G54: 64860920 | H54: =+G54/$H$4 -> 55436.684 | J54: =+H54/$H$59 -> 0.064233672 | K54: =+H54/$H$69 -> 0.044745449
B55: Subcontratos | G55: 4.6047904e+08 | H55: =+G55/$H$4 -> 393571.83 | J55: =+H55/$H$59 -> 0.4560259 | K55: =+H55/$H$69 -> 0.31766958
B56: Mano de obra | G56: 1.6799537e+08 | H56: =+G56/$H$4 -> 143585.78 | J56: =+H56/$H$59 -> 0.16637074 | K56: =+H56/$H$69 -> 0.11589457
B57: Equipos | G57: 21494483 | H57: =+G57/$H$4 -> 18371.353 | K57: =SUM(K53:K56) -> 0.6817759
J58: =SUM(J53:J57) -> 0.97871338 | L58: =1-J58 -> 0.021286617
A59: A | G59: =SUM(G53:G58) -> 1.0097651e+09 | H59: =SUM(H53:H58) -> 863047.09
J60: =+G57/G59 -> 0.021286617
B61: GG | F61: =+H51/G59 -> 0.27682194 | G61: =+F61*$G$59 -> 2.7952513e+08 | H61: =+G61/$H$4 -> 238910.37 | J61: 0.03
B62: Equipos | E62: 3 | F62: =+J62 -> 0.0087133829 | G62: =+F62*$G$59 -> 8798469.9 | H62: =+G62/$H$4 -> 7520.0597 | J62: =+J61-J60 -> 0.0087133829
B63: Imprevistos + Negociacion | E63: 5 | F63: =0.05 -> 0.05 | G63: =+F63*$G$59 -> 50488255 | H63: =+G63/$H$4 -> 43152.354
B64: Beneficio | E64: 9 | F64: 0.1 | G64: =+F64*$G$59 -> 1.0097651e+08 | H64: =+G64/$H$4 -> 86304.709
A65: B | F65: =SUM(F61:F64) -> 0.43553532 | G65: =SUM(G61:G64) -> 4.3978836e+08 | H65: =+G65/$H$4 -> 375887.49 | K65: =+H65/H69 -> 0.30339575
A67: K | F67: =1+F65 -> 1.4355353 | G67: =+G59*F67 -> 1.4495535e+09
A69: A+B | G69: =+G59+G65 -> 1.4495535e+09 | H69: =+G69/$H$4 -> 1238934.6 | K69: =SUM(K57:K65) -> 0.98517165

Sheet 1_Composicion
A1: Partida | B1: Tipo | C1: Subtipo | D1: Cod_Insumo | E1: Descripción | F1: Unidad de medida | G1: Cant | H1: %Desp | I1: Precio | J1: Costo | K1: Clave | L1: Count | M1: Clave2 | N1: Rend. Part. | O1: Cant MO/ALB Unit | P1: Cant. Ej. Part. | Q1: Cant MO/ALB Total | R1: Cod_Item_Ppto | S1: MO/ALB
A2: AIS-114 | B2: EQ | D2: EQ-SOLD00 | E2: Soldador Soplete A Gas Techista Membrana 10 Kg Boca 50mm | G2: 1 | H2: 0 | I2: 804.50569 | J2: 804.50569 | K2: AIS-114|EQ | L2: 1 | M2: AIS-114|EQ|1 | N2: 60 | O2: 1 | P2: - | Q2: 0 | R2: - | S2: -
A3: AIS-114 | B3: MAT | C3: OTR | D3: OTR-022 | E3: Aguarras Hydrarras Hydra x 18lts | F3: b | G3: 0.005 | H3: 0.05 | I3: 26907.33 | J3: 141.26348 | K3: AIS-114|MAT | L3: 1 | M3: AIS-114|MAT|1 | N3: 60 | O3: 0.005 | P3: - | Q3: 0 | R3: - | S3: -
A4: AIS-114 | B4: MAT | C4: OTR | D4: OTR-025 | E4: Trapo | F4: u | G4: 0.01 | H4: 0.05 | I4: 735.06 | J4: 7.71813 | K4: AIS-114|MAT | L4: 2 | M4: AIS-114|MAT|2 | N4: 60 | O4: 0.01 | P4: - | Q4: 0 | R4: - | S4: -
A5: AIS-114 | B5: MAT | C5: OTR | D5: OTR-027 | E5: Rodillo de lana pelo largo N°22 - El Galgo | F5: u | G5: 0.005 | H5: 0.05 | I5: 6678.36 | J5: 35.06139 | K5: AIS-114|MAT | L5: 3 | M5: AIS-114|MAT|3 | N5: 60 | O5: 0.005 | P5: - | Q5: 0 | R5: - | S5: -
A6: AIS-114 | B6: MAT | C6: OTR | D6: OTR-028 | E6: Pincel N° 20 - El Galgo | F6: u | G6: 0.01 | H6: 0.05 | I6: 5282.24 | J6: 55.46352 | K6: AIS-114|MAT | L6: 4 | M6: AIS-114|MAT|4 | N6: 60 | O6: 0.01 | P6: - | Q6: 0 | R6: - | S6: -
A7: AIS-114 | B7: MAT | C7: OTR | D7: OTR-047 | E7: Guante Vaqueta Medio Paseo | F7: par | G7: 0.03 | H7: 0.05 | I7: 4842 | J7: 152.523 | K7: AIS-114|MAT | L7: 5 | M7: AIS-114|MAT|5 | N7: 60 | O7: 0.03 | P7: - | Q7: 0 | R7: - | S7: -
A8: AIS-114 | B8: MAT | C8: OTR | D8: OTR-048 | E8: Recarga de garrafa | F8: u | G8: 0.01 | H8: 0.05 | I8: 12396.694 | J8: 130.16529 | K8: AIS-114|MAT | L8: 6 | M8: AIS-114|MAT|6 | N8: 60 | O8: 0.01 | P8: - | Q8: 0 | R8: - | S8: -
A9: AIS-114 | B9: MAT | C9: OTR | D9: PIN-008 | E9: Pintura Asfaltica Asfasol x18ts | F9: b | G9: 0.015 | H9: 0.1 | I9: 32845.78 | J9: 541.95537 | K9: AIS-114|MAT | L9: 7 | M9: AIS-114|MAT|7 | N9: 60 | O9: 0.015 | P9: - | Q9: 0 | R9: - | S9: -
A10: AIS-114 | B10: MAT | C10: OTR | D10: AIS-002 | E10: Membrana Geotextil Ormiflex 4mm - (35kg) x10m | F10: u | G10: 0.05 | H10: 0.1 | I10: 70192.21 | J10: 3860.5716 | K10: AIS-114|MAT | L10: 8 | M10: AIS-114|MAT|8 | N10: 60 | O10: 0.05 | P10: - | Q10: 0 | R10: - | S10: -
A11: AIS-114 | B11: MO | C11: ALB | D11: MO-EAYUD | E11: AYUDANTE | F11: j | G11: 1 | H11: 0 | I11: 60860.581 | J11: 60860.581 | K11: AIS-114|MO | L11: 1 | M11: AIS-114|MO|1 | N11: 60 | O11: 0.016666667 | P11: - | Q11: 0 | R11: - | S11: -
A12: AIS-114 | B12: MO | C12: ALB | D12: MO-EESPE | E12: ESPECIALIZADO | F12: j | G12: 1 | H12: 0 | I12: 85927.097 | J12: 85927.097 | K12: AIS-114|MO | L12: 2 | M12: AIS-114|MO|2 | N12: 60 | O12: 0.016666667 | P12: - | Q12: 0 | R12: - | S12: -
A13: ALB-033 | B13: EQ | D13: EQ-ANDAM0 | E13: ANDAMIO TUBULAR DE UNO A TRES CUERPOS | G13: 0.5 | H13: 0 | I13: 571.17949 | J13: 285.58975 | K13: ALB-033|EQ | L13: 1 | M13: ALB-033|EQ|1 | N13: 7 | O13: 0.5 | P13: - | Q13: 0 | R13: - | S13: -
A14: ALB-033 | B14: EQ | D14: EQ-EQALBA | E14: EQUIPO DE ALBAÑILERIA, carpetas, ladrillo | G14: 1 | H14: 0 | I14: 2287.1357 | J14: 2287.1357 | K14: ALB-033|EQ | L14: 2 | M14: ALB-033|EQ|2 | N14: 7 | O14: 1 | P14: - | Q14: 0 | R14: - | S14: -
A15: ALB-033 | B15: EQ | D15: EQ-TROMPO | E15: Hormigonera De 150 Litros 1hp Con Rueda Maciza | G15: 1 | H15: 0 | I15: 957.2532 | J15: 957.2532 | K15: ALB-033|EQ | L15: 3 | M15: ALB-033|EQ|3 | N15: 7 | O15: 1 | P15: - | Q15: 0 | R15: - | S15: -
A16: ALB-033 | B16: MAT | C16: OTR | D16: ACE-001 | E16: Barra de Acero Aleteado - 6mm x 12m | F16: u | G16: 0.17 | H16: 0.1 | I16: 3424.53 | J16: 640.38711 | K16: ALB-033|MAT | L16: 1 | M16: ALB-033|MAT|1 | N16: 7 | O16: 0.17 | P16: - | Q16: 0 | R16: - | S16: -
A17: ALB-033 | B17: MAT | C17: OTR | D17: AGR-001 | E17: ARENA LAVADA | F17: m3 | G17: 0.035 | H17: 0.1 | I17: 32399.77 | J17: 1247.3911 | K17: ALB-033|MAT | L17: 2 | M17: ALB-033|MAT|2 | N17: 7 | O17: 0.035 | P17: - | Q17: 0 | R17: - | S17: -
A18: ALB-033 | B18: MAT | C18: OTR | D18: AGR-004 | E18: Cemento Portland x 50kg | F18: Bol | G18: 0.15 | H18: 0.1 | I18: 7809.48 | J18: 1288.5642 | K18: ALB-033|MAT | L18: 3 | M18: ALB-033|MAT|3 | N18: 7 | O18: 0.15 | P18: - | Q18: 0 | R18: - | S18: -
A19: ALB-033 | B19: MAT | C19: OTR | D19: AGR-005 | E19: Cal Comun x 25kg | F19: bol | G19: 0.3 | H19: 0.1 | I19: 3837.96 | J19: 1266.5268 | K19: ALB-033|MAT | L19: 4 | M19: ALB-033|MAT|4 | N19: 7 | O19: 0.3 | P19: - | Q19: 0 | R19: - | S19: -
A20: ALB-033 | B20: MAT | C20: OTR | D20: CER-005 | E20: Ladrillo Comun 12.5 x 5.5 x 25 | F20: u | G20: 60 | H20: 0.05 | I20: 132.3 | J20: 8334.9 | K20: ALB-033|MAT | L20: 5 | M20: ALB-033|MAT|5 | N20: 7 | O20: 60 | P20: - | Q20: 0 | R20: - | S20: -
A21: ALB-033 | B21: MAT | C21: OTR | D21: MAT-CONS | E21: Consumibles | F21: gl | G21: 1.3161102 | H21: 0 | I21: 1 | J21: 1.3161102 | K21: ALB-033|MAT | L21: 6 | M21: ALB-033|MAT|6 | N21: 7 | O21: 1.3161102 | P21: - | Q21: 0 | R21: - | S21: -
A22: ALB-033 | B22: MO | C22: ALB | D22: MO-EAYUD | E22: AYUDANTE | F22: j | G22: 1 | H22: 0 | I22: 60860.581 | J22: 60860.581 | K22: ALB-033|MO | L22: 1 | M22: ALB-033|MO|1 | N22: 7 | O22: 0.14285714 | P22: - | Q22: 0 | R22: - | S22: -
A23: ALB-033 | B23: MO | C23: ALB | D23: MO-EESPE | E23: ESPECIALIZADO | F23: j | G23: 1 | H23: 0 | I23: 85927.097 | J23: 85927.097 | K23: ALB-033|MO | L23: 2 | M23: ALB-033|MO|2 | N23: 7 | O23: 0.14285714 | P23: - | Q23: 0 | R23: - | S23: -
A24: ALB-034 | B24: EQ | D24: EQ-ANDAM0 | E24: ANDAMIO TUBULAR DE UNO A TRES CUERPOS | G24: 0.5 | H24: 0 | I24: 571.17949 | J24: 285.58975 | K24: ALB-034|EQ | L24: 1 | M24: ALB-034|EQ|1 | N24: 15 | O24: 0.5 | P24: 621 | Q24: 310.5 | R24: 4.01 | S24: Albañilería
A25: ALB-034 | B25: EQ | D25: EQ-EQALBA | E25: EQUIPO DE ALBAÑILERIA, carpetas, ladrillo | G25: 1 | H25: 0 | I25: 2287.1357 | J25: 2287.1357 | K25: ALB-034|EQ | L25: 2 | M25: ALB-034|EQ|2 | N25: 15 | O25: 1 | P25: 621 | Q25: 621 | R25: 4.01 | S25: Albañilería
A26: ALB-034 | B26: EQ | D26: EQ-TROMPO | E26: Hormigonera De 150 Litros 1hp Con Rueda Maciza | G26: 1 | H26: 0 | I26: 957.2532 | J26: 957.2532 | K26: ALB-034|EQ | L26: 3 | M26: ALB-034|EQ|3 | N26: 15 | O26: 1 | P26: 621 | Q26: 621 | R26: 4.01 | S26: Albañilería
A27: ALB-034 | B27: MAT | C27: OTR | D27: ACE-001 | E27: Barra de Acero Aleteado - 6mm x 12m | F27: u | G27: 0.17 | H27: 0.1 | I27: 3424.53 | J27: 640.38711 | K27: ALB-034|MAT | L27: 1 | M27: ALB-034|MAT|1 | N27: 15 | O27: 0.17 | P27: 621 | Q27: 105.57 | R27: 4.01 | S27: Albañilería
A28: ALB-034 | B28: MAT | C28: OTR | D28: AGR-001 | E28: ARENA LAVADA | F28: m3 | G28: 0.012 | H28: 0.1 | I28: 32399.77 | J28: 427.67696 | K28: ALB-034|MAT | L28: 2 | M28: ALB-034|MAT|2 | N28: 15 | O28: 0.012 | P28: 621 | Q28: 7.452 | R28: 4.01 | S28: Albañilería
A29: ALB-034 | B29: MAT | C29: OTR | D29: AGR-004 | E29: Cemento Portland x 50kg | F29: Bol | G29: 0.05 | H29: 0.1 | I29: 7809.48 | J29: 429.5214 | K29: ALB-034|MAT | L29: 3 | M29: ALB-034|MAT|3 | N29: 15 | O29: 0.05 | P29: 621 | Q29: 31.05 | R29: 4.01 | S29: Albañilería
A30: ALB-034 | B30: MAT | C30: OTR | D30: AGR-005 | E30: Cal Comun x 25kg | F30: bol | G30: 0.1 | H30: 0.1 | I30: 3837.96 | J30: 422.1756 | K30: ALB-034|MAT | L30: 4 | M30: ALB-034|MAT|4 | N30: 15 | O30: 0.1 | P30: 621 | Q30: 62.1 | R30: 4.01 | S30: Albañilería
A31: ALB-034 | B31: MAT | C31: OTR | D31: CER-002 | E31: LADRILLO CERAMICO 8 x 18 x 33 cm | F31: u | G31: 15 | H31: 0.05 | I31: 292.32 | J31: 4604.04 | K31: ALB-034|MAT | L31: 5 | M31: ALB-034|MAT|5 | N31: 15 | O31: 15 | P31: 621 | Q31: 9315 | R31: 4.01 | S31: Albañilería
A32: ALB-034 | B32: MAT | C32: OTR | D32: MAT-CONS | E32: Consumibles | F32: gl | G32: 67.195151 | H32: 0 | I32: 1 | J32: 67.195151 | K32: ALB-034|MAT | L32: 6 | M32: ALB-034|MAT|6 | N32: 15 | O32: 67.195151 | P32: 621 | Q32: 41728.189 | R32: 4.01 | S32: Albañilería
A33: ALB-034 | B33: MO | C33: ALB | D33: MO-EAYUD | E33: AYUDANTE | F33: j | G33: 1 | H33: 0 | I33: 60860.581 | J33: 60860.581 | K33: ALB-034|MO | L33: 1 | M33: ALB-034|MO|1 | N33: 15 | O33: 0.066666667 | P33: 621 | Q33: 41.4 | R33: 4.01 | S33: Albañilería
A34: ALB-034 | B34: MO | C34: ALB | D34: MO-EESPE | E34: ESPECIALIZADO | F34: j | G34: 1 | H34: 0 | I34: 85927.097 | J34: 85927.097 | K34: ALB-034|MO | L34: 2 | M34: ALB-034|MO|2 | N34: 15 | O34: 0.066666667 | P34: 621 | Q34: 41.4 | R34: 4.01 | S34: Albañilería
A35: ALB-035 | B35: EQ | D35: EQ-ANDAM0 | E35: ANDAMIO TUBULAR DE UNO A TRES CUERPOS | G35: 0.5 | H35: 0 | I35: 571.17949 | J35: 285.58975 | K35: ALB-035|EQ | L35: 1 | M35: ALB-035|EQ|1 | N35: 15 | O35: 0.5 | P35: 780 | Q35: 390 | R35: 4.02 | S35: Albañilería
A36: ALB-035 | B36: EQ | D36: EQ-EQALBA | E36: EQUIPO DE ALBAÑILERIA, carpetas, ladrillo | G36: 1 | H36: 0 | I36: 2287.1357 | J36: 2287.1357 | K36: ALB-035|EQ | L36: 2 | M36: ALB-035|EQ|2 | N36: 15 | O36: 1 | P36: 780 | Q36: 780 | R36: 4.02 | S36: Albañilería
A37: ALB-035 | B37: EQ | D37: EQ-TROMPO | E37: Hormigonera De 150 Litros 1hp Con Rueda Maciza | G37: 1 | H37: 0 | I37: 957.2532 | J37: 957.2532 | K37: ALB-035|EQ | L37: 3 | M37: ALB-035|EQ|3 | N37: 15 | O37: 1 | P37: 780 | Q37: 780 | R37: 4.02 | S37: Albañilería
A38: ALB-035 | B38: MAT | C38: OTR | D38: ACE-001 | E38: Barra de Acero Aleteado - 6mm x 12m | F38: u | G38: 0.17 | H38: 0.1 | I38: 3424.53 | J38: 640.38711 | K38: ALB-035|MAT | L38: 1 | M38: ALB-035|MAT|1 | N38: 15 | O38: 0.17 | P38: 780 | Q38: 132.6 | R38: 4.02 | S38: Albañilería
A39: ALB-035 | B39: MAT | C39: OTR | D39: AGR-001 | E39: ARENA LAVADA | F39: m3 | G39: 0.018 | H39: 0.1 | I39: 32399.77 | J39: 641.51545 | K39: ALB-035|MAT | L39: 2 | M39: ALB-035|MAT|2 | N39: 15 | O39: 0.018 | P39: 780 | Q39: 14.04 | R39: 4.02 | S39: Albañilería
A40: ALB-035 | B40: MAT | C40: OTR | D40: AGR-004 | E40: Cemento Portland x 50kg | F40: Bol | G40: 0.075 | H40: 0.1 | I40: 7809.48 | J40: 644.2821 | K40: ALB-035|MAT | L40: 3 | M40: ALB-035|MAT|3 | N40: 15 | O40: 0.075 | P40: 780 | Q40: 58.5 | R40: 4.02 | S40: Albañilería
A41: ALB-035 | B41: MAT | C41: OTR | D41: AGR-005 | E41: Cal Comun x 25kg | F41: bol | G41: 0.15 | H41: 0.1 | I41: 3837.96 | J41: 633.2634 | K41: ALB-035|MAT | L41: 4 | M41: ALB-035|MAT|4 | N41: 15 | O41: 0.15 | P41: 780 | Q41: 117 | R41: 4.02 | S41: Albañilería
A42: ALB-035 | B42: MAT | C42: OTR | D42: CER-003 | E42: LADRILLO CERAMICO 12 x 18 x 33 cm | F42: u | G42: 15 | H42: 0.05 | I42: 365.4 | J42: 5755.05 | K42: ALB-035|MAT | L42: 5 | M42: ALB-035|MAT|5 | N42: 15 | O42: 15 | P42: 780 | Q42: 11700 | R42: 4.02 | S42: Albañilería
A43: ALB-035 | B43: MAT | C43: OTR | D43: MAT-CONS | E43: Consumibles | F43: gl | G43: 85.63933 | H43: 0 | I43: 1 | J43: 85.63933 | K43: ALB-035|MAT | L43: 6 | M43: ALB-035|MAT|6 | N43: 15 | O43: 85.63933 | P43: 780 | Q43: 66798.677 | R43: 4.02 | S43: Albañilería
A44: ALB-035 | B44: MO | C44: ALB | D44: MO-EAYUD | E44: AYUDANTE | F44: j | G44: 1 | H44: 0 | I44: 60860.581 | J44: 60860.581 | K44: ALB-035|MO | L44: 1 | M44: ALB-035|MO|1 | N44: 15 | O44: 0.066666667 | P44: 780 | Q44: 52 | R44: 4.02 | S44: Albañilería
A45: ALB-035 | B45: MO | C45: ALB | D45: MO-EESPE | E45: ESPECIALIZADO | F45: j | G45: 1 | H45: 0 | I45: 85927.097 | J45: 85927.097 | K45: ALB-035|MO | L45: 2 | M45: ALB-035|MO|2 | N45: 15 | O45: 0.066666667 | P45: 780 | Q45: 52 | R45: 4.02 | S45: Albañilería
A46: ALB-036 | B46: EQ | D46: EQ-ANDAM0 | E46: ANDAMIO TUBULAR DE UNO A TRES CUERPOS | G46: 0.5 | H46: 0 | I46: 571.17949 | J46: 285.58975 | K46: ALB-036|EQ | L46: 1 | M46: ALB-036|EQ|1 | N46: 15 | O46: 0.5 | P46: 5 | Q46: 2.5 | R46: 4.06 | S46: Albañilería
A47: ALB-036 | B47: EQ | D47: EQ-EQALBA | E47: EQUIPO DE ALBAÑILERIA, carpetas, ladrillo | G47: 1 | H47: 0 | I47: 2287.1357 | J47: 2287.1357 | K47: ALB-036|EQ | L47: 2 | M47: ALB-036|EQ|2 | N47: 15 | O47: 1 | P47: 5 | Q47: 5 | R47: 4.06 | S47: Albañilería
A48: ALB-036 | B48: EQ | D48: EQ-TROMPO | E48: Hormigonera De 150 Litros 1hp Con Rueda Maciza | G48: 1 | H48: 0 | I48: 957.2532 | J48: 957.2532 | K48: ALB-036|EQ | L48: 3 | M48: ALB-036|EQ|3 | N48: 15 | O48: 1 | P48: 5 | Q48: 5 | R48: 4.06 | S48: Albañilería
A49: ALB-036 | B49: MAT | C49: OTR | D49: ACE-001 | E49: Barra de Acero Aleteado - 6mm x 12m | F49: u | G49: 0.17 | H49: 0.1 | I49: 3424.53 | J49: 640.38711 | K49: ALB-036|MAT | L49: 1 | M49: ALB-036|MAT|1 | N49: 15 | O49: 0.17 | P49: 5 | Q49: 0.85 | R49: 4.06 | S49: Albañilería
A50: ALB-036 | B50: MAT | C50: OTR | D50: AGR-001 | E50: ARENA LAVADA | F50: m3 | G50: 0.024 | H50: 0.1 | I50: 32399.77 | J50: 855.35393 | K50: ALB-036|MAT | L50: 2 | M50: ALB-036|MAT|2 | N50: 15 | O50: 0.024 | P50: 5 | Q50: 0.12 | R50: 4.06 | S50: Albañilería
A51: ALB-036 | B51: MAT | C51: OTR | D51: AGR-004 | E51: Cemento Portland x 50kg | F51: Bol | G51: 0.1 | H51: 0.1 | I51: 7809.48 | J51: 859.0428 | K51: ALB-036|MAT | L51: 3 | M51: ALB-036|MAT|3 | N51: 15 | O51: 0.1 | P51: 5 | Q51: 0.5 | R51: 4.06 | S51: Albañilería
A52: ALB-036 | B52: MAT | C52: OTR | D52: AGR-005 | E52: Cal Comun x 25kg | F52: bol | G52: 0.2 | H52: 0.1 | I52: 3837.96 | J52: 844.3512 | K52: ALB-036|MAT | L52: 4 | M52: ALB-036|MAT|4 | N52: 15 | O52: 0.2 | P52: 5 | Q52: 1 | R52: 4.06 | S52: Albañilería
A53: ALB-036 | B53: MAT | C53: OTR | D53: CER-004 | E53: LADRILLO CERAMICO 18 x 18 x 33 cm | F53: u | G53: 15 | H53: 0.05 | I53: 519.12 | J53: 8176.14 | K53: ALB-036|MAT | L53: 5 | M53: ALB-036|MAT|5 | N53: 15 | O53: 15 | P53: 5 | Q53: 75 | R53: 4.06 | S53: Albañilería
A54: ALB-036 | B54: MAT | C54: OTR | D54: MAT-CONS | E54: Consumibles | F54: gl | G54: 117.16533 | H54: 0 | I54: 1 | J54: 117.16533 | K54: ALB-036|MAT | L54: 6 | M54: ALB-036|MAT|6 | N54: 15 | O54: 117.16533 | P54: 5 | Q54: 585.82666 | R54: 4.06 | S54: Albañilería
A55: ALB-036 | B55: MO | C55: ALB | D55: MO-EAYUD | E55: AYUDANTE | F55: j | G55: 1 | H55: 0 | I55: 60860.581 | J55: 60860.581 | K55: ALB-036|MO | L55: 1 | M55: ALB-036|MO|1 | N55: 15 | O55: 0.066666667 | P55: 5 | Q55: 0.33333333 | R55: 4.06 | S55: Albañilería
A56: ALB-036 | B56: MO | C56: ALB | D56: MO-EESPE | E56: ESPECIALIZADO | F56: j | G56: 1 | H56: 0 | I56: 85927.097 | J56: 85927.097 | K56: ALB-036|MO | L56: 2 | M56: ALB-036|MO|2 | N56: 15 | O56: 0.066666667 | P56: 5 | Q56: 0.33333333 | R56: 4.06 | S56: Albañilería
A57: ALB-037 | B57: EQ | D57: EQ-ANDAM0 | E57: ANDAMIO TUBULAR DE UNO A TRES CUERPOS | G57: 0.5 | H57: 0 | I57: 571.17949 | J57: 285.58975 | K57: ALB-037|EQ | L57: 1 | M57: ALB-037|EQ|1 | N57: 4 | O57: 0.5 | P57: - | Q57: 0 | R57: - | S57: -
A58: ALB-037 | B58: EQ | D58: EQ-EQALBA | E58: EQUIPO DE ALBAÑILERIA, carpetas, ladrillo | G58: 1 | H58: 0 | I58: 2287.1357 | J58: 2287.1357 | K58: ALB-037|EQ | L58: 2 | M58: ALB-037|EQ|2 | N58: 4 | O58: 1 | P58: - | Q58: 0 | R58: - | S58: -
A59: ALB-037 | B59: EQ | D59: EQ-TROMPO | E59: Hormigonera De 150 Litros 1hp Con Rueda Maciza | G59: 1 | H59: 0 | I59: 957.2532 | J59: 957.2532 | K59: ALB-037|EQ | L59: 3 | M59: ALB-037|EQ|3 | N59: 4 | O59: 1 | P59: - | Q59: 0 | R59: - | S59: -
A60: ALB-037 | B60: MAT | C60: OTR | D60: ACE-001 | E60: Barra de Acero Aleteado - 6mm x 12m | F60: u | G60: 0.34 | H60: 0.1 | I60: 3424.53 | J60: 1280.7742 | K60: ALB-037|MAT | L60: 1 | M60: ALB-037|MAT|1 | N60: 4 | O60: 0.34 | P60: - | Q60: 0 | R60: - | S60: -
A61: ALB-037 | B61: MAT | C61: OTR | D61: AGR-001 | E61: ARENA LAVADA | F61: m3 | G61: 0.053 | H61: 0.1 | I61: 32399.77 | J61: 1888.9066 | K61: ALB-037|MAT | L61: 2 | M61: ALB-037|MAT|2 | N61: 4 | O61: 0.053 | P61: - | Q61: 0 | R61: - | S61: -
A62: ALB-037 | B62: MAT | C62: OTR | D62: AGR-004 | E62: Cemento Portland x 50kg | F62: Bol | G62: 0.254 | H62: 0.1 | I62: 7809.48 | J62: 2181.9687 | K62: ALB-037|MAT | L62: 3 | M62: ALB-037|MAT|3 | N62: 4 | O62: 0.254 | P62: - | Q62: 0 | R62: - | S62: -
A63: ALB-037 | B63: MAT | C63: OTR | D63: AGR-005 | E63: Cal Comun x 25kg | F63: bol | G63: 0.4 | H63: 0.1 | I63: 3837.96 | J63: 1688.7024 | K63: ALB-037|MAT | L63: 4 | M63: ALB-037|MAT|4 | N63: 4 | O63: 0.4 | P63: - | Q63: 0 | R63: - | S63: -
A64: ALB-037 | B64: MAT | C64: OTR | D64: AIS-001 | E64: Aditivo Hidrofugo en pasta - Ceresita x 1kg | F64: kg | G64: 0.1 | H64: 0.05 | I64: 1256.128 | J64: 131.89344 | K64: ALB-037|MAT | L64: 5 | M64: ALB-037|MAT|5 | N64: 4 | O64: 0.1 | P64: - | Q64: 0 | R64: - | S64: -
A65: ALB-037 | B65: MAT | C65: OTR | D65: CER-002 | E65: LADRILLO CERAMICO 8 x 18 x 33 cm | F65: u | G65: 15 | H65: 0.05 | I65: 292.32 | J65: 4604.04 | K65: ALB-037|MAT | L65: 6 | M65: ALB-037|MAT|6 | N65: 4 | O65: 15 | P65: - | Q65: 0 | R65: - | S65: -
A66: ALB-037 | B66: MAT | C66: OTR | D66: CER-001 | E66: ladrillo a la vista 1 cara | F66: u | G66: 60 | H66: 0.05 | I66: 233.44 | J66: 14706.72 | K66: ALB-037|MAT | L66: 7 | M66: ALB-037|MAT|7 | N66: 4 | O66: 60 | P66: - | Q66: 0 | R66: - | S66: -
A67: ALB-037 | B67: MAT | C67: OTR | D67: MAT-CONS | E67: Consumibles | F67: gl | G67: 285.29 | H67: 0 | I67: 1 | J67: 285.29 | K67: ALB-037|MAT | L67: 8 | M67: ALB-037|MAT|8 | N67: 4 | O67: 285.29 | P67: - | Q67: 0 | R67: - | S67: -
A68: ALB-037 | B68: MAT | C68: OTR | D68: OTR-022 | E68: Aguarras Hydrarras Hydra x 18lts | F68: b | G68: 0.005 | H68: 0.05 | I68: 26907.33 | J68: 141.26348 | K68: ALB-037|MAT | L68: 9 | M68: ALB-037|MAT|9 | N68: 4 | O68: 0.005 | P68: - | Q68: 0 | R68: - | S68: -
A69: ALB-037 | B69: MAT | C69: OTR | D69: OTR-027 | E69: Rodillo de lana pelo largo N°22 - El Galgo | F69: u | G69: 0.01 | H69: 0.05 | I69: 6678.36 | J69: 70.12278 | K69: ALB-037|MAT | L69: 10 | M69: ALB-037|MAT|10 | N69: 4 | O69: 0.01 | P69: - | Q69: 0 | R69: - | S69: -
A70: ALB-037 | B70: MAT | C70: OTR | D70: PIN-008 | E70: Pintura Asfaltica Asfasol x18ts | F70: b | G70: 0.027777778 | H70: 0.1 | I70: 32845.78 | J70: 1003.6211 | K70: ALB-037|MAT | L70: 11 | M70: ALB-037|MAT|11 | N70: 4 | O70: 0.027777778 | P70: - | Q70: 0 | R70: - | S70: -
A71: ALB-037 | B71: MO | C71: ALB | D71: MO-EAYUD | E71: AYUDANTE | F71: j | G71: 0.91 | H71: 0 | I71: 60860.581 | J71: 55383.129 | K71: ALB-037|MO | L71: 1 | M71: ALB-037|MO|1 | N71: 4 | O71: 0.2275 | P71: - | Q71: 0 | R71: - | S71: -
A72: ALB-037 | B72: MO | C72: ALB | D72: MO-EESPE | E72: ESPECIALIZADO | F72: j | G72: 1 | H72: 0 | I72: 85927.097 | J72: 85927.097 | K72: ALB-037|MO | L72: 2 | M72: ALB-037|MO|2 | N72: 4 | O72: 0.25 | P72: - | Q72: 0 | R72: - | S72: -
A73: ALB-038 | B73: EQ | D73: EQ-ANDAM0 | E73: ANDAMIO TUBULAR DE UNO A TRES CUERPOS | G73: 0.5 | H73: 0 | I73: 571.17949 | J73: 285.58975 | K73: ALB-038|EQ | L73: 1 | M73: ALB-038|EQ|1 | N73: 15 | O73: 0.5 | P73: 42 | Q73: 21 | R73: 4.04 | S73: Albañilería
A74: ALB-038 | B74: EQ | D74: EQ-EQALBA | E74: EQUIPO DE ALBAÑILERIA, carpetas, ladrillo | G74: 1 | H74: 0 | I74: 2287.1357 | J74: 2287.1357 | K74: ALB-038|EQ | L74: 2 | M74: ALB-038|EQ|2 | N74: 15 | O74: 1 | P74: 42 | Q74: 42 | R74: 4.04 | S74: Albañilería
A75: ALB-038 | B75: EQ | D75: EQ-TROMPO | E75: Hormigonera De 150 Litros 1hp Con Rueda Maciza | G75: 1 | H75: 0 | I75: 957.2532 | J75: 957.2532 | K75: ALB-038|EQ | L75: 3 | M75: ALB-038|EQ|3 | N75: 15 | O75: 1 | P75: 42 | Q75: 42 | R75: 4.04 | S75: Albañilería
A76: ALB-038 | B76: MAT | C76: OTR | D76: ACE-001 | E76: Barra de Acero Aleteado - 6mm x 12m | F76: u | G76: 0.17 | H76: 0.1 | I76: 3424.53 | J76: 640.38711 | K76: ALB-038|MAT | L76: 1 | M76: ALB-038|MAT|1 | N76: 15 | O76: 0.17 | P76: 42 | Q76: 7.14 | R76: 4.04 | S76: Albañilería
A77: ALB-038 | B77: MAT | C77: OTR | D77: AGR-001 | E77: ARENA LAVADA | F77: m3 | G77: 0.018 | H77: 0.1 | I77: 32399.77 | J77: 641.51545 | K77: ALB-038|MAT | L77: 2 | M77: ALB-038|MAT|2 | N77: 15 | O77: 0.018 | P77: 42 | Q77: 0.756 | R77: 4.04 | S77: Albañilería
A78: ALB-038 | B78: MAT | C78: OTR | D78: AGR-004 | E78: Cemento Portland x 50kg | F78: Bol | G78: 0.075 | H78: 0.1 | I78: 7809.48 | J78: 644.2821 | K78: ALB-038|MAT | L78: 3 | M78: ALB-038|MAT|3 | N78: 15 | O78: 0.075 | P78: 42 | Q78: 3.15 | R78: 4.04 | S78: Albañilería
A79: ALB-038 | B79: MAT | C79: OTR | D79: AGR-005 | E79: Cal Comun x 25kg | F79: bol | G79: 0.15 | H79: 0.1 | I79: 3837.96 | J79: 633.2634 | K79: ALB-038|MAT | L79: 4 | M79: ALB-038|MAT|4 | N79: 15 | O79: 0.15 | P79: 42 | Q79: 6.3 | R79: 4.04 | S79: Albañilería
A80: ALB-038 | B80: MAT | C80: OTR | D80: CER-006 | E80: Ladrillo hueco ceramico 12x19x33 - Portante | F80: u | G80: 15 | H80: 0.05 | I80: 563.22 | J80: 8870.715 | K80: ALB-038|MAT | L80: 5 | M80: ALB-038|MAT|5 | N80: 15 | O80: 15 | P80: 42 | Q80: 630 | R80: 4.04 | S80: Albañilería
A81: ALB-038 | B81: MAT | C81: OTR | D81: MAT-CONS | E81: Consumibles | F81: gl | G81: 117.73068 | H81: 0 | I81: 1 | J81: 117.73068 | K81: ALB-038|MAT | L81: 6 | M81: ALB-038|MAT|6 | N81: 15 | O81: 117.73068 | P81: 42 | Q81: 4944.6885 | R81: 4.04 | S81: Albañilería
A82: ALB-038 | B82: MO | C82: ALB | D82: MO-EAYUD | E82: AYUDANTE | F82: j | G82: 1 | H82: 0 | I82: 60860.581 | J82: 60860.581 | K82: ALB-038|MO | L82: 1 | M82: ALB-038|MO|1 | N82: 15 | O82: 0.066666667 | P82: 42 | Q82: 2.8 | R82: 4.04 | S82: Albañilería
A83: ALB-038 | B83: MO | C83: ALB | D83: MO-EESPE | E83: ESPECIALIZADO | F83: j | G83: 1 | H83: 0 | I83: 85927.097 | J83: 85927.097 | K83: ALB-038|MO | L83: 2 | M83: ALB-038|MO|2 | N83: 15 | O83: 0.066666667 | P83: 42 | Q83: 2.8 | R83: 4.04 | S83: Albañilería
A84: ALB-039 | B84: EQ | D84: EQ-EQALBA | E84: EQUIPO DE ALBAÑILERIA, carpetas, ladrillo | G84: 0.25 | H84: 0 | I84: 2287.1357 | J84: 571.78394 | K84: ALB-039|EQ | L84: 1 | M84: ALB-039|EQ|1 | N84: 2 | O84: 0.25 | P84: - | Q84: 0 | R84: - | S84: -
A85: ALB-039 | B85: EQ | D85: EQ-TROMPO | E85: Hormigonera De 150 Litros 1hp Con Rueda Maciza | G85: 0.25 | H85: 0 | I85: 957.2532 | J85: 239.3133 | K85: ALB-039|EQ | L85: 2 | M85: ALB-039|EQ|2 | N85: 2 | O85: 0.25 | P85: - | Q85: 0 | R85: - | S85: -
A86: ALB-039 | B86: MAT | C86: OTR | D86: AGR-001 | E86: ARENA LAVADA | F86: m3 | G86: 0.036 | H86: 0.1 | I86: 32399.77 | J86: 1283.0309 | K86: ALB-039|MAT | L86: 1 | M86: ALB-039|MAT|1 | N86: 2 | O86: 0.036 | P86: - | Q86: 0 | R86: - | S86: -
A87: ALB-039 | B87: MAT | C87: OTR | D87: AGR-004 | E87: Cemento Portland x 50kg | F87: Bol | G87: 0.324 | H87: 0.1 | I87: 7809.48 | J87: 2783.2987 | K87: ALB-039|MAT | L87: 2 | M87: ALB-039|MAT|2 | N87: 2 | O87: 0.324 | P87: - | Q87: 0 | R87: - | S87: -
A88: ALB-039 | B88: MO | C88: ALB | D88: MO-EAYUD | E88: AYUDANTE | F88: j | G88: 0.75 | H88: 0 | I88: 60860.581 | J88: 45645.436 | K88: ALB-039|MO | L88: 1 | M88: ALB-039|MO|1 | N88: 2 | O88: 0.375 | P88: - | Q88: 0 | R88: - | S88: -
A89: ALB-039 | B89: MO | C89: ALB | D89: MO-EESPE | E89: ESPECIALIZADO | F89: j | G89: 0.75 | H89: 0 | I89: 85927.097 | J89: 64445.323 | K89: ALB-039|MO | L89: 2 | M89: ALB-039|MO|2 | N89: 2 | O89: 0.375 | P89: - | Q89: 0 | R89: - | S89: -
A90: ALB-040 | B90: EQ | D90: EQ-EQALBA | E90: EQUIPO DE ALBAÑILERIA, carpetas, ladrillo | G90: 0.25 | H90: 0 | I90: 2287.1357 | J90: 571.78394 | K90: ALB-040|EQ | L90: 1 | M90: ALB-040|EQ|1 | N90: 4 | O90: 0.25 | P90: - | Q90: 0 | R90: - | S90: -
A91: ALB-040 | B91: EQ | D91: EQ-TROMPO | E91: Hormigonera De 150 Litros 1hp Con Rueda Maciza | G91: 0.25 | H91: 0 | I91: 957.2532 | J91: 239.3133 | K91: ALB-040|EQ | L91: 2 | M91: ALB-040|EQ|2 | N91: 4 | O91: 0.25 | P91: - | Q91: 0 | R91: - | S91: -
A92: ALB-040 | B92: MAT | C92: OTR | D92: AGR-001 | E92: ARENA LAVADA | F92: m3 | G92: 0.0138 | H92: 0.05 | I92: 32399.77 | J92: 469.47267 | K92: ALB-040|MAT | L92: 1 | M92: ALB-040|MAT|1 | N92: 4 | O92: 0.0138 | P92: - | Q92: 0 | R92: - | S92: -
A93: ALB-040 | B93: MAT | C93: OTR | D93: AGR-004 | E93: Cemento Portland x 50kg | F93: Bol | G93: 0.1242 | H93: 0.05 | I93: 7809.48 | J93: 1018.4343 | K93: ALB-040|MAT | L93: 2 | M93: ALB-040|MAT|2 | N93: 4 | O93: 0.1242 | P93: - | Q93: 0 | R93: - | S93: -
A94: ALB-040 | B94: MO | C94: ALB | D94: MO-EAYUD | E94: AYUDANTE | F94: j | G94: 1 | H94: 0 | I94: 60860.581 | J94: 60860.581 | K94: ALB-040|MO | L94: 1 | M94: ALB-040|MO|1 | N94: 4 | O94: 0.25 | P94: - | Q94: 0 | R94: - | S94: -
A95: ALB-040 | B95: MO | C95: ALB | D95: MO-EESPE | E95: ESPECIALIZADO | F95: j | G95: 1 | H95: 0 | I95: 85927.097 | J95: 85927.097 | K95: ALB-040|MO | L95: 2 | M95: ALB-040|MO|2 | N95: 4 | O95: 0.25 | P95: - | Q95: 0 | R95: - | S95: -
A96: ALB-041 | B96: EQ | D96: EQ-EQALBA | E96: EQUIPO DE ALBAÑILERIA, carpetas, ladrillo | G96: 0.5 | H96: 0 | I96: 2287.1357 | J96: 1143.5679 | K96: ALB-041|EQ | L96: 1 | M96: ALB-041|EQ|1 | N96: 5 | O96: 0.5 | P96: - | Q96: 0 | R96: - | S96: -
A97: ALB-041 | B97: EQ | D97: EQ-TROMPO | E97: Hormigonera De 150 Litros 1hp Con Rueda Maciza | G97: 0.25 | H97: 0 | I97: 957.2532 | J97: 239.3133 | K97: ALB-041|EQ | L97: 2 | M97: ALB-041|EQ|2 | N97: 5 | O97: 0.25 | P97: - | Q97: 0 | R97: - | S97: -
A98: ALB-041 | B98: MAT | C98: OTR | D98: AGR-001 | E98: ARENA LAVADA | F98: m3 | G98: 0.0018 | H98: 0.1 | I98: 32399.77 | J98: 64.151545 | K98: ALB-041|MAT | L98: 1 | M98: ALB-041|MAT|1 | N98: 5 | O98: 0.0018 | P98: - | Q98: 0 | R98: - | S98: -
A99: ALB-041 | B99: MAT | C99: OTR | D99: AGR-004 | E99: Cemento Portland x 50kg | F99: Bol | G99: 0.0162 | H99: 0.1 | I99: 7809.48 | J99: 139.16493 | K99: ALB-041|MAT | L99: 2 | M99: ALB-041|MAT|2 | N99: 5 | O99: 0.0162 | P99: - | Q99: 0 | R99: - | S99: -
A100: ALB-041 | B100: MAT | C100: OTR | D100: MAT-CONS | E100: Consumibles | F100: gl | G100: 1.0470799 | H100: 0 | I100: 1 | J100: 1.0470799 | K100: ALB-041|MAT | L100: 3 | M100: ALB-041|MAT|3 | N100: 5 | O100: 1.0470799 | P100: - | Q100: 0 | R100: - | S100: -
...

Sheet 2_Gastos
A1: Rubro | B1: MT/MO | C1: Mes | D1: Cuenta | E1: Descripción de Cuenta | F1: Fecha Asiento | G1: Número de Asiento | H1: Observaciones | I1: Cliente / Proveedor | J1: Código de Comprobante | K1: Número de comprobante | L1: Debe | M1: Haber | N1: Unidad | O1: Descripción de Unidad | P1: Centro de Costo | Q1: Descripción de Centro de Costo | R1: Saldo Inicial | S1: Monto Descontado | T1: Monto Real | U1: Contrato | V1: Monto CAC | W1: Monto Base | X1: En Ppto
A2: - | B2: - | C2: =+EOMONTH(Tabla18[[#This Row],[Fecha Asiento]],-1)+1 -> 45597 | D2: 52210 | E2: H. Gestoria | F2: 45604 | G2: 89 | H2: Viarq U$ 250 | J2: OPXX | K2: 5521 | L2: 275000 | M2: 0 | N2: DESA | O2: Desarrollos | P2: GDR | Q2: García del Río 3760 | R2: 0 | S2: =(Tabla18[[#This Row],[Debe]]-Tabla18[[#This Row],[Haber]])* SUMIF('0_Indice_CAC'!$A:$A,Tabla18[[#This Row],[Mes]],'0_Indice_CAC'!$D:$D) -> 0 | T2: =Tabla18[[#This Row],[Debe]]-Tabla18[[#This Row],[Haber]] -> 275000 | W2: =IFERROR(T2-IF(V2="",0,V2),0) -> 275000 | X2: =ISNUMBER(MATCH(A2,'3_Control_Ppto'!$A$4:$A$70,0)) -> FALSE
A3: Gastos Generales Obra | B3: - | C3: =+EOMONTH(Tabla18[[#This Row],[Fecha Asiento]],-1)+1 -> 45627 | D3: 53022 | E3: Gastos Generales | F3: 45632 | G3: 413 | H3: Encomienda - Instalaciones DO | J3: OPG | K3: 3488 | L3: 53000 | M3: 0 | N3: DESA | O3: Desarrollos | P3: GDR | Q3: García del Río 3760 | R3: 0 | S3: =(Tabla18[[#This Row],[Debe]]-Tabla18[[#This Row],[Haber]])* SUMIF('0_Indice_CAC'!$A:$A,Tabla18[[#This Row],[Mes]],'0_Indice_CAC'!$D:$D) -> 53000 | T3: =Tabla18[[#This Row],[Debe]]-Tabla18[[#This Row],[Haber]] -> 53000 | W3: =IFERROR(T3-IF(V3="",0,V3),0) -> 53000 | X3: =ISNUMBER(MATCH(A3,'3_Control_Ppto'!$A$4:$A$70,0)) -> TRUE
A4: Gastos Generales Obra | B4: - | C4: =+EOMONTH(Tabla18[[#This Row],[Fecha Asiento]],-1)+1 -> 45627 | D4: 53022 | E4: Gastos Generales | F4: 45632 | G4: 414 | H4: Encomienda Obra - DO | J4: OPG | K4: 3489 | L4: 180000 | M4: 0 | N4: DESA | O4: Desarrollos | P4: GDR | Q4: García del Río 3760 | R4: 0 | S4: =(Tabla18[[#This Row],[Debe]]-Tabla18[[#This Row],[Haber]])* SUMIF('0_Indice_CAC'!$A:$A,Tabla18[[#This Row],[Mes]],'0_Indice_CAC'!$D:$D) -> 180000 | T4: =Tabla18[[#This Row],[Debe]]-Tabla18[[#This Row],[Haber]] -> 180000 | W4: =IFERROR(T4-IF(V4="",0,V4),0) -> 180000 | X4: =ISNUMBER(MATCH(A4,'3_Control_Ppto'!$A$4:$A$70,0)) -> TRUE
A5: - | B5: - | C5: =+EOMONTH(Tabla18[[#This Row],[Fecha Asiento]],-1)+1 -> 45627 | D5: 52210 | E5: H. Gestoria | F5: 45638 | G5: 865 | H5: H. Gestoria- USD 450 A TC 1070 | J5: OPXX | K5: 6281 | L5: 481500 | M5: 0 | N5: DESA | O5: Desarrollos | P5: GDR | Q5: García del Río 3760 | R5: 0 | S5: =(Tabla18[[#This Row],[Debe]]-Tabla18[[#This Row],[Haber]])* SUMIF('0_Indice_CAC'!$A:$A,Tabla18[[#This Row],[Mes]],'0_Indice_CAC'!$D:$D) -> 481500 | T5: =Tabla18[[#This Row],[Debe]]-Tabla18[[#This Row],[Haber]] -> 481500 | W5: =IFERROR(T5-IF(V5="",0,V5),0) -> 481500 | X5: =ISNUMBER(MATCH(A5,'3_Control_Ppto'!$A$4:$A$70,0)) -> FALSE
A6: - | B6: - | C6: =+EOMONTH(Tabla18[[#This Row],[Fecha Asiento]],-1)+1 -> 45627 | D6: 52205 | E6: H. Escribanía | F6: 45642 | G6: 252 | H6: Pto. 720 - Varios | J6: OPXX | K6: 5679 | L6: 3000000 | M6: 0 | N6: DESA | O6: Desarrollos | P6: GDR | Q6: García del Río 3760 | R6: 0 | S6: =(Tabla18[[#This Row],[Debe]]-Tabla18[[#This Row],[Haber]])* SUMIF('0_Indice_CAC'!$A:$A,Tabla18[[#This Row],[Mes]],'0_Indice_CAC'!$D:$D) -> 3000000 | T6: =Tabla18[[#This Row],[Debe]]-Tabla18[[#This Row],[Haber]] -> 3000000 | W6: =IFERROR(T6-IF(V6="",0,V6),0) -> 3000000 | X6: =ISNUMBER(MATCH(A6,'3_Control_Ppto'!$A$4:$A$70,0)) -> FALSE
A7: Gastos Generales Obra | B7: - | C7: =+EOMONTH(Tabla18[[#This Row],[Fecha Asiento]],-1)+1 -> 45627 | D7: 53022 | E7: Gastos Generales | F7: 45645 | G7: 186 | H7: Combustible para cortar pasto | J7: OPXX | K7: 5612 | L7: 7005 | M7: 0 | N7: DESA | O7: Desarrollos | P7: GDR | Q7: García del Río 3760 | R7: 0 | S7: =(Tabla18[[#This Row],[Debe]]-Tabla18[[#This Row],[Haber]])* SUMIF('0_Indice_CAC'!$A:$A,Tabla18[[#This Row],[Mes]],'0_Indice_CAC'!$D:$D) -> 7005 | T7: =Tabla18[[#This Row],[Debe]]-Tabla18[[#This Row],[Haber]] -> 7005 | W7: =IFERROR(T7-IF(V7="",0,V7),0) -> 7005 | X7: =ISNUMBER(MATCH(A7,'3_Control_Ppto'!$A$4:$A$70,0)) -> TRUE
A8: Gastos Generales Obra | B8: - | C8: =+EOMONTH(Tabla18[[#This Row],[Fecha Asiento]],-1)+1 -> 45627 | D8: 53022 | E8: Gastos Generales | F8: 45645 | G8: 538 | H8: Combustible para desmalecedora | I8: ESTACION DE SERVICIO NORTENA S.R.L. | J8: TIQA | K8: 2100049507 | L8: 5258.93 | M8: 0 | N8: DESA | O8: Desarrollos | P8: GDR | Q8: García del Río 3760 | R8: 0 | S8: =(Tabla18[[#This Row],[Debe]]-Tabla18[[#This Row],[Haber]])* SUMIF('0_Indice_CAC'!$A:$A,Tabla18[[#This Row],[Mes]],'0_Indice_CAC'!$D:$D) -> 5258.93 | T8: =Tabla18[[#This Row],[Debe]]-Tabla18[[#This Row],[Haber]] -> 5258.93 | W8: =IFERROR(T8-IF(V8="",0,V8),0) -> 5258.93 | X8: =ISNUMBER(MATCH(A8,'3_Control_Ppto'!$A$4:$A$70,0)) -> TRUE
A9: Gastos Generales Obra | B9: - | C9: =+EOMONTH(Tabla18[[#This Row],[Fecha Asiento]],-1)+1 -> 45627 | D9: 53022 | E9: Gastos Generales | F9: 45645 | G9: 538 | H9: GASTOS GENERALAES - ESTACION D | I9: ESTACION DE SERVICIO NORTENA S.R.L. | J9: TIQA | K9: 2100049507 | L9: 641.7 | M9: 0 | N9: DESA | O9: Desarrollos | P9: GDR | Q9: García del Río 3760 | R9: 0 | S9: =(Tabla18[[#This Row],[Debe]]-Tabla18[[#This Row],[Haber]])* SUMIF('0_Indice_CAC'!$A:$A,Tabla18[[#This Row],[Mes]],'0_Indice_CAC'!$D:$D) -> 641.7 | T9: =Tabla18[[#This Row],[Debe]]-Tabla18[[#This Row],[Haber]] -> 641.7 | W9: =IFERROR(T9-IF(V9="",0,V9),0) -> 641.7 | X9: =ISNUMBER(MATCH(A9,'3_Control_Ppto'!$A$4:$A$70,0)) -> TRUE
A10: - | B10: - | C10: =+EOMONTH(Tabla18[[#This Row],[Fecha Asiento]],-1)+1 -> 45627 | D10: 52206 | E10: H. Arquitectura | F10: 45646 | G10: 202 | H10: Alejandro Ardiles - Agrimensor | J10: OPXX | K10: 5628 | L10: 110000 | M10: 0 | N10: DESA | O10: Desarrollos | P10: GDR | Q10: García del Río 3760 | R10: 0 | S10: =(Tabla18[[#This Row],[Debe]]-Tabla18[[#This Row],[Haber]])* SUMIF('0_Indice_CAC'!$A:$A,Tabla18[[#This Row],[Mes]],'0_Indice_CAC'!$D:$D) -> 110000 | T10: =Tabla18[[#This Row],[Debe]]-Tabla18[[#This Row],[Haber]] -> 110000 | W10: =IFERROR(T10-IF(V10="",0,V10),0) -> 110000 | X10: =ISNUMBER(MATCH(A10,'3_Control_Ppto'!$A$4:$A$70,0)) -> FALSE
A11: - | B11: - | C11: =+EOMONTH(Tabla18[[#This Row],[Fecha Asiento]],-1)+1 -> 45658 | D11: 52205 | E11: H. Escribanía | F11: 45664 | G11: 253 | H11: Pto. 530 - Varios | J11: OPXX | K11: 5680 | L11: 1600900 | M11: 0 | N11: DESA | O11: Desarrollos | P11: GDR | Q11: García del Río 3760 | R11: 0 | S11: =(Tabla18[[#This Row],[Debe]]-Tabla18[[#This Row],[Haber]])* SUMIF('0_Indice_CAC'!$A:$A,Tabla18[[#This Row],[Mes]],'0_Indice_CAC'!$D:$D) -> 1576659.3 | T11: =Tabla18[[#This Row],[Debe]]-Tabla18[[#This Row],[Haber]] -> 1600900 | W11: =IFERROR(T11-IF(V11="",0,V11),0) -> 1600900 | X11: =ISNUMBER(MATCH(A11,'3_Control_Ppto'!$A$4:$A$70,0)) -> FALSE
A12: - | B12: - | C12: =+EOMONTH(Tabla18[[#This Row],[Fecha Asiento]],-1)+1 -> 45658 | D12: 52205 | E12: H. Escribanía | F12: 45664 | G12: 253 | H12: Pto. 720 - Varios | J12: OPXX | K12: 5680 | L12: 552500 | M12: 0 | N12: DESA | O12: Desarrollos | P12: GDR | Q12: García del Río 3760 | R12: 0 | S12: =(Tabla18[[#This Row],[Debe]]-Tabla18[[#This Row],[Haber]])* SUMIF('0_Indice_CAC'!$A:$A,Tabla18[[#This Row],[Mes]],'0_Indice_CAC'!$D:$D) -> 544134.1 | T12: =Tabla18[[#This Row],[Debe]]-Tabla18[[#This Row],[Haber]] -> 552500 | W12: =IFERROR(T12-IF(V12="",0,V12),0) -> 552500 | X12: =ISNUMBER(MATCH(A12,'3_Control_Ppto'!$A$4:$A$70,0)) -> FALSE
A13: Movilidad | B13: MO | C13: =+EOMONTH(Tabla18[[#This Row],[Fecha Asiento]],-1)+1 -> 45658 | D13: 52302 | E13: Mov. Variables | F13: 45673 | G13: 322 | H13: Agustin Fletes | J13: OPXX | K13: 5754 | L13: 320000 | M13: 0 | N13: DESA | O13: Desarrollos | P13: GDR | Q13: García del Río 3760 | R13: 0 | S13: =(Tabla18[[#This Row],[Debe]]-Tabla18[[#This Row],[Haber]])* SUMIF('0_Indice_CAC'!$A:$A,Tabla18[[#This Row],[Mes]],'0_Indice_CAC'!$D:$D) -> 315154.59 | T13: =Tabla18[[#This Row],[Debe]]-Tabla18[[#This Row],[Haber]] -> 320000 | W13: =IFERROR(T13-IF(V13="",0,V13),0) -> 320000 | X13: =ISNUMBER(MATCH(A13,'3_Control_Ppto'!$A$4:$A$70,0)) -> TRUE
A14: Albañilería | B14: - | C14: =+EOMONTH(Tabla18[[#This Row],[Fecha Asiento]],-1)+1 -> 45658 | D14: 53009 | E14: Albañilería MO | F14: 45673 | G14: 321 | H14: 2Q 12-2024 - Almaraz Oscar | J14: OPXX | K14: 5753 | L14: 30100 | M14: 0 | N14: DESA | O14: Desarrollos | P14: GDR | Q14: García del Río 3760 | R14: 0 | S14: =(Tabla18[[#This Row],[Debe]]-Tabla18[[#This Row],[Haber]])* SUMIF('0_Indice_CAC'!$A:$A,Tabla18[[#This Row],[Mes]],'0_Indice_CAC'!$D:$D) -> 29644.229 | T14: =Tabla18[[#This Row],[Debe]]-Tabla18[[#This Row],[Haber]] -> 30100 | W14: =IFERROR(T14-IF(V14="",0,V14),0) -> 30100 | X14: =ISNUMBER(MATCH(A14,'3_Control_Ppto'!$A$4:$A$70,0)) -> TRUE
A15: Gastos Generales Obra | B15: - | C15: =+EOMONTH(Tabla18[[#This Row],[Fecha Asiento]],-1)+1 -> 45658 | D15: 53022 | E15: Gastos Generales | F15: 45674 | G15: 983 | H15: Encomienda Demolicion | J15: OPG | K15: 3544 | L15: 48000 | M15: 0 | N15: DESA | O15: Desarrollos | P15: GDR | Q15: García del Río 3760 | R15: 0 | S15: =(Tabla18[[#This Row],[Debe]]-Tabla18[[#This Row],[Haber]])* SUMIF('0_Indice_CAC'!$A:$A,Tabla18[[#This Row],[Mes]],'0_Indice_CAC'!$D:$D) -> 47273.189 | T15: =Tabla18[[#This Row],[Debe]]-Tabla18[[#This Row],[Haber]] -> 48000 | W15: =IFERROR(T15-IF(V15="",0,V15),0) -> 48000 | X15: =ISNUMBER(MATCH(A15,'3_Control_Ppto'!$A$4:$A$70,0)) -> TRUE
A16: - | B16: - | C16: =+EOMONTH(Tabla18[[#This Row],[Fecha Asiento]],-1)+1 -> 45658 | D16: 52002 | E16: Edenor | F16: 45679 | G16: 340 | H16: EDENOR - Fact. 45239049 | J16: OPXX | K16: 5772 | L16: 64900 | M16: 0 | N16: DESA | O16: Desarrollos | P16: GDR | Q16: García del Río 3760 | R16: 0 | S16: =(Tabla18[[#This Row],[Debe]]-Tabla18[[#This Row],[Haber]])* SUMIF('0_Indice_CAC'!$A:$A,Tabla18[[#This Row],[Mes]],'0_Indice_CAC'!$D:$D) -> 63917.291 | T16: =Tabla18[[#This Row],[Debe]]-Tabla18[[#This Row],[Haber]] -> 64900 | W16: =IFERROR(T16-IF(V16="",0,V16),0) -> 64900 | X16: =ISNUMBER(MATCH(A16,'3_Control_Ppto'!$A$4:$A$70,0)) -> FALSE
A17: - | B17: - | C17: =+EOMONTH(Tabla18[[#This Row],[Fecha Asiento]],-1)+1 -> 45658 | D17: 52002 | E17: Edenor | F17: 45680 | G17: 274 | H17: Deuda Edenor | J17: OPXX | K17: 5702 | L17: 64897 | M17: 0 | N17: DESA | O17: Desarrollos | P17: GDR | Q17: García del Río 3760 | R17: 0 | S17: =(Tabla18[[#This Row],[Debe]]-Tabla18[[#This Row],[Haber]])* SUMIF('0_Indice_CAC'!$A:$A,Tabla18[[#This Row],[Mes]],'0_Indice_CAC'!$D:$D) -> 63914.336 | T17: =Tabla18[[#This Row],[Debe]]-Tabla18[[#This Row],[Haber]] -> 64897 | W17: =IFERROR(T17-IF(V17="",0,V17),0) -> 64897 | X17: =ISNUMBER(MATCH(A17,'3_Control_Ppto'!$A$4:$A$70,0)) -> FALSE
A18: Seguridad e Higiene | B18: MO | C18: =+EOMONTH(Tabla18[[#This Row],[Fecha Asiento]],-1)+1 -> 45689 | D18: 52204 | E18: H. Seguridad e Higiene | F18: 45691 | G18: 1089 | H18: Honorarios Seguridad e Higiene | I18: Petrini David Osvaldo | J18: FCA3 | K18: 300001153 | L18: 240000 | M18: 0 | N18: DESA | O18: Desarrollos | P18: GDR | Q18: García del Río 3760 | R18: 0 | S18: =(Tabla18[[#This Row],[Debe]]-Tabla18[[#This Row],[Haber]])* SUMIF('0_Indice_CAC'!$A:$A,Tabla18[[#This Row],[Mes]],'0_Indice_CAC'!$D:$D) -> 232490.73 | T18: =Tabla18[[#This Row],[Debe]]-Tabla18[[#This Row],[Haber]] -> 240000 | W18: =IFERROR(T18-IF(V18="",0,V18),0) -> 240000 | X18: =ISNUMBER(MATCH(A18,'3_Control_Ppto'!$A$4:$A$70,0)) -> TRUE
A19: Gastos Generales Obra | B19: - | C19: =+EOMONTH(Tabla18[[#This Row],[Fecha Asiento]],-1)+1 -> 45689 | D19: 53022 | E19: Gastos Generales | F19: 45694 | G19: 5720 | H19: GASTOS GENERALES - triunfo seg | I19: triunfo seguros | J19: FCA3 | K19: 100019779 | L19: 544061.54 | M19: 0 | N19: DESA | O19: Desarrollos | P19: GDR | Q19: García del Río 3760 | R19: 0 | S19: =(Tabla18[[#This Row],[Debe]]-Tabla18[[#This Row],[Haber]])* SUMIF('0_Indice_CAC'!$A:$A,Tabla18[[#This Row],[Mes]],'0_Indice_CAC'!$D:$D) -> 527038.6 | T19: =Tabla18[[#This Row],[Debe]]-Tabla18[[#This Row],[Haber]] -> 544061.54 | W19: =IFERROR(T19-IF(V19="",0,V19),0) -> 544061.54 | X19: =ISNUMBER(MATCH(A19,'3_Control_Ppto'!$A$4:$A$70,0)) -> TRUE
A20: Gastos Generales Obra | B20: - | C20: =+EOMONTH(Tabla18[[#This Row],[Fecha Asiento]],-1)+1 -> 45689 | D20: 53022 | E20: Gastos Generales | F20: 45694 | G20: 5720 | H20: GASTOS GENERALES - triunfo seg | I20: triunfo seguros | J20: FCA3 | K20: 100019779 | L20: 5440.62 | M20: 0 | N20: DESA | O20: Desarrollos | P20: GDR | Q20: García del Río 3760 | R20: 0 | S20: =(Tabla18[[#This Row],[Debe]]-Tabla18[[#This Row],[Haber]])* SUMIF('0_Indice_CAC'!$A:$A,Tabla18[[#This Row],[Mes]],'0_Indice_CAC'!$D:$D) -> 5270.3904 | T20: =Tabla18[[#This Row],[Debe]]-Tabla18[[#This Row],[Haber]] -> 5440.62 | W20: =IFERROR(T20-IF(V20="",0,V20),0) -> 5440.62 | X20: =ISNUMBER(MATCH(A20,'3_Control_Ppto'!$A$4:$A$70,0)) -> TRUE
A21: Gastos Generales Obra | B21: - | C21: =+EOMONTH(Tabla18[[#This Row],[Fecha Asiento]],-1)+1 -> 45689 | D21: 53022 | E21: Gastos Generales | F21: 45694 | G21: 5720 | H21: GASTOS GENERALES - triunfo seg | I21: triunfo seguros | J21: FCA3 | K21: 100019779 | L21: 6529.09 | M21: 0 | N21: DESA | O21: Desarrollos | P21: GDR | Q21: García del Río 3760 | R21: 0 | S21: =(Tabla18[[#This Row],[Debe]]-Tabla18[[#This Row],[Haber]])* SUMIF('0_Indice_CAC'!$A:$A,Tabla18[[#This Row],[Mes]],'0_Indice_CAC'!$D:$D) -> 6324.8037 | T21: =Tabla18[[#This Row],[Debe]]-Tabla18[[#This Row],[Haber]] -> 6529.09 | W21: =IFERROR(T21-IF(V21="",0,V21),0) -> 6529.09 | X21: =ISNUMBER(MATCH(A21,'3_Control_Ppto'!$A$4:$A$70,0)) -> TRUE
A22: Gastos Generales Obra | B22: - | C22: =+EOMONTH(Tabla18[[#This Row],[Fecha Asiento]],-1)+1 -> 45689 | D22: 53022 | E22: Gastos Generales | F22: 45694 | G22: 5720 | H22: GASTOS GENERALES - triunfo seg | I22: triunfo seguros | J22: FCA3 | K22: 100019779 | L22: 15951.1 | M22: 0 | N22: DESA | O22: Desarrollos | P22: GDR | Q22: García del Río 3760 | R22: 0 | S22: =(Tabla18[[#This Row],[Debe]]-Tabla18[[#This Row],[Haber]])* SUMIF('0_Indice_CAC'!$A:$A,Tabla18[[#This Row],[Mes]],'0_Indice_CAC'!$D:$D) -> 15452.012 | T22: =Tabla18[[#This Row],[Debe]]-Tabla18[[#This Row],[Haber]] -> 15951.1 | W22: =IFERROR(T22-IF(V22="",0,V22),0) -> 15951.1 | X22: =ISNUMBER(MATCH(A22,'3_Control_Ppto'!$A$4:$A$70,0)) -> TRUE
A23: Gastos Generales Obra | B23: - | C23: =+EOMONTH(Tabla18[[#This Row],[Fecha Asiento]],-1)+1 -> 45689 | D23: 53022 | E23: Gastos Generales | F23: 45694 | G23: 5720 | H23: GASTOS GENERALES - triunfo seg | I23: triunfo seguros | J23: FCA3 | K23: 100019779 | L23: 377415 | M23: 0 | N23: DESA | O23: Desarrollos | P23: GDR | Q23: García del Río 3760 | R23: 0 | S23: =(Tabla18[[#This Row],[Debe]]-Tabla18[[#This Row],[Haber]])* SUMIF('0_Indice_CAC'!$A:$A,Tabla18[[#This Row],[Mes]],'0_Indice_CAC'!$D:$D) -> 365606.2 | T23: =Tabla18[[#This Row],[Debe]]-Tabla18[[#This Row],[Haber]] -> 377415 | W23: =IFERROR(T23-IF(V23="",0,V23),0) -> 377415 | X23: =ISNUMBER(MATCH(A23,'3_Control_Ppto'!$A$4:$A$70,0)) -> TRUE
A24: Gastos Generales Obra | B24: MO | C24: =+EOMONTH(Tabla18[[#This Row],[Fecha Asiento]],-1)+1 -> 45689 | D24: 53022 | E24: Gastos Generales | F24: 45701 | G24: 1276 | H24: Baño Portatil - ECOBAT SRL | I24: ECOBAT SRL | J24: FCA3 | K24: 300021956 | L24: 80000 | M24: 0 | N24: DESA | O24: Desarrollos | P24: GDR | Q24: García del Río 3760 | R24: 0 | S24: =(Tabla18[[#This Row],[Debe]]-Tabla18[[#This Row],[Haber]])* SUMIF('0_Indice_CAC'!$A:$A,Tabla18[[#This Row],[Mes]],'0_Indice_CAC'!$D:$D) -> 77496.909 | T24: =Tabla18[[#This Row],[Debe]]-Tabla18[[#This Row],[Haber]] -> 80000 | W24: =IFERROR(T24-IF(V24="",0,V24),0) -> 80000 | X24: =ISNUMBER(MATCH(A24,'3_Control_Ppto'!$A$4:$A$70,0)) -> TRUE
A25: Gastos Generales Obra | B25: MO | C25: =+EOMONTH(Tabla18[[#This Row],[Fecha Asiento]],-1)+1 -> 45689 | D25: 53022 | E25: Gastos Generales | F25: 45701 | G25: 1276 | H25: Transporte Baño - ECOBAT SRL | I25: ECOBAT SRL | J25: FCA3 | K25: 300021956 | L25: 10000 | M25: 0 | N25: DESA | O25: Desarrollos | P25: GDR | Q25: García del Río 3760 | R25: 0 | S25: =(Tabla18[[#This Row],[Debe]]-Tabla18[[#This Row],[Haber]])* SUMIF('0_Indice_CAC'!$A:$A,Tabla18[[#This Row],[Mes]],'0_Indice_CAC'!$D:$D) -> 9687.1136 | T25: =Tabla18[[#This Row],[Debe]]-Tabla18[[#This Row],[Haber]] -> 10000 | W25: =IFERROR(T25-IF(V25="",0,V25),0) -> 10000 | X25: =ISNUMBER(MATCH(A25,'3_Control_Ppto'!$A$4:$A$70,0)) -> TRUE
A26: Electricidad | B26: MT | C26: =+EOMONTH(Tabla18[[#This Row],[Fecha Asiento]],-1)+1 -> 45689 | D26: 53019 | E26: Eléctrico MT | F26: 45702 | G26: 1735 | H26: ELECTRICO MT - Casa Castelao S | I26: Casa Castelao S.A. | J26: FCA3 | K26: 300004447 | L26: 1172127.4 | M26: 0 | N26: DESA | O26: Desarrollos | P26: GDR | Q26: García del Río 3760 | R26: 0 | S26: =(Tabla18[[#This Row],[Debe]]-Tabla18[[#This Row],[Haber]])* SUMIF('0_Indice_CAC'!$A:$A,Tabla18[[#This Row],[Mes]],'0_Indice_CAC'!$D:$D) -> 1135453.2 | T26: =Tabla18[[#This Row],[Debe]]-Tabla18[[#This Row],[Haber]] -> 1172127.4 | W26: =IFERROR(T26-IF(V26="",0,V26),0) -> 1172127.4 | X26: =ISNUMBER(MATCH(A26,'3_Control_Ppto'!$A$4:$A$70,0)) -> TRUE
A27: Electricidad | B27: MT | C27: =+EOMONTH(Tabla18[[#This Row],[Fecha Asiento]],-1)+1 -> 45689 | D27: 53019 | E27: Eléctrico MT | F27: 45702 | G27: 1735 | H27: ELECTRICO MT - Casa Castelao S | I27: Casa Castelao S.A. | J27: FCA3 | K27: 300004447 | L27: 11648.13 | M27: 0 | N27: DESA | O27: Desarrollos | P27: GDR | Q27: García del Río 3760 | R27: 0 | S27: =(Tabla18[[#This Row],[Debe]]-Tabla18[[#This Row],[Haber]])* SUMIF('0_Indice_CAC'!$A:$A,Tabla18[[#This Row],[Mes]],'0_Indice_CAC'!$D:$D) -> 11283.676 | T27: =Tabla18[[#This Row],[Debe]]-Tabla18[[#This Row],[Haber]] -> 11648.13 | W27: =IFERROR(T27-IF(V27="",0,V27),0) -> 11648.13 | X27: =ISNUMBER(MATCH(A27,'3_Control_Ppto'!$A$4:$A$70,0)) -> TRUE
A28: Preliminar | B28: MT | C28: =+EOMONTH(Tabla18[[#This Row],[Fecha Asiento]],-1)+1 -> 45689 | D28: 53001 | E28: Preliminares | F28: 45705 | G28: 1462 | H28: CLAVO - HOVSEPIAN HNOS. SH | I28: HOVSEPIAN HNOS. SH | J28: FCA3 | K28: 600010802 | L28: 4462.81 | M28: 0 | N28: DESA | O28: Desarrollos | P28: GDR | Q28: García del Río 3760 | R28: 0 | S28: =(Tabla18[[#This Row],[Debe]]-Tabla18[[#This Row],[Haber]])* SUMIF('0_Indice_CAC'!$A:$A,Tabla18[[#This Row],[Mes]],'0_Indice_CAC'!$D:$D) -> 4323.1748 | T28: =Tabla18[[#This Row],[Debe]]-Tabla18[[#This Row],[Haber]] -> 4462.81 | W28: =IFERROR(T28-IF(V28="",0,V28),0) -> 4462.81 | X28: =ISNUMBER(MATCH(A28,'3_Control_Ppto'!$A$4:$A$70,0)) -> TRUE
A29: Albañilería | B29: MT | C29: =+EOMONTH(Tabla18[[#This Row],[Fecha Asiento]],-1)+1 -> 45689 | D29: 53023 | E29: Varios Ferreteria | F29: 45705 | G29: 1155 | H29: Varios Ferreteria | J29: OPXX | K29: 6569 | L29: 5400 | M29: 0 | N29: DESA | O29: Desarrollos | P29: GDR | Q29: García del Río 3760 | R29: 0 | S29: =(Tabla18[[#This Row],[Debe]]-Tabla18[[#This Row],[Haber]])* SUMIF('0_Indice_CAC'!$A:$A,Tabla18[[#This Row],[Mes]],'0_Indice_CAC'!$D:$D) -> 5231.0414 | T29: =Tabla18[[#This Row],[Debe]]-Tabla18[[#This Row],[Haber]] -> 5400 | W29: =IFERROR(T29-IF(V29="",0,V29),0) -> 5400 | X29: =ISNUMBER(MATCH(A29,'3_Control_Ppto'!$A$4:$A$70,0)) -> TRUE
A30: - | B30: - | C30: =+EOMONTH(Tabla18[[#This Row],[Fecha Asiento]],-1)+1 -> 45689 | D30: 5108 | E30: Gastos en personal | F30: 45706 | G30: 1305 | H30: Gastos en Personales - Abrafer | I30: Abrafer S.R.L. | J30: FCA3 | K30: 1000192524 | L30: 138171.31 | M30: 0 | N30: DESA | O30: Desarrollos | P30: GDR | Q30: García del Río 3760 | R30: 0 | S30: =(Tabla18[[#This Row],[Debe]]-Tabla18[[#This Row],[Haber]])* SUMIF('0_Indice_CAC'!$A:$A,Tabla18[[#This Row],[Mes]],'0_Indice_CAC'!$D:$D) -> 133848.12 | T30: =Tabla18[[#This Row],[Debe]]-Tabla18[[#This Row],[Haber]] -> 138171.31 | W30: =IFERROR(T30-IF(V30="",0,V30),0) -> 138171.31 | X30: =ISNUMBER(MATCH(A30,'3_Control_Ppto'!$A$4:$A$70,0)) -> FALSE
A31: Hormigón | B31: MO | C31: =+EOMONTH(Tabla18[[#This Row],[Fecha Asiento]],-1)+1 -> 45689 | D31: 53005 | E31: Homigón MO | F31: 45706 | G31: 533 | H31: Anclajes Cima - Anticipo 30% | J31: OPXX | K31: 5959 | L31: 911200 | M31: 0 | N31: DESA | O31: Desarrollos | P31: GDR | Q31: García del Río 3760 | R31: 0 | S31: =(Tabla18[[#This Row],[Debe]]-Tabla18[[#This Row],[Haber]])* SUMIF('0_Indice_CAC'!$A:$A,Tabla18[[#This Row],[Mes]],'0_Indice_CAC'!$D:$D) -> 882689.79 | T31: =Tabla18[[#This Row],[Debe]]-Tabla18[[#This Row],[Haber]] -> 911200 | U31: SC-003 | W31: =IFERROR(T31-IF(V31="",0,V31),0) -> 911200 | X31: =ISNUMBER(MATCH(A31,'3_Control_Ppto'!$A$4:$A$70,0)) -> TRUE
A32: Albañilería | B32: MT | C32: =+EOMONTH(Tabla18[[#This Row],[Fecha Asiento]],-1)+1 -> 45689 | D32: 53023 | E32: Varios Ferreteria | F32: 45706 | G32: 1305 | H32: Varios Ferreteria - Abrafer S. | I32: Abrafer S.R.L. | J32: FCA3 | K32: 1000192524 | L32: 824299.87 | M32: 0 | N32: DESA | O32: Desarrollos | P32: GDR | Q32: García del Río 3760 | R32: 0 | S32: =(Tabla18[[#This Row],[Debe]]-Tabla18[[#This Row],[Haber]])* SUMIF('0_Indice_CAC'!$A:$A,Tabla18[[#This Row],[Mes]],'0_Indice_CAC'!$D:$D) -> 798508.65 | T32: =Tabla18[[#This Row],[Debe]]-Tabla18[[#This Row],[Haber]] -> 824299.87 | W32: =IFERROR(T32-IF(V32="",0,V32),0) -> 824299.87 | X32: =ISNUMBER(MATCH(A32,'3_Control_Ppto'!$A$4:$A$70,0)) -> TRUE
A33: Seguridad e Higiene | B33: MO | C33: =+EOMONTH(Tabla18[[#This Row],[Fecha Asiento]],-1)+1 -> 45689 | D33: 53026 | E33: Seguridad e Higiene | F33: 45706 | G33: 1305 | H33: Seguridad e Higiene - Abrafer | I33: Abrafer S.R.L. | J33: FCA3 | K33: 1000192524 | L33: 2835 | M33: 0 | N33: DESA | O33: Desarrollos | P33: GDR | Q33: García del Río 3760 | R33: 0 | S33: =(Tabla18[[#This Row],[Debe]]-Tabla18[[#This Row],[Haber]])* SUMIF('0_Indice_CAC'!$A:$A,Tabla18[[#This Row],[Mes]],'0_Indice_CAC'!$D:$D) -> 2746.2967 | T33: =Tabla18[[#This Row],[Debe]]-Tabla18[[#This Row],[Haber]] -> 2835 | W33: =IFERROR(T33-IF(V33="",0,V33),0) -> 2835 | X33: =ISNUMBER(MATCH(A33,'3_Control_Ppto'!$A$4:$A$70,0)) -> TRUE
A34: Movilidad | B34: MO | C34: =+EOMONTH(Tabla18[[#This Row],[Fecha Asiento]],-1)+1 -> 45689 | D34: 52103 | E34: Supermercados | F34: 45707 | G34: 1156 | H34: Supermercados | J34: OPXX | K34: 6570 | L34: 2495 | M34: 0 | N34: DESA | O34: Desarrollos | P34: GDR | Q34: García del Río 3760 | R34: 0 | S34: =(Tabla18[[#This Row],[Debe]]-Tabla18[[#This Row],[Haber]])* SUMIF('0_Indice_CAC'!$A:$A,Tabla18[[#This Row],[Mes]],'0_Indice_CAC'!$D:$D) -> 2416.9348 | T34: =Tabla18[[#This Row],[Debe]]-Tabla18[[#This Row],[Haber]] -> 2495 | W34: =IFERROR(T34-IF(V34="",0,V34),0) -> 2495 | X34: =ISNUMBER(MATCH(A34,'3_Control_Ppto'!$A$4:$A$70,0)) -> TRUE
A35: Movilidad | B35: MO | C35: =+EOMONTH(Tabla18[[#This Row],[Fecha Asiento]],-1)+1 -> 45689 | D35: 52103 | E35: Supermercados | F35: 45707 | G35: 1465 | H35: Supermercado - Dia Argentina S | I35: Dia Argentina S.A. | J35: FCA3 | K35: 1165500001127 | L35: 2061.98 | M35: 0 | N35: DESA | O35: Desarrollos | P35: GDR | Q35: García del Río 3760 | R35: 0 | S35: =(Tabla18[[#This Row],[Debe]]-Tabla18[[#This Row],[Haber]])* SUMIF('0_Indice_CAC'!$A:$A,Tabla18[[#This Row],[Mes]],'0_Indice_CAC'!$D:$D) -> 1997.4635 | T35: =Tabla18[[#This Row],[Debe]]-Tabla18[[#This Row],[Haber]] -> 2061.98 | W35: =IFERROR(T35-IF(V35="",0,V35),0) -> 2061.98 | X35: =ISNUMBER(MATCH(A35,'3_Control_Ppto'!$A$4:$A$70,0)) -> TRUE
A36: Preliminar | B36: MT | C36: =+EOMONTH(Tabla18[[#This Row],[Fecha Asiento]],-1)+1 -> 45689 | D36: 53001 | E36: Preliminares | F36: 45707 | G36: 1463 | H36: preliminares - LUNA FERNANDO | I36: LUNA FERNANDO | J36: FCA3 | K36: 500000403 | L36: 23307 | M36: 0 | N36: DESA | O36: Desarrollos | P36: GDR | Q36: García del Río 3760 | R36: 0 | S36: =(Tabla18[[#This Row],[Debe]]-Tabla18[[#This Row],[Haber]])* SUMIF('0_Indice_CAC'!$A:$A,Tabla18[[#This Row],[Mes]],'0_Indice_CAC'!$D:$D) -> 22577.756 | T36: =Tabla18[[#This Row],[Debe]]-Tabla18[[#This Row],[Haber]] -> 23307 | W36: =IFERROR(T36-IF(V36="",0,V36),0) -> 23307 | X36: =ISNUMBER(MATCH(A36,'3_Control_Ppto'!$A$4:$A$70,0)) -> TRUE
A37: Preliminar | B37: MT | C37: =+EOMONTH(Tabla18[[#This Row],[Fecha Asiento]],-1)+1 -> 45689 | D37: 53001 | E37: Preliminares | F37: 45707 | G37: 1464 | H37: preliminares - HOVSEPIAN HNOS. | I37: HOVSEPIAN HNOS. SH | J37: FCA3 | K37: 600010818 | L37: 17851.24 | M37: 0 | N37: DESA | O37: Desarrollos | P37: GDR | Q37: García del Río 3760 | R37: 0 | S37: =(Tabla18[[#This Row],[Debe]]-Tabla18[[#This Row],[Haber]])* SUMIF('0_Indice_CAC'!$A:$A,Tabla18[[#This Row],[Mes]],'0_Indice_CAC'!$D:$D) -> 17292.699 | T37: =Tabla18[[#This Row],[Debe]]-Tabla18[[#This Row],[Haber]] -> 17851.24 | W37: =IFERROR(T37-IF(V37="",0,V37),0) -> 17851.24 | X37: =ISNUMBER(MATCH(A37,'3_Control_Ppto'!$A$4:$A$70,0)) -> TRUE
A38: Albañilería | B38: MT | C38: =+EOMONTH(Tabla18[[#This Row],[Fecha Asiento]],-1)+1 -> 45689 | D38: 53023 | E38: Varios Ferreteria | F38: 45707 | G38: 1157 | H38: Varios Ferreteria | J38: OPXX | K38: 6571 | L38: 21600 | M38: 0 | N38: DESA | O38: Desarrollos | P38: GDR | Q38: García del Río 3760 | R38: 0 | S38: =(Tabla18[[#This Row],[Debe]]-Tabla18[[#This Row],[Haber]])* SUMIF('0_Indice_CAC'!$A:$A,Tabla18[[#This Row],[Mes]],'0_Indice_CAC'!$D:$D) -> 20924.165 | T38: =Tabla18[[#This Row],[Debe]]-Tabla18[[#This Row],[Haber]] -> 21600 | W38: =IFERROR(T38-IF(V38="",0,V38),0) -> 21600 | X38: =ISNUMBER(MATCH(A38,'3_Control_Ppto'!$A$4:$A$70,0)) -> TRUE
A39: Albañilería | B39: MT | C39: =+EOMONTH(Tabla18[[#This Row],[Fecha Asiento]],-1)+1 -> 45689 | D39: 53023 | E39: Varios Ferreteria | F39: 45707 | G39: 1158 | H39: Varios Ferreteria | J39: OPXX | K39: 6572 | L39: 28201.47 | M39: 0 | N39: DESA | O39: Desarrollos | P39: GDR | Q39: García del Río 3760 | R39: 0 | S39: =(Tabla18[[#This Row],[Debe]]-Tabla18[[#This Row],[Haber]])* SUMIF('0_Indice_CAC'!$A:$A,Tabla18[[#This Row],[Mes]],'0_Indice_CAC'!$D:$D) -> 27319.084 | T39: =Tabla18[[#This Row],[Debe]]-Tabla18[[#This Row],[Haber]] -> 28201.47 | W39: =IFERROR(T39-IF(V39="",0,V39),0) -> 28201.47 | X39: =ISNUMBER(MATCH(A39,'3_Control_Ppto'!$A$4:$A$70,0)) -> TRUE
A40: Movilidad | B40: MO | C40: =+EOMONTH(Tabla18[[#This Row],[Fecha Asiento]],-1)+1 -> 45689 | D40: 52103 | E40: Supermercados | F40: 45708 | G40: 1159 | H40: Supermercados | J40: OPXX | K40: 6573 | L40: 2495 | M40: 0 | N40: DESA | O40: Desarrollos | P40: GDR | Q40: García del Río 3760 | R40: 0 | S40: =(Tabla18[[#This Row],[Debe]]-Tabla18[[#This Row],[Haber]])* SUMIF('0_Indice_CAC'!$A:$A,Tabla18[[#This Row],[Mes]],'0_Indice_CAC'!$D:$D) -> 2416.9348 | T40: =Tabla18[[#This Row],[Debe]]-Tabla18[[#This Row],[Haber]] -> 2495 | W40: =IFERROR(T40-IF(V40="",0,V40),0) -> 2495 | X40: =ISNUMBER(MATCH(A40,'3_Control_Ppto'!$A$4:$A$70,0)) -> TRUE
A41: Movilidad | B41: MO | C41: =+EOMONTH(Tabla18[[#This Row],[Fecha Asiento]],-1)+1 -> 45689 | D41: 52103 | E41: Supermercados | F41: 45708 | G41: 1466 | H41: Supermercado - Dia Argentina S | I41: Dia Argentina S.A. | J41: FCA3 | K41: 1165500001129 | L41: 2061.98 | M41: 0 | N41: DESA | O41: Desarrollos | P41: GDR | Q41: García del Río 3760 | R41: 0 | S41: =(Tabla18[[#This Row],[Debe]]-Tabla18[[#This Row],[Haber]])* SUMIF('0_Indice_CAC'!$A:$A,Tabla18[[#This Row],[Mes]],'0_Indice_CAC'!$D:$D) -> 1997.4635 | T41: =Tabla18[[#This Row],[Debe]]-Tabla18[[#This Row],[Haber]] -> 2061.98 | W41: =IFERROR(T41-IF(V41="",0,V41),0) -> 2061.98 | X41: =ISNUMBER(MATCH(A41,'3_Control_Ppto'!$A$4:$A$70,0)) -> TRUE
A42: Preliminar | B42: MT | C42: =+EOMONTH(Tabla18[[#This Row],[Fecha Asiento]],-1)+1 -> 45689 | D42: 53001 | E42: Preliminares | F42: 45708 | G42: 1467 | H42: preliminares - HOVSEPIAN HNOS. | I42: HOVSEPIAN HNOS. SH | J42: FCA3 | K42: 600010837 | L42: 3553.72 | M42: 0 | N42: DESA | O42: Desarrollos | P42: GDR | Q42: García del Río 3760 | R42: 0 | S42: =(Tabla18[[#This Row],[Debe]]-Tabla18[[#This Row],[Haber]])* SUMIF('0_Indice_CAC'!$A:$A,Tabla18[[#This Row],[Mes]],'0_Indice_CAC'!$D:$D) -> 3442.5289 | T42: =Tabla18[[#This Row],[Debe]]-Tabla18[[#This Row],[Haber]] -> 3553.72 | W42: =IFERROR(T42-IF(V42="",0,V42),0) -> 3553.72 | X42: =ISNUMBER(MATCH(A42,'3_Control_Ppto'!$A$4:$A$70,0)) -> TRUE
A43: Albañilería | B43: - | C43: =+EOMONTH(Tabla18[[#This Row],[Fecha Asiento]],-1)+1 -> 45689 | D43: 53009 | E43: Albañilería MO | F43: 45708 | G43: 475 | H43: 2Q 02-2025 - Adelanto - Godoy | J43: OPXX | K43: 5901 | L43: 100000 | M43: 0 | N43: DESA | O43: Desarrollos | P43: GDR | Q43: García del Río 3760 | R43: 0 | S43: =(Tabla18[[#This Row],[Debe]]-Tabla18[[#This Row],[Haber]])* SUMIF('0_Indice_CAC'!$A:$A,Tabla18[[#This Row],[Mes]],'0_Indice_CAC'!$D:$D) -> 96871.136 | T43: =Tabla18[[#This Row],[Debe]]-Tabla18[[#This Row],[Haber]] -> 100000 | W43: =IFERROR(T43-IF(V43="",0,V43),0) -> 100000 | X43: =ISNUMBER(MATCH(A43,'3_Control_Ppto'!$A$4:$A$70,0)) -> TRUE
A44: Albañilería | B44: MT | C44: =+EOMONTH(Tabla18[[#This Row],[Fecha Asiento]],-1)+1 -> 45689 | D44: 53023 | E44: Varios Ferreteria | F44: 45708 | G44: 1160 | H44: Varios Ferreteria | J44: OPXX | K44: 6574 | L44: 4300 | M44: 0 | N44: DESA | O44: Desarrollos | P44: GDR | Q44: García del Río 3760 | R44: 0 | S44: =(Tabla18[[#This Row],[Debe]]-Tabla18[[#This Row],[Haber]])* SUMIF('0_Indice_CAC'!$A:$A,Tabla18[[#This Row],[Mes]],'0_Indice_CAC'!$D:$D) -> 4165.4589 | T44: =Tabla18[[#This Row],[Debe]]-Tabla18[[#This Row],[Haber]] -> 4300 | W44: =IFERROR(T44-IF(V44="",0,V44),0) -> 4300 | X44: =ISNUMBER(MATCH(A44,'3_Control_Ppto'!$A$4:$A$70,0)) -> TRUE
A45: Preliminar | B45: MT | C45: =+EOMONTH(Tabla18[[#This Row],[Fecha Asiento]],-1)+1 -> 45689 | D45: 53001 | E45: Preliminares | F45: 45709 | G45: 1163 | H45: Preliminares | J45: OPXX | K45: 6577 | L45: 9000 | M45: 0 | N45: DESA | O45: Desarrollos | P45: GDR | Q45: García del Río 3760 | R45: 0 | S45: =(Tabla18[[#This Row],[Debe]]-Tabla18[[#This Row],[Haber]])* SUMIF('0_Indice_CAC'!$A:$A,Tabla18[[#This Row],[Mes]],'0_Indice_CAC'!$D:$D) -> 8718.4023 | T45: =Tabla18[[#This Row],[Debe]]-Tabla18[[#This Row],[Haber]] -> 9000 | W45: =IFERROR(T45-IF(V45="",0,V45),0) -> 9000 | X45: =ISNUMBER(MATCH(A45,'3_Control_Ppto'!$A$4:$A$70,0)) -> TRUE
A46: Preliminar | B46: MT | C46: =+EOMONTH(Tabla18[[#This Row],[Fecha Asiento]],-1)+1 -> 45689 | D46: 53001 | E46: Preliminares | F46: 45709 | G46: 1164 | H46: Preliminares | J46: OPXX | K46: 6578 | L46: 7600.01 | M46: 0 | N46: DESA | O46: Desarrollos | P46: GDR | Q46: García del Río 3760 | R46: 0 | S46: =(Tabla18[[#This Row],[Debe]]-Tabla18[[#This Row],[Haber]])* SUMIF('0_Indice_CAC'!$A:$A,Tabla18[[#This Row],[Mes]],'0_Indice_CAC'!$D:$D) -> 7362.216 | T46: =Tabla18[[#This Row],[Debe]]-Tabla18[[#This Row],[Haber]] -> 7600.01 | W46: =IFERROR(T46-IF(V46="",0,V46),0) -> 7600.01 | X46: =ISNUMBER(MATCH(A46,'3_Control_Ppto'!$A$4:$A$70,0)) -> TRUE
A47: Preliminar | B47: MT | C47: =+EOMONTH(Tabla18[[#This Row],[Fecha Asiento]],-1)+1 -> 45689 | D47: 53001 | E47: Preliminares | F47: 45709 | G47: 1468 | H47: BISAGRA - HERRAJES TRONADOR SR | I47: HERRAJES TRONADOR SRL | J47: FCA3 | K47: 500000619 | L47: 7438.02 | M47: 0 | N47: DESA | O47: Desarrollos | P47: GDR | Q47: García del Río 3760 | R47: 0 | S47: =(Tabla18[[#This Row],[Debe]]-Tabla18[[#This Row],[Haber]])* SUMIF('0_Indice_CAC'!$A:$A,Tabla18[[#This Row],[Mes]],'0_Indice_CAC'!$D:$D) -> 7205.2945 | T47: =Tabla18[[#This Row],[Debe]]-Tabla18[[#This Row],[Haber]] -> 7438.02 | W47: =IFERROR(T47-IF(V47="",0,V47),0) -> 7438.02 | X47: =ISNUMBER(MATCH(A47,'3_Control_Ppto'!$A$4:$A$70,0)) -> TRUE
A48: Preliminar | B48: MT | C48: =+EOMONTH(Tabla18[[#This Row],[Fecha Asiento]],-1)+1 -> 45689 | D48: 53001 | E48: Preliminares | F48: 45709 | G48: 1470 | H48: preliminares - Denegri Gustavo | I48: Denegri Gustavo Ariel Jesus | J48: FCA3 | K48: 300005764 | L48: 5355.37 | M48: 0 | N48: DESA | O48: Desarrollos | P48: GDR | Q48: García del Río 3760 | R48: 0 | S48: =(Tabla18[[#This Row],[Debe]]-Tabla18[[#This Row],[Haber]])* SUMIF('0_Indice_CAC'!$A:$A,Tabla18[[#This Row],[Mes]],'0_Indice_CAC'!$D:$D) -> 5187.8078 | T48: =Tabla18[[#This Row],[Debe]]-Tabla18[[#This Row],[Haber]] -> 5355.37 | W48: =IFERROR(T48-IF(V48="",0,V48),0) -> 5355.37 | X48: =ISNUMBER(MATCH(A48,'3_Control_Ppto'!$A$4:$A$70,0)) -> TRUE
A49: Albañilería | B49: MT | C49: =+EOMONTH(Tabla18[[#This Row],[Fecha Asiento]],-1)+1 -> 45689 | D49: 53008 | E49: Albañilería MT | F49: 45709 | G49: 1469 | H49: ALBAÑILERIA MT - HOVSEPIAN HNO | I49: HOVSEPIAN HNOS. SH | J49: FCA3 | K49: 600010845 | L49: 7479.36 | M49: 0 | N49: DESA | O49: Desarrollos | P49: GDR | Q49: García del Río 3760 | R49: 0 | S49: =(Tabla18[[#This Row],[Debe]]-Tabla18[[#This Row],[Haber]])* SUMIF('0_Indice_CAC'!$A:$A,Tabla18[[#This Row],[Mes]],'0_Indice_CAC'!$D:$D) -> 7245.341 | T49: =Tabla18[[#This Row],[Debe]]-Tabla18[[#This Row],[Haber]] -> 7479.36 | W49: =IFERROR(T49-IF(V49="",0,V49),0) -> 7479.36 | X49: =ISNUMBER(MATCH(A49,'3_Control_Ppto'!$A$4:$A$70,0)) -> TRUE
A50: Albañilería | B50: MT | C50: =+EOMONTH(Tabla18[[#This Row],[Fecha Asiento]],-1)+1 -> 45689 | D50: 53023 | E50: Varios Ferreteria | F50: 45709 | G50: 1161 | H50: Varios Ferreteria | J50: OPXX | K50: 6575 | L50: 6480 | M50: 0 | N50: DESA | O50: Desarrollos | P50: GDR | Q50: García del Río 3760 | R50: 0 | S50: =(Tabla18[[#This Row],[Debe]]-Tabla18[[#This Row],[Haber]])* SUMIF('0_Indice_CAC'!$A:$A,Tabla18[[#This Row],[Mes]],'0_Indice_CAC'!$D:$D) -> 6277.2496 | T50: =Tabla18[[#This Row],[Debe]]-Tabla18[[#This Row],[Haber]] -> 6480 | W50: =IFERROR(T50-IF(V50="",0,V50),0) -> 6480 | X50: =ISNUMBER(MATCH(A50,'3_Control_Ppto'!$A$4:$A$70,0)) -> TRUE
A51: Albañilería | B51: MT | C51: =+EOMONTH(Tabla18[[#This Row],[Fecha Asiento]],-1)+1 -> 45689 | D51: 53023 | E51: Varios Ferreteria | F51: 45709 | G51: 1162 | H51: Varios Ferreteria | J51: OPXX | K51: 6576 | L51: 9050.03 | M51: 0 | N51: DESA | O51: Desarrollos | P51: GDR | Q51: García del Río 3760 | R51: 0 | S51: =(Tabla18[[#This Row],[Debe]]-Tabla18[[#This Row],[Haber]])* SUMIF('0_Indice_CAC'!$A:$A,Tabla18[[#This Row],[Mes]],'0_Indice_CAC'!$D:$D) -> 8766.8669 | T51: =Tabla18[[#This Row],[Debe]]-Tabla18[[#This Row],[Haber]] -> 9050.03 | W51: =IFERROR(T51-IF(V51="",0,V51),0) -> 9050.03 | X51: =ISNUMBER(MATCH(A51,'3_Control_Ppto'!$A$4:$A$70,0)) -> TRUE
A52: Movilidad | B52: MO | C52: =+EOMONTH(Tabla18[[#This Row],[Fecha Asiento]],-1)+1 -> 45689 | D52: 52103 | E52: Supermercados | F52: 45713 | G52: 1165 | H52: Supermercados | J52: OPXX | K52: 6579 | L52: 3050 | M52: 0 | N52: DESA | O52: Desarrollos | P52: GDR | Q52: García del Río 3760 | R52: 0 | S52: =(Tabla18[[#This Row],[Debe]]-Tabla18[[#This Row],[Haber]])* SUMIF('0_Indice_CAC'!$A:$A,Tabla18[[#This Row],[Mes]],'0_Indice_CAC'!$D:$D) -> 2954.5697 | T52: =Tabla18[[#This Row],[Debe]]-Tabla18[[#This Row],[Haber]] -> 3050 | W52: =IFERROR(T52-IF(V52="",0,V52),0) -> 3050 | X52: =ISNUMBER(MATCH(A52,'3_Control_Ppto'!$A$4:$A$70,0)) -> TRUE
A53: Movilidad | B53: MO | C53: =+EOMONTH(Tabla18[[#This Row],[Fecha Asiento]],-1)+1 -> 45689 | D53: 52103 | E53: Supermercados | F53: 45713 | G53: 1471 | H53: Supermercado - Dia Argentina S | I53: Dia Argentina S.A. | J53: FCA3 | K53: 1165100000041 | L53: 2520.66 | M53: 0 | N53: DESA | O53: Desarrollos | P53: GDR | Q53: García del Río 3760 | R53: 0 | S53: =(Tabla18[[#This Row],[Debe]]-Tabla18[[#This Row],[Haber]])* SUMIF('0_Indice_CAC'!$A:$A,Tabla18[[#This Row],[Mes]],'0_Indice_CAC'!$D:$D) -> 2441.792 | T53: =Tabla18[[#This Row],[Debe]]-Tabla18[[#This Row],[Haber]] -> 2520.66 | W53: =IFERROR(T53-IF(V53="",0,V53),0) -> 2520.66 | X53: =ISNUMBER(MATCH(A53,'3_Control_Ppto'!$A$4:$A$70,0)) -> TRUE
A54: Preliminar | B54: MT | C54: =+EOMONTH(Tabla18[[#This Row],[Fecha Asiento]],-1)+1 -> 45689 | D54: 53001 | E54: Preliminares | F54: 45713 | G54: 1472 | H54: BISAGRA 1842 - HERRAJES TRONAD | I54: HERRAJES TRONADOR SRL | J54: FCA3 | K54: 500000635 | L54: 6281 | M54: 0 | N54: DESA | O54: Desarrollos | P54: GDR | Q54: García del Río 3760 | R54: 0 | S54: =(Tabla18[[#This Row],[Debe]]-Tabla18[[#This Row],[Haber]])* SUMIF('0_Indice_CAC'!$A:$A,Tabla18[[#This Row],[Mes]],'0_Indice_CAC'!$D:$D) -> 6084.4761 | T54: =Tabla18[[#This Row],[Debe]]-Tabla18[[#This Row],[Haber]] -> 6281 | W54: =IFERROR(T54-IF(V54="",0,V54),0) -> 6281 | X54: =ISNUMBER(MATCH(A54,'3_Control_Ppto'!$A$4:$A$70,0)) -> TRUE
A55: - | B55: - | C55: =+EOMONTH(Tabla18[[#This Row],[Fecha Asiento]],-1)+1 -> 45689 | D55: 52405 | E55: Ajuste por Redondeo | F55: 45714 | G55: 1491 | H55: Ajuste por redondeo - Aserrade | I55: Aserradero Biel S.A. | J55: FCA3 | K55: 400011783 | L55: 0.05 | M55: 0 | N55: DESA | O55: Desarrollos | P55: GDR | Q55: García del Río 3760 | R55: 0 | S55: =(Tabla18[[#This Row],[Debe]]-Tabla18[[#This Row],[Haber]])* SUMIF('0_Indice_CAC'!$A:$A,Tabla18[[#This Row],[Mes]],'0_Indice_CAC'!$D:$D) -> 0.048435568 | T55: =Tabla18[[#This Row],[Debe]]-Tabla18[[#This Row],[Haber]] -> 0.05 | W55: =IFERROR(T55-IF(V55="",0,V55),0) -> 0.05 | X55: =ISNUMBER(MATCH(A55,'3_Control_Ppto'!$A$4:$A$70,0)) -> FALSE
A56: Hormigón | B56: MT | C56: =+EOMONTH(Tabla18[[#This Row],[Fecha Asiento]],-1)+1 -> 45689 | D56: 53004 | E56: Hormigón MT | F56: 45714 | G56: 1491 | H56: homigon MT - Aserradero Biel S | I56: Aserradero Biel S.A. | J56: FCA3 | K56: 400011783 | L56: 1220419 | M56: 0 | N56: DESA | O56: Desarrollos | P56: GDR | Q56: García del Río 3760 | R56: 0 | S56: =(Tabla18[[#This Row],[Debe]]-Tabla18[[#This Row],[Haber]])* SUMIF('0_Indice_CAC'!$A:$A,Tabla18[[#This Row],[Mes]],'0_Indice_CAC'!$D:$D) -> 1182233.8 | T56: =Tabla18[[#This Row],[Debe]]-Tabla18[[#This Row],[Haber]] -> 1220419 | W56: =IFERROR(T56-IF(V56="",0,V56),0) -> 1220419 | X56: =ISNUMBER(MATCH(A56,'3_Control_Ppto'!$A$4:$A$70,0)) -> TRUE
A57: Albañilería | B57: MT | C57: =+EOMONTH(Tabla18[[#This Row],[Fecha Asiento]],-1)+1 -> 45689 | D57: 53023 | E57: Varios Ferreteria | F57: 45714 | G57: 1166 | H57: Varios Ferreteria | J57: OPXX | K57: 6580 | L57: 6599.99 | M57: 0 | N57: DESA | O57: Desarrollos | P57: GDR | Q57: García del Río 3760 | R57: 0 | S57: =(Tabla18[[#This Row],[Debe]]-Tabla18[[#This Row],[Haber]])* SUMIF('0_Indice_CAC'!$A:$A,Tabla18[[#This Row],[Mes]],'0_Indice_CAC'!$D:$D) -> 6393.4853 | T57: =Tabla18[[#This Row],[Debe]]-Tabla18[[#This Row],[Haber]] -> 6599.99 | W57: =IFERROR(T57-IF(V57="",0,V57),0) -> 6599.99 | X57: =ISNUMBER(MATCH(A57,'3_Control_Ppto'!$A$4:$A$70,0)) -> TRUE
A58: Albañilería | B58: MT | C58: =+EOMONTH(Tabla18[[#This Row],[Fecha Asiento]],-1)+1 -> 45689 | D58: 53023 | E58: Varios Ferreteria | F58: 45714 | G58: 1473 | H58: Varios Ferreteria - HOVSEPIAN | I58: HOVSEPIAN HNOS. SH | J58: FCA3 | K58: 600010876 | L58: 5454.54 | M58: 0 | N58: DESA | O58: Desarrollos | P58: GDR | Q58: García del Río 3760 | R58: 0 | S58: =(Tabla18[[#This Row],[Debe]]-Tabla18[[#This Row],[Haber]])* SUMIF('0_Indice_CAC'!$A:$A,Tabla18[[#This Row],[Mes]],'0_Indice_CAC'!$D:$D) -> 5283.8749 | T58: =Tabla18[[#This Row],[Debe]]-Tabla18[[#This Row],[Haber]] -> 5454.54 | W58: =IFERROR(T58-IF(V58="",0,V58),0) -> 5454.54 | X58: =ISNUMBER(MATCH(A58,'3_Control_Ppto'!$A$4:$A$70,0)) -> TRUE
A59: Preliminar | B59: - | C59: =+EOMONTH(Tabla18[[#This Row],[Fecha Asiento]],-1)+1 -> 45689 | D59: 53001 | E59: Preliminares | F59: 45716 | G59: 592 | H59: 2Q 02-2025 Adelanto - Meza Raf | J59: OPXX | K59: 6018 | L59: 100000 | M59: 0 | N59: DESA | O59: Desarrollos | P59: GDR | Q59: García del Río 3760 | R59: 0 | S59: =(Tabla18[[#This Row],[Debe]]-Tabla18[[#This Row],[Haber]])* SUMIF('0_Indice_CAC'!$A:$A,Tabla18[[#This Row],[Mes]],'0_Indice_CAC'!$D:$D) -> 96871.136 | T59: =Tabla18[[#This Row],[Debe]]-Tabla18[[#This Row],[Haber]] -> 100000 | W59: =IFERROR(T59-IF(V59="",0,V59),0) -> 100000 | X59: =ISNUMBER(MATCH(A59,'3_Control_Ppto'!$A$4:$A$70,0)) -> TRUE
A60: Preliminar | B60: - | C60: =+EOMONTH(Tabla18[[#This Row],[Fecha Asiento]],-1)+1 -> 45689 | D60: 53001 | E60: Preliminares | F60: 45716 | G60: 593 | H60: 2Q 02-2025 Adelanto - Espinoza | J60: OPXX | K60: 6019 | L60: 100000 | M60: 0 | N60: DESA | O60: Desarrollos | P60: GDR | Q60: García del Río 3760 | R60: 0 | S60: =(Tabla18[[#This Row],[Debe]]-Tabla18[[#This Row],[Haber]])* SUMIF('0_Indice_CAC'!$A:$A,Tabla18[[#This Row],[Mes]],'0_Indice_CAC'!$D:$D) -> 96871.136 | T60: =Tabla18[[#This Row],[Debe]]-Tabla18[[#This Row],[Haber]] -> 100000 | W60: =IFERROR(T60-IF(V60="",0,V60),0) -> 100000 | X60: =ISNUMBER(MATCH(A60,'3_Control_Ppto'!$A$4:$A$70,0)) -> TRUE
A61: Preliminar | B61: - | C61: =+EOMONTH(Tabla18[[#This Row],[Fecha Asiento]],-1)+1 -> 45689 | D61: 53001 | E61: Preliminares | F61: 45716 | G61: 594 | H61: 2Q 02-2025 Adelanto - Cabrera | J61: OPXX | K61: 6020 | L61: 100000 | M61: 0 | N61: DESA | O61: Desarrollos | P61: GDR | Q61: García del Río 3760 | R61: 0 | S61: =(Tabla18[[#This Row],[Debe]]-Tabla18[[#This Row],[Haber]])* SUMIF('0_Indice_CAC'!$A:$A,Tabla18[[#This Row],[Mes]],'0_Indice_CAC'!$D:$D) -> 96871.136 | T61: =Tabla18[[#This Row],[Debe]]-Tabla18[[#This Row],[Haber]] -> 100000 | W61: =IFERROR(T61-IF(V61="",0,V61),0) -> 100000 | X61: =ISNUMBER(MATCH(A61,'3_Control_Ppto'!$A$4:$A$70,0)) -> TRUE
A62: Seguridad e Higiene | B62: MO | C62: =+EOMONTH(Tabla18[[#This Row],[Fecha Asiento]],-1)+1 -> 45717 | D62: 52204 | E62: H. Seguridad e Higiene | F62: 45721 | G62: 1438 | H62: Honorarios Seguridad e Higiene | I62: Petrini David Osvaldo | J62: FCA3 | K62: 300001173 | L62: 307000 | M62: 0 | N62: DESA | O62: Desarrollos | P62: GDR | Q62: García del Río 3760 | R62: 0 | S62: =(Tabla18[[#This Row],[Debe]]-Tabla18[[#This Row],[Haber]])* SUMIF('0_Indice_CAC'!$A:$A,Tabla18[[#This Row],[Mes]],'0_Indice_CAC'!$D:$D) -> 294735.66 | T62: =Tabla18[[#This Row],[Debe]]-Tabla18[[#This Row],[Haber]] -> 307000 | W62: =IFERROR(T62-IF(V62="",0,V62),0) -> 307000 | X62: =ISNUMBER(MATCH(A62,'3_Control_Ppto'!$A$4:$A$70,0)) -> TRUE
A63: Albañilería | B63: MT | C63: =+EOMONTH(Tabla18[[#This Row],[Fecha Asiento]],-1)+1 -> 45717 | D63: 53023 | E63: Varios Ferreteria | F63: 45721 | G63: 1500 | H63: Varios Ferreteria - Casa Caste | I63: Casa Castelao S.A. | J63: FCA3 | K63: 300004802 | L63: 11201.33 | M63: 0 | N63: DESA | O63: Desarrollos | P63: GDR | Q63: García del Río 3760 | R63: 0 | S63: =(Tabla18[[#This Row],[Debe]]-Tabla18[[#This Row],[Haber]])* SUMIF('0_Indice_CAC'!$A:$A,Tabla18[[#This Row],[Mes]],'0_Indice_CAC'!$D:$D) -> 10753.848 | T63: =Tabla18[[#This Row],[Debe]]-Tabla18[[#This Row],[Haber]] -> 11201.33 | W63: =IFERROR(T63-IF(V63="",0,V63),0) -> 11201.33 | X63: =ISNUMBER(MATCH(A63,'3_Control_Ppto'!$A$4:$A$70,0)) -> TRUE
A64: Seguridad e Higiene | B64: MO | C64: =+EOMONTH(Tabla18[[#This Row],[Fecha Asiento]],-1)+1 -> 45717 | D64: 53026 | E64: Seguridad e Higiene | F64: 45721 | G64: 1440 | H64: Matafuegos - Petrini Carlos Ja | I64: Petrini Carlos Javier | J64: FCA3 | K64: 300001240 | L64: 149000 | M64: 0 | N64: DESA | O64: Desarrollos | P64: GDR | Q64: García del Río 3760 | R64: 0 | S64: =(Tabla18[[#This Row],[Debe]]-Tabla18[[#This Row],[Haber]])* SUMIF('0_Indice_CAC'!$A:$A,Tabla18[[#This Row],[Mes]],'0_Indice_CAC'!$D:$D) -> 143047.6 | T64: =Tabla18[[#This Row],[Debe]]-Tabla18[[#This Row],[Haber]] -> 149000 | W64: =IFERROR(T64-IF(V64="",0,V64),0) -> 149000 | X64: =ISNUMBER(MATCH(A64,'3_Control_Ppto'!$A$4:$A$70,0)) -> TRUE
A65: Preliminar | B65: MT | C65: =+EOMONTH(Tabla18[[#This Row],[Fecha Asiento]],-1)+1 -> 45717 | D65: 53001 | E65: Preliminares | F65: 45722 | G65: 1945 | H65: preliminares - Centro Sec SRL | I65: Centro Sec SRL | J65: FCA3 | K65: 1400064174 | L65: 9092.01 | M65: 0 | N65: DESA | O65: Desarrollos | P65: GDR | Q65: García del Río 3760 | R65: 0 | S65: =(Tabla18[[#This Row],[Debe]]-Tabla18[[#This Row],[Haber]])* SUMIF('0_Indice_CAC'!$A:$A,Tabla18[[#This Row],[Mes]],'0_Indice_CAC'!$D:$D) -> 8728.7934 | T65: =Tabla18[[#This Row],[Debe]]-Tabla18[[#This Row],[Haber]] -> 9092.01 | W65: =IFERROR(T65-IF(V65="",0,V65),0) -> 9092.01 | X65: =ISNUMBER(MATCH(A65,'3_Control_Ppto'!$A$4:$A$70,0)) -> TRUE
A66: Durlock/Yeso | B66: MT | C66: =+EOMONTH(Tabla18[[#This Row],[Fecha Asiento]],-1)+1 -> 45717 | D66: 53010 | E66: Durlock MT | F66: 45722 | G66: 1167 | H66: Durlock MT | J66: OPXX | K66: 6581 | L66: 11228.53 | M66: 0 | N66: DESA | O66: Desarrollos | P66: GDR | Q66: García del Río 3760 | R66: 0 | S66: =(Tabla18[[#This Row],[Debe]]-Tabla18[[#This Row],[Haber]])* SUMIF('0_Indice_CAC'!$A:$A,Tabla18[[#This Row],[Mes]],'0_Indice_CAC'!$D:$D) -> 10779.962 | T66: =Tabla18[[#This Row],[Debe]]-Tabla18[[#This Row],[Haber]] -> 11228.53 | W66: =IFERROR(T66-IF(V66="",0,V66),0) -> 11228.53 | X66: =ISNUMBER(MATCH(A66,'3_Control_Ppto'!$A$4:$A$70,0)) -> TRUE
A67: - | B67: - | C67: =+EOMONTH(Tabla18[[#This Row],[Fecha Asiento]],-1)+1 -> 45717 | D67: 52405 | E67: Ajuste por Redondeo | F67: 45723 | G67: 1804 | H67: Ajuste por redondeo - TRANSPOR | I67: TRANSPORTES RT S.A. | J67: FCA3 | K67: 200011812 | L67: 0.01 | M67: 0 | N67: DESA | O67: Desarrollos | P67: GDR | Q67: García del Río 3760 | R67: 0 | S67: =(Tabla18[[#This Row],[Debe]]-Tabla18[[#This Row],[Haber]])* SUMIF('0_Indice_CAC'!$A:$A,Tabla18[[#This Row],[Mes]],'0_Indice_CAC'!$D:$D) -> 0.0096005101 | T67: =Tabla18[[#This Row],[Debe]]-Tabla18[[#This Row],[Haber]] -> 0.01 | W67: =IFERROR(T67-IF(V67="",0,V67),0) -> 0.01 | X67: =ISNUMBER(MATCH(A67,'3_Control_Ppto'!$A$4:$A$70,0)) -> FALSE
A68: - | B68: - | C68: =+EOMONTH(Tabla18[[#This Row],[Fecha Asiento]],-1)+1 -> 45717 | D68: 52405 | E68: Ajuste por Redondeo | F68: 45723 | G68: 1805 | H68: Ajuste por redondeo - TRANSPOR | I68: TRANSPORTES RT S.A. | J68: FCA3 | K68: 200011805 | L68: 0.01 | M68: 0 | N68: DESA | O68: Desarrollos | P68: GDR | Q68: García del Río 3760 | R68: 0 | S68: =(Tabla18[[#This Row],[Debe]]-Tabla18[[#This Row],[Haber]])* SUMIF('0_Indice_CAC'!$A:$A,Tabla18[[#This Row],[Mes]],'0_Indice_CAC'!$D:$D) -> 0.0096005101 | T68: =Tabla18[[#This Row],[Debe]]-Tabla18[[#This Row],[Haber]] -> 0.01 | W68: =IFERROR(T68-IF(V68="",0,V68),0) -> 0.01 | X68: =ISNUMBER(MATCH(A68,'3_Control_Ppto'!$A$4:$A$70,0)) -> FALSE
A69: Preliminar | B69: MT | C69: =+EOMONTH(Tabla18[[#This Row],[Fecha Asiento]],-1)+1 -> 45717 | D69: 53001 | E69: Preliminares | F69: 45723 | G69: 1804 | H69: preliminares - TRANSPORTES RT | I69: TRANSPORTES RT S.A. | J69: FCA3 | K69: 200011812 | L69: 2254328.2 | M69: 0 | N69: DESA | O69: Desarrollos | P69: GDR | Q69: García del Río 3760 | R69: 0 | S69: =(Tabla18[[#This Row],[Debe]]-Tabla18[[#This Row],[Haber]])* SUMIF('0_Indice_CAC'!$A:$A,Tabla18[[#This Row],[Mes]],'0_Indice_CAC'!$D:$D) -> 2164270.1 | T69: =Tabla18[[#This Row],[Debe]]-Tabla18[[#This Row],[Haber]] -> 2254328.2 | W69: =IFERROR(T69-IF(V69="",0,V69),0) -> 2254328.2 | X69: =ISNUMBER(MATCH(A69,'3_Control_Ppto'!$A$4:$A$70,0)) -> TRUE
A70: Hormigón | B70: MT | C70: =+EOMONTH(Tabla18[[#This Row],[Fecha Asiento]],-1)+1 -> 45717 | D70: 53004 | E70: Hormigón MT | F70: 45723 | G70: 1805 | H70: homigon MT - TRANSPORTES RT S. | I70: TRANSPORTES RT S.A. | J70: FCA3 | K70: 200011805 | L70: 2389199.1 | M70: 0 | N70: DESA | O70: Desarrollos | P70: GDR | Q70: García del Río 3760 | R70: 0 | S70: =(Tabla18[[#This Row],[Debe]]-Tabla18[[#This Row],[Haber]])* SUMIF('0_Indice_CAC'!$A:$A,Tabla18[[#This Row],[Mes]],'0_Indice_CAC'!$D:$D) -> 2293753 | T70: =Tabla18[[#This Row],[Debe]]-Tabla18[[#This Row],[Haber]] -> 2389199.1 | W70: =IFERROR(T70-IF(V70="",0,V70),0) -> 2389199.1 | X70: =ISNUMBER(MATCH(A70,'3_Control_Ppto'!$A$4:$A$70,0)) -> TRUE
A71: Albañilería | B71: - | C71: =+EOMONTH(Tabla18[[#This Row],[Fecha Asiento]],-1)+1 -> 45717 | D71: 53009 | E71: Albañilería MO | F71: 45723 | G71: 623 | H71: 2Q 02-2025 - Ayala Angel | J71: OPXX | K71: 6049 | L71: 81400 | M71: 0 | N71: DESA | O71: Desarrollos | P71: GDR | Q71: García del Río 3760 | R71: 0 | S71: =(Tabla18[[#This Row],[Debe]]-Tabla18[[#This Row],[Haber]])* SUMIF('0_Indice_CAC'!$A:$A,Tabla18[[#This Row],[Mes]],'0_Indice_CAC'!$D:$D) -> 78148.153 | T71: =Tabla18[[#This Row],[Debe]]-Tabla18[[#This Row],[Haber]] -> 81400 | W71: =IFERROR(T71-IF(V71="",0,V71),0) -> 81400 | X71: =ISNUMBER(MATCH(A71,'3_Control_Ppto'!$A$4:$A$70,0)) -> TRUE
A72: Albañilería | B72: - | C72: =+EOMONTH(Tabla18[[#This Row],[Fecha Asiento]],-1)+1 -> 45717 | D72: 53009 | E72: Albañilería MO | F72: 45723 | G72: 624 | H72: 2Q 02-2025 - Ayala Angel - SER | J72: OPXX | K72: 6050 | L72: 106666.67 | M72: 0 | N72: DESA | O72: Desarrollos | P72: GDR | Q72: García del Río 3760 | R72: 0 | S72: =(Tabla18[[#This Row],[Debe]]-Tabla18[[#This Row],[Haber]])* SUMIF('0_Indice_CAC'!$A:$A,Tabla18[[#This Row],[Mes]],'0_Indice_CAC'!$D:$D) -> 102405.44 | T72: =Tabla18[[#This Row],[Debe]]-Tabla18[[#This Row],[Haber]] -> 106666.67 | W72: =IFERROR(T72-IF(V72="",0,V72),0) -> 106666.67 | X72: =ISNUMBER(MATCH(A72,'3_Control_Ppto'!$A$4:$A$70,0)) -> TRUE
A73: Albañilería | B73: - | C73: =+EOMONTH(Tabla18[[#This Row],[Fecha Asiento]],-1)+1 -> 45717 | D73: 53009 | E73: Albañilería MO | F73: 45723 | G73: 626 | H73: 2Q 02-2025 - Espinosa Catriel | J73: OPXX | K73: 6052 | L73: 160700 | M73: 0 | N73: DESA | O73: Desarrollos | P73: GDR | Q73: García del Río 3760 | R73: 0 | S73: =(Tabla18[[#This Row],[Debe]]-Tabla18[[#This Row],[Haber]])* SUMIF('0_Indice_CAC'!$A:$A,Tabla18[[#This Row],[Mes]],'0_Indice_CAC'!$D:$D) -> 154280.2 | T73: =Tabla18[[#This Row],[Debe]]-Tabla18[[#This Row],[Haber]] -> 160700 | W73: =IFERROR(T73-IF(V73="",0,V73),0) -> 160700 | X73: =ISNUMBER(MATCH(A73,'3_Control_Ppto'!$A$4:$A$70,0)) -> TRUE
A74: Albañilería | B74: - | C74: =+EOMONTH(Tabla18[[#This Row],[Fecha Asiento]],-1)+1 -> 45717 | D74: 53009 | E74: Albañilería MO | F74: 45723 | G74: 627 | H74: 2Q 02-2025 - Cabrera Ruben | J74: OPXX | K74: 6053 | L74: 160700 | M74: 0 | N74: DESA | O74: Desarrollos | P74: GDR | Q74: García del Río 3760 | R74: 0 | S74: =(Tabla18[[#This Row],[Debe]]-Tabla18[[#This Row],[Haber]])* SUMIF('0_Indice_CAC'!$A:$A,Tabla18[[#This Row],[Mes]],'0_Indice_CAC'!$D:$D) -> 154280.2 | T74: =Tabla18[[#This Row],[Debe]]-Tabla18[[#This Row],[Haber]] -> 160700 | W74: =IFERROR(T74-IF(V74="",0,V74),0) -> 160700 | X74: =ISNUMBER(MATCH(A74,'3_Control_Ppto'!$A$4:$A$70,0)) -> TRUE
A75: Albañilería | B75: - | C75: =+EOMONTH(Tabla18[[#This Row],[Fecha Asiento]],-1)+1 -> 45717 | D75: 53009 | E75: Albañilería MO | F75: 45723 | G75: 628 | H75: 2Q 02-2025 - Meza Iturbe Rafae | J75: OPXX | K75: 6054 | L75: 160700 | M75: 0 | N75: DESA | O75: Desarrollos | P75: GDR | Q75: García del Río 3760 | R75: 0 | S75: =(Tabla18[[#This Row],[Debe]]-Tabla18[[#This Row],[Haber]])* SUMIF('0_Indice_CAC'!$A:$A,Tabla18[[#This Row],[Mes]],'0_Indice_CAC'!$D:$D) -> 154280.2 | T75: =Tabla18[[#This Row],[Debe]]-Tabla18[[#This Row],[Haber]] -> 160700 | W75: =IFERROR(T75-IF(V75="",0,V75),0) -> 160700 | X75: =ISNUMBER(MATCH(A75,'3_Control_Ppto'!$A$4:$A$70,0)) -> TRUE
A76: Albañilería | B76: - | C76: =+EOMONTH(Tabla18[[#This Row],[Fecha Asiento]],-1)+1 -> 45717 | D76: 53009 | E76: Albañilería MO | F76: 45723 | G76: 629 | H76: 2Q 02-2025 - Godoy Juan Ramon | J76: OPXX | K76: 6055 | L76: 83220 | M76: 0 | N76: DESA | O76: Desarrollos | P76: GDR | Q76: García del Río 3760 | R76: 0 | S76: =(Tabla18[[#This Row],[Debe]]-Tabla18[[#This Row],[Haber]])* SUMIF('0_Indice_CAC'!$A:$A,Tabla18[[#This Row],[Mes]],'0_Indice_CAC'!$D:$D) -> 79895.445 | T76: =Tabla18[[#This Row],[Debe]]-Tabla18[[#This Row],[Haber]] -> 83220 | W76: =IFERROR(T76-IF(V76="",0,V76),0) -> 83220 | X76: =ISNUMBER(MATCH(A76,'3_Control_Ppto'!$A$4:$A$70,0)) -> TRUE
A77: - | B77: - | C77: =+EOMONTH(Tabla18[[#This Row],[Fecha Asiento]],-1)+1 -> 45717 | D77: 5108 | E77: Gastos en personal | F77: 45726 | G77: 1808 | H77: Gastos en Personales - Abrafer | I77: Abrafer S.R.L. | J77: NCA3 | K77: 1000012643 | L77: 0 | M77: 59490.47 | N77: DESA | O77: Desarrollos | P77: GDR | Q77: García del Río 3760 | R77: 0 | S77: =(Tabla18[[#This Row],[Debe]]-Tabla18[[#This Row],[Haber]])* SUMIF('0_Indice_CAC'!$A:$A,Tabla18[[#This Row],[Mes]],'0_Indice_CAC'!$D:$D) -> -57113.886 | T77: =Tabla18[[#This Row],[Debe]]-Tabla18[[#This Row],[Haber]] -> -59490.47 | W77: =IFERROR(T77-IF(V77="",0,V77),0) -> -59490.47 | X77: =ISNUMBER(MATCH(A77,'3_Control_Ppto'!$A$4:$A$70,0)) -> FALSE
A78: Preliminar | B78: MT | C78: =+EOMONTH(Tabla18[[#This Row],[Fecha Asiento]],-1)+1 -> 45717 | D78: 53001 | E78: Preliminares | F78: 45726 | G78: 1168 | H78: Preliminares | J78: OPXX | K78: 6582 | L78: 12800 | M78: 0 | N78: DESA | O78: Desarrollos | P78: GDR | Q78: García del Río 3760 | R78: 0 | S78: =(Tabla18[[#This Row],[Debe]]-Tabla18[[#This Row],[Haber]])* SUMIF('0_Indice_CAC'!$A:$A,Tabla18[[#This Row],[Mes]],'0_Indice_CAC'!$D:$D) -> 12288.653 | T78: =Tabla18[[#This Row],[Debe]]-Tabla18[[#This Row],[Haber]] -> 12800 | W78: =IFERROR(T78-IF(V78="",0,V78),0) -> 12800 | X78: =ISNUMBER(MATCH(A78,'3_Control_Ppto'!$A$4:$A$70,0)) -> TRUE
A79: Preliminar | B79: MT | C79: =+EOMONTH(Tabla18[[#This Row],[Fecha Asiento]],-1)+1 -> 45717 | D79: 53001 | E79: Preliminares | F79: 45726 | G79: 1946 | H79: preliminares - Boyadsian Andre | I79: Boyadsian Andrea Walter | J79: FCA3 | K79: 400000327 | L79: 10578.51 | M79: 0 | N79: DESA | O79: Desarrollos | P79: GDR | Q79: García del Río 3760 | R79: 0 | S79: =(Tabla18[[#This Row],[Debe]]-Tabla18[[#This Row],[Haber]])* SUMIF('0_Indice_CAC'!$A:$A,Tabla18[[#This Row],[Mes]],'0_Indice_CAC'!$D:$D) -> 10155.909 | T79: =Tabla18[[#This Row],[Debe]]-Tabla18[[#This Row],[Haber]] -> 10578.51 | W79: =IFERROR(T79-IF(V79="",0,V79),0) -> 10578.51 | X79: =ISNUMBER(MATCH(A79,'3_Control_Ppto'!$A$4:$A$70,0)) -> TRUE
A80: - | B80: - | C80: =+EOMONTH(Tabla18[[#This Row],[Fecha Asiento]],-1)+1 -> 45717 | D80: 5108 | E80: Gastos en personal | F80: 45727 | G80: 1582 | H80: EPP - Abrafer S.R.L. | I80: Abrafer S.R.L. | J80: FCA3 | K80: 1000193810 | L80: 389523.63 | M80: 0 | N80: DESA | O80: Desarrollos | P80: GDR | Q80: García del Río 3760 | R80: 0 | S80: =(Tabla18[[#This Row],[Debe]]-Tabla18[[#This Row],[Haber]])* SUMIF('0_Indice_CAC'!$A:$A,Tabla18[[#This Row],[Mes]],'0_Indice_CAC'!$D:$D) -> 373962.56 | T80: =Tabla18[[#This Row],[Debe]]-Tabla18[[#This Row],[Haber]] -> 389523.63 | W80: =IFERROR(T80-IF(V80="",0,V80),0) -> 389523.63 | X80: =ISNUMBER(MATCH(A80,'3_Control_Ppto'!$A$4:$A$70,0)) -> FALSE
A81: Preliminar | B81: MT | C81: =+EOMONTH(Tabla18[[#This Row],[Fecha Asiento]],-1)+1 -> 45717 | D81: 53001 | E81: Preliminares | F81: 45727 | G81: 1171 | H81: Preliminares | J81: OPXX | K81: 6585 | L81: 6999.97 | M81: 0 | N81: DESA | O81: Desarrollos | P81: GDR | Q81: García del Río 3760 | R81: 0 | S81: =(Tabla18[[#This Row],[Debe]]-Tabla18[[#This Row],[Haber]])* SUMIF('0_Indice_CAC'!$A:$A,Tabla18[[#This Row],[Mes]],'0_Indice_CAC'!$D:$D) -> 6720.3283 | T81: =Tabla18[[#This Row],[Debe]]-Tabla18[[#This Row],[Haber]] -> 6999.97 | W81: =IFERROR(T81-IF(V81="",0,V81),0) -> 6999.97 | X81: =ISNUMBER(MATCH(A81,'3_Control_Ppto'!$A$4:$A$70,0)) -> TRUE
A82: Preliminar | B82: MT | C82: =+EOMONTH(Tabla18[[#This Row],[Fecha Asiento]],-1)+1 -> 45717 | D82: 53001 | E82: Preliminares | F82: 45727 | G82: 1947 | H82: preliminares - LUNA FERNANDO | I82: LUNA FERNANDO | J82: FCA3 | K82: 1000000052 | L82: 11984 | M82: 0 | N82: DESA | O82: Desarrollos | P82: GDR | Q82: García del Río 3760 | R82: 0 | S82: =(Tabla18[[#This Row],[Debe]]-Tabla18[[#This Row],[Haber]])* SUMIF('0_Indice_CAC'!$A:$A,Tabla18[[#This Row],[Mes]],'0_Indice_CAC'!$D:$D) -> 11505.251 | T82: =Tabla18[[#This Row],[Debe]]-Tabla18[[#This Row],[Haber]] -> 11984 | W82: =IFERROR(T82-IF(V82="",0,V82),0) -> 11984 | X82: =ISNUMBER(MATCH(A82,'3_Control_Ppto'!$A$4:$A$70,0)) -> TRUE
A83: Preliminar | B83: MT | C83: =+EOMONTH(Tabla18[[#This Row],[Fecha Asiento]],-1)+1 -> 45717 | D83: 53001 | E83: Preliminares | F83: 45727 | G83: 1948 | H83: preliminares - LUNA FERNANDO | I83: LUNA FERNANDO | J83: FCA3 | K83: 500000418 | L83: 2892.6 | M83: 0 | N83: DESA | O83: Desarrollos | P83: GDR | Q83: García del Río 3760 | R83: 0 | S83: =(Tabla18[[#This Row],[Debe]]-Tabla18[[#This Row],[Haber]])* SUMIF('0_Indice_CAC'!$A:$A,Tabla18[[#This Row],[Mes]],'0_Indice_CAC'!$D:$D) -> 2777.0436 | T83: =Tabla18[[#This Row],[Debe]]-Tabla18[[#This Row],[Haber]] -> 2892.6 | W83: =IFERROR(T83-IF(V83="",0,V83),0) -> 2892.6 | X83: =ISNUMBER(MATCH(A83,'3_Control_Ppto'!$A$4:$A$70,0)) -> TRUE
A84: Preliminar | B84: MT | C84: =+EOMONTH(Tabla18[[#This Row],[Fecha Asiento]],-1)+1 -> 45717 | D84: 53001 | E84: Preliminares | F84: 45727 | G84: 1949 | H84: preliminares - Boyadsian Andre | I84: Boyadsian Andrea Walter | J84: FCA3 | K84: 400000328 | L84: 5785.1 | M84: 0 | N84: DESA | O84: Desarrollos | P84: GDR | Q84: García del Río 3760 | R84: 0 | S84: =(Tabla18[[#This Row],[Debe]]-Tabla18[[#This Row],[Haber]])* SUMIF('0_Indice_CAC'!$A:$A,Tabla18[[#This Row],[Mes]],'0_Indice_CAC'!$D:$D) -> 5553.9911 | T84: =Tabla18[[#This Row],[Debe]]-Tabla18[[#This Row],[Haber]] -> 5785.1 | W84: =IFERROR(T84-IF(V84="",0,V84),0) -> 5785.1 | X84: =ISNUMBER(MATCH(A84,'3_Control_Ppto'!$A$4:$A$70,0)) -> TRUE
A85: Preliminar | B85: MT | C85: =+EOMONTH(Tabla18[[#This Row],[Fecha Asiento]],-1)+1 -> 45717 | D85: 53001 | E85: Preliminares | F85: 45727 | G85: 1950 | H85: preliminares - LUNA FERNANDO | I85: LUNA FERNANDO | J85: FCA3 | K85: 1000000051 | L85: 8762 | M85: 0 | N85: DESA | O85: Desarrollos | P85: GDR | Q85: García del Río 3760 | R85: 0 | S85: =(Tabla18[[#This Row],[Debe]]-Tabla18[[#This Row],[Haber]])* SUMIF('0_Indice_CAC'!$A:$A,Tabla18[[#This Row],[Mes]],'0_Indice_CAC'!$D:$D) -> 8411.967 | T85: =Tabla18[[#This Row],[Debe]]-Tabla18[[#This Row],[Haber]] -> 8762 | W85: =IFERROR(T85-IF(V85="",0,V85),0) -> 8762 | X85: =ISNUMBER(MATCH(A85,'3_Control_Ppto'!$A$4:$A$70,0)) -> TRUE
A86: Excavación y Mov. de Suelos | B86: MO | C86: =+EOMONTH(Tabla18[[#This Row],[Fecha Asiento]],-1)+1 -> 45717 | D86: 53003 | E86: Movimiento de Suelos | F86: 45727 | G86: 790 | H86: Celsi Vial - Excavacion | J86: OPXX | K86: 6213 | L86: 1580000 | M86: 0 | N86: DESA | O86: Desarrollos | P86: GDR | Q86: García del Río 3760 | R86: 0 | S86: =(Tabla18[[#This Row],[Debe]]-Tabla18[[#This Row],[Haber]])* SUMIF('0_Indice_CAC'!$A:$A,Tabla18[[#This Row],[Mes]],'0_Indice_CAC'!$D:$D) -> 1516880.6 | T86: =Tabla18[[#This Row],[Debe]]-Tabla18[[#This Row],[Haber]] -> 1580000 | U86: SC-004 | W86: =IFERROR(T86-IF(V86="",0,V86),0) -> 1580000 | X86: =ISNUMBER(MATCH(A86,'3_Control_Ppto'!$A$4:$A$70,0)) -> TRUE
A87: Albañilería | B87: MT | C87: =+EOMONTH(Tabla18[[#This Row],[Fecha Asiento]],-1)+1 -> 45717 | D87: 53023 | E87: Varios Ferreteria | F87: 45727 | G87: 1169 | H87: Varios Ferreteria | J87: OPXX | K87: 6583 | L87: 14500.64 | M87: 0 | N87: DESA | O87: Desarrollos | P87: GDR | Q87: García del Río 3760 | R87: 0 | S87: =(Tabla18[[#This Row],[Debe]]-Tabla18[[#This Row],[Haber]])* SUMIF('0_Indice_CAC'!$A:$A,Tabla18[[#This Row],[Mes]],'0_Indice_CAC'!$D:$D) -> 13921.354 | T87: =Tabla18[[#This Row],[Debe]]-Tabla18[[#This Row],[Haber]] -> 14500.64 | W87: =IFERROR(T87-IF(V87="",0,V87),0) -> 14500.64 | X87: =ISNUMBER(MATCH(A87,'3_Control_Ppto'!$A$4:$A$70,0)) -> TRUE
A88: Albañilería | B88: MT | C88: =+EOMONTH(Tabla18[[#This Row],[Fecha Asiento]],-1)+1 -> 45717 | D88: 53023 | E88: Varios Ferreteria | F88: 45727 | G88: 1170 | H88: Varios Ferreteria | J88: OPXX | K88: 6584 | L88: 3500.05 | M88: 0 | N88: DESA | O88: Desarrollos | P88: GDR | Q88: García del Río 3760 | R88: 0 | S88: =(Tabla18[[#This Row],[Debe]]-Tabla18[[#This Row],[Haber]])* SUMIF('0_Indice_CAC'!$A:$A,Tabla18[[#This Row],[Mes]],'0_Indice_CAC'!$D:$D) -> 3360.2266 | T88: =Tabla18[[#This Row],[Debe]]-Tabla18[[#This Row],[Haber]] -> 3500.05 | W88: =IFERROR(T88-IF(V88="",0,V88),0) -> 3500.05 | X88: =ISNUMBER(MATCH(A88,'3_Control_Ppto'!$A$4:$A$70,0)) -> TRUE
A89: Albañilería | B89: MT | C89: =+EOMONTH(Tabla18[[#This Row],[Fecha Asiento]],-1)+1 -> 45717 | D89: 53023 | E89: Varios Ferreteria | F89: 45727 | G89: 1172 | H89: Varios Ferreteria | J89: OPXX | K89: 6586 | L89: 10602.02 | M89: 0 | N89: DESA | O89: Desarrollos | P89: GDR | Q89: García del Río 3760 | R89: 0 | S89: =(Tabla18[[#This Row],[Debe]]-Tabla18[[#This Row],[Haber]])* SUMIF('0_Indice_CAC'!$A:$A,Tabla18[[#This Row],[Mes]],'0_Indice_CAC'!$D:$D) -> 10178.48 | T89: =Tabla18[[#This Row],[Debe]]-Tabla18[[#This Row],[Haber]] -> 10602.02 | W89: =IFERROR(T89-IF(V89="",0,V89),0) -> 10602.02 | X89: =ISNUMBER(MATCH(A89,'3_Control_Ppto'!$A$4:$A$70,0)) -> TRUE
A90: Albañilería | B90: MT | C90: =+EOMONTH(Tabla18[[#This Row],[Fecha Asiento]],-1)+1 -> 45717 | D90: 53023 | E90: Varios Ferreteria | F90: 45727 | G90: 1579 | H90: Varios Ferreteria - Abrafer S. | I90: Abrafer S.R.L. | J90: FCA3 | K90: 1000193811 | L90: 61701.43 | M90: 0 | N90: DESA | O90: Desarrollos | P90: GDR | Q90: García del Río 3760 | R90: 0 | S90: =(Tabla18[[#This Row],[Debe]]-Tabla18[[#This Row],[Haber]])* SUMIF('0_Indice_CAC'!$A:$A,Tabla18[[#This Row],[Mes]],'0_Indice_CAC'!$D:$D) -> 59236.52 | T90: =Tabla18[[#This Row],[Debe]]-Tabla18[[#This Row],[Haber]] -> 61701.43 | W90: =IFERROR(T90-IF(V90="",0,V90),0) -> 61701.43 | X90: =ISNUMBER(MATCH(A90,'3_Control_Ppto'!$A$4:$A$70,0)) -> TRUE
A91: Albañilería | B91: MT | C91: =+EOMONTH(Tabla18[[#This Row],[Fecha Asiento]],-1)+1 -> 45717 | D91: 53023 | E91: Varios Ferreteria | F91: 45727 | G91: 1580 | H91: Varios Ferreteria - Abrafer S. | I91: Abrafer S.R.L. | J91: FCA3 | K91: 1000193809 | L91: 120793.61 | M91: 0 | N91: DESA | O91: Desarrollos | P91: GDR | Q91: García del Río 3760 | R91: 0 | S91: =(Tabla18[[#This Row],[Debe]]-Tabla18[[#This Row],[Haber]])* SUMIF('0_Indice_CAC'!$A:$A,Tabla18[[#This Row],[Mes]],'0_Indice_CAC'!$D:$D) -> 115968.03 | T91: =Tabla18[[#This Row],[Debe]]-Tabla18[[#This Row],[Haber]] -> 120793.61 | W91: =IFERROR(T91-IF(V91="",0,V91),0) -> 120793.61 | X91: =ISNUMBER(MATCH(A91,'3_Control_Ppto'!$A$4:$A$70,0)) -> TRUE
A92: Albañilería | B92: MT | C92: =+EOMONTH(Tabla18[[#This Row],[Fecha Asiento]],-1)+1 -> 45717 | D92: 53023 | E92: Varios Ferreteria | F92: 45727 | G92: 1581 | H92: Varios Ferreteria - Abrafer S. | I92: Abrafer S.R.L. | J92: FCA3 | K92: 1000193808 | L92: 465215.14 | M92: 0 | N92: DESA | O92: Desarrollos | P92: GDR | Q92: García del Río 3760 | R92: 0 | S92: =(Tabla18[[#This Row],[Debe]]-Tabla18[[#This Row],[Haber]])* SUMIF('0_Indice_CAC'!$A:$A,Tabla18[[#This Row],[Mes]],'0_Indice_CAC'!$D:$D) -> 446630.27 | T92: =Tabla18[[#This Row],[Debe]]-Tabla18[[#This Row],[Haber]] -> 465215.14 | W92: =IFERROR(T92-IF(V92="",0,V92),0) -> 465215.14 | X92: =ISNUMBER(MATCH(A92,'3_Control_Ppto'!$A$4:$A$70,0)) -> TRUE
A93: Albañilería | B93: MT | C93: =+EOMONTH(Tabla18[[#This Row],[Fecha Asiento]],-1)+1 -> 45717 | D93: 53023 | E93: Varios Ferreteria | F93: 45727 | G93: 1582 | H93: Varios Ferreteria - Abrafer S. | I93: Abrafer S.R.L. | J93: FCA3 | K93: 1000193810 | L93: 3416.18 | M93: 0 | N93: DESA | O93: Desarrollos | P93: GDR | Q93: García del Río 3760 | R93: 0 | S93: =(Tabla18[[#This Row],[Debe]]-Tabla18[[#This Row],[Haber]])* SUMIF('0_Indice_CAC'!$A:$A,Tabla18[[#This Row],[Mes]],'0_Indice_CAC'!$D:$D) -> 3279.7071 | T93: =Tabla18[[#This Row],[Debe]]-Tabla18[[#This Row],[Haber]] -> 3416.18 | W93: =IFERROR(T93-IF(V93="",0,V93),0) -> 3416.18 | X93: =ISNUMBER(MATCH(A93,'3_Control_Ppto'!$A$4:$A$70,0)) -> TRUE
A94: Seguridad e Higiene | B94: MO | C94: =+EOMONTH(Tabla18[[#This Row],[Fecha Asiento]],-1)+1 -> 45717 | D94: 53026 | E94: Seguridad e Higiene | F94: 45727 | G94: 1582 | H94: Seguridad e Higiene - Abrafer | I94: Abrafer S.R.L. | J94: FCA3 | K94: 1000193810 | L94: 188910.95 | M94: 0 | N94: DESA | O94: Desarrollos | P94: GDR | Q94: García del Río 3760 | R94: 0 | S94: =(Tabla18[[#This Row],[Debe]]-Tabla18[[#This Row],[Haber]])* SUMIF('0_Indice_CAC'!$A:$A,Tabla18[[#This Row],[Mes]],'0_Indice_CAC'!$D:$D) -> 181364.15 | T94: =Tabla18[[#This Row],[Debe]]-Tabla18[[#This Row],[Haber]] -> 188910.95 | W94: =IFERROR(T94-IF(V94="",0,V94),0) -> 188910.95 | X94: =ISNUMBER(MATCH(A94,'3_Control_Ppto'!$A$4:$A$70,0)) -> TRUE
A95: Albañilería | B95: MT | C95: =+EOMONTH(Tabla18[[#This Row],[Fecha Asiento]],-1)+1 -> 45717 | D95: 53008 | E95: Albañilería MT | F95: 45728 | G95: 1568 | H95: ALBAÑILERIA MT - TRANSPORTES R | I95: TRANSPORTES RT S.A. | J95: FCA3 | K95: 200011848 | L95: 141995.76 | M95: 0 | N95: DESA | O95: Desarrollos | P95: GDR | Q95: García del Río 3760 | R95: 0 | S95: =(Tabla18[[#This Row],[Debe]]-Tabla18[[#This Row],[Haber]])* SUMIF('0_Indice_CAC'!$A:$A,Tabla18[[#This Row],[Mes]],'0_Indice_CAC'!$D:$D) -> 136323.17 | T95: =Tabla18[[#This Row],[Debe]]-Tabla18[[#This Row],[Haber]] -> 141995.76 | W95: =IFERROR(T95-IF(V95="",0,V95),0) -> 141995.76 | X95: =ISNUMBER(MATCH(A95,'3_Control_Ppto'!$A$4:$A$70,0)) -> TRUE
A96: Gastos Generales Obra | B96: MO | C96: =+EOMONTH(Tabla18[[#This Row],[Fecha Asiento]],-1)+1 -> 45717 | D96: 53022 | E96: Gastos Generales | F96: 45728 | G96: 1587 | H96: ALQ DE BAÑO - ECOBAT SRL | I96: ECOBAT SRL | J96: FCA3 | K96: 300022211 | L96: 80000 | M96: 0 | N96: DESA | O96: Desarrollos | P96: GDR | Q96: García del Río 3760 | R96: 0 | S96: =(Tabla18[[#This Row],[Debe]]-Tabla18[[#This Row],[Haber]])* SUMIF('0_Indice_CAC'!$A:$A,Tabla18[[#This Row],[Mes]],'0_Indice_CAC'!$D:$D) -> 76804.081 | T96: =Tabla18[[#This Row],[Debe]]-Tabla18[[#This Row],[Haber]] -> 80000 | W96: =IFERROR(T96-IF(V96="",0,V96),0) -> 80000 | X96: =ISNUMBER(MATCH(A96,'3_Control_Ppto'!$A$4:$A$70,0)) -> TRUE
A97: Gastos Generales Obra | B97: MO | C97: =+EOMONTH(Tabla18[[#This Row],[Fecha Asiento]],-1)+1 -> 45717 | D97: 52104 | E97: Aguas | F97: 45729 | G97: 1603 | H97: Aguas - Martin Guillermo Ibarl | I97: Martin Guillermo Ibarlucia | J97: FCA3 | K97: 200007273 | L97: 44000 | M97: 0 | N97: DESA | O97: Desarrollos | P97: GDR | Q97: García del Río 3760 | R97: 0 | S97: =(Tabla18[[#This Row],[Debe]]-Tabla18[[#This Row],[Haber]])* SUMIF('0_Indice_CAC'!$A:$A,Tabla18[[#This Row],[Mes]],'0_Indice_CAC'!$D:$D) -> 42242.245 | T97: =Tabla18[[#This Row],[Debe]]-Tabla18[[#This Row],[Haber]] -> 44000 | W97: =IFERROR(T97-IF(V97="",0,V97),0) -> 44000 | X97: =ISNUMBER(MATCH(A97,'3_Control_Ppto'!$A$4:$A$70,0)) -> TRUE
A98: Albañilería | B98: MT | C98: =+EOMONTH(Tabla18[[#This Row],[Fecha Asiento]],-1)+1 -> 45717 | D98: 53023 | E98: Varios Ferreteria | F98: 45730 | G98: 1173 | H98: Varios Ferreteria | J98: OPXX | K98: 6587 | L98: 12800.01 | M98: 0 | N98: DESA | O98: Desarrollos | P98: GDR | Q98: García del Río 3760 | R98: 0 | S98: =(Tabla18[[#This Row],[Debe]]-Tabla18[[#This Row],[Haber]])* SUMIF('0_Indice_CAC'!$A:$A,Tabla18[[#This Row],[Mes]],'0_Indice_CAC'!$D:$D) -> 12288.663 | T98: =Tabla18[[#This Row],[Debe]]-Tabla18[[#This Row],[Haber]] -> 12800.01 | W98: =IFERROR(T98-IF(V98="",0,V98),0) -> 12800.01 | X98: =ISNUMBER(MATCH(A98,'3_Control_Ppto'!$A$4:$A$70,0)) -> TRUE
A99: Albañilería | B99: MT | C99: =+EOMONTH(Tabla18[[#This Row],[Fecha Asiento]],-1)+1 -> 45717 | D99: 53023 | E99: Varios Ferreteria | F99: 45730 | G99: 1951 | H99: Varios Ferreteria - HOVSEPIAN | I99: HOVSEPIAN HNOS. SH | J99: FCA3 | K99: 600010990 | L99: 10578.52 | M99: 0 | N99: DESA | O99: Desarrollos | P99: GDR | Q99: García del Río 3760 | R99: 0 | S99: =(Tabla18[[#This Row],[Debe]]-Tabla18[[#This Row],[Haber]])* SUMIF('0_Indice_CAC'!$A:$A,Tabla18[[#This Row],[Mes]],'0_Indice_CAC'!$D:$D) -> 10155.919 | T99: =Tabla18[[#This Row],[Debe]]-Tabla18[[#This Row],[Haber]] -> 10578.52 | W99: =IFERROR(T99-IF(V99="",0,V99),0) -> 10578.52 | X99: =ISNUMBER(MATCH(A99,'3_Control_Ppto'!$A$4:$A$70,0)) -> TRUE
A100: Movilidad | B100: MO | C100: =+EOMONTH(Tabla18[[#This Row],[Fecha Asiento]],-1)+1 -> 45717 | D100: 52302 | E100: Mov. Variables | F100: 45731 | G100: 1818 | H100: Combustible - YPF S.A. | I100: YPF S.A. | J100: FCA3 | K100: 217201598671 | L100: 49673.86 | M100: 0 | N100: DESA | O100: Desarrollos | P100: GDR | Q100: García del Río 3760 | R100: 0 | S100: =(Tabla18[[#This Row],[Debe]]-Tabla18[[#This Row],[Haber]])* SUMIF('0_Indice_CAC'!$A:$A,Tabla18[[#This Row],[Mes]],'0_Indice_CAC'!$D:$D) -> 47689.44 | T100: =Tabla18[[#This Row],[Debe]]-Tabla18[[#This Row],[Haber]] -> 49673.86 | W100: =IFERROR(T100-IF(V100="",0,V100),0) -> 49673.86 | X100: =ISNUMBER(MATCH(A100,'3_Control_Ppto'!$A$4:$A$70,0)) -> TRUE
...

Sheet 2_Gastos_DirInd
A1: GASTOS DIRECTOS E INDIRECTOS — carga mensual
A2: Cargar manualmente el monto de cada mes (pesos corrientes). Los totales y deflactación CAC se calculan automáticamente. Alimenta 3_Control_Ppto y 3_Cash_Flow.
A3: Concepto | B3: Tipo | C3: 45627 | D3: 45658 | E3: 45689 | F3: 45717 | G3: 45748 | H3: 45778 | I3: 45809 | J3: 45839 | K3: 45870 | L3: 45901 | M3: 45931 | N3: 45962 | O3: 45992 | P3: 46023 | Q3: 46054 | R3: 46082 | S3: 46113 | T3: 46143 | U3: 46174 | V3: 46204 | W3: 46235 | X3: Total Real | Y3: Total Descontado
A4: Ratio CAC | C4: =IFERROR(VLOOKUP(C$3,'0_Indice_CAC'!$A:$D,4,FALSE()),0) -> 1 | D4: =IFERROR(VLOOKUP(D$3,'0_Indice_CAC'!$A:$D,4,FALSE()),0) -> 0.9848581 | E4: =IFERROR(VLOOKUP(E$3,'0_Indice_CAC'!$A:$D,4,FALSE()),0) -> 0.96871136 | F4: =IFERROR(VLOOKUP(F$3,'0_Indice_CAC'!$A:$D,4,FALSE()),0) -> 0.96005101 | G4: =IFERROR(VLOOKUP(G$3,'0_Indice_CAC'!$A:$D,4,FALSE()),0) -> 0.94480573 | H4: =IFERROR(VLOOKUP(H$3,'0_Indice_CAC'!$A:$D,4,FALSE()),0) -> 0.92949102 | I4: =IFERROR(VLOOKUP(I$3,'0_Indice_CAC'!$A:$D,4,FALSE()),0) -> 0.92267205 | J4: =IFERROR(VLOOKUP(J$3,'0_Indice_CAC'!$A:$D,4,FALSE()),0) -> 0.90654388 | ... W4: =IFERROR(VLOOKUP(W$3,'0_Indice_CAC'!$A:$D,4,FALSE()),0) -> 0
A5: Estado del mes | C5: OK | D5: OK | E5: OK | F5: OK | G5: OK | H5: OK | I5: OK | J5: OK | K5: OK | L5: OK | M5: OK | N5: OK | O5: OK | P5: OK | Q5: OK | R5: OK | X5: cargar "✓" o "OK" cuando se cierre el mes
A6: GASTOS DIRECTOS
A7: Oficina en obra (6x3 c/AA) | B7: D | X7: =SUM(C7:W7) -> 0 | Y7: =SUMPRODUCT(C7:W7,$C$4:$W$4) -> 0
A8: Obrador 6x3 s/AA | B8: D | X8: =SUM(C8:W8) -> 0 | Y8: =SUMPRODUCT(C8:W8,$C$4:$W$4) -> 0
A9: Pañol (6x3) | B9: D | X9: =SUM(C9:W9) -> 0 | Y9: =SUMPRODUCT(C9:W9,$C$4:$W$4) -> 0
A10: Baños | B10: D | X10: =SUM(C10:W10) -> 0 | Y10: =SUMPRODUCT(C10:W10,$C$4:$W$4) -> 0
A11: HyS permanente | B11: D | X11: =SUM(C11:W11) -> 0 | Y11: =SUMPRODUCT(C11:W11,$C$4:$W$4) -> 0
A12: Energía de obra | B12: D | X12: =SUM(C12:W12) -> 0 | Y12: =SUMPRODUCT(C12:W12,$C$4:$W$4) -> 0
A13: Agua de obra | B13: D | X13: =SUM(C13:W13) -> 0 | Y13: =SUMPRODUCT(C13:W13,$C$4:$W$4) -> 0
A14: Proyecto (50%) | B14: D | C14: 2657587 | D14: 1482428.3 | E14: 2402343.7 | F14: 1672761 | G14: 5758121.7 | H14: 1351332 | I14: 2021235.3 | J14: 1916553.9 | K14: 1898342.1 | L14: 3994139.4 | M14: 3276272.8 | N14: 2005645.5 | O14: 2870210.3 | P14: 1119889.8 | Q14: 1238690.1 | R14: 1313549 | X14: =SUM(C14:W14) -> 36979102 | Y14: =SUMPRODUCT(C14:W14,$C$4:$W$4) -> 33166449
A15: Coordinacion de obra | B15: D | C15: 285000 | D15: 380000 | E15: 400000 | F15: 404000 | G15: 300000 | H15: 400000 | I15: 580000 | J15: 600000 | K15: 1606011 | L15: 713070.9 | M15: 730897.5 | N15: 494000 | O15: 755700 | P15: 513876 | Q15: 523125.6 | R15: 523125.6 | X15: =SUM(C15:W15) -> 9208806.6 | Y15: =SUMPRODUCT(C15:W15,$C$4:$W$4) -> 8097506.1
A16: Sobrestante | B16: D | X16: =SUM(C16:W16) -> 0 | Y16: =SUMPRODUCT(C16:W16,$C$4:$W$4) -> 0
A17: Capataz | B17: D | X17: =SUM(C17:W17) -> 0 | Y17: =SUMPRODUCT(C17:W17,$C$4:$W$4) -> 0
A18: Logistica | B18: D | X18: =SUM(C18:W18) -> 0 | Y18: =SUMPRODUCT(C18:W18,$C$4:$W$4) -> 0
A19: Vehiculo obra | B19: D | C19: 232617.75 | D19: 158507.36 | E19: 81157.059 | F19: 209694.7 | G19: 215525.97 | H19: 212177.87 | I19: 215572.72 | J19: 291545.84 | K19: 371362.65 | L19: 379161.27 | M19: 387881.98 | N19: 397579.03 | O19: 408711.24 | P19: 420563.87 | Q19: 432760.22 | R19: 447474.07 | X19: =SUM(C19:W19) -> 4862293.6 | Y19: =SUMPRODUCT(C19:W19,$C$4:$W$4) -> 4213239.2
A20: TOTAL DIRECTOS | C20: =SUM(C7:C19) -> 3175204.8 | D20: =SUM(D7:D19) -> 2020935.7 | E20: =SUM(E7:E19) -> 2883500.7 | F20: =SUM(F7:F19) -> 2286455.7 | G20: =SUM(G7:G19) -> 6273647.6 | H20: =SUM(H7:H19) -> 1963509.9 | I20: =SUM(I7:I19) -> 2816808 | J20: =SUM(J7:J19) -> 2808099.8 | ... Y20: =SUM(Y7:Y19) -> 45477195
A22: GASTOS INDIRECTOS
A23: Payroll - Socios | B23: I | C23: 639132.78 | D23: 1284241.8 | E23: 322781.64 | F23: 648051 | G23: 651253.32 | H23: 651253.32 | I23: 651253.32 | J23: 1302506.6 | K23: 677659.84 | L23: 1016489.8 | M23: 1355319.6 | N23: 1543849.2 | O23: 2315774 | P23: 1875000 | Q23: 1875000.1 | R23: 1562500.1 | X23: =SUM(C23:W23) -> 18372066 | Y23: =SUMPRODUCT(C23:W23,$C$4:$W$4) -> 15842126
A24: Intereses Financiamiento | B24: I | F24: 80615.33 | G24: 0 | H24: 0 | I24: 0 | J24: 0 | K24: 0 | L24: 0 | M24: 0 | X24: =SUM(C24:W24) -> 80615.33 | Y24: =SUMPRODUCT(C24:W24,$C$4:$W$4) -> 77394.829
A25: Payroll - Administración | B25: I | D25: 541548.43 | E25: 1083683.3 | F25: 1985521 | G25: 1517776 | H25: 1149002.9 | I25: 2298005.8 | J25: 2872507.2 | K25: 1557715.5 | L25: 2058987.8 | M25: 2058987.8 | N25: 1448633.2 | O25: 2034382.5 | P25: 1609073.8 | Q25: 1663872.2 | R25: 1663872.2 | X25: =SUM(C25:W25) -> 25543570 | Y25: =SUMPRODUCT(C25:W25,$C$4:$W$4) -> 22394092
A26: TOTAL INDIRECTOS | C26: =SUM(C23:C25) -> 639132.78 | D26: =SUM(D23:D25) -> 1825790.3 | E26: =SUM(E23:E25) -> 1406464.9 | F26: =SUM(F23:F25) -> 2714187.3 | G26: =SUM(G23:G25) -> 2169029.3 | H26: =SUM(H23:H25) -> 1800256.2 | I26: =SUM(I23:I25) -> 2949259.1 | J26: =SUM(J23:J25) -> 4175013.8 | ... Y26: =SUM(Y23:Y25) -> 38313613

Sheet 2_Quincenas
A1: Resumen Consolidado por Obra (Horas)
A3: Mes | B3: Período | C3: Obra | D3: Categoría | E3: Rubro | F3: Horas totales | G3: Horas normales | H3: Horas extra 50% | I3: Horas extra 100% | K3: Costo Hs. Normales | L3: Costo Hs. Extra 50% | M3: Costo Hs. Extra 100% | N3: Total | O3: Total Descontado
A4: 45992 | B4: 1Q | C4: GARCIA DEL RIO | D4: MEDIO OFICIAL | E4: Albañilería | F4: =G4+H4+I4 -> 80 | G4: 68 | H4: 10 | I4: 2 | K4: =IFERROR(G4*INDEX('0_Jornales_MO'!$G$4:$J$21,MATCH(A4,'0_Jornales_MO'!$A$4:$A$21,0),MATCH(D4,{"ESPECIALIZADO","OFICIAL","MEDIO OFICIAL","AYUDANTE"},0)),"-") -> 691527.65 | L4: =IFERROR(H4*INDEX('0_Jornales_MO'!$G$4:$J$21,MATCH(A4,'0_Jornales_MO'!$A$4:$A$21,0),MATCH(D4,{"ESPECIALIZADO","OFICIAL","MEDIO OFICIAL","AYUDANTE"},0))*1.5,"-") -> 152542.86 | M4: =IFERROR(I4*INDEX('0_Jornales_MO'!$G$4:$J$21,MATCH(A4,'0_Jornales_MO'!$A$4:$A$21,0),MATCH(D4,{"ESPECIALIZADO","OFICIAL","MEDIO OFICIAL","AYUDANTE"},0))*2,"-") -> 40678.097 | N4: =IFERROR(SUM(K4:M4),"-") -> 884748.61 | O4: =IFERROR($N4 * SUMIF('0_Indice_CAC'!$A:$A,$A4,'0_Indice_CAC'!$D:$D),"-") -> 715311.75
A5: 45992 | B5: 1Q | C5: GARCIA DEL RIO | D5: MEDIO OFICIAL | E5: Electricidad | F5: =G5+H5+I5 -> 101 | G5: 88 | H5: 9 | I5: 4 | K5: =IFERROR(G5*INDEX('0_Jornales_MO'!$G$4:$J$21,MATCH(A5,'0_Jornales_MO'!$A$4:$A$21,0),MATCH(D5,{"ESPECIALIZADO","OFICIAL","MEDIO OFICIAL","AYUDANTE"},0)),"-") -> 894918.14 | L5: =IFERROR(H5*INDEX('0_Jornales_MO'!$G$4:$J$21,MATCH(A5,'0_Jornales_MO'!$A$4:$A$21,0),MATCH(D5,{"ESPECIALIZADO","OFICIAL","MEDIO OFICIAL","AYUDANTE"},0))*1.5,"-") -> 137288.58 | M5: =IFERROR(I5*INDEX('0_Jornales_MO'!$G$4:$J$21,MATCH(A5,'0_Jornales_MO'!$A$4:$A$21,0),MATCH(D5,{"ESPECIALIZADO","OFICIAL","MEDIO OFICIAL","AYUDANTE"},0))*2,"-") -> 81356.194 | N5: =IFERROR(SUM(K5:M5),"-") -> 1113562.9 | O5: =IFERROR($N5 * SUMIF('0_Indice_CAC'!$A:$A,$A5,'0_Indice_CAC'!$D:$D),"-") -> 900306.17
A6: 45992 | B6: 1Q | C6: GARCIA DEL RIO | D6: AYUDANTE | E6: Albañilería | F6: =G6+H6+I6 -> 401 | G6: 336 | H6: 57 | I6: 8 | K6: =IFERROR(G6*INDEX('0_Jornales_MO'!$G$4:$J$21,MATCH(A6,'0_Jornales_MO'!$A$4:$A$21,0),MATCH(D6,{"ESPECIALIZADO","OFICIAL","MEDIO OFICIAL","AYUDANTE"},0)),"-") -> 3201691.9 | L6: =IFERROR(H6*INDEX('0_Jornales_MO'!$G$4:$J$21,MATCH(A6,'0_Jornales_MO'!$A$4:$A$21,0),MATCH(D6,{"ESPECIALIZADO","OFICIAL","MEDIO OFICIAL","AYUDANTE"},0))*1.5,"-") -> 814716.24 | M6: =IFERROR(I6*INDEX('0_Jornales_MO'!$G$4:$J$21,MATCH(A6,'0_Jornales_MO'!$A$4:$A$21,0),MATCH(D6,{"ESPECIALIZADO","OFICIAL","MEDIO OFICIAL","AYUDANTE"},0))*2,"-") -> 152461.52 | N6: =IFERROR(SUM(K6:M6),"-") -> 4168869.6 | O6: =IFERROR($N6 * SUMIF('0_Indice_CAC'!$A:$A,$A6,'0_Indice_CAC'!$D:$D),"-") -> 3370495.7
A7: 45992 | B7: 1Q | C7: GARCIA DEL RIO | D7: ESPECIALIZADO | E7: Albañilería | F7: =G7+H7+I7 -> 96 | G7: 84 | H7: 10 | I7: 2 | K7: =IFERROR(G7*INDEX('0_Jornales_MO'!$G$4:$J$21,MATCH(A7,'0_Jornales_MO'!$A$4:$A$21,0),MATCH(D7,{"ESPECIALIZADO","OFICIAL","MEDIO OFICIAL","AYUDANTE"},0)),"-") -> 1195584.4 | L7: =IFERROR(H7*INDEX('0_Jornales_MO'!$G$4:$J$21,MATCH(A7,'0_Jornales_MO'!$A$4:$A$21,0),MATCH(D7,{"ESPECIALIZADO","OFICIAL","MEDIO OFICIAL","AYUDANTE"},0))*1.5,"-") -> 213497.22 | M7: =IFERROR(I7*INDEX('0_Jornales_MO'!$G$4:$J$21,MATCH(A7,'0_Jornales_MO'!$A$4:$A$21,0),MATCH(D7,{"ESPECIALIZADO","OFICIAL","MEDIO OFICIAL","AYUDANTE"},0))*2,"-") -> 56932.591 | N7: =IFERROR(SUM(K7:M7),"-") -> 1466014.2 | O7: =IFERROR($N7 * SUMIF('0_Indice_CAC'!$A:$A,$A7,'0_Indice_CAC'!$D:$D),"-") -> 1185260.1
A8: 45992 | B8: 1Q | C8: GARCIA DEL RIO | D8: OFICIAL | E8: Albañilería | F8: =G8+H8+I8 -> 231 | G8: 200 | H8: 27 | I8: 4 | K8: =IFERROR(G8*INDEX('0_Jornales_MO'!$G$4:$J$21,MATCH(A8,'0_Jornales_MO'!$A$4:$A$21,0),MATCH(D8,{"ESPECIALIZADO","OFICIAL","MEDIO OFICIAL","AYUDANTE"},0)),"-") -> 2379923.2 | L8: =IFERROR(H8*INDEX('0_Jornales_MO'!$G$4:$J$21,MATCH(A8,'0_Jornales_MO'!$A$4:$A$21,0),MATCH(D8,{"ESPECIALIZADO","OFICIAL","MEDIO OFICIAL","AYUDANTE"},0))*1.5,"-") -> 481934.44 | M8: =IFERROR(I8*INDEX('0_Jornales_MO'!$G$4:$J$21,MATCH(A8,'0_Jornales_MO'!$A$4:$A$21,0),MATCH(D8,{"ESPECIALIZADO","OFICIAL","MEDIO OFICIAL","AYUDANTE"},0))*2,"-") -> 95196.927 | N8: =IFERROR(SUM(K8:M8),"-") -> 2957054.5 | O8: =IFERROR($N8 * SUMIF('0_Indice_CAC'!$A:$A,$A8,'0_Indice_CAC'!$D:$D),"-") -> 2390753.5
A9: 45992 | B9: 1Q | C9: GARCIA DEL RIO | D9: OFICIAL | E9: Electricidad | F9: =G9+H9+I9 -> 96 | G9: 84 | H9: 10 | I9: 2 | K9: =IFERROR(G9*INDEX('0_Jornales_MO'!$G$4:$J$21,MATCH(A9,'0_Jornales_MO'!$A$4:$A$21,0),MATCH(D9,{"ESPECIALIZADO","OFICIAL","MEDIO OFICIAL","AYUDANTE"},0)),"-") -> 999567.73 | L9: =IFERROR(H9*INDEX('0_Jornales_MO'!$G$4:$J$21,MATCH(A9,'0_Jornales_MO'!$A$4:$A$21,0),MATCH(D9,{"ESPECIALIZADO","OFICIAL","MEDIO OFICIAL","AYUDANTE"},0))*1.5,"-") -> 178494.24 | M9: =IFERROR(I9*INDEX('0_Jornales_MO'!$G$4:$J$21,MATCH(A9,'0_Jornales_MO'!$A$4:$A$21,0),MATCH(D9,{"ESPECIALIZADO","OFICIAL","MEDIO OFICIAL","AYUDANTE"},0))*2,"-") -> 47598.464 | N9: =IFERROR(SUM(K9:M9),"-") -> 1225660.4 | O9: =IFERROR($N9 * SUMIF('0_Indice_CAC'!$A:$A,$A9,'0_Indice_CAC'!$D:$D),"-") -> 990936.06
