Workbook

Sheet CONFIG
A1: CONFIGURACIÓN DEL APU UNIFICADO — SVD 4140
A3: Parámetro | B3: Valor | C3: Notas
A4: Obra | B4: El Salvador 4140 (SVD)
A5: Mes de referencia | B5: Septiembre | C5: Mes de precios del APU 09-24
A6: Año de referencia | B6: 2024
A7: Versión | B7: v1.0 — APU Unificado SVD | C7: Generado desde El Salvador_Pres 04
A8: GG% | B8: 0 | C8: 0 = se aplica en presupuesto, no en APU
A9: BB% | B9: 0
A10: Coef. Cargas MO | B10: 1 | C10: Jornal P.MO ya es costo total/día
A11: IVA | B11: 0.105 | C11: Obra civil 10,5%

Sheet MATERIALES
A1: Código | B1: Descripción | C1: Unidad | D1: Precio $ | E1: Categoría
A2: MAT-0001 | B2: C. CIN. T101 ESP 0,50 MM (C25) | D2: 10599.984 | E2: Otros
A3: MAT-0002 | B3: Peril UPN 100 x 12 m | D3: 267019.02 | E3: Otros
A4: MAT-0003 | B4: Tubo estructural 40 x 40 x 2, Largo 6 metros | D4: 26250.62 | E4: Otros
A5: MAT-0004 | B5: Riel Roma 174 e: 2,1 mm. 53 x 60 x 6000 | D5: 81509.95 | E5: Otros
A6: MAT-0005 | B6: Carro acero 174 4 ruedas puertas portones Ø45mm | D6: 12131.562 | E6: Otros
A7: MAT-0006 | B7: Autoperforantes punta mecha 14 x 2 | D7: 120 | E7: Otros
A8: MAT-0007 | B8: Rollo Concertina | D8: 31404.959 | E8: Otros
A9: MAT-0008 | B9: C. CIN. T101 ESP 0,50 MM (C25) | D9: 5299.9917 | E9: Otros
A10: MAT-0009 | B10: Precio fenolico comun e: 18 mm | D10: 13161.34 | E10: Otros
A11: MAT-0010 | B11: Tabla 4 x 1 x 3,6 Saligna bruto | D11: 970.974 | E11: Otros
A12: MAT-0011 | B12: Tirante 3 x 3 x 3,6 Saligna bruto | D12: 2184.714 | E12: Otros
A13: MAT-0012 | B13: Flechas 3 x 6 x 3,7 - Reutilizado (estimado 3 usos) | D13: 4369.428 | E13: Otros
... A131: MAT-0130 | B131: Cupla PVC 3/4" | D131: 99.8298 | E131: Corralón
A132: MAT-0131 | B132: STECK DIFERENCIAL 2X25A 30MA | C132: u | D132: 26757.217 | E132: Otros
A133: MAT-0132 | B133: STECK DIFERENCIAL 4X40A 30MA | C133: u | D133: 51788.829 | E133: Otros
A134: MAT-0133 | B134: STECK DIFERENCIAL 4X63A 30MA | C134: u | D134: 62722.719 | E134: Otros
A135: MAT-0134 | B135: STECK TM BIPOLAR 10A 6KA | C135: u | D135: 7624.2992 | E135: Otros
A136: MAT-0135 | B136: STECK TM BIPOLAR 16A 6KA | C136: u | D136: 7624.2992 | E136: Otros
A137: MAT-0136 | B137: STECK TM TETRAPOLAR 32A 6KA | C137: u | D137: 16112.078 | E137: Otros
A138: MAT-0137 | B138: STECK TM TETRAPOLAR 50A 6KA | C138: u | D138: 17262.943 | E138: Otros
A139: MAT-0138 | B139: GAB. IP65 SERIE 9000 600X900X225 | C139: u | D139: 297024.27 | E139: Otros
A140: MAT-0139 | B140: CONTRAF ABISAG CALADO 60BIP S9000 600X900 | C140: u | D140: 106731.87 | E140: Otros
A141: MAT-0140 | B141: RIEL DIN 35MM 1 METRO PERFOR. | C141: u | D141: 5662.3777 | E141: Otros
A142: MAT-0141 | B142: RIEL PORTA ELEMENTOS X 1 METRO | C142: u | D142: 16325.561 | E142: Otros
A143: MAT-0142 | B143: SOP REG P/CONTRAFRENTE PROF 225 X1 | C143: u | D143: 10323.009 | E143: Otros
... A157: MAT-0156 | B157: CAJA EMB P/ TM 36 POLOS BC T/FUME | C157: u | D157: 30335.373 | E157: Otros
A158: MAT-0157 | B158: Montante eléctrica | D158: 5500000 | E158: Otros
A159: MAT-0158 | B159: CAÑOX3M RIGIDO 25MM PVC TUBE | C159: u | D159: 2038.6255 | E159: Otros
A160: MAT-0159 | B160: RIEL DE FIJAC.1.22 OLMAR | C160: u | D160: 5626.8379 | E160: Otros
A161: MAT-0160 | B161: BROCA METALICA 1/4 CJA X 100 | C161: u | D161: 78570.602 | E161: Otros
A162: MAT-0161 | B162: VARILLA ROSCADA 1/4"X1MTC/BUL. | C162: u | D162: 1220.467 | E162: Otros
A163: MAT-0162 | B163: GRAMPA P/RIEL 1 | C163: u | D163: 793.1237 | E163: Otros
A164: MAT-0163 | B164: CAJA DE CONEXION 30X40X10 CH20 | C164: u | D164: 18494.353 | E164: Otros
A165: MAT-0164 | B165: CONECTOR 25MM PVC RIG IP54 TUBE | C165: u | D165: 263.4609 | E165: Otros
A166: MAT-0165 | B166: RLLOX100M 1X 1,5MM NEGRO N.IRAM | C166: rol | D166: 34314.522 | E166: Otros
A167: MAT-0166 | B167: M SUBTERRANEO N IRAM 1X 120MM2 | C167: ml | D167: 26626.521 | E167: Otros
A168: MAT-0167 | B168: Gabinete columna 2 modulos trifasico Edesur | C168: u | D168: 499627.41 | E168: Otros
A169: MAT-0168 | B169: Gabinete columna 3 modulos monofasico Edesur | C169: u | D169: 448377.34 | E169: Otros
A170: MAT-0169 | B170: Caja de toma y secc. 400A c/6 bases NH T3 | C170: u | D170: 557199.73 | E170: Otros
... A176: MAT-0175 | B176: CAJA INSPECCION 15 x 15 PVC | C176: u | D176: 1205.3565 | E176: Otros
A177: MAT-0176 | B177: Tendido caño cloacal en planta baja y ss | D177: 2127230.4 | E177: Otros
A178: MAT-0177 | B178: Armado de pozo de bombeo cloacal | D178: 278565.88 | E178: Otros
A179: MAT-0178 | B179: Por armar CDV en planta tipo | D179: 2836307.1 | E179: Otros
A180: MAT-0179 | B180: Montantes, remate y ventilación a los 4 vientos | D180: 1215560.2 | E180: Otros
A181: MAT-0180 | B181: Tendido caño pluvial en planta baja y ss | D181: 599178.95 | E181: Otros
A182: MAT-0181 | B182: Tendido caño pluvial por pisos | D182: 898768.43 | E182: Otros
A183: MAT-0182 | B183: Instalación tanque de recupero y bombeo pluvial | D183: 213992.48 | E183: Otros
A184: MAT-0183 | B184: Tendido caño de agua en SS hasta TB. Colocación de TB, armado de colector y cuadro de bombas | D184: 979935.31 | E184: Otros
A185: MAT-0184 | B185: Colocación TR, armado de colector, subida y bajadas de AF | D185: 1959870.6 | E185: Otros
A186: MAT-0185 | B186: Colocación de bomba presurizadora, armado de colector y montantes presurizadas (ultimo piso 4°) AF | D186: 391974.12 | E186: Otros
A187: MAT-0186 | B187: Distribución agua fria y caliente en planta tipo | D187: 3135793 | E187: Otros
A188: MAT-0187 | B188: Colocación de artefactos y griferias - Provisión a cargo del comitente | D188: 2939805.9 | E188: Otros
... A209: MAT-0208 | B209: Colocación de artefactos a gas - Anafe/Horno | D209: 15000 | E209: Otros
A210: MAT-0209 | B210: Sup | C210: 7 | D210: 35122.669 | E210: Otros
A211: MAT-0210 | B211: Conducto ventilacion 30 x 30 - FRENTE | C211: =(12+9+6)-(5*3) -> 12 | D211: 20295.537 | E211: Otros
A212: MAT-0211 | B212: Conducto ventilacion 30 x 30 prep - FRENTE | C212: =5*3 -> 15 | D212: 37506.479 | E212: Otros
A213: MAT-0212 | B213: Sombrero - Spriros | C213: =+D23 -> 24793.388 | D213: 37506.479 | E213: Otros
A214: MAT-0213 | B214: SXXI MODULO toma doble 10A | D214: 4378.8099 | E214: Otros
A215: MAT-0214 | B215: S XXI/XXII BASTIDOR LUJO | D215: 455.6182 | E215: Otros
A216: MAT-0215 | B216: SXXII TAPA 2 MOD. BLANCA | D216: 1214.9853 | E216: Otros
A217: MAT-0216 | B217: SXXI MODULO toma simple | D217: 2189.4049 | E217: Otros
A218: MAT-0217 | B218: SXXII MODULO PUNTO | D218: 2075.6019 | E218: Otros
A219: MAT-0218 | B219: SXXII MODULO PULSADOR | D219: 2243.672 | E219: Otros
A220: MAT-0219 | B220: S XXI SOPORTE MIGNON | D220: 445.5004 | E220: Otros
A221: MAT-0220 | B221: SXXII TAPA MIGNON 1 MD.BLANCA | D221: 911.2364 | E221: Otros
A222: MAT-0221 | B222: CALEFA: Tendido de cañería por piso, m | D222: 8108346.1 | E222: Otros
A223: MAT-0222 | B223: CALEFA: Colectores y gabinetes | D223: 5535035.6 | E223: Otros
A224: MAT-0223 | B224: Flexibles caldera | D224: 75150 | E224: Otros
A225: MAT-CONS | B225: Consumibles | C225: gl | D225: 1 | E225: Consumible

Sheet MANO_DE_OBRA
A1: Código | B1: Descripción | C1: Salario/día $ | D1: Coef. Cargas | E1: Costo Jornal $
A2: MO-AYU | B2: AYUDANTE | C2: 49934.24 | D2: =CONFIG!$B$10 -> 1 | E2: =C2*D2 -> 49934.24
A3: MO-ESP | B3: ESPECIALIZADO | C3: 75113.05 | D3: =CONFIG!$B$10 -> 1 | E3: =C3*D3 -> 75113.05
A4: MO-MED | B4: MEDIO OFICIAL | C4: 54784.07 | D4: =CONFIG!$B$10 -> 1 | E4: =C4*D4 -> 54784.07
A5: MO-OFI | B5: OFICIAL | C5: 65360.25 | D5: =CONFIG!$B$10 -> 1 | E5: =C5*D5 -> 65360.25

Sheet EQUIPOS
A1: Código | B1: Descripción | C1: Precio $/día | D1: Categoría
A2: EQ-0001 | B2: Herramientas/consumibles - Topógrafo - Visita de obra replanteo | C2: 4463.1541 | D2: Equipo
A3: EQ-0002 | B3: Herramientas/consumibles - Cerco de obra perimetral - En chapa C25 | C3: 1660.4484 | D3: Equipo
A4: EQ-0003 | B4: Herramientas/consumibles - Obrador colgante, pañol y ducha | C4: 88757.838 | D4: Equipo
A5: EQ-0004 | B5: Herramientas/consumibles - Conexión pilar y luz de obra + Tablero d | C5: 20356.711 | D5: Equipo
A6: EQ-0005 | B6: Herramientas/consumibles - Conexión agua de obra, tanque + bomba | C6: 16527.298 | D6: Equipo
A7: EQ-0006 | B7: Herramientas/consumibles - Excavación a maquina para submuración y | C7: 117.1443 | D7: Equipo
A8: EQ-0007 | B8: Herramientas/consumibles - Hormigón de limpieza - e: 10 cm | C8: 3697.6064 | D8: Equipo
A9: EQ-0008 | B9: Herramientas/consumibles - Tabique submuración - H30 hidrófugo (95 | C9: 5678.0046 | D9: Equipo
A10: EQ-0009 | B10: Herramientas/consumibles - Zapata corrida tabique - H30 hidrófugo ( | C10: 4635.9445 | D10: Equipo
A11: EQ-0010 | B11: Herramientas/consumibles - Platea - H30 hidrófugo (95 kg/m3 de hier | C11: 2271.5846 | D11: Equipo
A12: EQ-0011 | B12: Herramientas/consumibles - Rampa - H30 (120 kg/m3 de hierro) | C12: 4901.2865 | D12: Equipo
A13: EQ-0012 | B13: Herramientas/consumibles - Losa maciza - H30 (110 kg/m3 de hierro) | C13: 3360.6568 | D13: Equipo
... A89: EQ-0088 | B89: Herramientas/consumibles - Flexibles caldera | C89: 1127.25 | D89: Equipo

Sheet SUBCONTRATOS_PRY
A1: Código | B1: Descripción | C1: Ud | D1: Precio Unitario $ | E1: Categoría
A2: SUB-0001 | B2: JEFE DE OBRA | D2: 172653.21 | E2: Subcontrato
A3: SUB-0002 | B3: Flete madera | D3: 250000 | E3: Subcontrato
A4: SUB-0003 | B4: Baño portatil / Ducha | D4: 295488.56 | E4: Subcontrato
A5: SUB-0004 | B5: Traslado flete entrega/ retiro | D5: 16416.031 | E5: Subcontrato
A6: SUB-0005 | B6: Gestion suministros luz de obra | D6: 139065.92 | E6: Subcontrato
A7: SUB-0006 | B7: Luz de Obra | D7: 100127.46 | E7: Subcontrato
A8: SUB-0007 | B8: Medicion PAT luz de obra | D8: 87611.528 | E8: Subcontrato
A9: SUB-0008 | B9: Total de Obra (3 perforaciones) | D9: 7800000 | E9: Subcontrato
A10: SUB-0009 | B10: Desmonte, retiro, aporte y compactación e: 40 cm | D10: 16000 | E10: Subcontrato
A11: SUB-0010 | B11: H.A. De vigas de fundación (115kg/m3 de hierro) | D11: 253994.14 | E11: Subcontrato
A12: SUB-0011 | B12: HA. De cabezales (90 kg/m3 de hierro) | D12: 148967.56 | E12: Subcontrato
A13: SUB-0012 | B13: OFICIAL ESPECIALIZADO ALBAÑIL | D13: 75113.048 | E13: Subcontrato
... A76: SUB-0075 | B76: Piso radiante + caldera | D76: 16174657 | E76: Subcontrato

Sheet PPTO_GENERADOR
A1: # | B1: Rubro | C1: Descripción | D1: Ud. | E1: Cant. | F1: MAT/ud | G1: MO/ud | H1: EQ/ud | I1: CD/ud | J1: MAT total | K1: MO total | L1: EQ total | M1: Costo Total | Q1: Código
A2: 1.01 | B2: Tareas Preliminares | C2: Limpieza y preparación del terreno - No cotiza | D2: gl | E2: 0 | F2: =IFERROR(VLOOKUP(Q2,PARTIDAS!$A:$P,13,FALSE),0) -> 0 | G2: =IFERROR(VLOOKUP(Q2,PARTIDAS!$A:$P,14,FALSE),0) -> 0 | H2: =IFERROR(VLOOKUP(Q2,PARTIDAS!$A:$P,15,FALSE),0) -> 0 | I2: =IFERROR(VLOOKUP(Q2,PARTIDAS!$A:$P,16,FALSE),0) -> 0 | J2: =F2*$E2 -> 0 | K2: =G2*$E2 -> 0 | L2: =H2*$E2 -> 0 | M2: =J2+K2+L2 -> 0 | Q2: PTO-0101
A3: 1.02 | B3: Tareas Preliminares | C3: Topógrafo - Visita de obra replanteo | D3: un | E3: 3 | F3: =IFERROR(VLOOKUP(Q3,PARTIDAS!$A:$P,13,FALSE),0) -> 41666.667 | G3: =IFERROR(VLOOKUP(Q3,PARTIDAS!$A:$P,14,FALSE),0) -> 255876.94 | H3: =IFERROR(VLOOKUP(Q3,PARTIDAS!$A:$P,15,FALSE),0) -> 4463.1541 | I3: =IFERROR(VLOOKUP(Q3,PARTIDAS!$A:$P,16,FALSE),0) -> 302006.76 | J3: =F3*$E3 -> 125000 | K3: =G3*$E3 -> 767630.83 | L3: =H3*$E3 -> 13389.462 | M3: =J3+K3+L3 -> 906020.29 | Q3: PTO-0102
A4: 1.03 | B4: Tareas Preliminares | C4: Cartel de Obra - No cotiza | D4: gl | E4: 0 | F4: =IFERROR(VLOOKUP(Q4,PARTIDAS!$A:$P,13,FALSE),0) -> 0 | G4: =IFERROR(VLOOKUP(Q4,PARTIDAS!$A:$P,14,FALSE),0) -> 0 | H4: =IFERROR(VLOOKUP(Q4,PARTIDAS!$A:$P,15,FALSE),0) -> 0 | I4: =IFERROR(VLOOKUP(Q4,PARTIDAS!$A:$P,16,FALSE),0) -> 0 | J4: =F4*$E4 -> 0 | K4: =G4*$E4 -> 0 | L4: =H4*$E4 -> 0 | M4: =J4+K4+L4 -> 0 | Q4: PTO-0103
A5: 1.04 | B5: Tareas Preliminares | C5: Cerco de obra perimetral - En chapa C25 + Concertina + Porton corredizo | D5: ml | E5: 11 | F5: =IFERROR(VLOOKUP(Q5,PARTIDAS!$A:$P,13,FALSE),0) -> 79773.18 | G5: =IFERROR(VLOOKUP(Q5,PARTIDAS!$A:$P,14,FALSE),0) -> 30923.374 | H5: =IFERROR(VLOOKUP(Q5,PARTIDAS!$A:$P,15,FALSE),0) -> 1660.4484 | I5: =IFERROR(VLOOKUP(Q5,PARTIDAS!$A:$P,16,FALSE),0) -> 112357 | J5: =F5*$E5 -> 877504.98 | K5: =G5*$E5 -> 340157.12 | L5: =H5*$E5 -> 18264.932 | M5: =J5+K5+L5 -> 1235927 | Q5: PTO-0104
A6: 1.05 | B6: Tareas Preliminares | C6: Obrador colgante, pañol y ducha | D6: gl | E6: 1 | F6: =IFERROR(VLOOKUP(Q6,PARTIDAS!$A:$P,13,FALSE),0) -> 2400856.7 | G6: =IFERROR(VLOOKUP(Q6,PARTIDAS!$A:$P,14,FALSE),0) -> 3516332.6 | H6: =IFERROR(VLOOKUP(Q6,PARTIDAS!$A:$P,15,FALSE),0) -> 88757.838 | I6: =IFERROR(VLOOKUP(Q6,PARTIDAS!$A:$P,16,FALSE),0) -> 6005947.1 | J6: =F6*$E6 -> 2400856.7 | K6: =G6*$E6 -> 3516332.6 | L6: =H6*$E6 -> 88757.838 | M6: =J6+K6+L6 -> 6005947.1 | Q6: PTO-0105
A7: 1.06 | B7: Tareas Preliminares | C7: Alquiler de baños quimicos y duchas portatiles | D7: mes | E7: 3 | F7: =IFERROR(VLOOKUP(Q7,PARTIDAS!$A:$P,13,FALSE),0) -> 0 | G7: =IFERROR(VLOOKUP(Q7,PARTIDAS!$A:$P,14,FALSE),0) -> 311904.59 | H7: =IFERROR(VLOOKUP(Q7,PARTIDAS!$A:$P,15,FALSE),0) -> 0 | I7: =IFERROR(VLOOKUP(Q7,PARTIDAS!$A:$P,16,FALSE),0) -> 311904.59 | J7: =F7*$E7 -> 0 | K7: =G7*$E7 -> 935713.77 | L7: =H7*$E7 -> 0 | M7: =J7+K7+L7 -> 935713.77 | Q7: PTO-0106
A8: 1.07 | B8: Tareas Preliminares | C8: Conexión pilar y luz de obra + Tablero de obra | D8: gl | E8: 1 | F8: =IFERROR(VLOOKUP(Q8,PARTIDAS!$A:$P,13,FALSE),0) -> 845578.51 | G8: =IFERROR(VLOOKUP(Q8,PARTIDAS!$A:$P,14,FALSE),0) -> 511535.58 | H8: =IFERROR(VLOOKUP(Q8,PARTIDAS!$A:$P,15,FALSE),0) -> 20356.711 | I8: =IFERROR(VLOOKUP(Q8,PARTIDAS!$A:$P,16,FALSE),0) -> 1377470.8 | J8: =F8*$E8 -> 845578.51 | K8: =G8*$E8 -> 511535.58 | L8: =H8*$E8 -> 20356.711 | M8: =J8+K8+L8 -> 1377470.8 | Q8: PTO-0107
A9: 1.08 | B9: Tareas Preliminares | C9: Conexión agua de obra, tanque + bomba | D9: gl | E9: 1 | F9: =IFERROR(VLOOKUP(Q9,PARTIDAS!$A:$P,13,FALSE),0) -> 680400 | G9: =IFERROR(VLOOKUP(Q9,PARTIDAS!$A:$P,14,FALSE),0) -> 421419.9 | H9: =IFERROR(VLOOKUP(Q9,PARTIDAS!$A:$P,15,FALSE),0) -> 16527.298 | I9: =IFERROR(VLOOKUP(Q9,PARTIDAS!$A:$P,16,FALSE),0) -> 1118347.2 | J9: =F9*$E9 -> 680400 | K9: =G9*$E9 -> 421419.9 | L9: =H9*$E9 -> 16527.298 | M9: =J9+K9+L9 -> 1118347.2 | Q9: PTO-0108
A10: 1.09 | B10: Tareas Preliminares | C10: Tramite luz de obra, certificado luz de obra (2) y medición PAT | D10: gl | E10: 1 | F10: =IFERROR(VLOOKUP(Q10,PARTIDAS!$A:$P,13,FALSE),0) -> 0 | G10: =IFERROR(VLOOKUP(Q10,PARTIDAS!$A:$P,14,FALSE),0) -> 339320.84 | H10: =IFERROR(VLOOKUP(Q10,PARTIDAS!$A:$P,15,FALSE),0) -> 0 | I10: =IFERROR(VLOOKUP(Q10,PARTIDAS!$A:$P,16,FALSE),0) -> 339320.84 | J10: =F10*$E10 -> 0 | K10: =G10*$E10 -> 339320.84 | L10: =H10*$E10 -> 0 | M10: =J10+K10+L10 -> 339320.84 | Q10: PTO-0109
A11: 1.1 | B11: Tareas Preliminares | C11: Sistema de depresión de napas | D11: gl | E11: 1 | F11: =IFERROR(VLOOKUP(Q11,PARTIDAS!$A:$P,13,FALSE),0) -> 0 | G11: =IFERROR(VLOOKUP(Q11,PARTIDAS!$A:$P,14,FALSE),0) -> 7800000 | H11: =IFERROR(VLOOKUP(Q11,PARTIDAS!$A:$P,15,FALSE),0) -> 0 | I11: =IFERROR(VLOOKUP(Q11,PARTIDAS!$A:$P,16,FALSE),0) -> 7800000 | J11: =F11*$E11 -> 0 | K11: =G11*$E11 -> 7800000 | L11: =H11*$E11 -> 0 | M11: =J11+K11+L11 -> 7800000 | Q11: PTO-0110
A12: 2.01 | B12: Movimiento de Suelos | C12: Excavación a maquina para submuración y subsuelo | D12: m3 | E12: 1266 | F12: =IFERROR(VLOOKUP(Q12,PARTIDAS!$A:$P,13,FALSE),0) -> 0 | G12: =IFERROR(VLOOKUP(Q12,PARTIDAS!$A:$P,14,FALSE),0) -> 26209.62 | H12: =IFERROR(VLOOKUP(Q12,PARTIDAS!$A:$P,15,FALSE),0) -> 117.1443 | I12: =IFERROR(VLOOKUP(Q12,PARTIDAS!$A:$P,16,FALSE),0) -> 26326.765 | J12: =F12*$E12 -> 0 | K12: =G12*$E12 -> 33181379 | L12: =H12*$E12 -> 148304.68 | M12: =J12+K12+L12 -> 33329684 | Q12: PTO-0201
A13: 2.02 | B13: Movimiento de Suelos | C13: Demolición y retiro de fundaciones existentes - No cotiza | D13: gl | E13: 0 | F13: =IFERROR(VLOOKUP(Q13,PARTIDAS!$A:$P,13,FALSE),0) -> 0 | G13: =IFERROR(VLOOKUP(Q13,PARTIDAS!$A:$P,14,FALSE),0) -> 0 | H13: =IFERROR(VLOOKUP(Q13,PARTIDAS!$A:$P,15,FALSE),0) -> 0 | I13: =IFERROR(VLOOKUP(Q13,PARTIDAS!$A:$P,16,FALSE),0) -> 0 | J13: =F13*$E13 -> 0 | K13: =G13*$E13 -> 0 | L13: =H13*$E13 -> 0 | M13: =J13+K13+L13 -> 0 | Q13: PTO-0202
... A190: 28.03 | B190: Calefacción | C190: Flexibles caldera | D190: u | E190: 16 | F190: =IFERROR(VLOOKUP(Q190,PARTIDAS!$A:$P,13,FALSE),0) -> 75150 | G190: =IFERROR(VLOOKUP(Q190,PARTIDAS!$A:$P,14,FALSE),0) -> 0 | H190: =IFERROR(VLOOKUP(Q190,PARTIDAS!$A:$P,15,FALSE),0) -> 1127.25 | I190: =IFERROR(VLOOKUP(Q190,PARTIDAS!$A:$P,16,FALSE),0) -> 76277.25 | J190: =F190*$E190 -> 1202400 | K190: =G190*$E190 -> 0 | L190: =H190*$E190 -> 18036 | M190: =J190+K190+L190 -> 1220436 | Q190: PTO-2803
C191: TOTAL OBRA | J191: =SUM(J2:J190) -> 4.8907854e+08 | K191: =SUM(K2:K190) -> 6.5281916e+08 | L191: =SUM(L2:L190) -> 21000045 | M191: =SUM(M2:M190) -> 1.1628977e+09

Sheet COMPOSICIÓN
A1: Partida | B1: Tipo | C1: Subtipo | D1: Cod_Insumo | E1: Descripción | F1: Unidad | G1: Cant | H1: %Desp | I1: Precio | J1: Costo | K1: Clave | L1: Count | M1: Clave2 | N1: Rend. Part. | O1: Cant MO/ALB Unit | P1: Cant. Ej. Part.
A2: PTO-0102 | B2: MO | C2: OTR | D2: SUB-0001 | E2: =IFERROR(VLOOKUP(D2,SUBCONTRATOS_PRY!A:B,2,FALSE),"?") -> JEFE DE OBRA | F2: j | G2: 1 | H2: 0 | I2: =IFERROR(VLOOKUP(D2,SUBCONTRATOS_PRY!A:D,4,FALSE),0) -> 172653.21 | J2: =G2*I2*(1+H2) -> 172653.21 | K2: =A2&"|"&B2 -> PTO-0102|MO | L2: =COUNTIFS($K$2:K2,K2) -> 1 | M2: =K2&"|"&L2 -> PTO-0102|MO|1 | N2: =IFERROR(VLOOKUP(A2,PARTIDAS!A:F,6,FALSE),0) -> 1 | O2: =IF(C2="ALB",IF(N2=0,0,G2/N2),0) -> 0 | P2: =IFERROR(_xlfn.XLOOKUP(A2,PPTO_GENERADOR!$Q:$Q,PPTO_GENERADOR!$E:$E,"-",0),"-") -> 3
A3: PTO-0102 | B3: MO | C3: ALB | D3: MO-AYU | E3: =IFERROR(VLOOKUP(D3,MANO_DE_OBRA!A:B,2,FALSE),"?") -> AYUDANTE | F3: j | G3: 1.6666667 | H3: 0 | I3: =IFERROR(VLOOKUP(D3,MANO_DE_OBRA!A:C,3,FALSE),0) -> 49934.24 | J3: =G3*I3*(1+H3) -> 83223.733 | K3: =A3&"|"&B3 -> PTO-0102|MO | L3: =COUNTIFS($K$2:K3,K3) -> 2 | M3: =K3&"|"&L3 -> PTO-0102|MO|2 | N3: =IFERROR(VLOOKUP(A3,PARTIDAS!A:F,6,FALSE),0) -> 1 | O3: =IF(C3="ALB",IF(N3=0,0,G3/N3),0) -> 1.6666667 | P3: =IFERROR(_xlfn.XLOOKUP(A3,PPTO_GENERADOR!$Q:$Q,PPTO_GENERADOR!$E:$E,"-",0),"-") -> 3
A4: PTO-0102 | B4: EQ | D4: EQ-0001 | E4: =IFERROR(VLOOKUP(D4,EQUIPOS!A:B,2,FALSE),"?") -> Herramientas/consumibles - Topógrafo - Visita de obra replanteo | G4: 1 | H4: 0 | I4: =IFERROR(VLOOKUP(D4,EQUIPOS!A:C,3,FALSE),0) -> 4463.1541 | J4: =G4*I4*(1+H4) -> 4463.1541 | K4: =A4&"|"&B4 -> PTO-0102|EQ | L4: =COUNTIFS($K$2:K4,K4) -> 1 | M4: =K4&"|"&L4 -> PTO-0102|EQ|1 | N4: =IFERROR(VLOOKUP(A4,PARTIDAS!A:F,6,FALSE),0) -> 1 | O4: =IF(C4="ALB",IF(N4=0,0,G4/N4),0) -> 0 | P4: =IFERROR(_xlfn.XLOOKUP(A4,PPTO_GENERADOR!$Q:$Q,PPTO_GENERADOR!$E:$E,"-",0),"-") -> 3
A5: PTO-0102 | B5: MAT | C5: CONS | D5: MAT-CONS | E5: =IFERROR(VLOOKUP(D5,MATERIALES!A:B,2,FALSE),"?") -> Consumibles | G5: 41666.667 | H5: 0 | I5: =IFERROR(VLOOKUP(D5,MATERIALES!A:D,4,FALSE),0) -> 1 | J5: =G5*I5*(1+H5) -> 41666.667 | K5: =A5&"|"&B5 -> PTO-0102|MAT | L5: =COUNTIFS($K$2:K5,K5) -> 1 | M5: =K5&"|"&L5 -> PTO-0102|MAT|1 | N5: =IFERROR(VLOOKUP(A5,PARTIDAS!A:F,6,FALSE),0) -> 1 | O5: =IF(C5="ALB",IF(N5=0,0,G5/N5),0) -> 0 | P5: =IFERROR(_xlfn.XLOOKUP(A5,PPTO_GENERADOR!$Q:$Q,PPTO_GENERADOR!$E:$E,"-",0),"-") -> 3
A6: PTO-0104 | B6: MAT | C6: OTR | D6: MAT-0001 | E6: =IFERROR(VLOOKUP(D6,MATERIALES!A:B,2,FALSE),"?") -> C. CIN. T101 ESP 0,50 MM (C25) | G6: 2.5 | H6: 0 | I6: =IFERROR(VLOOKUP(D6,MATERIALES!A:D,4,FALSE),0) -> 10599.984 | J6: =G6*I6*(1+H6) -> 26499.959 | K6: =A6&"|"&B6 -> PTO-0104|MAT | L6: =COUNTIFS($K$2:K6,K6) -> 1 | M6: =K6&"|"&L6 -> PTO-0104|MAT|1 | N6: =IFERROR(VLOOKUP(A6,PARTIDAS!A:F,6,FALSE),0) -> 1 | O6: =IF(C6="ALB",IF(N6=0,0,G6/N6),0) -> 0 | P6: =IFERROR(_xlfn.XLOOKUP(A6,PPTO_GENERADOR!$Q:$Q,PPTO_GENERADOR!$E:$E,"-",0),"-") -> 11
A7: PTO-0104 | B7: MAT | C7: OTR | D7: MAT-0002 | E7: =IFERROR(VLOOKUP(D7,MATERIALES!A:B,2,FALSE),"?") -> Peril UPN 100 x 12 m | G7: 0.09090909 | H7: 0 | I7: =IFERROR(VLOOKUP(D7,MATERIALES!A:D,4,FALSE),0) -> 267019.02 | J7: =G7*I7*(1+H7) -> 24274.456 | K7: =A7&"|"&B7 -> PTO-0104|MAT | L7: =COUNTIFS($K$2:K7,K7) -> 2 | M7: =K7&"|"&L7 -> PTO-0104|MAT|2 | N7: =IFERROR(VLOOKUP(A7,PARTIDAS!A:F,6,FALSE),0) -> 1 | O7: =IF(C7="ALB",IF(N7=0,0,G7/N7),0) -> 0 | P7: =IFERROR(_xlfn.XLOOKUP(A7,PPTO_GENERADOR!$Q:$Q,PPTO_GENERADOR!$E:$E,"-",0),"-") -> 11
A8: PTO-0104 | B8: MAT | C8: OTR | D8: MAT-0003 | E8: =IFERROR(VLOOKUP(D8,MATERIALES!A:B,2,FALSE),"?") -> Tubo estructural 40 x 40 x 2, Largo 6 metros | G8: 0.18181818 | H8: 0 | I8: =IFERROR(VLOOKUP(D8,MATERIALES!A:D,4,FALSE),0) -> 26250.62 | J8: =G8*I8*(1+H8) -> 4772.8399 | K8: =A8&"|"&B8 -> PTO-0104|MAT | L8: =COUNTIFS($K$2:K8,K8) -> 3 | M8: =K8&"|"&L8 -> PTO-0104|MAT|3 | N8: =IFERROR(VLOOKUP(A8,PARTIDAS!A:F,6,FALSE),0) -> 1 | O8: =IF(C8="ALB",IF(N8=0,0,G8/N8),0) -> 0 | P8: =IFERROR(_xlfn.XLOOKUP(A8,PPTO_GENERADOR!$Q:$Q,PPTO_GENERADOR!$E:$E,"-",0),"-") -> 11
A9: PTO-0104 | B9: MAT | C9: OTR | D9: MAT-0004 | E9: =IFERROR(VLOOKUP(D9,MATERIALES!A:B,2,FALSE),"?") -> Riel Roma 174 e: 2,1 mm. 53 x 60 x 6000 | G9: 0.09090909 | H9: 0 | I9: =IFERROR(VLOOKUP(D9,MATERIALES!A:D,4,FALSE),0) -> 81509.95 | J9: =G9*I9*(1+H9) -> 7409.9954 | K9: =A9&"|"&B9 -> PTO-0104|MAT | L9: =COUNTIFS($K$2:K9,K9) -> 4 | M9: =K9&"|"&L9 -> PTO-0104|MAT|4 | N9: =IFERROR(VLOOKUP(A9,PARTIDAS!A:F,6,FALSE),0) -> 1 | O9: =IF(C9="ALB",IF(N9=0,0,G9/N9),0) -> 0 | P9: =IFERROR(_xlfn.XLOOKUP(A9,PPTO_GENERADOR!$Q:$Q,PPTO_GENERADOR!$E:$E,"-",0),"-") -> 11
A10: PTO-0104 | B10: MAT | C10: OTR | D10: MAT-0005 | E10: =IFERROR(VLOOKUP(D10,MATERIALES!A:B,2,FALSE),"?") -> Carro acero 174 4 ruedas puertas portones Ø45mm | G10: 0.18181818 | H10: 0 | I10: =IFERROR(VLOOKUP(D10,MATERIALES!A:D,4,FALSE),0) -> 12131.562 | J10: =G10*I10*(1+H10) -> 2205.7385 | K10: =A10&"|"&B10 -> PTO-0104|MAT | L10: =COUNTIFS($K$2:K10,K10) -> 5 | M10: =K10&"|"&L10 -> PTO-0104|MAT|5 | N10: =IFERROR(VLOOKUP(A10,PARTIDAS!A:F,6,FALSE),0) -> 1 | O10: =IF(C10="ALB",IF(N10=0,0,G10/N10),0) -> 0 | P10: =IFERROR(_xlfn.XLOOKUP(A10,PPTO_GENERADOR!$Q:$Q,PPTO_GENERADOR!$E:$E,"-",0),"-") -> 11
A11: PTO-0104 | B11: MAT | C11: OTR | D11: MAT-0006 | E11: =IFERROR(VLOOKUP(D11,MATERIALES!A:B,2,FALSE),"?") -> Autoperforantes punta mecha 14 x 2 | G11: 11.25 | H11: 0 | I11: =IFERROR(VLOOKUP(D11,MATERIALES!A:D,4,FALSE),0) -> 120 | J11: =G11*I11*(1+H11) -> 1350 | K11: =A11&"|"&B11 -> PTO-0104|MAT | L11: =COUNTIFS($K$2:K11,K11) -> 6 | M11: =K11&"|"&L11 -> PTO-0104|MAT|6 | N11: =IFERROR(VLOOKUP(A11,PARTIDAS!A:F,6,FALSE),0) -> 1 | O11: =IF(C11="ALB",IF(N11=0,0,G11/N11),0) -> 0 | P11: =IFERROR(_xlfn.XLOOKUP(A11,PPTO_GENERADOR!$Q:$Q,PPTO_GENERADOR!$E:$E,"-",0),"-") -> 11
A12: PTO-0104 | B12: MAT | C12: OTR | D12: MAT-0007 | E12: =IFERROR(VLOOKUP(D12,MATERIALES!A:B,2,FALSE),"?") -> Rollo Concertina | G12: 0.09090909 | H12: 0 | I12: =IFERROR(VLOOKUP(D12,MATERIALES!A:D,4,FALSE),0) -> 31404.959 | J12: =G12*I12*(1+H12) -> 2854.9962 | K12: =A12&"|"&B12 -> PTO-0104|MAT | L12: =COUNTIFS($K$2:K12,K12) -> 7 | M12: =K12&"|"&L12 -> PTO-0104|MAT|7 | N12: =IFERROR(VLOOKUP(A12,PARTIDAS!A:F,6,FALSE),0) -> 1 | O12: =IF(C12="ALB",IF(N12=0,0,G12/N12),0) -> 0 | P12: =IFERROR(_xlfn.XLOOKUP(A12,PPTO_GENERADOR!$Q:$Q,PPTO_GENERADOR!$E:$E,"-",0),"-") -> 11
A13: PTO-0104 | B13: MO | C13: ALB | D13: MO-OFI | E13: =IFERROR(VLOOKUP(D13,MANO_DE_OBRA!A:B,2,FALSE),"?") -> OFICIAL | F13: j | G13: 0.18181818 | H13: 0 | I13: =IFERROR(VLOOKUP(D13,MANO_DE_OBRA!A:C,3,FALSE),0) -> 65360.25 | J13: =G13*I13*(1+H13) -> 11883.682 | K13: =A13&"|"&B13 -> PTO-0104|MO | L13: =COUNTIFS($K$2:K13,K13) -> 1 | M13: =K13&"|"&L13 -> PTO-0104|MO|1 | N13: =IFERROR(VLOOKUP(A13,PARTIDAS!A:F,6,FALSE),0) -> 1 | O13: =IF(C13="ALB",IF(N13=0,0,G13/N13),0) -> 0.18181818 | P13: =IFERROR(_xlfn.XLOOKUP(A13,PPTO_GENERADOR!$Q:$Q,PPTO_GENERADOR!$E:$E,"-",0),"-") -> 11
A14: PTO-0104 | B14: MO | C14: ALB | D14: MO-MED | E14: =IFERROR(VLOOKUP(D14,MANO_DE_OBRA!A:B,2,FALSE),"?") -> MEDIO OFICIAL | F14: j | G14: 0.18181818 | H14: 0 | I14: =IFERROR(VLOOKUP(D14,MANO_DE_OBRA!A:C,3,FALSE),0) -> 54784.07 | J14: =G14*I14*(1+H14) -> 9960.7399 | K14: =A14&"|"&B14 -> PTO-0104|MO | L14: =COUNTIFS($K$2:K14,K14) -> 2 | M14: =K14&"|"&L14 -> PTO-0104|MO|2 | N14: =IFERROR(VLOOKUP(A14,PARTIDAS!A:F,6,FALSE),0) -> 1 | O14: =IF(C14="ALB",IF(N14=0,0,G14/N14),0) -> 0.18181818 | P14: =IFERROR(_xlfn.XLOOKUP(A14,PPTO_GENERADOR!$Q:$Q,PPTO_GENERADOR!$E:$E,"-",0),"-") -> 11
A15: PTO-0104 | B15: MO | C15: ALB | D15: MO-AYU | E15: =IFERROR(VLOOKUP(D15,MANO_DE_OBRA!A:B,2,FALSE),"?") -> AYUDANTE | F15: j | G15: 0.18181818 | H15: 0 | I15: =IFERROR(VLOOKUP(D15,MANO_DE_OBRA!A:C,3,FALSE),0) -> 49934.24 | J15: =G15*I15*(1+H15) -> 9078.9526 | K15: =A15&"|"&B15 -> PTO-0104|MO | L15: =COUNTIFS($K$2:K15,K15) -> 3 | M15: =K15&"|"&L15 -> PTO-0104|MO|3 | N15: =IFERROR(VLOOKUP(A15,PARTIDAS!A:F,6,FALSE),0) -> 1 | O15: =IF(C15="ALB",IF(N15=0,0,G15/N15),0) -> 0.18181818 | P15: =IFERROR(_xlfn.XLOOKUP(A15,PPTO_GENERADOR!$Q:$Q,PPTO_GENERADOR!$E:$E,"-",0),"-") -> 11
A16: PTO-0104 | B16: EQ | D16: EQ-0002 | E16: =IFERROR(VLOOKUP(D16,EQUIPOS!A:B,2,FALSE),"?") -> Herramientas/consumibles - Cerco de obra perimetral - En chapa C25 | G16: 1 | H16: 0 | I16: =IFERROR(VLOOKUP(D16,EQUIPOS!A:C,3,FALSE),0) -> 1660.4484 | J16: =G16*I16*(1+H16) -> 1660.4484 | K16: =A16&"|"&B16 -> PTO-0104|EQ | L16: =COUNTIFS($K$2:K16,K16) -> 1 | M16: =K16&"|"&L16 -> PTO-0104|EQ|1 | N16: =IFERROR(VLOOKUP(A16,PARTIDAS!A:F,6,FALSE),0) -> 1 | O16: =IF(C16="ALB",IF(N16=0,0,G16/N16),0) -> 0 | P16: =IFERROR(_xlfn.XLOOKUP(A16,PPTO_GENERADOR!$Q:$Q,PPTO_GENERADOR!$E:$E,"-",0),"-") -> 11
A17: PTO-0104 | B17: MAT | C17: CONS | D17: MAT-CONS | E17: =IFERROR(VLOOKUP(D17,MATERIALES!A:B,2,FALSE),"?") -> Consumibles | G17: 10405.195 | H17: 0 | I17: =IFERROR(VLOOKUP(D17,MATERIALES!A:D,4,FALSE),0) -> 1 | J17: =G17*I17*(1+H17) -> 10405.195 | K17: =A17&"|"&B17 -> PTO-0104|MAT | L17: =COUNTIFS($K$2:K17,K17) -> 8 | M17: =K17&"|"&L17 -> PTO-0104|MAT|8 | N17: =IFERROR(VLOOKUP(A17,PARTIDAS!A:F,6,FALSE),0) -> 1 | O17: =IF(C17="ALB",IF(N17=0,0,G17/N17),0) -> 0 | P17: =IFERROR(_xlfn.XLOOKUP(A17,PPTO_GENERADOR!$Q:$Q,PPTO_GENERADOR!$E:$E,"-",0),"-") -> 11
A18: PTO-0105 | B18: MAT | C18: OTR | D18: MAT-0008 | E18: =IFERROR(VLOOKUP(D18,MATERIALES!A:B,2,FALSE),"?") -> C. CIN. T101 ESP 0,50 MM (C25) | G18: 35 | H18: 0 | I18: =IFERROR(VLOOKUP(D18,MATERIALES!A:D,4,FALSE),0) -> 5299.9917 | J18: =G18*I18*(1+H18) -> 185499.71 | K18: =A18&"|"&B18 -> PTO-0105|MAT | L18: =COUNTIFS($K$2:K18,K18) -> 1 | M18: =K18&"|"&L18 -> PTO-0105|MAT|1 | N18: =IFERROR(VLOOKUP(A18,PARTIDAS!A:F,6,FALSE),0) -> 1 | O18: =IF(C18="ALB",IF(N18=0,0,G18/N18),0) -> 0 | P18: =IFERROR(_xlfn.XLOOKUP(A18,PPTO_GENERADOR!$Q:$Q,PPTO_GENERADOR!$E:$E,"-",0),"-") -> 1
A19: PTO-0105 | B19: MAT | C19: OTR | D19: MAT-0009 | E19: =IFERROR(VLOOKUP(D19,MATERIALES!A:B,2,FALSE),"?") -> Precio fenolico comun e: 18 mm | G19: 33 | H19: 0 | I19: =IFERROR(VLOOKUP(D19,MATERIALES!A:D,4,FALSE),0) -> 13161.34 | J19: =G19*I19*(1+H19) -> 434324.22 | K19: =A19&"|"&B19 -> PTO-0105|MAT | L19: =COUNTIFS($K$2:K19,K19) -> 2 | M19: =K19&"|"&L19 -> PTO-0105|MAT|2 | N19: =IFERROR(VLOOKUP(A19,PARTIDAS!A:F,6,FALSE),0) -> 1 | O19: =IF(C19="ALB",IF(N19=0,0,G19/N19),0) -> 0 | P19: =IFERROR(_xlfn.XLOOKUP(A19,PPTO_GENERADOR!$Q:$Q,PPTO_GENERADOR!$E:$E,"-",0),"-") -> 1
A20: PTO-0105 | B20: MAT | C20: OTR | D20: MAT-0010 | E20: =IFERROR(VLOOKUP(D20,MATERIALES!A:B,2,FALSE),"?") -> Tabla 4 x 1 x 3,6 Saligna bruto | G20: 80 | H20: 0 | I20: =IFERROR(VLOOKUP(D20,MATERIALES!A:D,4,FALSE),0) -> 970.974 | J20: =G20*I20*(1+H20) -> 77677.92 | K20: =A20&"|"&B20 -> PTO-0105|MAT | L20: =COUNTIFS($K$2:K20,K20) -> 3 | M20: =K20&"|"&L20 -> PTO-0105|MAT|3 | N20: =IFERROR(VLOOKUP(A20,PARTIDAS!A:F,6,FALSE),0) -> 1 | O20: =IF(C20="ALB",IF(N20=0,0,G20/N20),0) -> 0 | P20: =IFERROR(_xlfn.XLOOKUP(A20,PPTO_GENERADOR!$Q:$Q,PPTO_GENERADOR!$E:$E,"-",0),"-") -> 1
A21: PTO-0105 | B21: MAT | C21: OTR | D21: MAT-0011 | E21: =IFERROR(VLOOKUP(D21,MATERIALES!A:B,2,FALSE),"?") -> Tirante 3 x 3 x 3,6 Saligna bruto | G21: 40 | H21: 0 | I21: =IFERROR(VLOOKUP(D21,MATERIALES!A:D,4,FALSE),0) -> 2184.714 | J21: =G21*I21*(1+H21) -> 87388.56 | K21: =A21&"|"&B21 -> PTO-0105|MAT | L21: =COUNTIFS($K$2:K21,K21) -> 4 | M21: =K21&"|"&L21 -> PTO-0105|MAT|4 | N21: =IFERROR(VLOOKUP(A21,PARTIDAS!A:F,6,FALSE),0) -> 1 | O21: =IF(C21="ALB",IF(N21=0,0,G21/N21),0) -> 0 | P21: =IFERROR(_xlfn.XLOOKUP(A21,PPTO_GENERADOR!$Q:$Q,PPTO_GENERADOR!$E:$E,"-",0),"-") -> 1
A22: PTO-0105 | B22: MAT | C22: OTR | D22: MAT-0012 | E22: =IFERROR(VLOOKUP(D22,MATERIALES!A:B,2,FALSE),"?") -> Flechas 3 x 6 x 3,7 - Reutilizado (estimado 3 usos) | G22: 20 | H22: 0 | I22: =IFERROR(VLOOKUP(D22,MATERIALES!A:D,4,FALSE),0) -> 4369.428 | J22: =G22*I22*(1+H22) -> 87388.56 | K22: =A22&"|"&B22 -> PTO-0105|MAT | L22: =COUNTIFS($K$2:K22,K22) -> 5 | M22: =K22&"|"&L22 -> PTO-0105|MAT|5 | N22: =IFERROR(VLOOKUP(A22,PARTIDAS!A:F,6,FALSE),0) -> 1 | O22: =IF(C22="ALB",IF(N22=0,0,G22/N22),0) -> 0 | P22: =IFERROR(_xlfn.XLOOKUP(A22,PPTO_GENERADOR!$Q:$Q,PPTO_GENERADOR!$E:$E,"-",0),"-") -> 1
A23: PTO-0105 | B23: MAT | C23: OTR | D23: MAT-0013 | E23: =IFERROR(VLOOKUP(D23,MATERIALES!A:B,2,FALSE),"?") -> Escalera | G23: 0.5 | H23: 0 | I23: =IFERROR(VLOOKUP(D23,MATERIALES!A:D,4,FALSE),0) -> 252455.04 | J23: =G23*I23*(1+H23) -> 126227.52 | K23: =A23&"|"&B23 -> PTO-0105|MAT | L23: =COUNTIFS($K$2:K23,K23) -> 6 | M23: =K23&"|"&L23 -> PTO-0105|MAT|6 | N23: =IFERROR(VLOOKUP(A23,PARTIDAS!A:F,6,FALSE),0) -> 1 | O23: =IF(C23="ALB",IF(N23=0,0,G23/N23),0) -> 0 | P23: =IFERROR(_xlfn.XLOOKUP(A23,PPTO_GENERADOR!$Q:$Q,PPTO_GENERADOR!$E:$E,"-",0),"-") -> 1
A24: PTO-0105 | B24: MO | C24: OTR | D24: SUB-0002 | E24: =IFERROR(VLOOKUP(D24,SUBCONTRATOS_PRY!A:B,2,FALSE),"?") -> Flete madera | F24: j | G24: 2 | H24: 0 | I24: =IFERROR(VLOOKUP(D24,SUBCONTRATOS_PRY!A:D,4,FALSE),0) -> 250000 | J24: =G24*I24*(1+H24) -> 500000 | K24: =A24&"|"&B24 -> PTO-0105|MO | L24: =COUNTIFS($K$2:K24,K24) -> 1 | M24: =K24&"|"&L24 -> PTO-0105|MO|1 | N24: =IFERROR(VLOOKUP(A24,PARTIDAS!A:F,6,FALSE),0) -> 1 | O24: =IF(C24="ALB",IF(N24=0,0,G24/N24),0) -> 0 | P24: =IFERROR(_xlfn.XLOOKUP(A24,PPTO_GENERADOR!$Q:$Q,PPTO_GENERADOR!$E:$E,"-",0),"-") -> 1
A25: PTO-0105 | B25: MAT | C25: COR | D25: MAT-0014 | E25: =IFERROR(VLOOKUP(D25,MATERIALES!A:B,2,FALSE),"?") -> Materiales varios | G25: 1 | H25: 0 | I25: =IFERROR(VLOOKUP(D25,MATERIALES!A:D,4,FALSE),0) -> 100000 | J25: =G25*I25*(1+H25) -> 100000 | K25: =A25&"|"&B25 -> PTO-0105|MAT | L25: =COUNTIFS($K$2:K25,K25) -> 7 | M25: =K25&"|"&L25 -> PTO-0105|MAT|7 | N25: =IFERROR(VLOOKUP(A25,PARTIDAS!A:F,6,FALSE),0) -> 1 | O25: =IF(C25="ALB",IF(N25=0,0,G25/N25),0) -> 0 | P25: =IFERROR(_xlfn.XLOOKUP(A25,PPTO_GENERADOR!$Q:$Q,PPTO_GENERADOR!$E:$E,"-",0),"-") -> 1
A26: PTO-0105 | B26: MO | C26: ALB | D26: MO-ESP | E26: =IFERROR(VLOOKUP(D26,MANO_DE_OBRA!A:B,2,FALSE),"?") -> ESPECIALIZADO | F26: j | G26: 12 | H26: 0 | I26: =IFERROR(VLOOKUP(D26,MANO_DE_OBRA!A:C,3,FALSE),0) -> 75113.05 | J26: =G26*I26*(1+H26) -> 901356.6 | K26: =A26&"|"&B26 -> PTO-0105|MO | L26: =COUNTIFS($K$2:K26,K26) -> 2 | M26: =K26&"|"&L26 -> PTO-0105|MO|2 | N26: =IFERROR(VLOOKUP(A26,PARTIDAS!A:F,6,FALSE),0) -> 1 | O26: =IF(C26="ALB",IF(N26=0,0,G26/N26),0) -> 12 | P26: =IFERROR(_xlfn.XLOOKUP(A26,PPTO_GENERADOR!$Q:$Q,PPTO_GENERADOR!$E:$E,"-",0),"-") -> 1
A27: PTO-0105 | B27: MO | C27: ALB | D27: MO-OFI | E27: =IFERROR(VLOOKUP(D27,MANO_DE_OBRA!A:B,2,FALSE),"?") -> OFICIAL | F27: j | G27: 19 | H27: 0 | I27: =IFERROR(VLOOKUP(D27,MANO_DE_OBRA!A:C,3,FALSE),0) -> 65360.25 | J27: =G27*I27*(1+H27) -> 1241844.8 | K27: =A27&"|"&B27 -> PTO-0105|MO | L27: =COUNTIFS($K$2:K27,K27) -> 3 | M27: =K27&"|"&L27 -> PTO-0105|MO|3 | N27: =IFERROR(VLOOKUP(A27,PARTIDAS!A:F,6,FALSE),0) -> 1 | O27: =IF(C27="ALB",IF(N27=0,0,G27/N27),0) -> 19 | P27: =IFERROR(_xlfn.XLOOKUP(A27,PPTO_GENERADOR!$Q:$Q,PPTO_GENERADOR!$E:$E,"-",0),"-") -> 1
A28: PTO-0105 | B28: MO | C28: ALB | D28: MO-MED | E28: =IFERROR(VLOOKUP(D28,MANO_DE_OBRA!A:B,2,FALSE),"?") -> MEDIO OFICIAL | F28: j | G28: 5 | H28: 0 | I28: =IFERROR(VLOOKUP(D28,MANO_DE_OBRA!A:C,3,FALSE),0) -> 54784.07 | J28: =G28*I28*(1+H28) -> 273920.35 | K28: =A28&"|"&B28 -> PTO-0105|MO | L28: =COUNTIFS($K$2:K28,K28) -> 4 | M28: =K28&"|"&L28 -> PTO-0105|MO|4 | N28: =IFERROR(VLOOKUP(A28,PARTIDAS!A:F,6,FALSE),0) -> 1 | O28: =IF(C28="ALB",IF(N28=0,0,G28/N28),0) -> 5 | P28: =IFERROR(_xlfn.XLOOKUP(A28,PPTO_GENERADOR!$Q:$Q,PPTO_GENERADOR!$E:$E,"-",0),"-") -> 1
A29: PTO-0105 | B29: MO | C29: ALB | D29: MO-AYU | E29: =IFERROR(VLOOKUP(D29,MANO_DE_OBRA!A:B,2,FALSE),"?") -> AYUDANTE | F29: j | G29: 12 | H29: 0 | I29: =IFERROR(VLOOKUP(D29,MANO_DE_OBRA!A:C,3,FALSE),0) -> 49934.24 | J29: =G29*I29*(1+H29) -> 599210.88 | K29: =A29&"|"&B29 -> PTO-0105|MO | L29: =COUNTIFS($K$2:K29,K29) -> 5 | M29: =K29&"|"&L29 -> PTO-0105|MO|5 | N29: =IFERROR(VLOOKUP(A29,PARTIDAS!A:F,6,FALSE),0) -> 1 | O29: =IF(C29="ALB",IF(N29=0,0,G29/N29),0) -> 12 | P29: =IFERROR(_xlfn.XLOOKUP(A29,PPTO_GENERADOR!$Q:$Q,PPTO_GENERADOR!$E:$E,"-",0),"-") -> 1
A30: PTO-0105 | B30: MAT | C30: OTR | D30: MAT-0015 | E30: =IFERROR(VLOOKUP(D30,MATERIALES!A:B,2,FALSE),"?") -> Rollo de cable TPR 3 x 2,5 | G30: 1 | H30: 0 | I30: =IFERROR(VLOOKUP(D30,MATERIALES!A:D,4,FALSE),0) -> 214876.03 | J30: =G30*I30*(1+H30) -> 214876.03 | K30: =A30&"|"&B30 -> PTO-0105|MAT | L30: =COUNTIFS($K$2:K30,K30) -> 8 | M30: =K30&"|"&L30 -> PTO-0105|MAT|8 | N30: =IFERROR(VLOOKUP(A30,PARTIDAS!A:F,6,FALSE),0) -> 1 | O30: =IF(C30="ALB",IF(N30=0,0,G30/N30),0) -> 0 | P30: =IFERROR(_xlfn.XLOOKUP(A30,PPTO_GENERADOR!$Q:$Q,PPTO_GENERADOR!$E:$E,"-",0),"-") -> 1
A31: PTO-0105 | B31: MAT | C31: OTR | D31: MAT-0016 | E31: =IFERROR(VLOOKUP(D31,MATERIALES!A:B,2,FALSE),"?") -> Zocalo E27 | G31: 10 | H31: 0 | I31: =IFERROR(VLOOKUP(D31,MATERIALES!A:D,4,FALSE),0) -> 369.8347 | J31: =G31*I31*(1+H31) -> 3698.347 | K31: =A31&"|"&B31 -> PTO-0105|MAT | L31: =COUNTIFS($K$2:K31,K31) -> 9 | M31: =K31&"|"&L31 -> PTO-0105|MAT|9 | N31: =IFERROR(VLOOKUP(A31,PARTIDAS!A:F,6,FALSE),0) -> 1 | O31: =IF(C31="ALB",IF(N31=0,0,G31/N31),0) -> 0 | P31: =IFERROR(_xlfn.XLOOKUP(A31,PPTO_GENERADOR!$Q:$Q,PPTO_GENERADOR!$E:$E,"-",0),"-") -> 1
A32: PTO-0105 | B32: MAT | C32: OTR | D32: MAT-0017 | E32: =IFERROR(VLOOKUP(D32,MATERIALES!A:B,2,FALSE),"?") -> Lampara Led 12 w | G32: 10 | H32: 0 | I32: =IFERROR(VLOOKUP(D32,MATERIALES!A:D,4,FALSE),0) -> 2363.6364 | J32: =G32*I32*(1+H32) -> 23636.364 | K32: =A32&"|"&B32 -> PTO-0105|MAT | L32: =COUNTIFS($K$2:K32,K32) -> 10 | M32: =K32&"|"&L32 -> PTO-0105|MAT|10 | N32: =IFERROR(VLOOKUP(A32,PARTIDAS!A:F,6,FALSE),0) -> 1 | O32: =IF(C32="ALB",IF(N32=0,0,G32/N32),0) -> 0 | P32: =IFERROR(_xlfn.XLOOKUP(A32,PPTO_GENERADOR!$Q:$Q,PPTO_GENERADOR!$E:$E,"-",0),"-") -> 1
A33: PTO-0105 | B33: MAT | C33: OTR | D33: MAT-0018 | E33: =IFERROR(VLOOKUP(D33,MATERIALES!A:B,2,FALSE),"?") -> Mat. Elect. (tomas, enchufes, etc.) | G33: 0.25 | H33: 0 | I33: =IFERROR(VLOOKUP(D33,MATERIALES!A:D,4,FALSE),0) -> 242210.74 | J33: =G33*I33*(1+H33) -> 60552.686 | K33: =A33&"|"&B33 -> PTO-0105|MAT | L33: =COUNTIFS($K$2:K33,K33) -> 11 | M33: =K33&"|"&L33 -> PTO-0105|MAT|11 | N33: =IFERROR(VLOOKUP(A33,PARTIDAS!A:F,6,FALSE),0) -> 1 | O33: =IF(C33="ALB",IF(N33=0,0,G33/N33),0) -> 0 | P33: =IFERROR(_xlfn.XLOOKUP(A33,PPTO_GENERADOR!$Q:$Q,PPTO_GENERADOR!$E:$E,"-",0),"-") -> 1
A34: PTO-0105 | B34: MAT | C34: OTR | D34: MAT-0019 | E34: =IFERROR(VLOOKUP(D34,MATERIALES!A:B,2,FALSE),"?") -> Materiales Sanit | G34: 1 | H34: 0 | I34: =IFERROR(VLOOKUP(D34,MATERIALES!A:D,4,FALSE),0) -> 500000 | J34: =G34*I34*(1+H34) -> 500000 | K34: =A34&"|"&B34 -> PTO-0105|MAT | L34: =COUNTIFS($K$2:K34,K34) -> 12 | M34: =K34&"|"&L34 -> PTO-0105|MAT|12 | N34: =IFERROR(VLOOKUP(A34,PARTIDAS!A:F,6,FALSE),0) -> 1 | O34: =IF(C34="ALB",IF(N34=0,0,G34/N34),0) -> 0 | P34: =IFERROR(_xlfn.XLOOKUP(A34,PPTO_GENERADOR!$Q:$Q,PPTO_GENERADOR!$E:$E,"-",0),"-") -> 1
A35: PTO-0105 | B35: MAT | C35: OTR | D35: MAT-0020 | E35: =IFERROR(VLOOKUP(D35,MATERIALES!A:B,2,FALSE),"?") -> Inodoro | G35: 2 | H35: 0 | I35: =IFERROR(VLOOKUP(D35,MATERIALES!A:D,4,FALSE),0) -> 100000 | J35: =G35*I35*(1+H35) -> 200000 | K35: =A35&"|"&B35 -> PTO-0105|MAT | L35: =COUNTIFS($K$2:K35,K35) -> 13 | M35: =K35&"|"&L35 -> PTO-0105|MAT|13 | N35: =IFERROR(VLOOKUP(A35,PARTIDAS!A:F,6,FALSE),0) -> 1 | O35: =IF(C35="ALB",IF(N35=0,0,G35/N35),0) -> 0 | P35: =IFERROR(_xlfn.XLOOKUP(A35,PPTO_GENERADOR!$Q:$Q,PPTO_GENERADOR!$E:$E,"-",0),"-") -> 1
A36: PTO-0105 | B36: MAT | C36: OTR | D36: MAT-0021 | E36: =IFERROR(VLOOKUP(D36,MATERIALES!A:B,2,FALSE),"?") -> Mochila plastico | G36: 2 | H36: 0 | I36: =IFERROR(VLOOKUP(D36,MATERIALES!A:D,4,FALSE),0) -> 25000 | J36: =G36*I36*(1+H36) -> 50000 | K36: =A36&"|"&B36 -> PTO-0105|MAT | L36: =COUNTIFS($K$2:K36,K36) -> 14 | M36: =K36&"|"&L36 -> PTO-0105|MAT|14 | N36: =IFERROR(VLOOKUP(A36,PARTIDAS!A:F,6,FALSE),0) -> 1 | O36: =IF(C36="ALB",IF(N36=0,0,G36/N36),0) -> 0 | P36: =IFERROR(_xlfn.XLOOKUP(A36,PPTO_GENERADOR!$Q:$Q,PPTO_GENERADOR!$E:$E,"-",0),"-") -> 1
A37: PTO-0105 | B37: MAT | C37: OTR | D37: MAT-0022 | E37: =IFERROR(VLOOKUP(D37,MATERIALES!A:B,2,FALSE),"?") -> Bacha | G37: 2 | H37: 0 | I37: =IFERROR(VLOOKUP(D37,MATERIALES!A:D,4,FALSE),0) -> 24793.388 | J37: =G37*I37*(1+H37) -> 49586.777 | K37: =A37&"|"&B37 -> PTO-0105|MAT | L37: =COUNTIFS($K$2:K37,K37) -> 15 | M37: =K37&"|"&L37 -> PTO-0105|MAT|15 | N37: =IFERROR(VLOOKUP(A37,PARTIDAS!A:F,6,FALSE),0) -> 1 | O37: =IF(C37="ALB",IF(N37=0,0,G37/N37),0) -> 0 | P37: =IFERROR(_xlfn.XLOOKUP(A37,PPTO_GENERADOR!$Q:$Q,PPTO_GENERADOR!$E:$E,"-",0),"-") -> 1
A38: PTO-0105 | B38: MAT | C38: OTR | D38: MAT-0023 | E38: =IFERROR(VLOOKUP(D38,MATERIALES!A:B,2,FALSE),"?") -> Termo electrico 40 lts | G38: 1 | H38: 0 | I38: =IFERROR(VLOOKUP(D38,MATERIALES!A:D,4,FALSE),0) -> 200000 | J38: =G38*I38*(1+H38) -> 200000 | K38: =A38&"|"&B38 -> PTO-0105|MAT | L38: =COUNTIFS($K$2:K38,K38) -> 16 | M38: =K38&"|"&L38 -> PTO-0105|MAT|16 | N38: =IFERROR(VLOOKUP(A38,PARTIDAS!A:F,6,FALSE),0) -> 1 | O38: =IF(C38="ALB",IF(N38=0,0,G38/N38),0) -> 0 | P38: =IFERROR(_xlfn.XLOOKUP(A38,PPTO_GENERADOR!$Q:$Q,PPTO_GENERADOR!$E:$E,"-",0),"-") -> 1
A39: PTO-0105 | B39: EQ | D39: EQ-0003 | E39: =IFERROR(VLOOKUP(D39,EQUIPOS!A:B,2,FALSE),"?") -> Herramientas/consumibles - Obrador colgante, pañol y ducha | G39: 1 | H39: 0 | I39: =IFERROR(VLOOKUP(D39,EQUIPOS!A:C,3,FALSE),0) -> 88757.838 | J39: =G39*I39*(1+H39) -> 88757.838 | K39: =A39&"|"&B39 -> PTO-0105|EQ | L39: =COUNTIFS($K$2:K39,K39) -> 1 | M39: =K39&"|"&L39 -> PTO-0105|EQ|1 | N39: =IFERROR(VLOOKUP(A39,PARTIDAS!A:F,6,FALSE),0) -> 1 | O39: =IF(C39="ALB",IF(N39=0,0,G39/N39),0) -> 0 | P39: =IFERROR(_xlfn.XLOOKUP(A39,PPTO_GENERADOR!$Q:$Q,PPTO_GENERADOR!$E:$E,"-",0),"-") -> 1
A40: PTO-0106 | B40: MO | C40: OTR | D40: SUB-0003 | E40: =IFERROR(VLOOKUP(D40,SUBCONTRATOS_PRY!A:B,2,FALSE),"?") -> Baño portatil / Ducha | F40: j | G40: 1 | H40: 0 | I40: =IFERROR(VLOOKUP(D40,SUBCONTRATOS_PRY!A:D,4,FALSE),0) -> 295488.56 | J40: =G40*I40*(1+H40) -> 295488.56 | K40: =A40&"|"&B40 -> PTO-0106|MO | L40: =COUNTIFS($K$2:K40,K40) -> 1 | M40: =K40&"|"&L40 -> PTO-0106|MO|1 | N40: =IFERROR(VLOOKUP(A40,PARTIDAS!A:F,6,FALSE),0) -> 1 | O40: =IF(C40="ALB",IF(N40=0,0,G40/N40),0) -> 0 | P40: =IFERROR(_xlfn.XLOOKUP(A40,PPTO_GENERADOR!$Q:$Q,PPTO_GENERADOR!$E:$E,"-",0),"-") -> 3
A41: PTO-0106 | B41: MO | C41: OTR | D41: SUB-0004 | E41: =IFERROR(VLOOKUP(D41,SUBCONTRATOS_PRY!A:B,2,FALSE),"?") -> Traslado flete entrega/ retiro | F41: j | G41: 1 | H41: 0 | I41: =IFERROR(VLOOKUP(D41,SUBCONTRATOS_PRY!A:D,4,FALSE),0) -> 16416.031 | J41: =G41*I41*(1+H41) -> 16416.031 | K41: =A41&"|"&B41 -> PTO-0106|MO | L41: =COUNTIFS($K$2:K41,K41) -> 2 | M41: =K41&"|"&L41 -> PTO-0106|MO|2 | N41: =IFERROR(VLOOKUP(A41,PARTIDAS!A:F,6,FALSE),0) -> 1 | O41: =IF(C41="ALB",IF(N41=0,0,G41/N41),0) -> 0 | P41: =IFERROR(_xlfn.XLOOKUP(A41,PPTO_GENERADOR!$Q:$Q,PPTO_GENERADOR!$E:$E,"-",0),"-") -> 3
A42: PTO-0107 | B42: MAT | C42: COR | D42: MAT-0024 | E42: =IFERROR(VLOOKUP(D42,MATERIALES!A:B,2,FALSE),"?") -> Pilar de obra, albañileria | G42: 2 | H42: 0 | I42: =IFERROR(VLOOKUP(D42,MATERIALES!A:D,4,FALSE),0) -> 25000 | J42: =G42*I42*(1+H42) -> 50000 | K42: =A42&"|"&B42 -> PTO-0107|MAT | L42: =COUNTIFS($K$2:K42,K42) -> 1 | M42: =K42&"|"&L42 -> PTO-0107|MAT|1 | N42: =IFERROR(VLOOKUP(A42,PARTIDAS!A:F,6,FALSE),0) -> 1 | O42: =IF(C42="ALB",IF(N42=0,0,G42/N42),0) -> 0 | P42: =IFERROR(_xlfn.XLOOKUP(A42,PPTO_GENERADOR!$Q:$Q,PPTO_GENERADOR!$E:$E,"-",0),"-") -> 1
A43: PTO-0107 | B43: MO | C43: ALB | D43: MO-OFI | E43: =IFERROR(VLOOKUP(D43,MANO_DE_OBRA!A:B,2,FALSE),"?") -> OFICIAL | F43: j | G43: 4 | H43: 0 | I43: =IFERROR(VLOOKUP(D43,MANO_DE_OBRA!A:C,3,FALSE),0) -> 65360.25 | J43: =G43*I43*(1+H43) -> 261441 | K43: =A43&"|"&B43 -> PTO-0107|MO | L43: =COUNTIFS($K$2:K43,K43) -> 1 | M43: =K43&"|"&L43 -> PTO-0107|MO|1 | N43: =IFERROR(VLOOKUP(A43,PARTIDAS!A:F,6,FALSE),0) -> 1 | O43: =IF(C43="ALB",IF(N43=0,0,G43/N43),0) -> 4 | P43: =IFERROR(_xlfn.XLOOKUP(A43,PPTO_GENERADOR!$Q:$Q,PPTO_GENERADOR!$E:$E,"-",0),"-") -> 1
A44: PTO-0107 | B44: MO | C44: ALB | D44: MO-AYU | E44: =IFERROR(VLOOKUP(D44,MANO_DE_OBRA!A:B,2,FALSE),"?") -> AYUDANTE | F44: j | G44: 2 | H44: 0 | I44: =IFERROR(VLOOKUP(D44,MANO_DE_OBRA!A:C,3,FALSE),0) -> 49934.24 | J44: =G44*I44*(1+H44) -> 99868.48 | K44: =A44&"|"&B44 -> PTO-0107|MO | L44: =COUNTIFS($K$2:K44,K44) -> 2 | M44: =K44&"|"&L44 -> PTO-0107|MO|2 | N44: =IFERROR(VLOOKUP(A44,PARTIDAS!A:F,6,FALSE),0) -> 1 | O44: =IF(C44="ALB",IF(N44=0,0,G44/N44),0) -> 2 | P44: =IFERROR(_xlfn.XLOOKUP(A44,PPTO_GENERADOR!$Q:$Q,PPTO_GENERADOR!$E:$E,"-",0),"-") -> 1
A45: PTO-0107 | B45: MAT | C45: OTR | D45: MAT-0025 | E45: =IFERROR(VLOOKUP(D45,MATERIALES!A:B,2,FALSE),"?") -> Kit medidor pilar Edenor Conextube | G45: 1 | H45: 0 | I45: =IFERROR(VLOOKUP(D45,MATERIALES!A:D,4,FALSE),0) -> 150000 | J45: =G45*I45*(1+H45) -> 150000 | K45: =A45&"|"&B45 -> PTO-0107|MAT | L45: =COUNTIFS($K$2:K45,K45) -> 2 | M45: =K45&"|"&L45 -> PTO-0107|MAT|2 | N45: =IFERROR(VLOOKUP(A45,PARTIDAS!A:F,6,FALSE),0) -> 1 | O45: =IF(C45="ALB",IF(N45=0,0,G45/N45),0) -> 0 | P45: =IFERROR(_xlfn.XLOOKUP(A45,PPTO_GENERADOR!$Q:$Q,PPTO_GENERADOR!$E:$E,"-",0),"-") -> 1
A46: PTO-0107 | B46: MAT | C46: OTR | D46: MAT-0026 | E46: =IFERROR(VLOOKUP(D46,MATERIALES!A:B,2,FALSE),"?") -> Kit jabalina + caja + toma cable | G46: 1 | H46: 0 | I46: =IFERROR(VLOOKUP(D46,MATERIALES!A:D,4,FALSE),0) -> 15000 | J46: =G46*I46*(1+H46) -> 15000 | K46: =A46&"|"&B46 -> PTO-0107|MAT | L46: =COUNTIFS($K$2:K46,K46) -> 3 | M46: =K46&"|"&L46 -> PTO-0107|MAT|3 | N46: =IFERROR(VLOOKUP(A46,PARTIDAS!A:F,6,FALSE),0) -> 1 | O46: =IF(C46="ALB",IF(N46=0,0,G46/N46),0) -> 0 | P46: =IFERROR(_xlfn.XLOOKUP(A46,PPTO_GENERADOR!$Q:$Q,PPTO_GENERADOR!$E:$E,"-",0),"-") -> 1
A47: PTO-0107 | B47: MAT | C47: OTR | D47: MAT-0027 | E47: =IFERROR(VLOOKUP(D47,MATERIALES!A:B,2,FALSE),"?") -> Cable subterraneo 5 x 10 mm2 | G47: 20 | H47: 0 | I47: =IFERROR(VLOOKUP(D47,MATERIALES!A:D,4,FALSE),0) -> 16528.926 | J47: =G47*I47*(1+H47) -> 330578.51 | K47: =A47&"|"&B47 -> PTO-0107|MAT | L47: =COUNTIFS($K$2:K47,K47) -> 4 | M47: =K47&"|"&L47 -> PTO-0107|MAT|4 | N47: =IFERROR(VLOOKUP(A47,PARTIDAS!A:F,6,FALSE),0) -> 1 | O47: =IF(C47="ALB",IF(N47=0,0,G47/N47),0) -> 0 | P47: =IFERROR(_xlfn.XLOOKUP(A47,PPTO_GENERADOR!$Q:$Q,PPTO_GENERADOR!$E:$E,"-",0),"-") -> 1
A48: PTO-0107 | B48: MAT | C48: OTR | D48: MAT-0028 | E48: =IFERROR(VLOOKUP(D48,MATERIALES!A:B,2,FALSE),"?") -> Tablero de obra | G48: 1 | H48: 0 | I48: =IFERROR(VLOOKUP(D48,MATERIALES!A:D,4,FALSE),0) -> 300000 | J48: =G48*I48*(1+H48) -> 300000 | K48: =A48&"|"&B48 -> PTO-0107|MAT | L48: =COUNTIFS($K$2:K48,K48) -> 5 | M48: =K48&"|"&L48 -> PTO-0107|MAT|5 | N48: =IFERROR(VLOOKUP(A48,PARTIDAS!A:F,6,FALSE),0) -> 1 | O48: =IF(C48="ALB",IF(N48=0,0,G48/N48),0) -> 0 | P48: =IFERROR(_xlfn.XLOOKUP(A48,PPTO_GENERADOR!$Q:$Q,PPTO_GENERADOR!$E:$E,"-",0),"-") -> 1
A49: PTO-0107 | B49: MO | C49: ALB | D49: MO-ESP | E49: =IFERROR(VLOOKUP(D49,MANO_DE_OBRA!A:B,2,FALSE),"?") -> ESPECIALIZADO | F49: j | G49: 2 | H49: 0 | I49: =IFERROR(VLOOKUP(D49,MANO_DE_OBRA!A:C,3,FALSE),0) -> 75113.05 | J49: =G49*I49*(1+H49) -> 150226.1 | K49: =A49&"|"&B49 -> PTO-0107|MO | L49: =COUNTIFS($K$2:K49,K49) -> 3 | M49: =K49&"|"&L49 -> PTO-0107|MO|3 | N49: =IFERROR(VLOOKUP(A49,PARTIDAS!A:F,6,FALSE),0) -> 1 | O49: =IF(C49="ALB",IF(N49=0,0,G49/N49),0) -> 2 | P49: =IFERROR(_xlfn.XLOOKUP(A49,PPTO_GENERADOR!$Q:$Q,PPTO_GENERADOR!$E:$E,"-",0),"-") -> 1
A50: PTO-0107 | B50: EQ | D50: EQ-0004 | E50: =IFERROR(VLOOKUP(D50,EQUIPOS!A:B,2,FALSE),"?") -> Herramientas/consumibles - Conexión pilar y luz de obra + Tablero d | G50: 1 | H50: 0 | I50: =IFERROR(VLOOKUP(D50,EQUIPOS!A:C,3,FALSE),0) -> 20356.711 | J50: =G50*I50*(1+H50) -> 20356.711 | K50: =A50&"|"&B50 -> PTO-0107|EQ | L50: =COUNTIFS($K$2:K50,K50) -> 1 | M50: =K50&"|"&L50 -> PTO-0107|EQ|1 | N50: =IFERROR(VLOOKUP(A50,PARTIDAS!A:F,6,FALSE),0) -> 1 | O50: =IF(C50="ALB",IF(N50=0,0,G50/N50),0) -> 0 | P50: =IFERROR(_xlfn.XLOOKUP(A50,PPTO_GENERADOR!$Q:$Q,PPTO_GENERADOR!$E:$E,"-",0),"-") -> 1
A51: PTO-0108 | B51: MAT | C51: OTR | D51: MAT-0029 | E51: =IFERROR(VLOOKUP(D51,MATERIALES!A:B,2,FALSE),"?") -> Tanque de Bombeo 500 lts (reutilizado) | G51: 1 | H51: 0 | I51: =IFERROR(VLOOKUP(D51,MATERIALES!A:D,4,FALSE),0) -> 150000 | J51: =G51*I51*(1+H51) -> 150000 | K51: =A51&"|"&B51 -> PTO-0108|MAT | L51: =COUNTIFS($K$2:K51,K51) -> 1 | M51: =K51&"|"&L51 -> PTO-0108|MAT|1 | N51: =IFERROR(VLOOKUP(A51,PARTIDAS!A:F,6,FALSE),0) -> 1 | O51: =IF(C51="ALB",IF(N51=0,0,G51/N51),0) -> 0 | P51: =IFERROR(_xlfn.XLOOKUP(A51,PPTO_GENERADOR!$Q:$Q,PPTO_GENERADOR!$E:$E,"-",0),"-") -> 1
A52: PTO-0108 | B52: MAT | C52: OTR | D52: MAT-0030 | E52: =IFERROR(VLOOKUP(D52,MATERIALES!A:B,2,FALSE),"?") -> Bomba pres (reutilizada) | G52: 1 | H52: 0 | I52: =IFERROR(VLOOKUP(D52,MATERIALES!A:D,4,FALSE),0) -> 200000 | J52: =G52*I52*(1+H52) -> 200000 | K52: =A52&"|"&B52 -> PTO-0108|MAT | L52: =COUNTIFS($K$2:K52,K52) -> 2 | M52: =K52&"|"&L52 -> PTO-0108|MAT|2 | N52: =IFERROR(VLOOKUP(A52,PARTIDAS!A:F,6,FALSE),0) -> 1 | O52: =IF(C52="ALB",IF(N52=0,0,G52/N52),0) -> 0 | P52: =IFERROR(_xlfn.XLOOKUP(A52,PPTO_GENERADOR!$Q:$Q,PPTO_GENERADOR!$E:$E,"-",0),"-") -> 1
A53: PTO-0108 | B53: MAT | C53: OTR | D53: MAT-0031 | E53: =IFERROR(VLOOKUP(D53,MATERIALES!A:B,2,FALSE),"?") -> Flotante mecanico 1" + boya | G53: 1 | H53: 0 | I53: =IFERROR(VLOOKUP(D53,MATERIALES!A:D,4,FALSE),0) -> 50000 | J53: =G53*I53*(1+H53) -> 50000 | K53: =A53&"|"&B53 -> PTO-0108|MAT | L53: =COUNTIFS($K$2:K53,K53) -> 3 | M53: =K53&"|"&L53 -> PTO-0108|MAT|3 | N53: =IFERROR(VLOOKUP(A53,PARTIDAS!A:F,6,FALSE),0) -> 1 | O53: =IF(C53="ALB",IF(N53=0,0,G53/N53),0) -> 0 | P53: =IFERROR(_xlfn.XLOOKUP(A53,PPTO_GENERADOR!$Q:$Q,PPTO_GENERADOR!$E:$E,"-",0),"-") -> 1
A54: PTO-0108 | B54: MAT | C54: OTR | D54: MAT-0032 | E54: =IFERROR(VLOOKUP(D54,MATERIALES!A:B,2,FALSE),"?") -> Flotante automatico | G54: 1 | H54: 0 | I54: =IFERROR(VLOOKUP(D54,MATERIALES!A:D,4,FALSE),0) -> 10000 | J54: =G54*I54*(1+H54) -> 10000 | K54: =A54&"|"&B54 -> PTO-0108|MAT | L54: =COUNTIFS($K$2:K54,K54) -> 4 | M54: =K54&"|"&L54 -> PTO-0108|MAT|4 | N54: =IFERROR(VLOOKUP(A54,PARTIDAS!A:F,6,FALSE),0) -> 1 | O54: =IF(C54="ALB",IF(N54=0,0,G54/N54),0) -> 0 | P54: =IFERROR(_xlfn.XLOOKUP(A54,PPTO_GENERADOR!$Q:$Q,PPTO_GENERADOR!$E:$E,"-",0),"-") -> 1
A55: PTO-0108 | B55: MAT | C55: OTR | D55: MAT-0033 | E55: =IFERROR(VLOOKUP(D55,MATERIALES!A:B,2,FALSE),"?") -> Caño 3/4" | G55: 10 | H55: 0 | I55: =IFERROR(VLOOKUP(D55,MATERIALES!A:D,4,FALSE),0) -> 10000 | J55: =G55*I55*(1+H55) -> 100000 | K55: =A55&"|"&B55 -> PTO-0108|MAT | L55: =COUNTIFS($K$2:K55,K55) -> 5 | M55: =K55&"|"&L55 -> PTO-0108|MAT|5 | N55: =IFERROR(VLOOKUP(A55,PARTIDAS!A:F,6,FALSE),0) -> 1 | O55: =IF(C55="ALB",IF(N55=0,0,G55/N55),0) -> 0 | P55: =IFERROR(_xlfn.XLOOKUP(A55,PPTO_GENERADOR!$Q:$Q,PPTO_GENERADOR!$E:$E,"-",0),"-") -> 1
A56: PTO-0108 | B56: MAT | C56: OTR | D56: MAT-0034 | E56: =IFERROR(VLOOKUP(D56,MATERIALES!A:B,2,FALSE),"?") -> Val. esf doble media union 1" | G56: 3 | H56: 0 | I56: =IFERROR(VLOOKUP(D56,MATERIALES!A:D,4,FALSE),0) -> 15000 | J56: =G56*I56*(1+H56) -> 45000 | K56: =A56&"|"&B56 -> PTO-0108|MAT | L56: =COUNTIFS($K$2:K56,K56) -> 6 | M56: =K56&"|"&L56 -> PTO-0108|MAT|6 | N56: =IFERROR(VLOOKUP(A56,PARTIDAS!A:F,6,FALSE),0) -> 1 | O56: =IF(C56="ALB",IF(N56=0,0,G56/N56),0) -> 0 | P56: =IFERROR(_xlfn.XLOOKUP(A56,PPTO_GENERADOR!$Q:$Q,PPTO_GENERADOR!$E:$E,"-",0),"-") -> 1
A57: PTO-0108 | B57: MAT | C57: OTR | D57: MAT-0035 | E57: =IFERROR(VLOOKUP(D57,MATERIALES!A:B,2,FALSE),"?") -> Canilla de pvc | G57: 6 | H57: 0 | I57: =IFERROR(VLOOKUP(D57,MATERIALES!A:D,4,FALSE),0) -> 2000 | J57: =G57*I57*(1+H57) -> 12000 | K57: =A57&"|"&B57 -> PTO-0108|MAT | L57: =COUNTIFS($K$2:K57,K57) -> 7 | M57: =K57&"|"&L57 -> PTO-0108|MAT|7 | N57: =IFERROR(VLOOKUP(A57,PARTIDAS!A:F,6,FALSE),0) -> 1 | O57: =IF(C57="ALB",IF(N57=0,0,G57/N57),0) -> 0 | P57: =IFERROR(_xlfn.XLOOKUP(A57,PPTO_GENERADOR!$Q:$Q,PPTO_GENERADOR!$E:$E,"-",0),"-") -> 1
A58: PTO-0108 | B58: MAT | C58: OTR | D58: MAT-0036 | E58: =IFERROR(VLOOKUP(D58,MATERIALES!A:B,2,FALSE),"?") -> Desperdicio | G58: 0.2 | H58: 0 | I58: =IFERROR(VLOOKUP(D58,MATERIALES!A:D,4,FALSE),0) -> 567000 | J58: =G58*I58*(1+H58) -> 113400 | K58: =A58&"|"&B58 -> PTO-0108|MAT | L58: =COUNTIFS($K$2:K58,K58) -> 8 | M58: =K58&"|"&L58 -> PTO-0108|MAT|8 | N58: =IFERROR(VLOOKUP(A58,PARTIDAS!A:F,6,FALSE),0) -> 1 | O58: =IF(C58="ALB",IF(N58=0,0,G58/N58),0) -> 0 | P58: =IFERROR(_xlfn.XLOOKUP(A58,PPTO_GENERADOR!$Q:$Q,PPTO_GENERADOR!$E:$E,"-",0),"-") -> 1
A59: PTO-0108 | B59: MO | C59: ALB | D59: MO-ESP | E59: =IFERROR(VLOOKUP(D59,MANO_DE_OBRA!A:B,2,FALSE),"?") -> ESPECIALIZADO | F59: j | G59: 3 | H59: 0 | I59: =IFERROR(VLOOKUP(D59,MANO_DE_OBRA!A:C,3,FALSE),0) -> 75113.05 | J59: =G59*I59*(1+H59) -> 225339.15 | K59: =A59&"|"&B59 -> PTO-0108|MO | L59: =COUNTIFS($K$2:K59,K59) -> 1 | M59: =K59&"|"&L59 -> PTO-0108|MO|1 | N59: =IFERROR(VLOOKUP(A59,PARTIDAS!A:F,6,FALSE),0) -> 1 | O59: =IF(C59="ALB",IF(N59=0,0,G59/N59),0) -> 3 | P59: =IFERROR(_xlfn.XLOOKUP(A59,PPTO_GENERADOR!$Q:$Q,PPTO_GENERADOR!$E:$E,"-",0),"-") -> 1
A60: PTO-0108 | B60: MO | C60: ALB | D60: MO-OFI | E60: =IFERROR(VLOOKUP(D60,MANO_DE_OBRA!A:B,2,FALSE),"?") -> OFICIAL | F60: j | G60: 3 | H60: 0 | I60: =IFERROR(VLOOKUP(D60,MANO_DE_OBRA!A:C,3,FALSE),0) -> 65360.25 | J60: =G60*I60*(1+H60) -> 196080.75 | K60: =A60&"|"&B60 -> PTO-0108|MO | L60: =COUNTIFS($K$2:K60,K60) -> 2 | M60: =K60&"|"&L60 -> PTO-0108|MO|2 | N60: =IFERROR(VLOOKUP(A60,PARTIDAS!A:F,6,FALSE),0) -> 1 | O60: =IF(C60="ALB",IF(N60=0,0,G60/N60),0) -> 3 | P60: =IFERROR(_xlfn.XLOOKUP(A60,PPTO_GENERADOR!$Q:$Q,PPTO_GENERADOR!$E:$E,"-",0),"-") -> 1
A61: PTO-0108 | B61: EQ | D61: EQ-0005 | E61: =IFERROR(VLOOKUP(D61,EQUIPOS!A:B,2,FALSE),"?") -> Herramientas/consumibles - Conexión agua de obra, tanque + bomba | G61: 1 | H61: 0 | I61: =IFERROR(VLOOKUP(D61,EQUIPOS!A:C,3,FALSE),0) -> 16527.298 | J61: =G61*I61*(1+H61) -> 16527.298 | K61: =A61&"|"&B61 -> PTO-0108|EQ | L61: =COUNTIFS($K$2:K61,K61) -> 1 | M61: =K61&"|"&L61 -> PTO-0108|EQ|1 | N61: =IFERROR(VLOOKUP(A61,PARTIDAS!A:F,6,FALSE),0) -> 1 | O61: =IF(C61="ALB",IF(N61=0,0,G61/N61),0) -> 0 | P61: =IFERROR(_xlfn.XLOOKUP(A61,PPTO_GENERADOR!$Q:$Q,PPTO_GENERADOR!$E:$E,"-",0),"-") -> 1
A62: PTO-0109 | B62: MO | C62: OTR | D62: SUB-0005 | E62: =IFERROR(VLOOKUP(D62,SUBCONTRATOS_PRY!A:B,2,FALSE),"?") -> Gestion suministros luz de obra | F62: j | G62: 0.79478827 | H62: 0 | I62: =IFERROR(VLOOKUP(D62,SUBCONTRATOS_PRY!A:D,4,FALSE),0) -> 139065.92 | J62: =G62*I62*(1+H62) -> 110527.96 | K62: =A62&"|"&B62 -> PTO-0109|MO | L62: =COUNTIFS($K$2:K62,K62) -> 1 | M62: =K62&"|"&L62 -> PTO-0109|MO|1 | N62: =IFERROR(VLOOKUP(A62,PARTIDAS!A:F,6,FALSE),0) -> 1 | O62: =IF(C62="ALB",IF(N62=0,0,G62/N62),0) -> 0 | P62: =IFERROR(_xlfn.XLOOKUP(A62,PPTO_GENERADOR!$Q:$Q,PPTO_GENERADOR!$E:$E,"-",0),"-") -> 1
A63: PTO-0109 | B63: MO | C63: OTR | D63: SUB-0006 | E63: =IFERROR(VLOOKUP(D63,SUBCONTRATOS_PRY!A:B,2,FALSE),"?") -> Luz de Obra | F63: j | G63: 1.5895766 | H63: 0 | I63: =IFERROR(VLOOKUP(D63,SUBCONTRATOS_PRY!A:D,4,FALSE),0) -> 100127.46 | J63: =G63*I63*(1+H63) -> 159160.26 | K63: =A63&"|"&B63 -> PTO-0109|MO | L63: =COUNTIFS($K$2:K63,K63) -> 2 | M63: =K63&"|"&L63 -> PTO-0109|MO|2 | N63: =IFERROR(VLOOKUP(A63,PARTIDAS!A:F,6,FALSE),0) -> 1 | O63: =IF(C63="ALB",IF(N63=0,0,G63/N63),0) -> 0 | P63: =IFERROR(_xlfn.XLOOKUP(A63,PPTO_GENERADOR!$Q:$Q,PPTO_GENERADOR!$E:$E,"-",0),"-") -> 1
A64: PTO-0109 | B64: MO | C64: OTR | D64: SUB-0007 | E64: =IFERROR(VLOOKUP(D64,SUBCONTRATOS_PRY!A:B,2,FALSE),"?") -> Medicion PAT luz de obra | F64: j | G64: 0.79478827 | H64: 0 | I64: =IFERROR(VLOOKUP(D64,SUBCONTRATOS_PRY!A:D,4,FALSE),0) -> 87611.528 | J64: =G64*I64*(1+H64) -> 69632.615 | K64: =A64&"|"&B64 -> PTO-0109|MO | L64: =COUNTIFS($K$2:K64,K64) -> 3 | M64: =K64&"|"&L64 -> PTO-0109|MO|3 | N64: =IFERROR(VLOOKUP(A64,PARTIDAS!A:F,6,FALSE),0) -> 1 | O64: =IF(C64="ALB",IF(N64=0,0,G64/N64),0) -> 0 | P64: =IFERROR(_xlfn.XLOOKUP(A64,PPTO_GENERADOR!$Q:$Q,PPTO_GENERADOR!$E:$E,"-",0),"-") -> 1
A65: PTO-0110 | B65: MO | C65: OTR | D65: SUB-0008 | E65: =IFERROR(VLOOKUP(D65,SUBCONTRATOS_PRY!A:B,2,FALSE),"?") -> Total de Obra (3 perforaciones) | F65: j | G65: 1 | H65: 0 | I65: =IFERROR(VLOOKUP(D65,SUBCONTRATOS_PRY!A:D,4,FALSE),0) -> 7800000 | J65: =G65*I65*(1+H65) -> 7800000 | K65: =A65&"|"&B65 -> PTO-0110|MO | L65: =COUNTIFS($K$2:K65,K65) -> 1 | M65: =K65&"|"&L65 -> PTO-0110|MO|1 | N65: =IFERROR(VLOOKUP(A65,PARTIDAS!A:F,6,FALSE),0) -> 1 | O65: =IF(C65="ALB",IF(N65=0,0,G65/N65),0) -> 0 | P65: =IFERROR(_xlfn.XLOOKUP(A65,PPTO_GENERADOR!$Q:$Q,PPTO_GENERADOR!$E:$E,"-",0),"-") -> 1
A66: PTO-0201 | B66: MO | C66: OTR | D66: SUB-0009 | E66: =IFERROR(VLOOKUP(D66,SUBCONTRATOS_PRY!A:B,2,FALSE),"?") -> Desmonte, retiro, aporte y compactación e: 40 cm | F66: j | G66: 1.15 | H66: 0 | I66: =IFERROR(VLOOKUP(D66,SUBCONTRATOS_PRY!A:D,4,FALSE),0) -> 16000 | J66: =G66*I66*(1+H66) -> 18400 | K66: =A66&"|"&B66 -> PTO-0201|MO | L66: =COUNTIFS($K$2:K66,K66) -> 1 | M66: =K66&"|"&L66 -> PTO-0201|MO|1 | N66: =IFERROR(VLOOKUP(A66,PARTIDAS!A:F,6,FALSE),0) -> 1 | O66: =IF(C66="ALB",IF(N66=0,0,G66/N66),0) -> 0 | P66: =IFERROR(_xlfn.XLOOKUP(A66,PPTO_GENERADOR!$Q:$Q,PPTO_GENERADOR!$E:$E,"-",0),"-") -> 1266
A67: PTO-0201 | B67: MO | C67: ALB | D67: MO-AYU | E67: =IFERROR(VLOOKUP(D67,MANO_DE_OBRA!A:B,2,FALSE),"?") -> AYUDANTE | F67: j | G67: 0.1563981 | H67: 0 | I67: =IFERROR(VLOOKUP(D67,MANO_DE_OBRA!A:C,3,FALSE),0) -> 49934.24 | J67: =G67*I67*(1+H67) -> 7809.6203 | K67: =A67&"|"&B67 -> PTO-0201|MO | L67: =COUNTIFS($K$2:K67,K67) -> 2 | M67: =K67&"|"&L67 -> PTO-0201|MO|2 | N67: =IFERROR(VLOOKUP(A67,PARTIDAS!A:F,6,FALSE),0) -> 1 | O67: =IF(C67="ALB",IF(N67=0,0,G67/N67),0) -> 0.1563981 | P67: =IFERROR(_xlfn.XLOOKUP(A67,PPTO_GENERADOR!$Q:$Q,PPTO_GENERADOR!$E:$E,"-",0),"-") -> 1266
A68: PTO-0201 | B68: EQ | D68: EQ-0006 | E68: =IFERROR(VLOOKUP(D68,EQUIPOS!A:B,2,FALSE),"?") -> Herramientas/consumibles - Excavación a maquina para submuración y | G68: 1 | H68: 0 | I68: =IFERROR(VLOOKUP(D68,EQUIPOS!A:C,3,FALSE),0) -> 117.1443 | J68: =G68*I68*(1+H68) -> 117.1443 | K68: =A68&"|"&B68 -> PTO-0201|EQ | L68: =COUNTIFS($K$2:K68,K68) -> 1 | M68: =K68&"|"&L68 -> PTO-0201|EQ|1 | N68: =IFERROR(VLOOKUP(A68,PARTIDAS!A:F,6,FALSE),0) -> 1 | O68: =IF(C68="ALB",IF(N68=0,0,G68/N68),0) -> 0 | P68: =IFERROR(_xlfn.XLOOKUP(A68,PPTO_GENERADOR!$Q:$Q,PPTO_GENERADOR!$E:$E,"-",0),"-") -> 1266
A69: PTO-0203 | B69: MO | C69: ALB | D69: MO-AYU | E69: =IFERROR(VLOOKUP(D69,MANO_DE_OBRA!A:B,2,FALSE),"?") -> AYUDANTE | F69: j | G69: 1 | H69: 0 | I69: =IFERROR(VLOOKUP(D69,MANO_DE_OBRA!A:C,3,FALSE),0) -> 49934.24 | J69: =G69*I69*(1+H69) -> 49934.24 | K69: =A69&"|"&B69 -> PTO-0203|MO | L69: =COUNTIFS($K$2:K69,K69) -> 1 | M69: =K69&"|"&L69 -> PTO-0203|MO|1 | N69: =IFERROR(VLOOKUP(A69,PARTIDAS!A:F,6,FALSE),0) -> 1 | O69: =IF(C69="ALB",IF(N69=0,0,G69/N69),0) -> 1 | P69: =IFERROR(_xlfn.XLOOKUP(A69,PPTO_GENERADOR!$Q:$Q,PPTO_GENERADOR!$E:$E,"-",0),"-") -> 2
A70: PTO-0301 | B70: MAT | C70: OTR | D70: MAT-0037 | E70: =IFERROR(VLOOKUP(D70,MATERIALES!A:B,2,FALSE),"?") -> H13 6.20 | G70: 1 | H70: 0 | I70: =IFERROR(VLOOKUP(D70,MATERIALES!A:D,4,FALSE),0) -> 115100 | J70: =G70*I70*(1+H70) -> 115100 | K70: =A70&"|"&B70 -> PTO-0301|MAT | L70: =COUNTIFS($K$2:K70,K70) -> 1 | M70: =K70&"|"&L70 -> PTO-0301|MAT|1 | N70: =IFERROR(VLOOKUP(A70,PARTIDAS!A:F,6,FALSE),0) -> 1 | O70: =IF(C70="ALB",IF(N70=0,0,G70/N70),0) -> 0 | P70: =IFERROR(_xlfn.XLOOKUP(A70,PPTO_GENERADOR!$Q:$Q,PPTO_GENERADOR!$E:$E,"-",0),"-") -> 35
A71: PTO-0301 | B71: MAT | C71: OTR | D71: MAT-0038 | E71: =IFERROR(VLOOKUP(D71,MATERIALES!A:B,2,FALSE),"?") -> Bombeo | G71: 1 | H71: 0 | I71: =IFERROR(VLOOKUP(D71,MATERIALES!A:D,4,FALSE),0) -> 5330 | J71: =G71*I71*(1+H71) -> 5330 | K71: =A71&"|"&B71 -> PTO-0301|MAT | L71: =COUNTIFS($K$2:K71,K71) -> 2 | M71: =K71&"|"&L71 -> PTO-0301|MAT|2 | N71: =IFERROR(VLOOKUP(A71,PARTIDAS!A:F,6,FALSE),0) -> 1 | O71: =IF(C71="ALB",IF(N71=0,0,G71/N71),0) -> 0 | P71: =IFERROR(_xlfn.XLOOKUP(A71,PPTO_GENERADOR!$Q:$Q,PPTO_GENERADOR!$E:$E,"-",0),"-") -> 35
A72: PTO-0301 | B72: MAT | C72: COR | D72: MAT-0039 | E72: =IFERROR(VLOOKUP(D72,MATERIALES!A:B,2,FALSE),"?") -> Acarreo | G72: 1 | H72: 0 | I72: =IFERROR(VLOOKUP(D72,MATERIALES!A:D,4,FALSE),0) -> 76142.857 | J72: =G72*I72*(1+H72) -> 76142.857 | K72: =A72&"|"&B72 -> PTO-0301|MAT | L72: =COUNTIFS($K$2:K72,K72) -> 3 | M72: =K72&"|"&L72 -> PTO-0301|MAT|3 | N72: =IFERROR(VLOOKUP(A72,PARTIDAS!A:F,6,FALSE),0) -> 1 | O72: =IF(C72="ALB",IF(N72=0,0,G72/N72),0) -> 0 | P72: =IFERROR(_xlfn.XLOOKUP(A72,PPTO_GENERADOR!$Q:$Q,PPTO_GENERADOR!$E:$E,"-",0),"-") -> 35
A73: PTO-0301 | B73: MO | C73: ALB | D73: MO-AYU | E73: =IFERROR(VLOOKUP(D73,MANO_DE_OBRA!A:B,2,FALSE),"?") -> AYUDANTE | F73: j | G73: 1 | H73: 0 | I73: =IFERROR(VLOOKUP(D73,MANO_DE_OBRA!A:C,3,FALSE),0) -> 49934.24 | J73: =G73*I73*(1+H73) -> 49934.24 | K73: =A73&"|"&B73 -> PTO-0301|MO | L73: =COUNTIFS($K$2:K73,K73) -> 1 | M73: =K73&"|"&L73 -> PTO-0301|MO|1 | N73: =IFERROR(VLOOKUP(A73,PARTIDAS!A:F,6,FALSE),0) -> 1 | O73: =IF(C73="ALB",IF(N73=0,0,G73/N73),0) -> 1 | P73: =IFERROR(_xlfn.XLOOKUP(A73,PPTO_GENERADOR!$Q:$Q,PPTO_GENERADOR!$E:$E,"-",0),"-") -> 35
A74: PTO-0301 | B74: EQ | D74: EQ-0007 | E74: =IFERROR(VLOOKUP(D74,EQUIPOS!A:B,2,FALSE),"?") -> Herramientas/consumibles - Hormigón de limpieza - e: 10 cm | G74: 1 | H74: 0 | I74: =IFERROR(VLOOKUP(D74,EQUIPOS!A:C,3,FALSE),0) -> 3697.6064 | J74: =G74*I74*(1+H74) -> 3697.6064 | K74: =A74&"|"&B74 -> PTO-0301|EQ | L74: =COUNTIFS($K$2:K74,K74) -> 1 | M74: =K74&"|"&L74 -> PTO-0301|EQ|1 | N74: =IFERROR(VLOOKUP(A74,PARTIDAS!A:F,6,FALSE),0) -> 1 | O74: =IF(C74="ALB",IF(N74=0,0,G74/N74),0) -> 0 | P74: =IFERROR(_xlfn.XLOOKUP(A74,PPTO_GENERADOR!$Q:$Q,PPTO_GENERADOR!$E:$E,"-",0),"-") -> 35
A75: PTO-0302 | B75: MAT | C75: OTR | D75: MAT-0040 | E75: =IFERROR(VLOOKUP(D75,MATERIALES!A:B,2,FALSE),"?") -> Encofrado Tabique submuración - H30 (95 kg/m3 de hierro) | G75: 1 | H75: 0 | I75: =IFERROR(VLOOKUP(D75,MATERIALES!A:D,4,FALSE),0) -> 70843.446 | J75: =G75*I75*(1+H75) -> 70843.446 | K75: =A75&"|"&B75 -> PTO-0302|MAT | L75: =COUNTIFS($K$2:K75,K75) -> 1 | M75: =K75&"|"&L75 -> PTO-0302|MAT|1 | N75: =IFERROR(VLOOKUP(A75,PARTIDAS!A:F,6,FALSE),0) -> 1 | O75: =IF(C75="ALB",IF(N75=0,0,G75/N75),0) -> 0 | P75: =IFERROR(_xlfn.XLOOKUP(A75,PPTO_GENERADOR!$Q:$Q,PPTO_GENERADOR!$E:$E,"-",0),"-") -> 40
A76: PTO-0302 | B76: MO | C76: ALB | D76: MO-ESP | E76: =IFERROR(VLOOKUP(D76,MANO_DE_OBRA!A:B,2,FALSE),"?") -> ESPECIALIZADO | F76: j | G76: 1.8939581 | H76: 0 | I76: =IFERROR(VLOOKUP(D76,MANO_DE_OBRA!A:C,3,FALSE),0) -> 75113.05 | J76: =G76*I76*(1+H76) -> 142260.97 | K76: =A76&"|"&B76 -> PTO-0302|MO | L76: =COUNTIFS($K$2:K76,K76) -> 1 | M76: =K76&"|"&L76 -> PTO-0302|MO|1 | N76: =IFERROR(VLOOKUP(A76,PARTIDAS!A:F,6,FALSE),0) -> 1 | O76: =IF(C76="ALB",IF(N76=0,0,G76/N76),0) -> 1.8939581 | P76: =IFERROR(_xlfn.XLOOKUP(A76,PPTO_GENERADOR!$Q:$Q,PPTO_GENERADOR!$E:$E,"-",0),"-") -> 40
A77: PTO-0302 | B77: MO | C77: ALB | D77: MO-OFI | E77: =IFERROR(VLOOKUP(D77,MANO_DE_OBRA!A:B,2,FALSE),"?") -> OFICIAL | F77: j | G77: 2.4858201 | H77: 0 | I77: =IFERROR(VLOOKUP(D77,MANO_DE_OBRA!A:C,3,FALSE),0) -> 65360.25 | J77: =G77*I77*(1+H77) -> 162473.82 | K77: =A77&"|"&B77 -> PTO-0302|MO | L77: =COUNTIFS($K$2:K77,K77) -> 2 | M77: =K77&"|"&L77 -> PTO-0302|MO|2 | N77: =IFERROR(VLOOKUP(A77,PARTIDAS!A:F,6,FALSE),0) -> 1 | O77: =IF(C77="ALB",IF(N77=0,0,G77/N77),0) -> 2.4858201 | P77: =IFERROR(_xlfn.XLOOKUP(A77,PPTO_GENERADOR!$Q:$Q,PPTO_GENERADOR!$E:$E,"-",0),"-") -> 40
A78: PTO-0302 | B78: MO | C78: ALB | D78: MO-AYU | E78: =IFERROR(VLOOKUP(D78,MANO_DE_OBRA!A:B,2,FALSE),"?") -> AYUDANTE | F78: j | G78: 0.059186 | H78: 0 | I78: =IFERROR(VLOOKUP(D78,MANO_DE_OBRA!A:C,3,FALSE),0) -> 49934.24 | J78: =G78*I78*(1+H78) -> 2955.4079 | K78: =A78&"|"&B78 -> PTO-0302|MO | L78: =COUNTIFS($K$2:K78,K78) -> 3 | M78: =K78&"|"&L78 -> PTO-0302|MO|3 | N78: =IFERROR(VLOOKUP(A78,PARTIDAS!A:F,6,FALSE),0) -> 1 | O78: =IF(C78="ALB",IF(N78=0,0,G78/N78),0) -> 0.059186 | P78: =IFERROR(_xlfn.XLOOKUP(A78,PPTO_GENERADOR!$Q:$Q,PPTO_GENERADOR!$E:$E,"-",0),"-") -> 40
A79: PTO-0302 | B79: EQ | D79: EQ-0008 | E79: =IFERROR(VLOOKUP(D79,EQUIPOS!A:B,2,FALSE),"?") -> Herramientas/consumibles - Tabique submuración - H30 hidrófugo (95 | G79: 1 | H79: 0 | I79: =IFERROR(VLOOKUP(D79,EQUIPOS!A:C,3,FALSE),0) -> 5678.0046 | J79: =G79*I79*(1+H79) -> 5678.0046 | K79: =A79&"|"&B79 -> PTO-0302|EQ | L79: =COUNTIFS($K$2:K79,K79) -> 1 | M79: =K79&"|"&L79 -> PTO-0302|EQ|1 | N79: =IFERROR(VLOOKUP(A79,PARTIDAS!A:F,6,FALSE),0) -> 1 | O79: =IF(C79="ALB",IF(N79=0,0,G79/N79),0) -> 0 | P79: =IFERROR(_xlfn.XLOOKUP(A79,PPTO_GENERADOR!$Q:$Q,PPTO_GENERADOR!$E:$E,"-",0),"-") -> 40
A80: PTO-0303 | B80: MAT | C80: OTR | D80: MAT-0041 | E80: =IFERROR(VLOOKUP(D80,MATERIALES!A:B,2,FALSE),"?") -> Encofrado Zapata corrida tabique - H30 (120 kg/m3) | G80: 1 | H80: 0 | I80: =IFERROR(VLOOKUP(D80,MATERIALES!A:D,4,FALSE),0) -> 55068.822 | J80: =G80*I80*(1+H80) -> 55068.822 | K80: =A80&"|"&B80 -> PTO-0303|MAT | L80: =COUNTIFS($K$2:K80,K80) -> 1 | M80: =K80&"|"&L80 -> PTO-0303|MAT|1 | N80: =IFERROR(VLOOKUP(A80,PARTIDAS!A:F,6,FALSE),0) -> 1 | O80: =IF(C80="ALB",IF(N80=0,0,G80/N80),0) -> 0 | P80: =IFERROR(_xlfn.XLOOKUP(A80,PPTO_GENERADOR!$Q:$Q,PPTO_GENERADOR!$E:$E,"-",0),"-") -> 28
A81: PTO-0303 | B81: MO | C81: OTR | D81: SUB-0010 | E81: =IFERROR(VLOOKUP(D81,SUBCONTRATOS_PRY!A:B,2,FALSE),"?") -> H.A. De vigas de fundación (115kg/m3 de hierro) | F81: j | G81: 1 | H81: 0 | I81: =IFERROR(VLOOKUP(D81,SUBCONTRATOS_PRY!A:D,4,FALSE),0) -> 253994.14 | J81: =G81*I81*(1+H81) -> 253994.14 | K81: =A81&"|"&B81 -> PTO-0303|MO | L81: =COUNTIFS($K$2:K81,K81) -> 1 | M81: =K81&"|"&L81 -> PTO-0303|MO|1 | N81: =IFERROR(VLOOKUP(A81,PARTIDAS!A:F,6,FALSE),0) -> 1 | O81: =IF(C81="ALB",IF(N81=0,0,G81/N81),0) -> 0 | P81: =IFERROR(_xlfn.XLOOKUP(A81,PPTO_GENERADOR!$Q:$Q,PPTO_GENERADOR!$E:$E,"-",0),"-") -> 28
A82: PTO-0303 | B82: EQ | D82: EQ-0009 | E82: =IFERROR(VLOOKUP(D82,EQUIPOS!A:B,2,FALSE),"?") -> Herramientas/consumibles - Zapata corrida tabique - H30 hidrófugo ( | G82: 1 | H82: 0 | I82: =IFERROR(VLOOKUP(D82,EQUIPOS!A:C,3,FALSE),0) -> 4635.9445 | J82: =G82*I82*(1+H82) -> 4635.9445 | K82: =A82&"|"&B82 -> PTO-0303|EQ | L82: =COUNTIFS($K$2:K82,K82) -> 1 | M82: =K82&"|"&L82 -> PTO-0303|EQ|1 | N82: =IFERROR(VLOOKUP(A82,PARTIDAS!A:F,6,FALSE),0) -> 1 | O82: =IF(C82="ALB",IF(N82=0,0,G82/N82),0) -> 0 | P82: =IFERROR(_xlfn.XLOOKUP(A82,PPTO_GENERADOR!$Q:$Q,PPTO_GENERADOR!$E:$E,"-",0),"-") -> 28
A83: PTO-0304 | B83: MAT | C83: OTR | D83: MAT-0042 | E83: =IFERROR(VLOOKUP(D83,MATERIALES!A:B,2,FALSE),"?") -> Encofrado Platea - H30 (95 kg/m3 de hierro) | G83: 1 | H83: 0 | I83: =IFERROR(VLOOKUP(D83,MATERIALES!A:D,4,FALSE),0) -> 2471.4098 | J83: =G83*I83*(1+H83) -> 2471.4098 | K83: =A83&"|"&B83 -> PTO-0304|MAT | L83: =COUNTIFS($K$2:K83,K83) -> 1 | M83: =K83&"|"&L83 -> PTO-0304|MAT|1 | N83: =IFERROR(VLOOKUP(A83,PARTIDAS!A:F,6,FALSE),0) -> 1 | O83: =IF(C83="ALB",IF(N83=0,0,G83/N83),0) -> 0 | P83: =IFERROR(_xlfn.XLOOKUP(A83,PPTO_GENERADOR!$Q:$Q,PPTO_GENERADOR!$E:$E,"-",0),"-") -> 179
A84: PTO-0304 | B84: MO | C84: OTR | D84: SUB-0011 | E84: =IFERROR(VLOOKUP(D84,SUBCONTRATOS_PRY!A:B,2,FALSE),"?") -> HA. De cabezales (90 kg/m3 de hierro) | F84: j | G84: 1 | H84: 0 | I84: =IFERROR(VLOOKUP(D84,SUBCONTRATOS_PRY!A:D,4,FALSE),0) -> 148967.56 | J84: =G84*I84*(1+H84) -> 148967.56 | K84: =A84&"|"&B84 -> PTO-0304|MO | L84: =COUNTIFS($K$2:K84,K84) -> 1 | M84: =K84&"|"&L84 -> PTO-0304|MO|1 | N84: =IFERROR(VLOOKUP(A84,PARTIDAS!A:F,6,FALSE),0) -> 1 | O84: =IF(C84="ALB",IF(N84=0,0,G84/N84),0) -> 0 | P84: =IFERROR(_xlfn.XLOOKUP(A84,PPTO_GENERADOR!$Q:$Q,PPTO_GENERADOR!$E:$E,"-",0),"-") -> 179
A85: PTO-0304 | B85: EQ | D85: EQ-0010 | E85: =IFERROR(VLOOKUP(D85,EQUIPOS!A:B,2,FALSE),"?") -> Herramientas/consumibles - Platea - H30 hidrófugo (95 kg/m3 de hier | G85: 1 | H85: 0 | I85: =IFERROR(VLOOKUP(D85,EQUIPOS!A:C,3,FALSE),0) -> 2271.5846 | J85: =G85*I85*(1+H85) -> 2271.5846 | K85: =A85&"|"&B85 -> PTO-0304|EQ | L85: =COUNTIFS($K$2:K85,K85) -> 1 | M85: =K85&"|"&L85 -> PTO-0304|EQ|1 | N85: =IFERROR(VLOOKUP(A85,PARTIDAS!A:F,6,FALSE),0) -> 1 | O85: =IF(C85="ALB",IF(N85=0,0,G85/N85),0) -> 0 | P85: =IFERROR(_xlfn.XLOOKUP(A85,PPTO_GENERADOR!$Q:$Q,PPTO_GENERADOR!$E:$E,"-",0),"-") -> 179
A86: PTO-0305 | B86: MAT | C86: OTR | D86: MAT-0043 | E86: =IFERROR(VLOOKUP(D86,MATERIALES!A:B,2,FALSE),"?") -> Encofrado Losa maciza visto - H30 (120 kg/m3 de hierro) | G86: 1 | H86: 0 | I86: =IFERROR(VLOOKUP(D86,MATERIALES!A:D,4,FALSE),0) -> 40150.005 | J86: =G86*I86*(1+H86) -> 40150.005 | K86: =A86&"|"&B86 -> PTO-0305|MAT | L86: =COUNTIFS($K$2:K86,K86) -> 1 | M86: =K86&"|"&L86 -> PTO-0305|MAT|1 | N86: =IFERROR(VLOOKUP(A86,PARTIDAS!A:F,6,FALSE),0) -> 1 | O86: =IF(C86="ALB",IF(N86=0,0,G86/N86),0) -> 0 | P86: =IFERROR(_xlfn.XLOOKUP(A86,PPTO_GENERADOR!$Q:$Q,PPTO_GENERADOR!$E:$E,"-",0),"-") -> 10
A87: PTO-0305 | B87: MO | C87: ALB | D87: MO-ESP | E87: =IFERROR(VLOOKUP(D87,MANO_DE_OBRA!A:B,2,FALSE),"?") -> ESPECIALIZADO | F87: j | G87: 1.9965872 | H87: 0 | I87: =IFERROR(VLOOKUP(D87,MANO_DE_OBRA!A:C,3,FALSE),0) -> 75113.05 | J87: =G87*I87*(1+H87) -> 149969.75 | K87: =A87&"|"&B87 -> PTO-0305|MO | L87: =COUNTIFS($K$2:K87,K87) -> 1 | M87: =K87&"|"&L87 -> PTO-0305|MO|1 | N87: =IFERROR(VLOOKUP(A87,PARTIDAS!A:F,6,FALSE),0) -> 1 | O87: =IF(C87="ALB",IF(N87=0,0,G87/N87),0) -> 1.9965872 | P87: =IFERROR(_xlfn.XLOOKUP(A87,PPTO_GENERADOR!$Q:$Q,PPTO_GENERADOR!$E:$E,"-",0),"-") -> 10
A88: PTO-0305 | B88: MO | C88: ALB | D88: MO-OFI | E88: =IFERROR(VLOOKUP(D88,MANO_DE_OBRA!A:B,2,FALSE),"?") -> OFICIAL | F88: j | G88: 1.9965872 | H88: 0 | I88: =IFERROR(VLOOKUP(D88,MANO_DE_OBRA!A:C,3,FALSE),0) -> 65360.25 | J88: =G88*I88*(1+H88) -> 130497.44 | K88: =A88&"|"&B88 -> PTO-0305|MO | L88: =COUNTIFS($K$2:K88,K88) -> 2 | M88: =K88&"|"&L88 -> PTO-0305|MO|2 | N88: =IFERROR(VLOOKUP(A88,PARTIDAS!A:F,6,FALSE),0) -> 1 | O88: =IF(C88="ALB",IF(N88=0,0,G88/N88),0) -> 1.9965872 | P88: =IFERROR(_xlfn.XLOOKUP(A88,PPTO_GENERADOR!$Q:$Q,PPTO_GENERADOR!$E:$E,"-",0),"-") -> 10
A89: PTO-0305 | B89: MO | C89: ALB | D89: MO-AYU | E89: =IFERROR(VLOOKUP(D89,MANO_DE_OBRA!A:B,2,FALSE),"?") -> AYUDANTE | F89: j | G89: 0.12286652 | H89: 0 | I89: =IFERROR(VLOOKUP(D89,MANO_DE_OBRA!A:C,3,FALSE),0) -> 49934.24 | J89: =G89*I89*(1+H89) -> 6135.2463 | K89: =A89&"|"&B89 -> PTO-0305|MO | L89: =COUNTIFS($K$2:K89,K89) -> 3 | M89: =K89&"|"&L89 -> PTO-0305|MO|3 | N89: =IFERROR(VLOOKUP(A89,PARTIDAS!A:F,6,FALSE),0) -> 1 | O89: =IF(C89="ALB",IF(N89=0,0,G89/N89),0) -> 0.12286652 | P89: =IFERROR(_xlfn.XLOOKUP(A89,PPTO_GENERADOR!$Q:$Q,PPTO_GENERADOR!$E:$E,"-",0),"-") -> 10
A90: PTO-0305 | B90: EQ | D90: EQ-0011 | E90: =IFERROR(VLOOKUP(D90,EQUIPOS!A:B,2,FALSE),"?") -> Herramientas/consumibles - Rampa - H30 (120 kg/m3 de hierro) | G90: 1 | H90: 0 | I90: =IFERROR(VLOOKUP(D90,EQUIPOS!A:C,3,FALSE),0) -> 4901.2865 | J90: =G90*I90*(1+H90) -> 4901.2865 | K90: =A90&"|"&B90 -> PTO-0305|EQ | L90: =COUNTIFS($K$2:K90,K90) -> 1 | M90: =K90&"|"&L90 -> PTO-0305|EQ|1 | N90: =IFERROR(VLOOKUP(A90,PARTIDAS!A:F,6,FALSE),0) -> 1 | O90: =IF(C90="ALB",IF(N90=0,0,G90/N90),0) -> 0 | P90: =IFERROR(_xlfn.XLOOKUP(A90,PPTO_GENERADOR!$Q:$Q,PPTO_GENERADOR!$E:$E,"-",0),"-") -> 10
A91: PTO-0306 | B91: MAT | C91: OTR | D91: MAT-0044 | E91: =IFERROR(VLOOKUP(D91,MATERIALES!A:B,2,FALSE),"?") -> Encofrado Losa maciza - H30 (120 kg/m3 de hierro) | G91: 1 | H91: 0 | I91: =IFERROR(VLOOKUP(D91,MATERIALES!A:D,4,FALSE),0) -> 32975.501 | J91: =G91*I91*(1+H91) -> 32975.501 | K91: =A91&"|"&B91 -> PTO-0306|MAT | L91: =COUNTIFS($K$2:K91,K91) -> 1 | M91: =K91&"|"&L91 -> PTO-0306|MAT|1 | N91: =IFERROR(VLOOKUP(A91,PARTIDAS!A:F,6,FALSE),0) -> 1 | O91: =IF(C91="ALB",IF(N91=0,0,G91/N91),0) -> 0 | P91: =IFERROR(_xlfn.XLOOKUP(A91,PPTO_GENERADOR!$Q:$Q,PPTO_GENERADOR!$E:$E,"-",0),"-") -> 177
A92: PTO-0306 | B92: MO | C92: ALB | D92: MO-ESP | E92: =IFERROR(VLOOKUP(D92,MANO_DE_OBRA!A:B,2,FALSE),"?") -> ESPECIALIZADO | F92: j | G92: 1.3310581 | H92: 0 | I92: =IFERROR(VLOOKUP(D92,MANO_DE_OBRA!A:C,3,FALSE),0) -> 75113.05 | J92: =G92*I92*(1+H92) -> 99979.834 | K92: =A92&"|"&B92 -> PTO-0306|MO | L92: =COUNTIFS($K$2:K92,K92) -> 1 | M92: =K92&"|"&L92 -> PTO-0306|MO|1 | N92: =IFERROR(VLOOKUP(A92,PARTIDAS!A:F,6,FALSE),0) -> 1 | O92: =IF(C92="ALB",IF(N92=0,0,G92/N92),0) -> 1.3310581 | P92: =IFERROR(_xlfn.XLOOKUP(A92,PPTO_GENERADOR!$Q:$Q,PPTO_GENERADOR!$E:$E,"-",0),"-") -> 177
A93: PTO-0306 | B93: MO | C93: ALB | D93: MO-OFI | E93: =IFERROR(VLOOKUP(D93,MANO_DE_OBRA!A:B,2,FALSE),"?") -> OFICIAL | F93: j | G93: 1.3310581 | H93: 0 | I93: =IFERROR(VLOOKUP(D93,MANO_DE_OBRA!A:C,3,FALSE),0) -> 65360.25 | J93: =G93*I93*(1+H93) -> 86998.291 | K93: =A93&"|"&B93 -> PTO-0306|MO | L93: =COUNTIFS($K$2:K93,K93) -> 2 | M93: =K93&"|"&L93 -> PTO-0306|MO|2 | N93: =IFERROR(VLOOKUP(A93,PARTIDAS!A:F,6,FALSE),0) -> 1 | O93: =IF(C93="ALB",IF(N93=0,0,G93/N93),0) -> 1.3310581 | P93: =IFERROR(_xlfn.XLOOKUP(A93,PPTO_GENERADOR!$Q:$Q,PPTO_GENERADOR!$E:$E,"-",0),"-") -> 177
A94: PTO-0306 | B94: MO | C94: ALB | D94: MO-AYU | E94: =IFERROR(VLOOKUP(D94,MANO_DE_OBRA!A:B,2,FALSE),"?") -> AYUDANTE | F94: j | G94: 0.08191101 | H94: 0 | I94: =IFERROR(VLOOKUP(D94,MANO_DE_OBRA!A:C,3,FALSE),0) -> 49934.24 | J94: =G94*I94*(1+H94) -> 4090.164 | K94: =A94&"|"&B94 -> PTO-0306|MO | L94: =COUNTIFS($K$2:K94,K94) -> 3 | M94: =K94&"|"&L94 -> PTO-0306|MO|3 | N94: =IFERROR(VLOOKUP(A94,PARTIDAS!A:F,6,FALSE),0) -> 1 | O94: =IF(C94="ALB",IF(N94=0,0,G94/N94),0) -> 0.08191101 | P94: =IFERROR(_xlfn.XLOOKUP(A94,PPTO_GENERADOR!$Q:$Q,PPTO_GENERADOR!$E:$E,"-",0),"-") -> 177
A95: PTO-0306 | B95: EQ | D95: EQ-0012 | E95: =IFERROR(VLOOKUP(D95,EQUIPOS!A:B,2,FALSE),"?") -> Herramientas/consumibles - Losa maciza - H30 (110 kg/m3 de hierro) | G95: 1 | H95: 0 | I95: =IFERROR(VLOOKUP(D95,EQUIPOS!A:C,3,FALSE),0) -> 3360.6568 | J95: =G95*I95*(1+H95) -> 3360.6568 | K95: =A95&"|"&B95 -> PTO-0306|EQ | L95: =COUNTIFS($K$2:K95,K95) -> 1 | M95: =K95&"|"&L95 -> PTO-0306|EQ|1 | N95: =IFERROR(VLOOKUP(A95,PARTIDAS!A:F,6,FALSE),0) -> 1 | O95: =IF(C95="ALB",IF(N95=0,0,G95/N95),0) -> 0 | P95: =IFERROR(_xlfn.XLOOKUP(A95,PPTO_GENERADOR!$Q:$Q,PPTO_GENERADOR!$E:$E,"-",0),"-") -> 177
A96: PTO-0307 | B96: MAT | C96: OTR | D96: MAT-0045 | E96: =IFERROR(VLOOKUP(D96,MATERIALES!A:B,2,FALSE),"?") -> Encofrado Vigas - H30 (130 kg/m3 de hierro) | G96: 1 | H96: 0 | I96: =IFERROR(VLOOKUP(D96,MATERIALES!A:D,4,FALSE),0) -> 94228.958 | J96: =G96*I96*(1+H96) -> 94228.958 | K96: =A96&"|"&B96 -> PTO-0307|MAT | L96: =COUNTIFS($K$2:K96,K96) -> 1 | M96: =K96&"|"&L96 -> PTO-0307|MAT|1 | N96: =IFERROR(VLOOKUP(A96,PARTIDAS!A:F,6,FALSE),0) -> 1 | O96: =IF(C96="ALB",IF(N96=0,0,G96/N96),0) -> 0 | P96: =IFERROR(_xlfn.XLOOKUP(A96,PPTO_GENERADOR!$Q:$Q,PPTO_GENERADOR!$E:$E,"-",0),"-") -> 65
A97: PTO-0307 | B97: MO | C97: ALB | D97: MO-ESP | E97: =IFERROR(VLOOKUP(D97,MANO_DE_OBRA!A:B,2,FALSE),"?") -> ESPECIALIZADO | F97: j | G97: 3.2673112 | H97: 0 | I97: =IFERROR(VLOOKUP(D97,MANO_DE_OBRA!A:C,3,FALSE),0) -> 75113.05 | J97: =G97*I97*(1+H97) -> 245417.71 | K97: =A97&"|"&B97 -> PTO-0307|MO | L97: =COUNTIFS($K$2:K97,K97) -> 1 | M97: =K97&"|"&L97 -> PTO-0307|MO|1 | N97: =IFERROR(VLOOKUP(A97,PARTIDAS!A:F,6,FALSE),0) -> 1 | O97: =IF(C97="ALB",IF(N97=0,0,G97/N97),0) -> 3.2673112 | P97: =IFERROR(_xlfn.XLOOKUP(A97,PPTO_GENERADOR!$Q:$Q,PPTO_GENERADOR!$E:$E,"-",0),"-") -> 65
A98: PTO-0307 | B98: MO | C98: ALB | D98: MO-OFI | E98: =IFERROR(VLOOKUP(D98,MANO_DE_OBRA!A:B,2,FALSE),"?") -> OFICIAL | F98: j | G98: 3.2673112 | H98: 0 | I98: =IFERROR(VLOOKUP(D98,MANO_DE_OBRA!A:C,3,FALSE),0) -> 65360.25 | J98: =G98*I98*(1+H98) -> 213552.28 | K98: =A98&"|"&B98 -> PTO-0307|MO | L98: =COUNTIFS($K$2:K98,K98) -> 2 | M98: =K98&"|"&L98 -> PTO-0307|MO|2 | N98: =IFERROR(VLOOKUP(A98,PARTIDAS!A:F,6,FALSE),0) -> 1 | O98: =IF(C98="ALB",IF(N98=0,0,G98/N98),0) -> 3.2673112 | P98: =IFERROR(_xlfn.XLOOKUP(A98,PPTO_GENERADOR!$Q:$Q,PPTO_GENERADOR!$E:$E,"-",0),"-") -> 65
A99: PTO-0307 | B99: MO | C99: ALB | D99: MO-AYU | E99: =IFERROR(VLOOKUP(D99,MANO_DE_OBRA!A:B,2,FALSE),"?") -> AYUDANTE | F99: j | G99: 0.07969101 | H99: 0 | I99: =IFERROR(VLOOKUP(D99,MANO_DE_OBRA!A:C,3,FALSE),0) -> 49934.24 | J99: =G99*I99*(1+H99) -> 3979.31 | K99: =A99&"|"&B99 -> PTO-0307|MO | L99: =COUNTIFS($K$2:K99,K99) -> 3 | M99: =K99&"|"&L99 -> PTO-0307|MO|3 | N99: =IFERROR(VLOOKUP(A99,PARTIDAS!A:F,6,FALSE),0) -> 1 | O99: =IF(C99="ALB",IF(N99=0,0,G99/N99),0) -> 0.07969101 | P99: =IFERROR(_xlfn.XLOOKUP(A99,PPTO_GENERADOR!$Q:$Q,PPTO_GENERADOR!$E:$E,"-",0),"-") -> 65
A100: PTO-0307 | B100: EQ | D100: EQ-0013 | E100: =IFERROR(VLOOKUP(D100,EQUIPOS!A:B,2,FALSE),"?") -> Herramientas/consumibles - Vigas - H30 (140 kg/m3 de hierro) | G100: 1 | H100: 0 | I100: =IFERROR(VLOOKUP(D100,EQUIPOS!A:C,3,FALSE),0) -> 8357.6737 | J100: =G100*I100*(1+H100) -> 8357.6737 | K100: =A100&"|"&B100 -> PTO-0307|EQ | L100: =COUNTIFS($K$2:K100,K100) -> 1 | M100: =K100&"|"&L100 -> PTO-0307|EQ|1 | N100: =IFERROR(VLOOKUP(A100,PARTIDAS!A:F,6,FALSE),0) -> 1 | O100: =IF(C100="ALB",IF(N100=0,0,G100/N100),0) -> 0 | P100: =IFERROR(_xlfn.XLOOKUP(A100,PPTO_GENERADOR!$Q:$Q,PPTO_GENERADOR!$E:$E,"-",0),"-") -> 65
...

Sheet PARTIDAS
A1: Código | B1: Ítem | C1: Rubro | D1: Descripción | E1: Ud. | F1: Rend. | G1: Cant Cons. | H1: % Cons. Desp. | I1: Grado Dif. | J1: MAT (sum/ud) | K1: MO (sum/día) | L1: EQ (sum/día) | M1: MAT/ud | N1: MO/ud | O1: EQ/ud | P1: CD/ud | Q1: # Comp. | R1: Cant Obra | S1: Fuente | T1: Orig MAT | U1: Orig MO | V1: Orig EQ | W1: Δ% CD
A2: PTO-0101 | B2: 1.01 | C2: Tareas Preliminares | D2: Limpieza y preparación del terreno - No cotiza | E2: gl | F2: 1 | G2: 0 | H2: 0 | I2: 1 | J2: =SUMIFS(COMPOSICIÓN!$J$2:$J$982,COMPOSICIÓN!$A$2:$A$982,A2,COMPOSICIÓN!$B$2:$B$982,"MAT") -> 0 | K2: =SUMIFS(COMPOSICIÓN!$J$2:$J$982,COMPOSICIÓN!$A$2:$A$982,A2,COMPOSICIÓN!$B$2:$B$982,"MO")*I2 -> 0 | L2: =SUMIFS(COMPOSICIÓN!$J$2:$J$982,COMPOSICIÓN!$A$2:$A$982,A2,COMPOSICIÓN!$B$2:$B$982,"EQ") -> 0 | M2: =J2 -> 0 | N2: =IF(F2=0,0,K2/F2) -> 0 | O2: =IF(F2=0,0,L2/F2) -> 0 | P2: =M2+N2+O2 -> 0 | Q2: =COUNTIF(COMPOSICIÓN!$A:$A,A2) -> 0 | R2: 0 | S2: directo | T2: 0 | U2: 0 | V2: 0 | W2: =IFERROR(P2/(T2+U2+V2)-1,0) -> 0
A3: PTO-0102 | B3: 1.02 | C3: Tareas Preliminares | D3: Topógrafo - Visita de obra replanteo | E3: un | F3: 1 | G3: 0 | H3: 0 | I3: 1 | J3: =SUMIFS(COMPOSICIÓN!$J$2:$J$982,COMPOSICIÓN!$A$2:$A$982,A3,COMPOSICIÓN!$B$2:$B$982,"MAT") -> 41666.667 | K3: =SUMIFS(COMPOSICIÓN!$J$2:$J$982,COMPOSICIÓN!$A$2:$A$982,A3,COMPOSICIÓN!$B$2:$B$982,"MO")*I3 -> 255876.94 | L3: =SUMIFS(COMPOSICIÓN!$J$2:$J$982,COMPOSICIÓN!$A$2:$A$982,A3,COMPOSICIÓN!$B$2:$B$982,"EQ") -> 4463.1541 | M3: =J3 -> 41666.667 | N3: =IF(F3=0,0,K3/F3) -> 255876.94 | O3: =IF(F3=0,0,L3/F3) -> 4463.1541 | P3: =M3+N3+O3 -> 302006.76 | Q3: =COUNTIF(COMPOSICIÓN!$A:$A,A3) -> 4 | R3: 3 | S3: Tareas | T3: 41666.667 | U3: 255876.94 | V3: 4463.1541 | W3: =IFERROR(P3/(T3+U3+V3)-1,0) -> 1.5892958e-08
A4: PTO-0103 | B4: 1.03 | C4: Tareas Preliminares | D4: Cartel de Obra - No cotiza | E4: gl | F4: 1 | G4: 0 | H4: 0 | I4: 1 | J4: =SUMIFS(COMPOSICIÓN!$J$2:$J$982,COMPOSICIÓN!$A$2:$A$982,A4,COMPOSICIÓN!$B$2:$B$982,"MAT") -> 0 | K4: =SUMIFS(COMPOSICIÓN!$J$2:$J$982,COMPOSICIÓN!$A$2:$A$982,A4,COMPOSICIÓN!$B$2:$B$982,"MO")*I4 -> 0 | L4: =SUMIFS(COMPOSICIÓN!$J$2:$J$982,COMPOSICIÓN!$A$2:$A$982,A4,COMPOSICIÓN!$B$2:$B$982,"EQ") -> 0 | M4: =J4 -> 0 | N4: =IF(F4=0,0,K4/F4) -> 0 | O4: =IF(F4=0,0,L4/F4) -> 0 | P4: =M4+N4+O4 -> 0 | Q4: =COUNTIF(COMPOSICIÓN!$A:$A,A4) -> 0 | R4: 0 | S4: directo | T4: 0 | U4: 0 | V4: 0 | W4: =IFERROR(P4/(T4+U4+V4)-1,0) -> 0
A5: PTO-0104 | B5: 1.04 | C5: Tareas Preliminares | D5: Cerco de obra perimetral - En chapa C25 + Concertina + Porton corredizo | E5: ml | F5: 1 | G5: 0 | H5: 0 | I5: 1 | J5: =SUMIFS(COMPOSICIÓN!$J$2:$J$982,COMPOSICIÓN!$A$2:$A$982,A5,COMPOSICIÓN!$B$2:$B$982,"MAT") -> 79773.18 | K5: =SUMIFS(COMPOSICIÓN!$J$2:$J$982,COMPOSICIÓN!$A$2:$A$982,A5,COMPOSICIÓN!$B$2:$B$982,"MO")*I5 -> 30923.374 | L5: =SUMIFS(COMPOSICIÓN!$J$2:$J$982,COMPOSICIÓN!$A$2:$A$982,A5,COMPOSICIÓN!$B$2:$B$982,"EQ") -> 1660.4484 | M5: =J5 -> 79773.18 | N5: =IF(F5=0,0,K5/F5) -> 30923.374 | O5: =IF(F5=0,0,L5/F5) -> 1660.4484 | P5: =M5+N5+O5 -> 112357 | Q5: =COUNTIF(COMPOSICIÓN!$A:$A,A5) -> 12 | R5: 11 | S5: Tareas | T5: 79773.183 | U5: 30923.374 | V5: 1660.4484 | W5: =IFERROR(P5/(T5+U5+V5)-1,0) -> -2.6149241e-08
A6: PTO-0105 | B6: 1.05 | C6: Tareas Preliminares | D6: Obrador colgante, pañol y ducha | E6: gl | F6: 1 | G6: 0 | H6: 0 | I6: 1 | J6: =SUMIFS(COMPOSICIÓN!$J$2:$J$982,COMPOSICIÓN!$A$2:$A$982,A6,COMPOSICIÓN!$B$2:$B$982,"MAT") -> 2400856.7 | K6: =SUMIFS(COMPOSICIÓN!$J$2:$J$982,COMPOSICIÓN!$A$2:$A$982,A6,COMPOSICIÓN!$B$2:$B$982,"MO")*I6 -> 3516332.6 | L6: =SUMIFS(COMPOSICIÓN!$J$2:$J$982,COMPOSICIÓN!$A$2:$A$982,A6,COMPOSICIÓN!$B$2:$B$982,"EQ") -> 88757.838 | M6: =J6 -> 2400856.7 | N6: =IF(F6=0,0,K6/F6) -> 3516332.6 | O6: =IF(F6=0,0,L6/F6) -> 88757.838 | P6: =M6+N6+O6 -> 6005947.1 | Q6: =COUNTIF(COMPOSICIÓN!$A:$A,A6) -> 22 | R6: 1 | S6: Tareas | T6: 2400856.7 | U6: 3516332.5 | V6: 88757.838 | W6: =IFERROR(P6/(T6+U6+V6)-1,0) -> 1.2795651e-08
A7: PTO-0106 | B7: 1.06 | C7: Tareas Preliminares | D7: Alquiler de baños quimicos y duchas portatiles | E7: mes | F7: 1 | G7: 0 | H7: 0 | I7: 1 | J7: =SUMIFS(COMPOSICIÓN!$J$2:$J$982,COMPOSICIÓN!$A$2:$A$982,A7,COMPOSICIÓN!$B$2:$B$982,"MAT") -> 0 | K7: =SUMIFS(COMPOSICIÓN!$J$2:$J$982,COMPOSICIÓN!$A$2:$A$982,A7,COMPOSICIÓN!$B$2:$B$982,"MO")*I7 -> 311904.59 | L7: =SUMIFS(COMPOSICIÓN!$J$2:$J$982,COMPOSICIÓN!$A$2:$A$982,A7,COMPOSICIÓN!$B$2:$B$982,"EQ") -> 0 | M7: =J7 -> 0 | N7: =IF(F7=0,0,K7/F7) -> 311904.59 | O7: =IF(F7=0,0,L7/F7) -> 0 | P7: =M7+N7+O7 -> 311904.59 | Q7: =COUNTIF(COMPOSICIÓN!$A:$A,A7) -> 2 | R7: 3 | S7: directo | T7: 0 | U7: 311904.59 | V7: 0 | W7: =IFERROR(P7/(T7+U7+V7)-1,0) -> 2.220446e-16
A8: PTO-0107 | B8: 1.07 | C8: Tareas Preliminares | D8: Conexión pilar y luz de obra + Tablero de obra | E8: gl | F8: 1 | G8: 0 | H8: 0 | I8: 1 | J8: =SUMIFS(COMPOSICIÓN!$J$2:$J$982,COMPOSICIÓN!$A$2:$A$982,A8,COMPOSICIÓN!$B$2:$B$982,"MAT") -> 845578.51 | K8: =SUMIFS(COMPOSICIÓN!$J$2:$J$982,COMPOSICIÓN!$A$2:$A$982,A8,COMPOSICIÓN!$B$2:$B$982,"MO")*I8 -> 511535.58 | L8: =SUMIFS(COMPOSICIÓN!$J$2:$J$982,COMPOSICIÓN!$A$2:$A$982,A8,COMPOSICIÓN!$B$2:$B$982,"EQ") -> 20356.711 | M8: =J8 -> 845578.51 | N8: =IF(F8=0,0,K8/F8) -> 511535.58 | O8: =IF(F8=0,0,L8/F8) -> 20356.711 | P8: =M8+N8+O8 -> 1377470.8 | Q8: =COUNTIF(COMPOSICIÓN!$A:$A,A8) -> 9 | R8: 1 | S8: Tareas | T8: 845578.51 | U8: 511535.56 | V8: 20356.711 | W8: =IFERROR(P8/(T8+U8+V8)-1,0) -> 1.1252507e-08
A9: PTO-0108 | B9: 1.08 | C9: Tareas Preliminares | D9: Conexión agua de obra, tanque + bomba | E9: gl | F9: 1 | G9: 0 | H9: 0 | I9: 1 | J9: =SUMIFS(COMPOSICIÓN!$J$2:$J$982,COMPOSICIÓN!$A$2:$A$982,A9,COMPOSICIÓN!$B$2:$B$982,"MAT") -> 680400 | K9: =SUMIFS(COMPOSICIÓN!$J$2:$J$982,COMPOSICIÓN!$A$2:$A$982,A9,COMPOSICIÓN!$B$2:$B$982,"MO")*I9 -> 421419.9 | L9: =SUMIFS(COMPOSICIÓN!$J$2:$J$982,COMPOSICIÓN!$A$2:$A$982,A9,COMPOSICIÓN!$B$2:$B$982,"EQ") -> 16527.298 | M9: =J9 -> 680400 | N9: =IF(F9=0,0,K9/F9) -> 421419.9 | O9: =IF(F9=0,0,L9/F9) -> 16527.298 | P9: =M9+N9+O9 -> 1118347.2 | Q9: =COUNTIF(COMPOSICIÓN!$A:$A,A9) -> 11 | R9: 1 | S9: Tareas | T9: 680400 | U9: 421419.89 | V9: 16527.298 | W9: =IFERROR(P9/(T9+U9+V9)-1,0) -> 9.2994377e-09
A10: PTO-0109 | B10: 1.09 | C10: Tareas Preliminares | D10: Tramite luz de obra, certificado luz de obra (2) y medición PAT | E10: gl | F10: 1 | G10: 0 | H10: 0 | I10: 1 | J10: =SUMIFS(COMPOSICIÓN!$J$2:$J$982,COMPOSICIÓN!$A$2:$A$982,A10,COMPOSICIÓN!$B$2:$B$982,"MAT") -> 0 | K10: =SUMIFS(COMPOSICIÓN!$J$2:$J$982,COMPOSICIÓN!$A$2:$A$982,A10,COMPOSICIÓN!$B$2:$B$982,"MO")*I10 -> 339320.84 | L10: =SUMIFS(COMPOSICIÓN!$J$2:$J$982,COMPOSICIÓN!$A$2:$A$982,A10,COMPOSICIÓN!$B$2:$B$982,"EQ") -> 0 | M10: =J10 -> 0 | N10: =IF(F10=0,0,K10/F10) -> 339320.84 | O10: =IF(F10=0,0,L10/F10) -> 0 | P10: =M10+N10+O10 -> 339320.84 | Q10: =COUNTIF(COMPOSICIÓN!$A:$A,A10) -> 3 | R10: 1 | S10: Tareas | T10: 0 | U10: 339320.84 | V10: 0 | W10: =IFERROR(P10/(T10+U10+V10)-1,0) -> -1.8613883e-09
A11: PTO-0110 | B11: 1.1 | C11: Tareas Preliminares | D11: Sistema de depresión de napas | E11: gl | F11: 1 | G11: 0 | H11: 0 | I11: 1 | J11: =SUMIFS(COMPOSICIÓN!$J$2:$J$982,COMPOSICIÓN!$A$2:$A$982,A11,COMPOSICIÓN!$B$2:$B$982,"MAT") -> 0 | K11: =SUMIFS(COMPOSICIÓN!$J$2:$J$982,COMPOSICIÓN!$A$2:$A$982,A11,COMPOSICIÓN!$B$2:$B$982,"MO")*I11 -> 7800000 | L11: =SUMIFS(COMPOSICIÓN!$J$2:$J$982,COMPOSICIÓN!$A$2:$A$982,A11,COMPOSICIÓN!$B$2:$B$982,"EQ") -> 0 | M11: =J11 -> 0 | N11: =IF(F11=0,0,K11/F11) -> 7800000 | O11: =IF(F11=0,0,L11/F11) -> 0 | P11: =M11+N11+O11 -> 7800000 | Q11: =COUNTIF(COMPOSICIÓN!$A:$A,A11) -> 1 | R11: 1 | S11: directo | T11: 0 | U11: 7800000 | V11: 0 | W11: =IFERROR(P11/(T11+U11+V11)-1,0) -> 0
A12: PTO-0201 | B12: 2.01 | C12: Movimiento de Suelos | D12: Excavación a maquina para submuración y subsuelo | E12: m3 | F12: 1 | G12: 0 | H12: 0 | I12: 1 | J12: =SUMIFS(COMPOSICIÓN!$J$2:$J$982,COMPOSICIÓN!$A$2:$A$982,A12,COMPOSICIÓN!$B$2:$B$982,"MAT") -> 0 | K12: =SUMIFS(COMPOSICIÓN!$J$2:$J$982,COMPOSICIÓN!$A$2:$A$982,A12,COMPOSICIÓN!$B$2:$B$982,"MO")*I12 -> 26209.62 | L12: =SUMIFS(COMPOSICIÓN!$J$2:$J$982,COMPOSICIÓN!$A$2:$A$982,A12,COMPOSICIÓN!$B$2:$B$982,"EQ") -> 117.1443 | M12: =J12 -> 0 | N12: =IF(F12=0,0,K12/F12) -> 26209.62 | O12: =IF(F12=0,0,L12/F12) -> 117.1443 | P12: =M12+N12+O12 -> 26326.765 | Q12: =COUNTIF(COMPOSICIÓN!$A:$A,A12) -> 3 | R12: 1266 | S12: Tareas | T12: 0 | U12: 26209.62 | V12: 117.1443 | W12: =IFERROR(P12/(T12+U12+V12)-1,0) -> 9.9117385e-09
A13: PTO-0202 | B13: 2.02 | C13: Movimiento de Suelos | D13: Demolición y retiro de fundaciones existentes - No cotiza | E13: gl | F13: 1 | G13: 0 | H13: 0 | I13: 1 | J13: =SUMIFS(COMPOSICIÓN!$J$2:$J$982,COMPOSICIÓN!$A$2:$A$982,A13,COMPOSICIÓN!$B$2:$B$982,"MAT") -> 0 | K13: =SUMIFS(COMPOSICIÓN!$J$2:$J$982,COMPOSICIÓN!$A$2:$A$982,A13,COMPOSICIÓN!$B$2:$B$982,"MO")*I13 -> 0 | L13: =SUMIFS(COMPOSICIÓN!$J$2:$J$982,COMPOSICIÓN!$A$2:$A$982,A13,COMPOSICIÓN!$B$2:$B$982,"EQ") -> 0 | M13: =J13 -> 0 | N13: =IF(F13=0,0,K13/F13) -> 0 | O13: =IF(F13=0,0,L13/F13) -> 0 | P13: =M13+N13+O13 -> 0 | Q13: =COUNTIF(COMPOSICIÓN!$A:$A,A13) -> 0 | R13: 0 | S13: directo | T13: 0 | U13: 0 | V13: 0 | W13: =IFERROR(P13/(T13+U13+V13)-1,0) -> 0
... A190: PTO-2803 | B190: 28.03 | C190: Calefacción | D190: Flexibles caldera | E190: u | F190: 1 | G190: 0 | H190: 0 | I190: 1 | J190: =SUMIFS(COMPOSICIÓN!$J$2:$J$982,COMPOSICIÓN!$A$2:$A$982,A190,COMPOSICIÓN!$B$2:$B$982,"MAT") -> 75150 | K190: =SUMIFS(COMPOSICIÓN!$J$2:$J$982,COMPOSICIÓN!$A$2:$A$982,A190,COMPOSICIÓN!$B$2:$B$982,"MO")*I190 -> 0 | L190: =SUMIFS(COMPOSICIÓN!$J$2:$J$982,COMPOSICIÓN!$A$2:$A$982,A190,COMPOSICIÓN!$B$2:$B$982,"EQ") -> 1127.25 | M190: =J190 -> 75150 | N190: =IF(F190=0,0,K190/F190) -> 0 | O190: =IF(F190=0,0,L190/F190) -> 1127.25 | P190: =M190+N190+O190 -> 76277.25 | Q190: =COUNTIF(COMPOSICIÓN!$A:$A,A190) -> 2 | R190: 16 | S190: directo | T190: 75150 | U190: 0 | V190: 1127.25 | W190: =IFERROR(P190/(T190+U190+V190)-1,0) -> 0
