Workbook
Name GASTOS_CONCEPTO: _Listas!$I$2:$I$17
Name RUBROS_PLAN: _Listas!$A$2:$A$34

Sheet 0_CONFIG
A1: ▌ CONFIGURACIÓN DE OBRA — CH 2171
A3: Nombre de obra | B3: Chivilcoy 2171
A4: Estado | B4: En ejecución
A5: Fecha inicio | B5: 46023
A6: Duración estimada (meses) | B6: 18
A7: — ÍNDICE CAC —
A8: Mes base CAC | B8: 45809
A9: Valor CAC base (INDEC) | B9: 16643.4
A10: Mes corriente | B10: ='0_Indice_CAC'!A4 -> 45778
A11: Ratio CAC corriente | B11: ='0_Indice_CAC'!D4 -> 1.0073905
A12: — COEFICIENTE K —
A13: K (Gastos Generales y Beneficio) | B13: ='1_GGBB'!F61 -> 1.3564671 | C13: CRÍTICO: no modificar manualmente
A14: — PRESUPUESTO —
A15: Apertura fiscal | B15: B65 / N35 / GDN
A16: Costo controlable (sin EQ) | B16: {=SUMPRODUCT(('1_Presupuesto'!$J$4:$J$212+'1_Presupuesto'!$K$4:$K$212+'1_Presupuesto'!$L$4:$L$212)*'1_Presupuesto'!$I$4:$I$212)} -> 1.109935e+09
A17: Costo total (con EQ) | B17: {=SUMPRODUCT('1_Presupuesto'!$N$4:$N$212*'1_Presupuesto'!$I$4:$I$212)} -> 1.1357519e+09
A18: Precio de venta total | B18: {=SUMPRODUCT('1_Presupuesto'!$S$4:$S$212*'1_Presupuesto'!$I$4:$I$212)} -> 1.5406101e+09
A19: Sanity check (debe ser 0) | B19: =+B17*B13-B18 -> 0 | C19: EQ no tiene rubro asignado → excluido de costo controlable
A44: — RECONCILIACIÓN MENSUAL —
A45: Total egresos (2_Movimientos) | B45: =SUMPRODUCT('2_Movimientos'!$I$2:$I$1000,N(LEFT(TEXT('2_Movimientos'!$A$2:$A$1000,"0"),1)<>"4"))-SUMPRODUCT('2_Movimientos'!$J$2:$J$1000,N(LEFT(TEXT('2_Movimientos'!$A$2:$A$1000,"0"),1)<>"4")) -> 93309801
A46: Total Tezamat (pegar mensual)
A47: Diferencia (debe ser 0) | B47: =B45-B46 -> 93309801
A49: Tolerancia conciliación ($) | B49: 100
A52: — PENDIENTES (celdas amarillas) —
A53: 0_Indice_CAC col B | B53: CAC meses futuros sin publicar
A54: 0_Jornales_MO | B54: Tarifas UOCRA meses futuros
A55: 0_CONFIG!B46 | B55: Input mensual total Tezamat
A56: 1_Presupuesto cols A,B,C,D | B56: Asignación de rubros por ítem (4 cols input manual)

Sheet 0_Indice_CAC
A1: INDICE CAC | F1: IMPORTACIÓN MAESTRA (pendiente): este índice se actualiza por proceso Python desde archivo maestro externo (p.ej. archivos/fuente/CAC_maestro.xlsx). NO usar vínculos externos vivos. Una sola actualización en el maestro -> import a cada Resumen.
A2: En rojo se pinta el mes cerrado anterior
A3: Mes | B3: Valor INDEC | C3: Previsión | D3: Ratio deflactación
A4: 45778 | B4: 16521.3 | D4: =$B$5/B4 -> 1.0073905
A5: 45809 | B5: 16643.4 | D5: =$B$5/B5 -> 1
A6: 45839 | B6: 16939.5 | D6: =$B$5/B6 -> 0.98252015
A7: 45870 | B7: 17187.6 | D7: =$B$5/B7 -> 0.96833764
A8: 45901 | B8: 17762.3 | D8: =$B$5/B8 -> 0.93700703
A9: 45931 | B9: 18172.8 | D9: =$B$5/B9 -> 0.91584126
A10: 45962 | B10: 18534.9 | D10: =$B$5/B10 -> 0.89794927
A11: 45992 | B11: 18776.5 | D11: =$B$5/B11 -> 0.88639523
A12: 46023 | B12: 19209.4 | D12: =$B$5/B12 -> 0.86641957
A13: 46054 | B13: 19453 | D13: =$B$5/B13 -> 0.85556983
A14: 46082 | B14: 19771.2 | D14: =$B$5/B14 -> 0.84180019
A15: 46113 | B15: 20138.793 | D15: =$B$5/B15 -> 0.82643481
... A18: 46204 | B18: 20800 | D18: =$B$5/B18 -> 0.80016346

Sheet 0_Jornales_MO
A1: TABLA DE TARIFAS UOCRA POR CATEGORÍA | L1: IMPORTACIÓN MAESTRA (pendiente): tarifas UOCRA se actualizan por proceso Python desde archivo maestro externo (p.ej. archivos/fuente/Jornales_maestro.xlsx). NO usar vínculos externos vivos.
A3: Mes | B3: ESPECIALIZADO | C3: OFICIAL | D3: MEDIO OFICIAL | E3: AYUDANTE | G3: ESP/hora | H3: OF/hora | I3: 1/2OF/hora | J3: AYU/hora
A4: 46023 | B4: 117452.66 | C4: 97866.77 | D4: 83614.94 | E4: 78291.04 | G4: =IF(B4="","",B4/8) -> 14681.583 | H4: =IF(C4="","",C4/8) -> 12233.346 | I4: =IF(D4="","",D4/8) -> 10451.868 | J4: =IF(E4="","",E4/8) -> 9786.38
A5: 46054 | B5: 119406.33 | C5: 99479.56 | D5: 84948.75 | E5: 79490.6 | G5: =IF(B5="","",B5/8) -> 14925.791 | H5: =IF(C5="","",C5/8) -> 12434.945 | I5: =IF(D5="","",D5/8) -> 10618.594 | J5: =IF(E5="","",E5/8) -> 9936.325
A6: 46082 | B6: 122445.79 | C6: 102029.07 | D6: 87100.47 | E6: 81453.72 | G6: =IF(B6="","",B6/8) -> 15305.724 | H6: =IF(C6="","",C6/8) -> 12753.634 | I6: =IF(D6="","",D6/8) -> 10887.559 | J6: =IF(E6="","",E6/8) -> 10181.715
A7: 46113 | B7: 128780.87 | C7: 106995.86 | D7: 91265.84 | E7: 85242.81 | G7: =IF(B7="","",B7/8) -> 16097.609 | H7: =IF(C7="","",C7/8) -> 13374.483 | I7: =IF(D7="","",D7/8) -> 11408.23 | J7: =IF(E7="","",E7/8) -> 10655.351
A8: 46143 | B8: 131727.59 | C8: 109491.85 | D8: 93345.07 | E8: 87239.92 | G8: =IF(B8="","",B8/8) -> 16465.949 | H8: =IF(C8="","",C8/8) -> 13686.481 | I8: =IF(D8="","",D8/8) -> 11668.134 | J8: =IF(E8="","",E8/8) -> 10904.99
A9: 46174 | G9: =IF(B9="","",B9/8) | H9: =IF(C9="","",C9/8) | I9: =IF(D9="","",D9/8) | J9: =IF(E9="","",E9/8)
A10: 46204 | G10: =IF(B10="","",B10/8) | H10: =IF(C10="","",C10/8) | I10: =IF(D10="","",D10/8) | J10: =IF(E10="","",E10/8)
A11: 46235 | G11: =IF(B11="","",B11/8) | H11: =IF(C11="","",C11/8) | I11: =IF(D11="","",D11/8) | J11: =IF(E11="","",E11/8)
A12: 46266 | G12: =IF(B12="","",B12/8) | H12: =IF(C12="","",C12/8) | I12: =IF(D12="","",D12/8) | J12: =IF(E12="","",E12/8)
A13: 46296 | G13: =IF(B13="","",B13/8) | H13: =IF(C13="","",C13/8) | I13: =IF(D13="","",D13/8) | J13: =IF(E13="","",E13/8)
A14: 46327 | G14: =IF(B14="","",B14/8) | H14: =IF(C14="","",C14/8) | I14: =IF(D14="","",D14/8) | J14: =IF(E14="","",E14/8)
A15: 46357 | G15: =IF(B15="","",B15/8) | H15: =IF(C15="","",C15/8) | I15: =IF(D15="","",D15/8) | J15: =IF(E15="","",E15/8)
A16: 46388 | G16: =IF(B16="","",B16/8) | H16: =IF(C16="","",C16/8) | I16: =IF(D16="","",D16/8) | J16: =IF(E16="","",E16/8)
A17: 46419 | G17: =IF(B17="","",B17/8) | H17: =IF(C17="","",C17/8) | I17: =IF(D17="","",D17/8) | J17: =IF(E17="","",E17/8)
A18: 46447 | G18: =IF(B18="","",B18/8) | H18: =IF(C18="","",C18/8) | I18: =IF(D18="","",D18/8) | J18: =IF(E18="","",E18/8)
A19: 46478 | G19: =IF(B19="","",B19/8) | H19: =IF(C19="","",C19/8) | I19: =IF(D19="","",D19/8) | J19: =IF(E19="","",E19/8)
A20: 46508 | G20: =IF(B20="","",B20/8) | H20: =IF(C20="","",C20/8) | I20: =IF(D20="","",D20/8) | J20: =IF(E20="","",E20/8)
A21: 46539 | G21: =IF(B21="","",B21/8) | H21: =IF(C21="","",C21/8) | I21: =IF(D21="","",D21/8) | J21: =IF(E21="","",E21/8)

Sheet 1_Presupuesto
A1: PRESUPUESTO AL COSTO Y PRECIO DE VENTA — CH 2171
A3: Rubro MT | B3: Rubro MT/Prov | C3: Rubro MO/OTR | D3: Rubro MO/ALB | E3: Cod. Ítem | F3: Estado | G3: Descripción | H3: U | I3: Cant | J3: MT | K3: MO/OTR | L3: MO/ALB | M3: EQ | N3: Costo Unit. | O3: MT | P3: MO/OTR | Q3: MO/ALB | R3: EQ | S3: P.Unit | T3: Margen | U3: Costo total | V3: PV subtotal | W3: Etapa | X3: Presupuesto | Y3: % Acum Tot
F4: - | G4: TAREAS PRELIMINARES | W4: Tareas Preliminares | X4: PTO 01
E5: 1.01 | F5: OK | G5: Limpieza y preparación del terreno - No cotiza | H5: gl | I5: 0 | J5: 0 | K5: 0 | L5: 0 | M5: 0 | N5: =SUM(J5:M5) -> 0 | O5: =IF($N5=0,$S5,J5/$N5*$S5) -> 0 | P5: =IF($N5=0,0,K5/$N5*$S5) -> 0 | Q5: =IF($N5=0,0,L5/$N5*$S5) -> 0 | R5: =IF($N5=0,0,M5/$N5*$S5) -> 0 | S5: 0 | T5: =IFERROR(S5/N5,"") | U5: =N5*I5 -> 0 | V5: =S5*I5 -> 0 | W5: Tareas Preliminares | X5: PTO 01 | Y5: =SUMIFS(Cert_App_Output!$G:$G,Cert_App_Output!$E:$E,$E5,Cert_App_Output!$K:$K,$X5) -> 0
A6: Preliminares | C6: Preliminares | D6: Preliminares | E6: 1.02 | F6: OK | G6: Topógrafo - Visita de obra replanteo | H6: un | I6: 4 | J6: 25000 | K6: 214394.06 | L6: 67240.5 | M6: 4599.52 | N6: =SUM(J6:M6) -> 311234.08 | O6: =IF($N6=0,$S6,J6/$N6*$S6) -> 33911.678 | P6: =IF($N6=0,0,K6/$N6*$S6) -> 290818.49 | Q6: =IF($N6=0,0,L6/$N6*$S6) -> 91209.528 | R6: =IF($N6=0,0,M6/$N6*$S6) -> 6239.0977 | S6: 422178.8 | T6: =IFERROR(S6/N6,"") -> 1.3564671 | U6: =N6*I6 -> 1244936.3 | V6: =S6*I6 -> 1688715.2 | W6: Tareas Preliminares | X6: PTO 01 | Y6: =SUMIFS(Cert_App_Output!$G:$G,Cert_App_Output!$E:$E,$E6,Cert_App_Output!$K:$K,$X6) -> 0.5
E7: 1.03 | F7: OK | G7: Cartel de Obra - No cotiza | H7: gl | I7: 1 | J7: 0 | K7: 0 | L7: 0 | M7: 0 | N7: =SUM(J7:M7) -> 0 | O7: =IF($N7=0,$S7,J7/$N7*$S7) -> 0 | P7: =IF($N7=0,0,K7/$N7*$S7) -> 0 | Q7: =IF($N7=0,0,L7/$N7*$S7) -> 0 | R7: =IF($N7=0,0,M7/$N7*$S7) -> 0 | S7: 0 | T7: =IFERROR(S7/N7,"") | U7: =N7*I7 -> 0 | V7: =S7*I7 -> 0 | W7: Tareas Preliminares | X7: PTO 01 | Y7: =SUMIFS(Cert_App_Output!$G:$G,Cert_App_Output!$E:$E,$E7,Cert_App_Output!$K:$K,$X7) -> 0
A8: Preliminares | D8: Preliminares | E8: 1.04 | F8: OK | G8: Cerco de obra perimetral - En chapa C25 + Concertina + Porton corredizo | H8: ml | I8: 10 | J8: 98815.57 | K8: 0 | L8: 111992.57 | M8: 3162.12 | N8: =SUM(J8:M8) -> 213970.26 | O8: =IF($N8=0,$S8,J8/$N8*$S8) -> 134040.07 | P8: =IF($N8=0,0,K8/$N8*$S8) -> 0 | Q8: =IF($N8=0,0,L8/$N8*$S8) -> 151914.24 | R8: =IF($N8=0,0,M8/$N8*$S8) -> 4289.3118 | S8: 290243.62 | T8: =IFERROR(S8/N8,"") -> 1.3564671 | U8: =N8*I8 -> 2139702.6 | V8: =S8*I8 -> 2902436.2 | W8: Tareas Preliminares | X8: PTO 01 | Y8: =SUMIFS(Cert_App_Output!$G:$G,Cert_App_Output!$E:$E,$E8,Cert_App_Output!$K:$K,$X8) -> 1
A9: Preliminares | C9: Preliminares | D9: Preliminares | E9: 1.05 | F9: OK | G9: Obrador, pañol y ducha | H9: gl | I9: 1 | J9: 2570625.2 | K9: 1000000 | L9: 5023936.3 | M9: 128918.42 | N9: =SUM(J9:M9) -> 8723479.9 | O9: =IF($N9=0,$S9,J9/$N9*$S9) -> 3486968.5 | P9: =IF($N9=0,0,K9/$N9*$S9) -> 1356467.1 | Q9: =IF($N9=0,0,L9/$N9*$S9) -> 6814804.5 | R9: =IF($N9=0,0,M9/$N9*$S9) -> 174873.6 | S9: 11833114 | T9: =IFERROR(S9/N9,"") -> 1.3564671 | U9: =N9*I9 -> 8723479.9 | V9: =S9*I9 -> 11833114 | W9: Tareas Preliminares | X9: PTO 01 | Y9: =SUMIFS(Cert_App_Output!$G:$G,Cert_App_Output!$E:$E,$E9,Cert_App_Output!$K:$K,$X9) -> 0.75
C10: Gastos Generales | E10: 1.06 | F10: OK | G10: Alquiler de baños quimicos y duchas portatiles | H10: mes | I10: 4 | J10: 0 | K10: 260000 | L10: 0 | M10: 0 | N10: =SUM(J10:M10) -> 260000 | O10: =IF($N10=0,$S10,J10/$N10*$S10) -> 0 | P10: =IF($N10=0,0,K10/$N10*$S10) -> 352681.45 | Q10: =IF($N10=0,0,L10/$N10*$S10) -> 0 | R10: =IF($N10=0,0,M10/$N10*$S10) -> 0 | S10: 352681.45 | T10: =IFERROR(S10/N10,"") -> 1.3564671 | U10: =N10*I10 -> 1040000 | V10: =S10*I10 -> 1410725.8 | W10: Tareas Preliminares | X10: PTO 01 | Y10: =SUMIFS(Cert_App_Output!$G:$G,Cert_App_Output!$E:$E,$E10,Cert_App_Output!$K:$K,$X10) -> 0.25
A11: Preliminares | D11: Preliminares | E11: 1.07 | F11: OK | G11: Conexión pilar y luz de obra + Tablero de obra | H11: gl | I11: 1 | J11: 1390000 | K11: 0 | L11: 661285.32 | M11: 30769.28 | N11: =SUM(J11:M11) -> 2082054.6 | O11: =IF($N11=0,$S11,J11/$N11*$S11) -> 1885489.3 | P11: =IF($N11=0,0,K11/$N11*$S11) -> 0 | Q11: =IF($N11=0,0,L11/$N11*$S11) -> 897011.8 | R11: =IF($N11=0,0,M11/$N11*$S11) -> 41737.517 | S11: 2824238.6 | T11: =IFERROR(S11/N11,"") -> 1.3564671 | U11: =N11*I11 -> 2082054.6 | V11: =S11*I11 -> 2824238.6 | W11: Tareas Preliminares | X11: PTO 01 | Y11: =SUMIFS(Cert_App_Output!$G:$G,Cert_App_Output!$E:$E,$E11,Cert_App_Output!$K:$K,$X11) -> 1
A12: Preliminares | D12: Preliminares | E12: 1.08 | F12: OK | G12: Conexión agua de obra, tanque + bomba | H12: gl | I12: 1 | J12: 936000 | K12: 0 | L12: 536368.95 | M12: 22085.53 | N12: =SUM(J12:M12) -> 1494454.5 | O12: =IF($N12=0,$S12,J12/$N12*$S12) -> 1269653.2 | P12: =IF($N12=0,0,K12/$N12*$S12) -> 0 | Q12: =IF($N12=0,0,L12/$N12*$S12) -> 727566.85 | R12: =IF($N12=0,0,M12/$N12*$S12) -> 29958.295 | S12: 2027178.4 | T12: =IFERROR(S12/N12,"") -> 1.3564671 | U12: =N12*I12 -> 1494454.5 | V12: =S12*I12 -> 2027178.4 | W12: Tareas Preliminares | X12: PTO 01 | Y12: =SUMIFS(Cert_App_Output!$G:$G,Cert_App_Output!$E:$E,$E12,Cert_App_Output!$K:$K,$X12) -> 0
C13: Preliminares | E13: 1.09 | F13: OK | G13: Tramite luz de obra, certificado luz de obra (2) y medición PAT | H13: gl | I13: 1 | J13: 0 | K13: 482995.31 | L13: 0 | M13: 0 | N13: =SUM(J13:M13) -> 482995.31 | O13: =IF($N13=0,$S13,J13/$N13*$S13) -> 0 | P13: =IF($N13=0,0,K13/$N13*$S13) -> 655167.26 | Q13: =IF($N13=0,0,L13/$N13*$S13) -> 0 | R13: =IF($N13=0,0,M13/$N13*$S13) -> 0 | S13: 655167.26 | T13: =IFERROR(S13/N13,"") -> 1.3564671 | U13: =N13*I13 -> 482995.31 | V13: =S13*I13 -> 655167.26 | W13: Tareas Preliminares | X13: PTO 01 | Y13: =SUMIFS(Cert_App_Output!$G:$G,Cert_App_Output!$E:$E,$E13,Cert_App_Output!$K:$K,$X13) -> 0.7
F14: - | G14: MOVIMIENTO DE TIERRA, COMPACTACION Y RELLENO | W14: Movimiento de Tierra | X14: PTO 01
C15: Movimiento de Suelos | D15: Homigón MO | E15: 2.01 | F15: OK | G15: Retiro de suelo vegetal e: 50 cm, aporte y compactación de tosca e: 40 cm (dos capas de 20 cm) | H15: m2 | I15: 219 | J15: 0 | K15: 25907.44 | L15: 3070.34 | M15: 0 | N15: =SUM(J15:M15) -> 28977.78 | O15: =IF($N15=0,$S15,J15/$N15*$S15) -> 0 | P15: =IF($N15=0,0,K15/$N15*$S15) -> 35142.591 | Q15: =IF($N15=0,0,L15/$N15*$S15) -> 4164.8153 | R15: =IF($N15=0,0,M15/$N15*$S15) -> 0 | S15: 39307.406 | T15: =IFERROR(S15/N15,"") -> 1.3564671 | U15: =N15*I15 -> 6346133.8 | V15: =S15*I15 -> 8608321.9 | W15: Movimiento de Tierra | X15: PTO 01 | Y15: =SUMIFS(Cert_App_Output!$G:$G,Cert_App_Output!$E:$E,$E15,Cert_App_Output!$K:$K,$X15) -> 0.5
C16: Movimiento de Suelos | D16: Homigón MO | E16: 2.02 | F16: OK | G16: Excavación para cámara transformadora | H16: m3 | I16: 100 | J16: 0 | K16: 24440 | L16: 6724.05 | M16: 467.46 | N16: =SUM(J16:M16) -> 31631.51 | O16: =IF($N16=0,$S16,J16/$N16*$S16) -> 0 | P16: =IF($N16=0,0,K16/$N16*$S16) -> 33152.057 | Q16: =IF($N16=0,0,L16/$N16*$S16) -> 9120.9528 | R16: =IF($N16=0,0,M16/$N16*$S16) -> 634.09412 | S16: 42907.103 | T16: =IFERROR(S16/N16,"") -> 1.3564671 | U16: =N16*I16 -> 3163151 | V16: =S16*I16 -> 4290710.3 | W16: Movimiento de Tierra | X16: PTO 01 | Y16: =SUMIFS(Cert_App_Output!$G:$G,Cert_App_Output!$E:$E,$E16,Cert_App_Output!$K:$K,$X16) -> 0
D17: Homigón MO | E17: 2.03 | F17: OK | G17: Excavación manual para tensores y vigas de fundación | H17: m3 | I17: 43 | J17: 0 | K17: 0 | L17: 67240.5 | M17: 0 | N17: =SUM(J17:M17) -> 67240.5 | O17: =IF($N17=0,$S17,J17/$N17*$S17) -> 0 | P17: =IF($N17=0,0,K17/$N17*$S17) -> 0 | Q17: =IF($N17=0,0,L17/$N17*$S17) -> 91209.528 | R17: =IF($N17=0,0,M17/$N17*$S17) -> 0 | S17: 91209.528 | T17: =IFERROR(S17/N17,"") -> 1.3564671 | U17: =N17*I17 -> 2891341.5 | V17: =S17*I17 -> 3922009.7 | W17: Movimiento de Tierra | X17: PTO 01 | Y17: =SUMIFS(Cert_App_Output!$G:$G,Cert_App_Output!$E:$E,$E17,Cert_App_Output!$K:$K,$X17) -> 0.4
E18: 2.04 | F18: OK | G18: Demolición y retiro de fundaciones existentes - No cotiza | H18: gl | I18: 0 | J18: 0 | K18: 0 | L18: 0 | M18: 0 | N18: =SUM(J18:M18) -> 0 | O18: =IF($N18=0,$S18,J18/$N18*$S18) -> 0 | P18: =IF($N18=0,0,K18/$N18*$S18) -> 0 | Q18: =IF($N18=0,0,L18/$N18*$S18) -> 0 | R18: =IF($N18=0,0,M18/$N18*$S18) -> 0 | S18: 0 | T18: =IFERROR(S18/N18,"") | U18: =N18*I18 -> 0 | V18: =S18*I18 -> 0 | W18: Movimiento de Tierra | X18: PTO 01 | Y18: =SUMIFS(Cert_App_Output!$G:$G,Cert_App_Output!$E:$E,$E18,Cert_App_Output!$K:$K,$X18) -> 0
F19: - | G19: ESTRUCTURA RESISTENTE | W19: Estructura Resistente | X19: PTO 01
A20: Hormigón MT | D20: Homigón MO | E20: 3.01 | F20: OK | G20: Hormigón de limpieza - e: 10 cm | H20: m3 | I20: 3 | J20: 120430 | K20: 0 | L20: 155041.22 | M20: 4132.07 | N20: =SUM(J20:M20) -> 279603.29 | O20: =IF($N20=0,$S20,J20/$N20*$S20) -> 163359.34 | P20: =IF($N20=0,0,K20/$N20*$S20) -> 0 | Q20: =IF($N20=0,0,L20/$N20*$S20) -> 210308.32 | R20: =IF($N20=0,0,M20/$N20*$S20) -> 5605.0171 | S20: 379272.67 | T20: =IFERROR(S20/N20,"") -> 1.3564671 | U20: =N20*I20 -> 838809.87 | V20: =S20*I20 -> 1137818 | W20: Estructura Resistente | X20: PTO 01 | Y20: =SUMIFS(Cert_App_Output!$G:$G,Cert_App_Output!$E:$E,$E20,Cert_App_Output!$K:$K,$X20) -> 0
A21: Hormigón MT | C21: Homigón MO | D21: Homigón MO | E21: 3.02 | F21: OK | G21: Micropilotes Ø 20 cm | H21: gl | I21: 1 | J21: 11090041 | K21: 34350000 | L21: 2460301.5 | M21: 718505.14 | N21: =SUM(J21:M21) -> 48618848 | O21: =IF($N21=0,$S21,J21/$N21*$S21) -> 15043276 | P21: =IF($N21=0,0,K21/$N21*$S21) -> 46594646 | Q21: =IF($N21=0,0,L21/$N21*$S21) -> 3337318.1 | R21: =IF($N21=0,0,M21/$N21*$S21) -> 974628.6 | S21: 65949869 | T21: =IFERROR(S21/N21,"") -> 1.3564671 | U21: =N21*I21 -> 48618848 | V21: =S21*I21 -> 65949869 | W21: Estructura Resistente | X21: PTO 01 | Y21: =SUMIFS(Cert_App_Output!$G:$G,Cert_App_Output!$E:$E,$E21,Cert_App_Output!$K:$K,$X21) -> 1
A22: Hormigón MT | C22: Homigón MO | E22: 3.03 | F22: OK | G22: Platea - H30 (110 kg/m3 de hierro) | H22: m3 | I22: 7 | J22: 357146.17 | K22: 222927.96 | L22: 0 | M22: 8701.11 | N22: =SUM(J22:M22) -> 588775.24 | O22: =IF($N22=0,$S22,J22/$N22*$S22) -> 484457.04 | P22: =IF($N22=0,0,K22/$N22*$S22) -> 302394.45 | Q22: =IF($N22=0,0,L22/$N22*$S22) -> 0 | R22: =IF($N22=0,0,M22/$N22*$S22) -> 11802.77 | S22: 798654.26 | T22: =IFERROR(S22/N22,"") -> 1.3564671 | U22: =N22*I22 -> 4121426.7 | V22: =S22*I22 -> 5590579.8 | W22: Estructura Resistente | X22: PTO 01 | Y22: =SUMIFS(Cert_App_Output!$G:$G,Cert_App_Output!$E:$E,$E22,Cert_App_Output!$K:$K,$X22) -> 0.5
A23: Hormigón MT | C23: Homigón MO | E23: 3.04 | F23: OK | G23: Zapata corrida tabique - H30 (180 kg/m3 de hierro) | H23: m3 | I23: 4 | J23: 537813.29 | K23: 323084 | L23: 0 | M23: 12913.46 | N23: =SUM(J23:M23) -> 873810.75 | O23: =IF($N23=0,$S23,J23/$N23*$S23) -> 729526.05 | P23: =IF($N23=0,0,K23/$N23*$S23) -> 438252.82 | Q23: =IF($N23=0,0,L23/$N23*$S23) -> 0 | R23: =IF($N23=0,0,M23/$N23*$S23) -> 17516.684 | S23: 1185295.6 | T23: =IFERROR(S23/N23,"") -> 1.3564671 | U23: =N23*I23 -> 3495243 | V23: =S23*I23 -> 4741182.2 | W23: Estructura Resistente | X23: PTO 01 | Y23: =SUMIFS(Cert_App_Output!$G:$G,Cert_App_Output!$E:$E,$E23,Cert_App_Output!$K:$K,$X23) -> 0.5
A24: Hormigón MT | C24: Homigón MO | E24: 3.05 | F24: OK | G24: Bases aisladas - H30 (110 kg/m3 de hierro) | H24: m3 | I24: 2 | J24: 357146.17 | K24: 222927.96 | L24: 0 | M24: 8701.11 | N24: =SUM(J24:M24) -> 588775.24 | O24: =IF($N24=0,$S24,J24/$N24*$S24) -> 484457.04 | P24: =IF($N24=0,0,K24/$N24*$S24) -> 302394.45 | Q24: =IF($N24=0,0,L24/$N24*$S24) -> 0 | R24: =IF($N24=0,0,M24/$N24*$S24) -> 11802.77 | S24: 798654.26 | T24: =IFERROR(S24/N24,"") -> 1.3564671 | U24: =N24*I24 -> 1177550.5 | V24: =S24*I24 -> 1597308.5 | W24: Estructura Resistente | X24: PTO 01 | Y24: =SUMIFS(Cert_App_Output!$G:$G,Cert_App_Output!$E:$E,$E24,Cert_App_Output!$K:$K,$X24) -> 0.5
A25: Hormigón MT | C25: Homigón MO | E25: 3.06 | F25: OK | G25: Cabezales - H30 (130 kg/m3 de hierro) | H25: m3 | I25: 11 | J25: 392586.17 | K25: 222927.96 | L25: 0 | M25: 9232.71 | N25: =SUM(J25:M25) -> 624746.84 | O25: =IF($N25=0,$S25,J25/$N25*$S25) -> 532530.23 | P25: =IF($N25=0,0,K25/$N25*$S25) -> 302394.45 | Q25: =IF($N25=0,0,L25/$N25*$S25) -> 0 | R25: =IF($N25=0,0,M25/$N25*$S25) -> 12523.868 | S25: 847448.55 | T25: =IFERROR(S25/N25,"") -> 1.3564671 | U25: =N25*I25 -> 6872215.2 | V25: =S25*I25 -> 9321934 | W25: Estructura Resistente | X25: PTO 01 | Y25: =SUMIFS(Cert_App_Output!$G:$G,Cert_App_Output!$E:$E,$E25,Cert_App_Output!$K:$K,$X25) -> 0.7
A26: Hormigón MT | C26: Homigón MO | E26: 3.07 | F26: OK | G26: Viga de fundación - H30 (180 kg/m3 de hierro) | H26: m3 | I26: 9 | J26: 537813.29 | K26: 323084 | L26: 0 | M26: 12913.46 | N26: =SUM(J26:M26) -> 873810.75 | O26: =IF($N26=0,$S26,J26/$N26*$S26) -> 729526.05 | P26: =IF($N26=0,0,K26/$N26*$S26) -> 438252.82 | Q26: =IF($N26=0,0,L26/$N26*$S26) -> 0 | R26: =IF($N26=0,0,M26/$N26*$S26) -> 17516.684 | S26: 1185295.6 | T26: =IFERROR(S26/N26,"") -> 1.3564671 | U26: =N26*I26 -> 7864296.8 | V26: =S26*I26 -> 10667660 | W26: Estructura Resistente | X26: PTO 01 | Y26: =SUMIFS(Cert_App_Output!$G:$G,Cert_App_Output!$E:$E,$E26,Cert_App_Output!$K:$K,$X26) -> 0.7
A27: Hormigón MT | C27: Homigón MO | E27: 3.08 | F27: OK | G27: Tabique submuración - H30 (90 kg/m3 de hierro) | H27: m3 | I27: 9 | J27: 394401.89 | K27: 392678.73 | L27: 0 | M27: 11806.21 | N27: =SUM(J27:M27) -> 798886.83 | O27: =IF($N27=0,$S27,J27/$N27*$S27) -> 534993.2 | P27: =IF($N27=0,0,K27/$N27*$S27) -> 532655.79 | Q27: =IF($N27=0,0,L27/$N27*$S27) -> 0 | R27: =IF($N27=0,0,M27/$N27*$S27) -> 16014.736 | S27: 1083663.7 | T27: =IFERROR(S27/N27,"") -> 1.3564671 | U27: =N27*I27 -> 7189981.5 | V27: =S27*I27 -> 9752973.5 | W27: Estructura Resistente | X27: PTO 01 | Y27: =SUMIFS(Cert_App_Output!$G:$G,Cert_App_Output!$E:$E,$E27,Cert_App_Output!$K:$K,$X27) -> 0.5
A28: Hormigón MT | C28: Homigón MO | E28: 3.09 | F28: OK | G28: Puntales de compresión/codales - H30 (120 kg/m3) | H28: m3 | I28: 1 | J28: 542036.05 | K28: 362209.61 | L28: 0 | M28: 13563.68 | N28: =SUM(J28:M28) -> 917809.34 | O28: =IF($N28=0,$S28,J28/$N28*$S28) -> 735254.08 | P28: =IF($N28=0,0,K28/$N28*$S28) -> 491325.43 | Q28: =IF($N28=0,0,L28/$N28*$S28) -> 0 | R28: =IF($N28=0,0,M28/$N28*$S28) -> 18398.686 | S28: 1244978.2 | T28: =IFERROR(S28/N28,"") -> 1.3564671 | U28: =N28*I28 -> 917809.34 | V28: =S28*I28 -> 1244978.2 | W28: Estructura Resistente | X28: PTO 01 | Y28: =SUMIFS(Cert_App_Output!$G:$G,Cert_App_Output!$E:$E,$E28,Cert_App_Output!$K:$K,$X28) -> 0.5
A29: Hormigón MT | C29: Homigón MO | E29: 3.1 | F29: OK | G29: Columna - H30 (240 kg/m3 de hierro) | H29: m3 | I29: 32 | J29: 648356.05 | K29: 362209.61 | L29: 0 | M29: 15158.48 | N29: =SUM(J29:M29) -> 1025724.1 | O29: =IF($N29=0,$S29,J29/$N29*$S29) -> 879473.67 | P29: =IF($N29=0,0,K29/$N29*$S29) -> 491325.43 | Q29: =IF($N29=0,0,L29/$N29*$S29) -> 0 | R29: =IF($N29=0,0,M29/$N29*$S29) -> 20561.98 | S29: 1391361.1 | T29: =IFERROR(S29/N29,"") -> 1.3564671 | U29: =N29*I29 -> 32823172 | V29: =S29*I29 -> 44523554 | W29: Estructura Resistente | X29: PTO 01 | Y29: =SUMIFS(Cert_App_Output!$G:$G,Cert_App_Output!$E:$E,$E29,Cert_App_Output!$K:$K,$X29) -> 0
A30: Hormigón MT | C30: Homigón MO | E30: 3.11 | F30: OK | G30: Tabiques - H30 (120 kg/m3 de hierro) | H30: m3 | I30: 30 | J30: 447561.89 | K30: 392678.73 | L30: 0 | M30: 12603.61 | N30: =SUM(J30:M30) -> 852844.23 | O30: =IF($N30=0,$S30,J30/$N30*$S30) -> 607102.99 | P30: =IF($N30=0,0,K30/$N30*$S30) -> 532655.79 | Q30: =IF($N30=0,0,L30/$N30*$S30) -> 0 | R30: =IF($N30=0,0,M30/$N30*$S30) -> 17096.383 | S30: 1156855.2 | T30: =IFERROR(S30/N30,"") -> 1.3564671 | U30: =N30*I30 -> 25585327 | V30: =S30*I30 -> 34705655 | W30: Estructura Resistente | X30: PTO 01 | Y30: =SUMIFS(Cert_App_Output!$G:$G,Cert_App_Output!$E:$E,$E30,Cert_App_Output!$K:$K,$X30) -> 0
A31: Hormigón MT | C31: Homigón MO | D31: Homigón MO | E31: 3.12 | F31: OK | G31: Viga H° Visto - H30 (120 kg/m3 de hierro) | H31: m3 | I31: 7 | J31: 466389.3 | K31: 629584.36 | L31: 157396.09 | M31: 18800.55 | N31: =SUM(J31:M31) -> 1272170.3 | O31: =IF($N31=0,$S31,J31/$N31*$S31) -> 632641.75 | P31: =IF($N31=0,0,K31/$N31*$S31) -> 854010.49 | Q31: =IF($N31=0,0,L31/$N31*$S31) -> 213502.62 | R31: =IF($N31=0,0,M31/$N31*$S31) -> 25502.328 | S31: 1725657.2 | T31: =IFERROR(S31/N31,"") -> 1.3564671 | U31: =N31*I31 -> 8905192.1 | V31: =S31*I31 -> 12079600 | W31: Estructura Resistente | X31: PTO 01 | Y31: =SUMIFS(Cert_App_Output!$G:$G,Cert_App_Output!$E:$E,$E31,Cert_App_Output!$K:$K,$X31) -> 0
A32: Hormigón MT | C32: Homigón MO | D32: Homigón MO | E32: 3.13 | F32: OK | G32: Viga apeo s/PB - H30 (180 kg/m3 de hierro) | H32: m3 | I32: 12 | J32: 578369.51 | K32: 629584.36 | L32: 157396.09 | M32: 20480.25 | N32: =SUM(J32:M32) -> 1385830.2 | O32: =IF($N32=0,$S32,J32/$N32*$S32) -> 784539.23 | P32: =IF($N32=0,0,K32/$N32*$S32) -> 854010.49 | Q32: =IF($N32=0,0,L32/$N32*$S32) -> 213502.62 | R32: =IF($N32=0,0,M32/$N32*$S32) -> 27780.786 | S32: 1879833.1 | T32: =IFERROR(S32/N32,"") -> 1.3564671 | U32: =N32*I32 -> 16629963 | V32: =S32*I32 -> 22557997 | W32: Estructura Resistente | X32: PTO 01 | Y32: =SUMIFS(Cert_App_Output!$G:$G,Cert_App_Output!$E:$E,$E32,Cert_App_Output!$K:$K,$X32) -> 0.2
A33: Hormigón MT | C33: Homigón MO | E33: 3.14 | F33: OK | G33: Viga - H30 (120 kg/m3 de hierro) | H33: m3 | I33: 41 | J33: 472049.51 | K33: 629584.36 | L33: 0 | M33: 16524.51 | N33: =SUM(J33:M33) -> 1118158.4 | O33: =IF($N33=0,$S33,J33/$N33*$S33) -> 640319.64 | P33: =IF($N33=0,0,K33/$N33*$S33) -> 854010.49 | Q33: =IF($N33=0,0,L33/$N33*$S33) -> 0 | R33: =IF($N33=0,0,M33/$N33*$S33) -> 22414.955 | S33: 1516745.1 | T33: =IFERROR(S33/N33,"") -> 1.3564671 | U33: =N33*I33 -> 45844494 | V33: =S33*I33 -> 62186548 | W33: Estructura Resistente | X33: PTO 01 | Y33: =SUMIFS(Cert_App_Output!$G:$G,Cert_App_Output!$E:$E,$E33,Cert_App_Output!$K:$K,$X33) -> 0
A34: Hormigón MT | C34: Homigón MO | E34: 3.15 | F34: OK | G34: Losa - H30 (95 kg/m3 de hierro) | H34: m3 | I34: 135 | J34: 361563.22 | K34: 253632.45 | L34: 0 | M34: 9227.94 | N34: =SUM(J34:M34) -> 624423.61 | O34: =IF($N34=0,$S34,J34/$N34*$S34) -> 490448.62 | P34: =IF($N34=0,0,K34/$N34*$S34) -> 344044.08 | Q34: =IF($N34=0,0,L34/$N34*$S34) -> 0 | R34: =IF($N34=0,0,M34/$N34*$S34) -> 12517.397 | S34: 847010.1 | T34: =IFERROR(S34/N34,"") -> 1.3564671 | U34: =N34*I34 -> 84297187 | V34: =S34*I34 -> 1.1434636e+08 | W34: Estructura Resistente | X34: PTO 01 | Y34: =SUMIFS(Cert_App_Output!$G:$G,Cert_App_Output!$E:$E,$E34,Cert_App_Output!$K:$K,$X34) -> 0
A35: Hormigón MT | C35: Homigón MO | D35: Homigón MO | E35: 3.16 | F35: OK | G35: Losa H° Visto - H30 (95 kg/m3 de hierro) | H35: m3 | I35: 13 | J35: 367994.55 | K35: 253632.45 | L35: 63408.11 | M35: 10275.53 | N35: =SUM(J35:M35) -> 695310.64 | O35: =IF($N35=0,$S35,J35/$N35*$S35) -> 499172.51 | P35: =IF($N35=0,0,K35/$N35*$S35) -> 344044.08 | Q35: =IF($N35=0,0,L35/$N35*$S35) -> 86011.017 | R35: =IF($N35=0,0,M35/$N35*$S35) -> 13938.419 | S35: 943166.02 | T35: =IFERROR(S35/N35,"") -> 1.3564671 | U35: =N35*I35 -> 9039038.3 | V35: =S35*I35 -> 12261158 | W35: Estructura Resistente | X35: PTO 01 | Y35: =SUMIFS(Cert_App_Output!$G:$G,Cert_App_Output!$E:$E,$E35,Cert_App_Output!$K:$K,$X35) -> 0
A36: Hormigón MT | C36: Homigón MO | E36: 3.17 | F36: OK | G36: Escalera - H30 (105 kg/m3) | H36: m3 | I36: 14 | J36: 404870.23 | K36: 370454.15 | L36: 0 | M36: 11629.87 | N36: =SUM(J36:M36) -> 786954.25 | O36: =IF($N36=0,$S36,J36/$N36*$S36) -> 549193.16 | P36: =IF($N36=0,0,K36/$N36*$S36) -> 502508.88 | Q36: =IF($N36=0,0,L36/$N36*$S36) -> 0 | R36: =IF($N36=0,0,M36/$N36*$S36) -> 15775.536 | S36: 1067477.6 | T36: =IFERROR(S36/N36,"") -> 1.3564671 | U36: =N36*I36 -> 11017360 | V36: =S36*I36 -> 14944686 | W36: Estructura Resistente | X36: PTO 01 | Y36: =SUMIFS(Cert_App_Output!$G:$G,Cert_App_Output!$E:$E,$E36,Cert_App_Output!$K:$K,$X36) -> 0
A37: Hormigón MT | C37: Homigón MO | D37: Homigón MO | E37: 3.18 | F37: OK | G37: Viga alero - H30 (120 kg/m3 de hierro) | H37: m3 | I37: 2 | J37: 466389.3 | K37: 629584.36 | L37: 157396.09 | M37: 18800.55 | N37: =SUM(J37:M37) -> 1272170.3 | O37: =IF($N37=0,$S37,J37/$N37*$S37) -> 632641.75 | P37: =IF($N37=0,0,K37/$N37*$S37) -> 854010.49 | Q37: =IF($N37=0,0,L37/$N37*$S37) -> 213502.62 | R37: =IF($N37=0,0,M37/$N37*$S37) -> 25502.328 | S37: 1725657.2 | T37: =IFERROR(S37/N37,"") -> 1.3564671 | U37: =N37*I37 -> 2544340.6 | V37: =S37*I37 -> 3451314.4 | W37: Estructura Resistente | X37: PTO 01 | Y37: =SUMIFS(Cert_App_Output!$G:$G,Cert_App_Output!$E:$E,$E37,Cert_App_Output!$K:$K,$X37) -> 0
E38: 3.19 | F38: OK | G38: Sistema de apuntalamiento y reapuntalamiento | H38: gl | I38: 1 | J38: 0 | K38: 0 | L38: 0 | M38: 10584988 | N38: =SUM(J38:M38) -> 10584988 | O38: =IF($N38=0,$S38,J38/$N38*$S38) -> 0 | P38: =IF($N38=0,0,K38/$N38*$S38) -> 0 | Q38: =IF($N38=0,0,L38/$N38*$S38) -> 0 | R38: =IF($N38=0,0,M38/$N38*$S38) -> 14358188 | S38: 14358188 | T38: =IFERROR(S38/N38,"") -> 1.3564671 | U38: =N38*I38 -> 10584988 | V38: =S38*I38 -> 14358188 | W38: Estructura Resistente | X38: PTO 01 | Y38: =SUMIFS(Cert_App_Output!$G:$G,Cert_App_Output!$E:$E,$E38,Cert_App_Output!$K:$K,$X38) -> 0
C39: Homigón MO | E39: 3.2 | F39: OK | G39: Ensayos de Hormigon por etapas de hormigonado | H39: u | I39: 13 | J39: 0 | K39: 246942.15 | L39: 0 | M39: 0 | N39: =SUM(J39:M39) -> 246942.15 | O39: =IF($N39=0,$S39,J39/$N39*$S39) -> 0 | P39: =IF($N39=0,0,K39/$N39*$S39) -> 334968.91 | Q39: =IF($N39=0,0,L39/$N39*$S39) -> 0 | R39: =IF($N39=0,0,M39/$N39*$S39) -> 0 | S39: 334968.91 | T39: =IFERROR(S39/N39,"") -> 1.3564671 | U39: =N39*I39 -> 3210247.9 | V39: =S39*I39 -> 4354595.8 | W39: Estructura Resistente | X39: PTO 01 | Y39: =SUMIFS(Cert_App_Output!$G:$G,Cert_App_Output!$E:$E,$E39,Cert_App_Output!$K:$K,$X39) -> 0
A40: Hormigón MT | E40: 3.21 | F40: OK | G40: Permiso de estacionamiento de bomba de hormigón a contramano | H40: gl | I40: 3 | J40: 55000 | K40: 0 | L40: 0 | M40: 0 | N40: =SUM(J40:M40) -> 55000 | O40: =IF($N40=0,$S40,J40/$N40*$S40) -> 74605.692 | P40: =IF($N40=0,0,K40/$N40*$S40) -> 0 | Q40: =IF($N40=0,0,L40/$N40*$S40) -> 0 | R40: =IF($N40=0,0,M40/$N40*$S40) -> 0 | S40: 74605.692 | T40: =IFERROR(S40/N40,"") -> 1.3564671 | U40: =N40*I40 -> 165000 | V40: =S40*I40 -> 223817.08 | W40: Estructura Resistente | X40: PTO 01 | Y40: =SUMIFS(Cert_App_Output!$G:$G,Cert_App_Output!$E:$E,$E40,Cert_App_Output!$K:$K,$X40) -> 0.35
A41: Hormigón MT | D41: Homigón MO | E41: 3.22 | F41: OK | G41: Picado de medianeras para columnas y vigas - Cotizado solo para PB, 1P, NO contempla picado en CT | H41: m2 | I41: 65 | J41: 9230.77 | K41: 0 | L41: 20224.02 | M41: 441.82 | N41: =SUM(J41:M41) -> 29896.61 | O41: =IF($N41=0,$S41,J41/$N41*$S41) -> 12521.236 | P41: =IF($N41=0,0,K41/$N41*$S41) -> 0 | Q41: =IF($N41=0,0,L41/$N41*$S41) -> 27433.218 | R41: =IF($N41=0,0,M41/$N41*$S41) -> 599.3143 | S41: 40553.769 | T41: =IFERROR(S41/N41,"") -> 1.3564671 | U41: =N41*I41 -> 1943279.7 | V41: =S41*I41 -> 2635995 | W41: Estructura Resistente | X41: PTO 01 | Y41: =SUMIFS(Cert_App_Output!$G:$G,Cert_App_Output!$E:$E,$E41,Cert_App_Output!$K:$K,$X41) -> 0
F42: - | G42: AYUDA DE GREMIOS | W42: Ayuda de Gremios | X42: PTO 01
C43: Albañilería MO | E43: 24.01 | F43: OK | G43: Sereno | H43: mes | I43: 10 | J43: 0 | K43: 806885.99 | L43: 0 | M43: 0 | N43: =SUM(J43:M43) -> 806885.99 | O43: =IF($N43=0,$S43,J43/$N43*$S43) -> 0 | P43: =IF($N43=0,0,K43/$N43*$S43) -> 1094514.3 | Q43: =IF($N43=0,0,L43/$N43*$S43) -> 0 | R43: =IF($N43=0,0,M43/$N43*$S43) -> 0 | S43: 1094514.3 | T43: =IFERROR(S43/N43,"") -> 1.3564671 | U43: =N43*I43 -> 8068859.9 | V43: =S43*I43 -> 10945143 | W43: Ayuda de Gremios | X43: PTO 01 | Y43: =SUMIFS(Cert_App_Output!$G:$G,Cert_App_Output!$E:$E,$E43,Cert_App_Output!$K:$K,$X43) -> 0.2
C44: Seguridad e Higiene | E44: 24.02 | F44: OK | G44: Tecnico de seguridad & higiene permanente en Obra | H44: mes | I44: 1 | J44: 0 | K44: 1623254.5 | L44: 0 | M44: 0 | N44: =SUM(J44:M44) -> 1623254.5 | O44: =IF($N44=0,$S44,J44/$N44*$S44) -> 0 | P44: =IF($N44=0,0,K44/$N44*$S44) -> 2201891.3 | Q44: =IF($N44=0,0,L44/$N44*$S44) -> 0 | R44: =IF($N44=0,0,M44/$N44*$S44) -> 0 | S44: 2201891.3 | T44: =IFERROR(S44/N44,"") -> 1.3564671 | U44: =N44*I44 -> 1623254.5 | V44: =S44*I44 -> 2201891.3 | W44: Ayuda de Gremios | X44: PTO 01 | Y44: =SUMIFS(Cert_App_Output!$G:$G,Cert_App_Output!$E:$E,$E44,Cert_App_Output!$K:$K,$X44) -> 0
C45: Seguridad e Higiene | E45: 24.03 | F45: OK | G45: Higiene y seguridad Res 51 | H45: mes | I45: 10 | J45: 0 | K45: 300000 | L45: 0 | M45: 0 | N45: =SUM(J45:M45) -> 300000 | O45: =IF($N45=0,$S45,J45/$N45*$S45) -> 0 | P45: =IF($N45=0,0,K45/$N45*$S45) -> 406940.14 | Q45: =IF($N45=0,0,L45/$N45*$S45) -> 0 | R45: =IF($N45=0,0,M45/$N45*$S45) -> 0 | S45: 406940.14 | T45: =IFERROR(S45/N45,"") -> 1.3564671 | U45: =N45*I45 -> 3000000 | V45: =S45*I45 -> 4069401.4 | W45: Ayuda de Gremios | X45: PTO 01 | Y45: =SUMIFS(Cert_App_Output!$G:$G,Cert_App_Output!$E:$E,$E45,Cert_App_Output!$K:$K,$X45) -> 0.2
A46: Hormigón MT | C46: Homigón MO | D46: Homigón MO | E46: 24.04 | F46: OK | G46: Protecciones y defensas | H46: gl | I46: 1 | J46: 4076935.9 | K46: 600000 | L46: 4999453.5 | M46: 145145.84 | N46: =SUM(J46:M46) -> 9821535.2 | O46: =IF($N46=0,$S46,J46/$N46*$S46) -> 5530229.6 | P46: =IF($N46=0,0,K46/$N46*$S46) -> 813880.27 | Q46: =IF($N46=0,0,L46/$N46*$S46) -> 6781594.3 | R46: =IF($N46=0,0,M46/$N46*$S46) -> 196885.56 | S46: 13322590 | T46: =IFERROR(S46/N46,"") -> 1.3564671 | U46: =N46*I46 -> 9821535.2 | V46: =S46*I46 -> 13322590 | W46: Ayuda de Gremios | X46: PTO 01 | Y46: =SUMIFS(Cert_App_Output!$G:$G,Cert_App_Output!$E:$E,$E46,Cert_App_Output!$K:$K,$X46) -> 0
A47: Albañilería MT | D47: Albañilería MO | E47: 24.05 | F47: OK | G47: Ayuda de gremios | H47: mes | I47: 10 | J47: 50000 | K47: 0 | L47: 657280.53 | M47: 10609.21 | N47: =SUM(J47:M47) -> 717889.74 | O47: =IF($N47=0,$S47,J47/$N47*$S47) -> 67823.356 | P47: =IF($N47=0,0,K47/$N47*$S47) -> 0 | Q47: =IF($N47=0,0,L47/$N47*$S47) -> 891579.43 | R47: =IF($N47=0,0,M47/$N47*$S47) -> 14391.045 | S47: 973793.83 | T47: =IFERROR(S47/N47,"") -> 1.3564671 | U47: =N47*I47 -> 7178897.4 | V47: =S47*I47 -> 9737938.3 | W47: Ayuda de Gremios | X47: PTO 01 | Y47: =SUMIFS(Cert_App_Output!$G:$G,Cert_App_Output!$E:$E,$E47,Cert_App_Output!$K:$K,$X47) -> 0
A48: Albañilería MT | D48: Albañilería MO | E48: 24.06 | F48: OK | G48: Limpieza periódica | H48: mes | I48: 10 | J48: 50000 | K48: 0 | L48: 591716.39 | M48: 9625.75 | N48: =SUM(J48:M48) -> 651342.14 | O48: =IF($N48=0,$S48,J48/$N48*$S48) -> 67823.356 | P48: =IF($N48=0,0,K48/$N48*$S48) -> 0 | Q48: =IF($N48=0,0,L48/$N48*$S48) -> 802643.83 | R48: =IF($N48=0,0,M48/$N48*$S48) -> 13057.013 | S48: 883524.2 | T48: =IFERROR(S48/N48,"") -> 1.3564671 | U48: =N48*I48 -> 6513421.4 | V48: =S48*I48 -> 8835242 | W48: Ayuda de Gremios | X48: PTO 01 | Y48: =SUMIFS(Cert_App_Output!$G:$G,Cert_App_Output!$E:$E,$E48,Cert_App_Output!$K:$K,$X48) -> 0.1
C49: Mov. Variables | E49: 24.08 | F49: OK | G49: Fletes | H49: mes | I49: 10 | J49: 0 | K49: 300000 | L49: 0 | M49: 0 | N49: =SUM(J49:M49) -> 300000 | O49: =IF($N49=0,$S49,J49/$N49*$S49) -> 0 | P49: =IF($N49=0,0,K49/$N49*$S49) -> 406940.14 | Q49: =IF($N49=0,0,L49/$N49*$S49) -> 0 | R49: =IF($N49=0,0,M49/$N49*$S49) -> 0 | S49: 406940.14 | T49: =IFERROR(S49/N49,"") -> 1.3564671 | U49: =N49*I49 -> 3000000 | V49: =S49*I49 -> 4069401.4 | W49: Ayuda de Gremios | X49: PTO 01 | Y49: =SUMIFS(Cert_App_Output!$G:$G,Cert_App_Output!$E:$E,$E49,Cert_App_Output!$K:$K,$X49) -> 0
A50: Gastos Generales | D50: Gastos Generales | E50: 24.09 | F50: OK | G50: Volquetes | H50: mes | I50: 10 | J50: 200000 | K50: 0 | L50: 67240.5 | M50: 4008.61 | N50: =SUM(J50:M50) -> 271249.11 | O50: =IF($N50=0,$S50,J50/$N50*$S50) -> 271293.42 | P50: =IF($N50=0,0,K50/$N50*$S50) -> 0 | Q50: =IF($N50=0,0,L50/$N50*$S50) -> 91209.528 | R50: =IF($N50=0,0,M50/$N50*$S50) -> 5437.5477 | S50: 367940.5 | T50: =IFERROR(S50/N50,"") -> 1.3564671 | U50: =N50*I50 -> 2712491.1 | V50: =S50*I50 -> 3679405 | W50: Ayuda de Gremios | X50: PTO 01 | Y50: =SUMIFS(Cert_App_Output!$G:$G,Cert_App_Output!$E:$E,$E50,Cert_App_Output!$K:$K,$X50) -> 0.2
F51: - | G51: JEFATURA DE OBRA | W51: Jefatura de Obra | X51: PTO 01
C52: Supervisión de Obra MO | E52: 25.01 | F52: OK | G52: Proyecto Ejecutivo y Supervisión profesional de Obra | H52: mes | I52: 10 | J52: 0 | K52: 3246508.9 | L52: 0 | M52: 0 | N52: =SUM(J52:M52) -> 3246508.9 | O52: =IF($N52=0,$S52,J52/$N52*$S52) -> 0 | P52: =IF($N52=0,0,K52/$N52*$S52) -> 4403782.6 | Q52: =IF($N52=0,0,L52/$N52*$S52) -> 0 | R52: =IF($N52=0,0,M52/$N52*$S52) -> 0 | S52: 4403782.6 | T52: =IFERROR(S52/N52,"") -> 1.3564671 | U52: =N52*I52 -> 32465089 | V52: =S52*I52 -> 44037826 | W52: Jefatura de Obra | X52: PTO 01 | Y52: =SUMIFS(Cert_App_Output!$G:$G,Cert_App_Output!$E:$E,$E52,Cert_App_Output!$K:$K,$X52) -> 0.2
C53: Mov. Variables | E53: 25.02 | F53: OK | G53: Movilidad y viaticos | H53: mes | I53: 10 | J53: 0 | K53: 500000 | L53: 0 | M53: 0 | N53: =SUM(J53:M53) -> 500000 | O53: =IF($N53=0,$S53,J53/$N53*$S53) -> 0 | P53: =IF($N53=0,0,K53/$N53*$S53) -> 678233.56 | Q53: =IF($N53=0,0,L53/$N53*$S53) -> 0 | R53: =IF($N53=0,0,M53/$N53*$S53) -> 0 | S53: 678233.56 | T53: =IFERROR(S53/N53,"") -> 1.3564671 | U53: =N53*I53 -> 5000000 | V53: =S53*I53 -> 6782335.6 | W53: Jefatura de Obra | X53: PTO 01 | Y53: =SUMIFS(Cert_App_Output!$G:$G,Cert_App_Output!$E:$E,$E53,Cert_App_Output!$K:$K,$X53) -> 0.2
F54: - | G54: MAMPOSTERÍA | W54: Mampostería | X54: PTO 02
A55: Albañilería MT | D55: Albañilería MO | E55: 4.01 | F55: OK | G55: Muro tipo 1 (interiores, divisorio de locales) e: 10 cm - Ladrillo hueco 08 x 18 x 33 | H55: m2 | I55: 437 | J55: 10053.79 | K55: 0 | L55: 10761.18 | M55: 255.78 | N55: =SUM(J55:M55) -> 21070.75 | O55: =IF($N55=0,$S55,J55/$N55*$S55) -> 13637.636 | P55: =IF($N55=0,0,K55/$N55*$S55) -> 0 | Q55: =IF($N55=0,0,L55/$N55*$S55) -> 14597.187 | R55: =IF($N55=0,0,M55/$N55*$S55) -> 346.95716 | S55: 28581.78 | T55: =IFERROR(S55/N55,"") -> 1.3564671 | U55: =N55*I55 -> 9207917.8 | V55: =S55*I55 -> 12490238 | W55: Mampostería | X55: PTO 02 | Y55: =SUMIFS(Cert_App_Output!$G:$G,Cert_App_Output!$E:$E,$E55,Cert_App_Output!$K:$K,$X55) -> 0
A56: Albañilería MT | D56: Albañilería MO | E56: 4.02 | F56: OK | G56: Muro tipo 2 y 3 (medianera, caja de escaleras y ascensor) e: 15 cm - Ladrillo hueco portante 12 x 19 x 33 | H56: m2 | I56: 723 | J56: 18207.26 | K56: 0 | L56: 10761.18 | M56: 255.78 | N56: =SUM(J56:M56) -> 29224.22 | O56: =IF($N56=0,$S56,J56/$N56*$S56) -> 24697.55 | P56: =IF($N56=0,0,K56/$N56*$S56) -> 0 | Q56: =IF($N56=0,0,L56/$N56*$S56) -> 14597.187 | R56: =IF($N56=0,0,M56/$N56*$S56) -> 346.95716 | S56: 39641.694 | T56: =IFERROR(S56/N56,"") -> 1.3564671 | U56: =N56*I56 -> 21129111 | V56: =S56*I56 -> 28660945 | W56: Mampostería | X56: PTO 02 | Y56: =SUMIFS(Cert_App_Output!$G:$G,Cert_App_Output!$E:$E,$E56,Cert_App_Output!$K:$K,$X56) -> 0
A57: Albañilería MT | D57: Albañilería MO | E57: 4.03 | F57: OK | G57: Muro tipo 4 (divisorio de unidades y fachadas) e: 15 cm - Ladrillo hueco 12 x 18 x 33 | H57: m2 | I57: 1008 | J57: 12465.04 | K57: 0 | L57: 10761.18 | M57: 255.78 | N57: =SUM(J57:M57) -> 23482 | O57: =IF($N57=0,$S57,J57/$N57*$S57) -> 16908.417 | P57: =IF($N57=0,0,K57/$N57*$S57) -> 0 | Q57: =IF($N57=0,0,L57/$N57*$S57) -> 14597.187 | R57: =IF($N57=0,0,M57/$N57*$S57) -> 346.95716 | S57: 31852.561 | T57: =IFERROR(S57/N57,"") -> 1.3564671 | U57: =N57*I57 -> 23669856 | V57: =S57*I57 -> 32107382 | W57: Mampostería | X57: PTO 02 | Y57: =SUMIFS(Cert_App_Output!$G:$G,Cert_App_Output!$E:$E,$E57,Cert_App_Output!$K:$K,$X57) -> 0
A58: Albañilería MT | D58: Albañilería MO | E58: 4.04 | F58: OK | G58: Enchape medianeras existentes - Contemplamos picado zonas sueltas y enchape con ladrillo comun para PB y 1° | H58: m2 | I58: 199 | J58: 6069.09 | K58: 0 | L58: 5380.59 | M58: 255.78 | N58: =SUM(J58:M58) -> 11705.46 | O58: =IF($N58=0,$S58,J58/$N58*$S58) -> 8232.5211 | P58: =IF($N58=0,0,K58/$N58*$S58) -> 0 | Q58: =IF($N58=0,0,L58/$N58*$S58) -> 7298.5934 | R58: =IF($N58=0,0,M58/$N58*$S58) -> 346.95716 | S58: 15878.072 | T58: =IFERROR(S58/N58,"") -> 1.3564671 | U58: =N58*I58 -> 2329386.5 | V58: =S58*I58 -> 3159736.3 | W58: Mampostería | X58: PTO 02 | Y58: =SUMIFS(Cert_App_Output!$G:$G,Cert_App_Output!$E:$E,$E58,Cert_App_Output!$K:$K,$X58) -> 0
A59: Albañilería MT | C59: Albañilería MO | E59: 4.05 | F59: IN | G59: Muro de tabique seco ignifugo | H59: m2 | I59: 34 | J59: 28944.11 | K59: 27718.21 | L59: 0 | M59: 441.16 | N59: =SUM(J59:M59) -> 57103.48 | O59: =IF($N59=0,$S59,J59/$N59*$S59) -> 39261.734 | P59: =IF($N59=0,0,K59/$N59*$S59) -> 37598.841 | Q59: =IF($N59=0,0,L59/$N59*$S59) -> 0 | R59: =IF($N59=0,0,M59/$N59*$S59) -> 598.41904 | S59: 77458.993 | T59: =IFERROR(S59/N59,"") -> 1.3564671 | U59: =N59*I59 -> 1941518.3 | V59: =S59*I59 -> 2633605.8 | W59: Mampostería | X59: PTO 02 | Y59: =SUMIFS(Cert_App_Output!$G:$G,Cert_App_Output!$E:$E,$E59,Cert_App_Output!$K:$K,$X59) -> 0
A60: Albañilería MT | D60: Albañilería MO | E60: 4.06 | F60: OK | G60: Vigas de encadenado - En muros de PB, incl. excavación y armado | H60: ml | I60: 24 | J60: 23405.01 | K60: 0 | L60: 36357.14 | M60: 896.43 | N60: =SUM(J60:M60) -> 60658.58 | O60: =IF($N60=0,$S60,J60/$N60*$S60) -> 31748.127 | P60: =IF($N60=0,0,K60/$N60*$S60) -> 0 | Q60: =IF($N60=0,0,L60/$N60*$S60) -> 49317.265 | R60: =IF($N60=0,0,M60/$N60*$S60) -> 1215.9778 | S60: 82281.37 | T60: =IFERROR(S60/N60,"") -> 1.3564671 | U60: =N60*I60 -> 1455805.9 | V60: =S60*I60 -> 1974752.9 | W60: Mampostería | X60: PTO 02 | Y60: =SUMIFS(Cert_App_Output!$G:$G,Cert_App_Output!$E:$E,$E60,Cert_App_Output!$K:$K,$X60) -> 0
F61: - | G61: AISLACIONES | W61: Aislaciones | X61: PTO 02
A62: Albañilería MT | C62: Albañilería MO | D62: Albañilería MO | E62: 5.01 | F62: OK | G62: Aislación hidrófuga horizontal (baños) - Inc. membrana geotextil y 35% en concepto de babetas | H62: m2 | I62: 79 | J62: 11767.71 | K62: 4471.47 | L62: 12775.62 | M62: 34.98 | N62: =SUM(J62:M62) -> 29049.78 | O62: =IF($N62=0,$S62,J62/$N62*$S62) -> 15962.512 | P62: =IF($N62=0,0,K62/$N62*$S62) -> 6065.4021 | Q62: =IF($N62=0,0,L62/$N62*$S62) -> 17329.709 | R62: =IF($N62=0,0,M62/$N62*$S62) -> 47.44922 | S62: 39405.072 | T62: =IFERROR(S62/N62,"") -> 1.3564671 | U62: =N62*I62 -> 2294932.6 | V62: =S62*I62 -> 3113000.7 | W62: Aislaciones | X62: PTO 02 | Y62: =SUMIFS(Cert_App_Output!$G:$G,Cert_App_Output!$E:$E,$E62,Cert_App_Output!$K:$K,$X62) -> 0
A63: Albañilería MT | D63: Albañilería MO | E63: 5.02 | F63: OK | G63: Cajón hidrófugo - Muros de PB | H63: ml | I63: 113 | J63: 827.28 | K63: 0 | L63: 4324.05 | M63: 137.03 | N63: =SUM(J63:M63) -> 5288.36 | O63: =IF($N63=0,$S63,J63/$N63*$S63) -> 1122.1781 | P63: =IF($N63=0,0,K63/$N63*$S63) -> 0 | Q63: =IF($N63=0,0,L63/$N63*$S63) -> 5865.4317 | R63: =IF($N63=0,0,M63/$N63*$S63) -> 185.87669 | S63: 7173.4865 | T63: =IFERROR(S63/N63,"") -> 1.3564671 | U63: =N63*I63 -> 597584.68 | V63: =S63*I63 -> 810603.97 | W63: Aislaciones | X63: PTO 02 | Y63: =SUMIFS(Cert_App_Output!$G:$G,Cert_App_Output!$E:$E,$E63,Cert_App_Output!$K:$K,$X63) -> 0
A64: Albañilería MT | D64: Albañilería MO | E64: 5.03 | F64: OK | G64: Azotado hidrófugo - Sobre contrapiso en vereda y PB | H64: m2 | I64: 207 | J64: 827.28 | K64: 0 | L64: 4324.05 | M64: 137.03 | N64: =SUM(J64:M64) -> 5288.36 | O64: =IF($N64=0,$S64,J64/$N64*$S64) -> 1122.1781 | P64: =IF($N64=0,0,K64/$N64*$S64) -> 0 | Q64: =IF($N64=0,0,L64/$N64*$S64) -> 5865.4317 | R64: =IF($N64=0,0,M64/$N64*$S64) -> 185.87669 | S64: 7173.4865 | T64: =IFERROR(S64/N64,"") -> 1.3564671 | U64: =N64*I64 -> 1094690.5 | V64: =S64*I64 -> 1484911.7 | W64: Aislaciones | X64: PTO 02 | Y64: =SUMIFS(Cert_App_Output!$G:$G,Cert_App_Output!$E:$E,$E64,Cert_App_Output!$K:$K,$X64) -> 0
A65: Albañilería MT | E65: 5.04 | F65: OK | G65: Aislación térmica en terrazas, eps e:2,00 cm | H65: m2 | I65: 165 | J65: 3538.08 | K65: 0 | L65: 0 | M65: 0 | N65: =SUM(J65:M65) -> 3538.08 | O65: =IF($N65=0,$S65,J65/$N65*$S65) -> 4799.2892 | P65: =IF($N65=0,0,K65/$N65*$S65) -> 0 | Q65: =IF($N65=0,0,L65/$N65*$S65) -> 0 | R65: =IF($N65=0,0,M65/$N65*$S65) -> 0 | S65: 4799.2892 | T65: =IFERROR(S65/N65,"") -> 1.3564671 | U65: =N65*I65 -> 583783.2 | V65: =S65*I65 -> 791882.72 | W65: Aislaciones | X65: PTO 02 | Y65: =SUMIFS(Cert_App_Output!$G:$G,Cert_App_Output!$E:$E,$E65,Cert_App_Output!$K:$K,$X65) -> 0
A66: Albañilería MT | D66: Albañilería MO | E66: 5.05 | F66: OK | G66: Barrera de vapor | H66: m2 | I66: 165 | J66: 1392.61 | K66: 0 | L66: 2017.72 | M66: 10.93 | N66: =SUM(J66:M66) -> 3421.26 | O66: =IF($N66=0,$S66,J66/$N66*$S66) -> 1889.0297 | P66: =IF($N66=0,0,K66/$N66*$S66) -> 0 | Q66: =IF($N66=0,0,L66/$N66*$S66) -> 2736.9708 | R66: =IF($N66=0,0,M66/$N66*$S66) -> 14.826186 | S66: 4640.8267 | T66: =IFERROR(S66/N66,"") -> 1.3564671 | U66: =N66*I66 -> 564507.9 | V66: =S66*I66 -> 765736.41 | W66: Aislaciones | X66: PTO 02 | Y66: =SUMIFS(Cert_App_Output!$G:$G,Cert_App_Output!$E:$E,$E66,Cert_App_Output!$K:$K,$X66) -> 0
A67: Albañilería MT | C67: Albañilería MO | D67: Albañilería MO | E67: 5.06 | F67: OK | G67: Membrana asfaltica geotextil 4mm - Balcones y azotea - Inc. 20% en concepto de babetas | H67: m2 | I67: 274 | J67: 10460.18 | K67: 2555.12 | L67: 12775.62 | M67: 34.98 | N67: =SUM(J67:M67) -> 25825.9 | O67: =IF($N67=0,$S67,J67/$N67*$S67) -> 14188.89 | P67: =IF($N67=0,0,K67/$N67*$S67) -> 3465.9363 | Q67: =IF($N67=0,0,L67/$N67*$S67) -> 17329.709 | R67: =IF($N67=0,0,M67/$N67*$S67) -> 47.44922 | S67: 35031.984 | T67: =IFERROR(S67/N67,"") -> 1.3564671 | U67: =N67*I67 -> 7076296.6 | V67: =S67*I67 -> 9598763.7 | W67: Aislaciones | X67: PTO 02 | Y67: =SUMIFS(Cert_App_Output!$G:$G,Cert_App_Output!$E:$E,$E67,Cert_App_Output!$K:$K,$X67) -> 0
F68: - | G68: CUBIERTAS | W68: Cubiertas | X68: PTO 02
A69: Albañilería MT | D69: Albañilería MO | E69: 6.01 | F69: OK | G69: Babeta de chapa galvanizada en medianeras | H69: ml | I69: 44 | J69: 16295 | K69: 0 | L69: 8126.8 | M69: 366.33 | N69: =SUM(J69:M69) -> 24788.13 | O69: =IF($N69=0,$S69,J69/$N69*$S69) -> 22103.632 | P69: =IF($N69=0,0,K69/$N69*$S69) -> 0 | Q69: =IF($N69=0,0,L69/$N69*$S69) -> 11023.737 | R69: =IF($N69=0,0,M69/$N69*$S69) -> 496.9146 | S69: 33624.283 | T69: =IFERROR(S69/N69,"") -> 1.3564671 | U69: =N69*I69 -> 1090677.7 | V69: =S69*I69 -> 1479468.5 | W69: Cubiertas | X69: PTO 02 | Y69: =SUMIFS(Cert_App_Output!$G:$G,Cert_App_Output!$E:$E,$E69,Cert_App_Output!$K:$K,$X69) -> 0
F70: - | G70: REVOQUES | W70: Revoques | X70: PTO 02
A71: Albañilería MT | D71: Albañilería MO | E71: 7.01 | F71: OK | G71: Revoque Grueso Impermeable Exterior | H71: m2 | I71: 663 | J71: 4061.17 | K71: 0 | L71: 11697.52 | M71: 333.63 | N71: =SUM(J71:M71) -> 16092.32 | O71: =IF($N71=0,$S71,J71/$N71*$S71) -> 5508.8436 | P71: =IF($N71=0,0,K71/$N71*$S71) -> 0 | Q71: =IF($N71=0,0,L71/$N71*$S71) -> 15867.301 | R71: =IF($N71=0,0,M71/$N71*$S71) -> 452.55813 | S71: 21828.703 | T71: =IFERROR(S71/N71,"") -> 1.3564671 | U71: =N71*I71 -> 10669208 | V71: =S71*I71 -> 14472430 | W71: Revoques | X71: PTO 02 | Y71: =SUMIFS(Cert_App_Output!$G:$G,Cert_App_Output!$E:$E,$E71,Cert_App_Output!$K:$K,$X71) -> 0
A72: Albañilería MT | D72: Albañilería MO | E72: 7.02 | F72: OK | G72: Revoque Grueso Impermeable Exterior a mas de 3m - Medianero y fachadas | H72: m2 | I72: 1164 | J72: 4061.17 | K72: 0 | L72: 16815.18 | M72: 863.36 | N72: =SUM(J72:M72) -> 21739.71 | O72: =IF($N72=0,$S72,J72/$N72*$S72) -> 5508.8436 | P72: =IF($N72=0,0,K72/$N72*$S72) -> 0 | Q72: =IF($N72=0,0,L72/$N72*$S72) -> 22809.239 | R72: =IF($N72=0,0,M72/$N72*$S72) -> 1171.1195 | S72: 29489.202 | T72: =IFERROR(S72/N72,"") -> 1.3564671 | U72: =N72*I72 -> 25305022 | V72: =S72*I72 -> 34325431 | W72: Revoques | X72: PTO 02 | Y72: =SUMIFS(Cert_App_Output!$G:$G,Cert_App_Output!$E:$E,$E72,Cert_App_Output!$K:$K,$X72) -> 0
C73: Albañilería MO | E73: 7.03 | F73: OK | G73: Buña en revoque - Estimados ml en medianeras | H73: ml | I73: 500 | J73: 0 | K73: 11122.34 | L73: 0 | M73: 0 | N73: =SUM(J73:M73) -> 11122.34 | O73: =IF($N73=0,$S73,J73/$N73*$S73) -> 0 | P73: =IF($N73=0,0,K73/$N73*$S73) -> 15087.089 | Q73: =IF($N73=0,0,L73/$N73*$S73) -> 0 | R73: =IF($N73=0,0,M73/$N73*$S73) -> 0 | S73: 15087.089 | T73: =IFERROR(S73/N73,"") -> 1.3564671 | U73: =N73*I73 -> 5561170 | V73: =S73*I73 -> 7543544.3 | W73: Revoques | X73: PTO 02 | Y73: =SUMIFS(Cert_App_Output!$G:$G,Cert_App_Output!$E:$E,$E73,Cert_App_Output!$K:$K,$X73) -> 0
A74: Albañilería MT | D74: Albañilería MO | E74: 7.04 | F74: OK | G74: Revoque Grueso Interior + fino | H74: m2 | I74: 521 | J74: 2891.22 | K74: 0 | L74: 22980.58 | M74: 639.45 | N74: =SUM(J74:M74) -> 26511.25 | O74: =IF($N74=0,$S74,J74/$N74*$S74) -> 3921.8449 | P74: =IF($N74=0,0,K74/$N74*$S74) -> 0 | Q74: =IF($N74=0,0,L74/$N74*$S74) -> 31172.401 | R74: =IF($N74=0,0,M74/$N74*$S74) -> 867.3929 | S74: 35961.639 | T74: =IFERROR(S74/N74,"") -> 1.3564671 | U74: =N74*I74 -> 13812361 | V74: =S74*I74 -> 18736014 | W74: Revoques | X74: PTO 02 | Y74: =SUMIFS(Cert_App_Output!$G:$G,Cert_App_Output!$E:$E,$E74,Cert_App_Output!$K:$K,$X74) -> 0
A75: Durlock MT | C75: Durlock MO | E75: 7.05 | F75: OK | G75: Yeso interior | H75: m2 | I75: 2180 | J75: 5780.87 | K75: 12252.55 | L75: 0 | M75: 270.5 | N75: =SUM(J75:M75) -> 18303.92 | O75: =IF($N75=0,$S75,J75/$N75*$S75) -> 7841.5601 | P75: =IF($N75=0,0,K75/$N75*$S75) -> 16620.181 | Q75: =IF($N75=0,0,L75/$N75*$S75) -> 0 | R75: =IF($N75=0,0,M75/$N75*$S75) -> 366.92436 | S75: 24828.666 | T75: =IFERROR(S75/N75,"") -> 1.3564671 | U75: =N75*I75 -> 39902546 | V75: =S75*I75 -> 54126491 | W75: Revoques | X75: PTO 02 | Y75: =SUMIFS(Cert_App_Output!$G:$G,Cert_App_Output!$E:$E,$E75,Cert_App_Output!$K:$K,$X75) -> 0
C76: Durlock MO | E76: 7.06 | F76: OK | G76: Arista en yeso | H76: ml | I76: 255 | J76: 0 | K76: 13144.58 | L76: 0 | M76: 197.17 | N76: =SUM(J76:M76) -> 13341.75 | O76: =IF($N76=0,$S76,J76/$N76*$S76) -> 0 | P76: =IF($N76=0,0,K76/$N76*$S76) -> 17830.191 | Q76: =IF($N76=0,0,L76/$N76*$S76) -> 0 | R76: =IF($N76=0,0,M76/$N76*$S76) -> 267.45462 | S76: 18097.645 | T76: =IFERROR(S76/N76,"") -> 1.3564671 | U76: =N76*I76 -> 3402146.2 | V76: =S76*I76 -> 4614899.5 | W76: Revoques | X76: PTO 02 | Y76: =SUMIFS(Cert_App_Output!$G:$G,Cert_App_Output!$E:$E,$E76,Cert_App_Output!$K:$K,$X76) -> 0
A77: Durlock MT | C77: Durlock MO | E77: 7.07 | F77: OK | G77: Provisión y colocación de guardacanto yesero | H77: u | I77: 102 | J77: 1658.12 | K77: 13917.79 | L77: 0 | M77: 233.64 | N77: =SUM(J77:M77) -> 15809.55 | O77: =IF($N77=0,$S77,J77/$N77*$S77) -> 2249.1853 | P77: =IF($N77=0,0,K77/$N77*$S77) -> 18879.025 | Q77: =IF($N77=0,0,L77/$N77*$S77) -> 0 | R77: =IF($N77=0,0,M77/$N77*$S77) -> 316.92498 | S77: 21445.135 | T77: =IFERROR(S77/N77,"") -> 1.3564671 | U77: =N77*I77 -> 1612574.1 | V77: =S77*I77 -> 2187403.8 | W77: Revoques | X77: PTO 02 | Y77: =SUMIFS(Cert_App_Output!$G:$G,Cert_App_Output!$E:$E,$E77,Cert_App_Output!$K:$K,$X77) -> 0
A78: Albañilería MT | D78: Albañilería MO | E78: 7.08 | F78: OK | G78: Revoque Grueso Impermeable Interior b/ revestimiento | H78: m2 | I78: 715 | J78: 4061.17 | K78: 0 | L78: 11697.52 | M78: 333.63 | N78: =SUM(J78:M78) -> 16092.32 | O78: =IF($N78=0,$S78,J78/$N78*$S78) -> 5508.8436 | P78: =IF($N78=0,0,K78/$N78*$S78) -> 0 | Q78: =IF($N78=0,0,L78/$N78*$S78) -> 15867.301 | R78: =IF($N78=0,0,M78/$N78*$S78) -> 452.55813 | S78: 21828.703 | T78: =IFERROR(S78/N78,"") -> 1.3564671 | U78: =N78*I78 -> 11506009 | V78: =S78*I78 -> 15607523 | W78: Revoques | X78: PTO 02 | Y78: =SUMIFS(Cert_App_Output!$G:$G,Cert_App_Output!$E:$E,$E78,Cert_App_Output!$K:$K,$X78) -> 0
F79: - | G79: CONTRAPISOS Y CARPETAS | W79: Contrapisos y Carpetas | X79: PTO 02
A80: Albañilería MT | D80: Albañilería MO | E80: 8.01 | F80: OK | G80: Contrapiso de cascotes s/ss e: 15 cm | H80: m2 | I80: 21 | J80: 13595.33 | K80: 0 | L80: 19696.19 | M80: 503.76 | N80: =SUM(J80:M80) -> 33795.28 | O80: =IF($N80=0,$S80,J80/$N80*$S80) -> 18441.618 | P80: =IF($N80=0,0,K80/$N80*$S80) -> 0 | Q80: =IF($N80=0,0,L80/$N80*$S80) -> 26717.234 | R80: =IF($N80=0,0,M80/$N80*$S80) -> 683.33388 | S80: 45842.186 | T80: =IFERROR(S80/N80,"") -> 1.3564671 | U80: =N80*I80 -> 709700.88 | V80: =S80*I80 -> 962685.91 | W80: Contrapisos y Carpetas | X80: PTO 02 | Y80: =SUMIFS(Cert_App_Output!$G:$G,Cert_App_Output!$E:$E,$E80,Cert_App_Output!$K:$K,$X80) -> 0
A81: Albañilería MT | D81: Albañilería MO | E81: 8.02 | F81: OK | G81: Contrapiso armado de H° pobre s/terreno natural e: 20 cm - Incluye film de polietileno | H81: m2 | I81: 201 | J81: 30954.75 | K81: 0 | L81: 8768.73 | M81: 595.85 | N81: =SUM(J81:M81) -> 40319.33 | O81: =IF($N81=0,$S81,J81/$N81*$S81) -> 41989.101 | P81: =IF($N81=0,0,K81/$N81*$S81) -> 0 | Q81: =IF($N81=0,0,L81/$N81*$S81) -> 11894.494 | R81: =IF($N81=0,0,M81/$N81*$S81) -> 808.25094 | S81: 54691.846 | T81: =IFERROR(S81/N81,"") -> 1.3564671 | U81: =N81*I81 -> 8104185.3 | V81: =S81*I81 -> 10993061 | W81: Contrapisos y Carpetas | X81: PTO 02 | Y81: =SUMIFS(Cert_App_Output!$G:$G,Cert_App_Output!$E:$E,$E81,Cert_App_Output!$K:$K,$X81) -> 0
A82: Albañilería MT | D82: Albañilería MO | E82: 8.03 | F82: OK | G82: Contrapiso de cascotes en azoteas c/pendiente e: 15 cm | H82: m2 | I82: 107 | J82: 13595.33 | K82: 0 | L82: 19696.19 | M82: 503.76 | N82: =SUM(J82:M82) -> 33795.28 | O82: =IF($N82=0,$S82,J82/$N82*$S82) -> 18441.618 | P82: =IF($N82=0,0,K82/$N82*$S82) -> 0 | Q82: =IF($N82=0,0,L82/$N82*$S82) -> 26717.234 | R82: =IF($N82=0,0,M82/$N82*$S82) -> 683.33388 | S82: 45842.186 | T82: =IFERROR(S82/N82,"") -> 1.3564671 | U82: =N82*I82 -> 3616095 | V82: =S82*I82 -> 4905113.9 | W82: Contrapisos y Carpetas | X82: PTO 02 | Y82: =SUMIFS(Cert_App_Output!$G:$G,Cert_App_Output!$E:$E,$E82,Cert_App_Output!$K:$K,$X82) -> 0
A83: Albañilería MT | D83: Albañilería MO | E83: 8.04 | F83: OK | G83: Contrapiso - Carpeta monolitico e: 6 cm | H83: m2 | I83: 850 | J83: 6717.88 | K83: 0 | L83: 11145.02 | M83: 130.48 | N83: =SUM(J83:M83) -> 17993.38 | O83: =IF($N83=0,$S83,J83/$N83*$S83) -> 9112.5834 | P83: =IF($N83=0,0,K83/$N83*$S83) -> 0 | Q83: =IF($N83=0,0,L83/$N83*$S83) -> 15117.853 | R83: =IF($N83=0,0,M83/$N83*$S83) -> 176.99183 | S83: 24407.428 | T83: =IFERROR(S83/N83,"") -> 1.3564671 | U83: =N83*I83 -> 15294373 | V83: =S83*I83 -> 20746314 | W83: Contrapisos y Carpetas | X83: PTO 02 | Y83: =SUMIFS(Cert_App_Output!$G:$G,Cert_App_Output!$E:$E,$E83,Cert_App_Output!$K:$K,$X83) -> 0
A84: Albañilería MT | D84: Albañilería MO | E84: 8.05 | F84: OK | G84: Carpeta en PB, balcones, baños y azoteas e: 3,00 cm | H84: m2 | I84: 365 | J84: 3420.32 | K84: 0 | L84: 8295.69 | M84: 235.09 | N84: =SUM(J84:M84) -> 11951.1 | O84: =IF($N84=0,$S84,J84/$N84*$S84) -> 4639.5516 | P84: =IF($N84=0,0,K84/$N84*$S84) -> 0 | Q84: =IF($N84=0,0,L84/$N84*$S84) -> 11252.831 | R84: =IF($N84=0,0,M84/$N84*$S84) -> 318.89186 | S84: 16211.274 | T84: =IFERROR(S84/N84,"") -> 1.3564671 | U84: =N84*I84 -> 4362151.5 | V84: =S84*I84 -> 5917115.1 | W84: Contrapisos y Carpetas | X84: PTO 02 | Y84: =SUMIFS(Cert_App_Output!$G:$G,Cert_App_Output!$E:$E,$E84,Cert_App_Output!$K:$K,$X84) -> 0
A85: Albañilería MT | D85: Albañilería MO | E85: 8.06 | F85: OK | G85: Carpeta sobre membrana, e: 3,00 cm | H85: m2 | I85: 357 | J85: 3420.32 | K85: 0 | L85: 8295.69 | M85: 235.09 | N85: =SUM(J85:M85) -> 11951.1 | O85: =IF($N85=0,$S85,J85/$N85*$S85) -> 4639.5516 | P85: =IF($N85=0,0,K85/$N85*$S85) -> 0 | Q85: =IF($N85=0,0,L85/$N85*$S85) -> 11252.831 | R85: =IF($N85=0,0,M85/$N85*$S85) -> 318.89186 | S85: 16211.274 | T85: =IFERROR(S85/N85,"") -> 1.3564671 | U85: =N85*I85 -> 4266542.7 | V85: =S85*I85 -> 5787424.9 | W85: Contrapisos y Carpetas | X85: PTO 02 | Y85: =SUMIFS(Cert_App_Output!$G:$G,Cert_App_Output!$E:$E,$E85,Cert_App_Output!$K:$K,$X85) -> 0
E86: 8.07 | F86: R | G86: Banquinas para cocinas - N/A | H86: gl | I86: 0 | J86: 0 | K86: 0 | L86: 0 | M86: 0 | N86: =SUM(J86:M86) -> 0 | O86: =IF($N86=0,$S86,J86/$N86*$S86) -> 0 | P86: =IF($N86=0,0,K86/$N86*$S86) -> 0 | Q86: =IF($N86=0,0,L86/$N86*$S86) -> 0 | R86: =IF($N86=0,0,M86/$N86*$S86) -> 0 | S86: 0 | T86: =IFERROR(S86/N86,"") | U86: =N86*I86 -> 0 | V86: =S86*I86 -> 0 | W86: Contrapisos y Carpetas | X86: PTO 02 | Y86: =SUMIFS(Cert_App_Output!$G:$G,Cert_App_Output!$E:$E,$E86,Cert_App_Output!$K:$K,$X86) -> 0
A87: Albañilería MT | D87: Albañilería MO | E87: 8.08 | F87: OK | G87: Banquinas para bombas, TT, etc. h: 15 cm | H87: gl | I87: 1 | J87: 93485.02 | K87: 0 | L87: 303706.02 | M87: 5957.87 | N87: =SUM(J87:M87) -> 403148.91 | O87: =IF($N87=0,$S87,J87/$N87*$S87) -> 126809.36 | P87: =IF($N87=0,0,K87/$N87*$S87) -> 0 | Q87: =IF($N87=0,0,L87/$N87*$S87) -> 411967.23 | R87: =IF($N87=0,0,M87/$N87*$S87) -> 8081.6548 | S87: 546858.24 | T87: =IFERROR(S87/N87,"") -> 1.3564671 | U87: =N87*I87 -> 403148.91 | V87: =S87*I87 -> 546858.24 | W87: Contrapisos y Carpetas | X87: PTO 02 | Y87: =SUMIFS(Cert_App_Output!$G:$G,Cert_App_Output!$E:$E,$E87,Cert_App_Output!$K:$K,$X87) -> 0
F88: - | G88: ESCALERAS | W88: Escaleras | X88: PTO 02
A89: Albañilería MT | D89: Albañilería MO | E89: 9.01 | F89: OK | G89: Provisión y ejecución de alisado de cemento en pedadas y alzadas | H89: gl | I89: 1 | J89: 427508.24 | K89: 0 | L89: 2044758.2 | M89: 37084 | N89: =SUM(J89:M89) -> 2509350.4 | O89: =IF($N89=0,$S89,J89/$N89*$S89) -> 579900.87 | P89: =IF($N89=0,0,K89/$N89*$S89) -> 0 | Q89: =IF($N89=0,0,L89/$N89*$S89) -> 2773647.3 | R89: =IF($N89=0,0,M89/$N89*$S89) -> 50303.227 | S89: 3403851.4 | T89: =IFERROR(S89/N89,"") -> 1.3564671 | U89: =N89*I89 -> 2509350.4 | V89: =S89*I89 -> 3403851.4 | W89: Escaleras | X89: PTO 02 | Y89: =SUMIFS(Cert_App_Output!$G:$G,Cert_App_Output!$E:$E,$E89,Cert_App_Output!$K:$K,$X89) -> 0
A90: Albañilería MT | D90: Albañilería MO | E90: 9.02 | F90: OK | G90: Provisión y colocación de nariz metálica en escalones | H90: gl | I90: 1 | J90: 463902.77 | K90: 0 | L90: 1775796.2 | M90: 33595.48 | N90: =SUM(J90:M90) -> 2273294.4 | O90: =IF($N90=0,$S90,J90/$N90*$S90) -> 629268.86 | P90: =IF($N90=0,0,K90/$N90*$S90) -> 0 | Q90: =IF($N90=0,0,L90/$N90*$S90) -> 2408809.2 | R90: =IF($N90=0,0,M90/$N90*$S90) -> 45571.164 | S90: 3083649.2 | T90: =IFERROR(S90/N90,"") -> 1.3564671 | U90: =N90*I90 -> 2273294.4 | V90: =S90*I90 -> 3083649.2 | W90: Escaleras | X90: PTO 02 | Y90: =SUMIFS(Cert_App_Output!$G:$G,Cert_App_Output!$E:$E,$E90,Cert_App_Output!$K:$K,$X90) -> 0
A91: Albañilería MT | C91: Albañilería MO | D91: Albañilería MO | E91: 9.03 | F91: OK | G91: Zócalo de concreto en escalera - No incluye el ojo | H91: ml | I91: 114 | J91: 827.28 | K91: 4324.05 | L91: 4324.05 | M91: 137.03 | N91: =SUM(J91:M91) -> 9612.41 | O91: =IF($N91=0,$S91,J91/$N91*$S91) -> 1122.1781 | P91: =IF($N91=0,0,K91/$N91*$S91) -> 5865.4317 | Q91: =IF($N91=0,0,L91/$N91*$S91) -> 5865.4317 | R91: =IF($N91=0,0,M91/$N91*$S91) -> 185.87669 | S91: 13038.918 | T91: =IFERROR(S91/N91,"") -> 1.3564671 | U91: =N91*I91 -> 1095814.7 | V91: =S91*I91 -> 1486436.7 | W91: Escaleras | X91: PTO 02 | Y91: =SUMIFS(Cert_App_Output!$G:$G,Cert_App_Output!$E:$E,$E91,Cert_App_Output!$K:$K,$X91) -> 0
F92: - | G92: VENTILACIONES - PROVISION COTIZADA EN ITEM 26 | W92: Ventilaciones | X92: PTO 02
A93: Albañilería MT | D93: Albañilería MO | E93: 10.01 | F93: OK | G93: Colocación de ventilación de conducto de humos. Inc. toma de aire en PB | H93: gl | I93: 1 | J93: 250000 | K93: 0 | L93: 1663092.8 | M93: 28696.39 | N93: =SUM(J93:M93) -> 1941789.1 | O93: =IF($N93=0,$S93,J93/$N93*$S93) -> 339116.78 | P93: =IF($N93=0,0,K93/$N93*$S93) -> 0 | Q93: =IF($N93=0,0,L93/$N93*$S93) -> 2255930.7 | R93: =IF($N93=0,0,M93/$N93*$S93) -> 38925.71 | S93: 2633973.1 | T93: =IFERROR(S93/N93,"") -> 1.3564671 | U93: =N93*I93 -> 1941789.1 | V93: =S93*I93 -> 2633973.1 | W93: Ventilaciones | X93: PTO 02 | Y93: =SUMIFS(Cert_App_Output!$G:$G,Cert_App_Output!$E:$E,$E93,Cert_App_Output!$K:$K,$X93) -> 0
A94: Albañilería MT | D94: Albañilería MO | E94: 10.02 | F94: OK | G94: Colocación y montaje de conducto de ventilación en baños | H94: gl | I94: 1 | J94: 250000 | K94: 0 | L94: 1663092.8 | M94: 28696.39 | N94: =SUM(J94:M94) -> 1941789.1 | O94: =IF($N94=0,$S94,J94/$N94*$S94) -> 339116.78 | P94: =IF($N94=0,0,K94/$N94*$S94) -> 0 | Q94: =IF($N94=0,0,L94/$N94*$S94) -> 2255930.7 | R94: =IF($N94=0,0,M94/$N94*$S94) -> 38925.71 | S94: 2633973.1 | T94: =IFERROR(S94/N94,"") -> 1.3564671 | U94: =N94*I94 -> 1941789.1 | V94: =S94*I94 -> 2633973.1 | W94: Ventilaciones | X94: PTO 02 | Y94: =SUMIFS(Cert_App_Output!$G:$G,Cert_App_Output!$E:$E,$E94,Cert_App_Output!$K:$K,$X94) -> 0
A95: Albañilería MT | D95: Albañilería MO | E95: 10.03 | F95: OK | G95: Colocación sombreretes en chapa prepintada C25 - Provisión en item 26 | H95: u | I95: 7 | J95: 31772.28 | K95: 0 | L95: 95033.87 | M95: 1902.09 | N95: =SUM(J95:M95) -> 128708.24 | O95: =IF($N95=0,$S95,J95/$N95*$S95) -> 43098.053 | P95: =IF($N95=0,0,K95/$N95*$S95) -> 0 | Q95: =IF($N95=0,0,L95/$N95*$S95) -> 128910.32 | R95: =IF($N95=0,0,M95/$N95*$S95) -> 2580.1226 | S95: 174588.5 | T95: =IFERROR(S95/N95,"") -> 1.3564671 | U95: =N95*I95 -> 900957.68 | V95: =S95*I95 -> 1222119.5 | W95: Ventilaciones | X95: PTO 02 | Y95: =SUMIFS(Cert_App_Output!$G:$G,Cert_App_Output!$E:$E,$E95,Cert_App_Output!$K:$K,$X95) -> 0
F96: - | G96: PISOS - PROVISION A CARGO DEL COMITENTE | W96: Pisos | X96: PTO 02
A97: Revestimiento MT | D97: Revestimiento MO | E97: 11.01 | F97: OK | G97: Colocación de baldosas en palieres - Provisión a cargo del comitente | H97: m2 | I97: 101 | J97: 6932.27 | K97: 0 | L97: 12793.02 | M97: 245.43 | N97: =SUM(J97:M97) -> 19970.72 | O97: =IF($N97=0,$S97,J97/$N97*$S97) -> 9403.3964 | P97: =IF($N97=0,0,K97/$N97*$S97) -> 0 | Q97: =IF($N97=0,0,L97/$N97*$S97) -> 17353.311 | R97: =IF($N97=0,0,M97/$N97*$S97) -> 332.91773 | S97: 27089.625 | T97: =IFERROR(S97/N97,"") -> 1.3564671 | U97: =N97*I97 -> 2017042.7 | V97: =S97*I97 -> 2736052.1 | W97: Pisos | X97: PTO 02 | Y97: =SUMIFS(Cert_App_Output!$G:$G,Cert_App_Output!$E:$E,$E97,Cert_App_Output!$K:$K,$X97) -> 0
A98: Revestimiento MT | D98: Revestimiento MO | E98: 11.02 | F98: OK | G98: Colocación de porcelanato en UF - Provisión a cargo del comitente | H98: m2 | I98: 898 | J98: 6932.27 | K98: 0 | L98: 12793.02 | M98: 245.43 | N98: =SUM(J98:M98) -> 19970.72 | O98: =IF($N98=0,$S98,J98/$N98*$S98) -> 9403.3964 | P98: =IF($N98=0,0,K98/$N98*$S98) -> 0 | Q98: =IF($N98=0,0,L98/$N98*$S98) -> 17353.311 | R98: =IF($N98=0,0,M98/$N98*$S98) -> 332.91773 | S98: 27089.625 | T98: =IFERROR(S98/N98,"") -> 1.3564671 | U98: =N98*I98 -> 17933707 | V98: =S98*I98 -> 24326483 | W98: Pisos | X98: PTO 02 | Y98: =SUMIFS(Cert_App_Output!$G:$G,Cert_App_Output!$E:$E,$E98,Cert_App_Output!$K:$K,$X98) -> 0
A99: Revestimiento MT | D99: Revestimiento MO | E99: 11.03 | F99: OK | G99: Colocación de porcelanato en baños - Provisión a cargo del comitente | H99: m2 | I99: 88 | J99: 6932.27 | K99: 0 | L99: 16630.93 | M99: 319.06 | N99: =SUM(J99:M99) -> 23882.26 | O99: =IF($N99=0,$S99,J99/$N99*$S99) -> 9403.3964 | P99: =IF($N99=0,0,K99/$N99*$S99) -> 0 | Q99: =IF($N99=0,0,L99/$N99*$S99) -> 22559.31 | R99: =IF($N99=0,0,M99/$N99*$S99) -> 432.7944 | S99: 32395.501 | T99: =IFERROR(S99/N99,"") -> 1.3564671 | U99: =N99*I99 -> 2101638.9 | V99: =S99*I99 -> 2850804 | W99: Pisos | X99: PTO 02 | Y99: =SUMIFS(Cert_App_Output!$G:$G,Cert_App_Output!$E:$E,$E99,Cert_App_Output!$K:$K,$X99) -> 0
A100: Revestimiento MT | D100: Revestimiento MO | E100: 11.04 | F100: OK | G100: Colocación de porcelanato en exterior - Provisión a cargo del comitente | H100: m2 | I100: 63 | J100: 6932.27 | K100: 0 | L100: 12793.02 | M100: 245.43 | N100: =SUM(J100:M100) -> 19970.72 | O100: =IF($N100=0,$S100,J100/$N100*$S100) -> 9403.3964 | P100: =IF($N100=0,0,K100/$N100*$S100) -> 0 | Q100: =IF($N100=0,0,L100/$N100*$S100) -> 17353.311 | R100: =IF($N100=0,0,M100/$N100*$S100) -> 332.91773 | S100: 27089.625 | T100: =IFERROR(S100/N100,"") -> 1.3564671 | U100: =N100*I100 -> 1258155.4 | V100: =S100*I100 -> 1706646.4 | W100: Pisos | X100: PTO 02 | Y100: =SUMIFS(Cert_App_Output!$G:$G,Cert_App_Output!$E:$E,$E100,Cert_App_Output!$K:$K,$X100) -> 0
E101: 11.05 | F101: OK | G101: Provisión y colocación de sustrato - No cotiza | H101: m2 | I101: 25 | J101: 0 | K101: 0 | L101: 0 | M101: 0 | N101: =SUM(J101:M101) -> 0 | O101: =IF($N101=0,$S101,J101/$N101*$S101) -> 0 | P101: =IF($N101=0,0,K101/$N101*$S101) -> 0 | Q101: =IF($N101=0,0,L101/$N101*$S101) -> 0 | R101: =IF($N101=0,0,M101/$N101*$S101) -> 0 | S101: 0 | T101: =IFERROR(S101/N101,"") | U101: =N101*I101 -> 0 | V101: =S101*I101 -> 0 | W101: Pisos | X101: PTO 02 | Y101: =SUMIFS(Cert_App_Output!$G:$G,Cert_App_Output!$E:$E,$E101,Cert_App_Output!$K:$K,$X101) -> 0
...

Sheet 1_Composicion
A1: Partida | B1: Tipo | C1: Subtipo | D1: Cod_Insumo | E1: Descripción | F1: Unidad de medida | G1: Cant | H1: %Desp | I1: Precio | J1: Costo | K1: Clave | L1: Count | M1: Clave2 | N1: Rend. Part. | O1: Cant MO/ALB Unit | P1: Cant. Ej. Part. | Q1: Cant MO/ALB Total | R1: Cod_Item_Ppto | S1: Rubro
A2: APU-101 | B2: MO | C2: ALB | D2: MO-EESPE | E2: ESPECIALIZADO | F2: j | G2: 1 | H2: 0 | I2: 94177.138 | J2: 94177.138 | K2: APU-101|MO | L2: 1 | M2: APU-101|MO|1 | N2: 1 | O2: 1 | P2: - | Q2: 0 | R2: - | S2: =IFERROR(_xlfn.XLOOKUP(R2,'1_Presupuesto'!$E:$E,'1_Presupuesto'!$D:$D),"")
A3: APU-101 | B3: MO | C3: ALB | D3: MO-EAYUD | E3: AYUDANTE | F3: j | G3: 1 | H3: 0 | I3: 67240.499 | J3: 67240.499 | K3: APU-101|MO | L3: 2 | M3: APU-101|MO|2 | N3: 1 | O3: 1 | P3: - | Q3: 0 | R3: - | S3: =IFERROR(_xlfn.XLOOKUP(R3,'1_Presupuesto'!$E:$E,'1_Presupuesto'!$D:$D),"")
A4: BAN-106 | B4: MO | C4: ALB | D4: MO-EESPE | E4: ESPECIALIZADO | F4: j | G4: 1 | H4: 0 | I4: 94177.138 | J4: 94177.138 | K4: BAN-106|MO | L4: 1 | M4: BAN-106|MO|1 | N4: 3.8 | O4: 0.26315789 | P4: - | Q4: 0 | R4: - | S4: =IFERROR(_xlfn.XLOOKUP(R4,'1_Presupuesto'!$E:$E,'1_Presupuesto'!$D:$D),"")
A5: BAN-106 | B5: MO | C5: ALB | D5: MO-EAYUD | E5: AYUDANTE | F5: j | G5: 1 | H5: 0 | I5: 67240.499 | J5: 67240.499 | K5: BAN-106|MO | L5: 2 | M5: BAN-106|MO|2 | N5: 3.8 | O5: 0.26315789 | P5: - | Q5: 0 | R5: - | S5: =IFERROR(_xlfn.XLOOKUP(R5,'1_Presupuesto'!$E:$E,'1_Presupuesto'!$D:$D),"")
A6: ALB-110 | B6: MO | C6: ALB | D6: MO-EESPE | E6: ESPECIALIZADO | F6: j | G6: 1 | H6: 0 | I6: 94177.138 | J6: 94177.138 | K6: ALB-110|MO | L6: 1 | M6: ALB-110|MO|1 | N6: 36 | O6: 0.027777778 | P6: - | Q6: 0 | R6: - | S6: =IFERROR(_xlfn.XLOOKUP(R6,'1_Presupuesto'!$E:$E,'1_Presupuesto'!$D:$D),"")
A7: ALB-110 | B7: MO | C7: ALB | D7: MO-EAYUD | E7: AYUDANTE | F7: j | G7: 2 | H7: 0 | I7: 67240.499 | J7: 134481 | K7: ALB-110|MO | L7: 2 | M7: ALB-110|MO|2 | N7: 36 | O7: 0.055555556 | P7: - | Q7: 0 | R7: - | S7: =IFERROR(_xlfn.XLOOKUP(R7,'1_Presupuesto'!$E:$E,'1_Presupuesto'!$D:$D),"")
A8: ALB-110 | B8: MO | C8: ALB | D8: MO-EMEDI | E8: MEDIO OFICIAL | F8: j | G8: 5 | H8: 0 | I8: 72132.138 | J8: 360660.69 | K8: ALB-110|MO | L8: 3 | M8: ALB-110|MO|3 | N8: 36 | O8: 0.13888889 | P8: - | Q8: 0 | R8: - | S8: =IFERROR(_xlfn.XLOOKUP(R8,'1_Presupuesto'!$E:$E,'1_Presupuesto'!$D:$D),"")
A9: AIS-113 | B9: MAT | C9: OTR | D9: PIN-008 | E9: Pintura Asfaltica Asfasol x18ts | F9: 0 | G9: 0.0278 | H9: 0.1 | I9: 35525.95 | J9: 1086.3836 | K9: AIS-113|MAT | L9: 1 | M9: AIS-113|MAT|1 | N9: 80 | O9: 0 | P9: - | Q9: 0 | R9: - | S9: =IFERROR(_xlfn.XLOOKUP(R9,'1_Presupuesto'!$E:$E,'1_Presupuesto'!$D:$D),"")
A10: AIS-113 | B10: MAT | C10: OTR | D10: OTR-027 | E10: Rodillo de lana pelo largo N°22 - El Galgo | F10: u | G10: 0.01 | H10: 0.05 | I10: 6442.15 | J10: 67.642575 | K10: AIS-113|MAT | L10: 2 | M10: AIS-113|MAT|2 | N10: 80 | O10: 0 | P10: - | Q10: 0 | R10: - | S10: =IFERROR(_xlfn.XLOOKUP(R10,'1_Presupuesto'!$E:$E,'1_Presupuesto'!$D:$D),"")
A11: AIS-113 | B11: MAT | C11: OTR | D11: OTR-028 | E11: Pincel N° 20 - El Galgo | F11: u | G11: 0.02 | H11: 0.05 | I11: 4418.1818 | J11: 92.781818 | K11: AIS-113|MAT | L11: 3 | M11: AIS-113|MAT|3 | N11: 80 | O11: 0 | P11: - | Q11: 0 | R11: - | S11: =IFERROR(_xlfn.XLOOKUP(R11,'1_Presupuesto'!$E:$E,'1_Presupuesto'!$D:$D),"")
A12: AIS-113 | B12: MAT | C12: OTR | D12: OTR-022 | E12: Aguarras Hydrarras Hydra x 18lts | F12: 0 | G12: 0.002 | H12: 0.05 | I12: 58016.529 | J12: 121.83471 | K12: AIS-113|MAT | L12: 4 | M12: AIS-113|MAT|4 | N12: 80 | O12: 0 | P12: - | Q12: 0 | R12: - | S12: =IFERROR(_xlfn.XLOOKUP(R12,'1_Presupuesto'!$E:$E,'1_Presupuesto'!$D:$D),"")
A13: AIS-113 | B13: MAT | C13: OTR | D13: OTR-025 | E13: Trapo | F13: 0 | G13: 0.02 | H13: 0.05 | I13: 1182.6446 | J13: 24.835537 | K13: AIS-113|MAT | L13: 5 | M13: AIS-113|MAT|5 | N13: 80 | O13: 0 | P13: - | Q13: 0 | R13: - | S13: =IFERROR(_xlfn.XLOOKUP(R13,'1_Presupuesto'!$E:$E,'1_Presupuesto'!$D:$D),"")
A14: AIS-113 | B14: EQ | D14: EQ-SOLD00 | E14: Soldador Soplete A Gas Techista Membrana 10 Kg Boca 50mm | G14: 1 | H14: 0 | I14: 874.41131 | J14: 874.41131 | K14: AIS-113|EQ | L14: 1 | M14: AIS-113|EQ|1 | N14: 80 | O14: 0 | P14: - | Q14: 0 | R14: - | S14: =IFERROR(_xlfn.XLOOKUP(R14,'1_Presupuesto'!$E:$E,'1_Presupuesto'!$D:$D),"")
A15: AIS-113 | B15: MO | C15: ALB | D15: MO-EAYUD | E15: AYUDANTE | F15: j | G15: 1 | H15: 0 | I15: 67240.499 | J15: 67240.499 | K15: AIS-113|MO | L15: 1 | M15: AIS-113|MO|1 | N15: 80 | O15: 0.0125 | P15: - | Q15: 0 | R15: - | S15: =IFERROR(_xlfn.XLOOKUP(R15,'1_Presupuesto'!$E:$E,'1_Presupuesto'!$D:$D),"")
A16: AIS-113 | B16: MO | C16: ALB | D16: MO-EESPE | E16: ESPECIALIZADO | F16: j | G16: 1 | H16: 0 | I16: 94177.138 | J16: 94177.138 | K16: AIS-113|MO | L16: 2 | M16: AIS-113|MO|2 | N16: 80 | O16: 0.0125 | P16: - | Q16: 0 | R16: - | S16: =IFERROR(_xlfn.XLOOKUP(R16,'1_Presupuesto'!$E:$E,'1_Presupuesto'!$D:$D),"")
A17: AIS-114 | B17: MAT | C17: OTR | D17: PIN-008 | E17: Pintura Asfaltica Asfasol x18ts | F17: 0 | G17: 0.015 | H17: 0.1 | I17: 35525.95 | J17: 586.17818 | K17: AIS-114|MAT | L17: 1 | M17: AIS-114|MAT|1 | N17: 60 | O17: 0 | P17: - | Q17: 0 | R17: - | S17: =IFERROR(_xlfn.XLOOKUP(R17,'1_Presupuesto'!$E:$E,'1_Presupuesto'!$D:$D),"")
A18: AIS-114 | B18: MAT | C18: OTR | D18: AIS-002 | E18: Membrana Geotextil Ormiflex 4mm - (35kg) x10m | F18: u | G18: 0.05 | H18: 0.1 | I18: 57227.91 | J18: 3147.535 | K18: AIS-114|MAT | L18: 2 | M18: AIS-114|MAT|2 | N18: 60 | O18: 0 | P18: - | Q18: 0 | R18: - | S18: =IFERROR(_xlfn.XLOOKUP(R18,'1_Presupuesto'!$E:$E,'1_Presupuesto'!$D:$D),"")
A19: AIS-114 | B19: EQ | D19: EQ-SOLD00 | E19: Soldador Soplete A Gas Techista Membrana 10 Kg Boca 50mm | G19: 1 | H19: 0 | I19: 874.41131 | J19: 874.41131 | K19: AIS-114|EQ | L19: 1 | M19: AIS-114|EQ|1 | N19: 60 | O19: 0 | P19: - | Q19: 0 | R19: - | S19: =IFERROR(_xlfn.XLOOKUP(R19,'1_Presupuesto'!$E:$E,'1_Presupuesto'!$D:$D),"")
A20: AIS-114 | B20: MO | C20: ALB | D20: MO-EAYUD | E20: AYUDANTE | F20: j | G20: 1 | H20: 0 | I20: 67240.499 | J20: 67240.499 | K20: AIS-114|MO | L20: 1 | M20: AIS-114|MO|1 | N20: 60 | O20: 0.016666667 | P20: - | Q20: 0 | R20: - | S20: =IFERROR(_xlfn.XLOOKUP(R20,'1_Presupuesto'!$E:$E,'1_Presupuesto'!$D:$D),"")
A21: AIS-114 | B21: MO | C21: ALB | D21: MO-EESPE | E21: ESPECIALIZADO | F21: j | G21: 1 | H21: 0 | I21: 94177.138 | J21: 94177.138 | K21: AIS-114|MO | L21: 2 | M21: AIS-114|MO|2 | N21: 60 | O21: 0.016666667 | P21: - | Q21: 0 | R21: - | S21: =IFERROR(_xlfn.XLOOKUP(R21,'1_Presupuesto'!$E:$E,'1_Presupuesto'!$D:$D),"")
A22: REV-115 | B22: MAT | C22: OTR | D22: AGR-001 | E22: ARENA LAVADA | F22: 0 | G22: 0.02 | H22: 0.03 | I22: 32620.38 | J22: 671.97983 | K22: REV-115|MAT | L22: 1 | M22: REV-115|MAT|1 | N22: 15 | O22: 0 | P22: - | Q22: 0 | R22: - | S22: =IFERROR(_xlfn.XLOOKUP(R22,'1_Presupuesto'!$E:$E,'1_Presupuesto'!$D:$D),"")
A23: REV-115 | B23: MAT | C23: OTR | D23: AGR-005 | E23: Cal Comun x 25kg | F23: 0 | G23: 0.06 | H23: 0.05 | I23: 3927.28 | J23: 247.41864 | K23: REV-115|MAT | L23: 2 | M23: REV-115|MAT|2 | N23: 15 | O23: 0 | P23: - | Q23: 0 | R23: - | S23: =IFERROR(_xlfn.XLOOKUP(R23,'1_Presupuesto'!$E:$E,'1_Presupuesto'!$D:$D),"")
A24: REV-115 | B24: MAT | C24: OTR | D24: AGR-004 | E24: Cemento Portland x 50kg | F24: 0 | G24: 0.26 | H24: 0.03 | I24: 7891.74 | J24: 2113.408 | K24: REV-115|MAT | L24: 3 | M24: REV-115|MAT|3 | N24: 15 | O24: 0 | P24: - | Q24: 0 | R24: - | S24: =IFERROR(_xlfn.XLOOKUP(R24,'1_Presupuesto'!$E:$E,'1_Presupuesto'!$D:$D),"")
A25: REV-115 | B25: MO | C25: ALB | D25: MO-EESPE | E25: ESPECIALIZADO | F25: j | G25: 1 | H25: 0 | I25: 94177.138 | J25: 94177.138 | K25: REV-115|MO | L25: 1 | M25: REV-115|MO|1 | N25: 15 | O25: 0.066666667 | P25: - | Q25: 0 | R25: - | S25: =IFERROR(_xlfn.XLOOKUP(R25,'1_Presupuesto'!$E:$E,'1_Presupuesto'!$D:$D),"")
A26: REV-115 | B26: MO | C26: ALB | D26: MO-EAYUD | E26: AYUDANTE | F26: j | G26: 1 | H26: 0 | I26: 67240.499 | J26: 67240.499 | K26: REV-115|MO | L26: 2 | M26: REV-115|MO|2 | N26: 15 | O26: 0.066666667 | P26: - | Q26: 0 | R26: - | S26: =IFERROR(_xlfn.XLOOKUP(R26,'1_Presupuesto'!$E:$E,'1_Presupuesto'!$D:$D),"")
A27: REV-115 | B27: MO | C27: ALB | D27: MO-EMEDI | E27: MEDIO OFICIAL | F27: j | G27: 0 | H27: 0 | I27: 72132.138 | J27: 0 | K27: REV-115|MO | L27: 3 | M27: REV-115|MO|3 | N27: 15 | O27: 0 | P27: - | Q27: 0 | R27: - | S27: =IFERROR(_xlfn.XLOOKUP(R27,'1_Presupuesto'!$E:$E,'1_Presupuesto'!$D:$D),"")
A28: REV-116 | B28: MAT | C28: OTR | D28: DUR-007 | E28: Perfil Perimetral x 3.05 | F28: u | G28: 0.495 | H28: 0.1 | I28: 3028.9421 | J28: 1649.259 | K28: REV-116|MAT | L28: 1 | M28: REV-116|MAT|1 | N28: 12 | O28: 0 | P28: - | Q28: 0 | R28: - | S28: =IFERROR(_xlfn.XLOOKUP(R28,'1_Presupuesto'!$E:$E,'1_Presupuesto'!$D:$D),"")
A29: REV-116 | B29: MAT | C29: OTR | D29: OTR-015 | E29: Larguero x 3.66 | F29: u | G29: 0.45 | H29: 0.1 | I29: 4774.9091 | J29: 2363.58 | K29: REV-116|MAT | L29: 2 | M29: REV-116|MAT|2 | N29: 12 | O29: 0 | P29: - | Q29: 0 | R29: - | S29: =IFERROR(_xlfn.XLOOKUP(R29,'1_Presupuesto'!$E:$E,'1_Presupuesto'!$D:$D),"")
A30: REV-116 | B30: MAT | C30: OTR | D30: OTR-016 | E30: Travesaño x 1.22 | F30: u | G30: 2.62 | H30: 0.1 | I30: 1547.438 | J30: 4459.7164 | K30: REV-116|MAT | L30: 3 | M30: REV-116|MAT|3 | N30: 12 | O30: 0 | P30: - | Q30: 0 | R30: - | S30: =IFERROR(_xlfn.XLOOKUP(R30,'1_Presupuesto'!$E:$E,'1_Presupuesto'!$D:$D),"")
A31: REV-116 | B31: MAT | C31: OTR | D31: OTR-017 | E31: Travesaño x 0.60 | F31: u | G31: 0 | H31: 0.1 | I31: 793.53719 | J31: 0 | K31: REV-116|MAT | L31: 4 | M31: REV-116|MAT|4 | N31: 12 | O31: 0 | P31: - | Q31: 0 | R31: - | S31: =IFERROR(_xlfn.XLOOKUP(R31,'1_Presupuesto'!$E:$E,'1_Presupuesto'!$D:$D),"")
A32: REV-116 | B32: MAT | C32: OTR | D32: OTR-010 | E32: Fijacion completa del 8 | F32: u | G32: 6 | H32: 0.1 | I32: 63.381983 | J32: 418.32109 | K32: REV-116|MAT | L32: 5 | M32: REV-116|MAT|5 | N32: 12 | O32: 0 | P32: - | Q32: 0 | R32: - | S32: =IFERROR(_xlfn.XLOOKUP(R32,'1_Presupuesto'!$E:$E,'1_Presupuesto'!$D:$D),"")
A33: REV-116 | B33: MAT | C33: OTR | D33: ACE-014 | E33: Alambre galvanizado N°14 x kg | F33: kg | G33: 0.06 | H33: 0.1 | I33: 2755.6116 | J33: 181.87036 | K33: REV-116|MAT | L33: 6 | M33: REV-116|MAT|6 | N33: 12 | O33: 0 | P33: - | Q33: 0 | R33: - | S33: =IFERROR(_xlfn.XLOOKUP(R33,'1_Presupuesto'!$E:$E,'1_Presupuesto'!$D:$D),"")
A34: REV-116 | B34: MAT | C34: OTR | D34: OTR-019 | E34: Placa Decovinyl Liso 120x60 | F34: u | G34: 1.3889 | H34: 0.1 | I34: 4751.7079 | J34: 7259.6118 | K34: REV-116|MAT | L34: 7 | M34: REV-116|MAT|7 | N34: 12 | O34: 0 | P34: - | Q34: 0 | R34: - | S34: =IFERROR(_xlfn.XLOOKUP(R34,'1_Presupuesto'!$E:$E,'1_Presupuesto'!$D:$D),"")
A35: REV-116 | B35: EQ | D35: EQ-ESCALE | E35: ESCALERA GLOSS ALUMINIO ARTICULADA 4 X 4 ESCALONES HASTA 150KG | G35: 1 | H35: 0 | I35: 152.38027 | J35: 152.38027 | K35: REV-116|EQ | L35: 1 | M35: REV-116|EQ|1 | N35: 12 | O35: 0 | P35: - | Q35: 0 | R35: - | S35: =IFERROR(_xlfn.XLOOKUP(R35,'1_Presupuesto'!$E:$E,'1_Presupuesto'!$D:$D),"")
A36: REV-116 | B36: EQ | D36: EQ-PTO024 | E36: EQUIPO DE CONSTRUCCION EN SECO | G36: 1 | H36: 0 | I36: 2570.7599 | J36: 2570.7599 | K36: REV-116|EQ | L36: 2 | M36: REV-116|EQ|2 | N36: 12 | O36: 0 | P36: - | Q36: 0 | R36: - | S36: =IFERROR(_xlfn.XLOOKUP(R36,'1_Presupuesto'!$E:$E,'1_Presupuesto'!$D:$D),"")
A37: REV-116 | B37: MO | C37: ALB | D37: MO-EESPE | E37: ESPECIALIZADO | F37: j | G37: 1 | H37: 0 | I37: 94177.138 | J37: 94177.138 | K37: REV-116|MO | L37: 1 | M37: REV-116|MO|1 | N37: 12 | O37: 0.083333333 | P37: - | Q37: 0 | R37: - | S37: =IFERROR(_xlfn.XLOOKUP(R37,'1_Presupuesto'!$E:$E,'1_Presupuesto'!$D:$D),"")
A38: REV-116 | B38: MO | C38: ALB | D38: MO-EMEDI | E38: MEDIO OFICIAL | F38: j | G38: 1 | H38: 0 | I38: 72132.138 | J38: 72132.138 | K38: REV-116|MO | L38: 2 | M38: REV-116|MO|2 | N38: 12 | O38: 0.083333333 | P38: - | Q38: 0 | R38: - | S38: =IFERROR(_xlfn.XLOOKUP(R38,'1_Presupuesto'!$E:$E,'1_Presupuesto'!$D:$D),"")
A39: YES-117 | B39: MAT | C39: OTR | D39: OTR-014 | E39: Buña Z x 2.60m | F39: u | G39: 0.39 | H39: 0.1 | I39: 2234.18 | J39: 958.46322 | K39: YES-117|MAT | L39: 1 | M39: YES-117|MAT|1 | N39: 15 | O39: 0 | P39: - | Q39: 0 | R39: - | S39: =IFERROR(_xlfn.XLOOKUP(R39,'1_Presupuesto'!$E:$E,'1_Presupuesto'!$D:$D),"")
A40: YES-117 | B40: MAT | C40: OTR | D40: OTR-008 | E40: Tornillo T2 - Aguja | F40: u | G40: 3 | H40: 0.05 | I40: 9.114692 | J40: 28.71128 | K40: YES-117|MAT | L40: 2 | M40: YES-117|MAT|2 | N40: 15 | O40: 0 | P40: - | Q40: 0 | R40: - | S40: =IFERROR(_xlfn.XLOOKUP(R40,'1_Presupuesto'!$E:$E,'1_Presupuesto'!$D:$D),"")
A41: CER-060 | B41: EQ | D41: EQ-ESCALE | E41: ESCALERA GLOSS ALUMINIO ARTICULADA 4 X 4 ESCALONES HASTA 150KG | G41: 1 | H41: 0 | I41: 152.38027 | J41: 152.38027 | K41: CER-060|EQ | L41: 1 | M41: CER-060|EQ|1 | N41: 9.5 | O41: 0 | P41: - | Q41: 0 | R41: - | S41: =IFERROR(_xlfn.XLOOKUP(R41,'1_Presupuesto'!$E:$E,'1_Presupuesto'!$D:$D),"")
A42: CER-060 | B42: EQ | D42: EQ-PTO024 | E42: EQUIPO DE CONSTRUCCION EN SECO | G42: 1 | H42: 0 | I42: 2570.7599 | J42: 2570.7599 | K42: CER-060|EQ | L42: 2 | M42: CER-060|EQ|2 | N42: 9.5 | O42: 0 | P42: - | Q42: 0 | R42: - | S42: =IFERROR(_xlfn.XLOOKUP(R42,'1_Presupuesto'!$E:$E,'1_Presupuesto'!$D:$D),"")
A43: YES-117 | B43: MO | C43: ALB | D43: MO-EESPE | E43: ESPECIALIZADO | F43: j | G43: 1 | H43: 0 | I43: 94177.138 | J43: 94177.138 | K43: YES-117|MO | L43: 1 | M43: YES-117|MO|1 | N43: 15 | O43: 0.066666667 | P43: - | Q43: 0 | R43: - | S43: =IFERROR(_xlfn.XLOOKUP(R43,'1_Presupuesto'!$E:$E,'1_Presupuesto'!$D:$D),"")
A44: YES-118 | B44: MAT | C44: OTR | D44: MAT-CONS | E44: CONSUMIBLES (varios) | F44: gl | G44: 129.82087 | H44: 0 | I44: 1 | J44: 129.82087 | K44: YES-118|MAT | L44: 1 | M44: YES-118|MAT|1 | N44: 11.5 | O44: 0 | P44: - | Q44: 0 | R44: - | S44: =IFERROR(_xlfn.XLOOKUP(R44,'1_Presupuesto'!$E:$E,'1_Presupuesto'!$D:$D),"")
A45: YES-118 | B45: MAT | C45: OTR | D45: ACE-001 | E45: Barra de Acero Aleteado - 6mm x 12m | F45: 0 | G45: 0.17 | H45: 0.1 | I45: 3620.13 | J45: 676.96431 | K45: YES-118|MAT | L45: 2 | M45: YES-118|MAT|2 | N45: 11.5 | O45: 0 | P45: - | Q45: 0 | R45: - | S45: =IFERROR(_xlfn.XLOOKUP(R45,'1_Presupuesto'!$E:$E,'1_Presupuesto'!$D:$D),"")
A46: YES-118 | B46: MAT | C46: OTR | D46: AGR-001 | E46: ARENA LAVADA | F46: 0 | G46: 0.012 | H46: 0.1 | I46: 32620.38 | J46: 430.58902 | K46: YES-118|MAT | L46: 3 | M46: YES-118|MAT|3 | N46: 11.5 | O46: 0 | P46: - | Q46: 0 | R46: - | S46: =IFERROR(_xlfn.XLOOKUP(R46,'1_Presupuesto'!$E:$E,'1_Presupuesto'!$D:$D),"")
A47: YES-118 | B47: MAT | C47: OTR | D47: YES-BLOQUE10 | E47: Bloque hormigón 10×19×39 | F47: u | G47: 12.5 | H47: 0.05 | I47: 808.61 | J47: 10613.006 | K47: YES-118|MAT | L47: 4 | M47: YES-118|MAT|4 | N47: 11.5 | O47: 0 | P47: - | Q47: 0 | R47: - | S47: =IFERROR(_xlfn.XLOOKUP(R47,'1_Presupuesto'!$E:$E,'1_Presupuesto'!$D:$D),"")
A48: YES-118 | B48: MAT | C48: OTR | D48: AGR-004 | E48: Cemento Portland x 50kg | F48: 0 | G48: 0.052 | H48: 0.1 | I48: 7891.74 | J48: 451.40753 | K48: YES-118|MAT | L48: 5 | M48: YES-118|MAT|5 | N48: 11.5 | O48: 0 | P48: - | Q48: 0 | R48: - | S48: =IFERROR(_xlfn.XLOOKUP(R48,'1_Presupuesto'!$E:$E,'1_Presupuesto'!$D:$D),"")
A49: YES-118 | B49: EQ | D49: EQ-EQALBA | E49: EQUIPO DE ALBAÑILERIA, carpetas, ladrillo | G49: 1 | H49: 0 | I49: 2485.871 | J49: 2485.871 | K49: YES-118|EQ | L49: 1 | M49: YES-118|EQ|1 | N49: 11.5 | O49: 0 | P49: - | Q49: 0 | R49: - | S49: =IFERROR(_xlfn.XLOOKUP(R49,'1_Presupuesto'!$E:$E,'1_Presupuesto'!$D:$D),"")
A50: YES-118 | B50: EQ | D50: EQ-ANDAM0 | E50: ANDAMIO TUBULAR DE UNO A TRES CUERPOS | G50: 0.5 | H50: 0 | I50: 620.81078 | J50: 310.40539 | K50: YES-118|EQ | L50: 2 | M50: YES-118|EQ|2 | N50: 11.5 | O50: 0 | P50: - | Q50: 0 | R50: - | S50: =IFERROR(_xlfn.XLOOKUP(R50,'1_Presupuesto'!$E:$E,'1_Presupuesto'!$D:$D),"")
A51: YES-118 | B51: EQ | D51: EQ-TROMPO | E51: Hormigonera De 150 Litros 1hp Con Rueda Maciza | G51: 1 | H51: 0 | I51: 1040.4314 | J51: 1040.4314 | K51: YES-118|EQ | L51: 3 | M51: YES-118|EQ|3 | N51: 11.5 | O51: 0 | P51: - | Q51: 0 | R51: - | S51: =IFERROR(_xlfn.XLOOKUP(R51,'1_Presupuesto'!$E:$E,'1_Presupuesto'!$D:$D),"")
A52: YES-118 | B52: MO | C52: ALB | D52: MO-EESPE | E52: ESPECIALIZADO | F52: j | G52: 1 | H52: 0 | I52: 94177.138 | J52: 94177.138 | K52: YES-118|MO | L52: 1 | M52: YES-118|MO|1 | N52: 11.5 | O52: 0.086956522 | P52: - | Q52: 0 | R52: - | S52: =IFERROR(_xlfn.XLOOKUP(R52,'1_Presupuesto'!$E:$E,'1_Presupuesto'!$D:$D),"")
A53: YES-118 | B53: MO | C53: ALB | D53: MO-EMEDI | E53: MEDIO OFICIAL | F53: j | G53: 0.75 | H53: 0 | I53: 72132.138 | J53: 54099.104 | K53: YES-118|MO | L53: 2 | M53: YES-118|MO|2 | N53: 11.5 | O53: 0.065217391 | P53: - | Q53: 0 | R53: - | S53: =IFERROR(_xlfn.XLOOKUP(R53,'1_Presupuesto'!$E:$E,'1_Presupuesto'!$D:$D),"")
A54: PIN-119 | B54: MAT | C54: OTR | D54: MAT-CONS | E54: CONSUMIBLES (varios) | F54: gl | G54: 186.03762 | H54: 0 | I54: 1 | J54: 186.03762 | K54: PIN-119|MAT | L54: 1 | M54: PIN-119|MAT|1 | N54: 11.5 | O54: 0 | P54: - | Q54: 0 | R54: - | S54: =IFERROR(_xlfn.XLOOKUP(R54,'1_Presupuesto'!$E:$E,'1_Presupuesto'!$D:$D),"")
A55: PIN-119 | B55: MAT | C55: OTR | D55: ACE-001 | E55: Barra de Acero Aleteado - 6mm x 12m | F55: 0 | G55: 0.17 | H55: 0.1 | I55: 3620.13 | J55: 676.96431 | K55: PIN-119|MAT | L55: 2 | M55: PIN-119|MAT|2 | N55: 11.5 | O55: 0 | P55: - | Q55: 0 | R55: - | S55: =IFERROR(_xlfn.XLOOKUP(R55,'1_Presupuesto'!$E:$E,'1_Presupuesto'!$D:$D),"")
A56: PIN-119 | B56: MAT | C56: OTR | D56: AGR-001 | E56: ARENA LAVADA | F56: 0 | G56: 0.0144 | H56: 0.1 | I56: 32620.38 | J56: 516.70682 | K56: PIN-119|MAT | L56: 3 | M56: PIN-119|MAT|3 | N56: 11.5 | O56: 0 | P56: - | Q56: 0 | R56: - | S56: =IFERROR(_xlfn.XLOOKUP(R56,'1_Presupuesto'!$E:$E,'1_Presupuesto'!$D:$D),"")
A57: PIN-119 | B57: MAT | C57: OTR | D57: YES-BLOQUE19 | E57: Bloque hormigón 19×19×39 | F57: u | G57: 12.5 | H57: 0.05 | I57: 1204.43 | J57: 15808.144 | K57: PIN-119|MAT | L57: 4 | M57: PIN-119|MAT|4 | N57: 11.5 | O57: 0 | P57: - | Q57: 0 | R57: - | S57: =IFERROR(_xlfn.XLOOKUP(R57,'1_Presupuesto'!$E:$E,'1_Presupuesto'!$D:$D),"")
A58: PIN-119 | B58: MAT | C58: OTR | D58: AGR-004 | E58: Cemento Portland x 50kg | F58: 0 | G58: 0.0624 | H58: 0.1 | I58: 7891.74 | J58: 541.68903 | K58: PIN-119|MAT | L58: 5 | M58: PIN-119|MAT|5 | N58: 11.5 | O58: 0 | P58: - | Q58: 0 | R58: - | S58: =IFERROR(_xlfn.XLOOKUP(R58,'1_Presupuesto'!$E:$E,'1_Presupuesto'!$D:$D),"")
A59: PIN-119 | B59: EQ | D59: EQ-EQALBA | E59: EQUIPO DE ALBAÑILERIA, carpetas, ladrillo | G59: 1 | H59: 0 | I59: 2485.871 | J59: 2485.871 | K59: PIN-119|EQ | L59: 1 | M59: PIN-119|EQ|1 | N59: 11.5 | O59: 0 | P59: - | Q59: 0 | R59: - | S59: =IFERROR(_xlfn.XLOOKUP(R59,'1_Presupuesto'!$E:$E,'1_Presupuesto'!$D:$D),"")
A60: PIN-119 | B60: EQ | D60: EQ-ANDAM0 | E60: ANDAMIO TUBULAR DE UNO A TRES CUERPOS | G60: 0.5 | H60: 0 | I60: 620.81078 | J60: 310.40539 | K60: PIN-119|EQ | L60: 2 | M60: PIN-119|EQ|2 | N60: 11.5 | O60: 0 | P60: - | Q60: 0 | R60: - | S60: =IFERROR(_xlfn.XLOOKUP(R60,'1_Presupuesto'!$E:$E,'1_Presupuesto'!$D:$D),"")
A61: PIN-119 | B61: EQ | D61: EQ-TROMPO | E61: Hormigonera De 150 Litros 1hp Con Rueda Maciza | G61: 1 | H61: 0 | I61: 1040.4314 | J61: 1040.4314 | K61: PIN-119|EQ | L61: 3 | M61: PIN-119|EQ|3 | N61: 11.5 | O61: 0 | P61: - | Q61: 0 | R61: - | S61: =IFERROR(_xlfn.XLOOKUP(R61,'1_Presupuesto'!$E:$E,'1_Presupuesto'!$D:$D),"")
A62: PIN-119 | B62: MO | C62: ALB | D62: MO-EESPE | E62: ESPECIALIZADO | F62: j | G62: 1 | H62: 0 | I62: 94177.138 | J62: 94177.138 | K62: PIN-119|MO | L62: 1 | M62: PIN-119|MO|1 | N62: 11.5 | O62: 0.086956522 | P62: - | Q62: 0 | R62: - | S62: =IFERROR(_xlfn.XLOOKUP(R62,'1_Presupuesto'!$E:$E,'1_Presupuesto'!$D:$D),"")
A63: PIN-119 | B63: MO | C63: ALB | D63: MO-EMEDI | E63: MEDIO OFICIAL | F63: j | G63: 0.75 | H63: 0 | I63: 72132.138 | J63: 54099.104 | K63: PIN-119|MO | L63: 2 | M63: PIN-119|MO|2 | N63: 11.5 | O63: 0.065217391 | P63: - | Q63: 0 | R63: - | S63: =IFERROR(_xlfn.XLOOKUP(R63,'1_Presupuesto'!$E:$E,'1_Presupuesto'!$D:$D),"")
A64: ELE-120 | B64: MAT | C64: OTR | D64: MAT-CONS | E64: CONSUMIBLES (varios) | F64: gl | G64: 3056.3166 | H64: 0 | I64: 1 | J64: 3056.3166 | K64: ELE-120|MAT | L64: 1 | M64: ELE-120|MAT|1 | N64: 3.25 | O64: 0 | P64: - | Q64: 0 | R64: - | S64: =IFERROR(_xlfn.XLOOKUP(R64,'1_Presupuesto'!$E:$E,'1_Presupuesto'!$D:$D),"")
A65: ELE-120 | B65: EQ | D65: EQ-EQUIP0 | E65: EQUIPO PARA INSTALACION ELECTRICA | G65: 1 | H65: 0 | I65: 5503.0404 | J65: 5503.0404 | K65: ELE-120|EQ | L65: 1 | M65: ELE-120|EQ|1 | N65: 3.25 | O65: 0 | P65: - | Q65: 0 | R65: - | S65: =IFERROR(_xlfn.XLOOKUP(R65,'1_Presupuesto'!$E:$E,'1_Presupuesto'!$D:$D),"")
A66: ELE-120 | B66: EQ | D66: EQ-ANDAM0 | E66: ANDAMIO TUBULAR DE UNO A TRES CUERPOS | G66: 0.5 | H66: 0 | I66: 620.81078 | J66: 310.40539 | K66: ELE-120|EQ | L66: 2 | M66: ELE-120|EQ|2 | N66: 3.25 | O66: 0 | P66: - | Q66: 0 | R66: - | S66: =IFERROR(_xlfn.XLOOKUP(R66,'1_Presupuesto'!$E:$E,'1_Presupuesto'!$D:$D),"")
A67: ELE-120 | B67: EQ | D67: EQ-ESCALE | E67: ESCALERA GLOSS ALUMINIO ARTICULADA 4 X 4 ESCALONES HASTA 150KG | G67: 0.5 | H67: 0 | I67: 152.38027 | J67: 76.190137 | K67: ELE-120|EQ | L67: 3 | M67: ELE-120|EQ|3 | N67: 3.25 | O67: 0 | P67: - | Q67: 0 | R67: - | S67: =IFERROR(_xlfn.XLOOKUP(R67,'1_Presupuesto'!$E:$E,'1_Presupuesto'!$D:$D),"")
A68: ELE-120 | B68: MO | C68: ALB | D68: MO-EESPE | E68: ESPECIALIZADO | F68: j | G68: 1 | H68: 0 | I68: 94177.138 | J68: 94177.138 | K68: ELE-120|MO | L68: 1 | M68: ELE-120|MO|1 | N68: 3.25 | O68: 0.30769231 | P68: - | Q68: 0 | R68: - | S68: =IFERROR(_xlfn.XLOOKUP(R68,'1_Presupuesto'!$E:$E,'1_Presupuesto'!$D:$D),"")
A69: ELE-120 | B69: MO | C69: ALB | D69: MO-EAYUD | E69: AYUDANTE | F69: j | G69: 1 | H69: 0 | I69: 67240.499 | J69: 67240.499 | K69: ELE-120|MO | L69: 2 | M69: ELE-120|MO|2 | N69: 3.25 | O69: 0.30769231 | P69: - | Q69: 0 | R69: - | S69: =IFERROR(_xlfn.XLOOKUP(R69,'1_Presupuesto'!$E:$E,'1_Presupuesto'!$D:$D),"")
A70: ELE-121 | B70: MAT | C70: OTR | D70: ELE-004 | E70: Caño rigido 3/4" | F70: u | G70: 5 | H70: 0.05 | I70: 504.29657 | J70: 2647.557 | K70: ELE-121|MAT | L70: 1 | M70: ELE-121|MAT|1 | N70: 3.25 | O70: 0 | P70: - | Q70: 0 | R70: - | S70: =IFERROR(_xlfn.XLOOKUP(R70,'1_Presupuesto'!$E:$E,'1_Presupuesto'!$D:$D),"")
A71: ELE-121 | B71: MAT | C71: OTR | D71: ACE-017 | E71: Conector hierro 3/4" | F71: u | G71: 4 | H71: 0.1 | I71: 250.319 | J71: 1101.4036 | K71: ELE-121|MAT | L71: 2 | M71: ELE-121|MAT|2 | N71: 3.25 | O71: 0 | P71: - | Q71: 0 | R71: - | S71: =IFERROR(_xlfn.XLOOKUP(R71,'1_Presupuesto'!$E:$E,'1_Presupuesto'!$D:$D),"")
A72: ELE-121 | B72: MAT | C72: OTR | D72: ELE-005 | E72: Cupla PVC 3/4" | F72: u | G72: 1.2 | H72: 0.1 | I72: 110.121 | J72: 145.35972 | K72: ELE-121|MAT | L72: 3 | M72: ELE-121|MAT|3 | N72: 3.25 | O72: 0 | P72: - | Q72: 0 | R72: - | S72: =IFERROR(_xlfn.XLOOKUP(R72,'1_Presupuesto'!$E:$E,'1_Presupuesto'!$D:$D),"")
A73: ELE-121 | B73: MAT | C73: OTR | D73: ELE-009 | E73: Cable unipolar 1 x 2,50 VA | F73: m | G73: 5 | H73: 0.1 | I73: 546.37688 | J73: 3005.0728 | K73: ELE-121|MAT | L73: 4 | M73: ELE-121|MAT|4 | N73: 3.25 | O73: 0 | P73: - | Q73: 0 | R73: - | S73: =IFERROR(_xlfn.XLOOKUP(R73,'1_Presupuesto'!$E:$E,'1_Presupuesto'!$D:$D),"")
A74: ELE-121 | B74: MAT | C74: OTR | D74: ELE-009 | E74: Cable unipolar 1 x 2,50 VA | F74: m | G74: 10 | H74: 0.1 | I74: 546.37688 | J74: 6010.1456 | K74: ELE-121|MAT | L74: 5 | M74: ELE-121|MAT|5 | N74: 3.25 | O74: 0 | P74: - | Q74: 0 | R74: - | S74: =IFERROR(_xlfn.XLOOKUP(R74,'1_Presupuesto'!$E:$E,'1_Presupuesto'!$D:$D),"")
A75: ELE-121 | B75: MAT | C75: OTR | D75: ELE-014 | E75: Caja rectangular chica | F75: u | G75: 1 | H75: 0.05 | I75: 217.14976 | J75: 228.00725 | K75: ELE-121|MAT | L75: 6 | M75: ELE-121|MAT|6 | N75: 3.25 | O75: 0 | P75: - | Q75: 0 | R75: - | S75: =IFERROR(_xlfn.XLOOKUP(R75,'1_Presupuesto'!$E:$E,'1_Presupuesto'!$D:$D),"")
A76: ELE-121 | B76: MAT | C76: OTR | D76: MAT-CONS | E76: CONSUMIBLES (varios) | F76: gl | G76: 2758.8847 | H76: 0 | I76: 1 | J76: 2758.8847 | K76: ELE-121|MAT | L76: 7 | M76: ELE-121|MAT|7 | N76: 3.25 | O76: 0 | P76: - | Q76: 0 | R76: - | S76: =IFERROR(_xlfn.XLOOKUP(R76,'1_Presupuesto'!$E:$E,'1_Presupuesto'!$D:$D),"")
A77: ELE-121 | B77: EQ | D77: EQ-EQUIP0 | E77: EQUIPO PARA INSTALACION ELECTRICA | G77: 1 | H77: 0 | I77: 5503.0404 | J77: 5503.0404 | K77: ELE-121|EQ | L77: 1 | M77: ELE-121|EQ|1 | N77: 3.25 | O77: 0 | P77: - | Q77: 0 | R77: - | S77: =IFERROR(_xlfn.XLOOKUP(R77,'1_Presupuesto'!$E:$E,'1_Presupuesto'!$D:$D),"")
A78: ELE-121 | B78: EQ | D78: EQ-ANDAM0 | E78: ANDAMIO TUBULAR DE UNO A TRES CUERPOS | G78: 0.5 | H78: 0 | I78: 620.81078 | J78: 310.40539 | K78: ELE-121|EQ | L78: 2 | M78: ELE-121|EQ|2 | N78: 3.25 | O78: 0 | P78: - | Q78: 0 | R78: - | S78: =IFERROR(_xlfn.XLOOKUP(R78,'1_Presupuesto'!$E:$E,'1_Presupuesto'!$D:$D),"")
A79: ELE-121 | B79: EQ | D79: EQ-ESCALE | E79: ESCALERA GLOSS ALUMINIO ARTICULADA 4 X 4 ESCALONES HASTA 150KG | G79: 0.5 | H79: 0 | I79: 152.38027 | J79: 76.190137 | K79: ELE-121|EQ | L79: 3 | M79: ELE-121|EQ|3 | N79: 3.25 | O79: 0 | P79: - | Q79: 0 | R79: - | S79: =IFERROR(_xlfn.XLOOKUP(R79,'1_Presupuesto'!$E:$E,'1_Presupuesto'!$D:$D),"")
A80: ELE-121 | B80: MO | C80: ALB | D80: MO-EESPE | E80: ESPECIALIZADO | F80: j | G80: 1 | H80: 0 | I80: 94177.138 | J80: 94177.138 | K80: ELE-121|MO | L80: 1 | M80: ELE-121|MO|1 | N80: 3.25 | O80: 0.30769231 | P80: - | Q80: 0 | R80: - | S80: =IFERROR(_xlfn.XLOOKUP(R80,'1_Presupuesto'!$E:$E,'1_Presupuesto'!$D:$D),"")
A81: ELE-121 | B81: MO | C81: ALB | D81: MO-EAYUD | E81: AYUDANTE | F81: j | G81: 1 | H81: 0 | I81: 67240.499 | J81: 67240.499 | K81: ELE-121|MO | L81: 2 | M81: ELE-121|MO|2 | N81: 3.25 | O81: 0.30769231 | P81: - | Q81: 0 | R81: - | S81: =IFERROR(_xlfn.XLOOKUP(R81,'1_Presupuesto'!$E:$E,'1_Presupuesto'!$D:$D),"")
A82: BAN-122 | B82: MAT | C82: OTR | D82: OTR-038 | E82: SMARTTRAY TRX3M BJA PERF 200-22 | F82: u | G82: 0.35 | H82: 0.05 | I82: 25108.056 | J82: 9227.2106 | K82: BAN-122|MAT | L82: 1 | M82: BAN-122|MAT|1 | N82: 12 | O82: 0 | P82: - | Q82: 0 | R82: - | S82: =IFERROR(_xlfn.XLOOKUP(R82,'1_Presupuesto'!$E:$E,'1_Presupuesto'!$D:$D),"")
A83: BAN-122 | B83: MAT | C83: OTR | D83: OTR-039 | E83: SMARTTRAY TAPA CIEGA P/BJA 200-22 | F83: u | G83: 0.35 | H83: 0.1 | I83: 16853.812 | J83: 6488.7176 | K83: BAN-122|MAT | L83: 2 | M83: BAN-122|MAT|2 | N83: 12 | O83: 0 | P83: - | Q83: 0 | R83: - | S83: =IFERROR(_xlfn.XLOOKUP(R83,'1_Presupuesto'!$E:$E,'1_Presupuesto'!$D:$D),"")
A84: BAN-122 | B84: MAT | C84: OTR | D84: BAN-MAT003 | E84: SMARTTRAY CUPLA UNION JBCC-M6-100 | F84: u | G84: 0.015 | H84: 0.1 | I84: 14030.018 | J84: 231.49529 | K84: BAN-122|MAT | L84: 3 | M84: BAN-122|MAT|3 | N84: 12 | O84: 0 | P84: - | Q84: 0 | R84: - | S84: =IFERROR(_xlfn.XLOOKUP(R84,'1_Presupuesto'!$E:$E,'1_Presupuesto'!$D:$D),"")
A85: BAN-122 | B85: MAT | C85: OTR | D85: BAN-MAT004 | E85: GRAMPA FIJACION CABLE | F85: u | G85: 0.35 | H85: 0.1 | I85: 2124.5318 | J85: 817.94474 | K85: BAN-122|MAT | L85: 4 | M85: BAN-122|MAT|4 | N85: 12 | O85: 0 | P85: - | Q85: 0 | R85: - | S85: =IFERROR(_xlfn.XLOOKUP(R85,'1_Presupuesto'!$E:$E,'1_Presupuesto'!$D:$D),"")
A86: BAN-122 | B86: MAT | C86: OTR | D86: OTR-040 | E86: ACOMETIDA PARA TABLERO | F86: u | G86: 0.03 | H86: 0.1 | I86: 6773.5985 | J86: 223.52875 | K86: BAN-122|MAT | L86: 5 | M86: BAN-122|MAT|5 | N86: 12 | O86: 0 | P86: - | Q86: 0 | R86: - | S86: =IFERROR(_xlfn.XLOOKUP(R86,'1_Presupuesto'!$E:$E,'1_Presupuesto'!$D:$D),"")
A87: BAN-122 | B87: MAT | C87: OTR | D87: OTR-041 | E87: EMBUDO | F87: u | G87: 0.03 | H87: 0.1 | I87: 6773.5985 | J87: 223.52875 | K87: BAN-122|MAT | L87: 6 | M87: BAN-122|MAT|6 | N87: 12 | O87: 0 | P87: - | Q87: 0 | R87: - | S87: =IFERROR(_xlfn.XLOOKUP(R87,'1_Presupuesto'!$E:$E,'1_Presupuesto'!$D:$D),"")
A88: BAN-122 | B88: MAT | C88: OTR | D88: BAN-MAT007 | E88: GRAMPA FIJACION 200-22 | F88: u | G88: 0.57 | H88: 0.1 | I88: 1979.0429 | J88: 1240.8599 | K88: BAN-122|MAT | L88: 7 | M88: BAN-122|MAT|7 | N88: 12 | O88: 0 | P88: - | Q88: 0 | R88: - | S88: =IFERROR(_xlfn.XLOOKUP(R88,'1_Presupuesto'!$E:$E,'1_Presupuesto'!$D:$D),"")
A89: BAN-122 | B89: MAT | C89: OTR | D89: OTR-044 | E89: VARILLA ROSCADA 1/4 | F89: u | G89: 0.3 | H89: 0.1 | I89: 1069.6694 | J89: 352.99091 | K89: BAN-122|MAT | L89: 8 | M89: BAN-122|MAT|8 | N89: 12 | O89: 0 | P89: - | Q89: 0 | R89: - | S89: =IFERROR(_xlfn.XLOOKUP(R89,'1_Presupuesto'!$E:$E,'1_Presupuesto'!$D:$D),"")
A90: BAN-122 | B90: MAT | C90: OTR | D90: OTR-045 | E90: TUERCA Y ARANDELA 1/4 | F90: u | G90: 1.2 | H90: 0.05 | I90: 33.3 | J90: 41.958 | K90: BAN-122|MAT | L90: 9 | M90: BAN-122|MAT|9 | N90: 12 | O90: 0 | P90: - | Q90: 0 | R90: - | S90: =IFERROR(_xlfn.XLOOKUP(R90,'1_Presupuesto'!$E:$E,'1_Presupuesto'!$D:$D),"")
A91: BAN-122 | B91: MO | C91: ALB | D91: MO-EESPE | E91: ESPECIALIZADO | F91: j | G91: 1 | H91: 0 | I91: 94177.138 | J91: 94177.138 | K91: BAN-122|MO | L91: 1 | M91: BAN-122|MO|1 | N91: 12 | O91: 0.083333333 | P91: - | Q91: 0 | R91: - | S91: =IFERROR(_xlfn.XLOOKUP(R91,'1_Presupuesto'!$E:$E,'1_Presupuesto'!$D:$D),"")
... A99: HHA-124 | B99: MO | C99: ALB | D99: MO-EMEDI | E99: MEDIO OFICIAL | F99: j | G99: 0.75 | H99: 0 | I99: 72132.138 | J99: 54099.104 | K99: HHA-124|MO | L99: 2 | M99: HHA-124|MO|2 | N99: 12 | O99: 0.0625 | P99: - | Q99: 0 | R99: - | S99: =IFERROR(_xlfn.XLOOKUP(R99,'1_Presupuesto'!$E:$E,'1_Presupuesto'!$D:$D),"")
A100: CER-134 | B100: MAT | C100: OTR | D100: AGR-001 | E100: ARENA LAVADA | F100: 0 | G100: 0.017 | H100: 0.1 | I100: 32620.38 | J100: 610.00111 | K100: CER-134|MAT | L100: 1 | M100: CER-134|MAT|1 | N100: 18 | O100: 0 | P100: - | Q100: 0 | R100: - | S100: =IFERROR(_xlfn.XLOOKUP(R100,'1_Presupuesto'!$E:$E,'1_Presupuesto'!$D:$D),"")
A101: CER-134 | B101: MAT | C101: OTR | D101: AGR-005 | E101: Cal Comun x 25kg | F101: 0 | G101: 0.144 | H101: 0.1 | I101: 3927.28 | J101: 622.08115 | K101: CER-134|MAT | L101: 2 | M101: CER-134|MAT|2 | N101: 18 | O101: 0 | P101: - | Q101: 0 | R101: - | S101: =IFERROR(_xlfn.XLOOKUP(R101,'1_Presupuesto'!$E:$E,'1_Presupuesto'!$D:$D),"")
A102: CER-134 | B102: MAT | C102: OTR | D102: AGR-004 | E102: Cemento Portland x 50kg | F102: 0 | G102: 0.037 | H102: 0.1 | I102: 7891.74 | J102: 321.19382 | K102: CER-134|MAT | L102: 3 | M102: CER-134|MAT|3 | N102: 18 | O102: 0 | P102: - | Q102: 0 | R102: - | S102: =IFERROR(_xlfn.XLOOKUP(R102,'1_Presupuesto'!$E:$E,'1_Presupuesto'!$D:$D),"")
A103: CER-134 | B103: EQ | D103: EQ-ANDAM0 | E103: ANDAMIO TUBULAR DE UNO A TRES CUERPOS | G103: 1 | H103: 0 | I103: 620.81078 | J103: 620.81078 | K103: CER-134|EQ | L103: 1 | M103: CER-134|EQ|1 | N103: 18 | O103: 0 | P103: - | Q103: 0 | R103: - | S103: =IFERROR(_xlfn.XLOOKUP(R103,'1_Presupuesto'!$E:$E,'1_Presupuesto'!$D:$D),"")
A104: CER-134 | B104: EQ | D104: EQ-EQALBA | E104: EQUIPO DE ALBAÑILERIA, carpetas, ladrillo | G104: 1 | H104: 0 | I104: 2485.871 | J104: 2485.871 | K104: CER-134|EQ | L104: 2 | M104: CER-134|EQ|2 | N104: 18 | O104: 0 | P104: - | Q104: 0 | R104: - | S104: =IFERROR(_xlfn.XLOOKUP(R104,'1_Presupuesto'!$E:$E,'1_Presupuesto'!$D:$D),"")
A105: CER-134 | B105: EQ | D105: EQ-TROMPO | E105: Hormigonera De 150 Litros 1hp Con Rueda Maciza | G105: 0 | H105: 0 | I105: 1040.4314 | J105: 0 | K105: CER-134|EQ | L105: 3 | M105: CER-134|EQ|3 | N105: 18 | O105: 0 | P105: - | Q105: 0 | R105: - | S105: =IFERROR(_xlfn.XLOOKUP(R105,'1_Presupuesto'!$E:$E,'1_Presupuesto'!$D:$D),"")
A106: CER-134 | B106: MO | C106: ALB | D106: MO-EESPE | E106: ESPECIALIZADO | F106: j | G106: 1 | H106: 0 | I106: 94177.138 | J106: 94177.138 | K106: CER-134|MO | L106: 1 | M106: CER-134|MO|1 | N106: 18 | O106: 0.055555556 | P106: - | Q106: 0 | R106: - | S106: =IFERROR(_xlfn.XLOOKUP(R106,'1_Presupuesto'!$E:$E,'1_Presupuesto'!$D:$D),"")
A107: CER-134 | B107: MO | C107: ALB | D107: MO-EAYUD | E107: AYUDANTE | F107: j | G107: 0.75 | H107: 0 | I107: 67240.499 | J107: 50430.374 | K107: CER-134|MO | L107: 2 | M107: CER-134|MO|2 | N107: 18 | O107: 0.041666667 | P107: - | Q107: 0 | R107: - | S107: =IFERROR(_xlfn.XLOOKUP(R107,'1_Presupuesto'!$E:$E,'1_Presupuesto'!$D:$D),"")
...

Sheet 1_GGBB
H2: 45846 | O2: 24
F3: MESES | G3: DÓLAR BNA | H3: DÓLAR MEP | M3: Descrip | N3: Mes | O3: Total Dias
B4: GASTOS GENERALES y BENEFICIO | F4: 19 | G4: 1280 | H4: 1276 | M4: Prelim | N4: 0.5 | O4: 12 | Q4: Syh permanente
M5: Micropilotes | N5: 2 | O5: 48 | Q5: 1
B6: Gastos Grales de obra en items | C6: Un | D6: Meses | E6: Cant | F6: Precio Unit | G6: Subtotal | H6: 3040000 | M6: Subsuelo y VF | N6: 1 | O6: 24
B7: Oficina en obra (6x3 c/AA) | C7: mes | D7: 19 | E7: 0 | F7: 0 | G7: 0 | M7: Losa sobre PB | N7: 1 | O7: 24
B8: Obrador 6x3 s/AA | C8: mes | D8: 19 | E8: 0 | F8: 0 | G8: 0 | M8: Losa sobre 1 | N8: 0.75 | O8: 18
B9: Pañol (6x3) | C9: mes | D9: 19 | E9: 0 | F9: 180000 | G9: 0 | M9: Losa sobre 2 | N9: 0.75 | O9: 18
B10: Baños | C10: mes | D10: 19 | E10: 2 | F10: 80000 | G10: 3040000 | M10: Losa sobre 3 | N10: 0.75 | O10: 18
B11: Gastos Grales de obra en items | H11: 39866835 | M11: Losa sobre 4 | N11: 0.75 | O11: 18 | P11: Inicio mamposteria | Q11: Meses H° | R11: Estacionamiento en contramano
B12: HyS permanente | C12: mes | D12: 1 | E12: 1 | J12: 1623254.5 | K12: 1623254.5 | M12: Losa sobre 5 | N12: 0.75 | O12: 18 | Q12: 7.5 | R12: 3
B13: HyS | C13: mes | D13: 19 | E13: 1 | J13: 300000 | K13: 5700000 | M13: Losa sobre 6 | N13: 0.75 | O13: 18
B14: Energía de obra | C14: mes | D14: 19 | E14: 0.5 | F14: 200000 | G14: 1900000 | M14: Losa sobre 7 | N14: 0.5 | O14: 12
B15: Agua de obra | C15: mes | D15: 19 | E15: 1 | F15: 300000 | G15: 5700000 | M15: Losa Techos | N15: 0.5 | O15: 12
B16: Internet | C16: mes | D16: 19 | E16: 1 | F16: 75000 | G16: 1425000 | M16: Mampostería | N16: 2 | O16: 48
B17: Alquiler cerco de obra chapa | C17: mes | D17: 19 | E17: 0 | F17: 10000 | G17: 0 | M17: Revoques, contrap y carp | N17: 2 | O17: 48
B18: Proyecto Ejecutivo | C18: mes | D18: 19 | E18: 0 | F18: 3246508.9 | G18: 0 | M18: Colocación | N18: 2 | O18: 48
B19: Proyecto (50%) | C19: mes | D19: 19 | E19: 0.5 | F19: 3246508.9 | G19: 30841835 | M19: Pintura | N19: 2 | O19: 48
B20: Gastos Directos | H20: 89942566 | M20: Terminaciones | N20: 1 | O20: 24
B21: Coordinacion de obra | C21: mes | D21: 19 | E21: 0.15 | F21: 5688802.4 | G21: 16213087 | N21: 19 | O21: 456
B22: Jefe de obra | C22: mes | D22: 19 | E22: 0.2 | F22: 4716669.4 | G22: 17923344
B23: Sobrestante | C23: mes | D23: 19 | E23: 1 | J23: 3246508.9 | K23: 61683669
B24: Administrativo en obra | C24: mes | D24: 19 | E24: 0 | F24: 3246508.9 | G24: 0
B25: Capataz | C25: mes | D25: 19 | E25: 0.5 | F25: 3874330.1 | G25: 36806136
B26: Logistica | C26: mes | D26: 19 | E26: 1 | F26: 500000 | G26: 9500000
B27: Vehiculo obra | C27: mes | D27: 19 | E27: 1 | F27: 500000 | G27: 9500000
B28: Mov y viaticos | C28: mes | D28: 19 | E28: 1 | J28: 500000 | K28: 9500000
B29: UOCRA | C29: mes | D29: 19 | E29: 1 | G29: 0
B30: Pañolero/Sereno | C30: mes | D30: 19 | E30: 1 | J30: 806885.99 | K30: 15330834
B31: Equipos | H31: 0
B32: Bobcat | C32: mes | F32: 130000 | G32: 0
B33: Camion limpieza | C33: mes | F33: 100000 | G33: 0
B34: Tijera electrica 12 | C34: mes | F34: 33600 | G34: 0
B35: JLG | C35: mes | F35: 89000 | G35: 0
B36: Grua 20ton | C36: mes | F36: 70000 | G36: 0
B37: Gastos Indirectos | H37: 94164835
B38: Admin (50%Compras - 50%RRHH) | C38: mes | D38: 19 | E38: 0.5 | F38: 3246508.9 | G38: 30841835
B39: Seguros | C39: gl | D39: 19 | E39: 1 | F39: 250000 | G39: 4750000
B40: IIBB (monto venta obra gris) | C40: gl | D40: 0.04 | E40: 0.7 | F40: 1550000000 | G40: 43400000
B41: Imp cheque | C41: gl | D41: 0.012 | E41: 0.7 | F41: 1782500000 | G41: 14973000
B42: Contrato | C42: gl | D42: 1 | E42: 1 | F42: 200000 | G42: 200000
G43: 2.2701424e+08 | H43: 2.2701424e+08 | K43: 93837758 | L43: 3.2085199e+08
B44: Monto puesto en Ayuda de gremio que no se eroga | K44: Imputados en pres | L44: Total GGBB
B45: Total de Gastos Generales | H45: 2.2701424e+08 | L45: 0.28250185
B47: Otro | G47: 2.8879873e+08 | H47: 226331.29
B48: Corralon | G48: 92831284 | H48: 72751.79
B49: Subcontratos | G49: 5.0875751e+08 | H49: 398712.78
B50: Mano de obra | G50: 2.1954745e+08 | H50: 172059.13
B51: Equipos | G51: 25816869 | H51: 20232.656
A53: A | G53: 1.1357518e+09 | H53: 890087.65
J54: 1.109935e+09
B55: GG | F55: 0.19988014 | G55: 2.2701424e+08 | H55: 177910.84 | J55: 33298049 | K55: 0.03
B56: Equipos | E56: 3 | F56: 0.0065869852 | G56: 7481180.5 | H56: 5862.9941 | J56: 7481180.5
B57: Imprevistos + Negociación | E57: 5 | F57: 0.05 | G57: 56787592 | H57: 44504.382
B58: Beneficio | E58: 9 | F58: 0.1 | G58: 1.1357518e+08 | H58: 89008.765
A59: B | F59: 0.35646712 | G59: 4.0485819e+08 | H59: 317286.98
A61: K | F61: 1.3564671 | G61: 1.54061e+09
A63: A+B | G63: 1.54061e+09 | H63: 1207374.6

Sheet 2_Movimientos
A1: Cuenta | B1: Desc Cuenta | C1: Fecha Asiento | D1: Nº Asiento | E1: Observaciones | F1: Cliente/Proveedor | G1: Cód Comprobante | H1: Nº Comprobante | I1: Debe | J1: Haber | K1: Unidad | L1: Desc Unidad | M1: Centro de Costo | N1: Desc Centro Costo | O1: Saldo Inicial | P1: Observaciones original | Q1: mov_id | R1: mov_tipo
A2: 53001 | B2: Preliminares | C2: 46042 | D2: 972 | E2: PRELIMINARES - Comercial cmp S | F2: Comercial cmp S.A | G2: FCA3 | H2: 21100144871 | I2: 885229.7 | J2: 0 | K2: DESA | L2: Desarrollos | M2: CHIVILCOY | N2: CHIVILCOY 2171 | O2: 0 | P2: PRELIMINARES - Comercial cmp S | Q2: =IFERROR(TRIM(LEFT($E2,FIND(" | ",$E2)-1)),"") | R2: =IFERROR(TRIM(UPPER(MID($E2,FIND(" | ",$E2)+3,IFERROR(FIND(" | ",$E2,FIND(" | ",$E2)+3),LEN($E2)+1)-FIND(" | ",$E2)-3))),"")
A3: 53023 | B3: Varios Ferreteria | C3: 46044 | D3: 393 | E3: Varios Ferreteria | G3: OPXX | H3: 8417 | I3: 2000 | J3: 0 | K3: DESA | L3: Desarrollos | M3: CHIVILCOY | N3: CHIVILCOY 2171 | O3: 0 | P3: Varios Ferreteria | Q3: =IFERROR(TRIM(LEFT($E3,FIND(" | ",$E3)-1)),"") | R3: =IFERROR(TRIM(UPPER(MID($E3,FIND(" | ",$E3)+3,IFERROR(FIND(" | ",$E3,FIND(" | ",$E3)+3),LEN($E3)+1)-FIND(" | ",$E3)-3))),"")
A4: 53001 | B4: Preliminares | C4: 46045 | D4: 986 | E4: PRELIMINARES - CUTULI HNOS S.A | F4: CUTULI HNOS S.A. | G4: FCA3 | H4: 1500090204 | I4: 45752.4 | J4: 0 | K4: DESA | L4: Desarrollos | M4: CHIVILCOY | N4: CHIVILCOY 2171 | O4: 0 | P4: PRELIMINARES - CUTULI HNOS S.A | Q4: =IFERROR(TRIM(LEFT($E4,FIND(" | ",$E4)-1)),"") | R4: =IFERROR(TRIM(UPPER(MID($E4,FIND(" | ",$E4)+3,IFERROR(FIND(" | ",$E4,FIND(" | ",$E4)+3),LEN($E4)+1)-FIND(" | ",$E4)-3))),"")
A5: 53023 | B5: Varios Ferreteria | C5: 46045 | D5: 398 | E5: Varios Ferreteria | G5: OPXX | H5: 8422 | I5: 6200 | J5: 0 | K5: DESA | L5: Desarrollos | M5: CHIVILCOY | N5: CHIVILCOY 2171 | O5: 0 | P5: Varios Ferreteria | Q5: =IFERROR(TRIM(LEFT($E5,FIND(" | ",$E5)-1)),"") | R5: =IFERROR(TRIM(UPPER(MID($E5,FIND(" | ",$E5)+3,IFERROR(FIND(" | ",$E5,FIND(" | ",$E5)+3),LEN($E5)+1)-FIND(" | ",$E5)-3))),"")
A6: 52204 | B6: H. Seguridad e Higiene | C6: 46055 | D6: 1381 | E6: Honorarios Seguridad e Higiene | F6: Petrini David Osvaldo | G6: FCA3 | H6: 300001414 | I6: 517195 | J6: 0 | K6: DESA | L6: Desarrollos | M6: CHIVILCOY | N6: CHIVILCOY 2171 | O6: 0 | P6: Honorarios Seguridad e Higiene | Q6: =IFERROR(TRIM(LEFT($E6,FIND(" | ",$E6)-1)),"") | R6: =IFERROR(TRIM(UPPER(MID($E6,FIND(" | ",$E6)+3,IFERROR(FIND(" | ",$E6,FIND(" | ",$E6)+3),LEN($E6)+1)-FIND(" | ",$E6)-3))),"")
A7: 53001 | B7: Preliminares | C7: 46057 | D7: 2341 | E7: Cerco de obra - Pinturerias Pr | F7: Pinturerias Prestigio S.A | G7: FCA3 | H7: 502000000000 | I7: 119384.31 | J7: 0 | K7: DESA | L7: Desarrollos | M7: CHIVILCOY | N7: CHIVILCOY 2171 | O7: 0 | P7: Cerco de obra - Pinturerias Pr | Q7: =IFERROR(TRIM(LEFT($E7,FIND(" | ",$E7)-1)),"") | R7: =IFERROR(TRIM(UPPER(MID($E7,FIND(" | ",$E7)+3,IFERROR(FIND(" | ",$E7,FIND(" | ",$E7)+3),LEN($E7)+1)-FIND(" | ",$E7)-3))),"")
A8: 53008 | B8: Albañilería MT | C8: 46057 | D8: 1242 | E8: ALBAÑILERIA MT - CUTULI HNOS S | F8: CUTULI HNOS S.A. | G8: FCA3 | H8: 1500090674 | I8: 48248.1 | J8: 0 | K8: DESA | L8: Desarrollos | M8: CHIVILCOY | N8: CHIVILCOY 2171 | O8: 0 | P8: ALBAÑILERIA MT - CUTULI HNOS S | Q8: =IFERROR(TRIM(LEFT($E8,FIND(" | ",$E8)-1)),"") | R8: =IFERROR(TRIM(UPPER(MID($E8,FIND(" | ",$E8)+3,IFERROR(FIND(" | ",$E8,FIND(" | ",$E8)+3),LEN($E8)+1)-FIND(" | ",$E8)-3))),"")
A9: 53022 | B9: Gastos Generales | C9: 46077 | D9: 1388 | E9: Baño portatil - ECOBAT SRL | F9: ECOBAT SRL | G9: FCA3 | H9: 300025194 | I9: 247000 | J9: 0 | K9: DESA | L9: Desarrollos | M9: CHIVILCOY | N9: CHIVILCOY 2171 | O9: 0 | P9: Baño portatil - ECOBAT SRL | Q9: =IFERROR(TRIM(LEFT($E9,FIND(" | ",$E9)-1)),"") | R9: =IFERROR(TRIM(UPPER(MID($E9,FIND(" | ",$E9)+3,IFERROR(FIND(" | ",$E9,FIND(" | ",$E9)+3),LEN($E9)+1)-FIND(" | ",$E9)-3))),"")
A10: 53001 | B10: Preliminares | C10: 46080 | D10: 1406 | E10: PRELIMINARES - Pinturerias Pre | F10: Pinturerias Prestigio S.A | G10: FCA3 | H10: 126000000000 | I10: 89183.46 | J10: 0 | K10: DESA | L10: Desarrollos | M10: CHIVILCOY | N10: CHIVILCOY 2171 | O10: 0 | P10: PRELIMINARES - Pinturerias Pre | Q10: =IFERROR(TRIM(LEFT($E10,FIND(" | ",$E10)-1)),"") | R10: =IFERROR(TRIM(UPPER(MID($E10,FIND(" | ",$E10)+3,IFERROR(FIND(" | ",$E10,FIND(" | ",$E10)+3),LEN($E10)+1)-FIND(" | ",$E10)-3))),"")
A11: 53001 | B11: Preliminares | C11: 46080 | D11: 614 | E11: CH-SC-001 | BASE | Claudio Balaclav - Gestor Elec | G11: OPXX | H11: 8632 | I11: 520000 | J11: 0 | K11: DESA | L11: Desarrollos | M11: CHIVILCOY | N11: CHIVILCOY 2171 | O11: 0 | P11: Claudio Balaclav - Gestor Elec | Q11: =IFERROR(TRIM(LEFT($E11,FIND(" | ",$E11)-1)),"") -> CH-SC-001 | R11: =IFERROR(TRIM(UPPER(MID($E11,FIND(" | ",$E11)+3,IFERROR(FIND(" | ",$E11,FIND(" | ",$E11)+3),LEN($E11)+1)-FIND(" | ",$E11)-3))),"") -> BASE
A12: 53001 | B12: Preliminares | C12: 46080 | D12: 1398 | E12: PRELIMINARES - FABELEC | F12: FABELEC | G12: FCA3 | H12: 500005390 | I12: 291421.17 | J12: 0 | K12: DESA | L12: Desarrollos | M12: CHIVILCOY | N12: CHIVILCOY 2171 | O12: 0 | P12: PRELIMINARES - FABELEC | Q12: =IFERROR(TRIM(LEFT($E12,FIND(" | ",$E12)-1)),"") | R12: =IFERROR(TRIM(UPPER(MID($E12,FIND(" | ",$E12)+3,IFERROR(FIND(" | ",$E12,FIND(" | ",$E12)+3),LEN($E12)+1)-FIND(" | ",$E12)-3))),"")
A13: 53001 | B13: Preliminares | C13: 46083 | D13: 1405 | E13: Constancia Inspeccion Cartel - | F13: DESSINS CARTELERIA S.R.L | G13: FCA3 | H13: 200008045 | I13: 8181.82 | J13: 0 | K13: DESA | L13: Desarrollos | M13: CHIVILCOY | N13: CHIVILCOY 2171 | O13: 0 | P13: Constancia Inspeccion Cartel - | Q13: =IFERROR(TRIM(LEFT($E13,FIND(" | ",$E13)-1)),"") | R13: =IFERROR(TRIM(UPPER(MID($E13,FIND(" | ",$E13)+3,IFERROR(FIND(" | ",$E13,FIND(" | ",$E13)+3),LEN($E13)+1)-FIND(" | ",$E13)-3))),"")
A14: 52204 | B14: H. Seguridad e Higiene | C14: 46084 | D14: 2072 | E14: Honorarios Seguridad e Higiene | F14: Petrini David Osvaldo | G14: FCA3 | H14: 300001433 | I14: 517195 | J14: 0 | K14: DESA | L14: Desarrollos | M14: CHIVILCOY | N14: CHIVILCOY 2171 | O14: 0 | P14: Honorarios Seguridad e Higiene | Q14: =IFERROR(TRIM(LEFT($E14,FIND(" | ",$E14)-1)),"") | R14: =IFERROR(TRIM(UPPER(MID($E14,FIND(" | ",$E14)+3,IFERROR(FIND(" | ",$E14,FIND(" | ",$E14)+3),LEN($E14)+1)-FIND(" | ",$E14)-3))),"")
A15: 53023 | B15: Varios Ferreteria | C15: 46084 | D15: 870 | E15: Varios Ferreteria | G15: OPXX | H15: 8902 | I15: 18500 | J15: 0 | K15: DESA | L15: Desarrollos | M15: CHIVILCOY | N15: CHIVILCOY 2171 | O15: 0 | P15: Varios Ferreteria | Q15: =IFERROR(TRIM(LEFT($E15,FIND(" | ",$E15)-1)),"") | R15: =IFERROR(TRIM(UPPER(MID($E15,FIND(" | ",$E15)+3,IFERROR(FIND(" | ",$E15,FIND(" | ",$E15)+3),LEN($E15)+1)-FIND(" | ",$E15)-3))),"")
A16: 53001 | B16: Preliminares | C16: 46085 | D16: 1499 | E16: PRELIMINARES - CUTULI HNOS S.A | F16: CUTULI HNOS S.A. | G16: FCA3 | H16: 1500091777 | I16: 111030.25 | J16: 0 | K16: DESA | L16: Desarrollos | M16: CHIVILCOY | N16: CHIVILCOY 2171 | O16: 0 | P16: PRELIMINARES - CUTULI HNOS S.A | Q16: =IFERROR(TRIM(LEFT($E16,FIND(" | ",$E16)-1)),"") | R16: =IFERROR(TRIM(UPPER(MID($E16,FIND(" | ",$E16)+3,IFERROR(FIND(" | ",$E16,FIND(" | ",$E16)+3),LEN($E16)+1)-FIND(" | ",$E16)-3))),"")
A17: 5108 | B17: Gastos en personal | C17: 46086 | D17: 875 | E17: Gastos en personal | G17: OPXX | H17: 8907 | I17: 8000 | J17: 0 | K17: DESA | L17: Desarrollos | M17: CHIVILCOY | N17: CHIVILCOY 2171 | O17: 0 | P17: Gastos en personal | Q17: =IFERROR(TRIM(LEFT($E17,FIND(" | ",$E17)-1)),"") | R17: =IFERROR(TRIM(UPPER(MID($E17,FIND(" | ",$E17)+3,IFERROR(FIND(" | ",$E17,FIND(" | ",$E17)+3),LEN($E17)+1)-FIND(" | ",$E17)-3))),"")
A18: 53001 | B18: Preliminares | C18: 46086 | D18: 649 | E18: CH-SC-002 | BASE | Alejandro Ardiles - Agrimensor | G18: OPXX | H18: 8667 | I18: 380000 | J18: 0 | K18: DESA | L18: Desarrollos | M18: CHIVILCOY | N18: CHIVILCOY 2171 | O18: 0 | P18: Alejandro Ardiles - Agrimensor | Q18: =IFERROR(TRIM(LEFT($E18,FIND(" | ",$E18)-1)),"") -> CH-SC-002 | R18: =IFERROR(TRIM(UPPER(MID($E18,FIND(" | ",$E18)+3,IFERROR(FIND(" | ",$E18,FIND(" | ",$E18)+3),LEN($E18)+1)-FIND(" | ",$E18)-3))),"") -> BASE
A19: 53023 | B19: Varios Ferreteria | C19: 46087 | D19: 871 | E19: Varios Ferreteria | G19: OPXX | H19: 8903 | I19: 21000 | J19: 0 | K19: DESA | L19: Desarrollos | M19: CHIVILCOY | N19: CHIVILCOY 2171 | O19: 0 | P19: Varios Ferreteria | Q19: =IFERROR(TRIM(LEFT($E19,FIND(" | ",$E19)-1)),"") | R19: =IFERROR(TRIM(UPPER(MID($E19,FIND(" | ",$E19)+3,IFERROR(FIND(" | ",$E19,FIND(" | ",$E19)+3),LEN($E19)+1)-FIND(" | ",$E19)-3))),"")
A20: 53001 | B20: Preliminares | C20: 46090 | D20: 1637 | E20: PRELIMINARES - Casa Castelao S | F20: Casa Castelao S.A. | G20: FCA3 | H20: 300011389 | I20: 676125.38 | J20: 0 | K20: DESA | L20: Desarrollos | M20: CHIVILCOY | N20: CHIVILCOY 2171 | O20: 0 | P20: PRELIMINARES - Casa Castelao S | Q20: =IFERROR(TRIM(LEFT($E20,FIND(" | ",$E20)-1)),"") | R20: =IFERROR(TRIM(UPPER(MID($E20,FIND(" | ",$E20)+3,IFERROR(FIND(" | ",$E20,FIND(" | ",$E20)+3),LEN($E20)+1)-FIND(" | ",$E20)-3))),"")
A21: 53001 | B21: Preliminares | C21: 46090 | D21: 1637 | E21: PRELIMINARES - Casa Castelao S | F21: Casa Castelao S.A. | G21: FCA3 | H21: 300011389 | I21: 15605.79 | J21: 0 | K21: DESA | L21: Desarrollos | M21: CHIVILCOY | N21: CHIVILCOY 2171 | O21: 0 | P21: PRELIMINARES - Casa Castelao S | Q21: =IFERROR(TRIM(LEFT($E21,FIND(" | ",$E21)-1)),"") | R21: =IFERROR(TRIM(UPPER(MID($E21,FIND(" | ",$E21)+3,IFERROR(FIND(" | ",$E21,FIND(" | ",$E21)+3),LEN($E21)+1)-FIND(" | ",$E21)-3))),"")
A22: 53001 | B22: Preliminares | C22: 46090 | D22: 1638 | E22: PRELIMINARES - Casa Castelao S | F22: Casa Castelao S.A. | G22: FCA3 | H22: 300011390 | I22: 32617.84 | J22: 0 | K22: DESA | L22: Desarrollos | M22: CHIVILCOY | N22: CHIVILCOY 2171 | O22: 0 | P22: PRELIMINARES - Casa Castelao S | Q22: =IFERROR(TRIM(LEFT($E22,FIND(" | ",$E22)-1)),"") | R22: =IFERROR(TRIM(UPPER(MID($E22,FIND(" | ",$E22)+3,IFERROR(FIND(" | ",$E22,FIND(" | ",$E22)+3),LEN($E22)+1)-FIND(" | ",$E22)-3))),"")
A23: 53001 | B23: Preliminares | C23: 46091 | D23: 1640 | E23: PRELIMINARES - Comercial cmp S | F23: Comercial cmp S.A | G23: FCA3 | H23: 21100146499 | I23: 115372.69 | J23: 0 | K23: DESA | L23: Desarrollos | M23: CHIVILCOY | N23: CHIVILCOY 2171 | O23: 0 | P23: PRELIMINARES - Comercial cmp S | Q23: =IFERROR(TRIM(LEFT($E23,FIND(" | ",$E23)-1)),"") | R23: =IFERROR(TRIM(UPPER(MID($E23,FIND(" | ",$E23)+3,IFERROR(FIND(" | ",$E23,FIND(" | ",$E23)+3),LEN($E23)+1)-FIND(" | ",$E23)-3))),"")
A24: 53004 | B24: Hormigón MT | C24: 46091 | D24: 1590 | E24: CH-SC-003 | BASE | HORMIGON MT - FEIS DEL OESTE C | F24: FEIS DEL OESTE CONSTRUCTORA SA | G24: FCA3 | H24: 100001478 | I24: 16781280 | J24: 0 | K24: DESA | L24: Desarrollos | M24: CHIVILCOY | N24: CHIVILCOY 2171 | O24: 0 | P24: HORMIGON MT - FEIS DEL OESTE C | Q24: =IFERROR(TRIM(LEFT($E24,FIND(" | ",$E24)-1)),"") -> CH-SC-003 | R24: =IFERROR(TRIM(UPPER(MID($E24,FIND(" | ",$E24)+3,IFERROR(FIND(" | ",$E24,FIND(" | ",$E24)+3),LEN($E24)+1)-FIND(" | ",$E24)-3))),"") -> BASE
A25: 53017 | B25: Sanitaria MT | C25: 46091 | D25: 1641 | E25: SANITARIA MT - Sanitriun S.R.L | F25: Sanitriun S.R.L | G25: FCA3 | H25: 400033694 | I25: 434539.28 | J25: 0 | K25: DESA | L25: Desarrollos | M25: CHIVILCOY | N25: CHIVILCOY 2171 | O25: 0 | P25: SANITARIA MT - Sanitriun S.R.L | Q25: =IFERROR(TRIM(LEFT($E25,FIND(" | ",$E25)-1)),"") | R25: =IFERROR(TRIM(UPPER(MID($E25,FIND(" | ",$E25)+3,IFERROR(FIND(" | ",$E25,FIND(" | ",$E25)+3),LEN($E25)+1)-FIND(" | ",$E25)-3))),"")
A26: 53001 | B26: Preliminares | C26: 46092 | D26: 1644 | E26: Cartel obra - DESSINS CARTELER | F26: DESSINS CARTELERIA S.R.L | G26: FCA3 | H26: 200008143 | I26: 23223.14 | J26: 0 | K26: DESA | L26: Desarrollos | M26: CHIVILCOY | N26: CHIVILCOY 2171 | O26: 0 | P26: Cartel obra - DESSINS CARTELER | Q26: =IFERROR(TRIM(LEFT($E26,FIND(" | ",$E26)-1)),"") | R26: =IFERROR(TRIM(UPPER(MID($E26,FIND(" | ",$E26)+3,IFERROR(FIND(" | ",$E26,FIND(" | ",$E26)+3),LEN($E26)+1)-FIND(" | ",$E26)-3))),"")
A27: 53001 | B27: Preliminares | C27: 46092 | D27: 1650 | E27: PRELIMINARES - CUTULI HNOS S.A | F27: CUTULI HNOS S.A. | G27: FCA3 | H27: 1500092093 | I27: 47742.28 | J27: 0 | K27: DESA | L27: Desarrollos | M27: CHIVILCOY | N27: CHIVILCOY 2171 | O27: 0 | P27: PRELIMINARES - CUTULI HNOS S.A | Q27: =IFERROR(TRIM(LEFT($E27,FIND(" | ",$E27)-1)),"") | R27: =IFERROR(TRIM(UPPER(MID($E27,FIND(" | ",$E27)+3,IFERROR(FIND(" | ",$E27,FIND(" | ",$E27)+3),LEN($E27)+1)-FIND(" | ",$E27)-3))),"")
A28: 52302 | B28: Mov. Variables | C28: 46093 | D28: 2156 | E28: Fletes - ROBLES EDUARDO NICOLA | F28: ROBLES EDUARDO NICOLAS | G28: FCA3 | H28: 200000062 | I28: 200000 | J28: 0 | K28: DESA | L28: Desarrollos | M28: CHIVILCOY | N28: CHIVILCOY 2171 | O28: 0 | P28: Fletes - ROBLES EDUARDO NICOLA | Q28: =IFERROR(TRIM(LEFT($E28,FIND(" | ",$E28)-1)),"") | R28: =IFERROR(TRIM(UPPER(MID($E28,FIND(" | ",$E28)+3,IFERROR(FIND(" | ",$E28,FIND(" | ",$E28)+3),LEN($E28)+1)-FIND(" | ",$E28)-3))),"")
A29: 53001 | B29: Preliminares | C29: 46094 | D29: 1674 | E29: PRELIMINARES - Casa Castelao S | F29: Casa Castelao S.A. | G29: FCA3 | H29: 300011508 | I29: 187369.3 | J29: 0 | K29: DESA | L29: Desarrollos | M29: CHIVILCOY | N29: CHIVILCOY 2171 | O29: 0 | P29: PRELIMINARES - Casa Castelao S | Q29: =IFERROR(TRIM(LEFT($E29,FIND(" | ",$E29)-1)),"") | R29: =IFERROR(TRIM(UPPER(MID($E29,FIND(" | ",$E29)+3,IFERROR(FIND(" | ",$E29,FIND(" | ",$E29)+3),LEN($E29)+1)-FIND(" | ",$E29)-3))),"")
A30: 53001 | B30: Preliminares | C30: 46094 | D30: 1675 | E30: PRELIMINARES - Casa Castelao S | F30: Casa Castelao S.A. | G30: FCA3 | H30: 300011507 | I30: 706017.99 | J30: 0 | K30: DESA | L30: Desarrollos | M30: CHIVILCOY | N30: CHIVILCOY 2171 | O30: 0 | P30: PRELIMINARES - Casa Castelao S | Q30: =IFERROR(TRIM(LEFT($E30,FIND(" | ",$E30)-1)),"") | R30: =IFERROR(TRIM(UPPER(MID($E30,FIND(" | ",$E30)+3,IFERROR(FIND(" | ",$E30,FIND(" | ",$E30)+3),LEN($E30)+1)-FIND(" | ",$E30)-3))),"")
A31: 53001 | B31: Preliminares | C31: 46094 | D31: 1679 | E31: PRELIMINARES - CUTULI HNOS S.A | F31: CUTULI HNOS S.A. | G31: FCA3 | H31: 1500092213 | I31: 52488.39 | J31: 0 | K31: DESA | L31: Desarrollos | M31: CHIVILCOY | N31: CHIVILCOY 2171 | O31: 0 | P31: PRELIMINARES - CUTULI HNOS S.A | Q31: =IFERROR(TRIM(LEFT($E31,FIND(" | ",$E31)-1)),"") | R31: =IFERROR(TRIM(UPPER(MID($E31,FIND(" | ",$E31)+3,IFERROR(FIND(" | ",$E31,FIND(" | ",$E31)+3),LEN($E31)+1)-FIND(" | ",$E31)-3))),"")
A32: 53001 | B32: Preliminares | C32: 46094 | D32: 1716 | E32: PRELIMINARES - DESSINS CARTELE | F32: DESSINS CARTELERIA S.R.L | G32: FCA3 | H32: 200008156 | I32: 9917.36 | J32: 0 | K32: DESA | L32: Desarrollos | M32: CHIVILCOY | N32: CHIVILCOY 2171 | O32: 0 | P32: PRELIMINARES - DESSINS CARTELE | Q32: =IFERROR(TRIM(LEFT($E32,FIND(" | ",$E32)-1)),"") | R32: =IFERROR(TRIM(UPPER(MID($E32,FIND(" | ",$E32)+3,IFERROR(FIND(" | ",$E32,FIND(" | ",$E32)+3),LEN($E32)+1)-FIND(" | ",$E32)-3))),"")
A33: 53023 | B33: Varios Ferreteria | C33: 46094 | D33: 872 | E33: Varios Ferreteria | G33: OPXX | H33: 8904 | I33: 1000 | J33: 0 | K33: DESA | L33: Desarrollos | M33: CHIVILCOY | N33: CHIVILCOY 2171 | O33: 0 | P33: Varios Ferreteria | Q33: =IFERROR(TRIM(LEFT($E33,FIND(" | ",$E33)-1)),"") | R33: =IFERROR(TRIM(UPPER(MID($E33,FIND(" | ",$E33)+3,IFERROR(FIND(" | ",$E33,FIND(" | ",$E33)+3),LEN($E33)+1)-FIND(" | ",$E33)-3))),"")
A34: 53023 | B34: Varios Ferreteria | C34: 46094 | D34: 873 | E34: Varios Ferreteria | G34: OPXX | H34: 8905 | I34: 14500 | J34: 0 | K34: DESA | L34: Desarrollos | M34: CHIVILCOY | N34: CHIVILCOY 2171 | O34: 0 | P34: Varios Ferreteria | Q34: =IFERROR(TRIM(LEFT($E34,FIND(" | ",$E34)-1)),"") | R34: =IFERROR(TRIM(UPPER(MID($E34,FIND(" | ",$E34)+3,IFERROR(FIND(" | ",$E34,FIND(" | ",$E34)+3),LEN($E34)+1)-FIND(" | ",$E34)-3))),"")
A35: 52302 | B35: Mov. Variables | C35: 46096 | D35: 1717 | E35: Nafta Super - YPF S.A. | F35: YPF S.A. | G35: FCA3 | H35: 142000000000 | I35: 93458.79 | J35: 0 | K35: DESA | L35: Desarrollos | M35: CHIVILCOY | N35: CHIVILCOY 2171 | O35: 0 | P35: Nafta Super - YPF S.A. | Q35: =IFERROR(TRIM(LEFT($E35,FIND(" | ",$E35)-1)),"") | R35: =IFERROR(TRIM(UPPER(MID($E35,FIND(" | ",$E35)+3,IFERROR(FIND(" | ",$E35,FIND(" | ",$E35)+3),LEN($E35)+1)-FIND(" | ",$E35)-3))),"")
A36: 52302 | B36: Mov. Variables | C36: 46096 | D36: 1717 | E36: ICL - YPF S.A. | F36: YPF S.A. | G36: FCA3 | H36: 142000000000 | I36: 19382.5 | J36: 0 | K36: DESA | L36: Desarrollos | M36: CHIVILCOY | N36: CHIVILCOY 2171 | O36: 0 | P36: ICL - YPF S.A. | Q36: =IFERROR(TRIM(LEFT($E36,FIND(" | ",$E36)-1)),"") | R36: =IFERROR(TRIM(UPPER(MID($E36,FIND(" | ",$E36)+3,IFERROR(FIND(" | ",$E36,FIND(" | ",$E36)+3),LEN($E36)+1)-FIND(" | ",$E36)-3))),"")
A37: 53026 | B37: Seguridad e Higiene | C37: 46097 | D37: 1719 | E37: Matafuegos - LSH Servicios SRL | F37: LSH Servicios SRL | G37: FCA3 | H37: 200001017 | I37: 309090.91 | J37: 0 | K37: DESA | L37: Desarrollos | M37: CHIVILCOY | N37: CHIVILCOY 2171 | O37: 0 | P37: Matafuegos - LSH Servicios SRL | Q37: =IFERROR(TRIM(LEFT($E37,FIND(" | ",$E37)-1)),"") | R37: =IFERROR(TRIM(UPPER(MID($E37,FIND(" | ",$E37)+3,IFERROR(FIND(" | ",$E37,FIND(" | ",$E37)+3),LEN($E37)+1)-FIND(" | ",$E37)-3))),"")
A38: 52302 | B38: Mov. Variables | C38: 46099 | D38: 874 | E38: Estacionamiento | G38: OPXX | H38: 8906 | I38: 4500 | J38: 0 | K38: DESA | L38: Desarrollos | M38: CHIVILCOY | N38: CHIVILCOY 2171 | O38: 0 | P38: Estacionamiento | Q38: =IFERROR(TRIM(LEFT($E38,FIND(" | ",$E38)-1)),"") | R38: =IFERROR(TRIM(UPPER(MID($E38,FIND(" | ",$E38)+3,IFERROR(FIND(" | ",$E38,FIND(" | ",$E38)+3),LEN($E38)+1)-FIND(" | ",$E38)-3))),"")
A39: 53008 | B39: Albañilería MT | C39: 46099 | D39: 1802 | E39: ALBAÑILERIA MT - CUTULI HNOS S | F39: CUTULI HNOS S.A. | G39: FCA3 | H39: 1500092503 | I39: 87942.03 | J39: 0 | K39: DESA | L39: Desarrollos | M39: CHIVILCOY | N39: CHIVILCOY 2171 | O39: 0 | P39: ALBAÑILERIA MT - CUTULI HNOS S | Q39: =IFERROR(TRIM(LEFT($E39,FIND(" | ",$E39)-1)),"") | R39: =IFERROR(TRIM(UPPER(MID($E39,FIND(" | ",$E39)+3,IFERROR(FIND(" | ",$E39,FIND(" | ",$E39)+3),LEN($E39)+1)-FIND(" | ",$E39)-3))),"")
A40: 53009 | B40: Albañilería MO | C40: 46100 | D40: 810 | E40: 1Q 03-2026 - Obra Chivilcoy | G40: OPXX | H40: 8838 | I40: 455500 | J40: 0 | K40: DESA | L40: Desarrollos | M40: CHIVILCOY | N40: CHIVILCOY 2171 | O40: 0 | P40: 1Q 03-2026 - Obra Chivilcoy | Q40: =IFERROR(TRIM(LEFT($E40,FIND(" | ",$E40)-1)),"") | R40: =IFERROR(TRIM(UPPER(MID($E40,FIND(" | ",$E40)+3,IFERROR(FIND(" | ",$E40,FIND(" | ",$E40)+3),LEN($E40)+1)-FIND(" | ",$E40)-3))),"")
A41: 53009 | B41: Albañilería MO | C41: 46104 | D41: 838 | E41: 1Q 03-2026 - Lescano S. Oscar | G41: OPXX | H41: 8866 | I41: 64000 | J41: 0 | K41: DESA | L41: Desarrollos | M41: CHIVILCOY | N41: CHIVILCOY 2171 | O41: 0 | P41: 1Q 03-2026 - Lescano S. Oscar | Q41: =IFERROR(TRIM(LEFT($E41,FIND(" | ",$E41)-1)),"") | R41: =IFERROR(TRIM(UPPER(MID($E41,FIND(" | ",$E41)+3,IFERROR(FIND(" | ",$E41,FIND(" | ",$E41)+3),LEN($E41)+1)-FIND(" | ",$E41)-3))),"")
A42: 53001 | B42: Preliminares | C42: 46106 | D42: 840 | E42: CH-SC-002 | BASE | Alejandro Ardiles - Agrimensor | G42: OPXX | H42: 8868 | I42: 350000 | J42: 0 | K42: DESA | L42: Desarrollos | M42: CHIVILCOY | N42: CHIVILCOY 2171 | O42: 0 | P42: Alejandro Ardiles - Agrimensor | Q42: =IFERROR(TRIM(LEFT($E42,FIND(" | ",$E42)-1)),"") -> CH-SC-002 | R42: =IFERROR(TRIM(UPPER(MID($E42,FIND(" | ",$E42)+3,IFERROR(FIND(" | ",$E42,FIND(" | ",$E42)+3),LEN($E42)+1)-FIND(" | ",$E42)-3))),"") -> BASE
A43: 53001 | B43: Preliminares | C43: 46107 | D43: 2104 | E43: PRELIMINARES - DESSINS CARTELE | F43: DESSINS CARTELERIA S.R.L | G43: FCA3 | H43: 200008240 | I43: 20661.16 | J43: 0 | K43: DESA | L43: Desarrollos | M43: CHIVILCOY | N43: CHIVILCOY 2171 | O43: 0 | P43: PRELIMINARES - DESSINS CARTELE | Q43: =IFERROR(TRIM(LEFT($E43,FIND(" | ",$E43)-1)),"") | R43: =IFERROR(TRIM(UPPER(MID($E43,FIND(" | ",$E43)+3,IFERROR(FIND(" | ",$E43,FIND(" | ",$E43)+3),LEN($E43)+1)-FIND(" | ",$E43)-3))),"")
A44: 52302 | B44: Mov. Variables | C44: 46108 | D44: 877 | E44: Viaticos | G44: OPXX | H44: 8909 | I44: 8700 | J44: 0 | K44: DESA | L44: Desarrollos | M44: CHIVILCOY | N44: CHIVILCOY 2171 | O44: 0 | P44: Viaticos | Q44: =IFERROR(TRIM(LEFT($E44,FIND(" | ",$E44)-1)),"") | R44: =IFERROR(TRIM(UPPER(MID($E44,FIND(" | ",$E44)+3,IFERROR(FIND(" | ",$E44,FIND(" | ",$E44)+3),LEN($E44)+1)-FIND(" | ",$E44)-3))),"")
A45: 53001 | B45: Preliminares | C45: 46108 | D45: 2110 | E45: PRELIMINARES - Casa Castelao S | F45: Casa Castelao S.A. | G45: NCA3 | H45: 300001370 | I45: 0 | J45: 45848.34 | K45: DESA | L45: Desarrollos | M45: CHIVILCOY | N45: CHIVILCOY 2171 | O45: 0 | P45: PRELIMINARES - Casa Castelao S | Q45: =IFERROR(TRIM(LEFT($E45,FIND(" | ",$E45)-1)),"") | R45: =IFERROR(TRIM(UPPER(MID($E45,FIND(" | ",$E45)+3,IFERROR(FIND(" | ",$E45,FIND(" | ",$E45)+3),LEN($E45)+1)-FIND(" | ",$E45)-3))),"")
A46: 410222 | B46: Obra civil Reforma | C46: 46111 | D46: 2023 | E46: Obras - Fideicomiso Arquinerin | F46: Fideicomiso Arquinering Parque | G46: FAWS | H46: 300000834 | I46: 0 | J46: 35000000 | K46: DESA | L46: Desarrollos | M46: CHIVILCOY | N46: CHIVILCOY 2171 | O46: 0 | P46: Obras - Fideicomiso Arquinerin | Q46: =IFERROR(TRIM(LEFT($E46,FIND(" | ",$E46)-1)),"") | R46: =IFERROR(TRIM(UPPER(MID($E46,FIND(" | ",$E46)+3,IFERROR(FIND(" | ",$E46,FIND(" | ",$E46)+3),LEN($E46)+1)-FIND(" | ",$E46)-3))),"")
A47: 53022 | B47: Gastos Generales | C47: 46111 | D47: 2116 | E47: Baño quimico - ECOBAT SRL | F47: ECOBAT SRL | G47: FCA3 | H47: 300025429 | I47: 227000 | J47: 0 | K47: DESA | L47: Desarrollos | M47: CHIVILCOY | N47: CHIVILCOY 2171 | O47: 0 | P47: Baño quimico - ECOBAT SRL | Q47: =IFERROR(TRIM(LEFT($E47,FIND(" | ",$E47)-1)),"") | R47: =IFERROR(TRIM(UPPER(MID($E47,FIND(" | ",$E47)+3,IFERROR(FIND(" | ",$E47,FIND(" | ",$E47)+3),LEN($E47)+1)-FIND(" | ",$E47)-3))),"")
A48: 52302 | B48: Mov. Variables | C48: 46112 | D48: 2351 | E48: ICL - YPF S.A. | F48: YPF S.A. | G48: FCA3 | H48: 142000000000 | I48: 49028.59 | J48: 0 | K48: DESA | L48: Desarrollos | M48: CHIVILCOY | N48: CHIVILCOY 2171 | O48: 0 | P48: ICL - YPF S.A. | Q48: =IFERROR(TRIM(LEFT($E48,FIND(" | ",$E48)-1)),"") | R48: =IFERROR(TRIM(UPPER(MID($E48,FIND(" | ",$E48)+3,IFERROR(FIND(" | ",$E48,FIND(" | ",$E48)+3),LEN($E48)+1)-FIND(" | ",$E48)-3))),"")
A49: 52302 | B49: Mov. Variables | C49: 46112 | D49: 2351 | E49: IDC - YPF S.A. | F49: YPF S.A. | G49: FCA3 | H49: 142000000000 | I49: 3775.02 | J49: 0 | K49: DESA | L49: Desarrollos | M49: CHIVILCOY | N49: CHIVILCOY 2171 | O49: 0 | P49: IDC - YPF S.A. | Q49: =IFERROR(TRIM(LEFT($E49,FIND(" | ",$E49)-1)),"") | R49: =IFERROR(TRIM(UPPER(MID($E49,FIND(" | ",$E49)+3,IFERROR(FIND(" | ",$E49,FIND(" | ",$E49)+3),LEN($E49)+1)-FIND(" | ",$E49)-3))),"")
A50: 52302 | B50: Mov. Variables | C50: 46112 | D50: 2351 | E50: Infinia Diesel - YPF S.A. | F50: YPF S.A. | G50: FCA3 | H50: 142000000000 | I50: 54265.6 | J50: 0 | K50: DESA | L50: Desarrollos | M50: CHIVILCOY | N50: CHIVILCOY 2171 | O50: 0 | P50: Infinia Diesel - YPF S.A. | Q50: =IFERROR(TRIM(LEFT($E50,FIND(" | ",$E50)-1)),"") | R50: =IFERROR(TRIM(UPPER(MID($E50,FIND(" | ",$E50)+3,IFERROR(FIND(" | ",$E50,FIND(" | ",$E50)+3),LEN($E50)+1)-FIND(" | ",$E50)-3))),"")
A51: 52302 | B51: Mov. Variables | C51: 46112 | D51: 2351 | E51: Nafta Super - YPF S.A. | F51: YPF S.A. | G51: FCA3 | H51: 142000000000 | I51: 191066.46 | J51: 0 | K51: DESA | L51: Desarrollos | M51: CHIVILCOY | N51: CHIVILCOY 2171 | O51: 0 | P51: Nafta Super - YPF S.A. | Q51: =IFERROR(TRIM(LEFT($E51,FIND(" | ",$E51)-1)),"") | R51: =IFERROR(TRIM(UPPER(MID($E51,FIND(" | ",$E51)+3,IFERROR(FIND(" | ",$E51,FIND(" | ",$E51)+3),LEN($E51)+1)-FIND(" | ",$E51)-3))),"")
A52: 52302 | B52: Mov. Variables | C52: 46112 | D52: 2351 | E52: Nafta Infinia - YPF S.A. | F52: YPF S.A. | G52: FCA3 | H52: 142000000000 | I52: 15565.68 | J52: 0 | K52: DESA | L52: Desarrollos | M52: CHIVILCOY | N52: CHIVILCOY 2171 | O52: 0 | P52: Nafta Infinia - YPF S.A. | Q52: =IFERROR(TRIM(LEFT($E52,FIND(" | ",$E52)-1)),"") | R52: =IFERROR(TRIM(UPPER(MID($E52,FIND(" | ",$E52)+3,IFERROR(FIND(" | ",$E52,FIND(" | ",$E52)+3),LEN($E52)+1)-FIND(" | ",$E52)-3))),"")
A53: 52204 | B53: H. Seguridad e Higiene | C53: 46113 | D53: 2174 | E53: Honorarios Seguridad e Higiene | F53: Petrini David Osvaldo | G53: FCA3 | H53: 300001454 | I53: 517195 | J53: 0 | K53: DESA | L53: Desarrollos | M53: CHIVILCOY | N53: CHIVILCOY 2171 | O53: 0 | P53: Honorarios Seguridad e Higiene | Q53: =IFERROR(TRIM(LEFT($E53,FIND(" | ",$E53)-1)),"") | R53: =IFERROR(TRIM(UPPER(MID($E53,FIND(" | ",$E53)+3,IFERROR(FIND(" | ",$E53,FIND(" | ",$E53)+3),LEN($E53)+1)-FIND(" | ",$E53)-3))),"")
A54: 53001 | B54: Preliminares | C54: 46113 | D54: 2178 | E54: PRELIMINARES - Casa Castelao S | F54: Casa Castelao S.A. | G54: FCA3 | H54: 300011847 | I54: 166340.01 | J54: 0 | K54: DESA | L54: Desarrollos | M54: CHIVILCOY | N54: CHIVILCOY 2171 | O54: 0 | P54: PRELIMINARES - Casa Castelao S | Q54: =IFERROR(TRIM(LEFT($E54,FIND(" | ",$E54)-1)),"") | R54: =IFERROR(TRIM(UPPER(MID($E54,FIND(" | ",$E54)+3,IFERROR(FIND(" | ",$E54,FIND(" | ",$E54)+3),LEN($E54)+1)-FIND(" | ",$E54)-3))),"")
A55: 53008 | B55: Albañilería MT | C55: 46113 | D55: 2177 | E55: ALBAÑILERIA MT - CUTULI HNOS S | F55: CUTULI HNOS S.A. | G55: FCA3 | H55: 1500093023 | I55: 30448.16 | J55: 0 | K55: DESA | L55: Desarrollos | M55: CHIVILCOY | N55: CHIVILCOY 2171 | O55: 0 | P55: ALBAÑILERIA MT - CUTULI HNOS S | Q55: =IFERROR(TRIM(LEFT($E55,FIND(" | ",$E55)-1)),"") | R55: =IFERROR(TRIM(UPPER(MID($E55,FIND(" | ",$E55)+3,IFERROR(FIND(" | ",$E55,FIND(" | ",$E55)+3),LEN($E55)+1)-FIND(" | ",$E55)-3))),"")
A56: 53023 | B56: Varios Ferreteria | C56: 46113 | D56: 876 | E56: Varios Ferreteria | G56: OPXX | H56: 8908 | I56: 52000 | J56: 0 | K56: DESA | L56: Desarrollos | M56: CHIVILCOY | N56: CHIVILCOY 2171 | O56: 0 | P56: Varios Ferreteria | Q56: =IFERROR(TRIM(LEFT($E56,FIND(" | ",$E56)-1)),"") | R56: =IFERROR(TRIM(UPPER(MID($E56,FIND(" | ",$E56)+3,IFERROR(FIND(" | ",$E56,FIND(" | ",$E56)+3),LEN($E56)+1)-FIND(" | ",$E56)-3))),"")
A57: 53009 | B57: Albañilería MO | C57: 46119 | D57: 1068 | E57: 2Q 03-2026 - CHIVILCOY | G57: OPXX | H57: 9095 | I57: 726500 | J57: 0 | K57: DESA | L57: Desarrollos | M57: CHIVILCOY | N57: CHIVILCOY 2171 | O57: 0 | P57: 2Q 03-2026 - CHIVILCOY | Q57: =IFERROR(TRIM(LEFT($E57,FIND(" | ",$E57)-1)),"") | R57: =IFERROR(TRIM(UPPER(MID($E57,FIND(" | ",$E57)+3,IFERROR(FIND(" | ",$E57,FIND(" | ",$E57)+3),LEN($E57)+1)-FIND(" | ",$E57)-3))),"")
A58: 52104 | B58: Aguas | C58: 46123 | D58: 2360 | E58: Aguas - EMBOTELLADORA BONSAL | F58: EMBOTELLADORA BONSAL | G58: FCA3 | H58: 400037178 | I58: 66528.93 | J58: 0 | K58: DESA | L58: Desarrollos | M58: CHIVILCOY | N58: CHIVILCOY 2171 | O58: 0 | P58: Aguas - EMBOTELLADORA BONSAL | Q58: =IFERROR(TRIM(LEFT($E58,FIND(" | ",$E58)-1)),"") | R58: =IFERROR(TRIM(UPPER(MID($E58,FIND(" | ",$E58)+3,IFERROR(FIND(" | ",$E58,FIND(" | ",$E58)+3),LEN($E58)+1)-FIND(" | ",$E58)-3))),"")
A59: 52302 | B59: Mov. Variables | C59: 46123 | D59: 2359 | E59: Saveiro - RUGGERI LEANDRO RAUL | F59: RUGGERI LEANDRO RAUL | G59: FC3 | H59: 300000995 | I59: 230000 | J59: 0 | K59: DESA | L59: Desarrollos | M59: CHIVILCOY | N59: CHIVILCOY 2171 | O59: 0 | P59: Saveiro - RUGGERI LEANDRO RAUL | Q59: =IFERROR(TRIM(LEFT($E59,FIND(" | ",$E59)-1)),"") | R59: =IFERROR(TRIM(UPPER(MID($E59,FIND(" | ",$E59)+3,IFERROR(FIND(" | ",$E59,FIND(" | ",$E59)+3),LEN($E59)+1)-FIND(" | ",$E59)-3))),"")
A60: 52210 | B60: H. Gestoria | C60: 46125 | D60: 986 | E60: CH-SC-001 | BASE | Claudio Balaclav - Gestor Elec | G60: OPXX | H60: 9014 | I60: 520000 | J60: 0 | K60: DESA | L60: Desarrollos | M60: CHIVILCOY | N60: CHIVILCOY 2171 | O60: 0 | P60: Claudio Balaclav - Gestor Elec | Q60: =IFERROR(TRIM(LEFT($E60,FIND(" | ",$E60)-1)),"") -> CH-SC-001 | R60: =IFERROR(TRIM(UPPER(MID($E60,FIND(" | ",$E60)+3,IFERROR(FIND(" | ",$E60,FIND(" | ",$E60)+3),LEN($E60)+1)-FIND(" | ",$E60)-3))),"") -> BASE
A61: 5108 | B61: Gastos en personal | C61: 46126 | D61: 1170 | E61: Farmacia | G61: OPXX | H61: 9198 | I61: 30220 | J61: 0 | K61: DESA | L61: Desarrollos | M61: CHIVILCOY | N61: CHIVILCOY 2171 | O61: 0 | P61: Farmacia | Q61: =IFERROR(TRIM(LEFT($E61,FIND(" | ",$E61)-1)),"") | R61: =IFERROR(TRIM(UPPER(MID($E61,FIND(" | ",$E61)+3,IFERROR(FIND(" | ",$E61,FIND(" | ",$E61)+3),LEN($E61)+1)-FIND(" | ",$E61)-3))),"")
A62: 52302 | B62: Mov. Variables | C62: 46126 | D62: 1177 | E62: Viaticos | G62: OPXX | H62: 9205 | I62: 20000 | J62: 0 | K62: DESA | L62: Desarrollos | M62: CHIVILCOY | N62: CHIVILCOY 2171 | O62: 0 | P62: Viaticos | Q62: =IFERROR(TRIM(LEFT($E62,FIND(" | ",$E62)-1)),"") | R62: =IFERROR(TRIM(UPPER(MID($E62,FIND(" | ",$E62)+3,IFERROR(FIND(" | ",$E62,FIND(" | ",$E62)+3),LEN($E62)+1)-FIND(" | ",$E62)-3))),"")
A63: 53001 | B63: Preliminares | C63: 46126 | D63: 1176 | E63: Preliminares | G63: OPXX | H63: 9204 | I63: 48569.87 | J63: 0 | K63: DESA | L63: Desarrollos | M63: CHIVILCOY | N63: CHIVILCOY 2171 | O63: 0 | P63: Preliminares | Q63: =IFERROR(TRIM(LEFT($E63,FIND(" | ",$E63)-1)),"") | R63: =IFERROR(TRIM(UPPER(MID($E63,FIND(" | ",$E63)+3,IFERROR(FIND(" | ",$E63,FIND(" | ",$E63)+3),LEN($E63)+1)-FIND(" | ",$E63)-3))),"")
A64: 53004 | B64: Hormigón MT | C64: 46126 | D64: 2870 | E64: HORMIGON MT - Comercial cmp S. | F64: Comercial cmp S.A | G64: FCA3 | H64: 21100147636 | I64: 766357.68 | J64: 0 | K64: DESA | L64: Desarrollos | M64: CHIVILCOY | N64: CHIVILCOY 2171 | O64: 0 | P64: HORMIGON MT - Comercial cmp S. | Q64: =IFERROR(TRIM(LEFT($E64,FIND(" | ",$E64)-1)),"") | R64: =IFERROR(TRIM(UPPER(MID($E64,FIND(" | ",$E64)+3,IFERROR(FIND(" | ",$E64,FIND(" | ",$E64)+3),LEN($E64)+1)-FIND(" | ",$E64)-3))),"")
A65: 53022 | B65: Gastos Generales | C65: 46126 | D65: 1175 | E65: Kit de ollas y utensilios | G65: OPXX | H65: 9203 | I65: 49000 | J65: 0 | K65: DESA | L65: Desarrollos | M65: CHIVILCOY | N65: CHIVILCOY 2171 | O65: 0 | P65: Kit de ollas y utensilios | Q65: =IFERROR(TRIM(LEFT($E65,FIND(" | ",$E65)-1)),"") | R65: =IFERROR(TRIM(UPPER(MID($E65,FIND(" | ",$E65)+3,IFERROR(FIND(" | ",$E65,FIND(" | ",$E65)+3),LEN($E65)+1)-FIND(" | ",$E65)-3))),"")
A66: 53023 | B66: Varios Ferreteria | C66: 46126 | D66: 1171 | E66: Varios Ferreteria | G66: OPXX | H66: 9199 | I66: 10000 | J66: 0 | K66: DESA | L66: Desarrollos | M66: CHIVILCOY | N66: CHIVILCOY 2171 | O66: 0 | P66: Varios Ferreteria | Q66: =IFERROR(TRIM(LEFT($E66,FIND(" | ",$E66)-1)),"") | R66: =IFERROR(TRIM(UPPER(MID($E66,FIND(" | ",$E66)+3,IFERROR(FIND(" | ",$E66,FIND(" | ",$E66)+3),LEN($E66)+1)-FIND(" | ",$E66)-3))),"")
A67: 53023 | B67: Varios Ferreteria | C67: 46126 | D67: 1172 | E67: Varios Ferreteria | G67: OPXX | H67: 9200 | I67: 7000 | J67: 0 | K67: DESA | L67: Desarrollos | M67: CHIVILCOY | N67: CHIVILCOY 2171 | O67: 0 | P67: Varios Ferreteria | Q67: =IFERROR(TRIM(LEFT($E67,FIND(" | ",$E67)-1)),"") | R67: =IFERROR(TRIM(UPPER(MID($E67,FIND(" | ",$E67)+3,IFERROR(FIND(" | ",$E67,FIND(" | ",$E67)+3),LEN($E67)+1)-FIND(" | ",$E67)-3))),"")
A68: 53023 | B68: Varios Ferreteria | C68: 46126 | D68: 1174 | E68: Varios Ferreteria | G68: OPXX | H68: 9202 | I68: 78892 | J68: 0 | K68: DESA | L68: Desarrollos | M68: CHIVILCOY | N68: CHIVILCOY 2171 | O68: 0 | P68: Varios Ferreteria | Q68: =IFERROR(TRIM(LEFT($E68,FIND(" | ",$E68)-1)),"") | R68: =IFERROR(TRIM(UPPER(MID($E68,FIND(" | ",$E68)+3,IFERROR(FIND(" | ",$E68,FIND(" | ",$E68)+3),LEN($E68)+1)-FIND(" | ",$E68)-3))),"")
A69: 52302 | B69: Mov. Variables | C69: 46127 | D69: 2376 | E69: Infinia Diesel - YPF S.A. | F69: YPF S.A. | G69: FCA3 | H69: 142000000000 | I69: 27160.13 | J69: 0 | K69: DESA | L69: Desarrollos | M69: CHIVILCOY | N69: CHIVILCOY 2171 | O69: 0 | P69: Infinia Diesel - YPF S.A. | Q69: =IFERROR(TRIM(LEFT($E69,FIND(" | ",$E69)-1)),"") | R69: =IFERROR(TRIM(UPPER(MID($E69,FIND(" | ",$E69)+3,IFERROR(FIND(" | ",$E69,FIND(" | ",$E69)+3),LEN($E69)+1)-FIND(" | ",$E69)-3))),"")
A70: 52302 | B70: Mov. Variables | C70: 46127 | D70: 2376 | E70: Nafta Super - YPF S.A. | F70: YPF S.A. | G70: FCA3 | H70: 142000000000 | I70: 139378.65 | J70: 0 | K70: DESA | L70: Desarrollos | M70: CHIVILCOY | N70: CHIVILCOY 2171 | O70: 0 | P70: Nafta Super - YPF S.A. | Q70: =IFERROR(TRIM(LEFT($E70,FIND(" | ",$E70)-1)),"") | R70: =IFERROR(TRIM(UPPER(MID($E70,FIND(" | ",$E70)+3,IFERROR(FIND(" | ",$E70,FIND(" | ",$E70)+3),LEN($E70)+1)-FIND(" | ",$E70)-3))),"")
A71: 52302 | B71: Mov. Variables | C71: 46127 | D71: 2376 | E71: Nafta Infinia - YPF S.A. | F71: YPF S.A. | G71: FCA3 | H71: 142000000000 | I71: 23190.49 | J71: 0 | K71: DESA | L71: Desarrollos | M71: CHIVILCOY | N71: CHIVILCOY 2171 | O71: 0 | P71: Nafta Infinia - YPF S.A. | Q71: =IFERROR(TRIM(LEFT($E71,FIND(" | ",$E71)-1)),"") | R71: =IFERROR(TRIM(UPPER(MID($E71,FIND(" | ",$E71)+3,IFERROR(FIND(" | ",$E71,FIND(" | ",$E71)+3),LEN($E71)+1)-FIND(" | ",$E71)-3))),"")
A72: 52302 | B72: Mov. Variables | C72: 46127 | D72: 2376 | E72: ICL - YPF S.A. | F72: YPF S.A. | G72: FCA3 | H72: 142000000000 | I72: 34462.79 | J72: 0 | K72: DESA | L72: Desarrollos | M72: CHIVILCOY | N72: CHIVILCOY 2171 | O72: 0 | P72: ICL - YPF S.A. | Q72: =IFERROR(TRIM(LEFT($E72,FIND(" | ",$E72)-1)),"") | R72: =IFERROR(TRIM(UPPER(MID($E72,FIND(" | ",$E72)+3,IFERROR(FIND(" | ",$E72,FIND(" | ",$E72)+3),LEN($E72)+1)-FIND(" | ",$E72)-3))),"")
A73: 52302 | B73: Mov. Variables | C73: 46127 | D73: 2376 | E73: IDC - YPF S.A. | F73: YPF S.A. | G73: FCA3 | H73: 142000000000 | I73: 2395.85 | J73: 0 | K73: DESA | L73: Desarrollos | M73: CHIVILCOY | N73: CHIVILCOY 2171 | O73: 0 | P73: IDC - YPF S.A. | Q73: =IFERROR(TRIM(LEFT($E73,FIND(" | ",$E73)-1)),"") | R73: =IFERROR(TRIM(UPPER(MID($E73,FIND(" | ",$E73)+3,IFERROR(FIND(" | ",$E73,FIND(" | ",$E73)+3),LEN($E73)+1)-FIND(" | ",$E73)-3))),"")
A74: 53001 | B74: Preliminares | C74: 46128 | D74: 1143 | E74: CH-SC-004 | BASE | Celsi Vial - Certif. #1 | G74: OPXX | H74: 9171 | I74: 1310000 | J74: 0 | K74: DESA | L74: Desarrollos | M74: CHIVILCOY | N74: CHIVILCOY 2171 | O74: 0 | P74: Celsi Vial - Certif. #1 | Q74: =IFERROR(TRIM(LEFT($E74,FIND(" | ",$E74)-1)),"") -> CH-SC-004 | R74: =IFERROR(TRIM(UPPER(MID($E74,FIND(" | ",$E74)+3,IFERROR(FIND(" | ",$E74,FIND(" | ",$E74)+3),LEN($E74)+1)-FIND(" | ",$E74)-3))),"") -> BASE
A75: 53008 | B75: Albañilería MT | C75: 46129 | D75: 2384 | E75: ALBAÑILERIA MT - CUTULI HNOS S | F75: CUTULI HNOS S.A. | G75: FCA3 | H75: 1500093635 | I75: 341339.24 | J75: 0 | K75: DESA | L75: Desarrollos | M75: CHIVILCOY | N75: CHIVILCOY 2171 | O75: 0 | P75: ALBAÑILERIA MT - CUTULI HNOS S | Q75: =IFERROR(TRIM(LEFT($E75,FIND(" | ",$E75)-1)),"") | R75: =IFERROR(TRIM(UPPER(MID($E75,FIND(" | ",$E75)+3,IFERROR(FIND(" | ",$E75,FIND(" | ",$E75)+3),LEN($E75)+1)-FIND(" | ",$E75)-3))),"")
A76: 53009 | B76: Albañilería MO | C76: 46129 | D76: 1000 | E76: 1Q 04-2026 | G76: OPXX | H76: 9028 | I76: 624000 | J76: 0 | K76: DESA | L76: Desarrollos | M76: CHIVILCOY | N76: CHIVILCOY 2171 | O76: 0 | P76: 1Q 04-2026 | Q76: =IFERROR(TRIM(LEFT($E76,FIND(" | ",$E76)-1)),"") | R76: =IFERROR(TRIM(UPPER(MID($E76,FIND(" | ",$E76)+3,IFERROR(FIND(" | ",$E76,FIND(" | ",$E76)+3),LEN($E76)+1)-FIND(" | ",$E76)-3))),"")
A77: 53009 | B77: Albañilería MO | C77: 46129 | D77: 1004 | E77: 1Q 04-26-Lezcano Oscar-SERENO | G77: OPXX | H77: 9032 | I77: 250000 | J77: 0 | K77: DESA | L77: Desarrollos | M77: CHIVILCOY | N77: CHIVILCOY 2171 | O77: 0 | P77: 1Q 04-26-Lezcano Oscar-SERENO | Q77: =IFERROR(TRIM(LEFT($E77,FIND(" | ",$E77)-1)),"") | R77: =IFERROR(TRIM(UPPER(MID($E77,FIND(" | ",$E77)+3,IFERROR(FIND(" | ",$E77,FIND(" | ",$E77)+3),LEN($E77)+1)-FIND(" | ",$E77)-3))),"")
A78: 53022 | B78: Gastos Generales | C78: 46129 | D78: 1243 | E78: Volquetes | G78: OPXX | H78: 9267 | I78: 900000 | J78: 0 | K78: DESA | L78: Desarrollos | M78: CHIVILCOY | N78: CHIVILCOY 2171 | O78: 0 | P78: Volquetes | Q78: =IFERROR(TRIM(LEFT($E78,FIND(" | ",$E78)-1)),"") | R78: =IFERROR(TRIM(UPPER(MID($E78,FIND(" | ",$E78)+3,IFERROR(FIND(" | ",$E78,FIND(" | ",$E78)+3),LEN($E78)+1)-FIND(" | ",$E78)-3))),"")
A79: 53023 | B79: Varios Ferreteria | C79: 46135 | D79: 2592 | E79: Varios Ferreteria - Sabatini D | F79: Sabatini Daniel Gerardo y Diamantini Luciano | G79: FCA3 | H79: 400006882 | I79: 328016.53 | J79: 0 | K79: DESA | L79: Desarrollos | M79: CHIVILCOY | N79: CHIVILCOY 2171 | O79: 0 | P79: Varios Ferreteria - Sabatini D | Q79: =IFERROR(TRIM(LEFT($E79,FIND(" | ",$E79)-1)),"") | R79: =IFERROR(TRIM(UPPER(MID($E79,FIND(" | ",$E79)+3,IFERROR(FIND(" | ",$E79,FIND(" | ",$E79)+3),LEN($E79)+1)-FIND(" | ",$E79)-3))),"")
A80: 410222 | B80: Obra civil Reforma | C80: 46136 | D80: 2493 | E80: Obras - Fideicomiso Arquinerin | F80: Fideicomiso Arquinering Parque | G80: FAWS | H80: 300000852 | I80: 0 | J80: 32000000 | K80: DESA | L80: Desarrollos | M80: CHIVILCOY | N80: CHIVILCOY 2171 | O80: 0 | P80: Obras - Fideicomiso Arquinerin | Q80: =IFERROR(TRIM(LEFT($E80,FIND(" | ",$E80)-1)),"") | R80: =IFERROR(TRIM(UPPER(MID($E80,FIND(" | ",$E80)+3,IFERROR(FIND(" | ",$E80,FIND(" | ",$E80)+3),LEN($E80)+1)-FIND(" | ",$E80)-3))),"")
A81: 53004 | B81: Hormigón MT | C81: 46136 | D81: 2547 | E81: HORMIGON MT - CUTULI HNOS S.A. | F81: CUTULI HNOS S.A. | G81: FCA3 | H81: 1500093970 | I81: 2957208.5 | J81: 0 | K81: DESA | L81: Desarrollos | M81: CHIVILCOY | N81: CHIVILCOY 2171 | O81: 0 | P81: HORMIGON MT - CUTULI HNOS S.A. | Q81: =IFERROR(TRIM(LEFT($E81,FIND(" | ",$E81)-1)),"") | R81: =IFERROR(TRIM(UPPER(MID($E81,FIND(" | ",$E81)+3,IFERROR(FIND(" | ",$E81,FIND(" | ",$E81)+3),LEN($E81)+1)-FIND(" | ",$E81)-3))),"")
A82: 53004 | B82: Hormigón MT | C82: 46139 | D82: 2548 | E82: HORMIGON MT - CUTULI HNOS S.A. | F82: CUTULI HNOS S.A. | G82: NCA3 | H82: 1500005603 | I82: 0 | J82: 2957208.5 | K82: DESA | L82: Desarrollos | M82: CHIVILCOY | N82: CHIVILCOY 2171 | O82: 0 | P82: HORMIGON MT - CUTULI HNOS S.A. | Q82: =IFERROR(TRIM(LEFT($E82,FIND(" | ",$E82)-1)),"") | R82: =IFERROR(TRIM(UPPER(MID($E82,FIND(" | ",$E82)+3,IFERROR(FIND(" | ",$E82,FIND(" | ",$E82)+3),LEN($E82)+1)-FIND(" | ",$E82)-3))),"")
A83: 53005 | B83: Homigón MO | C83: 46140 | D83: 2557 | E83: CH-SC-003 | BASE | Micropilotes - FEIS DEL OESTE | F83: FEIS DEL OESTE CONSTRUCTORA SA | G83: FCA3 | H83: 100001506 | I83: 6837217.1 | J83: 0 | K83: DESA | L83: Desarrollos | M83: CHIVILCOY | N83: CHIVILCOY 2171 | O83: 0 | P83: Micropilotes - FEIS DEL OESTE | Q83: =IFERROR(TRIM(LEFT($E83,FIND(" | ",$E83)-1)),"") -> CH-SC-003 | R83: =IFERROR(TRIM(UPPER(MID($E83,FIND(" | ",$E83)+3,IFERROR(FIND(" | ",$E83,FIND(" | ",$E83)+3),LEN($E83)+1)-FIND(" | ",$E83)-3))),"") -> BASE
A84: 53022 | B84: Gastos Generales | C84: 46140 | D84: 2563 | E84: Baño portatil - ECOBAT SRL | F84: ECOBAT SRL | G84: FCA3 | H84: 300025673 | I84: 227000 | J84: 0 | K84: DESA | L84: Desarrollos | M84: CHIVILCOY | N84: CHIVILCOY 2171 | O84: 0 | P84: Baño portatil - ECOBAT SRL | Q84: =IFERROR(TRIM(LEFT($E84,FIND(" | ",$E84)-1)),"") | R84: =IFERROR(TRIM(UPPER(MID($E84,FIND(" | ",$E84)+3,IFERROR(FIND(" | ",$E84,FIND(" | ",$E84)+3),LEN($E84)+1)-FIND(" | ",$E84)-3))),"")
A85: 53022 | B85: Gastos Generales | C85: 46141 | D85: 2597 | E85: GASTOS GENERALES - ECOBAT SRL | F85: ECOBAT SRL | G85: NCA3 | H85: 300002604 | I85: 0 | J85: 75000 | K85: DESA | L85: Desarrollos | M85: CHIVILCOY | N85: CHIVILCOY 2171 | O85: 0 | P85: GASTOS GENERALES - ECOBAT SRL | Q85: =IFERROR(TRIM(LEFT($E85,FIND(" | ",$E85)-1)),"") | R85: =IFERROR(TRIM(UPPER(MID($E85,FIND(" | ",$E85)+3,IFERROR(FIND(" | ",$E85,FIND(" | ",$E85)+3),LEN($E85)+1)-FIND(" | ",$E85)-3))),"")
A86: 52302 | B86: Mov. Variables | C86: 46142 | D86: 2598 | E86: Infinia Diesel - YPF S.A. | F86: YPF S.A. | G86: FCA3 | H86: 142000000000 | I86: 74897.92 | J86: 0 | K86: DESA | L86: Desarrollos | M86: CHIVILCOY | N86: CHIVILCOY 2171 | O86: 0 | P86: Infinia Diesel - YPF S.A. | Q86: =IFERROR(TRIM(LEFT($E86,FIND(" | ",$E86)-1)),"") | R86: =IFERROR(TRIM(UPPER(MID($E86,FIND(" | ",$E86)+3,IFERROR(FIND(" | ",$E86,FIND(" | ",$E86)+3),LEN($E86)+1)-FIND(" | ",$E86)-3))),"")
A87: 52302 | B87: Mov. Variables | C87: 46142 | D87: 2598 | E87: Nafta Super - YPF S.A. | F87: YPF S.A. | G87: FCA3 | H87: 142000000000 | I87: 45883.56 | J87: 0 | K87: DESA | L87: Desarrollos | M87: CHIVILCOY | N87: CHIVILCOY 2171 | O87: 0 | P87: Nafta Super - YPF S.A. | Q87: =IFERROR(TRIM(LEFT($E87,FIND(" | ",$E87)-1)),"") | R87: =IFERROR(TRIM(UPPER(MID($E87,FIND(" | ",$E87)+3,IFERROR(FIND(" | ",$E87,FIND(" | ",$E87)+3),LEN($E87)+1)-FIND(" | ",$E87)-3))),"")
A88: 52302 | B88: Mov. Variables | C88: 46142 | D88: 2598 | E88: ICL - YPF S.A. | F88: YPF S.A. | G88: FCA3 | H88: 142000000000 | I88: 20757.93 | J88: 0 | K88: DESA | L88: Desarrollos | M88: CHIVILCOY | N88: CHIVILCOY 2171 | O88: 0 | P88: ICL - YPF S.A. | Q88: =IFERROR(TRIM(LEFT($E88,FIND(" | ",$E88)-1)),"") | R88: =IFERROR(TRIM(UPPER(MID($E88,FIND(" | ",$E88)+3,IFERROR(FIND(" | ",$E88,FIND(" | ",$E88)+3),LEN($E88)+1)-FIND(" | ",$E88)-3))),"")
A89: 52302 | B89: Mov. Variables | C89: 46142 | D89: 2598 | E89: IDC - YPF S.A. | F89: YPF S.A. | G89: FCA3 | H89: 142000000000 | I89: 1649.34 | J89: 0 | K89: DESA | L89: Desarrollos | M89: CHIVILCOY | N89: CHIVILCOY 2171 | O89: 0 | P89: IDC - YPF S.A. | Q89: =IFERROR(TRIM(LEFT($E89,FIND(" | ",$E89)-1)),"") | R89: =IFERROR(TRIM(UPPER(MID($E89,FIND(" | ",$E89)+3,IFERROR(FIND(" | ",$E89,FIND(" | ",$E89)+3),LEN($E89)+1)-FIND(" | ",$E89)-3))),"")
A90: 53005 | B90: Homigón MO | C90: 46142 | D90: 1085 | E90: CH-SC-003 | BASE | FEIS Construcciones - Certif. | G90: OPXX | H90: 9112 | I90: 10000000 | J90: 0 | K90: DESA | L90: Desarrollos | M90: CHIVILCOY | N90: CHIVILCOY 2171 | O90: 0 | P90: FEIS Construcciones - Certif. | Q90: =IFERROR(TRIM(LEFT($E90,FIND(" | ",$E90)-1)),"") -> CH-SC-003 | R90: =IFERROR(TRIM(UPPER(MID($E90,FIND(" | ",$E90)+3,IFERROR(FIND(" | ",$E90,FIND(" | ",$E90)+3),LEN($E90)+1)-FIND(" | ",$E90)-3))),"") -> BASE
A91: 5108 | B91: Gastos en personal | C91: 46146 | D91: 2912 | E91: Gastos en Personales - Sabatin | F91: Sabatini Daniel Gerardo y Diamantini Luciano | G91: FCA3 | H91: 400006934 | I91: 28000 | J91: 0 | K91: DESA | L91: Desarrollos | M91: CHIVILCOY | N91: CHIVILCOY 2171 | O91: 0 | P91: Gastos en Personales - Sabatin | Q91: =IFERROR(TRIM(LEFT($E91,FIND(" | ",$E91)-1)),"") | R91: =IFERROR(TRIM(UPPER(MID($E91,FIND(" | ",$E91)+3,IFERROR(FIND(" | ",$E91,FIND(" | ",$E91)+3),LEN($E91)+1)-FIND(" | ",$E91)-3))),"")
A92: 5108 | B92: Gastos en personal | C92: 46146 | D92: 2913 | E92: Gastos en Personales - Sabatin | F92: Sabatini Daniel Gerardo y Diamantini Luciano | G92: FCA3 | H92: 400006950 | I92: 18000 | J92: 0 | K92: DESA | L92: Desarrollos | M92: CHIVILCOY | N92: CHIVILCOY 2171 | O92: 0 | P92: Gastos en Personales - Sabatin | Q92: =IFERROR(TRIM(LEFT($E92,FIND(" | ",$E92)-1)),"") | R92: =IFERROR(TRIM(UPPER(MID($E92,FIND(" | ",$E92)+3,IFERROR(FIND(" | ",$E92,FIND(" | ",$E92)+3),LEN($E92)+1)-FIND(" | ",$E92)-3))),"")
A93: 53023 | B93: Varios Ferreteria | C93: 46146 | D93: 2913 | E93: Varios Ferreteria - Sabatini D | F93: Sabatini Daniel Gerardo y Diamantini Luciano | G93: FCA3 | H93: 400006950 | I93: 19500 | J93: 0 | K93: DESA | L93: Desarrollos | M93: CHIVILCOY | N93: CHIVILCOY 2171 | O93: 0 | P93: Varios Ferreteria - Sabatini D | Q93: =IFERROR(TRIM(LEFT($E93,FIND(" | ",$E93)-1)),"") | R93: =IFERROR(TRIM(UPPER(MID($E93,FIND(" | ",$E93)+3,IFERROR(FIND(" | ",$E93,FIND(" | ",$E93)+3),LEN($E93)+1)-FIND(" | ",$E93)-3))),"")
A94: 5108 | B94: Gastos en personal | C94: 46147 | D94: 2731 | E94: EPP - Abrafer S.R.L. | F94: Abrafer S.R.L. | G94: FCA3 | H94: 1000224499 | I94: 307848.2 | J94: 0 | K94: DESA | L94: Desarrollos | M94: CHIVILCOY | N94: CHIVILCOY 2171 | O94: 0 | P94: EPP - Abrafer S.R.L. | Q94: =IFERROR(TRIM(LEFT($E94,FIND(" | ",$E94)-1)),"") | R94: =IFERROR(TRIM(UPPER(MID($E94,FIND(" | ",$E94)+3,IFERROR(FIND(" | ",$E94,FIND(" | ",$E94)+3),LEN($E94)+1)-FIND(" | ",$E94)-3))),"")
A95: 52204 | B95: H. Seguridad e Higiene | C95: 46147 | D95: 2725 | E95: Honorarios Seguridad e Higiene | F95: Petrini David Osvaldo | G95: FCA3 | H95: 300001481 | I95: 1195790 | J95: 0 | K95: DESA | L95: Desarrollos | M95: CHIVILCOY | N95: CHIVILCOY 2171 | O95: 0 | P95: Honorarios Seguridad e Higiene | Q95: =IFERROR(TRIM(LEFT($E95,FIND(" | ",$E95)-1)),"") | R95: =IFERROR(TRIM(UPPER(MID($E95,FIND(" | ",$E95)+3,IFERROR(FIND(" | ",$E95,FIND(" | ",$E95)+3),LEN($E95)+1)-FIND(" | ",$E95)-3))),"")
A96: 52104 | B96: Aguas | C96: 46149 | D96: 2766 | E96: Aguas - EMBOTELLADORA BONSAL | F96: EMBOTELLADORA BONSAL | G96: FCA3 | H96: 400037951 | I96: 38016.53 | J96: 0 | K96: DESA | L96: Desarrollos | M96: CHIVILCOY | N96: CHIVILCOY 2171 | O96: 0 | P96: Aguas - EMBOTELLADORA BONSAL | Q96: =IFERROR(TRIM(LEFT($E96,FIND(" | ",$E96)-1)),"") | R96: =IFERROR(TRIM(UPPER(MID($E96,FIND(" | ",$E96)+3,IFERROR(FIND(" | ",$E96,FIND(" | ",$E96)+3),LEN($E96)+1)-FIND(" | ",$E96)-3))),"")
A97: 53009 | B97: Albañilería MO | C97: 46149 | D97: 1108 | E97: 2Q 04-2026 - CHIV | G97: OPXX | H97: 9135 | I97: 945500 | J97: 0 | K97: DESA | L97: Desarrollos | M97: CHIVILCOY | N97: CHIVILCOY 2171 | O97: 0 | P97: 2Q 04-2026 - CHIV | Q97: =IFERROR(TRIM(LEFT($E97,FIND(" | ",$E97)-1)),"") | R97: =IFERROR(TRIM(UPPER(MID($E97,FIND(" | ",$E97)+3,IFERROR(FIND(" | ",$E97,FIND(" | ",$E97)+3),LEN($E97)+1)-FIND(" | ",$E97)-3))),"")
A98: 53004 | B98: Hormigón MT | C98: 46150 | D98: 1113 | E98: Oro Gris - Hormigon Chivilcoy | G98: OPXX | H98: 9140 | I98: 3526487.8 | J98: 0 | K98: DESA | L98: Desarrollos | M98: CHIVILCOY | N98: CHIVILCOY 2171 | O98: 0 | P98: Oro Gris - Hormigon Chivilcoy | Q98: =IFERROR(TRIM(LEFT($E98,FIND(" | ",$E98)-1)),"") | R98: =IFERROR(TRIM(UPPER(MID($E98,FIND(" | ",$E98)+3,IFERROR(FIND(" | ",$E98,FIND(" | ",$E98)+3),LEN($E98)+1)-FIND(" | ",$E98)-3))),"")
A99: 53004 | B99: Hormigón MT | C99: 46150 | D99: 2844 | E99: HORMIGON MT - CUTULI HNOS S.A. | F99: CUTULI HNOS S.A. | G99: FCA3 | H99: 1500094672 | I99: 4015198.1 | J99: 0 | K99: DESA | L99: Desarrollos | M99: CHIVILCOY | N99: CHIVILCOY 2171 | O99: 0 | P99: HORMIGON MT - CUTULI HNOS S.A. | Q99: =IFERROR(TRIM(LEFT($E99,FIND(" | ",$E99)-1)),"") | R99: =IFERROR(TRIM(UPPER(MID($E99,FIND(" | ",$E99)+3,IFERROR(FIND(" | ",$E99,FIND(" | ",$E99)+3),LEN($E99)+1)-FIND(" | ",$E99)-3))),"")
A100: 53004 | B100: Hormigón MT | C100: 46150 | D100: 2846 | E100: HORMIGON MT - CUTULI HNOS S.A. | F100: CUTULI HNOS S.A. | G100: FCA3 | H100: 1500094634 | I100: 4540985.1 | J100: 0 | K100: DESA | L100: Desarrollos | M100: CHIVILCOY | N100: CHIVILCOY 2171 | O100: 0 | P100: HORMIGON MT - CUTULI HNOS S.A. | Q100: =IFERROR(TRIM(LEFT($E100,FIND(" | ",$E100)-1)),"") | R100: =IFERROR(TRIM(UPPER(MID($E100,FIND(" | ",$E100)+3,IFERROR(FIND(" | ",$E100,FIND(" | ",$E100)+3),LEN($E100)+1)-FIND(" | ",$E100)-3))),"")
...

Sheet 2_Quincenas
A1: Resumen Consolidado por Obra (Horas)
A2: Cargar horas por quincena: G=normales, H=extra 50%, I=extra 100%. F y costos K-O se calculan solos.
A3: Mes | B3: Período | C3: Obra | D3: Categoría | E3: Rubro | F3: Horas totales | G3: Horas normales | H3: Horas extra 50% | I3: Horas extra 100% | K3: Costo Hs. Normales | L3: Costo Hs. Extra 50% | M3: Costo Hs. Extra 100% | N3: Total | O3: Total Descontado
A4: 46023 | B4: 2Q | C4: CHIVILCOY | D4: OFICIAL | E4: Herrería MO | F4: =G4+H4+I4 -> 24 | G4: 24 | H4: 0 | I4: 0 | K4: =IFERROR(G4*INDEX('0_Jornales_MO'!$G$4:$J$21,MATCH(A4,'0_Jornales_MO'!$A$4:$A$21,0),MATCH(D4,{"ESPECIALIZADO","OFICIAL","MEDIO OFICIAL","AYUDANTE"},0)),"-") -> 293600.31 | L4: =IFERROR(H4*INDEX('0_Jornales_MO'!$G$4:$J$21,MATCH(A4,'0_Jornales_MO'!$A$4:$A$21,0),MATCH(D4,{"ESPECIALIZADO","OFICIAL","MEDIO OFICIAL","AYUDANTE"},0))*1.5,"-") -> 0 | M4: =IFERROR(I4*INDEX('0_Jornales_MO'!$G$4:$J$21,MATCH(A4,'0_Jornales_MO'!$A$4:$A$21,0),MATCH(D4,{"ESPECIALIZADO","OFICIAL","MEDIO OFICIAL","AYUDANTE"},0))*2,"-") -> 0 | N4: =IFERROR(SUM(K4:M4),"-") -> 293600.31 | O4: =IFERROR($N4 * SUMIF('0_Indice_CAC'!$A:$A,$A4,'0_Indice_CAC'!$D:$D),"-") -> 254381.05
A5: 46054 | B5: 1Q | C5: CHIVILCOY | D5: AYUDANTE | E5: Albañilería MO | F5: =G5+H5+I5 -> 40 | G5: 40 | H5: 0 | I5: 0 | K5: =IFERROR(G5*INDEX('0_Jornales_MO'!$G$4:$J$21,MATCH(A5,'0_Jornales_MO'!$A$4:$A$21,0),MATCH(D5,{"ESPECIALIZADO","OFICIAL","MEDIO OFICIAL","AYUDANTE"},0)),"-") -> 397453 | L5: =IFERROR(H5*INDEX('0_Jornales_MO'!$G$4:$J$21,MATCH(A5,'0_Jornales_MO'!$A$4:$A$21,0),MATCH(D5,{"ESPECIALIZADO","OFICIAL","MEDIO OFICIAL","AYUDANTE"},0))*1.5,"-") -> 0 | M5: =IFERROR(I5*INDEX('0_Jornales_MO'!$G$4:$J$21,MATCH(A5,'0_Jornales_MO'!$A$4:$A$21,0),MATCH(D5,{"ESPECIALIZADO","OFICIAL","MEDIO OFICIAL","AYUDANTE"},0))*2,"-") -> 0 | N5: =IFERROR(SUM(K5:M5),"-") -> 397453 | O5: =IFERROR($N5 * SUMIF('0_Indice_CAC'!$A:$A,$A5,'0_Indice_CAC'!$D:$D),"-") -> 340048.8
A6: 46082 | B6: 1Q | C6: CHIVILCOY | D6: MEDIO OFICIAL | E6: Eléctrico MO | F6: =G6+H6+I6 -> 8 | G6: 8 | H6: 0 | I6: 0 | K6: =IFERROR(G6*INDEX('0_Jornales_MO'!$G$4:$J$21,MATCH(A6,'0_Jornales_MO'!$A$4:$A$21,0),MATCH(D6,{"ESPECIALIZADO","OFICIAL","MEDIO OFICIAL","AYUDANTE"},0)),"-") -> 87100.47 | L6: =IFERROR(H6*INDEX('0_Jornales_MO'!$G$4:$J$21,MATCH(A6,'0_Jornales_MO'!$A$4:$A$21,0),MATCH(D6,{"ESPECIALIZADO","OFICIAL","MEDIO OFICIAL","AYUDANTE"},0))*1.5,"-") -> 0 | M6: =IFERROR(I6*INDEX('0_Jornales_MO'!$G$4:$J$21,MATCH(A6,'0_Jornales_MO'!$A$4:$A$21,0),MATCH(D6,{"ESPECIALIZADO","OFICIAL","MEDIO OFICIAL","AYUDANTE"},0))*2,"-") -> 0 | N6: =IFERROR(SUM(K6:M6),"-") -> 87100.47 | O6: =IFERROR($N6 * SUMIF('0_Indice_CAC'!$A:$A,$A6,'0_Indice_CAC'!$D:$D),"-") -> 73321.193
A7: 46082 | B7: 1Q | C7: CHIVILCOY | D7: ESPECIALIZADO | E7: Homigón MO | F7: =G7+H7+I7 -> 96 | G7: 84 | H7: 10 | I7: 2 | K7: =IFERROR(G7*INDEX('0_Jornales_MO'!$G$4:$J$21,MATCH(A7,'0_Jornales_MO'!$A$4:$A$21,0),MATCH(D7,{"ESPECIALIZADO","OFICIAL","MEDIO OFICIAL","AYUDANTE"},0)),"-") -> 1285680.8 | L7: =IFERROR(H7*INDEX('0_Jornales_MO'!$G$4:$J$21,MATCH(A7,'0_Jornales_MO'!$A$4:$A$21,0),MATCH(D7,{"ESPECIALIZADO","OFICIAL","MEDIO OFICIAL","AYUDANTE"},0))*1.5,"-") -> 229585.86 | M7: =IFERROR(I7*INDEX('0_Jornales_MO'!$G$4:$J$21,MATCH(A7,'0_Jornales_MO'!$A$4:$A$21,0),MATCH(D7,{"ESPECIALIZADO","OFICIAL","MEDIO OFICIAL","AYUDANTE"},0))*2,"-") -> 61222.895 | N7: =IFERROR(SUM(K7:M7),"-") -> 1576489.5 | O7: =IFERROR($N7 * SUMIF('0_Indice_CAC'!$A:$A,$A7,'0_Indice_CAC'!$D:$D),"-") -> 1327089.2
A8: 46082 | B8: 1Q | C8: CHIVILCOY | D8: OFICIAL | E8: Albañilería MO | F8: =G8+H8+I8 -> 66 | G8: 56 | H8: 6 | I8: 4 | K8: =IFERROR(G8*INDEX('0_Jornales_MO'!$G$4:$J$21,MATCH(A8,'0_Jornales_MO'!$A$4:$A$21,0),MATCH(D8,{"ESPECIALIZADO","OFICIAL","MEDIO OFICIAL","AYUDANTE"},0)),"-") -> 714203.49 | L8: =IFERROR(H8*INDEX('0_Jornales_MO'!$G$4:$J$21,MATCH(A8,'0_Jornales_MO'!$A$4:$A$21,0),MATCH(D8,{"ESPECIALIZADO","OFICIAL","MEDIO OFICIAL","AYUDANTE"},0))*1.5,"-") -> 114782.7 | M8: =IFERROR(I8*INDEX('0_Jornales_MO'!$G$4:$J$21,MATCH(A8,'0_Jornales_MO'!$A$4:$A$21,0),MATCH(D8,{"ESPECIALIZADO","OFICIAL","MEDIO OFICIAL","AYUDANTE"},0))*2,"-") -> 102029.07 | N8: =IFERROR(SUM(K8:M8),"-") -> 931015.26 | O8: =IFERROR($N8 * SUMIF('0_Indice_CAC'!$A:$A,$A8,'0_Indice_CAC'!$D:$D),"-") -> 783728.83
A9: 46082 | B9: 1Q | C9: CHIVILCOY | D9: OFICIAL | E9: Eléctrico MO | F9: =G9+H9+I9 -> 8 | G9: 8 | H9: 0 | I9: 0 | K9: =IFERROR(G9*INDEX('0_Jornales_MO'!$G$4:$J$21,MATCH(A9,'0_Jornales_MO'!$A$4:$A$21,0),MATCH(D9,{"ESPECIALIZADO","OFICIAL","MEDIO OFICIAL","AYUDANTE"},0)),"-") -> 102029.07 | L9: =IFERROR(H9*INDEX('0_Jornales_MO'!$G$4:$J$21,MATCH(A9,'0_Jornales_MO'!$A$4:$A$21,0),MATCH(D9,{"ESPECIALIZADO","OFICIAL","MEDIO OFICIAL","AYUDANTE"},0))*1.5,"-") -> 0 | M9: =IFERROR(I9*INDEX('0_Jornales_MO'!$G$4:$J$21,MATCH(A9,'0_Jornales_MO'!$A$4:$A$21,0),MATCH(D9,{"ESPECIALIZADO","OFICIAL","MEDIO OFICIAL","AYUDANTE"},0))*2,"-") -> 0 | N9: =IFERROR(SUM(K9:M9),"-") -> 102029.07 | O9: =IFERROR($N9 * SUMIF('0_Indice_CAC'!$A:$A,$A9,'0_Indice_CAC'!$D:$D),"-") -> 85888.091
A10: 46082 | B10: 1Q | C10: CHIVILCOY | D10: OFICIAL | E10: Homigón MO | F10: =G10+H10+I10 -> 90 | G10: 80 | H10: 10 | I10: 0 | K10: =IFERROR(G10*INDEX('0_Jornales_MO'!$G$4:$J$21,MATCH(A10,'0_Jornales_MO'!$A$4:$A$21,0),MATCH(D10,{"ESPECIALIZADO","OFICIAL","MEDIO OFICIAL","AYUDANTE"},0)),"-") -> 1020290.7 | L10: =IFERROR(H10*INDEX('0_Jornales_MO'!$G$4:$J$21,MATCH(A10,'0_Jornales_MO'!$A$4:$A$21,0),MATCH(D10,{"ESPECIALIZADO","OFICIAL","MEDIO OFICIAL","AYUDANTE"},0))*1.5,"-") -> 191304.51 | M10: =IFERROR(I10*INDEX('0_Jornales_MO'!$G$4:$J$21,MATCH(A10,'0_Jornales_MO'!$A$4:$A$21,0),MATCH(D10,{"ESPECIALIZADO","OFICIAL","MEDIO OFICIAL","AYUDANTE"},0))*2,"-") -> 0 | N10: =IFERROR(SUM(K10:M10),"-") -> 1211595.2 | O10: =IFERROR($N10 * SUMIF('0_Indice_CAC'!$A:$A,$A10,'0_Indice_CAC'!$D:$D),"-") -> 1019921.1
A11: 46082 | B11: 2Q | C11: CHIVILCOY | D11: MEDIO OFICIAL | E11: Eléctrico MO | F11: =G11+H11+I11 -> 16 | G11: 16 | H11: 0 | I11: 0 | K11: =IFERROR(G11*INDEX('0_Jornales_MO'!$G$4:$J$21,MATCH(A11,'0_Jornales_MO'!$A$4:$A$21,0),MATCH(D11,{"ESPECIALIZADO","OFICIAL","MEDIO OFICIAL","AYUDANTE"},0)),"-") -> 174200.94 | L11: =IFERROR(H11*INDEX('0_Jornales_MO'!$G$4:$J$21,MATCH(A11,'0_Jornales_MO'!$A$4:$A$21,0),MATCH(D11,{"ESPECIALIZADO","OFICIAL","MEDIO OFICIAL","AYUDANTE"},0))*1.5,"-") -> 0 | M11: =IFERROR(I11*INDEX('0_Jornales_MO'!$G$4:$J$21,MATCH(A11,'0_Jornales_MO'!$A$4:$A$21,0),MATCH(D11,{"ESPECIALIZADO","OFICIAL","MEDIO OFICIAL","AYUDANTE"},0))*2,"-") -> 0 | N11: =IFERROR(SUM(K11:M11),"-") -> 174200.94 | O11: =IFERROR($N11 * SUMIF('0_Indice_CAC'!$A:$A,$A11,'0_Indice_CAC'!$D:$D),"-") -> 146642.39
A12: 46082 | B12: 2Q | C12: CHIVILCOY | D12: ESPECIALIZADO | E12: Homigón MO | F12: =G12+H12+I12 -> 44 | G12: 40 | H12: 4 | I12: 0 | K12: =IFERROR(G12*INDEX('0_Jornales_MO'!$G$4:$J$21,MATCH(A12,'0_Jornales_MO'!$A$4:$A$21,0),MATCH(D12,{"ESPECIALIZADO","OFICIAL","MEDIO OFICIAL","AYUDANTE"},0)),"-") -> 612228.95 | L12: =IFERROR(H12*INDEX('0_Jornales_MO'!$G$4:$J$21,MATCH(A12,'0_Jornales_MO'!$A$4:$A$21,0),MATCH(D12,{"ESPECIALIZADO","OFICIAL","MEDIO OFICIAL","AYUDANTE"},0))*1.5,"-") -> 91834.342 | M12: =IFERROR(I12*INDEX('0_Jornales_MO'!$G$4:$J$21,MATCH(A12,'0_Jornales_MO'!$A$4:$A$21,0),MATCH(D12,{"ESPECIALIZADO","OFICIAL","MEDIO OFICIAL","AYUDANTE"},0))*2,"-") -> 0 | N12: =IFERROR(SUM(K12:M12),"-") -> 704063.29 | O12: =IFERROR($N12 * SUMIF('0_Indice_CAC'!$A:$A,$A12,'0_Indice_CAC'!$D:$D),"-") -> 592680.62
A13: 46082 | B13: 2Q | C13: CHIVILCOY | D13: OFICIAL | E13: Albañilería MO | F13: =G13+H13+I13 -> 93 | G13: 84 | H13: 9 | I13: 0 | K13: =IFERROR(G13*INDEX('0_Jornales_MO'!$G$4:$J$21,MATCH(A13,'0_Jornales_MO'!$A$4:$A$21,0),MATCH(D13,{"ESPECIALIZADO","OFICIAL","MEDIO OFICIAL","AYUDANTE"},0)),"-") -> 1071305.2 | L13: =IFERROR(H13*INDEX('0_Jornales_MO'!$G$4:$J$21,MATCH(A13,'0_Jornales_MO'!$A$4:$A$21,0),MATCH(D13,{"ESPECIALIZADO","OFICIAL","MEDIO OFICIAL","AYUDANTE"},0))*1.5,"-") -> 172174.06 | M13: =IFERROR(I13*INDEX('0_Jornales_MO'!$G$4:$J$21,MATCH(A13,'0_Jornales_MO'!$A$4:$A$21,0),MATCH(D13,{"ESPECIALIZADO","OFICIAL","MEDIO OFICIAL","AYUDANTE"},0))*2,"-") -> 0 | N13: =IFERROR(SUM(K13:M13),"-") -> 1243479.3 | O13: =IFERROR($N13 * SUMIF('0_Indice_CAC'!$A:$A,$A13,'0_Indice_CAC'!$D:$D),"-") -> 1046761.1
A14: 46082 | B14: 2Q | C14: CHIVILCOY | D14: OFICIAL | E14: Eléctrico MO | F14: =G14+H14+I14 -> 16 | G14: 16 | H14: 0 | I14: 0 | K14: =IFERROR(G14*INDEX('0_Jornales_MO'!$G$4:$J$21,MATCH(A14,'0_Jornales_MO'!$A$4:$A$21,0),MATCH(D14,{"ESPECIALIZADO","OFICIAL","MEDIO OFICIAL","AYUDANTE"},0)),"-") -> 204058.14 | L14: =IFERROR(H14*INDEX('0_Jornales_MO'!$G$4:$J$21,MATCH(A14,'0_Jornales_MO'!$A$4:$A$21,0),MATCH(D14,{"ESPECIALIZADO","OFICIAL","MEDIO OFICIAL","AYUDANTE"},0))*1.5,"-") -> 0 | M14: =IFERROR(I14*INDEX('0_Jornales_MO'!$G$4:$J$21,MATCH(A14,'0_Jornales_MO'!$A$4:$A$21,0),MATCH(D14,{"ESPECIALIZADO","OFICIAL","MEDIO OFICIAL","AYUDANTE"},0))*2,"-") -> 0 | N14: =IFERROR(SUM(K14:M14),"-") -> 204058.14 | O14: =IFERROR($N14 * SUMIF('0_Indice_CAC'!$A:$A,$A14,'0_Indice_CAC'!$D:$D),"-") -> 171776.18
A15: 46082 | B15: 2Q | C15: CHIVILCOY | D15: OFICIAL | E15: Herrería MO | F15: =G15+H15+I15 -> 8 | G15: 8 | H15: 0 | I15: 0 | K15: =IFERROR(G15*INDEX('0_Jornales_MO'!$G$4:$J$21,MATCH(A15,'0_Jornales_MO'!$A$4:$A$21,0),MATCH(D15,{"ESPECIALIZADO","OFICIAL","MEDIO OFICIAL","AYUDANTE"},0)),"-") -> 102029.07 | L15: =IFERROR(H15*INDEX('0_Jornales_MO'!$G$4:$J$21,MATCH(A15,'0_Jornales_MO'!$A$4:$A$21,0),MATCH(D15,{"ESPECIALIZADO","OFICIAL","MEDIO OFICIAL","AYUDANTE"},0))*1.5,"-") -> 0 | M15: =IFERROR(I15*INDEX('0_Jornales_MO'!$G$4:$J$21,MATCH(A15,'0_Jornales_MO'!$A$4:$A$21,0),MATCH(D15,{"ESPECIALIZADO","OFICIAL","MEDIO OFICIAL","AYUDANTE"},0))*2,"-") -> 0 | N15: =IFERROR(SUM(K15:M15),"-") -> 102029.07 | O15: =IFERROR($N15 * SUMIF('0_Indice_CAC'!$A:$A,$A15,'0_Indice_CAC'!$D:$D),"-") -> 85888.091
... A19: 46113 | B19: 1Q | C19: CHIVILCOY | D19: OFICIAL | E19: Homigón MO | F19: =G19+H19+I19 -> 88 | G19: 80 | H19: 8 | I19: 0 | K19: =IFERROR(G19*INDEX('0_Jornales_MO'!$G$4:$J$21,MATCH(A19,'0_Jornales_MO'!$A$4:$A$21,0),MATCH(D19,{"ESPECIALIZADO","OFICIAL","MEDIO OFICIAL","AYUDANTE"},0)),"-") -> 1069958.6 | L19: =IFERROR(H19*INDEX('0_Jornales_MO'!$G$4:$J$21,MATCH(A19,'0_Jornales_MO'!$A$4:$A$21,0),MATCH(D19,{"ESPECIALIZADO","OFICIAL","MEDIO OFICIAL","AYUDANTE"},0))*1.5,"-") -> 160493.79 | M19: =IFERROR(I19*INDEX('0_Jornales_MO'!$G$4:$J$21,MATCH(A19,'0_Jornales_MO'!$A$4:$A$21,0),MATCH(D19,{"ESPECIALIZADO","OFICIAL","MEDIO OFICIAL","AYUDANTE"},0))*2,"-") -> 0 | N19: =IFERROR(SUM(K19:M19),"-") -> 1230452.4 | O19: =IFERROR($N19 * SUMIF('0_Indice_CAC'!$A:$A,$A19,'0_Indice_CAC'!$D:$D),"-") -> 1016888.7

Sheet 2_Gastos_DirInd
A1: Fecha | B1: Tipo | C1: Concepto | D1: Monto
A2: 46082 | B2: Directo | C2: Coordinacion de obra | D2: 261562.8
A3: 46082 | B3: Directo | C3: Proyecto (50%) | D3: 1259725.3
A4: 46082 | B4: Indirecto | C4: Payroll - Administración | D4: 1109248.1
A5: 46082 | B5: Indirecto | C5: Payroll - Socios | D5: 625000.05
A6: 46113 | B6: Directo | C6: Coordinacion de obra | D6: 266794
A7: 46113 | B7: Directo | C7: Proyecto (50%) | D7: 1330802
A8: 46113 | B8: Indirecto | C8: Payroll - Administración | D8: 1261946.3
A9: 46113 | B9: Indirecto | C9: Payroll - Socios | D9: 625000.05
A10: 46143 | B10: Directo | C10: Coordinacion de obra | D10: 271596.2
A11: 46143 | B11: Directo | C11: Proyecto (50%) | D11: 994750.57
A12: 46143 | B12: Directo | C12: Vehiculo obra | D12: 469667.89
A13: 46143 | B13: Indirecto | C13: Payroll - Administración | D13: 1208735.9
A14: 46143 | B14: Indirecto | C14: Payroll - Socios | D14: 625000

Sheet 2_Subcontratos
A1: SUBCONTRATOS — MAESTRO DE CONTRATOS
A3: Contrato# | B3: Proveedor | C3: Rubro | D3: Descripción | E3: Monto Presup. | F3: Ajusta CAC | G3: % Anticipo | H3: Pagado BASE+ANT | I3: CAC pagado | J3: CS pagado | K3: Total pagado | L3: Saldo disponible | M3: % consumido | N3: Estado
A4: CH-SC-001 | B4: CLAUDIO BALACLAV | C4: Electricidad | D4: GESTOR ELECTRICO | E4: 1040000 | F4: NO | G4: 0 | H4: =SUMIFS('2_Movimientos'!$I:$I,'2_Movimientos'!$Q:$Q,$A4,'2_Movimientos'!$R:$R,"BASE")+SUMIFS('2_Movimientos'!$I:$I,'2_Movimientos'!$Q:$Q,$A4,'2_Movimientos'!$R:$R,"ANT") -> 1040000 | I4: =SUMIFS('2_Movimientos'!$I:$I,'2_Movimientos'!$Q:$Q,$A4,'2_Movimientos'!$R:$R,"CAC") -> 0 | J4: =SUMIFS('2_Movimientos'!$I:$I,'2_Movimientos'!$Q:$Q,$A4,'2_Movimientos'!$R:$R,"CS") -> 0 | K4: =H4+I4+J4 -> 1040000 | L4: =$E4-H4 -> 0 | M4: =IFERROR(H4/$E4,0) -> 1 | N4: =IF(L4<=0,"🔴 Sin saldo",IF(M4>=0.9,"🟠 <10% saldo","🟢 OK")) -> 🔴 Sin saldo
A5: CH-SC-002 | B5: ALEJANDRO ARDILES | C5: Agrimensura | D5: AGRIMENSOR | E5: 680000 | F5: NO | G5: 0 | H5: =SUMIFS('2_Movimientos'!$I:$I,'2_Movimientos'!$Q:$Q,$A5,'2_Movimientos'!$R:$R,"BASE")+SUMIFS('2_Movimientos'!$I:$I,'2_Movimientos'!$Q:$Q,$A5,'2_Movimientos'!$R:$R,"ANT") -> 730000 | I5: =SUMIFS('2_Movimientos'!$I:$I,'2_Movimientos'!$Q:$Q,$A5,'2_Movimientos'!$R:$R,"CAC") -> 0 | J5: =SUMIFS('2_Movimientos'!$I:$I,'2_Movimientos'!$Q:$Q,$A5,'2_Movimientos'!$R:$R,"CS") -> 0 | K5: =H5+I5+J5 -> 730000 | L5: =$E5-H5 -> -50000 | M5: =IFERROR(H5/$E5,0) -> 1.0735294 | N5: =IF(L5<=0,"🔴 Sin saldo",IF(M5>=0.9,"🟠 <10% saldo","🟢 OK")) -> 🔴 Sin saldo
A6: CH-SC-003 | B6: MICROPILOTES | C6: Hormigón | D6: MICROPILOTES | E6: 55937600 | F6: SI | G6: 0.3 | H6: =SUMIFS('2_Movimientos'!$I:$I,'2_Movimientos'!$Q:$Q,$A6,'2_Movimientos'!$R:$R,"BASE")+SUMIFS('2_Movimientos'!$I:$I,'2_Movimientos'!$Q:$Q,$A6,'2_Movimientos'!$R:$R,"ANT") -> 50757590 | I6: =SUMIFS('2_Movimientos'!$I:$I,'2_Movimientos'!$Q:$Q,$A6,'2_Movimientos'!$R:$R,"CAC") -> 1145169.6 | J6: =SUMIFS('2_Movimientos'!$I:$I,'2_Movimientos'!$Q:$Q,$A6,'2_Movimientos'!$R:$R,"CS") -> 0 | K6: =H6+I6+J6 -> 51902760 | L6: =$E6-H6 -> 5180009.6 | M6: =IFERROR(H6/$E6,0) -> 0.90739664 | N6: =IF(L6<=0,"🔴 Sin saldo",IF(M6>=0.9,"🟠 <10% saldo","🟢 OK")) -> 🟠 <10% saldo
A7: CH-SC-004 | B7: CELSI VIAL | C7: Excavación y Mov. de Suelos | D7: EXCAVACIÓN / VIAL | E7: 1310000 | F7: SI | G7: 0 | H7: =SUMIFS('2_Movimientos'!$I:$I,'2_Movimientos'!$Q:$Q,$A7,'2_Movimientos'!$R:$R,"BASE")+SUMIFS('2_Movimientos'!$I:$I,'2_Movimientos'!$Q:$Q,$A7,'2_Movimientos'!$R:$R,"ANT") -> 1310000 | I7: =SUMIFS('2_Movimientos'!$I:$I,'2_Movimientos'!$Q:$Q,$A7,'2_Movimientos'!$R:$R,"CAC") -> 0 | J7: =SUMIFS('2_Movimientos'!$I:$I,'2_Movimientos'!$Q:$Q,$A7,'2_Movimientos'!$R:$R,"CS") -> 0 | K7: =H7+I7+J7 -> 1310000 | L7: =$E7-H7 -> 0 | M7: =IFERROR(H7/$E7,0) -> 1 | N7: =IF(L7<=0,"🔴 Sin saldo",IF(M7>=0.9,"🟠 <10% saldo","🟢 OK")) -> 🔴 Sin saldo

Sheet _Listas
A1: RUBROS CANÓNICOS (Plan de Cuentas Tezamat — rama 53 OBRA + especiales) | B1: Código | C1: TIPOS | E1: VALIDACIÓN — rubros de tarea ∈ plan de cuentas | I1: CONCEPTOS GASTOS DIR/IND | J1: Tipo
A2: Preliminares | B2: 53001 | C2: MT | E2: Rubros fuera de plan — 1_Presupuesto (A/B/C/D) | F2: =SUMPRODUCT(('1_Presupuesto'!A4:A213<>"")*('1_Presupuesto'!A4:A213<>"-")*ISNA(MATCH('1_Presupuesto'!A4:A213,$A$2:$A$34,0)))+SUMPRODUCT(('1_Presupuesto'!B4:B213<>"")*('1_Presupuesto'!B4:B213<>"-")*ISNA(MATCH('1_Presupuesto'!B4:B213,$A$2:$A$34,0)))+SUMPRODUCT(('1_Presupuesto'!C4:C213<>"")*('1_Presupuesto'!C4:C213<>"-")*ISNA(MATCH('1_Presupuesto'!C4:C213,$A$2:$A$34,0)))+SUMPRODUCT(('1_Presupuesto'!D4:D213<>"")*('1_Presupuesto'!D4:D213<>"-")*ISNA(MATCH('1_Presupuesto'!D4:D213,$A$2:$A$34,0))) -> 0 | G2: =IF(F2=0,"✓","⚠") -> ✓ | I2: Oficina en obra (6x3 c/AA) | J2: Directo
A3: Demolición | B3: 53002 | C3: MO | E3: Rubros fuera de plan — 2_Quincenas (E) | F3: =SUMPRODUCT(('2_Quincenas'!E4:E72<>"")*('2_Quincenas'!E4:E72<>"-")*ISNA(MATCH('2_Quincenas'!E4:E72,$A$2:$A$34,0))) -> 0 | G3: =IF(F3=0,"✓","⚠") -> ✓ | I3: Obrador 6x3 s/AA | J3: Directo
A4: Movimiento de Suelos | B4: 53003 | I4: Pañol (6x3) | J4: Directo
A5: Hormigón MT | B5: 53004 | I5: Baños | J5: Directo
A6: Homigón MO | B6: 53005 | I6: HyS permanente | J6: Directo
A7: Metálica MT | B7: 53006 | I7: Energía de obra | J7: Directo
A8: Metálica MO | B8: 53007 | I8: Agua de obra | J8: Directo
A9: Albañilería MT | B9: 53008 | I9: Proyecto (50%) | J9: Directo
A10: Albañilería MO | B10: 53009 | I10: Coordinacion de obra | J10: Directo
A11: Durlock MT | B11: 53010 | I11: Sobrestante | J11: Directo
A12: Durlock MO | B12: 53011 | I12: Capataz | J12: Directo
A13: Aberturas | B13: 53012 | I13: Logistica | J13: Directo
A14: Revestimiento MT | B14: 53013 | I14: Vehiculo obra | J14: Directo
A15: Revestimiento MO | B15: 53014 | I15: Payroll - Socios | J15: Indirecto
... A17: Pintura MO | B17: 53016 | I17: Payroll - Administración | J17: Indirecto
A18: Sanitaria MT | B18: 53017
A19: Sanitaria MO | B19: 53018
A20: Eléctrico MT | B20: 53019
A21: Eléctrico MO | B21: 53020
A22: Provisiones | B22: 53021
A23: Gastos Generales | B23: 53022
A24: Varios Ferreteria | B24: 53023
A25: Termomecánica MT | B25: 53024
A26: Termomecánica MO | B26: 53025
A27: Seguridad e Higiene | B27: 53026
A28: Herrería MT | B28: 53027
A29: Herrería MO | B29: 53028
... A34: Supervisión de Obra MO | B34: 52209

Sheet Cert_OC_Cliente
A1: Obra | B1: ID OC | C1: Descripcion | D1: Presupuesto aprobado | E1: % anticipo | F1: Mes base CAC | G1: Indice base CAC | H1: % Blanco sugerido | I1: % Negro sugerido | J1: % desacopio sugerido | K1: % IVA sugerido | L1: Presupuesto | M1: Fecha anticipo
A2: CH 2171 | B2: CH-OC01 | C2: Pto 1 - Preliminares y estructura | D2: 600478155 | E2: 0.2 | F2: 45809 | G2: =_xlfn.XLOOKUP(F2,'0_Indice_CAC'!$A:$A,'0_Indice_CAC'!$B:$B) -> 16643.4 | H2: 0.65 | I2: 0.35 | J2: 0.1 | K2: 0.21 | L2: PTO 01 | M2: 46037
A3: CH 2171 | B3: CH-OC02 | C3: Pto 2 - Albanileria e Instalaciones | D3: 940144849 | E3: 0.4 | F3: 45809 | G3: =_xlfn.XLOOKUP(F3,'0_Indice_CAC'!$A:$A,'0_Indice_CAC'!$B:$B) -> 16643.4 | H3: 0.65 | I3: 0.35 | J3: 0.1 | K3: 0.21 | L3: PTO 02 | M3: 46188

Sheet Cert_App_Output
A1: Obra | B1: ID OC | C1: ID Certif | D1: Fecha | E1: Cod. tarea | F1: % anterior | G1: % actual | H1: % total | I1: PV total tarea | J1: $ base tarea (cert act.) | K1: Presupuesto | L1: Control vs Ppto | N1: rank_pend
A2: CH 2171 | B2: CH-OC01 | C2: CH-OC01-C01 | D2: 46142 | E2: 1.02 | F2: 0 | G2: 0.5 | H2: =F2+G2 -> 0.5 | I2: =SUMIFS('1_Presupuesto'!$V:$V,'1_Presupuesto'!$X:$X,K2,'1_Presupuesto'!$E:$E,E2) -> 1688715.2 | J2: =G2*I2 -> 844357.6 | K2: =_xlfn.XLOOKUP(B2,Cert_OC_Cliente!$B:$B,Cert_OC_Cliente!$L:$L) -> PTO 01 | L2: =IF($E2="","",IF(AND(ISNUMBER($I2),$H2<=1.0001),"✓","⚠")) -> ✓ | N2: =IF($C2="","",IF(AND(COUNTIF($C$2:$C2,$C2)=1,COUNTIF(Cert_Calculo!$A:$A,$C2)=0),MAX($N$1:N1)+1,""))
A3: CH 2171 | B3: CH-OC01 | C3: CH-OC01-C01 | D3: 46142 | E3: 1.04 | F3: 0 | G3: 1 | H3: =F3+G3 -> 1 | I3: =SUMIFS('1_Presupuesto'!$V:$V,'1_Presupuesto'!$X:$X,K3,'1_Presupuesto'!$E:$E,E3) -> 2902436.2 | J3: =G3*I3 -> 2902436.2 | K3: =_xlfn.XLOOKUP(B3,Cert_OC_Cliente!$B:$B,Cert_OC_Cliente!$L:$L) -> PTO 01 | L3: =IF($E3="","",IF(AND(ISNUMBER($I3),$H3<=1.0001),"✓","⚠")) -> ✓ | N3: =IF($C3="","",IF(AND(COUNTIF($C$2:$C3,$C3)=1,COUNTIF(Cert_Calculo!$A:$A,$C3)=0),MAX($N$1:N2)+1,""))
A4: CH 2171 | B4: CH-OC01 | C4: CH-OC01-C01 | D4: 46142 | E4: 1.05 | F4: 0 | G4: 0.75 | H4: =F4+G4 -> 0.75 | I4: =SUMIFS('1_Presupuesto'!$V:$V,'1_Presupuesto'!$X:$X,K4,'1_Presupuesto'!$E:$E,E4) -> 11833114 | J4: =G4*I4 -> 8874835.3 | K4: =_xlfn.XLOOKUP(B4,Cert_OC_Cliente!$B:$B,Cert_OC_Cliente!$L:$L) -> PTO 01 | L4: =IF($E4="","",IF(AND(ISNUMBER($I4),$H4<=1.0001),"✓","⚠")) -> ✓ | N4: =IF($C4="","",IF(AND(COUNTIF($C$2:$C4,$C4)=1,COUNTIF(Cert_Calculo!$A:$A,$C4)=0),MAX($N$1:N3)+1,""))
A5: CH 2171 | B5: CH-OC01 | C5: CH-OC01-C01 | D5: 46142 | E5: 1.06 | F5: 0 | G5: 0.25 | H5: =F5+G5 -> 0.25 | I5: =SUMIFS('1_Presupuesto'!$V:$V,'1_Presupuesto'!$X:$X,K5,'1_Presupuesto'!$E:$E,E5) -> 1410725.8 | J5: =G5*I5 -> 352681.45 | K5: =_xlfn.XLOOKUP(B5,Cert_OC_Cliente!$B:$B,Cert_OC_Cliente!$L:$L) -> PTO 01 | L5: =IF($E5="","",IF(AND(ISNUMBER($I5),$H5<=1.0001),"✓","⚠")) -> ✓ | N5: =IF($C5="","",IF(AND(COUNTIF($C$2:$C5,$C5)=1,COUNTIF(Cert_Calculo!$A:$A,$C5)=0),MAX($N$1:N4)+1,""))
A6: CH 2171 | B6: CH-OC01 | C6: CH-OC01-C01 | D6: 46142 | E6: 1.07 | F6: 0 | G6: 1 | H6: =F6+G6 -> 1 | I6: =SUMIFS('1_Presupuesto'!$V:$V,'1_Presupuesto'!$X:$X,K6,'1_Presupuesto'!$E:$E,E6) -> 2824238.6 | J6: =G6*I6 -> 2824238.6 | K6: =_xlfn.XLOOKUP(B6,Cert_OC_Cliente!$B:$B,Cert_OC_Cliente!$L:$L) -> PTO 01 | L6: =IF($E6="","",IF(AND(ISNUMBER($I6),$H6<=1.0001),"✓","⚠")) -> ✓ | N6: =IF($C6="","",IF(AND(COUNTIF($C$2:$C6,$C6)=1,COUNTIF(Cert_Calculo!$A:$A,$C6)=0),MAX($N$1:N5)+1,""))
A7: CH 2171 | B7: CH-OC01 | C7: CH-OC01-C01 | D7: 46142 | E7: 1.09 | F7: 0 | G7: 0.5 | H7: =F7+G7 -> 0.5 | I7: =SUMIFS('1_Presupuesto'!$V:$V,'1_Presupuesto'!$X:$X,K7,'1_Presupuesto'!$E:$E,E7) -> 655167.26 | J7: =G7*I7 -> 327583.63 | K7: =_xlfn.XLOOKUP(B7,Cert_OC_Cliente!$B:$B,Cert_OC_Cliente!$L:$L) -> PTO 01 | L7: =IF($E7="","",IF(AND(ISNUMBER($I7),$H7<=1.0001),"✓","⚠")) -> ✓ | N7: =IF($C7="","",IF(AND(COUNTIF($C$2:$C7,$C7)=1,COUNTIF(Cert_Calculo!$A:$A,$C7)=0),MAX($N$1:N6)+1,""))
A8: CH 2171 | B8: CH-OC01 | C8: CH-OC01-C01 | D8: 46142 | E8: 2.01 | F8: 0 | G8: 0.5 | H8: =F8+G8 -> 0.5 | I8: =SUMIFS('1_Presupuesto'!$V:$V,'1_Presupuesto'!$X:$X,K8,'1_Presupuesto'!$E:$E,E8) -> 8608321.9 | J8: =G8*I8 -> 4304160.9 | K8: =_xlfn.XLOOKUP(B8,Cert_OC_Cliente!$B:$B,Cert_OC_Cliente!$L:$L) -> PTO 01 | L8: =IF($E8="","",IF(AND(ISNUMBER($I8),$H8<=1.0001),"✓","⚠")) -> ✓ | N8: =IF($C8="","",IF(AND(COUNTIF($C$2:$C8,$C8)=1,COUNTIF(Cert_Calculo!$A:$A,$C8)=0),MAX($N$1:N7)+1,""))
A9: CH 2171 | B9: CH-OC01 | C9: CH-OC01-C01 | D9: 46142 | E9: 3.02 | F9: 0 | G9: 0.47 | H9: =F9+G9 -> 0.47 | I9: =SUMIFS('1_Presupuesto'!$V:$V,'1_Presupuesto'!$X:$X,K9,'1_Presupuesto'!$E:$E,E9) -> 65949869 | J9: =G9*I9 -> 30996438 | K9: =_xlfn.XLOOKUP(B9,Cert_OC_Cliente!$B:$B,Cert_OC_Cliente!$L:$L) -> PTO 01 | L9: =IF($E9="","",IF(AND(ISNUMBER($I9),$H9<=1.0001),"✓","⚠")) -> ✓ | N9: =IF($C9="","",IF(AND(COUNTIF($C$2:$C9,$C9)=1,COUNTIF(Cert_Calculo!$A:$A,$C9)=0),MAX($N$1:N8)+1,""))
A10: CH 2171 | B10: CH-OC01 | C10: CH-OC01-C01 | D10: 46142 | E10: 3.06 | F10: 0 | G10: 0.3 | H10: =F10+G10 -> 0.3 | I10: =SUMIFS('1_Presupuesto'!$V:$V,'1_Presupuesto'!$X:$X,K10,'1_Presupuesto'!$E:$E,E10) -> 9321934 | J10: =G10*I10 -> 2796580.2 | K10: =_xlfn.XLOOKUP(B10,Cert_OC_Cliente!$B:$B,Cert_OC_Cliente!$L:$L) -> PTO 01 | L10: =IF($E10="","",IF(AND(ISNUMBER($I10),$H10<=1.0001),"✓","⚠")) -> ✓ | N10: =IF($C10="","",IF(AND(COUNTIF($C$2:$C10,$C10)=1,COUNTIF(Cert_Calculo!$A:$A,$C10)=0),MAX($N$1:N9)+1,""))
A11: CH 2171 | B11: CH-OC01 | C11: CH-OC01-C01 | D11: 46142 | E11: 3.07 | F11: 0 | G11: 0.3 | H11: =F11+G11 -> 0.3 | I11: =SUMIFS('1_Presupuesto'!$V:$V,'1_Presupuesto'!$X:$X,K11,'1_Presupuesto'!$E:$E,E11) -> 10667660 | J11: =G11*I11 -> 3200298 | K11: =_xlfn.XLOOKUP(B11,Cert_OC_Cliente!$B:$B,Cert_OC_Cliente!$L:$L) -> PTO 01 | L11: =IF($E11="","",IF(AND(ISNUMBER($I11),$H11<=1.0001),"✓","⚠")) -> ✓ | N11: =IF($C11="","",IF(AND(COUNTIF($C$2:$C11,$C11)=1,COUNTIF(Cert_Calculo!$A:$A,$C11)=0),MAX($N$1:N10)+1,""))
A12: CH 2171 | B12: CH-OC01 | C12: CH-OC01-C01 | D12: 46142 | E12: 24.01 | F12: 0 | G12: 0.1 | H12: =F12+G12 -> 0.1 | I12: =SUMIFS('1_Presupuesto'!$V:$V,'1_Presupuesto'!$X:$X,K12,'1_Presupuesto'!$E:$E,E12) -> 10945143 | J12: =G12*I12 -> 1094514.3 | K12: =_xlfn.XLOOKUP(B12,Cert_OC_Cliente!$B:$B,Cert_OC_Cliente!$L:$L) -> PTO 01 | L12: =IF($E12="","",IF(AND(ISNUMBER($I12),$H12<=1.0001),"✓","⚠")) -> ✓ | N12: =IF($C12="","",IF(AND(COUNTIF($C$2:$C12,$C12)=1,COUNTIF(Cert_Calculo!$A:$A,$C12)=0),MAX($N$1:N11)+1,""))
A13: CH 2171 | B13: CH-OC01 | C13: CH-OC01-C01 | D13: 46142 | E13: 24.03 | F13: 0 | G13: 0.1 | H13: =F13+G13 -> 0.1 | I13: =SUMIFS('1_Presupuesto'!$V:$V,'1_Presupuesto'!$X:$X,K13,'1_Presupuesto'!$E:$E,E13) -> 4069401.4 | J13: =G13*I13 -> 406940.14 | K13: =_xlfn.XLOOKUP(B13,Cert_OC_Cliente!$B:$B,Cert_OC_Cliente!$L:$L) -> PTO 01 | L13: =IF($E13="","",IF(AND(ISNUMBER($I13),$H13<=1.0001),"✓","⚠")) -> ✓ | N13: =IF($C13="","",IF(AND(COUNTIF($C$2:$C13,$C13)=1,COUNTIF(Cert_Calculo!$A:$A,$C13)=0),MAX($N$1:N12)+1,""))
... A33: CH 2171 | B33: CH-OC01 | C33: CH-OC01-C02 | D33: 46175 | E33: 25.02 | F33: 0.1 | G33: 0.1 | H33: =F33+G33 -> 0.2 | I33: =SUMIFS('1_Presupuesto'!$V:$V,'1_Presupuesto'!$X:$X,K33,'1_Presupuesto'!$E:$E,E33) -> 6782335.6 | J33: =G33*I33 -> 678233.56 | K33: =_xlfn.XLOOKUP(B33,Cert_OC_Cliente!$B:$B,Cert_OC_Cliente!$L:$L) -> PTO 01 | L33: =IF($E33="","",IF(AND(ISNUMBER($I33),$H33<=1.0001),"✓","⚠")) -> ✓ | N33: =IF($C33="","",IF(AND(COUNTIF($C$2:$C33,$C33)=1,COUNTIF(Cert_Calculo!$A:$A,$C33)=0),MAX($N$1:N32)+1,""))

Sheet Cert_Calculo
A1: ID Certif | B1: ID Cert+Fact | C1: Tipo | D1: Obra | E1: ID OC | F1: Fecha | G1: $ base certif (total) | H1: % facturacion | I1: $ base de esta parte | J1: % desacopio | K1: $ desacopio | L1: $ base neta | M1: Indice base CAC | N1: Indice CAC a la fecha | O1: Ratio CAC | P1: $ CAC | Q1: $ base + CAC | R1: % IVA | S1: $ IVA | T1: $ Total certificacion | U1: USD MEP a la fecha | V1: U$ Total | X1: Control B/N suma 100% | Y1: Indice CAC override
A2: CH-OC01-C01 | B2: CH-OC01-C01-B | C2: Blanco | D2: =_xlfn.XLOOKUP(A2,Cert_App_Output!$C:$C,Cert_App_Output!$A:$A) -> CH 2171 | E2: =_xlfn.XLOOKUP(A2,Cert_App_Output!$C:$C,Cert_App_Output!$B:$B) -> CH-OC01 | F2: =_xlfn.XLOOKUP(A2,Cert_App_Output!$C:$C,Cert_App_Output!$D:$D) -> 46142 | G2: =SUMIFS(Cert_App_Output!$J:$J,Cert_App_Output!$C:$C,$A2) -> 64007081 | H2: 0.65 | I2: =$G2*H2 -> 41604603 | J2: =_xlfn.XLOOKUP($A2,Cert_Cabecera!$A:$A,Cert_Cabecera!$E:$E) -> 0.2 | K2: =-I2*J2 -> -8320920.5 | L2: =I2+K2 -> 33283682 | M2: =_xlfn.XLOOKUP($E2,Cert_OC_Cliente!$B:$B,Cert_OC_Cliente!$G:$G) -> 16643.4 | N2: =IF($Y2="",_xlfn.XLOOKUP(DATE(YEAR(F2),MONTH(F2),1),'0_Indice_CAC'!$A:$A,'0_Indice_CAC'!$B:$B),$Y2) -> 20138.793 | O2: =N2/M2 -> 1.2100168 | P2: =L2*(O2-1) -> 6990132 | Q2: =L2+P2 -> 40273814 | R2: 0.21 | S2: =Q2*R2 -> 8457501 | T2: =Q2+S2 -> 48731315 | U2: 1276 | V2: =IF(C2="Negro",T2/U2,"") | X2: =IF(ABS(SUMIFS($H:$H,$A:$A,$A2)-1)<0.0001,"✓","⚠ ≠100%") -> ✓
A3: CH-OC01-C01 | B3: CH-OC01-C01-N | C3: Negro | D3: =_xlfn.XLOOKUP(A3,Cert_App_Output!$C:$C,Cert_App_Output!$A:$A) -> CH 2171 | E3: =_xlfn.XLOOKUP(A3,Cert_App_Output!$C:$C,Cert_App_Output!$B:$B) -> CH-OC01 | F3: =_xlfn.XLOOKUP(A3,Cert_App_Output!$C:$C,Cert_App_Output!$D:$D) -> 46142 | G3: =SUMIFS(Cert_App_Output!$J:$J,Cert_App_Output!$C:$C,$A3) -> 64007081 | H3: 0.35 | I3: =$G3*H3 -> 22402478 | J3: =_xlfn.XLOOKUP($A3,Cert_Cabecera!$A:$A,Cert_Cabecera!$E:$E) -> 0.2 | K3: =-I3*J3 -> -4480495.7 | L3: =I3+K3 -> 17921983 | M3: =_xlfn.XLOOKUP($E3,Cert_OC_Cliente!$B:$B,Cert_OC_Cliente!$G:$G) -> 16643.4 | N3: =IF($Y3="",_xlfn.XLOOKUP(DATE(YEAR(F3),MONTH(F3),1),'0_Indice_CAC'!$A:$A,'0_Indice_CAC'!$B:$B),$Y3) -> 20138.793 | O3: =N3/M3 -> 1.2100168 | P3: =L3*(O3-1) -> 3763917.2 | Q3: =L3+P3 -> 21685900 | R3: 0 | S3: =Q3*R3 -> 0 | T3: =Q3+S3 -> 21685900 | U3: 1276 | V3: =IF(C3="Negro",T3/U3,"") -> 16995.219 | X3: =IF(ABS(SUMIFS($H:$H,$A:$A,$A3)-1)<0.0001,"✓","⚠ ≠100%") -> ✓
A4: CH-OC01-C02 | B4: CH-OC01-C02-B | C4: Blanco | D4: =_xlfn.XLOOKUP(A4,Cert_App_Output!$C:$C,Cert_App_Output!$A:$A) -> CH 2171 | E4: =_xlfn.XLOOKUP(A4,Cert_App_Output!$C:$C,Cert_App_Output!$B:$B) -> CH-OC01 | F4: =_xlfn.XLOOKUP(A4,Cert_App_Output!$C:$C,Cert_App_Output!$D:$D) -> 46175 | G4: =SUMIFS(Cert_App_Output!$J:$J,Cert_App_Output!$C:$C,$A4) -> 68905428 | H4: 0.65 | I4: =$G4*H4 -> 44788528 | J4: =_xlfn.XLOOKUP($A4,Cert_Cabecera!$A:$A,Cert_Cabecera!$E:$E) -> 0.2 | K4: =-I4*J4 -> -8957705.6 | L4: =I4+K4 -> 35830822 | M4: =_xlfn.XLOOKUP($E4,Cert_OC_Cliente!$B:$B,Cert_OC_Cliente!$G:$G) -> 16643.4 | N4: =IF($Y4="",_xlfn.XLOOKUP(DATE(YEAR(F4),MONTH(F4),1),'0_Indice_CAC'!$A:$A,'0_Indice_CAC'!$B:$B),$Y4) -> 20471.346 | O4: =N4/M4 -> 1.2299979 | P4: =L4*(O4-1) -> 8241012.1 | Q4: =L4+P4 -> 44071835 | R4: 0.21 | S4: =Q4*R4 -> 9255085.3 | T4: =Q4+S4 -> 53326920 | U4: 1276 | V4: =IF(C4="Negro",T4/U4,"") | X4: =IF(ABS(SUMIFS($H:$H,$A:$A,$A4)-1)<0.0001,"✓","⚠ ≠100%") -> ✓
A5: CH-OC01-C02 | B5: CH-OC01-C02-N | C5: Negro | D5: =_xlfn.XLOOKUP(A5,Cert_App_Output!$C:$C,Cert_App_Output!$A:$A) -> CH 2171 | E5: =_xlfn.XLOOKUP(A5,Cert_App_Output!$C:$C,Cert_App_Output!$B:$B) -> CH-OC01 | F5: =_xlfn.XLOOKUP(A5,Cert_App_Output!$C:$C,Cert_App_Output!$D:$D) -> 46175 | G5: =SUMIFS(Cert_App_Output!$J:$J,Cert_App_Output!$C:$C,$A5) -> 68905428 | H5: 0.35 | I5: =$G5*H5 -> 24116900 | J5: =_xlfn.XLOOKUP($A5,Cert_Cabecera!$A:$A,Cert_Cabecera!$E:$E) -> 0.2 | K5: =-I5*J5 -> -4823379.9 | L5: =I5+K5 -> 19293520 | M5: =_xlfn.XLOOKUP($E5,Cert_OC_Cliente!$B:$B,Cert_OC_Cliente!$G:$G) -> 16643.4 | N5: =IF($Y5="",_xlfn.XLOOKUP(DATE(YEAR(F5),MONTH(F5),1),'0_Indice_CAC'!$A:$A,'0_Indice_CAC'!$B:$B),$Y5) -> 20471.346 | O5: =N5/M5 -> 1.2299979 | P5: =L5*(O5-1) -> 4437468.1 | Q5: =L5+P5 -> 23730988 | R5: 0 | S5: =Q5*R5 -> 0 | T5: =Q5+S5 -> 23730988 | U5: 1276 | V5: =IF(C5="Negro",T5/U5,"") -> 18597.953 | X5: =IF(ABS(SUMIFS($H:$H,$A:$A,$A5)-1)<0.0001,"✓","⚠ ≠100%") -> ✓
A12: CH-OC01-ANT | B12: CH-OC01-ANT-B | C12: Blanco | D12: =_xlfn.XLOOKUP($E12,Cert_OC_Cliente!$B:$B,Cert_OC_Cliente!$A:$A) -> CH 2171 | E12: =LEFT(A12,LEN(A12)-4) -> CH-OC01 | F12: =_xlfn.XLOOKUP($E12,Cert_OC_Cliente!$B:$B,Cert_OC_Cliente!$M:$M) -> 46037 | G12: =_xlfn.XLOOKUP($E12,Cert_OC_Cliente!$B:$B,Cert_OC_Cliente!$D:$D)*_xlfn.XLOOKUP($E12,Cert_OC_Cliente!$B:$B,Cert_OC_Cliente!$E:$E) -> 120095631 | H12: 0.65 | I12: =$G12*H12 -> 78062160 | J12: =_xlfn.XLOOKUP($A12,Cert_Cabecera!$A:$A,Cert_Cabecera!$E:$E) -> 0 | K12: =-I12*J12 -> 0 | L12: =I12+K12 -> 78062160 | M12: =_xlfn.XLOOKUP($E12,Cert_OC_Cliente!$B:$B,Cert_OC_Cliente!$G:$G) -> 16643.4 | N12: =IF($Y12="",_xlfn.XLOOKUP(DATE(YEAR(F12),MONTH(F12),1),'0_Indice_CAC'!$A:$A,'0_Indice_CAC'!$B:$B),$Y12) -> 19209.4 | O12: =N12/M12 -> 1.1541752 | P12: =L12*(O12-1) -> 12035251 | Q12: =L12+P12 -> 90097412 | R12: 0.21 | S12: =Q12*R12 -> 18920456 | T12: =Q12+S12 -> 1.0901787e+08 | U12: 1276 | V12: =IF(C12="Negro",T12/U12,"") | X12: =IF(ABS(SUMIFS($H:$H,$A:$A,$A12)-1)<0.0001,"✓","⚠ ≠100%") -> ✓
A13: CH-OC01-ANT | B13: CH-OC01-ANT-N | C13: Negro | D13: =_xlfn.XLOOKUP($E13,Cert_OC_Cliente!$B:$B,Cert_OC_Cliente!$A:$A) -> CH 2171 | E13: =LEFT(A13,LEN(A13)-4) -> CH-OC01 | F13: =_xlfn.XLOOKUP($E13,Cert_OC_Cliente!$B:$B,Cert_OC_Cliente!$M:$M) -> 46037 | G13: =_xlfn.XLOOKUP($E13,Cert_OC_Cliente!$B:$B,Cert_OC_Cliente!$D:$D)*_xlfn.XLOOKUP($E13,Cert_OC_Cliente!$B:$B,Cert_OC_Cliente!$E:$E) -> 120095631 | H13: 0.35 | I13: =$G13*H13 -> 42033471 | J13: =_xlfn.XLOOKUP($A13,Cert_Cabecera!$A:$A,Cert_Cabecera!$E:$E) -> 0 | K13: =-I13*J13 -> 0 | L13: =I13+K13 -> 42033471 | M13: =_xlfn.XLOOKUP($E13,Cert_OC_Cliente!$B:$B,Cert_OC_Cliente!$G:$G) -> 16643.4 | N13: =IF($Y13="",_xlfn.XLOOKUP(DATE(YEAR(F13),MONTH(F13),1),'0_Indice_CAC'!$A:$A,'0_Indice_CAC'!$B:$B),$Y13) -> 19209.4 | O13: =N13/M13 -> 1.1541752 | P13: =L13*(O13-1) -> 6480520 | Q13: =L13+P13 -> 48513991 | R13: 0 | S13: =Q13*R13 -> 0 | T13: =Q13+S13 -> 48513991 | U13: 1276 | V13: =IF(C13="Negro",T13/U13,"") -> 38020.369 | X13: =IF(ABS(SUMIFS($H:$H,$A:$A,$A13)-1)<0.0001,"✓","⚠ ≠100%") -> ✓

Sheet Cert_Cabecera
A1: ID Certif | B1: ID OC | C1: Fecha | D1: $ base bruta certif. | E1: % desacopio (madre) | F1: $ desacopio | G1: Subtotal neto | H1: Chequeo
A2: CH-OC01-ANT | B2: =LEFT($A2,FIND("|",SUBSTITUTE($A2,"-","|",2))-1) -> CH-OC01 | C2: =IFERROR(_xlfn.XLOOKUP($A2,Cert_App_Output!$C:$C,Cert_App_Output!$D:$D),"") | D2: =SUMIFS(Cert_App_Output!$J:$J,Cert_App_Output!$C:$C,$A2) -> 0 | E2: 0 | F2: =$D2*$E2 -> 0 | G2: =$D2-$F2 -> 0 | H2: =IF(COUNTIF(Cert_Calculo!$A:$A,$A2)>0,"OK","FALTA en Calculo") -> OK
A3: CH-OC01-C01 | B3: =LEFT($A3,FIND("|",SUBSTITUTE($A3,"-","|",2))-1) -> CH-OC01 | C3: =IFERROR(_xlfn.XLOOKUP($A3,Cert_App_Output!$C:$C,Cert_App_Output!$D:$D),"") -> 46142 | D3: =SUMIFS(Cert_App_Output!$J:$J,Cert_App_Output!$C:$C,$A3) -> 64007081 | E3: 0.2 | F3: =$D3*$E3 -> 12801416 | G3: =$D3-$F3 -> 51205665 | H3: =IF(COUNTIF(Cert_Calculo!$A:$A,$A3)>0,"OK","FALTA en Calculo") -> OK
A4: CH-OC01-C02 | B4: =LEFT($A4,FIND("|",SUBSTITUTE($A4,"-","|",2))-1) -> CH-OC01 | C4: =IFERROR(_xlfn.XLOOKUP($A4,Cert_App_Output!$C:$C,Cert_App_Output!$D:$D),"") -> 46175 | D4: =SUMIFS(Cert_App_Output!$J:$J,Cert_App_Output!$C:$C,$A4) -> 68905428 | E4: 0.2 | F4: =$D4*$E4 -> 13781086 | G4: =$D4-$F4 -> 55124342 | H4: =IF(COUNTIF(Cert_Calculo!$A:$A,$A4)>0,"OK","FALTA en Calculo") -> OK

Sheet Cert_Facturacion
A1: id_cert_fact | B1: Comprobante | C1: Tipo | D1: monto | E1: moneda | F1: Fecha cobro | G1: monto_ars_equiv | H1: Estado conciliado | I1: $ certificado (control) | J1: Saldo a facturar | K1: id_factura | L1: TC cobro | M1: id_cert_madre | N1: id_OC | O1: Clase | P1: Retención | Q1: Haber conciliado

Sheet Cert_Control_OC
A1: ID OC | B1: Presupuesto | C1: Descripcion | D1: $ Contrato | E1: % Avance fisico | F1: $ Certificado | G1: $ Facturado | H1: $ Cobrado | I1: $ Anticipo certif. | J1: $ Avance s/certificar | K1: Saldo a facturar | L1: Saldo a cobrar | M1: Estado
A2: =Cert_OC_Cliente!B2 -> CH-OC01 | B2: =_xlfn.XLOOKUP($A2,Cert_OC_Cliente!$B:$B,Cert_OC_Cliente!$L:$L) -> PTO 01 | C2: =_xlfn.XLOOKUP($A2,Cert_OC_Cliente!$B:$B,Cert_OC_Cliente!$C:$C) -> Pto 1 - Preliminares y estructura | D2: =_xlfn.XLOOKUP($A2,Cert_OC_Cliente!$B:$B,Cert_OC_Cliente!$D:$D) -> 600478155 | E2: =SUMPRODUCT(('1_Presupuesto'!$X$5:$X$211=$B2)*'1_Presupuesto'!$Y$5:$Y$211*'1_Presupuesto'!$V$5:$V$211)/SUMPRODUCT(('1_Presupuesto'!$X$5:$X$211=$B2)*'1_Presupuesto'!$V$5:$V$211) -> 0.22134467 | F2: =SUMIFS(Cert_Calculo!$T:$T,Cert_Calculo!$E:$E,$A2) -> 3.0500698e+08 | G2: =SUMIFS(Cert_Facturacion!$G:$G,Cert_Facturacion!$A:$A,$A2&"-*") -> 0 | H2: =SUMIFS(Cert_Facturacion!$G:$G,Cert_Facturacion!$A:$A,$A2&"-*",Cert_Facturacion!$F:$F,">0") -> 0 | I2: =SUMIFS(Cert_Calculo!$T:$T,Cert_Calculo!$E:$E,$A2,Cert_Calculo!$B:$B,"*ANT*") -> 1.5753186e+08 | J2: =SUMIFS(Cert_App_Output!$J:$J,Cert_App_Output!$B:$B,$A2)-SUMIFS(Cert_Calculo!$I:$I,Cert_Calculo!$E:$E,$A2,Cert_Calculo!$B:$B,"<>*ANT*") -> 0 | K2: =F2-G2 -> 3.0500698e+08 | L2: =G2-H2 -> 0 | M2: =IF(J2>1000,"⚠ Certificar",IF(F2=0,"🔴 Sin iniciar",IF(K2>1000,"🟠 Por facturar",IF(L2>1000,"🔵 Por cobrar",IF(E2>=0.999,"🟢 Cerrada","🟡 En ejecucion"))))) -> 🟠 Por facturar
A3: =Cert_OC_Cliente!B3 -> CH-OC02 | B3: =_xlfn.XLOOKUP($A3,Cert_OC_Cliente!$B:$B,Cert_OC_Cliente!$L:$L) -> PTO 02 | C3: =_xlfn.XLOOKUP($A3,Cert_OC_Cliente!$B:$B,Cert_OC_Cliente!$C:$C) -> Pto 2 - Albanileria e Instalaciones | D3: =_xlfn.XLOOKUP($A3,Cert_OC_Cliente!$B:$B,Cert_OC_Cliente!$D:$D) -> 940144849 | E3: =SUMPRODUCT(('1_Presupuesto'!$X$5:$X$211=$B3)*'1_Presupuesto'!$Y$5:$Y$211*'1_Presupuesto'!$V$5:$V$211)/SUMPRODUCT(('1_Presupuesto'!$X$5:$X$211=$B3)*'1_Presupuesto'!$V$5:$V$211) -> 0 | F3: =SUMIFS(Cert_Calculo!$T:$T,Cert_Calculo!$E:$E,$A3) -> 0 | G3: =SUMIFS(Cert_Facturacion!$G:$G,Cert_Facturacion!$A:$A,$A3&"-*") -> 0 | H3: =SUMIFS(Cert_Facturacion!$G:$G,Cert_Facturacion!$A:$A,$A3&"-*",Cert_Facturacion!$F:$F,">0") -> 0 | I3: =SUMIFS(Cert_Calculo!$T:$T,Cert_Calculo!$E:$E,$A3,Cert_Calculo!$B:$B,"*ANT*") -> 0 | J3: =SUMIFS(Cert_App_Output!$J:$J,Cert_App_Output!$B:$B,$A3)-SUMIFS(Cert_Calculo!$I:$I,Cert_Calculo!$E:$E,$A3,Cert_Calculo!$B:$B,"<>*ANT*") -> 0 | K3: =F3-G3 -> 0 | L3: =G3-H3 -> 0 | M3: =IF(J3>1000,"⚠ Certificar",IF(F3=0,"🔴 Sin iniciar",IF(K3>1000,"🟠 Por facturar",IF(L3>1000,"🔵 Por cobrar",IF(E3>=0.999,"🟢 Cerrada","🟡 En ejecucion"))))) -> 🔴 Sin iniciar
A4: TOTAL | D4: =SUM(D2:D3) -> 1540623004 | E4: =SUMPRODUCT($D$2:$D$3,$E$2:$E$3)/SUM($D$2:$D$3) -> 0.086272007 | F4: =SUM(F2:F3) -> 3.0500698e+08 | G4: =SUM(G2:G3) -> 0 | H4: =SUM(H2:H3) -> 0 | I4: =SUM(I2:I3) -> 1.5753186e+08 | J4: =SUM(J2:J3) -> 0 | K4: =SUM(K2:K3) -> 3.0500698e+08 | L4: =SUM(L2:L3) -> 0
A6: ▌ PENDIENTES DE CERTIFICAR (avance cargado por el JO sin Cert_Calculo)
A7: # | B7: ID Certif | C7: ID OC | D7: Fecha | E7: $ base avance
A8: =IF($B8="","",1) | B8: =IFERROR(INDEX(Cert_App_Output!$C:$C,MATCH(1,Cert_App_Output!$N:$N,0)),"") | C8: =IF($B8="","",_xlfn.XLOOKUP($B8,Cert_App_Output!$C:$C,Cert_App_Output!$B:$B)) | D8: =IF($B8="","",_xlfn.XLOOKUP($B8,Cert_App_Output!$C:$C,Cert_App_Output!$D:$D)) | E8: =IF($B8="","",SUMIFS(Cert_App_Output!$J:$J,Cert_App_Output!$C:$C,$B8))
A9: =IF($B9="","",2) | B9: =IFERROR(INDEX(Cert_App_Output!$C:$C,MATCH(2,Cert_App_Output!$N:$N,0)),"") | C9: =IF($B9="","",_xlfn.XLOOKUP($B9,Cert_App_Output!$C:$C,Cert_App_Output!$B:$B)) | D9: =IF($B9="","",_xlfn.XLOOKUP($B9,Cert_App_Output!$C:$C,Cert_App_Output!$D:$D)) | E9: =IF($B9="","",SUMIFS(Cert_App_Output!$J:$J,Cert_App_Output!$C:$C,$B9))
A10: =IF($B10="","",3) | B10: =IFERROR(INDEX(Cert_App_Output!$C:$C,MATCH(3,Cert_App_Output!$N:$N,0)),"") | C10: =IF($B10="","",_xlfn.XLOOKUP($B10,Cert_App_Output!$C:$C,Cert_App_Output!$B:$B)) | D10: =IF($B10="","",_xlfn.XLOOKUP($B10,Cert_App_Output!$C:$C,Cert_App_Output!$D:$D)) | E10: =IF($B10="","",SUMIFS(Cert_App_Output!$J:$J,Cert_App_Output!$C:$C,$B10))
A11: =IF($B11="","",4) | B11: =IFERROR(INDEX(Cert_App_Output!$C:$C,MATCH(4,Cert_App_Output!$N:$N,0)),"") | C11: =IF($B11="","",_xlfn.XLOOKUP($B11,Cert_App_Output!$C:$C,Cert_App_Output!$B:$B)) | D11: =IF($B11="","",_xlfn.XLOOKUP($B11,Cert_App_Output!$C:$C,Cert_App_Output!$D:$D)) | E11: =IF($B11="","",SUMIFS(Cert_App_Output!$J:$J,Cert_App_Output!$C:$C,$B11))
A12: =IF($B12="","",5) | B12: =IFERROR(INDEX(Cert_App_Output!$C:$C,MATCH(5,Cert_App_Output!$N:$N,0)),"") | C12: =IF($B12="","",_xlfn.XLOOKUP($B12,Cert_App_Output!$C:$C,Cert_App_Output!$B:$B)) | D12: =IF($B12="","",_xlfn.XLOOKUP($B12,Cert_App_Output!$C:$C,Cert_App_Output!$D:$D)) | E12: =IF($B12="","",SUMIFS(Cert_App_Output!$J:$J,Cert_App_Output!$C:$C,$B12))
A13: =IF($B13="","",6) | B13: =IFERROR(INDEX(Cert_App_Output!$C:$C,MATCH(6,Cert_App_Output!$N:$N,0)),"") | C13: =IF($B13="","",_xlfn.XLOOKUP($B13,Cert_App_Output!$C:$C,Cert_App_Output!$B:$B)) | D13: =IF($B13="","",_xlfn.XLOOKUP($B13,Cert_App_Output!$C:$C,Cert_App_Output!$D:$D)) | E13: =IF($B13="","",SUMIFS(Cert_App_Output!$J:$J,Cert_App_Output!$C:$C,$B13))
A14: =IF($B14="","",7) | B14: =IFERROR(INDEX(Cert_App_Output!$C:$C,MATCH(7,Cert_App_Output!$N:$N,0)),"") | C14: =IF($B14="","",_xlfn.XLOOKUP($B14,Cert_App_Output!$C:$C,Cert_App_Output!$B:$B)) | D14: =IF($B14="","",_xlfn.XLOOKUP($B14,Cert_App_Output!$C:$C,Cert_App_Output!$D:$D)) | E14: =IF($B14="","",SUMIFS(Cert_App_Output!$J:$J,Cert_App_Output!$C:$C,$B14))
A15: =IF($B15="","",8) | B15: =IFERROR(INDEX(Cert_App_Output!$C:$C,MATCH(8,Cert_App_Output!$N:$N,0)),"") | C15: =IF($B15="","",_xlfn.XLOOKUP($B15,Cert_App_Output!$C:$C,Cert_App_Output!$B:$B)) | D15: =IF($B15="","",_xlfn.XLOOKUP($B15,Cert_App_Output!$C:$C,Cert_App_Output!$D:$D)) | E15: =IF($B15="","",SUMIFS(Cert_App_Output!$J:$J,Cert_App_Output!$C:$C,$B15))
A16: =IF($B16="","",9) | B16: =IFERROR(INDEX(Cert_App_Output!$C:$C,MATCH(9,Cert_App_Output!$N:$N,0)),"") | C16: =IF($B16="","",_xlfn.XLOOKUP($B16,Cert_App_Output!$C:$C,Cert_App_Output!$B:$B)) | D16: =IF($B16="","",_xlfn.XLOOKUP($B16,Cert_App_Output!$C:$C,Cert_App_Output!$D:$D)) | E16: =IF($B16="","",SUMIFS(Cert_App_Output!$J:$J,Cert_App_Output!$C:$C,$B16))
A17: =IF($B17="","",10) | B17: =IFERROR(INDEX(Cert_App_Output!$C:$C,MATCH(10,Cert_App_Output!$N:$N,0)),"") | C17: =IF($B17="","",_xlfn.XLOOKUP($B17,Cert_App_Output!$C:$C,Cert_App_Output!$B:$B)) | D17: =IF($B17="","",_xlfn.XLOOKUP($B17,Cert_App_Output!$C:$C,Cert_App_Output!$D:$D)) | E17: =IF($B17="","",SUMIFS(Cert_App_Output!$J:$J,Cert_App_Output!$C:$C,$B17))
A18: =IF($B18="","",11) | B18: =IFERROR(INDEX(Cert_App_Output!$C:$C,MATCH(11,Cert_App_Output!$N:$N,0)),"") | C18: =IF($B18="","",_xlfn.XLOOKUP($B18,Cert_App_Output!$C:$C,Cert_App_Output!$B:$B)) | D18: =IF($B18="","",_xlfn.XLOOKUP($B18,Cert_App_Output!$C:$C,Cert_App_Output!$D:$D)) | E18: =IF($B18="","",SUMIFS(Cert_App_Output!$J:$J,Cert_App_Output!$C:$C,$B18))
A19: =IF($B19="","",12) | B19: =IFERROR(INDEX(Cert_App_Output!$C:$C,MATCH(12,Cert_App_Output!$N:$N,0)),"") | C19: =IF($B19="","",_xlfn.XLOOKUP($B19,Cert_App_Output!$C:$C,Cert_App_Output!$B:$B)) | D19: =IF($B19="","",_xlfn.XLOOKUP($B19,Cert_App_Output!$C:$C,Cert_App_Output!$D:$D)) | E19: =IF($B19="","",SUMIFS(Cert_App_Output!$J:$J,Cert_App_Output!$C:$C,$B19))

Sheet CHANGELOG
A1: CHANGELOG — CH 2171 v8_3 (versión EGRESOS, prototipo estado futuro)
A3: Principio: rubros alineados al plan de cuentas de Tezamat; ID de SC + tipo de
A4: movimiento + CAC cargados de forma estandarizada en Tezamat (aguas arriba).
A5: El circuito de INGRESOS no se modifica en esta versión.
A7: CAMBIO | B7: DETALLE | C7: MOTIVO
A8: Rubros -> token único | B8: 1_Presupuesto A/B='X MT', C/D='X MO'; Hormigón MO='Homigón MO' (typo Tezamat) | C8: Plan de cuentas Tezamat trae rubro+tipo en un solo campo (Desc Cuenta)
A9: Cruce Control_Ppto por E | B9: SUMIFS sobre 2_Gastos!E (Desc Cuenta), no por col A reclasificada | C9: Elimina reclasificación manual; rubro viene alineado de origen
A10: 2_Gastos A,B,U,V,W obsoletas | B10: Vaciadas + header (OBSOLETA). NO borradas físicamente | C10: delete_cols corrompe refs por letra (openpyxl no reajusta). Vaciar es reference-safe
A11: 2_Gastos X repunteada | B11: X = ISNUMBER(MATCH(E, Control_Ppto rubros)) = 'rubro reconocido' | C11: Alimenta sanity check de gasto sin rubro
A12: 2_Quincenas col E | B12: Códigos ALBAMO/HORMIMO/ELECTMO/HERRERO -> tokens MO | C12: Alinea con Control (arregla bug: antes no matcheaba por usar códigos)
A13: Control_Ppto fórmulas unificadas | B13: 1 fórmula por columna (sin IF B=MT/MO); 27 tokens (17 canónicos + 10 extras debajo) | C13: Mantenibilidad; reconciliación exacta del presupuesto
A14: Sanity 'gasto sin rubro' | B14: Control_Ppto E102 = SUMIFS(2_Gastos!T, X=FALSE) | C14: Detecta cuentas Tezamat fuera del plan de rubros
A15: Subcontratos por Observaciones | B15: ID CH-SC-001; SUMIFS comodín '*ID TIPO*' (AVANCE/QUINCENA/CAC/CARGAS SOCIALES) | C15: ID vive en Observaciones (col H), no en col U
A16: Saldo SC | B16: Saldo = Presup - (AVANCE + QUINCENA); CAC y Cargas suman a Total pero no descuentan saldo | C16: Definición de proceso nueva
A17: CAC fila separada | B17: El CAC viene como fila aparte marcada en Observaciones; col S deflacta por fila (sin cambios) | C17: Ya no se deriva restando en la misma fila (V/W obsoletas)
A18: Hojas eliminadas | B18: 2_Pagos_Subc, 2_Pagos_Quincena_SC, 2_Certificaciones | C18: Deep-dive SC va al dashboard; certificaciones -> versión de ingresos
... A20: Maestros documentados | B20: 0_Indice_CAC / 0_Jornales_MO: nota de import futuro (sin vínculo vivo) | C20: Una sola actualización en maestro externo
A22: v8_4 (2026-06-18) — ingresos+egresos conviven en 2_Movimientos
A23: CAMBIO | B23: DETALLE | C23: MOTIVO
A24: Hoja 2_Gastos -> 2_Movimientos | B24: Refs de fórmula actualizadas en todo el libro | C24: Ingresos y egresos conviven; cashflow sale de acá
A25: Col Tipo Mov (Y) | B25: INGRESO si cuenta serie 4, EGRESO si no | C25: Separa ing/egr sin umbral mágico
A26: Col En 3_Control_Ppto (X) | B26: SÍ/NO si Desc Cuenta matchea rubro del control | C26: Identifica movimientos no contabilizados para revisar
A27: Col Observaciones original (Z) | B27: Guarda la observación previa (cómo se cargaba antes) | C27: Demo antes/después del proceso Tezamat
A28: Re-tag SC en Observaciones | B28: 10 pagos -> 'CH-SC-00X AVANCE'; 2 CAC desagregados como fila aparte | C28: Demostrar el tracking de SC por Observaciones
A29: Cash_Flow ingresos | B29: Fila 4 (cobros) = -Σ T INGRESO por mes; fila 6 egresos filtra EGRESO | C29: Ingresos del cashflow salen de 2_Movimientos
A30: Sanity egreso sin rubro | B30: E102 = SUMIFS(T, X=NO, Tipo=EGRESO) | C30: Excluye ingresos del flag
A32: v8_5 (2026-06-18) — quincenas como movimientos; fuente única de egresos
A33: CAMBIO | B33: DETALLE | C33: MOTIVO
A34: Quincenas -> 2_Movimientos | B34: 11 filas (Mes,Período,Rubro); monto pegado, D=cuenta del rubro, Obs 'QUINCENA aaaa-mm NQ' | C34: MO entra a Tezamat con cuenta y rubro; una sola fuente de egresos
A35: Control_Ppto fuente única | B35: E/F = SUMIFS(2_Movimientos S/T por rubro), sin término 2_Quincenas | C35: Elimina la doble fuente de costo de MO
A36: Cash_Flow sin doble conteo | B36: Fila 6 egresos = solo 2_Movimientos EGRESO por mes | C36: La quincena ya entra por movimientos
A37: 2_Quincenas = staging | B37: Se mantiene: 3_Control_Jornales lee sus horas (G/H/I) para horas vs ppto | C37: Sigue siendo origen del dato; no se elimina
A38: Pendiente nº cuenta | B38: Eléctrico MO y Herrería MO sin cuenta Tezamat (D vacía) | C38: Completar cuando Tezamat provea el plan de cuentas
A39: v8_7 (2026-06-19): rubros alineados al Plan de Cuentas oficial | B39: Recibido AING - Plan de Cuentas.xlsx. _Listas reescrito = rama 53 OBRA (con código) + Mov.Variables(52302) + Supervisión(52209). Renames/merges en 1_Presupuesto: Agrimensura MT/MO->Preliminares; Gastos Generales Obra MT/MO + Mantenimiento MO->Gastos Generales; Seguridad e Higiene MO->Seguridad e Higiene. Dropdowns (nombre definido RUBROS_PLAN) en 1_Presupuesto A:D y 2_Quincenas E. Sanity _Listas!F2/F3 (rubros de tarea ∈ plan = ✓). | C39: Plan de cuentas Tezamat = fuente de verdad de rubros (decisión Pedro 2026-06-18). Value-preserving: total presupuestado intacto (1.109.935.042,56); cruce presup↔gasto mejora (Gastos Generales y Seguridad e Higiene dejan de ser sin-ppto falsos).
