Workbook
Name GASTOS_CONCEPTO: _Listas!$I$2:$I$17
Name RUBROS_PLAN: _Listas!$A$2:$A$34

Sheet 0_CONFIG
A1: ▌ CONFIGURACIÓN DE OBRA — GDR 3760
A3: Nombre de obra | B3: Edificio GDR 3760 — García del Río 3760
A4: Estado | B4: En ejecución
A5: Fecha inicio | B5: 45689 | C5: presupuesto cerrado dic-2024
A6: Duración estimada (meses) | B6: 18 | C6: feb-2025 a ago-2026
A7: — ÍNDICE CAC —
A8: Mes base CAC | B8: 45627 | C8: fecha base del presupuesto
A9: Valor CAC base (INDEC) | B9: 15356.4 | C9: índice INDEC del mes base
A10: Mes corriente | B10: =INDEX('0_Indice_CAC'!$A$4:$A$33,MATCH(1E+300,'0_Indice_CAC'!$B$4:$B$33)) -> 46174 | C10: último mes cargado
A11: Ratio CAC corriente | B11: =MIN('0_Indice_CAC'!$D$4:$D$33) -> 0.79437459 | C11: ratio del mes más reciente
A12: — COEFICIENTE K —
A13: K (Gastos Generales y Beneficio) | B13: ='1_GGBB'!F67 -> 1.3327274 | C13: CRÍTICO: no modificar manualmente
A14: — PRESUPUESTO —
A15: Apertura fiscal | B15: B70 / N30 / GGN | C15: Blanco 70% c/IVA · Negro 30% · GGN
A16: Costo controlable (sin EQ) | B16: =SUMPRODUCT(('1_Presupuesto'!$J$5:$J$227+'1_Presupuesto'!$K$5:$K$227+'1_Presupuesto'!$L$5:$L$227)*'1_Presupuesto'!$I$5:$I$227) -> 9.9459803e+08 | C16: MT+MO/OTR+MO/ALB × Cant (EQ excluido)
A17: Costo total (con EQ) | B17: =SUMPRODUCT('1_Presupuesto'!$N$5:$N$227*'1_Presupuesto'!$I$5:$I$227) -> 1.0161736e+09 | C17: Costo Unit. × Cant
A18: Precio de venta total | B18: =SUMPRODUCT('1_Presupuesto'!$S$5:$S$227*'1_Presupuesto'!$I$5:$I$227) -> 1.3542825e+09 | C18: P Unit. × Cant
A19: Sanity check (debe ser 0) | B19: =+B17*B13-B18 -> 0 | C19: EQ no tiene rubro → excluido de costo controlable
A44: — RECONCILIACIÓN MENSUAL —
A45: Total egresos (2_Movimientos) | B45: =SUMPRODUCT('2_Movimientos'!$I$2:$I$1000,N(LEFT(TEXT('2_Movimientos'!$A$2:$A$1000,"0"),1)<>"4"))-SUMPRODUCT('2_Movimientos'!$J$2:$J$1000,N(LEFT(TEXT('2_Movimientos'!$A$2:$A$1000,"0"),1)<>"4")) -> 4.2322121e+08 | C45: ← se cablea en bloque 6 (crear 2_Movimientos)
A46: Total Tezamat (pegar mensual) | C46: input mensual
A47: Diferencia (debe ser 0) | B47: =B45-B46 -> 4.2322121e+08 | C47: se activa al cablear B45
A49: Tolerancia conciliación ($) | B49: 100
A52: — PENDIENTES (celdas amarillas) —
A53: 0_Indice_CAC col B | B53: CAC meses futuros sin publicar
A54: 0_Jornales_MO | B54: Tarifas UOCRA meses futuros
A55: 0_CONFIG!B46 | B55: Input mensual total Tezamat
A56: 1_Presupuesto cols A,B,C,D | B56: Asignación de rubros por ítem (4 cols input manual)

Sheet 0_Indice_CAC
A1: INDICE CAC
A3: Escala de tiempo | B3: Valores | C3: Previsión | D3: Indice
A4: 45627 | B4: 15356.4 | D4: =$B$4/B4 -> 1
A5: 45658 | B5: 15592.5 | D5: =$B$4/B5 -> 0.9848581
A6: 45689 | B6: 15852.4 | D6: =$B$4/B6 -> 0.96871136
A7: 45717 | B7: 15995.4 | D7: =$B$4/B7 -> 0.96005101
A8: 45748 | B8: 16253.5 | D8: =$B$4/B8 -> 0.94480573
A9: 45778 | B9: 16521.3 | D9: =$B$4/B9 -> 0.92949102
A10: 45809 | B10: 16643.4 | D10: =$B$4/B10 -> 0.92267205
A11: 45839 | B11: 16939.5 | D11: =$B$4/B11 -> 0.90654388
A12: 45870 | B12: 17187.6 | D12: =$B$4/B12 -> 0.89345807
A13: 45901 | B13: 17762.3 | D13: =$B$4/B13 -> 0.8645502
A14: 45931 | B14: 18172.8 | D14: =$B$4/B14 -> 0.84502113
A15: 45962 | B15: 18534.9 | D15: =$B$4/B15 -> 0.8285127
A16: 45992 | B16: 18993.891 | C16: 18993.891 | D16: =$B$4/B16 -> 0.80849152
A17: 46023 | B17: 19331.434 | C17: 19331.434 | D17: =$B$4/B17 -> 0.79437459
A18: 46054 | B18: 19331.434 | D18: =$B$4/B18 -> 0.79437459
A19: 46082 | B19: 19331.434 | D19: =$B$4/B19 -> 0.79437459
A20: 46113 | B20: 19331.434 | D20: =$B$4/B20 -> 0.79437459
A21: 46143 | B21: 19331.434 | D21: =$B$4/B21 -> 0.79437459
A22: 46174 | B22: 19331.434 | D22: =$B$4/B22 -> 0.79437459

Sheet 0_Jornales_MO
A1: SECCIÓN A — TABLA DE TARIFAS POR CATEGORÍA (Costo por Día/Quincena)
A3: PERÍODO | B3: ESPEC. ($/día) | C3: OFICIAL ($/día) | D3: 1/2 OFICIAL ($/día) | E3: AYUDANTE ($/día) | G3: ESPEC. ($/hr) | H3: OFICIAL ($/día) | I3: 1/2 OFICIAL ($/día) | J3: AYUDANTE ($/día)
A4: 45627 | B4: 85927.1 | C4: 76955.08 | D4: 65493.07 | E4: 60860.58 | G4: =+B4/8 -> 10740.888 | H4: =+C4/8 -> 9619.385 | I4: =+D4/8 -> 8186.6337 | J4: =+E4/8 -> 7607.5725
A5: 45658 | B5: 87384 | C5: 78375 | D5: 66853 | E5: 61892 | G5: =+B5/8 -> 10923 | H5: =+C5/8 -> 9796.875 | I5: =+D5/8 -> 8356.625 | J5: =+E5/8 -> 7736.5
A6: 45689 | B6: 89383 | C6: 80395 | D6: 68472 | E6: 63382 | G6: =+B6/8 -> 11172.875 | H6: =+C6/8 -> 10049.375 | I6: =+D6/8 -> 8559 | J6: =+E6/8 -> 7922.75
A7: 45717 | B7: 91464 | C7: 82269 | D7: 70296 | E7: 65595 | G7: =+B7/8 -> 11433 | H7: =+C7/8 -> 10283.625 | I7: =+D7/8 -> 8787 | J7: =+E7/8 -> 8199.375
A8: 45778 | B8: 93235.367 | C8: 83766.388 | D8: 71410.817 | E8: 66568.094 | G8: =+B8/8 -> 11654.421 | H8: =+C8/8 -> 10470.798 | I8: =+D8/8 -> 8926.3521 | J8: =+E8/8 -> 8321.0117
A9: 45809 | B9: 94177.138 | C9: 84612.513 | D9: 72132.138 | E9: 67240.499 | G9: =+B9/8 -> 11772.142 | H9: =+C9/8 -> 10576.564 | I9: =+D9/8 -> 9016.5173 | J9: =+E9/8 -> 8405.0624
A10: 45839 | B10: 95080 | C10: 85425 | D10: 72871 | E10: 67908 | G10: =+B10/8 -> 11885 | H10: =+C10/8 -> 10678.125 | I10: =+D10/8 -> 9108.875 | J10: =+E10/8 -> 8488.5
A11: 45870 | B11: 95889.2 | C11: 86356.18 | D11: 73781.11 | E11: 68935.35 | G11: =+B11/8 -> 11986.15 | H11: =+C11/8 -> 10794.522 | I11: =+D11/8 -> 9222.6388 | J11: =+E11/8 -> 8616.9188
A12: 45901 | B12: 106516.02 | C12: 88649.808 | D12: 75758.192 | E12: 71041.119 | G12: =+B12/8 -> 13314.502 | H12: =+C12/8 -> 11081.226 | I12: =+D12/8 -> 9469.774 | J12: =+E12/8 -> 8880.1398
A13: 45931 | B13: 106864.21 | C13: 88971.073 | D13: 76032.176 | E13: 71292.271 | G13: =+B13/8 -> 13358.026 | H13: =+C13/8 -> 11121.384 | I13: =+D13/8 -> 9504.0221 | J13: =+E13/8 -> 8911.5339
A14: 45962 | B14: 109621.11 | C14: 91252.851 | D14: 77612.118 | E14: 72486.683 | G14: =+B14/8 -> 13702.638 | H14: =+C14/8 -> 11406.606 | I14: =+D14/8 -> 9701.5148 | J14: =+E14/8 -> 9060.8353
A15: 45992 | B15: 113865.18 | C15: 95196.927 | D15: 81356.194 | E15: 76230.759 | G15: =+B15/8 -> 14233.148 | H15: =+C15/8 -> 11899.616 | I15: =+D15/8 -> 10169.524 | J15: =+E15/8 -> 9528.8449
... A21: 46174 | B21: 122445.79 | C21: 102029.07 | D21: 87100.47 | E21: 81453.719 | G21: =+B21/8 -> 15305.724 | H21: =+C21/8 -> 12753.633 | I21: =+D21/8 -> 10887.559 | J21: =+E21/8 -> 10181.715

Sheet 1_Presupuesto
A1: PRESUPUESTO OBRA CIVIL y CERTIFICACIONES DE AVANCE
A3: Rubro MT | B3: Rubro MT/Prov | C3: Rubro MO/OTR | D3: Rubro MO/ALB | E3: Cod. Ítem | F3: Estado | G3: Descripción | H3: U | I3: Cant | J3: MT | K3: MO/OTR | L3: MO/ALB | M3: EQ | N3: Costo Unit. | O3: MT | P3: MO/OTR | Q3: MO/ALB | R3: EQ | S3: P.Unit | T3: Margen | U3: Costo total | V3: PV subtotal | W3: Etapa | X3: Presupuesto | Y3: % Acum Tot
E4: 1 | G4: TAREAS PRELIMINARES | W4: TAREAS PRELIMINARES
A5: - | B5: - | C5: - | D5: - | E5: 1.01 | F5: OK | G5: Limpieza y preparación del terreno - No cotiza | H5: gl | I5: 1 | J5: 0 | K5: 0 | L5: 0 | M5: 0 | N5: =SUM(J5:M5) -> 0 | O5: =IF($N5=0,$S5,J5/$N5*$S5) -> 0 | P5: =IF($N5=0,0,K5/$N5*$S5) -> 0 | Q5: =IF($N5=0,0,L5/$N5*$S5) -> 0 | R5: =IF($N5=0,0,M5/$N5*$S5) -> 0 | S5: 0 | T5: =IFERROR(S5/N5,"") | U5: =N5*I5 -> 0 | V5: =S5*I5 -> 0 | W5: TAREAS PRELIMINARES | X5: PTO 01 | Y5: =SUMIFS(Cert_App_Output!$G:$G,Cert_App_Output!$E:$E,$E5,Cert_App_Output!$K:$K,$X5) -> 0
A6: Preliminares | B6: - | C6: Preliminares | D6: Preliminares | E6: 1.02 | F6: OK | G6: Topógrafo - Visita de obra replanteo | H6: gl | I6: 3 | J6: 25000 | K6: 198736.84 | L6: 60860.581 | M6: 4268.9614 | N6: =SUM(J6:M6) -> 288866.39 | O6: =IF($N6=0,$S6,J6/$N6*$S6) -> 33318.186 | P6: =IF($N6=0,0,K6/$N6*$S6) -> 264862.04 | Q6: =IF($N6=0,0,L6/$N6*$S6) -> 81110.565 | R6: =IF($N6=0,0,M6/$N6*$S6) -> 5689.3619 | S6: 384980.16 | T6: =IFERROR(S6/N6,"") -> 1.3327274 | U6: =N6*I6 -> 866599.16 | V6: =S6*I6 -> 1154940.5 | W6: TAREAS PRELIMINARES | X6: PTO 01 | Y6: =SUMIFS(Cert_App_Output!$G:$G,Cert_App_Output!$E:$E,$E6,Cert_App_Output!$K:$K,$X6) -> 1
A7: - | B7: - | C7: - | D7: - | E7: 1.03 | F7: OK | G7: Cartel de Obra - No cotiza | H7: gl | I7: 1 | J7: 0 | K7: 0 | L7: 0 | M7: 0 | N7: =SUM(J7:M7) -> 0 | O7: =IF($N7=0,$S7,J7/$N7*$S7) -> 0 | P7: =IF($N7=0,0,K7/$N7*$S7) -> 0 | Q7: =IF($N7=0,0,L7/$N7*$S7) -> 0 | R7: =IF($N7=0,0,M7/$N7*$S7) -> 0 | S7: 0 | T7: =IFERROR(S7/N7,"") | U7: =N7*I7 -> 0 | V7: =S7*I7 -> 0 | W7: TAREAS PRELIMINARES | X7: PTO 01 | Y7: =SUMIFS(Cert_App_Output!$G:$G,Cert_App_Output!$E:$E,$E7,Cert_App_Output!$K:$K,$X7) -> 0
A8: Preliminares | B8: - | C8: - | D8: Preliminares | E8: 1.04 | F8: OK | G8: Cerco de obra perimetral - En chapa C25 + Concertina + Porton corredizo | H8: ml | I8: 10 | J8: 88330.703 | K8: 0 | L8: 101654.37 | M8: 2849.776 | N8: =SUM(J8:M8) -> 192834.84 | O8: =IF($N8=0,$S8,J8/$N8*$S8) -> 117720.75 | P8: =IF($N8=0,0,K8/$N8*$S8) -> 0 | Q8: =IF($N8=0,0,L8/$N8*$S8) -> 135477.56 | R8: =IF($N8=0,0,M8/$N8*$S8) -> 3797.9747 | S8: 256996.29 | T8: =IFERROR(S8/N8,"") -> 1.3327274 | U8: =N8*I8 -> 1928348.4 | V8: =S8*I8 -> 2569962.9 | W8: TAREAS PRELIMINARES | X8: PTO 01 | Y8: =SUMIFS(Cert_App_Output!$G:$G,Cert_App_Output!$E:$E,$E8,Cert_App_Output!$K:$K,$X8) -> 1
A9: Preliminares | B9: - | C9: Preliminares | D9: Preliminares | E9: 1.05 | F9: OK | G9: Obrador, pañol y ducha. | H9: gl | I9: 1 | J9: 2078824.7 | K9: 750000 | L9: 4424962.9 | M9: 108806.81 | N9: =SUM(J9:M9) -> 7362594.4 | O9: =IF($N9=0,$S9,J9/$N9*$S9) -> 2770506.7 | P9: =IF($N9=0,0,K9/$N9*$S9) -> 999545.57 | Q9: =IF($N9=0,0,L9/$N9*$S9) -> 5897269.4 | R9: =IF($N9=0,0,M9/$N9*$S9) -> 145009.82 | S9: 9812331.4 | T9: =IFERROR(S9/N9,"") -> 1.3327274 | U9: =N9*I9 -> 7362594.4 | V9: =S9*I9 -> 9812331.4 | W9: TAREAS PRELIMINARES | X9: PTO 01 | Y9: =SUMIFS(Cert_App_Output!$G:$G,Cert_App_Output!$E:$E,$E9,Cert_App_Output!$K:$K,$X9) -> 1
A10: Gastos Generales | B10: - | C10: Gastos Generales | D10: Preliminares | E10: 1.06 | F10: OK | G10: Alquiler de baños quimicos y duchas portatiles | H10: mes | I10: 4 | J10: 0 | K10: 318994.12 | L10: 13291.422 | M10: 0 | N10: =SUM(J10:M10) -> 332285.54 | O10: =IF($N10=0,$S10,J10/$N10*$S10) -> 0 | P10: =IF($N10=0,0,K10/$N10*$S10) -> 425132.21 | Q10: =IF($N10=0,0,L10/$N10*$S10) -> 17713.842 | R10: =IF($N10=0,0,M10/$N10*$S10) -> 0 | S10: 442846.06 | T10: =IFERROR(S10/N10,"") -> 1.3327274 | U10: =N10*I10 -> 1329142.2 | V10: =S10*I10 -> 1771384.2 | W10: TAREAS PRELIMINARES | X10: PTO 01 | Y10: =SUMIFS(Cert_App_Output!$G:$G,Cert_App_Output!$E:$E,$E10,Cert_App_Output!$K:$K,$X10) -> 1
A11: Preliminares | B11: - | C11: - | D11: Preliminares | E11: 1.07 | F11: OK | G11: Conexión pilar y luz de obra + Tablero de obra | H11: gl | I11: 1 | J11: 1090000 | K11: 0 | L11: 601395.67 | M11: 25370.935 | N11: =SUM(J11:M11) -> 1716766.6 | O11: =IF($N11=0,$S11,J11/$N11*$S11) -> 1452672.9 | P11: =IF($N11=0,0,K11/$N11*$S11) -> 0 | Q11: =IF($N11=0,0,L11/$N11*$S11) -> 801496.51 | R11: =IF($N11=0,0,M11/$N11*$S11) -> 33812.541 | S11: 2287981.9 | T11: =IFERROR(S11/N11,"") -> 1.3327274 | U11: =N11*I11 -> 1716766.6 | V11: =S11*I11 -> 2287981.9 | W11: TAREAS PRELIMINARES | X11: PTO 01 | Y11: =SUMIFS(Cert_App_Output!$G:$G,Cert_App_Output!$E:$E,$E11,Cert_App_Output!$K:$K,$X11) -> 1
A12: Preliminares | B12: - | C12: - | D12: Preliminares | E12: 1.08 | F12: OK | G12: Conexión agua de obra, tanque + bomba | H12: gl | I12: 1 | J12: 685200 | K12: 0 | L12: 651528.71 | M12: 20050.931 | N12: =SUM(J12:M12) -> 1356779.6 | O12: =IF($N12=0,$S12,J12/$N12*$S12) -> 913184.83 | P12: =IF($N12=0,0,K12/$N12*$S12) -> 0 | Q12: =IF($N12=0,0,L12/$N12*$S12) -> 868310.18 | R12: =IF($N12=0,0,M12/$N12*$S12) -> 26722.425 | S12: 1808217.4 | T12: =IFERROR(S12/N12,"") -> 1.3327274 | U12: =N12*I12 -> 1356779.6 | V12: =S12*I12 -> 1808217.4 | W12: TAREAS PRELIMINARES | X12: PTO 01 | Y12: =SUMIFS(Cert_App_Output!$G:$G,Cert_App_Output!$E:$E,$E12,Cert_App_Output!$K:$K,$X12) -> 1
A13: Preliminares | B13: - | C13: Preliminares | D13: - | E13: 1.09 | F13: OK | G13: Tramite luz de obra, certificado luz de obra (2) y medición PAT | H13: gl | I13: 1 | J13: 0 | K13: 362691.09 | L13: 0 | M13: 0 | N13: =SUM(J13:M13) -> 362691.09 | O13: =IF($N13=0,$S13,J13/$N13*$S13) -> 0 | P13: =IF($N13=0,0,K13/$N13*$S13) -> 483368.36 | Q13: =IF($N13=0,0,L13/$N13*$S13) -> 0 | R13: =IF($N13=0,0,M13/$N13*$S13) -> 0 | S13: 483368.36 | T13: =IFERROR(S13/N13,"") -> 1.3327274 | U13: =N13*I13 -> 362691.09 | V13: =S13*I13 -> 483368.36 | W13: TAREAS PRELIMINARES | X13: PTO 01 | Y13: =SUMIFS(Cert_App_Output!$G:$G,Cert_App_Output!$E:$E,$E13,Cert_App_Output!$K:$K,$X13) -> 1
A14: - | B14: - | C14: - | D14: - | E14: 2 | G14: MOVIMIENTO DE TIERRA, COMPACTACION Y RELLENO | W14: MOVIMIENTO DE TIERRA, COMPACTACION Y RELLENO | X14: PTO 01
A15: Movimiento de Suelos | B15: - | C15: Movimiento de Suelos | D15: Homigón MO | E15: 2.01 | F15: OK | G15: Excavación a maquina para submuración, subsuelo y fundaciones | H15: m3 | I15: 308 | J15: 0 | K15: 33000 | L15: 6520.7765 | M15: 97.811648 | N15: =SUM(J15:M15) -> 39618.588 | O15: =IF($N15=0,$S15,J15/$N15*$S15) -> 0 | P15: =IF($N15=0,0,K15/$N15*$S15) -> 43980.005 | Q15: =IF($N15=0,0,L15/$N15*$S15) -> 8690.4177 | R15: =IF($N15=0,0,M15/$N15*$S15) -> 130.35627 | S15: 52800.779 | T15: =IFERROR(S15/N15,"") -> 1.3327274 | U15: =N15*I15 -> 12202525 | V15: =S15*I15 -> 16262640 | W15: MOVIMIENTO DE TIERRA, COMPACTACION Y RELLENO | X15: PTO 01 | Y15: =SUMIFS(Cert_App_Output!$G:$G,Cert_App_Output!$E:$E,$E15,Cert_App_Output!$K:$K,$X15) -> 1
A16: Movimiento de Suelos | B16: - | C16: Movimiento de Suelos | D16: Preliminares | E16: 2.02 | F16: OK | G16: Perfilado manual de bases. Relleno y compactación de pozos | H16: gl | I16: 1 | J16: 105000 | K16: 455000 | L16: 8033596.7 | M16: 128903.95 | N16: =SUM(J16:M16) -> 8722500.6 | O16: =IF($N16=0,$S16,J16/$N16*$S16) -> 139936.38 | P16: =IF($N16=0,0,K16/$N16*$S16) -> 606390.98 | Q16: =IF($N16=0,0,L16/$N16*$S16) -> 10706595 | R16: =IF($N16=0,0,M16/$N16*$S16) -> 171793.83 | S16: 11624716 | T16: =IFERROR(S16/N16,"") -> 1.3327274 | U16: =N16*I16 -> 8722500.6 | V16: =S16*I16 -> 11624716 | W16: MOVIMIENTO DE TIERRA, COMPACTACION Y RELLENO | X16: PTO 01 | Y16: =SUMIFS(Cert_App_Output!$G:$G,Cert_App_Output!$E:$E,$E16,Cert_App_Output!$K:$K,$X16) -> 1
A17: Movimiento de Suelos | B17: - | C17: - | D17: Preliminares | E17: 2.03 | F17: OK | G17: Excavación manual para vigas de fundación | H17: m3 | I17: 15 | J17: 26000 | K17: 0 | L17: 60860.581 | M17: 1302.9087 | N17: =SUM(J17:M17) -> 88163.489 | O17: =IF($N17=0,$S17,J17/$N17*$S17) -> 34650.913 | P17: =IF($N17=0,0,K17/$N17*$S17) -> 0 | Q17: =IF($N17=0,0,L17/$N17*$S17) -> 81110.565 | R17: =IF($N17=0,0,M17/$N17*$S17) -> 1736.4222 | S17: 117497.9 | T17: =IFERROR(S17/N17,"") -> 1.3327274 | U17: =N17*I17 -> 1322452.3 | V17: =S17*I17 -> 1762468.5 | W17: MOVIMIENTO DE TIERRA, COMPACTACION Y RELLENO | X17: PTO 01 | Y17: =SUMIFS(Cert_App_Output!$G:$G,Cert_App_Output!$E:$E,$E17,Cert_App_Output!$K:$K,$X17) -> 1
A18: - | B18: - | C18: - | D18: - | E18: 2.04 | F18: IN | G18: Aporte y compactación de suelo seleccionado, e: 40 cm (2 capas de 20 cm) - Cotizado Hº Pobre en item 8,02 | H18: m2 | I18: 0 | J18: 0 | K18: 0 | L18: 0 | M18: 0 | N18: =SUM(J18:M18) -> 0 | O18: =IF($N18=0,$S18,J18/$N18*$S18) -> 0 | P18: =IF($N18=0,0,K18/$N18*$S18) -> 0 | Q18: =IF($N18=0,0,L18/$N18*$S18) -> 0 | R18: =IF($N18=0,0,M18/$N18*$S18) -> 0 | S18: 0 | T18: =IFERROR(S18/N18,"") | U18: =N18*I18 -> 0 | V18: =S18*I18 -> 0 | W18: MOVIMIENTO DE TIERRA, COMPACTACION Y RELLENO | X18: PTO 01 | Y18: =SUMIFS(Cert_App_Output!$G:$G,Cert_App_Output!$E:$E,$E18,Cert_App_Output!$K:$K,$X18) -> 0
A19: - | B19: - | C19: - | D19: - | E19: 2.05 | F19: OK | G19: Demolición de bases existentes - No cotiza | H19: gl | I19: 0 | J19: 0 | K19: 0 | L19: 0 | M19: 0 | N19: =SUM(J19:M19) -> 0 | O19: =IF($N19=0,$S19,J19/$N19*$S19) -> 0 | P19: =IF($N19=0,0,K19/$N19*$S19) -> 0 | Q19: =IF($N19=0,0,L19/$N19*$S19) -> 0 | R19: =IF($N19=0,0,M19/$N19*$S19) -> 0 | S19: 0 | T19: =IFERROR(S19/N19,"") | U19: =N19*I19 -> 0 | V19: =S19*I19 -> 0 | W19: MOVIMIENTO DE TIERRA, COMPACTACION Y RELLENO | X19: PTO 01 | Y19: =SUMIFS(Cert_App_Output!$G:$G,Cert_App_Output!$E:$E,$E19,Cert_App_Output!$K:$K,$X19) -> 0
A20: - | B20: - | C20: - | D20: - | E20: 3 | G20: ESTRUCTURA RESISTENTE | W20: ESTRUCTURA RESISTENTE | X20: PTO 01
A21: Hormigón MT | B21: - | C21: - | D21: Homigón MO | E21: 3.01 | F21: OK | G21: Hormigón de limpieza - e: 10 cm | H21: m3 | I21: 13 | J21: 115100 | K21: 0 | L21: 101603.58 | M21: 3250.5537 | N21: =SUM(J21:M21) -> 219954.14 | O21: =IF($N21=0,$S21,J21/$N21*$S21) -> 153396.93 | P21: =IF($N21=0,0,K21/$N21*$S21) -> 0 | Q21: =IF($N21=0,0,L21/$N21*$S21) -> 135409.88 | R21: =IF($N21=0,0,M21/$N21*$S21) -> 4332.1021 | S21: 293138.91 | T21: =IFERROR(S21/N21,"") -> 1.3327274 | U21: =N21*I21 -> 2859403.8 | V21: =S21*I21 -> 3810805.8 | W21: ESTRUCTURA RESISTENTE | X21: PTO 01 | Y21: =SUMIFS(Cert_App_Output!$G:$G,Cert_App_Output!$E:$E,$E21,Cert_App_Output!$K:$K,$X21) -> 1
A22: Hormigón MT | B22: - | C22: Homigón MO | D22: - | E22: 3.02 | F22: OK | G22: Pilotes de tracción Ø 20 cm - (120 kg/m3 de hierro) | H22: u | I22: 18 | J22: 90570.796 | K22: 250000 | L22: 0 | M22: 5108.5619 | N22: =SUM(J22:M22) -> 345679.36 | O22: =IF($N22=0,$S22,J22/$N22*$S22) -> 120706.18 | P22: =IF($N22=0,0,K22/$N22*$S22) -> 333181.86 | Q22: =IF($N22=0,0,L22/$N22*$S22) -> 0 | R22: =IF($N22=0,0,M22/$N22*$S22) -> 6808.3206 | S22: 460696.36 | T22: =IFERROR(S22/N22,"") -> 1.3327274 | U22: =N22*I22 -> 6222228.4 | V22: =S22*I22 -> 8292534.5 | W22: ESTRUCTURA RESISTENTE | X22: PTO 01 | Y22: =SUMIFS(Cert_App_Output!$G:$G,Cert_App_Output!$E:$E,$E22,Cert_App_Output!$K:$K,$X22) -> 1
A23: Hormigón MT | B23: - | C23: Homigón MO | D23: - | E23: 3.03 | F23: OK | G23: Tabique submuración - H35 (95 kg/m3 de hierro) | H23: m3 | I23: 12 | J23: 402072.54 | K23: 357640.9 | L23: 0 | M23: 11395.702 | N23: =SUM(J23:M23) -> 771109.14 | O23: =IF($N23=0,$S23,J23/$N23*$S23) -> 535853.1 | P23: =IF($N23=0,0,K23/$N23*$S23) -> 476637.84 | Q23: =IF($N23=0,0,L23/$N23*$S23) -> 0 | R23: =IF($N23=0,0,M23/$N23*$S23) -> 15187.364 | S23: 1027678.3 | T23: =IFERROR(S23/N23,"") -> 1.3327274 | U23: =N23*I23 -> 9253309.7 | V23: =S23*I23 -> 12332140 | W23: ESTRUCTURA RESISTENTE | X23: PTO 01 | Y23: =SUMIFS(Cert_App_Output!$G:$G,Cert_App_Output!$E:$E,$E23,Cert_App_Output!$K:$K,$X23) -> 1
A24: Hormigón MT | B24: - | C24: Homigón MO | D24: - | E24: 3.04 | F24: OK | G24: Zapata corrida tabique - H35 (120 kg/m3 de hierro) | H24: m3 | I24: 7 | J24: 428196.58 | K24: 281633.96 | L24: 0 | M24: 10647.458 | N24: =SUM(J24:M24) -> 720478 | O24: =IF($N24=0,$S24,J24/$N24*$S24) -> 570669.33 | P24: =IF($N24=0,0,K24/$N24*$S24) -> 375341.31 | Q24: =IF($N24=0,0,L24/$N24*$S24) -> 0 | R24: =IF($N24=0,0,M24/$N24*$S24) -> 14190.159 | S24: 960200.79 | T24: =IFERROR(S24/N24,"") -> 1.3327274 | U24: =N24*I24 -> 5043346 | V24: =S24*I24 -> 6721405.5 | W24: ESTRUCTURA RESISTENTE | X24: PTO 01 | Y24: =SUMIFS(Cert_App_Output!$G:$G,Cert_App_Output!$E:$E,$E24,Cert_App_Output!$K:$K,$X24) -> 1
A25: Hormigón MT | B25: - | C25: Homigón MO | D25: - | E25: 3.05 | F25: OK | G25: Platea - H35 (95 kg/m3 de hierro) | H25: m3 | I25: 38 | J25: 333700.51 | K25: 194327.43 | L25: 0 | M25: 7920.4191 | N25: =SUM(J25:M25) -> 535948.36 | O25: =IF($N25=0,$S25,J25/$N25*$S25) -> 444731.82 | P25: =IF($N25=0,0,K25/$N25*$S25) -> 258985.5 | Q25: =IF($N25=0,0,L25/$N25*$S25) -> 0 | R25: =IF($N25=0,0,M25/$N25*$S25) -> 10555.76 | S25: 714273.08 | T25: =IFERROR(S25/N25,"") -> 1.3327274 | U25: =N25*I25 -> 20366038 | V25: =S25*I25 -> 27142377 | W25: ESTRUCTURA RESISTENTE | X25: PTO 01 | Y25: =SUMIFS(Cert_App_Output!$G:$G,Cert_App_Output!$E:$E,$E25,Cert_App_Output!$K:$K,$X25) -> 1
A26: Hormigón MT | B26: - | C26: Homigón MO | D26: - | E26: 3.06 | F26: OK | G26: Bases aisladas - (60 kg/m3 de hierro) | H26: m3 | I26: 51 | J26: 275042.38 | K26: 194327.43 | L26: 0 | M26: 7040.5472 | N26: =SUM(J26:M26) -> 476410.36 | O26: =IF($N26=0,$S26,J26/$N26*$S26) -> 366556.52 | P26: =IF($N26=0,0,K26/$N26*$S26) -> 258985.5 | Q26: =IF($N26=0,0,L26/$N26*$S26) -> 0 | R26: =IF($N26=0,0,M26/$N26*$S26) -> 9383.1303 | S26: 634925.15 | T26: =IFERROR(S26/N26,"") -> 1.3327274 | U26: =N26*I26 -> 24296928 | V26: =S26*I26 -> 32381183 | W26: ESTRUCTURA RESISTENTE | X26: PTO 01 | Y26: =SUMIFS(Cert_App_Output!$G:$G,Cert_App_Output!$E:$E,$E26,Cert_App_Output!$K:$K,$X26) -> 1
A27: Hormigón MT | B27: - | C27: Homigón MO | D27: - | E27: 3.07 | F27: OK | G27: Troncos de columnas - H35 (240 kg/m3 de hierro) | H27: m3 | I27: 16 | J27: 635192.72 | K27: 317914.05 | L27: 0 | M27: 14296.601 | N27: =SUM(J27:M27) -> 967403.37 | O27: =IF($N27=0,$S27,J27/$N27*$S27) -> 846538.76 | P27: =IF($N27=0,0,K27/$N27*$S27) -> 423692.77 | Q27: =IF($N27=0,0,L27/$N27*$S27) -> 0 | R27: =IF($N27=0,0,M27/$N27*$S27) -> 19053.473 | S27: 1289285 | T27: =IFERROR(S27/N27,"") -> 1.3327274 | U27: =N27*I27 -> 15478454 | V27: =S27*I27 -> 20628560 | W27: ESTRUCTURA RESISTENTE | X27: PTO 01 | Y27: =SUMIFS(Cert_App_Output!$G:$G,Cert_App_Output!$E:$E,$E27,Cert_App_Output!$K:$K,$X27) -> 1
A28: Hormigón MT | B28: - | C28: Homigón MO | D28: - | E28: 3.08 | F28: OK | G28: Viga de encadenado - H35 (180 kg/m3 de hierro) | H28: m3 | I28: 7 | J28: 528753.37 | K28: 281633.96 | L28: 0 | M28: 12155.81 | N28: =SUM(J28:M28) -> 822543.14 | O28: =IF($N28=0,$S28,J28/$N28*$S28) -> 704684.12 | P28: =IF($N28=0,0,K28/$N28*$S28) -> 375341.31 | Q28: =IF($N28=0,0,L28/$N28*$S28) -> 0 | R28: =IF($N28=0,0,M28/$N28*$S28) -> 16200.381 | S28: 1096225.8 | T28: =IFERROR(S28/N28,"") -> 1.3327274 | U28: =N28*I28 -> 5757802 | V28: =S28*I28 -> 7673580.6 | W28: ESTRUCTURA RESISTENTE | X28: PTO 01 | Y28: =SUMIFS(Cert_App_Output!$G:$G,Cert_App_Output!$E:$E,$E28,Cert_App_Output!$K:$K,$X28) -> 1
A29: Hormigón MT | B29: - | C29: Homigón MO | D29: - | E29: 3.09 | F29: OK | G29: Losa maciza - H35 (100 kg/m3 de hierro) | H29: m3 | I29: 90 | J29: 372584.33 | K29: 221790.79 | L29: 0 | M29: 8915.6269 | N29: =SUM(J29:M29) -> 603290.75 | O29: =IF($N29=0,$S29,J29/$N29*$S29) -> 496553.36 | P29: =IF($N29=0,0,K29/$N29*$S29) -> 295586.68 | Q29: =IF($N29=0,0,L29/$N29*$S29) -> 0 | R29: =IF($N29=0,0,M29/$N29*$S29) -> 11882.1 | S29: 804022.13 | T29: =IFERROR(S29/N29,"") -> 1.3327274 | U29: =N29*I29 -> 54296168 | V29: =S29*I29 -> 72361992 | W29: ESTRUCTURA RESISTENTE | X29: PTO 01 | Y29: =SUMIFS(Cert_App_Output!$G:$G,Cert_App_Output!$E:$E,$E29,Cert_App_Output!$K:$K,$X29) -> 1
A30: Hormigón MT | B30: - | C30: Homigón MO | D30: Homigón MO | E30: 3.1 | F30: OK | G30: Losa maciza de Hº visto - H35 (100 kg/m3 de hierro) | H30: m3 | I30: 32 | J30: 379758.83 | K30: 221790.79 | L30: 55447.699 | M30: 9854.9599 | N30: =SUM(J30:M30) -> 666852.29 | O30: =IF($N30=0,$S30,J30/$N30*$S30) -> 506115.01 | P30: =IF($N30=0,0,K30/$N30*$S30) -> 295586.68 | Q30: =IF($N30=0,0,L30/$N30*$S30) -> 73896.669 | R30: =IF($N30=0,0,M30/$N30*$S30) -> 13133.975 | S30: 888732.33 | T30: =IFERROR(S30/N30,"") -> 1.3327274 | U30: =N30*I30 -> 21339273 | V30: =S30*I30 -> 28439435 | W30: ESTRUCTURA RESISTENTE | X30: PTO 01 | Y30: =SUMIFS(Cert_App_Output!$G:$G,Cert_App_Output!$E:$E,$E30,Cert_App_Output!$K:$K,$X30) -> 1
A31: Hormigón MT | B31: - | C31: Homigón MO | D31: - | E31: 3.11 | F31: OK | G31: Vigas - H35 (180 kg/m3 de hierro) | H31: m3 | I31: 46 | J31: 567913.51 | K31: 537036.81 | L31: 0 | M31: 16574.255 | N31: =SUM(J31:M31) -> 1121524.6 | O31: =IF($N31=0,$S31,J31/$N31*$S31) -> 756873.91 | P31: =IF($N31=0,0,K31/$N31*$S31) -> 715723.68 | Q31: =IF($N31=0,0,L31/$N31*$S31) -> 0 | R31: =IF($N31=0,0,M31/$N31*$S31) -> 22088.964 | S31: 1494686.6 | T31: =IFERROR(S31/N31,"") -> 1.3327274 | U31: =N31*I31 -> 51590130 | V31: =S31*I31 -> 68755581 | W31: ESTRUCTURA RESISTENTE | X31: PTO 01 | Y31: =SUMIFS(Cert_App_Output!$G:$G,Cert_App_Output!$E:$E,$E31,Cert_App_Output!$K:$K,$X31) -> 1
A32: Hormigón MT | B32: - | C32: Homigón MO | D32: Homigón MO | E32: 3.12 | F32: OK | G32: Vigas de H° visto - H35 (180 kg/m3 de hierro) | H32: m3 | I32: 31 | J32: 565756.87 | K32: 537036.81 | L32: 134259.2 | M32: 18555.793 | N32: =SUM(J32:M32) -> 1255608.7 | O32: =IF($N32=0,$S32,J32/$N32*$S32) -> 753999.69 | P32: =IF($N32=0,0,K32/$N32*$S32) -> 715723.68 | Q32: =IF($N32=0,0,L32/$N32*$S32) -> 178930.92 | R32: =IF($N32=0,0,M32/$N32*$S32) -> 24729.814 | S32: 1673384.1 | T32: =IFERROR(S32/N32,"") -> 1.3327274 | U32: =N32*I32 -> 38923869 | V32: =S32*I32 -> 51874907 | W32: ESTRUCTURA RESISTENTE | X32: PTO 01 | Y32: =SUMIFS(Cert_App_Output!$G:$G,Cert_App_Output!$E:$E,$E32,Cert_App_Output!$K:$K,$X32) -> 1
... A41: Hormigón MT | B41: - | C41: - | D41: Homigón MO | E41: 3.22 | F41: OK | G41: Picado de medianeras para columnas y vigas - Cotizado para PB y 1P | H41: m2 | I41: 78 | J41: 7051.2821 | K41: 0 | L41: 17829.919 | M41: 373.21802 | N41: =SUM(J41:M41) -> 25254.419 | O41: =IF($N41=0,$S41,J41/$N41*$S41) -> 9397.437 | P41: =IF($N41=0,0,K41/$N41*$S41) -> 0 | Q41: =IF($N41=0,0,L41/$N41*$S41) -> 23762.422 | R41: =IF($N41=0,0,M41/$N41*$S41) -> 497.39789 | S41: 33657.257 | T41: =IFERROR(S41/N41,"") -> 1.3327274 | U41: =N41*I41 -> 1969844.7 | V41: =S41*I41 -> 2625266.1 | W41: ESTRUCTURA RESISTENTE | X41: PTO 01 | Y41: =SUMIFS(Cert_App_Output!$G:$G,Cert_App_Output!$E:$E,$E41,Cert_App_Output!$K:$K,$X41) -> 1
A42: - | B42: - | C42: - | D42: - | E42: 4 | G42: MAMPOSTERÍA | W42: MAMPOSTERÍA | X42: PTO 02
A43: Albañilería MT | B43: - | C43: - | D43: Albañilería MO | E43: 4.01 | F43: OK | G43: Muro tipo 1 - Ladrillo hueco 8 x 18 x 33 | H43: m2 | I43: 621 | J43: 10253.952 | K43: 0 | L43: 16311.975 | M43: 365.95526 | N43: =SUM(J43:M43) -> 26931.882 | O43: =IF($N43=0,$S43,J43/$N43*$S43) -> 13665.723 | P43: =IF($N43=0,0,K43/$N43*$S43) -> 0 | Q43: =IF($N43=0,0,L43/$N43*$S43) -> 21739.416 | R43: =IF($N43=0,0,M43/$N43*$S43) -> 487.71862 | S43: 35892.858 | T43: =IFERROR(S43/N43,"") -> 1.3327274 | U43: =N43*I43 -> 16724699 | V43: =S43*I43 -> 22289465 | W43: MAMPOSTERÍA | X43: PTO 02 | Y43: =SUMIFS(Cert_App_Output!$G:$G,Cert_App_Output!$E:$E,$E43,Cert_App_Output!$K:$K,$X43) -> 0.93
A44: Albañilería MT | B44: - | C44: - | D44: Albañilería MO | E44: 4.02 | F44: OK | G44: Muro tipo 2 - Ladrillo hueco 12 x 18 x 33 | H44: m2 | I44: 780 | J44: 8314.4981 | K44: 0 | L44: 9785.8452 | M44: 235.33191 | N44: =SUM(J44:M44) -> 18335.675 | O44: =IF($N44=0,$S44,J44/$N44*$S44) -> 11080.96 | P44: =IF($N44=0,0,K44/$N44*$S44) -> 0 | Q44: =IF($N44=0,0,L44/$N44*$S44) -> 13041.864 | R44: =IF($N44=0,0,M44/$N44*$S44) -> 313.63329 | S44: 24436.457 | T44: =IFERROR(S44/N44,"") -> 1.3327274 | U44: =N44*I44 -> 14301827 | V44: =S44*I44 -> 19060437 | W44: MAMPOSTERÍA | X44: PTO 02 | Y44: =SUMIFS(Cert_App_Output!$G:$G,Cert_App_Output!$E:$E,$E44,Cert_App_Output!$K:$K,$X44) -> 0.94
A45: Albañilería MT | B45: - | C45: - | D45: Albañilería MO | E45: 4.03 | F45: OK | G45: Muro tipo 3 - Ladrillo comun en panderete | H45: m2 | I45: 56 | J45: 6454.6901 | K45: 0 | L45: 10484.834 | M45: 504.28267 | N45: =SUM(J45:M45) -> 17443.807 | O45: =IF($N45=0,$S45,J45/$N45*$S45) -> 8602.3426 | P45: =IF($N45=0,0,K45/$N45*$S45) -> 0 | Q45: =IF($N45=0,0,L45/$N45*$S45) -> 13973.426 | R45: =IF($N45=0,0,M45/$N45*$S45) -> 672.07134 | S45: 23247.84 | T45: =IFERROR(S45/N45,"") -> 1.3327274 | U45: =N45*I45 -> 976853.19 | V45: =S45*I45 -> 1301879 | W45: MAMPOSTERÍA | X45: PTO 02 | Y45: =SUMIFS(Cert_App_Output!$G:$G,Cert_App_Output!$E:$E,$E45,Cert_App_Output!$K:$K,$X45) -> 1
A46: Albañilería MT | B46: - | C46: - | D46: Albañilería MO | E46: 4.04 | F46: OK | G46: Muro tipo 4 - Ladrillo hueco portante 12 x 18 x 33 | H46: m2 | I46: 42 | J46: 11547.894 | K46: 0 | L46: 9785.8452 | M46: 235.33191 | N46: =SUM(J46:M46) -> 21569.071 | O46: =IF($N46=0,$S46,J46/$N46*$S46) -> 15390.195 | P46: =IF($N46=0,0,K46/$N46*$S46) -> 0 | Q46: =IF($N46=0,0,L46/$N46*$S46) -> 13041.864 | R46: =IF($N46=0,0,M46/$N46*$S46) -> 313.63329 | S46: 28745.692 | T46: =IFERROR(S46/N46,"") -> 1.3327274 | U46: =N46*I46 -> 905900.98 | V46: =S46*I46 -> 1207319.1 | W46: MAMPOSTERÍA | X46: PTO 02 | Y46: =SUMIFS(Cert_App_Output!$G:$G,Cert_App_Output!$E:$E,$E46,Cert_App_Output!$K:$K,$X46) -> 0.95
A47: Albañilería MT | B47: - | C47: - | D47: Albañilería MO | E47: 4.05 | F47: IN | G47: Muro tipo 5 - Bloque HCCA e: 7,5 cm | H47: m2 | I47: 70 | J47: 16817.941 | K47: 0 | L47: 10484.834 | M47: 409.54162 | N47: =SUM(J47:M47) -> 27712.316 | O47: =IF($N47=0,$S47,J47/$N47*$S47) -> 22413.731 | P47: =IF($N47=0,0,K47/$N47*$S47) -> 0 | Q47: =IF($N47=0,0,L47/$N47*$S47) -> 13973.426 | R47: =IF($N47=0,0,M47/$N47*$S47) -> 545.80735 | S47: 36932.964 | T47: =IFERROR(S47/N47,"") -> 1.3327274 | U47: =N47*I47 -> 1939862.2 | V47: =S47*I47 -> 2585307.5 | W47: MAMPOSTERÍA | X47: PTO 02 | Y47: =SUMIFS(Cert_App_Output!$G:$G,Cert_App_Output!$E:$E,$E47,Cert_App_Output!$K:$K,$X47) -> 0.8
A48: Albañilería MT | B48: - | C48: - | D48: Albañilería MO | E48: 4.06 | F48: OK | G48: Muro tipo 6 - Ladrillo hueco 18 x 18 x 33 | H48: m2 | I48: 5 | J48: 11492.44 | K48: 0 | L48: 9785.8452 | M48: 235.33191 | N48: =SUM(J48:M48) -> 21513.617 | O48: =IF($N48=0,$S48,J48/$N48*$S48) -> 15316.29 | P48: =IF($N48=0,0,K48/$N48*$S48) -> 0 | Q48: =IF($N48=0,0,L48/$N48*$S48) -> 13041.864 | R48: =IF($N48=0,0,M48/$N48*$S48) -> 313.63329 | S48: 28671.788 | T48: =IFERROR(S48/N48,"") -> 1.3327274 | U48: =N48*I48 -> 107568.09 | V48: =S48*I48 -> 143358.94 | W48: MAMPOSTERÍA | X48: PTO 02 | Y48: =SUMIFS(Cert_App_Output!$G:$G,Cert_App_Output!$E:$E,$E48,Cert_App_Output!$K:$K,$X48) -> 1
A49: Albañilería MT | B49: - | C49: - | D49: Albañilería MO | E49: 4.07 | F49: OK | G49: Enchape de medianeras existentes - Contemplamos picado zonas sueltas y enchape con ladrillo comun para PB | H49: m2 | I49: 193 | J49: 3227.3451 | K49: 0 | L49: 10484.834 | M49: 252.14133 | N49: =SUM(J49:M49) -> 13964.321 | O49: =IF($N49=0,$S49,J49/$N49*$S49) -> 4301.1713 | P49: =IF($N49=0,0,K49/$N49*$S49) -> 0 | Q49: =IF($N49=0,0,L49/$N49*$S49) -> 13973.426 | R49: =IF($N49=0,0,M49/$N49*$S49) -> 336.03567 | S49: 18610.633 | T49: =IFERROR(S49/N49,"") -> 1.3327274 | U49: =N49*I49 -> 2695113.9 | V49: =S49*I49 -> 3591852.2 | W49: MAMPOSTERÍA | X49: PTO 02 | Y49: =SUMIFS(Cert_App_Output!$G:$G,Cert_App_Output!$E:$E,$E49,Cert_App_Output!$K:$K,$X49) -> 0.1
A50: Albañilería MT | B50: - | C50: - | D50: Albañilería MO | E50: 4.08 | F50: IN | G50: Cordón de hormigón en umbrales carpinterías | H50: ml | I50: 61 | J50: 9093.9863 | K50: 0 | L50: 12031.777 | M50: 316.88645 | N50: =SUM(J50:M50) -> 21442.65 | O50: =IF($N50=0,$S50,J50/$N50*$S50) -> 12119.805 | P50: =IF($N50=0,0,K50/$N50*$S50) -> 0 | Q50: =IF($N50=0,0,L50/$N50*$S50) -> 16035.079 | R50: =IF($N50=0,0,M50/$N50*$S50) -> 422.32326 | S50: 28577.207 | T50: =IFERROR(S50/N50,"") -> 1.3327274 | U50: =N50*I50 -> 1308001.6 | V50: =S50*I50 -> 1743209.6 | W50: MAMPOSTERÍA | X50: PTO 02 | Y50: =SUMIFS(Cert_App_Output!$G:$G,Cert_App_Output!$E:$E,$E50,Cert_App_Output!$K:$K,$X50) -> 1
A51: Albañilería MT | B51: - | C51: - | D51: Albañilería MO | E51: 4.09 | F51: IN | G51: Banquina Sala tanque de bombeo | H51: gl | I51: 1 | J51: 60811.031 | K51: 0 | L51: 146787.68 | M51: 3113.9806 | N51: =SUM(J51:M51) -> 210712.69 | O51: =IF($N51=0,$S51,J51/$N51*$S51) -> 81044.529 | P51: =IF($N51=0,0,K51/$N51*$S51) -> 0 | Q51: =IF($N51=0,0,L51/$N51*$S51) -> 195627.96 | R51: =IF($N51=0,0,M51/$N51*$S51) -> 4150.0874 | S51: 280822.58 | T51: =IFERROR(S51/N51,"") -> 1.3327274 | U51: =N51*I51 -> 210712.69 | V51: =S51*I51 -> 280822.58 | W51: MAMPOSTERÍA | X51: PTO 02 | Y51: =SUMIFS(Cert_App_Output!$G:$G,Cert_App_Output!$E:$E,$E51,Cert_App_Output!$K:$K,$X51) -> 0
A52: Albañilería MT | B52: - | C52: - | D52: Albañilería MO | E52: 4.1 | F52: IN | G52: Banquina en parrillas | H52: gl | I52: 1 | J52: 151935.62 | K52: 0 | L52: 440363.03 | M52: 8884.4798 | N52: =SUM(J52:M52) -> 601183.14 | O52: =IF($N52=0,$S52,J52/$N52*$S52) -> 202488.77 | P52: =IF($N52=0,0,K52/$N52*$S52) -> 0 | Q52: =IF($N52=0,0,L52/$N52*$S52) -> 586883.89 | R52: =IF($N52=0,0,M52/$N52*$S52) -> 11840.59 | S52: 801213.25 | T52: =IFERROR(S52/N52,"") -> 1.3327274 | U52: =N52*I52 -> 601183.14 | V52: =S52*I52 -> 801213.25 | W52: MAMPOSTERÍA | X52: PTO 02 | Y52: =SUMIFS(Cert_App_Output!$G:$G,Cert_App_Output!$E:$E,$E52,Cert_App_Output!$K:$K,$X52) -> 0
A53: Albañilería MT | B53: - | C53: - | D53: Albañilería MO | E53: 4.11 | F53: OK | G53: Excavación y amurado con Hº tanque de recuperación de agua de lluvia | H53: gl | I53: 1 | J53: 128742.9 | K53: 0 | L53: 259536.82 | M53: 5824.1958 | N53: =SUM(J53:M53) -> 394103.91 | O53: =IF($N53=0,$S53,J53/$N53*$S53) -> 171579.19 | P53: =IF($N53=0,0,K53/$N53*$S53) -> 0 | Q53: =IF($N53=0,0,L53/$N53*$S53) -> 345891.84 | R53: =IF($N53=0,0,M53/$N53*$S53) -> 7762.0654 | S53: 525233.09 | T53: =IFERROR(S53/N53,"") -> 1.3327274 | U53: =N53*I53 -> 394103.91 | V53: =S53*I53 -> 525233.09 | W53: MAMPOSTERÍA | X53: PTO 02 | Y53: =SUMIFS(Cert_App_Output!$G:$G,Cert_App_Output!$E:$E,$E53,Cert_App_Output!$K:$K,$X53) -> 0
A54: Albañilería MT | B54: - | C54: - | D54: Albañilería MO | E54: 4.12 | F54: OK | G54: Provisión y amurado de tapas de inspección para tanque de reserva | H54: u | I54: 3 | J54: 121487.6 | K54: 0 | L54: 54294.059 | M54: 2636.7249 | N54: =SUM(J54:M54) -> 178418.39 | O54: =IF($N54=0,$S54,J54/$N54*$S54) -> 161909.86 | P54: =IF($N54=0,0,K54/$N54*$S54) -> 0 | Q54: =IF($N54=0,0,L54/$N54*$S54) -> 72359.181 | R54: =IF($N54=0,0,M54/$N54*$S54) -> 3514.0356 | S54: 237783.08 | T54: =IFERROR(S54/N54,"") -> 1.3327274 | U54: =N54*I54 -> 535255.16 | V54: =S54*I54 -> 713349.23 | W54: MAMPOSTERÍA | X54: PTO 02 | Y54: =SUMIFS(Cert_App_Output!$G:$G,Cert_App_Output!$E:$E,$E54,Cert_App_Output!$K:$K,$X54) -> 1
... A56: Albañilería MT | B56: - | C56: - | D56: Albañilería MO | E56: 4.14 | F56: IN | G56: Amurado de bañera | H56: u | I56: 8 | J56: 23946.262 | K56: 0 | L56: 107385.37 | M56: 1969.9745 | N56: =SUM(J56:M56) -> 133301.61 | O56: =IF($N56=0,$S56,J56/$N56*$S56) -> 31913.84 | P56: =IF($N56=0,0,K56/$N56*$S56) -> 0 | Q56: =IF($N56=0,0,L56/$N56*$S56) -> 143115.43 | R56: =IF($N56=0,0,M56/$N56*$S56) -> 2625.439 | S56: 177654.71 | T56: =IFERROR(S56/N56,"") -> 1.3327274 | U56: =N56*I56 -> 1066412.9 | V56: =S56*I56 -> 1421237.7 | W56: MAMPOSTERÍA | X56: PTO 02 | Y56: =SUMIFS(Cert_App_Output!$G:$G,Cert_App_Output!$E:$E,$E56,Cert_App_Output!$K:$K,$X56) -> 0
A57: - | B57: - | C57: - | D57: - | E57: 5 | G57: AISLACIONES | W57: AISLACIONES | X57: PTO 02
A58: Albañilería MT | B58: - | C58: - | D58: Albañilería MO | E58: 5.01 | F58: OK | G58: Cajón hidrofugo | H58: ml | I58: 136 | J58: 809.61503 | K58: 0 | L58: 3938.2618 | M58: 126.07067 | N58: =SUM(J58:M58) -> 4873.9475 | O58: =IF($N58=0,$S58,J58/$N58*$S58) -> 1078.9962 | P58: =IF($N58=0,0,K58/$N58*$S58) -> 0 | Q58: =IF($N58=0,0,L58/$N58*$S58) -> 5248.6295 | R58: =IF($N58=0,0,M58/$N58*$S58) -> 168.01784 | S58: 6495.6435 | T58: =IFERROR(S58/N58,"") -> 1.3327274 | U58: =N58*I58 -> 662856.86 | V58: =S58*I58 -> 883407.51 | W58: AISLACIONES | X58: PTO 02 | Y58: =SUMIFS(Cert_App_Output!$G:$G,Cert_App_Output!$E:$E,$E58,Cert_App_Output!$K:$K,$X58) -> 0.5
A59: Albañilería MT | B59: - | C59: Albañilería MO | D59: Albañilería MO | E59: 5.02 | F59: OK | G59: Aislación hidrófuga horizontal (baños) - Inc. membrana geotextil y 35% en concepto de babetas | H59: m2 | I59: 77 | J59: 13188.358 | K59: 5871.5071 | L59: 5871.5071 | M59: 32.180227 | N59: =SUM(J59:M59) -> 24963.552 | O59: =IF($N59=0,$S59,J59/$N59*$S59) -> 17576.486 | P59: =IF($N59=0,0,K59/$N59*$S59) -> 7825.1186 | Q59: =IF($N59=0,0,L59/$N59*$S59) -> 7825.1186 | R59: =IF($N59=0,0,M59/$N59*$S59) -> 42.887472 | S59: 33269.611 | T59: =IFERROR(S59/N59,"") -> 1.3327274 | U59: =N59*I59 -> 1922193.5 | V59: =S59*I59 -> 2561760 | W59: AISLACIONES | X59: PTO 02 | Y59: =SUMIFS(Cert_App_Output!$G:$G,Cert_App_Output!$E:$E,$E59,Cert_App_Output!$K:$K,$X59) -> 0.5
A60: Albañilería MT | B60: - | C60: - | D60: Albañilería MO | E60: 5.03 | F60: OK | G60: Azotado hidrófugo - Contrapiso de PB | H60: m2 | I60: 107 | J60: 809.61503 | K60: 0 | L60: 3938.2618 | M60: 126.07067 | N60: =SUM(J60:M60) -> 4873.9475 | O60: =IF($N60=0,$S60,J60/$N60*$S60) -> 1078.9962 | P60: =IF($N60=0,0,K60/$N60*$S60) -> 0 | Q60: =IF($N60=0,0,L60/$N60*$S60) -> 5248.6295 | R60: =IF($N60=0,0,M60/$N60*$S60) -> 168.01784 | S60: 6495.6435 | T60: =IFERROR(S60/N60,"") -> 1.3327274 | U60: =N60*I60 -> 521512.38 | V60: =S60*I60 -> 695033.85 | W60: AISLACIONES | X60: PTO 02 | Y60: =SUMIFS(Cert_App_Output!$G:$G,Cert_App_Output!$E:$E,$E60,Cert_App_Output!$K:$K,$X60) -> 0
A61: Albañilería MT | B61: - | C61: - | D61: - | E61: 5.04 | F61: OK | G61: Aislación térmica en terrazas, eps e:2,00 cm | H61: m2 | I61: 186 | J61: 3625.4 | K61: 0 | L61: 0 | M61: 0 | N61: =SUM(J61:M61) -> 3625.4 | O61: =IF($N61=0,$S61,J61/$N61*$S61) -> 4831.67 | P61: =IF($N61=0,0,K61/$N61*$S61) -> 0 | Q61: =IF($N61=0,0,L61/$N61*$S61) -> 0 | R61: =IF($N61=0,0,M61/$N61*$S61) -> 0 | S61: 4831.67 | T61: =IFERROR(S61/N61,"") -> 1.3327274 | U61: =N61*I61 -> 674324.4 | V61: =S61*I61 -> 898690.62 | W61: AISLACIONES | X61: PTO 02 | Y61: =SUMIFS(Cert_App_Output!$G:$G,Cert_App_Output!$E:$E,$E61,Cert_App_Output!$K:$K,$X61) -> 0
A62: Albañilería MT | B62: - | C62: - | D62: Albañilería MO | E62: 5.05 | F62: OK | G62: Barrera de vapor | H62: m2 | I62: 186 | J62: 1256.6125 | K62: 0 | L62: 1834.846 | M62: 10.056321 | N62: =SUM(J62:M62) -> 3101.5148 | O62: =IF($N62=0,$S62,J62/$N62*$S62) -> 1674.722 | P62: =IF($N62=0,0,K62/$N62*$S62) -> 0 | Q62: =IF($N62=0,0,L62/$N62*$S62) -> 2445.3496 | R62: =IF($N62=0,0,M62/$N62*$S62) -> 13.402335 | S62: 4133.4739 | T62: =IFERROR(S62/N62,"") -> 1.3327274 | U62: =N62*I62 -> 576881.76 | V62: =S62*I62 -> 768826.14 | W62: AISLACIONES | X62: PTO 02 | Y62: =SUMIFS(Cert_App_Output!$G:$G,Cert_App_Output!$E:$E,$E62,Cert_App_Output!$K:$K,$X62) -> 1
A63: Albañilería MT | B63: - | C63: Albañilería MO | D63: Albañilería MO | E63: 5.06 | F63: OK | G63: Membrana asfáltica geotextil 4mm - Balcones y azotea - Inc. 20% en concepto de babetas | H63: m2 | I63: 390 | J63: 11722.985 | K63: 3522.9043 | L63: 5871.5071 | M63: 32.180227 | N63: =SUM(J63:M63) -> 21149.576 | O63: =IF($N63=0,$S63,J63/$N63*$S63) -> 15623.543 | P63: =IF($N63=0,0,K63/$N63*$S63) -> 4695.0711 | Q63: =IF($N63=0,0,L63/$N63*$S63) -> 7825.1186 | R63: =IF($N63=0,0,M63/$N63*$S63) -> 42.887472 | S63: 28186.62 | T63: =IFERROR(S63/N63,"") -> 1.3327274 | U63: =N63*I63 -> 8248334.7 | V63: =S63*I63 -> 10992782 | W63: AISLACIONES | X63: PTO 02 | Y63: =SUMIFS(Cert_App_Output!$G:$G,Cert_App_Output!$E:$E,$E63,Cert_App_Output!$K:$K,$X63) -> 0.3
A64: Albañilería MT | B64: - | C64: Albañilería MO | D64: - | E64: 5.07 | F64: OK | G64: Impermeabilización de tanque de reserva de HºAº | H64: gl | I64: 1 | J64: 0 | K64: 1829911.6 | L64: 0 | M64: 0 | N64: =SUM(J64:M64) -> 1829911.6 | O64: =IF($N64=0,$S64,J64/$N64*$S64) -> 0 | P64: =IF($N64=0,0,K64/$N64*$S64) -> 2438773.4 | Q64: =IF($N64=0,0,L64/$N64*$S64) -> 0 | R64: =IF($N64=0,0,M64/$N64*$S64) -> 0 | S64: 2438773.4 | T64: =IFERROR(S64/N64,"") -> 1.3327274 | U64: =N64*I64 -> 1829911.6 | V64: =S64*I64 -> 2438773.4 | W64: AISLACIONES | X64: PTO 02 | Y64: =SUMIFS(Cert_App_Output!$G:$G,Cert_App_Output!$E:$E,$E64,Cert_App_Output!$K:$K,$X64) -> 1
A65: - | B65: - | C65: - | D65: - | E65: 6 | G65: CUBIERTAS | W65: CUBIERTAS | X65: PTO 02
A66: Albañilería MT | B66: - | C66: - | D66: Albañilería MO | E66: 6.02 | F66: OK | G66: Babeta de chapa galvanizada en medianeras | H66: ml | I66: 55 | J66: 14897.521 | K66: 0 | L66: 8259.2819 | M66: 347.35204 | N66: =SUM(J66:M66) -> 23504.155 | O66: =IF($N66=0,$S66,J66/$N66*$S66) -> 19854.334 | P66: =IF($N66=0,0,K66/$N66*$S66) -> 0 | Q66: =IF($N66=0,0,L66/$N66*$S66) -> 11007.372 | R66: =IF($N66=0,0,M66/$N66*$S66) -> 462.92559 | S66: 31324.632 | T66: =IFERROR(S66/N66,"") -> 1.3327274 | U66: =N66*I66 -> 1292728.5 | V66: =S66*I66 -> 1722854.7 | W66: CUBIERTAS | X66: PTO 02 | Y66: =SUMIFS(Cert_App_Output!$G:$G,Cert_App_Output!$E:$E,$E66,Cert_App_Output!$K:$K,$X66) -> 0
A67: - | B67: - | C67: - | D67: - | E67: 7 | G67: REVOQUES | W67: REVOQUES | X67: PTO 02
A68: Albañilería MT | B68: - | C68: - | D68: Albañilería MO | E68: 7.01 | F68: OK | G68: Revoque Grueso Impermeable Exterior | H68: m2 | I68: 879 | J68: 4009.2266 | K68: 0 | L68: 10647.256 | M68: 306.95467 | N68: =SUM(J68:M68) -> 14963.437 | O68: =IF($N68=0,$S68,J68/$N68*$S68) -> 5343.2063 | P68: =IF($N68=0,0,K68/$N68*$S68) -> 0 | Q68: =IF($N68=0,0,L68/$N68*$S68) -> 14189.89 | R68: =IF($N68=0,0,M68/$N68*$S68) -> 409.08691 | S68: 19942.183 | T68: =IFERROR(S68/N68,"") -> 1.3327274 | U68: =N68*I68 -> 13152861 | V68: =S68*I68 -> 17529179 | W68: REVOQUES | X68: PTO 02 | Y68: =SUMIFS(Cert_App_Output!$G:$G,Cert_App_Output!$E:$E,$E68,Cert_App_Output!$K:$K,$X68) -> 0.65
A69: Albañilería MT | B69: - | C69: - | D69: Albañilería MO | E69: 7.02 | F69: OK | G69: Revoque Grueso Impermeable Exterior a mas de 3m - Medianero y fachadas | H69: m2 | I69: 716 | J69: 4009.2266 | K69: 0 | L69: 15305.431 | M69: 769.31526 | N69: =SUM(J69:M69) -> 20083.973 | O69: =IF($N69=0,$S69,J69/$N69*$S69) -> 5343.2063 | P69: =IF($N69=0,0,K69/$N69*$S69) -> 0 | Q69: =IF($N69=0,0,L69/$N69*$S69) -> 20397.967 | R69: =IF($N69=0,0,M69/$N69*$S69) -> 1025.2876 | S69: 26766.461 | T69: =IFERROR(S69/N69,"") -> 1.3327274 | U69: =N69*I69 -> 14380124 | V69: =S69*I69 -> 19164786 | W69: REVOQUES | X69: PTO 02 | Y69: =SUMIFS(Cert_App_Output!$G:$G,Cert_App_Output!$E:$E,$E69,Cert_App_Output!$K:$K,$X69) -> 0.85
A70: Durlock MT | B70: - | C70: Durlock MO | D70: - | E70: 7.03 | F70: OK | G70: Yeso interior | H70: m2 | I70: 1439 | J70: 5324.1715 | K70: 11651.218 | L70: 0 | M70: 254.63085 | N70: =SUM(J70:M70) -> 17230.021 | O70: =IF($N70=0,$S70,J70/$N70*$S70) -> 7095.6693 | P70: =IF($N70=0,0,K70/$N70*$S70) -> 15527.898 | Q70: =IF($N70=0,0,L70/$N70*$S70) -> 0 | R70: =IF($N70=0,0,M70/$N70*$S70) -> 339.35351 | S70: 22962.921 | T70: =IFERROR(S70/N70,"") -> 1.3327274 | U70: =N70*I70 -> 24794000 | V70: =S70*I70 -> 33043643 | W70: REVOQUES | X70: PTO 02 | Y70: =SUMIFS(Cert_App_Output!$G:$G,Cert_App_Output!$E:$E,$E70,Cert_App_Output!$K:$K,$X70) -> 1
A71: Durlock MT | B71: - | C71: Durlock MO | D71: - | E71: 7.04 | F71: OK | G71: Arista en yeso | H71: ml | I71: 347 | J71: 0 | K71: 12499.473 | L71: 0 | M71: 187.4921 | N71: =SUM(J71:M71) -> 12686.965 | O71: =IF($N71=0,$S71,J71/$N71*$S71) -> 0 | P71: =IF($N71=0,0,K71/$N71*$S71) -> 16658.391 | Q71: =IF($N71=0,0,L71/$N71*$S71) -> 0 | R71: =IF($N71=0,0,M71/$N71*$S71) -> 249.87586 | S71: 16908.267 | T71: =IFERROR(S71/N71,"") -> 1.3327274 | U71: =N71*I71 -> 4402376.9 | V71: =S71*I71 -> 5867168.5 | W71: REVOQUES | X71: PTO 02 | Y71: =SUMIFS(Cert_App_Output!$G:$G,Cert_App_Output!$E:$E,$E71,Cert_App_Output!$K:$K,$X71) -> 0.95
A72: Albañilería MT | B72: - | C72: Albañilería MO | D72: - | E72: 7.05 | F72: OK | G72: Provisión y colocación de guardacanto yesero | H72: un | I72: 132 | J72: 1167.2736 | K72: 13162.324 | L72: 0 | M72: 214.94396 | N72: =SUM(J72:M72) -> 14544.542 | O72: =IF($N72=0,$S72,J72/$N72*$S72) -> 1555.6575 | P72: =IF($N72=0,0,K72/$N72*$S72) -> 17541.79 | Q72: =IF($N72=0,0,L72/$N72*$S72) -> 0 | R72: =IF($N72=0,0,M72/$N72*$S72) -> 286.46172 | S72: 19383.909 | T72: =IFERROR(S72/N72,"") -> 1.3327274 | U72: =N72*I72 -> 1919879.5 | V72: =S72*I72 -> 2558676 | W72: REVOQUES | X72: PTO 02 | Y72: =SUMIFS(Cert_App_Output!$G:$G,Cert_App_Output!$E:$E,$E72,Cert_App_Output!$K:$K,$X72) -> 0.95
A73: Albañilería MT | B73: - | C73: - | D73: Albañilería MO | E73: 7.06 | F73: OK | G73: Revoque Grueso Impermeable Interior b/ revestimiento | H73: m2 | I73: 710 | J73: 4009.2266 | K73: 0 | L73: 10647.256 | M73: 306.95467 | N73: =SUM(J73:M73) -> 14963.437 | O73: =IF($N73=0,$S73,J73/$N73*$S73) -> 5343.2063 | P73: =IF($N73=0,0,K73/$N73*$S73) -> 0 | Q73: =IF($N73=0,0,L73/$N73*$S73) -> 14189.89 | R73: =IF($N73=0,0,M73/$N73*$S73) -> 409.08691 | S73: 19942.183 | T73: =IFERROR(S73/N73,"") -> 1.3327274 | U73: =N73*I73 -> 10624041 | V73: =S73*I73 -> 14158950 | W73: REVOQUES | X73: PTO 02 | Y73: =SUMIFS(Cert_App_Output!$G:$G,Cert_App_Output!$E:$E,$E73,Cert_App_Output!$K:$K,$X73) -> 0.85
A74: - | B74: - | C74: - | D74: - | E74: 8 | G74: CONTRAPISOS Y CARPETAS | W74: CONTRAPISOS Y CARPETAS | X74: PTO 02
A75: Albañilería MT | B75: - | C75: - | D75: Albañilería MO | E75: 8.01 | F75: IN | G75: Contrapiso de Hº armado e: 18 cm, incluye malla Ø 6 mm y film 200 mic. | H75: m2 | I75: 107 | J75: 30940.007 | K75: 0 | L75: 12364.893 | M75: 649.5735 | N75: =SUM(J75:M75) -> 43954.474 | O75: =IF($N75=0,$S75,J75/$N75*$S75) -> 41234.596 | P75: =IF($N75=0,0,K75/$N75*$S75) -> 0 | Q75: =IF($N75=0,0,L75/$N75*$S75) -> 16479.033 | R75: =IF($N75=0,0,M75/$N75*$S75) -> 865.70442 | S75: 58579.333 | T75: =IFERROR(S75/N75,"") -> 1.3327274 | U75: =N75*I75 -> 4703128.7 | V75: =S75*I75 -> 6267988.6 | W75: CONTRAPISOS Y CARPETAS | X75: PTO 02 | Y75: =SUMIFS(Cert_App_Output!$G:$G,Cert_App_Output!$E:$E,$E75,Cert_App_Output!$K:$K,$X75) -> 0
A76: Albañilería MT | B76: - | C76: Albañilería MO | D76: Albañilería MO | E76: 8.02 | F76: IN | G76: Contrapiso de H13 subase bajo intertrabado y garden block | H76: m2 | I76: 258 | J76: 22041.278 | K76: 891.47287 | L76: 5697.0204 | M76: 429.44656 | N76: =SUM(J76:M76) -> 29059.217 | O76: =IF($N76=0,$S76,J76/$N76*$S76) -> 29375.015 | P76: =IF($N76=0,0,K76/$N76*$S76) -> 1188.0903 | Q76: =IF($N76=0,0,L76/$N76*$S76) -> 7592.5754 | R76: =IF($N76=0,0,M76/$N76*$S76) -> 572.33521 | S76: 38728.016 | T76: =IFERROR(S76/N76,"") -> 1.3327274 | U76: =N76*I76 -> 7497278.1 | V76: =S76*I76 -> 9991828.1 | W76: CONTRAPISOS Y CARPETAS | X76: PTO 02 | Y76: =SUMIFS(Cert_App_Output!$G:$G,Cert_App_Output!$E:$E,$E76,Cert_App_Output!$K:$K,$X76) -> 0
A77: Albañilería MT | B77: - | C77: - | D77: Albañilería MO | E77: 8.03 | F77: OK | G77: Monolítico e: 6 cm | H77: m2 | I77: 425 | J77: 6968.0306 | K77: 0 | L77: 10126.741 | M77: 120.04692 | N77: =SUM(J77:M77) -> 17214.819 | O77: =IF($N77=0,$S77,J77/$N77*$S77) -> 9286.4855 | P77: =IF($N77=0,0,K77/$N77*$S77) -> 0 | Q77: =IF($N77=0,0,L77/$N77*$S77) -> 13496.186 | R77: =IF($N77=0,0,M77/$N77*$S77) -> 159.98982 | S77: 22942.661 | T77: =IFERROR(S77/N77,"") -> 1.3327274 | U77: =N77*I77 -> 7316297.9 | V77: =S77*I77 -> 9750630.9 | W77: CONTRAPISOS Y CARPETAS | X77: PTO 02 | Y77: =SUMIFS(Cert_App_Output!$G:$G,Cert_App_Output!$E:$E,$E77,Cert_App_Output!$K:$K,$X77) -> 0.5
A78: Albañilería MT | B78: - | C78: - | D78: Albañilería MO | E78: 8.04 | F78: IN | G78: Contrapiso alivianado en azoteas (RDC), e: 15 cm | H78: m2 | I78: 200 | J78: 24469.45 | K78: 0 | L78: 5362.3939 | M78: 447.47766 | N78: =SUM(J78:M78) -> 30279.322 | O78: =IF($N78=0,$S78,J78/$N78*$S78) -> 32611.107 | P78: =IF($N78=0,0,K78/$N78*$S78) -> 0 | Q78: =IF($N78=0,0,L78/$N78*$S78) -> 7146.6095 | R78: =IF($N78=0,0,M78/$N78*$S78) -> 596.36575 | S78: 40354.082 | T78: =IFERROR(S78/N78,"") -> 1.3327274 | U78: =N78*I78 -> 6055864.3 | V78: =S78*I78 -> 8070816.5 | W78: CONTRAPISOS Y CARPETAS | X78: PTO 02 | Y78: =SUMIFS(Cert_App_Output!$G:$G,Cert_App_Output!$E:$E,$E78,Cert_App_Output!$K:$K,$X78) -> 0.5
A79: Albañilería MT | B79: - | C79: - | D79: Albañilería MO | E79: 8.05 | F79: IN | G79: Contrapiso con piedra binder e: 4/5 cm - En locales húmedos (baños) | H79: m2 | I79: 77 | J79: 8233.9595 | K79: 0 | L79: 15063.227 | M79: 349.45779 | N79: =SUM(J79:M79) -> 23646.644 | O79: =IF($N79=0,$S79,J79/$N79*$S79) -> 10973.624 | P79: =IF($N79=0,0,K79/$N79*$S79) -> 0 | Q79: =IF($N79=0,0,L79/$N79*$S79) -> 20075.175 | R79: =IF($N79=0,0,M79/$N79*$S79) -> 465.73198 | S79: 31514.531 | T79: =IFERROR(S79/N79,"") -> 1.3327274 | U79: =N79*I79 -> 1820791.6 | V79: =S79*I79 -> 2426618.9 | W79: CONTRAPISOS Y CARPETAS | X79: PTO 02 | Y79: =SUMIFS(Cert_App_Output!$G:$G,Cert_App_Output!$E:$E,$E79,Cert_App_Output!$K:$K,$X79) -> 0.5
A80: Albañilería MT | B80: - | C80: - | D80: Albañilería MO | E80: 8.06 | F80: IN | G80: Carpeta autonivelante e: 4/10 mm - En locales húmedos (baños) | H80: m2 | I80: 77 | J80: 7390.791 | K80: 0 | L80: 7159.2551 | M80: 218.25069 | N80: =SUM(J80:M80) -> 14768.297 | O80: =IF($N80=0,$S80,J80/$N80*$S80) -> 9849.9099 | P80: =IF($N80=0,0,K80/$N80*$S80) -> 0 | Q80: =IF($N80=0,0,L80/$N80*$S80) -> 9541.3356 | R80: =IF($N80=0,0,M80/$N80*$S80) -> 290.86868 | S80: 19682.114 | T80: =IFERROR(S80/N80,"") -> 1.3327274 | U80: =N80*I80 -> 1137158.9 | V80: =S80*I80 -> 1515522.8 | W80: CONTRAPISOS Y CARPETAS | X80: PTO 02 | Y80: =SUMIFS(Cert_App_Output!$G:$G,Cert_App_Output!$E:$E,$E80,Cert_App_Output!$K:$K,$X80) -> 0
A81: Albañilería MT | B81: - | C81: - | D81: Albañilería MO | E81: 8.07 | F81: OK | G81: Carpeta a la cal reforzada | H81: m2 | I81: 442 | J81: 2717.5179 | K81: 0 | L81: 7814.7833 | M81: 223.75096 | N81: =SUM(J81:M81) -> 10756.052 | O81: =IF($N81=0,$S81,J81/$N81*$S81) -> 3621.7106 | P81: =IF($N81=0,0,K81/$N81*$S81) -> 0 | Q81: =IF($N81=0,0,L81/$N81*$S81) -> 10414.976 | R81: =IF($N81=0,0,M81/$N81*$S81) -> 298.19904 | S81: 14334.886 | T81: =IFERROR(S81/N81,"") -> 1.3327274 | U81: =N81*I81 -> 4754175.1 | V81: =S81*I81 -> 6336019.5 | W81: CONTRAPISOS Y CARPETAS | X81: PTO 02 | Y81: =SUMIFS(Cert_App_Output!$G:$G,Cert_App_Output!$E:$E,$E81,Cert_App_Output!$K:$K,$X81) -> 0.25
A82: Albañilería MT | B82: - | C82: - | D82: Albañilería MO | E82: 8.08 | F82: OK | G82: Carpeta a la cal reforzada s/membrana | H82: m2 | I82: 360 | J82: 2717.5179 | K82: 0 | L82: 7814.7833 | M82: 223.75096 | N82: =SUM(J82:M82) -> 10756.052 | O82: =IF($N82=0,$S82,J82/$N82*$S82) -> 3621.7106 | P82: =IF($N82=0,0,K82/$N82*$S82) -> 0 | Q82: =IF($N82=0,0,L82/$N82*$S82) -> 10414.976 | R82: =IF($N82=0,0,M82/$N82*$S82) -> 298.19904 | S82: 14334.886 | T82: =IFERROR(S82/N82,"") -> 1.3327274 | U82: =N82*I82 -> 3872178.8 | V82: =S82*I82 -> 5160558.9 | W82: CONTRAPISOS Y CARPETAS | X82: PTO 02 | Y82: =SUMIFS(Cert_App_Output!$G:$G,Cert_App_Output!$E:$E,$E82,Cert_App_Output!$K:$K,$X82) -> 0
A83: - | B83: - | C83: - | D83: - | E83: 9 | G83: ESCALERAS | W83: ESCALERAS | X83: PTO 02
A84: Albañilería MT | B84: - | C84: - | D84: Albañilería MO | E84: 9.01 | F84: OK | G84: Provisión y ejecución de cemento alisado arrodillado, e: 3,00 cm, en alzada y pedad | H84: gl | I84: 1 | J84: 181154.98 | K84: 0 | L84: 1378156.6 | M84: 23389.674 | N84: =SUM(J84:M84) -> 1582701.3 | O84: =IF($N84=0,$S84,J84/$N84*$S84) -> 241430.21 | P84: =IF($N84=0,0,K84/$N84*$S84) -> 0 | Q84: =IF($N84=0,0,L84/$N84*$S84) -> 1836707.1 | R84: =IF($N84=0,0,M84/$N84*$S84) -> 31172.06 | S84: 2109309.4 | T84: =IFERROR(S84/N84,"") -> 1.3327274 | U84: =N84*I84 -> 1582701.3 | V84: =S84*I84 -> 2109309.4 | W84: ESCALERAS | X84: PTO 02 | Y84: =SUMIFS(Cert_App_Output!$G:$G,Cert_App_Output!$E:$E,$E84,Cert_App_Output!$K:$K,$X84) -> 0
A85: Albañilería MT | B85: - | C85: - | D85: Albañilería MO | E85: 9.02 | F85: OK | G85: Provisión nariz escalera, hierro angulo 5/8 x 1/8" | H85: un | I85: 81 | J85: 2592.9773 | K85: 0 | L85: 18121.936 | M85: 310.72369 | N85: =SUM(J85:M85) -> 21025.637 | O85: =IF($N85=0,$S85,J85/$N85*$S85) -> 3455.732 | P85: =IF($N85=0,0,K85/$N85*$S85) -> 0 | Q85: =IF($N85=0,0,L85/$N85*$S85) -> 24151.601 | R85: =IF($N85=0,0,M85/$N85*$S85) -> 414.10999 | S85: 28021.443 | T85: =IFERROR(S85/N85,"") -> 1.3327274 | U85: =N85*I85 -> 1703076.6 | V85: =S85*I85 -> 2269736.8 | W85: ESCALERAS | X85: PTO 02 | Y85: =SUMIFS(Cert_App_Output!$G:$G,Cert_App_Output!$E:$E,$E85,Cert_App_Output!$K:$K,$X85) -> 0
A86: Albañilería MT | B86: - | C86: - | D86: Albañilería MO | E86: 9.03 | F86: OK | G86: Ejecución de zócalo rampante de concreto h: 10 cm | H86: ml | I86: 46 | J86: 609.94943 | K86: 0 | L86: 7003.3937 | M86: 114.20015 | N86: =SUM(J86:M86) -> 7727.5433 | O86: =IF($N86=0,$S86,J86/$N86*$S86) -> 812.89634 | P86: =IF($N86=0,0,K86/$N86*$S86) -> 0 | Q86: =IF($N86=0,0,L86/$N86*$S86) -> 9333.6149 | R86: =IF($N86=0,0,M86/$N86*$S86) -> 152.19767 | S86: 10298.709 | T86: =IFERROR(S86/N86,"") -> 1.3327274 | U86: =N86*I86 -> 355466.99 | V86: =S86*I86 -> 473740.61 | W86: ESCALERAS | X86: PTO 02 | Y86: =SUMIFS(Cert_App_Output!$G:$G,Cert_App_Output!$E:$E,$E86,Cert_App_Output!$K:$K,$X86) -> 0
A87: - | B87: - | C87: - | D87: - | E87: 10 | G87: VENTILACIONES - PROVISION A CARGO DEL COMITENTE | W87: VENTILACIONES - PROVISION A CARGO DEL COMITENTE | X87: PTO 02
A88: Albañilería MT | B88: - | C88: - | D88: Albañilería MO | E88: 10.01 | F88: IN | G88: Montaje de conductos de ventilación de baños C27 - Provisión a cargo del comitente | H88: gl | I88: 1 | J88: 200000 | K88: 0 | L88: 1163573.9 | M88: 20453.608 | N88: =SUM(J88:M88) -> 1384027.5 | O88: =IF($N88=0,$S88,J88/$N88*$S88) -> 266545.49 | P88: =IF($N88=0,0,K88/$N88*$S88) -> 0 | Q88: =IF($N88=0,0,L88/$N88*$S88) -> 1550726.8 | R88: =IF($N88=0,0,M88/$N88*$S88) -> 27259.085 | S88: 1844531.4 | T88: =IFERROR(S88/N88,"") -> 1.3327274 | U88: =N88*I88 -> 1384027.5 | V88: =S88*I88 -> 1844531.4 | W88: VENTILACIONES - PROVISION A CARGO DEL COMITENTE | X88: PTO 02 | Y88: =SUMIFS(Cert_App_Output!$G:$G,Cert_App_Output!$E:$E,$E88,Cert_App_Output!$K:$K,$X88) -> 0.95
A89: Albañilería MT | B89: - | C89: - | D89: Albañilería MO | E89: 10.02 | F89: IN | G89: Montaje de conductos de ventilación de parrillas C27 - Provisión a cargo del comitente | H89: gl | I89: 1 | J89: 200000 | K89: 0 | L89: 698144.33 | M89: 13472.165 | N89: =SUM(J89:M89) -> 911616.49 | O89: =IF($N89=0,$S89,J89/$N89*$S89) -> 266545.49 | P89: =IF($N89=0,0,K89/$N89*$S89) -> 0 | Q89: =IF($N89=0,0,L89/$N89*$S89) -> 930436.09 | R89: =IF($N89=0,0,M89/$N89*$S89) -> 17954.724 | S89: 1214936.3 | T89: =IFERROR(S89/N89,"") -> 1.3327274 | U89: =N89*I89 -> 911616.49 | V89: =S89*I89 -> 1214936.3 | W89: VENTILACIONES - PROVISION A CARGO DEL COMITENTE | X89: PTO 02 | Y89: =SUMIFS(Cert_App_Output!$G:$G,Cert_App_Output!$E:$E,$E89,Cert_App_Output!$K:$K,$X89) -> 0.8
A90: Albañilería MT | B90: - | C90: - | D90: Albañilería MO | E90: 10.03 | F90: IN | G90: Montaje de campanas de parrillas C22 - Provisión a cargo del comitente | H90: gl | I90: 1 | J90: 50000 | K90: 0 | L90: 349072.16 | M90: 5986.0824 | N90: =SUM(J90:M90) -> 405058.25 | O90: =IF($N90=0,$S90,J90/$N90*$S90) -> 66636.371 | P90: =IF($N90=0,0,K90/$N90*$S90) -> 0 | Q90: =IF($N90=0,0,L90/$N90*$S90) -> 465218.05 | R90: =IF($N90=0,0,M90/$N90*$S90) -> 7977.8162 | S90: 539832.23 | T90: =IFERROR(S90/N90,"") -> 1.3327274 | U90: =N90*I90 -> 405058.25 | V90: =S90*I90 -> 539832.23 | W90: VENTILACIONES - PROVISION A CARGO DEL COMITENTE | X90: PTO 02 | Y90: =SUMIFS(Cert_App_Output!$G:$G,Cert_App_Output!$E:$E,$E90,Cert_App_Output!$K:$K,$X90) -> 0
A91: Albañilería MT | B91: - | C91: - | D91: Albañilería MO | E91: 10.04 | F91: IN | G91: Montaje de sombreretes en chapa prepintada C25 - Provisión a cargo del comitente | H91: u | I91: 10 | J91: 20000 | K91: 0 | L91: 23271.478 | M91: 649.07216 | N91: =SUM(J91:M91) -> 43920.55 | O91: =IF($N91=0,$S91,J91/$N91*$S91) -> 26654.549 | P91: =IF($N91=0,0,K91/$N91*$S91) -> 0 | Q91: =IF($N91=0,0,L91/$N91*$S91) -> 31014.536 | R91: =IF($N91=0,0,M91/$N91*$S91) -> 865.03627 | S91: 58534.121 | T91: =IFERROR(S91/N91,"") -> 1.3327274 | U91: =N91*I91 -> 439205.5 | V91: =S91*I91 -> 585341.21 | W91: VENTILACIONES - PROVISION A CARGO DEL COMITENTE | X91: PTO 02 | Y91: =SUMIFS(Cert_App_Output!$G:$G,Cert_App_Output!$E:$E,$E91,Cert_App_Output!$K:$K,$X91) -> 0
A92: - | B92: - | C92: - | D92: - | E92: 11 | G92: PISOS - PROVISION A CARGO DEL COMITENTE | W92: PISOS - PROVISION A CARGO DEL COMITENTE | X92: PTO 02
A93: - | B93: - | C93: - | D93: - | E93: 11.01 | F93: OK | G93: Provisión y ejecución de alisado de cemento a la llana metálica, e: 6,00 cm | H93: m2 | I93: 0 | J93: 0 | K93: 0 | L93: 0 | M93: 0 | N93: =SUM(J93:M93) -> 0 | O93: =IF($N93=0,$S93,J93/$N93*$S93) -> 0 | P93: =IF($N93=0,0,K93/$N93*$S93) -> 0 | Q93: =IF($N93=0,0,L93/$N93*$S93) -> 0 | R93: =IF($N93=0,0,M93/$N93*$S93) -> 0 | S93: 0 | T93: =IFERROR(S93/N93,"") | U93: =N93*I93 -> 0 | V93: =S93*I93 -> 0 | W93: PISOS - PROVISION A CARGO DEL COMITENTE | X93: PTO 02 | Y93: =SUMIFS(Cert_App_Output!$G:$G,Cert_App_Output!$E:$E,$E93,Cert_App_Output!$K:$K,$X93) -> 0
A94: Revestimiento MT | B94: - | C94: - | D94: Revestimiento MO | E94: 11.02 | F94: OK | G94: Provisión y ejecución de cemento alisado arrodillado, e: 3,00 cm | H94: m2 | I94: 39 | J94: 4066.3296 | K94: 0 | L94: 10118.034 | M94: 282.12078 | N94: =SUM(J94:M94) -> 14466.484 | O94: =IF($N94=0,$S94,J94/$N94*$S94) -> 5419.3089 | P94: =IF($N94=0,0,K94/$N94*$S94) -> 0 | Q94: =IF($N94=0,0,L94/$N94*$S94) -> 13484.581 | R94: =IF($N94=0,0,M94/$N94*$S94) -> 375.9901 | S94: 19279.88 | T94: =IFERROR(S94/N94,"") -> 1.3327274 | U94: =N94*I94 -> 564192.88 | V94: =S94*I94 -> 751915.32 | W94: PISOS - PROVISION A CARGO DEL COMITENTE | X94: PTO 02 | Y94: =SUMIFS(Cert_App_Output!$G:$G,Cert_App_Output!$E:$E,$E94,Cert_App_Output!$K:$K,$X94) -> 0
A95: Revestimiento MT | B95: - | C95: - | D95: Revestimiento MO | E95: 11.03 | F95: OK | G95: Colocación de porcelanato a definir en sspacios comunes - Provisión a cargo del comitente | H95: m2 | I95: 48 | J95: 7156.2986 | K95: 0 | L95: 11647.705 | M95: 225.81275 | N95: =SUM(J95:M95) -> 19029.817 | O95: =IF($N95=0,$S95,J95/$N95*$S95) -> 9537.3954 | P95: =IF($N95=0,0,K95/$N95*$S95) -> 0 | Q95: =IF($N95=0,0,L95/$N95*$S95) -> 15523.216 | R95: =IF($N95=0,0,M95/$N95*$S95) -> 300.94684 | S95: 25361.559 | T95: =IFERROR(S95/N95,"") -> 1.3327274 | U95: =N95*I95 -> 913431.2 | V95: =S95*I95 -> 1217354.8 | W95: PISOS - PROVISION A CARGO DEL COMITENTE | X95: PTO 02 | Y95: =SUMIFS(Cert_App_Output!$G:$G,Cert_App_Output!$E:$E,$E95,Cert_App_Output!$K:$K,$X95) -> 0
A96: Revestimiento MT | B96: - | C96: Revestimiento MO | D96: Revestimiento MO | E96: 11.04 | F96: OK | G96: Colocación de pavimento intertrabado de H°, incluye provisión y colocación de cama de arena + tomado de junta - Provisión a cargo del comitente | H96: m2 | I96: 174 | J96: 1303.439 | K96: 1609.1954 | L96: 11254.144 | M96: 212.50168 | N96: =SUM(J96:M96) -> 14379.281 | O96: =IF($N96=0,$S96,J96/$N96*$S96) -> 1737.1289 | P96: =IF($N96=0,0,K96/$N96*$S96) -> 2144.6188 | Q96: =IF($N96=0,0,L96/$N96*$S96) -> 14998.707 | R96: =IF($N96=0,0,M96/$N96*$S96) -> 283.20682 | S96: 19163.662 | T96: =IFERROR(S96/N96,"") -> 1.3327274 | U96: =N96*I96 -> 2501994.8 | V96: =S96*I96 -> 3334477.1 | W96: PISOS - PROVISION A CARGO DEL COMITENTE | X96: PTO 02 | Y96: =SUMIFS(Cert_App_Output!$G:$G,Cert_App_Output!$E:$E,$E96,Cert_App_Output!$K:$K,$X96) -> 0
A97: Revestimiento MT | B97: - | C97: Revestimiento MO | D97: Revestimiento MO | E97: 11.05 | F97: OK | G97: Colocación de garden block, incluye provisión y colocación de cama de arena + tomado de junta - Provisión a cargo del comitente | H97: m2 | I97: 92 | J97: 1303.439 | K97: 1609.1954 | L97: 11254.144 | M97: 212.50168 | N97: =SUM(J97:M97) -> 14379.281 | O97: =IF($N97=0,$S97,J97/$N97*$S97) -> 1737.1289 | P97: =IF($N97=0,0,K97/$N97*$S97) -> 2144.6188 | Q97: =IF($N97=0,0,L97/$N97*$S97) -> 14998.707 | R97: =IF($N97=0,0,M97/$N97*$S97) -> 283.20682 | S97: 19163.662 | T97: =IFERROR(S97/N97,"") -> 1.3327274 | U97: =N97*I97 -> 1322893.8 | V97: =S97*I97 -> 1763056.9 | W97: PISOS - PROVISION A CARGO DEL COMITENTE | X97: PTO 02 | Y97: =SUMIFS(Cert_App_Output!$G:$G,Cert_App_Output!$E:$E,$E97,Cert_App_Output!$K:$K,$X97) -> 0
A98: Revestimiento MT | B98: - | C98: - | D98: Revestimiento MO | E98: 11.06 | F98: OK | G98: Provisión y colocación de relleno de piedra binder | H98: m2 | I98: 8 | J98: 2773.008 | K98: 0 | L98: 7607.5726 | M98: 155.70871 | N98: =SUM(J98:M98) -> 10536.289 | O98: =IF($N98=0,$S98,J98/$N98*$S98) -> 3695.6638 | P98: =IF($N98=0,0,K98/$N98*$S98) -> 0 | Q98: =IF($N98=0,0,L98/$N98*$S98) -> 10138.821 | R98: =IF($N98=0,0,M98/$N98*$S98) -> 207.51727 | S98: 14042.002 | T98: =IFERROR(S98/N98,"") -> 1.3327274 | U98: =N98*I98 -> 84290.314 | V98: =S98*I98 -> 112336.01 | W98: PISOS - PROVISION A CARGO DEL COMITENTE | X98: PTO 02 | Y98: =SUMIFS(Cert_App_Output!$G:$G,Cert_App_Output!$E:$E,$E98,Cert_App_Output!$K:$K,$X98) -> 0
A99: Revestimiento MT | B99: - | C99: - | D99: Revestimiento MO | E99: 11.07 | F99: OK | G99: Colocación de baldoson granítico vereda 40 x 40 - Provisión a cargo del comitente | H99: m2 | I99: 46 | J99: 7701.7949 | K99: 0 | L99: 11983.97 | M99: 295.28648 | N99: =SUM(J99:M99) -> 19981.052 | O99: =IF($N99=0,$S99,J99/$N99*$S99) -> 10264.393 | P99: =IF($N99=0,0,K99/$N99*$S99) -> 0 | Q99: =IF($N99=0,0,L99/$N99*$S99) -> 15971.366 | R99: =IF($N99=0,0,M99/$N99*$S99) -> 393.53639 | S99: 26629.296 | T99: =IFERROR(S99/N99,"") -> 1.3327274 | U99: =N99*I99 -> 919128.39 | V99: =S99*I99 -> 1224947.6 | W99: PISOS - PROVISION A CARGO DEL COMITENTE | X99: PTO 02 | Y99: =SUMIFS(Cert_App_Output!$G:$G,Cert_App_Output!$E:$E,$E99,Cert_App_Output!$K:$K,$X99) -> 0
A100: Revestimiento MT | B100: - | C100: - | D100: Revestimiento MO | E100: 11.08 | F100: OK | G100: Colocación de porcelanato a definir Interior UF - Provisión a cargo del comitente | H100: m2 | I100: 562 | J100: 7156.2986 | K100: 0 | L100: 11647.705 | M100: 225.81275 | N100: =SUM(J100:M100) -> 19029.817 | O100: =IF($N100=0,$S100,J100/$N100*$S100) -> 9537.3954 | P100: =IF($N100=0,0,K100/$N100*$S100) -> 0 | Q100: =IF($N100=0,0,L100/$N100*$S100) -> 15523.216 | R100: =IF($N100=0,0,M100/$N100*$S100) -> 300.94684 | S100: 25361.559 | T100: =IFERROR(S100/N100,"") -> 1.3327274 | U100: =N100*I100 -> 10694757 | V100: =S100*I100 -> 14253196 | W100: PISOS - PROVISION A CARGO DEL COMITENTE | X100: PTO 02 | Y100: =SUMIFS(Cert_App_Output!$G:$G,Cert_App_Output!$E:$E,$E100,Cert_App_Output!$K:$K,$X100) -> 0
A101: Revestimiento MT | B101: - | C101: - | D101: Revestimiento MO | E101: 11.09 | F101: OK | G101: Colocación de porcelanato a definir Baños - Provisión a cargo del comitente | H101: m2 | I101: 73 | J101: 7156.2986 | K101: 0 | L101: 15142.017 | M101: 293.55657 | N101: =SUM(J101:M101) -> 22591.872 | O101: =IF($N101=0,$S101,J101/$N101*$S101) -> 9537.3954 | P101: =IF($N101=0,0,K101/$N101*$S101) -> 0 | Q101: =IF($N101=0,0,L101/$N101*$S101) -> 20180.181 | R101: =IF($N101=0,0,M101/$N101*$S101) -> 391.23089 | S101: 30108.808 | T101: =IFERROR(S101/N101,"") -> 1.3327274 | U101: =N101*I101 -> 1649206.7 | V101: =S101*I101 -> 2197942.9 | W101: PISOS - PROVISION A CARGO DEL COMITENTE | X101: PTO 02 | Y101: =SUMIFS(Cert_App_Output!$G:$G,Cert_App_Output!$E:$E,$E101,Cert_App_Output!$K:$K,$X101) -> 0
A102: Revestimiento MT | B102: - | C102: - | D102: Revestimiento MO | E102: 11.1 | F102: OK | G102: Colocación de porcelanato a definir Balcones - Provisión a cargo del comitente | H102: m2 | I102: 143 | J102: 7156.2986 | K102: 0 | L102: 11647.705 | M102: 225.81275 | N102: =SUM(J102:M102) -> 19029.817 | O102: =IF($N102=0,$S102,J102/$N102*$S102) -> 9537.3954 | P102: =IF($N102=0,0,K102/$N102*$S102) -> 0 | Q102: =IF($N102=0,0,L102/$N102*$S102) -> 15523.216 | R102: =IF($N102=0,0,M102/$N102*$S102) -> 300.94684 | S102: 25361.559 | T102: =IFERROR(S102/N102,"") -> 1.3327274 | U102: =N102*I102 -> 2721263.8 | V102: =S102*I102 -> 3626702.9 | W102: PISOS - PROVISION A CARGO DEL COMITENTE | X102: PTO 02 | Y102: =SUMIFS(Cert_App_Output!$G:$G,Cert_App_Output!$E:$E,$E102,Cert_App_Output!$K:$K,$X102) -> 0
A103: Revestimiento MT | B103: - | C103: - | D103: Revestimiento MO | E103: 11.11 | F103: OK | G103: Colocación de porcelanato a definir Palier - Provisión a cargo del comitente | H103: m2 | I103: 106 | J103: 7156.2986 | K103: 0 | L103: 11647.705 | M103: 225.81275 | N103: =SUM(J103:M103) -> 19029.817 | O103: =IF($N103=0,$S103,J103/$N103*$S103) -> 9537.3954 | P103: =IF($N103=0,0,K103/$N103*$S103) -> 0 | Q103: =IF($N103=0,0,L103/$N103*$S103) -> 15523.216 | R103: =IF($N103=0,0,M103/$N103*$S103) -> 300.94684 | S103: 25361.559 | T103: =IFERROR(S103/N103,"") -> 1.3327274 | U103: =N103*I103 -> 2017160.6 | V103: =S103*I103 -> 2688325.2 | W103: PISOS - PROVISION A CARGO DEL COMITENTE | X103: PTO 02 | Y103: =SUMIFS(Cert_App_Output!$G:$G,Cert_App_Output!$E:$E,$E103,Cert_App_Output!$K:$K,$X103) -> 0
A104: - | B104: - | C104: - | D104: - | E104: 12 | G104: ZOCALOS Y SOLIAS - PROVISION A CARGO DEL COMITENTE | W104: ZOCALOS Y SOLIAS - PROVISION A CARGO DEL COMITENTE | X104: PTO 02
A105: Revestimiento MT | B105: - | C105: - | D105: Revestimiento MO | E105: 12.01 | F105: OK | G105: Ejecución de zócalo de concreto h: 10 cm | H105: ml | I105: 19 | J105: 809.61503 | K105: 0 | L105: 3938.2618 | M105: 126.07067 | N105: =SUM(J105:M105) -> 4873.9475 | O105: =IF($N105=0,$S105,J105/$N105*$S105) -> 1078.9962 | P105: =IF($N105=0,0,K105/$N105*$S105) -> 0 | Q105: =IF($N105=0,0,L105/$N105*$S105) -> 5248.6295 | R105: =IF($N105=0,0,M105/$N105*$S105) -> 168.01784 | S105: 6495.6435 | T105: =IFERROR(S105/N105,"") -> 1.3327274 | U105: =N105*I105 -> 92605.002 | V105: =S105*I105 -> 123417.23 | W105: ZOCALOS Y SOLIAS - PROVISION A CARGO DEL COMITENTE | Y105: =SUMIFS(Cert_App_Output!$G:$G,Cert_App_Output!$E:$E,$E105,Cert_App_Output!$K:$K,$X105) -> 0
A106: Revestimiento MT | B106: - | C106: - | D106: Revestimiento MO | E106: 12.02 | F106: OK | G106: Provisión y colocación de zócalo de MDF prepintado color bco. h: 7cm | H106: ml | I106: 626 | J106: 3500 | K106: 0 | L106: 3196.2174 | M106: 100.44326 | N106: =SUM(J106:M106) -> 6796.6606 | O106: =IF($N106=0,$S106,J106/$N106*$S106) -> 4664.546 | P106: =IF($N106=0,0,K106/$N106*$S106) -> 0 | Q106: =IF($N106=0,0,L106/$N106*$S106) -> 4259.6865 | R106: =IF($N106=0,0,M106/$N106*$S106) -> 133.86349 | S106: 9058.096 | T106: =IFERROR(S106/N106,"") -> 1.3327274 | U106: =N106*I106 -> 4254709.6 | V106: =S106*I106 -> 5670368.1 | W106: ZOCALOS Y SOLIAS - PROVISION A CARGO DEL COMITENTE | X106: PTO 02 | Y106: =SUMIFS(Cert_App_Output!$G:$G,Cert_App_Output!$E:$E,$E106,Cert_App_Output!$K:$K,$X106) -> 0
A107: Revestimiento MT | B107: - | C107: - | D107: Revestimiento MO | E107: 12.03 | F107: OK | G107: Colocación de zócalo de porcelanato - Provisión a cargo del comitente | H107: ml | I107: 386 | J107: 1066.3432 | K107: 0 | L107: 5047.339 | M107: 97.85219 | N107: =SUM(J107:M107) -> 6211.5344 | O107: =IF($N107=0,$S107,J107/$N107*$S107) -> 1421.1449 | P107: =IF($N107=0,0,K107/$N107*$S107) -> 0 | Q107: =IF($N107=0,0,L107/$N107*$S107) -> 6726.7271 | R107: =IF($N107=0,0,M107/$N107*$S107) -> 130.4103 | S107: 8278.2823 | T107: =IFERROR(S107/N107,"") -> 1.3327274 | U107: =N107*I107 -> 2397652.3 | V107: =S107*I107 -> 3195416.9 | W107: ZOCALOS Y SOLIAS - PROVISION A CARGO DEL COMITENTE | X107: PTO 02 | Y107: =SUMIFS(Cert_App_Output!$G:$G,Cert_App_Output!$E:$E,$E107,Cert_App_Output!$K:$K,$X107) -> 0
A108: - | B108: - | C108: - | D108: - | E108: 13 | G108: REVESTIMIENTOS - PROVISION A CARGO DEL COMITENTE | W108: REVESTIMIENTOS - PROVISION A CARGO DEL COMITENTE | X108: PTO 02
A109: Revestimiento MT | B109: - | C109: - | D109: Revestimiento MO | E109: 13.01 | F109: OK | G109: Colocación de porcelanato en baños - Provisión a cargo del comitente | H109: m2 | I109: 413 | J109: 7156.2986 | K109: 0 | L109: 15142.017 | M109: 293.55657 | N109: =SUM(J109:M109) -> 22591.872 | O109: =IF($N109=0,$S109,J109/$N109*$S109) -> 9537.3954 | P109: =IF($N109=0,0,K109/$N109*$S109) -> 0 | Q109: =IF($N109=0,0,L109/$N109*$S109) -> 20180.181 | R109: =IF($N109=0,0,M109/$N109*$S109) -> 391.23089 | S109: 30108.808 | T109: =IFERROR(S109/N109,"") -> 1.3327274 | U109: =N109*I109 -> 9330443.2 | V109: =S109*I109 -> 12434938 | W109: REVESTIMIENTOS - PROVISION A CARGO DEL COMITENTE | X109: PTO 02 | Y109: =SUMIFS(Cert_App_Output!$G:$G,Cert_App_Output!$E:$E,$E109,Cert_App_Output!$K:$K,$X109) -> 0
A110: Revestimiento MT | B110: - | C110: - | D110: Revestimiento MO | E110: 13.02 | F110: OK | G110: Colocación de revestimiento en cocinas - Provisión a cargo del comitente | H110: m2 | I110: 18 | J110: 7156.2986 | K110: 0 | L110: 15142.017 | M110: 293.55657 | N110: =SUM(J110:M110) -> 22591.872 | O110: =IF($N110=0,$S110,J110/$N110*$S110) -> 9537.3954 | P110: =IF($N110=0,0,K110/$N110*$S110) -> 0 | Q110: =IF($N110=0,0,L110/$N110*$S110) -> 20180.181 | R110: =IF($N110=0,0,M110/$N110*$S110) -> 391.23089 | S110: 30108.808 | T110: =IFERROR(S110/N110,"") -> 1.3327274 | U110: =N110*I110 -> 406653.7 | V110: =S110*I110 -> 541958.54 | W110: REVESTIMIENTOS - PROVISION A CARGO DEL COMITENTE | X110: PTO 02 | Y110: =SUMIFS(Cert_App_Output!$G:$G,Cert_App_Output!$E:$E,$E110,Cert_App_Output!$K:$K,$X110) -> 0
...

Sheet 1_GGBB
H2: 45679 | O2: 26
F3: MESES | G3: DÓLAR BNA | H3: DÓLAR MEP | M3: Descrip | N3: Mes | O3: Total Dias
B4: GASTOS GENERALES y BENEFICIO | F4: =+ROUNDUP(N17,0) -> 17 | G4: 1066.5 | H4: 1170 | M4: Prelim | N4: 1 | O4: =+N4*$O$2 -> 26 | Q4: Syh permanente
M5: Mov de suelos y excav. | N5: 2.5 | O5: =+N5*$O$2 -> 65 | Q5: =+ROUNDUP(SUM(N4:N5),0) -> 4
B6: Gastos Grales de obra en items | C6: U | D6: Cant | F6: Precio Unit | G6: Subtotal | H6: =SUM(G7:G10) -> 0 | M6: Losa sobre PB | N6: 1 | O6: =+N6*$O$2 -> 26
B7: Oficina en obra (6x3 c/AA) | C7: mes | D7: =+$F$4 -> 17 | E7: 0 | F7: =E7*I7+J7 -> 0 | G7: =+F7*D7*E7 -> 0 | M7: Losa sobre 1 | N7: 0.75 | O7: =+N7*$O$2 -> 19.5
B8: Obrador 6x3 s/AA | C8: mes | D8: =+$F$4 -> 17 | E8: 0 | F8: =E8*I8+J8 -> 0 | G8: =+F8*D8*E8 -> 0 | M8: Losa sobre 2 | N8: 0.75 | O8: =+N8*$O$2 -> 19.5
B9: Pañol (6x3) | C9: mes | D9: =+$F$4 -> 17 | E9: 1 | F9: =E9*I9+J9 -> 0 | G9: =+F9*D9*E9 -> 0 | M9: Losa sobre 3 | N9: 0.75 | O9: =+N9*$O$2 -> 19.5 | P9: Inicio mamposteria
B10: Baños | C10: mes | D10: =+$F$4 -> 17 | E10: 2 | F10: =E10*I10+J10 -> 0 | G10: =+F10*D10*E10 -> 0 | M10: Losa sobre 4 | N10: 0.75 | O10: =+N10*$O$2 -> 19.5
B11: Gastos Grales de obra en items | H11: =SUM(G12:G19) -> 32379395 | M11: Losa sobre SM | N11: 0.5 | O11: =+N11*$O$2 -> 13 | Q11: Meses H° | R11: Estacionamiento en contramano
B12: HyS permanente | C12: mes | D12: =+Q5 -> 4 | E12: 1 | J12: 1504670.3 | K12: =+J12*D12*E12 -> 6018681.2 | M12: Mampostería | N12: 2 | O12: =+N12*$O$2 -> 52 | Q12: =+SUM(N5:N11) -> 7 | R12: =+ROUNDUP(Q12/3,0) -> 3
B13: HyS | C13: mes | D13: =+$F$4 -> 17 | E13: 1 | J13: 150000 | K13: =+J13*D13*E13 -> 2550000 | M13: Revoques, contrap y carp | N13: 2 | O13: =+N13*$O$2 -> 52
B14: Energía de obra | C14: mes | D14: =+$F$4 -> 17 | E14: 0.5 | F14: 200000 | G14: =+F14*D14*E14 -> 1700000 | M14: Colocación | N14: 2 | O14: =+N14*$O$2 -> 52
B15: Agua de obra | C15: mes | D15: =+$F$4 -> 17 | E15: 1 | F15: 250000 | G15: =+F15*D15*E15 -> 4250000 | M15: Pintura | N15: 2 | O15: =+N15*$O$2 -> 52
B16: Internet | C16: mes | D16: =+$F$4 -> 17 | E16: 1 | F16: 50000 | G16: =+F16*D16*E16 -> 850000 | M16: Terminaciones | N16: 1 | O16: =+N16*$O$2 -> 26
B17: Alquiler cerco de obra chapa | C17: mes | D17: =+$F$4 -> 17 | E17: 0 | F17: 10000 | G17: =+F17*D17*E17 -> 0 | N17: =SUM(N4:N16) -> 17 | O17: =SUM(O4:O16) -> 442
B18: Proyecto Ejecutivo | C18: mes | D18: =+$F$4 -> 17 | E18: 0 | F18: 3009340.6 | G18: =+F18*D18*E18 -> 0
B19: Proyecto (50%) | C19: mes | D19: =+$F$4 -> 17 | E19: 0.5 | F19: 3009340.6 | G19: =+F19*D19*E19 -> 25579395
B20: Gastos Directos | H20: =SUM(G21:G31) -> 60580518
B21: Coordinacion de obra | C21: mes | D21: =+$F$4 -> 17 | E21: 0.15 | F21: 5273644.1 | G21: =+F21*D21*E21 -> 13447792
B22: Jefe de obra | C22: mes | D22: =+$F$4 -> 17 | E22: 1 | J22: 4372210.6 | K22: =+J22*D22*E22 -> 74327580
B23: Sobrestante | C23: mes | D23: =+$F$4 -> 17 | E23: 0 | F23: 3009340.6 | G23: =+F23*D23*E23 -> 0
B24: Administrativo en obra | C24: mes | D24: =+$F$4 -> 17 | E24: 0 | F24: =+F23 -> 3009340.6 | G24: =+F24*D24*E24 -> 0
B25: Capataz | C25: mes | D25: =+$F$4 -> 17 | E25: 0.5 | F25: 3545026.5 | G25: =+F25*D25*E25 -> 30132725
B26: Logistica | C26: mes | D26: =+$F$4 -> 17 | E26: 1 | F26: 500000 | G26: =+F26*D26*E26 -> 8500000
B27: Vehiculo obra | C27: mes | D27: =+$F$4 -> 17 | E27: 1 | F27: =F26 -> 500000 | G27: =+F27*D27*E27 -> 8500000
B28: Mov y viaticos | C28: mes | D28: =+$F$4 -> 17 | E28: 1 | J28: =F26 -> 500000 | K28: =+J28*D28*E28 -> 8500000
B29: UOCRA | C29: mes | D29: =+$F$4 -> 17 | E29: 1 | G29: =+F29*D29*E29 -> 0
B30: Pañolero/Sereno | C30: mes | D30: =+$F$4 -> 17 | E30: 1 | J30: 730326.97 | K30: =+J30*D30*E30 -> 12415558
B32: Equipos | H32: =SUM(G33:G41) -> 0
B33: Bobcat | C33: mes | F33: 130000 | G33: =+F33*D33 -> 0
B34: Camion limpieza | C34: mes | F34: 100000 | G34: =+F34*D34 -> 0
B35: Tijera electrica 12 | C35: mes | F35: 33600 | G35: =+F35*D35 -> 0
B36: JLG | C36: mes | F36: 89000 | G36: =+F36*D36 -> 0
B37: Grua 20ton | C37: mes | F37: 70000 | G37: =+F37*D37 -> 0
B42: Gastos Indirectos | H42: =SUM(G43:G48) -> 82753395
B43: Admin (50%Compras - 50%RRHH) | C43: mes | D43: =+$F$4 -> 17 | E43: 0.5 | F43: 3009340.6 | G43: =+F43*D43*E43 -> 25579395
B44: Seguros | C44: gl | D44: =+D43 -> 17 | E44: 1 | F44: 250000 | G44: =+F44*D44 -> 4250000
B45: IIBB (monto venta obra gris) | C45: gl | D45: 0.04 | E45: 0.7 | F45: 1400000000 | G45: =+F45*D45*E45 -> 39200000
B46: Imp cheque | C46: gl | D46: =1.2/100 -> 0.012 | E46: =+E45 -> 0.7 | F46: =+F45*1.15 -> 1.61e+09 | G46: =+F46*D46*E46 -> 13524000
B47: Contrato | C47: gl | D47: 1 | E47: 1 | F47: 200000 | G47: =+F47*D47*E47 -> 200000
G49: =SUM(G7:G48) -> 1.7571331e+08 | H49: =SUM(H6:H48) -> 1.7571331e+08 | K49: =SUM(K6:K48) -> 1.0381182e+08 | L49: =+H49+K49 -> 2.7952513e+08
B50: Monto puesto en Ayuda de gremio que no se eroga | K50: Imputados en pres | L50: Total GGBB
B51: Total de Gastos Generales | H51: =+H50+H49 -> 1.7571331e+08
B53: Otro | G53: 2.9493528e+08 | H53: =+G53/$H$4 -> 252081.44 | J53: =+H53/$H$59 -> 0.29208306 | K53: =+H53/$H$69 -> 0.21916189
B54: Corralon | G54: 64860920 | H54: =+G54/$H$4 -> 55436.684 | J54: =+H54/$H$59 -> 0.064233672 | K54: =+H54/$H$69 -> 0.048197157
B55: Subcontratos | G55: 4.6047904e+08 | H55: =+G55/$H$4 -> 393571.83 | J55: =+H55/$H$59 -> 0.4560259 | K55: =+H55/$H$69 -> 0.34217492
B56: Mano de obra | G56: 1.6799537e+08 | H56: =+G56/$H$4 -> 143585.78 | J56: =+H56/$H$59 -> 0.16637074 | K56: =+H56/$H$69 -> 0.12483479
B57: Equipos | G57: 21494483 | H57: =+G57/$H$4 -> 18371.353 | K57: =SUM(K53:K56) -> 0.73436876
J58: =SUM(J53:J57) -> 0.97871338 | L58: =1-J58 -> 0.021286617
A59: A | G59: =SUM(G53:G58) -> 1.0097651e+09 | H59: =SUM(H53:H58) -> 863047.09
J60: =+G57/G59 -> 0.021286617
B61: GG | F61: =+H51/G59 -> 0.17401404 | G61: =+F61*$G$59 -> 1.7571331e+08 | H61: =+G61/$H$4 -> 150182.31 | J61: 0.03
B62: Equipos | E62: 3 | F62: =+J62 -> 0.0087133829 | G62: =+F62*$G$59 -> 8798469.9 | H62: =+G62/$H$4 -> 7520.0597 | J62: =+J61-J60 -> 0.0087133829
B63: Imprevistos + Negociacion | E63: 5 | F63: =0.05 -> 0.05 | G63: =+F63*$G$59 -> 50488255 | H63: =+G63/$H$4 -> 43152.354
B64: Beneficio | E64: 9 | F64: 0.1 | G64: =+F64*$G$59 -> 1.0097651e+08 | H64: =+G64/$H$4 -> 86304.709
A65: B | F65: =SUM(F61:F64) -> 0.33272743 | G65: =SUM(G61:G64) -> 3.3597654e+08 | H65: =+G65/$H$4 -> 287159.44 | K65: =+H65/H69 -> 0.24965902
A67: K | F67: =1+F65 -> 1.3327274 | G67: =+G59*F67 -> 1.3457416e+09
A69: A+B | G69: =+G59+G65 -> 1.3457416e+09 | H69: =+G69/$H$4 -> 1150206.5 | K69: =SUM(K57:K65) -> 0.98402778

Sheet 2_Movimientos
A1: Cuenta | B1: Desc Cuenta | C1: Fecha Asiento | D1: Nº Asiento | E1: Observaciones | F1: Cliente/Proveedor | G1: Cód Comprobante | H1: Nº Comprobante | I1: Debe | J1: Haber | K1: Unidad | L1: Desc Unidad | M1: Centro de Costo | N1: Desc Centro Costo | O1: Saldo Inicial | P1: Observaciones original | Q1: mov_id | R1: mov_tipo
A2: 410222 | B2: Obra civil Reforma | C2: 45784 | D2: 2442 | E2: Obras - Garcia del Rio 3760 CA | F2: Garcia del Rio 3760 CABA Fideicomiso | G2: FAWS | H2: 300000653 | I2: 0 | J2: 44000000 | K2: DESA | L2: Desarrollos | M2: GDR | N2: García del Río 3760 | O2: 0 | Q2: =IFERROR(TRIM(LEFT($E2,FIND(" | ",$E2)-1)),"") | R2: =IFERROR(TRIM(UPPER(MID($E2,FIND(" | ",$E2)+3,IFERROR(FIND(" | ",$E2,FIND(" | ",$E2)+3),LEN($E2)+1)-FIND(" | ",$E2)-3))),"")
A3: 410222 | B3: Obra civil Reforma | C3: 45838 | D3: 3476 | E3: Obras - Garcia del Rio 3760 CA | F3: Garcia del Rio 3760 CABA Fideicomiso | G3: FAWS | H3: 300000683 | I3: 0 | J3: 34000000 | K3: DESA | L3: Desarrollos | M3: GDR | N3: García del Río 3760 | O3: 0 | Q3: =IFERROR(TRIM(LEFT($E3,FIND(" | ",$E3)-1)),"") | R3: =IFERROR(TRIM(UPPER(MID($E3,FIND(" | ",$E3)+3,IFERROR(FIND(" | ",$E3,FIND(" | ",$E3)+3),LEN($E3)+1)-FIND(" | ",$E3)-3))),"")
A4: 410222 | B4: Obra civil Reforma | C4: 45866 | D4: 3872 | E4: Obras - Garcia del Rio 3760 CA | F4: Garcia del Rio 3760 CABA Fideicomiso | G4: FAWS | H4: 300000699 | I4: 0 | J4: 27500000 | K4: DESA | L4: Desarrollos | M4: GDR | N4: García del Río 3760 | O4: 0 | Q4: =IFERROR(TRIM(LEFT($E4,FIND(" | ",$E4)-1)),"") | R4: =IFERROR(TRIM(UPPER(MID($E4,FIND(" | ",$E4)+3,IFERROR(FIND(" | ",$E4,FIND(" | ",$E4)+3),LEN($E4)+1)-FIND(" | ",$E4)-3))),"")
A5: 410222 | B5: Obra civil Reforma | C5: 45869 | D5: 3914 | E5: Obras - Garcia del Rio 3760 CA | F5: Garcia del Rio 3760 CABA Fideicomiso | G5: FAWS | H5: 300000704 | I5: 0 | J5: 20000000 | K5: DESA | L5: Desarrollos | M5: GDR | N5: García del Río 3760 | O5: 0 | Q5: =IFERROR(TRIM(LEFT($E5,FIND(" | ",$E5)-1)),"") | R5: =IFERROR(TRIM(UPPER(MID($E5,FIND(" | ",$E5)+3,IFERROR(FIND(" | ",$E5,FIND(" | ",$E5)+3),LEN($E5)+1)-FIND(" | ",$E5)-3))),"")
A6: 410222 | B6: Obra civil Reforma | C6: 45891 | D6: 4284 | E6: Obras - Garcia del Rio 3760 CA | F6: Garcia del Rio 3760 CABA Fideicomiso | G6: FAWS | H6: 300000719 | I6: 0 | J6: 17731795 | K6: DESA | L6: Desarrollos | M6: GDR | N6: García del Río 3760 | O6: 0 | Q6: =IFERROR(TRIM(LEFT($E6,FIND(" | ",$E6)-1)),"") | R6: =IFERROR(TRIM(UPPER(MID($E6,FIND(" | ",$E6)+3,IFERROR(FIND(" | ",$E6,FIND(" | ",$E6)+3),LEN($E6)+1)-FIND(" | ",$E6)-3))),"")
A7: 410222 | B7: Obra civil Reforma | C7: 45898 | D7: 4424 | E7: Obras - Garcia del Rio 3760 CA | F7: Garcia del Rio 3760 CABA Fideicomiso | G7: FAWS | H7: 300000721 | I7: 0 | J7: 9049773.8 | K7: DESA | L7: Desarrollos | M7: GDR | N7: García del Río 3760 | O7: 0 | Q7: =IFERROR(TRIM(LEFT($E7,FIND(" | ",$E7)-1)),"") | R7: =IFERROR(TRIM(UPPER(MID($E7,FIND(" | ",$E7)+3,IFERROR(FIND(" | ",$E7,FIND(" | ",$E7)+3),LEN($E7)+1)-FIND(" | ",$E7)-3))),"")
A8: 410222 | B8: Obra civil Reforma | C8: 45900 | D8: 4425 | E8: Obras - Garcia del Rio 3760 CA | F8: Garcia del Rio 3760 CABA Fideicomiso | G8: FAWS | H8: 300000722 | I8: 0 | J8: 30190424 | K8: DESA | L8: Desarrollos | M8: GDR | N8: García del Río 3760 | O8: 0 | Q8: =IFERROR(TRIM(LEFT($E8,FIND(" | ",$E8)-1)),"") | R8: =IFERROR(TRIM(UPPER(MID($E8,FIND(" | ",$E8)+3,IFERROR(FIND(" | ",$E8,FIND(" | ",$E8)+3),LEN($E8)+1)-FIND(" | ",$E8)-3))),"")
A9: 410222 | B9: Obra civil Reforma | C9: 45900 | D9: 4426 | E9: Obras - Garcia del Rio 3760 CA | F9: Garcia del Rio 3760 CABA Fideicomiso | G9: FAWS | H9: 300000723 | I9: 0 | J9: 35460488 | K9: DESA | L9: Desarrollos | M9: GDR | N9: García del Río 3760 | O9: 0 | Q9: =IFERROR(TRIM(LEFT($E9,FIND(" | ",$E9)-1)),"") | R9: =IFERROR(TRIM(UPPER(MID($E9,FIND(" | ",$E9)+3,IFERROR(FIND(" | ",$E9,FIND(" | ",$E9)+3),LEN($E9)+1)-FIND(" | ",$E9)-3))),"")
A10: 410222 | B10: Obra civil Reforma | C10: 45930 | D10: 5100 | E10: Obras - Garcia del Rio 3760 CA | F10: Garcia del Rio 3760 CABA Fideicomiso | G10: FAWS | H10: 300000736 | I10: 0 | J10: 22499464 | K10: DESA | L10: Desarrollos | M10: GDR | N10: García del Río 3760 | O10: 0 | Q10: =IFERROR(TRIM(LEFT($E10,FIND(" | ",$E10)-1)),"") | R10: =IFERROR(TRIM(UPPER(MID($E10,FIND(" | ",$E10)+3,IFERROR(FIND(" | ",$E10,FIND(" | ",$E10)+3),LEN($E10)+1)-FIND(" | ",$E10)-3))),"")
A11: 410222 | B11: Obra civil Reforma | C11: 45959 | D11: 5524 | E11: Obras - Garcia del Rio 3760 CA | F11: Garcia del Rio 3760 CABA Fideicomiso | G11: FAWS | H11: 300000754 | I11: 0 | J11: 50900937 | K11: DESA | L11: Desarrollos | M11: GDR | N11: García del Río 3760 | O11: 0 | Q11: =IFERROR(TRIM(LEFT($E11,FIND(" | ",$E11)-1)),"") | R11: =IFERROR(TRIM(UPPER(MID($E11,FIND(" | ",$E11)+3,IFERROR(FIND(" | ",$E11,FIND(" | ",$E11)+3),LEN($E11)+1)-FIND(" | ",$E11)-3))),"")
A12: 410222 | B12: Obra civil Reforma | C12: 46009 | D12: 490 | E12: Obras - Garcia del Rio 3760 CA | F12: Garcia del Rio 3760 CABA Fideicomiso | G12: FAWS | H12: 300000784 | I12: 0 | J12: 33776391 | K12: DESA | L12: Desarrollos | M12: GDR | N12: García del Río 3760 | O12: 0 | Q12: =IFERROR(TRIM(LEFT($E12,FIND(" | ",$E12)-1)),"") | R12: =IFERROR(TRIM(UPPER(MID($E12,FIND(" | ",$E12)+3,IFERROR(FIND(" | ",$E12,FIND(" | ",$E12)+3),LEN($E12)+1)-FIND(" | ",$E12)-3))),"")
A13: 410222 | B13: Obra civil Reforma | C13: 46041 | D13: 988 | E13: Obras - Garcia del Rio 3760 CA | F13: Garcia del Rio 3760 CABA Fideicomiso | G13: FAWS | H13: 300000800 | I13: 0 | J13: 25136093 | K13: DESA | L13: Desarrollos | M13: GDR | N13: García del Río 3760 | O13: 0 | Q13: =IFERROR(TRIM(LEFT($E13,FIND(" | ",$E13)-1)),"") | R13: =IFERROR(TRIM(UPPER(MID($E13,FIND(" | ",$E13)+3,IFERROR(FIND(" | ",$E13,FIND(" | ",$E13)+3),LEN($E13)+1)-FIND(" | ",$E13)-3))),"")
... A18: 410222 | B18: Obra civil Reforma | C18: 46120 | D18: 2138 | E18: Obras - Garcia del Rio 3760 CA | F18: Garcia del Rio 3760 CABA Fideicomiso | G18: FAWS | H18: 300000845 | I18: 0 | J18: 27641241 | K18: DESA | L18: Desarrollos | M18: GDR | N18: García del Río 3760 | O18: 0 | Q18: =IFERROR(TRIM(LEFT($E18,FIND(" | ",$E18)-1)),"") | R18: =IFERROR(TRIM(UPPER(MID($E18,FIND(" | ",$E18)+3,IFERROR(FIND(" | ",$E18,FIND(" | ",$E18)+3),LEN($E18)+1)-FIND(" | ",$E18)-3))),"")
A19: 4201 | B19: Otros ingresos | C19: 45751 | D19: 1405 | E19: A cuent Ant Obra-10000 TC 1300 | G19: OIXX | H19: 185 | I19: 0 | J19: 13000000 | K19: DESA | L19: Desarrollos | M19: GDR | N19: García del Río 3760 | O19: 0 | Q19: =IFERROR(TRIM(LEFT($E19,FIND(" | ",$E19)-1)),"") | R19: =IFERROR(TRIM(UPPER(MID($E19,FIND(" | ",$E19)+3,IFERROR(FIND(" | ",$E19,FIND(" | ",$E19)+3),LEN($E19)+1)-FIND(" | ",$E19)-3))),"")
A20: 4201 | B20: Otros ingresos | C20: 45762 | D20: 1406 | E20: A cta Ant Obra-4000 TC 1270 | G20: OIXX | H20: 186 | I20: 0 | J20: 5080000 | K20: DESA | L20: Desarrollos | M20: GDR | N20: García del Río 3760 | O20: 0 | Q20: =IFERROR(TRIM(LEFT($E20,FIND(" | ",$E20)-1)),"") | R20: =IFERROR(TRIM(UPPER(MID($E20,FIND(" | ",$E20)+3,IFERROR(FIND(" | ",$E20,FIND(" | ",$E20)+3),LEN($E20)+1)-FIND(" | ",$E20)-3))),"")
A21: 4201 | B21: Otros ingresos | C21: 45779 | D21: 1597 | E21: Deposito factura GDR TC 1.190 | G21: OIXX | H21: 193 | I21: 0 | J21: 23800000 | K21: DESA | L21: Desarrollos | M21: GDR | N21: García del Río 3760 | O21: 0 | Q21: =IFERROR(TRIM(LEFT($E21,FIND(" | ",$E21)-1)),"") | R21: =IFERROR(TRIM(UPPER(MID($E21,FIND(" | ",$E21)+3,IFERROR(FIND(" | ",$E21,FIND(" | ",$E21)+3),LEN($E21)+1)-FIND(" | ",$E21)-3))),"")
A22: 4201 | B22: Otros ingresos | C22: 45786 | D22: 1598 | E22: A cta de Deuda de GDR TC 1.555 | G22: OIXX | H22: 194 | I22: 0 | J22: 57750000 | K22: DESA | L22: Desarrollos | M22: GDR | N22: García del Río 3760 | O22: 0 | Q22: =IFERROR(TRIM(LEFT($E22,FIND(" | ",$E22)-1)),"") | R22: =IFERROR(TRIM(UPPER(MID($E22,FIND(" | ",$E22)+3,IFERROR(FIND(" | ",$E22,FIND(" | ",$E22)+3),LEN($E22)+1)-FIND(" | ",$E22)-3))),"")
A23: 4201 | B23: Otros ingresos | C23: 45787 | D23: 1599 | E23: A cta de Deuda de GDR TC 1155 | G23: OIXX | H23: 195 | I23: 0 | J23: 3465000 | K23: DESA | L23: Desarrollos | M23: GDR | N23: García del Río 3760 | O23: 0 | Q23: =IFERROR(TRIM(LEFT($E23,FIND(" | ",$E23)-1)),"") | R23: =IFERROR(TRIM(UPPER(MID($E23,FIND(" | ",$E23)+3,IFERROR(FIND(" | ",$E23,FIND(" | ",$E23)+3),LEN($E23)+1)-FIND(" | ",$E23)-3))),"")
A24: 4201 | B24: Otros ingresos | C24: 45793 | D24: 1600 | E24: A cta de Deuda de GDR TC 1.155 | G24: OIXX | H24: 196 | I24: 0 | J24: 57750000 | K24: DESA | L24: Desarrollos | M24: GDR | N24: García del Río 3760 | O24: 0 | Q24: =IFERROR(TRIM(LEFT($E24,FIND(" | ",$E24)-1)),"") | R24: =IFERROR(TRIM(UPPER(MID($E24,FIND(" | ",$E24)+3,IFERROR(FIND(" | ",$E24,FIND(" | ",$E24)+3),LEN($E24)+1)-FIND(" | ",$E24)-3))),"")
A25: 4201 | B25: Otros ingresos | C25: 45831 | D25: 1969 | E25: Pago Cta Ant-usd 30000 tc 1190 | G25: OIXX | H25: 206 | I25: 0 | J25: 35700000 | K25: DESA | L25: Desarrollos | M25: GDR | N25: García del Río 3760 | O25: 0 | Q25: =IFERROR(TRIM(LEFT($E25,FIND(" | ",$E25)-1)),"") | R25: =IFERROR(TRIM(UPPER(MID($E25,FIND(" | ",$E25)+3,IFERROR(FIND(" | ",$E25,FIND(" | ",$E25)+3),LEN($E25)+1)-FIND(" | ",$E25)-3))),"")
A26: 4201 | B26: Otros ingresos | C26: 45835 | D26: 1970 | E26: Pago Cta Ant-usd 3505 tc 1200 | G26: OIXX | H26: 207 | I26: 0 | J26: 4206000 | K26: DESA | L26: Desarrollos | M26: GDR | N26: García del Río 3760 | O26: 0 | Q26: =IFERROR(TRIM(LEFT($E26,FIND(" | ",$E26)-1)),"") | R26: =IFERROR(TRIM(UPPER(MID($E26,FIND(" | ",$E26)+3,IFERROR(FIND(" | ",$E26,FIND(" | ",$E26)+3),LEN($E26)+1)-FIND(" | ",$E26)-3))),"")
A27: 4201 | B27: Otros ingresos | C27: 45877 | D27: 2072 | E27: cta deu AING-usd 1200 tc 1310 | G27: OIXX | H27: 215 | I27: 0 | J27: 1572000 | K27: DESA | L27: Desarrollos | M27: GDR | N27: García del Río 3760 | O27: 0 | Q27: =IFERROR(TRIM(LEFT($E27,FIND(" | ",$E27)-1)),"") | R27: =IFERROR(TRIM(UPPER(MID($E27,FIND(" | ",$E27)+3,IFERROR(FIND(" | ",$E27,FIND(" | ",$E27)+3),LEN($E27)+1)-FIND(" | ",$E27)-3))),"")
A28: 4201 | B28: Otros ingresos | C28: 45891 | D28: 2073 | E28: A cta d deu AIN-usd 2650 1315 | G28: OIXX | H28: 216 | I28: 0 | J28: 3484750 | K28: DESA | L28: Desarrollos | M28: GDR | N28: García del Río 3760 | O28: 0 | Q28: =IFERROR(TRIM(LEFT($E28,FIND(" | ",$E28)-1)),"") | R28: =IFERROR(TRIM(UPPER(MID($E28,FIND(" | ",$E28)+3,IFERROR(FIND(" | ",$E28,FIND(" | ",$E28)+3),LEN($E28)+1)-FIND(" | ",$E28)-3))),"")
A29: 5101 | B29: Sueldos | C29: 45845 | D29: 1738 | E29: Javier Antequera - 06-2025 | G29: OPXX | H29: 7138 | I29: 3500000 | J29: 0 | K29: DESA | L29: Desarrollos | M29: GDR | N29: García del Río 3760 | O29: 0 | Q29: =IFERROR(TRIM(LEFT($E29,FIND(" | ",$E29)-1)),"") | R29: =IFERROR(TRIM(UPPER(MID($E29,FIND(" | ",$E29)+3,IFERROR(FIND(" | ",$E29,FIND(" | ",$E29)+3),LEN($E29)+1)-FIND(" | ",$E29)-3))),"")
A30: 5101 | B30: Sueldos | C30: 45845 | D30: 1739 | E30: Javier Antequera - SAC | G30: OPXX | H30: 7139 | I30: 875000 | J30: 0 | K30: DESA | L30: Desarrollos | M30: GDR | N30: García del Río 3760 | O30: 0 | Q30: =IFERROR(TRIM(LEFT($E30,FIND(" | ",$E30)-1)),"") | R30: =IFERROR(TRIM(UPPER(MID($E30,FIND(" | ",$E30)+3,IFERROR(FIND(" | ",$E30,FIND(" | ",$E30)+3),LEN($E30)+1)-FIND(" | ",$E30)-3))),"")
... A34: 5101 | B34: Sueldos | C34: 46073 | D34: 576 | E34: Yohen Rodriguez-Premio Hormigo | G34: OPXX | H34: 8597 | I34: 2078000 | J34: 0 | K34: DESA | L34: Desarrollos | M34: GDR | N34: García del Río 3760 | O34: 0 | Q34: =IFERROR(TRIM(LEFT($E34,FIND(" | ",$E34)-1)),"") | R34: =IFERROR(TRIM(UPPER(MID($E34,FIND(" | ",$E34)+3,IFERROR(FIND(" | ",$E34,FIND(" | ",$E34)+3),LEN($E34)+1)-FIND(" | ",$E34)-3))),"")
A35: 5108 | B35: Gastos en personal | C35: 45706 | D35: 1305 | E35: Gastos en Personales - Abrafer | F35: Abrafer S.R.L. | G35: FCA3 | H35: 1000192524 | I35: 138171.31 | J35: 0 | K35: DESA | L35: Desarrollos | M35: GDR | N35: García del Río 3760 | O35: 0 | Q35: =IFERROR(TRIM(LEFT($E35,FIND(" | ",$E35)-1)),"") | R35: =IFERROR(TRIM(UPPER(MID($E35,FIND(" | ",$E35)+3,IFERROR(FIND(" | ",$E35,FIND(" | ",$E35)+3),LEN($E35)+1)-FIND(" | ",$E35)-3))),"")
A36: 5108 | B36: Gastos en personal | C36: 45726 | D36: 1808 | E36: Gastos en Personales - Abrafer | F36: Abrafer S.R.L. | G36: NCA3 | H36: 1000012643 | I36: 0 | J36: 59490.47 | K36: DESA | L36: Desarrollos | M36: GDR | N36: García del Río 3760 | O36: 0 | Q36: =IFERROR(TRIM(LEFT($E36,FIND(" | ",$E36)-1)),"") | R36: =IFERROR(TRIM(UPPER(MID($E36,FIND(" | ",$E36)+3,IFERROR(FIND(" | ",$E36,FIND(" | ",$E36)+3),LEN($E36)+1)-FIND(" | ",$E36)-3))),"")
A37: 5108 | B37: Gastos en personal | C37: 45727 | D37: 1582 | E37: EPP - Abrafer S.R.L. | F37: Abrafer S.R.L. | G37: FCA3 | H37: 1000193810 | I37: 389523.63 | J37: 0 | K37: DESA | L37: Desarrollos | M37: GDR | N37: García del Río 3760 | O37: 0 | Q37: =IFERROR(TRIM(LEFT($E37,FIND(" | ",$E37)-1)),"") | R37: =IFERROR(TRIM(UPPER(MID($E37,FIND(" | ",$E37)+3,IFERROR(FIND(" | ",$E37,FIND(" | ",$E37)+3),LEN($E37)+1)-FIND(" | ",$E37)-3))),"")
A38: 5108 | B38: Gastos en personal | C38: 45850 | D38: 3670 | E38: Gastos en Personales - Abrafer | F38: Abrafer S.R.L. | G38: FCA3 | H38: 1000203135 | I38: 440804.68 | J38: 0 | K38: DESA | L38: Desarrollos | M38: GDR | N38: García del Río 3760 | O38: 0 | Q38: =IFERROR(TRIM(LEFT($E38,FIND(" | ",$E38)-1)),"") | R38: =IFERROR(TRIM(UPPER(MID($E38,FIND(" | ",$E38)+3,IFERROR(FIND(" | ",$E38,FIND(" | ",$E38)+3),LEN($E38)+1)-FIND(" | ",$E38)-3))),"")
A39: 5108 | B39: Gastos en personal | C39: 45850 | D39: 3671 | E39: Gastos en Personales - Abrafer | F39: Abrafer S.R.L. | G39: FCA3 | H39: 1000203122 | I39: 993.6 | J39: 0 | K39: DESA | L39: Desarrollos | M39: GDR | N39: García del Río 3760 | O39: 0 | Q39: =IFERROR(TRIM(LEFT($E39,FIND(" | ",$E39)-1)),"") | R39: =IFERROR(TRIM(UPPER(MID($E39,FIND(" | ",$E39)+3,IFERROR(FIND(" | ",$E39,FIND(" | ",$E39)+3),LEN($E39)+1)-FIND(" | ",$E39)-3))),"")
A40: 5108 | B40: Gastos en personal | C40: 45867 | D40: 3899 | E40: Gastos en Personales - Abrafer | F40: Abrafer S.R.L. | G40: NCA3 | H40: 1000013415 | I40: 0 | J40: 993.6 | K40: DESA | L40: Desarrollos | M40: GDR | N40: García del Río 3760 | O40: 0 | Q40: =IFERROR(TRIM(LEFT($E40,FIND(" | ",$E40)-1)),"") | R40: =IFERROR(TRIM(UPPER(MID($E40,FIND(" | ",$E40)+3,IFERROR(FIND(" | ",$E40,FIND(" | ",$E40)+3),LEN($E40)+1)-FIND(" | ",$E40)-3))),"")
A41: 5108 | B41: Gastos en personal | C41: 45895 | D41: 4361 | E41: Gastos en Personales - Abrafer | F41: Abrafer S.R.L. | G41: FCA3 | H41: 1000206822 | I41: 27040.04 | J41: 0 | K41: DESA | L41: Desarrollos | M41: GDR | N41: García del Río 3760 | O41: 0 | Q41: =IFERROR(TRIM(LEFT($E41,FIND(" | ",$E41)-1)),"") | R41: =IFERROR(TRIM(UPPER(MID($E41,FIND(" | ",$E41)+3,IFERROR(FIND(" | ",$E41,FIND(" | ",$E41)+3),LEN($E41)+1)-FIND(" | ",$E41)-3))),"")
A42: 52001 | B42: Aysa | C42: 45841 | D42: 1716 | E42: AYSA - pendientes | G42: OPXX | H42: 7116 | I42: 32438.6 | J42: 0 | K42: DESA | L42: Desarrollos | M42: GDR | N42: García del Río 3760 | O42: 0 | Q42: =IFERROR(TRIM(LEFT($E42,FIND(" | ",$E42)-1)),"") | R42: =IFERROR(TRIM(UPPER(MID($E42,FIND(" | ",$E42)+3,IFERROR(FIND(" | ",$E42,FIND(" | ",$E42)+3),LEN($E42)+1)-FIND(" | ",$E42)-3))),"")
A43: 52001 | B43: Aysa | C43: 45841 | D43: 1761 | E43: AYSA - pendientes | G43: OPXX | H43: 7161 | I43: 32438.6 | J43: 0 | K43: DESA | L43: Desarrollos | M43: GDR | N43: García del Río 3760 | O43: 0 | Q43: =IFERROR(TRIM(LEFT($E43,FIND(" | ",$E43)-1)),"") | R43: =IFERROR(TRIM(UPPER(MID($E43,FIND(" | ",$E43)+3,IFERROR(FIND(" | ",$E43,FIND(" | ",$E43)+3),LEN($E43)+1)-FIND(" | ",$E43)-3))),"")
A44: 52002 | B44: Edenor | C44: 45679 | D44: 340 | E44: EDENOR - Fact. 45239049 | G44: OPXX | H44: 5772 | I44: 64900 | J44: 0 | K44: DESA | L44: Desarrollos | M44: GDR | N44: García del Río 3760 | O44: 0 | Q44: =IFERROR(TRIM(LEFT($E44,FIND(" | ",$E44)-1)),"") | R44: =IFERROR(TRIM(UPPER(MID($E44,FIND(" | ",$E44)+3,IFERROR(FIND(" | ",$E44,FIND(" | ",$E44)+3),LEN($E44)+1)-FIND(" | ",$E44)-3))),"")
A45: 52002 | B45: Edenor | C45: 45680 | D45: 274 | E45: Deuda Edenor | G45: OPXX | H45: 5702 | I45: 64897 | J45: 0 | K45: DESA | L45: Desarrollos | M45: GDR | N45: García del Río 3760 | O45: 0 | Q45: =IFERROR(TRIM(LEFT($E45,FIND(" | ",$E45)-1)),"") | R45: =IFERROR(TRIM(UPPER(MID($E45,FIND(" | ",$E45)+3,IFERROR(FIND(" | ",$E45,FIND(" | ",$E45)+3),LEN($E45)+1)-FIND(" | ",$E45)-3))),"")
A46: 52002 | B46: Edenor | C46: 45832 | D46: 3946 | E46: Edenor - Prestamo a GDR | G46: OPG | H46: 3947 | I46: 283606.9 | J46: 0 | K46: DESA | L46: Desarrollos | M46: GDR | N46: García del Río 3760 | O46: 0 | Q46: =IFERROR(TRIM(LEFT($E46,FIND(" | ",$E46)-1)),"") | R46: =IFERROR(TRIM(UPPER(MID($E46,FIND(" | ",$E46)+3,IFERROR(FIND(" | ",$E46,FIND(" | ",$E46)+3),LEN($E46)+1)-FIND(" | ",$E46)-3))),"")
A47: 52005 | B47: Internet | C47: 45765 | D47: 2337 | E47: Internet - Telecom Argentina S | F47: Telecom Argentina S.A. | G47: FCA3 | H47: 426405225578 | I47: 19365 | J47: 0 | K47: DESA | L47: Desarrollos | M47: GDR | N47: García del Río 3760 | O47: 0 | Q47: =IFERROR(TRIM(LEFT($E47,FIND(" | ",$E47)-1)),"") | R47: =IFERROR(TRIM(UPPER(MID($E47,FIND(" | ",$E47)+3,IFERROR(FIND(" | ",$E47,FIND(" | ",$E47)+3),LEN($E47)+1)-FIND(" | ",$E47)-3))),"")
A48: 52005 | B48: Internet | C48: 45798 | D48: 3485 | E48: Internet - Telecom Argentina S | F48: Telecom Argentina S.A. | G48: FCA3 | H48: 426405353103 | I48: 20205 | J48: 0 | K48: DESA | L48: Desarrollos | M48: GDR | N48: García del Río 3760 | O48: 0 | Q48: =IFERROR(TRIM(LEFT($E48,FIND(" | ",$E48)-1)),"") | R48: =IFERROR(TRIM(UPPER(MID($E48,FIND(" | ",$E48)+3,IFERROR(FIND(" | ",$E48,FIND(" | ",$E48)+3),LEN($E48)+1)-FIND(" | ",$E48)-3))),"")
A49: 52005 | B49: Internet | C49: 45826 | D49: 3490 | E49: Internet - Telecom Argentina S | F49: Telecom Argentina S.A. | G49: FCA3 | H49: 426405489994 | I49: 20595 | J49: 0 | K49: DESA | L49: Desarrollos | M49: GDR | N49: García del Río 3760 | O49: 0 | Q49: =IFERROR(TRIM(LEFT($E49,FIND(" | ",$E49)-1)),"") | R49: =IFERROR(TRIM(UPPER(MID($E49,FIND(" | ",$E49)+3,IFERROR(FIND(" | ",$E49,FIND(" | ",$E49)+3),LEN($E49)+1)-FIND(" | ",$E49)-3))),"")
A50: 52005 | B50: Internet | C50: 45855 | D50: 3863 | E50: Internet - Telecom Argentina S | F50: Telecom Argentina S.A. | G50: FCA3 | H50: 426405626926 | I50: 21195 | J50: 0 | K50: DESA | L50: Desarrollos | M50: GDR | N50: García del Río 3760 | O50: 0 | Q50: =IFERROR(TRIM(LEFT($E50,FIND(" | ",$E50)-1)),"") | R50: =IFERROR(TRIM(UPPER(MID($E50,FIND(" | ",$E50)+3,IFERROR(FIND(" | ",$E50,FIND(" | ",$E50)+3),LEN($E50)+1)-FIND(" | ",$E50)-3))),"")
A51: 52005 | B51: Internet | C51: 45888 | D51: 4351 | E51: Internet - Telecom Argentina S | F51: Telecom Argentina S.A. | G51: FCA3 | H51: 426405763893 | I51: 21825 | J51: 0 | K51: DESA | L51: Desarrollos | M51: GDR | N51: García del Río 3760 | O51: 0 | Q51: =IFERROR(TRIM(LEFT($E51,FIND(" | ",$E51)-1)),"") | R51: =IFERROR(TRIM(UPPER(MID($E51,FIND(" | ",$E51)+3,IFERROR(FIND(" | ",$E51,FIND(" | ",$E51)+3),LEN($E51)+1)-FIND(" | ",$E51)-3))),"")
A52: 52005 | B52: Internet | C52: 45918 | D52: 4822 | E52: Internet - Telecom Argentina S | F52: Telecom Argentina S.A. | G52: FCA3 | H52: 426405904143 | I52: 22365 | J52: 0 | K52: DESA | L52: Desarrollos | M52: GDR | N52: García del Río 3760 | O52: 0 | Q52: =IFERROR(TRIM(LEFT($E52,FIND(" | ",$E52)-1)),"") | R52: =IFERROR(TRIM(UPPER(MID($E52,FIND(" | ",$E52)+3,IFERROR(FIND(" | ",$E52,FIND(" | ",$E52)+3),LEN($E52)+1)-FIND(" | ",$E52)-3))),"")
A53: 52005 | B53: Internet | C53: 45951 | D53: 5506 | E53: Internet - Telecom Argentina S | F53: Telecom Argentina S.A. | G53: FCA3 | H53: 395005176382 | I53: 10973.81 | J53: 0 | K53: DESA | L53: Desarrollos | M53: GDR | N53: García del Río 3760 | O53: 0 | Q53: =IFERROR(TRIM(LEFT($E53,FIND(" | ",$E53)-1)),"") | R53: =IFERROR(TRIM(UPPER(MID($E53,FIND(" | ",$E53)+3,IFERROR(FIND(" | ",$E53,FIND(" | ",$E53)+3),LEN($E53)+1)-FIND(" | ",$E53)-3))),"")
A54: 52005 | B54: Internet | C54: 45982 | D54: 215 | E54: Internet - Telecom Argentina S | F54: Telecom Argentina S.A. | G54: FCA3 | H54: 395005465477 | I54: 16776.87 | J54: 0 | K54: DESA | L54: Desarrollos | M54: GDR | N54: García del Río 3760 | O54: 0 | Q54: =IFERROR(TRIM(LEFT($E54,FIND(" | ",$E54)-1)),"") | R54: =IFERROR(TRIM(UPPER(MID($E54,FIND(" | ",$E54)+3,IFERROR(FIND(" | ",$E54,FIND(" | ",$E54)+3),LEN($E54)+1)-FIND(" | ",$E54)-3))),"")
A55: 52005 | B55: Internet | C55: 46043 | D55: 999 | E55: Internet - Telecom Argentina S | F55: Telecom Argentina S.A. | G55: FCA3 | H55: 395006029702 | I55: 17702.49 | J55: 0 | K55: DESA | L55: Desarrollos | M55: GDR | N55: García del Río 3760 | O55: 0 | Q55: =IFERROR(TRIM(LEFT($E55,FIND(" | ",$E55)-1)),"") | R55: =IFERROR(TRIM(UPPER(MID($E55,FIND(" | ",$E55)+3,IFERROR(FIND(" | ",$E55,FIND(" | ",$E55)+3),LEN($E55)+1)-FIND(" | ",$E55)-3))),"")
A56: 52005 | B56: Internet | C56: 46074 | D56: 1385 | E56: Internet - Telecom Argentina S | F56: Telecom Argentina S.A. | G56: FCA3 | H56: 395006310943 | I56: 18231.41 | J56: 0 | K56: DESA | L56: Desarrollos | M56: GDR | N56: García del Río 3760 | O56: 0 | Q56: =IFERROR(TRIM(LEFT($E56,FIND(" | ",$E56)-1)),"") | R56: =IFERROR(TRIM(UPPER(MID($E56,FIND(" | ",$E56)+3,IFERROR(FIND(" | ",$E56,FIND(" | ",$E56)+3),LEN($E56)+1)-FIND(" | ",$E56)-3))),"")
A57: 52005 | B57: Internet | C57: 46102 | D57: 2165 | E57: Internet - Telecom Argentina S | F57: Telecom Argentina S.A. | G57: FCA3 | H57: 395006591497 | I57: 18865.71 | J57: 0 | K57: DESA | L57: Desarrollos | M57: GDR | N57: García del Río 3760 | O57: 0 | Q57: =IFERROR(TRIM(LEFT($E57,FIND(" | ",$E57)-1)),"") | R57: =IFERROR(TRIM(UPPER(MID($E57,FIND(" | ",$E57)+3,IFERROR(FIND(" | ",$E57,FIND(" | ",$E57)+3),LEN($E57)+1)-FIND(" | ",$E57)-3))),"")
A58: 52005 | B58: Internet | C58: 46133 | D58: 2524 | E58: Internet - Telecom Argentina S | F58: Telecom Argentina S.A. | G58: FCA3 | H58: 395006870609 | I58: 19524.8 | J58: 0 | K58: DESA | L58: Desarrollos | M58: GDR | N58: García del Río 3760 | O58: 0 | Q58: =IFERROR(TRIM(LEFT($E58,FIND(" | ",$E58)-1)),"") | R58: =IFERROR(TRIM(UPPER(MID($E58,FIND(" | ",$E58)+3,IFERROR(FIND(" | ",$E58,FIND(" | ",$E58)+3),LEN($E58)+1)-FIND(" | ",$E58)-3))),"")
A59: 52101 | B59: Librería | C59: 45896 | D59: 2006 | E59: Librería | G59: OPXX | H59: 7403 | I59: 9800 | J59: 0 | K59: DESA | L59: Desarrollos | M59: GDR | N59: García del Río 3760 | O59: 0 | Q59: =IFERROR(TRIM(LEFT($E59,FIND(" | ",$E59)-1)),"") | R59: =IFERROR(TRIM(UPPER(MID($E59,FIND(" | ",$E59)+3,IFERROR(FIND(" | ",$E59,FIND(" | ",$E59)+3),LEN($E59)+1)-FIND(" | ",$E59)-3))),"")
A60: 52101 | B60: Librería | C60: 45905 | D60: 2100 | E60: Librería | G60: OPXX | H60: 7479 | I60: 9800 | J60: 0 | K60: DESA | L60: Desarrollos | M60: GDR | N60: García del Río 3760 | O60: 0 | Q60: =IFERROR(TRIM(LEFT($E60,FIND(" | ",$E60)-1)),"") | R60: =IFERROR(TRIM(UPPER(MID($E60,FIND(" | ",$E60)+3,IFERROR(FIND(" | ",$E60,FIND(" | ",$E60)+3),LEN($E60)+1)-FIND(" | ",$E60)-3))),"")
A61: 52101 | B61: Librería | C61: 45923 | D61: 2166 | E61: Librería | G61: OPXX | H61: 7545 | I61: 19600 | J61: 0 | K61: DESA | L61: Desarrollos | M61: GDR | N61: García del Río 3760 | O61: 0 | Q61: =IFERROR(TRIM(LEFT($E61,FIND(" | ",$E61)-1)),"") | R61: =IFERROR(TRIM(UPPER(MID($E61,FIND(" | ",$E61)+3,IFERROR(FIND(" | ",$E61,FIND(" | ",$E61)+3),LEN($E61)+1)-FIND(" | ",$E61)-3))),"")
A62: 52101 | B62: Librería | C62: 45987 | D62: 73 | E62: Librería | G62: OPXX | H62: 7998 | I62: 4900 | J62: 0 | K62: DESA | L62: Desarrollos | M62: GDR | N62: García del Río 3760 | O62: 0 | Q62: =IFERROR(TRIM(LEFT($E62,FIND(" | ",$E62)-1)),"") | R62: =IFERROR(TRIM(UPPER(MID($E62,FIND(" | ",$E62)+3,IFERROR(FIND(" | ",$E62,FIND(" | ",$E62)+3),LEN($E62)+1)-FIND(" | ",$E62)-3))),"")
A63: 52101 | B63: Librería | C63: 45987 | D63: 75 | E63: Librería | G63: OPXX | H63: 8000 | I63: 7800 | J63: 0 | K63: DESA | L63: Desarrollos | M63: GDR | N63: García del Río 3760 | O63: 0 | Q63: =IFERROR(TRIM(LEFT($E63,FIND(" | ",$E63)-1)),"") | R63: =IFERROR(TRIM(UPPER(MID($E63,FIND(" | ",$E63)+3,IFERROR(FIND(" | ",$E63,FIND(" | ",$E63)+3),LEN($E63)+1)-FIND(" | ",$E63)-3))),"")
A64: 52101 | B64: Librería | C64: 46013 | D64: 586 | E64: LIBRERIA - Parise Paola Beatri | F64: Parise Paola Beatriz | G64: FCA3 | H64: 400010860 | I64: 12892.56 | J64: 0 | K64: DESA | L64: Desarrollos | M64: GDR | N64: García del Río 3760 | O64: 0 | Q64: =IFERROR(TRIM(LEFT($E64,FIND(" | ",$E64)-1)),"") | R64: =IFERROR(TRIM(UPPER(MID($E64,FIND(" | ",$E64)+3,IFERROR(FIND(" | ",$E64,FIND(" | ",$E64)+3),LEN($E64)+1)-FIND(" | ",$E64)-3))),"")
A65: 52101 | B65: Librería | C65: 46077 | D65: 631 | E65: Librería | G65: OPXX | H65: 8649 | I65: 4300 | J65: 0 | K65: DESA | L65: Desarrollos | M65: GDR | N65: García del Río 3760 | O65: 0 | Q65: =IFERROR(TRIM(LEFT($E65,FIND(" | ",$E65)-1)),"") | R65: =IFERROR(TRIM(UPPER(MID($E65,FIND(" | ",$E65)+3,IFERROR(FIND(" | ",$E65,FIND(" | ",$E65)+3),LEN($E65)+1)-FIND(" | ",$E65)-3))),"")
A66: 52101 | B66: Librería | C66: 46086 | D66: 1510 | E66: LIBRERIA - Parise Paola Beatri | F66: Parise Paola Beatriz | G66: FCA3 | H66: 400011113 | I66: 6446.28 | J66: 0 | K66: DESA | L66: Desarrollos | M66: GDR | N66: García del Río 3760 | O66: 0 | Q66: =IFERROR(TRIM(LEFT($E66,FIND(" | ",$E66)-1)),"") | R66: =IFERROR(TRIM(UPPER(MID($E66,FIND(" | ",$E66)+3,IFERROR(FIND(" | ",$E66,FIND(" | ",$E66)+3),LEN($E66)+1)-FIND(" | ",$E66)-3))),"")
A67: 52101 | B67: Librería | C67: 46107 | D67: 869 | E67: Librería | G67: OPXX | H67: 8901 | I67: 5000 | J67: 0 | K67: DESA | L67: Desarrollos | M67: GDR | N67: García del Río 3760 | O67: 0 | Q67: =IFERROR(TRIM(LEFT($E67,FIND(" | ",$E67)-1)),"") | R67: =IFERROR(TRIM(UPPER(MID($E67,FIND(" | ",$E67)+3,IFERROR(FIND(" | ",$E67,FIND(" | ",$E67)+3),LEN($E67)+1)-FIND(" | ",$E67)-3))),"")
A68: 52101 | B68: Librería | C68: 46125 | D68: 2363 | E68: LIBRERIA - Parise Paola Beatri | F68: Parise Paola Beatriz | G68: FCA3 | H68: 400011296 | I68: 12892.56 | J68: 0 | K68: DESA | L68: Desarrollos | M68: GDR | N68: García del Río 3760 | O68: 0 | Q68: =IFERROR(TRIM(LEFT($E68,FIND(" | ",$E68)-1)),"") | R68: =IFERROR(TRIM(UPPER(MID($E68,FIND(" | ",$E68)+3,IFERROR(FIND(" | ",$E68,FIND(" | ",$E68)+3),LEN($E68)+1)-FIND(" | ",$E68)-3))),"")
A69: 52102 | B69: Limpieza | C69: 45733 | D69: 1952 | E69: Limpieza - Dia Argentina S.A. | F69: Dia Argentina S.A. | G69: FCA3 | H69: 1165500001157 | I69: 4128.07 | J69: 0 | K69: DESA | L69: Desarrollos | M69: GDR | N69: García del Río 3760 | O69: 0 | Q69: =IFERROR(TRIM(LEFT($E69,FIND(" | ",$E69)-1)),"") | R69: =IFERROR(TRIM(UPPER(MID($E69,FIND(" | ",$E69)+3,IFERROR(FIND(" | ",$E69,FIND(" | ",$E69)+3),LEN($E69)+1)-FIND(" | ",$E69)-3))),"")
A70: 52102 | B70: Limpieza | C70: 45769 | D70: 2397 | E70: Limpieza - Dia Argentina S.A. | F70: Dia Argentina S.A. | G70: TIQA | H70: 1165500001217 | I70: 3702.46 | J70: 0 | K70: DESA | L70: Desarrollos | M70: GDR | N70: García del Río 3760 | O70: 0 | Q70: =IFERROR(TRIM(LEFT($E70,FIND(" | ",$E70)-1)),"") | R70: =IFERROR(TRIM(UPPER(MID($E70,FIND(" | ",$E70)+3,IFERROR(FIND(" | ",$E70,FIND(" | ",$E70)+3),LEN($E70)+1)-FIND(" | ",$E70)-3))),"")
A71: 52102 | B71: Limpieza | C71: 45771 | D71: 2398 | E71: Limpieza - Dia Argentina S.A. | F71: Dia Argentina S.A. | G71: TIQA | H71: 1165500001227 | I71: 5454.55 | J71: 0 | K71: DESA | L71: Desarrollos | M71: GDR | N71: García del Río 3760 | O71: 0 | Q71: =IFERROR(TRIM(LEFT($E71,FIND(" | ",$E71)-1)),"") | R71: =IFERROR(TRIM(UPPER(MID($E71,FIND(" | ",$E71)+3,IFERROR(FIND(" | ",$E71,FIND(" | ",$E71)+3),LEN($E71)+1)-FIND(" | ",$E71)-3))),"")
A72: 52102 | B72: Limpieza | C72: 45812 | D72: 3380 | E72: Limpieza - STRIETZEL WALTER FA | F72: STRIETZEL WALTER FABIAN | G72: FC3 | H72: 400006365 | I72: 19700 | J72: 0 | K72: DESA | L72: Desarrollos | M72: GDR | N72: García del Río 3760 | O72: 0 | Q72: =IFERROR(TRIM(LEFT($E72,FIND(" | ",$E72)-1)),"") | R72: =IFERROR(TRIM(UPPER(MID($E72,FIND(" | ",$E72)+3,IFERROR(FIND(" | ",$E72,FIND(" | ",$E72)+3),LEN($E72)+1)-FIND(" | ",$E72)-3))),"")
A73: 52102 | B73: Limpieza | C73: 45839 | D73: 3825 | E73: Limpieza - STRIETZEL WALTER FA | F73: STRIETZEL WALTER FABIAN | G73: FC3 | H73: 400006525 | I73: 15000 | J73: 0 | K73: DESA | L73: Desarrollos | M73: GDR | N73: García del Río 3760 | O73: 0 | Q73: =IFERROR(TRIM(LEFT($E73,FIND(" | ",$E73)-1)),"") | R73: =IFERROR(TRIM(UPPER(MID($E73,FIND(" | ",$E73)+3,IFERROR(FIND(" | ",$E73,FIND(" | ",$E73)+3),LEN($E73)+1)-FIND(" | ",$E73)-3))),"")
A74: 52102 | B74: Limpieza | C74: 45859 | D74: 3838 | E74: Limpieza - STRIETZEL WALTER FA | F74: STRIETZEL WALTER FABIAN | G74: FC3 | H74: 400006643 | I74: 15200 | J74: 0 | K74: DESA | L74: Desarrollos | M74: GDR | N74: García del Río 3760 | O74: 0 | Q74: =IFERROR(TRIM(LEFT($E74,FIND(" | ",$E74)-1)),"") | R74: =IFERROR(TRIM(UPPER(MID($E74,FIND(" | ",$E74)+3,IFERROR(FIND(" | ",$E74,FIND(" | ",$E74)+3),LEN($E74)+1)-FIND(" | ",$E74)-3))),"")
A75: 52102 | B75: Limpieza | C75: 45875 | D75: 1867 | E75: Limpieza | G75: OPXX | H75: 7262 | I75: 8000 | J75: 0 | K75: DESA | L75: Desarrollos | M75: GDR | N75: García del Río 3760 | O75: 0 | Q75: =IFERROR(TRIM(LEFT($E75,FIND(" | ",$E75)-1)),"") | R75: =IFERROR(TRIM(UPPER(MID($E75,FIND(" | ",$E75)+3,IFERROR(FIND(" | ",$E75,FIND(" | ",$E75)+3),LEN($E75)+1)-FIND(" | ",$E75)-3))),"")
A76: 52102 | B76: Limpieza | C76: 45885 | D76: 4347 | E76: Limpieza - Dia Argentina S.A. | F76: Dia Argentina S.A. | G76: TIQA | H76: 1165100000133 | I76: 3359.49 | J76: 0 | K76: DESA | L76: Desarrollos | M76: GDR | N76: García del Río 3760 | O76: 0 | Q76: =IFERROR(TRIM(LEFT($E76,FIND(" | ",$E76)-1)),"") | R76: =IFERROR(TRIM(UPPER(MID($E76,FIND(" | ",$E76)+3,IFERROR(FIND(" | ",$E76,FIND(" | ",$E76)+3),LEN($E76)+1)-FIND(" | ",$E76)-3))),"")
A77: 52102 | B77: Limpieza | C77: 45894 | D77: 4357 | E77: Limpieza - STRIETZEL WALTER FA | F77: STRIETZEL WALTER FABIAN | G77: FC3 | H77: 400006851 | I77: 25800 | J77: 0 | K77: DESA | L77: Desarrollos | M77: GDR | N77: García del Río 3760 | O77: 0 | Q77: =IFERROR(TRIM(LEFT($E77,FIND(" | ",$E77)-1)),"") | R77: =IFERROR(TRIM(UPPER(MID($E77,FIND(" | ",$E77)+3,IFERROR(FIND(" | ",$E77,FIND(" | ",$E77)+3),LEN($E77)+1)-FIND(" | ",$E77)-3))),"")
A78: 52102 | B78: Limpieza | C78: 45898 | D78: 4560 | E78: Limpieza - STRIETZEL WALTER FA | F78: STRIETZEL WALTER FABIAN | G78: FC3 | H78: 400006892 | I78: 3400 | J78: 0 | K78: DESA | L78: Desarrollos | M78: GDR | N78: García del Río 3760 | O78: 0 | Q78: =IFERROR(TRIM(LEFT($E78,FIND(" | ",$E78)-1)),"") | R78: =IFERROR(TRIM(UPPER(MID($E78,FIND(" | ",$E78)+3,IFERROR(FIND(" | ",$E78,FIND(" | ",$E78)+3),LEN($E78)+1)-FIND(" | ",$E78)-3))),"")
A79: 52102 | B79: Limpieza | C79: 45918 | D79: 4818 | E79: Limpieza - STRIETZEL WALTER FA | F79: STRIETZEL WALTER FABIAN | G79: FC3 | H79: 400007042 | I79: 12000 | J79: 0 | K79: DESA | L79: Desarrollos | M79: GDR | N79: García del Río 3760 | O79: 0 | Q79: =IFERROR(TRIM(LEFT($E79,FIND(" | ",$E79)-1)),"") | R79: =IFERROR(TRIM(UPPER(MID($E79,FIND(" | ",$E79)+3,IFERROR(FIND(" | ",$E79,FIND(" | ",$E79)+3),LEN($E79)+1)-FIND(" | ",$E79)-3))),"")
A80: 52102 | B80: Limpieza | C80: 45920 | D80: 4828 | E80: Limpieza - STRIETZEL WALTER FA | F80: STRIETZEL WALTER FABIAN | G80: FC3 | H80: 400007053 | I80: 3200 | J80: 0 | K80: DESA | L80: Desarrollos | M80: GDR | N80: García del Río 3760 | O80: 0 | Q80: =IFERROR(TRIM(LEFT($E80,FIND(" | ",$E80)-1)),"") | R80: =IFERROR(TRIM(UPPER(MID($E80,FIND(" | ",$E80)+3,IFERROR(FIND(" | ",$E80,FIND(" | ",$E80)+3),LEN($E80)+1)-FIND(" | ",$E80)-3))),"")
A81: 52102 | B81: Limpieza | C81: 45940 | D81: 2336 | E81: Limpieza | G81: OPXX | H81: 7706 | I81: 28900 | J81: 0 | K81: DESA | L81: Desarrollos | M81: GDR | N81: García del Río 3760 | O81: 0 | Q81: =IFERROR(TRIM(LEFT($E81,FIND(" | ",$E81)-1)),"") | R81: =IFERROR(TRIM(UPPER(MID($E81,FIND(" | ",$E81)+3,IFERROR(FIND(" | ",$E81,FIND(" | ",$E81)+3),LEN($E81)+1)-FIND(" | ",$E81)-3))),"")
A82: 52102 | B82: Limpieza | C82: 45965 | D82: 195 | E82: Limpieza - STRIETZEL WALTER FA | F82: STRIETZEL WALTER FABIAN | G82: FC3 | H82: 400007304 | I82: 29600 | J82: 0 | K82: DESA | L82: Desarrollos | M82: GDR | N82: García del Río 3760 | O82: 0 | Q82: =IFERROR(TRIM(LEFT($E82,FIND(" | ",$E82)-1)),"") | R82: =IFERROR(TRIM(UPPER(MID($E82,FIND(" | ",$E82)+3,IFERROR(FIND(" | ",$E82,FIND(" | ",$E82)+3),LEN($E82)+1)-FIND(" | ",$E82)-3))),"")
A83: 52102 | B83: Limpieza | C83: 45988 | D83: 240 | E83: Limpieza - STRIETZEL WALTER FA | F83: STRIETZEL WALTER FABIAN | G83: FC3 | H83: 400007441 | I83: 27600 | J83: 0 | K83: DESA | L83: Desarrollos | M83: GDR | N83: García del Río 3760 | O83: 0 | Q83: =IFERROR(TRIM(LEFT($E83,FIND(" | ",$E83)-1)),"") | R83: =IFERROR(TRIM(UPPER(MID($E83,FIND(" | ",$E83)+3,IFERROR(FIND(" | ",$E83,FIND(" | ",$E83)+3),LEN($E83)+1)-FIND(" | ",$E83)-3))),"")
A84: 52102 | B84: Limpieza | C84: 46021 | D84: 903 | E84: Limpieza - STRIETZEL WALTER FA | F84: STRIETZEL WALTER FABIAN | G84: FC3 | H84: 400007646 | I84: 32200 | J84: 0 | K84: DESA | L84: Desarrollos | M84: GDR | N84: García del Río 3760 | O84: 0 | Q84: =IFERROR(TRIM(LEFT($E84,FIND(" | ",$E84)-1)),"") | R84: =IFERROR(TRIM(UPPER(MID($E84,FIND(" | ",$E84)+3,IFERROR(FIND(" | ",$E84,FIND(" | ",$E84)+3),LEN($E84)+1)-FIND(" | ",$E84)-3))),"")
A85: 52102 | B85: Limpieza | C85: 46045 | D85: 1184 | E85: Limpieza - STRIETZEL WALTER FA | F85: STRIETZEL WALTER FABIAN | G85: FC3 | H85: 400007790 | I85: 27000 | J85: 0 | K85: DESA | L85: Desarrollos | M85: GDR | N85: García del Río 3760 | O85: 0 | Q85: =IFERROR(TRIM(LEFT($E85,FIND(" | ",$E85)-1)),"") | R85: =IFERROR(TRIM(UPPER(MID($E85,FIND(" | ",$E85)+3,IFERROR(FIND(" | ",$E85,FIND(" | ",$E85)+3),LEN($E85)+1)-FIND(" | ",$E85)-3))),"")
A86: 52102 | B86: Limpieza | C86: 46073 | D86: 633 | E86: Limpieza | G86: OPXX | H86: 8651 | I86: 14800 | J86: 0 | K86: DESA | L86: Desarrollos | M86: GDR | N86: García del Río 3760 | O86: 0 | Q86: =IFERROR(TRIM(LEFT($E86,FIND(" | ",$E86)-1)),"") | R86: =IFERROR(TRIM(UPPER(MID($E86,FIND(" | ",$E86)+3,IFERROR(FIND(" | ",$E86,FIND(" | ",$E86)+3),LEN($E86)+1)-FIND(" | ",$E86)-3))),"")
A87: 52102 | B87: Limpieza | C87: 46079 | D87: 634 | E87: Limpieza | G87: OPXX | H87: 8652 | I87: 15600 | J87: 0 | K87: DESA | L87: Desarrollos | M87: GDR | N87: García del Río 3760 | O87: 0 | Q87: =IFERROR(TRIM(LEFT($E87,FIND(" | ",$E87)-1)),"") | R87: =IFERROR(TRIM(UPPER(MID($E87,FIND(" | ",$E87)+3,IFERROR(FIND(" | ",$E87,FIND(" | ",$E87)+3),LEN($E87)+1)-FIND(" | ",$E87)-3))),"")
A88: 52102 | B88: Limpieza | C88: 46092 | D88: 1670 | E88: Limpieza - STRIETZEL WALTER FA | F88: STRIETZEL WALTER FABIAN | G88: FC3 | H88: 400008126 | I88: 21600 | J88: 0 | K88: DESA | L88: Desarrollos | M88: GDR | N88: García del Río 3760 | O88: 0 | Q88: =IFERROR(TRIM(LEFT($E88,FIND(" | ",$E88)-1)),"") | R88: =IFERROR(TRIM(UPPER(MID($E88,FIND(" | ",$E88)+3,IFERROR(FIND(" | ",$E88,FIND(" | ",$E88)+3),LEN($E88)+1)-FIND(" | ",$E88)-3))),"")
A89: 52102 | B89: Limpieza | C89: 46106 | D89: 2344 | E89: Limpieza - STRIETZEL WALTER FA | F89: STRIETZEL WALTER FABIAN | G89: FC3 | H89: 400008199 | I89: 34600 | J89: 0 | K89: DESA | L89: Desarrollos | M89: GDR | N89: García del Río 3760 | O89: 0 | Q89: =IFERROR(TRIM(LEFT($E89,FIND(" | ",$E89)-1)),"") | R89: =IFERROR(TRIM(UPPER(MID($E89,FIND(" | ",$E89)+3,IFERROR(FIND(" | ",$E89,FIND(" | ",$E89)+3),LEN($E89)+1)-FIND(" | ",$E89)-3))),"")
A90: 52102 | B90: Limpieza | C90: 46125 | D90: 2362 | E90: Limpieza - STRIETZEL WALTER FA | F90: STRIETZEL WALTER FABIAN | G90: FC3 | H90: 400008327 | I90: 19200 | J90: 0 | K90: DESA | L90: Desarrollos | M90: GDR | N90: García del Río 3760 | O90: 0 | Q90: =IFERROR(TRIM(LEFT($E90,FIND(" | ",$E90)-1)),"") | R90: =IFERROR(TRIM(UPPER(MID($E90,FIND(" | ",$E90)+3,IFERROR(FIND(" | ",$E90,FIND(" | ",$E90)+3),LEN($E90)+1)-FIND(" | ",$E90)-3))),"")
A91: 52103 | B91: Supermercados | C91: 45707 | D91: 1156 | E91: Supermercados | G91: OPXX | H91: 6570 | I91: 2495 | J91: 0 | K91: DESA | L91: Desarrollos | M91: GDR | N91: García del Río 3760 | O91: 0 | Q91: =IFERROR(TRIM(LEFT($E91,FIND(" | ",$E91)-1)),"") | R91: =IFERROR(TRIM(UPPER(MID($E91,FIND(" | ",$E91)+3,IFERROR(FIND(" | ",$E91,FIND(" | ",$E91)+3),LEN($E91)+1)-FIND(" | ",$E91)-3))),"")
A92: 52103 | B92: Supermercados | C92: 45707 | D92: 1465 | E92: Supermercado - Dia Argentina S | F92: Dia Argentina S.A. | G92: FCA3 | H92: 1165500001127 | I92: 2061.98 | J92: 0 | K92: DESA | L92: Desarrollos | M92: GDR | N92: García del Río 3760 | O92: 0 | Q92: =IFERROR(TRIM(LEFT($E92,FIND(" | ",$E92)-1)),"") | R92: =IFERROR(TRIM(UPPER(MID($E92,FIND(" | ",$E92)+3,IFERROR(FIND(" | ",$E92,FIND(" | ",$E92)+3),LEN($E92)+1)-FIND(" | ",$E92)-3))),"")
A93: 52103 | B93: Supermercados | C93: 45708 | D93: 1159 | E93: Supermercados | G93: OPXX | H93: 6573 | I93: 2495 | J93: 0 | K93: DESA | L93: Desarrollos | M93: GDR | N93: García del Río 3760 | O93: 0 | Q93: =IFERROR(TRIM(LEFT($E93,FIND(" | ",$E93)-1)),"") | R93: =IFERROR(TRIM(UPPER(MID($E93,FIND(" | ",$E93)+3,IFERROR(FIND(" | ",$E93,FIND(" | ",$E93)+3),LEN($E93)+1)-FIND(" | ",$E93)-3))),"")
A94: 52103 | B94: Supermercados | C94: 45708 | D94: 1466 | E94: Supermercado - Dia Argentina S | F94: Dia Argentina S.A. | G94: FCA3 | H94: 1165500001129 | I94: 2061.98 | J94: 0 | K94: DESA | L94: Desarrollos | M94: GDR | N94: García del Río 3760 | O94: 0 | Q94: =IFERROR(TRIM(LEFT($E94,FIND(" | ",$E94)-1)),"") | R94: =IFERROR(TRIM(UPPER(MID($E94,FIND(" | ",$E94)+3,IFERROR(FIND(" | ",$E94,FIND(" | ",$E94)+3),LEN($E94)+1)-FIND(" | ",$E94)-3))),"")
A95: 52103 | B95: Supermercados | C95: 45713 | D95: 1165 | E95: Supermercados | G95: OPXX | H95: 6579 | I95: 3050 | J95: 0 | K95: DESA | L95: Desarrollos | M95: GDR | N95: García del Río 3760 | O95: 0 | Q95: =IFERROR(TRIM(LEFT($E95,FIND(" | ",$E95)-1)),"") | R95: =IFERROR(TRIM(UPPER(MID($E95,FIND(" | ",$E95)+3,IFERROR(FIND(" | ",$E95,FIND(" | ",$E95)+3),LEN($E95)+1)-FIND(" | ",$E95)-3))),"")
A96: 52103 | B96: Supermercados | C96: 45713 | D96: 1471 | E96: Supermercado - Dia Argentina S | F96: Dia Argentina S.A. | G96: FCA3 | H96: 1165100000041 | I96: 2520.66 | J96: 0 | K96: DESA | L96: Desarrollos | M96: GDR | N96: García del Río 3760 | O96: 0 | Q96: =IFERROR(TRIM(LEFT($E96,FIND(" | ",$E96)-1)),"") | R96: =IFERROR(TRIM(UPPER(MID($E96,FIND(" | ",$E96)+3,IFERROR(FIND(" | ",$E96,FIND(" | ",$E96)+3),LEN($E96)+1)-FIND(" | ",$E96)-3))),"")
A97: 52103 | B97: Supermercados | C97: 45733 | D97: 1174 | E97: Supermercados | G97: OPXX | H97: 6588 | I97: 5036.25 | J97: 0 | K97: DESA | L97: Desarrollos | M97: GDR | N97: García del Río 3760 | O97: 0 | Q97: =IFERROR(TRIM(LEFT($E97,FIND(" | ",$E97)-1)),"") | R97: =IFERROR(TRIM(UPPER(MID($E97,FIND(" | ",$E97)+3,IFERROR(FIND(" | ",$E97,FIND(" | ",$E97)+3),LEN($E97)+1)-FIND(" | ",$E97)-3))),"")
A98: 52103 | B98: Supermercados | C98: 45750 | D98: 2213 | E98: Supermercado - INC S.A | F98: INC S.A | G98: FCA3 | H98: 1178700000206 | I98: 2471.07 | J98: 0 | K98: DESA | L98: Desarrollos | M98: GDR | N98: García del Río 3760 | O98: 0 | Q98: =IFERROR(TRIM(LEFT($E98,FIND(" | ",$E98)-1)),"") | R98: =IFERROR(TRIM(UPPER(MID($E98,FIND(" | ",$E98)+3,IFERROR(FIND(" | ",$E98,FIND(" | ",$E98)+3),LEN($E98)+1)-FIND(" | ",$E98)-3))),"")
A99: 52103 | B99: Supermercados | C99: 45751 | D99: 2215 | E99: Supermercado - Coto C.I.C.S.A. | F99: Coto C.I.C.S.A. | G99: FCA3 | H99: 418100126642 | I99: 9617.12 | J99: 0 | K99: DESA | L99: Desarrollos | M99: GDR | N99: García del Río 3760 | O99: 0 | Q99: =IFERROR(TRIM(LEFT($E99,FIND(" | ",$E99)-1)),"") | R99: =IFERROR(TRIM(UPPER(MID($E99,FIND(" | ",$E99)+3,IFERROR(FIND(" | ",$E99,FIND(" | ",$E99)+3),LEN($E99)+1)-FIND(" | ",$E99)-3))),"")
A100: 52103 | B100: Supermercados | C100: 45751 | D100: 2215 | E100: Supermercado - Coto C.I.C.S.A. | F100: Coto C.I.C.S.A. | G100: FCA3 | H100: 418100126642 | I100: 60947.5 | J100: 0 | K100: DESA | L100: Desarrollos | M100: GDR | N100: García del Río 3760 | O100: 0 | Q100: =IFERROR(TRIM(LEFT($E100,FIND(" | ",$E100)-1)),"") | R100: =IFERROR(TRIM(UPPER(MID($E100,FIND(" | ",$E100)+3,IFERROR(FIND(" | ",$E100,FIND(" | ",$E100)+3),LEN($E100)+1)-FIND(" | ",$E100)-3))),"")
A101: 52103 | B101: Supermercados | C101: 45772 | D101: 2399 | E101: Supermercado - Coto C.I.C.S.A. | F101: Coto C.I.C.S.A. | G101: FCA3 | H101: 418100128029 | I101: 7514.82 | J101: 0 | K101: DESA | L101: Desarrollos | M101: GDR | N101: García del Río 3760 | O101: 0 | Q101: =IFERROR(TRIM(LEFT($E101,FIND(" | ",$E101)-1)),"") | R101: =IFERROR(TRIM(UPPER(MID($E101,FIND(" | ",$E101)+3,IFERROR(FIND(" | ",$E101,FIND(" | ",$E101)+3),LEN($E101)+1)-FIND(" | ",$E101)-3))),"")
A102: 52103 | B102: Supermercados | C102: 45772 | D102: 2399 | E102: Supermercado - Coto C.I.C.S.A. | F102: Coto C.I.C.S.A. | G102: FCA3 | H102: 418100128029 | I102: 49173.67 | J102: 0 | K102: DESA | L102: Desarrollos | M102: GDR | N102: García del Río 3760 | O102: 0 | Q102: =IFERROR(TRIM(LEFT($E102,FIND(" | ",$E102)-1)),"") | R102: =IFERROR(TRIM(UPPER(MID($E102,FIND(" | ",$E102)+3,IFERROR(FIND(" | ",$E102,FIND(" | ",$E102)+3),LEN($E102)+1)-FIND(" | ",$E102)-3))),"")
A103: 52103 | B103: Supermercados | C103: 45779 | D103: 2832 | E103: Supermercado - Coto C.I.C.S.A. | F103: Coto C.I.C.S.A. | G103: FCA3 | H103: 1165500001249 | I103: 7095.04 | J103: 0 | K103: DESA | L103: Desarrollos | M103: GDR | N103: García del Río 3760 | O103: 0 | Q103: =IFERROR(TRIM(LEFT($E103,FIND(" | ",$E103)-1)),"") | R103: =IFERROR(TRIM(UPPER(MID($E103,FIND(" | ",$E103)+3,IFERROR(FIND(" | ",$E103,FIND(" | ",$E103)+3),LEN($E103)+1)-FIND(" | ",$E103)-3))),"")
A104: 52103 | B104: Supermercados | C104: 45779 | D104: 2833 | E104: Supermercado - Dia Argentina S | F104: Dia Argentina S.A. | G104: TIQA | H104: 1165500001249 | I104: 7095.04 | J104: 0 | K104: DESA | L104: Desarrollos | M104: GDR | N104: García del Río 3760 | O104: 0 | Q104: =IFERROR(TRIM(LEFT($E104,FIND(" | ",$E104)-1)),"") | R104: =IFERROR(TRIM(UPPER(MID($E104,FIND(" | ",$E104)+3,IFERROR(FIND(" | ",$E104,FIND(" | ",$E104)+3),LEN($E104)+1)-FIND(" | ",$E104)-3))),"")
A105: 52103 | B105: Supermercados | C105: 45782 | D105: 2835 | E105: Supermercado - Dia Argentina S | F105: Dia Argentina S.A. | G105: TIQA | H105: 1165600000044 | I105: 2074.38 | J105: 0 | K105: DESA | L105: Desarrollos | M105: GDR | N105: García del Río 3760 | O105: 0 | Q105: =IFERROR(TRIM(LEFT($E105,FIND(" | ",$E105)-1)),"") | R105: =IFERROR(TRIM(UPPER(MID($E105,FIND(" | ",$E105)+3,IFERROR(FIND(" | ",$E105,FIND(" | ",$E105)+3),LEN($E105)+1)-FIND(" | ",$E105)-3))),"")
A106: 52103 | B106: Supermercados | C106: 45786 | D106: 2838 | E106: Supermercado - Coto C.I.C.S.A. | F106: Coto C.I.C.S.A. | G106: FCA3 | H106: 418100128972 | I106: 11049.53 | J106: 0 | K106: DESA | L106: Desarrollos | M106: GDR | N106: García del Río 3760 | O106: 0 | Q106: =IFERROR(TRIM(LEFT($E106,FIND(" | ",$E106)-1)),"") | R106: =IFERROR(TRIM(UPPER(MID($E106,FIND(" | ",$E106)+3,IFERROR(FIND(" | ",$E106,FIND(" | ",$E106)+3),LEN($E106)+1)-FIND(" | ",$E106)-3))),"")
A107: 52103 | B107: Supermercados | C107: 45786 | D107: 2838 | E107: Supermercado - Coto C.I.C.S.A. | F107: Coto C.I.C.S.A. | G107: FCA3 | H107: 418100128972 | I107: 49941.34 | J107: 0 | K107: DESA | L107: Desarrollos | M107: GDR | N107: García del Río 3760 | O107: 0 | Q107: =IFERROR(TRIM(LEFT($E107,FIND(" | ",$E107)-1)),"") | R107: =IFERROR(TRIM(UPPER(MID($E107,FIND(" | ",$E107)+3,IFERROR(FIND(" | ",$E107,FIND(" | ",$E107)+3),LEN($E107)+1)-FIND(" | ",$E107)-3))),"")
...

Sheet 1_Composicion
A1: Partida | B1: Tipo | C1: Subtipo | D1: Cod_Insumo | E1: Descripción | F1: Unidad de medida | G1: Cant | H1: %Desp | I1: Precio | J1: Costo | K1: Clave | L1: Count | M1: Clave2 | N1: Rend. Part. | O1: Cant MO/ALB Unit | P1: Cant. Ej. Part. | Q1: Cant MO/ALB Total | R1: Cod_Item_Ppto | S1: MO/ALB
A2: AIS-114 | B2: EQ | D2: EQ-SOLD00 | E2: Soldador Soplete A Gas Techista Membrana 10 Kg Boca 50mm | G2: 1 | H2: 0 | I2: 804.50569 | J2: 804.50569 | K2: AIS-114|EQ | L2: 1 | M2: AIS-114|EQ|1 | N2: 60 | O2: 1 | P2: - | Q2: 0 | R2: - | S2: -
A3: AIS-114 | B3: MAT | C3: OTR | D3: OTR-022 | E3: Aguarras Hydrarras Hydra x 18lts | F3: b | G3: 0.005 | H3: 0.05 | I3: 26907.33 | J3: 141.26348 | K3: AIS-114|MAT | L3: 1 | M3: AIS-114|MAT|1 | N3: 60 | O3: 0.005 | P3: - | Q3: 0 | R3: - | S3: -
A4: AIS-114 | B4: MAT | C4: OTR | D4: OTR-025 | E4: Trapo | F4: u | G4: 0.01 | H4: 0.05 | I4: 735.06 | J4: 7.71813 | K4: AIS-114|MAT | L4: 2 | M4: AIS-114|MAT|2 | N4: 60 | O4: 0.01 | P4: - | Q4: 0 | R4: - | S4: -
A5: AIS-114 | B5: MAT | C5: OTR | D5: OTR-027 | E5: Rodillo de lana pelo largo N°22 - El Galgo | F5: u | G5: 0.005 | H5: 0.05 | I5: 6678.36 | J5: 35.06139 | K5: AIS-114|MAT | L5: 3 | M5: AIS-114|MAT|3 | N5: 60 | O5: 0.005 | P5: - | Q5: 0 | R5: - | S5: -
A6: AIS-114 | B6: MAT | C6: OTR | D6: OTR-028 | E6: Pincel N° 20 - El Galgo | F6: u | G6: 0.01 | H6: 0.05 | I6: 5282.24 | J6: 55.46352 | K6: AIS-114|MAT | L6: 4 | M6: AIS-114|MAT|4 | N6: 60 | O6: 0.01 | P6: - | Q6: 0 | R6: - | S6: -
A7: AIS-114 | B7: MAT | C7: OTR | D7: OTR-047 | E7: Guante Vaqueta Medio Paseo | F7: par | G7: 0.03 | H7: 0.05 | I7: 4842 | J7: 152.523 | K7: AIS-114|MAT | L7: 5 | M7: AIS-114|MAT|5 | N7: 60 | O7: 0.03 | P7: - | Q7: 0 | R7: - | S7: -
A8: AIS-114 | B8: MAT | C8: OTR | D8: OTR-048 | E8: Recarga de garrafa | F8: u | G8: 0.01 | H8: 0.05 | I8: 12396.694 | J8: 130.16529 | K8: AIS-114|MAT | L8: 6 | M8: AIS-114|MAT|6 | N8: 60 | O8: 0.01 | P8: - | Q8: 0 | R8: - | S8: -
A9: AIS-114 | B9: MAT | C9: OTR | D9: PIN-008 | E9: Pintura Asfaltica Asfasol x18ts | F9: b | G9: 0.015 | H9: 0.1 | I9: 32845.78 | J9: 541.95537 | K9: AIS-114|MAT | L9: 7 | M9: AIS-114|MAT|7 | N9: 60 | O9: 0.015 | P9: - | Q9: 0 | R9: - | S9: -
A10: AIS-114 | B10: MAT | C10: OTR | D10: AIS-002 | E10: Membrana Geotextil Ormiflex 4mm - (35kg) x10m | F10: u | G10: 0.05 | H10: 0.1 | I10: 70192.21 | J10: 3860.5716 | K10: AIS-114|MAT | L10: 8 | M10: AIS-114|MAT|8 | N10: 60 | O10: 0.05 | P10: - | Q10: 0 | R10: - | S10: -
A11: AIS-114 | B11: MO | C11: ALB | D11: MO-EAYUD | E11: AYUDANTE | F11: j | G11: 1 | H11: 0 | I11: 60860.581 | J11: 60860.581 | K11: AIS-114|MO | L11: 1 | M11: AIS-114|MO|1 | N11: 60 | O11: 0.016666667 | P11: - | Q11: 0 | R11: - | S11: -
A12: AIS-114 | B12: MO | C12: ALB | D12: MO-EESPE | E12: ESPECIALIZADO | F12: j | G12: 1 | H12: 0 | I12: 85927.097 | J12: 85927.097 | K12: AIS-114|MO | L12: 2 | M12: AIS-114|MO|2 | N12: 60 | O12: 0.016666667 | P12: - | Q12: 0 | R12: - | S12: -
A13: ALB-033 | B13: EQ | D13: EQ-ANDAM0 | E13: ANDAMIO TUBULAR DE UNO A TRES CUERPOS | G13: 0.5 | H13: 0 | I13: 571.17949 | J13: 285.58975 | K13: ALB-033|EQ | L13: 1 | M13: ALB-033|EQ|1 | N13: 7 | O13: 0.5 | P13: - | Q13: 0 | R13: - | S13: -
A14: ALB-033 | B14: EQ | D14: EQ-EQALBA | E14: EQUIPO DE ALBAÑILERIA, carpetas, ladrillo | G14: 1 | H14: 0 | I14: 2287.1357 | J14: 2287.1357 | K14: ALB-033|EQ | L14: 2 | M14: ALB-033|EQ|2 | N14: 7 | O14: 1 | P14: - | Q14: 0 | R14: - | S14: -
A15: ALB-033 | B15: EQ | D15: EQ-TROMPO | E15: Hormigonera De 150 Litros 1hp Con Rueda Maciza | G15: 1 | H15: 0 | I15: 957.2532 | J15: 957.2532 | K15: ALB-033|EQ | L15: 3 | M15: ALB-033|EQ|3 | N15: 7 | O15: 1 | P15: - | Q15: 0 | R15: - | S15: -
A16: ALB-033 | B16: MAT | C16: OTR | D16: ACE-001 | E16: Barra de Acero Aleteado - 6mm x 12m | F16: u | G16: 0.17 | H16: 0.1 | I16: 3424.53 | J16: 640.38711 | K16: ALB-033|MAT | L16: 1 | M16: ALB-033|MAT|1 | N16: 7 | O16: 0.17 | P16: - | Q16: 0 | R16: - | S16: -
A17: ALB-033 | B17: MAT | C17: OTR | D17: AGR-001 | E17: ARENA LAVADA | F17: m3 | G17: 0.035 | H17: 0.1 | I17: 32399.77 | J17: 1247.3911 | K17: ALB-033|MAT | L17: 2 | M17: ALB-033|MAT|2 | N17: 7 | O17: 0.035 | P17: - | Q17: 0 | R17: - | S17: -
A18: ALB-033 | B18: MAT | C18: OTR | D18: AGR-004 | E18: Cemento Portland x 50kg | F18: Bol | G18: 0.15 | H18: 0.1 | I18: 7809.48 | J18: 1288.5642 | K18: ALB-033|MAT | L18: 3 | M18: ALB-033|MAT|3 | N18: 7 | O18: 0.15 | P18: - | Q18: 0 | R18: - | S18: -
A19: ALB-033 | B19: MAT | C19: OTR | D19: AGR-005 | E19: Cal Comun x 25kg | F19: bol | G19: 0.3 | H19: 0.1 | I19: 3837.96 | J19: 1266.5268 | K19: ALB-033|MAT | L19: 4 | M19: ALB-033|MAT|4 | N19: 7 | O19: 0.3 | P19: - | Q19: 0 | R19: - | S19: -
A20: ALB-033 | B20: MAT | C20: OTR | D20: CER-005 | E20: Ladrillo Comun 12.5 x 5.5 x 25 | F20: u | G20: 60 | H20: 0.05 | I20: 132.3 | J20: 8334.9 | K20: ALB-033|MAT | L20: 5 | M20: ALB-033|MAT|5 | N20: 7 | O20: 60 | P20: - | Q20: 0 | R20: - | S20: -
A21: ALB-033 | B21: MAT | C21: OTR | D21: MAT-CONS | E21: Consumibles | F21: gl | G21: 1.3161102 | H21: 0 | I21: 1 | J21: 1.3161102 | K21: ALB-033|MAT | L21: 6 | M21: ALB-033|MAT|6 | N21: 7 | O21: 1.3161102 | P21: - | Q21: 0 | R21: - | S21: -
A22: ALB-033 | B22: MO | C22: ALB | D22: MO-EAYUD | E22: AYUDANTE | F22: j | G22: 1 | H22: 0 | I22: 60860.581 | J22: 60860.581 | K22: ALB-033|MO | L22: 1 | M22: ALB-033|MO|1 | N22: 7 | O22: 0.14285714 | P22: - | Q22: 0 | R22: - | S22: -
A23: ALB-033 | B23: MO | C23: ALB | D23: MO-EESPE | E23: ESPECIALIZADO | F23: j | G23: 1 | H23: 0 | I23: 85927.097 | J23: 85927.097 | K23: ALB-033|MO | L23: 2 | M23: ALB-033|MO|2 | N23: 7 | O23: 0.14285714 | P23: - | Q23: 0 | R23: - | S23: -
A24: ALB-034 | B24: EQ | D24: EQ-ANDAM0 | E24: ANDAMIO TUBULAR DE UNO A TRES CUERPOS | G24: 0.5 | H24: 0 | I24: 571.17949 | J24: 285.58975 | K24: ALB-034|EQ | L24: 1 | M24: ALB-034|EQ|1 | N24: 15 | O24: 0.5 | P24: 621 | Q24: 310.5 | R24: 4.01 | S24: Albañilería
A25: ALB-034 | B25: EQ | D25: EQ-EQALBA | E25: EQUIPO DE ALBAÑILERIA, carpetas, ladrillo | G25: 1 | H25: 0 | I25: 2287.1357 | J25: 2287.1357 | K25: ALB-034|EQ | L25: 2 | M25: ALB-034|EQ|2 | N25: 15 | O25: 1 | P25: 621 | Q25: 621 | R25: 4.01 | S25: Albañilería
A26: ALB-034 | B26: EQ | D26: EQ-TROMPO | E26: Hormigonera De 150 Litros 1hp Con Rueda Maciza | G26: 1 | H26: 0 | I26: 957.2532 | J26: 957.2532 | K26: ALB-034|EQ | L26: 3 | M26: ALB-034|EQ|3 | N26: 15 | O26: 1 | P26: 621 | Q26: 621 | R26: 4.01 | S26: Albañilería
A27: ALB-034 | B27: MAT | C27: OTR | D27: ACE-001 | E27: Barra de Acero Aleteado - 6mm x 12m | F27: u | G27: 0.17 | H27: 0.1 | I27: 3424.53 | J27: 640.38711 | K27: ALB-034|MAT | L27: 1 | M27: ALB-034|MAT|1 | N27: 15 | O27: 0.17 | P27: 621 | Q27: 105.57 | R27: 4.01 | S27: Albañilería
A28: ALB-034 | B28: MAT | C28: OTR | D28: AGR-001 | E28: ARENA LAVADA | F28: m3 | G28: 0.012 | H28: 0.1 | I28: 32399.77 | J28: 427.67696 | K28: ALB-034|MAT | L28: 2 | M28: ALB-034|MAT|2 | N28: 15 | O28: 0.012 | P28: 621 | Q28: 7.452 | R28: 4.01 | S28: Albañilería
A29: ALB-034 | B29: MAT | C29: OTR | D29: AGR-004 | E29: Cemento Portland x 50kg | F29: Bol | G29: 0.05 | H29: 0.1 | I29: 7809.48 | J29: 429.5214 | K29: ALB-034|MAT | L29: 3 | M29: ALB-034|MAT|3 | N29: 15 | O29: 0.05 | P29: 621 | Q29: 31.05 | R29: 4.01 | S29: Albañilería
A30: ALB-034 | B30: MAT | C30: OTR | D30: AGR-005 | E30: Cal Comun x 25kg | F30: bol | G30: 0.1 | H30: 0.1 | I30: 3837.96 | J30: 422.1756 | K30: ALB-034|MAT | L30: 4 | M30: ALB-034|MAT|4 | N30: 15 | O30: 0.1 | P30: 621 | Q30: 62.1 | R30: 4.01 | S30: Albañilería
A31: ALB-034 | B31: MAT | C31: OTR | D31: CER-002 | E31: LADRILLO CERAMICO 8 x 18 x 33 cm | F31: u | G31: 15 | H31: 0.05 | I31: 292.32 | J31: 4604.04 | K31: ALB-034|MAT | L31: 5 | M31: ALB-034|MAT|5 | N31: 15 | O31: 15 | P31: 621 | Q31: 9315 | R31: 4.01 | S31: Albañilería
A32: ALB-034 | B32: MAT | C32: OTR | D32: MAT-CONS | E32: Consumibles | F32: gl | G32: 67.195151 | H32: 0 | I32: 1 | J32: 67.195151 | K32: ALB-034|MAT | L32: 6 | M32: ALB-034|MAT|6 | N32: 15 | O32: 67.195151 | P32: 621 | Q32: 41728.189 | R32: 4.01 | S32: Albañilería
A33: ALB-034 | B33: MO | C33: ALB | D33: MO-EAYUD | E33: AYUDANTE | F33: j | G33: 1 | H33: 0 | I33: 60860.581 | J33: 60860.581 | K33: ALB-034|MO | L33: 1 | M33: ALB-034|MO|1 | N33: 15 | O33: 0.066666667 | P33: 621 | Q33: 41.4 | R33: 4.01 | S33: Albañilería
A34: ALB-034 | B34: MO | C34: ALB | D34: MO-EESPE | E34: ESPECIALIZADO | F34: j | G34: 1 | H34: 0 | I34: 85927.097 | J34: 85927.097 | K34: ALB-034|MO | L34: 2 | M34: ALB-034|MO|2 | N34: 15 | O34: 0.066666667 | P34: 621 | Q34: 41.4 | R34: 4.01 | S34: Albañilería
A35: ALB-035 | B35: EQ | D35: EQ-ANDAM0 | E35: ANDAMIO TUBULAR DE UNO A TRES CUERPOS | G35: 0.5 | H35: 0 | I35: 571.17949 | J35: 285.58975 | K35: ALB-035|EQ | L35: 1 | M35: ALB-035|EQ|1 | N35: 15 | O35: 0.5 | P35: 780 | Q35: 390 | R35: 4.02 | S35: Albañilería
A36: ALB-035 | B36: EQ | D36: EQ-EQALBA | E36: EQUIPO DE ALBAÑILERIA, carpetas, ladrillo | G36: 1 | H36: 0 | I36: 2287.1357 | J36: 2287.1357 | K36: ALB-035|EQ | L36: 2 | M36: ALB-035|EQ|2 | N36: 15 | O36: 1 | P36: 780 | Q36: 780 | R36: 4.02 | S36: Albañilería
A37: ALB-035 | B37: EQ | D37: EQ-TROMPO | E37: Hormigonera De 150 Litros 1hp Con Rueda Maciza | G37: 1 | H37: 0 | I37: 957.2532 | J37: 957.2532 | K37: ALB-035|EQ | L37: 3 | M37: ALB-035|EQ|3 | N37: 15 | O37: 1 | P37: 780 | Q37: 780 | R37: 4.02 | S37: Albañilería
A38: ALB-035 | B38: MAT | C38: OTR | D38: ACE-001 | E38: Barra de Acero Aleteado - 6mm x 12m | F38: u | G38: 0.17 | H38: 0.1 | I38: 3424.53 | J38: 640.38711 | K38: ALB-035|MAT | L38: 1 | M38: ALB-035|MAT|1 | N38: 15 | O38: 0.17 | P38: 780 | Q38: 132.6 | R38: 4.02 | S38: Albañilería
A39: ALB-035 | B39: MAT | C39: OTR | D39: AGR-001 | E39: ARENA LAVADA | F39: m3 | G39: 0.018 | H39: 0.1 | I39: 32399.77 | J39: 641.51545 | K39: ALB-035|MAT | L39: 2 | M39: ALB-035|MAT|2 | N39: 15 | O39: 0.018 | P39: 780 | Q39: 14.04 | R39: 4.02 | S39: Albañilería
A40: ALB-035 | B40: MAT | C40: OTR | D40: AGR-004 | E40: Cemento Portland x 50kg | F40: Bol | G40: 0.075 | H40: 0.1 | I40: 7809.48 | J40: 644.2821 | K40: ALB-035|MAT | L40: 3 | M40: ALB-035|MAT|3 | N40: 15 | O40: 0.075 | P40: 780 | Q40: 58.5 | R40: 4.02 | S40: Albañilería
A41: ALB-035 | B41: MAT | C41: OTR | D41: AGR-005 | E41: Cal Comun x 25kg | F41: bol | G41: 0.15 | H41: 0.1 | I41: 3837.96 | J41: 633.2634 | K41: ALB-035|MAT | L41: 4 | M41: ALB-035|MAT|4 | N41: 15 | O41: 0.15 | P41: 780 | Q41: 117 | R41: 4.02 | S41: Albañilería
A42: ALB-035 | B42: MAT | C42: OTR | D42: CER-003 | E42: LADRILLO CERAMICO 12 x 18 x 33 cm | F42: u | G42: 15 | H42: 0.05 | I42: 365.4 | J42: 5755.05 | K42: ALB-035|MAT | L42: 5 | M42: ALB-035|MAT|5 | N42: 15 | O42: 15 | P42: 780 | Q42: 11700 | R42: 4.02 | S42: Albañilería
A43: ALB-035 | B43: MAT | C43: OTR | D43: MAT-CONS | E43: Consumibles | F43: gl | G43: 85.63933 | H43: 0 | I43: 1 | J43: 85.63933 | K43: ALB-035|MAT | L43: 6 | M43: ALB-035|MAT|6 | N43: 15 | O43: 85.63933 | P43: 780 | Q43: 66798.677 | R43: 4.02 | S43: Albañilería
A44: ALB-035 | B44: MO | C44: ALB | D44: MO-EAYUD | E44: AYUDANTE | F44: j | G44: 1 | H44: 0 | I44: 60860.581 | J44: 60860.581 | K44: ALB-035|MO | L44: 1 | M44: ALB-035|MO|1 | N44: 15 | O44: 0.066666667 | P44: 780 | Q44: 52 | R44: 4.02 | S44: Albañilería
A45: ALB-035 | B45: MO | C45: ALB | D45: MO-EESPE | E45: ESPECIALIZADO | F45: j | G45: 1 | H45: 0 | I45: 85927.097 | J45: 85927.097 | K45: ALB-035|MO | L45: 2 | M45: ALB-035|MO|2 | N45: 15 | O45: 0.066666667 | P45: 780 | Q45: 52 | R45: 4.02 | S45: Albañilería
A46: ALB-036 | B46: EQ | D46: EQ-ANDAM0 | E46: ANDAMIO TUBULAR DE UNO A TRES CUERPOS | G46: 0.5 | H46: 0 | I46: 571.17949 | J46: 285.58975 | K46: ALB-036|EQ | L46: 1 | M46: ALB-036|EQ|1 | N46: 15 | O46: 0.5 | P46: 5 | Q46: 2.5 | R46: 4.06 | S46: Albañilería
A47: ALB-036 | B47: EQ | D47: EQ-EQALBA | E47: EQUIPO DE ALBAÑILERIA, carpetas, ladrillo | G47: 1 | H47: 0 | I47: 2287.1357 | J47: 2287.1357 | K47: ALB-036|EQ | L47: 2 | M47: ALB-036|EQ|2 | N47: 15 | O47: 1 | P47: 5 | Q47: 5 | R47: 4.06 | S47: Albañilería
A48: ALB-036 | B48: EQ | D48: EQ-TROMPO | E48: Hormigonera De 150 Litros 1hp Con Rueda Maciza | G48: 1 | H48: 0 | I48: 957.2532 | J48: 957.2532 | K48: ALB-036|EQ | L48: 3 | M48: ALB-036|EQ|3 | N48: 15 | O48: 1 | P48: 5 | Q48: 5 | R48: 4.06 | S48: Albañilería
A49: ALB-036 | B49: MAT | C49: OTR | D49: ACE-001 | E49: Barra de Acero Aleteado - 6mm x 12m | F49: u | G49: 0.17 | H49: 0.1 | I49: 3424.53 | J49: 640.38711 | K49: ALB-036|MAT | L49: 1 | M49: ALB-036|MAT|1 | N49: 15 | O49: 0.17 | P49: 5 | Q49: 0.85 | R49: 4.06 | S49: Albañilería
A50: ALB-036 | B50: MAT | C50: OTR | D50: AGR-001 | E50: ARENA LAVADA | F50: m3 | G50: 0.024 | H50: 0.1 | I50: 32399.77 | J50: 855.35393 | K50: ALB-036|MAT | L50: 2 | M50: ALB-036|MAT|2 | N50: 15 | O50: 0.024 | P50: 5 | Q50: 0.12 | R50: 4.06 | S50: Albañilería
A51: ALB-036 | B51: MAT | C51: OTR | D51: AGR-004 | E51: Cemento Portland x 50kg | F51: Bol | G51: 0.1 | H51: 0.1 | I51: 7809.48 | J51: 859.0428 | K51: ALB-036|MAT | L51: 3 | M51: ALB-036|MAT|3 | N51: 15 | O51: 0.1 | P51: 5 | Q51: 0.5 | R51: 4.06 | S51: Albañilería
A52: ALB-036 | B52: MAT | C52: OTR | D52: AGR-005 | E52: Cal Comun x 25kg | F52: bol | G52: 0.2 | H52: 0.1 | I52: 3837.96 | J52: 844.3512 | K52: ALB-036|MAT | L52: 4 | M52: ALB-036|MAT|4 | N52: 15 | O52: 0.2 | P52: 5 | Q52: 1 | R52: 4.06 | S52: Albañilería
A53: ALB-036 | B53: MAT | C53: OTR | D53: CER-004 | E53: LADRILLO CERAMICO 18 x 18 x 33 cm | F53: u | G53: 15 | H53: 0.05 | I53: 519.12 | J53: 8176.14 | K53: ALB-036|MAT | L53: 5 | M53: ALB-036|MAT|5 | N53: 15 | O53: 15 | P53: 5 | Q53: 75 | R53: 4.06 | S53: Albañilería
A54: ALB-036 | B54: MAT | C54: OTR | D54: MAT-CONS | E54: Consumibles | F54: gl | G54: 117.16533 | H54: 0 | I54: 1 | J54: 117.16533 | K54: ALB-036|MAT | L54: 6 | M54: ALB-036|MAT|6 | N54: 15 | O54: 117.16533 | P54: 5 | Q54: 585.82666 | R54: 4.06 | S54: Albañilería
A55: ALB-036 | B55: MO | C55: ALB | D55: MO-EAYUD | E55: AYUDANTE | F55: j | G55: 1 | H55: 0 | I55: 60860.581 | J55: 60860.581 | K55: ALB-036|MO | L55: 1 | M55: ALB-036|MO|1 | N55: 15 | O55: 0.066666667 | P55: 5 | Q55: 0.33333333 | R55: 4.06 | S55: Albañilería
A56: ALB-036 | B56: MO | C56: ALB | D56: MO-EESPE | E56: ESPECIALIZADO | F56: j | G56: 1 | H56: 0 | I56: 85927.097 | J56: 85927.097 | K56: ALB-036|MO | L56: 2 | M56: ALB-036|MO|2 | N56: 15 | O56: 0.066666667 | P56: 5 | Q56: 0.33333333 | R56: 4.06 | S56: Albañilería
A57: ALB-037 | B57: EQ | D57: EQ-ANDAM0 | E57: ANDAMIO TUBULAR DE UNO A TRES CUERPOS | G57: 0.5 | H57: 0 | I57: 571.17949 | J57: 285.58975 | K57: ALB-037|EQ | L57: 1 | M57: ALB-037|EQ|1 | N57: 4 | O57: 0.5 | P57: - | Q57: 0 | R57: - | S57: -
A58: ALB-037 | B58: EQ | D58: EQ-EQALBA | E58: EQUIPO DE ALBAÑILERIA, carpetas, ladrillo | G58: 1 | H58: 0 | I58: 2287.1357 | J58: 2287.1357 | K58: ALB-037|EQ | L58: 2 | M58: ALB-037|EQ|2 | N58: 4 | O58: 1 | P58: - | Q58: 0 | R58: - | S58: -
A59: ALB-037 | B59: EQ | D59: EQ-TROMPO | E59: Hormigonera De 150 Litros 1hp Con Rueda Maciza | G59: 1 | H59: 0 | I59: 957.2532 | J59: 957.2532 | K59: ALB-037|EQ | L59: 3 | M59: ALB-037|EQ|3 | N59: 4 | O59: 1 | P59: - | Q59: 0 | R59: - | S59: -
A60: ALB-037 | B60: MAT | C60: OTR | D60: ACE-001 | E60: Barra de Acero Aleteado - 6mm x 12m | F60: u | G60: 0.34 | H60: 0.1 | I60: 3424.53 | J60: 1280.7742 | K60: ALB-037|MAT | L60: 1 | M60: ALB-037|MAT|1 | N60: 4 | O60: 0.34 | P60: - | Q60: 0 | R60: - | S60: -
A61: ALB-037 | B61: MAT | C61: OTR | D61: AGR-001 | E61: ARENA LAVADA | F61: m3 | G61: 0.053 | H61: 0.1 | I61: 32399.77 | J61: 1888.9066 | K61: ALB-037|MAT | L61: 2 | M61: ALB-037|MAT|2 | N61: 4 | O61: 0.053 | P61: - | Q61: 0 | R61: - | S61: -
A62: ALB-037 | B62: MAT | C62: OTR | D62: AGR-004 | E62: Cemento Portland x 50kg | F62: Bol | G62: 0.254 | H62: 0.1 | I62: 7809.48 | J62: 2181.9687 | K62: ALB-037|MAT | L62: 3 | M62: ALB-037|MAT|3 | N62: 4 | O62: 0.254 | P62: - | Q62: 0 | R62: - | S62: -
A63: ALB-037 | B63: MAT | C63: OTR | D63: AGR-005 | E63: Cal Comun x 25kg | F63: bol | G63: 0.4 | H63: 0.1 | I63: 3837.96 | J63: 1688.7024 | K63: ALB-037|MAT | L63: 4 | M63: ALB-037|MAT|4 | N63: 4 | O63: 0.4 | P63: - | Q63: 0 | R63: - | S63: -
A64: ALB-037 | B64: MAT | C64: OTR | D64: AIS-001 | E64: Aditivo Hidrofugo en pasta - Ceresita x 1kg | F64: kg | G64: 0.1 | H64: 0.05 | I64: 1256.128 | J64: 131.89344 | K64: ALB-037|MAT | L64: 5 | M64: ALB-037|MAT|5 | N64: 4 | O64: 0.1 | P64: - | Q64: 0 | R64: - | S64: -
A65: ALB-037 | B65: MAT | C65: OTR | D65: CER-002 | E65: LADRILLO CERAMICO 8 x 18 x 33 cm | F65: u | G65: 15 | H65: 0.05 | I65: 292.32 | J65: 4604.04 | K65: ALB-037|MAT | L65: 6 | M65: ALB-037|MAT|6 | N65: 4 | O65: 15 | P65: - | Q65: 0 | R65: - | S65: -
A66: ALB-037 | B66: MAT | C66: OTR | D66: CER-001 | E66: ladrillo a la vista 1 cara | F66: u | G66: 60 | H66: 0.05 | I66: 233.44 | J66: 14706.72 | K66: ALB-037|MAT | L66: 7 | M66: ALB-037|MAT|7 | N66: 4 | O66: 60 | P66: - | Q66: 0 | R66: - | S66: -
A67: ALB-037 | B67: MAT | C67: OTR | D67: MAT-CONS | E67: Consumibles | F67: gl | G67: 285.29 | H67: 0 | I67: 1 | J67: 285.29 | K67: ALB-037|MAT | L67: 8 | M67: ALB-037|MAT|8 | N67: 4 | O67: 285.29 | P67: - | Q67: 0 | R67: - | S67: -
A68: ALB-037 | B68: MAT | C68: OTR | D68: OTR-022 | E68: Aguarras Hydrarras Hydra x 18lts | F68: b | G68: 0.005 | H68: 0.05 | I68: 26907.33 | J68: 141.26348 | K68: ALB-037|MAT | L68: 9 | M68: ALB-037|MAT|9 | N68: 4 | O68: 0.005 | P68: - | Q68: 0 | R68: - | S68: -
A69: ALB-037 | B69: MAT | C69: OTR | D69: OTR-027 | E69: Rodillo de lana pelo largo N°22 - El Galgo | F69: u | G69: 0.01 | H69: 0.05 | I69: 6678.36 | J69: 70.12278 | K69: ALB-037|MAT | L69: 10 | M69: ALB-037|MAT|10 | N69: 4 | O69: 0.01 | P69: - | Q69: 0 | R69: - | S69: -
A70: ALB-037 | B70: MAT | C70: OTR | D70: PIN-008 | E70: Pintura Asfaltica Asfasol x18ts | F70: b | G70: 0.027777778 | H70: 0.1 | I70: 32845.78 | J70: 1003.6211 | K70: ALB-037|MAT | L70: 11 | M70: ALB-037|MAT|11 | N70: 4 | O70: 0.027777778 | P70: - | Q70: 0 | R70: - | S70: -
A71: ALB-037 | B71: MO | C71: ALB | D71: MO-EAYUD | E71: AYUDANTE | F71: j | G71: 0.91 | H71: 0 | I71: 60860.581 | J71: 55383.129 | K71: ALB-037|MO | L71: 1 | M71: ALB-037|MO|1 | N71: 4 | O71: 0.2275 | P71: - | Q71: 0 | R71: - | S71: -
A72: ALB-037 | B72: MO | C72: ALB | D72: MO-EESPE | E72: ESPECIALIZADO | F72: j | G72: 1 | H72: 0 | I72: 85927.097 | J72: 85927.097 | K72: ALB-037|MO | L72: 2 | M72: ALB-037|MO|2 | N72: 4 | O72: 0.25 | P72: - | Q72: 0 | R72: - | S72: -
A73: ALB-038 | B73: EQ | D73: EQ-ANDAM0 | E73: ANDAMIO TUBULAR DE UNO A TRES CUERPOS | G73: 0.5 | H73: 0 | I73: 571.17949 | J73: 285.58975 | K73: ALB-038|EQ | L73: 1 | M73: ALB-038|EQ|1 | N73: 15 | O73: 0.5 | P73: 42 | Q73: 21 | R73: 4.04 | S73: Albañilería
A74: ALB-038 | B74: EQ | D74: EQ-EQALBA | E74: EQUIPO DE ALBAÑILERIA, carpetas, ladrillo | G74: 1 | H74: 0 | I74: 2287.1357 | J74: 2287.1357 | K74: ALB-038|EQ | L74: 2 | M74: ALB-038|EQ|2 | N74: 15 | O74: 1 | P74: 42 | Q74: 42 | R74: 4.04 | S74: Albañilería
A75: ALB-038 | B75: EQ | D75: EQ-TROMPO | E75: Hormigonera De 150 Litros 1hp Con Rueda Maciza | G75: 1 | H75: 0 | I75: 957.2532 | J75: 957.2532 | K75: ALB-038|EQ | L75: 3 | M75: ALB-038|EQ|3 | N75: 15 | O75: 1 | P75: 42 | Q75: 42 | R75: 4.04 | S75: Albañilería
A76: ALB-038 | B76: MAT | C76: OTR | D76: ACE-001 | E76: Barra de Acero Aleteado - 6mm x 12m | F76: u | G76: 0.17 | H76: 0.1 | I76: 3424.53 | J76: 640.38711 | K76: ALB-038|MAT | L76: 1 | M76: ALB-038|MAT|1 | N76: 15 | O76: 0.17 | P76: 42 | Q76: 7.14 | R76: 4.04 | S76: Albañilería
A77: ALB-038 | B77: MAT | C77: OTR | D77: AGR-001 | E77: ARENA LAVADA | F77: m3 | G77: 0.018 | H77: 0.1 | I77: 32399.77 | J77: 641.51545 | K77: ALB-038|MAT | L77: 2 | M77: ALB-038|MAT|2 | N77: 15 | O77: 0.018 | P77: 42 | Q77: 0.756 | R77: 4.04 | S77: Albañilería
A78: ALB-038 | B78: MAT | C78: OTR | D78: AGR-004 | E78: Cemento Portland x 50kg | F78: Bol | G78: 0.075 | H78: 0.1 | I78: 7809.48 | J78: 644.2821 | K78: ALB-038|MAT | L78: 3 | M78: ALB-038|MAT|3 | N78: 15 | O78: 0.075 | P78: 42 | Q78: 3.15 | R78: 4.04 | S78: Albañilería
A79: ALB-038 | B79: MAT | C79: OTR | D79: AGR-005 | E79: Cal Comun x 25kg | F79: bol | G79: 0.15 | H79: 0.1 | I79: 3837.96 | J79: 633.2634 | K79: ALB-038|MAT | L79: 4 | M79: ALB-038|MAT|4 | N79: 15 | O79: 0.15 | P79: 42 | Q79: 6.3 | R79: 4.04 | S79: Albañilería
A80: ALB-038 | B80: MAT | C80: OTR | D80: CER-006 | E80: Ladrillo hueco ceramico 12x19x33 - Portante | F80: u | G80: 15 | H80: 0.05 | I80: 563.22 | J80: 8870.715 | K80: ALB-038|MAT | L80: 5 | M80: ALB-038|MAT|5 | N80: 15 | O80: 15 | P80: 42 | Q80: 630 | R80: 4.04 | S80: Albañilería
A81: ALB-038 | B81: MAT | C81: OTR | D81: MAT-CONS | E81: Consumibles | F81: gl | G81: 117.73068 | H81: 0 | I81: 1 | J81: 117.73068 | K81: ALB-038|MAT | L81: 6 | M81: ALB-038|MAT|6 | N81: 15 | O81: 117.73068 | P81: 42 | Q81: 4944.6885 | R81: 4.04 | S81: Albañilería
A82: ALB-038 | B82: MO | C82: ALB | D82: MO-EAYUD | E82: AYUDANTE | F82: j | G82: 1 | H82: 0 | I82: 60860.581 | J82: 60860.581 | K82: ALB-038|MO | L82: 1 | M82: ALB-038|MO|1 | N82: 15 | O82: 0.066666667 | P82: 42 | Q82: 2.8 | R82: 4.04 | S82: Albañilería
A83: ALB-038 | B83: MO | C83: ALB | D83: MO-EESPE | E83: ESPECIALIZADO | F83: j | G83: 1 | H83: 0 | I83: 85927.097 | J83: 85927.097 | K83: ALB-038|MO | L83: 2 | M83: ALB-038|MO|2 | N83: 15 | O83: 0.066666667 | P83: 42 | Q83: 2.8 | R83: 4.04 | S83: Albañilería
A84: ALB-039 | B84: EQ | D84: EQ-EQALBA | E84: EQUIPO DE ALBAÑILERIA, carpetas, ladrillo | G84: 0.25 | H84: 0 | I84: 2287.1357 | J84: 571.78394 | K84: ALB-039|EQ | L84: 1 | M84: ALB-039|EQ|1 | N84: 2 | O84: 0.25 | P84: - | Q84: 0 | R84: - | S84: -
A85: ALB-039 | B85: EQ | D85: EQ-TROMPO | E85: Hormigonera De 150 Litros 1hp Con Rueda Maciza | G85: 0.25 | H85: 0 | I85: 957.2532 | J85: 239.3133 | K85: ALB-039|EQ | L85: 2 | M85: ALB-039|EQ|2 | N85: 2 | O85: 0.25 | P85: - | Q85: 0 | R85: - | S85: -
A86: ALB-039 | B86: MAT | C86: OTR | D86: AGR-001 | E86: ARENA LAVADA | F86: m3 | G86: 0.036 | H86: 0.1 | I86: 32399.77 | J86: 1283.0309 | K86: ALB-039|MAT | L86: 1 | M86: ALB-039|MAT|1 | N86: 2 | O86: 0.036 | P86: - | Q86: 0 | R86: - | S86: -
A87: ALB-039 | B87: MAT | C87: OTR | D87: AGR-004 | E87: Cemento Portland x 50kg | F87: Bol | G87: 0.324 | H87: 0.1 | I87: 7809.48 | J87: 2783.2987 | K87: ALB-039|MAT | L87: 2 | M87: ALB-039|MAT|2 | N87: 2 | O87: 0.324 | P87: - | Q87: 0 | R87: - | S87: -
A88: ALB-039 | B88: MO | C88: ALB | D88: MO-EAYUD | E88: AYUDANTE | F88: j | G88: 0.75 | H88: 0 | I88: 60860.581 | J88: 45645.436 | K88: ALB-039|MO | L88: 1 | M88: ALB-039|MO|1 | N88: 2 | O88: 0.375 | P88: - | Q88: 0 | R88: - | S88: -
A89: ALB-039 | B89: MO | C89: ALB | D89: MO-EESPE | E89: ESPECIALIZADO | F89: j | G89: 0.75 | H89: 0 | I89: 85927.097 | J89: 64445.323 | K89: ALB-039|MO | L89: 2 | M89: ALB-039|MO|2 | N89: 2 | O89: 0.375 | P89: - | Q89: 0 | R89: - | S89: -
A90: ALB-040 | B90: EQ | D90: EQ-EQALBA | E90: EQUIPO DE ALBAÑILERIA, carpetas, ladrillo | G90: 0.25 | H90: 0 | I90: 2287.1357 | J90: 571.78394 | K90: ALB-040|EQ | L90: 1 | M90: ALB-040|EQ|1 | N90: 4 | O90: 0.25 | P90: - | Q90: 0 | R90: - | S90: -
A91: ALB-040 | B91: EQ | D91: EQ-TROMPO | E91: Hormigonera De 150 Litros 1hp Con Rueda Maciza | G91: 0.25 | H91: 0 | I91: 957.2532 | J91: 239.3133 | K91: ALB-040|EQ | L91: 2 | M91: ALB-040|EQ|2 | N91: 4 | O91: 0.25 | P91: - | Q91: 0 | R91: - | S91: -
A92: ALB-040 | B92: MAT | C92: OTR | D92: AGR-001 | E92: ARENA LAVADA | F92: m3 | G92: 0.0138 | H92: 0.05 | I92: 32399.77 | J92: 469.47267 | K92: ALB-040|MAT | L92: 1 | M92: ALB-040|MAT|1 | N92: 4 | O92: 0.0138 | P92: - | Q92: 0 | R92: - | S92: -
A93: ALB-040 | B93: MAT | C93: OTR | D93: AGR-004 | E93: Cemento Portland x 50kg | F93: Bol | G93: 0.1242 | H93: 0.05 | I93: 7809.48 | J93: 1018.4343 | K93: ALB-040|MAT | L93: 2 | M93: ALB-040|MAT|2 | N93: 4 | O93: 0.1242 | P93: - | Q93: 0 | R93: - | S93: -
A94: ALB-040 | B94: MO | C94: ALB | D94: MO-EAYUD | E94: AYUDANTE | F94: j | G94: 1 | H94: 0 | I94: 60860.581 | J94: 60860.581 | K94: ALB-040|MO | L94: 1 | M94: ALB-040|MO|1 | N94: 4 | O94: 0.25 | P94: - | Q94: 0 | R94: - | S94: -
A95: ALB-040 | B95: MO | C95: ALB | D95: MO-EESPE | E95: ESPECIALIZADO | F95: j | G95: 1 | H95: 0 | I95: 85927.097 | J95: 85927.097 | K95: ALB-040|MO | L95: 2 | M95: ALB-040|MO|2 | N95: 4 | O95: 0.25 | P95: - | Q95: 0 | R95: - | S95: -
A96: ALB-041 | B96: EQ | D96: EQ-EQALBA | E96: EQUIPO DE ALBAÑILERIA, carpetas, ladrillo | G96: 0.5 | H96: 0 | I96: 2287.1357 | J96: 1143.5679 | K96: ALB-041|EQ | L96: 1 | M96: ALB-041|EQ|1 | N96: 5 | O96: 0.5 | P96: - | Q96: 0 | R96: - | S96: -
A97: ALB-041 | B97: EQ | D97: EQ-TROMPO | E97: Hormigonera De 150 Litros 1hp Con Rueda Maciza | G97: 0.25 | H97: 0 | I97: 957.2532 | J97: 239.3133 | K97: ALB-041|EQ | L97: 2 | M97: ALB-041|EQ|2 | N97: 5 | O97: 0.25 | P97: - | Q97: 0 | R97: - | S97: -
A98: ALB-041 | B98: MAT | C98: OTR | D98: AGR-001 | E98: ARENA LAVADA | F98: m3 | G98: 0.0018 | H98: 0.1 | I98: 32399.77 | J98: 64.151545 | K98: ALB-041|MAT | L98: 1 | M98: ALB-041|MAT|1 | N98: 5 | O98: 0.0018 | P98: - | Q98: 0 | R98: - | S98: -
A99: ALB-041 | B99: MAT | C99: OTR | D99: AGR-004 | E99: Cemento Portland x 50kg | F99: Bol | G99: 0.0162 | H99: 0.1 | I99: 7809.48 | J99: 139.16493 | K99: ALB-041|MAT | L99: 2 | M99: ALB-041|MAT|2 | N99: 5 | O99: 0.0162 | P99: - | Q99: 0 | R99: - | S99: -
A100: ALB-041 | B100: MAT | C100: OTR | D100: MAT-CONS | E100: Consumibles | F100: gl | G100: 1.0470799 | H100: 0 | I100: 1 | J100: 1.0470799 | K100: ALB-041|MAT | L100: 3 | M100: ALB-041|MAT|3 | N100: 5 | O100: 1.0470799 | P100: - | Q100: 0 | R100: - | S100: -
...

Sheet 2_Gastos_DirInd
A1: Fecha | B1: Tipo | C1: Concepto | D1: Monto
A2: 45627 | B2: Directo | C2: Coordinacion de obra | D2: 285000
A3: 45627 | B3: Directo | C3: Proyecto (50%) | D3: 2657587
A4: 45627 | B4: Directo | C4: Vehiculo obra | D4: 232617.75
A5: 45627 | B5: Indirecto | C5: Payroll - Socios | D5: 639132.78
A6: 45658 | B6: Directo | C6: Coordinacion de obra | D6: 380000
A7: 45658 | B7: Directo | C7: Proyecto (50%) | D7: 1482428.3
A8: 45658 | B8: Directo | C8: Vehiculo obra | D8: 158507.36
A9: 45658 | B9: Indirecto | C9: Payroll - Administración | D9: 541548.43
A10: 45658 | B10: Indirecto | C10: Payroll - Socios | D10: 1284241.8
A11: 45689 | B11: Directo | C11: Coordinacion de obra | D11: 400000
A12: 45689 | B12: Directo | C12: Proyecto (50%) | D12: 2402343.7
A13: 45689 | B13: Directo | C13: Vehiculo obra | D13: 81157.059
... A81: 46082 | B81: Indirecto | C81: Payroll - Socios | D81: 1562500.1

Sheet 2_Quincenas
A1: Resumen Consolidado por Obra (Horas)
A3: Mes | B3: Período | C3: Obra | D3: Categoría | E3: Rubro | F3: Horas totales | G3: Horas normales | H3: Horas extra 50% | I3: Horas extra 100% | K3: Costo Hs. Normales | L3: Costo Hs. Extra 50% | M3: Costo Hs. Extra 100% | N3: Total | O3: Total Descontado
A4: 45992 | B4: 1Q | C4: GARCIA DEL RIO | D4: MEDIO OFICIAL | E4: Albañilería MO | F4: =G4+H4+I4 -> 80 | G4: 68 | H4: 10 | I4: 2 | K4: =IFERROR(G4*INDEX('0_Jornales_MO'!$G$4:$J$21,MATCH(A4,'0_Jornales_MO'!$A$4:$A$21,0),MATCH(D4,{"ESPECIALIZADO","OFICIAL","MEDIO OFICIAL","AYUDANTE"},0)),"-") -> 691527.65 | L4: =IFERROR(H4*INDEX('0_Jornales_MO'!$G$4:$J$21,MATCH(A4,'0_Jornales_MO'!$A$4:$A$21,0),MATCH(D4,{"ESPECIALIZADO","OFICIAL","MEDIO OFICIAL","AYUDANTE"},0))*1.5,"-") -> 152542.86 | M4: =IFERROR(I4*INDEX('0_Jornales_MO'!$G$4:$J$21,MATCH(A4,'0_Jornales_MO'!$A$4:$A$21,0),MATCH(D4,{"ESPECIALIZADO","OFICIAL","MEDIO OFICIAL","AYUDANTE"},0))*2,"-") -> 40678.097 | N4: =IFERROR(SUM(K4:M4),"-") -> 884748.61 | O4: =IFERROR($N4 * SUMIF('0_Indice_CAC'!$A:$A,$A4,'0_Indice_CAC'!$D:$D),"-") -> 715311.75
A5: 45992 | B5: 1Q | C5: GARCIA DEL RIO | D5: MEDIO OFICIAL | E5: Eléctrico MO | F5: =G5+H5+I5 -> 101 | G5: 88 | H5: 9 | I5: 4 | K5: =IFERROR(G5*INDEX('0_Jornales_MO'!$G$4:$J$21,MATCH(A5,'0_Jornales_MO'!$A$4:$A$21,0),MATCH(D5,{"ESPECIALIZADO","OFICIAL","MEDIO OFICIAL","AYUDANTE"},0)),"-") -> 894918.14 | L5: =IFERROR(H5*INDEX('0_Jornales_MO'!$G$4:$J$21,MATCH(A5,'0_Jornales_MO'!$A$4:$A$21,0),MATCH(D5,{"ESPECIALIZADO","OFICIAL","MEDIO OFICIAL","AYUDANTE"},0))*1.5,"-") -> 137288.58 | M5: =IFERROR(I5*INDEX('0_Jornales_MO'!$G$4:$J$21,MATCH(A5,'0_Jornales_MO'!$A$4:$A$21,0),MATCH(D5,{"ESPECIALIZADO","OFICIAL","MEDIO OFICIAL","AYUDANTE"},0))*2,"-") -> 81356.194 | N5: =IFERROR(SUM(K5:M5),"-") -> 1113562.9 | O5: =IFERROR($N5 * SUMIF('0_Indice_CAC'!$A:$A,$A5,'0_Indice_CAC'!$D:$D),"-") -> 900306.17
A6: 45992 | B6: 1Q | C6: GARCIA DEL RIO | D6: AYUDANTE | E6: Albañilería MO | F6: =G6+H6+I6 -> 401 | G6: 336 | H6: 57 | I6: 8 | K6: =IFERROR(G6*INDEX('0_Jornales_MO'!$G$4:$J$21,MATCH(A6,'0_Jornales_MO'!$A$4:$A$21,0),MATCH(D6,{"ESPECIALIZADO","OFICIAL","MEDIO OFICIAL","AYUDANTE"},0)),"-") -> 3201691.9 | L6: =IFERROR(H6*INDEX('0_Jornales_MO'!$G$4:$J$21,MATCH(A6,'0_Jornales_MO'!$A$4:$A$21,0),MATCH(D6,{"ESPECIALIZADO","OFICIAL","MEDIO OFICIAL","AYUDANTE"},0))*1.5,"-") -> 814716.24 | M6: =IFERROR(I6*INDEX('0_Jornales_MO'!$G$4:$J$21,MATCH(A6,'0_Jornales_MO'!$A$4:$A$21,0),MATCH(D6,{"ESPECIALIZADO","OFICIAL","MEDIO OFICIAL","AYUDANTE"},0))*2,"-") -> 152461.52 | N6: =IFERROR(SUM(K6:M6),"-") -> 4168869.6 | O6: =IFERROR($N6 * SUMIF('0_Indice_CAC'!$A:$A,$A6,'0_Indice_CAC'!$D:$D),"-") -> 3370495.7
A7: 45992 | B7: 1Q | C7: GARCIA DEL RIO | D7: ESPECIALIZADO | E7: Albañilería MO | F7: =G7+H7+I7 -> 96 | G7: 84 | H7: 10 | I7: 2 | K7: =IFERROR(G7*INDEX('0_Jornales_MO'!$G$4:$J$21,MATCH(A7,'0_Jornales_MO'!$A$4:$A$21,0),MATCH(D7,{"ESPECIALIZADO","OFICIAL","MEDIO OFICIAL","AYUDANTE"},0)),"-") -> 1195584.4 | L7: =IFERROR(H7*INDEX('0_Jornales_MO'!$G$4:$J$21,MATCH(A7,'0_Jornales_MO'!$A$4:$A$21,0),MATCH(D7,{"ESPECIALIZADO","OFICIAL","MEDIO OFICIAL","AYUDANTE"},0))*1.5,"-") -> 213497.22 | M7: =IFERROR(I7*INDEX('0_Jornales_MO'!$G$4:$J$21,MATCH(A7,'0_Jornales_MO'!$A$4:$A$21,0),MATCH(D7,{"ESPECIALIZADO","OFICIAL","MEDIO OFICIAL","AYUDANTE"},0))*2,"-") -> 56932.591 | N7: =IFERROR(SUM(K7:M7),"-") -> 1466014.2 | O7: =IFERROR($N7 * SUMIF('0_Indice_CAC'!$A:$A,$A7,'0_Indice_CAC'!$D:$D),"-") -> 1185260.1
A8: 45992 | B8: 1Q | C8: GARCIA DEL RIO | D8: OFICIAL | E8: Albañilería MO | F8: =G8+H8+I8 -> 231 | G8: 200 | H8: 27 | I8: 4 | K8: =IFERROR(G8*INDEX('0_Jornales_MO'!$G$4:$J$21,MATCH(A8,'0_Jornales_MO'!$A$4:$A$21,0),MATCH(D8,{"ESPECIALIZADO","OFICIAL","MEDIO OFICIAL","AYUDANTE"},0)),"-") -> 2379923.2 | L8: =IFERROR(H8*INDEX('0_Jornales_MO'!$G$4:$J$21,MATCH(A8,'0_Jornales_MO'!$A$4:$A$21,0),MATCH(D8,{"ESPECIALIZADO","OFICIAL","MEDIO OFICIAL","AYUDANTE"},0))*1.5,"-") -> 481934.44 | M8: =IFERROR(I8*INDEX('0_Jornales_MO'!$G$4:$J$21,MATCH(A8,'0_Jornales_MO'!$A$4:$A$21,0),MATCH(D8,{"ESPECIALIZADO","OFICIAL","MEDIO OFICIAL","AYUDANTE"},0))*2,"-") -> 95196.927 | N8: =IFERROR(SUM(K8:M8),"-") -> 2957054.5 | O8: =IFERROR($N8 * SUMIF('0_Indice_CAC'!$A:$A,$A8,'0_Indice_CAC'!$D:$D),"-") -> 2390753.5
A9: 45992 | B9: 1Q | C9: GARCIA DEL RIO | D9: OFICIAL | E9: Eléctrico MO | F9: =G9+H9+I9 -> 96 | G9: 84 | H9: 10 | I9: 2 | K9: =IFERROR(G9*INDEX('0_Jornales_MO'!$G$4:$J$21,MATCH(A9,'0_Jornales_MO'!$A$4:$A$21,0),MATCH(D9,{"ESPECIALIZADO","OFICIAL","MEDIO OFICIAL","AYUDANTE"},0)),"-") -> 999567.73 | L9: =IFERROR(H9*INDEX('0_Jornales_MO'!$G$4:$J$21,MATCH(A9,'0_Jornales_MO'!$A$4:$A$21,0),MATCH(D9,{"ESPECIALIZADO","OFICIAL","MEDIO OFICIAL","AYUDANTE"},0))*1.5,"-") -> 178494.24 | M9: =IFERROR(I9*INDEX('0_Jornales_MO'!$G$4:$J$21,MATCH(A9,'0_Jornales_MO'!$A$4:$A$21,0),MATCH(D9,{"ESPECIALIZADO","OFICIAL","MEDIO OFICIAL","AYUDANTE"},0))*2,"-") -> 47598.464 | N9: =IFERROR(SUM(K9:M9),"-") -> 1225660.4 | O9: =IFERROR($N9 * SUMIF('0_Indice_CAC'!$A:$A,$A9,'0_Indice_CAC'!$D:$D),"-") -> 990936.06
A10: 45992 | B10: 1Q | C10: GARCIA DEL RIO | D10: OFICIAL | E10: Sanitaria MO | F10: =G10+H10+I10 -> 96 | G10: 96 | H10: 0 | I10: 0 | K10: =IFERROR(G10*INDEX('0_Jornales_MO'!$G$4:$J$21,MATCH(A10,'0_Jornales_MO'!$A$4:$A$21,0),MATCH(D10,{"ESPECIALIZADO","OFICIAL","MEDIO OFICIAL","AYUDANTE"},0)),"-") -> 1142363.1 | L10: =IFERROR(H10*INDEX('0_Jornales_MO'!$G$4:$J$21,MATCH(A10,'0_Jornales_MO'!$A$4:$A$21,0),MATCH(D10,{"ESPECIALIZADO","OFICIAL","MEDIO OFICIAL","AYUDANTE"},0))*1.5,"-") -> 0 | M10: =IFERROR(I10*INDEX('0_Jornales_MO'!$G$4:$J$21,MATCH(A10,'0_Jornales_MO'!$A$4:$A$21,0),MATCH(D10,{"ESPECIALIZADO","OFICIAL","MEDIO OFICIAL","AYUDANTE"},0))*2,"-") -> 0 | N10: =IFERROR(SUM(K10:M10),"-") -> 1142363.1 | O10: =IFERROR($N10 * SUMIF('0_Indice_CAC'!$A:$A,$A10,'0_Indice_CAC'!$D:$D),"-") -> 923590.89
A11: 45992 | B11: 2Q | C11: GARCIA DEL RIO | D11: MEDIO OFICIAL | E11: Albañilería MO | F11: =G11+H11+I11 -> 94 | G11: 88 | H11: 6 | I11: 0 | K11: =IFERROR(G11*INDEX('0_Jornales_MO'!$G$4:$J$21,MATCH(A11,'0_Jornales_MO'!$A$4:$A$21,0),MATCH(D11,{"ESPECIALIZADO","OFICIAL","MEDIO OFICIAL","AYUDANTE"},0)),"-") -> 894918.14 | L11: =IFERROR(H11*INDEX('0_Jornales_MO'!$G$4:$J$21,MATCH(A11,'0_Jornales_MO'!$A$4:$A$21,0),MATCH(D11,{"ESPECIALIZADO","OFICIAL","MEDIO OFICIAL","AYUDANTE"},0))*1.5,"-") -> 91525.719 | M11: =IFERROR(I11*INDEX('0_Jornales_MO'!$G$4:$J$21,MATCH(A11,'0_Jornales_MO'!$A$4:$A$21,0),MATCH(D11,{"ESPECIALIZADO","OFICIAL","MEDIO OFICIAL","AYUDANTE"},0))*2,"-") -> 0 | N11: =IFERROR(SUM(K11:M11),"-") -> 986443.86 | O11: =IFERROR($N11 * SUMIF('0_Indice_CAC'!$A:$A,$A11,'0_Indice_CAC'!$D:$D),"-") -> 797531.49
A12: 45992 | B12: 2Q | C12: GARCIA DEL RIO | D12: MEDIO OFICIAL | E12: Eléctrico MO | F12: =G12+H12+I12 -> 61 | G12: 56 | H12: 5 | I12: 0 | K12: =IFERROR(G12*INDEX('0_Jornales_MO'!$G$4:$J$21,MATCH(A12,'0_Jornales_MO'!$A$4:$A$21,0),MATCH(D12,{"ESPECIALIZADO","OFICIAL","MEDIO OFICIAL","AYUDANTE"},0)),"-") -> 569493.36 | L12: =IFERROR(H12*INDEX('0_Jornales_MO'!$G$4:$J$21,MATCH(A12,'0_Jornales_MO'!$A$4:$A$21,0),MATCH(D12,{"ESPECIALIZADO","OFICIAL","MEDIO OFICIAL","AYUDANTE"},0))*1.5,"-") -> 76271.432 | M12: =IFERROR(I12*INDEX('0_Jornales_MO'!$G$4:$J$21,MATCH(A12,'0_Jornales_MO'!$A$4:$A$21,0),MATCH(D12,{"ESPECIALIZADO","OFICIAL","MEDIO OFICIAL","AYUDANTE"},0))*2,"-") -> 0 | N12: =IFERROR(SUM(K12:M12),"-") -> 645764.79 | O12: =IFERROR($N12 * SUMIF('0_Indice_CAC'!$A:$A,$A12,'0_Indice_CAC'!$D:$D),"-") -> 522095.36
A13: 45992 | B13: 2Q | C13: GARCIA DEL RIO | D13: AYUDANTE | E13: Albañilería MO | F13: =G13+H13+I13 -> 412 | G13: 384 | H13: 28 | I13: 0 | K13: =IFERROR(G13*INDEX('0_Jornales_MO'!$G$4:$J$21,MATCH(A13,'0_Jornales_MO'!$A$4:$A$21,0),MATCH(D13,{"ESPECIALIZADO","OFICIAL","MEDIO OFICIAL","AYUDANTE"},0)),"-") -> 3659076.4 | L13: =IFERROR(H13*INDEX('0_Jornales_MO'!$G$4:$J$21,MATCH(A13,'0_Jornales_MO'!$A$4:$A$21,0),MATCH(D13,{"ESPECIALIZADO","OFICIAL","MEDIO OFICIAL","AYUDANTE"},0))*1.5,"-") -> 400211.48 | M13: =IFERROR(I13*INDEX('0_Jornales_MO'!$G$4:$J$21,MATCH(A13,'0_Jornales_MO'!$A$4:$A$21,0),MATCH(D13,{"ESPECIALIZADO","OFICIAL","MEDIO OFICIAL","AYUDANTE"},0))*2,"-") -> 0 | N13: =IFERROR(SUM(K13:M13),"-") -> 4059287.9 | O13: =IFERROR($N13 * SUMIF('0_Indice_CAC'!$A:$A,$A13,'0_Indice_CAC'!$D:$D),"-") -> 3281899.8
A14: 45992 | B14: 2Q | C14: GARCIA DEL RIO | D14: ESPECIALIZADO | E14: Albañilería MO | F14: =G14+H14+I14 -> 103 | G14: 96 | H14: 7 | I14: 0 | K14: =IFERROR(G14*INDEX('0_Jornales_MO'!$G$4:$J$21,MATCH(A14,'0_Jornales_MO'!$A$4:$A$21,0),MATCH(D14,{"ESPECIALIZADO","OFICIAL","MEDIO OFICIAL","AYUDANTE"},0)),"-") -> 1366382.2 | L14: =IFERROR(H14*INDEX('0_Jornales_MO'!$G$4:$J$21,MATCH(A14,'0_Jornales_MO'!$A$4:$A$21,0),MATCH(D14,{"ESPECIALIZADO","OFICIAL","MEDIO OFICIAL","AYUDANTE"},0))*1.5,"-") -> 149448.05 | M14: =IFERROR(I14*INDEX('0_Jornales_MO'!$G$4:$J$21,MATCH(A14,'0_Jornales_MO'!$A$4:$A$21,0),MATCH(D14,{"ESPECIALIZADO","OFICIAL","MEDIO OFICIAL","AYUDANTE"},0))*2,"-") -> 0 | N14: =IFERROR(SUM(K14:M14),"-") -> 1515830.2 | O14: =IFERROR($N14 * SUMIF('0_Indice_CAC'!$A:$A,$A14,'0_Indice_CAC'!$D:$D),"-") -> 1225535.9
A15: 45992 | B15: 2Q | C15: GARCIA DEL RIO | D15: OFICIAL | E15: Albañilería MO | F15: =G15+H15+I15 -> 301 | G15: 280 | H15: 21 | I15: 0 | K15: =IFERROR(G15*INDEX('0_Jornales_MO'!$G$4:$J$21,MATCH(A15,'0_Jornales_MO'!$A$4:$A$21,0),MATCH(D15,{"ESPECIALIZADO","OFICIAL","MEDIO OFICIAL","AYUDANTE"},0)),"-") -> 3331892.4 | L15: =IFERROR(H15*INDEX('0_Jornales_MO'!$G$4:$J$21,MATCH(A15,'0_Jornales_MO'!$A$4:$A$21,0),MATCH(D15,{"ESPECIALIZADO","OFICIAL","MEDIO OFICIAL","AYUDANTE"},0))*1.5,"-") -> 374837.9 | M15: =IFERROR(I15*INDEX('0_Jornales_MO'!$G$4:$J$21,MATCH(A15,'0_Jornales_MO'!$A$4:$A$21,0),MATCH(D15,{"ESPECIALIZADO","OFICIAL","MEDIO OFICIAL","AYUDANTE"},0))*2,"-") -> 0 | N15: =IFERROR(SUM(K15:M15),"-") -> 3706730.3 | O15: =IFERROR($N15 * SUMIF('0_Indice_CAC'!$A:$A,$A15,'0_Indice_CAC'!$D:$D),"-") -> 2996860
... A77: 46113 | B77: 1Q | C77: GARCIA DEL RIO | D77: OFICIAL | E77: Revestimiento MO | F77: =G77+H77+I77 -> 4 | G77: 4 | H77: 0 | I77: 0 | K77: =IFERROR(G77*INDEX('0_Jornales_MO'!$G$4:$J$21,MATCH(A77,'0_Jornales_MO'!$A$4:$A$21,0),MATCH(D77,{"ESPECIALIZADO","OFICIAL","MEDIO OFICIAL","AYUDANTE"},0)),"-") -> 51014.533 | L77: =IFERROR(H77*INDEX('0_Jornales_MO'!$G$4:$J$21,MATCH(A77,'0_Jornales_MO'!$A$4:$A$21,0),MATCH(D77,{"ESPECIALIZADO","OFICIAL","MEDIO OFICIAL","AYUDANTE"},0))*1.5,"-") -> 0 | M77: =IFERROR(I77*INDEX('0_Jornales_MO'!$G$4:$J$21,MATCH(A77,'0_Jornales_MO'!$A$4:$A$21,0),MATCH(D77,{"ESPECIALIZADO","OFICIAL","MEDIO OFICIAL","AYUDANTE"},0))*2,"-") -> 0 | N77: =IFERROR(SUM(K77:M77),"-") -> 51014.533 | O77: =IFERROR($N77 * SUMIF('0_Indice_CAC'!$A:$A,$A77,'0_Indice_CAC'!$D:$D),"-") -> 40524.649
K78: =IFERROR(G78*INDEX('0_Jornales_MO'!$G$4:$J$21,MATCH(A78,'0_Jornales_MO'!$A$4:$A$21,0),MATCH(D78,{"ESPECIALIZADO","OFICIAL","MEDIO OFICIAL","AYUDANTE"},0)),"-") -> - | L78: =IFERROR(H78*INDEX('0_Jornales_MO'!$G$4:$J$21,MATCH(A78,'0_Jornales_MO'!$A$4:$A$21,0),MATCH(D78,{"ESPECIALIZADO","OFICIAL","MEDIO OFICIAL","AYUDANTE"},0))*1.5,"-") -> - | M78: =IFERROR(I78*INDEX('0_Jornales_MO'!$G$4:$J$21,MATCH(A78,'0_Jornales_MO'!$A$4:$A$21,0),MATCH(D78,{"ESPECIALIZADO","OFICIAL","MEDIO OFICIAL","AYUDANTE"},0))*2,"-") -> - | N78: =IFERROR(SUM(K78:M78),"-") -> 0 | O78: =IFERROR($N78 * SUMIF('0_Indice_CAC'!$A:$A,$A78,'0_Indice_CAC'!$D:$D),"-") -> 0
K79: =IFERROR(G79*INDEX('0_Jornales_MO'!$G$4:$J$21,MATCH(A79,'0_Jornales_MO'!$A$4:$A$21,0),MATCH(D79,{"ESPECIALIZADO","OFICIAL","MEDIO OFICIAL","AYUDANTE"},0)),"-") -> - | L79: =IFERROR(H79*INDEX('0_Jornales_MO'!$G$4:$J$21,MATCH(A79,'0_Jornales_MO'!$A$4:$A$21,0),MATCH(D79,{"ESPECIALIZADO","OFICIAL","MEDIO OFICIAL","AYUDANTE"},0))*1.5,"-") -> - | M79: =IFERROR(I79*INDEX('0_Jornales_MO'!$G$4:$J$21,MATCH(A79,'0_Jornales_MO'!$A$4:$A$21,0),MATCH(D79,{"ESPECIALIZADO","OFICIAL","MEDIO OFICIAL","AYUDANTE"},0))*2,"-") -> - | N79: =IFERROR(SUM(K79:M79),"-") -> 0 | O79: =IFERROR($N79 * SUMIF('0_Indice_CAC'!$A:$A,$A79,'0_Indice_CAC'!$D:$D),"-") -> 0
K80: =IFERROR(G80*INDEX('0_Jornales_MO'!$G$4:$J$21,MATCH(A80,'0_Jornales_MO'!$A$4:$A$21,0),MATCH(D80,{"ESPECIALIZADO","OFICIAL","MEDIO OFICIAL","AYUDANTE"},0)),"-") -> - | L80: =IFERROR(H80*INDEX('0_Jornales_MO'!$G$4:$J$21,MATCH(A80,'0_Jornales_MO'!$A$4:$A$21,0),MATCH(D80,{"ESPECIALIZADO","OFICIAL","MEDIO OFICIAL","AYUDANTE"},0))*1.5,"-") -> - | M80: =IFERROR(I80*INDEX('0_Jornales_MO'!$G$4:$J$21,MATCH(A80,'0_Jornales_MO'!$A$4:$A$21,0),MATCH(D80,{"ESPECIALIZADO","OFICIAL","MEDIO OFICIAL","AYUDANTE"},0))*2,"-") -> - | N80: =IFERROR(SUM(K80:M80),"-") -> 0 | O80: =IFERROR($N80 * SUMIF('0_Indice_CAC'!$A:$A,$A80,'0_Indice_CAC'!$D:$D),"-") -> 0
K81: =IFERROR(G81*INDEX('0_Jornales_MO'!$G$4:$J$21,MATCH(A81,'0_Jornales_MO'!$A$4:$A$21,0),MATCH(D81,{"ESPECIALIZADO","OFICIAL","MEDIO OFICIAL","AYUDANTE"},0)),"-") -> - | L81: =IFERROR(H81*INDEX('0_Jornales_MO'!$G$4:$J$21,MATCH(A81,'0_Jornales_MO'!$A$4:$A$21,0),MATCH(D81,{"ESPECIALIZADO","OFICIAL","MEDIO OFICIAL","AYUDANTE"},0))*1.5,"-") -> - | M81: =IFERROR(I81*INDEX('0_Jornales_MO'!$G$4:$J$21,MATCH(A81,'0_Jornales_MO'!$A$4:$A$21,0),MATCH(D81,{"ESPECIALIZADO","OFICIAL","MEDIO OFICIAL","AYUDANTE"},0))*2,"-") -> - | N81: =IFERROR(SUM(K81:M81),"-") -> 0 | O81: =IFERROR($N81 * SUMIF('0_Indice_CAC'!$A:$A,$A81,'0_Indice_CAC'!$D:$D),"-") -> 0
K82: =IFERROR(G82*INDEX('0_Jornales_MO'!$G$4:$J$21,MATCH(A82,'0_Jornales_MO'!$A$4:$A$21,0),MATCH(D82,{"ESPECIALIZADO","OFICIAL","MEDIO OFICIAL","AYUDANTE"},0)),"-") -> - | L82: =IFERROR(H82*INDEX('0_Jornales_MO'!$G$4:$J$21,MATCH(A82,'0_Jornales_MO'!$A$4:$A$21,0),MATCH(D82,{"ESPECIALIZADO","OFICIAL","MEDIO OFICIAL","AYUDANTE"},0))*1.5,"-") -> - | M82: =IFERROR(I82*INDEX('0_Jornales_MO'!$G$4:$J$21,MATCH(A82,'0_Jornales_MO'!$A$4:$A$21,0),MATCH(D82,{"ESPECIALIZADO","OFICIAL","MEDIO OFICIAL","AYUDANTE"},0))*2,"-") -> - | N82: =IFERROR(SUM(K82:M82),"-") -> 0 | O82: =IFERROR($N82 * SUMIF('0_Indice_CAC'!$A:$A,$A82,'0_Indice_CAC'!$D:$D),"-") -> 0
K83: =IFERROR(G83*INDEX('0_Jornales_MO'!$G$4:$J$21,MATCH(A83,'0_Jornales_MO'!$A$4:$A$21,0),MATCH(D83,{"ESPECIALIZADO","OFICIAL","MEDIO OFICIAL","AYUDANTE"},0)),"-") -> - | L83: =IFERROR(H83*INDEX('0_Jornales_MO'!$G$4:$J$21,MATCH(A83,'0_Jornales_MO'!$A$4:$A$21,0),MATCH(D83,{"ESPECIALIZADO","OFICIAL","MEDIO OFICIAL","AYUDANTE"},0))*1.5,"-") -> - | M83: =IFERROR(I83*INDEX('0_Jornales_MO'!$G$4:$J$21,MATCH(A83,'0_Jornales_MO'!$A$4:$A$21,0),MATCH(D83,{"ESPECIALIZADO","OFICIAL","MEDIO OFICIAL","AYUDANTE"},0))*2,"-") -> - | N83: =IFERROR(SUM(K83:M83),"-") -> 0 | O83: =IFERROR($N83 * SUMIF('0_Indice_CAC'!$A:$A,$A83,'0_Indice_CAC'!$D:$D),"-") -> 0
K84: =IFERROR(G84*INDEX('0_Jornales_MO'!$G$4:$J$21,MATCH(A84,'0_Jornales_MO'!$A$4:$A$21,0),MATCH(D84,{"ESPECIALIZADO","OFICIAL","MEDIO OFICIAL","AYUDANTE"},0)),"-") -> - | L84: =IFERROR(H84*INDEX('0_Jornales_MO'!$G$4:$J$21,MATCH(A84,'0_Jornales_MO'!$A$4:$A$21,0),MATCH(D84,{"ESPECIALIZADO","OFICIAL","MEDIO OFICIAL","AYUDANTE"},0))*1.5,"-") -> - | M84: =IFERROR(I84*INDEX('0_Jornales_MO'!$G$4:$J$21,MATCH(A84,'0_Jornales_MO'!$A$4:$A$21,0),MATCH(D84,{"ESPECIALIZADO","OFICIAL","MEDIO OFICIAL","AYUDANTE"},0))*2,"-") -> - | N84: =IFERROR(SUM(K84:M84),"-") -> 0 | O84: =IFERROR($N84 * SUMIF('0_Indice_CAC'!$A:$A,$A84,'0_Indice_CAC'!$D:$D),"-") -> 0
K85: =IFERROR(G85*INDEX('0_Jornales_MO'!$G$4:$J$21,MATCH(A85,'0_Jornales_MO'!$A$4:$A$21,0),MATCH(D85,{"ESPECIALIZADO","OFICIAL","MEDIO OFICIAL","AYUDANTE"},0)),"-") -> - | L85: =IFERROR(H85*INDEX('0_Jornales_MO'!$G$4:$J$21,MATCH(A85,'0_Jornales_MO'!$A$4:$A$21,0),MATCH(D85,{"ESPECIALIZADO","OFICIAL","MEDIO OFICIAL","AYUDANTE"},0))*1.5,"-") -> - | M85: =IFERROR(I85*INDEX('0_Jornales_MO'!$G$4:$J$21,MATCH(A85,'0_Jornales_MO'!$A$4:$A$21,0),MATCH(D85,{"ESPECIALIZADO","OFICIAL","MEDIO OFICIAL","AYUDANTE"},0))*2,"-") -> - | N85: =IFERROR(SUM(K85:M85),"-") -> 0 | O85: =IFERROR($N85 * SUMIF('0_Indice_CAC'!$A:$A,$A85,'0_Indice_CAC'!$D:$D),"-") -> 0
K86: =IFERROR(G86*INDEX('0_Jornales_MO'!$G$4:$J$21,MATCH(A86,'0_Jornales_MO'!$A$4:$A$21,0),MATCH(D86,{"ESPECIALIZADO","OFICIAL","MEDIO OFICIAL","AYUDANTE"},0)),"-") -> - | L86: =IFERROR(H86*INDEX('0_Jornales_MO'!$G$4:$J$21,MATCH(A86,'0_Jornales_MO'!$A$4:$A$21,0),MATCH(D86,{"ESPECIALIZADO","OFICIAL","MEDIO OFICIAL","AYUDANTE"},0))*1.5,"-") -> - | M86: =IFERROR(I86*INDEX('0_Jornales_MO'!$G$4:$J$21,MATCH(A86,'0_Jornales_MO'!$A$4:$A$21,0),MATCH(D86,{"ESPECIALIZADO","OFICIAL","MEDIO OFICIAL","AYUDANTE"},0))*2,"-") -> - | N86: =IFERROR(SUM(K86:M86),"-") -> 0 | O86: =IFERROR($N86 * SUMIF('0_Indice_CAC'!$A:$A,$A86,'0_Indice_CAC'!$D:$D),"-") -> 0
K87: =IFERROR(G87*INDEX('0_Jornales_MO'!$G$4:$J$21,MATCH(A87,'0_Jornales_MO'!$A$4:$A$21,0),MATCH(D87,{"ESPECIALIZADO","OFICIAL","MEDIO OFICIAL","AYUDANTE"},0)),"-") -> - | L87: =IFERROR(H87*INDEX('0_Jornales_MO'!$G$4:$J$21,MATCH(A87,'0_Jornales_MO'!$A$4:$A$21,0),MATCH(D87,{"ESPECIALIZADO","OFICIAL","MEDIO OFICIAL","AYUDANTE"},0))*1.5,"-") -> - | M87: =IFERROR(I87*INDEX('0_Jornales_MO'!$G$4:$J$21,MATCH(A87,'0_Jornales_MO'!$A$4:$A$21,0),MATCH(D87,{"ESPECIALIZADO","OFICIAL","MEDIO OFICIAL","AYUDANTE"},0))*2,"-") -> - | N87: =IFERROR(SUM(K87:M87),"-") -> 0 | O87: =IFERROR($N87 * SUMIF('0_Indice_CAC'!$A:$A,$A87,'0_Indice_CAC'!$D:$D),"-") -> 0
K88: =IFERROR(G88*INDEX('0_Jornales_MO'!$G$4:$J$21,MATCH(A88,'0_Jornales_MO'!$A$4:$A$21,0),MATCH(D88,{"ESPECIALIZADO","OFICIAL","MEDIO OFICIAL","AYUDANTE"},0)),"-") -> - | L88: =IFERROR(H88*INDEX('0_Jornales_MO'!$G$4:$J$21,MATCH(A88,'0_Jornales_MO'!$A$4:$A$21,0),MATCH(D88,{"ESPECIALIZADO","OFICIAL","MEDIO OFICIAL","AYUDANTE"},0))*1.5,"-") -> - | M88: =IFERROR(I88*INDEX('0_Jornales_MO'!$G$4:$J$21,MATCH(A88,'0_Jornales_MO'!$A$4:$A$21,0),MATCH(D88,{"ESPECIALIZADO","OFICIAL","MEDIO OFICIAL","AYUDANTE"},0))*2,"-") -> - | N88: =IFERROR(SUM(K88:M88),"-") -> 0 | O88: =IFERROR($N88 * SUMIF('0_Indice_CAC'!$A:$A,$A88,'0_Indice_CAC'!$D:$D),"-") -> 0
K89: =IFERROR(G89*INDEX('0_Jornales_MO'!$G$4:$J$21,MATCH(A89,'0_Jornales_MO'!$A$4:$A$21,0),MATCH(D89,{"ESPECIALIZADO","OFICIAL","MEDIO OFICIAL","AYUDANTE"},0)),"-") -> - | L89: =IFERROR(H89*INDEX('0_Jornales_MO'!$G$4:$J$21,MATCH(A89,'0_Jornales_MO'!$A$4:$A$21,0),MATCH(D89,{"ESPECIALIZADO","OFICIAL","MEDIO OFICIAL","AYUDANTE"},0))*1.5,"-") -> - | M89: =IFERROR(I89*INDEX('0_Jornales_MO'!$G$4:$J$21,MATCH(A89,'0_Jornales_MO'!$A$4:$A$21,0),MATCH(D89,{"ESPECIALIZADO","OFICIAL","MEDIO OFICIAL","AYUDANTE"},0))*2,"-") -> - | N89: =IFERROR(SUM(K89:M89),"-") -> 0 | O89: =IFERROR($N89 * SUMIF('0_Indice_CAC'!$A:$A,$A89,'0_Indice_CAC'!$D:$D),"-") -> 0
... K94: =IFERROR(G94*INDEX('0_Jornales_MO'!$G$4:$J$21,MATCH(A94,'0_Jornales_MO'!$A$4:$A$21,0),MATCH(D94,{"ESPECIALIZADO","OFICIAL","MEDIO OFICIAL","AYUDANTE"},0)),"-") -> - | L94: =IFERROR(H94*INDEX('0_Jornales_MO'!$G$4:$J$21,MATCH(A94,'0_Jornales_MO'!$A$4:$A$21,0),MATCH(D94,{"ESPECIALIZADO","OFICIAL","MEDIO OFICIAL","AYUDANTE"},0))*1.5,"-") -> - | M94: =IFERROR(I94*INDEX('0_Jornales_MO'!$G$4:$J$21,MATCH(A94,'0_Jornales_MO'!$A$4:$A$21,0),MATCH(D94,{"ESPECIALIZADO","OFICIAL","MEDIO OFICIAL","AYUDANTE"},0))*2,"-") -> - | N94: =IFERROR(SUM(K94:M94),"-") -> 0 | O94: =IFERROR($N94 * SUMIF('0_Indice_CAC'!$A:$A,$A94,'0_Indice_CAC'!$D:$D),"-") -> 0

Sheet 2_Subcontratos
A1: SUBCONTRATOS — MAESTRO DE CONTRATOS
A3: Contrato# | B3: Proveedor | C3: Rubro | D3: Descripción | E3: Monto Presup. | F3: Ajusta CAC | G3: % Anticipo | H3: Pagado BASE+ANT | I3: CAC pagado | J3: CS pagado | K3: Total pagado | L3: Saldo disponible | M3: % consumido | N3: Estado
A4: GDR-SC-001 | B4: ELVIO CESPEDES | C4: Durlock/Yeso | D4: Yeso | E4: 14940000 | F4: SI | G4: 0 | H4: =SUMIFS('2_Movimientos'!$I:$I,'2_Movimientos'!$Q:$Q,$A4,'2_Movimientos'!$R:$R,"BASE")+SUMIFS('2_Movimientos'!$I:$I,'2_Movimientos'!$Q:$Q,$A4,'2_Movimientos'!$R:$R,"ANT") -> 0 | I4: =SUMIFS('2_Movimientos'!$I:$I,'2_Movimientos'!$Q:$Q,$A4,'2_Movimientos'!$R:$R,"CAC") -> 0 | J4: =SUMIFS('2_Movimientos'!$I:$I,'2_Movimientos'!$Q:$Q,$A4,'2_Movimientos'!$R:$R,"CS") -> 0 | K4: =H4+I4+J4 -> 0 | L4: =$E4-H4 -> 14940000 | M4: =IFERROR(H4/$E4,0) -> 0 | N4: =IF(L4<=0,"🔴 Sin saldo",IF(M4>=0.9,"🟠 <10% saldo","🟢 OK")) -> 🟢 OK
A5: GDR-SC-002 | B5: ELVIO CESPEDES | C5: Revoque Exterior | D5: Revoque Exterior | E5: 8360000 | F5: SI | G5: 0 | H5: =SUMIFS('2_Movimientos'!$I:$I,'2_Movimientos'!$Q:$Q,$A5,'2_Movimientos'!$R:$R,"BASE")+SUMIFS('2_Movimientos'!$I:$I,'2_Movimientos'!$Q:$Q,$A5,'2_Movimientos'!$R:$R,"ANT") -> 0 | I5: =SUMIFS('2_Movimientos'!$I:$I,'2_Movimientos'!$Q:$Q,$A5,'2_Movimientos'!$R:$R,"CAC") -> 0 | J5: =SUMIFS('2_Movimientos'!$I:$I,'2_Movimientos'!$Q:$Q,$A5,'2_Movimientos'!$R:$R,"CS") -> 0 | K5: =H5+I5+J5 -> 0 | L5: =$E5-H5 -> 8360000 | M5: =IFERROR(H5/$E5,0) -> 0 | N5: =IF(L5<=0,"🔴 Sin saldo",IF(M5>=0.9,"🟠 <10% saldo","🟢 OK")) -> 🟢 OK
A6: GDR-SC-003 | B6: ANCLAJES CIMA | C6: Fundaciones | D6: Fundaciones | E6: 3037256.1 | F6: SI | G6: 0.3 | H6: =SUMIFS('2_Movimientos'!$I:$I,'2_Movimientos'!$Q:$Q,$A6,'2_Movimientos'!$R:$R,"BASE")+SUMIFS('2_Movimientos'!$I:$I,'2_Movimientos'!$Q:$Q,$A6,'2_Movimientos'!$R:$R,"ANT") -> 0 | I6: =SUMIFS('2_Movimientos'!$I:$I,'2_Movimientos'!$Q:$Q,$A6,'2_Movimientos'!$R:$R,"CAC") -> 0 | J6: =SUMIFS('2_Movimientos'!$I:$I,'2_Movimientos'!$Q:$Q,$A6,'2_Movimientos'!$R:$R,"CS") -> 0 | K6: =H6+I6+J6 -> 0 | L6: =$E6-H6 -> 3037256.1 | M6: =IFERROR(H6/$E6,0) -> 0 | N6: =IF(L6<=0,"🔴 Sin saldo",IF(M6>=0.9,"🟠 <10% saldo","🟢 OK")) -> 🟢 OK
A7: GDR-SC-004 | B7: CELSI VIAL S.A. | C7: Exc. y Mov. de Suelos | D7: Excavacion y Mov. Suelos | E7: 0 | F7: SI | G7: 0 | H7: =SUMIFS('2_Movimientos'!$I:$I,'2_Movimientos'!$Q:$Q,$A7,'2_Movimientos'!$R:$R,"BASE")+SUMIFS('2_Movimientos'!$I:$I,'2_Movimientos'!$Q:$Q,$A7,'2_Movimientos'!$R:$R,"ANT") -> 0 | I7: =SUMIFS('2_Movimientos'!$I:$I,'2_Movimientos'!$Q:$Q,$A7,'2_Movimientos'!$R:$R,"CAC") -> 0 | J7: =SUMIFS('2_Movimientos'!$I:$I,'2_Movimientos'!$Q:$Q,$A7,'2_Movimientos'!$R:$R,"CS") -> 0 | K7: =H7+I7+J7 -> 0 | L7: =$E7-H7 -> 0 | M7: =IFERROR(H7/$E7,0) -> 0 | N7: =IF(L7<=0,"🔴 Sin saldo",IF(M7>=0.9,"🟠 <10% saldo","🟢 OK")) -> 🔴 Sin saldo
A8: GDR-SC-005 | B8: CUADRILLA HORMIGON | C8: Hormigón MO | D8: Hormigon M.O. | E8: 89779071 | F8: SI | G8: 0 | H8: =SUMIFS('2_Movimientos'!$I:$I,'2_Movimientos'!$Q:$Q,$A8,'2_Movimientos'!$R:$R,"BASE")+SUMIFS('2_Movimientos'!$I:$I,'2_Movimientos'!$Q:$Q,$A8,'2_Movimientos'!$R:$R,"ANT") -> 0 | I8: =SUMIFS('2_Movimientos'!$I:$I,'2_Movimientos'!$Q:$Q,$A8,'2_Movimientos'!$R:$R,"CAC") -> 0 | J8: =SUMIFS('2_Movimientos'!$I:$I,'2_Movimientos'!$Q:$Q,$A8,'2_Movimientos'!$R:$R,"CS") -> 0 | K8: =H8+I8+J8 -> 0 | L8: =$E8-H8 -> 89779071 | M8: =IFERROR(H8/$E8,0) -> 0 | N8: =IF(L8<=0,"🔴 Sin saldo",IF(M8>=0.9,"🟠 <10% saldo","🟢 OK")) -> 🟢 OK

Sheet _Listas
A1: RUBROS CANÓNICOS (Plan de Cuentas Tezamat — rama 53 OBRA + especiales) | B1: Código | C1: TIPOS | E1: VALIDACIÓN — rubros de tarea ∈ plan de cuentas | I1: CONCEPTOS GASTOS DIR/IND | J1: Tipo
A2: Preliminares | B2: 53001 | C2: MT | E2: Rubros fuera de plan — 1_Presupuesto (A/B/C/D) | F2: =SUMPRODUCT(('1_Presupuesto'!A4:A229<>"")*('1_Presupuesto'!A4:A229<>"-")*ISNA(MATCH('1_Presupuesto'!A4:A229,$A$2:$A$34,0)))+SUMPRODUCT(('1_Presupuesto'!B4:B229<>"")*('1_Presupuesto'!B4:B229<>"-")*ISNA(MATCH('1_Presupuesto'!B4:B229,$A$2:$A$34,0)))+SUMPRODUCT(('1_Presupuesto'!C4:C229<>"")*('1_Presupuesto'!C4:C229<>"-")*ISNA(MATCH('1_Presupuesto'!C4:C229,$A$2:$A$34,0)))+SUMPRODUCT(('1_Presupuesto'!D4:D229<>"")*('1_Presupuesto'!D4:D229<>"-")*ISNA(MATCH('1_Presupuesto'!D4:D229,$A$2:$A$34,0))) -> 0 | G2: =IF(F2=0,"✓","⚠") -> ✓ | I2: Oficina en obra (6x3 c/AA) | J2: Directo
A3: Demolición | B3: 53002 | C3: MO | E3: Rubros fuera de plan — 2_Quincenas (E) | F3: =SUMPRODUCT(('2_Quincenas'!E4:E95<>"")*('2_Quincenas'!E4:E95<>"-")*ISNA(MATCH('2_Quincenas'!E4:E95,$A$2:$A$34,0))) -> 0 | G3: =IF(F3=0,"✓","⚠") -> ✓ | I3: Obrador 6x3 s/AA | J3: Directo
A4: Movimiento de Suelos | B4: 53003 | I4: Pañol (6x3) | J4: Directo
A5: Hormigón MT | B5: 53004 | I5: Baños | J5: Directo
A6: Homigón MO | B6: 53005 | I6: HyS permanente | J6: Directo
A7: Metálica MT | B7: 53006 | I7: Energía de obra | J7: Directo
A8: Metálica MO | B8: 53007 | I8: Agua de obra | J8: Directo
A9: Albañilería MT | B9: 53008 | I9: Proyecto (50%) | J9: Directo
A10: Albañilería MO | B10: 53009 | I10: Coordinacion de obra | J10: Directo
A11: Durlock MT | B11: 53010 | I11: Sobrestante | J11: Directo
A12: Durlock MO | B12: 53011 | I12: Capataz | J12: Directo
A13: Aberturas | B13: 53012 | I13: Logistica | J13: Directo
A14: Revestimiento MT | B14: 53013 | I14: Vehiculo obra | J14: Directo
A15: Revestimiento MO | B15: 53014 | I15: Payroll - Socios | J15: Indirecto
... A17: Pintura MO | B17: 53016 | I17: Payroll - Administración | J17: Indirecto
A18: Sanitaria MT | B18: 53017
A19: Sanitaria MO | B19: 53018
A20: Eléctrico MT | B20: 53019
A21: Eléctrico MO | B21: 53020
A22: Provisiones | B22: 53021
A23: Gastos Generales | B23: 53022
A24: Varios Ferreteria | B24: 53023
A25: Termomecánica MT | B25: 53024
A26: Termomecánica MO | B26: 53025
A27: Seguridad e Higiene | B27: 53026
A28: Herrería MT | B28: 53027
A29: Herrería MO | B29: 53028
... A34: Supervisión de Obra MO | B34: 52209

Sheet Cert_OC_Cliente
A1: Obra | B1: ID OC | C1: Descripcion | D1: Presupuesto aprobado | E1: % anticipo | F1: Mes base CAC | G1: Indice base CAC | H1: % Blanco sugerido | I1: % Negro sugerido | J1: % desacopio sugerido | K1: % IVA sugerido | L1: Presupuesto | M1: Fecha anticipo
A2: GDR 3760 | B2: GDR-OC01 | C2: Pto 1 - Preliminar y Hormigón | D2: 500907720 | E2: 0.4 | F2: 45627 | G2: =_xlfn.XLOOKUP(F2,'0_Indice_CAC'!$A:$A,'0_Indice_CAC'!$B:$B) -> 15356.4 | H2: 0.7 | I2: 0.3 | J2: 0.4 | K2: 0.21 | L2: PTO 01 | M2: 45689
A3: GDR 3760 | B3: GDR-OC02 | C3: Pto 2 - Albañilería e Instalaciones | D3: 844845248 | E3: 0.1 | F3: 45627 | G3: =_xlfn.XLOOKUP(F3,'0_Indice_CAC'!$A:$A,'0_Indice_CAC'!$B:$B) -> 15356.4 | H3: 0.7 | I3: 0.3 | J3: 0.1 | K3: 0.21 | L3: PTO 02 | M3: 45689
A4: GDR 3760 | B4: GDR-OC03 | C4: Adicionales 01 | D4: 96300019 | E4: 0 | F4: 45627 | G4: =_xlfn.XLOOKUP(F4,'0_Indice_CAC'!$A:$A,'0_Indice_CAC'!$B:$B) -> 15356.4 | H4: 0 | I4: 1 | J4: 0 | K4: 0 | L4: PTO 03

Sheet Cert_App_Output
A1: Obra | B1: ID OC | C1: ID Certif | D1: Fecha | E1: Cod. tarea | F1: % anterior | G1: % actual | H1: % total | I1: PV total tarea | J1: $ base tarea (cert act.) | K1: Presupuesto | L1: Control vs Ppto
A2: GDR 3760 | B2: GDR-OC01 | C2: GDR-OC01-C01 | D2: 45747 | E2: 1.02 | F2: 0 | G2: 0.33 | H2: =F2+G2 -> 0.33 | I2: =SUMIFS('1_Presupuesto'!$V:$V,'1_Presupuesto'!$X:$X,K2,'1_Presupuesto'!$E:$E,E2) -> 1154940.5 | J2: =G2*I2 -> 381130.35 | K2: =_xlfn.XLOOKUP(B2,Cert_OC_Cliente!$B:$B,Cert_OC_Cliente!$L:$L) -> PTO 01 | L2: =IF($E2="","",IF(AND(ISNUMBER($I2),$H2<=1.0001),"✓","⚠")) -> ✓
A3: GDR 3760 | B3: GDR-OC01 | C3: GDR-OC01-C01 | D3: 45747 | E3: 1.05 | F3: 0 | G3: 0.7 | H3: =F3+G3 -> 0.7 | I3: =SUMIFS('1_Presupuesto'!$V:$V,'1_Presupuesto'!$X:$X,K3,'1_Presupuesto'!$E:$E,E3) -> 9812331.4 | J3: =G3*I3 -> 6868632 | K3: =_xlfn.XLOOKUP(B3,Cert_OC_Cliente!$B:$B,Cert_OC_Cliente!$L:$L) -> PTO 01 | L3: =IF($E3="","",IF(AND(ISNUMBER($I3),$H3<=1.0001),"✓","⚠")) -> ✓
A4: GDR 3760 | B4: GDR-OC01 | C4: GDR-OC01-C01 | D4: 45747 | E4: 1.06 | F4: 0 | G4: 0.25 | H4: =F4+G4 -> 0.25 | I4: =SUMIFS('1_Presupuesto'!$V:$V,'1_Presupuesto'!$X:$X,K4,'1_Presupuesto'!$E:$E,E4) -> 1771384.2 | J4: =G4*I4 -> 442846.06 | K4: =_xlfn.XLOOKUP(B4,Cert_OC_Cliente!$B:$B,Cert_OC_Cliente!$L:$L) -> PTO 01 | L4: =IF($E4="","",IF(AND(ISNUMBER($I4),$H4<=1.0001),"✓","⚠")) -> ✓
A5: GDR 3760 | B5: GDR-OC01 | C5: GDR-OC01-C01 | D5: 45747 | E5: 1.07 | F5: 0 | G5: 0.5 | H5: =F5+G5 -> 0.5 | I5: =SUMIFS('1_Presupuesto'!$V:$V,'1_Presupuesto'!$X:$X,K5,'1_Presupuesto'!$E:$E,E5) -> 2287981.9 | J5: =G5*I5 -> 1143991 | K5: =_xlfn.XLOOKUP(B5,Cert_OC_Cliente!$B:$B,Cert_OC_Cliente!$L:$L) -> PTO 01 | L5: =IF($E5="","",IF(AND(ISNUMBER($I5),$H5<=1.0001),"✓","⚠")) -> ✓
A6: GDR 3760 | B6: GDR-OC01 | C6: GDR-OC01-C01 | D6: 45747 | E6: 1.08 | F6: 0 | G6: 0.2 | H6: =F6+G6 -> 0.2 | I6: =SUMIFS('1_Presupuesto'!$V:$V,'1_Presupuesto'!$X:$X,K6,'1_Presupuesto'!$E:$E,E6) -> 1808217.4 | J6: =G6*I6 -> 361643.49 | K6: =_xlfn.XLOOKUP(B6,Cert_OC_Cliente!$B:$B,Cert_OC_Cliente!$L:$L) -> PTO 01 | L6: =IF($E6="","",IF(AND(ISNUMBER($I6),$H6<=1.0001),"✓","⚠")) -> ✓
A7: GDR 3760 | B7: GDR-OC01 | C7: GDR-OC01-C01 | D7: 45747 | E7: 1.09 | F7: 0 | G7: 0.6 | H7: =F7+G7 -> 0.6 | I7: =SUMIFS('1_Presupuesto'!$V:$V,'1_Presupuesto'!$X:$X,K7,'1_Presupuesto'!$E:$E,E7) -> 483368.36 | J7: =G7*I7 -> 290021.01 | K7: =_xlfn.XLOOKUP(B7,Cert_OC_Cliente!$B:$B,Cert_OC_Cliente!$L:$L) -> PTO 01 | L7: =IF($E7="","",IF(AND(ISNUMBER($I7),$H7<=1.0001),"✓","⚠")) -> ✓
A8: GDR 3760 | B8: GDR-OC01 | C8: GDR-OC01-C01 | D8: 45747 | E8: 2.01 | F8: 0 | G8: 0.35 | H8: =F8+G8 -> 0.35 | I8: =SUMIFS('1_Presupuesto'!$V:$V,'1_Presupuesto'!$X:$X,K8,'1_Presupuesto'!$E:$E,E8) -> 16262640 | J8: =G8*I8 -> 5691924 | K8: =_xlfn.XLOOKUP(B8,Cert_OC_Cliente!$B:$B,Cert_OC_Cliente!$L:$L) -> PTO 01 | L8: =IF($E8="","",IF(AND(ISNUMBER($I8),$H8<=1.0001),"✓","⚠")) -> ✓
A9: GDR 3760 | B9: GDR-OC01 | C9: GDR-OC01-C01 | D9: 45747 | E9: 2.02 | F9: 0 | G9: 0.15 | H9: =F9+G9 -> 0.15 | I9: =SUMIFS('1_Presupuesto'!$V:$V,'1_Presupuesto'!$X:$X,K9,'1_Presupuesto'!$E:$E,E9) -> 11624716 | J9: =G9*I9 -> 1743707.4 | K9: =_xlfn.XLOOKUP(B9,Cert_OC_Cliente!$B:$B,Cert_OC_Cliente!$L:$L) -> PTO 01 | L9: =IF($E9="","",IF(AND(ISNUMBER($I9),$H9<=1.0001),"✓","⚠")) -> ✓
A10: GDR 3760 | B10: GDR-OC01 | C10: GDR-OC01-C01 | D10: 45747 | E10: 3.02 | F10: 0 | G10: 1 | H10: =F10+G10 -> 1 | I10: =SUMIFS('1_Presupuesto'!$V:$V,'1_Presupuesto'!$X:$X,K10,'1_Presupuesto'!$E:$E,E10) -> 8292534.5 | J10: =G10*I10 -> 8292534.5 | K10: =_xlfn.XLOOKUP(B10,Cert_OC_Cliente!$B:$B,Cert_OC_Cliente!$L:$L) -> PTO 01 | L10: =IF($E10="","",IF(AND(ISNUMBER($I10),$H10<=1.0001),"✓","⚠")) -> ✓
A11: GDR 3760 | B11: GDR-OC01 | C11: GDR-OC01-C01 | D11: 45747 | E11: 3.03 | F11: 0 | G11: 0.35 | H11: =F11+G11 -> 0.35 | I11: =SUMIFS('1_Presupuesto'!$V:$V,'1_Presupuesto'!$X:$X,K11,'1_Presupuesto'!$E:$E,E11) -> 12332140 | J11: =G11*I11 -> 4316248.9 | K11: =_xlfn.XLOOKUP(B11,Cert_OC_Cliente!$B:$B,Cert_OC_Cliente!$L:$L) -> PTO 01 | L11: =IF($E11="","",IF(AND(ISNUMBER($I11),$H11<=1.0001),"✓","⚠")) -> ✓
A12: GDR 3760 | B12: GDR-OC01 | C12: GDR-OC01-C01 | D12: 45747 | E12: 3.04 | F12: 0 | G12: 0.35 | H12: =F12+G12 -> 0.35 | I12: =SUMIFS('1_Presupuesto'!$V:$V,'1_Presupuesto'!$X:$X,K12,'1_Presupuesto'!$E:$E,E12) -> 6721405.5 | J12: =G12*I12 -> 2352491.9 | K12: =_xlfn.XLOOKUP(B12,Cert_OC_Cliente!$B:$B,Cert_OC_Cliente!$L:$L) -> PTO 01 | L12: =IF($E12="","",IF(AND(ISNUMBER($I12),$H12<=1.0001),"✓","⚠")) -> ✓
A13: GDR 3760 | B13: GDR-OC01 | C13: GDR-OC01-C01 | D13: 45747 | E13: 3.22 | F13: 0 | G13: 0.3 | H13: =F13+G13 -> 0.3 | I13: =SUMIFS('1_Presupuesto'!$V:$V,'1_Presupuesto'!$X:$X,K13,'1_Presupuesto'!$E:$E,E13) -> 2625266.1 | J13: =G13*I13 -> 787579.82 | K13: =_xlfn.XLOOKUP(B13,Cert_OC_Cliente!$B:$B,Cert_OC_Cliente!$L:$L) -> PTO 01 | L13: =IF($E13="","",IF(AND(ISNUMBER($I13),$H13<=1.0001),"✓","⚠")) -> ✓
... A468: GDR 3760 | B468: GDR-OC02 | C468: GDR-OC02-C15 | D468: 46172 | E468: 25.02 | F468: 0.7 | G468: 0.05 | H468: =F468+G468 -> 0.75 | I468: =SUMIFS('1_Presupuesto'!$V:$V,'1_Presupuesto'!$X:$X,K468,'1_Presupuesto'!$E:$E,E468) -> 11328183 | J468: =G468*I468 -> 566409.16 | K468: =_xlfn.XLOOKUP(B468,Cert_OC_Cliente!$B:$B,Cert_OC_Cliente!$L:$L) -> PTO 02 | L468: =IF($E468="","",IF(AND(ISNUMBER($I468),$H468<=1.0001),"✓","⚠")) -> ✓
A469: GDR 3760 | B469: GDR-OC03 | C469: GDR-OC03-C01 | D469: 45900 | E469: 5.01 | F469: 0 | G469: 0.03 | H469: =F469+G469 -> 0.03 | I469: 73764839 | J469: =G469*I469 -> 2212945.2 | K469: =_xlfn.XLOOKUP(B469,Cert_OC_Cliente!$B:$B,Cert_OC_Cliente!$L:$L) -> PTO 03 | L469: =IF($E469="","",IF(AND(ISNUMBER($I469),$H469<=1.0001),"✓","⚠")) -> ✓
A470: GDR 3760 | B470: GDR-OC03 | C470: GDR-OC03-C02 | D470: 45930 | E470: 5.01 | F470: 0.03 | G470: 0.3228 | H470: =F470+G470 -> 0.3528 | I470: 73764839 | J470: =G470*I470 -> 23811290 | K470: =_xlfn.XLOOKUP(B470,Cert_OC_Cliente!$B:$B,Cert_OC_Cliente!$L:$L) -> PTO 03 | L470: =IF($E470="","",IF(AND(ISNUMBER($I470),$H470<=1.0001),"✓","⚠")) -> ✓
A471: GDR 3760 | B471: GDR-OC03 | C471: GDR-OC03-C03 | D471: 45958 | E471: 5.01 | F471: 0.3528 | G471: 0.3228 | H471: =F471+G471 -> 0.6756 | I471: 73764839 | J471: =G471*I471 -> 23811290 | K471: =_xlfn.XLOOKUP(B471,Cert_OC_Cliente!$B:$B,Cert_OC_Cliente!$L:$L) -> PTO 03 | L471: =IF($E471="","",IF(AND(ISNUMBER($I471),$H471<=1.0001),"✓","⚠")) -> ✓
A472: GDR 3760 | B472: GDR-OC03 | C472: GDR-OC03-C03 | D472: 45958 | E472: 5.02 | F472: 0 | G472: 0.566 | H472: =F472+G472 -> 0.566 | I472: 20080620 | J472: =G472*I472 -> 11365631 | K472: =_xlfn.XLOOKUP(B472,Cert_OC_Cliente!$B:$B,Cert_OC_Cliente!$L:$L) -> PTO 03 | L472: =IF($E472="","",IF(AND(ISNUMBER($I472),$H472<=1.0001),"✓","⚠")) -> ✓

Sheet Cert_Cabecera
A1: ID Certif | B1: ID OC | C1: Fecha | D1: $ base bruta certif. | E1: % desacopio (madre) | F1: $ desacopio | G1: Subtotal neto | H1: Chequeo
A2: GDR-OC01-ANT | B2: =LEFT($A2,FIND("|",SUBSTITUTE($A2,"-","|",2))-1) -> GDR-OC01 | C2: =IFERROR(_xlfn.XLOOKUP($A2,Cert_App_Output!$C:$C,Cert_App_Output!$D:$D),"") | D2: =SUMIFS(Cert_App_Output!$J:$J,Cert_App_Output!$C:$C,$A2) -> 0 | E2: 0 | F2: =$D2*$E2 -> 0 | G2: =$D2-$F2 -> 0 | H2: =IF(COUNTIF(Cert_Calculo!$A:$A,$A2)>0,"OK","FALTA en Calculo") -> OK
A3: GDR-OC02-ANT | B3: =LEFT($A3,FIND("|",SUBSTITUTE($A3,"-","|",2))-1) -> GDR-OC02 | C3: =IFERROR(_xlfn.XLOOKUP($A3,Cert_App_Output!$C:$C,Cert_App_Output!$D:$D),"") | D3: =SUMIFS(Cert_App_Output!$J:$J,Cert_App_Output!$C:$C,$A3) -> 0 | E3: 0 | F3: =$D3*$E3 -> 0 | G3: =$D3-$F3 -> 0 | H3: =IF(COUNTIF(Cert_Calculo!$A:$A,$A3)>0,"OK","FALTA en Calculo") -> OK
A4: GDR-OC03-ANT | B4: =LEFT($A4,FIND("|",SUBSTITUTE($A4,"-","|",2))-1) -> GDR-OC03 | C4: =IFERROR(_xlfn.XLOOKUP($A4,Cert_App_Output!$C:$C,Cert_App_Output!$D:$D),"") | D4: =SUMIFS(Cert_App_Output!$J:$J,Cert_App_Output!$C:$C,$A4) -> 0 | E4: 0 | F4: =$D4*$E4 -> 0 | G4: =$D4-$F4 -> 0 | H4: =IF(COUNTIF(Cert_Calculo!$A:$A,$A4)>0,"OK","FALTA en Calculo") -> OK
A5: GDR-OC01-C01 | B5: =LEFT($A5,FIND("|",SUBSTITUTE($A5,"-","|",2))-1) -> GDR-OC01 | C5: =IFERROR(_xlfn.XLOOKUP($A5,Cert_App_Output!$C:$C,Cert_App_Output!$D:$D),"") -> 45747 | D5: =SUMIFS(Cert_App_Output!$J:$J,Cert_App_Output!$C:$C,$A5) -> 32672750 | E5: 0.4 | F5: =$D5*$E5 -> 13069100 | G5: =$D5-$F5 -> 19603650 | H5: =IF(COUNTIF(Cert_Calculo!$A:$A,$A5)>0,"OK","FALTA en Calculo") -> OK
A6: GDR-OC01-C02 | B6: =LEFT($A6,FIND("|",SUBSTITUTE($A6,"-","|",2))-1) -> GDR-OC01 | C6: =IFERROR(_xlfn.XLOOKUP($A6,Cert_App_Output!$C:$C,Cert_App_Output!$D:$D),"") -> 45777 | D6: =SUMIFS(Cert_App_Output!$J:$J,Cert_App_Output!$C:$C,$A6) -> 27443238 | E6: 0.4 | F6: =$D6*$E6 -> 10977295 | G6: =$D6-$F6 -> 16465943 | H6: =IF(COUNTIF(Cert_Calculo!$A:$A,$A6)>0,"OK","FALTA en Calculo") -> OK
A7: GDR-OC01-C03 | B7: =LEFT($A7,FIND("|",SUBSTITUTE($A7,"-","|",2))-1) -> GDR-OC01 | C7: =IFERROR(_xlfn.XLOOKUP($A7,Cert_App_Output!$C:$C,Cert_App_Output!$D:$D),"") -> 45808 | D7: =SUMIFS(Cert_App_Output!$J:$J,Cert_App_Output!$C:$C,$A7) -> 64830796 | E7: 0.4 | F7: =$D7*$E7 -> 25932318 | G7: =$D7-$F7 -> 38898478 | H7: =IF(COUNTIF(Cert_Calculo!$A:$A,$A7)>0,"OK","FALTA en Calculo") -> OK
A8: GDR-OC01-C04 | B8: =LEFT($A8,FIND("|",SUBSTITUTE($A8,"-","|",2))-1) -> GDR-OC01 | C8: =IFERROR(_xlfn.XLOOKUP($A8,Cert_App_Output!$C:$C,Cert_App_Output!$D:$D),"") -> 45838 | D8: =SUMIFS(Cert_App_Output!$J:$J,Cert_App_Output!$C:$C,$A8) -> 36057302 | E8: 0.4 | F8: =$D8*$E8 -> 14422921 | G8: =$D8-$F8 -> 21634381 | H8: =IF(COUNTIF(Cert_Calculo!$A:$A,$A8)>0,"OK","FALTA en Calculo") -> OK
A9: GDR-OC01-C05 | B9: =LEFT($A9,FIND("|",SUBSTITUTE($A9,"-","|",2))-1) -> GDR-OC01 | C9: =IFERROR(_xlfn.XLOOKUP($A9,Cert_App_Output!$C:$C,Cert_App_Output!$D:$D),"") -> 45869 | D9: =SUMIFS(Cert_App_Output!$J:$J,Cert_App_Output!$C:$C,$A9) -> 93958182 | E9: 0.4 | F9: =$D9*$E9 -> 37583273 | G9: =$D9-$F9 -> 56374909 | H9: =IF(COUNTIF(Cert_Calculo!$A:$A,$A9)>0,"OK","FALTA en Calculo") -> OK
A10: GDR-OC01-C06 | B10: =LEFT($A10,FIND("|",SUBSTITUTE($A10,"-","|",2))-1) -> GDR-OC01 | C10: =IFERROR(_xlfn.XLOOKUP($A10,Cert_App_Output!$C:$C,Cert_App_Output!$D:$D),"") -> 45900 | D10: =SUMIFS(Cert_App_Output!$J:$J,Cert_App_Output!$C:$C,$A10) -> 55865246 | E10: 0.4 | F10: =$D10*$E10 -> 22346098 | G10: =$D10-$F10 -> 33519148 | H10: =IF(COUNTIF(Cert_Calculo!$A:$A,$A10)>0,"OK","FALTA en Calculo") -> OK
A11: GDR-OC01-C07 | B11: =LEFT($A11,FIND("|",SUBSTITUTE($A11,"-","|",2))-1) -> GDR-OC01 | C11: =IFERROR(_xlfn.XLOOKUP($A11,Cert_App_Output!$C:$C,Cert_App_Output!$D:$D),"") -> 45930 | D11: =SUMIFS(Cert_App_Output!$J:$J,Cert_App_Output!$C:$C,$A11) -> 33864200 | E11: 0.4 | F11: =$D11*$E11 -> 13545680 | G11: =$D11-$F11 -> 20318520 | H11: =IF(COUNTIF(Cert_Calculo!$A:$A,$A11)>0,"OK","FALTA en Calculo") -> OK
A12: GDR-OC01-C08 | B12: =LEFT($A12,FIND("|",SUBSTITUTE($A12,"-","|",2))-1) -> GDR-OC01 | C12: =IFERROR(_xlfn.XLOOKUP($A12,Cert_App_Output!$C:$C,Cert_App_Output!$D:$D),"") -> 45958 | D12: =SUMIFS(Cert_App_Output!$J:$J,Cert_App_Output!$C:$C,$A12) -> 25319767 | E12: 0.4 | F12: =$D12*$E12 -> 10127907 | G12: =$D12-$F12 -> 15191860 | H12: =IF(COUNTIF(Cert_Calculo!$A:$A,$A12)>0,"OK","FALTA en Calculo") -> OK
A13: GDR-OC01-C09 | B13: =LEFT($A13,FIND("|",SUBSTITUTE($A13,"-","|",2))-1) -> GDR-OC01 | C13: =IFERROR(_xlfn.XLOOKUP($A13,Cert_App_Output!$C:$C,Cert_App_Output!$D:$D),"") -> 45988 | D13: =SUMIFS(Cert_App_Output!$J:$J,Cert_App_Output!$C:$C,$A13) -> 1.3089582e+08 | E13: 0.4 | F13: =$D13*$E13 -> 52358330 | G13: =$D13-$F13 -> 78537494 | H13: =IF(COUNTIF(Cert_Calculo!$A:$A,$A13)>0,"OK","FALTA en Calculo") -> OK
... A31: GDR-OC03-C03 | B31: =LEFT($A31,FIND("|",SUBSTITUTE($A31,"-","|",2))-1) -> GDR-OC03 | C31: =IFERROR(_xlfn.XLOOKUP($A31,Cert_App_Output!$C:$C,Cert_App_Output!$D:$D),"") -> 45958 | D31: =SUMIFS(Cert_App_Output!$J:$J,Cert_App_Output!$C:$C,$A31) -> 35176921 | E31: 0 | F31: =$D31*$E31 -> 0 | G31: =$D31-$F31 -> 35176921 | H31: =IF(COUNTIF(Cert_Calculo!$A:$A,$A31)>0,"OK","FALTA en Calculo") -> OK

Sheet Cert_Calculo
A1: ID Certif | B1: ID Cert+Fact | C1: Tipo | D1: Obra | E1: ID OC | F1: Fecha | G1: $ base certif (total) | H1: % facturacion | I1: $ base de esta parte | J1: % desacopio | K1: $ desacopio | L1: $ base neta | M1: Indice base CAC | N1: Indice CAC a la fecha | O1: Ratio CAC | P1: $ CAC | Q1: $ base + CAC | R1: % IVA | S1: $ IVA | T1: $ Total certificacion | U1: USD MEP a la fecha | V1: U$ Total | X1: Control B/N suma 100% | Y1: Indice CAC override
A2: GDR-OC01-ANT | B2: GDR-OC01-ANT-B | C2: Blanco | D2: GDR 3760 | E2: GDR-OC01 | G2: 200363088 | H2: 0.7 | I2: =$G2*H2 -> 1.4025416e+08 | J2: =_xlfn.XLOOKUP($A2,Cert_Cabecera!$A:$A,Cert_Cabecera!$E:$E) -> 0 | K2: =-I2*J2 -> 0 | L2: =I2+K2 -> 1.4025416e+08 | M2: =_xlfn.XLOOKUP($E2,Cert_OC_Cliente!$B:$B,Cert_OC_Cliente!$G:$G) -> 15356.4 | N2: =IF($Y2="",'0_Indice_CAC'!$B$4,$Y2) -> 15356.4 | O2: =N2/M2 -> 1 | P2: =L2*(O2-1) -> 0 | Q2: =L2+P2 -> 1.4025416e+08 | R2: 0.21 | S2: =Q2*R2 -> 29453374 | T2: =Q2+S2 -> 1.6970754e+08 | U2: 1170 | V2: =IF(C2="Negro",T2/U2,"") | X2: =IF(ABS(SUMIFS($H:$H,$A:$A,$A2)-1)<0.0001,"✓","⚠ ≠100%") -> ✓
A3: GDR-OC01-ANT | B3: GDR-OC01-ANT-N | C3: Negro | D3: GDR 3760 | E3: GDR-OC01 | G3: 200363088 | H3: 0.3 | I3: =$G3*H3 -> 60108926 | J3: =_xlfn.XLOOKUP($A3,Cert_Cabecera!$A:$A,Cert_Cabecera!$E:$E) -> 0 | K3: =-I3*J3 -> 0 | L3: =I3+K3 -> 60108926 | M3: =_xlfn.XLOOKUP($E3,Cert_OC_Cliente!$B:$B,Cert_OC_Cliente!$G:$G) -> 15356.4 | N3: =IF($Y3="",'0_Indice_CAC'!$B$4,$Y3) -> 15356.4 | O3: =N3/M3 -> 1 | P3: =L3*(O3-1) -> 0 | Q3: =L3+P3 -> 60108926 | R3: 0 | S3: =Q3*R3 -> 0 | T3: =Q3+S3 -> 60108926 | U3: 1170 | V3: =IF(C3="Negro",T3/U3,"") -> 51375.151 | X3: =IF(ABS(SUMIFS($H:$H,$A:$A,$A3)-1)<0.0001,"✓","⚠ ≠100%") -> ✓
A4: GDR-OC02-ANT | B4: GDR-OC02-ANT-B | C4: Blanco | D4: GDR 3760 | E4: GDR-OC02 | G4: 84484525 | H4: 0.7 | I4: =$G4*H4 -> 59139167 | J4: =_xlfn.XLOOKUP($A4,Cert_Cabecera!$A:$A,Cert_Cabecera!$E:$E) -> 0 | K4: =-I4*J4 -> 0 | L4: =I4+K4 -> 59139167 | M4: =_xlfn.XLOOKUP($E4,Cert_OC_Cliente!$B:$B,Cert_OC_Cliente!$G:$G) -> 15356.4 | N4: =IF($Y4="",'0_Indice_CAC'!$B$4,$Y4) -> 15356.4 | O4: =N4/M4 -> 1 | P4: =L4*(O4-1) -> 0 | Q4: =L4+P4 -> 59139167 | R4: 0.21 | S4: =Q4*R4 -> 12419225 | T4: =Q4+S4 -> 71558393 | U4: 1170 | V4: =IF(C4="Negro",T4/U4,"") | X4: =IF(ABS(SUMIFS($H:$H,$A:$A,$A4)-1)<0.0001,"✓","⚠ ≠100%") -> ✓
A5: GDR-OC02-ANT | B5: GDR-OC02-ANT-N | C5: Negro | D5: GDR 3760 | E5: GDR-OC02 | G5: 84484525 | H5: 0.3 | I5: =$G5*H5 -> 25345357 | J5: =_xlfn.XLOOKUP($A5,Cert_Cabecera!$A:$A,Cert_Cabecera!$E:$E) -> 0 | K5: =-I5*J5 -> 0 | L5: =I5+K5 -> 25345357 | M5: =_xlfn.XLOOKUP($E5,Cert_OC_Cliente!$B:$B,Cert_OC_Cliente!$G:$G) -> 15356.4 | N5: =IF($Y5="",'0_Indice_CAC'!$B$4,$Y5) -> 15356.4 | O5: =N5/M5 -> 1 | P5: =L5*(O5-1) -> 0 | Q5: =L5+P5 -> 25345357 | R5: 0 | S5: =Q5*R5 -> 0 | T5: =Q5+S5 -> 25345357 | U5: 1170 | V5: =IF(C5="Negro",T5/U5,"") -> 21662.699 | X5: =IF(ABS(SUMIFS($H:$H,$A:$A,$A5)-1)<0.0001,"✓","⚠ ≠100%") -> ✓
A6: GDR-OC03-ANT | B6: GDR-OC03-ANT-N | C6: Negro | D6: GDR 3760 | E6: GDR-OC03 | G6: 0 | H6: 1 | I6: =$G6*H6 -> 0 | J6: =_xlfn.XLOOKUP($A6,Cert_Cabecera!$A:$A,Cert_Cabecera!$E:$E) -> 0 | K6: =-I6*J6 -> 0 | L6: =I6+K6 -> 0 | M6: =_xlfn.XLOOKUP($E6,Cert_OC_Cliente!$B:$B,Cert_OC_Cliente!$G:$G) -> 15356.4 | N6: =IF($Y6="",'0_Indice_CAC'!$B$4,$Y6) -> 15356.4 | O6: =N6/M6 -> 1 | P6: =L6*(O6-1) -> 0 | Q6: =L6+P6 -> 0 | R6: 0 | S6: =Q6*R6 -> 0 | T6: =Q6+S6 -> 0 | U6: 1170 | V6: =IF(C6="Negro",T6/U6,"") -> 0 | X6: =IF(ABS(SUMIFS($H:$H,$A:$A,$A6)-1)<0.0001,"✓","⚠ ≠100%") -> ✓
A7: GDR-OC01-C01 | B7: GDR-OC01-C01-B | C7: Blanco | D7: =_xlfn.XLOOKUP(A7,Cert_App_Output!$C:$C,Cert_App_Output!$A:$A) -> GDR 3760 | E7: GDR-OC01 | F7: =_xlfn.XLOOKUP(A7,Cert_App_Output!$C:$C,Cert_App_Output!$D:$D) -> 45747 | G7: =SUMIFS(Cert_App_Output!$J:$J,Cert_App_Output!$C:$C,$A7) -> 32672750 | H7: 0.7 | I7: =$G7*H7 -> 22870925 | J7: =_xlfn.XLOOKUP($A7,Cert_Cabecera!$A:$A,Cert_Cabecera!$E:$E) -> 0.4 | K7: =-I7*J7 -> -9148370.1 | L7: =I7+K7 -> 13722555 | M7: =_xlfn.XLOOKUP($E7,Cert_OC_Cliente!$B:$B,Cert_OC_Cliente!$G:$G) -> 15356.4 | N7: =IF($Y7="",_xlfn.XLOOKUP(DATE(YEAR(F7),MONTH(F7),1),'0_Indice_CAC'!$A:$A,'0_Indice_CAC'!$B:$B),$Y7) -> 15995.4 | O7: =N7/M7 -> 1.0416113 | P7: =L7*(O7-1) -> 571013.57 | Q7: =L7+P7 -> 14293569 | R7: 0.21 | S7: =Q7*R7 -> 3001649.4 | T7: =Q7+S7 -> 17295218 | U7: 1170 | V7: =IF(C7="Negro",T7/U7,"") | X7: =IF(ABS(SUMIFS($H:$H,$A:$A,$A7)-1)<0.0001,"✓","⚠ ≠100%") -> ✓
A8: GDR-OC01-C01 | B8: GDR-OC01-C01-N | C8: Negro | D8: =_xlfn.XLOOKUP(A8,Cert_App_Output!$C:$C,Cert_App_Output!$A:$A) -> GDR 3760 | E8: GDR-OC01 | F8: =_xlfn.XLOOKUP(A8,Cert_App_Output!$C:$C,Cert_App_Output!$D:$D) -> 45747 | G8: =SUMIFS(Cert_App_Output!$J:$J,Cert_App_Output!$C:$C,$A8) -> 32672750 | H8: 0.3 | I8: =$G8*H8 -> 9801825.1 | J8: =_xlfn.XLOOKUP($A8,Cert_Cabecera!$A:$A,Cert_Cabecera!$E:$E) -> 0.4 | K8: =-I8*J8 -> -3920730 | L8: =I8+K8 -> 5881095.1 | M8: =_xlfn.XLOOKUP($E8,Cert_OC_Cliente!$B:$B,Cert_OC_Cliente!$G:$G) -> 15356.4 | N8: =IF($Y8="",_xlfn.XLOOKUP(DATE(YEAR(F8),MONTH(F8),1),'0_Indice_CAC'!$A:$A,'0_Indice_CAC'!$B:$B),$Y8) -> 15995.4 | O8: =N8/M8 -> 1.0416113 | P8: =L8*(O8-1) -> 244720.1 | Q8: =L8+P8 -> 6125815.2 | R8: 0 | S8: =Q8*R8 -> 0 | T8: =Q8+S8 -> 6125815.2 | U8: 1170 | V8: =IF(C8="Negro",T8/U8,"") -> 5235.7395 | X8: =IF(ABS(SUMIFS($H:$H,$A:$A,$A8)-1)<0.0001,"✓","⚠ ≠100%") -> ✓
A9: GDR-OC01-C02 | B9: GDR-OC01-C02-B | C9: Blanco | D9: =_xlfn.XLOOKUP(A9,Cert_App_Output!$C:$C,Cert_App_Output!$A:$A) -> GDR 3760 | E9: GDR-OC01 | F9: =_xlfn.XLOOKUP(A9,Cert_App_Output!$C:$C,Cert_App_Output!$D:$D) -> 45777 | G9: =SUMIFS(Cert_App_Output!$J:$J,Cert_App_Output!$C:$C,$A9) -> 27443238 | H9: 0.7 | I9: =$G9*H9 -> 19210266 | J9: =_xlfn.XLOOKUP($A9,Cert_Cabecera!$A:$A,Cert_Cabecera!$E:$E) -> 0.4 | K9: =-I9*J9 -> -7684106.5 | L9: =I9+K9 -> 11526160 | M9: =_xlfn.XLOOKUP($E9,Cert_OC_Cliente!$B:$B,Cert_OC_Cliente!$G:$G) -> 15356.4 | N9: =IF($Y9="",_xlfn.XLOOKUP(DATE(YEAR(F9),MONTH(F9),1),'0_Indice_CAC'!$A:$A,'0_Indice_CAC'!$B:$B),$Y9) -> 16253.5 | O9: =N9/M9 -> 1.0584186 | P9: =L9*(O9-1) -> 673342.58 | Q9: =L9+P9 -> 12199502 | R9: 0.21 | S9: =Q9*R9 -> 2561895.5 | T9: =Q9+S9 -> 14761398 | U9: 1170 | V9: =IF(C9="Negro",T9/U9,"") | X9: =IF(ABS(SUMIFS($H:$H,$A:$A,$A9)-1)<0.0001,"✓","⚠ ≠100%") -> ✓
A10: GDR-OC01-C02 | B10: GDR-OC01-C02-N | C10: Negro | D10: =_xlfn.XLOOKUP(A10,Cert_App_Output!$C:$C,Cert_App_Output!$A:$A) -> GDR 3760 | E10: GDR-OC01 | F10: =_xlfn.XLOOKUP(A10,Cert_App_Output!$C:$C,Cert_App_Output!$D:$D) -> 45777 | G10: =SUMIFS(Cert_App_Output!$J:$J,Cert_App_Output!$C:$C,$A10) -> 27443238 | H10: 0.3 | I10: =$G10*H10 -> 8232971.3 | J10: =_xlfn.XLOOKUP($A10,Cert_Cabecera!$A:$A,Cert_Cabecera!$E:$E) -> 0.4 | K10: =-I10*J10 -> -3293188.5 | L10: =I10+K10 -> 4939782.8 | M10: =_xlfn.XLOOKUP($E10,Cert_OC_Cliente!$B:$B,Cert_OC_Cliente!$G:$G) -> 15356.4 | N10: =IF($Y10="",_xlfn.XLOOKUP(DATE(YEAR(F10),MONTH(F10),1),'0_Indice_CAC'!$A:$A,'0_Indice_CAC'!$B:$B),$Y10) -> 16253.5 | O10: =N10/M10 -> 1.0584186 | P10: =L10*(O10-1) -> 288575.39 | Q10: =L10+P10 -> 5228358.2 | R10: 0 | S10: =Q10*R10 -> 0 | T10: =Q10+S10 -> 5228358.2 | U10: 1170 | V10: =IF(C10="Negro",T10/U10,"") -> 4468.6822 | X10: =IF(ABS(SUMIFS($H:$H,$A:$A,$A10)-1)<0.0001,"✓","⚠ ≠100%") -> ✓
A11: GDR-OC01-C03 | B11: GDR-OC01-C03-B | C11: Blanco | D11: =_xlfn.XLOOKUP(A11,Cert_App_Output!$C:$C,Cert_App_Output!$A:$A) -> GDR 3760 | E11: GDR-OC01 | F11: =_xlfn.XLOOKUP(A11,Cert_App_Output!$C:$C,Cert_App_Output!$D:$D) -> 45808 | G11: =SUMIFS(Cert_App_Output!$J:$J,Cert_App_Output!$C:$C,$A11) -> 64830796 | H11: 0.7 | I11: =$G11*H11 -> 45381557 | J11: =_xlfn.XLOOKUP($A11,Cert_Cabecera!$A:$A,Cert_Cabecera!$E:$E) -> 0.4 | K11: =-I11*J11 -> -18152623 | L11: =I11+K11 -> 27228934 | M11: =_xlfn.XLOOKUP($E11,Cert_OC_Cliente!$B:$B,Cert_OC_Cliente!$G:$G) -> 15356.4 | N11: =IF($Y11="",_xlfn.XLOOKUP(DATE(YEAR(F11),MONTH(F11),1),'0_Indice_CAC'!$A:$A,'0_Indice_CAC'!$B:$B),$Y11) -> 16521.3 | O11: =N11/M11 -> 1.0758576 | P11: =L11*(O11-1) -> 2065522.2 | Q11: =L11+P11 -> 29294457 | R11: 0.21 | S11: =Q11*R11 -> 6151835.9 | T11: =Q11+S11 -> 35446292 | U11: 1170 | V11: =IF(C11="Negro",T11/U11,"") | X11: =IF(ABS(SUMIFS($H:$H,$A:$A,$A11)-1)<0.0001,"✓","⚠ ≠100%") -> ✓
A12: GDR-OC01-C03 | B12: GDR-OC01-C03-N | C12: Negro | D12: =_xlfn.XLOOKUP(A12,Cert_App_Output!$C:$C,Cert_App_Output!$A:$A) -> GDR 3760 | E12: GDR-OC01 | F12: =_xlfn.XLOOKUP(A12,Cert_App_Output!$C:$C,Cert_App_Output!$D:$D) -> 45808 | G12: =SUMIFS(Cert_App_Output!$J:$J,Cert_App_Output!$C:$C,$A12) -> 64830796 | H12: 0.3 | I12: =$G12*H12 -> 19449239 | J12: =_xlfn.XLOOKUP($A12,Cert_Cabecera!$A:$A,Cert_Cabecera!$E:$E) -> 0.4 | K12: =-I12*J12 -> -7779695.5 | L12: =I12+K12 -> 11669543 | M12: =_xlfn.XLOOKUP($E12,Cert_OC_Cliente!$B:$B,Cert_OC_Cliente!$G:$G) -> 15356.4 | N12: =IF($Y12="",_xlfn.XLOOKUP(DATE(YEAR(F12),MONTH(F12),1),'0_Indice_CAC'!$A:$A,'0_Indice_CAC'!$B:$B),$Y12) -> 16521.3 | O12: =N12/M12 -> 1.0758576 | P12: =L12*(O12-1) -> 885223.81 | Q12: =L12+P12 -> 12554767 | R12: 0 | S12: =Q12*R12 -> 0 | T12: =Q12+S12 -> 12554767 | U12: 1170 | V12: =IF(C12="Negro",T12/U12,"") -> 10730.57 | X12: =IF(ABS(SUMIFS($H:$H,$A:$A,$A12)-1)<0.0001,"✓","⚠ ≠100%") -> ✓
A13: GDR-OC01-C04 | B13: GDR-OC01-C04-B | C13: Blanco | D13: =_xlfn.XLOOKUP(A13,Cert_App_Output!$C:$C,Cert_App_Output!$A:$A) -> GDR 3760 | E13: GDR-OC01 | F13: =_xlfn.XLOOKUP(A13,Cert_App_Output!$C:$C,Cert_App_Output!$D:$D) -> 45838 | G13: =SUMIFS(Cert_App_Output!$J:$J,Cert_App_Output!$C:$C,$A13) -> 36057302 | H13: 0.7 | I13: =$G13*H13 -> 25240111 | J13: =_xlfn.XLOOKUP($A13,Cert_Cabecera!$A:$A,Cert_Cabecera!$E:$E) -> 0.4 | K13: =-I13*J13 -> -10096044 | L13: =I13+K13 -> 15144067 | M13: =_xlfn.XLOOKUP($E13,Cert_OC_Cliente!$B:$B,Cert_OC_Cliente!$G:$G) -> 15356.4 | N13: =IF($Y13="",_xlfn.XLOOKUP(DATE(YEAR(F13),MONTH(F13),1),'0_Indice_CAC'!$A:$A,'0_Indice_CAC'!$B:$B),$Y13) -> 16643.4 | O13: =N13/M13 -> 1.0838087 | P13: =L13*(O13-1) -> 1269204.6 | Q13: =L13+P13 -> 16413271 | R13: 0.21 | S13: =Q13*R13 -> 3446787 | T13: =Q13+S13 -> 19860058 | U13: 1170 | V13: =IF(C13="Negro",T13/U13,"") | X13: =IF(ABS(SUMIFS($H:$H,$A:$A,$A13)-1)<0.0001,"✓","⚠ ≠100%") -> ✓
A14: GDR-OC01-C04 | B14: GDR-OC01-C04-N | C14: Negro | D14: =_xlfn.XLOOKUP(A14,Cert_App_Output!$C:$C,Cert_App_Output!$A:$A) -> GDR 3760 | E14: GDR-OC01 | F14: =_xlfn.XLOOKUP(A14,Cert_App_Output!$C:$C,Cert_App_Output!$D:$D) -> 45838 | G14: =SUMIFS(Cert_App_Output!$J:$J,Cert_App_Output!$C:$C,$A14) -> 36057302 | H14: 0.3 | I14: =$G14*H14 -> 10817190 | J14: =_xlfn.XLOOKUP($A14,Cert_Cabecera!$A:$A,Cert_Cabecera!$E:$E) -> 0.4 | K14: =-I14*J14 -> -4326876.2 | L14: =I14+K14 -> 6490314.3 | M14: =_xlfn.XLOOKUP($E14,Cert_OC_Cliente!$B:$B,Cert_OC_Cliente!$G:$G) -> 15356.4 | N14: =IF($Y14="",_xlfn.XLOOKUP(DATE(YEAR(F14),MONTH(F14),1),'0_Indice_CAC'!$A:$A,'0_Indice_CAC'!$B:$B),$Y14) -> 16643.4 | O14: =N14/M14 -> 1.0838087 | P14: =L14*(O14-1) -> 543944.84 | Q14: =L14+P14 -> 7034259.1 | R14: 0 | S14: =Q14*R14 -> 0 | T14: =Q14+S14 -> 7034259.1 | U14: 1170 | V14: =IF(C14="Negro",T14/U14,"") -> 6012.1873 | X14: =IF(ABS(SUMIFS($H:$H,$A:$A,$A14)-1)<0.0001,"✓","⚠ ≠100%") -> ✓
A15: GDR-OC01-C05 | B15: GDR-OC01-C05-B | C15: Blanco | D15: =_xlfn.XLOOKUP(A15,Cert_App_Output!$C:$C,Cert_App_Output!$A:$A) -> GDR 3760 | E15: GDR-OC01 | F15: =_xlfn.XLOOKUP(A15,Cert_App_Output!$C:$C,Cert_App_Output!$D:$D) -> 45869 | G15: =SUMIFS(Cert_App_Output!$J:$J,Cert_App_Output!$C:$C,$A15) -> 93958182 | H15: 0.7 | I15: =$G15*H15 -> 65770728 | J15: =_xlfn.XLOOKUP($A15,Cert_Cabecera!$A:$A,Cert_Cabecera!$E:$E) -> 0.4 | K15: =-I15*J15 -> -26308291 | L15: =I15+K15 -> 39462437 | M15: =_xlfn.XLOOKUP($E15,Cert_OC_Cliente!$B:$B,Cert_OC_Cliente!$G:$G) -> 15356.4 | N15: =IF($Y15="",_xlfn.XLOOKUP(DATE(YEAR(F15),MONTH(F15),1),'0_Indice_CAC'!$A:$A,'0_Indice_CAC'!$B:$B),$Y15) -> 16939.5 | O15: =N15/M15 -> 1.1030906 | P15: =L15*(O15-1) -> 4068205 | Q15: =L15+P15 -> 43530642 | R15: 0.21 | S15: =Q15*R15 -> 9141434.7 | T15: =Q15+S15 -> 52672076 | U15: 1170 | V15: =IF(C15="Negro",T15/U15,"") | X15: =IF(ABS(SUMIFS($H:$H,$A:$A,$A15)-1)<0.0001,"✓","⚠ ≠100%") -> ✓
A16: GDR-OC01-C05 | B16: GDR-OC01-C05-N | C16: Negro | D16: =_xlfn.XLOOKUP(A16,Cert_App_Output!$C:$C,Cert_App_Output!$A:$A) -> GDR 3760 | E16: GDR-OC01 | F16: =_xlfn.XLOOKUP(A16,Cert_App_Output!$C:$C,Cert_App_Output!$D:$D) -> 45869 | G16: =SUMIFS(Cert_App_Output!$J:$J,Cert_App_Output!$C:$C,$A16) -> 93958182 | H16: 0.3 | I16: =$G16*H16 -> 28187455 | J16: =_xlfn.XLOOKUP($A16,Cert_Cabecera!$A:$A,Cert_Cabecera!$E:$E) -> 0.4 | K16: =-I16*J16 -> -11274982 | L16: =I16+K16 -> 16912473 | M16: =_xlfn.XLOOKUP($E16,Cert_OC_Cliente!$B:$B,Cert_OC_Cliente!$G:$G) -> 15356.4 | N16: =IF($Y16="",_xlfn.XLOOKUP(DATE(YEAR(F16),MONTH(F16),1),'0_Indice_CAC'!$A:$A,'0_Indice_CAC'!$B:$B),$Y16) -> 16939.5 | O16: =N16/M16 -> 1.1030906 | P16: =L16*(O16-1) -> 1743516.4 | Q16: =L16+P16 -> 18655989 | R16: 0 | S16: =Q16*R16 -> 0 | T16: =Q16+S16 -> 18655989 | U16: 1170 | V16: =IF(C16="Negro",T16/U16,"") -> 15945.29 | X16: =IF(ABS(SUMIFS($H:$H,$A:$A,$A16)-1)<0.0001,"✓","⚠ ≠100%") -> ✓
A17: GDR-OC01-C06 | B17: GDR-OC01-C06-B | C17: Blanco | D17: =_xlfn.XLOOKUP(A17,Cert_App_Output!$C:$C,Cert_App_Output!$A:$A) -> GDR 3760 | E17: GDR-OC01 | F17: =_xlfn.XLOOKUP(A17,Cert_App_Output!$C:$C,Cert_App_Output!$D:$D) -> 45900 | G17: =SUMIFS(Cert_App_Output!$J:$J,Cert_App_Output!$C:$C,$A17) -> 55865246 | H17: 0.7 | I17: =$G17*H17 -> 39105672 | J17: =_xlfn.XLOOKUP($A17,Cert_Cabecera!$A:$A,Cert_Cabecera!$E:$E) -> 0.4 | K17: =-I17*J17 -> -15642269 | L17: =I17+K17 -> 23463403 | M17: =_xlfn.XLOOKUP($E17,Cert_OC_Cliente!$B:$B,Cert_OC_Cliente!$G:$G) -> 15356.4 | N17: =IF($Y17="",_xlfn.XLOOKUP(DATE(YEAR(F17),MONTH(F17),1),'0_Indice_CAC'!$A:$A,'0_Indice_CAC'!$B:$B),$Y17) -> 17187.6 | O17: =N17/M17 -> 1.1192467 | P17: =L17*(O17-1) -> 2797933.4 | Q17: =L17+P17 -> 26261337 | R17: 0.21 | S17: =Q17*R17 -> 5514880.7 | T17: =Q17+S17 -> 31776217 | U17: 1170 | V17: =IF(C17="Negro",T17/U17,"") | X17: =IF(ABS(SUMIFS($H:$H,$A:$A,$A17)-1)<0.0001,"✓","⚠ ≠100%") -> ✓
A18: GDR-OC01-C06 | B18: GDR-OC01-C06-N | C18: Negro | D18: =_xlfn.XLOOKUP(A18,Cert_App_Output!$C:$C,Cert_App_Output!$A:$A) -> GDR 3760 | E18: GDR-OC01 | F18: =_xlfn.XLOOKUP(A18,Cert_App_Output!$C:$C,Cert_App_Output!$D:$D) -> 45900 | G18: =SUMIFS(Cert_App_Output!$J:$J,Cert_App_Output!$C:$C,$A18) -> 55865246 | H18: 0.3 | I18: =$G18*H18 -> 16759574 | J18: =_xlfn.XLOOKUP($A18,Cert_Cabecera!$A:$A,Cert_Cabecera!$E:$E) -> 0.4 | K18: =-I18*J18 -> -6703829.5 | L18: =I18+K18 -> 10055744 | M18: =_xlfn.XLOOKUP($E18,Cert_OC_Cliente!$B:$B,Cert_OC_Cliente!$G:$G) -> 15356.4 | N18: =IF($Y18="",_xlfn.XLOOKUP(DATE(YEAR(F18),MONTH(F18),1),'0_Indice_CAC'!$A:$A,'0_Indice_CAC'!$B:$B),$Y18) -> 17187.6 | O18: =N18/M18 -> 1.1192467 | P18: =L18*(O18-1) -> 1199114.3 | Q18: =L18+P18 -> 11254859 | R18: 0 | S18: =Q18*R18 -> 0 | T18: =Q18+S18 -> 11254859 | U18: 1170 | V18: =IF(C18="Negro",T18/U18,"") -> 9619.5372 | X18: =IF(ABS(SUMIFS($H:$H,$A:$A,$A18)-1)<0.0001,"✓","⚠ ≠100%") -> ✓
... A57: GDR-OC03-C03 | B57: GDR-OC03-C03-N | C57: Negro | D57: =_xlfn.XLOOKUP(A57,Cert_App_Output!$C:$C,Cert_App_Output!$A:$A) -> GDR 3760 | E57: GDR-OC03 | F57: =_xlfn.XLOOKUP(A57,Cert_App_Output!$C:$C,Cert_App_Output!$D:$D) -> 45958 | G57: =SUMIFS(Cert_App_Output!$J:$J,Cert_App_Output!$C:$C,$A57) -> 35176921 | H57: 1 | I57: =$G57*H57 -> 35176921 | J57: =_xlfn.XLOOKUP($A57,Cert_Cabecera!$A:$A,Cert_Cabecera!$E:$E) -> 0 | K57: =-I57*J57 -> 0 | L57: =I57+K57 -> 35176921 | M57: =_xlfn.XLOOKUP($E57,Cert_OC_Cliente!$B:$B,Cert_OC_Cliente!$G:$G) -> 15356.4 | N57: =IF($Y57="",_xlfn.XLOOKUP(DATE(YEAR(F57),MONTH(F57),1),'0_Indice_CAC'!$A:$A,'0_Indice_CAC'!$B:$B),$Y57) -> 18172.8 | O57: =N57/M57 -> 1.1834024 | P57: =L57*(O57-1) -> 6451530.3 | Q57: =L57+P57 -> 41628451 | R57: 0 | S57: =Q57*R57 -> 0 | T57: =Q57+S57 -> 41628451 | U57: 1170 | V57: =IF(C57="Negro",T57/U57,"") -> 35579.873 | X57: =IF(ABS(SUMIFS($H:$H,$A:$A,$A57)-1)<0.0001,"✓","⚠ ≠100%") -> ✓

Sheet Cert_Facturacion
A1: id_cert_fact | B1: Comprobante | C1: Tipo | D1: monto | E1: moneda | F1: Fecha cobro | G1: monto_ars_equiv | H1: Estado conciliado | I1: $ certificado (control) | J1: Saldo a facturar | K1: id_factura | L1: TC cobro | M1: id_cert_madre | N1: id_OC | O1: Clase | P1: Retención | Q1: Haber conciliado

Sheet Cert_Control_OC
A1: ID OC | B1: Presupuesto | C1: Descripcion | D1: $ Contrato | E1: % Avance fisico | F1: $ Certificado | G1: $ Facturado | H1: $ Cobrado | I1: $ Anticipo certif. | J1: $ Avance s/certificar | K1: Saldo a facturar | L1: Saldo a cobrar | M1: Estado
A2: =Cert_OC_Cliente!B2 -> GDR-OC01 | B2: =_xlfn.XLOOKUP($A2,Cert_OC_Cliente!$B:$B,Cert_OC_Cliente!$L:$L) -> PTO 01 | C2: =_xlfn.XLOOKUP($A2,Cert_OC_Cliente!$B:$B,Cert_OC_Cliente!$C:$C) -> Pto 1 - Preliminar y Hormigón | D2: =_xlfn.XLOOKUP($A2,Cert_OC_Cliente!$B:$B,Cert_OC_Cliente!$D:$D) -> 500907720 | E2: =IFERROR(SUMPRODUCT(('1_Presupuesto'!$X$5:$X$227=$B2)*'1_Presupuesto'!$Y$5:$Y$227*'1_Presupuesto'!$V$5:$V$227)/SUMPRODUCT(('1_Presupuesto'!$X$5:$X$227=$B2)*'1_Presupuesto'!$V$5:$V$227),0) -> 1 | F2: =SUMIFS(Cert_Calculo!$T:$T,Cert_Calculo!$E:$E,$A2) -> 6.1878721e+08 | G2: =SUMIFS(Cert_Facturacion!$G:$G,Cert_Facturacion!$A:$A,$A2&"-*") -> 0 | H2: =SUMIFS(Cert_Facturacion!$G:$G,Cert_Facturacion!$A:$A,$A2&"-*",Cert_Facturacion!$F:$F,">0") -> 0 | I2: =SUMIFS(Cert_Calculo!$T:$T,Cert_Calculo!$E:$E,$A2,Cert_Calculo!$B:$B,"*ANT*") -> 2.2981646e+08 | J2: =SUMIFS(Cert_App_Output!$J:$J,Cert_App_Output!$B:$B,$A2)-SUMIFS(Cert_Calculo!$I:$I,Cert_Calculo!$E:$E,$A2,Cert_Calculo!$B:$B,"<>*ANT*") -> 0 | K2: =F2-G2 -> 6.1878721e+08 | L2: =G2-H2 -> 0 | M2: =IF(J2>1000,"⚠ Certificar",IF(F2=0,"🔴 Sin iniciar",IF(K2>1000,"🟠 Por facturar",IF(L2>1000,"🔵 Por cobrar",IF(E2>=0.999,"🟢 Cerrada","🟡 En ejecucion"))))) -> 🟠 Por facturar
