Workbook
Name GASTOS_CONCEPTO: _Listas!$I$2:$I$17
Name RUBROS_PLAN: _Listas!$A$2:$A$34

Sheet 0_CONFIG
A1: ▌ CONFIGURACIÓN DE OBRA — SVD 4140
A3: Nombre de obra | B3: Edificio El Salvador 4140
A4: Estado | B4: En ejecución
A5: Fecha inicio | B5: 45658 | C5: presupuesto base sep-2024
A6: Duración estimada (meses) | B6: 18 | C6: feb-2025 a ago-2026
A7: — ÍNDICE CAC —
A8: Mes base CAC | B8: 45536 | C8: fecha base del presupuesto (sep-2024)
A9: Valor CAC base (INDEC) | B9: 14366.9 | C9: índice INDEC del mes base
A10: Mes corriente | B10: =INDEX('0_Indice_CAC'!$A$4:$A$33,MATCH(1E+300,'0_Indice_CAC'!$B$4:$B$33)) -> 46174 | C10: último mes cargado
A11: Ratio CAC corriente | B11: =MIN('0_Indice_CAC'!$D$4:$D$33) -> 0.70180534 | C11: ratio del mes más reciente
A12: — COEFICIENTE K —
A13: K (Gastos Generales y Beneficio) | B13: ='1_GGBB'!F66 -> 1.2568826 | C13: CRÍTICO: no modificar manualmente
A14: — PRESUPUESTO —
A15: Apertura fiscal | B15: B31 / N69 / GGN | C15: Blanco 31% c/IVA · Negro 69% — DERIVADO de Facturación, revisar
A16: Costo controlable (sin EQ) | B16: =SUMPRODUCT(('1_Presupuesto'!$J$5:$J$219+'1_Presupuesto'!$K$5:$K$219+'1_Presupuesto'!$L$5:$L$219)*'1_Presupuesto'!$I$5:$I$219) -> 8.7650815e+08 | C16: MT+MO/OTR+MO/ALB × Cant (EQ excluido)
A17: Costo total (con EQ) | B17: =SUMPRODUCT('1_Presupuesto'!$N$5:$N$219*'1_Presupuesto'!$I$5:$I$219) -> 8.9704289e+08 | C17: Costo Unit. × Cant
A18: Precio de venta total | B18: =SUMPRODUCT('1_Presupuesto'!$S$5:$S$219*'1_Presupuesto'!$I$5:$I$219) -> 1.1581632e+09 | C18: P Unit. × Cant
A19: Sanity check venta (debe ser 0) | B19: =+B18-1158163185 -> 0.019499779 | C19: venta total = subtotales legacy Pto.Vta (markup no uniforme; K solo informativo)
A44: — RECONCILIACIÓN MENSUAL —
A45: Total egresos (2_Movimientos) | B45: =SUMPRODUCT('2_Movimientos'!$I$2:$I$999,N(LEFT(TEXT('2_Movimientos'!$A$2:$A$999,"0"),1)<>"4"))-SUMPRODUCT('2_Movimientos'!$J$2:$J$999,N(LEFT(TEXT('2_Movimientos'!$A$2:$A$999,"0"),1)<>"4")) -> 2.809937e+08 | C45: ← se cablea en bloque 6 (crear 2_Movimientos)
A46: Total Tezamat (pegar mensual) | C46: input mensual
A47: Diferencia (debe ser 0) | B47: =B45-B46 -> 2.809937e+08 | C47: se activa al cablear B45
A49: Tolerancia conciliación ($) | B49: 100
A52: — PENDIENTES (celdas amarillas) —
A53: 0_Indice_CAC col B | B53: CAC meses futuros sin publicar
A54: 0_Jornales_MO | B54: Tarifas UOCRA meses futuros
A55: 0_CONFIG!B46 | B55: Input mensual total Tezamat
A56: 1_Presupuesto cols A,B,C,D | B56: Asignación de rubros por ítem (4 cols input manual)

Sheet 0_Indice_CAC
A1: INDICE CAC
A3: Escala de tiempo | B3: Valores | C3: Previsión | D3: Indice
A4: 45536 | B4: 14366.9 | D4: =$B$4/B4 -> 1
A5: 45566 | B5: 14614.9 | D5: =$B$4/B5 -> 0.98303102
A6: 45597 | B6: 15043 | D6: =$B$4/B6 -> 0.95505551
A7: 45627 | B7: 15356.4 | D7: =$B$4/B7 -> 0.93556432
A8: 45658 | B8: 15592.5 | D8: =$B$4/B8 -> 0.92139811
A9: 45689 | B9: 15852.4 | D9: =$B$4/B9 -> 0.90629179
A10: 45717 | B10: 15995.4 | D10: =$B$4/B10 -> 0.89818948
A11: 45748 | B11: 16253.5 | D11: =$B$4/B11 -> 0.88392654
A12: 45778 | B12: 16521.3 | D12: =$B$4/B12 -> 0.86959864
A13: 45809 | B13: 16643.4 | D13: =$B$4/B13 -> 0.86321905
A14: 45839 | B14: 16939.5 | D14: =$B$4/B14 -> 0.84813011
A15: 45870 | B15: 17187.6 | D15: =$B$4/B15 -> 0.8358875
... A21: 46054 | B21: 19453 | D21: =$B$4/B21 -> 0.73854418
A22: 46082 | B22: 19806.241 | C22: 19806.241 | D22: =$B$4/B22 -> 0.72537239
A23: 46113 | B23: 20138.793 | C23: 20138.793 | D23: =$B$4/B23 -> 0.71339428
A24: 46143 | B24: 20471.346 | C24: 20471.346 | D24: =$B$4/B24 -> 0.70180534
A25: 46174 | B25: 20471.346 | C25: 20471.346 | D25: =$B$4/B25 -> 0.70180534

Sheet 0_Jornales_MO
A1: SECCIÓN A — TABLA DE TARIFAS POR CATEGORÍA (Costo por Día/Quincena)
A3: PERÍODO | B3: ESPEC. ($/día) | C3: OFICIAL ($/día) | D3: 1/2 OFICIAL ($/día) | E3: AYUDANTE ($/día) | G3: ESPEC. ($/hr) | H3: OFICIAL ($/día) | I3: 1/2 OFICIAL ($/día) | J3: AYUDANTE ($/día)
A4: 45627 | B4: 85927.1 | C4: 76955.08 | D4: 65493.07 | E4: 60860.58 | G4: =+B4/8 -> 10740.888 | H4: =+C4/8 -> 9619.385 | I4: =+D4/8 -> 8186.6337 | J4: =+E4/8 -> 7607.5725
A5: 45658 | B5: 87384 | C5: 78375 | D5: 66853 | E5: 61892 | G5: =+B5/8 -> 10923 | H5: =+C5/8 -> 9796.875 | I5: =+D5/8 -> 8356.625 | J5: =+E5/8 -> 7736.5
A6: 45689 | B6: 89383 | C6: 80395 | D6: 68472 | E6: 63382 | G6: =+B6/8 -> 11172.875 | H6: =+C6/8 -> 10049.375 | I6: =+D6/8 -> 8559 | J6: =+E6/8 -> 7922.75
A7: 45717 | B7: 91464 | C7: 82269 | D7: 70296 | E7: 65595 | G7: =+B7/8 -> 11433 | H7: =+C7/8 -> 10283.625 | I7: =+D7/8 -> 8787 | J7: =+E7/8 -> 8199.375
A8: 45778 | B8: 93235.367 | C8: 83766.388 | D8: 71410.817 | E8: 66568.094 | G8: =+B8/8 -> 11654.421 | H8: =+C8/8 -> 10470.798 | I8: =+D8/8 -> 8926.3521 | J8: =+E8/8 -> 8321.0117
A9: 45809 | B9: 94177.138 | C9: 84612.513 | D9: 72132.138 | E9: 67240.499 | G9: =+B9/8 -> 11772.142 | H9: =+C9/8 -> 10576.564 | I9: =+D9/8 -> 9016.5173 | J9: =+E9/8 -> 8405.0624
A10: 45839 | B10: 95080 | C10: 85425 | D10: 72871 | E10: 67908 | G10: =+B10/8 -> 11885 | H10: =+C10/8 -> 10678.125 | I10: =+D10/8 -> 9108.875 | J10: =+E10/8 -> 8488.5
A11: 45870 | B11: 95889.2 | C11: 86356.18 | D11: 73781.11 | E11: 68935.35 | G11: =+B11/8 -> 11986.15 | H11: =+C11/8 -> 10794.522 | I11: =+D11/8 -> 9222.6388 | J11: =+E11/8 -> 8616.9188
A12: 45901 | B12: 106516.02 | C12: 88649.808 | D12: 75758.192 | E12: 71041.119 | G12: =+B12/8 -> 13314.502 | H12: =+C12/8 -> 11081.226 | I12: =+D12/8 -> 9469.774 | J12: =+E12/8 -> 8880.1398
A13: 45931 | B13: 106864.21 | C13: 88971.073 | D13: 76032.176 | E13: 71292.271 | G13: =+B13/8 -> 13358.026 | H13: =+C13/8 -> 11121.384 | I13: =+D13/8 -> 9504.0221 | J13: =+E13/8 -> 8911.5339
A14: 45962 | B14: 109621.11 | C14: 91252.851 | D14: 77612.118 | E14: 72486.683 | G14: =+B14/8 -> 13702.638 | H14: =+C14/8 -> 11406.606 | I14: =+D14/8 -> 9701.5148 | J14: =+E14/8 -> 9060.8353
A15: 45992 | B15: 113865.18 | C15: 95196.927 | D15: 81356.194 | E15: 76230.759 | G15: =+B15/8 -> 14233.148 | H15: =+C15/8 -> 11899.616 | I15: =+D15/8 -> 10169.524 | J15: =+E15/8 -> 9528.8449
... A21: 46174 | B21: 122445.79 | C21: 102029.07 | D21: 87100.47 | E21: 81453.719 | G21: =+B21/8 -> 15305.724 | H21: =+C21/8 -> 12753.633 | I21: =+D21/8 -> 10887.559 | J21: =+E21/8 -> 10181.715

Sheet 1_Presupuesto
A1: PRESUPUESTO OBRA CIVIL y CERTIFICACIONES DE AVANCE
A3: Rubro MT | B3: Rubro MT/Prov | C3: Rubro MO/OTR | D3: Rubro MO/ALB | E3: Cod. Ítem | F3: Estado | G3: Descripción | H3: U | I3: Cant | J3: MT | K3: MO/OTR | L3: MO/ALB | M3: EQ | N3: Costo Unit. | O3: MT | P3: MO/OTR | Q3: MO/ALB | R3: EQ | S3: P.Unit | T3: Margen | U3: Costo total | V3: PV subtotal | W3: Etapa | X3: Presupuesto | Y3: % Acum Tot
E4: 1 | G4: TAREAS PRELIMINARES
A5: Preliminares | B5: - | C5: - | D5: - | E5: 1.01 | F5: OK | G5: Limpieza y preparación del terreno - No cotiza | H5: gl | I5: 0 | J5: 0 | K5: 0 | L5: 0 | M5: 0 | N5: =SUM(J5:M5) -> 0 | O5: =IF($N5=0,$S5,J5/$N5*$S5) -> 0 | P5: =IF($N5=0,0,K5/$N5*$S5) -> 0 | Q5: =IF($N5=0,0,L5/$N5*$S5) -> 0 | R5: =IF($N5=0,0,M5/$N5*$S5) -> 0 | S5: 0 | T5: =IFERROR(S5/N5,"") | U5: =N5*I5 -> 0 | V5: =S5*I5 -> 0 | W5: TAREAS PRELIMINARES | X5: PTO 01 | Y5: =SUMIFS(Cert_App_Output!$G:$G,Cert_App_Output!$E:$E,$E5,Cert_App_Output!$K:$K,$X5) -> 0
A6: Preliminares | B6: - | C6: Preliminares | D6: Preliminares | E6: 1.02 | F6: OK | G6: Topógrafo - Visita de obra replanteo | H6: un | I6: 3 | J6: 41666.667 | K6: 172653.21 | L6: 83223.729 | M6: 4463.1541 | N6: =SUM(J6:M6) -> 302006.76 | O6: =IF($N6=0,$S6,J6/$N6*$S6) -> 52370.241 | P6: =IF($N6=0,0,K6/$N6*$S6) -> 217005.36 | Q6: =IF($N6=0,0,L6/$N6*$S6) -> 104602.72 | R6: =IF($N6=0,0,M6/$N6*$S6) -> 5609.6749 | S6: 379588 | T6: =IFERROR(S6/N6,"") -> 1.2568858 | U6: =N6*I6 -> 906020.27 | V6: =S6*I6 -> 1138764 | W6: TAREAS PRELIMINARES | X6: PTO 01 | Y6: =SUMIFS(Cert_App_Output!$G:$G,Cert_App_Output!$E:$E,$E6,Cert_App_Output!$K:$K,$X6) -> 1
A7: Preliminares | B7: - | C7: - | D7: - | E7: 1.03 | F7: OK | G7: Cartel de Obra - No cotiza | H7: gl | I7: 0 | J7: 0 | K7: 0 | L7: 0 | M7: 0 | N7: =SUM(J7:M7) -> 0 | O7: =IF($N7=0,$S7,J7/$N7*$S7) -> 0 | P7: =IF($N7=0,0,K7/$N7*$S7) -> 0 | Q7: =IF($N7=0,0,L7/$N7*$S7) -> 0 | R7: =IF($N7=0,0,M7/$N7*$S7) -> 0 | S7: 0 | T7: =IFERROR(S7/N7,"") | U7: =N7*I7 -> 0 | V7: =S7*I7 -> 0 | W7: TAREAS PRELIMINARES | X7: PTO 01 | Y7: =SUMIFS(Cert_App_Output!$G:$G,Cert_App_Output!$E:$E,$E7,Cert_App_Output!$K:$K,$X7) -> 0
A8: Preliminares | B8: - | C8: - | D8: Preliminares | E8: 1.04 | F8: OK | G8: Cerco de obra perimetral - En chapa C25 + Concertina + Porton corredizo | H8: ml | I8: 11 | J8: 79773.183 | K8: 0 | L8: 30923.374 | M8: 1660.4484 | N8: =SUM(J8:M8) -> 112357.01 | O8: =IF($N8=0,$S8,J8/$N8*$S8) -> 100265.83 | P8: =IF($N8=0,0,K8/$N8*$S8) -> 0 | Q8: =IF($N8=0,0,L8/$N8*$S8) -> 38867.171 | R8: =IF($N8=0,0,M8/$N8*$S8) -> 2086.9951 | S8: 141220 | T8: =IFERROR(S8/N8,"") -> 1.2568865 | U8: =N8*I8 -> 1235927.1 | V8: =S8*I8 -> 1553420 | W8: TAREAS PRELIMINARES | X8: PTO 01 | Y8: =SUMIFS(Cert_App_Output!$G:$G,Cert_App_Output!$E:$E,$E8,Cert_App_Output!$K:$K,$X8) -> 1
A9: Preliminares | B9: - | C9: Preliminares | D9: Preliminares | E9: 1.05 | F9: OK | G9: Obrador colgante, pañol y ducha | H9: gl | I9: 1 | J9: 2400856.7 | K9: 500000 | L9: 3016332.5 | M9: 88757.838 | N9: =SUM(J9:M9) -> 6005947 | O9: =IF($N9=0,$S9,J9/$N9*$S9) -> 3017595.3 | P9: =IF($N9=0,0,K9/$N9*$S9) -> 628441.36 | Q9: =IF($N9=0,0,L9/$N9*$S9) -> 3791176.2 | R9: =IF($N9=0,0,M9/$N9*$S9) -> 111558.19 | S9: 7548771 | T9: =IFERROR(S9/N9,"") -> 1.2568827 | U9: =N9*I9 -> 6005947 | V9: =S9*I9 -> 7548771 | W9: TAREAS PRELIMINARES | X9: PTO 01 | Y9: =SUMIFS(Cert_App_Output!$G:$G,Cert_App_Output!$E:$E,$E9,Cert_App_Output!$K:$K,$X9) -> 1
A10: - | B10: - | C10: Gastos Generales | D10: - | E10: 1.06 | F10: OK | G10: Alquiler de baños quimicos y duchas portatiles | H10: mes | I10: 3 | J10: 0 | K10: 311904.59 | L10: 0 | M10: 0 | N10: =SUM(J10:M10) -> 311904.59 | O10: =IF($N10=0,$S10,J10/$N10*$S10) -> 0 | P10: =IF($N10=0,0,K10/$N10*$S10) -> 392028 | Q10: =IF($N10=0,0,L10/$N10*$S10) -> 0 | R10: =IF($N10=0,0,M10/$N10*$S10) -> 0 | S10: 392028 | T10: =IFERROR(S10/N10,"") -> 1.2568844 | U10: =N10*I10 -> 935713.77 | V10: =S10*I10 -> 1176084 | W10: TAREAS PRELIMINARES | X10: PTO 01 | Y10: =SUMIFS(Cert_App_Output!$G:$G,Cert_App_Output!$E:$E,$E10,Cert_App_Output!$K:$K,$X10) -> 1
A11: Preliminares | B11: - | C11: - | D11: Preliminares | E11: 1.07 | F11: OK | G11: Conexión pilar y luz de obra + Tablero de obra | H11: gl | I11: 1 | J11: 845578.51 | K11: 0 | L11: 511535.56 | M11: 20356.711 | N11: =SUM(J11:M11) -> 1377470.8 | O11: =IF($N11=0,$S11,J11/$N11*$S11) -> 1062793.5 | P11: =IF($N11=0,0,K11/$N11*$S11) -> 0 | Q11: =IF($N11=0,0,L11/$N11*$S11) -> 642940.5 | R11: =IF($N11=0,0,M11/$N11*$S11) -> 25586.01 | S11: 1731320 | T11: =IFERROR(S11/N11,"") -> 1.2568833 | U11: =N11*I11 -> 1377470.8 | V11: =S11*I11 -> 1731320 | W11: TAREAS PRELIMINARES | X11: PTO 01 | Y11: =SUMIFS(Cert_App_Output!$G:$G,Cert_App_Output!$E:$E,$E11,Cert_App_Output!$K:$K,$X11) -> 1
A12: Preliminares | B12: - | C12: - | D12: Preliminares | E12: 1.08 | F12: OK | G12: Conexión agua de obra, tanque + bomba | H12: gl | I12: 1 | J12: 680400 | K12: 0 | L12: 421419.89 | M12: 16527.298 | N12: =SUM(J12:M12) -> 1118347.2 | O12: =IF($N12=0,$S12,J12/$N12*$S12) -> 855183.46 | P12: =IF($N12=0,0,K12/$N12*$S12) -> 0 | Q12: =IF($N12=0,0,L12/$N12*$S12) -> 529675.66 | R12: =IF($N12=0,0,M12/$N12*$S12) -> 20772.887 | S12: 1405632 | T12: =IFERROR(S12/N12,"") -> 1.2568834 | U12: =N12*I12 -> 1118347.2 | V12: =S12*I12 -> 1405632 | W12: TAREAS PRELIMINARES | X12: PTO 01 | Y12: =SUMIFS(Cert_App_Output!$G:$G,Cert_App_Output!$E:$E,$E12,Cert_App_Output!$K:$K,$X12) -> 1
A13: - | B13: - | C13: Gastos Generales | D13: - | E13: 1.09 | F13: OK | G13: Tramite luz de obra, certificado luz de obra (2) y medición PAT | H13: gl | I13: 1 | J13: 0 | K13: 339320.84 | L13: 0 | M13: 0 | N13: =SUM(J13:M13) -> 339320.84 | O13: =IF($N13=0,$S13,J13/$N13*$S13) -> 0 | P13: =IF($N13=0,0,K13/$N13*$S13) -> 426487 | Q13: =IF($N13=0,0,L13/$N13*$S13) -> 0 | R13: =IF($N13=0,0,M13/$N13*$S13) -> 0 | S13: 426487 | T13: =IFERROR(S13/N13,"") -> 1.2568842 | U13: =N13*I13 -> 339320.84 | V13: =S13*I13 -> 426487 | W13: TAREAS PRELIMINARES | X13: PTO 01 | Y13: =SUMIFS(Cert_App_Output!$G:$G,Cert_App_Output!$E:$E,$E13,Cert_App_Output!$K:$K,$X13) -> 1
A14: - | B14: - | C14: Movimiento de Suelos | D14: - | E14: 1.1 | F14: OK | G14: Sistema de depresión de napas | H14: gl | I14: 1 | J14: 0 | K14: 7800000 | L14: 0 | M14: 0 | N14: =SUM(J14:M14) -> 7800000 | O14: =IF($N14=0,$S14,J14/$N14*$S14) -> 0 | P14: =IF($N14=0,0,K14/$N14*$S14) -> 9803685 | Q14: =IF($N14=0,0,L14/$N14*$S14) -> 0 | R14: =IF($N14=0,0,M14/$N14*$S14) -> 0 | S14: 9803685 | T14: =IFERROR(S14/N14,"") -> 1.2568827 | U14: =N14*I14 -> 7800000 | V14: =S14*I14 -> 9803685 | W14: TAREAS PRELIMINARES | X14: PTO 01 | Y14: =SUMIFS(Cert_App_Output!$G:$G,Cert_App_Output!$E:$E,$E14,Cert_App_Output!$K:$K,$X14) -> 1
E15: 2 | G15: MOVIMIENTO DE TIERRA, COMPACTACION Y RELLENO
A16: - | B16: - | C16: Movimiento de Suelos | D16: Homigón MO | E16: 2.01 | F16: OK | G16: Excavación a maquina para submuración y subsuelo | H16: m3 | I16: 1266 | J16: 0 | K16: 18400 | L16: 7809.62 | M16: 117.1443 | N16: =SUM(J16:M16) -> 26326.764 | O16: =IF($N16=0,$S16,J16/$N16*$S16) -> 0 | P16: =IF($N16=0,0,K16/$N16*$S16) -> 23126.883 | Q16: =IF($N16=0,0,L16/$N16*$S16) -> 9815.8788 | R16: =IF($N16=0,0,M16/$N16*$S16) -> 147.23818 | S16: 33090 | T16: =IFERROR(S16/N16,"") -> 1.2568958 | U16: =N16*I16 -> 33329684 | V16: =S16*I16 -> 41891940 | W16: MOVIMIENTO DE TIERRA, COMPACTACION Y RELLENO | X16: PTO 01 | Y16: =SUMIFS(Cert_App_Output!$G:$G,Cert_App_Output!$E:$E,$E16,Cert_App_Output!$K:$K,$X16) -> 1
A17: Movimiento de Suelos | B17: - | C17: - | D17: - | E17: 2.02 | F17: OK | G17: Demolición y retiro de fundaciones existentes - No cotiza | H17: gl | I17: 0 | J17: 0 | K17: 0 | L17: 0 | M17: 0 | N17: =SUM(J17:M17) -> 0 | O17: =IF($N17=0,$S17,J17/$N17*$S17) -> 0 | P17: =IF($N17=0,0,K17/$N17*$S17) -> 0 | Q17: =IF($N17=0,0,L17/$N17*$S17) -> 0 | R17: =IF($N17=0,0,M17/$N17*$S17) -> 0 | S17: 0 | T17: =IFERROR(S17/N17,"") | U17: =N17*I17 -> 0 | V17: =S17*I17 -> 0 | W17: MOVIMIENTO DE TIERRA, COMPACTACION Y RELLENO | X17: PTO 01 | Y17: =SUMIFS(Cert_App_Output!$G:$G,Cert_App_Output!$E:$E,$E17,Cert_App_Output!$K:$K,$X17) -> 0
A18: - | B18: - | C18: - | D18: Homigón MO | E18: 2.03 | F18: OK | G18: Excavación manual para pozo de achique y bombeo | H18: m3 | I18: 2 | J18: 0 | K18: 0 | L18: 49934.237 | M18: 0 | N18: =SUM(J18:M18) -> 49934.237 | O18: =IF($N18=0,$S18,J18/$N18*$S18) -> 0 | P18: =IF($N18=0,0,K18/$N18*$S18) -> 0 | Q18: =IF($N18=0,0,L18/$N18*$S18) -> 62762 | R18: =IF($N18=0,0,M18/$N18*$S18) -> 0 | S18: 62762 | T18: =IFERROR(S18/N18,"") -> 1.2568931 | U18: =N18*I18 -> 99868.474 | V18: =S18*I18 -> 125524 | W18: MOVIMIENTO DE TIERRA, COMPACTACION Y RELLENO | X18: PTO 01 | Y18: =SUMIFS(Cert_App_Output!$G:$G,Cert_App_Output!$E:$E,$E18,Cert_App_Output!$K:$K,$X18) -> 1
E19: 3 | G19: ESTRUCTURA RESISTENTE - sin provision de hierro y hormigon (incluye corte y doblado en obra)
A20: Hormigón MT | B20: - | C20: - | D20: Homigón MO | E20: 3.01 | F20: OK | G20: Hormigón de limpieza - e: 10 cm | H20: m3 | I20: 35 | J20: 196572.86 | K20: 0 | L20: 49934.237 | M20: 3697.6064 | N20: =SUM(J20:M20) -> 250204.7 | O20: =IF($N20=0,$S20,J20/$N20*$S20) -> 247069.05 | P20: =IF($N20=0,0,K20/$N20*$S20) -> 0 | Q20: =IF($N20=0,0,L20/$N20*$S20) -> 62761.487 | R20: =IF($N20=0,0,M20/$N20*$S20) -> 4647.4581 | S20: 314478 | T20: =IFERROR(S20/N20,"") -> 1.2568829 | U20: =N20*I20 -> 8757164.5 | V20: =S20*I20 -> 11006730 | W20: ESTRUCTURA RESISTENTE - sin provision de hierro y hormigon (incluye corte y doblado en obra) | X20: PTO 01 | Y20: =SUMIFS(Cert_App_Output!$G:$G,Cert_App_Output!$E:$E,$E20,Cert_App_Output!$K:$K,$X20) -> 1
A21: Hormigón MT | B21: - | C21: - | D21: Homigón MO | E21: 3.02 | F21: OK | G21: Tabique submuración - H30 hidrófugo (95 kg/m3 de hierro) | H21: m3 | I21: 40 | J21: 70843.446 | K21: 0 | L21: 307690.19 | M21: 5678.0046 | N21: =SUM(J21:M21) -> 384211.64 | O21: =IF($N21=0,$S21,J21/$N21*$S21) -> 98842.531 | P21: =IF($N21=0,0,K21/$N21*$S21) -> 0 | Q21: =IF($N21=0,0,L21/$N21*$S21) -> 429296.98 | R21: =IF($N21=0,0,M21/$N21*$S21) -> 7922.0927 | S21: 536061.6 | T21: =IFERROR(S21/N21,"") -> 1.3952248 | U21: =N21*I21 -> 15368466 | V21: =S21*I21 -> 21442464 | W21: ESTRUCTURA RESISTENTE - sin provision de hierro y hormigon (incluye corte y doblado en obra) | X21: PTO 01 | Y21: =SUMIFS(Cert_App_Output!$G:$G,Cert_App_Output!$E:$E,$E21,Cert_App_Output!$K:$K,$X21) -> 1
A22: Hormigón MT | B22: - | C22: Homigón MO | D22: - | E22: 3.03 | F22: OK | G22: Zapata corrida tabique - H30 hidrófugo (120 kg/m3) | H22: m3 | I22: 28 | J22: 55068.822 | K22: 253994.14 | L22: 3e-05 | M22: 4635.9445 | N22: =SUM(J22:M22) -> 313698.91 | O22: =IF($N22=0,$S22,J22/$N22*$S22) -> 76833.432 | P22: =IF($N22=0,0,K22/$N22*$S22) -> 354379.14 | Q22: =IF($N22=0,0,L22/$N22*$S22) -> 4.1856769e-05 | R22: =IF($N22=0,0,M22/$N22*$S22) -> 6468.1886 | S22: 437680.76 | T22: =IFERROR(S22/N22,"") -> 1.3952256 | U22: =N22*I22 -> 8783569.5 | V22: =S22*I22 -> 12255061 | W22: ESTRUCTURA RESISTENTE - sin provision de hierro y hormigon (incluye corte y doblado en obra) | X22: PTO 01 | Y22: =SUMIFS(Cert_App_Output!$G:$G,Cert_App_Output!$E:$E,$E22,Cert_App_Output!$K:$K,$X22) -> 1
A23: Hormigón MT | B23: - | C23: Homigón MO | D23: - | E23: 3.04 | F23: OK | G23: Platea - H30 hidrófugo (95 kg/m3 de hierro) | H23: m3 | I23: 179 | J23: 2471.4098 | K23: 148967.56 | L23: -3e-05 | M23: 2271.5846 | N23: =SUM(J23:M23) -> 153710.56 | O23: =IF($N23=0,$S23,J23/$N23*$S23) -> 3448.1872 | P23: =IF($N23=0,0,K23/$N23*$S23) -> 207844.15 | Q23: =IF($N23=0,0,L23/$N23*$S23) -> -4.1856926e-05 | R23: =IF($N23=0,0,M23/$N23*$S23) -> 3169.385 | S23: 214461.72 | T23: =IFERROR(S23/N23,"") -> 1.3952309 | U23: =N23*I23 -> 27514190 | V23: =S23*I23 -> 38388648 | W23: ESTRUCTURA RESISTENTE - sin provision de hierro y hormigon (incluye corte y doblado en obra) | X23: PTO 01 | Y23: =SUMIFS(Cert_App_Output!$G:$G,Cert_App_Output!$E:$E,$E23,Cert_App_Output!$K:$K,$X23) -> 1
A24: Hormigón MT | B24: - | C24: - | D24: Homigón MO | E24: 3.05 | F24: OK | G24: Rampa - H30 (120 kg/m3 de hierro) | H24: m3 | I24: 10 | J24: 40150.005 | K24: 0 | L24: 286602.43 | M24: 4901.2865 | N24: =SUM(J24:M24) -> 331653.72 | O24: =IF($N24=0,$S24,J24/$N24*$S24) -> 56018.303 | P24: =IF($N24=0,0,K24/$N24*$S24) -> 0 | Q24: =IF($N24=0,0,L24/$N24*$S24) -> 399874.95 | R24: =IF($N24=0,0,M24/$N24*$S24) -> 6838.3988 | S24: 462731.65 | T24: =IFERROR(S24/N24,"") -> 1.3952253 | U24: =N24*I24 -> 3316537.2 | V24: =S24*I24 -> 4627316.5 | W24: ESTRUCTURA RESISTENTE - sin provision de hierro y hormigon (incluye corte y doblado en obra) | X24: PTO 01 | Y24: =SUMIFS(Cert_App_Output!$G:$G,Cert_App_Output!$E:$E,$E24,Cert_App_Output!$K:$K,$X24) -> 1
A25: Hormigón MT | B25: - | C25: - | D25: Homigón MO | E25: 3.06 | F25: OK | G25: Losa maciza - H30 (110 kg/m3 de hierro) | H25: m3 | I25: 177 | J25: 32975.501 | K25: 0 | L25: 191068.28 | M25: 3360.6568 | N25: =SUM(J25:M25) -> 227404.44 | O25: =IF($N25=0,$S25,J25/$N25*$S25) -> 46008.28 | P25: =IF($N25=0,0,K25/$N25*$S25) -> 0 | Q25: =IF($N25=0,0,L25/$N25*$S25) -> 266583.46 | R25: =IF($N25=0,0,M25/$N25*$S25) -> 4688.8761 | S25: 317280.61 | T25: =IFERROR(S25/N25,"") -> 1.3952261 | U25: =N25*I25 -> 40250586 | V25: =S25*I25 -> 56158669 | W25: ESTRUCTURA RESISTENTE - sin provision de hierro y hormigon (incluye corte y doblado en obra) | X25: PTO 01 | Y25: =SUMIFS(Cert_App_Output!$G:$G,Cert_App_Output!$E:$E,$E25,Cert_App_Output!$K:$K,$X25) -> 1
A26: Hormigón MT | B26: - | C26: - | D26: Homigón MO | E26: 3.07 | F26: OK | G26: Vigas - H30 (140 kg/m3 de hierro) | H26: m3 | I26: 65 | J26: 94228.958 | K26: 0 | L26: 462949.29 | M26: 8357.6737 | N26: =SUM(J26:M26) -> 565535.92 | O26: =IF($N26=0,$S26,J26/$N26*$S26) -> 131470.69 | P26: =IF($N26=0,0,K26/$N26*$S26) -> 0 | Q26: =IF($N26=0,0,L26/$N26*$S26) -> 645918.9 | R26: =IF($N26=0,0,M26/$N26*$S26) -> 11660.844 | S26: 789050.44 | T26: =IFERROR(S26/N26,"") -> 1.395226 | U26: =N26*I26 -> 36759835 | V26: =S26*I26 -> 51288278 | W26: ESTRUCTURA RESISTENTE - sin provision de hierro y hormigon (incluye corte y doblado en obra) | X26: PTO 01 | Y26: =SUMIFS(Cert_App_Output!$G:$G,Cert_App_Output!$E:$E,$E26,Cert_App_Output!$K:$K,$X26) -> 1
A27: Hormigón MT | B27: - | C27: - | D27: Homigón MO | E27: 3.08 | F27: OK | G27: Vigas de H° visto - H30 (140 kg/m3 de hierro) | H27: m3 | I27: 12 | J27: 92072.317 | K27: 0 | L27: 555539.15 | M27: 9714.172 | N27: =SUM(J27:M27) -> 657325.64 | O27: =IF($N27=0,$S27,J27/$N27*$S27) -> 128461.69 | P27: =IF($N27=0,0,K27/$N27*$S27) -> 0 | Q27: =IF($N27=0,0,L27/$N27*$S27) -> 775102.66 | R27: =IF($N27=0,0,M27/$N27*$S27) -> 13553.465 | S27: 917117.82 | T27: =IFERROR(S27/N27,"") -> 1.395226 | U27: =N27*I27 -> 7887907.6 | V27: =S27*I27 -> 11005414 | W27: ESTRUCTURA RESISTENTE - sin provision de hierro y hormigon (incluye corte y doblado en obra) | X27: PTO 01 | Y27: =SUMIFS(Cert_App_Output!$G:$G,Cert_App_Output!$E:$E,$E27,Cert_App_Output!$K:$K,$X27) -> 1
A28: Hormigón MT | B28: - | C28: - | D28: Homigón MO | E28: 3.09 | F28: OK | G28: Tabiques - H30 (120 kg/m3 de hierro) | H28: m3 | I28: 28 | J28: 70843.446 | K28: 0 | L28: 307690.19 | M28: 5678.0046 | N28: =SUM(J28:M28) -> 384211.64 | O28: =IF($N28=0,$S28,J28/$N28*$S28) -> 98842.531 | P28: =IF($N28=0,0,K28/$N28*$S28) -> 0 | Q28: =IF($N28=0,0,L28/$N28*$S28) -> 429296.98 | R28: =IF($N28=0,0,M28/$N28*$S28) -> 7922.0927 | S28: 536061.6 | T28: =IFERROR(S28/N28,"") -> 1.3952248 | U28: =N28*I28 -> 10757926 | V28: =S28*I28 -> 15009725 | W28: ESTRUCTURA RESISTENTE - sin provision de hierro y hormigon (incluye corte y doblado en obra) | X28: PTO 01 | Y28: =SUMIFS(Cert_App_Output!$G:$G,Cert_App_Output!$E:$E,$E28,Cert_App_Output!$K:$K,$X28) -> 1
A29: Hormigón MT | B29: - | C29: - | D29: Homigón MO | E29: 3.1 | F29: OK | G29: Columna - H30 (240 Kg/m3 de hierro) | H29: m3 | I29: 54 | J29: 60951.379 | K29: 0 | L29: 273658.45 | M29: 5019.1474 | N29: =SUM(J29:M29) -> 339628.98 | O29: =IF($N29=0,$S29,J29/$N29*$S29) -> 85040.911 | P29: =IF($N29=0,0,K29/$N29*$S29) -> 0 | Q29: =IF($N29=0,0,L29/$N29*$S29) -> 381815.22 | R29: =IF($N29=0,0,M29/$N29*$S29) -> 7002.8419 | S29: 473858.97 | T29: =IFERROR(S29/N29,"") -> 1.3952254 | U29: =N29*I29 -> 18339965 | V29: =S29*I29 -> 25588384 | W29: ESTRUCTURA RESISTENTE - sin provision de hierro y hormigon (incluye corte y doblado en obra) | X29: PTO 01 | Y29: =SUMIFS(Cert_App_Output!$G:$G,Cert_App_Output!$E:$E,$E29,Cert_App_Output!$K:$K,$X29) -> 1
A30: Hormigón MT | B30: - | C30: - | D30: Homigón MO | E30: 3.11 | F30: OK | G30: Escaleras - H30 (105 kg/m3 de hierro) | H30: m3 | I30: 11 | J30: 68185.041 | K30: 0 | L30: 283180.32 | M30: 5270.4803 | N30: =SUM(J30:M30) -> 356635.84 | O30: =IF($N30=0,$S30,J30/$N30*$S30) -> 95133.577 | P30: =IF($N30=0,0,K30/$N30*$S30) -> 0 | Q30: =IF($N30=0,0,L30/$N30*$S30) -> 395100.68 | R30: =IF($N30=0,0,M30/$N30*$S30) -> 7353.5139 | S30: 497587.77 | T30: =IFERROR(S30/N30,"") -> 1.3952265 | U30: =N30*I30 -> 3922994.2 | V30: =S30*I30 -> 5473465.5 | W30: ESTRUCTURA RESISTENTE - sin provision de hierro y hormigon (incluye corte y doblado en obra) | X30: PTO 01 | Y30: =SUMIFS(Cert_App_Output!$G:$G,Cert_App_Output!$E:$E,$E30,Cert_App_Output!$K:$K,$X30) -> 1
A31: Hormigón MT | B31: - | C31: - | D31: Homigón MO | E31: 3.12 | F31: OK | G31: Tabiques tanques de H° - H30 (120 kg/m3 de hierro) | H31: m3 | I31: 3 | J31: 70843.446 | K31: 0 | L31: 307690.19 | M31: 5678.0046 | N31: =SUM(J31:M31) -> 384211.64 | O31: =IF($N31=0,$S31,J31/$N31*$S31) -> 98842.531 | P31: =IF($N31=0,0,K31/$N31*$S31) -> 0 | Q31: =IF($N31=0,0,L31/$N31*$S31) -> 429296.98 | R31: =IF($N31=0,0,M31/$N31*$S31) -> 7922.0927 | S31: 536061.6 | T31: =IFERROR(S31/N31,"") -> 1.3952248 | U31: =N31*I31 -> 1152634.9 | V31: =S31*I31 -> 1608184.8 | W31: ESTRUCTURA RESISTENTE - sin provision de hierro y hormigon (incluye corte y doblado en obra) | X31: PTO 01 | Y31: =SUMIFS(Cert_App_Output!$G:$G,Cert_App_Output!$E:$E,$E31,Cert_App_Output!$K:$K,$X31) -> 1
... A36: Hormigón MT | B36: - | C36: - | D36: Homigón MO | E36: 3.17 | F36: OK | G36: Picado de medianeras para columnas y vigas - Cotizado solo para PB y 1P, No contempla picado en SS | H36: m2 | I36: 93 | J36: 5053.7634 | K36: 0 | L36: 14213.223 | M36: 289.0048 | N36: =SUM(J36:M36) -> 19555.992 | O36: =IF($N36=0,$S36,J36/$N36*$S36) -> 6352.0944 | P36: =IF($N36=0,0,K36/$N36*$S36) -> 0 | Q36: =IF($N36=0,0,L36/$N36*$S36) -> 17864.654 | R36: =IF($N36=0,0,M36/$N36*$S36) -> 363.25123 | S36: 24580 | T36: =IFERROR(S36/N36,"") -> 1.2569038 | U36: =N36*I36 -> 1818707.2 | V36: =S36*I36 -> 2285940 | W36: ESTRUCTURA RESISTENTE - sin provision de hierro y hormigon (incluye corte y doblado en obra) | X36: PTO 01 | Y36: =SUMIFS(Cert_App_Output!$G:$G,Cert_App_Output!$E:$E,$E36,Cert_App_Output!$K:$K,$X36) -> 1
E37: 24 | G37: AYUDA DE GREMIOS
A38: - | B38: - | C38: Albañilería MO | D38: - | E38: 24.01 | F38: OK | G38: Sereno | H38: mes | I38: 8 | J38: 0 | K38: 599210.85 | L38: 1.9e-05 | M38: 0 | N38: =SUM(J38:M38) -> 599210.85 | O38: =IF($N38=0,$S38,J38/$N38*$S38) -> 0 | P38: =IF($N38=0,0,K38/$N38*$S38) -> 753138 | Q38: =IF($N38=0,0,L38/$N38*$S38) -> 2.3880779e-05 | R38: =IF($N38=0,0,M38/$N38*$S38) -> 0 | S38: 753138 | T38: =IFERROR(S38/N38,"") -> 1.2568831 | U38: =N38*I38 -> 4793686.8 | V38: =S38*I38 -> 6025104 | W38: AYUDA DE GREMIOS | X38: PTO 01 | Y38: =SUMIFS(Cert_App_Output!$G:$G,Cert_App_Output!$E:$E,$E38,Cert_App_Output!$K:$K,$X38) -> 1
A39: - | B39: - | C39: Seguridad e Higiene | D39: - | E39: 24.02 | F39: OK | G39: Tecnico de seguridad & higiene permanente en Obra | H39: mes | I39: 4 | J39: 0 | K39: 1547376.3 | L39: 0 | M39: 0 | N39: =SUM(J39:M39) -> 1547376.3 | O39: =IF($N39=0,$S39,J39/$N39*$S39) -> 0 | P39: =IF($N39=0,0,K39/$N39*$S39) -> 1944871 | Q39: =IF($N39=0,0,L39/$N39*$S39) -> 0 | R39: =IF($N39=0,0,M39/$N39*$S39) -> 0 | S39: 1944871 | T39: =IFERROR(S39/N39,"") -> 1.256883 | U39: =N39*I39 -> 6189505.4 | V39: =S39*I39 -> 7779484 | W39: AYUDA DE GREMIOS | X39: PTO 01 | Y39: =SUMIFS(Cert_App_Output!$G:$G,Cert_App_Output!$E:$E,$E39,Cert_App_Output!$K:$K,$X39) -> 1
A40: - | B40: - | C40: Seguridad e Higiene | D40: - | E40: 24.03 | F40: OK | G40: Higiene y seguridad Res 51 | H40: mes | I40: 8 | J40: 0 | K40: 150000 | L40: 0 | M40: 0 | N40: =SUM(J40:M40) -> 150000 | O40: =IF($N40=0,$S40,J40/$N40*$S40) -> 0 | P40: =IF($N40=0,0,K40/$N40*$S40) -> 188533 | Q40: =IF($N40=0,0,L40/$N40*$S40) -> 0 | R40: =IF($N40=0,0,M40/$N40*$S40) -> 0 | S40: 188533 | T40: =IFERROR(S40/N40,"") -> 1.2568867 | U40: =N40*I40 -> 1200000 | V40: =S40*I40 -> 1508264 | W40: AYUDA DE GREMIOS | X40: PTO 01 | Y40: =SUMIFS(Cert_App_Output!$G:$G,Cert_App_Output!$E:$E,$E40,Cert_App_Output!$K:$K,$X40) -> 1
A41: Albañilería MT | B41: - | C41: - | D41: Albañilería MO | E41: 24.04 | F41: OK | G41: Protecciones y defensas | H41: gl | I41: 1 | J41: 2388097.3 | K41: 0 | L41: 1222808.1 | M41: 54163.58 | N41: =SUM(J41:M41) -> 3665068.9 | O41: =IF($N41=0,$S41,J41/$N41*$S41) -> 3001558.3 | P41: =IF($N41=0,0,K41/$N41*$S41) -> 0 | Q41: =IF($N41=0,0,L41/$N41*$S41) -> 1536926.4 | R41: =IF($N41=0,0,M41/$N41*$S41) -> 68077.271 | S41: 4606562 | T41: =IFERROR(S41/N41,"") -> 1.2568828 | U41: =N41*I41 -> 3665068.9 | V41: =S41*I41 -> 4606562 | W41: AYUDA DE GREMIOS | X41: PTO 01 | Y41: =SUMIFS(Cert_App_Output!$G:$G,Cert_App_Output!$E:$E,$E41,Cert_App_Output!$K:$K,$X41) -> 1
A42: Albañilería MT | B42: - | C42: - | D42: Albañilería MO | E42: 24.05 | F42: OK | G42: Ayuda de Gremios | H42: mes | I42: 8 | J42: 50000 | K42: 0 | L42: 495686.17 | M42: 8185.2925 | N42: =SUM(J42:M42) -> 553871.46 | O42: =IF($N42=0,$S42,J42/$N42*$S42) -> 62844.184 | P42: =IF($N42=0,0,K42/$N42*$S42) -> 0 | Q42: =IF($N42=0,0,L42/$N42*$S42) -> 623019.86 | R42: =IF($N42=0,0,M42/$N42*$S42) -> 10287.961 | S42: 696152 | T42: =IFERROR(S42/N42,"") -> 1.2568837 | U42: =N42*I42 -> 4430971.7 | V42: =S42*I42 -> 5569216 | W42: AYUDA DE GREMIOS | X42: PTO 01 | Y42: =SUMIFS(Cert_App_Output!$G:$G,Cert_App_Output!$E:$E,$E42,Cert_App_Output!$K:$K,$X42) -> 1
A43: Albañilería MT | B43: - | C43: - | D43: Albañilería MO | E43: 24.06 | F43: OK | G43: Limpieza periodica | H43: mes | I43: 8 | J43: 25000 | K43: 0 | L43: 329565.97 | M43: 5318.4895 | N43: =SUM(J43:M43) -> 359884.46 | O43: =IF($N43=0,$S43,J43/$N43*$S43) -> 31422.099 | P43: =IF($N43=0,0,K43/$N43*$S43) -> 0 | Q43: =IF($N43=0,0,L43/$N43*$S43) -> 414226.18 | R43: =IF($N43=0,0,M43/$N43*$S43) -> 6684.7241 | S43: 452333 | T43: =IFERROR(S43/N43,"") -> 1.256884 | U43: =N43*I43 -> 2879075.6 | V43: =S43*I43 -> 3618664 | W43: AYUDA DE GREMIOS | X43: PTO 01 | Y43: =SUMIFS(Cert_App_Output!$G:$G,Cert_App_Output!$E:$E,$E43,Cert_App_Output!$K:$K,$X43) -> 1
A44: Albañilería MT | B44: - | C44: - | D44: - | E44: 24.07 | F44: OK | G44: Limpieza final de Obra | H44: gl | I44: 0 | J44: 0 | K44: 0 | L44: 0 | M44: 0 | N44: =SUM(J44:M44) -> 0 | O44: =IF($N44=0,$S44,J44/$N44*$S44) -> 0 | P44: =IF($N44=0,0,K44/$N44*$S44) -> 0 | Q44: =IF($N44=0,0,L44/$N44*$S44) -> 0 | R44: =IF($N44=0,0,M44/$N44*$S44) -> 0 | S44: 0 | T44: =IFERROR(S44/N44,"") | U44: =N44*I44 -> 0 | V44: =S44*I44 -> 0 | W44: AYUDA DE GREMIOS | X44: PTO 01 | Y44: =SUMIFS(Cert_App_Output!$G:$G,Cert_App_Output!$E:$E,$E44,Cert_App_Output!$K:$K,$X44) -> 0
A45: - | B45: - | C45: Mov. Variables | D45: - | E45: 24.08 | F45: OK | G45: Fletes | H45: mes | I45: 8 | J45: 0 | K45: 250000 | L45: 0 | M45: 0 | N45: =SUM(J45:M45) -> 250000 | O45: =IF($N45=0,$S45,J45/$N45*$S45) -> 0 | P45: =IF($N45=0,0,K45/$N45*$S45) -> 314221 | Q45: =IF($N45=0,0,L45/$N45*$S45) -> 0 | R45: =IF($N45=0,0,M45/$N45*$S45) -> 0 | S45: 314221 | T45: =IFERROR(S45/N45,"") -> 1.256884 | U45: =N45*I45 -> 2000000 | V45: =S45*I45 -> 2513768 | W45: AYUDA DE GREMIOS | X45: PTO 01 | Y45: =SUMIFS(Cert_App_Output!$G:$G,Cert_App_Output!$E:$E,$E45,Cert_App_Output!$K:$K,$X45) -> 1
A46: Alquiler de Equipos | B46: - | C46: - | D46: - | E46: 24.09 | F46: OK | G46: Alquiler de equipos - Montacargas, tubos de descarga y balancin | H46: mes | I46: 4 | J46: 0 | K46: 0 | L46: 0 | M46: 0 | N46: =SUM(J46:M46) -> 0 | O46: =IF($N46=0,$S46,J46/$N46*$S46) -> 0 | P46: =IF($N46=0,0,K46/$N46*$S46) -> 0 | Q46: =IF($N46=0,0,L46/$N46*$S46) -> 0 | R46: =IF($N46=0,0,M46/$N46*$S46) -> 0 | S46: 0 | T46: =IFERROR(S46/N46,"") | U46: =N46*I46 -> 0 | V46: =S46*I46 -> 0 | W46: AYUDA DE GREMIOS | X46: PTO 01 | Y46: =SUMIFS(Cert_App_Output!$G:$G,Cert_App_Output!$E:$E,$E46,Cert_App_Output!$K:$K,$X46) -> 0
A47: Gastos Generales | B47: - | C47: - | D47: Albañilería MO | E47: 24.1 | F47: OK | G47: Volquetes | H47: mes | I47: 8 | J47: 200000 | K47: 0 | L47: 49934.237 | M47: 0 | N47: =SUM(J47:M47) -> 249934.24 | O47: =IF($N47=0,$S47,J47/$N47*$S47) -> 251376.52 | P47: =IF($N47=0,0,K47/$N47*$S47) -> 0 | Q47: =IF($N47=0,0,L47/$N47*$S47) -> 62761.475 | R47: =IF($N47=0,0,M47/$N47*$S47) -> 0 | S47: 314138 | T47: =IFERROR(S47/N47,"") -> 1.2568826 | U47: =N47*I47 -> 1999473.9 | V47: =S47*I47 -> 2513104 | W47: AYUDA DE GREMIOS | X47: PTO 01 | Y47: =SUMIFS(Cert_App_Output!$G:$G,Cert_App_Output!$E:$E,$E47,Cert_App_Output!$K:$K,$X47) -> 1
E48: 25 | G48: JEFATURA DE OBRA
A49: - | B49: - | C49: Supervisión de Obra MO | D49: - | E49: 25.01 | F49: OK | G49: Supervisión profesional de Obra | H49: mes | I49: 8 | J49: 0 | K49: 3798370.6 | L49: 0 | M49: 0 | N49: =SUM(J49:M49) -> 3798370.6 | O49: =IF($N49=0,$S49,J49/$N49*$S49) -> 0 | P49: =IF($N49=0,0,K49/$N49*$S49) -> 4774106 | Q49: =IF($N49=0,0,L49/$N49*$S49) -> 0 | R49: =IF($N49=0,0,M49/$N49*$S49) -> 0 | S49: 4774106 | T49: =IFERROR(S49/N49,"") -> 1.2568826 | U49: =N49*I49 -> 30386965 | V49: =S49*I49 -> 38192848 | W49: JEFATURA DE OBRA | X49: PTO 01 | Y49: =SUMIFS(Cert_App_Output!$G:$G,Cert_App_Output!$E:$E,$E49,Cert_App_Output!$K:$K,$X49) -> 1
A50: - | B50: - | C50: Mov. Variables | D50: - | E50: 25.02 | F50: OK | G50: Movilidad y viaticos | H50: mes | I50: 8 | J50: 0 | K50: 500000 | L50: 0 | M50: 0 | N50: =SUM(J50:M50) -> 500000 | O50: =IF($N50=0,$S50,J50/$N50*$S50) -> 0 | P50: =IF($N50=0,0,K50/$N50*$S50) -> 628442 | Q50: =IF($N50=0,0,L50/$N50*$S50) -> 0 | R50: =IF($N50=0,0,M50/$N50*$S50) -> 0 | S50: 628442 | T50: =IFERROR(S50/N50,"") -> 1.256884 | U50: =N50*I50 -> 4000000 | V50: =S50*I50 -> 5027536 | W50: JEFATURA DE OBRA | X50: PTO 01 | Y50: =SUMIFS(Cert_App_Output!$G:$G,Cert_App_Output!$E:$E,$E50,Cert_App_Output!$K:$K,$X50) -> 1
E51: 4 | G51: ALBAÑILERIA
A52: Albañilería MT | B52: - | C52: - | D52: Albañilería MO | E52: 4.01 | F52: OK | G52: Muro tipo 1 (interiores, divisorio de locales) e: 10 cm - Ladrillo hueco 08 x 18 x 33 | H52: m2 | I52: 819 | J52: 6545.2009 | K52: 0 | L52: 8336.4857 | M52: 229.16796 | N52: =SUM(J52:M52) -> 15110.855 | O52: =IF($N52=0,$S52,J52/$N52*$S52) -> 8226.7353 | P52: =IF($N52=0,0,K52/$N52*$S52) -> 0 | Q52: =IF($N52=0,0,L52/$N52*$S52) -> 10478.221 | R52: =IF($N52=0,0,M52/$N52*$S52) -> 288.04374 | S52: 18993 | T52: =IFERROR(S52/N52,"") -> 1.256911 | U52: =N52*I52 -> 12375790 | V52: =S52*I52 -> 15555267 | W52: ALBAÑILERIA | X52: PTO 02 | Y52: =SUMIFS(Cert_App_Output!$G:$G,Cert_App_Output!$E:$E,$E52,Cert_App_Output!$K:$K,$X52) -> 1.05
A53: Albañilería MT | B53: - | C53: - | D53: Albañilería MO | E53: 4.02 | F53: OK | G53: Muro tipo 2 y 3 (medianera, caja de escaleras y ascensor) e: 15 cm - Ladrillo hueco portante 12 x 19 x 33 | H53: m2 | I53: 612 | J53: 11461.565 | K53: 0 | L53: 8336.4857 | M53: 229.16796 | N53: =SUM(J53:M53) -> 20027.219 | O53: =IF($N53=0,$S53,J53/$N53*$S53) -> 14405.92 | P53: =IF($N53=0,0,K53/$N53*$S53) -> 0 | Q53: =IF($N53=0,0,L53/$N53*$S53) -> 10478.041 | R53: =IF($N53=0,0,M53/$N53*$S53) -> 288.03879 | S53: 25172 | T53: =IFERROR(S53/N53,"") -> 1.2568894 | U53: =N53*I53 -> 12256658 | V53: =S53*I53 -> 15405264 | W53: ALBAÑILERIA | X53: PTO 02 | Y53: =SUMIFS(Cert_App_Output!$G:$G,Cert_App_Output!$E:$E,$E53,Cert_App_Output!$K:$K,$X53) -> 1.25
A54: Albañilería MT | B54: - | C54: - | D54: Albañilería MO | E54: 4.03 | F54: OK | G54: Muro tipo 4 (divisorio de unidades y fachas) e: 15 cm - Ladrillo hueco 12 x 18 x 33 | H54: m2 | I54: 636 | J54: 8229.0499 | K54: 0 | L54: 8336.4857 | M54: 229.16796 | N54: =SUM(J54:M54) -> 16794.704 | O54: =IF($N54=0,$S54,J54/$N54*$S54) -> 10342.964 | P54: =IF($N54=0,0,K54/$N54*$S54) -> 0 | Q54: =IF($N54=0,0,L54/$N54*$S54) -> 10477.998 | R54: =IF($N54=0,0,M54/$N54*$S54) -> 288.03763 | S54: 21109 | T54: =IFERROR(S54/N54,"") -> 1.2568843 | U54: =N54*I54 -> 10681431 | V54: =S54*I54 -> 13425324 | W54: ALBAÑILERIA | X54: PTO 02 | Y54: =SUMIFS(Cert_App_Output!$G:$G,Cert_App_Output!$E:$E,$E54,Cert_App_Output!$K:$K,$X54) -> 1.05
A55: Albañilería MT | B55: - | C55: - | D55: Albañilería MO | E55: 4.04 | F55: OK | G55: Enchape medianeras existentes - Contemplamos picado zonas sueltas y enchape con ladrillo comun para PB | H55: m2 | I55: 195 | J55: 5807.159 | K55: 0 | L55: 5954.6326 | M55: 245.5371 | N55: =SUM(J55:M55) -> 12007.329 | O55: =IF($N55=0,$S55,J55/$N55*$S55) -> 7299.0126 | P55: =IF($N55=0,0,K55/$N55*$S55) -> 0 | Q55: =IF($N55=0,0,L55/$N55*$S55) -> 7484.3721 | R55: =IF($N55=0,0,M55/$N55*$S55) -> 308.61535 | S55: 15092 | T55: =IFERROR(S55/N55,"") -> 1.256899 | U55: =N55*I55 -> 2341429.1 | V55: =S55*I55 -> 2942940 | W55: ALBAÑILERIA | X55: PTO 02 | Y55: =SUMIFS(Cert_App_Output!$G:$G,Cert_App_Output!$E:$E,$E55,Cert_App_Output!$K:$K,$X55) -> 0.15
A56: Albañilería MT | B56: - | C56: Albañilería MO | D56: Albañilería MO | E56: 4.05 | F56: OK | G56: Mamposteria cribada de ladrillo visto en balcones | H56: m2 | I56: 30.054 | J56: 17421.477 | K56: 17863.898 | L56: 17863.898 | M56: 491.07421 | N56: =SUM(J56:M56) -> 53640.347 | O56: =IF($N56=0,$S56,J56/$N56*$S56) -> 21896.875 | P56: =IF($N56=0,0,K56/$N56*$S56) -> 22452.949 | Q56: =IF($N56=0,0,L56/$N56*$S56) -> 22452.95 | R56: =IF($N56=0,0,M56/$N56*$S56) -> 617.22612 | S56: 67420 | T56: =IFERROR(S56/N56,"") -> 1.2568897 | U56: =N56*I56 -> 1612107 | V56: =S56*I56 -> 2026240.7 | W56: ALBAÑILERIA | X56: PTO 02 | Y56: =SUMIFS(Cert_App_Output!$G:$G,Cert_App_Output!$E:$E,$E56,Cert_App_Output!$K:$K,$X56) -> 0
A57: Albañilería MT | B57: - | C57: Albañilería MO | D57: Albañilería MO | E57: 4.06 | F57: OK | G57: Bloque de H° con masillado de hormigon | H57: m2 | I57: 24 | J57: 28704.1 | K57: 4894.0752 | L57: 9788.15 | M57: 298.91474 | N57: =SUM(J57:M57) -> 43685.24 | O57: =IF($N57=0,$S57,J57/$N57*$S57) -> 36078.198 | P57: =IF($N57=0,0,K57/$N57*$S57) -> 6151.3656 | Q57: =IF($N57=0,0,L57/$N57*$S57) -> 12302.731 | R57: =IF($N57=0,0,M57/$N57*$S57) -> 375.70608 | S57: 54908 | T57: =IFERROR(S57/N57,"") -> 1.2569005 | U57: =N57*I57 -> 1048445.8 | V57: =S57*I57 -> 1317792 | W57: ALBAÑILERIA | X57: PTO 02 | Y57: =SUMIFS(Cert_App_Output!$G:$G,Cert_App_Output!$E:$E,$E57,Cert_App_Output!$K:$K,$X57) -> 1
A58: Albañilería MT | B58: - | C58: - | D58: Albañilería MO | E58: 4.07 | F58: OK | G58: Cordón de hormigón en umbrales carpinterías | H58: ml | I58: 81 | J58: 17364.128 | K58: 0 | L58: 6926.499 | M58: 364.3594 | N58: =SUM(J58:M58) -> 24654.986 | O58: =IF($N58=0,$S58,J58/$N58*$S58) -> 21825.076 | P58: =IF($N58=0,0,K58/$N58*$S58) -> 0 | Q58: =IF($N58=0,0,L58/$N58*$S58) -> 8705.9581 | R58: =IF($N58=0,0,M58/$N58*$S58) -> 457.96552 | S58: 30989 | T58: =IFERROR(S58/N58,"") -> 1.256906 | U58: =N58*I58 -> 1997053.9 | V58: =S58*I58 -> 2510109 | W58: ALBAÑILERIA | X58: PTO 02 | Y58: =SUMIFS(Cert_App_Output!$G:$G,Cert_App_Output!$E:$E,$E58,Cert_App_Output!$K:$K,$X58) -> 0.9
A59: Albañilería MT | B59: - | C59: - | D59: Albañilería MO | E59: 4.08 | F59: OK | G59: Pozo de bombeo pluvial y cloacal | H59: gl | I59: 1 | J59: 451217.95 | K59: 0 | L59: 426669.72 | M59: 13168.315 | N59: =SUM(J59:M59) -> 891055.98 | O59: =IF($N59=0,$S59,J59/$N59*$S59) -> 567128.11 | P59: =IF($N59=0,0,K59/$N59*$S59) -> 0 | Q59: =IF($N59=0,0,L59/$N59*$S59) -> 536273.86 | R59: =IF($N59=0,0,M59/$N59*$S59) -> 16551.03 | S59: 1119953 | T59: =IFERROR(S59/N59,"") -> 1.2568829 | U59: =N59*I59 -> 891055.98 | V59: =S59*I59 -> 1119953 | W59: ALBAÑILERIA | X59: PTO 02 | Y59: =SUMIFS(Cert_App_Output!$G:$G,Cert_App_Output!$E:$E,$E59,Cert_App_Output!$K:$K,$X59) -> 0.5
E60: 5 | G60: AISLACIONES
A61: Albañilería MT | B61: - | C61: Albañilería MO | D61: Albañilería MO | E61: 5.01 | F61: OK | G61: Aislación hidrófuga horizontal (baños) - Inc. membrana geotextil y 35% en concepto de babetas | H61: m2 | I61: 139.05 | J61: 9809.5604 | K61: 2500.9457 | L61: 5001.8914 | M61: 31.337345 | N61: =SUM(J61:M61) -> 17343.735 | O61: =IF($N61=0,$S61,J61/$N61*$S61) -> 12330.01 | P61: =IF($N61=0,0,K61/$N61*$S61) -> 3143.5338 | Q61: =IF($N61=0,0,L61/$N61*$S61) -> 6287.0676 | R61: =IF($N61=0,0,M61/$N61*$S61) -> 39.3891 | S61: 21800 | T61: =IFERROR(S61/N61,"") -> 1.256938 | U61: =N61*I61 -> 2411646.3 | V61: =S61*I61 -> 3031290 | W61: AISLACIONES | X61: PTO 02 | Y61: =SUMIFS(Cert_App_Output!$G:$G,Cert_App_Output!$E:$E,$E61,Cert_App_Output!$K:$K,$X61) -> 0.3
A62: Albañilería MT | B62: - | C62: - | D62: Albañilería MO | E62: 5.02 | F62: OK | G62: Azotado hidrofugo - Sobre medianeras existentes | H62: m2 | I62: 300 | J62: 758.10738 | K62: 0 | L62: 3395.9551 | M62: 122.76855 | N62: =SUM(J62:M62) -> 4276.831 | O62: =IF($N62=0,$S62,J62/$N62*$S62) -> 952.94512 | P62: =IF($N62=0,0,K62/$N62*$S62) -> 0 | Q62: =IF($N62=0,0,L62/$N62*$S62) -> 4268.7341 | R62: =IF($N62=0,0,M62/$N62*$S62) -> 154.32074 | S62: 5376 | T62: =IFERROR(S62/N62,"") -> 1.2570055 | U62: =N62*I62 -> 1283049.3 | V62: =S62*I62 -> 1612800 | W62: AISLACIONES | X62: PTO 02 | Y62: =SUMIFS(Cert_App_Output!$G:$G,Cert_App_Output!$E:$E,$E62,Cert_App_Output!$K:$K,$X62) -> 1
A63: Albañilería MT | B63: - | C63: - | D63: Albañilería MO | E63: 5.03 | F63: OK | G63: Azotado hidrofugo - Contrapiso de vereda | H63: m2 | I63: 48 | J63: 758.10738 | K63: 0 | L63: 3395.9551 | M63: 122.76855 | N63: =SUM(J63:M63) -> 4276.831 | O63: =IF($N63=0,$S63,J63/$N63*$S63) -> 952.94512 | P63: =IF($N63=0,0,K63/$N63*$S63) -> 0 | Q63: =IF($N63=0,0,L63/$N63*$S63) -> 4268.7341 | R63: =IF($N63=0,0,M63/$N63*$S63) -> 154.32074 | S63: 5376 | T63: =IFERROR(S63/N63,"") -> 1.2570055 | U63: =N63*I63 -> 205287.89 | V63: =S63*I63 -> 258048 | W63: AISLACIONES | X63: PTO 02 | Y63: =SUMIFS(Cert_App_Output!$G:$G,Cert_App_Output!$E:$E,$E63,Cert_App_Output!$K:$K,$X63) -> 0
A64: Albañilería MT | B64: - | C64: - | D64: - | E64: 5.04 | F64: OK | G64: Aislación térmica en terrazas, eps e:2,00 cm | H64: m2 | I64: 262 | J64: 3502.8 | K64: 0 | L64: 0 | M64: 0 | N64: =SUM(J64:M64) -> 3502.8 | O64: =IF($N64=0,$S64,J64/$N64*$S64) -> 4403 | P64: =IF($N64=0,0,K64/$N64*$S64) -> 0 | Q64: =IF($N64=0,0,L64/$N64*$S64) -> 0 | R64: =IF($N64=0,0,M64/$N64*$S64) -> 0 | S64: 4403 | T64: =IFERROR(S64/N64,"") -> 1.2569944 | U64: =N64*I64 -> 917733.6 | V64: =S64*I64 -> 1153586 | W64: AISLACIONES | X64: PTO 02 | Y64: =SUMIFS(Cert_App_Output!$G:$G,Cert_App_Output!$E:$E,$E64,Cert_App_Output!$K:$K,$X64) -> 0
A65: Albañilería MT | B65: - | C65: - | D65: Albañilería MO | E65: 5.05 | F65: OK | G65: Barrera de vapor | H65: m2 | I65: 510 | J65: 1273.3407 | K65: 0 | L65: 1563.0911 | M65: 9.7929202 | N65: =SUM(J65:M65) -> 2846.2247 | O65: =IF($N65=0,$S65,J65/$N65*$S65) -> 1600.7215 | P65: =IF($N65=0,0,K65/$N65*$S65) -> 0 | Q65: =IF($N65=0,0,L65/$N65*$S65) -> 1964.9678 | R65: =IF($N65=0,0,M65/$N65*$S65) -> 12.310717 | S65: 3578 | T65: =IFERROR(S65/N65,"") -> 1.2571038 | U65: =N65*I65 -> 1451574.6 | V65: =S65*I65 -> 1824780 | W65: AISLACIONES | X65: PTO 02 | Y65: =SUMIFS(Cert_App_Output!$G:$G,Cert_App_Output!$E:$E,$E65,Cert_App_Output!$K:$K,$X65) -> 0.7
A66: Albañilería MT | B66: - | C66: Albañilería MO | D66: Albañilería MO | E66: 5.06 | F66: OK | G66: Membrana asfaltica geotextil 4mm - Balcones y azotea - Inc. 20% en concepto de babetas | H66: m2 | I66: 510 | J66: 9809.5604 | K66: 2500.9457 | L66: 5001.8914 | M66: 31.337345 | N66: =SUM(J66:M66) -> 17343.735 | O66: =IF($N66=0,$S66,J66/$N66*$S66) -> 12330.01 | P66: =IF($N66=0,0,K66/$N66*$S66) -> 3143.5338 | Q66: =IF($N66=0,0,L66/$N66*$S66) -> 6287.0676 | R66: =IF($N66=0,0,M66/$N66*$S66) -> 39.3891 | S66: 21800 | T66: =IFERROR(S66/N66,"") -> 1.256938 | U66: =N66*I66 -> 8845304.8 | V66: =S66*I66 -> 11118000 | W66: AISLACIONES | X66: PTO 02 | Y66: =SUMIFS(Cert_App_Output!$G:$G,Cert_App_Output!$E:$E,$E66,Cert_App_Output!$K:$K,$X66) -> 0
A67: - | B67: - | C67: Albañilería MO | D67: - | E67: 5.07 | F67: OK | G67: Impermeabilización de subsuelo | H67: gl | I67: 1 | J67: 0 | K67: 13500000 | L67: 0 | M67: 0 | N67: =SUM(J67:M67) -> 13500000 | O67: =IF($N67=0,$S67,J67/$N67*$S67) -> 0 | P67: =IF($N67=0,0,K67/$N67*$S67) -> 16967915 | Q67: =IF($N67=0,0,L67/$N67*$S67) -> 0 | R67: =IF($N67=0,0,M67/$N67*$S67) -> 0 | S67: 16967915 | T67: =IFERROR(S67/N67,"") -> 1.2568826 | U67: =N67*I67 -> 13500000 | V67: =S67*I67 -> 16967915 | W67: AISLACIONES | X67: PTO 02 | Y67: =SUMIFS(Cert_App_Output!$G:$G,Cert_App_Output!$E:$E,$E67,Cert_App_Output!$K:$K,$X67) -> 1
E68: 6 | G68: CUBIERTAS
A69: Albañilería MT | B69: - | C69: - | D69: Albañilería MO | E69: 6.02 | F69: OK | G69: Babeta de chapa galvanizada en medianeras | H69: ml | I69: 60 | J69: 13939.394 | K69: 0 | L69: 4329.904 | M69: 14004.342 | N69: =SUM(J69:M69) -> 32273.64 | O69: =IF($N69=0,$S69,J69/$N69*$S69) -> 17520.537 | P69: =IF($N69=0,0,K69/$N69*$S69) -> 0 | Q69: =IF($N69=0,0,L69/$N69*$S69) -> 5442.2914 | R69: =IF($N69=0,0,M69/$N69*$S69) -> 17602.171 | S69: 40565 | T69: =IFERROR(S69/N69,"") -> 1.2569081 | U69: =N69*I69 -> 1936418.4 | V69: =S69*I69 -> 2433900 | W69: CUBIERTAS | X69: PTO 02 | Y69: =SUMIFS(Cert_App_Output!$G:$G,Cert_App_Output!$E:$E,$E69,Cert_App_Output!$K:$K,$X69) -> 0
E70: 7 | G70: REVOQUES
A71: Albañilería MT | B71: - | C71: - | D71: Albañilería MO | E71: 7.01 | F71: OK | G71: Revoque Grueso Impermeable Exterior proyectable | H71: m2 | I71: 678.252 | J71: 3747.8693 | K71: 0 | L71: 9136.834 | M71: 298.91474 | N71: =SUM(J71:M71) -> 13183.618 | O71: =IF($N71=0,$S71,J71/$N71*$S71) -> 4710.8421 | P71: =IF($N71=0,0,K71/$N71*$S71) -> 0 | Q71: =IF($N71=0,0,L71/$N71*$S71) -> 11484.44 | R71: =IF($N71=0,0,M71/$N71*$S71) -> 375.71751 | S71: 16571 | T71: =IFERROR(S71/N71,"") -> 1.2569387 | U71: =N71*I71 -> 8941815.3 | V71: =S71*I71 -> 11239314 | W71: REVOQUES | X71: PTO 02 | Y71: =SUMIFS(Cert_App_Output!$G:$G,Cert_App_Output!$E:$E,$E71,Cert_App_Output!$K:$K,$X71) -> 0.15
A72: Albañilería MT | B72: - | C72: - | D72: Albañilería MO | E72: 7.02 | F72: OK | G72: Revoque Grueso Impermeable Exterior a mas de 3m proyectable - Medianero y fachadas | H72: m2 | I72: 876.0812 | J72: 3747.8693 | K72: 0 | L72: 13134.199 | M72: 766.41029 | N72: =SUM(J72:M72) -> 17648.478 | O72: =IF($N72=0,$S72,J72/$N72*$S72) -> 4710.8302 | P72: =IF($N72=0,0,K72/$N72*$S72) -> 0 | Q72: =IF($N72=0,0,L72/$N72*$S72) -> 16508.841 | R72: =IF($N72=0,0,M72/$N72*$S72) -> 963.32835 | S72: 22183 | T72: =IFERROR(S72/N72,"") -> 1.2569356 | U72: =N72*I72 -> 15461500 | V72: =S72*I72 -> 19434109 | W72: REVOQUES | X72: PTO 02 | Y72: =SUMIFS(Cert_App_Output!$G:$G,Cert_App_Output!$E:$E,$E72,Cert_App_Output!$K:$K,$X72) -> 1
A73: - | B73: - | C73: Albañilería MO | D73: - | E73: 7.03 | F73: OK | G73: Buña en revoque | H73: ml | I73: 182 | J73: 0 | K73: 8597.4065 | L73: 1.5e-05 | M73: 0 | N73: =SUM(J73:M73) -> 8597.4065 | O73: =IF($N73=0,$S73,J73/$N73*$S73) -> 0 | P73: =IF($N73=0,0,K73/$N73*$S73) -> 10806 | Q73: =IF($N73=0,0,L73/$N73*$S73) -> 1.885336e-05 | R73: =IF($N73=0,0,M73/$N73*$S73) -> 0 | S73: 10806 | T73: =IFERROR(S73/N73,"") -> 1.2568907 | U73: =N73*I73 -> 1564728 | V73: =S73*I73 -> 1966692 | W73: REVOQUES | X73: PTO 02 | Y73: =SUMIFS(Cert_App_Output!$G:$G,Cert_App_Output!$E:$E,$E73,Cert_App_Output!$K:$K,$X73) -> 0.65
A74: Albañilería MT | B74: - | C74: - | D74: Albañilería MO | E74: 7.04 | F74: OK | G74: Revoque Grueso Interior + fino | H74: m2 | I74: 995.8511 | J74: 2606.0756 | K74: 0 | L74: 17928.384 | M74: 572.91991 | N74: =SUM(J74:M74) -> 21107.379 | O74: =IF($N74=0,$S74,J74/$N74*$S74) -> 3275.5931 | P74: =IF($N74=0,0,K74/$N74*$S74) -> 0 | Q74: =IF($N74=0,0,L74/$N74*$S74) -> 22534.3 | R74: =IF($N74=0,0,M74/$N74*$S74) -> 720.1067 | S74: 26530 | T74: =IFERROR(S74/N74,"") -> 1.2569064 | U74: =N74*I74 -> 21019807 | V74: =S74*I74 -> 26419930 | W74: REVOQUES | X74: PTO 02 | Y74: =SUMIFS(Cert_App_Output!$G:$G,Cert_App_Output!$E:$E,$E74,Cert_App_Output!$K:$K,$X74) -> 0.6
A75: Durlock MT | B75: - | C75: Durlock MO | D75: - | E75: 7.05 | F75: OK | G75: Yeso interior | H75: m2 | I75: 2514.897 | J75: 5135.3399 | K75: 12817.952 | L75: 0 | M75: 0 | N75: =SUM(J75:M75) -> 17953.291 | O75: =IF($N75=0,$S75,J75/$N75*$S75) -> 6454.754 | P75: =IF($N75=0,0,K75/$N75*$S75) -> 16111.246 | Q75: =IF($N75=0,0,L75/$N75*$S75) -> 0 | R75: =IF($N75=0,0,M75/$N75*$S75) -> 0 | S75: 22566 | T75: =IFERROR(S75/N75,"") -> 1.2569283 | U75: =N75*I75 -> 45150679 | V75: =S75*I75 -> 56751166 | W75: REVOQUES | X75: PTO 02 | Y75: =SUMIFS(Cert_App_Output!$G:$G,Cert_App_Output!$E:$E,$E75,Cert_App_Output!$K:$K,$X75) -> 0.5
A76: - | B76: - | C76: Durlock MO | D76: - | E76: 7.06 | F76: OK | G76: Arista en yeso | H76: ml | I76: 509.9 | J76: 0 | K76: 10160.571 | L76: 0 | M76: 0 | N76: =SUM(J76:M76) -> 10160.571 | O76: =IF($N76=0,$S76,J76/$N76*$S76) -> 0 | P76: =IF($N76=0,0,K76/$N76*$S76) -> 12771 | Q76: =IF($N76=0,0,L76/$N76*$S76) -> 0 | R76: =IF($N76=0,0,M76/$N76*$S76) -> 0 | S76: 12771 | T76: =IFERROR(S76/N76,"") -> 1.2569175 | U76: =N76*I76 -> 5180875.3 | V76: =S76*I76 -> 6511932.9 | W76: REVOQUES | X76: PTO 02 | Y76: =SUMIFS(Cert_App_Output!$G:$G,Cert_App_Output!$E:$E,$E76,Cert_App_Output!$K:$K,$X76) -> 0.5
A77: Durlock MT | B77: - | C77: Durlock MO | D77: - | E77: 7.07 | F77: OK | G77: Provisión y colocación de guardacanto yesero | H77: u | I77: 198 | J77: 1217.7455 | K77: 10673.732 | L77: 0 | M77: 0 | N77: =SUM(J77:M77) -> 11891.477 | O77: =IF($N77=0,$S77,J77/$N77*$S77) -> 1530.646 | P77: =IF($N77=0,0,K77/$N77*$S77) -> 13416.354 | Q77: =IF($N77=0,0,L77/$N77*$S77) -> 0 | R77: =IF($N77=0,0,M77/$N77*$S77) -> 0 | S77: 14947 | T77: =IFERROR(S77/N77,"") -> 1.2569507 | U77: =N77*I77 -> 2354512.4 | V77: =S77*I77 -> 2959506 | W77: REVOQUES | X77: PTO 02 | Y77: =SUMIFS(Cert_App_Output!$G:$G,Cert_App_Output!$E:$E,$E77,Cert_App_Output!$K:$K,$X77) -> 0.5
A78: Albañilería MT | B78: - | C78: - | D78: Albañilería MO | E78: 7.08 | F78: OK | G78: Revoque Grueso Impermeable Interior b/ revestimiento | H78: m2 | I78: 670.322 | J78: 3747.8693 | K78: 0 | L78: 9136.834 | M78: 298.91474 | N78: =SUM(J78:M78) -> 13183.618 | O78: =IF($N78=0,$S78,J78/$N78*$S78) -> 4710.8421 | P78: =IF($N78=0,0,K78/$N78*$S78) -> 0 | Q78: =IF($N78=0,0,L78/$N78*$S78) -> 11484.44 | R78: =IF($N78=0,0,M78/$N78*$S78) -> 375.71751 | S78: 16571 | T78: =IFERROR(S78/N78,"") -> 1.2569387 | U78: =N78*I78 -> 8837269.2 | V78: =S78*I78 -> 11107906 | W78: REVOQUES | X78: PTO 02 | Y78: =SUMIFS(Cert_App_Output!$G:$G,Cert_App_Output!$E:$E,$E78,Cert_App_Output!$K:$K,$X78) -> 0.55
E79: 8 | G79: CONTRAPISOS Y CARPETAS
A80: Albañilería MT | B80: - | C80: - | D80: Albañilería MO | E80: 8.01 | F80: OK | G80: Contrapiso de cascotes en SS e: 15 cm | H80: m2 | I80: 104 | J80: 9763.519 | K80: 0 | L80: 15181.289 | M80: 451.34429 | N80: =SUM(J80:M80) -> 25396.152 | O80: =IF($N80=0,$S80,J80/$N80*$S80) -> 12271.604 | P80: =IF($N80=0,0,K80/$N80*$S80) -> 0 | Q80: =IF($N80=0,0,L80/$N80*$S80) -> 19081.109 | R80: =IF($N80=0,0,M80/$N80*$S80) -> 567.28711 | S80: 31920 | T80: =IFERROR(S80/N80,"") -> 1.2568833 | U80: =N80*I80 -> 2641199.8 | V80: =S80*I80 -> 3319680 | W80: CONTRAPISOS Y CARPETAS | X80: PTO 02 | Y80: =SUMIFS(Cert_App_Output!$G:$G,Cert_App_Output!$E:$E,$E80,Cert_App_Output!$K:$K,$X80) -> 1
A81: Albañilería MT | B81: - | C81: Albañilería MO | D81: Albañilería MO | E81: 8.02 | F81: OK | G81: Contrapiso de cascote s/terreno natural e: 20 cm - Incluye film de polietileno | H81: m2 | I81: 48 | J81: 13518.025 | K81: 500 | L81: 15181.289 | M81: 451.34429 | N81: =SUM(J81:M81) -> 29650.659 | O81: =IF($N81=0,$S81,J81/$N81*$S81) -> 16990.846 | P81: =IF($N81=0,0,K81/$N81*$S81) -> 628.45147 | Q81: =IF($N81=0,0,L81/$N81*$S81) -> 19081.407 | R81: =IF($N81=0,0,M81/$N81*$S81) -> 567.29597 | S81: 37268 | T81: =IFERROR(S81/N81,"") -> 1.2569029 | U81: =N81*I81 -> 1423231.6 | V81: =S81*I81 -> 1788864 | W81: CONTRAPISOS Y CARPETAS | X81: PTO 02 | Y81: =SUMIFS(Cert_App_Output!$G:$G,Cert_App_Output!$E:$E,$E81,Cert_App_Output!$K:$K,$X81) -> 0
A82: Albañilería MT | B82: - | C82: - | D82: Albañilería MO | E82: 8.03 | F82: OK | G82: Contrapiso de cascotes en azoteas c/pendiente e: 15 cm | H82: m2 | I82: 235 | J82: 11716.223 | K82: 0 | L82: 13663.16 | M82: 406.20986 | N82: =SUM(J82:M82) -> 25785.593 | O82: =IF($N82=0,$S82,J82/$N82*$S82) -> 14726.161 | P82: =IF($N82=0,0,K82/$N82*$S82) -> 0 | Q82: =IF($N82=0,0,L82/$N82*$S82) -> 17173.273 | R82: =IF($N82=0,0,M82/$N82*$S82) -> 510.56657 | S82: 32410 | T82: =IFERROR(S82/N82,"") -> 1.2569034 | U82: =N82*I82 -> 6059614.3 | V82: =S82*I82 -> 7616350 | W82: CONTRAPISOS Y CARPETAS | X82: PTO 02 | Y82: =SUMIFS(Cert_App_Output!$G:$G,Cert_App_Output!$E:$E,$E82,Cert_App_Output!$K:$K,$X82) -> 0
A83: Albañilería MT | B83: - | C83: - | D83: Albañilería MO | E83: 8.04 | F83: OK | G83: Contrapiso - Carpeta monolitico e: 7 cm | H83: m2 | I83: 878 | J83: 6431.8162 | K83: 0 | L83: 8572.2517 | M83: 116.90258 | N83: =SUM(J83:M83) -> 15120.97 | O83: =IF($N83=0,$S83,J83/$N83*$S83) -> 8084.3421 | P83: =IF($N83=0,0,K83/$N83*$S83) -> 0 | Q83: =IF($N83=0,0,L83/$N83*$S83) -> 10774.72 | R83: =IF($N83=0,0,M83/$N83*$S83) -> 146.93835 | S83: 19006 | T83: =IFERROR(S83/N83,"") -> 1.2569299 | U83: =N83*I83 -> 13276212 | V83: =S83*I83 -> 16687268 | W83: CONTRAPISOS Y CARPETAS | X83: PTO 02 | Y83: =SUMIFS(Cert_App_Output!$G:$G,Cert_App_Output!$E:$E,$E83,Cert_App_Output!$K:$K,$X83) -> 0.05
A84: Albañilería MT | B84: - | C84: - | D84: Albañilería MO | E84: 8.05 | F84: OK | G84: Carpeta en PB y balcones, baños y azoteas e: 3,00 cm | H84: m2 | I84: 564 | J84: 3180.0905 | K84: 0 | L84: 6505.5637 | M84: 210.62734 | N84: =SUM(J84:M84) -> 9896.2815 | O84: =IF($N84=0,$S84,J84/$N84*$S84) -> 3997.1727 | P84: =IF($N84=0,0,K84/$N84*$S84) -> 0 | Q84: =IF($N84=0,0,L84/$N84*$S84) -> 8177.0821 | R84: =IF($N84=0,0,M84/$N84*$S84) -> 264.74524 | S84: 12439 | T84: =IFERROR(S84/N84,"") -> 1.2569368 | U84: =N84*I84 -> 5581502.8 | V84: =S84*I84 -> 7015596 | W84: CONTRAPISOS Y CARPETAS | X84: PTO 02 | Y84: =SUMIFS(Cert_App_Output!$G:$G,Cert_App_Output!$E:$E,$E84,Cert_App_Output!$K:$K,$X84) -> 0
A85: Albañilería MT | B85: - | C85: - | D85: Albañilería MO | E85: 8.06 | F85: OK | G85: Carpeta sobre membrana | H85: m2 | I85: 438 | J85: 3180.0905 | K85: 0 | L85: 6505.5637 | M85: 210.62734 | N85: =SUM(J85:M85) -> 9896.2815 | O85: =IF($N85=0,$S85,J85/$N85*$S85) -> 3997.1727 | P85: =IF($N85=0,0,K85/$N85*$S85) -> 0 | Q85: =IF($N85=0,0,L85/$N85*$S85) -> 8177.0821 | R85: =IF($N85=0,0,M85/$N85*$S85) -> 264.74524 | S85: 12439 | T85: =IFERROR(S85/N85,"") -> 1.2569368 | U85: =N85*I85 -> 4334571.3 | V85: =S85*I85 -> 5448282 | W85: CONTRAPISOS Y CARPETAS | X85: PTO 02 | Y85: =SUMIFS(Cert_App_Output!$G:$G,Cert_App_Output!$E:$E,$E85,Cert_App_Output!$K:$K,$X85) -> 0
A86: Albañilería MT | B86: - | C86: - | D86: Albañilería MO | E86: 8.07 | F86: OK | G86: Banquinas para cocinas | H86: gl | I86: 1 | J86: 1076227.7 | K86: 0 | L86: 826143.61 | M86: 28535.569 | N86: =SUM(J86:M86) -> 1930906.8 | O86: =IF($N86=0,$S86,J86/$N86*$S86) -> 1352692.3 | P86: =IF($N86=0,0,K86/$N86*$S86) -> 0 | Q86: =IF($N86=0,0,L86/$N86*$S86) -> 1038365.9 | R86: =IF($N86=0,0,M86/$N86*$S86) -> 35865.872 | S86: 2426924 | T86: =IFERROR(S86/N86,"") -> 1.256883 | U86: =N86*I86 -> 1930906.8 | V86: =S86*I86 -> 2426924 | W86: CONTRAPISOS Y CARPETAS | X86: PTO 02 | Y86: =SUMIFS(Cert_App_Output!$G:$G,Cert_App_Output!$E:$E,$E86,Cert_App_Output!$K:$K,$X86) -> 0.05
A87: Albañilería MT | B87: - | C87: - | D87: Albañilería MO | E87: 8.08 | F87: OK | G87: Banquinas para bombas y tanques en SB | H87: gl | I87: 1 | J87: 215055.5 | K87: 0 | L87: 165228.72 | M87: 5704.2633 | N87: =SUM(J87:M87) -> 385988.48 | O87: =IF($N87=0,$S87,J87/$N87*$S87) -> 270299.95 | P87: =IF($N87=0,0,K87/$N87*$S87) -> 0 | Q87: =IF($N87=0,0,L87/$N87*$S87) -> 207673.45 | R87: =IF($N87=0,0,M87/$N87*$S87) -> 7169.601 | S87: 485143 | T87: =IFERROR(S87/N87,"") -> 1.2568847 | U87: =N87*I87 -> 385988.48 | V87: =S87*I87 -> 485143 | W87: CONTRAPISOS Y CARPETAS | X87: PTO 02 | Y87: =SUMIFS(Cert_App_Output!$G:$G,Cert_App_Output!$E:$E,$E87,Cert_App_Output!$K:$K,$X87) -> 0
E88: 9 | G88: ESCALERAS
A89: Albañilería MT | B89: - | C89: - | D89: Albañilería MO | E89: 9.01 | F89: OK | G89: Cemento alisado arrodillado en escaleras | H89: gl | I89: 1 | J89: 203505.44 | K89: 0 | L89: 1383533.8 | M89: 23805.589 | N89: =SUM(J89:M89) -> 1610844.9 | O89: =IF($N89=0,$S89,J89/$N89*$S89) -> 255782.47 | P89: =IF($N89=0,0,K89/$N89*$S89) -> 0 | Q89: =IF($N89=0,0,L89/$N89*$S89) -> 1738939.7 | R89: =IF($N89=0,0,M89/$N89*$S89) -> 29920.833 | S89: 2024643 | T89: =IFERROR(S89/N89,"") -> 1.2568827 | U89: =N89*I89 -> 1610844.9 | V89: =S89*I89 -> 2024643 | W89: ESCALERAS | X89: PTO 02 | Y89: =SUMIFS(Cert_App_Output!$G:$G,Cert_App_Output!$E:$E,$E89,Cert_App_Output!$K:$K,$X89) -> 0
A90: Albañilería MT | B90: - | C90: - | D90: Albañilería MO | E90: 9.02 | F90: OK | G90: Provisión nariz escalera, hierro angulo 5/8 x 1/8" | H90: ml | I90: 122 | J90: 2447.0972 | K90: 0 | L90: 12299.733 | M90: 221.20245 | N90: =SUM(J90:M90) -> 14968.033 | O90: =IF($N90=0,$S90,J90/$N90*$S90) -> 3075.8676 | P90: =IF($N90=0,0,K90/$N90*$S90) -> 0 | Q90: =IF($N90=0,0,L90/$N90*$S90) -> 15460.093 | R90: =IF($N90=0,0,M90/$N90*$S90) -> 278.03941 | S90: 18814 | T90: =IFERROR(S90/N90,"") -> 1.2569454 | U90: =N90*I90 -> 1826100 | V90: =S90*I90 -> 2295308 | W90: ESCALERAS | X90: PTO 02 | Y90: =SUMIFS(Cert_App_Output!$G:$G,Cert_App_Output!$E:$E,$E90,Cert_App_Output!$K:$K,$X90) -> 0
A91: Albañilería MT | B91: - | C91: - | D91: Albañilería MO | E91: 9.03 | F91: OK | G91: Zócalo de concreto | H91: ml | I91: 155 | J91: 758.10738 | K91: 0 | L91: 3395.9551 | M91: 122.76855 | N91: =SUM(J91:M91) -> 4276.831 | O91: =IF($N91=0,$S91,J91/$N91*$S91) -> 952.94512 | P91: =IF($N91=0,0,K91/$N91*$S91) -> 0 | Q91: =IF($N91=0,0,L91/$N91*$S91) -> 4268.7341 | R91: =IF($N91=0,0,M91/$N91*$S91) -> 154.32074 | S91: 5376 | T91: =IFERROR(S91/N91,"") -> 1.2570055 | U91: =N91*I91 -> 662908.81 | V91: =S91*I91 -> 833280 | W91: ESCALERAS | X91: PTO 02 | Y91: =SUMIFS(Cert_App_Output!$G:$G,Cert_App_Output!$E:$E,$E91,Cert_App_Output!$K:$K,$X91) -> 0
A92: Albañilería MT | B92: - | C92: - | D92: Albañilería MO | E92: 9.04 | F92: OK | G92: Provisión y colocación de Rodapie/ Zócalo rampante en placa cementicia | H92: ml | I92: 31.2 | J92: 7086.2111 | K92: 0 | L92: 10591.585 | M92: 265.16694 | N92: =SUM(J92:M92) -> 17942.963 | O92: =IF($N92=0,$S92,J92/$N92*$S92) -> 7795.1248 | P92: =IF($N92=0,0,K92/$N92*$S92) -> 0 | Q92: =IF($N92=0,0,L92/$N92*$S92) -> 11651.181 | R92: =IF($N92=0,0,M92/$N92*$S92) -> 291.69458 | S92: 19738 | T92: =IFERROR(S92/N92,"") -> 1.1000413 | U92: =N92*I92 -> 559820.44 | V92: =S92*I92 -> 615825.6 | W92: ESCALERAS | X92: PTO 02 | Y92: =SUMIFS(Cert_App_Output!$G:$G,Cert_App_Output!$E:$E,$E92,Cert_App_Output!$K:$K,$X92) -> 0
E93: 10 | G93: VENTILACIONES
A94: Albañilería MT | B94: - | C94: - | D94: - | E94: 10.01 | F94: OK | G94: Ventilación Conducto Humos. Incluye toma de aire en PB - No aplica s/proyecto | H94: gl | I94: 0 | J94: 0 | K94: 0 | L94: 0 | M94: 0 | N94: =SUM(J94:M94) -> 0 | O94: =IF($N94=0,$S94,J94/$N94*$S94) -> 0 | P94: =IF($N94=0,0,K94/$N94*$S94) -> 0 | Q94: =IF($N94=0,0,L94/$N94*$S94) -> 0 | R94: =IF($N94=0,0,M94/$N94*$S94) -> 0 | S94: 0 | T94: =IFERROR(S94/N94,"") | U94: =N94*I94 -> 0 | V94: =S94*I94 -> 0 | W94: VENTILACIONES | X94: PTO 02 | Y94: =SUMIFS(Cert_App_Output!$G:$G,Cert_App_Output!$E:$E,$E94,Cert_App_Output!$K:$K,$X94) -> 0
A95: Albañilería MT | B95: - | C95: Albañilería MO | D95: - | E95: 10.02 | F95: OK | G95: Ventilación Baños - En caño Ø 110 | H95: gl | I95: 1 | J95: 700000 | K95: 1050000 | L95: 0 | M95: 0 | N95: =SUM(J95:M95) -> 1750000 | O95: =IF($N95=0,$S95,J95/$N95*$S95) -> 879818 | P95: =IF($N95=0,0,K95/$N95*$S95) -> 1319727 | Q95: =IF($N95=0,0,L95/$N95*$S95) -> 0 | R95: =IF($N95=0,0,M95/$N95*$S95) -> 0 | S95: 2199545 | T95: =IFERROR(S95/N95,"") -> 1.2568829 | U95: =N95*I95 -> 1750000 | V95: =S95*I95 -> 2199545 | W95: VENTILACIONES | X95: PTO 02 | Y95: =SUMIFS(Cert_App_Output!$G:$G,Cert_App_Output!$E:$E,$E95,Cert_App_Output!$K:$K,$X95) -> 0.85
A96: Albañilería MT | B96: - | C96: - | D96: - | E96: 10.03 | F96: OK | G96: Colocación de rejillas de inyección y extracción - No aplica s/proyecto | H96: un | I96: 0 | J96: 0 | K96: 0 | L96: 0 | M96: 0 | N96: =SUM(J96:M96) -> 0 | O96: =IF($N96=0,$S96,J96/$N96*$S96) -> 0 | P96: =IF($N96=0,0,K96/$N96*$S96) -> 0 | Q96: =IF($N96=0,0,L96/$N96*$S96) -> 0 | R96: =IF($N96=0,0,M96/$N96*$S96) -> 0 | S96: 0 | T96: =IFERROR(S96/N96,"") | U96: =N96*I96 -> 0 | V96: =S96*I96 -> 0 | W96: VENTILACIONES | X96: PTO 02 | Y96: =SUMIFS(Cert_App_Output!$G:$G,Cert_App_Output!$E:$E,$E96,Cert_App_Output!$K:$K,$X96) -> 0
A97: Albañilería MT | B97: - | C97: Albañilería MO | D97: - | E97: 10.04 | F97: OK | G97: Sombreretes en chapa prepintada C25 | H97: u | I97: 7 | J97: 225038.88 | K97: 55670.194 | L97: -1.7e-05 | M97: 0 | N97: =SUM(J97:M97) -> 280709.07 | O97: =IF($N97=0,$S97,J97/$N97*$S97) -> 282847.97 | P97: =IF($N97=0,0,K97/$N97*$S97) -> 69971.028 | Q97: =IF($N97=0,0,L97/$N97*$S97) -> -2.1367044e-05 | R97: =IF($N97=0,0,M97/$N97*$S97) -> 0 | S97: 352819 | T97: =IFERROR(S97/N97,"") -> 1.2568849 | U97: =N97*I97 -> 1964963.5 | V97: =S97*I97 -> 2469733 | W97: VENTILACIONES | X97: PTO 02 | Y97: =SUMIFS(Cert_App_Output!$G:$G,Cert_App_Output!$E:$E,$E97,Cert_App_Output!$K:$K,$X97) -> 0
E98: 11 | G98: PISOS - PROVISION A CARGO DEL COMITENTE
A99: Revestimiento MT | B99: - | C99: - | D99: Revestimiento MO | E99: 11.01 | F99: OK | G99: Colocación de travertino en hall PB - Provisión a cargo del comitente | H99: m2 | I99: 30 | J99: 7250.1087 | K99: 0 | L99: 9992.0862 | M99: 219.89813 | N99: =SUM(J99:M99) -> 17462.093 | O99: =IF($N99=0,$S99,J99/$N99*$S99) -> 9112.6181 | P99: =IF($N99=0,0,K99/$N99*$S99) -> 0 | Q99: =IF($N99=0,0,L99/$N99*$S99) -> 12558.993 | R99: =IF($N99=0,0,M99/$N99*$S99) -> 276.38864 | S99: 21948 | T99: =IFERROR(S99/N99,"") -> 1.256894 | U99: =N99*I99 -> 523862.79 | V99: =S99*I99 -> 658440 | W99: PISOS - PROVISION A CARGO DEL COMITENTE | X99: PTO 02 | Y99: =SUMIFS(Cert_App_Output!$G:$G,Cert_App_Output!$E:$E,$E99,Cert_App_Output!$K:$K,$X99) -> 0
A100: Revestimiento MT | B100: - | C100: - | D100: Revestimiento MO | E100: 11.02 | F100: OK | G100: Colocación de porcelanato en paliers, terraza y espacios comunes - Provisión a cargo del comitente | H100: m2 | I100: 185 | J100: 7250.1087 | K100: 0 | L100: 9992.0862 | M100: 219.89813 | N100: =SUM(J100:M100) -> 17462.093 | O100: =IF($N100=0,$S100,J100/$N100*$S100) -> 9112.6181 | P100: =IF($N100=0,0,K100/$N100*$S100) -> 0 | Q100: =IF($N100=0,0,L100/$N100*$S100) -> 12558.993 | R100: =IF($N100=0,0,M100/$N100*$S100) -> 276.38864 | S100: 21948 | T100: =IFERROR(S100/N100,"") -> 1.256894 | U100: =N100*I100 -> 3230487.2 | V100: =S100*I100 -> 4060380 | W100: PISOS - PROVISION A CARGO DEL COMITENTE | X100: PTO 02 | Y100: =SUMIFS(Cert_App_Output!$G:$G,Cert_App_Output!$E:$E,$E100,Cert_App_Output!$K:$K,$X100) -> 0
A101: Revestimiento MT | B101: - | C101: - | D101: Revestimiento MO | E101: 11.03 | F101: OK | G101: Colocación de porcelanato en UF - Provisión a cargo del comitente | H101: m2 | I101: 942 | J101: 7250.1087 | K101: 0 | L101: 9992.0862 | M101: 219.89813 | N101: =SUM(J101:M101) -> 17462.093 | O101: =IF($N101=0,$S101,J101/$N101*$S101) -> 9112.6181 | P101: =IF($N101=0,0,K101/$N101*$S101) -> 0 | Q101: =IF($N101=0,0,L101/$N101*$S101) -> 12558.993 | R101: =IF($N101=0,0,M101/$N101*$S101) -> 276.38864 | S101: 21948 | T101: =IFERROR(S101/N101,"") -> 1.256894 | U101: =N101*I101 -> 16449292 | V101: =S101*I101 -> 20675016 | W101: PISOS - PROVISION A CARGO DEL COMITENTE | X101: PTO 02 | Y101: =SUMIFS(Cert_App_Output!$G:$G,Cert_App_Output!$E:$E,$E101,Cert_App_Output!$K:$K,$X101) -> 0
A102: Revestimiento MT | B102: - | C102: - | D102: Revestimiento MO | E102: 11.04 | F102: OK | G102: Colocación de porcelanato en baños - Provisión a cargo del comitente | H102: m2 | I102: 110 | J102: 7250.1087 | K102: 0 | L102: 12989.712 | M102: 285.86757 | N102: =SUM(J102:M102) -> 20525.688 | O102: =IF($N102=0,$S102,J102/$N102*$S102) -> 9112.7543 | P102: =IF($N102=0,0,K102/$N102*$S102) -> 0 | Q102: =IF($N102=0,0,L102/$N102*$S102) -> 16326.935 | R102: =IF($N102=0,0,M102/$N102*$S102) -> 359.3106 | S102: 25799 | T102: =IFERROR(S102/N102,"") -> 1.2569128 | U102: =N102*I102 -> 2257825.7 | V102: =S102*I102 -> 2837890 | W102: PISOS - PROVISION A CARGO DEL COMITENTE | X102: PTO 02 | Y102: =SUMIFS(Cert_App_Output!$G:$G,Cert_App_Output!$E:$E,$E102,Cert_App_Output!$K:$K,$X102) -> 0
A103: Revestimiento MT | B103: - | C103: - | D103: Revestimiento MO | E103: 11.05 | F103: OK | G103: Provisión y ejecución de alisado de cemento rodillado | H103: m2 | I103: 128 | J103: 3816.1086 | K103: 0 | L103: 8702.6232 | M103: 274.73131 | N103: =SUM(J103:M103) -> 12793.463 | O103: =IF($N103=0,$S103,J103/$N103*$S103) -> 4796.436 | P103: =IF($N103=0,0,K103/$N103*$S103) -> 0 | Q103: =IF($N103=0,0,L103/$N103*$S103) -> 10938.256 | R103: =IF($N103=0,0,M103/$N103*$S103) -> 345.30755 | S103: 16080 | T103: =IFERROR(S103/N103,"") -> 1.2568919 | U103: =N103*I103 -> 1637563.3 | V103: =S103*I103 -> 2058240 | W103: PISOS - PROVISION A CARGO DEL COMITENTE | X103: PTO 02 | Y103: =SUMIFS(Cert_App_Output!$G:$G,Cert_App_Output!$E:$E,$E103,Cert_App_Output!$K:$K,$X103) -> 0
A104: Revestimiento MT | B104: - | C104: - | D104: Revestimiento MO | E104: 11.06 | F104: OK | G104: Colocación de baldoson de vereda - Provisión a cargo del comitente | H104: m2 | I104: 48 | J104: 7250.1087 | K104: 0 | L104: 9992.0862 | M104: 219.89813 | N104: =SUM(J104:M104) -> 17462.093 | O104: =IF($N104=0,$S104,J104/$N104*$S104) -> 9112.6181 | P104: =IF($N104=0,0,K104/$N104*$S104) -> 0 | Q104: =IF($N104=0,0,L104/$N104*$S104) -> 12558.993 | R104: =IF($N104=0,0,M104/$N104*$S104) -> 276.38864 | S104: 21948 | T104: =IFERROR(S104/N104,"") -> 1.256894 | U104: =N104*I104 -> 838180.46 | V104: =S104*I104 -> 1053504 | W104: PISOS - PROVISION A CARGO DEL COMITENTE | X104: PTO 02 | Y104: =SUMIFS(Cert_App_Output!$G:$G,Cert_App_Output!$E:$E,$E104,Cert_App_Output!$K:$K,$X104) -> 0
A105: Revestimiento MT | B105: - | C105: Revestimiento MO | D105: Revestimiento MO | E105: 11.07 | F105: OK | G105: Provisión y ejecución de pavimento e: 18 cm, incluye malla Q188 | H105: m2 | I105: 226 | J105: 44376.422 | K105: 1659.2925 | L105: 11877.483 | M105: 868.69795 | N105: =SUM(J105:M105) -> 58781.895 | O105: =IF($N105=0,$S105,J105/$N105*$S105) -> 55775.997 | P105: =IF($N105=0,0,K105/$N105*$S105) -> 2085.5375 | Q105: =IF($N105=0,0,L105/$N105*$S105) -> 14928.613 | R105: =IF($N105=0,0,M105/$N105*$S105) -> 1091.8522 | S105: 73882 | T105: =IFERROR(S105/N105,"") -> 1.2568836 | U105: =N105*I105 -> 13284708 | V105: =S105*I105 -> 16697332 | W105: PISOS - PROVISION A CARGO DEL COMITENTE | X105: PTO 02 | Y105: =SUMIFS(Cert_App_Output!$G:$G,Cert_App_Output!$E:$E,$E105,Cert_App_Output!$K:$K,$X105) -> 1
...

Sheet 1_GGBB
H2: 45590 | O2: 22
F3: MESES | G3: DÓLAR BNA | H3: DÓLAR MEP | M3: Descrip | N3: Mes | O3: Total Dias
B4: GASTOS GENERALES y BENEFICIO | F4: 14 | G4: 1005 | H4: 1170 | M4: Prelim | N4: 0.75 | O4: =+N4*$O$2 -> 16.5 | Q4: Syh permanente
M5: Mov de suelos y excav. + micro | N5: 2.5 | O5: =+N5*$O$2 -> 55 | Q5: =+ROUNDUP(SUM(N4:N5),0) -> 4
B6: Gastos Grales de obra en items | C6: U | D6: Cant | F6: Precio Unit | G6: Subtotal | H6: =SUM(G7:G10) -> 0 | M6: Fundac | N6: 0 | O6: =+N6*$O$2 -> 0
B7: Oficina en obra (6x3 c/AA) | C7: mes | D7: =+$F$4 -> 14 | E7: 0 | F7: =E7*I7+J7 -> 0 | G7: =+F7*D7*E7 -> 0 | M7: Losa sobre PB | N7: 1 | O7: =+N7*$O$2 -> 22
B8: Obrador 6x3 s/AA | C8: mes | D8: =+$F$4 -> 14 | E8: 0 | F8: =E8*I8+J8 -> 0 | G8: =+F8*D8*E8 -> 0 | M8: Losa sobre 1 | N8: 1 | O8: =+N8*$O$2 -> 22
B9: Pañol (6x3) | C9: mes | D9: =+$F$4 -> 14 | E9: 1 | F9: =E9*I9+J9 -> 0 | G9: =+F9*D9*E9 -> 0 | M9: Losa sobre 2 | N9: 0.75 | O9: =+N9*$O$2 -> 16.5
B10: Baños | C10: mes | D10: =+$F$4 -> 14 | E10: 2 | F10: =E10*I10+J10 -> 0 | G10: =+F10*D10*E10 -> 0 | M10: Losa sobre 3 | N10: 0.75 | O10: =+N10*$O$2 -> 16.5 | P10: Inicio mamposteria
B11: Gastos Grales de obra en items | H11: =SUM(G12:G18) -> 16192179 | M11: Losa sobre 4 | N11: 0.75 | O11: =+N11*$O$2 -> 16.5 | Q11: Meses H° | R11: Estacionamiento en contramano
B12: HyS permanente | C12: mes | D12: 4 | E12: 1 | G12: =+F12*D12*E12 -> 0 | J12: 2578960.6 | K12: =+J12*D12*E12 -> 10315842 | M12: Techo escalera y sobrerecorrido | N12: 0.5 | O12: =+N12*$O$2 -> 11 | Q12: =+SUM(N4:N12) -> 8 | R12: =+Q12/2 -> 4
B13: HyS | C13: mes | D13: =+$F$4 -> 14 | E13: 1 | G13: =+F13*D13*E13 -> 0 | J13: 150000 | K13: =+J13*D13*E13 -> 2100000 | M13: Mampostería | N13: 2 | O13: =+N13*$O$2 -> 44
B14: Energía de obra | C14: mes | D14: =+F4 -> 14 | E14: 0.5 | F14: 200000 | G14: =+F14*D14*E14 -> 1400000 | I14: =+G14/$H$4 -> 1196.5812 | M14: Revoques, contrap y carp | N14: 2 | O14: =+N14*$O$2 -> 44 | P14: =+SUM(N13:N14) -> 4
B15: Agua de obra | C15: mes | D15: =+$F$4 -> 14 | E15: 1 | F15: 25000 | G15: =+F15*D15*E15 -> 350000 | M15: Amures | N15: 0 | O15: =+N15*$O$2 -> 0
B16: Alquiler cerco de obra chapa | C16: mes | D16: =+$F$4 -> 14 | E16: 0 | F16: 10000 | G16: =+F16*D16*E16 -> 0 | M16: Colocación | N16: 2 | O16: =+N16*$O$2 -> 44
B17: Proyecto Ejecutivo | C17: mes | D17: =+$F$4 -> 14 | E17: 0 | F17: 2578960.6 | G17: =+F17*D17*E17 -> 0 | M17: Pintura | N17: 2 | O17: =+N17*$O$2 -> 44
B18: Proyecto (50%) | C18: mes | D18: =+$F$4 -> 14 | E18: 0.4 | F18: 2578960.6 | G18: =+F18*D18*E18 -> 14442179 | I18: =+G18/$H$4 -> 12343.743 | M18: Terminaciones | N18: 0 | O18: =+L18*$O$2 -> 0
B19: Gastos Directos | H19: =SUM(G20:G30) -> 38913603 | N19: =SUM(N4:N18) -> 16 | O19: =SUM(O4:O18) -> 352
B20: Coordinacion de obra | C20: mes | D20: =+$F$4 -> 14 | E20: 0.15 | F20: 4680364.1 | G20: =+F20*D20*E20 -> 9828764.6 | I20: =+G20/$H$4 -> 8400.6535
B21: Jefe de obra | C21: mes | D21: =+$F$4 -> 14 | E21: 1 | G21: =+F21*D21*E21 -> 0 | J21: 3798370.6 | K21: =+J21*D21*E21 -> 53177188
B22: Sobrestante | C22: mes | D22: =+$F$4 -> 14 | E22: 0 | F22: 2578960.6 | G22: =+F22*D22*E22 -> 0
B23: Administrativo en obra | C23: mes | D23: =+$F$4 -> 14 | E23: 0 | F23: =+F22 -> 2578960.6 | G23: =+F23*D23*E23 -> 0
B24: Capataz | C24: mes | D24: =+$F$4 -> 14 | E24: 0.5 | F24: 3154977 | G24: =+F24*D24*E24 -> 22084839 | I24: =+G24/$H$4 -> 18875.931
B25: Logistica | C25: mes | D25: =+$F$4 -> 14 | E25: 0.5 | F25: 500000 | G25: =+F25*D25*E25 -> 3500000 | I25: =+G25/$H$4 -> 2991.453
B26: Vehiculo obra | C26: mes | D26: =+$F$4 -> 14 | E26: 0.5 | F26: =F25 -> 500000 | G26: =+F26*D26*E26 -> 3500000 | I26: =+G26/$H$4 -> 2991.453
B27: Mov y viaticos | C27: mes | D27: =+$F$4 -> 14 | E27: 1 | G27: =+F27*D27*E27 -> 0 | J27: =F25 -> 500000 | K27: =+J27*D27*E27 -> 7000000
B28: UOCRA | C28: mes | D28: =+$F$4 -> 14 | E28: 1 | G28: =+F28*D28*E28 -> 0
B29: Pañolero/Sereno | C29: mes | D29: =+$F$4 -> 14 | E29: 1 | J29: 1198421.7 | K29: =+J29*D29*E29 -> 16777904
B31: Equipos | H31: =SUM(G32:G40) -> 0
B32: Bobcat | C32: mes | D32: 0 | F32: 130000 | G32: =+F32*D32 -> 0
B33: Camion limpieza | C33: mes | D33: 0 | F33: 100000 | G33: =+F33*D33 -> 0
B34: Tijera electrica 12 | C34: mes | F34: 33600 | G34: =+F34*D34 -> 0
B35: JLG | C35: mes | F35: 89000 | G35: =+F35*D35 -> 0
B36: Grua 20ton | C36: mes | F36: 70000 | G36: =+F36*D36 -> 0
B41: Gastos Indirectos | H41: =SUM(G42:G47) -> 58713324
B42: Admin (50%Compras - 50%RRHH) | C42: mes | D42: =+$F$4 -> 14 | E42: 0.5 | F42: 2578960.6 | G42: =+F42*D42*E42 -> 18052724 | I42: =+G42/$H$4 -> 15429.679
B43: Seguros | C43: gl | D43: =+D42 -> 14 | E43: 1 | F43: 250000 | G43: =+F43*D43 -> 3500000 | I43: =+G43/$H$4 -> 2991.453
B44: IIBB (monto venta obra gris) | C44: gl | D44: 0.04 | E44: 0.6 | F44: 1145000000 | G44: =+F44*D44*E44 -> 27480000 | I44: =+G44/$H$4 -> 23487.179
B45: Imp cheque | C45: gl | D45: =1.2/100 -> 0.012 | E45: =+E44 -> 0.6 | F45: =+F44*1.15 -> 1316750000 | G45: =+F45*D45*E45 -> 9480600 | I45: =+G45/$H$4 -> 8103.0769
B46: Contrato | C46: gl | D46: 1 | E46: 1 | F46: 200000 | G46: =+F46*D46*E46 -> 200000 | I46: =+G46/$H$4 -> 170.94017
G48: =SUM(G7:G47) -> 1.1381911e+08 | H48: =SUM(H6:H47) -> 1.1381911e+08 | I48: =SUM(I6:I47) -> 96982.142 | K48: =SUM(K6:K47) -> 89370934 | L48: =+K48+G64 -> 3.1980562e+08 | M48: =+L48/N19 -> 19987851
B49: Monto puesto en Ayuda de gremio que no se eroga
B50: Total de Gastos Generales | G50: =+G49+H48 -> 1.1381911e+08
B52: Otro | G52: 1.5263579e+08 | I52: =+G52/$H$4 -> 130457.94
B53: Corralon | G53: 89943825 | I53: =+G53/$H$4 -> 76875.064
B54: Subcontratos | G54: 4.6615773e+08 | I54: =+G54/$H$4 -> 398425.41
B55: Mano de obra | G55: 1.677708e+08 | I55: =+G55/$H$4 -> 143393.85
B56: Equipos | G56: 20534738 | I56: =+G56/$H$4 -> 17551.058
A58: A | G58: =SUM(G52:G57) -> 8.9704289e+08 | I58: =SUM(I52:I57) -> 766703.32
B60: GG | F60: =+G50/G58 -> 0.12688257 | G60: =+F60*$G$58 -> 1.1381911e+08 | I60: =+G60/$H$4 -> 97281.288
B61: Equipos | E61: 3 | F61: 0 | G61: =+F61*$G$58 -> 0 | I61: =+G61/$H$4 -> 0
B62: Imprevistos + Negciacion | E62: 5 | F62: 0.03 | G62: =+F62*$G$58 -> 26911287 | I62: =+G62/$H$4 -> 23001.1 | L62: 987276976
B63: Beneficio | E63: 9 | F63: 0.1 | G63: =+F63*$G$58 -> 89704289 | I63: =+G63/$H$4 -> 76670.332 | L63: 1.1274028e+09
A64: B | F64: =SUM(F60:F63) -> 0.25688257 | G64: =SUM(G60:G63) -> 2.3043468e+08 | I64: =+G64/$H$4 -> 196952.72 | L64: =+L63-L62 -> 1.4012578e+08
A66: K | F66: =1+F64 -> 1.2568826 | G66: =+G58*F66 -> 1.1274776e+09
L67: 1.1381953e+09
A68: A+B | G68: =+G58+G64 -> 1.1274776e+09 | I68: =+G68/$H$4 -> 963656.04
F70: =+G71/G58 -> 0.033443217
F71: =+G71/G66 -> 0.026608068 | G71: 30000000
I72: =+I63+I62+I20 -> 108072.09

Sheet 2_Movimientos
A1: Cuenta | B1: Desc Cuenta | C1: Fecha Asiento | D1: Nº Asiento | E1: Observaciones | F1: Cliente/Proveedor | G1: Cód Comprobante | H1: Nº Comprobante | I1: Debe | J1: Haber | K1: Unidad | L1: Desc Unidad | M1: Centro de Costo | N1: Desc Centro Costo | O1: Saldo Inicial | P1: Observaciones original | Q1: mov_id | R1: mov_tipo
A2: 410222 | B2: Obra civil Reforma | C2: 45964 | D2: 4 | E2: Obras - SVD HOUSE S.R.L. | F2: SVD HOUSE S.R.L. | G2: FAWS | H2: 300000760 | I2: 0 | J2: 15000000 | K2: DESA | L2: Desarrollos | M2: SALVA4140 | N2: El Salvador 4140
A3: 410222 | B3: Obra civil Reforma | C3: 45964 | D3: 4 | E3: Obras - SVD HOUSE S.R.L. | F3: SVD HOUSE S.R.L. | G3: FAWS | H3: 300000760 | I3: 0 | J3: 5000000 | K3: DESA | L3: Desarrollos | M3: SALVA4140 | N3: El Salvador 4140
A4: 410222 | B4: Obra civil Reforma | C4: 46009 | D4: 489 | E4: Obras - SVD HOUSE S.R.L. | F4: SVD HOUSE S.R.L. | G4: FAWS | H4: 300000783 | I4: 0 | J4: 13000000 | K4: DESA | L4: Desarrollos | M4: SALVA4140 | N4: El Salvador 4140
A5: 410222 | B5: Obra civil Reforma | C5: 46009 | D5: 489 | E5: Obras - SVD HOUSE S.R.L. | F5: SVD HOUSE S.R.L. | G5: FAWS | H5: 300000783 | I5: 0 | J5: 3500000 | K5: DESA | L5: Desarrollos | M5: SALVA4140 | N5: El Salvador 4140
A6: 410222 | B6: Obra civil Reforma | C6: 46028 | D6: 680 | E6: Obras - SVD HOUSE S.R.L. | F6: SVD HOUSE S.R.L. | G6: FAWS | H6: 300000791 | I6: 0 | J6: 15750000 | K6: DESA | L6: Desarrollos | M6: SALVA4140 | N6: El Salvador 4140
A7: 410222 | B7: Obra civil Reforma | C7: 46028 | D7: 680 | E7: Obras - SVD HOUSE S.R.L. | F7: SVD HOUSE S.R.L. | G7: FAWS | H7: 300000791 | I7: 0 | J7: 5480000 | K7: DESA | L7: Desarrollos | M7: SALVA4140 | N7: El Salvador 4140
A8: 410222 | B8: Obra civil Reforma | C8: 46056 | D8: 1144 | E8: Obras - SVD HOUSE S.R.L. | F8: SVD HOUSE S.R.L. | G8: FAWS | H8: 300000809 | I8: 0 | J8: 20200000 | K8: DESA | L8: Desarrollos | M8: SALVA4140 | N8: El Salvador 4140
A9: 410222 | B9: Obra civil Reforma | C9: 46056 | D9: 1144 | E9: Obras - SVD HOUSE S.R.L. | F9: SVD HOUSE S.R.L. | G9: FAWS | H9: 300000809 | I9: 0 | J9: 13150000 | K9: DESA | L9: Desarrollos | M9: SALVA4140 | N9: El Salvador 4140
A10: 410222 | B10: Obra civil Reforma | C10: 46056 | D10: 1144 | E10: Obras - SVD HOUSE S.R.L. | F10: SVD HOUSE S.R.L. | G10: FAWS | H10: 300000809 | I10: 0 | J10: 4650000 | K10: DESA | L10: Desarrollos | M10: SALVA4140 | N10: El Salvador 4140
A11: 410222 | B11: Obra civil Reforma | C11: 46098 | D11: 1712 | E11: Obras - SVD HOUSE S.R.L. | F11: SVD HOUSE S.R.L. | G11: FAWS | H11: 300000831 | I11: 0 | J11: 13000000 | K11: DESA | L11: Desarrollos | M11: SALVA4140 | N11: El Salvador 4140
A12: 410222 | B12: Obra civil Reforma | C12: 46098 | D12: 1712 | E12: Obras - SVD HOUSE S.R.L. | F12: SVD HOUSE S.R.L. | G12: FAWS | H12: 300000831 | I12: 0 | J12: 5000000 | K12: DESA | L12: Desarrollos | M12: SALVA4140 | N12: El Salvador 4140
A13: 410222 | B13: Obra civil Reforma | C13: 46120 | D13: 2139 | E13: Obras - SVD HOUSE S.R.L. | F13: SVD HOUSE S.R.L. | G13: FAWS | H13: 300000846 | I13: 0 | J13: 20000000 | K13: DESA | L13: Desarrollos | M13: SALVA4140 | N13: El Salvador 4140
A14: 410222 | B14: Obra civil Reforma | C14: 46164 | D14: 2839 | E14: Obras - SVD HOUSE S.R.L. | F14: SVD HOUSE S.R.L. | G14: FAWS | H14: 300000865 | I14: 0 | J14: 29650000 | K14: DESA | L14: Desarrollos | M14: SALVA4140 | N14: El Salvador 4140
A15: 4201 | B15: Otros ingresos | C15: 45973 | D15: 23 | E15: SVD House SRL-Pto 1 Cert 8 | G15: OIXX | H15: 237 | I15: 0 | J15: 1350661 | K15: DESA | L15: Desarrollos | M15: SALVA4140 | N15: El Salvador 4140
A16: 4201 | B16: Otros ingresos | C16: 45973 | D16: 24 | E16: SVD House SRL-Pto. 2 Cert 1 | G16: OIXX | H16: 238 | I16: 0 | J16: 9792918 | K16: DESA | L16: Desarrollos | M16: SALVA4140 | N16: El Salvador 4140
A17: 4201 | B17: Otros ingresos | C17: 45995 | D17: 163 | E17: SVD House SRL | G17: OIXX | H17: 242 | I17: 0 | J17: 43800000 | K17: DESA | L17: Desarrollos | M17: SALVA4140 | N17: El Salvador 4140
A18: 4201 | B18: Otros ingresos | C18: 46037 | D18: 326 | E18: SVD House SRL - Certif. | G18: OIXX | H18: 252 | I18: 0 | J18: 30330000 | K18: DESA | L18: Desarrollos | M18: SALVA4140 | N18: El Salvador 4140
A19: 4201 | B19: Otros ingresos | C19: 46086 | D19: 672 | E19: SVD House SRL | G19: OIXX | H19: 263 | I19: 0 | J19: 27240000 | K19: DESA | L19: Desarrollos | M19: SALVA4140 | N19: El Salvador 4140
A20: 4201 | B20: Otros ingresos | C20: 46122 | D20: 937 | E20: SVD House SRL | G20: OIXX | H20: 271 | I20: 0 | J20: 35025000 | K20: DESA | L20: Desarrollos | M20: SALVA4140 | N20: El Salvador 4140
A21: 4201 | B21: Otros ingresos | C21: 46154 | D21: 1227 | E21: SVD HOUSE SRL - Certif. #7 Pto | G21: OIXX | H21: 274 | I21: 0 | J21: 56000000 | K21: DESA | L21: Desarrollos | M21: SALVA4140 | N21: El Salvador 4140
A22: 4201 | B22: Otros ingresos | C22: 46154 | D22: 1228 | E22: SVD HOUSE SRL - Certif. #2 Pto | G22: OIXX | H22: 275 | I22: 0 | J22: 1870000 | K22: DESA | L22: Desarrollos | M22: SALVA4140 | N22: El Salvador 4140
A23: 5101 | B23: Sueldos | C23: 46073 | D23: 577 | E23: Nelson Aguilera-Premio Hormigo | G23: OPXX | H23: 8598 | I23: 2199000 | J23: 0 | K23: DESA | L23: Desarrollos | M23: SALVA4140 | N23: El Salvador 4140
A24: 5108 | B24: Gastos en personal | C24: 46134 | D24: 2535 | E24: Gastos en Personales - Abrafer | F24: Abrafer S.R.L. | G24: FCA3 | H24: 1000223626 | I24: 26100 | J24: 0 | K24: DESA | L24: Desarrollos | M24: SALVA4140 | N24: El Salvador 4140
A25: 52005 | B25: Internet | C25: 45982 | D25: 218 | E25: Internet - Telecom Argentina S | F25: Telecom Argentina S.A. | G25: FCA3 | H25: 395005503422 | I25: 57041.33 | J25: 0 | K25: DESA | L25: Desarrollos | M25: SALVA4140 | N25: El Salvador 4140
A26: 52005 | B26: Internet | C26: 46012 | D26: 841 | E26: Internet - Telecom Argentina S | F26: Telecom Argentina S.A. | G26: FCA3 | H26: 395005786141 | I26: 58734.3 | J26: 0 | K26: DESA | L26: Desarrollos | M26: SALVA4140 | N26: El Salvador 4140
A27: 52005 | B27: Internet | C27: 46043 | D27: 1003 | E27: Internet - Telecom Argentina S | F27: Telecom Argentina S.A. | G27: FCA3 | H27: 395006067664 | I27: 60188.44 | J27: 0 | K27: DESA | L27: Desarrollos | M27: SALVA4140 | N27: El Salvador 4140
A28: 52005 | B28: Internet | C28: 46074 | D28: 1383 | E28: Internet - Telecom Argentina S | F28: Telecom Argentina S.A. | G28: FCA3 | H28: 395006348871 | I28: 61986.79 | J28: 0 | K28: DESA | L28: Desarrollos | M28: SALVA4140 | N28: El Salvador 4140
A29: 52005 | B29: Internet | C29: 46102 | D29: 2164 | E29: Internet - Telecom Argentina S | F29: Telecom Argentina S.A. | G29: FCA3 | H29: 395006630182 | I29: 64143.4 | J29: 0 | K29: DESA | L29: Desarrollos | M29: SALVA4140 | N29: El Salvador 4140
A30: 52005 | B30: Internet | C30: 46133 | D30: 2525 | E30: Internet - Telecom Argentina S | F30: Telecom Argentina S.A. | G30: FCA3 | H30: 395006903339 | I30: 54669.43 | J30: 0 | K30: DESA | L30: Desarrollos | M30: SALVA4140 | N30: El Salvador 4140
A31: 52101 | B31: Librería | C31: 45974 | D31: 461 | E31: LIBRERIA - D&D PAPELERA SRL | F31: D&D PAPELERA SRL | G31: TIQA | H31: 300008979 | I31: 6198.35 | J31: 0 | K31: DESA | L31: Desarrollos | M31: SALVA4140 | N31: El Salvador 4140
A32: 52103 | B32: Supermercados | C32: 45996 | D32: 162 | E32: Supermercados | G32: OPXX | H32: 8181 | I32: 150000 | J32: 0 | K32: DESA | L32: Desarrollos | M32: SALVA4140 | N32: El Salvador 4140
A33: 52103 | B33: Supermercados | C33: 46104 | D33: 1058 | E33: Supermercados | G33: OPXX | H33: 9086 | I33: 11810 | J33: 0 | K33: DESA | L33: Desarrollos | M33: SALVA4140 | N33: El Salvador 4140
A34: 52104 | B34: Aguas | C34: 45962 | D34: 15 | E34: Aguas - La Estradense SRL | F34: La Estradense SRL | G34: FCA3 | H34: 2900053162 | I34: 164600 | J34: 0 | K34: DESA | L34: Desarrollos | M34: SALVA4140 | N34: El Salvador 4140
A35: 52104 | B35: Aguas | C35: 45992 | D35: 246 | E35: Aguas - La Estradense SRL | F35: La Estradense SRL | G35: FCA3 | H35: 2900053592 | I35: 281250 | J35: 0 | K35: DESA | L35: Desarrollos | M35: SALVA4140 | N35: El Salvador 4140
A36: 52104 | B36: Aguas | C36: 46023 | D36: 700 | E36: Aguas - La Estradense SRL | F36: La Estradense SRL | G36: FCA3 | H36: 2900054002 | I36: 320400 | J36: 0 | K36: DESA | L36: Desarrollos | M36: SALVA4140 | N36: El Salvador 4140
A37: 52104 | B37: Aguas | C37: 46055 | D37: 1199 | E37: Aguas - La Estradense SRL | F37: La Estradense SRL | G37: FCA3 | H37: 2900054427 | I37: 431150 | J37: 0 | K37: DESA | L37: Desarrollos | M37: SALVA4140 | N37: El Salvador 4140
A38: 52104 | B38: Aguas | C38: 46082 | D38: 1402 | E38: Aguas - La Estradense SRL | F38: La Estradense SRL | G38: FCA3 | H38: 2900054845 | I38: 240000 | J38: 0 | K38: DESA | L38: Desarrollos | M38: SALVA4140 | N38: El Salvador 4140
A39: 52104 | B39: Aguas | C39: 46113 | D39: 2124 | E39: Aguas - La Estradense SRL | F39: La Estradense SRL | G39: FCA3 | H39: 2900055264 | I39: 291400 | J39: 0 | K39: DESA | L39: Desarrollos | M39: SALVA4140 | N39: El Salvador 4140
A40: 52104 | B40: Aguas | C40: 46143 | D40: 2604 | E40: Aguas - La Estradense SRL | F40: La Estradense SRL | G40: FCA3 | H40: 2900055674 | I40: 281750 | J40: 0 | K40: DESA | L40: Desarrollos | M40: SALVA4140 | N40: El Salvador 4140
A41: 52204 | B41: H. Seguridad e Higiene | C41: 45966 | D41: 33 | E41: Honorarios Seguridad e Higiene | F41: Petrini David Osvaldo | G41: FCA3 | H41: 300001370 | I41: 332000 | J41: 0 | K41: DESA | L41: Desarrollos | M41: SALVA4140 | N41: El Salvador 4140
A42: 52204 | B42: H. Seguridad e Higiene | C42: 45966 | D42: 33 | E42: Honorarios Seguridad e Higiene | F42: Petrini David Osvaldo | G42: FCA3 | H42: 300001370 | I42: 296000 | J42: 0 | K42: DESA | L42: Desarrollos | M42: SALVA4140 | N42: El Salvador 4140
A43: 52204 | B43: H. Seguridad e Higiene | C43: 45979 | D43: 54 | E43: David Petrini | G43: OPXX | H43: 7979 | I43: 279500 | J43: 0 | K43: DESA | L43: Desarrollos | M43: SALVA4140 | N43: El Salvador 4140
A44: 52204 | B44: H. Seguridad e Higiene | C44: 45993 | D44: 318 | E44: Honorarios Seguridad e Higiene | F44: Petrini David Osvaldo | G44: FCA3 | H44: 300001373 | I44: 339775 | J44: 0 | K44: DESA | L44: Desarrollos | M44: SALVA4140 | N44: El Salvador 4140
A45: 52204 | B45: H. Seguridad e Higiene | C45: 45995 | D45: 327 | E45: David Petrini | G45: OPXX | H45: 8348 | I45: 170400 | J45: 0 | K45: DESA | L45: Desarrollos | M45: SALVA4140 | N45: El Salvador 4140
A46: 52204 | B46: H. Seguridad e Higiene | C46: 45995 | D46: 327 | E46: David Petrini | G46: OPXX | H46: 8348 | I46: 115650 | J46: 0 | K46: DESA | L46: Desarrollos | M46: SALVA4140 | N46: El Salvador 4140
A47: 52204 | B47: H. Seguridad e Higiene | C47: 46024 | D47: 704 | E47: Honorarios Seguridad e Higiene | F47: Petrini David Osvaldo | G47: FCA3 | H47: 300001392 | I47: 348178 | J47: 0 | K47: DESA | L47: Desarrollos | M47: SALVA4140 | N47: El Salvador 4140
A48: 52204 | B48: H. Seguridad e Higiene | C48: 46045 | D48: 392 | E48: David Petrini - S&H | G48: OPXX | H48: 8416 | I48: 292600 | J48: 0 | K48: DESA | L48: Desarrollos | M48: SALVA4140 | N48: El Salvador 4140
A49: 52204 | B49: H. Seguridad e Higiene | C49: 46047 | D49: 1007 | E49: Honorarios Seguridad e Higiene | F49: Petrini Omar Daniel | G49: FC3 | H49: 300000843 | I49: 380000 | J49: 0 | K49: DESA | L49: Desarrollos | M49: SALVA4140 | N49: El Salvador 4140
A50: 52204 | B50: H. Seguridad e Higiene | C50: 46055 | D50: 1381 | E50: Honorarios Seguridad e Higiene | F50: Petrini David Osvaldo | G50: FCA3 | H50: 300001414 | I50: 358083 | J50: 0 | K50: DESA | L50: Desarrollos | M50: SALVA4140 | N50: El Salvador 4140
A51: 52204 | B51: H. Seguridad e Higiene | C51: 46079 | D51: 608 | E51: David Petrini | G51: OPXX | H51: 8626 | I51: 300918 | J51: 0 | K51: DESA | L51: Desarrollos | M51: SALVA4140 | N51: El Salvador 4140
A52: 52204 | B52: H. Seguridad e Higiene | C52: 46083 | D52: 1490 | E52: Honorarios Seguridad e Higiene | F52: Petrini Omar Daniel | G52: FC3 | H52: 300000870 | I52: 80000 | J52: 0 | K52: DESA | L52: Desarrollos | M52: SALVA4140 | N52: El Salvador 4140
A53: 52204 | B53: H. Seguridad e Higiene | C53: 46084 | D53: 2072 | E53: Honorarios Seguridad e Higiene | F53: Petrini David Osvaldo | G53: FCA3 | H53: 300001433 | I53: 370000 | J53: 0 | K53: DESA | L53: Desarrollos | M53: SALVA4140 | N53: El Salvador 4140
A54: 52204 | B54: H. Seguridad e Higiene | C54: 46098 | D54: 802 | E54: Petrini David | G54: OPXX | H54: 8830 | I54: 601000 | J54: 0 | K54: DESA | L54: Desarrollos | M54: SALVA4140 | N54: El Salvador 4140
A55: 52204 | B55: H. Seguridad e Higiene | C55: 46113 | D55: 2174 | E55: Honorarios Seguridad e Higiene | F55: Petrini David Osvaldo | G55: FCA3 | H55: 300001454 | I55: 370000 | J55: 0 | K55: DESA | L55: Desarrollos | M55: SALVA4140 | N55: El Salvador 4140
A56: 52204 | B56: H. Seguridad e Higiene | C56: 46113 | D56: 2174 | E56: Honorarios Seguridad e Higiene | F56: Petrini David Osvaldo | G56: FCA3 | H56: 300001454 | I56: 420000 | J56: 0 | K56: DESA | L56: Desarrollos | M56: SALVA4140 | N56: El Salvador 4140
A57: 52204 | B57: H. Seguridad e Higiene | C57: 46139 | D57: 1076 | E57: David Petrini - S&H | G57: OPXX | H57: 9103 | I57: 437000 | J57: 0 | K57: DESA | L57: Desarrollos | M57: SALVA4140 | N57: El Salvador 4140
A58: 52204 | B58: H. Seguridad e Higiene | C58: 46145 | D58: 2610 | E58: Honorarios Seguridad e Higiene | F58: Petrini Omar Daniel | G58: FC3 | H58: 300000901 | I58: 570000 | J58: 0 | K58: DESA | L58: Desarrollos | M58: SALVA4140 | N58: El Salvador 4140
A59: 52204 | B59: H. Seguridad e Higiene | C59: 46147 | D59: 2725 | E59: Honorarios Seguridad e Higiene | F59: Petrini David Osvaldo | G59: FCA3 | H59: 300001481 | I59: 370000 | J59: 0 | K59: DESA | L59: Desarrollos | M59: SALVA4140 | N59: El Salvador 4140
A60: 52204 | B60: H. Seguridad e Higiene | C60: 46149 | D60: 2739 | E60: Honorarios Seguridad e Higiene | F60: PETRINI MATAFUEGOS | G60: FCA3 | H60: 400000693 | I60: 30000 | J60: 0 | K60: DESA | L60: Desarrollos | M60: SALVA4140 | N60: El Salvador 4140
A61: 52204 | B61: H. Seguridad e Higiene | C61: 46169 | D61: 1269 | E61: David Petrini - S&H | G61: OPXX | H61: 9294 | I61: 437000 | J61: 0 | K61: DESA | L61: Desarrollos | M61: SALVA4140 | N61: El Salvador 4140
A62: 52302 | B62: Mov. Variables | C62: 45976 | D62: 203 | E62: Diesel 500 B 0 - YPF S.A. | F62: YPF S.A. | G62: FCA3 | H62: 217201892519 | I62: 26131.51 | J62: 0 | K62: DESA | L62: Desarrollos | M62: SALVA4140 | N62: El Salvador 4140
A63: 52302 | B63: Mov. Variables | C63: 45976 | D63: 203 | E63: Infinia Diesel B 10 - YPF S.A. | F63: YPF S.A. | G63: FCA3 | H63: 217201892519 | I63: 15494.56 | J63: 0 | K63: DESA | L63: Desarrollos | M63: SALVA4140 | N63: El Salvador 4140
A64: 52302 | B64: Mov. Variables | C64: 45976 | D64: 203 | E64: Infinia E 12 - YPF S.A. | F64: YPF S.A. | G64: FCA3 | H64: 217201892519 | I64: 58594.18 | J64: 0 | K64: DESA | L64: Desarrollos | M64: SALVA4140 | N64: El Salvador 4140
A65: 52302 | B65: Mov. Variables | C65: 45976 | D65: 203 | E65: ITC - YPF S.A. | F65: YPF S.A. | G65: FCA3 | H65: 217201892519 | I65: 17664.35 | J65: 0 | K65: DESA | L65: Desarrollos | M65: SALVA4140 | N65: El Salvador 4140
A66: 52302 | B66: Mov. Variables | C66: 45976 | D66: 203 | E66: ICO2 - YPF S.A. | F66: YPF S.A. | G66: FCA3 | H66: 217201892519 | I66: 1585.33 | J66: 0 | K66: DESA | L66: Desarrollos | M66: SALVA4140 | N66: El Salvador 4140
A67: 52302 | B67: Mov. Variables | C67: 45991 | D67: 351 | E67: Diesel B11 - YPF S.A. | F67: YPF S.A. | G67: FCA3 | H67: 217201905588 | I67: 27897.85 | J67: 0 | K67: DESA | L67: Desarrollos | M67: SALVA4140 | N67: El Salvador 4140
A68: 52302 | B68: Mov. Variables | C68: 45991 | D68: 351 | E68: Nafta Infinia E12 - YPF S.A. | F68: YPF S.A. | G68: FCA3 | H68: 217201905588 | I68: 56608.92 | J68: 0 | K68: DESA | L68: Desarrollos | M68: SALVA4140 | N68: El Salvador 4140
A69: 52302 | B69: Mov. Variables | C69: 45991 | D69: 351 | E69: ICO - YPF S.A. | F69: YPF S.A. | G69: FCA3 | H69: 217201905588 | I69: 1130.29 | J69: 0 | K69: DESA | L69: Desarrollos | M69: SALVA4140 | N69: El Salvador 4140
A70: 52302 | B70: Mov. Variables | C70: 45991 | D70: 351 | E70: ITC - YPF S.A. | F70: YPF S.A. | G70: FCA3 | H70: 217201905588 | I70: 14617.01 | J70: 0 | K70: DESA | L70: Desarrollos | M70: SALVA4140 | N70: El Salvador 4140
A71: 52302 | B71: Mov. Variables | C71: 45995 | D71: 161 | E71: Lavadero | G71: OPXX | H71: 8180 | I71: 30000 | J71: 0 | K71: DESA | L71: Desarrollos | M71: SALVA4140 | N71: El Salvador 4140
A72: 52302 | B72: Mov. Variables | C72: 46006 | D72: 685 | E72: Diesel B11 - YPF S.A. | F72: YPF S.A. | G72: FCA3 | H72: 217201931277 | I72: 49751.23 | J72: 0 | K72: DESA | L72: Desarrollos | M72: SALVA4140 | N72: El Salvador 4140
A73: 52302 | B73: Mov. Variables | C73: 46006 | D73: 685 | E73: Infinie E12 - YPF S.A. | F73: YPF S.A. | G73: FCA3 | H73: 217201931277 | I73: 130554.16 | J73: 0 | K73: DESA | L73: Desarrollos | M73: SALVA4140 | N73: El Salvador 4140
A74: 52302 | B74: Mov. Variables | C74: 46006 | D74: 685 | E74: ICO - YPF S.A. | F74: YPF S.A. | G74: FCA3 | H74: 217201931277 | I74: 2518.03 | J74: 0 | K74: DESA | L74: Desarrollos | M74: SALVA4140 | N74: El Salvador 4140
A75: 52302 | B75: Mov. Variables | C75: 46006 | D75: 685 | E75: ITC - YPF S.A. | F75: YPF S.A. | G75: FCA3 | H75: 217201931277 | I75: 34047.82 | J75: 0 | K75: DESA | L75: Desarrollos | M75: SALVA4140 | N75: El Salvador 4140
A76: 52302 | B76: Mov. Variables | C76: 46022 | D76: 695 | E76: Diesel B10 - YPF S.A. | F76: YPF S.A. | G76: FCA3 | H76: 217201945178 | I76: 39470.15 | J76: 0 | K76: DESA | L76: Desarrollos | M76: SALVA4140 | N76: El Salvador 4140
A77: 52302 | B77: Mov. Variables | C77: 46022 | D77: 695 | E77: Infinia E12 - YPF S.A. | F77: YPF S.A. | G77: FCA3 | H77: 217201945178 | I77: 81458.34 | J77: 0 | K77: DESA | L77: Desarrollos | M77: SALVA4140 | N77: El Salvador 4140
A78: 52302 | B78: Mov. Variables | C78: 46022 | D78: 695 | E78: ICO - YPF S.A. | F78: YPF S.A. | G78: FCA3 | H78: 217201945178 | I78: 1643.68 | J78: 0 | K78: DESA | L78: Desarrollos | M78: SALVA4140 | N78: El Salvador 4140
A79: 52302 | B79: Mov. Variables | C79: 46022 | D79: 695 | E79: ITC - YPF S.A. | F79: YPF S.A. | G79: FCA3 | H79: 217201945178 | I79: 21975.63 | J79: 0 | K79: DESA | L79: Desarrollos | M79: SALVA4140 | N79: El Salvador 4140
A80: 52302 | B80: Mov. Variables | C80: 46028 | D80: 1059 | E80: Nafta | G80: OPXX | H80: 9087 | I80: 81007 | J80: 0 | K80: DESA | L80: Desarrollos | M80: SALVA4140 | N80: El Salvador 4140
A81: 52302 | B81: Mov. Variables | C81: 46028 | D81: 1064 | E81: Nafta | G81: OPXX | H81: 9092 | I81: 20900 | J81: 0 | K81: DESA | L81: Desarrollos | M81: SALVA4140 | N81: El Salvador 4140
A82: 52302 | B82: Mov. Variables | C82: 46040 | D82: 919 | E82: Combustible General - YPF S.A. | F82: YPF S.A. | G82: FCA3 | H82: 142000009935 | I82: 14310.76 | J82: 0 | K82: DESA | L82: Desarrollos | M82: SALVA4140 | N82: El Salvador 4140
A83: 52302 | B83: Mov. Variables | C83: 46040 | D83: 919 | E83: Combustible General - YPF S.A. | F83: YPF S.A. | G83: FCA3 | H83: 142000009935 | I83: 15394.57 | J83: 0 | K83: DESA | L83: Desarrollos | M83: SALVA4140 | N83: El Salvador 4140
A84: 52302 | B84: Mov. Variables | C84: 46040 | D84: 919 | E84: ICL - YPF S.A. | F84: YPF S.A. | G84: FCA3 | H84: 142000009935 | I84: 6440.09 | J84: 0 | K84: DESA | L84: Desarrollos | M84: SALVA4140 | N84: El Salvador 4140
A85: 52302 | B85: Mov. Variables | C85: 46040 | D85: 919 | E85: IDC - YPF S.A. | F85: YPF S.A. | G85: FCA3 | H85: 142000009935 | I85: 394.49 | J85: 0 | K85: DESA | L85: Desarrollos | M85: SALVA4140 | N85: El Salvador 4140
A86: 52302 | B86: Mov. Variables | C86: 46040 | D86: 919 | E86: TASA VIAL - YPF S.A. | F86: YPF S.A. | G86: FCA3 | H86: 142000009935 | I86: 131.49 | J86: 0 | K86: DESA | L86: Desarrollos | M86: SALVA4140 | N86: El Salvador 4140
A87: 52302 | B87: Mov. Variables | C87: 46044 | D87: 1057 | E87: Nafta | G87: OPXX | H87: 9085 | I87: 7633.99 | J87: 0 | K87: DESA | L87: Desarrollos | M87: SALVA4140 | N87: El Salvador 4140
A88: 52302 | B88: Mov. Variables | C88: 46048 | D88: 1062 | E88: Nafta | G88: OPXX | H88: 9090 | I88: 7047.6 | J88: 0 | K88: DESA | L88: Desarrollos | M88: SALVA4140 | N88: El Salvador 4140
A89: 52302 | B89: Mov. Variables | C89: 46048 | D89: 1108 | E89: Estacionamiento | G89: OPG | H89: 4371 | I89: 9000 | J89: 0 | K89: DESA | L89: Desarrollos | M89: SALVA4140 | N89: El Salvador 4140
A90: 52302 | B90: Mov. Variables | C90: 46053 | D90: 1323 | E90: Combustible General - YPF S.A. | F90: YPF S.A. | G90: FCA3 | H90: 142000021052 | I90: 202970.28 | J90: 0 | K90: DESA | L90: Desarrollos | M90: SALVA4140 | N90: El Salvador 4140
A91: 52302 | B91: Mov. Variables | C91: 46053 | D91: 1323 | E91: ICL - YPF S.A. | F91: YPF S.A. | G91: FCA3 | H91: 142000021052 | I91: 35692.39 | J91: 0 | K91: DESA | L91: Desarrollos | M91: SALVA4140 | N91: El Salvador 4140
A92: 52302 | B92: Mov. Variables | C92: 46053 | D92: 1323 | E92: IDC - YPF S.A. | F92: YPF S.A. | G92: FCA3 | H92: 142000021052 | I92: 2875.36 | J92: 0 | K92: DESA | L92: Desarrollos | M92: SALVA4140 | N92: El Salvador 4140
A93: 52302 | B93: Mov. Variables | C93: 46066 | D93: 1318 | E93: Flete - ROBLES EDUARDO NICOLAS | F93: ROBLES EDUARDO NICOLAS | G93: FCA3 | H93: 200000053 | I93: 250000 | J93: 0 | K93: DESA | L93: Desarrollos | M93: SALVA4140 | N93: El Salvador 4140
A94: 52302 | B94: Mov. Variables | C94: 46066 | D94: 1319 | E94: Fletes - ROBLES EDUARDO NICOLA | F94: ROBLES EDUARDO NICOLAS | G94: FCA3 | H94: 200000054 | I94: 500000 | J94: 0 | K94: DESA | L94: Desarrollos | M94: SALVA4140 | N94: El Salvador 4140
A95: 52302 | B95: Mov. Variables | C95: 46074 | D95: 1345 | E95: Combustible General - YPF S.A. | F95: YPF S.A. | G95: FCA3 | H95: 142000054718 | I95: 120925.97 | J95: 0 | K95: DESA | L95: Desarrollos | M95: SALVA4140 | N95: El Salvador 4140
A96: 52302 | B96: Mov. Variables | C96: 46081 | D96: 1485 | E96: Infinia Diesel - YPF S.A. | F96: YPF S.A. | G96: FCA3 | H96: 142000071412 | I96: 32310.03 | J96: 0 | K96: DESA | L96: Desarrollos | M96: SALVA4140 | N96: El Salvador 4140
A97: 52302 | B97: Mov. Variables | C97: 46081 | D97: 1485 | E97: Nafta Infinia - YPF S.A. | F97: YPF S.A. | G97: FCA3 | H97: 142000071412 | I97: 70941.9 | J97: 0 | K97: DESA | L97: Desarrollos | M97: SALVA4140 | N97: El Salvador 4140
A98: 52302 | B98: Mov. Variables | C98: 46081 | D98: 1485 | E98: ICL - YPF S.A. | F98: YPF S.A. | G98: FCA3 | H98: 142000071412 | I98: 20930 | J98: 0 | K98: DESA | L98: Desarrollos | M98: SALVA4140 | N98: El Salvador 4140
A99: 52302 | B99: Mov. Variables | C99: 46081 | D99: 1485 | E99: IDC - YPF S.A. | F99: YPF S.A. | G99: FCA3 | H99: 142000071412 | I99: 1587.18 | J99: 0 | K99: DESA | L99: Desarrollos | M99: SALVA4140 | N99: El Salvador 4140
A100: 52302 | B100: Mov. Variables | C100: 46084 | D100: 1587 | E100: Fletes - ROBLES EDUARDO NICOLA | F100: ROBLES EDUARDO NICOLAS | G100: FCA3 | H100: 200000057 | I100: 150000 | J100: 0 | K100: DESA | L100: Desarrollos | M100: SALVA4140 | N100: El Salvador 4140
...

Sheet 1_Composicion
A1: Partida | B1: Tipo | C1: Subtipo | D1: Cod_Insumo | E1: Descripción | F1: Unidad de medida | G1: Cant | H1: %Desp | I1: Precio | J1: Costo | K1: Clave | L1: Count | M1: Clave2 | N1: Rend. Part. | O1: Cant MO/ALB Unit | P1: Cant. Ej. Part. | Q1: Cant MO/ALB Total | R1: Cod_Item_Ppto | S1: Rubro
A2: PTO-0102 | B2: MO | C2: OTR | D2: SUB-0001 | E2: JEFE DE OBRA | F2: j | G2: 1 | H2: 0 | I2: 172653.21 | J2: 172653.21 | K2: PTO-0102|MO | L2: 1 | M2: PTO-0102|MO|1 | N2: 1 | O2: 0 | P2: 3 | Q2: 0 | R2: 1.02 | S2: =IFERROR(_xlfn.XLOOKUP(R2,'1_Presupuesto'!$E:$E,'1_Presupuesto'!$D:$D),"") -> Preliminares
A3: PTO-0102 | B3: MO | C3: ALB | D3: MO-AYU | E3: AYUDANTE | F3: j | G3: 1.6666667 | H3: 0 | I3: 49934.24 | J3: 83223.733 | K3: PTO-0102|MO | L3: 2 | M3: PTO-0102|MO|2 | N3: 1 | O3: 1.6666667 | P3: 3 | Q3: 5 | R3: 1.02 | S3: =IFERROR(_xlfn.XLOOKUP(R3,'1_Presupuesto'!$E:$E,'1_Presupuesto'!$D:$D),"") -> Preliminares
A4: PTO-0102 | B4: EQ | D4: EQ-0001 | E4: Herramientas/consumibles - Topógrafo - Visita de obra replanteo | G4: 1 | H4: 0 | I4: 4463.1541 | J4: 4463.1541 | K4: PTO-0102|EQ | L4: 1 | M4: PTO-0102|EQ|1 | N4: 1 | O4: 0 | P4: 3 | Q4: 0 | R4: 1.02 | S4: =IFERROR(_xlfn.XLOOKUP(R4,'1_Presupuesto'!$E:$E,'1_Presupuesto'!$D:$D),"") -> Preliminares
A5: PTO-0102 | B5: MAT | C5: CONS | D5: MAT-CONS | E5: Consumibles | G5: 41666.667 | H5: 0 | I5: 1 | J5: 41666.667 | K5: PTO-0102|MAT | L5: 1 | M5: PTO-0102|MAT|1 | N5: 1 | O5: 0 | P5: 3 | Q5: 0 | R5: 1.02 | S5: =IFERROR(_xlfn.XLOOKUP(R5,'1_Presupuesto'!$E:$E,'1_Presupuesto'!$D:$D),"") -> Preliminares
A6: PTO-0104 | B6: MAT | C6: OTR | D6: MAT-0001 | E6: C. CIN. T101 ESP 0,50 MM (C25) | G6: 2.5 | H6: 0 | I6: 10599.984 | J6: 26499.959 | K6: PTO-0104|MAT | L6: 1 | M6: PTO-0104|MAT|1 | N6: 1 | O6: 0 | P6: 11 | Q6: 0 | R6: 1.04 | S6: =IFERROR(_xlfn.XLOOKUP(R6,'1_Presupuesto'!$E:$E,'1_Presupuesto'!$D:$D),"") -> Preliminares
A7: PTO-0104 | B7: MAT | C7: OTR | D7: MAT-0002 | E7: Peril UPN 100 x 12 m | G7: 0.09090909 | H7: 0 | I7: 267019.02 | J7: 24274.456 | K7: PTO-0104|MAT | L7: 2 | M7: PTO-0104|MAT|2 | N7: 1 | O7: 0 | P7: 11 | Q7: 0 | R7: 1.04 | S7: =IFERROR(_xlfn.XLOOKUP(R7,'1_Presupuesto'!$E:$E,'1_Presupuesto'!$D:$D),"") -> Preliminares
A8: PTO-0104 | B8: MAT | C8: OTR | D8: MAT-0003 | E8: Tubo estructural 40 x 40 x 2, Largo 6 metros | G8: 0.18181818 | H8: 0 | I8: 26250.62 | J8: 4772.8399 | K8: PTO-0104|MAT | L8: 3 | M8: PTO-0104|MAT|3 | N8: 1 | O8: 0 | P8: 11 | Q8: 0 | R8: 1.04 | S8: =IFERROR(_xlfn.XLOOKUP(R8,'1_Presupuesto'!$E:$E,'1_Presupuesto'!$D:$D),"") -> Preliminares
A9: PTO-0104 | B9: MAT | C9: OTR | D9: MAT-0004 | E9: Riel Roma 174 e: 2,1 mm. 53 x 60 x 6000 | G9: 0.09090909 | H9: 0 | I9: 81509.95 | J9: 7409.9954 | K9: PTO-0104|MAT | L9: 4 | M9: PTO-0104|MAT|4 | N9: 1 | O9: 0 | P9: 11 | Q9: 0 | R9: 1.04 | S9: =IFERROR(_xlfn.XLOOKUP(R9,'1_Presupuesto'!$E:$E,'1_Presupuesto'!$D:$D),"") -> Preliminares
A10: PTO-0104 | B10: MAT | C10: OTR | D10: MAT-0005 | E10: Carro acero 174 4 ruedas puertas portones Ø45mm | G10: 0.18181818 | H10: 0 | I10: 12131.562 | J10: 2205.7385 | K10: PTO-0104|MAT | L10: 5 | M10: PTO-0104|MAT|5 | N10: 1 | O10: 0 | P10: 11 | Q10: 0 | R10: 1.04 | S10: =IFERROR(_xlfn.XLOOKUP(R10,'1_Presupuesto'!$E:$E,'1_Presupuesto'!$D:$D),"") -> Preliminares
A11: PTO-0104 | B11: MAT | C11: OTR | D11: MAT-0006 | E11: Autoperforantes punta mecha 14 x 2 | G11: 11.25 | H11: 0 | I11: 120 | J11: 1350 | K11: PTO-0104|MAT | L11: 6 | M11: PTO-0104|MAT|6 | N11: 1 | O11: 0 | P11: 11 | Q11: 0 | R11: 1.04 | S11: =IFERROR(_xlfn.XLOOKUP(R11,'1_Presupuesto'!$E:$E,'1_Presupuesto'!$D:$D),"") -> Preliminares
A12: PTO-0104 | B12: MAT | C12: OTR | D12: MAT-0007 | E12: Rollo Concertina | G12: 0.09090909 | H12: 0 | I12: 31404.959 | J12: 2854.9962 | K12: PTO-0104|MAT | L12: 7 | M12: PTO-0104|MAT|7 | N12: 1 | O12: 0 | P12: 11 | Q12: 0 | R12: 1.04 | S12: =IFERROR(_xlfn.XLOOKUP(R12,'1_Presupuesto'!$E:$E,'1_Presupuesto'!$D:$D),"") -> Preliminares
A13: PTO-0104 | B13: MO | C13: ALB | D13: MO-OFI | E13: OFICIAL | F13: j | G13: 0.18181818 | H13: 0 | I13: 65360.25 | J13: 11883.682 | K13: PTO-0104|MO | L13: 1 | M13: PTO-0104|MO|1 | N13: 1 | O13: 0.18181818 | P13: 11 | Q13: 2 | R13: 1.04 | S13: =IFERROR(_xlfn.XLOOKUP(R13,'1_Presupuesto'!$E:$E,'1_Presupuesto'!$D:$D),"") -> Preliminares
A14: PTO-0104 | B14: MO | C14: ALB | D14: MO-MED | E14: MEDIO OFICIAL | F14: j | G14: 0.18181818 | H14: 0 | I14: 54784.07 | J14: 9960.7399 | K14: PTO-0104|MO | L14: 2 | M14: PTO-0104|MO|2 | N14: 1 | O14: 0.18181818 | P14: 11 | Q14: 2 | R14: 1.04 | S14: =IFERROR(_xlfn.XLOOKUP(R14,'1_Presupuesto'!$E:$E,'1_Presupuesto'!$D:$D),"") -> Preliminares
A15: PTO-0104 | B15: MO | C15: ALB | D15: MO-AYU | E15: AYUDANTE | F15: j | G15: 0.18181818 | H15: 0 | I15: 49934.24 | J15: 9078.9526 | K15: PTO-0104|MO | L15: 3 | M15: PTO-0104|MO|3 | N15: 1 | O15: 0.18181818 | P15: 11 | Q15: 2 | R15: 1.04 | S15: =IFERROR(_xlfn.XLOOKUP(R15,'1_Presupuesto'!$E:$E,'1_Presupuesto'!$D:$D),"") -> Preliminares
A16: PTO-0104 | B16: EQ | D16: EQ-0002 | E16: Herramientas/consumibles - Cerco de obra perimetral - En chapa C25 | G16: 1 | H16: 0 | I16: 1660.4484 | J16: 1660.4484 | K16: PTO-0104|EQ | L16: 1 | M16: PTO-0104|EQ|1 | N16: 1 | O16: 0 | P16: 11 | Q16: 0 | R16: 1.04 | S16: =IFERROR(_xlfn.XLOOKUP(R16,'1_Presupuesto'!$E:$E,'1_Presupuesto'!$D:$D),"") -> Preliminares
A17: PTO-0104 | B17: MAT | C17: CONS | D17: MAT-CONS | E17: Consumibles | G17: 10405.195 | H17: 0 | I17: 1 | J17: 10405.195 | K17: PTO-0104|MAT | L17: 8 | M17: PTO-0104|MAT|8 | N17: 1 | O17: 0 | P17: 11 | Q17: 0 | R17: 1.04 | S17: =IFERROR(_xlfn.XLOOKUP(R17,'1_Presupuesto'!$E:$E,'1_Presupuesto'!$D:$D),"") -> Preliminares
A18: PTO-0105 | B18: MAT | C18: OTR | D18: MAT-0008 | E18: C. CIN. T101 ESP 0,50 MM (C25) | G18: 35 | H18: 0 | I18: 5299.9917 | J18: 185499.71 | K18: PTO-0105|MAT | L18: 1 | M18: PTO-0105|MAT|1 | N18: 1 | O18: 0 | P18: 1 | Q18: 0 | R18: 1.05 | S18: =IFERROR(_xlfn.XLOOKUP(R18,'1_Presupuesto'!$E:$E,'1_Presupuesto'!$D:$D),"") -> Preliminares
A19: PTO-0105 | B19: MAT | C19: OTR | D19: MAT-0009 | E19: Precio fenolico comun e: 18 mm | G19: 33 | H19: 0 | I19: 13161.34 | J19: 434324.22 | K19: PTO-0105|MAT | L19: 2 | M19: PTO-0105|MAT|2 | N19: 1 | O19: 0 | P19: 1 | Q19: 0 | R19: 1.05 | S19: =IFERROR(_xlfn.XLOOKUP(R19,'1_Presupuesto'!$E:$E,'1_Presupuesto'!$D:$D),"") -> Preliminares
A20: PTO-0105 | B20: MAT | C20: OTR | D20: MAT-0010 | E20: Tabla 4 x 1 x 3,6 Saligna bruto | G20: 80 | H20: 0 | I20: 970.974 | J20: 77677.92 | K20: PTO-0105|MAT | L20: 3 | M20: PTO-0105|MAT|3 | N20: 1 | O20: 0 | P20: 1 | Q20: 0 | R20: 1.05 | S20: =IFERROR(_xlfn.XLOOKUP(R20,'1_Presupuesto'!$E:$E,'1_Presupuesto'!$D:$D),"") -> Preliminares
A21: PTO-0105 | B21: MAT | C21: OTR | D21: MAT-0011 | E21: Tirante 3 x 3 x 3,6 Saligna bruto | G21: 40 | H21: 0 | I21: 2184.714 | J21: 87388.56 | K21: PTO-0105|MAT | L21: 4 | M21: PTO-0105|MAT|4 | N21: 1 | O21: 0 | P21: 1 | Q21: 0 | R21: 1.05 | S21: =IFERROR(_xlfn.XLOOKUP(R21,'1_Presupuesto'!$E:$E,'1_Presupuesto'!$D:$D),"") -> Preliminares
A22: PTO-0105 | B22: MAT | C22: OTR | D22: MAT-0012 | E22: Flechas 3 x 6 x 3,7 - Reutilizado (estimado 3 usos) | G22: 20 | H22: 0 | I22: 4369.428 | J22: 87388.56 | K22: PTO-0105|MAT | L22: 5 | M22: PTO-0105|MAT|5 | N22: 1 | O22: 0 | P22: 1 | Q22: 0 | R22: 1.05 | S22: =IFERROR(_xlfn.XLOOKUP(R22,'1_Presupuesto'!$E:$E,'1_Presupuesto'!$D:$D),"") -> Preliminares
A23: PTO-0105 | B23: MAT | C23: OTR | D23: MAT-0013 | E23: Escalera | G23: 0.5 | H23: 0 | I23: 252455.04 | J23: 126227.52 | K23: PTO-0105|MAT | L23: 6 | M23: PTO-0105|MAT|6 | N23: 1 | O23: 0 | P23: 1 | Q23: 0 | R23: 1.05 | S23: =IFERROR(_xlfn.XLOOKUP(R23,'1_Presupuesto'!$E:$E,'1_Presupuesto'!$D:$D),"") -> Preliminares
A24: PTO-0105 | B24: MO | C24: OTR | D24: SUB-0002 | E24: Flete madera | F24: j | G24: 2 | H24: 0 | I24: 250000 | J24: 500000 | K24: PTO-0105|MO | L24: 1 | M24: PTO-0105|MO|1 | N24: 1 | O24: 0 | P24: 1 | Q24: 0 | R24: 1.05 | S24: =IFERROR(_xlfn.XLOOKUP(R24,'1_Presupuesto'!$E:$E,'1_Presupuesto'!$D:$D),"") -> Preliminares
A25: PTO-0105 | B25: MAT | C25: COR | D25: MAT-0014 | E25: Materiales varios | G25: 1 | H25: 0 | I25: 100000 | J25: 100000 | K25: PTO-0105|MAT | L25: 7 | M25: PTO-0105|MAT|7 | N25: 1 | O25: 0 | P25: 1 | Q25: 0 | R25: 1.05 | S25: =IFERROR(_xlfn.XLOOKUP(R25,'1_Presupuesto'!$E:$E,'1_Presupuesto'!$D:$D),"") -> Preliminares
A26: PTO-0105 | B26: MO | C26: ALB | D26: MO-ESP | E26: ESPECIALIZADO | F26: j | G26: 12 | H26: 0 | I26: 75113.05 | J26: 901356.6 | K26: PTO-0105|MO | L26: 2 | M26: PTO-0105|MO|2 | N26: 1 | O26: 12 | P26: 1 | Q26: 12 | R26: 1.05 | S26: =IFERROR(_xlfn.XLOOKUP(R26,'1_Presupuesto'!$E:$E,'1_Presupuesto'!$D:$D),"") -> Preliminares
A27: PTO-0105 | B27: MO | C27: ALB | D27: MO-OFI | E27: OFICIAL | F27: j | G27: 19 | H27: 0 | I27: 65360.25 | J27: 1241844.8 | K27: PTO-0105|MO | L27: 3 | M27: PTO-0105|MO|3 | N27: 1 | O27: 19 | P27: 1 | Q27: 19 | R27: 1.05 | S27: =IFERROR(_xlfn.XLOOKUP(R27,'1_Presupuesto'!$E:$E,'1_Presupuesto'!$D:$D),"") -> Preliminares
A28: PTO-0105 | B28: MO | C28: ALB | D28: MO-MED | E28: MEDIO OFICIAL | F28: j | G28: 5 | H28: 0 | I28: 54784.07 | J28: 273920.35 | K28: PTO-0105|MO | L28: 4 | M28: PTO-0105|MO|4 | N28: 1 | O28: 5 | P28: 1 | Q28: 5 | R28: 1.05 | S28: =IFERROR(_xlfn.XLOOKUP(R28,'1_Presupuesto'!$E:$E,'1_Presupuesto'!$D:$D),"") -> Preliminares
A29: PTO-0105 | B29: MO | C29: ALB | D29: MO-AYU | E29: AYUDANTE | F29: j | G29: 12 | H29: 0 | I29: 49934.24 | J29: 599210.88 | K29: PTO-0105|MO | L29: 5 | M29: PTO-0105|MO|5 | N29: 1 | O29: 12 | P29: 1 | Q29: 12 | R29: 1.05 | S29: =IFERROR(_xlfn.XLOOKUP(R29,'1_Presupuesto'!$E:$E,'1_Presupuesto'!$D:$D),"") -> Preliminares
A30: PTO-0105 | B30: MAT | C30: OTR | D30: MAT-0015 | E30: Rollo de cable TPR 3 x 2,5 | G30: 1 | H30: 0 | I30: 214876.03 | J30: 214876.03 | K30: PTO-0105|MAT | L30: 8 | M30: PTO-0105|MAT|8 | N30: 1 | O30: 0 | P30: 1 | Q30: 0 | R30: 1.05 | S30: =IFERROR(_xlfn.XLOOKUP(R30,'1_Presupuesto'!$E:$E,'1_Presupuesto'!$D:$D),"") -> Preliminares
A31: PTO-0105 | B31: MAT | C31: OTR | D31: MAT-0016 | E31: Zocalo E27 | G31: 10 | H31: 0 | I31: 369.8347 | J31: 3698.347 | K31: PTO-0105|MAT | L31: 9 | M31: PTO-0105|MAT|9 | N31: 1 | O31: 0 | P31: 1 | Q31: 0 | R31: 1.05 | S31: =IFERROR(_xlfn.XLOOKUP(R31,'1_Presupuesto'!$E:$E,'1_Presupuesto'!$D:$D),"") -> Preliminares
A32: PTO-0105 | B32: MAT | C32: OTR | D32: MAT-0017 | E32: Lampara Led 12 w | G32: 10 | H32: 0 | I32: 2363.6364 | J32: 23636.364 | K32: PTO-0105|MAT | L32: 10 | M32: PTO-0105|MAT|10 | N32: 1 | O32: 0 | P32: 1 | Q32: 0 | R32: 1.05 | S32: =IFERROR(_xlfn.XLOOKUP(R32,'1_Presupuesto'!$E:$E,'1_Presupuesto'!$D:$D),"") -> Preliminares
A33: PTO-0105 | B33: MAT | C33: OTR | D33: MAT-0018 | E33: Mat. Elect. (tomas, enchufes, etc.) | G33: 0.25 | H33: 0 | I33: 242210.74 | J33: 60552.686 | K33: PTO-0105|MAT | L33: 11 | M33: PTO-0105|MAT|11 | N33: 1 | O33: 0 | P33: 1 | Q33: 0 | R33: 1.05 | S33: =IFERROR(_xlfn.XLOOKUP(R33,'1_Presupuesto'!$E:$E,'1_Presupuesto'!$D:$D),"") -> Preliminares
A34: PTO-0105 | B34: MAT | C34: OTR | D34: MAT-0019 | E34: Materiales Sanit | G34: 1 | H34: 0 | I34: 500000 | J34: 500000 | K34: PTO-0105|MAT | L34: 12 | M34: PTO-0105|MAT|12 | N34: 1 | O34: 0 | P34: 1 | Q34: 0 | R34: 1.05 | S34: =IFERROR(_xlfn.XLOOKUP(R34,'1_Presupuesto'!$E:$E,'1_Presupuesto'!$D:$D),"") -> Preliminares
A35: PTO-0105 | B35: MAT | C35: OTR | D35: MAT-0020 | E35: Inodoro | G35: 2 | H35: 0 | I35: 100000 | J35: 200000 | K35: PTO-0105|MAT | L35: 13 | M35: PTO-0105|MAT|13 | N35: 1 | O35: 0 | P35: 1 | Q35: 0 | R35: 1.05 | S35: =IFERROR(_xlfn.XLOOKUP(R35,'1_Presupuesto'!$E:$E,'1_Presupuesto'!$D:$D),"") -> Preliminares
A36: PTO-0105 | B36: MAT | C36: OTR | D36: MAT-0021 | E36: Mochila plastico | G36: 2 | H36: 0 | I36: 25000 | J36: 50000 | K36: PTO-0105|MAT | L36: 14 | M36: PTO-0105|MAT|14 | N36: 1 | O36: 0 | P36: 1 | Q36: 0 | R36: 1.05 | S36: =IFERROR(_xlfn.XLOOKUP(R36,'1_Presupuesto'!$E:$E,'1_Presupuesto'!$D:$D),"") -> Preliminares
A37: PTO-0105 | B37: MAT | C37: OTR | D37: MAT-0022 | E37: Bacha | G37: 2 | H37: 0 | I37: 24793.388 | J37: 49586.777 | K37: PTO-0105|MAT | L37: 15 | M37: PTO-0105|MAT|15 | N37: 1 | O37: 0 | P37: 1 | Q37: 0 | R37: 1.05 | S37: =IFERROR(_xlfn.XLOOKUP(R37,'1_Presupuesto'!$E:$E,'1_Presupuesto'!$D:$D),"") -> Preliminares
A38: PTO-0105 | B38: MAT | C38: OTR | D38: MAT-0023 | E38: Termo electrico 40 lts | G38: 1 | H38: 0 | I38: 200000 | J38: 200000 | K38: PTO-0105|MAT | L38: 16 | M38: PTO-0105|MAT|16 | N38: 1 | O38: 0 | P38: 1 | Q38: 0 | R38: 1.05 | S38: =IFERROR(_xlfn.XLOOKUP(R38,'1_Presupuesto'!$E:$E,'1_Presupuesto'!$D:$D),"") -> Preliminares
A39: PTO-0105 | B39: EQ | D39: EQ-0003 | E39: Herramientas/consumibles - Obrador colgante, pañol y ducha | G39: 1 | H39: 0 | I39: 88757.838 | J39: 88757.838 | K39: PTO-0105|EQ | L39: 1 | M39: PTO-0105|EQ|1 | N39: 1 | O39: 0 | P39: 1 | Q39: 0 | R39: 1.05 | S39: =IFERROR(_xlfn.XLOOKUP(R39,'1_Presupuesto'!$E:$E,'1_Presupuesto'!$D:$D),"") -> Preliminares
A40: PTO-0106 | B40: MO | C40: OTR | D40: SUB-0003 | E40: Baño portatil / Ducha | F40: j | G40: 1 | H40: 0 | I40: 295488.56 | J40: 295488.56 | K40: PTO-0106|MO | L40: 1 | M40: PTO-0106|MO|1 | N40: 1 | O40: 0 | P40: 3 | Q40: 0 | R40: 1.06 | S40: =IFERROR(_xlfn.XLOOKUP(R40,'1_Presupuesto'!$E:$E,'1_Presupuesto'!$D:$D),"") -> -
A41: PTO-0106 | B41: MO | C41: OTR | D41: SUB-0004 | E41: Traslado flete entrega/ retiro | F41: j | G41: 1 | H41: 0 | I41: 16416.031 | J41: 16416.031 | K41: PTO-0106|MO | L41: 2 | M41: PTO-0106|MO|2 | N41: 1 | O41: 0 | P41: 3 | Q41: 0 | R41: 1.06 | S41: =IFERROR(_xlfn.XLOOKUP(R41,'1_Presupuesto'!$E:$E,'1_Presupuesto'!$D:$D),"") -> -
A42: PTO-0107 | B42: MAT | C42: COR | D42: MAT-0024 | E42: Pilar de obra, albañileria | G42: 2 | H42: 0 | I42: 25000 | J42: 50000 | K42: PTO-0107|MAT | L42: 1 | M42: PTO-0107|MAT|1 | N42: 1 | O42: 0 | P42: 1 | Q42: 0 | R42: 1.07 | S42: =IFERROR(_xlfn.XLOOKUP(R42,'1_Presupuesto'!$E:$E,'1_Presupuesto'!$D:$D),"") -> Preliminares
A43: PTO-0107 | B43: MO | C43: ALB | D43: MO-OFI | E43: OFICIAL | F43: j | G43: 4 | H43: 0 | I43: 65360.25 | J43: 261441 | K43: PTO-0107|MO | L43: 1 | M43: PTO-0107|MO|1 | N43: 1 | O43: 4 | P43: 1 | Q43: 4 | R43: 1.07 | S43: =IFERROR(_xlfn.XLOOKUP(R43,'1_Presupuesto'!$E:$E,'1_Presupuesto'!$D:$D),"") -> Preliminares
A44: PTO-0107 | B44: MO | C44: ALB | D44: MO-AYU | E44: AYUDANTE | F44: j | G44: 2 | H44: 0 | I44: 49934.24 | J44: 99868.48 | K44: PTO-0107|MO | L44: 2 | M44: PTO-0107|MO|2 | N44: 1 | O44: 2 | P44: 1 | Q44: 2 | R44: 1.07 | S44: =IFERROR(_xlfn.XLOOKUP(R44,'1_Presupuesto'!$E:$E,'1_Presupuesto'!$D:$D),"") -> Preliminares
A45: PTO-0107 | B45: MAT | C45: OTR | D45: MAT-0025 | E45: Kit medidor pilar Edenor Conextube | G45: 1 | H45: 0 | I45: 150000 | J45: 150000 | K45: PTO-0107|MAT | L45: 2 | M45: PTO-0107|MAT|2 | N45: 1 | O45: 0 | P45: 1 | Q45: 0 | R45: 1.07 | S45: =IFERROR(_xlfn.XLOOKUP(R45,'1_Presupuesto'!$E:$E,'1_Presupuesto'!$D:$D),"") -> Preliminares
A46: PTO-0107 | B46: MAT | C46: OTR | D46: MAT-0026 | E46: Kit jabalina + caja + toma cable | G46: 1 | H46: 0 | I46: 15000 | J46: 15000 | K46: PTO-0107|MAT | L46: 3 | M46: PTO-0107|MAT|3 | N46: 1 | O46: 0 | P46: 1 | Q46: 0 | R46: 1.07 | S46: =IFERROR(_xlfn.XLOOKUP(R46,'1_Presupuesto'!$E:$E,'1_Presupuesto'!$D:$D),"") -> Preliminares
A47: PTO-0107 | B47: MAT | C47: OTR | D47: MAT-0027 | E47: Cable subterraneo 5 x 10 mm2 | G47: 20 | H47: 0 | I47: 16528.926 | J47: 330578.51 | K47: PTO-0107|MAT | L47: 4 | M47: PTO-0107|MAT|4 | N47: 1 | O47: 0 | P47: 1 | Q47: 0 | R47: 1.07 | S47: =IFERROR(_xlfn.XLOOKUP(R47,'1_Presupuesto'!$E:$E,'1_Presupuesto'!$D:$D),"") -> Preliminares
A48: PTO-0107 | B48: MAT | C48: OTR | D48: MAT-0028 | E48: Tablero de obra | G48: 1 | H48: 0 | I48: 300000 | J48: 300000 | K48: PTO-0107|MAT | L48: 5 | M48: PTO-0107|MAT|5 | N48: 1 | O48: 0 | P48: 1 | Q48: 0 | R48: 1.07 | S48: =IFERROR(_xlfn.XLOOKUP(R48,'1_Presupuesto'!$E:$E,'1_Presupuesto'!$D:$D),"") -> Preliminares
A49: PTO-0107 | B49: MO | C49: ALB | D49: MO-ESP | E49: ESPECIALIZADO | F49: j | G49: 2 | H49: 0 | I49: 75113.05 | J49: 150226.1 | K49: PTO-0107|MO | L49: 3 | M49: PTO-0107|MO|3 | N49: 1 | O49: 2 | P49: 1 | Q49: 2 | R49: 1.07 | S49: =IFERROR(_xlfn.XLOOKUP(R49,'1_Presupuesto'!$E:$E,'1_Presupuesto'!$D:$D),"") -> Preliminares
A50: PTO-0107 | B50: EQ | D50: EQ-0004 | E50: Herramientas/consumibles - Conexión pilar y luz de obra + Tablero d | G50: 1 | H50: 0 | I50: 20356.711 | J50: 20356.711 | K50: PTO-0107|EQ | L50: 1 | M50: PTO-0107|EQ|1 | N50: 1 | O50: 0 | P50: 1 | Q50: 0 | R50: 1.07 | S50: =IFERROR(_xlfn.XLOOKUP(R50,'1_Presupuesto'!$E:$E,'1_Presupuesto'!$D:$D),"") -> Preliminares
A51: PTO-0108 | B51: MAT | C51: OTR | D51: MAT-0029 | E51: Tanque de Bombeo 500 lts (reutilizado) | G51: 1 | H51: 0 | I51: 150000 | J51: 150000 | K51: PTO-0108|MAT | L51: 1 | M51: PTO-0108|MAT|1 | N51: 1 | O51: 0 | P51: 1 | Q51: 0 | R51: 1.08 | S51: =IFERROR(_xlfn.XLOOKUP(R51,'1_Presupuesto'!$E:$E,'1_Presupuesto'!$D:$D),"") -> Preliminares
A52: PTO-0108 | B52: MAT | C52: OTR | D52: MAT-0030 | E52: Bomba pres (reutilizada) | G52: 1 | H52: 0 | I52: 200000 | J52: 200000 | K52: PTO-0108|MAT | L52: 2 | M52: PTO-0108|MAT|2 | N52: 1 | O52: 0 | P52: 1 | Q52: 0 | R52: 1.08 | S52: =IFERROR(_xlfn.XLOOKUP(R52,'1_Presupuesto'!$E:$E,'1_Presupuesto'!$D:$D),"") -> Preliminares
A53: PTO-0108 | B53: MAT | C53: OTR | D53: MAT-0031 | E53: Flotante mecanico 1" + boya | G53: 1 | H53: 0 | I53: 50000 | J53: 50000 | K53: PTO-0108|MAT | L53: 3 | M53: PTO-0108|MAT|3 | N53: 1 | O53: 0 | P53: 1 | Q53: 0 | R53: 1.08 | S53: =IFERROR(_xlfn.XLOOKUP(R53,'1_Presupuesto'!$E:$E,'1_Presupuesto'!$D:$D),"") -> Preliminares
A54: PTO-0108 | B54: MAT | C54: OTR | D54: MAT-0032 | E54: Flotante automatico | G54: 1 | H54: 0 | I54: 10000 | J54: 10000 | K54: PTO-0108|MAT | L54: 4 | M54: PTO-0108|MAT|4 | N54: 1 | O54: 0 | P54: 1 | Q54: 0 | R54: 1.08 | S54: =IFERROR(_xlfn.XLOOKUP(R54,'1_Presupuesto'!$E:$E,'1_Presupuesto'!$D:$D),"") -> Preliminares
A55: PTO-0108 | B55: MAT | C55: OTR | D55: MAT-0033 | E55: Caño 3/4" | G55: 10 | H55: 0 | I55: 10000 | J55: 100000 | K55: PTO-0108|MAT | L55: 5 | M55: PTO-0108|MAT|5 | N55: 1 | O55: 0 | P55: 1 | Q55: 0 | R55: 1.08 | S55: =IFERROR(_xlfn.XLOOKUP(R55,'1_Presupuesto'!$E:$E,'1_Presupuesto'!$D:$D),"") -> Preliminares
A56: PTO-0108 | B56: MAT | C56: OTR | D56: MAT-0034 | E56: Val. esf doble media union 1" | G56: 3 | H56: 0 | I56: 15000 | J56: 45000 | K56: PTO-0108|MAT | L56: 6 | M56: PTO-0108|MAT|6 | N56: 1 | O56: 0 | P56: 1 | Q56: 0 | R56: 1.08 | S56: =IFERROR(_xlfn.XLOOKUP(R56,'1_Presupuesto'!$E:$E,'1_Presupuesto'!$D:$D),"") -> Preliminares
A57: PTO-0108 | B57: MAT | C57: OTR | D57: MAT-0035 | E57: Canilla de pvc | G57: 6 | H57: 0 | I57: 2000 | J57: 12000 | K57: PTO-0108|MAT | L57: 7 | M57: PTO-0108|MAT|7 | N57: 1 | O57: 0 | P57: 1 | Q57: 0 | R57: 1.08 | S57: =IFERROR(_xlfn.XLOOKUP(R57,'1_Presupuesto'!$E:$E,'1_Presupuesto'!$D:$D),"") -> Preliminares
A58: PTO-0108 | B58: MAT | C58: OTR | D58: MAT-0036 | E58: Desperdicio | G58: 0.2 | H58: 0 | I58: 567000 | J58: 113400 | K58: PTO-0108|MAT | L58: 8 | M58: PTO-0108|MAT|8 | N58: 1 | O58: 0 | P58: 1 | Q58: 0 | R58: 1.08 | S58: =IFERROR(_xlfn.XLOOKUP(R58,'1_Presupuesto'!$E:$E,'1_Presupuesto'!$D:$D),"") -> Preliminares
A59: PTO-0108 | B59: MO | C59: ALB | D59: MO-ESP | E59: ESPECIALIZADO | F59: j | G59: 3 | H59: 0 | I59: 75113.05 | J59: 225339.15 | K59: PTO-0108|MO | L59: 1 | M59: PTO-0108|MO|1 | N59: 1 | O59: 3 | P59: 1 | Q59: 3 | R59: 1.08 | S59: =IFERROR(_xlfn.XLOOKUP(R59,'1_Presupuesto'!$E:$E,'1_Presupuesto'!$D:$D),"") -> Preliminares
A60: PTO-0108 | B60: MO | C60: ALB | D60: MO-OFI | E60: OFICIAL | F60: j | G60: 3 | H60: 0 | I60: 65360.25 | J60: 196080.75 | K60: PTO-0108|MO | L60: 2 | M60: PTO-0108|MO|2 | N60: 1 | O60: 3 | P60: 1 | Q60: 3 | R60: 1.08 | S60: =IFERROR(_xlfn.XLOOKUP(R60,'1_Presupuesto'!$E:$E,'1_Presupuesto'!$D:$D),"") -> Preliminares
A61: PTO-0108 | B61: EQ | D61: EQ-0005 | E61: Herramientas/consumibles - Conexión agua de obra, tanque + bomba | G61: 1 | H61: 0 | I61: 16527.298 | J61: 16527.298 | K61: PTO-0108|EQ | L61: 1 | M61: PTO-0108|EQ|1 | N61: 1 | O61: 0 | P61: 1 | Q61: 0 | R61: 1.08 | S61: =IFERROR(_xlfn.XLOOKUP(R61,'1_Presupuesto'!$E:$E,'1_Presupuesto'!$D:$D),"") -> Preliminares
A62: PTO-0109 | B62: MO | C62: OTR | D62: SUB-0005 | E62: Gestion suministros luz de obra | F62: j | G62: 0.79478827 | H62: 0 | I62: 139065.92 | J62: 110527.96 | K62: PTO-0109|MO | L62: 1 | M62: PTO-0109|MO|1 | N62: 1 | O62: 0 | P62: 1 | Q62: 0 | R62: 1.09 | S62: =IFERROR(_xlfn.XLOOKUP(R62,'1_Presupuesto'!$E:$E,'1_Presupuesto'!$D:$D),"") -> -
A63: PTO-0109 | B63: MO | C63: OTR | D63: SUB-0006 | E63: Luz de Obra | F63: j | G63: 1.5895766 | H63: 0 | I63: 100127.46 | J63: 159160.26 | K63: PTO-0109|MO | L63: 2 | M63: PTO-0109|MO|2 | N63: 1 | O63: 0 | P63: 1 | Q63: 0 | R63: 1.09 | S63: =IFERROR(_xlfn.XLOOKUP(R63,'1_Presupuesto'!$E:$E,'1_Presupuesto'!$D:$D),"") -> -
A64: PTO-0109 | B64: MO | C64: OTR | D64: SUB-0007 | E64: Medicion PAT luz de obra | F64: j | G64: 0.79478827 | H64: 0 | I64: 87611.528 | J64: 69632.615 | K64: PTO-0109|MO | L64: 3 | M64: PTO-0109|MO|3 | N64: 1 | O64: 0 | P64: 1 | Q64: 0 | R64: 1.09 | S64: =IFERROR(_xlfn.XLOOKUP(R64,'1_Presupuesto'!$E:$E,'1_Presupuesto'!$D:$D),"") -> -
A65: PTO-0110 | B65: MO | C65: OTR | D65: SUB-0008 | E65: Total de Obra (3 perforaciones) | F65: j | G65: 1 | H65: 0 | I65: 7800000 | J65: 7800000 | K65: PTO-0110|MO | L65: 1 | M65: PTO-0110|MO|1 | N65: 1 | O65: 0 | P65: 1 | Q65: 0 | R65: 1.1 | S65: =IFERROR(_xlfn.XLOOKUP(R65,'1_Presupuesto'!$E:$E,'1_Presupuesto'!$D:$D),"") -> -
A66: PTO-0201 | B66: MO | C66: OTR | D66: SUB-0009 | E66: Desmonte, retiro, aporte y compactación e: 40 cm | F66: j | G66: 1.15 | H66: 0 | I66: 16000 | J66: 18400 | K66: PTO-0201|MO | L66: 1 | M66: PTO-0201|MO|1 | N66: 1 | O66: 0 | P66: 1266 | Q66: 0 | R66: 2.01 | S66: =IFERROR(_xlfn.XLOOKUP(R66,'1_Presupuesto'!$E:$E,'1_Presupuesto'!$D:$D),"") -> Homigón MO
A67: PTO-0201 | B67: MO | C67: ALB | D67: MO-AYU | E67: AYUDANTE | F67: j | G67: 0.1563981 | H67: 0 | I67: 49934.24 | J67: 7809.6203 | K67: PTO-0201|MO | L67: 2 | M67: PTO-0201|MO|2 | N67: 1 | O67: 0.1563981 | P67: 1266 | Q67: 197.99999 | R67: 2.01 | S67: =IFERROR(_xlfn.XLOOKUP(R67,'1_Presupuesto'!$E:$E,'1_Presupuesto'!$D:$D),"") -> Homigón MO
A68: PTO-0201 | B68: EQ | D68: EQ-0006 | E68: Herramientas/consumibles - Excavación a maquina para submuración y | G68: 1 | H68: 0 | I68: 117.1443 | J68: 117.1443 | K68: PTO-0201|EQ | L68: 1 | M68: PTO-0201|EQ|1 | N68: 1 | O68: 0 | P68: 1266 | Q68: 0 | R68: 2.01 | S68: =IFERROR(_xlfn.XLOOKUP(R68,'1_Presupuesto'!$E:$E,'1_Presupuesto'!$D:$D),"") -> Homigón MO
A69: PTO-0203 | B69: MO | C69: ALB | D69: MO-AYU | E69: AYUDANTE | F69: j | G69: 1 | H69: 0 | I69: 49934.24 | J69: 49934.24 | K69: PTO-0203|MO | L69: 1 | M69: PTO-0203|MO|1 | N69: 1 | O69: 1 | P69: 2 | Q69: 2 | R69: 2.03 | S69: =IFERROR(_xlfn.XLOOKUP(R69,'1_Presupuesto'!$E:$E,'1_Presupuesto'!$D:$D),"") -> Homigón MO
A70: PTO-0301 | B70: MAT | C70: OTR | D70: MAT-0037 | E70: H13 6.20 | G70: 1 | H70: 0 | I70: 115100 | J70: 115100 | K70: PTO-0301|MAT | L70: 1 | M70: PTO-0301|MAT|1 | N70: 1 | O70: 0 | P70: 35 | Q70: 0 | R70: 3.01 | S70: =IFERROR(_xlfn.XLOOKUP(R70,'1_Presupuesto'!$E:$E,'1_Presupuesto'!$D:$D),"") -> Homigón MO
A71: PTO-0301 | B71: MAT | C71: OTR | D71: MAT-0038 | E71: Bombeo | G71: 1 | H71: 0 | I71: 5330 | J71: 5330 | K71: PTO-0301|MAT | L71: 2 | M71: PTO-0301|MAT|2 | N71: 1 | O71: 0 | P71: 35 | Q71: 0 | R71: 3.01 | S71: =IFERROR(_xlfn.XLOOKUP(R71,'1_Presupuesto'!$E:$E,'1_Presupuesto'!$D:$D),"") -> Homigón MO
A72: PTO-0301 | B72: MAT | C72: COR | D72: MAT-0039 | E72: Acarreo | G72: 1 | H72: 0 | I72: 76142.857 | J72: 76142.857 | K72: PTO-0301|MAT | L72: 3 | M72: PTO-0301|MAT|3 | N72: 1 | O72: 0 | P72: 35 | Q72: 0 | R72: 3.01 | S72: =IFERROR(_xlfn.XLOOKUP(R72,'1_Presupuesto'!$E:$E,'1_Presupuesto'!$D:$D),"") -> Homigón MO
A73: PTO-0301 | B73: MO | C73: ALB | D73: MO-AYU | E73: AYUDANTE | F73: j | G73: 1 | H73: 0 | I73: 49934.24 | J73: 49934.24 | K73: PTO-0301|MO | L73: 1 | M73: PTO-0301|MO|1 | N73: 1 | O73: 1 | P73: 35 | Q73: 35 | R73: 3.01 | S73: =IFERROR(_xlfn.XLOOKUP(R73,'1_Presupuesto'!$E:$E,'1_Presupuesto'!$D:$D),"") -> Homigón MO
A74: PTO-0301 | B74: EQ | D74: EQ-0007 | E74: Herramientas/consumibles - Hormigón de limpieza - e: 10 cm | G74: 1 | H74: 0 | I74: 3697.6064 | J74: 3697.6064 | K74: PTO-0301|EQ | L74: 1 | M74: PTO-0301|EQ|1 | N74: 1 | O74: 0 | P74: 35 | Q74: 0 | R74: 3.01 | S74: =IFERROR(_xlfn.XLOOKUP(R74,'1_Presupuesto'!$E:$E,'1_Presupuesto'!$D:$D),"") -> Homigón MO
A75: PTO-0302 | B75: MAT | C75: OTR | D75: MAT-0040 | E75: Encofrado Tabique submuración - H30 (95 kg/m3 de hierro) | G75: 1 | H75: 0 | I75: 70843.446 | J75: 70843.446 | K75: PTO-0302|MAT | L75: 1 | M75: PTO-0302|MAT|1 | N75: 1 | O75: 0 | P75: 40 | Q75: 0 | R75: 3.02 | S75: =IFERROR(_xlfn.XLOOKUP(R75,'1_Presupuesto'!$E:$E,'1_Presupuesto'!$D:$D),"") -> Homigón MO
A76: PTO-0302 | B76: MO | C76: ALB | D76: MO-ESP | E76: ESPECIALIZADO | F76: j | G76: 1.8939581 | H76: 0 | I76: 75113.05 | J76: 142260.97 | K76: PTO-0302|MO | L76: 1 | M76: PTO-0302|MO|1 | N76: 1 | O76: 1.8939581 | P76: 40 | Q76: 75.758323 | R76: 3.02 | S76: =IFERROR(_xlfn.XLOOKUP(R76,'1_Presupuesto'!$E:$E,'1_Presupuesto'!$D:$D),"") -> Homigón MO
A77: PTO-0302 | B77: MO | C77: ALB | D77: MO-OFI | E77: OFICIAL | F77: j | G77: 2.4858201 | H77: 0 | I77: 65360.25 | J77: 162473.82 | K77: PTO-0302|MO | L77: 2 | M77: PTO-0302|MO|2 | N77: 1 | O77: 2.4858201 | P77: 40 | Q77: 99.432804 | R77: 3.02 | S77: =IFERROR(_xlfn.XLOOKUP(R77,'1_Presupuesto'!$E:$E,'1_Presupuesto'!$D:$D),"") -> Homigón MO
A78: PTO-0302 | B78: MO | C78: ALB | D78: MO-AYU | E78: AYUDANTE | F78: j | G78: 0.059186 | H78: 0 | I78: 49934.24 | J78: 2955.4079 | K78: PTO-0302|MO | L78: 3 | M78: PTO-0302|MO|3 | N78: 1 | O78: 0.059186 | P78: 40 | Q78: 2.36744 | R78: 3.02 | S78: =IFERROR(_xlfn.XLOOKUP(R78,'1_Presupuesto'!$E:$E,'1_Presupuesto'!$D:$D),"") -> Homigón MO
A79: PTO-0302 | B79: EQ | D79: EQ-0008 | E79: Herramientas/consumibles - Tabique submuración - H30 hidrófugo (95 | G79: 1 | H79: 0 | I79: 5678.0046 | J79: 5678.0046 | K79: PTO-0302|EQ | L79: 1 | M79: PTO-0302|EQ|1 | N79: 1 | O79: 0 | P79: 40 | Q79: 0 | R79: 3.02 | S79: =IFERROR(_xlfn.XLOOKUP(R79,'1_Presupuesto'!$E:$E,'1_Presupuesto'!$D:$D),"") -> Homigón MO
A80: PTO-0303 | B80: MAT | C80: OTR | D80: MAT-0041 | E80: Encofrado Zapata corrida tabique - H30 (120 kg/m3) | G80: 1 | H80: 0 | I80: 55068.822 | J80: 55068.822 | K80: PTO-0303|MAT | L80: 1 | M80: PTO-0303|MAT|1 | N80: 1 | O80: 0 | P80: 28 | Q80: 0 | R80: 3.03 | S80: =IFERROR(_xlfn.XLOOKUP(R80,'1_Presupuesto'!$E:$E,'1_Presupuesto'!$D:$D),"") -> -
A81: PTO-0303 | B81: MO | C81: OTR | D81: SUB-0010 | E81: H.A. De vigas de fundación (115kg/m3 de hierro) | F81: j | G81: 1 | H81: 0 | I81: 253994.14 | J81: 253994.14 | K81: PTO-0303|MO | L81: 1 | M81: PTO-0303|MO|1 | N81: 1 | O81: 0 | P81: 28 | Q81: 0 | R81: 3.03 | S81: =IFERROR(_xlfn.XLOOKUP(R81,'1_Presupuesto'!$E:$E,'1_Presupuesto'!$D:$D),"") -> -
A82: PTO-0303 | B82: EQ | D82: EQ-0009 | E82: Herramientas/consumibles - Zapata corrida tabique - H30 hidrófugo ( | G82: 1 | H82: 0 | I82: 4635.9445 | J82: 4635.9445 | K82: PTO-0303|EQ | L82: 1 | M82: PTO-0303|EQ|1 | N82: 1 | O82: 0 | P82: 28 | Q82: 0 | R82: 3.03 | S82: =IFERROR(_xlfn.XLOOKUP(R82,'1_Presupuesto'!$E:$E,'1_Presupuesto'!$D:$D),"") -> -
A83: PTO-0304 | B83: MAT | C83: OTR | D83: MAT-0042 | E83: Encofrado Platea - H30 (95 kg/m3 de hierro) | G83: 1 | H83: 0 | I83: 2471.4098 | J83: 2471.4098 | K83: PTO-0304|MAT | L83: 1 | M83: PTO-0304|MAT|1 | N83: 1 | O83: 0 | P83: 179 | Q83: 0 | R83: 3.04 | S83: =IFERROR(_xlfn.XLOOKUP(R83,'1_Presupuesto'!$E:$E,'1_Presupuesto'!$D:$D),"") -> -
A84: PTO-0304 | B84: MO | C84: OTR | D84: SUB-0011 | E84: HA. De cabezales (90 kg/m3 de hierro) | F84: j | G84: 1 | H84: 0 | I84: 148967.56 | J84: 148967.56 | K84: PTO-0304|MO | L84: 1 | M84: PTO-0304|MO|1 | N84: 1 | O84: 0 | P84: 179 | Q84: 0 | R84: 3.04 | S84: =IFERROR(_xlfn.XLOOKUP(R84,'1_Presupuesto'!$E:$E,'1_Presupuesto'!$D:$D),"") -> -
A85: PTO-0304 | B85: EQ | D85: EQ-0010 | E85: Herramientas/consumibles - Platea - H30 hidrófugo (95 kg/m3 de hier | G85: 1 | H85: 0 | I85: 2271.5846 | J85: 2271.5846 | K85: PTO-0304|EQ | L85: 1 | M85: PTO-0304|EQ|1 | N85: 1 | O85: 0 | P85: 179 | Q85: 0 | R85: 3.04 | S85: =IFERROR(_xlfn.XLOOKUP(R85,'1_Presupuesto'!$E:$E,'1_Presupuesto'!$D:$D),"") -> -
A86: PTO-0305 | B86: MAT | C86: OTR | D86: MAT-0043 | E86: Encofrado Losa maciza visto - H30 (120 kg/m3 de hierro) | G86: 1 | H86: 0 | I86: 40150.005 | J86: 40150.005 | K86: PTO-0305|MAT | L86: 1 | M86: PTO-0305|MAT|1 | N86: 1 | O86: 0 | P86: 10 | Q86: 0 | R86: 3.05 | S86: =IFERROR(_xlfn.XLOOKUP(R86,'1_Presupuesto'!$E:$E,'1_Presupuesto'!$D:$D),"") -> Homigón MO
A87: PTO-0305 | B87: MO | C87: ALB | D87: MO-ESP | E87: ESPECIALIZADO | F87: j | G87: 1.9965872 | H87: 0 | I87: 75113.05 | J87: 149969.75 | K87: PTO-0305|MO | L87: 1 | M87: PTO-0305|MO|1 | N87: 1 | O87: 1.9965872 | P87: 10 | Q87: 19.965872 | R87: 3.05 | S87: =IFERROR(_xlfn.XLOOKUP(R87,'1_Presupuesto'!$E:$E,'1_Presupuesto'!$D:$D),"") -> Homigón MO
A88: PTO-0305 | B88: MO | C88: ALB | D88: MO-OFI | E88: OFICIAL | F88: j | G88: 1.9965872 | H88: 0 | I88: 65360.25 | J88: 130497.44 | K88: PTO-0305|MO | L88: 2 | M88: PTO-0305|MO|2 | N88: 1 | O88: 1.9965872 | P88: 10 | Q88: 19.965872 | R88: 3.05 | S88: =IFERROR(_xlfn.XLOOKUP(R88,'1_Presupuesto'!$E:$E,'1_Presupuesto'!$D:$D),"") -> Homigón MO
A89: PTO-0305 | B89: MO | C89: ALB | D89: MO-AYU | E89: AYUDANTE | F89: j | G89: 0.12286652 | H89: 0 | I89: 49934.24 | J89: 6135.2463 | K89: PTO-0305|MO | L89: 3 | M89: PTO-0305|MO|3 | N89: 1 | O89: 0.12286652 | P89: 10 | Q89: 1.2286652 | R89: 3.05 | S89: =IFERROR(_xlfn.XLOOKUP(R89,'1_Presupuesto'!$E:$E,'1_Presupuesto'!$D:$D),"") -> Homigón MO
A90: PTO-0305 | B90: EQ | D90: EQ-0011 | E90: Herramientas/consumibles - Rampa - H30 (120 kg/m3 de hierro) | G90: 1 | H90: 0 | I90: 4901.2865 | J90: 4901.2865 | K90: PTO-0305|EQ | L90: 1 | M90: PTO-0305|EQ|1 | N90: 1 | O90: 0 | P90: 10 | Q90: 0 | R90: 3.05 | S90: =IFERROR(_xlfn.XLOOKUP(R90,'1_Presupuesto'!$E:$E,'1_Presupuesto'!$D:$D),"") -> Homigón MO
A91: PTO-0306 | B91: MAT | C91: OTR | D91: MAT-0044 | E91: Encofrado Losa maciza - H30 (120 kg/m3 de hierro) | G91: 1 | H91: 0 | I91: 32975.501 | J91: 32975.501 | K91: PTO-0306|MAT | L91: 1 | M91: PTO-0306|MAT|1 | N91: 1 | O91: 0 | P91: 177 | Q91: 0 | R91: 3.06 | S91: =IFERROR(_xlfn.XLOOKUP(R91,'1_Presupuesto'!$E:$E,'1_Presupuesto'!$D:$D),"") -> Homigón MO
A92: PTO-0306 | B92: MO | C92: ALB | D92: MO-ESP | E92: ESPECIALIZADO | F92: j | G92: 1.3310581 | H92: 0 | I92: 75113.05 | J92: 99979.834 | K92: PTO-0306|MO | L92: 1 | M92: PTO-0306|MO|1 | N92: 1 | O92: 1.3310581 | P92: 177 | Q92: 235.59729 | R92: 3.06 | S92: =IFERROR(_xlfn.XLOOKUP(R92,'1_Presupuesto'!$E:$E,'1_Presupuesto'!$D:$D),"") -> Homigón MO
A93: PTO-0306 | B93: MO | C93: ALB | D93: MO-OFI | E93: OFICIAL | F93: j | G93: 1.3310581 | H93: 0 | I93: 65360.25 | J93: 86998.291 | K93: PTO-0306|MO | L93: 2 | M93: PTO-0306|MO|2 | N93: 1 | O93: 1.3310581 | P93: 177 | Q93: 235.59729 | R93: 3.06 | S93: =IFERROR(_xlfn.XLOOKUP(R93,'1_Presupuesto'!$E:$E,'1_Presupuesto'!$D:$D),"") -> Homigón MO
A94: PTO-0306 | B94: MO | C94: ALB | D94: MO-AYU | E94: AYUDANTE | F94: j | G94: 0.08191101 | H94: 0 | I94: 49934.24 | J94: 4090.164 | K94: PTO-0306|MO | L94: 3 | M94: PTO-0306|MO|3 | N94: 1 | O94: 0.08191101 | P94: 177 | Q94: 14.498249 | R94: 3.06 | S94: =IFERROR(_xlfn.XLOOKUP(R94,'1_Presupuesto'!$E:$E,'1_Presupuesto'!$D:$D),"") -> Homigón MO
A95: PTO-0306 | B95: EQ | D95: EQ-0012 | E95: Herramientas/consumibles - Losa maciza - H30 (110 kg/m3 de hierro) | G95: 1 | H95: 0 | I95: 3360.6568 | J95: 3360.6568 | K95: PTO-0306|EQ | L95: 1 | M95: PTO-0306|EQ|1 | N95: 1 | O95: 0 | P95: 177 | Q95: 0 | R95: 3.06 | S95: =IFERROR(_xlfn.XLOOKUP(R95,'1_Presupuesto'!$E:$E,'1_Presupuesto'!$D:$D),"") -> Homigón MO
A96: PTO-0307 | B96: MAT | C96: OTR | D96: MAT-0045 | E96: Encofrado Vigas - H30 (130 kg/m3 de hierro) | G96: 1 | H96: 0 | I96: 94228.958 | J96: 94228.958 | K96: PTO-0307|MAT | L96: 1 | M96: PTO-0307|MAT|1 | N96: 1 | O96: 0 | P96: 65 | Q96: 0 | R96: 3.07 | S96: =IFERROR(_xlfn.XLOOKUP(R96,'1_Presupuesto'!$E:$E,'1_Presupuesto'!$D:$D),"") -> Homigón MO
A97: PTO-0307 | B97: MO | C97: ALB | D97: MO-ESP | E97: ESPECIALIZADO | F97: j | G97: 3.2673112 | H97: 0 | I97: 75113.05 | J97: 245417.71 | K97: PTO-0307|MO | L97: 1 | M97: PTO-0307|MO|1 | N97: 1 | O97: 3.2673112 | P97: 65 | Q97: 212.37523 | R97: 3.07 | S97: =IFERROR(_xlfn.XLOOKUP(R97,'1_Presupuesto'!$E:$E,'1_Presupuesto'!$D:$D),"") -> Homigón MO
A98: PTO-0307 | B98: MO | C98: ALB | D98: MO-OFI | E98: OFICIAL | F98: j | G98: 3.2673112 | H98: 0 | I98: 65360.25 | J98: 213552.28 | K98: PTO-0307|MO | L98: 2 | M98: PTO-0307|MO|2 | N98: 1 | O98: 3.2673112 | P98: 65 | Q98: 212.37523 | R98: 3.07 | S98: =IFERROR(_xlfn.XLOOKUP(R98,'1_Presupuesto'!$E:$E,'1_Presupuesto'!$D:$D),"") -> Homigón MO
A99: PTO-0307 | B99: MO | C99: ALB | D99: MO-AYU | E99: AYUDANTE | F99: j | G99: 0.07969101 | H99: 0 | I99: 49934.24 | J99: 3979.31 | K99: PTO-0307|MO | L99: 3 | M99: PTO-0307|MO|3 | N99: 1 | O99: 0.07969101 | P99: 65 | Q99: 5.1799156 | R99: 3.07 | S99: =IFERROR(_xlfn.XLOOKUP(R99,'1_Presupuesto'!$E:$E,'1_Presupuesto'!$D:$D),"") -> Homigón MO
A100: PTO-0307 | B100: EQ | D100: EQ-0013 | E100: Herramientas/consumibles - Vigas - H30 (140 kg/m3 de hierro) | G100: 1 | H100: 0 | I100: 8357.6737 | J100: 8357.6737 | K100: PTO-0307|EQ | L100: 1 | M100: PTO-0307|EQ|1 | N100: 1 | O100: 0 | P100: 65 | Q100: 0 | R100: 3.07 | S100: =IFERROR(_xlfn.XLOOKUP(R100,'1_Presupuesto'!$E:$E,'1_Presupuesto'!$D:$D),"") -> Homigón MO
...

Sheet 2_Gastos_DirInd
A1: Fecha | B1: Tipo | C1: Concepto | D1: Monto

Sheet 2_Quincenas
A1: Resumen Consolidado por Obra (Horas)
A3: Mes | B3: Período | C3: Obra | D3: Categoría | E3: Rubro | F3: Horas totales | G3: Horas normales | H3: Horas extra 50% | I3: Horas extra 100% | K3: Costo Hs. Normales | L3: Costo Hs. Extra 50% | M3: Costo Hs. Extra 100% | N3: Total | O3: Total Descontado
A4: 45689 | B4: 2Q | C4: EL SALVADOR | D4: OFICIAL | E4: Homigón MO | F4: =G4+H4+I4 -> 248 | G4: 248 | H4: 0 | I4: 0
A5: 45689 | B5: 2Q | C5: EL SALVADOR | D5: AYUDANTE | E5: Homigón MO | F5: =G5+H5+I5 -> 8 | G5: 8 | H5: 0 | I5: 0
A6: 45717 | B6: 1Q | C6: EL SALVADOR | D6: OFICIAL | E6: Homigón MO | F6: =G6+H6+I6 -> 280 | G6: 280 | H6: 0 | I6: 0
A7: 45717 | B7: 2Q | C7: EL SALVADOR | D7: CAPATAZ | E7: Homigón MO | F7: =G7+H7+I7 -> 136 | G7: 136 | H7: 0 | I7: 0
A8: 45717 | B8: 2Q | C8: EL SALVADOR | D8: OFICIAL | E8: Homigón MO | F8: =G8+H8+I8 -> 28 | G8: 28 | H8: 0 | I8: 0
A9: 45717 | B9: 2Q | C9: EL SALVADOR | D9: MEDIO OFICIAL | E9: Homigón MO | F9: =G9+H9+I9 -> 44 | G9: 44 | H9: 0 | I9: 0
A10: 45748 | B10: 1Q | C10: EL SALVADOR | D10: CAPATAZ | E10: Homigón MO | F10: =G10+H10+I10 -> 288 | G10: 288 | H10: 0 | I10: 0
A11: 45748 | B11: 1Q | C11: EL SALVADOR | D11: OFICIAL | E11: Homigón MO | F11: =G11+H11+I11 -> 304 | G11: 304 | H11: 0 | I11: 0
A12: 45748 | B12: 1Q | C12: EL SALVADOR | D12: MEDIO OFICIAL | E12: Homigón MO | F12: =G12+H12+I12 -> 88 | G12: 88 | H12: 0 | I12: 0
A13: 45748 | B13: 2Q | C13: EL SALVADOR | D13: CAPATAZ | E13: Homigón MO | F13: =G13+H13+I13 -> 384 | G13: 384 | H13: 0 | I13: 0
A14: 45748 | B14: 2Q | C14: EL SALVADOR | D14: OFICIAL | E14: Homigón MO | F14: =G14+H14+I14 -> 456 | G14: 456 | H14: 0 | I14: 0
A15: 45748 | B15: 2Q | C15: EL SALVADOR | D15: MEDIO OFICIAL | E15: Homigón MO | F15: =G15+H15+I15 -> 96 | G15: 96 | H15: 0 | I15: 0
... A166: 46143 | B166: 2Q | C166: EL SALVADOR | D166: AYUDANTE | E166: Sanitaria MO | F166: =G166+H166+I166 -> 88 | G166: 88 | H166: 0 | I166: 0

Sheet 2_Subcontratos
A1: SUBCONTRATOS — MAESTRO DE CONTRATOS
A3: Contrato# | B3: Proveedor | C3: Rubro | D3: Descripción | E3: Monto Presup. | F3: Ajusta CAC | G3: % Anticipo | H3: Pagado BASE+ANT | I3: CAC pagado | J3: CS pagado | K3: Total pagado | L3: Saldo disponible | M3: % consumido | N3: Estado
A4: SVD-SC-001 | B4: CELSI VIAL S.A. | C4: Movimiento de Suelos | D4: Movimiento de Suelos | E4: 20625000 | F4: SI | G4: 0 | H4: =SUMIFS('2_Movimientos'!$I:$I,'2_Movimientos'!$Q:$Q,$A4,'2_Movimientos'!$R:$R,"BASE")+SUMIFS('2_Movimientos'!$I:$I,'2_Movimientos'!$Q:$Q,$A4,'2_Movimientos'!$R:$R,"ANT") -> 0 | I4: =SUMIFS('2_Movimientos'!$I:$I,'2_Movimientos'!$Q:$Q,$A4,'2_Movimientos'!$R:$R,"CAC") -> 0 | J4: =SUMIFS('2_Movimientos'!$I:$I,'2_Movimientos'!$Q:$Q,$A4,'2_Movimientos'!$R:$R,"CS") -> 0 | K4: =H4+I4+J4 -> 0 | L4: =$E4-H4 -> 20625000 | M4: =IFERROR(H4/$E4,0) -> 0 | N4: =IF(L4<=0,"🔴 Sin saldo",IF(M4>=0.9,"🟠 <10% saldo","🟢 OK")) -> 🟢 OK
A5: SVD-SC-002 | B5: SERENO DE OBRA | C5: Albañilería MO | D5: ALBAMO | E5: 0 | F5: NO | G5: 0 | H5: =SUMIFS('2_Movimientos'!$I:$I,'2_Movimientos'!$Q:$Q,$A5,'2_Movimientos'!$R:$R,"BASE")+SUMIFS('2_Movimientos'!$I:$I,'2_Movimientos'!$Q:$Q,$A5,'2_Movimientos'!$R:$R,"ANT") -> 0 | I5: =SUMIFS('2_Movimientos'!$I:$I,'2_Movimientos'!$Q:$Q,$A5,'2_Movimientos'!$R:$R,"CAC") -> 0 | J5: =SUMIFS('2_Movimientos'!$I:$I,'2_Movimientos'!$Q:$Q,$A5,'2_Movimientos'!$R:$R,"CS") -> 0 | K5: =H5+I5+J5 -> 0 | L5: =$E5-H5 -> 0 | M5: =IFERROR(H5/$E5,0) -> 0 | N5: =IF(L5<=0,"🔴 Sin saldo",IF(M5>=0.9,"🟠 <10% saldo","🟢 OK")) -> 🔴 Sin saldo
A6: SVD-SC-003 | B6: SILVIO AGUIRRE | C6: Eléctrico MO | D6: ELECMO | E6: 37170000 | F6: SI | G6: 0 | H6: =SUMIFS('2_Movimientos'!$I:$I,'2_Movimientos'!$Q:$Q,$A6,'2_Movimientos'!$R:$R,"BASE")+SUMIFS('2_Movimientos'!$I:$I,'2_Movimientos'!$Q:$Q,$A6,'2_Movimientos'!$R:$R,"ANT") -> 0 | I6: =SUMIFS('2_Movimientos'!$I:$I,'2_Movimientos'!$Q:$Q,$A6,'2_Movimientos'!$R:$R,"CAC") -> 0 | J6: =SUMIFS('2_Movimientos'!$I:$I,'2_Movimientos'!$Q:$Q,$A6,'2_Movimientos'!$R:$R,"CS") -> 0 | K6: =H6+I6+J6 -> 0 | L6: =$E6-H6 -> 37170000 | M6: =IFERROR(H6/$E6,0) -> 0 | N6: =IF(L6<=0,"🔴 Sin saldo",IF(M6>=0.9,"🟠 <10% saldo","🟢 OK")) -> 🟢 OK
A7: SVD-SC-004 | B7: EMANUEL PASQUARIELLO | C7: H. Gestoria | D7: GESTORIA | E7: 180000 | F7: NO | G7: 0 | H7: =SUMIFS('2_Movimientos'!$I:$I,'2_Movimientos'!$Q:$Q,$A7,'2_Movimientos'!$R:$R,"BASE")+SUMIFS('2_Movimientos'!$I:$I,'2_Movimientos'!$Q:$Q,$A7,'2_Movimientos'!$R:$R,"ANT") -> 0 | I7: =SUMIFS('2_Movimientos'!$I:$I,'2_Movimientos'!$Q:$Q,$A7,'2_Movimientos'!$R:$R,"CAC") -> 0 | J7: =SUMIFS('2_Movimientos'!$I:$I,'2_Movimientos'!$Q:$Q,$A7,'2_Movimientos'!$R:$R,"CS") -> 0 | K7: =H7+I7+J7 -> 0 | L7: =$E7-H7 -> 180000 | M7: =IFERROR(H7/$E7,0) -> 0 | N7: =IF(L7<=0,"🔴 Sin saldo",IF(M7>=0.9,"🟠 <10% saldo","🟢 OK")) -> 🟢 OK
A8: SVD-SC-005 | B8: FERNANDO AMARILLA | C8: Eléctrico MO | D8: ELECMO | E8: 550000 | F8: NO | G8: 0 | H8: =SUMIFS('2_Movimientos'!$I:$I,'2_Movimientos'!$Q:$Q,$A8,'2_Movimientos'!$R:$R,"BASE")+SUMIFS('2_Movimientos'!$I:$I,'2_Movimientos'!$Q:$Q,$A8,'2_Movimientos'!$R:$R,"ANT") -> 0 | I8: =SUMIFS('2_Movimientos'!$I:$I,'2_Movimientos'!$Q:$Q,$A8,'2_Movimientos'!$R:$R,"CAC") -> 0 | J8: =SUMIFS('2_Movimientos'!$I:$I,'2_Movimientos'!$Q:$Q,$A8,'2_Movimientos'!$R:$R,"CS") -> 0 | K8: =H8+I8+J8 -> 0 | L8: =$E8-H8 -> 550000 | M8: =IFERROR(H8/$E8,0) -> 0 | N8: =IF(L8<=0,"🔴 Sin saldo",IF(M8>=0.9,"🟠 <10% saldo","🟢 OK")) -> 🟢 OK
A9: SVD-SC-006 | B9: ELVIO CESPEDES | C9: Durlock MO | D9: Proyectado/Revoque/Yeso/Carp.Monolitico | E9: 66989647 | F9: SI | G9: 0 | H9: =SUMIFS('2_Movimientos'!$I:$I,'2_Movimientos'!$Q:$Q,$A9,'2_Movimientos'!$R:$R,"BASE")+SUMIFS('2_Movimientos'!$I:$I,'2_Movimientos'!$Q:$Q,$A9,'2_Movimientos'!$R:$R,"ANT") -> 0 | I9: =SUMIFS('2_Movimientos'!$I:$I,'2_Movimientos'!$Q:$Q,$A9,'2_Movimientos'!$R:$R,"CAC") -> 0 | J9: =SUMIFS('2_Movimientos'!$I:$I,'2_Movimientos'!$Q:$Q,$A9,'2_Movimientos'!$R:$R,"CS") -> 0 | K9: =H9+I9+J9 -> 0 | L9: =$E9-H9 -> 66989647 | M9: =IFERROR(H9/$E9,0) -> 0 | N9: =IF(L9<=0,"🔴 Sin saldo",IF(M9>=0.9,"🟠 <10% saldo","🟢 OK")) -> 🟢 OK
A10: SVD-SC-007 | B10: MARCELO FABIAN SILVA | C10: Termomecánica MO | D10: INSTALACION AIRE ACONDICIONADO | E10: 18570000 | F10: NO | G10: 0 | H10: =SUMIFS('2_Movimientos'!$I:$I,'2_Movimientos'!$Q:$Q,$A10,'2_Movimientos'!$R:$R,"BASE")+SUMIFS('2_Movimientos'!$I:$I,'2_Movimientos'!$Q:$Q,$A10,'2_Movimientos'!$R:$R,"ANT") -> 0 | I10: =SUMIFS('2_Movimientos'!$I:$I,'2_Movimientos'!$Q:$Q,$A10,'2_Movimientos'!$R:$R,"CAC") -> 0 | J10: =SUMIFS('2_Movimientos'!$I:$I,'2_Movimientos'!$Q:$Q,$A10,'2_Movimientos'!$R:$R,"CS") -> 0 | K10: =H10+I10+J10 -> 0 | L10: =$E10-H10 -> 18570000 | M10: =IFERROR(H10/$E10,0) -> 0 | N10: =IF(L10<=0,"🔴 Sin saldo",IF(M10>=0.9,"🟠 <10% saldo","🟢 OK")) -> 🟢 OK
A11: SVD-SC-008 | B11: EZEQUIEL MENDOZA | C11: Termomecánica MO | D11: INSTALACION AIRE ACONDICIONADO | E11: 4200000 | F11: NO | G11: 0 | H11: =SUMIFS('2_Movimientos'!$I:$I,'2_Movimientos'!$Q:$Q,$A11,'2_Movimientos'!$R:$R,"BASE")+SUMIFS('2_Movimientos'!$I:$I,'2_Movimientos'!$Q:$Q,$A11,'2_Movimientos'!$R:$R,"ANT") -> 0 | I11: =SUMIFS('2_Movimientos'!$I:$I,'2_Movimientos'!$Q:$Q,$A11,'2_Movimientos'!$R:$R,"CAC") -> 0 | J11: =SUMIFS('2_Movimientos'!$I:$I,'2_Movimientos'!$Q:$Q,$A11,'2_Movimientos'!$R:$R,"CS") -> 0 | K11: =H11+I11+J11 -> 0 | L11: =$E11-H11 -> 4200000 | M11: =IFERROR(H11/$E11,0) -> 0 | N11: =IF(L11<=0,"🔴 Sin saldo",IF(M11>=0.9,"🟠 <10% saldo","🟢 OK")) -> 🟢 OK
A12: SVD-SC-009 | B12: MARCELO SCHULZE | C12: Revestimiento MO | D12: HORMIGON ALISADO - Revestimiento | E12: 4361700 | F12: NO | G12: 0 | H12: =SUMIFS('2_Movimientos'!$I:$I,'2_Movimientos'!$Q:$Q,$A12,'2_Movimientos'!$R:$R,"BASE")+SUMIFS('2_Movimientos'!$I:$I,'2_Movimientos'!$Q:$Q,$A12,'2_Movimientos'!$R:$R,"ANT") -> 0 | I12: =SUMIFS('2_Movimientos'!$I:$I,'2_Movimientos'!$Q:$Q,$A12,'2_Movimientos'!$R:$R,"CAC") -> 0 | J12: =SUMIFS('2_Movimientos'!$I:$I,'2_Movimientos'!$Q:$Q,$A12,'2_Movimientos'!$R:$R,"CS") -> 0 | K12: =H12+I12+J12 -> 0 | L12: =$E12-H12 -> 4361700 | M12: =IFERROR(H12/$E12,0) -> 0 | N12: =IF(L12<=0,"🔴 Sin saldo",IF(M12>=0.9,"🟠 <10% saldo","🟢 OK")) -> 🟢 OK
A13: SVD-SC-010 | B13: MANSILLA DERQUI | C13: Termomecánica MO | D13: CALEFACCION PISO RADIANTE | E13: 40300000 | F13: NO | G13: 0 | H13: =SUMIFS('2_Movimientos'!$I:$I,'2_Movimientos'!$Q:$Q,$A13,'2_Movimientos'!$R:$R,"BASE")+SUMIFS('2_Movimientos'!$I:$I,'2_Movimientos'!$Q:$Q,$A13,'2_Movimientos'!$R:$R,"ANT") -> 0 | I13: =SUMIFS('2_Movimientos'!$I:$I,'2_Movimientos'!$Q:$Q,$A13,'2_Movimientos'!$R:$R,"CAC") -> 0 | J13: =SUMIFS('2_Movimientos'!$I:$I,'2_Movimientos'!$Q:$Q,$A13,'2_Movimientos'!$R:$R,"CS") -> 0 | K13: =H13+I13+J13 -> 0 | L13: =$E13-H13 -> 40300000 | M13: =IFERROR(H13/$E13,0) -> 0 | N13: =IF(L13<=0,"🔴 Sin saldo",IF(M13>=0.9,"🟠 <10% saldo","🟢 OK")) -> 🟢 OK

Sheet _Listas
A1: RUBROS CANÓNICOS (Plan de Cuentas Tezamat — rama 53 OBRA + especiales) | B1: Código | C1: TIPOS | E1: VALIDACIÓN — rubros de tarea ∈ plan de cuentas | I1: CONCEPTOS GASTOS DIR/IND | J1: Tipo
A2: Preliminares | B2: 53001 | C2: MT | E2: Rubros fuera de plan — 1_Presupuesto (A/B/C/D) | F2: =SUMPRODUCT(('1_Presupuesto'!A4:A219<>"")*('1_Presupuesto'!A4:A219<>"-")*ISNA(MATCH('1_Presupuesto'!A4:A219,$A$2:$A$34,0)))+SUMPRODUCT(('1_Presupuesto'!B4:B219<>"")*('1_Presupuesto'!B4:B219<>"-")*ISNA(MATCH('1_Presupuesto'!B4:B219,$A$2:$A$34,0)))+SUMPRODUCT(('1_Presupuesto'!C4:C219<>"")*('1_Presupuesto'!C4:C219<>"-")*ISNA(MATCH('1_Presupuesto'!C4:C219,$A$2:$A$34,0)))+SUMPRODUCT(('1_Presupuesto'!D4:D219<>"")*('1_Presupuesto'!D4:D219<>"-")*ISNA(MATCH('1_Presupuesto'!D4:D219,$A$2:$A$34,0))) -> 0 | G2: =IF(F2=0,"✓","⚠") -> ✓ | I2: Oficina en obra (6x3 c/AA) | J2: Directo
A3: Demolición | B3: 53002 | C3: MO | E3: Rubros fuera de plan — 2_Quincenas (E) | F3: =SUMPRODUCT(('2_Quincenas'!E4:E166<>"")*('2_Quincenas'!E4:E166<>"-")*ISNA(MATCH('2_Quincenas'!E4:E166,$A$2:$A$34,0))) -> 0 | G3: =IF(F3=0,"✓","⚠") -> ✓ | I3: Obrador 6x3 s/AA | J3: Directo
A4: Movimiento de Suelos | B4: 53003 | I4: Pañol (6x3) | J4: Directo
A5: Hormigón MT | B5: 53004 | I5: Baños | J5: Directo
A6: Homigón MO | B6: 53005 | I6: HyS permanente | J6: Directo
A7: Metálica MT | B7: 53006 | I7: Energía de obra | J7: Directo
A8: Metálica MO | B8: 53007 | I8: Agua de obra | J8: Directo
A9: Albañilería MT | B9: 53008 | I9: Proyecto (50%) | J9: Directo
A10: Albañilería MO | B10: 53009 | I10: Coordinacion de obra | J10: Directo
A11: Durlock MT | B11: 53010 | I11: Sobrestante | J11: Directo
A12: Durlock MO | B12: 53011 | I12: Capataz | J12: Directo
A13: Aberturas | B13: 53012 | I13: Logistica | J13: Directo
A14: Revestimiento MT | B14: 53013 | I14: Vehiculo obra | J14: Directo
A15: Revestimiento MO | B15: 53014 | I15: Payroll - Socios | J15: Indirecto
... A17: Pintura MO | B17: 53016 | I17: Payroll - Administración | J17: Indirecto
A18: Sanitaria MT | B18: 53017
A19: Sanitaria MO | B19: 53018
A20: Eléctrico MT | B20: 53019
A21: Eléctrico MO | B21: 53020
A22: Provisiones | B22: 53021
A23: Gastos Generales | B23: 53022
A24: Varios Ferreteria | B24: 53023
A25: Termomecánica MT | B25: 53024
A26: Termomecánica MO | B26: 53025
A27: Seguridad e Higiene | B27: 53026
A28: Herrería MT | B28: 53027
A29: Herrería MO | B29: 53028
... A34: Supervisión de Obra MO | B34: 52209

Sheet Cert_OC_Cliente
A1: Obra | B1: ID OC | C1: Descripcion | D1: Presupuesto aprobado | E1: % anticipo | F1: Mes base CAC | G1: Indice base CAC | H1: % Blanco sugerido | I1: % Negro sugerido | J1: % desacopio sugerido | K1: % IVA sugerido | L1: Presupuesto | M1: Fecha anticipo
A2: SVD 4140 | B2: SVD-OC01 | C2: Pto 1 - Preliminares + Mov.Suelo + Hormigón | D2: 421306052 | E2: 0.2 | F2: 45536 | G2: =_xlfn.XLOOKUP(F2,'0_Indice_CAC'!$A:$A,'0_Indice_CAC'!$B:$B) -> 14366.9 | H2: 0.3745 | I2: 0.6255 | J2: 0.2 | K2: 0.105 | L2: PTO 01
A3: SVD 4140 | B3: SVD-OC02 | C3: Pto 2 - Albañilería + Instalaciones + Terminaciones | D3: 7.3685713e+08 | E3: 0.4 | F3: 45536 | G3: =_xlfn.XLOOKUP(F3,'0_Indice_CAC'!$A:$A,'0_Indice_CAC'!$B:$B) -> 14366.9 | H3: 0.2407 | I3: 0.7593 | J3: 0.4 | K3: 0.105 | L3: PTO 02
A4: SVD 4140 | B4: SVD-OC03 | C4: Adicionales / Trabajos Complementarios | D4: 15315355 | E4: 0 | F4: 45536 | G4: =_xlfn.XLOOKUP(F4,'0_Indice_CAC'!$A:$A,'0_Indice_CAC'!$B:$B) -> 14366.9 | H4: 0.31 | I4: 0.69 | J4: 0 | K4: 0.105 | L4: PTO 03

Sheet Cert_App_Output
A1: Obra | B1: ID OC | C1: ID Certif | D1: Fecha | E1: Cod. tarea | F1: % anterior | G1: % actual | H1: % total | I1: PV total tarea | J1: $ base tarea (cert act.) | K1: Presupuesto | L1: Control vs Ppto
A2: SVD 4140 | B2: SVD-OC01 | C2: SVD-OC01-C01 | D2: 45747 | E2: 1.02 | F2: 0 | G2: 0.65 | H2: =F2+G2 -> 0.65 | I2: 1138764 | J2: =G2*I2 -> 740196.6 | K2: =_xlfn.XLOOKUP(B2,Cert_OC_Cliente!$B:$B,Cert_OC_Cliente!$L:$L) -> PTO 01 | L2: =IF($E2="","",IF(AND(ISNUMBER($I2),$H2<=1.0001),"✓","⚠")) -> ✓
A3: SVD 4140 | B3: SVD-OC01 | C3: SVD-OC01-C01 | D3: 45747 | E3: 1.05 | F3: 0 | G3: 0.5 | H3: =F3+G3 -> 0.5 | I3: 7548771 | J3: =G3*I3 -> 3774385.5 | K3: =_xlfn.XLOOKUP(B3,Cert_OC_Cliente!$B:$B,Cert_OC_Cliente!$L:$L) -> PTO 01 | L3: =IF($E3="","",IF(AND(ISNUMBER($I3),$H3<=1.0001),"✓","⚠")) -> ✓
A4: SVD 4140 | B4: SVD-OC01 | C4: SVD-OC01-C01 | D4: 45747 | E4: 1.06 | F4: 0 | G4: 0.3 | H4: =F4+G4 -> 0.3 | I4: 1176084 | J4: =G4*I4 -> 352825.2 | K4: =_xlfn.XLOOKUP(B4,Cert_OC_Cliente!$B:$B,Cert_OC_Cliente!$L:$L) -> PTO 01 | L4: =IF($E4="","",IF(AND(ISNUMBER($I4),$H4<=1.0001),"✓","⚠")) -> ✓
A5: SVD 4140 | B5: SVD-OC01 | C5: SVD-OC01-C01 | D5: 45747 | E5: 1.07 | F5: 0 | G5: 0.5 | H5: =F5+G5 -> 0.5 | I5: 1731320 | J5: =G5*I5 -> 865660 | K5: =_xlfn.XLOOKUP(B5,Cert_OC_Cliente!$B:$B,Cert_OC_Cliente!$L:$L) -> PTO 01 | L5: =IF($E5="","",IF(AND(ISNUMBER($I5),$H5<=1.0001),"✓","⚠")) -> ✓
A6: SVD 4140 | B6: SVD-OC01 | C6: SVD-OC01-C01 | D6: 45747 | E6: 1.09 | F6: 0 | G6: 0.5 | H6: =F6+G6 -> 0.5 | I6: 426487 | J6: =G6*I6 -> 213243.5 | K6: =_xlfn.XLOOKUP(B6,Cert_OC_Cliente!$B:$B,Cert_OC_Cliente!$L:$L) -> PTO 01 | L6: =IF($E6="","",IF(AND(ISNUMBER($I6),$H6<=1.0001),"✓","⚠")) -> ✓
A7: SVD 4140 | B7: SVD-OC01 | C7: SVD-OC01-C01 | D7: 45747 | E7: 1.1 | F7: 0 | G7: 1 | H7: =F7+G7 -> 1 | I7: 9803685 | J7: =G7*I7 -> 9803685 | K7: =_xlfn.XLOOKUP(B7,Cert_OC_Cliente!$B:$B,Cert_OC_Cliente!$L:$L) -> PTO 01 | L7: =IF($E7="","",IF(AND(ISNUMBER($I7),$H7<=1.0001),"✓","⚠")) -> ✓
A8: SVD 4140 | B8: SVD-OC01 | C8: SVD-OC01-C01 | D8: 45747 | E8: 2.01 | F8: 0 | G8: 0.35 | H8: =F8+G8 -> 0.35 | I8: 41891940 | J8: =G8*I8 -> 14662179 | K8: =_xlfn.XLOOKUP(B8,Cert_OC_Cliente!$B:$B,Cert_OC_Cliente!$L:$L) -> PTO 01 | L8: =IF($E8="","",IF(AND(ISNUMBER($I8),$H8<=1.0001),"✓","⚠")) -> ✓
A9: SVD 4140 | B9: SVD-OC01 | C9: SVD-OC01-C01 | D9: 45747 | E9: 24.01 | F9: 0 | G9: 0.1 | H9: =F9+G9 -> 0.1 | I9: 6025104 | J9: =G9*I9 -> 602510.4 | K9: =_xlfn.XLOOKUP(B9,Cert_OC_Cliente!$B:$B,Cert_OC_Cliente!$L:$L) -> PTO 01 | L9: =IF($E9="","",IF(AND(ISNUMBER($I9),$H9<=1.0001),"✓","⚠")) -> ✓
A10: SVD 4140 | B10: SVD-OC01 | C10: SVD-OC01-C01 | D10: 45747 | E10: 24.03 | F10: 0 | G10: 0.1 | H10: =F10+G10 -> 0.1 | I10: 1508264 | J10: =G10*I10 -> 150826.4 | K10: =_xlfn.XLOOKUP(B10,Cert_OC_Cliente!$B:$B,Cert_OC_Cliente!$L:$L) -> PTO 01 | L10: =IF($E10="","",IF(AND(ISNUMBER($I10),$H10<=1.0001),"✓","⚠")) -> ✓
A11: SVD 4140 | B11: SVD-OC01 | C11: SVD-OC01-C01 | D11: 45747 | E11: 25.01 | F11: 0 | G11: 0.1 | H11: =F11+G11 -> 0.1 | I11: 38192848 | J11: =G11*I11 -> 3819284.8 | K11: =_xlfn.XLOOKUP(B11,Cert_OC_Cliente!$B:$B,Cert_OC_Cliente!$L:$L) -> PTO 01 | L11: =IF($E11="","",IF(AND(ISNUMBER($I11),$H11<=1.0001),"✓","⚠")) -> ✓
A12: SVD 4140 | B12: SVD-OC01 | C12: SVD-OC01-C01 | D12: 45747 | E12: 25.02 | F12: 0 | G12: 0.1 | H12: =F12+G12 -> 0.1 | I12: 5027536 | J12: =G12*I12 -> 502753.6 | K12: =_xlfn.XLOOKUP(B12,Cert_OC_Cliente!$B:$B,Cert_OC_Cliente!$L:$L) -> PTO 01 | L12: =IF($E12="","",IF(AND(ISNUMBER($I12),$H12<=1.0001),"✓","⚠")) -> ✓
A13: SVD 4140 | B13: SVD-OC01 | C13: SVD-OC01-C02 | D13: 45777 | E13: 1.06 | F13: 0.3 | G13: 0.2 | H13: =F13+G13 -> 0.5 | I13: 1176084 | J13: =G13*I13 -> 235216.8 | K13: =_xlfn.XLOOKUP(B13,Cert_OC_Cliente!$B:$B,Cert_OC_Cliente!$L:$L) -> PTO 01 | L13: =IF($E13="","",IF(AND(ISNUMBER($I13),$H13<=1.0001),"✓","⚠")) -> ✓
... A405: SVD 4140 | B405: SVD-OC02 | C405: SVD-OC02-C08 | D405: 46174 | E405: 8.07 | F405: 0 | G405: 0.05 | H405: =F405+G405 -> 0.05 | I405: 2426924 | J405: =G405*I405 -> 121346.2 | K405: =_xlfn.XLOOKUP(B405,Cert_OC_Cliente!$B:$B,Cert_OC_Cliente!$L:$L) -> PTO 02 | L405: =IF($E405="","",IF(AND(ISNUMBER($I405),$H405<=1.0001),"✓","⚠")) -> ✓

Sheet Cert_Cabecera
A1: ID Certif | B1: ID OC | C1: Fecha | D1: $ base bruta certif. | E1: % desacopio (madre) | F1: $ desacopio | G1: Subtotal neto | H1: Chequeo
A2: SVD-OC01-ANT | B2: =LEFT($A2,FIND("|",SUBSTITUTE($A2,"-","|",2))-1) -> SVD-OC01 | C2: =IFERROR(_xlfn.XLOOKUP($A2,Cert_App_Output!$C:$C,Cert_App_Output!$D:$D),"") | D2: =SUMIFS(Cert_App_Output!$J:$J,Cert_App_Output!$C:$C,$A2) -> 0 | E2: 0 | F2: =$D2*$E2 -> 0 | G2: =$D2-$F2 -> 0 | H2: =IF(COUNTIF(Cert_Calculo!$A:$A,$A2)>0,"OK","FALTA en Calculo") -> OK
A3: SVD-OC02-ANT | B3: =LEFT($A3,FIND("|",SUBSTITUTE($A3,"-","|",2))-1) -> SVD-OC02 | C3: =IFERROR(_xlfn.XLOOKUP($A3,Cert_App_Output!$C:$C,Cert_App_Output!$D:$D),"") | D3: =SUMIFS(Cert_App_Output!$J:$J,Cert_App_Output!$C:$C,$A3) -> 0 | E3: 0 | F3: =$D3*$E3 -> 0 | G3: =$D3-$F3 -> 0 | H3: =IF(COUNTIF(Cert_Calculo!$A:$A,$A3)>0,"OK","FALTA en Calculo") -> OK
A4: SVD-OC03-ANT | B4: =LEFT($A4,FIND("|",SUBSTITUTE($A4,"-","|",2))-1) -> SVD-OC03 | C4: =IFERROR(_xlfn.XLOOKUP($A4,Cert_App_Output!$C:$C,Cert_App_Output!$D:$D),"") | D4: =SUMIFS(Cert_App_Output!$J:$J,Cert_App_Output!$C:$C,$A4) -> 0 | E4: 0 | F4: =$D4*$E4 -> 0 | G4: =$D4-$F4 -> 0 | H4: =IF(COUNTIF(Cert_Calculo!$A:$A,$A4)>0,"OK","FALTA en Calculo") -> OK
A5: SVD-OC01-C01 | B5: =LEFT($A5,FIND("|",SUBSTITUTE($A5,"-","|",2))-1) -> SVD-OC01 | C5: =IFERROR(_xlfn.XLOOKUP($A5,Cert_App_Output!$C:$C,Cert_App_Output!$D:$D),"") -> 45747 | D5: =SUMIFS(Cert_App_Output!$J:$J,Cert_App_Output!$C:$C,$A5) -> 35487550 | E5: 0.2 | F5: =$D5*$E5 -> 7097510 | G5: =$D5-$F5 -> 28390040 | H5: =IF(COUNTIF(Cert_Calculo!$A:$A,$A5)>0,"OK","FALTA en Calculo") -> OK
A6: SVD-OC01-C02 | B6: =LEFT($A6,FIND("|",SUBSTITUTE($A6,"-","|",2))-1) -> SVD-OC01 | C6: =IFERROR(_xlfn.XLOOKUP($A6,Cert_App_Output!$C:$C,Cert_App_Output!$D:$D),"") -> 45777 | D6: =SUMIFS(Cert_App_Output!$J:$J,Cert_App_Output!$C:$C,$A6) -> 25040749 | E6: 0.2 | F6: =$D6*$E6 -> 5008149.9 | G6: =$D6-$F6 -> 20032600 | H6: =IF(COUNTIF(Cert_Calculo!$A:$A,$A6)>0,"OK","FALTA en Calculo") -> OK
A7: SVD-OC01-C03 | B7: =LEFT($A7,FIND("|",SUBSTITUTE($A7,"-","|",2))-1) -> SVD-OC01 | C7: =IFERROR(_xlfn.XLOOKUP($A7,Cert_App_Output!$C:$C,Cert_App_Output!$D:$D),"") -> 45807 | D7: =SUMIFS(Cert_App_Output!$J:$J,Cert_App_Output!$C:$C,$A7) -> 29836634 | E7: 0.2 | F7: =$D7*$E7 -> 5967326.9 | G7: =$D7-$F7 -> 23869308 | H7: =IF(COUNTIF(Cert_Calculo!$A:$A,$A7)>0,"OK","FALTA en Calculo") -> OK
A8: SVD-OC01-C04 | B8: =LEFT($A8,FIND("|",SUBSTITUTE($A8,"-","|",2))-1) -> SVD-OC01 | C8: =IFERROR(_xlfn.XLOOKUP($A8,Cert_App_Output!$C:$C,Cert_App_Output!$D:$D),"") -> 45835 | D8: =SUMIFS(Cert_App_Output!$J:$J,Cert_App_Output!$C:$C,$A8) -> 41634494 | E8: 0.2 | F8: =$D8*$E8 -> 8326898.8 | G8: =$D8-$F8 -> 33307595 | H8: =IF(COUNTIF(Cert_Calculo!$A:$A,$A8)>0,"OK","FALTA en Calculo") -> OK
A9: SVD-OC01-C05 | B9: =LEFT($A9,FIND("|",SUBSTITUTE($A9,"-","|",2))-1) -> SVD-OC01 | C9: =IFERROR(_xlfn.XLOOKUP($A9,Cert_App_Output!$C:$C,Cert_App_Output!$D:$D),"") -> 45861 | D9: =SUMIFS(Cert_App_Output!$J:$J,Cert_App_Output!$C:$C,$A9) -> 40708426 | E9: 0.2 | F9: =$D9*$E9 -> 8141685.1 | G9: =$D9-$F9 -> 32566741 | H9: =IF(COUNTIF(Cert_Calculo!$A:$A,$A9)>0,"OK","FALTA en Calculo") -> OK
A10: SVD-OC01-C06 | B10: =LEFT($A10,FIND("|",SUBSTITUTE($A10,"-","|",2))-1) -> SVD-OC01 | C10: =IFERROR(_xlfn.XLOOKUP($A10,Cert_App_Output!$C:$C,Cert_App_Output!$D:$D),"") -> 45898 | D10: =SUMIFS(Cert_App_Output!$J:$J,Cert_App_Output!$C:$C,$A10) -> 60880923 | E10: 0.2 | F10: =$D10*$E10 -> 12176185 | G10: =$D10-$F10 -> 48704739 | H10: =IF(COUNTIF(Cert_Calculo!$A:$A,$A10)>0,"OK","FALTA en Calculo") -> OK
A11: SVD-OC01-C07 | B11: =LEFT($A11,FIND("|",SUBSTITUTE($A11,"-","|",2))-1) -> SVD-OC01 | C11: =IFERROR(_xlfn.XLOOKUP($A11,Cert_App_Output!$C:$C,Cert_App_Output!$D:$D),"") -> 45931 | D11: =SUMIFS(Cert_App_Output!$J:$J,Cert_App_Output!$C:$C,$A11) -> 44531102 | E11: 0.2 | F11: =$D11*$E11 -> 8906220.4 | G11: =$D11-$F11 -> 35624881 | H11: =IF(COUNTIF(Cert_Calculo!$A:$A,$A11)>0,"OK","FALTA en Calculo") -> OK
A12: SVD-OC01-C08 | B12: =LEFT($A12,FIND("|",SUBSTITUTE($A12,"-","|",2))-1) -> SVD-OC01 | C12: =IFERROR(_xlfn.XLOOKUP($A12,Cert_App_Output!$C:$C,Cert_App_Output!$D:$D),"") -> 45957 | D12: =SUMIFS(Cert_App_Output!$J:$J,Cert_App_Output!$C:$C,$A12) -> 41228689 | E12: 0.2 | F12: =$D12*$E12 -> 8245737.9 | G12: =$D12-$F12 -> 32982952 | H12: =IF(COUNTIF(Cert_Calculo!$A:$A,$A12)>0,"OK","FALTA en Calculo") -> OK
A13: SVD-OC01-C09 | B13: =LEFT($A13,FIND("|",SUBSTITUTE($A13,"-","|",2))-1) -> SVD-OC01 | C13: =IFERROR(_xlfn.XLOOKUP($A13,Cert_App_Output!$C:$C,Cert_App_Output!$D:$D),"") -> 45988 | D13: =SUMIFS(Cert_App_Output!$J:$J,Cert_App_Output!$C:$C,$A13) -> 36158272 | E13: 0.2 | F13: =$D13*$E13 -> 7231654.4 | G13: =$D13-$F13 -> 28926618 | H13: =IF(COUNTIF(Cert_Calculo!$A:$A,$A13)>0,"OK","FALTA en Calculo") -> OK
... A24: SVD-OC02-C08 | B24: =LEFT($A24,FIND("|",SUBSTITUTE($A24,"-","|",2))-1) -> SVD-OC02 | C24: =IFERROR(_xlfn.XLOOKUP($A24,Cert_App_Output!$C:$C,Cert_App_Output!$D:$D),"") -> 46174 | D24: =SUMIFS(Cert_App_Output!$J:$J,Cert_App_Output!$C:$C,$A24) -> 85954678 | E24: 0.4 | F24: =$D24*$E24 -> 34381871 | G24: =$D24-$F24 -> 51572807 | H24: =IF(COUNTIF(Cert_Calculo!$A:$A,$A24)>0,"OK","FALTA en Calculo") -> OK

Sheet Cert_Calculo
A1: ID Certif | B1: ID Cert+Fact | C1: Tipo | D1: Obra | E1: ID OC | F1: Fecha | G1: $ base certif (total) | H1: % facturacion | I1: $ base de esta parte | J1: % desacopio | K1: $ desacopio | L1: $ base neta | M1: Indice base CAC | N1: Indice CAC a la fecha | O1: Ratio CAC | P1: $ CAC | Q1: $ base + CAC | R1: % IVA | S1: $ IVA | T1: $ Total certificacion | U1: USD MEP a la fecha | V1: U$ Total | X1: Control B/N suma 100% | Y1: Indice CAC override
A2: SVD-OC01-ANT | B2: SVD-OC01-ANT-B | C2: Blanco | D2: SVD 4140 | E2: SVD-OC01 | G2: 84261210 | H2: 0.3745 | I2: =$G2*H2 -> 31555823 | J2: =_xlfn.XLOOKUP($A2,Cert_Cabecera!$A:$A,Cert_Cabecera!$E:$E) -> 0 | K2: =-I2*J2 -> 0 | L2: =I2+K2 -> 31555823 | M2: =_xlfn.XLOOKUP($E2,Cert_OC_Cliente!$B:$B,Cert_OC_Cliente!$G:$G) -> 14366.9 | N2: =IF($Y2="",'0_Indice_CAC'!$B$4,$Y2) -> 14366.9 | O2: =N2/M2 -> 1 | P2: =L2*(O2-1) -> 0 | Q2: =L2+P2 -> 31555823 | R2: 0.105 | S2: =Q2*R2 -> 3313361.4 | T2: =Q2+S2 -> 34869185 | U2: 1170 | V2: =IF(C2="Negro",T2/U2,"") | X2: =IF(ABS(SUMIFS($H:$H,$A:$A,$A2)-1)<0.0001,"✓","⚠ ≠100%") -> ✓
A3: SVD-OC01-ANT | B3: SVD-OC01-ANT-N | C3: Negro | D3: SVD 4140 | E3: SVD-OC01 | G3: 84261210 | H3: 0.6255 | I3: =$G3*H3 -> 52705387 | J3: =_xlfn.XLOOKUP($A3,Cert_Cabecera!$A:$A,Cert_Cabecera!$E:$E) -> 0 | K3: =-I3*J3 -> 0 | L3: =I3+K3 -> 52705387 | M3: =_xlfn.XLOOKUP($E3,Cert_OC_Cliente!$B:$B,Cert_OC_Cliente!$G:$G) -> 14366.9 | N3: =IF($Y3="",'0_Indice_CAC'!$B$4,$Y3) -> 14366.9 | O3: =N3/M3 -> 1 | P3: =L3*(O3-1) -> 0 | Q3: =L3+P3 -> 52705387 | R3: 0 | S3: =Q3*R3 -> 0 | T3: =Q3+S3 -> 52705387 | U3: 1170 | V3: =IF(C3="Negro",T3/U3,"") -> 45047.339 | X3: =IF(ABS(SUMIFS($H:$H,$A:$A,$A3)-1)<0.0001,"✓","⚠ ≠100%") -> ✓
A4: SVD-OC02-ANT | B4: SVD-OC02-ANT-B | C4: Blanco | D4: SVD 4140 | E4: SVD-OC02 | G4: 2.9474285e+08 | H4: 0.2407 | I4: =$G4*H4 -> 70944605 | J4: =_xlfn.XLOOKUP($A4,Cert_Cabecera!$A:$A,Cert_Cabecera!$E:$E) -> 0 | K4: =-I4*J4 -> 0 | L4: =I4+K4 -> 70944605 | M4: =_xlfn.XLOOKUP($E4,Cert_OC_Cliente!$B:$B,Cert_OC_Cliente!$G:$G) -> 14366.9 | N4: =IF($Y4="",'0_Indice_CAC'!$B$4,$Y4) -> 14366.9 | O4: =N4/M4 -> 1 | P4: =L4*(O4-1) -> 0 | Q4: =L4+P4 -> 70944605 | R4: 0.105 | S4: =Q4*R4 -> 7449183.5 | T4: =Q4+S4 -> 78393788 | U4: 1170 | V4: =IF(C4="Negro",T4/U4,"") | X4: =IF(ABS(SUMIFS($H:$H,$A:$A,$A4)-1)<0.0001,"✓","⚠ ≠100%") -> ✓
A5: SVD-OC02-ANT | B5: SVD-OC02-ANT-N | C5: Negro | D5: SVD 4140 | E5: SVD-OC02 | G5: 2.9474285e+08 | H5: 0.7593 | I5: =$G5*H5 -> 2.2379825e+08 | J5: =_xlfn.XLOOKUP($A5,Cert_Cabecera!$A:$A,Cert_Cabecera!$E:$E) -> 0 | K5: =-I5*J5 -> 0 | L5: =I5+K5 -> 2.2379825e+08 | M5: =_xlfn.XLOOKUP($E5,Cert_OC_Cliente!$B:$B,Cert_OC_Cliente!$G:$G) -> 14366.9 | N5: =IF($Y5="",'0_Indice_CAC'!$B$4,$Y5) -> 14366.9 | O5: =N5/M5 -> 1 | P5: =L5*(O5-1) -> 0 | Q5: =L5+P5 -> 2.2379825e+08 | R5: 0 | S5: =Q5*R5 -> 0 | T5: =Q5+S5 -> 2.2379825e+08 | U5: 1170 | V5: =IF(C5="Negro",T5/U5,"") -> 191280.55 | X5: =IF(ABS(SUMIFS($H:$H,$A:$A,$A5)-1)<0.0001,"✓","⚠ ≠100%") -> ✓
A6: SVD-OC03-ANT | B6: SVD-OC03-ANT-B | C6: Blanco | D6: SVD 4140 | E6: SVD-OC03 | G6: 0 | H6: 0.31 | I6: =$G6*H6 -> 0 | J6: =_xlfn.XLOOKUP($A6,Cert_Cabecera!$A:$A,Cert_Cabecera!$E:$E) -> 0 | K6: =-I6*J6 -> 0 | L6: =I6+K6 -> 0 | M6: =_xlfn.XLOOKUP($E6,Cert_OC_Cliente!$B:$B,Cert_OC_Cliente!$G:$G) -> 14366.9 | N6: =IF($Y6="",'0_Indice_CAC'!$B$4,$Y6) -> 14366.9 | O6: =N6/M6 -> 1 | P6: =L6*(O6-1) -> 0 | Q6: =L6+P6 -> 0 | R6: 0.105 | S6: =Q6*R6 -> 0 | T6: =Q6+S6 -> 0 | U6: 1170 | V6: =IF(C6="Negro",T6/U6,"") | X6: =IF(ABS(SUMIFS($H:$H,$A:$A,$A6)-1)<0.0001,"✓","⚠ ≠100%") -> ✓
A7: SVD-OC03-ANT | B7: SVD-OC03-ANT-N | C7: Negro | D7: SVD 4140 | E7: SVD-OC03 | G7: 0 | H7: 0.69 | I7: =$G7*H7 -> 0 | J7: =_xlfn.XLOOKUP($A7,Cert_Cabecera!$A:$A,Cert_Cabecera!$E:$E) -> 0 | K7: =-I7*J7 -> 0 | L7: =I7+K7 -> 0 | M7: =_xlfn.XLOOKUP($E7,Cert_OC_Cliente!$B:$B,Cert_OC_Cliente!$G:$G) -> 14366.9 | N7: =IF($Y7="",'0_Indice_CAC'!$B$4,$Y7) -> 14366.9 | O7: =N7/M7 -> 1 | P7: =L7*(O7-1) -> 0 | Q7: =L7+P7 -> 0 | R7: 0 | S7: =Q7*R7 -> 0 | T7: =Q7+S7 -> 0 | U7: 1170 | V7: =IF(C7="Negro",T7/U7,"") -> 0 | X7: =IF(ABS(SUMIFS($H:$H,$A:$A,$A7)-1)<0.0001,"✓","⚠ ≠100%") -> ✓
A8: SVD-OC01-C01 | B8: SVD-OC01-C01-B | C8: Blanco | D8: =_xlfn.XLOOKUP(A8,Cert_App_Output!$C:$C,Cert_App_Output!$A:$A) -> SVD 4140 | E8: SVD-OC01 | F8: =_xlfn.XLOOKUP(A8,Cert_App_Output!$C:$C,Cert_App_Output!$D:$D) -> 45747 | G8: =SUMIFS(Cert_App_Output!$J:$J,Cert_App_Output!$C:$C,$A8) -> 35487550 | H8: 0.3745 | I8: =$G8*H8 -> 13290087 | J8: =_xlfn.XLOOKUP($A8,Cert_Cabecera!$A:$A,Cert_Cabecera!$E:$E) -> 0.2 | K8: =-I8*J8 -> -2658017.5 | L8: =I8+K8 -> 10632070 | M8: =_xlfn.XLOOKUP($E8,Cert_OC_Cliente!$B:$B,Cert_OC_Cliente!$G:$G) -> 14366.9 | N8: =IF($Y8="",_xlfn.XLOOKUP(DATE(YEAR(F8),MONTH(F8),1),'0_Indice_CAC'!$A:$A,'0_Indice_CAC'!$B:$B),$Y8) -> 15995.4 | O8: =N8/M8 -> 1.1133508 | P8: =L8*(O8-1) -> 1205153.9 | Q8: =L8+P8 -> 11837224 | R8: 0.105 | S8: =Q8*R8 -> 1242908.5 | T8: =Q8+S8 -> 13080132 | U8: 1170 | V8: =IF(C8="Negro",T8/U8,"") | X8: =IF(ABS(SUMIFS($H:$H,$A:$A,$A8)-1)<0.0001,"✓","⚠ ≠100%") -> ✓
A9: SVD-OC01-C01 | B9: SVD-OC01-C01-N | C9: Negro | D9: =_xlfn.XLOOKUP(A9,Cert_App_Output!$C:$C,Cert_App_Output!$A:$A) -> SVD 4140 | E9: SVD-OC01 | F9: =_xlfn.XLOOKUP(A9,Cert_App_Output!$C:$C,Cert_App_Output!$D:$D) -> 45747 | G9: =SUMIFS(Cert_App_Output!$J:$J,Cert_App_Output!$C:$C,$A9) -> 35487550 | H9: 0.6255 | I9: =$G9*H9 -> 22197463 | J9: =_xlfn.XLOOKUP($A9,Cert_Cabecera!$A:$A,Cert_Cabecera!$E:$E) -> 0.2 | K9: =-I9*J9 -> -4439492.5 | L9: =I9+K9 -> 17757970 | M9: =_xlfn.XLOOKUP($E9,Cert_OC_Cliente!$B:$B,Cert_OC_Cliente!$G:$G) -> 14366.9 | N9: =IF($Y9="",_xlfn.XLOOKUP(DATE(YEAR(F9),MONTH(F9),1),'0_Indice_CAC'!$A:$A,'0_Indice_CAC'!$B:$B),$Y9) -> 15995.4 | O9: =N9/M9 -> 1.1133508 | P9: =L9*(O9-1) -> 2012880.6 | Q9: =L9+P9 -> 19770851 | R9: 0 | S9: =Q9*R9 -> 0 | T9: =Q9+S9 -> 19770851 | U9: 1170 | V9: =IF(C9="Negro",T9/U9,"") -> 16898.163 | X9: =IF(ABS(SUMIFS($H:$H,$A:$A,$A9)-1)<0.0001,"✓","⚠ ≠100%") -> ✓
A10: SVD-OC01-C02 | B10: SVD-OC01-C02-B | C10: Blanco | D10: =_xlfn.XLOOKUP(A10,Cert_App_Output!$C:$C,Cert_App_Output!$A:$A) -> SVD 4140 | E10: SVD-OC01 | F10: =_xlfn.XLOOKUP(A10,Cert_App_Output!$C:$C,Cert_App_Output!$D:$D) -> 45777 | G10: =SUMIFS(Cert_App_Output!$J:$J,Cert_App_Output!$C:$C,$A10) -> 25040749 | H10: 0.3745 | I10: =$G10*H10 -> 9377760.7 | J10: =_xlfn.XLOOKUP($A10,Cert_Cabecera!$A:$A,Cert_Cabecera!$E:$E) -> 0.2 | K10: =-I10*J10 -> -1875552.1 | L10: =I10+K10 -> 7502208.5 | M10: =_xlfn.XLOOKUP($E10,Cert_OC_Cliente!$B:$B,Cert_OC_Cliente!$G:$G) -> 14366.9 | N10: =IF($Y10="",_xlfn.XLOOKUP(DATE(YEAR(F10),MONTH(F10),1),'0_Indice_CAC'!$A:$A,'0_Indice_CAC'!$B:$B),$Y10) -> 16253.5 | O10: =N10/M10 -> 1.1313157 | P10: =L10*(O10-1) -> 985158.01 | Q10: =L10+P10 -> 8487366.6 | R10: 0.105 | S10: =Q10*R10 -> 891173.49 | T10: =Q10+S10 -> 9378540 | U10: 1170 | V10: =IF(C10="Negro",T10/U10,"") | X10: =IF(ABS(SUMIFS($H:$H,$A:$A,$A10)-1)<0.0001,"✓","⚠ ≠100%") -> ✓
A11: SVD-OC01-C02 | B11: SVD-OC01-C02-N | C11: Negro | D11: =_xlfn.XLOOKUP(A11,Cert_App_Output!$C:$C,Cert_App_Output!$A:$A) -> SVD 4140 | E11: SVD-OC01 | F11: =_xlfn.XLOOKUP(A11,Cert_App_Output!$C:$C,Cert_App_Output!$D:$D) -> 45777 | G11: =SUMIFS(Cert_App_Output!$J:$J,Cert_App_Output!$C:$C,$A11) -> 25040749 | H11: 0.6255 | I11: =$G11*H11 -> 15662989 | J11: =_xlfn.XLOOKUP($A11,Cert_Cabecera!$A:$A,Cert_Cabecera!$E:$E) -> 0.2 | K11: =-I11*J11 -> -3132597.8 | L11: =I11+K11 -> 12530391 | M11: =_xlfn.XLOOKUP($E11,Cert_OC_Cliente!$B:$B,Cert_OC_Cliente!$G:$G) -> 14366.9 | N11: =IF($Y11="",_xlfn.XLOOKUP(DATE(YEAR(F11),MONTH(F11),1),'0_Indice_CAC'!$A:$A,'0_Indice_CAC'!$B:$B),$Y11) -> 16253.5 | O11: =N11/M11 -> 1.1313157 | P11: =L11*(O11-1) -> 1645437.5 | Q11: =L11+P11 -> 14175829 | R11: 0 | S11: =Q11*R11 -> 0 | T11: =Q11+S11 -> 14175829 | U11: 1170 | V11: =IF(C11="Negro",T11/U11,"") -> 12116.093 | X11: =IF(ABS(SUMIFS($H:$H,$A:$A,$A11)-1)<0.0001,"✓","⚠ ≠100%") -> ✓
A12: SVD-OC01-C03 | B12: SVD-OC01-C03-B | C12: Blanco | D12: =_xlfn.XLOOKUP(A12,Cert_App_Output!$C:$C,Cert_App_Output!$A:$A) -> SVD 4140 | E12: SVD-OC01 | F12: =_xlfn.XLOOKUP(A12,Cert_App_Output!$C:$C,Cert_App_Output!$D:$D) -> 45807 | G12: =SUMIFS(Cert_App_Output!$J:$J,Cert_App_Output!$C:$C,$A12) -> 29836634 | H12: 0.3745 | I12: =$G12*H12 -> 11173820 | J12: =_xlfn.XLOOKUP($A12,Cert_Cabecera!$A:$A,Cert_Cabecera!$E:$E) -> 0.2 | K12: =-I12*J12 -> -2234763.9 | L12: =I12+K12 -> 8939055.7 | M12: =_xlfn.XLOOKUP($E12,Cert_OC_Cliente!$B:$B,Cert_OC_Cliente!$G:$G) -> 14366.9 | N12: =IF($Y12="",_xlfn.XLOOKUP(DATE(YEAR(F12),MONTH(F12),1),'0_Indice_CAC'!$A:$A,'0_Indice_CAC'!$B:$B),$Y12) -> 16521.3 | O12: =N12/M12 -> 1.1499558 | P12: =L12*(O12-1) -> 1340463.3 | Q12: =L12+P12 -> 10279519 | R12: 0.105 | S12: =Q12*R12 -> 1079349.5 | T12: =Q12+S12 -> 11358868 | U12: 1170 | V12: =IF(C12="Negro",T12/U12,"") | X12: =IF(ABS(SUMIFS($H:$H,$A:$A,$A12)-1)<0.0001,"✓","⚠ ≠100%") -> ✓
A13: SVD-OC01-C03 | B13: SVD-OC01-C03-N | C13: Negro | D13: =_xlfn.XLOOKUP(A13,Cert_App_Output!$C:$C,Cert_App_Output!$A:$A) -> SVD 4140 | E13: SVD-OC01 | F13: =_xlfn.XLOOKUP(A13,Cert_App_Output!$C:$C,Cert_App_Output!$D:$D) -> 45807 | G13: =SUMIFS(Cert_App_Output!$J:$J,Cert_App_Output!$C:$C,$A13) -> 29836634 | H13: 0.6255 | I13: =$G13*H13 -> 18662815 | J13: =_xlfn.XLOOKUP($A13,Cert_Cabecera!$A:$A,Cert_Cabecera!$E:$E) -> 0.2 | K13: =-I13*J13 -> -3732563 | L13: =I13+K13 -> 14930252 | M13: =_xlfn.XLOOKUP($E13,Cert_OC_Cliente!$B:$B,Cert_OC_Cliente!$G:$G) -> 14366.9 | N13: =IF($Y13="",_xlfn.XLOOKUP(DATE(YEAR(F13),MONTH(F13),1),'0_Indice_CAC'!$A:$A,'0_Indice_CAC'!$B:$B),$Y13) -> 16521.3 | O13: =N13/M13 -> 1.1499558 | P13: =L13*(O13-1) -> 2238877.9 | Q13: =L13+P13 -> 17169130 | R13: 0 | S13: =Q13*R13 -> 0 | T13: =Q13+S13 -> 17169130 | U13: 1170 | V13: =IF(C13="Negro",T13/U13,"") -> 14674.47 | X13: =IF(ABS(SUMIFS($H:$H,$A:$A,$A13)-1)<0.0001,"✓","⚠ ≠100%") -> ✓
A14: SVD-OC01-C04 | B14: SVD-OC01-C04-B | C14: Blanco | D14: =_xlfn.XLOOKUP(A14,Cert_App_Output!$C:$C,Cert_App_Output!$A:$A) -> SVD 4140 | E14: SVD-OC01 | F14: =_xlfn.XLOOKUP(A14,Cert_App_Output!$C:$C,Cert_App_Output!$D:$D) -> 45835 | G14: =SUMIFS(Cert_App_Output!$J:$J,Cert_App_Output!$C:$C,$A14) -> 41634494 | H14: 0.3745 | I14: =$G14*H14 -> 15592118 | J14: =_xlfn.XLOOKUP($A14,Cert_Cabecera!$A:$A,Cert_Cabecera!$E:$E) -> 0.2 | K14: =-I14*J14 -> -3118423.6 | L14: =I14+K14 -> 12473694 | M14: =_xlfn.XLOOKUP($E14,Cert_OC_Cliente!$B:$B,Cert_OC_Cliente!$G:$G) -> 14366.9 | N14: =IF($Y14="",_xlfn.XLOOKUP(DATE(YEAR(F14),MONTH(F14),1),'0_Indice_CAC'!$A:$A,'0_Indice_CAC'!$B:$B),$Y14) -> 16643.4 | O14: =N14/M14 -> 1.1584545 | P14: =L14*(O14-1) -> 1976513 | Q14: =L14+P14 -> 14450207 | R14: 0.105 | S14: =Q14*R14 -> 1517271.8 | T14: =Q14+S14 -> 15967479 | U14: 1170 | V14: =IF(C14="Negro",T14/U14,"") | X14: =IF(ABS(SUMIFS($H:$H,$A:$A,$A14)-1)<0.0001,"✓","⚠ ≠100%") -> ✓
A15: SVD-OC01-C04 | B15: SVD-OC01-C04-N | C15: Negro | D15: =_xlfn.XLOOKUP(A15,Cert_App_Output!$C:$C,Cert_App_Output!$A:$A) -> SVD 4140 | E15: SVD-OC01 | F15: =_xlfn.XLOOKUP(A15,Cert_App_Output!$C:$C,Cert_App_Output!$D:$D) -> 45835 | G15: =SUMIFS(Cert_App_Output!$J:$J,Cert_App_Output!$C:$C,$A15) -> 41634494 | H15: 0.6255 | I15: =$G15*H15 -> 26042376 | J15: =_xlfn.XLOOKUP($A15,Cert_Cabecera!$A:$A,Cert_Cabecera!$E:$E) -> 0.2 | K15: =-I15*J15 -> -5208475.2 | L15: =I15+K15 -> 20833901 | M15: =_xlfn.XLOOKUP($E15,Cert_OC_Cliente!$B:$B,Cert_OC_Cliente!$G:$G) -> 14366.9 | N15: =IF($Y15="",_xlfn.XLOOKUP(DATE(YEAR(F15),MONTH(F15),1),'0_Indice_CAC'!$A:$A,'0_Indice_CAC'!$B:$B),$Y15) -> 16643.4 | O15: =N15/M15 -> 1.1584545 | P15: =L15*(O15-1) -> 3301225.4 | Q15: =L15+P15 -> 24135126 | R15: 0 | S15: =Q15*R15 -> 0 | T15: =Q15+S15 -> 24135126 | U15: 1170 | V15: =IF(C15="Negro",T15/U15,"") -> 20628.313 | X15: =IF(ABS(SUMIFS($H:$H,$A:$A,$A15)-1)<0.0001,"✓","⚠ ≠100%") -> ✓
A16: SVD-OC01-C05 | B16: SVD-OC01-C05-B | C16: Blanco | D16: =_xlfn.XLOOKUP(A16,Cert_App_Output!$C:$C,Cert_App_Output!$A:$A) -> SVD 4140 | E16: SVD-OC01 | F16: =_xlfn.XLOOKUP(A16,Cert_App_Output!$C:$C,Cert_App_Output!$D:$D) -> 45861 | G16: =SUMIFS(Cert_App_Output!$J:$J,Cert_App_Output!$C:$C,$A16) -> 40708426 | H16: 0.3745 | I16: =$G16*H16 -> 15245305 | J16: =_xlfn.XLOOKUP($A16,Cert_Cabecera!$A:$A,Cert_Cabecera!$E:$E) -> 0.2 | K16: =-I16*J16 -> -3049061.1 | L16: =I16+K16 -> 12196244 | M16: =_xlfn.XLOOKUP($E16,Cert_OC_Cliente!$B:$B,Cert_OC_Cliente!$G:$G) -> 14366.9 | N16: =IF($Y16="",_xlfn.XLOOKUP(DATE(YEAR(F16),MONTH(F16),1),'0_Indice_CAC'!$A:$A,'0_Indice_CAC'!$B:$B),$Y16) -> 16939.5 | O16: =N16/M16 -> 1.1790644 | P16: =L16*(O16-1) -> 2183912.9 | Q16: =L16+P16 -> 14380157 | R16: 0.105 | S16: =Q16*R16 -> 1509916.5 | T16: =Q16+S16 -> 15890074 | U16: 1170 | V16: =IF(C16="Negro",T16/U16,"") | X16: =IF(ABS(SUMIFS($H:$H,$A:$A,$A16)-1)<0.0001,"✓","⚠ ≠100%") -> ✓
A17: SVD-OC01-C05 | B17: SVD-OC01-C05-N | C17: Negro | D17: =_xlfn.XLOOKUP(A17,Cert_App_Output!$C:$C,Cert_App_Output!$A:$A) -> SVD 4140 | E17: SVD-OC01 | F17: =_xlfn.XLOOKUP(A17,Cert_App_Output!$C:$C,Cert_App_Output!$D:$D) -> 45861 | G17: =SUMIFS(Cert_App_Output!$J:$J,Cert_App_Output!$C:$C,$A17) -> 40708426 | H17: 0.6255 | I17: =$G17*H17 -> 25463120 | J17: =_xlfn.XLOOKUP($A17,Cert_Cabecera!$A:$A,Cert_Cabecera!$E:$E) -> 0.2 | K17: =-I17*J17 -> -5092624.1 | L17: =I17+K17 -> 20370496 | M17: =_xlfn.XLOOKUP($E17,Cert_OC_Cliente!$B:$B,Cert_OC_Cliente!$G:$G) -> 14366.9 | N17: =IF($Y17="",_xlfn.XLOOKUP(DATE(YEAR(F17),MONTH(F17),1),'0_Indice_CAC'!$A:$A,'0_Indice_CAC'!$B:$B),$Y17) -> 16939.5 | O17: =N17/M17 -> 1.1790644 | P17: =L17*(O17-1) -> 3647630.2 | Q17: =L17+P17 -> 24018126 | R17: 0 | S17: =Q17*R17 -> 0 | T17: =Q17+S17 -> 24018126 | U17: 1170 | V17: =IF(C17="Negro",T17/U17,"") -> 20528.313 | X17: =IF(ABS(SUMIFS($H:$H,$A:$A,$A17)-1)<0.0001,"✓","⚠ ≠100%") -> ✓
A18: SVD-OC01-C06 | B18: SVD-OC01-C06-B | C18: Blanco | D18: =_xlfn.XLOOKUP(A18,Cert_App_Output!$C:$C,Cert_App_Output!$A:$A) -> SVD 4140 | E18: SVD-OC01 | F18: =_xlfn.XLOOKUP(A18,Cert_App_Output!$C:$C,Cert_App_Output!$D:$D) -> 45898 | G18: =SUMIFS(Cert_App_Output!$J:$J,Cert_App_Output!$C:$C,$A18) -> 60880923 | H18: 0.3745 | I18: =$G18*H18 -> 22799906 | J18: =_xlfn.XLOOKUP($A18,Cert_Cabecera!$A:$A,Cert_Cabecera!$E:$E) -> 0.2 | K18: =-I18*J18 -> -4559981.2 | L18: =I18+K18 -> 18239925 | M18: =_xlfn.XLOOKUP($E18,Cert_OC_Cliente!$B:$B,Cert_OC_Cliente!$G:$G) -> 14366.9 | N18: =IF($Y18="",_xlfn.XLOOKUP(DATE(YEAR(F18),MONTH(F18),1),'0_Indice_CAC'!$A:$A,'0_Indice_CAC'!$B:$B),$Y18) -> 17187.6 | O18: =N18/M18 -> 1.1963332 | P18: =L18*(O18-1) -> 3581103.5 | Q18: =L18+P18 -> 21821028 | R18: 0.105 | S18: =Q18*R18 -> 2291208 | T18: =Q18+S18 -> 24112236 | U18: 1170 | V18: =IF(C18="Negro",T18/U18,"") | X18: =IF(ABS(SUMIFS($H:$H,$A:$A,$A18)-1)<0.0001,"✓","⚠ ≠100%") -> ✓
A19: SVD-OC01-C06 | B19: SVD-OC01-C06-N | C19: Negro | D19: =_xlfn.XLOOKUP(A19,Cert_App_Output!$C:$C,Cert_App_Output!$A:$A) -> SVD 4140 | E19: SVD-OC01 | F19: =_xlfn.XLOOKUP(A19,Cert_App_Output!$C:$C,Cert_App_Output!$D:$D) -> 45898 | G19: =SUMIFS(Cert_App_Output!$J:$J,Cert_App_Output!$C:$C,$A19) -> 60880923 | H19: 0.6255 | I19: =$G19*H19 -> 38081018 | J19: =_xlfn.XLOOKUP($A19,Cert_Cabecera!$A:$A,Cert_Cabecera!$E:$E) -> 0.2 | K19: =-I19*J19 -> -7616203.5 | L19: =I19+K19 -> 30464814 | M19: =_xlfn.XLOOKUP($E19,Cert_OC_Cliente!$B:$B,Cert_OC_Cliente!$G:$G) -> 14366.9 | N19: =IF($Y19="",_xlfn.XLOOKUP(DATE(YEAR(F19),MONTH(F19),1),'0_Indice_CAC'!$A:$A,'0_Indice_CAC'!$B:$B),$Y19) -> 17187.6 | O19: =N19/M19 -> 1.1963332 | P19: =L19*(O19-1) -> 5981255.6 | Q19: =L19+P19 -> 36446070 | R19: 0 | S19: =Q19*R19 -> 0 | T19: =Q19+S19 -> 36446070 | U19: 1170 | V19: =IF(C19="Negro",T19/U19,"") -> 31150.487 | X19: =IF(ABS(SUMIFS($H:$H,$A:$A,$A19)-1)<0.0001,"✓","⚠ ≠100%") -> ✓
... A47: SVD-OC02-C08 | B47: SVD-OC02-C08-N | C47: Negro | D47: =_xlfn.XLOOKUP(A47,Cert_App_Output!$C:$C,Cert_App_Output!$A:$A) -> SVD 4140 | E47: SVD-OC02 | F47: =_xlfn.XLOOKUP(A47,Cert_App_Output!$C:$C,Cert_App_Output!$D:$D) -> 46174 | G47: =SUMIFS(Cert_App_Output!$J:$J,Cert_App_Output!$C:$C,$A47) -> 85954678 | H47: 0.7593 | I47: =$G47*H47 -> 65265387 | J47: =_xlfn.XLOOKUP($A47,Cert_Cabecera!$A:$A,Cert_Cabecera!$E:$E) -> 0.4 | K47: =-I47*J47 -> -26106155 | L47: =I47+K47 -> 39159232 | M47: =_xlfn.XLOOKUP($E47,Cert_OC_Cliente!$B:$B,Cert_OC_Cliente!$G:$G) -> 14366.9 | N47: =IF($Y47="",_xlfn.XLOOKUP(DATE(YEAR(F47),MONTH(F47),1),'0_Indice_CAC'!$A:$A,'0_Indice_CAC'!$B:$B),$Y47) -> 20471.346 | O47: =N47/M47 -> 1.4248965 | P47: =L47*(O47-1) -> 16638623 | Q47: =L47+P47 -> 55797855 | R47: 0 | S47: =Q47*R47 -> 0 | T47: =Q47+S47 -> 55797855 | U47: 1170 | V47: =IF(C47="Negro",T47/U47,"") -> 47690.474 | X47: =IF(ABS(SUMIFS($H:$H,$A:$A,$A47)-1)<0.0001,"✓","⚠ ≠100%") -> ✓

Sheet Cert_Facturacion
A1: id_cert_fact | B1: Comprobante | C1: Tipo | D1: monto | E1: moneda | F1: Fecha cobro | G1: monto_ars_equiv | H1: Estado conciliado | I1: $ certificado (control) | J1: Saldo a facturar | K1: id_factura | L1: TC cobro | M1: id_cert_madre | N1: id_OC | O1: Clase | P1: Retención | Q1: Haber conciliado

Sheet Cert_Control_OC
A1: ID OC | B1: Presupuesto | C1: Descripcion | D1: $ Contrato | E1: % Avance fisico | F1: $ Certificado | G1: $ Facturado | H1: $ Cobrado | I1: $ Anticipo certif. | J1: $ Avance s/certificar | K1: Saldo a facturar | L1: Saldo a cobrar | M1: Estado
A2: =Cert_OC_Cliente!B2 -> SVD-OC01 | B2: =_xlfn.XLOOKUP($A2,Cert_OC_Cliente!$B:$B,Cert_OC_Cliente!$L:$L) -> PTO 01 | C2: =_xlfn.XLOOKUP($A2,Cert_OC_Cliente!$B:$B,Cert_OC_Cliente!$C:$C) -> Pto 1 - Preliminares + Mov.Suelo + Hormigón | D2: =_xlfn.XLOOKUP($A2,Cert_OC_Cliente!$B:$B,Cert_OC_Cliente!$D:$D) -> 421306052 | E2: =IFERROR(SUMPRODUCT(('1_Presupuesto'!$X$5:$X$219=$B2)*'1_Presupuesto'!$Y$5:$Y$219*'1_Presupuesto'!$V$5:$V$219)/SUMPRODUCT(('1_Presupuesto'!$X$5:$X$219=$B2)*'1_Presupuesto'!$V$5:$V$219),0) -> 1 | F2: =SUMIFS(Cert_Calculo!$T:$T,Cert_Calculo!$E:$E,$A2) -> 5.1078807e+08 | G2: =SUMIFS(Cert_Facturacion!$G:$G,Cert_Facturacion!$A:$A,$A2&"-*") -> 0 | H2: =SUMIFS(Cert_Facturacion!$G:$G,Cert_Facturacion!$A:$A,$A2&"-*",Cert_Facturacion!$F:$F,">0") -> 0 | I2: =SUMIFS(Cert_Calculo!$T:$T,Cert_Calculo!$E:$E,$A2,Cert_Calculo!$B:$B,"*ANT*") -> 87574572 | J2: =SUMIFS(Cert_App_Output!$J:$J,Cert_App_Output!$B:$B,$A2)-SUMIFS(Cert_Calculo!$I:$I,Cert_Calculo!$E:$E,$A2,Cert_Calculo!$B:$B,"<>*ANT*") -> -5.364418e-07 | K2: =F2-G2 -> 5.1078807e+08 | L2: =G2-H2 -> 0 | M2: =IF(J2>1000,"⚠ Certificar",IF(F2=0,"🔴 Sin iniciar",IF(K2>1000,"🟠 Por facturar",IF(L2>1000,"🔵 Por cobrar",IF(E2>=0.999,"🟢 Cerrada","🟡 En ejecucion"))))) -> 🟠 Por facturar
A3: =Cert_OC_Cliente!B3 -> SVD-OC02 | B3: =_xlfn.XLOOKUP($A3,Cert_OC_Cliente!$B:$B,Cert_OC_Cliente!$L:$L) -> PTO 02 | C3: =_xlfn.XLOOKUP($A3,Cert_OC_Cliente!$B:$B,Cert_OC_Cliente!$C:$C) -> Pto 2 - Albañilería + Instalaciones + Terminaciones | D3: =_xlfn.XLOOKUP($A3,Cert_OC_Cliente!$B:$B,Cert_OC_Cliente!$D:$D) -> 7.3685713e+08 | E3: =IFERROR(SUMPRODUCT(('1_Presupuesto'!$X$5:$X$219=$B3)*'1_Presupuesto'!$Y$5:$Y$219*'1_Presupuesto'!$V$5:$V$219)/SUMPRODUCT(('1_Presupuesto'!$X$5:$X$219=$B3)*'1_Presupuesto'!$V$5:$V$219),0) -> 0.48791246 | F3: =SUMIFS(Cert_Calculo!$T:$T,Cert_Calculo!$E:$E,$A3) -> 5.437405e+08 | G3: =SUMIFS(Cert_Facturacion!$G:$G,Cert_Facturacion!$A:$A,$A3&"-*") -> 0 | H3: =SUMIFS(Cert_Facturacion!$G:$G,Cert_Facturacion!$A:$A,$A3&"-*",Cert_Facturacion!$F:$F,">0") -> 0 | I3: =SUMIFS(Cert_Calculo!$T:$T,Cert_Calculo!$E:$E,$A3,Cert_Calculo!$B:$B,"*ANT*") -> 3.0219204e+08 | J3: =SUMIFS(Cert_App_Output!$J:$J,Cert_App_Output!$B:$B,$A3)-SUMIFS(Cert_Calculo!$I:$I,Cert_Calculo!$E:$E,$A3,Cert_Calculo!$B:$B,"<>*ANT*") -> 0 | K3: =F3-G3 -> 5.437405e+08 | L3: =G3-H3 -> 0 | M3: =IF(J3>1000,"⚠ Certificar",IF(F3=0,"🔴 Sin iniciar",IF(K3>1000,"🟠 Por facturar",IF(L3>1000,"🔵 Por cobrar",IF(E3>=0.999,"🟢 Cerrada","🟡 En ejecucion"))))) -> 🟠 Por facturar
A4: =Cert_OC_Cliente!B4 -> SVD-OC03 | B4: =_xlfn.XLOOKUP($A4,Cert_OC_Cliente!$B:$B,Cert_OC_Cliente!$L:$L) -> PTO 03 | C4: =_xlfn.XLOOKUP($A4,Cert_OC_Cliente!$B:$B,Cert_OC_Cliente!$C:$C) -> Adicionales / Trabajos Complementarios | D4: =_xlfn.XLOOKUP($A4,Cert_OC_Cliente!$B:$B,Cert_OC_Cliente!$D:$D) -> 15315355 | E4: =IFERROR(SUMPRODUCT(('1_Presupuesto'!$X$5:$X$219=$B4)*'1_Presupuesto'!$Y$5:$Y$219*'1_Presupuesto'!$V$5:$V$219)/SUMPRODUCT(('1_Presupuesto'!$X$5:$X$219=$B4)*'1_Presupuesto'!$V$5:$V$219),0) -> 0 | F4: =SUMIFS(Cert_Calculo!$T:$T,Cert_Calculo!$E:$E,$A4) -> 0 | G4: =SUMIFS(Cert_Facturacion!$G:$G,Cert_Facturacion!$A:$A,$A4&"-*") -> 0 | H4: =SUMIFS(Cert_Facturacion!$G:$G,Cert_Facturacion!$A:$A,$A4&"-*",Cert_Facturacion!$F:$F,">0") -> 0 | I4: =SUMIFS(Cert_Calculo!$T:$T,Cert_Calculo!$E:$E,$A4,Cert_Calculo!$B:$B,"*ANT*") -> 0 | J4: =SUMIFS(Cert_App_Output!$J:$J,Cert_App_Output!$B:$B,$A4)-SUMIFS(Cert_Calculo!$I:$I,Cert_Calculo!$E:$E,$A4,Cert_Calculo!$B:$B,"<>*ANT*") -> 0 | K4: =F4-G4 -> 0 | L4: =G4-H4 -> 0 | M4: =IF(J4>1000,"⚠ Certificar",IF(F4=0,"🔴 Sin iniciar",IF(K4>1000,"🟠 Por facturar",IF(L4>1000,"🔵 Por cobrar",IF(E4>=0.999,"🟢 Cerrada","🟡 En ejecucion"))))) -> 🔴 Sin iniciar
A5: TOTAL | D5: =SUM(D2:D4) -> 1.1734785e+09 | E5: =SUMPRODUCT($D$2:$D$4,$E$2:$E$4)/SUM($D$2:$D$4) -> 0.66539592 | F5: =SUM(F2:F4) -> 1.0545286e+09 | G5: =SUM(G2:G4) -> 0 | H5: =SUM(H2:H4) -> 0 | I5: =SUM(I2:I4) -> 3.8976661e+08 | J5: =SUM(J2:J4) -> -5.364418e-07 | K5: =SUM(K2:K4) -> 1.0545286e+09 | L5: =SUM(L2:L4) -> 0
